{
  "type": "Feature",
  "properties": {
    "gn:admin1_code":"84.0",
    "gn:admin2_code":"2608.0",
    "gn:admin3_code":"260801.0",
    "gn:asciiname":"Zagorze",
    "gn:country_code":"PL",
    "gn:dem":294,
    "gn:feature_class":"P",
    "gn:feature_code":"PPL",
    "gn:name":"Zag\u00f3rze",
    "gn:population":0,
    "gn:timezone":"Europe/Warsaw",
    "iso:country":"PL",
    "wof:name":"Zagorze",
    "wof:placetype":"locality"
},
  "geometry": {"coordinates":[20.38333,50.41667],"type":"Point"}
}