{
  "type": "Feature",
  "properties": {
    "gn:country":"PL",
    "gn:fcode":"PPLA3",
    "gn:population":1904,
    "iso:country":"PL",
    "name:ceb_x_preferred":[
        "Modliborzyce"
    ],
    "name:eng_x_preferred":[
        "Gmina Modliborzyce"
    ],
    "name:fra_x_preferred":[
        "Modliborzyce"
    ],
    "name:nld_x_preferred":[
        "Modliborzyce"
    ],
    "name:pol_x_preferred":[
        "Modliborzyce"
    ],
    "name:por_x_preferred":[
        "Comuna de Modliborzyce"
    ],
    "name:rus_x_preferred":[
        "\u041c\u043e\u0434\u043b\u0438\u0431\u043e\u0436\u0438\u0446\u0435"
    ],
    "name:slk_x_preferred":[
        "Gmina Modliborzyce"
    ],
    "name:ukr_x_preferred":[
        "\u0490\u043c\u0456\u043d\u0430 \u041c\u043e\u0434\u043b\u0456\u0431\u043e\u0436\u0438\u0446\u0435"
    ],
    "name:ukr_x_variant":[
        "\u041c\u043e\u0434\u043b\u0456\u0431\u043e\u0436\u0438\u0446\u0435"
    ],
    "name:war_x_preferred":[
        "Gmina Modliborzyce"
    ],
    "qs_pg:aaroncc":"PL",
    "qs_pg:gn_country":"PL",
    "qs_pg:gn_fcode":"PPLA3",
    "qs_pg:gn_pop":1904,
    "qs_pg:name":"Modliborzyce",
    "qs_pg:name_adm0":"Polska",
    "qs_pg:name_adm1":"Lubelskie",
    "qs_pg:photos_9k":1,
    "qs_pg:photos_9r":1,
    "qs_pg:photos_all":1,
    "qs_pg:photos_sr":0,
    "qs_pg:pop_sr":3,
    "qs_pg:qs_pg_placetype":"localadmin",
    "qs_pg:qs_pg_placetype_gp":"LocalAdmin",
    "qs_pg:woe_adm0":23424923,
    "woe:adm0_id":23424923,
    "woe:name_adm0":"Polska",
    "woe:name_adm1":"Lubelskie",
    "woe:placetype":"LocalAdmin",
    "wof:name":"Modliborzyce",
    "wof:placetype":"localadmin",
    "wof:population":1904
},
  "geometry": {"coordinates":[22.32945,50.75416],"type":"Point"}
}