{
  "type": "Feature",
  "properties": {
    "gn:admin1_code":"72.0",
    "gn:admin2_code":"202.0",
    "gn:admin3_code":"20201.0",
    "gn:asciiname":"Zeromin",
    "gn:country_code":"PL",
    "gn:dem":339,
    "gn:feature_class":"P",
    "gn:feature_code":"PPL",
    "gn:name":"Zeromin",
    "gn:population":0,
    "gn:timezone":"Europe/Warsaw",
    "iso:country":"PL",
    "wof:name":"Zeromin",
    "wof:placetype":"neighbourhood"
},
  "geometry": {"coordinates":[16.60699,50.67494],"type":"Point"}
}