{
  "type": "Feature",
  "properties": {
    "gn:admin1_code":"86.0",
    "gn:admin2_code":"3023.0",
    "gn:admin3_code":"302304.0",
    "gn:asciiname":"Izdebno",
    "gn:country_code":"PL",
    "gn:dem":104,
    "gn:feature_class":"P",
    "gn:feature_code":"PPL",
    "gn:name":"Izdebno",
    "gn:population":0,
    "gn:timezone":"Europe/Warsaw",
    "iso:country":"PL",
    "name:deu_x_preferred":[
        "Izdebno"
    ],
    "name:fra_x_preferred":[
        "Izdebno"
    ],
    "name:pol_x_preferred":[
        "Izdebno"
    ],
    "name:ukr_x_preferred":[
        "\u0406\u0437\u0434\u0435\u0431\u043d\u043e"
    ],
    "wof:name":"Izdebno",
    "wof:placetype":"locality"
},
  "geometry": {"coordinates":[18.07114,52.35858],"type":"Point"}
}