{
  "type": "Feature",
  "properties": {
    "gn:admin1_code":"74.0",
    "gn:admin2_code":"1009.0",
    "gn:admin3_code":"100907.0",
    "gn:asciiname":"Praca",
    "gn:country_code":"PL",
    "gn:dem":213,
    "gn:feature_class":"P",
    "gn:feature_code":"PPL",
    "gn:name":"Praca",
    "gn:population":0,
    "gn:timezone":"Europe/Warsaw",
    "iso:country":"PL",
    "name:ceb_x_preferred":[
        "Praca"
    ],
    "name:swe_x_preferred":[
        "Praca"
    ],
    "wof:name":"Praca",
    "wof:placetype":"locality"
},
  "geometry": {"coordinates":[19.23448,51.10369],"type":"Point"}
}