{
  "type": "Feature",
  "properties": {
    "gn:admin1_code":"86.0",
    "gn:admin2_code":"3018.0",
    "gn:admin3_code":"301801.0",
    "gn:asciiname":"Kopna",
    "gn:country_code":"PL",
    "gn:dem":143,
    "gn:feature_class":"P",
    "gn:feature_code":"PPL",
    "gn:name":"Kopna",
    "gn:population":0,
    "gn:timezone":"Europe/Warsaw",
    "iso:country":"PL",
    "name:und_x_variant":[
        "Kolonia Kopna",
        "Kopna"
    ],
    "wof:name":"Kopna",
    "wof:placetype":"locality"
},
  "geometry": {"coordinates":[18.24593,51.4556],"type":"Point"}
}