{
  "type": "Feature",
  "properties": {
    "gn:admin1_code":"81.0",
    "gn:admin2_code":"2005.0",
    "gn:admin3_code":"200509.0",
    "gn:asciiname":"Zablotczyzna",
    "gn:country_code":"PL",
    "gn:dem":147,
    "gn:feature_class":"P",
    "gn:feature_code":"PPL",
    "gn:name":"Zab\u0142otczyzna",
    "gn:population":0,
    "gn:timezone":"Europe/Warsaw",
    "iso:country":"PL",
    "name:azb_x_preferred":[
        "\u0632\u0627\u0628\u0648\u0648\u062a\u0686\u0632\u0646\u0627"
    ],
    "name:ceb_x_preferred":[
        "Zab\u0142otczyzna"
    ],
    "name:fas_x_preferred":[
        "\u0632\u0627\u0628\u0648\u0648\u062a\u0686\u0632\u0646\u0627"
    ],
    "name:lit_x_preferred":[
        "Zablot\u010dizna"
    ],
    "name:pol_x_preferred":[
        "Zab\u0142otczyzna"
    ],
    "name:ukr_x_preferred":[
        "\u0417\u0430\u0431\u043b\u043e\u0442\u0447\u0438\u0437\u043d\u0430"
    ],
    "name:und_x_variant":[
        "Zab\u0142otczyna"
    ],
    "name:urd_x_preferred":[
        "\u0636\u0627\u0628\u0648\u0648\u062a\u06a9\u0632\u06cc\u0632\u0646\u06c1"
    ],
    "wof:name":"Zablotczyzna",
    "wof:placetype":"locality"
},
  "geometry": {"coordinates":[23.74216,52.84055],"type":"Point"}
}