{
  "type": "Feature",
  "properties": {
    "gn:admin1_code":"81.0",
    "gn:admin2_code":"2005.0",
    "gn:admin3_code":"200509.0",
    "gn:asciiname":"Zablotczyzna",
    "gn:country_code":"PL",
    "gn:dem":147,
    "gn:feature_class":"P",
    "gn:feature_code":"PPL",
    "gn:name":"Zab\u0142otczyzna",
    "gn:population":0,
    "gn:timezone":"Europe/Warsaw",
    "iso:country":"PL",
    "name:und_x_variant":[
        "Zab\u0142otczyna",
        "Zab\u0142otczyzna"
    ],
    "wof:name":"Zablotczyzna",
    "wof:placetype":"locality"
},
  "geometry": {"coordinates":[23.74216,52.84055],"type":"Point"}
}