{
  "type": "Feature",
  "properties": {
    "gn:admin1_code":"74.0",
    "gn:admin2_code":"1009.0",
    "gn:admin3_code":"100906.0",
    "gn:asciiname":"Delfina",
    "gn:country_code":"PL",
    "gn:dem":175,
    "gn:feature_class":"P",
    "gn:feature_code":"PPL",
    "gn:name":"Delfina",
    "gn:population":0,
    "gn:timezone":"Europe/Warsaw",
    "iso:country":"PL",
    "name:fra_x_preferred":[
        "Delfina"
    ],
    "name:pol_x_preferred":[
        "Delfina"
    ],
    "name:ukr_x_preferred":[
        "\u0414\u0435\u043b\u044c\u0444\u0456\u043d\u0430"
    ],
    "wof:name":"Delfina",
    "wof:placetype":"locality"
},
  "geometry": {"coordinates":[18.90716,51.24345],"type":"Point"}
}