{
  "type": "Feature",
  "properties": {
    "gn:gn_country":"PL",
    "gn:gn_fcode":"PPLA3",
    "gn:gn_pop":1150,
    "gn:population":1150,
    "iso:country":"PL",
    "name:ceb_x_preferred":[
        "Dubiecko"
    ],
    "name:ces_x_preferred":[
        "Dubiecko"
    ],
    "name:fra_x_preferred":[
        "Dubiecko"
    ],
    "name:heb_x_preferred":[
        "\u05d3\u05d5\u05d1\u05e6\u05e7"
    ],
    "name:nld_x_preferred":[
        "Dubiecko"
    ],
    "name:pol_x_preferred":[
        "Dubiecko"
    ],
    "name:ukr_x_preferred":[
        "\u0414\u0443\u0431\u0435\u0446\u044c\u043a\u043e"
    ],
    "name:vie_x_preferred":[
        "Dubiecko"
    ],
    "name:yid_x_preferred":[
        "dubetsk"
    ],
    "qs_pg:aaroncc":"PL",
    "qs_pg:gn_country":"PL",
    "qs_pg:gn_fcode":"PPLA3",
    "qs_pg:gn_pop":1150,
    "qs_pg:name":"Dubiecko",
    "qs_pg:name_adm0":"Polska",
    "qs_pg:name_adm1":"Podkarpackie",
    "qs_pg:photos":59,
    "qs_pg:photos_1k":12,
    "qs_pg:photos_9k":1,
    "qs_pg:photos_9r":2,
    "qs_pg:photos_all":59,
    "qs_pg:photos_sr":2,
    "qs_pg:pop_sr":3,
    "qs_pg:qs_pg_placetype":"localadmin",
    "qs_pg:qs_pg_placetype_gp":"LocalAdmin",
    "qs_pg:woe_adm0":23424923,
    "woe:adm0_id":23424923,
    "woe:name_adm0":"Polska",
    "woe:name_adm1":"Podkarpackie",
    "woe:placetype":"LocalAdmin",
    "wof:name":"Dubiecko",
    "wof:placetype":"localadmin",
    "wof:population":1150
},
  "geometry": {"coordinates":[22.39117,49.82608],"type":"Point"}
}