{
  "type": "Feature",
  "properties": {
    "gn:admin1_code":"85.0",
    "gn:admin2_code":"2815.0",
    "gn:admin3_code":"281506.0",
    "gn:asciiname":"Pityny",
    "gn:country_code":"PL",
    "gn:dem":75,
    "gn:feature_class":"P",
    "gn:feature_code":"PPL",
    "gn:name":"Pityny",
    "gn:population":0,
    "gn:timezone":"Europe/Warsaw",
    "iso:country":"PL",
    "name:fra_x_preferred":[
        "Pityny"
    ],
    "name:pol_x_preferred":[
        "Pityny"
    ],
    "name:ukr_x_preferred":[
        "\u041f\u0456\u0442\u0438\u043d\u0438"
    ],
    "wof:name":"Pityny",
    "wof:placetype":"locality"
},
  "geometry": {"coordinates":[20.14396,54.00853000000001],"type":"Point"}
}