{
  "type": "Feature",
  "properties": {
    "gn:admin1_code":"86.0",
    "gn:admin2_code":"3027.0",
    "gn:admin3_code":"302708.0",
    "gn:asciiname":"Kaczki Mostowe",
    "gn:country_code":"PL",
    "gn:dem":125,
    "gn:feature_class":"P",
    "gn:feature_code":"PPL",
    "gn:name":"Kaczki Mostowe",
    "gn:population":0,
    "gn:timezone":"Europe/Warsaw",
    "iso:country":"PL",
    "wof:name":"Kaczki Mostowe",
    "wof:placetype":"locality"
},
  "geometry": {"coordinates":[18.53404,51.96924],"type":"Point"}
}