{
  "type": "Feature",
  "properties": {
    "gn:admin1_code":"85.0",
    "gn:admin2_code":"2805.0",
    "gn:admin3_code":"280503.0",
    "gn:asciiname":"Dudki",
    "gn:country_code":"PL",
    "gn:dem":130,
    "gn:feature_class":"P",
    "gn:feature_code":"PPL",
    "gn:name":"Dudki",
    "gn:population":0,
    "gn:timezone":"Europe/Warsaw",
    "iso:country":"PL",
    "name:azb_x_preferred":[
        "\u062f\u0648\u062f\u06a9\u06cc"
    ],
    "name:deu_x_preferred":[
        "Dudki"
    ],
    "name:fas_x_preferred":[
        "\u062f\u0648\u062f\u06a9\u06cc"
    ],
    "name:fra_x_preferred":[
        "Dudki"
    ],
    "name:pol_x_preferred":[
        "Dudki"
    ],
    "name:ukr_x_preferred":[
        "\u0414\u0443\u0434\u043a\u0456"
    ],
    "name:und_x_variant":[
        "Petzkau",
        "Duttken"
    ],
    "wof:name":"Dudki",
    "wof:placetype":"locality"
},
  "geometry": {"coordinates":[22.68471,53.83521],"type":"Point"}
}