{
  "type": "Feature",
  "properties": {
    "gn:admin1_code":"78.0",
    "gn:admin2_code":"1427.0",
    "gn:admin3_code":"142702.0",
    "gn:asciiname":"Bombalice",
    "gn:country_code":"PL",
    "gn:dem":127,
    "gn:feature_class":"P",
    "gn:feature_code":"PPL",
    "gn:name":"Bombalice",
    "gn:population":0,
    "gn:timezone":"Europe/Warsaw",
    "iso:country":"PL",
    "name:fra_x_preferred":[
        "Bombalice"
    ],
    "name:pol_x_preferred":[
        "Bombalice"
    ],
    "name:szl_x_preferred":[
        "B\u016fmbalicy"
    ],
    "name:ukr_x_preferred":[
        "\u0411\u043e\u043c\u0431\u0430\u043b\u0456\u0446\u0435"
    ],
    "wof:name":"Bombalice",
    "wof:placetype":"locality"
},
  "geometry": {"coordinates":[19.77874,52.71331],"type":"Point"}
}