{
  "type": "Feature",
  "properties": {
    "gn:admin1_code":"80.0",
    "gn:admin2_code":"1814.0",
    "gn:admin3_code":"181405.0",
    "gn:asciiname":"Nizatyce",
    "gn:country_code":"PL",
    "gn:dem":206,
    "gn:feature_class":"P",
    "gn:feature_code":"PPL",
    "gn:name":"Ni\u017catyce",
    "gn:population":0,
    "gn:timezone":"Europe/Warsaw",
    "iso:country":"PL",
    "wof:name":"Nizatyce",
    "wof:placetype":"locality"
},
  "geometry": {"coordinates":[22.42601,49.99648],"type":"Point"}
}