{
  "type": "Feature",
  "properties": {
    "gn:admin1_code":"74.0",
    "gn:admin2_code":"1014.0",
    "gn:admin3_code":"101406.0",
    "gn:asciiname":"Wilczkow",
    "gn:country_code":"PL",
    "gn:dem":132,
    "gn:feature_class":"P",
    "gn:feature_code":"PPL",
    "gn:name":"Wilczk\u00f3w",
    "gn:population":0,
    "gn:timezone":"Europe/Warsaw",
    "iso:country":"PL",
    "name:pol_x_preferred":[
        "Wilczk\u00f3w"
    ],
    "name:ukr_x_preferred":[
        "\u0412\u0456\u043b\u044c\u0447\u043a\u0443\u0432"
    ],
    "wof:name":"Wilczkow",
    "wof:placetype":"locality"
},
  "geometry": {"coordinates":[18.57634,51.83599],"type":"Point"}
}