{
  "type": "Feature",
  "properties": {
    "gn:admin1_code":"74.0",
    "gn:admin2_code":"1014.0",
    "gn:admin3_code":"101408.0",
    "gn:asciiname":"Klocko",
    "gn:country_code":"PL",
    "gn:dem":147,
    "gn:feature_class":"P",
    "gn:feature_code":"PPL",
    "gn:name":"K\u0142ocko",
    "gn:population":0,
    "gn:timezone":"Europe/Warsaw",
    "iso:country":"PL",
    "name:ceb_x_preferred":[
        "K\u0142ocko"
    ],
    "name:pol_x_preferred":[
        "K\u0142ocko"
    ],
    "name:ukr_x_preferred":[
        "\u041a\u043b\u043e\u0446\u044c\u043a\u043e"
    ],
    "wof:name":"Klocko",
    "wof:placetype":"locality"
},
  "geometry": {"coordinates":[18.67401,51.56995],"type":"Point"}
}