{
  "type": "Feature",
  "properties": {
    "gn:admin1_code":"78.0",
    "gn:admin2_code":"1427.0",
    "gn:admin3_code":"142703.0",
    "gn:asciiname":"Bendorzyn",
    "gn:country_code":"PL",
    "gn:dem":110,
    "gn:feature_class":"P",
    "gn:feature_code":"PPL",
    "gn:name":"Bendorzyn",
    "gn:population":0,
    "gn:timezone":"Europe/Warsaw",
    "iso:country":"PL",
    "name:fra_x_preferred":[
        "Bendorzyn"
    ],
    "name:pol_x_preferred":[
        "Bendorzyn"
    ],
    "name:ukr_x_preferred":[
        "\u0411\u0435\u043d\u0434\u043e\u0436\u0438\u043d"
    ],
    "wof:name":"Bendorzyn",
    "wof:placetype":"locality"
},
  "geometry": {"coordinates":[19.58169,52.71009],"type":"Point"}
}