{
  "type": "Feature",
  "properties": {
    "gn:admin1_code":"75.0",
    "gn:admin2_code":"604.0",
    "gn:admin3_code":"60405.0",
    "gn:asciiname":"Radostow",
    "gn:country_code":"PL",
    "gn:dem":248,
    "gn:feature_class":"P",
    "gn:feature_code":"PPL",
    "gn:name":"Radost\u00f3w",
    "gn:population":0,
    "gn:timezone":"Europe/Warsaw",
    "iso:country":"PL",
    "name:fra_x_preferred":[
        "Radost\u00f3w"
    ],
    "name:pol_x_preferred":[
        "Radost\u00f3w"
    ],
    "name:ukr_x_preferred":[
        "\u0420\u0430\u0434\u043e\u0441\u0442\u0456\u0432"
    ],
    "wof:name":"Radostow",
    "wof:placetype":"locality"
},
  "geometry": {"coordinates":[23.86489,50.56755],"type":"Point"}
}