{
  "type": "Feature",
  "properties": {
    "gn:admin1_code":"72",
    "gn:admin2_code":"0226",
    "gn:admin3_code":"22606.0",
    "gn:asciiname":"Brennik",
    "gn:country_code":"PL",
    "gn:dem":184,
    "gn:feature_class":"P",
    "gn:feature_code":"PPL",
    "gn:name":"Brennik",
    "gn:population":0,
    "gn:timezone":"Europe/Warsaw",
    "iso:country":"PL",
    "name:deu_x_historical":[
        "Rothbr\u00fcnnig"
    ],
    "name:deu_x_preferred":[
        "Rothbr\u00fcnnig"
    ],
    "name:pol_x_preferred":[
        "Brennik"
    ],
    "name:ukr_x_preferred":[
        "\u0411\u0440\u0435\u043d\u043d\u0438\u043a"
    ],
    "wof:name":"Brennik",
    "wof:placetype":"locality"
},
  "geometry": {"coordinates":[15.98159,51.17028],"type":"Point"}
}