{
  "type": "Feature",
  "properties": {
    "gn:admin1_code":"74.0",
    "gn:admin2_code":"1010.0",
    "gn:admin3_code":"101004.0",
    "gn:asciiname":"Majkow Sredni",
    "gn:country_code":"PL",
    "gn:dem":227,
    "gn:feature_class":"P",
    "gn:feature_code":"PPL",
    "gn:name":"Majk\u00f3w \u015aredni",
    "gn:population":0,
    "gn:timezone":"Europe/Warsaw",
    "iso:country":"PL",
    "name:fra_x_preferred":[
        "Majk\u00f3w \u015aredni"
    ],
    "name:pol_x_preferred":[
        "Majk\u00f3w \u015aredni"
    ],
    "name:ukr_x_preferred":[
        "\u041c\u0430\u0439\u043a\u0443\u0432-\u0421\u0435\u0440\u0435\u0434\u043d\u0456\u0439"
    ],
    "wof:name":"Majkow Sredni",
    "wof:placetype":"locality"
},
  "geometry": {"coordinates":[19.60184,51.43272],"type":"Point"}
}