{
  "type": "Feature",
  "properties": {
    "gn:admin1_code":"78.0",
    "gn:admin2_code":"1429.0",
    "gn:admin3_code":"142904.0",
    "gn:asciiname":"Grodek Dwor",
    "gn:country_code":"PL",
    "gn:dem":127,
    "gn:feature_class":"P",
    "gn:feature_code":"PPL",
    "gn:name":"Gr\u00f3dek Dw\u00f3r",
    "gn:population":0,
    "gn:timezone":"Europe/Warsaw",
    "iso:country":"PL",
    "name:azb_x_preferred":[
        "\u0642\u0631\u0648\u062f\u06a9-\u062f\u0648\u0648\u0631"
    ],
    "name:fas_x_preferred":[
        "\u06af\u0631\u0648\u062f\u06a9-\u062f\u0648\u0648\u0631"
    ],
    "name:fra_x_preferred":[
        "Gr\u00f3dek-Dw\u00f3r"
    ],
    "name:lit_x_preferred":[
        "Grudek Dvuras"
    ],
    "name:pol_x_preferred":[
        "Gr\u00f3dek-Dw\u00f3r"
    ],
    "name:ukr_x_preferred":[
        "\u0490\u0440\u0443\u0434\u0435\u043a-\u0414\u0432\u0443\u0440"
    ],
    "wof:name":"Grodek Dwor",
    "wof:placetype":"locality"
},
  "geometry": {"coordinates":[22.4973,52.47133],"type":"Point"}
}