{
  "type": "Feature",
  "properties": {
    "gn:country":"PL",
    "gn:fcode":"PPL",
    "gn:population":0,
    "iso:country":"PL",
    "name:azb_x_preferred":[
        "\u062f\u0648\u0645\u0627\u062a\u0648\u0648\u06a9\u0648"
    ],
    "name:ceb_x_preferred":[
        "Domat\u00f3wko"
    ],
    "name:csb_x_preferred":[
        "Dom\u00f4t\u00f3wk\u00f2"
    ],
    "name:fas_x_preferred":[
        "\u062f\u0648\u0645\u0627\u062a\u0648\u0648\u06a9\u0648"
    ],
    "name:nld_x_preferred":[
        "Domat\u00f3wko"
    ],
    "name:pol_x_preferred":[
        "Domat\u00f3wko"
    ],
    "name:ukr_x_preferred":[
        "\u0414\u043e\u043c\u0430\u0442\u0443\u0432\u043a\u043e"
    ],
    "qs_pg:aaroncc":"PL",
    "qs_pg:gn_country":"PL",
    "qs_pg:gn_fcode":"PPL",
    "qs_pg:gn_pop":0,
    "qs_pg:name":"Domat\u00f3wko",
    "qs_pg:name_adm0":"Polska",
    "qs_pg:name_adm1":"Pomorskie",
    "qs_pg:photos_9k":1,
    "qs_pg:photos_9r":1,
    "qs_pg:photos_all":1,
    "qs_pg:photos_sr":0,
    "qs_pg:pop_sr":0,
    "qs_pg:qs_pg_placetype":"locality",
    "qs_pg:qs_pg_placetype_gp":"Town",
    "qs_pg:woe_adm0":23424923,
    "woe:adm0_id":23424923,
    "woe:name_adm0":"Polska",
    "woe:name_adm1":"Pomorskie",
    "woe:placetype":"Town",
    "wof:name":"Domat\u00f3wko",
    "wof:placetype":"locality"
},
  "geometry": {"coordinates":[18.21012,54.68715],"type":"Point"}
}