{
  "type": "Feature",
  "properties": {
    "gn:admin1_code":"75.0",
    "gn:admin2_code":"618.0",
    "gn:admin3_code":"61813.0",
    "gn:asciiname":"Rzeplin",
    "gn:country_code":"PL",
    "gn:dem":218,
    "gn:feature_class":"P",
    "gn:feature_code":"PPL",
    "gn:name":"Rzeplin",
    "gn:population":0,
    "gn:timezone":"Europe/Warsaw",
    "iso:country":"PL",
    "name:ceb_x_preferred":[
        "Rzeplin"
    ],
    "name:fra_x_preferred":[
        "Rzeplin"
    ],
    "name:pol_x_preferred":[
        "Rzeplin"
    ],
    "name:ukr_x_preferred":[
        "\u0420\u0435\u043f\u043b\u0456\u043d"
    ],
    "wof:name":"Rzeplin",
    "wof:placetype":"locality"
},
  "geometry": {"coordinates":[23.85239,50.46884],"type":"Point"}
}