{
  "type": "Feature",
  "properties": {
    "gn:admin1_code":"74.0",
    "gn:admin2_code":"1012.0",
    "gn:admin3_code":"101212.0",
    "gn:asciiname":"Bobry",
    "gn:country_code":"PL",
    "gn:dem":207,
    "gn:feature_class":"P",
    "gn:feature_code":"PPL",
    "gn:name":"Bobry",
    "gn:population":0,
    "gn:timezone":"Europe/Warsaw",
    "iso:country":"PL",
    "name:fra_x_preferred":[
        "Bobry"
    ],
    "name:pol_x_preferred":[
        "Bobry"
    ],
    "name:ukr_x_preferred":[
        "\u0411\u043e\u0431\u0440\u0438"
    ],
    "wof:name":"Bobry",
    "wof:placetype":"locality"
},
  "geometry": {"coordinates":[19.40937000000001,51.01967],"type":"Point"}
}