{
  "type": "Feature",
  "properties": {
    "gn:admin1_code":"74.0",
    "gn:admin2_code":"1010.0",
    "gn:admin3_code":"101006.0",
    "gn:asciiname":"Baby",
    "gn:country_code":"PL",
    "gn:dem":200,
    "gn:feature_class":"P",
    "gn:feature_code":"PPL",
    "gn:name":"Baby",
    "gn:population":0,
    "gn:timezone":"Europe/Warsaw",
    "iso:country":"PL",
    "name:azb_x_preferred":[
        "\u0628\u0627\u0628\u0647"
    ],
    "name:ceb_x_preferred":[
        "Baby"
    ],
    "name:fas_x_preferred":[
        "\u0628\u0627\u0628\u0647"
    ],
    "name:fra_x_preferred":[
        "Baby"
    ],
    "name:nld_x_preferred":[
        "Baby"
    ],
    "name:pol_x_preferred":[
        "Baby"
    ],
    "name:ukr_x_preferred":[
        "\u0411\u0430\u0431\u0438"
    ],
    "wof:name":"Baby",
    "wof:placetype":"locality"
},
  "geometry": {"coordinates":[19.71691,51.53054],"type":"Point"}
}