{
  "type": "Feature",
  "properties": {
    "gn:admin1_code":"78.0",
    "gn:asciiname":"Sierzputy Zagajne",
    "gn:country_code":"PL",
    "gn:dem":135,
    "gn:feature_class":"P",
    "gn:feature_code":"PPL",
    "gn:name":"Sierzputy Zagajne",
    "gn:population":0,
    "gn:timezone":"Europe/Warsaw",
    "iso:country":"PL",
    "wof:name":"Sierzputy Zagajne",
    "wof:placetype":"locality"
},
  "geometry": {"coordinates":[22.03686,53.0833],"type":"Point"}
}