{
  "type": "Feature",
  "properties": {
    "gn:admin1_code":"78.0",
    "gn:asciiname":"Sierzputy Zagajne",
    "gn:country_code":"PL",
    "gn:dem":135,
    "gn:feature_class":"P",
    "gn:feature_code":"PPL",
    "gn:name":"Sierzputy Zagajne",
    "gn:population":0,
    "gn:timezone":"Europe/Warsaw",
    "iso:country":"PL",
    "name:lit_x_preferred":[
        "Se\u017eputi Zagain\u0117"
    ],
    "name:pol_x_preferred":[
        "Sierzputy Zagajne"
    ],
    "name:ukr_x_preferred":[
        "\u0421\u0435\u0436\u043f\u0443\u0442\u0438-\u0417\u0430\u0491\u0430\u0439\u043d\u0435"
    ],
    "wof:name":"Sierzputy Zagajne",
    "wof:placetype":"locality"
},
  "geometry": {"coordinates":[22.03686,53.0833],"type":"Point"}
}