{
  "type": "Feature",
  "properties": {
    "gn:admin1_code":"87.0",
    "gn:admin2_code":"3202.0",
    "gn:admin3_code":"320203.0",
    "gn:asciiname":"Kepa",
    "gn:country_code":"PL",
    "gn:dem":99,
    "gn:feature_class":"P",
    "gn:feature_code":"PPL",
    "gn:name":"K\u0119pa",
    "gn:population":0,
    "gn:timezone":"Europe/Warsaw",
    "iso:country":"PL",
    "name:und_x_variant":[
        "K\u0119pa"
    ],
    "wof:name":"Kepa",
    "wof:placetype":"locality"
},
  "geometry": {"coordinates":[15.73453,53.23975],"type":"Point"}
}