{
  "type": "Feature",
  "properties": {
    "gn:admin1_code":"85.0",
    "gn:admin2_code":"2814.0",
    "gn:admin3_code":"281401.0",
    "gn:asciiname":"Bogdany",
    "gn:country_code":"PL",
    "gn:dem":117,
    "gn:feature_class":"P",
    "gn:feature_code":"PPL",
    "gn:name":"Bogdany",
    "gn:population":0,
    "gn:timezone":"Europe/Warsaw",
    "iso:country":"PL",
    "name:fra_x_preferred":[
        "Bogdany"
    ],
    "name:pol_x_preferred":[
        "Bogdany"
    ],
    "name:und_x_variant":[
        "Bogdainen",
        "Bogdany"
    ],
    "wof:name":"Bogdany",
    "wof:placetype":"locality"
},
  "geometry": {"coordinates":[20.63738,53.78317],"type":"Point"}
}