{
  "type": "Feature",
  "properties": {
    "gn:admin1_code":"87.0",
    "gn:admin2_code":"3209.0",
    "gn:admin3_code":"320906.0",
    "gn:asciiname":"Cetun",
    "gn:country_code":"PL",
    "gn:dem":138,
    "gn:feature_class":"P",
    "gn:feature_code":"PPL",
    "gn:name":"Cetu\u0144",
    "gn:population":0,
    "gn:timezone":"Europe/Warsaw",
    "iso:country":"PL",
    "name:azb_x_preferred":[
        "\u062a\u0633\u062a\u0648\u0646\u0642"
    ],
    "name:ceb_x_preferred":[
        "Cetu\u0144"
    ],
    "name:deu_x_preferred":[
        "Cetu\u0144"
    ],
    "name:fas_x_preferred":[
        "\u062a\u0633\u062a\u0648\u0646\u06af"
    ],
    "name:pol_x_preferred":[
        "Cetu\u0144"
    ],
    "name:ukr_x_preferred":[
        "\u0426\u0435\u0442\u0443\u043d\u044c"
    ],
    "name:vie_x_preferred":[
        "Cetu\u0144"
    ],
    "wof:name":"Cetun",
    "wof:placetype":"locality"
},
  "geometry": {"coordinates":[16.59196,54.0897],"type":"Point"}
}