{
  "type": "Feature",
  "properties": {
    "gn:admin1_code":"75.0",
    "gn:admin2_code":"601.0",
    "gn:admin3_code":"60112.0",
    "gn:asciiname":"Olszyn",
    "gn:country_code":"PL",
    "gn:dem":146,
    "gn:feature_class":"P",
    "gn:feature_code":"PPL",
    "gn:name":"Olszyn",
    "gn:population":0,
    "gn:timezone":"Europe/Warsaw",
    "iso:country":"PL",
    "wof:name":"Olszyn",
    "wof:placetype":"locality"
},
  "geometry": {"coordinates":[23.38158,52.12578],"type":"Point"}
}