{
  "type": "Feature",
  "properties": {
    "gn:admin1_code":"75.0",
    "gn:admin2_code":"601.0",
    "gn:admin3_code":"60112.0",
    "gn:asciiname":"Olszyn",
    "gn:country_code":"PL",
    "gn:dem":146,
    "gn:feature_class":"P",
    "gn:feature_code":"PPL",
    "gn:name":"Olszyn",
    "gn:population":0,
    "gn:timezone":"Europe/Warsaw",
    "iso:country":"PL",
    "name:azb_x_preferred":[
        "\u0627\u0648\u0644\u0634\u0646"
    ],
    "name:ceb_x_preferred":[
        "Olszyn"
    ],
    "name:fas_x_preferred":[
        "\u0627\u0648\u0644\u0634\u0646"
    ],
    "name:fra_x_preferred":[
        "Olszyn"
    ],
    "name:lit_x_preferred":[
        "Ol\u0161inas"
    ],
    "name:pol_x_preferred":[
        "Olszyn"
    ],
    "name:ukr_x_preferred":[
        "\u041e\u043b\u044c\u0448\u0438\u043d"
    ],
    "wof:name":"Olszyn",
    "wof:placetype":"locality"
},
  "geometry": {"coordinates":[23.38158,52.12578],"type":"Point"}
}