{
  "type": "Feature",
  "properties": {
    "gn:admin1_code":"83.0",
    "gn:admin2_code":"2416.0",
    "gn:admin3_code":"241607.0",
    "gn:asciiname":"Kidow",
    "gn:country_code":"PL",
    "gn:dem":340,
    "gn:feature_class":"P",
    "gn:feature_code":"PPL",
    "gn:name":"Kid\u00f3w",
    "gn:population":0,
    "gn:timezone":"Europe/Warsaw",
    "iso:country":"PL",
    "name:pol_x_preferred":[
        "Kid\u00f3w"
    ],
    "name:ukr_x_preferred":[
        "\u041a\u0456\u0434\u0443\u0432"
    ],
    "name:und_x_variant":[
        "Kid\u00f3w"
    ],
    "wof:name":"Kidow",
    "wof:placetype":"locality"
},
  "geometry": {"coordinates":[19.70088,50.50716],"type":"Point"}
}