{
  "type": "Feature",
  "properties": {
    "gn:admin1_code":"84.0",
    "gn:admin2_code":"2607.0",
    "gn:admin3_code":"260704.0",
    "gn:asciiname":"Borownia",
    "gn:country_code":"PL",
    "gn:dem":162,
    "gn:feature_class":"P",
    "gn:feature_code":"PPL",
    "gn:name":"Borownia",
    "gn:population":0,
    "gn:timezone":"Europe/Warsaw",
    "iso:country":"PL",
    "name:nld_x_preferred":[
        "Borownia"
    ],
    "name:pol_x_preferred":[
        "Borownia"
    ],
    "name:ukr_x_preferred":[
        "\u0411\u043e\u0440\u043e\u0432\u043d\u044f"
    ],
    "wof:name":"Borownia",
    "wof:placetype":"locality"
},
  "geometry": {"coordinates":[21.56324,50.91867],"type":"Point"}
}