{
  "type": "Feature",
  "properties": {
    "gn:admin1_code":"85.0",
    "gn:admin2_code":"2802.0",
    "gn:admin3_code":"280202.0",
    "gn:asciiname":"Rudlowo",
    "gn:country_code":"PL",
    "gn:dem":18,
    "gn:feature_class":"P",
    "gn:feature_code":"PPL",
    "gn:name":"Rud\u0142owo",
    "gn:population":0,
    "gn:timezone":"Europe/Warsaw",
    "iso:country":"PL",
    "name:azb_x_preferred":[
        "\u0631\u0648\u062f\u0648\u0648\u0648\u0648"
    ],
    "name:ceb_x_preferred":[
        "Rud\u0142owo"
    ],
    "name:deu_x_preferred":[
        "Rud\u0142owo"
    ],
    "name:fas_x_preferred":[
        "\u0631\u0648\u062f\u0648\u0648\u0648\u0648"
    ],
    "name:fra_x_preferred":[
        "Rud\u0142owo"
    ],
    "name:pol_x_preferred":[
        "Rud\u0142owo"
    ],
    "name:und_x_variant":[
        "Rodelsh\u00f6fen",
        "Rud\u0142owo"
    ],
    "name:vie_x_preferred":[
        "Rud\u0142owo"
    ],
    "wof:name":"Rudlowo",
    "wof:placetype":"locality"
},
  "geometry": {"coordinates":[19.83314,54.3702],"type":"Point"}
}