{
  "type": "Feature",
  "properties": {
    "gn:admin1_code":"78.0",
    "gn:admin2_code":"1424.0",
    "gn:admin3_code":"142404.0",
    "gn:asciiname":"Bialowieza",
    "gn:country_code":"PL",
    "gn:dem":91,
    "gn:feature_class":"P",
    "gn:feature_code":"PPL",
    "gn:name":"Bia\u0142owie\u017ca",
    "gn:population":0,
    "gn:timezone":"Europe/Warsaw",
    "iso:country":"PL",
    "name:und_x_variant":[
        "Bia\u0142owie\u017ca"
    ],
    "wof:name":"Bialowieza",
    "wof:placetype":"locality"
},
  "geometry": {"coordinates":[21.05215,52.73467],"type":"Point"}
}