{
  "type": "Feature",
  "properties": {
    "gn:admin1_code":"81.0",
    "gn:admin2_code":"2011.0",
    "gn:admin3_code":"201102.0",
    "gn:asciiname":"Franckowa Buda",
    "gn:country_code":"PL",
    "gn:dem":151,
    "gn:feature_class":"P",
    "gn:feature_code":"PPL",
    "gn:name":"Franckowa Buda",
    "gn:population":0,
    "gn:timezone":"Europe/Warsaw",
    "iso:country":"PL",
    "wof:name":"Franckowa Buda",
    "wof:placetype":"locality"
},
  "geometry": {"coordinates":[23.18333,53.48333],"type":"Point"}
}