{
  "type": "Feature",
  "properties": {
    "gn:admin1_code":"81.0",
    "gn:admin2_code":"2011.0",
    "gn:admin3_code":"201102.0",
    "gn:asciiname":"Franckowa Buda",
    "gn:country_code":"PL",
    "gn:dem":151,
    "gn:feature_class":"P",
    "gn:feature_code":"PPL",
    "gn:name":"Franckowa Buda",
    "gn:population":0,
    "gn:timezone":"Europe/Warsaw",
    "iso:country":"PL",
    "name:azb_x_preferred":[
        "\u0641\u0631\u0627\u0646\u062a\u0633\u06a9\u0648\u0648\u0627 \u0628\u0648\u062f\u0627"
    ],
    "name:fas_x_preferred":[
        "\u0641\u0631\u0627\u0646\u062a\u0633\u06a9\u0648\u0648\u0627 \u0628\u0648\u062f\u0627"
    ],
    "name:fra_x_preferred":[
        "Franckowa Buda"
    ],
    "name:lit_x_preferred":[
        "Franckova Buda"
    ],
    "name:pol_x_preferred":[
        "Franckowa Buda"
    ],
    "name:ukr_x_preferred":[
        "\u0424\u0440\u0430\u043d\u0446\u043a\u043e\u0432\u0430-\u0411\u0443\u0434\u0430"
    ],
    "wof:name":"Franckowa Buda",
    "wof:placetype":"locality"
},
  "geometry": {"coordinates":[23.18333,53.48333],"type":"Point"}
}