{
  "type": "Feature",
  "properties": {
    "gn:admin1_code":"81.0",
    "gn:admin2_code":"2007.0",
    "gn:admin3_code":"200703.0",
    "gn:asciiname":"Drogoszewo",
    "gn:country_code":"PL",
    "gn:dem":102,
    "gn:feature_class":"P",
    "gn:feature_code":"PPL",
    "gn:name":"Drogoszewo",
    "gn:population":0,
    "gn:timezone":"Europe/Warsaw",
    "iso:country":"PL",
    "name:lit_x_preferred":[
        "Drogo\u0161evas"
    ],
    "name:pol_x_preferred":[
        "Drogoszewo"
    ],
    "name:ukr_x_preferred":[
        "\u0414\u0440\u043e\u0491\u043e\u0448\u0435\u0432\u043e"
    ],
    "wof:name":"Drogoszewo",
    "wof:placetype":"locality"
},
  "geometry": {"coordinates":[21.75087000000001,53.14686999999999],"type":"Point"}
}