{
  "type": "Feature",
  "properties": {
    "gn:population":2283,
    "iso:country":"PL",
    "name:ast_x_preferred":[
        "Przystaj\u0144"
    ],
    "name:deu_x_preferred":[
        "Przystaj\u0144"
    ],
    "name:eng_x_preferred":[
        "Przystaj\u0144"
    ],
    "name:fra_x_preferred":[
        "Przystaj\u0144"
    ],
    "name:nld_x_preferred":[
        "Przystaj\u0144"
    ],
    "name:pol_x_preferred":[
        "Przystaj\u0144"
    ],
    "name:ukr_x_preferred":[
        "\u041f\u0448\u0438\u0441\u0442\u0430\u0439\u043d\u044c"
    ],
    "qs:a0":"Rzeczpospolita Polska",
    "qs:a1":"*Slaskie",
    "qs:a1r":"0",
    "qs:a2":"Klobucki",
    "qs:adm0":"Rzeczpospolita Polska",
    "qs:la":"Panki",
    "qs:la_lc":"*PL2406062",
    "qs:level":"locality",
    "qs:loc":"Przystaj\u0144",
    "qs:loc_alt":"Przystajn",
    "qs:pop":0,
    "qs:type":"rural point-in-poly",
    "wd:wordcount":89,
    "wof:name":"Przystaj\u0144",
    "wof:placetype":"locality",
    "wof:population":2283
},
  "geometry": {"coordinates":[18.6690802847579,50.8614040618854],"type":"Point"}
}