{
  "type": "Feature",
  "properties": {
    "gn:admin1_code":"86.0",
    "gn:admin2_code":"3024.0",
    "gn:admin3_code":"302406.0",
    "gn:asciiname":"Luboczesnica",
    "gn:country_code":"PL",
    "gn:dem":100,
    "gn:feature_class":"P",
    "gn:feature_code":"PPL",
    "gn:name":"Lubocze\u015bnica",
    "gn:population":0,
    "gn:timezone":"Europe/Warsaw",
    "iso:country":"PL",
    "name:ceb_x_preferred":[
        "Lubocze\u015bnica"
    ],
    "name:fra_x_preferred":[
        "Lubocze\u015bnica"
    ],
    "name:pol_x_preferred":[
        "Lubocze\u015bnica"
    ],
    "name:ukr_x_preferred":[
        "\u041b\u044e\u0431\u043e\u0447\u0435\u0441\u044c\u043d\u0438\u0446\u044f"
    ],
    "wof:name":"Luboczesnica",
    "wof:placetype":"locality"
},
  "geometry": {"coordinates":[16.23929,52.52988000000001],"type":"Point"}
}