{
  "type": "Feature",
  "properties": {
    "gn:admin1_code":"78.0",
    "gn:admin2_code":"1412.0",
    "gn:admin3_code":"141212.0",
    "gn:asciiname":"Rudka",
    "gn:country_code":"PL",
    "gn:dem":157,
    "gn:feature_class":"P",
    "gn:feature_code":"PPL",
    "gn:name":"Rudka",
    "gn:population":0,
    "gn:timezone":"Europe/Warsaw",
    "iso:country":"PL",
    "name:fra_x_preferred":[
        "Rudka"
    ],
    "name:pol_x_preferred":[
        "Rudka"
    ],
    "name:ukr_x_preferred":[
        "\u0420\u0443\u0434\u043a\u0430"
    ],
    "wof:name":"Rudka",
    "wof:placetype":"locality"
},
  "geometry": {"coordinates":[21.83962,52.15545],"type":"Point"}
}