{
  "type": "Feature",
  "properties": {
    "gn:admin1_code":"80.0",
    "gn:admin2_code":"1805.0",
    "gn:admin3_code":"180508.0",
    "gn:asciiname":"Mrukowa",
    "gn:country_code":"PL",
    "gn:dem":351,
    "gn:feature_class":"P",
    "gn:feature_code":"PPL",
    "gn:name":"Mrukowa",
    "gn:population":0,
    "gn:timezone":"Europe/Warsaw",
    "iso:country":"PL",
    "name:ceb_x_preferred":[
        "Mrukowa"
    ],
    "name:nld_x_preferred":[
        "Mrukowa"
    ],
    "name:pol_x_preferred":[
        "Mrukowa"
    ],
    "name:ukr_x_preferred":[
        "\u041c\u0440\u043e\u043a\u043e\u0432\u0430"
    ],
    "wof:name":"Mrukowa",
    "wof:placetype":"locality"
},
  "geometry": {"coordinates":[21.45191,49.59201],"type":"Point"}
}