{
  "type": "Feature",
  "properties": {
    "gn:admin1_code":"86.0",
    "gn:admin2_code":"3003.0",
    "gn:admin3_code":"300302.0",
    "gn:asciiname":"Graby",
    "gn:country_code":"PL",
    "gn:dem":118,
    "gn:feature_class":"P",
    "gn:feature_code":"PPL",
    "gn:name":"Graby",
    "gn:population":0,
    "gn:timezone":"Europe/Warsaw",
    "iso:country":"PL",
    "name:azb_x_preferred":[
        "\u0642\u0631\u0627\u0628\u0647"
    ],
    "name:fas_x_preferred":[
        "\u06af\u0631\u0627\u0628\u0647"
    ],
    "name:fra_x_preferred":[
        "Graby"
    ],
    "name:pol_x_preferred":[
        "Graby"
    ],
    "name:ukr_x_preferred":[
        "\u0490\u0440\u0430\u0431\u0438"
    ],
    "wof:name":"Graby",
    "wof:placetype":"locality"
},
  "geometry": {"coordinates":[17.41972,52.41219],"type":"Point"}
}