{
  "type": "Feature",
  "properties": {
    "gn:country":"PL",
    "gn:fcode":"PPL",
    "gn:population":370,
    "iso:country":"PL",
    "name:ast_x_preferred":[
        "Lipno"
    ],
    "name:ceb_x_preferred":[
        "Lipno"
    ],
    "name:eng_x_preferred":[
        "Lipno"
    ],
    "name:fra_x_preferred":[
        "Lipno"
    ],
    "name:pol_x_preferred":[
        "Lipno"
    ],
    "name:ukr_x_preferred":[
        "\u041b\u0456\u043f\u043d\u043e"
    ],
    "qs_pg:aaroncc":"PL",
    "qs_pg:gn_country":"PL",
    "qs_pg:gn_fcode":"PPL",
    "qs_pg:gn_pop":370,
    "qs_pg:name":"Lipno",
    "qs_pg:name_adm0":"Polska",
    "qs_pg:name_adm1":"Swi\u0119tokrzyskie",
    "qs_pg:photos_9r":0,
    "qs_pg:photos_sr":0,
    "qs_pg:pop_sr":2,
    "qs_pg:qs_pg_placetype":"locality",
    "qs_pg:qs_pg_placetype_gp":"Town",
    "qs_pg:woe_adm0":23424923,
    "woe:adm0_id":23424923,
    "woe:name_adm0":"Polska",
    "woe:name_adm1":"Swi\u0119tokrzyskie",
    "woe:placetype":"Town",
    "wof:name":"Lipno",
    "wof:placetype":"locality",
    "wof:population":370
},
  "geometry": {"coordinates":[20.11047,50.78613],"type":"Point"}
}