{
  "type": "Feature",
  "properties": {
    "gn:admin1_code":"83.0",
    "gn:admin2_code":"2417.0",
    "gn:admin3_code":"241715.0",
    "gn:asciiname":"Bednarze",
    "gn:country_code":"PL",
    "gn:dem":545,
    "gn:feature_class":"P",
    "gn:feature_code":"PPL",
    "gn:name":"Bednarze",
    "gn:population":0,
    "gn:timezone":"Europe/Warsaw",
    "iso:country":"PL",
    "name:fra_x_preferred":[
        "Bednarze"
    ],
    "name:pol_x_preferred":[
        "Bednarze"
    ],
    "name:ukr_x_preferred":[
        "\u0411\u0435\u0434\u043d\u0430\u0436\u0435"
    ],
    "wof:name":"Bednarze",
    "wof:placetype":"neighbourhood"
},
  "geometry": {"coordinates":[19.16994,49.57043],"type":"Point"}
}