{
  "type": "Feature",
  "properties": {
    "gn:admin1_code":"74.0",
    "gn:admin2_code":"1011.0",
    "gn:admin3_code":"101106.0",
    "gn:asciiname":"Charchow Panski",
    "gn:country_code":"PL",
    "gn:dem":140,
    "gn:feature_class":"P",
    "gn:feature_code":"PPL",
    "gn:name":"Charch\u00f3w Pa\u0144ski",
    "gn:population":0,
    "gn:timezone":"Europe/Warsaw",
    "iso:country":"PL",
    "name:fra_x_preferred":[
        "Charch\u00f3w Pa\u0144ski"
    ],
    "name:pol_x_preferred":[
        "Charch\u00f3w Pa\u0144ski"
    ],
    "name:ukr_x_preferred":[
        "\u0425\u0430\u0440\u0445\u0443\u0432-\u041f\u0430\u043d\u0441\u044c\u043a\u0438\u0439"
    ],
    "name:und_x_variant":[
        "Pa\u0144ski"
    ],
    "wof:name":"Charchow Panski",
    "wof:placetype":"locality"
},
  "geometry": {"coordinates":[18.85169,51.82855],"type":"Point"}
}