{
  "type": "Feature",
  "properties": {
    "gn:admin1_code":"74.0",
    "gn:admin2_code":"1013.0",
    "gn:admin3_code":"101301.0",
    "gn:asciiname":"Osada Dolna",
    "gn:country_code":"PL",
    "gn:dem":155,
    "gn:feature_class":"P",
    "gn:feature_code":"PPL",
    "gn:name":"Osada Dolna",
    "gn:population":0,
    "gn:timezone":"Europe/Warsaw",
    "iso:country":"PL",
    "wof:name":"Osada Dolna",
    "wof:placetype":"locality"
},
  "geometry": {"coordinates":[20.23812,51.74847000000001],"type":"Point"}
}