{
  "type": "Feature",
  "properties": {
    "gn:population":1300,
    "iso:country":"PL",
    "name:ast_x_preferred":[
        "M\u0119drzech\u00f3w"
    ],
    "name:deu_x_preferred":[
        "M\u0119drzech\u00f3w"
    ],
    "name:eng_x_preferred":[
        "M\u0119drzech\u00f3w"
    ],
    "name:fra_x_preferred":[
        "M\u0119drzech\u00f3w"
    ],
    "name:nld_x_preferred":[
        "M\u0119drzech\u00f3w"
    ],
    "name:pol_x_preferred":[
        "M\u0119drzech\u00f3w"
    ],
    "name:rus_x_preferred":[
        "\u041c\u0435\u043d\u0434\u0436\u0435\u0445\u0443\u0432"
    ],
    "name:swe_x_preferred":[
        "M\u0119drzech\u00f3w"
    ],
    "name:ukr_x_preferred":[
        "\u041c\u0435\u043d\u0434\u0436\u0435\u0445\u0443\u0432"
    ],
    "qs:a0":"Rzeczpospolita Polska",
    "qs:a1":"*Malopolskie",
    "qs:a1r":"0",
    "qs:a2":"Dabrowski",
    "qs:adm0":"Rzeczpospolita Polska",
    "qs:la":"M\u0119drzech\u00f3w",
    "qs:la_lc":"*PL1204042",
    "qs:level":"locality",
    "qs:loc":"M\u0119drzech\u00f3w",
    "qs:loc_alt":"Medrzechow",
    "qs:pop":0,
    "qs:type":"rural point-in-poly",
    "wd:wordcount":72,
    "wof:name":"M\u0119drzech\u00f3w",
    "wof:placetype":"locality",
    "wof:population":1300
},
  "geometry": {"coordinates":[20.9627407413697,50.2840516418738],"type":"Point"}
}