{
  "type": "Feature",
  "properties": {
    "gn:admin1_code":"85.0",
    "gn:admin2_code":"2801.0",
    "gn:admin3_code":"280103.0",
    "gn:asciiname":"Tromity",
    "gn:country_code":"PL",
    "gn:dem":43,
    "gn:feature_class":"P",
    "gn:feature_code":"PPL",
    "gn:name":"Tromity",
    "gn:population":0,
    "gn:timezone":"Europe/Warsaw",
    "iso:country":"PL",
    "name:fra_x_preferred":[
        "Tromity"
    ],
    "name:pol_x_preferred":[
        "Tromity"
    ],
    "name:ukr_x_preferred":[
        "\u0422\u0440\u043e\u043c\u0456\u0442\u0438"
    ],
    "name:vie_x_preferred":[
        "Tromity"
    ],
    "wof:name":"Tromity",
    "wof:placetype":"locality"
},
  "geometry": {"coordinates":[20.89734,54.24728],"type":"Point"}
}