{
  "type": "Feature",
  "properties": {
    "gn:admin1_code":"80.0",
    "gn:admin2_code":"1806.0",
    "gn:admin3_code":"180602.0",
    "gn:asciiname":"Wola Domatkowska",
    "gn:country_code":"PL",
    "gn:dem":221,
    "gn:feature_class":"P",
    "gn:feature_code":"PPL",
    "gn:name":"Wola Domatkowska",
    "gn:population":0,
    "gn:timezone":"Europe/Warsaw",
    "iso:country":"PL",
    "wof:name":"Wola Domatkowska",
    "wof:placetype":"locality"
},
  "geometry": {"coordinates":[21.72552,50.20362],"type":"Point"}
}