{
  "type": "Feature",
  "properties": {
    "gn:admin1_code":"82.0",
    "gn:admin2_code":"2215.0",
    "gn:admin3_code":"221504.0",
    "gn:asciiname":"Zelazno",
    "gn:country_code":"PL",
    "gn:dem":85,
    "gn:feature_class":"P",
    "gn:feature_code":"PPL",
    "gn:name":"\u017belazno",
    "gn:population":0,
    "gn:timezone":"Europe/Warsaw",
    "iso:country":"PL",
    "name:ceb_x_preferred":[
        "\u017belazno"
    ],
    "name:pol_x_preferred":[
        "\u017belazno"
    ],
    "name:und_x_variant":[
        "Hohenwaldheim",
        "Zelasen",
        "Hohenwadheim"
    ],
    "wof:name":"Zelazno",
    "wof:placetype":"locality"
},
  "geometry": {"coordinates":[17.85806000000001,54.72467],"type":"Point"}
}