{
  "type": "Feature",
  "properties": {
    "gn:admin1_code":"86.0",
    "gn:admin2_code":"3031.0",
    "gn:admin3_code":"303104.0",
    "gn:asciiname":"Kielpin",
    "gn:country_code":"PL",
    "gn:dem":151,
    "gn:feature_class":"P",
    "gn:feature_code":"PPL",
    "gn:name":"Kie\u0142pin",
    "gn:population":0,
    "gn:timezone":"Europe/Warsaw",
    "iso:country":"PL",
    "name:ceb_x_preferred":[
        "Kie\u0142pin"
    ],
    "name:fra_x_preferred":[
        "Kie\u0142pin"
    ],
    "name:pol_x_preferred":[
        "Kie\u0142pin"
    ],
    "name:ukr_x_preferred":[
        "\u041a\u0435\u043b\u043f\u0456\u043d"
    ],
    "wof:name":"Kielpin",
    "wof:placetype":"locality"
},
  "geometry": {"coordinates":[17.05833,53.49652],"type":"Point"}
}