{
  "type": "Feature",
  "properties": {
    "gn:admin1_code":"77.0",
    "gn:admin2_code":"1201.0",
    "gn:admin3_code":"120103.0",
    "gn:asciiname":"Bienkowice",
    "gn:country_code":"PL",
    "gn:dem":183,
    "gn:feature_class":"P",
    "gn:feature_code":"PPL",
    "gn:name":"Bie\u0144kowice",
    "gn:population":0,
    "gn:timezone":"Europe/Warsaw",
    "iso:country":"PL",
    "wof:name":"Bienkowice",
    "wof:placetype":"locality"
},
  "geometry": {"coordinates":[20.49697,50.09966],"type":"Point"}
}