{
  "type": "Feature",
  "properties": {
    "gn:admin1_code":"77.0",
    "gn:admin2_code":"1201.0",
    "gn:admin3_code":"120103.0",
    "gn:asciiname":"Bienkowice",
    "gn:country_code":"PL",
    "gn:dem":183,
    "gn:feature_class":"P",
    "gn:feature_code":"PPL",
    "gn:name":"Bie\u0144kowice",
    "gn:population":0,
    "gn:timezone":"Europe/Warsaw",
    "iso:country":"PL",
    "name:pol_x_preferred":[
        "Bie\u0144kowice"
    ],
    "name:ukr_x_preferred":[
        "\u0411\u0435\u043d\u044c\u043a\u043e\u0432\u0456\u0446\u0435"
    ],
    "wof:name":"Bienkowice",
    "wof:placetype":"locality"
},
  "geometry": {"coordinates":[20.49697,50.09966],"type":"Point"}
}