{
  "type": "Feature",
  "properties": {
    "gn:country":"PL",
    "gn:fcode":"PPL",
    "gn:population":720,
    "iso:country":"PL",
    "name:ast_x_preferred":[
        "Brz\u00f3stowa"
    ],
    "name:azb_x_preferred":[
        "\u0628\u0698\u0648\u0633\u062a\u0648\u0648\u0627"
    ],
    "name:ceb_x_preferred":[
        "Brz\u00f3stowa"
    ],
    "name:eng_x_preferred":[
        "Brz\u00f3stowa"
    ],
    "name:fas_x_preferred":[
        "\u0628\u0698\u0648\u0633\u062a\u0648\u0648\u0627"
    ],
    "name:fra_x_preferred":[
        "Brz\u00f3stowa"
    ],
    "name:nan_x_preferred":[
        "Brz\u00f3stowa"
    ],
    "name:nld_x_preferred":[
        "Brz\u00f3stowa"
    ],
    "name:pol_x_preferred":[
        "Brz\u00f3stowa"
    ],
    "name:ukr_x_preferred":[
        "\u0411\u0436\u0443\u0441\u0442\u043e\u0432\u0430"
    ],
    "name:und_x_variant":[
        "Brzustowa"
    ],
    "name:urd_x_preferred":[
        "\u0628\u0631\u0636\u0648\u0633\u062a\u0648\u0648\u0627"
    ],
    "qs_pg:aaroncc":"PL",
    "qs_pg:gn_country":"PL",
    "qs_pg:gn_fcode":"PPL",
    "qs_pg:gn_pop":720,
    "qs_pg:name":"Brz\u00f3stowa",
    "qs_pg:name_adm0":"Polska",
    "qs_pg:name_adm1":"Swi\u0119tokrzyskie",
    "qs_pg:photos_9r":0,
    "qs_pg:photos_sr":0,
    "qs_pg:pop_sr":2,
    "qs_pg:qs_pg_placetype":"locality",
    "qs_pg:qs_pg_placetype_gp":"Town",
    "qs_pg:woe_adm0":23424923,
    "woe:adm0_id":23424923,
    "woe:name_adm0":"Polska",
    "woe:name_adm1":"Swi\u0119tokrzyskie",
    "woe:placetype":"Town",
    "wof:name":"Brz\u00f3stowa",
    "wof:placetype":"locality",
    "wof:population":720
},
  "geometry": {"coordinates":[21.48273,50.89058],"type":"Point"}
}