{
  "type": "Feature",
  "properties": {
    "iso:country":"PL",
    "name:pol_x_preferred":[
        "Kantorowice"
    ],
    "wof:name":"Kantorowice",
    "wof:placetype":"neighbourhood"
},
  "geometry": {"coordinates":[20.05527283196338,50.10909942367716],"type":"Point"}
}