{
  "type": "Feature",
  "properties": {
    "gn:admin1_code":"74.0",
    "gn:admin2_code":"1010.0",
    "gn:admin3_code":"101006.0",
    "gn:asciiname":"Podolin",
    "gn:country_code":"PL",
    "gn:dem":209,
    "gn:feature_class":"P",
    "gn:feature_code":"PPL",
    "gn:name":"Podolin",
    "gn:population":0,
    "gn:timezone":"Europe/Warsaw",
    "iso:country":"PL",
    "name:fra_x_preferred":[
        "Podolin"
    ],
    "name:pol_x_preferred":[
        "Podolin"
    ],
    "name:ukr_x_preferred":[
        "\u041f\u043e\u0434\u043e\u043b\u0456\u043d"
    ],
    "wof:name":"Podolin",
    "wof:placetype":"locality"
},
  "geometry": {"coordinates":[19.65173,51.54507],"type":"Point"}
}