{
  "type": "Feature",
  "properties": {
    "gn:admin1_code":"77.0",
    "gn:admin2_code":"1211.0",
    "gn:admin3_code":"121110.0",
    "gn:asciiname":"Tylmanowa",
    "gn:country_code":"PL",
    "gn:dem":411,
    "gn:feature_class":"P",
    "gn:feature_code":"PPL",
    "gn:name":"Tylmanowa",
    "gn:population":0,
    "gn:timezone":"Europe/Warsaw",
    "iso:country":"PL",
    "wof:name":"Tylmanowa",
    "wof:placetype":"locality"
},
  "geometry": {"coordinates":[20.39575,49.51001],"type":"Point"}
}