{
  "type": "Feature",
  "properties": {
    "gn:admin1_code":"77.0",
    "gn:admin2_code":"1211.0",
    "gn:admin3_code":"121110.0",
    "gn:asciiname":"Tylmanowa",
    "gn:country_code":"PL",
    "gn:dem":411,
    "gn:feature_class":"P",
    "gn:feature_code":"PPL",
    "gn:name":"Tylmanowa",
    "gn:population":0,
    "gn:timezone":"Europe/Warsaw",
    "iso:country":"PL",
    "name:azb_x_preferred":[
        "\u062a\u06cc\u0644\u0645\u0627\u0646\u0648\u0627"
    ],
    "name:ceb_x_preferred":[
        "Tylmanowa"
    ],
    "name:deu_x_preferred":[
        "Tylmanowa"
    ],
    "name:fas_x_preferred":[
        "\u062a\u06cc\u0644\u0645\u0627\u0646\u0648\u0627"
    ],
    "name:pol_x_preferred":[
        "Tylmanowa"
    ],
    "name:ukr_x_preferred":[
        "\u0422\u0438\u043b\u044c\u043c\u0430\u043d\u043e\u0432\u0430"
    ],
    "wof:name":"Tylmanowa",
    "wof:placetype":"locality"
},
  "geometry": {"coordinates":[20.39575,49.51001],"type":"Point"}
}