{
  "type": "Feature",
  "properties": {
    "gn:admin1_code":"84.0",
    "gn:admin2_code":"2607.0",
    "gn:admin3_code":"260703.0",
    "gn:asciiname":"Kolonia Boksycka",
    "gn:country_code":"PL",
    "gn:dem":224,
    "gn:feature_class":"P",
    "gn:feature_code":"PPL",
    "gn:name":"Kolonia Boksycka",
    "gn:population":0,
    "gn:timezone":"Europe/Warsaw",
    "iso:country":"PL",
    "wof:name":"Kolonia Boksycka",
    "wof:placetype":"locality"
},
  "geometry": {"coordinates":[21.33333,50.93333],"type":"Point"}
}