{
  "type": "Feature",
  "properties": {
    "gn:admin1_code":"74.0",
    "gn:admin2_code":"1010.0",
    "gn:admin3_code":"101003.0",
    "gn:asciiname":"Wola Kotkowska",
    "gn:country_code":"PL",
    "gn:dem":230,
    "gn:feature_class":"P",
    "gn:feature_code":"PPL",
    "gn:name":"Wola Kotkowska",
    "gn:population":0,
    "gn:timezone":"Europe/Warsaw",
    "iso:country":"PL",
    "name:fra_x_preferred":[
        "Wola Kotkowska"
    ],
    "name:pol_x_preferred":[
        "Wola Kotkowska"
    ],
    "name:ukr_x_preferred":[
        "\u0412\u043e\u043b\u044f-\u041a\u043e\u0442\u043a\u043e\u0432\u0441\u044c\u043a\u0430"
    ],
    "name:und_x_variant":[
        "Kotkowska Wola"
    ],
    "wof:name":"Wola Kotkowska",
    "wof:placetype":"locality"
},
  "geometry": {"coordinates":[19.61517000000001,51.15866],"type":"Point"}
}