{
  "type": "Feature",
  "properties": {
    "gn:admin1_code":"74.0",
    "gn:admin2_code":"1010.0",
    "gn:admin3_code":"101003.0",
    "gn:asciiname":"Wola Kotkowska",
    "gn:country_code":"PL",
    "gn:dem":230,
    "gn:feature_class":"P",
    "gn:feature_code":"PPL",
    "gn:name":"Wola Kotkowska",
    "gn:population":0,
    "gn:timezone":"Europe/Warsaw",
    "iso:country":"PL",
    "name:und_x_variant":[
        "Kotkowska Wola",
        "Wola Kotkowska"
    ],
    "wof:name":"Wola Kotkowska",
    "wof:placetype":"locality"
},
  "geometry": {"coordinates":[19.61517000000001,51.15866],"type":"Point"}
}