{
  "type": "Feature",
  "properties": {
    "gn:admin1_code":"72.0",
    "gn:admin2_code":"205.0",
    "gn:admin3_code":"20506.0",
    "gn:asciiname":"Granowice",
    "gn:country_code":"PL",
    "gn:dem":181,
    "gn:feature_class":"P",
    "gn:feature_code":"PPL",
    "gn:name":"Granowice",
    "gn:population":0,
    "gn:timezone":"Europe/Warsaw",
    "iso:country":"PL",
    "name:deu_x_historical":[
        "Gr\u00e4nowitz"
    ],
    "name:deu_x_preferred":[
        "Gr\u00e4nowitz"
    ],
    "name:pol_x_preferred":[
        "Granowice"
    ],
    "name:ukr_x_preferred":[
        "\u0490\u0440\u0430\u043d\u043e\u0432\u0456\u0446\u0435"
    ],
    "wof:name":"Granowice",
    "wof:placetype":"locality"
},
  "geometry": {"coordinates":[16.35083,51.07732],"type":"Point"}
}