{
  "type": "Feature",
  "properties": {
    "gn:admin1_code":"83.0",
    "gn:admin2_code":"2403.0",
    "gn:admin3_code":"240308.0",
    "gn:asciiname":"Brzezowka",
    "gn:country_code":"PL",
    "gn:dem":283,
    "gn:feature_class":"P",
    "gn:feature_code":"PPL",
    "gn:name":"Brzez\u00f3wka",
    "gn:population":0,
    "gn:timezone":"Europe/Warsaw",
    "iso:country":"PL",
    "name:azb_x_preferred":[
        "\u0628\u0698\u0632\u0648\u0648\u06a9\u0627"
    ],
    "name:ceb_x_preferred":[
        "Brzez\u00f3wka"
    ],
    "name:ces_x_preferred":[
        "B\u0159ez\u016fvka"
    ],
    "name:deu_x_preferred":[
        "Brzez\u00f3wka"
    ],
    "name:fas_x_preferred":[
        "\u0628\u0698\u0632\u0648\u0648\u06a9\u0627"
    ],
    "name:pol_x_preferred":[
        "Brzez\u00f3wka"
    ],
    "name:ukr_x_preferred":[
        "\u0411\u0436\u0435\u0437\u0443\u0432\u043a\u0430"
    ],
    "name:und_x_variant":[
        "Brzez\u00f3wka"
    ],
    "name:urd_x_preferred":[
        "\u0628\u0631\u0632\u06cc\u0632\u0648\u0648\u06a9\u0627"
    ],
    "wof:name":"Brzezowka",
    "wof:placetype":"locality"
},
  "geometry": {"coordinates":[18.62321,49.8132],"type":"Point"}
}