{
  "type": "Feature",
  "properties": {
    "gn:admin1_code":"72.0",
    "gn:admin2_code":"219.0",
    "gn:admin3_code":"21903.0",
    "gn:asciiname":"Pietrzykow",
    "gn:country_code":"PL",
    "gn:dem":345,
    "gn:feature_class":"P",
    "gn:feature_code":"PPL",
    "gn:name":"Pietrzyk\u00f3w",
    "gn:population":0,
    "gn:timezone":"Europe/Warsaw",
    "iso:country":"PL",
    "name:pol_x_preferred":[
        "Pietrzyk\u00f3w"
    ],
    "name:ukr_x_preferred":[
        "\u041f\u0435\u0442\u0448\u0438\u043a\u0443\u0432"
    ],
    "wof:name":"Pietrzykow",
    "wof:placetype":"locality"
},
  "geometry": {"coordinates":[16.22234,50.89556],"type":"Point"}
}