{
  "type": "Feature",
  "properties": {
    "gn:admin1_code":"80.0",
    "gn:admin2_code":"1809.0",
    "gn:admin3_code":"180905.0",
    "gn:asciiname":"Zagrody",
    "gn:country_code":"PL",
    "gn:dem":336,
    "gn:feature_class":"P",
    "gn:feature_code":"PPL",
    "gn:name":"Zagrody",
    "gn:population":0,
    "gn:timezone":"Europe/Warsaw",
    "iso:country":"PL",
    "name:fra_x_preferred":[
        "Zagrody"
    ],
    "name:pol_x_preferred":[
        "Zagrody"
    ],
    "name:ukr_x_preferred":[
        "\u0417\u0430\u0491\u0440\u043e\u0434\u0438"
    ],
    "wof:name":"Zagrody",
    "wof:placetype":"locality"
},
  "geometry": {"coordinates":[23.35,50.28333],"type":"Point"}
}