{
  "type": "Feature",
  "properties": {
    "gn:admin1_code":"77.0",
    "gn:admin2_code":"1210.0",
    "gn:admin3_code":"121005.0",
    "gn:asciiname":"Krolowa Polska",
    "gn:country_code":"PL",
    "gn:dem":393,
    "gn:feature_class":"P",
    "gn:feature_code":"PPL",
    "gn:name":"Kr\u00f3lowa Polska",
    "gn:population":0,
    "gn:timezone":"Europe/Warsaw",
    "iso:country":"PL",
    "name:pol_x_preferred":[
        "Kr\u00f3lowa Polska"
    ],
    "name:ukr_x_preferred":[
        "\u041a\u0440\u0443\u043b\u044c\u043e\u0432\u0430-\u041f\u043e\u043b\u044c\u0441\u044c\u043a\u0430"
    ],
    "name:und_x_variant":[
        "Kr\u00f3lowa Polska"
    ],
    "wof:name":"Krolowa Polska",
    "wof:placetype":"locality"
},
  "geometry": {"coordinates":[20.81345,49.58391],"type":"Point"}
}