{
  "type": "Feature",
  "properties": {
    "gn:country":"PL",
    "gn:fcode":"PPL",
    "gn:population":216,
    "iso:country":"PL",
    "name:ast_x_preferred":[
        "Janikowo"
    ],
    "name:ceb_x_preferred":[
        "Janikowo"
    ],
    "name:ces_x_preferred":[
        "Janikowo"
    ],
    "name:che_x_preferred":[
        "\u042f\u043d\u0438\u043a\u043e\u0432\u043e"
    ],
    "name:eng_x_preferred":[
        "Janikowo"
    ],
    "name:fra_x_preferred":[
        "Janikowo"
    ],
    "name:nan_x_preferred":[
        "Janikowo"
    ],
    "name:pol_x_preferred":[
        "Janikowo"
    ],
    "name:tat_x_preferred":[
        "\u042f\u043d\u0438\u043a\u043e\u0432\u043e"
    ],
    "name:ukr_x_preferred":[
        "\u042f\u043d\u0456\u043a\u043e\u0432\u043e"
    ],
    "name:urd_x_preferred":[
        "\u062c\u0627\u0646\u06a9\u0648\u0648\u060c \u0645\u0633\u0648\u0648\u06cc\u0627\u06ba \u0635\u0648\u0628\u06c1"
    ],
    "name:urd_x_variant":[
        "\u062c\u0627\u0646\u06a9\u0648\u0648"
    ],
    "qs_pg:aaroncc":"PL",
    "qs_pg:gn_country":"PL",
    "qs_pg:gn_fcode":"PPL",
    "qs_pg:gn_pop":216,
    "qs_pg:name":"Janikowo",
    "qs_pg:name_adm0":"Polska",
    "qs_pg:name_adm1":"Mazowieckie",
    "qs_pg:photos_9r":0,
    "qs_pg:photos_sr":0,
    "qs_pg:pop_sr":2,
    "qs_pg:qs_pg_placetype":"locality",
    "qs_pg:qs_pg_placetype_gp":"Town",
    "qs_pg:woe_adm0":23424923,
    "woe:adm0_id":23424923,
    "woe:name_adm0":"Polska",
    "woe:name_adm1":"Mazowieckie",
    "woe:placetype":"Town",
    "wof:name":"Janikowo",
    "wof:placetype":"locality",
    "wof:population":216
},
  "geometry": {"coordinates":[20.29896,52.42697],"type":"Point"}
}