{
  "type": "Feature",
  "properties": {
    "gn:admin1_code":"78.0",
    "gn:admin2_code":"1414.0",
    "gn:admin3_code":"141404.0",
    "gn:asciiname":"Morgi",
    "gn:country_code":"PL",
    "gn:dem":101,
    "gn:feature_class":"P",
    "gn:feature_code":"PPL",
    "gn:name":"Morgi",
    "gn:population":0,
    "gn:timezone":"Europe/Warsaw",
    "iso:country":"PL",
    "name:fra_x_preferred":[
        "Morgi"
    ],
    "name:lit_x_preferred":[
        "Morgai"
    ],
    "name:pol_x_preferred":[
        "Morgi"
    ],
    "name:ukr_x_preferred":[
        "\u041c\u043e\u0440\u0491\u0456"
    ],
    "wof:name":"Morgi",
    "wof:placetype":"locality"
},
  "geometry": {"coordinates":[20.74294,52.5668],"type":"Point"}
}