{
  "type": "Feature",
  "properties": {
    "gn:admin1_code":"85.0",
    "gn:admin2_code":"2802.0",
    "gn:admin3_code":"280204.0",
    "gn:asciiname":"Glebock",
    "gn:cc2":"PL",
    "gn:country_code":"PL",
    "gn:dem":127,
    "gn:feature_class":"P",
    "gn:feature_code":"PPL",
    "gn:name":"G\u0142\u0119bock",
    "gn:population":0,
    "gn:timezone":"Europe/Warsaw",
    "iso:country":"PL",
    "name:azb_x_preferred":[
        "\u0642\u0648\u0646\u0628\u0648\u062a\u0633\u06a9"
    ],
    "name:ceb_x_preferred":[
        "G\u0142\u0119bock"
    ],
    "name:deu_x_preferred":[
        "G\u0142\u0119bock"
    ],
    "name:fas_x_preferred":[
        "\u06af\u0648\u0646\u0628\u0648\u062a\u0633\u06a9"
    ],
    "name:fra_x_preferred":[
        "G\u0142\u0119bock"
    ],
    "name:pol_x_preferred":[
        "G\u0142\u0119bock"
    ],
    "name:ukr_x_preferred":[
        "\u0490\u043b\u0435\u043c\u0431\u043e\u0446\u044c\u043a"
    ],
    "name:und_x_variant":[
        "Tiefensee"
    ],
    "wof:name":"Glebock",
    "wof:placetype":"locality"
},
  "geometry": {"coordinates":[20.2739,54.37906],"type":"Point"}
}