{
  "type": "Feature",
  "properties": {
    "gn:admin1_code":"85.0",
    "gn:admin2_code":"2801.0",
    "gn:admin3_code":"280105.0",
    "gn:asciiname":"Kiwajny",
    "gn:cc2":"PL",
    "gn:country_code":"PL",
    "gn:dem":140,
    "gn:feature_class":"P",
    "gn:feature_code":"PPL",
    "gn:name":"Kiwajny",
    "gn:population":0,
    "gn:timezone":"Europe/Warsaw",
    "iso:country":"PL",
    "name:fra_x_preferred":[
        "Kiwajny"
    ],
    "name:pol_x_preferred":[
        "Kiwajny"
    ],
    "name:ukr_x_preferred":[
        "\u041a\u0456\u0432\u0430\u0439\u043d\u0438"
    ],
    "name:und_x_variant":[
        "Quehnen"
    ],
    "wof:name":"Kiwajny",
    "wof:placetype":"locality"
},
  "geometry": {"coordinates":[20.39097000000001,54.37296],"type":"Point"}
}