{
  "type": "Feature",
  "properties": {
    "gn:admin1_code":"81.0",
    "gn:admin2_code":"2002.0",
    "gn:admin3_code":"200204.0",
    "gn:asciiname":"Zaluki",
    "gn:country_code":"PL",
    "gn:dem":137,
    "gn:feature_class":"P",
    "gn:feature_code":"PPL",
    "gn:name":"Za\u0142uki",
    "gn:population":0,
    "gn:timezone":"Europe/Warsaw",
    "iso:country":"PL",
    "name:azb_x_preferred":[
        "\u0632\u0627\u0648\u0648\u06a9\u06cc"
    ],
    "name:ceb_x_preferred":[
        "Za\u0142uki"
    ],
    "name:fas_x_preferred":[
        "\u0632\u0627\u0648\u0648\u06a9\u06cc"
    ],
    "name:fra_x_preferred":[
        "Za\u0142uki"
    ],
    "name:lit_x_preferred":[
        "Zalukai"
    ],
    "name:pol_x_preferred":[
        "Za\u0142uki"
    ],
    "name:ukr_x_preferred":[
        "\u0417\u0430\u043b\u0443\u043a\u0456"
    ],
    "name:und_x_variant":[
        "Za\u0142uki"
    ],
    "wof:name":"Zaluki",
    "wof:placetype":"locality"
},
  "geometry": {"coordinates":[23.54407,53.15943000000001],"type":"Point"}
}