{
  "type": "Feature",
  "properties": {
    "gn:admin1_code":"74.0",
    "gn:admin2_code":"1011.0",
    "gn:admin3_code":"101103.0",
    "gn:asciiname":"Zagorzyce",
    "gn:country_code":"PL",
    "gn:dem":123,
    "gn:feature_class":"P",
    "gn:feature_code":"PPL",
    "gn:name":"Zag\u00f3rzyce",
    "gn:population":0,
    "gn:timezone":"Europe/Warsaw",
    "iso:country":"PL",
    "name:fra_x_preferred":[
        "Zag\u00f3rzyce"
    ],
    "name:pol_x_preferred":[
        "Zag\u00f3rzyce"
    ],
    "name:ukr_x_preferred":[
        "\u0417\u0430\u0491\u0443\u0436\u0438\u0446\u0435"
    ],
    "name:urd_x_preferred":[
        "\u0632\u06af\u0648\u0631\u0636\u06cc\u06a9\u06d2"
    ],
    "wof:name":"Zagorzyce",
    "wof:placetype":"locality"
},
  "geometry": {"coordinates":[18.93712,51.85922],"type":"Point"}
}