{
  "type": "Feature",
  "properties": {
    "gn:population":1410,
    "iso:country":"PL",
    "name:ast_x_preferred":[
        "Ma\u0142dyty"
    ],
    "name:ceb_x_preferred":[
        "Ma\u0142dyty"
    ],
    "name:deu_x_preferred":[
        "Ma\u0142dyty"
    ],
    "name:eng_x_preferred":[
        "Ma\u0142dyty"
    ],
    "name:fra_x_preferred":[
        "Ma\u0142dyty"
    ],
    "name:nld_x_preferred":[
        "Ma\u0142dyty"
    ],
    "name:pol_x_preferred":[
        "Ma\u0142dyty"
    ],
    "name:rus_x_preferred":[
        "\u041c\u0430\u043b\u0434\u044b\u0442\u044b"
    ],
    "name:ukr_x_preferred":[
        "\u041c\u0430\u043b\u0434\u0438\u0442\u0438"
    ],
    "name:und_x_variant":[
        "Maldeuten"
    ],
    "qs:a0":"Rzeczpospolita Polska",
    "qs:a1":"*Warminsko-mazurskie",
    "qs:a1r":"0",
    "qs:a2":"Ostr\u00f3dzki",
    "qs:adm0":"Rzeczpospolita Polska",
    "qs:la":"Ma\u0142dyty",
    "qs:la_lc":"*PL2815052",
    "qs:level":"locality",
    "qs:loc":"Ma\u0142dyty",
    "qs:loc_alt":"Maldyty",
    "qs:pop":0,
    "qs:type":"rural point-in-poly",
    "wd:wordcount":117,
    "wof:coterminous":[
        1477752789
    ],
    "wof:name":"Ma\u0142dyty",
    "wof:placetype":"locality",
    "wof:population":1410
},
  "geometry": {"coordinates":[19.7417134592154,53.9103054718838],"type":"Point"}
}