{
  "type": "Feature",
  "properties": {
    "gn:admin1_code":"78.0",
    "gn:admin2_code":"1421.0",
    "gn:admin3_code":"142103.0",
    "gn:asciiname":"Czubin",
    "gn:country_code":"PL",
    "gn:dem":86,
    "gn:feature_class":"P",
    "gn:feature_code":"PPL",
    "gn:name":"Czubin",
    "gn:population":0,
    "gn:timezone":"Europe/Warsaw",
    "iso:country":"PL",
    "name:ceb_x_preferred":[
        "Czubin"
    ],
    "name:ces_x_preferred":[
        "Czubin"
    ],
    "name:fra_x_preferred":[
        "Czubin"
    ],
    "name:pol_x_preferred":[
        "Czubin"
    ],
    "name:ukr_x_preferred":[
        "\u0427\u0443\u0431\u0456\u043d"
    ],
    "wof:name":"Czubin",
    "wof:placetype":"locality"
},
  "geometry": {"coordinates":[20.66681,52.1775],"type":"Point"}
}