{
  "type": "Feature",
  "properties": {
    "gn:admin1_code":"86.0",
    "gn:admin2_code":"3027.0",
    "gn:admin3_code":"302709.0",
    "gn:asciiname":"Beznazwa",
    "gn:country_code":"PL",
    "gn:dem":93,
    "gn:feature_class":"P",
    "gn:feature_code":"PPL",
    "gn:name":"Beznazwa",
    "gn:population":0,
    "gn:timezone":"Europe/Warsaw",
    "iso:country":"PL",
    "name:ceb_x_preferred":[
        "Beznazwa"
    ],
    "name:nld_x_preferred":[
        "Beznazwa"
    ],
    "name:pol_x_preferred":[
        "Beznazwa"
    ],
    "name:ukr_x_preferred":[
        "\u0411\u0435\u0437\u043d\u0430\u0437\u0432\u0430"
    ],
    "wof:name":"Beznazwa",
    "wof:placetype":"locality"
},
  "geometry": {"coordinates":[18.41029,52.14821],"type":"Point"}
}