{
  "type": "Feature",
  "properties": {
    "gn:country":"PL",
    "gn:fcode":"PPL",
    "gn:population":297,
    "iso:country":"PL",
    "name:ceb_x_preferred":[
        "Aleksandr\u00f3w"
    ],
    "name:deu_x_preferred":[
        "Aleksandr\u00f3w"
    ],
    "name:fra_x_preferred":[
        "Aleksandr\u00f3w"
    ],
    "name:hsb_x_preferred":[
        "Aleksandr\u00f3w"
    ],
    "name:ita_x_preferred":[
        "Aleksandr\u00f3w"
    ],
    "name:nld_x_preferred":[
        "Aleksandr\u00f3w"
    ],
    "name:pol_x_preferred":[
        "Aleksandr\u00f3w"
    ],
    "name:ron_x_preferred":[
        "Aleksandr\u00f3w"
    ],
    "name:rus_x_preferred":[
        "\u0410\u043b\u0435\u043a\u0441\u0430\u043d\u0434\u0440\u0443\u0432"
    ],
    "name:ukr_x_preferred":[
        "\u0410\u043b\u0435\u043a\u0441\u0430\u043d\u0434\u0440\u0443\u0432"
    ],
    "name:yid_x_preferred":[
        "\u05d0\u05dc\u05e2\u05e7\u05e1\u05d0\u05e0\u05d3\u05e2\u05e8"
    ],
    "qs_pg:aaroncc":"PL",
    "qs_pg:gn_country":"PL",
    "qs_pg:gn_fcode":"PPL",
    "qs_pg:gn_pop":297,
    "qs_pg:name":"Aleksandr\u00f3w",
    "qs_pg:name_adm0":"Polska",
    "qs_pg:name_adm1":"Wielkopolskie",
    "qs_pg:photos_9r":0,
    "qs_pg:photos_sr":0,
    "qs_pg:pop_sr":2,
    "qs_pg:qs_pg_placetype":"locality",
    "qs_pg:qs_pg_placetype_gp":"Town",
    "qs_pg:woe_adm0":23424923,
    "woe:adm0_id":23424923,
    "woe:name_adm0":"Polska",
    "woe:name_adm1":"Wielkopolskie",
    "woe:placetype":"Town",
    "wof:name":"Aleksandr\u00f3w",
    "wof:placetype":"locality",
    "wof:population":297
},
  "geometry": {"coordinates":[17.4099,52.06215],"type":"Point"}
}