{
  "type": "Feature",
  "properties": {
    "gn:country":"PL",
    "gn:fcode":"PPLA3",
    "gn:population":2100,
    "iso:country":"PL",
    "name:azb_x_preferred":[
        "\u0645\u06cc\u0698\u062a\u0633"
    ],
    "name:ceb_x_preferred":[
        "Mirzec"
    ],
    "name:deu_x_preferred":[
        "Mirzec"
    ],
    "name:fas_x_preferred":[
        "\u0645\u06cc\u0698\u062a\u0633"
    ],
    "name:fra_x_preferred":[
        "Mirzec"
    ],
    "name:nld_x_preferred":[
        "Mirzec"
    ],
    "name:pol_x_preferred":[
        "Mirzec"
    ],
    "name:ukr_x_preferred":[
        "\u041c\u0456\u0436\u0435\u0446\u044c"
    ],
    "qs_pg:aaroncc":"PL",
    "qs_pg:gn_country":"PL",
    "qs_pg:gn_fcode":"PPLA3",
    "qs_pg:gn_pop":2100,
    "qs_pg:name":"Mirzec",
    "qs_pg:name_adm0":"Polska",
    "qs_pg:name_adm1":"Swi\u0119tokrzyskie",
    "qs_pg:photos_9k":1,
    "qs_pg:photos_9r":1,
    "qs_pg:photos_all":3,
    "qs_pg:photos_sr":0,
    "qs_pg:pop_sr":4,
    "qs_pg:qs_pg_placetype":"localadmin",
    "qs_pg:qs_pg_placetype_gp":"LocalAdmin",
    "qs_pg:woe_adm0":23424923,
    "woe:adm0_id":23424923,
    "woe:name_adm0":"Polska",
    "woe:name_adm1":"Swi\u0119tokrzyskie",
    "woe:placetype":"LocalAdmin",
    "wof:name":"Mirzec",
    "wof:placetype":"localadmin",
    "wof:population":2100
},
  "geometry": {"coordinates":[21.0571,51.13466],"type":"Point"}
}