{
  "type": "Feature",
  "properties": {
    "gn:admin1_code":"85.0",
    "gn:admin2_code":"2809.0",
    "gn:admin3_code":"280902.0",
    "gn:asciiname":"Klajty",
    "gn:country_code":"PL",
    "gn:dem":113,
    "gn:feature_class":"P",
    "gn:feature_code":"PPL",
    "gn:name":"K\u0142ajty",
    "gn:population":0,
    "gn:timezone":"Europe/Warsaw",
    "iso:country":"PL",
    "name:und_x_variant":[
        "Cloytz",
        "Kleitz",
        "K\u0142ajty"
    ],
    "wof:name":"Klajty",
    "wof:placetype":"locality"
},
  "geometry": {"coordinates":[20.66467,54.10287],"type":"Point"}
}