{
  "type": "Feature",
  "properties": {
    "gn:admin1_code":"84.0",
    "gn:admin2_code":"2604.0",
    "gn:admin3_code":"260410.0",
    "gn:asciiname":"Cminsk Wykien",
    "gn:country_code":"PL",
    "gn:dem":277,
    "gn:feature_class":"P",
    "gn:feature_code":"PPL",
    "gn:name":"\u0106mi\u0144sk Wykie\u0144",
    "gn:population":0,
    "gn:timezone":"Europe/Warsaw",
    "iso:country":"PL",
    "name:und_x_variant":[
        "Wykie\u0144",
        "\u0106mi\u0144sk Wykie\u0144"
    ],
    "wof:name":"Cminsk Wykien",
    "wof:placetype":"locality"
},
  "geometry": {"coordinates":[20.54809,50.96374],"type":"Point"}
}