{
  "type": "Feature",
  "properties": {
    "gn:admin1_code":"83.0",
    "gn:admin2_code":"2402.0",
    "gn:admin3_code":"240204.0",
    "gn:asciiname":"Brozisko",
    "gn:country_code":"PL",
    "gn:dem":267,
    "gn:feature_class":"P",
    "gn:feature_code":"PPL",
    "gn:name":"Brozisko",
    "gn:population":0,
    "gn:timezone":"Europe/Warsaw",
    "iso:country":"PL",
    "wof:name":"Brozisko",
    "wof:placetype":"neighbourhood"
},
  "geometry": {"coordinates":[19.03333,49.88333],"type":"Point"}
}