{
  "type": "Feature",
  "properties": {
    "gn:admin1_code":"86.0",
    "gn:admin2_code":"3016.0",
    "gn:admin3_code":"301601.0",
    "gn:asciiname":"Stobnica",
    "gn:country_code":"PL",
    "gn:dem":52,
    "gn:feature_class":"P",
    "gn:feature_code":"PPL",
    "gn:name":"Stobnica",
    "gn:population":0,
    "gn:timezone":"Europe/Warsaw",
    "iso:country":"PL",
    "name:ceb_x_preferred":[
        "Stobnica"
    ],
    "name:fra_x_preferred":[
        "Stobnica"
    ],
    "name:pol_x_preferred":[
        "Stobnica"
    ],
    "name:ukr_x_preferred":[
        "\u0421\u0442\u043e\u0431\u043d\u0438\u0446\u044f"
    ],
    "wof:name":"Stobnica",
    "wof:placetype":"locality"
},
  "geometry": {"coordinates":[16.6083,52.70506],"type":"Point"}
}