{
  "type": "Feature",
  "properties": {
    "gn:admin1_code":"80.0",
    "gn:admin2_code":"1817.0",
    "gn:admin3_code":"181704.0",
    "gn:asciiname":"Mikow",
    "gn:country_code":"PL",
    "gn:dem":511,
    "gn:feature_class":"P",
    "gn:feature_code":"PPL",
    "gn:name":"Mik\u00f3w",
    "gn:population":0,
    "gn:timezone":"Europe/Warsaw",
    "iso:country":"PL",
    "name:nld_x_preferred":[
        "Mik\u00f3w"
    ],
    "name:pol_x_preferred":[
        "Mik\u00f3w"
    ],
    "name:ukr_x_preferred":[
        "\u041c\u0438\u043a\u0456\u0432"
    ],
    "wof:name":"Mikow",
    "wof:placetype":"locality"
},
  "geometry": {"coordinates":[22.11823,49.28886],"type":"Point"}
}