{
  "type": "Feature",
  "properties": {
    "gn:country":"PL",
    "gn:fcode":"PPL",
    "gn:population":294,
    "iso:country":"PL",
    "name:ceb_x_preferred":[
        "Roszkowo"
    ],
    "name:deu_x_preferred":[
        "Roszkowo"
    ],
    "name:fra_x_preferred":[
        "Roszkowo"
    ],
    "name:pol_x_preferred":[
        "Roszkowo"
    ],
    "name:ukr_x_preferred":[
        "\u0420\u043e\u0448\u043a\u043e\u0432\u043e"
    ],
    "qs_pg:aaroncc":"PL",
    "qs_pg:gn_country":"PL",
    "qs_pg:gn_fcode":"PPL",
    "qs_pg:gn_pop":294,
    "qs_pg:name":"Roszkowo",
    "qs_pg:name_adm0":"Polska",
    "qs_pg:name_adm1":"Wielkopolskie",
    "qs_pg:photos_9r":0,
    "qs_pg:photos_sr":0,
    "qs_pg:pop_sr":2,
    "qs_pg:qs_pg_placetype":"locality",
    "qs_pg:qs_pg_placetype_gp":"Town",
    "qs_pg:woe_adm0":23424923,
    "woe:adm0_id":23424923,
    "woe:name_adm0":"Polska",
    "woe:name_adm1":"Wielkopolskie",
    "woe:placetype":"Town",
    "wof:name":"Roszkowo",
    "wof:placetype":"locality",
    "wof:population":294
},
  "geometry": {"coordinates":[16.92444,51.68586],"type":"Point"}
}