{
  "type": "Feature",
  "properties": {
    "gn:admin1_code":"85.0",
    "gn:admin2_code":"2803.0",
    "gn:admin3_code":"280302.0",
    "gn:asciiname":"Gnojno",
    "gn:country_code":"PL",
    "gn:dem":149,
    "gn:feature_class":"P",
    "gn:feature_code":"PPL",
    "gn:name":"Gnojno",
    "gn:population":0,
    "gn:timezone":"Europe/Warsaw",
    "iso:country":"PL",
    "wof:name":"Gnojno",
    "wof:placetype":"locality"
},
  "geometry": {"coordinates":[20.10172,53.17651],"type":"Point"}
}