{
  "type": "Feature",
  "properties": {
    "gn:admin1_code":"80.0",
    "gn:admin2_code":"1807.0",
    "gn:admin3_code":"180710.0",
    "gn:asciiname":"Wola Nizna",
    "gn:country_code":"PL",
    "gn:dem":467,
    "gn:feature_class":"P",
    "gn:feature_code":"PPL",
    "gn:name":"Wola Ni\u017cna",
    "gn:population":0,
    "gn:timezone":"Europe/Warsaw",
    "iso:country":"PL",
    "name:ceb_x_preferred":[
        "Wola Ni\u017cna"
    ],
    "name:pol_x_preferred":[
        "Wola Ni\u017cna"
    ],
    "name:ukr_x_preferred":[
        "\u0412\u043e\u043b\u044f \u041d\u0438\u0436\u043d\u044f"
    ],
    "name:und_x_variant":[
        "Wola Ni\u017cna"
    ],
    "wof:name":"Wola Nizna",
    "wof:placetype":"locality"
},
  "geometry": {"coordinates":[21.84933,49.42944],"type":"Point"}
}