{
  "type": "Feature",
  "properties": {
    "gn:admin1_code":"74.0",
    "gn:admin2_code":"1015.0",
    "gn:admin3_code":"101502.0",
    "gn:asciiname":"Janislawice",
    "gn:country_code":"PL",
    "gn:dem":152,
    "gn:feature_class":"P",
    "gn:feature_code":"PPL",
    "gn:name":"Janis\u0142awice",
    "gn:population":0,
    "gn:timezone":"Europe/Warsaw",
    "iso:country":"PL",
    "name:pol_x_preferred":[
        "Janis\u0142awice"
    ],
    "name:ukr_x_preferred":[
        "\u042f\u043d\u0456\u0441\u043b\u0430\u0432\u0456\u0446\u0435"
    ],
    "name:und_x_variant":[
        "Janis\u0142awice"
    ],
    "name:urd_x_preferred":[
        "\u062c\u0646\u0633\u0648\u0627\u0648\u06a9\u06d2"
    ],
    "wof:name":"Janislawice",
    "wof:placetype":"locality"
},
  "geometry": {"coordinates":[20.05345,51.84578],"type":"Point"}
}