{
  "type": "Feature",
  "properties": {
    "gn:admin1_code":"75.0",
    "gn:admin2_code":"617.0",
    "gn:admin3_code":"61703.0",
    "gn:asciiname":"Mlodziejow",
    "gn:country_code":"PL",
    "gn:dem":195,
    "gn:feature_class":"P",
    "gn:feature_code":"PPL",
    "gn:name":"M\u0142odziej\u00f3w",
    "gn:population":0,
    "gn:timezone":"Europe/Warsaw",
    "iso:country":"PL",
    "name:fra_x_preferred":[
        "M\u0142odziej\u00f3w"
    ],
    "name:pol_x_preferred":[
        "M\u0142odziej\u00f3w"
    ],
    "name:ukr_x_preferred":[
        "\u041c\u043b\u043e\u0434\u0437\u0435\u044e\u0432"
    ],
    "name:und_x_variant":[
        "M\u0142odziej\u00f3w"
    ],
    "wof:name":"Mlodziejow",
    "wof:placetype":"locality"
},
  "geometry": {"coordinates":[22.87854,51.11296],"type":"Point"}
}