{
  "type": "Feature",
  "properties": {
    "gn:admin1_code":"86.0",
    "gn:admin2_code":"3006.0",
    "gn:admin3_code":"300601.0",
    "gn:asciiname":"Gola",
    "gn:country_code":"PL",
    "gn:dem":103,
    "gn:feature_class":"P",
    "gn:feature_code":"PPL",
    "gn:name":"Gola",
    "gn:population":0,
    "gn:timezone":"Europe/Warsaw",
    "iso:country":"PL",
    "name:bre_x_preferred":[
        "Gola"
    ],
    "name:cat_x_preferred":[
        "Gola"
    ],
    "name:ceb_x_preferred":[
        "Gola"
    ],
    "name:deu_x_preferred":[
        "Gola"
    ],
    "name:fra_x_preferred":[
        "Gola"
    ],
    "name:heb_x_preferred":[
        "\u05d2\u05d5\u05dc\u05d4"
    ],
    "name:hun_x_preferred":[
        "Gola"
    ],
    "name:ita_x_preferred":[
        "Gola"
    ],
    "name:new_x_preferred":[
        "\u0917\u094b\u0932\u093e"
    ],
    "name:nld_x_preferred":[
        "Gola"
    ],
    "name:pol_x_preferred":[
        "Gola"
    ],
    "name:por_x_preferred":[
        "Gola"
    ],
    "name:rus_x_preferred":[
        "\u0413\u043e\u043b\u0430"
    ],
    "name:spa_x_preferred":[
        "Gola"
    ],
    "name:swe_x_preferred":[
        "Gola"
    ],
    "name:ukr_x_preferred":[
        "\u0413\u043e\u043b\u0430"
    ],
    "wof:name":"Gola",
    "wof:placetype":"locality"
},
  "geometry": {"coordinates":[17.26432,51.97275],"type":"Point"}
}