{
  "type": "Feature",
  "properties": {
    "gn:admin1_code":"82.0",
    "gn:admin2_code":"2201.0",
    "gn:admin3_code":"220109.0",
    "gn:asciiname":"Bozanka",
    "gn:country_code":"PL",
    "gn:dem":75,
    "gn:feature_class":"P",
    "gn:feature_code":"PPL",
    "gn:name":"Bo\u017canka",
    "gn:population":0,
    "gn:timezone":"Europe/Warsaw",
    "iso:country":"PL",
    "name:azb_x_preferred":[
        "\u0628\u0648\u0698\u0627\u0646\u06a9\u0627"
    ],
    "name:csb_x_preferred":[
        "B\u00f2\u017c\u00f3nka"
    ],
    "name:fas_x_preferred":[
        "\u0628\u0648\u0698\u0627\u0646\u06a9\u0627"
    ],
    "name:nld_x_preferred":[
        "Bo\u017canka"
    ],
    "name:pol_x_preferred":[
        "Bo\u017canka"
    ],
    "name:ukr_x_preferred":[
        "\u0411\u043e\u0436\u0430\u043d\u043a\u0430"
    ],
    "wof:name":"Bozanka",
    "wof:placetype":"locality"
},
  "geometry": {"coordinates":[17.03381,54.14239],"type":"Point"}
}