{
  "type": "Feature",
  "properties": {
    "gn:admin1_code":"82.0",
    "gn:admin2_code":"2201.0",
    "gn:admin3_code":"220109.0",
    "gn:asciiname":"Bozanka",
    "gn:country_code":"PL",
    "gn:dem":75,
    "gn:feature_class":"P",
    "gn:feature_code":"PPL",
    "gn:name":"Bo\u017canka",
    "gn:population":0,
    "gn:timezone":"Europe/Warsaw",
    "iso:country":"PL",
    "name:und_x_variant":[
        "Bo\u017canka"
    ],
    "wof:name":"Bozanka",
    "wof:placetype":"locality"
},
  "geometry": {"coordinates":[17.03381,54.14239],"type":"Point"}
}