{
  "type": "Feature",
  "properties": {
    "gn:admin1_code":"85.0",
    "gn:admin2_code":"2813.0",
    "gn:admin3_code":"281305.0",
    "gn:asciiname":"Dybowo",
    "gn:country_code":"PL",
    "gn:dem":158,
    "gn:feature_class":"P",
    "gn:feature_code":"PPL",
    "gn:name":"Dybowo",
    "gn:population":0,
    "gn:timezone":"Europe/Warsaw",
    "iso:country":"PL",
    "name:bul_x_preferred":[
        "\u0414\u044a\u0431\u043e\u0432\u043e"
    ],
    "name:deu_x_preferred":[
        "Dybowo"
    ],
    "name:fra_x_preferred":[
        "Dybowo"
    ],
    "name:pol_x_preferred":[
        "Dybowo"
    ],
    "name:rus_x_preferred":[
        "\u0414\u044b\u0431\u043e\u0432\u043e"
    ],
    "name:ukr_x_preferred":[
        "\u0414\u0438\u0431\u043e\u0432\u043e"
    ],
    "name:und_x_variant":[
        "Diebauen",
        "Diebowen",
        "Diebauen Kreis Treuburg"
    ],
    "wof:name":"Dybowo",
    "wof:placetype":"locality"
},
  "geometry": {"coordinates":[22.29293,54.08205],"type":"Point"}
}