{
  "type": "Feature",
  "properties": {
    "gn:admin1_code":"85.0",
    "gn:admin2_code":"2813.0",
    "gn:admin3_code":"281305.0",
    "gn:asciiname":"Dybowo",
    "gn:country_code":"PL",
    "gn:dem":158,
    "gn:feature_class":"P",
    "gn:feature_code":"PPL",
    "gn:name":"Dybowo",
    "gn:population":0,
    "gn:timezone":"Europe/Warsaw",
    "iso:country":"PL",
    "name:und_x_variant":[
        "Diebauen",
        "Diebowen",
        "Diebauen Kreis Treuburg",
        "Dybowo"
    ],
    "wof:name":"Dybowo",
    "wof:placetype":"locality"
},
  "geometry": {"coordinates":[22.29293,54.08205],"type":"Point"}
}