{
  "type": "Feature",
  "properties": {
    "gn:admin1_code":"87.0",
    "gn:admin2_code":"3206.0",
    "gn:admin3_code":"320601.0",
    "gn:asciiname":"Swobnica",
    "gn:cc2":"PL",
    "gn:country_code":"PL",
    "gn:dem":59,
    "gn:feature_class":"P",
    "gn:feature_code":"PPL",
    "gn:name":"Swobnica",
    "gn:population":0,
    "gn:timezone":"Europe/Warsaw",
    "iso:country":"PL",
    "name:azb_x_preferred":[
        "\u0633\u0648\u0648\u0628\u0646\u0642\u062a\u0633\u0627"
    ],
    "name:ceb_x_preferred":[
        "Swobnica"
    ],
    "name:deu_x_preferred":[
        "Swobnica"
    ],
    "name:fas_x_preferred":[
        "\u0633\u0648\u0648\u0628\u0646\u06af\u062a\u0633\u0627"
    ],
    "name:nld_x_preferred":[
        "Swobnica"
    ],
    "name:pol_x_preferred":[
        "Swobnica"
    ],
    "name:swe_x_preferred":[
        "Swobnica"
    ],
    "name:ukr_x_preferred":[
        "\u0421\u0432\u043e\u0431\u043d\u0438\u0446\u044f"
    ],
    "name:und_x_variant":[
        "Wildenbruch"
    ],
    "name:vie_x_preferred":[
        "Swobnica"
    ],
    "wof:name":"Swobnica",
    "wof:placetype":"locality"
},
  "geometry": {"coordinates":[14.62409,53.04013000000001],"type":"Point"}
}