{
  "type": "Feature",
  "properties": {
    "gn:admin1_code":"87.0",
    "gn:admin2_code":"3206.0",
    "gn:admin3_code":"320601.0",
    "gn:asciiname":"Swobnica",
    "gn:cc2":"PL",
    "gn:country_code":"PL",
    "gn:dem":59,
    "gn:feature_class":"P",
    "gn:feature_code":"PPL",
    "gn:name":"Swobnica",
    "gn:population":0,
    "gn:timezone":"Europe/Warsaw",
    "iso:country":"PL",
    "name:und_x_variant":[
        "Wildenbruch"
    ],
    "wof:name":"Swobnica",
    "wof:placetype":"locality"
},
  "geometry": {"coordinates":[14.62409,53.04013000000001],"type":"Point"}
}