{
  "type": "Feature",
  "properties": {
    "gn:admin1_code":"76.0",
    "gn:admin2_code":"862.0",
    "gn:admin3_code":"86201.0",
    "gn:asciiname":"Lezyca",
    "gn:country_code":"PL",
    "gn:dem":77,
    "gn:feature_class":"P",
    "gn:feature_code":"PPL",
    "gn:name":"\u0141\u0119\u017cyca",
    "gn:population":0,
    "gn:timezone":"Europe/Warsaw",
    "iso:country":"PL",
    "wof:name":"Lezyca",
    "wof:placetype":"locality"
},
  "geometry": {"coordinates":[15.4763,51.99566],"type":"Point"}
}