{
  "type": "Feature",
  "properties": {
    "gn:admin1_code":"78.0",
    "gn:admin2_code":"1463.0",
    "gn:admin3_code":"146301.0",
    "gn:asciiname":"Krzewien",
    "gn:country_code":"PL",
    "gn:dem":136,
    "gn:feature_class":"P",
    "gn:feature_code":"PPL",
    "gn:name":"Krzewie\u0144",
    "gn:population":0,
    "gn:timezone":"Europe/Warsaw",
    "iso:country":"PL",
    "wof:name":"Krzewien",
    "wof:placetype":"locality"
},
  "geometry": {"coordinates":[21.18262,51.46004],"type":"Point"}
}