{
  "type": "Feature",
  "properties": {
    "gn:admin1_code":"86.0",
    "gn:admin2_code":"3009.0",
    "gn:admin3_code":"300902.0",
    "gn:asciiname":"Gryglaki",
    "gn:country_code":"PL",
    "gn:dem":128,
    "gn:feature_class":"P",
    "gn:feature_code":"PPL",
    "gn:name":"Gryglaki",
    "gn:population":0,
    "gn:timezone":"Europe/Warsaw",
    "iso:country":"PL",
    "name:pol_x_preferred":[
        "Gryglaki"
    ],
    "name:ukr_x_preferred":[
        "\u0490\u0440\u0438\u0491\u043b\u044f\u043a\u0438"
    ],
    "wof:name":"Gryglaki",
    "wof:placetype":"locality"
},
  "geometry": {"coordinates":[18.63804,52.33608],"type":"Point"}
}