{
  "type": "Feature",
  "properties": {
    "gn:admin1_code":"75.0",
    "gn:admin2_code":"608.0",
    "gn:admin3_code":"60807.0",
    "gn:asciiname":"Wolka Rokicka",
    "gn:country_code":"PL",
    "gn:dem":158,
    "gn:feature_class":"P",
    "gn:feature_code":"PPL",
    "gn:name":"W\u00f3lka Rokicka",
    "gn:population":0,
    "gn:timezone":"Europe/Warsaw",
    "iso:country":"PL",
    "name:und_x_variant":[
        "W\u00f3lka Rokicka"
    ],
    "wof:name":"Wolka Rokicka",
    "wof:placetype":"locality"
},
  "geometry": {"coordinates":[22.68028,51.40451],"type":"Point"}
}