{
  "type": "Feature",
  "properties": {
    "gn:gn_country":"PL",
    "gn:gn_fcode":"PPL",
    "gn:gn_pop":0,
    "iso:country":"PL",
    "name:ast_x_preferred":[
        "Wetlina"
    ],
    "name:azb_x_preferred":[
        "\u0648\u062a\u0644\u06cc\u0646\u0627"
    ],
    "name:ceb_x_preferred":[
        "Wetlina"
    ],
    "name:deu_x_preferred":[
        "Wetlina"
    ],
    "name:eng_x_preferred":[
        "Wetlina"
    ],
    "name:fas_x_preferred":[
        "\u0648\u062a\u0644\u06cc\u0646\u0627"
    ],
    "name:fra_x_preferred":[
        "Wetlina"
    ],
    "name:nld_x_preferred":[
        "Wetlina"
    ],
    "name:pol_x_preferred":[
        "Wetlina"
    ],
    "name:spa_x_preferred":[
        "Wetlina"
    ],
    "name:szl_x_preferred":[
        "Wetlina"
    ],
    "name:ukr_x_preferred":[
        "\u0412\u0435\u0442\u043b\u0438\u043d\u0430"
    ],
    "qs_pg:aaroncc":"PL",
    "qs_pg:gn_country":"PL",
    "qs_pg:gn_fcode":"PPL",
    "qs_pg:gn_pop":0,
    "qs_pg:name":"Wetlina",
    "qs_pg:name_adm0":"Polska",
    "qs_pg:name_adm1":"Podkarpackie",
    "qs_pg:photos":207,
    "qs_pg:photos_1k":42,
    "qs_pg:photos_9k":1,
    "qs_pg:photos_9r":4,
    "qs_pg:photos_all":207,
    "qs_pg:photos_sr":4,
    "qs_pg:pop_sr":0,
    "qs_pg:qs_pg_placetype":"locality",
    "qs_pg:qs_pg_placetype_gp":"Town",
    "qs_pg:woe_adm0":23424923,
    "woe:adm0_id":23424923,
    "woe:name_adm0":"Polska",
    "woe:name_adm1":"Podkarpackie",
    "woe:placetype":"Town",
    "wof:name":"Wetlina",
    "wof:placetype":"locality"
},
  "geometry": {"coordinates":[22.47734,49.14792],"type":"Point"}
}