{
  "type": "Feature",
  "properties": {
    "gn:admin1_code":"73.0",
    "gn:admin2_code":"402.0",
    "gn:admin3_code":"40210.0",
    "gn:asciiname":"Ciche",
    "gn:country_code":"PL",
    "gn:dem":92,
    "gn:feature_class":"P",
    "gn:feature_code":"PPL",
    "gn:name":"Ciche",
    "gn:population":0,
    "gn:timezone":"Europe/Warsaw",
    "iso:country":"PL",
    "name:ceb_x_preferred":[
        "Ciche"
    ],
    "name:pol_x_preferred":[
        "Ciche"
    ],
    "name:ukr_x_preferred":[
        "\u0426\u0438\u0445\u0435"
    ],
    "wof:name":"Ciche",
    "wof:placetype":"locality"
},
  "geometry": {"coordinates":[19.37628,53.38118000000001],"type":"Point"}
}