{
  "type": "Feature",
  "properties": {
    "gn:admin1_code":"78.0",
    "gn:admin2_code":"1427.0",
    "gn:admin3_code":"142704.0",
    "gn:asciiname":"Wrzesnia",
    "gn:country_code":"PL",
    "gn:dem":114,
    "gn:feature_class":"P",
    "gn:feature_code":"PPL",
    "gn:name":"Wrze\u015bnia",
    "gn:population":0,
    "gn:timezone":"Europe/Warsaw",
    "iso:country":"PL",
    "name:fra_x_preferred":[
        "Wrze\u015bnia"
    ],
    "name:pol_x_preferred":[
        "Wrze\u015bnia"
    ],
    "name:ukr_x_preferred":[
        "\u0412\u0436\u0435\u0441\u043d\u044f"
    ],
    "name:und_x_variant":[
        "Wrze\u015bnia"
    ],
    "wof:name":"Wrzesnia",
    "wof:placetype":"locality"
},
  "geometry": {"coordinates":[19.7681,52.94712],"type":"Point"}
}