{
  "type": "Feature",
  "properties": {
    "gn:admin1_code":"86.0",
    "gn:admin2_code":"3009.0",
    "gn:admin3_code":"300906.0",
    "gn:asciiname":"Bierzwienna",
    "gn:country_code":"PL",
    "gn:dem":116,
    "gn:feature_class":"P",
    "gn:feature_code":"PPL",
    "gn:name":"Bierzwienna",
    "gn:population":0,
    "gn:timezone":"Europe/Warsaw",
    "iso:country":"PL",
    "wof:name":"Bierzwienna",
    "wof:placetype":"locality"
},
  "geometry": {"coordinates":[18.88333,52.28333],"type":"Point"}
}