{
  "type": "Feature",
  "properties": {
    "gn:admin1_code":"85.0",
    "gn:admin2_code":"2812.0",
    "gn:admin3_code":"281203.0",
    "gn:asciiname":"Zwiniarz",
    "gn:country_code":"PL",
    "gn:dem":172,
    "gn:feature_class":"P",
    "gn:feature_code":"PPL",
    "gn:name":"Zwiniarz",
    "gn:population":0,
    "gn:timezone":"Europe/Warsaw",
    "iso:country":"PL",
    "name:pol_x_preferred":[
        "Zwiniarz"
    ],
    "name:ukr_x_preferred":[
        "\u0417\u0432\u0456\u043d\u044f\u0436"
    ],
    "wof:name":"Zwiniarz",
    "wof:placetype":"locality"
},
  "geometry": {"coordinates":[19.84269,53.43612],"type":"Point"}
}