{
  "type": "Feature",
  "properties": {
    "gn:admin1_code":"85.0",
    "gn:admin2_code":"2816.0",
    "gn:admin3_code":"281601.0",
    "gn:asciiname":"Sokoly Jeziorno",
    "gn:country_code":"PL",
    "gn:dem":146,
    "gn:feature_class":"P",
    "gn:feature_code":"PPL",
    "gn:name":"Soko\u0142y Jeziorno",
    "gn:population":0,
    "gn:timezone":"Europe/Warsaw",
    "iso:country":"PL",
    "name:und_x_variant":[
        "Rosensee",
        "Sokollen am See",
        "Sokollen R",
        "Soko\u0142y",
        "Sokollen",
        "Soko\u0142y Jeziorno"
    ],
    "wof:name":"Sokoly Jeziorno",
    "wof:placetype":"locality"
},
  "geometry": {"coordinates":[22.28569,53.63291],"type":"Point"}
}