{
  "type": "Feature",
  "properties": {
    "gn:admin1_code":"78.0",
    "gn:admin2_code":"1409.0",
    "gn:admin3_code":"140904.0",
    "gn:asciiname":"Dubrowa",
    "gn:country_code":"PL",
    "gn:dem":210,
    "gn:feature_class":"P",
    "gn:feature_code":"PPL",
    "gn:name":"Dubrowa",
    "gn:population":0,
    "gn:timezone":"Europe/Warsaw",
    "iso:country":"PL",
    "wof:name":"Dubrowa",
    "wof:placetype":"locality"
},
  "geometry": {"coordinates":[21.35972000000001,51.10544],"type":"Point"}
}