{
  "type": "Feature",
  "properties": {
    "gn:admin1_code":"76.0",
    "gn:admin2_code":"810.0",
    "gn:admin3_code":"81006.0",
    "gn:asciiname":"Goscieszowice",
    "gn:country_code":"PL",
    "gn:dem":138,
    "gn:feature_class":"P",
    "gn:feature_code":"PPL",
    "gn:name":"Go\u015bcieszowice",
    "gn:population":0,
    "gn:timezone":"Europe/Warsaw",
    "iso:country":"PL",
    "name:deu_x_historical":[
        "Gie\u00dfmannsdorf"
    ],
    "name:deu_x_preferred":[
        "Gie\u00dfmannsdorf"
    ],
    "name:fas_x_preferred":[
        "\u06af\u0648\u0634\u0686\u06cc\u0634\u0648\u0648\u06cc\u062a\u0633\u0647"
    ],
    "name:fra_x_preferred":[
        "Go\u015bcieszowice"
    ],
    "name:pol_x_preferred":[
        "Go\u015bcieszowice"
    ],
    "name:ukr_x_preferred":[
        "\u0490\u043e\u0441\u044c\u0446\u0435\u0448\u043e\u0432\u0456\u0446\u0435"
    ],
    "name:und_x_variant":[
        "Go\u015bciszowice"
    ],
    "wof:name":"Goscieszowice",
    "wof:placetype":"locality"
},
  "geometry": {"coordinates":[15.66904,51.61162],"type":"Point"}
}