{
  "type": "Feature",
  "properties": {
    "gn:admin1_code":"76.0",
    "gn:admin2_code":"810.0",
    "gn:admin3_code":"81006.0",
    "gn:asciiname":"Goscieszowice",
    "gn:country_code":"PL",
    "gn:dem":138,
    "gn:feature_class":"P",
    "gn:feature_code":"PPL",
    "gn:name":"Go\u015bcieszowice",
    "gn:population":0,
    "gn:timezone":"Europe/Warsaw",
    "iso:country":"PL",
    "name:deu_x_historical":[
        "Gie\u00dfmannsdorf"
    ],
    "name:deu_x_preferred":[
        "Gie\u00dfmannsdorf"
    ],
    "name:und_x_variant":[
        "Go\u015bciszowice",
        "Go\u015bcieszowice"
    ],
    "wof:name":"Goscieszowice",
    "wof:placetype":"locality"
},
  "geometry": {"coordinates":[15.66904,51.61162],"type":"Point"}
}