{
  "type": "Feature",
  "properties": {
    "gn:admin1_code":"78.0",
    "gn:admin2_code":"1414.0",
    "gn:admin3_code":"141404.0",
    "gn:asciiname":"Winniki",
    "gn:country_code":"PL",
    "gn:dem":107,
    "gn:feature_class":"P",
    "gn:feature_code":"PPL",
    "gn:name":"Winniki",
    "gn:population":0,
    "gn:timezone":"Europe/Warsaw",
    "iso:country":"PL",
    "name:fra_x_preferred":[
        "Winniki"
    ],
    "name:mkd_x_preferred":[
        "\u0412\u0438\u043d\u0438\u043a\u0438"
    ],
    "name:pol_x_preferred":[
        "Winniki"
    ],
    "name:ukr_x_preferred":[
        "\u0412\u0456\u043d\u043d\u0438\u043a\u0438"
    ],
    "wof:name":"Winniki",
    "wof:placetype":"locality"
},
  "geometry": {"coordinates":[20.72973,52.61212],"type":"Point"}
}