{
  "type": "Feature",
  "properties": {
    "gn:admin1_code":"77.0",
    "gn:admin2_code":"1216.0",
    "gn:admin3_code":"121609.0",
    "gn:asciiname":"Biala",
    "gn:country_code":"PL",
    "gn:dem":189,
    "gn:feature_class":"P",
    "gn:feature_code":"PPL",
    "gn:name":"Bia\u0142a",
    "gn:population":0,
    "gn:timezone":"Europe/Warsaw",
    "iso:country":"PL",
    "name:ceb_x_preferred":[
        "Bia\u0142a"
    ],
    "name:pol_x_preferred":[
        "Bia\u0142a"
    ],
    "name:ukr_x_preferred":[
        "\u0411\u0456\u043b\u0430"
    ],
    "wof:name":"Biala",
    "wof:placetype":"locality"
},
  "geometry": {"coordinates":[20.92381,50.04138],"type":"Point"}
}