{
  "type": "Feature",
  "properties": {
    "gn:admin1_code":"86.0",
    "gn:admin2_code":"3027.0",
    "gn:admin3_code":"302704.0",
    "gn:asciiname":"Marianow",
    "gn:cc2":"PL",
    "gn:country_code":"PL",
    "gn:dem":131,
    "gn:feature_class":"P",
    "gn:feature_code":"PPL",
    "gn:name":"Marian\u00f3w",
    "gn:population":0,
    "gn:timezone":"Europe/Warsaw",
    "iso:country":"PL",
    "name:und_x_variant":[
        "Marjan\u00f3w",
        "Marian\u00f3w"
    ],
    "wof:name":"Marianow",
    "wof:placetype":"locality"
},
  "geometry": {"coordinates":[18.53333,51.95],"type":"Point"}
}