{
  "type": "Feature",
  "properties": {
    "gn:admin1_code":"74.0",
    "gn:admin2_code":"1016.0",
    "gn:admin3_code":"101601.0",
    "gn:asciiname":"Wola Wiaderno",
    "gn:country_code":"PL",
    "gn:dem":178,
    "gn:feature_class":"P",
    "gn:feature_code":"PPL",
    "gn:name":"Wola Wiaderno",
    "gn:population":0,
    "gn:timezone":"Europe/Warsaw",
    "iso:country":"PL",
    "name:und_x_variant":[
        "Wiaderno-Wola",
        "Wola Wiaderno"
    ],
    "wof:name":"Wola Wiaderno",
    "wof:placetype":"locality"
},
  "geometry": {"coordinates":[19.97136,51.50927],"type":"Point"}
}