{
  "type": "Feature",
  "properties": {
    "gn:admin1_code":"78.0",
    "gn:admin2_code":"1412.0",
    "gn:admin3_code":"141209.0",
    "gn:asciiname":"Ryczolek",
    "gn:country_code":"PL",
    "gn:dem":186,
    "gn:feature_class":"P",
    "gn:feature_code":"PPL",
    "gn:name":"Ryczo\u0142ek",
    "gn:population":0,
    "gn:timezone":"Europe/Warsaw",
    "iso:country":"PL",
    "name:fra_x_preferred":[
        "Ryczo\u0142ek"
    ],
    "name:pol_x_preferred":[
        "Ryczo\u0142ek"
    ],
    "name:spa_x_preferred":[
        "Ryczo\u0142ek"
    ],
    "name:ukr_x_preferred":[
        "\u0420\u0438\u0447\u043e\u043b\u0435\u043a"
    ],
    "wof:name":"Ryczolek",
    "wof:placetype":"locality"
},
  "geometry": {"coordinates":[21.77387,52.19919],"type":"Point"}
}