{
  "type": "Feature",
  "properties": {
    "gn:admin1_code":"86.0",
    "gn:admin2_code":"3015.0",
    "gn:admin3_code":"301503.0",
    "gn:asciiname":"Jablonka Stara",
    "gn:country_code":"PL",
    "gn:dem":61,
    "gn:feature_class":"P",
    "gn:feature_code":"PPL",
    "gn:name":"Jab\u0142onka Stara",
    "gn:population":0,
    "gn:timezone":"Europe/Warsaw",
    "iso:country":"PL",
    "name:und_x_variant":[
        "Jab\u0142onka Stara"
    ],
    "wof:name":"Jablonka Stara",
    "wof:placetype":"locality"
},
  "geometry": {"coordinates":[15.87976,52.42039000000001],"type":"Point"}
}