{
  "type": "Feature",
  "properties": {
    "gn:admin1_code":"86.0",
    "gn:admin2_code":"3015.0",
    "gn:admin3_code":"301503.0",
    "gn:asciiname":"Jablonka Stara",
    "gn:country_code":"PL",
    "gn:dem":61,
    "gn:feature_class":"P",
    "gn:feature_code":"PPL",
    "gn:name":"Jab\u0142onka Stara",
    "gn:population":0,
    "gn:timezone":"Europe/Warsaw",
    "iso:country":"PL",
    "name:azb_x_preferred":[
        "\u06cc\u0627\u0628\u0648\u0648\u0646\u06a9\u0627 \u0633\u062a\u0627\u0631\u0627"
    ],
    "name:ceb_x_preferred":[
        "Jab\u0142onka Stara"
    ],
    "name:fas_x_preferred":[
        "\u06cc\u0627\u0628\u0648\u0648\u0646\u06a9\u0627 \u0633\u062a\u0627\u0631\u0627"
    ],
    "name:fra_x_preferred":[
        "Jab\u0142onka Stara"
    ],
    "name:pol_x_preferred":[
        "Jab\u0142onka Stara"
    ],
    "name:ukr_x_preferred":[
        "\u042f\u0431\u043b\u043e\u043d\u043a\u0430-\u0421\u0442\u0430\u0440\u0430"
    ],
    "name:und_x_variant":[
        "Jab\u0142onka Stara"
    ],
    "name:urd_x_preferred":[
        "\u062c\u0628\u0648\u0627\u0646\u06a9\u0627 \u0633\u062a\u0631\u06c1"
    ],
    "wof:name":"Jablonka Stara",
    "wof:placetype":"locality"
},
  "geometry": {"coordinates":[15.87976,52.42039000000001],"type":"Point"}
}