{
  "type": "Feature",
  "properties": {
    "gn:admin1_code":"75.0",
    "gn:admin2_code":"610.0",
    "gn:admin3_code":"61001.0",
    "gn:asciiname":"Swierszczow",
    "gn:country_code":"PL",
    "gn:dem":178,
    "gn:feature_class":"P",
    "gn:feature_code":"PPL",
    "gn:name":"\u015awierszcz\u00f3w",
    "gn:population":0,
    "gn:timezone":"Europe/Warsaw",
    "iso:country":"PL",
    "wof:name":"Swierszczow",
    "wof:placetype":"locality"
},
  "geometry": {"coordinates":[23.18939,51.33726],"type":"Point"}
}