{
  "type": "Feature",
  "properties": {
    "gn:admin1_code":"82.0",
    "gn:admin2_code":"2202.0",
    "gn:admin3_code":"220203.0",
    "gn:asciiname":"Wielkie Zanie",
    "gn:country_code":"PL",
    "gn:dem":129,
    "gn:feature_class":"P",
    "gn:feature_code":"PPL",
    "gn:name":"Wielkie Zanie",
    "gn:population":0,
    "gn:timezone":"Europe/Warsaw",
    "iso:country":"PL",
    "name:ceb_x_preferred":[
        "Wielkie Zanie"
    ],
    "name:pol_x_preferred":[
        "Wielkie Zanie"
    ],
    "name:und_x_variant":[
        "Kolonia Wielkie Zanie"
    ],
    "wof:name":"Wielkie Zanie",
    "wof:placetype":"locality"
},
  "geometry": {"coordinates":[17.46596,53.88266],"type":"Point"}
}