{
  "type": "Feature",
  "properties": {
    "gn:country":"PL",
    "gn:fcode":"PPLA3",
    "gn:population":2670,
    "iso:country":"PL",
    "name:bul_x_preferred":[
        "\u0427\u0438\u0436\u0435\u0432"
    ],
    "name:ceb_x_preferred":[
        "Czy\u017cew"
    ],
    "name:deu_x_preferred":[
        "Czy\u017cew"
    ],
    "name:eng_x_preferred":[
        "Czy\u017cew-Osada"
    ],
    "name:eng_x_variant":[
        "Gmina Czy\u017cew"
    ],
    "name:est_x_preferred":[
        "Czy\u017cew"
    ],
    "name:fra_x_preferred":[
        "Czy\u017cew"
    ],
    "name:heb_x_preferred":[
        "\u05e6'\u05d9\u05d6'\u05d1"
    ],
    "name:ita_x_preferred":[
        "Czy\u017cew-Osada"
    ],
    "name:lav_x_preferred":[
        "\u010ci\u017eeva"
    ],
    "name:lit_x_preferred":[
        "\u010ci\u017eevo vals\u010dius"
    ],
    "name:lit_x_variant":[
        "\u010ci\u017eevas"
    ],
    "name:msa_x_preferred":[
        "Czy\u017cew"
    ],
    "name:nld_x_preferred":[
        "Czy\u017cew"
    ],
    "name:pol_x_preferred":[
        "Czy\u017cew-Osada"
    ],
    "name:pol_x_variant":[
        "Czy\u017cew"
    ],
    "name:por_x_preferred":[
        "Comuna de Czy\u017cew-Osada"
    ],
    "name:rus_x_preferred":[
        "\u0427\u0438\u0436\u0435\u0432-\u041e\u0441\u0430\u0434\u0430"
    ],
    "name:rus_x_variant":[
        "\u0427\u0438\u0436\u0435\u0432"
    ],
    "name:slk_x_preferred":[
        "Gmina Czy\u017cew-Osada"
    ],
    "name:srp_x_preferred":[
        "\u0427\u0438\u0436\u0435\u0432"
    ],
    "name:ukr_x_preferred":[
        "\u0490\u043c\u0456\u043d\u0430 \u0427\u0438\u0436\u0435\u0432"
    ],
    "name:ukr_x_variant":[
        "\u0427\u0438\u0436\u0435\u0432"
    ],
    "name:und_x_variant":[
        "Czy\u017cewo"
    ],
    "name:vie_x_preferred":[
        "Czy\u017cew"
    ],
    "name:war_x_preferred":[
        "Gmina Czy\u017cew-Osada"
    ],
    "name:zho_x_preferred":[
        "\u5947\u71b1\u592b"
    ],
    "qs_pg:aaroncc":"PL",
    "qs_pg:gn_country":"PL",
    "qs_pg:gn_fcode":"PPLA3",
    "qs_pg:gn_pop":2670,
    "qs_pg:name":"Czy\u017cew",
    "qs_pg:photos_9r":0,
    "qs_pg:photos_sr":0,
    "qs_pg:pop_sr":4,
    "qs_pg:qs_pg_placetype":"locality",
    "wof:name":"Czy\u017cew",
    "wof:placetype":"locality",
    "wof:population":2670
},
  "geometry": {"coordinates":[22.31237,52.79768],"type":"Point"}
}