{
  "type": "Feature",
  "properties": {
    "gn:gn_country":"PL",
    "gn:gn_fcode":"PPLA3",
    "gn:gn_pop":2670,
    "gn:population":2670,
    "iso:country":"PL",
    "name:eng_x_preferred":[
        "Czy\u017cew-Osada"
    ],
    "name:eng_x_variant":[
        "Gmina Czy\u017cew"
    ],
    "name:ita_x_preferred":[
        "Czy\u017cew-Osada"
    ],
    "name:lit_x_preferred":[
        "\u010ci\u017eevo vals\u010dius"
    ],
    "name:pol_x_preferred":[
        "Czy\u017cew-Osada"
    ],
    "name:por_x_preferred":[
        "Comuna de Czy\u017cew-Osada"
    ],
    "name:rus_x_preferred":[
        "\u0427\u0438\u0436\u0435\u0432-\u041e\u0441\u0430\u0434\u0430"
    ],
    "name:rus_x_variant":[
        "\u0427\u0438\u0436\u0435\u0432"
    ],
    "name:slk_x_preferred":[
        "Gmina Czy\u017cew-Osada"
    ],
    "name:ukr_x_preferred":[
        "\u0490\u043c\u0456\u043d\u0430 \u0427\u0438\u0436\u0435\u0432"
    ],
    "name:unk_x_variant":[
        "Czy\u017cewo"
    ],
    "name:war_x_preferred":[
        "Gmina Czy\u017cew-Osada"
    ],
    "qs_pg:aaroncc":"PL",
    "qs_pg:gn_country":"PL",
    "qs_pg:gn_fcode":"PPLA3",
    "qs_pg:gn_pop":2670,
    "qs_pg:name":"Czy\u017cew",
    "qs_pg:photos_9r":0,
    "qs_pg:photos_sr":0,
    "qs_pg:pop_sr":4,
    "qs_pg:qs_pg_placetype":"locality",
    "wof:name":"Czy\u017cew",
    "wof:placetype":"locality",
    "wof:population":2670
},
  "geometry": {"coordinates":[22.31237,52.79768],"type":"Point"}
}