{
  "type": "Feature",
  "properties": {
    "gn:admin1_code":"74.0",
    "gn:admin2_code":"1011.0",
    "gn:admin3_code":"101101.0",
    "gn:asciiname":"Budzynek",
    "gn:country_code":"PL",
    "gn:dem":127,
    "gn:feature_class":"P",
    "gn:feature_code":"PPL",
    "gn:name":"Budzynek",
    "gn:population":0,
    "gn:timezone":"Europe/Warsaw",
    "iso:country":"PL",
    "name:azb_x_preferred":[
        "\u0628\u0648\u0632\u0646\u06a9"
    ],
    "name:ceb_x_preferred":[
        "Budzynek"
    ],
    "name:fas_x_preferred":[
        "\u0628\u0648\u0632\u0646\u06a9"
    ],
    "name:fra_x_preferred":[
        "Budzynek"
    ],
    "name:nld_x_preferred":[
        "Budzynek"
    ],
    "name:pol_x_preferred":[
        "Budzynek"
    ],
    "name:ukr_x_preferred":[
        "\u0411\u0443\u0434\u0437\u0438\u043d\u0435\u043a"
    ],
    "wof:name":"Budzynek",
    "wof:placetype":"locality"
},
  "geometry": {"coordinates":[19.12958,51.93168],"type":"Point"}
}