{
  "type": "Feature",
  "properties": {
    "gn:admin1_code":"72.0",
    "gn:admin2_code":"212.0",
    "gn:admin3_code":"21203.0",
    "gn:asciiname":"Skala",
    "gn:country_code":"PL",
    "gn:dem":215,
    "gn:feature_class":"P",
    "gn:feature_code":"PPL",
    "gn:name":"Ska\u0142a",
    "gn:population":0,
    "gn:timezone":"Europe/Warsaw",
    "iso:country":"PL",
    "wof:name":"Skala",
    "wof:placetype":"locality"
},
  "geometry": {"coordinates":[15.59319,51.15745],"type":"Point"}
}