{
  "type": "Feature",
  "properties": {
    "gn:admin1_code":"72.0",
    "gn:admin2_code":"207.0",
    "gn:admin3_code":"20703.0",
    "gn:asciiname":"Blazejow",
    "gn:country_code":"PL",
    "gn:dem":529,
    "gn:feature_class":"P",
    "gn:feature_code":"PPL",
    "gn:name":"B\u0142a\u017cej\u00f3w",
    "gn:population":0,
    "gn:timezone":"Europe/Warsaw",
    "iso:country":"PL",
    "wof:name":"Blazejow",
    "wof:placetype":"locality"
},
  "geometry": {"coordinates":[16.05051,50.66665],"type":"Point"}
}