{
  "type": "Feature",
  "properties": {
    "gn:admin1_code":"72.0",
    "gn:admin2_code":"218.0",
    "gn:admin3_code":"21804.0",
    "gn:asciiname":"Jastzebce",
    "gn:country_code":"PL",
    "gn:dem":110,
    "gn:feature_class":"P",
    "gn:feature_code":"PPL",
    "gn:name":"Jastz\u0119bce",
    "gn:population":0,
    "gn:timezone":"Europe/Warsaw",
    "iso:country":"PL",
    "wof:name":"Jastzebce",
    "wof:placetype":"locality"
},
  "geometry": {"coordinates":[16.5564,51.18644000000001],"type":"Point"}
}