{
  "type": "Feature",
  "properties": {
    "gn:admin1_code":"78.0",
    "gn:admin2_code":"1436.0",
    "gn:admin3_code":"143604.0",
    "gn:asciiname":"Borki",
    "gn:cc2":"PL",
    "gn:country_code":"PL",
    "gn:dem":169,
    "gn:feature_class":"P",
    "gn:feature_code":"PPL",
    "gn:name":"Borki",
    "gn:population":0,
    "gn:timezone":"Europe/Warsaw",
    "iso:country":"PL",
    "name:ceb_x_preferred":[
        "Borki"
    ],
    "name:fra_x_preferred":[
        "Borki"
    ],
    "name:pol_x_preferred":[
        "Borki"
    ],
    "name:ukr_x_preferred":[
        "\u0411\u043e\u0440\u043a\u0456"
    ],
    "name:und_x_variant":[
        "Tcz\u00f3w Borki"
    ],
    "wof:name":"Borki",
    "wof:placetype":"locality"
},
  "geometry": {"coordinates":[21.443,51.34059],"type":"Point"}
}