{
  "type": "Feature",
  "properties": {
    "gn:admin1_code":"85.0",
    "gn:admin2_code":"2806.0",
    "gn:admin3_code":"280610.0",
    "gn:asciiname":"Pamry",
    "gn:country_code":"PL",
    "gn:dem":162,
    "gn:feature_class":"P",
    "gn:feature_code":"PPL",
    "gn:name":"Pamry",
    "gn:population":0,
    "gn:timezone":"Europe/Warsaw",
    "iso:country":"PL",
    "name:ceb_x_preferred":[
        "Pamry"
    ],
    "name:deu_x_preferred":[
        "Pamry"
    ],
    "name:fra_x_preferred":[
        "Pamry"
    ],
    "name:pol_x_preferred":[
        "Pamry"
    ],
    "wof:name":"Pamry",
    "wof:placetype":"locality"
},
  "geometry": {"coordinates":[22.00107,53.92841],"type":"Point"}
}