{
  "type": "Feature",
  "properties": {
    "gn:gn_country":"PL",
    "gn:gn_fcode":"PPLA3",
    "gn:gn_pop":6090,
    "gn:population":6090,
    "iso:country":"PL",
    "name:bel_x_preferred":[
        "\u0413\u043e\u0440\u0430\u0434 \u0421\u044f\u0440\u0430\u043a\u0430\u045e"
    ],
    "name:fra_x_preferred":[
        "Sierakow"
    ],
    "name:lav_x_preferred":[
        "Serakova"
    ],
    "name:rus_x_preferred":[
        "\u0421\u0435\u0440\u0430\u043a\u0443\u0432"
    ],
    "name:srp_x_preferred":[
        "\u0421\u0458\u0435\u0440\u0430\u043a\u043e\u0432"
    ],
    "name:ukr_x_preferred":[
        "\u0421\u0435\u0440\u0430\u043a\u0443\u0432"
    ],
    "name:zho_x_preferred":[
        "\u8b1d\u62c9\u5eab\u592b"
    ],
    "qs_pg:aaroncc":"PL",
    "qs_pg:gn_country":"PL",
    "qs_pg:gn_fcode":"PPLA3",
    "qs_pg:gn_pop":6090,
    "qs_pg:name":"Sierak\u00f3w",
    "qs_pg:name_adm0":"Polska",
    "qs_pg:name_adm1":"Wielkopolskie",
    "qs_pg:photos":3,
    "qs_pg:photos_1k":1,
    "qs_pg:photos_9k":1,
    "qs_pg:photos_9r":1,
    "qs_pg:photos_all":3,
    "qs_pg:photos_sr":1,
    "qs_pg:pop_sr":5,
    "qs_pg:qs_pg_placetype":"localadmin",
    "qs_pg:qs_pg_placetype_gp":"LocalAdmin",
    "qs_pg:woe_adm0":23424923,
    "woe:adm0_id":23424923,
    "woe:name_adm0":"Polska",
    "woe:name_adm1":"Wielkopolskie",
    "woe:placetype":"LocalAdmin",
    "wof:name":"Sierak\u00f3w",
    "wof:placetype":"localadmin",
    "wof:population":6090
},
  "geometry": {"coordinates":[16.08047,52.65134],"type":"Point"}
}