{
  "type": "Feature",
  "properties": {
    "gn:admin1_code":"72.0",
    "gn:admin2_code":"217.0",
    "gn:admin3_code":"21704.0",
    "gn:asciiname":"Gesiniec",
    "gn:country_code":"PL",
    "gn:dem":183,
    "gn:feature_class":"P",
    "gn:feature_code":"PPL",
    "gn:name":"G\u0119siniec",
    "gn:population":0,
    "gn:timezone":"Europe/Warsaw",
    "iso:country":"PL",
    "name:ces_x_preferred":[
        "G\u0119siniec"
    ],
    "name:pol_x_preferred":[
        "G\u0119siniec"
    ],
    "name:ukr_x_preferred":[
        "\u0490\u0435\u043d\u0441\u0456\u043d\u0435\u0446\u044c"
    ],
    "name:und_x_variant":[
        "G\u0119siniec"
    ],
    "wof:name":"Gesiniec",
    "wof:placetype":"locality"
},
  "geometry": {"coordinates":[17.06424,50.7647],"type":"Point"}
}