{
  "type": "Feature",
  "properties": {
    "gn:admin1_code":"72.0",
    "gn:admin2_code":"225.0",
    "gn:admin3_code":"22505.0",
    "gn:asciiname":"Wrociszow Dolny",
    "gn:country_code":"PL",
    "gn:dem":232,
    "gn:feature_class":"P",
    "gn:feature_code":"PPL",
    "gn:name":"Wrocisz\u00f3w Dolny",
    "gn:population":0,
    "gn:timezone":"Europe/Warsaw",
    "iso:country":"PL",
    "name:pol_x_preferred":[
        "Wrocisz\u00f3w Dolny"
    ],
    "name:ukr_x_preferred":[
        "\u0412\u0440\u043e\u0446\u0438\u0448\u0443\u0432-\u0414\u043e\u043b\u044c\u043d\u0438"
    ],
    "wof:name":"Wrociszow Dolny",
    "wof:placetype":"locality"
},
  "geometry": {"coordinates":[15.0305,51.04744],"type":"Point"}
}