{
  "type": "Feature",
  "properties": {
    "gn:admin1_code":"75.0",
    "gn:admin2_code":"615.0",
    "gn:admin3_code":"61506.0",
    "gn:asciiname":"Glowne",
    "gn:country_code":"PL",
    "gn:dem":154,
    "gn:feature_class":"P",
    "gn:feature_code":"PPL",
    "gn:name":"G\u0142owne",
    "gn:population":0,
    "gn:timezone":"Europe/Warsaw",
    "iso:country":"PL",
    "name:fra_x_preferred":[
        "G\u0142\u00f3wne"
    ],
    "name:pol_x_preferred":[
        "G\u0142\u00f3wne"
    ],
    "name:ukr_x_preferred":[
        "\u0490\u043b\u0443\u0432\u043d\u0435"
    ],
    "name:und_x_variant":[
        "Kostunin",
        "G\u0142owne"
    ],
    "wof:name":"Glowne",
    "wof:placetype":"locality"
},
  "geometry": {"coordinates":[22.59127,51.86684],"type":"Point"}
}