{
  "type": "Feature",
  "properties": {
    "gn:admin1_code":"81.0",
    "gn:admin2_code":"2010.0",
    "gn:admin3_code":"201004.0",
    "gn:asciiname":"Czarna Wielka",
    "gn:cc2":"PL",
    "gn:country_code":"PL",
    "gn:dem":160,
    "gn:feature_class":"P",
    "gn:feature_code":"PPL",
    "gn:name":"Czarna Wielka",
    "gn:population":0,
    "gn:timezone":"Europe/Warsaw",
    "iso:country":"PL",
    "name:azb_x_preferred":[
        "\u0686\u0627\u0631\u0646\u0627 \u0648\u06cc\u0644\u06a9\u0627"
    ],
    "name:fas_x_preferred":[
        "\u0686\u0627\u0631\u0646\u0627 \u0648\u06cc\u0644\u06a9\u0627"
    ],
    "name:fra_x_preferred":[
        "Czarna Wielka"
    ],
    "name:lit_x_preferred":[
        "\u010carna Vielka"
    ],
    "name:pol_x_preferred":[
        "Czarna Wielka"
    ],
    "name:rue_x_preferred":[
        "\u0427\u043e\u0440\u043d\u0430 \u0412\u0435\u043b\u0456\u043a\u0430"
    ],
    "name:ukr_x_preferred":[
        "\u0427\u0430\u0440\u043d\u0430-\u0412\u0435\u043b\u0438\u043a\u0430"
    ],
    "name:und_x_variant":[
        "Czarna Wielkie"
    ],
    "wof:name":"Czarna Wielka",
    "wof:placetype":"locality"
},
  "geometry": {"coordinates":[22.82624,52.57004000000001],"type":"Point"}
}