{
  "type": "Feature",
  "properties": {
    "gn:admin1_code":"81.0",
    "gn:admin2_code":"2010.0",
    "gn:admin3_code":"201004.0",
    "gn:asciiname":"Czarna Wielka",
    "gn:cc2":"PL",
    "gn:country_code":"PL",
    "gn:dem":160,
    "gn:feature_class":"P",
    "gn:feature_code":"PPL",
    "gn:name":"Czarna Wielka",
    "gn:population":0,
    "gn:timezone":"Europe/Warsaw",
    "iso:country":"PL",
    "name:und_x_variant":[
        "Czarna Wielkie"
    ],
    "wof:name":"Czarna Wielka",
    "wof:placetype":"locality"
},
  "geometry": {"coordinates":[22.82624,52.57004000000001],"type":"Point"}
}