{
  "type": "Feature",
  "properties": {
    "gn:admin1_code":"72.0",
    "gn:admin2_code":"208.0",
    "gn:admin3_code":"20806.0",
    "gn:asciiname":"Spalona",
    "gn:country_code":"PL",
    "gn:dem":712,
    "gn:feature_class":"P",
    "gn:feature_code":"PPL",
    "gn:name":"Spalona",
    "gn:population":0,
    "gn:timezone":"Europe/Warsaw",
    "iso:country":"PL",
    "name:deu_x_preferred":[
        "Brand"
    ],
    "wof:name":"Spalona",
    "wof:placetype":"locality"
},
  "geometry": {"coordinates":[16.52937,50.28508],"type":"Point"}
}