{
  "type": "Feature",
  "properties": {
    "gn:admin1_code":"77.0",
    "gn:admin2_code":"1210.0",
    "gn:admin3_code":"121002.0",
    "gn:asciiname":"Januszowa",
    "gn:country_code":"PL",
    "gn:dem":467,
    "gn:feature_class":"P",
    "gn:feature_code":"PPL",
    "gn:name":"Januszowa",
    "gn:population":0,
    "gn:timezone":"Europe/Warsaw",
    "iso:country":"PL",
    "wof:name":"Januszowa",
    "wof:placetype":"locality"
},
  "geometry": {"coordinates":[20.73622,49.6502],"type":"Point"}
}