{
  "type": "Feature",
  "properties": {
    "gn:admin1_code":"77.0",
    "gn:admin2_code":"1210.0",
    "gn:admin3_code":"121002.0",
    "gn:asciiname":"Januszowa",
    "gn:country_code":"PL",
    "gn:dem":467,
    "gn:feature_class":"P",
    "gn:feature_code":"PPL",
    "gn:name":"Januszowa",
    "gn:population":0,
    "gn:timezone":"Europe/Warsaw",
    "iso:country":"PL",
    "name:azb_x_preferred":[
        "\u06cc\u0627\u0646\u0648\u0634\u0648\u0648\u0627"
    ],
    "name:ceb_x_preferred":[
        "Januszowa"
    ],
    "name:deu_x_preferred":[
        "Januszowa"
    ],
    "name:fas_x_preferred":[
        "\u06cc\u0627\u0646\u0648\u0634\u0648\u0648\u0627"
    ],
    "name:fra_x_preferred":[
        "Januszowa"
    ],
    "name:nld_x_preferred":[
        "Januszowa"
    ],
    "name:pol_x_preferred":[
        "Januszowa"
    ],
    "name:ukr_x_preferred":[
        "\u042f\u043d\u0443\u0448\u043e\u0432\u0430"
    ],
    "name:urd_x_preferred":[
        "\u062c\u0627\u0646\u0633\u0632\u0648\u0648\u0627"
    ],
    "wof:name":"Januszowa",
    "wof:placetype":"locality"
},
  "geometry": {"coordinates":[20.73622,49.6502],"type":"Point"}
}