{
  "type": "Feature",
  "properties": {
    "gn:admin1_code":"80.0",
    "gn:asciiname":"Dlugie",
    "gn:country_code":"PL",
    "gn:dem":528,
    "gn:feature_class":"P",
    "gn:feature_code":"PPL",
    "gn:name":"D\u0142ugie",
    "gn:population":0,
    "gn:timezone":"Europe/Warsaw",
    "iso:country":"PL",
    "wof:name":"Dlugie",
    "wof:placetype":"locality"
},
  "geometry": {"coordinates":[21.39351,49.46374],"type":"Point"}
}