{
  "type": "Feature",
  "properties": {
    "gn:admin1_code":"77.0",
    "gn:admin2_code":"1202.0",
    "gn:admin3_code":"120202.0",
    "gn:asciiname":"Kopaliny",
    "gn:country_code":"PL",
    "gn:dem":220,
    "gn:feature_class":"P",
    "gn:feature_code":"PPL",
    "gn:name":"Kopaliny",
    "gn:population":0,
    "gn:timezone":"Europe/Warsaw",
    "iso:country":"PL",
    "wof:name":"Kopaliny",
    "wof:placetype":"locality"
},
  "geometry": {"coordinates":[20.59324,49.97758],"type":"Point"}
}