{
  "type": "Feature",
  "properties": {
    "gn:admin1_code":"80.0",
    "gn:admin2_code":"1863.0",
    "gn:admin3_code":"186301.0",
    "gn:asciiname":"Baranowka",
    "gn:country_code":"PL",
    "gn:dem":220,
    "gn:feature_class":"P",
    "gn:feature_code":"PPL",
    "gn:name":"Baran\u00f3wka",
    "gn:population":0,
    "gn:timezone":"Europe/Warsaw",
    "iso:country":"PL",
    "wof:name":"Baranowka",
    "wof:placetype":"neighbourhood"
},
  "geometry": {"coordinates":[21.98107000000001,50.05887],"type":"Point"}
}