{
  "type": "Feature",
  "properties": {
    "gn:admin1_code":"81.0",
    "gn:admin2_code":"2006.0",
    "gn:admin3_code":"200602.0",
    "gn:asciiname":"Skroda Wielka",
    "gn:country_code":"PL",
    "gn:dem":130,
    "gn:feature_class":"P",
    "gn:feature_code":"PPL",
    "gn:name":"Skroda Wielka",
    "gn:population":0,
    "gn:timezone":"Europe/Warsaw",
    "iso:country":"PL",
    "name:ceb_x_preferred":[
        "Skroda Wielka"
    ],
    "name:fra_x_preferred":[
        "Skroda Wielka"
    ],
    "name:lit_x_preferred":[
        "Skroda Velka"
    ],
    "name:pol_x_preferred":[
        "Skroda Wielka"
    ],
    "name:ukr_x_preferred":[
        "\u0421\u043a\u0440\u043e\u0434\u0430-\u0412\u0435\u043b\u0438\u043a\u0430"
    ],
    "wof:name":"Skroda Wielka",
    "wof:placetype":"locality"
},
  "geometry": {"coordinates":[22.0929,53.42851],"type":"Point"}
}