{
  "type": "Feature",
  "properties": {
    "gn:admin1_code":"78.0",
    "gn:admin2_code":"1425.0",
    "gn:admin3_code":"142509.0",
    "gn:asciiname":"Goszczewice",
    "gn:country_code":"PL",
    "gn:dem":155,
    "gn:feature_class":"P",
    "gn:feature_code":"PPL",
    "gn:name":"Goszczewice",
    "gn:population":0,
    "gn:timezone":"Europe/Warsaw",
    "iso:country":"PL",
    "name:fra_x_preferred":[
        "Goszczewice"
    ],
    "name:pol_x_preferred":[
        "Goszczewice"
    ],
    "name:ukr_x_preferred":[
        "\u0490\u043e\u0449\u0435\u0432\u0456\u0446\u0435"
    ],
    "wof:name":"Goszczewice",
    "wof:placetype":"locality"
},
  "geometry": {"coordinates":[20.79696,51.45878],"type":"Point"}
}