{
  "type": "Feature",
  "properties": {
    "iso:country":"PL",
    "name:azb_x_preferred":[
        "\u062e\u0648\u062a\u0686\u0627"
    ],
    "name:ceb_x_preferred":[
        "Chotcza"
    ],
    "name:deu_x_preferred":[
        "Chotcza-J\u00f3zef\u00f3w"
    ],
    "name:fas_x_preferred":[
        "\u062e\u0648\u062a\u0686\u0627"
    ],
    "name:fra_x_preferred":[
        "Chotcza"
    ],
    "name:nld_x_preferred":[
        "Chotcza"
    ],
    "name:pol_x_preferred":[
        "Chotcza"
    ],
    "name:pol_x_variant":[
        "Chotcza-J\u00f3zef\u00f3w"
    ],
    "name:ukr_x_preferred":[
        "\u0425\u043e\u0442\u0447\u0430-\u042e\u0437\u0435\u0444\u0443\u0432"
    ],
    "wof:coterminous":[
        1125288625
    ],
    "wof:name":"Chotcza",
    "wof:placetype":"locality"
},
  "geometry": {"coordinates":[21.7330928959346,51.2422445911439],"type":"Point"}
}