{
  "type": "Feature",
  "properties": {
    "iso:country":"PL",
    "name:pol_x_preferred":[
        "Chotcza"
    ],
    "wof:coterminous":[
        1125288625
    ],
    "wof:name":"Chotcza",
    "wof:placetype":"locality"
},
  "geometry": {"coordinates":[21.7330928959346,51.2422445911439],"type":"Point"}
}