{
  "type": "Feature",
  "properties": {
    "gn:admin1_code":"74.0",
    "gn:admin2_code":"1014.0",
    "gn:admin3_code":"101405.0",
    "gn:asciiname":"Nieczuj",
    "gn:country_code":"PL",
    "gn:dem":157,
    "gn:feature_class":"P",
    "gn:feature_code":"PPL",
    "gn:name":"Nieczuj",
    "gn:population":0,
    "gn:timezone":"Europe/Warsaw",
    "iso:country":"PL",
    "name:ceb_x_preferred":[
        "Nieczuj"
    ],
    "name:pol_x_preferred":[
        "Nieczuj"
    ],
    "name:ukr_x_preferred":[
        "\u041d\u0435\u0447\u0443\u0439"
    ],
    "wof:name":"Nieczuj",
    "wof:placetype":"locality"
},
  "geometry": {"coordinates":[18.75765,51.41986],"type":"Point"}
}