{
  "type": "Feature",
  "properties": {
    "gn:admin1_code":"74.0",
    "gn:admin2_code":"1012.0",
    "gn:admin3_code":"101206.0",
    "gn:asciiname":"Orzechow",
    "gn:country_code":"PL",
    "gn:dem":236,
    "gn:feature_class":"P",
    "gn:feature_code":"PPL",
    "gn:name":"Orzech\u00f3w",
    "gn:population":0,
    "gn:timezone":"Europe/Warsaw",
    "iso:country":"PL",
    "wof:name":"Orzechow",
    "wof:placetype":"locality"
},
  "geometry": {"coordinates":[19.53985,51.03448],"type":"Point"}
}