{
  "type": "Feature",
  "properties": {
    "gn:admin1_code":"82.0",
    "gn:admin2_code":"2213.0",
    "gn:admin3_code":"221306.0",
    "gn:asciiname":"Lipinki Krolewskie",
    "gn:country_code":"PL",
    "gn:dem":103,
    "gn:feature_class":"P",
    "gn:feature_code":"PPL",
    "gn:name":"Lipinki Kr\u00f3lewskie",
    "gn:population":0,
    "gn:timezone":"Europe/Warsaw",
    "iso:country":"PL",
    "name:pol_x_preferred":[
        "Lipinki Kr\u00f3lewskie"
    ],
    "name:ukr_x_preferred":[
        "\u041b\u0456\u043f\u0456\u043d\u043a\u0456-\u041a\u0440\u0443\u043b\u0435\u0432\u0441\u044c\u043a\u0456"
    ],
    "name:und_x_variant":[
        "Lipinki Kr\u00f3lewskie"
    ],
    "wof:name":"Lipinki Krolewskie",
    "wof:placetype":"locality"
},
  "geometry": {"coordinates":[18.46948,53.88817],"type":"Point"}
}