{
  "type": "Feature",
  "properties": {
    "gn:admin1_code":"81.0",
    "gn:admin2_code":"2001.0",
    "gn:admin3_code":"200102.0",
    "gn:asciiname":"Bialobrzegi",
    "gn:country_code":"PL",
    "gn:dem":128,
    "gn:feature_class":"P",
    "gn:feature_code":"PPL",
    "gn:name":"Bia\u0142obrzegi",
    "gn:population":0,
    "gn:timezone":"Europe/Warsaw",
    "iso:country":"PL",
    "name:azb_x_preferred":[
        "\u0628\u06cc\u0627\u0648\u0648\u0628\u0698\u0642\u06cc"
    ],
    "name:ceb_x_preferred":[
        "Bia\u0142obrzegi"
    ],
    "name:eng_x_preferred":[
        "Bia\u0142obrzegi"
    ],
    "name:fas_x_preferred":[
        "\u0628\u06cc\u0627\u0648\u0648\u0628\u0698\u06af\u06cc"
    ],
    "name:fra_x_preferred":[
        "Bia\u0142obrzegi"
    ],
    "name:lit_x_preferred":[
        "Bialob\u017eegai"
    ],
    "name:pol_x_preferred":[
        "Bia\u0142obrzegi"
    ],
    "name:rus_x_preferred":[
        "\u0411\u044f\u043b\u043e\u0431\u0436\u0435\u0433\u0438"
    ],
    "name:ukr_x_preferred":[
        "\u0411\u044f\u043b\u043e\u0431\u0436\u0435\u0491\u0456"
    ],
    "name:und_x_variant":[
        "Bia\u0142obrzegi"
    ],
    "wof:name":"Bialobrzegi",
    "wof:placetype":"locality"
},
  "geometry": {"coordinates":[22.96763,53.80193000000001],"type":"Point"}
}