{
  "type": "Feature",
  "properties": {
    "gn:admin1_code":"80.0",
    "gn:admin2_code":"1803.0",
    "gn:admin3_code":"180301.0",
    "gn:asciiname":"Wolica",
    "gn:country_code":"PL",
    "gn:dem":230,
    "gn:feature_class":"P",
    "gn:feature_code":"PPL",
    "gn:name":"Wolica",
    "gn:population":0,
    "gn:timezone":"Europe/Warsaw",
    "iso:country":"PL",
    "wof:name":"Wolica",
    "wof:placetype":"locality"
},
  "geometry": {"coordinates":[21.40294,50.03219],"type":"Point"}
}