{
  "type": "Feature",
  "properties": {
    "gn:admin1_code":"73.0",
    "gn:admin2_code":"401.0",
    "gn:admin3_code":"40109.0",
    "gn:asciiname":"Wola Bachorna",
    "gn:country_code":"PL",
    "gn:dem":89,
    "gn:feature_class":"P",
    "gn:feature_code":"PPL",
    "gn:name":"Wola Bachorna",
    "gn:population":0,
    "gn:timezone":"Europe/Warsaw",
    "iso:country":"PL",
    "name:pol_x_preferred":[
        "Wola Bachorna"
    ],
    "name:ukr_x_preferred":[
        "\u0412\u043e\u043b\u044f-\u0411\u0430\u0445\u043e\u0440\u043d\u0430"
    ],
    "wof:name":"Wola Bachorna",
    "wof:placetype":"locality"
},
  "geometry": {"coordinates":[18.65346,52.73458],"type":"Point"}
}