{
  "type": "Feature",
  "properties": {
    "gn:admin1_code":"83.0",
    "gn:admin2_code":"2409.0",
    "gn:admin3_code":"240901.0",
    "gn:asciiname":"Kreciwilk",
    "gn:country_code":"PL",
    "gn:dem":308,
    "gn:feature_class":"P",
    "gn:feature_code":"PPL",
    "gn:name":"Kr\u0119ciwilk",
    "gn:population":0,
    "gn:timezone":"Europe/Warsaw",
    "iso:country":"PL",
    "wof:name":"Kreciwilk",
    "wof:placetype":"locality"
},
  "geometry": {"coordinates":[19.36984,50.54884000000001],"type":"Point"}
}