{
  "type": "Feature",
  "properties": {
    "gn:admin1_code":"73.0",
    "gn:admin2_code":"401.0",
    "gn:admin3_code":"40106.0",
    "gn:asciiname":"Opalonka",
    "gn:cc2":"PL",
    "gn:country_code":"PL",
    "gn:dem":92,
    "gn:feature_class":"P",
    "gn:feature_code":"PPL",
    "gn:name":"Opalonka",
    "gn:population":0,
    "gn:timezone":"Europe/Warsaw",
    "iso:country":"PL",
    "name:und_x_variant":[
        "Opalanka",
        "Opalonka"
    ],
    "wof:name":"Opalonka",
    "wof:placetype":"locality"
},
  "geometry": {"coordinates":[18.73358,52.7659],"type":"Point"}
}