{
  "type": "Feature",
  "properties": {
    "gn:admin1_code":"87.0",
    "gn:admin2_code":"3202.0",
    "gn:admin3_code":"320205.0",
    "gn:asciiname":"Lubiana Pyrzycka",
    "gn:country_code":"PL",
    "gn:dem":52,
    "gn:feature_class":"P",
    "gn:feature_code":"PPL",
    "gn:name":"Lubiana Pyrzycka",
    "gn:population":0,
    "gn:timezone":"Europe/Warsaw",
    "iso:country":"PL",
    "name:pol_x_preferred":[
        "Lubiana"
    ],
    "name:und_x_variant":[
        "Alt Liabehne",
        "Alt Libbehne",
        "Lubiana Pyrzycka"
    ],
    "name:vie_x_preferred":[
        "Lubiana"
    ],
    "wof:name":"Lubiana Pyrzycka",
    "wof:placetype":"locality"
},
  "geometry": {"coordinates":[15.34529,53.09882],"type":"Point"}
}