{
  "type": "Feature",
  "properties": {
    "gn:admin1_code":"84.0",
    "gn:admin2_code":"2601.0",
    "gn:admin3_code":"260108.0",
    "gn:asciiname":"Szczerbakow",
    "gn:country_code":"PL",
    "gn:dem":177,
    "gn:feature_class":"P",
    "gn:feature_code":"PPL",
    "gn:name":"Szczerbak\u00f3w",
    "gn:population":0,
    "gn:timezone":"Europe/Warsaw",
    "iso:country":"PL",
    "name:pol_x_preferred":[
        "Szczerbak\u00f3w"
    ],
    "name:ukr_x_preferred":[
        "\u0429\u0435\u0440\u0431\u0430\u043a\u0443\u0432"
    ],
    "name:und_x_variant":[
        "Szczerbak\u00f3w"
    ],
    "wof:name":"Szczerbakow",
    "wof:placetype":"locality"
},
  "geometry": {"coordinates":[20.71619,50.33904],"type":"Point"}
}