{
  "type": "Feature",
  "properties": {
    "gn:admin1_code":"75.0",
    "gn:admin2_code":"601.0",
    "gn:admin3_code":"60113.0",
    "gn:asciiname":"Mokre",
    "gn:country_code":"PL",
    "gn:dem":147,
    "gn:feature_class":"P",
    "gn:feature_code":"PPL",
    "gn:name":"Mokre",
    "gn:population":0,
    "gn:timezone":"Europe/Warsaw",
    "iso:country":"PL",
    "name:bel_x_preferred":[
        "\u041c\u043e\u043a\u0440\u0430\u0435"
    ],
    "name:ceb_x_preferred":[
        "Mokre"
    ],
    "name:deu_x_preferred":[
        "Mokre"
    ],
    "name:fra_x_preferred":[
        "Mokre"
    ],
    "name:hye_x_preferred":[
        "\u0544\u0578\u056f\u0580\u0578\u0565"
    ],
    "name:lit_x_preferred":[
        "Mokr\u0117"
    ],
    "name:pol_x_preferred":[
        "Mokre"
    ],
    "name:rus_x_preferred":[
        "\u041c\u043e\u043a\u0440\u043e\u0435"
    ],
    "name:swe_x_preferred":[
        "Mokre"
    ],
    "name:ukr_x_preferred":[
        "\u041c\u043e\u043a\u0440\u0435"
    ],
    "wof:name":"Mokre",
    "wof:placetype":"locality"
},
  "geometry": {"coordinates":[23.07762,51.85034],"type":"Point"}
}