{
  "type": "Feature",
  "properties": {
    "gn:admin1_code":"72.0",
    "gn:admin2_code":"216.0",
    "gn:admin3_code":"21601.0",
    "gn:asciiname":"Rakow",
    "gn:country_code":"PL",
    "gn:dem":153,
    "gn:feature_class":"P",
    "gn:feature_code":"PPL",
    "gn:name":"Rak\u00f3w",
    "gn:population":167,
    "gn:timezone":"Europe/Warsaw",
    "iso:country":"PL",
    "wof:name":"Rakow",
    "wof:placetype":"locality",
    "wof:population":167
},
  "geometry": {"coordinates":[15.93266,51.37425],"type":"Point"}
}