{
  "type": "Feature",
  "properties": {
    "gn:admin1_code":"81.0",
    "gn:admin2_code":"2003.0",
    "gn:admin3_code":"200303.0",
    "gn:asciiname":"Skrzypki Male",
    "gn:country_code":"PL",
    "gn:dem":175,
    "gn:feature_class":"P",
    "gn:feature_code":"PPL",
    "gn:name":"Skrzypki Ma\u0142e",
    "gn:population":0,
    "gn:timezone":"Europe/Warsaw",
    "iso:country":"PL",
    "name:azb_x_preferred":[
        "\u0633\u06a9\u0698\u067e\u06a9\u06cc \u0645\u0627\u0648\u0647"
    ],
    "name:fas_x_preferred":[
        "\u0633\u06a9\u0698\u067e\u06a9\u06cc \u0645\u0627\u0648\u0647"
    ],
    "name:fra_x_preferred":[
        "Skrzypki Ma\u0142e"
    ],
    "name:lit_x_preferred":[
        "Sk\u017eipki Mal\u0117"
    ],
    "name:pol_x_preferred":[
        "Skrzypki Ma\u0142e"
    ],
    "name:ukr_x_preferred":[
        "\u0421\u043a\u0448\u0438\u043f\u043a\u0456-\u041c\u0430\u043b\u0456"
    ],
    "name:und_x_variant":[
        "Skrzypki Ma\u0142e"
    ],
    "wof:name":"Skrzypki Male",
    "wof:placetype":"locality"
},
  "geometry": {"coordinates":[23.03842,52.72417],"type":"Point"}
}