{
  "type": "Feature",
  "properties": {
    "gn:admin1_code":"74.0",
    "gn:admin2_code":"1001.0",
    "gn:admin3_code":"100108.0",
    "gn:asciiname":"Bujny Szlacheckie",
    "gn:country_code":"PL",
    "gn:dem":193,
    "gn:feature_class":"P",
    "gn:feature_code":"PPL",
    "gn:name":"Bujny Szlacheckie",
    "gn:population":0,
    "gn:timezone":"Europe/Warsaw",
    "iso:country":"PL",
    "name:fra_x_preferred":[
        "Bujny Szlacheckie"
    ],
    "name:pol_x_preferred":[
        "Bujny Szlacheckie"
    ],
    "name:ukr_x_preferred":[
        "\u0411\u0443\u0439\u043d\u0438-\u0428\u043b\u044f\u0445\u0435\u0446\u044c\u043a\u0456"
    ],
    "wof:name":"Bujny Szlacheckie",
    "wof:placetype":"locality"
},
  "geometry": {"coordinates":[19.28333,51.46596],"type":"Point"}
}