{
  "type": "Feature",
  "properties": {
    "gn:admin1_code":"78.0",
    "gn:admin2_code":"1403.0",
    "gn:admin3_code":"140310.0",
    "gn:asciiname":"Lucznica",
    "gn:country_code":"PL",
    "gn:dem":144,
    "gn:feature_class":"P",
    "gn:feature_code":"PPL",
    "gn:name":"\u0141ucznica",
    "gn:population":0,
    "gn:timezone":"Europe/Warsaw",
    "iso:country":"PL",
    "name:fra_x_preferred":[
        "\u0141ucznica"
    ],
    "name:pol_x_preferred":[
        "\u0141ucznica"
    ],
    "name:spa_x_preferred":[
        "\u0141ucznica"
    ],
    "name:ukr_x_preferred":[
        "\u041b\u0443\u0447\u043d\u0438\u0446\u044f"
    ],
    "wof:name":"Lucznica",
    "wof:placetype":"locality"
},
  "geometry": {"coordinates":[21.48746,51.94179000000001],"type":"Point"}
}