{
  "type": "Feature",
  "properties": {
    "gn:admin1_code":"74.0",
    "gn:admin2_code":"1018.0",
    "gn:admin3_code":"101807.0",
    "gn:asciiname":"Mirkow",
    "gn:country_code":"PL",
    "gn:dem":156,
    "gn:feature_class":"P",
    "gn:feature_code":"PPL",
    "gn:name":"Mirk\u00f3w",
    "gn:population":0,
    "gn:timezone":"Europe/Warsaw",
    "iso:country":"PL",
    "name:ceb_x_preferred":[
        "Mirk\u00f3w"
    ],
    "name:pol_x_preferred":[
        "Mirk\u00f3w"
    ],
    "name:ukr_x_preferred":[
        "\u041c\u0456\u0440\u043a\u0443\u0432"
    ],
    "wof:name":"Mirkow",
    "wof:placetype":"locality"
},
  "geometry": {"coordinates":[18.15096,51.31913],"type":"Point"}
}