{
  "type": "Feature",
  "properties": {
    "gn:gn_country":"PL",
    "gn:gn_fcode":"PPL",
    "gn:gn_pop":1724,
    "gn:population":1724,
    "iso:country":"PL",
    "name:eng_x_preferred":[
        "Krosno"
    ],
    "name:fre_x_preferred":[
        "Krosno"
    ],
    "name:pol_x_preferred":[
        "Krosno"
    ],
    "qs_pg:aaroncc":"PL",
    "qs_pg:gn_country":"PL",
    "qs_pg:gn_fcode":"PPL",
    "qs_pg:gn_pop":1724,
    "qs_pg:name":"Krosno",
    "qs_pg:name_adm0":"Polska",
    "qs_pg:name_adm1":"Wielkopolskie",
    "qs_pg:photos_9r":0,
    "qs_pg:photos_sr":0,
    "qs_pg:pop_sr":3,
    "qs_pg:qs_pg_placetype":"locality",
    "qs_pg:qs_pg_placetype_gp":"Town",
    "qs_pg:woe_adm0":23424923,
    "woe:adm0_id":23424923,
    "woe:name_adm0":"Polska",
    "woe:name_adm1":"Wielkopolskie",
    "woe:placetype":"Town",
    "wof:name":"Krosno",
    "wof:placetype":"locality",
    "wof:population":1724
},
  "geometry": {"coordinates":[16.83251,52.22357],"type":"Point"}
}