{
  "type": "Feature",
  "properties": {
    "gn:admin1_code":"75.0",
    "gn:admin2_code":"620.0",
    "gn:admin3_code":"62005.0",
    "gn:asciiname":"Majdan Ruszkowski",
    "gn:country_code":"PL",
    "gn:dem":280,
    "gn:feature_class":"P",
    "gn:feature_code":"PPL",
    "gn:name":"Majdan Ruszkowski",
    "gn:population":0,
    "gn:timezone":"Europe/Warsaw",
    "iso:country":"PL",
    "name:und_x_variant":[
        "Majdan Ruszowski",
        "Majdan Ruszkowski"
    ],
    "wof:name":"Majdan Ruszkowski",
    "wof:placetype":"locality"
},
  "geometry": {"coordinates":[23.30396,50.61443],"type":"Point"}
}