{
  "type": "Feature",
  "properties": {
    "gn:admin1_code":"75.0",
    "gn:admin2_code":"620.0",
    "gn:admin3_code":"62005.0",
    "gn:asciiname":"Majdan Ruszkowski",
    "gn:country_code":"PL",
    "gn:dem":280,
    "gn:feature_class":"P",
    "gn:feature_code":"PPL",
    "gn:name":"Majdan Ruszkowski",
    "gn:population":0,
    "gn:timezone":"Europe/Warsaw",
    "iso:country":"PL",
    "name:azb_x_preferred":[
        "\u0645\u0627\u06cc\u062f\u0627\u0646 \u0631\u0648\u0634\u0648\u0648\u0633\u06a9\u06cc"
    ],
    "name:fas_x_preferred":[
        "\u0645\u0627\u06cc\u062f\u0627\u0646 \u0631\u0648\u0634\u0648\u0648\u0633\u06a9\u06cc"
    ],
    "name:fra_x_preferred":[
        "Majdan Ruszowski"
    ],
    "name:nld_x_preferred":[
        "Majdan Ruszowski"
    ],
    "name:pol_x_preferred":[
        "Majdan Ruszowski"
    ],
    "name:ukr_x_preferred":[
        "\u041c\u0430\u0439\u0434\u0430\u043d-\u0420\u0443\u0448\u043e\u0432\u0441\u044c\u043a\u0438\u0439"
    ],
    "name:und_x_variant":[
        "Majdan Ruszkowski"
    ],
    "wof:name":"Majdan Ruszkowski",
    "wof:placetype":"locality"
},
  "geometry": {"coordinates":[23.30396,50.61443],"type":"Point"}
}