{
  "type": "Feature",
  "properties": {
    "gn:admin1_code":"84.0",
    "gn:admin2_code":"2607.0",
    "gn:admin3_code":"260703.0",
    "gn:asciiname":"Mychow",
    "gn:country_code":"PL",
    "gn:dem":261,
    "gn:feature_class":"P",
    "gn:feature_code":"PPL",
    "gn:name":"Mych\u00f3w",
    "gn:population":0,
    "gn:timezone":"Europe/Warsaw",
    "iso:country":"PL",
    "name:und_x_variant":[
        "Mych\u00f3w"
    ],
    "wof:name":"Mychow",
    "wof:placetype":"locality"
},
  "geometry": {"coordinates":[21.28333,50.91667],"type":"Point"}
}