{
  "type": "Feature",
  "properties": {
    "gn:admin1_code":"86.0",
    "gn:admin2_code":"3009.0",
    "gn:admin3_code":"300901.0",
    "gn:asciiname":"Piaseczno",
    "gn:country_code":"PL",
    "gn:dem":94,
    "gn:feature_class":"P",
    "gn:feature_code":"PPL",
    "gn:name":"Piaseczno",
    "gn:population":0,
    "gn:timezone":"Europe/Warsaw",
    "iso:country":"PL",
    "name:ara_x_preferred":[
        "\u0628\u064a\u0627\u0633\u064a\u062a\u0634\u0646\u0648"
    ],
    "name:bul_x_preferred":[
        "\u041f\u044f\u0441\u0435\u0447\u043d\u043e"
    ],
    "name:ces_x_preferred":[
        "Piaseczno"
    ],
    "name:csb_x_preferred":[
        "Piaseczno"
    ],
    "name:deu_x_preferred":[
        "Piaseczno"
    ],
    "name:epo_x_preferred":[
        "Piaseczno"
    ],
    "name:est_x_preferred":[
        "Piaseczno"
    ],
    "name:fra_x_preferred":[
        "Piaseczno"
    ],
    "name:heb_x_preferred":[
        "\u05e4\u05d9\u05d0\u05e1\u05e6'\u05e0\u05d5"
    ],
    "name:isl_x_preferred":[
        "Piaseczno"
    ],
    "name:jav_x_preferred":[
        "Piaseczno"
    ],
    "name:lav_x_preferred":[
        "Pjase\u010dno"
    ],
    "name:lit_x_preferred":[
        "Piase\u010dnas"
    ],
    "name:msa_x_preferred":[
        "Piaseczno"
    ],
    "name:nld_x_preferred":[
        "Piaseczno"
    ],
    "name:pol_x_preferred":[
        "Piaseczno"
    ],
    "name:por_x_preferred":[
        "Piaseczno"
    ],
    "name:ron_x_preferred":[
        "Piaseczno"
    ],
    "name:rus_x_preferred":[
        "\u041f\u044f\u0441\u0435\u0447\u043d\u043e"
    ],
    "name:slk_x_preferred":[
        "Piaseczno"
    ],
    "name:srp_x_preferred":[
        "\u041f\u0458\u0430\u0441\u0435\u0447\u043d\u043e"
    ],
    "name:swe_x_preferred":[
        "Piaseczno"
    ],
    "name:szl_x_preferred":[
        "Pjoseczno"
    ],
    "name:ukr_x_preferred":[
        "\u041f\u044f\u0441\u0435\u0447\u043d\u043e"
    ],
    "name:vie_x_preferred":[
        "Piaseczno"
    ],
    "name:war_x_preferred":[
        "Piaseczno"
    ],
    "name:zho_x_preferred":[
        "\u76ae\u4e9e\u585e\u5947\u8afe"
    ],
    "wof:name":"Piaseczno",
    "wof:placetype":"neighbourhood"
},
  "geometry": {"coordinates":[18.63717,52.17019000000001],"type":"Point"}
}