{
  "type": "Feature",
  "properties": {
    "gn:admin1_code":"84.0",
    "gn:admin2_code":"2606.0",
    "gn:admin3_code":"260608.0",
    "gn:asciiname":"Kaliszany",
    "gn:country_code":"PL",
    "gn:dem":209,
    "gn:feature_class":"P",
    "gn:feature_code":"PPL",
    "gn:name":"Kaliszany",
    "gn:population":0,
    "gn:timezone":"Europe/Warsaw",
    "iso:country":"PL",
    "wof:name":"Kaliszany",
    "wof:placetype":"locality"
},
  "geometry": {"coordinates":[21.53752,50.83199000000001],"type":"Point"}
}