{
  "type": "Feature",
  "properties": {
    "gn:admin1_code":"85.0",
    "gn:admin2_code":"2801.0",
    "gn:admin3_code":"280104.0",
    "gn:asciiname":"Prosity",
    "gn:country_code":"PL",
    "gn:dem":144,
    "gn:feature_class":"P",
    "gn:feature_code":"PPL",
    "gn:name":"Prosity",
    "gn:population":0,
    "gn:timezone":"Europe/Warsaw",
    "iso:country":"PL",
    "name:azb_x_preferred":[
        "\u067e\u0631\u0648\u0634\u062a\u0647"
    ],
    "name:deu_x_preferred":[
        "Prosity"
    ],
    "name:fas_x_preferred":[
        "\u067e\u0631\u0648\u0634\u062a\u0647"
    ],
    "name:fra_x_preferred":[
        "Prosity"
    ],
    "name:pol_x_preferred":[
        "Prosity"
    ],
    "name:ukr_x_preferred":[
        "\u041f\u0440\u043e\u0441\u0456\u0442\u0438"
    ],
    "name:und_x_variant":[
        "Prossitten",
        "Prositten",
        "Prosity"
    ],
    "name:vie_x_preferred":[
        "Prosity"
    ],
    "wof:name":"Prosity",
    "wof:placetype":"locality"
},
  "geometry": {"coordinates":[20.80215,54.05627],"type":"Point"}
}