{
  "type": "Feature",
  "properties": {
    "gn:admin1_code":"85.0",
    "gn:admin2_code":"2801.0",
    "gn:admin3_code":"280104.0",
    "gn:asciiname":"Prosity",
    "gn:country_code":"PL",
    "gn:dem":144,
    "gn:feature_class":"P",
    "gn:feature_code":"PPL",
    "gn:name":"Prosity",
    "gn:population":0,
    "gn:timezone":"Europe/Warsaw",
    "iso:country":"PL",
    "name:und_x_variant":[
        "Prossitten",
        "Prositten",
        "Prosity"
    ],
    "wof:name":"Prosity",
    "wof:placetype":"locality"
},
  "geometry": {"coordinates":[20.80215,54.05627],"type":"Point"}
}