{
  "type": "Feature",
  "properties": {
    "gn:country":"PL",
    "gn:fcode":"PPL",
    "gn:population":625,
    "iso:country":"PL",
    "name:ast_x_preferred":[
        "Postomino"
    ],
    "name:deu_x_preferred":[
        "Postomino"
    ],
    "name:eng_x_preferred":[
        "Postomino"
    ],
    "name:fra_x_preferred":[
        "Postomino"
    ],
    "name:jpn_x_preferred":[
        "\u30dd\u30b9\u30c8\u30df\u30ce"
    ],
    "name:nld_x_preferred":[
        "Postomino"
    ],
    "name:pol_x_preferred":[
        "Postomino"
    ],
    "name:ukr_x_preferred":[
        "\u041f\u043e\u0441\u0442\u043e\u043c\u0456\u043d\u043e"
    ],
    "name:und_x_variant":[
        "Pustamin"
    ],
    "name:vie_x_preferred":[
        "Postomino"
    ],
    "qs_pg:aaroncc":"PL",
    "qs_pg:gn_country":"PL",
    "qs_pg:gn_fcode":"PPL",
    "qs_pg:gn_pop":625,
    "qs_pg:name":"Postomino",
    "qs_pg:name_adm0":"Polska",
    "qs_pg:name_adm1":"Zachodniopomorskie",
    "qs_pg:photos_9k":1,
    "qs_pg:photos_9r":1,
    "qs_pg:photos_all":1,
    "qs_pg:photos_sr":0,
    "qs_pg:pop_sr":2,
    "qs_pg:qs_pg_placetype":"locality",
    "qs_pg:qs_pg_placetype_gp":"Town",
    "qs_pg:woe_adm0":23424923,
    "woe:adm0_id":23424923,
    "woe:name_adm0":"Polska",
    "woe:name_adm1":"Zachodniopomorskie",
    "woe:placetype":"Town",
    "wof:name":"Postomino",
    "wof:placetype":"locality",
    "wof:population":625
},
  "geometry": {"coordinates":[16.71381,54.49377],"type":"Point"}
}