{
  "type": "Feature",
  "properties": {
    "gn:gn_country":"PL",
    "gn:gn_fcode":"PPLA3",
    "gn:gn_pop":523,
    "gn:population":523,
    "iso:country":"PL",
    "name:eng_x_preferred":[
        "Regimin"
    ],
    "name:rus_x_preferred":[
        "\u0420\u0435\u0433\u0438\u043c\u0438\u043d"
    ],
    "qs_pg:aaroncc":"PL",
    "qs_pg:gn_country":"PL",
    "qs_pg:gn_fcode":"PPLA3",
    "qs_pg:gn_pop":523,
    "qs_pg:name":"Regimin",
    "qs_pg:name_adm0":"Polska",
    "qs_pg:name_adm1":"Mazowieckie",
    "qs_pg:photos_9r":0,
    "qs_pg:photos_sr":0,
    "qs_pg:pop_sr":2,
    "qs_pg:qs_pg_placetype":"localadmin",
    "qs_pg:qs_pg_placetype_gp":"LocalAdmin",
    "qs_pg:woe_adm0":23424923,
    "woe:adm0_id":23424923,
    "woe:name_adm0":"Polska",
    "woe:name_adm1":"Mazowieckie",
    "woe:placetype":"LocalAdmin",
    "wof:name":"Regimin",
    "wof:placetype":"localadmin",
    "wof:population":523
},
  "geometry": {"coordinates":[20.55319,52.94166],"type":"Point"}
}