{
  "type": "Feature",
  "properties": {
    "gn:admin1_code":"78.0",
    "gn:admin2_code":"1462.0",
    "gn:admin3_code":"146201.0",
    "gn:asciiname":"Maszewo Male",
    "gn:country_code":"PL",
    "gn:dem":99,
    "gn:feature_class":"P",
    "gn:feature_code":"PPL",
    "gn:name":"Maszewo Ma\u0142e",
    "gn:population":0,
    "gn:timezone":"Europe/Warsaw",
    "iso:country":"PL",
    "wof:name":"Maszewo Male",
    "wof:placetype":"neighbourhood"
},
  "geometry": {"coordinates":[19.65,52.56667],"type":"Point"}
}