{
  "type": "Feature",
  "properties": {
    "gn:admin1_code":"85.0",
    "gn:admin2_code":"2815.0",
    "gn:admin3_code":"281502.0",
    "gn:asciiname":"Lewald Wielki",
    "gn:country_code":"PL",
    "gn:dem":219,
    "gn:feature_class":"P",
    "gn:feature_code":"PPL",
    "gn:name":"Lewa\u0142d Wielki",
    "gn:population":0,
    "gn:timezone":"Europe/Warsaw",
    "iso:country":"PL",
    "name:azb_x_preferred":[
        "\u0644\u0648\u0627\u0648\u062f \u0648\u06cc\u0644\u06a9\u06cc"
    ],
    "name:ceb_x_preferred":[
        "Lewa\u0142d Wielki"
    ],
    "name:fas_x_preferred":[
        "\u0644\u0648\u0627\u0648\u062f \u0648\u06cc\u0644\u06a9\u06cc"
    ],
    "name:fra_x_preferred":[
        "Lewa\u0142d Wielki"
    ],
    "name:nld_x_preferred":[
        "Lewa\u0142d Wielki"
    ],
    "name:pol_x_preferred":[
        "Lewa\u0142d Wielki"
    ],
    "name:ukr_x_preferred":[
        "\u041b\u0435\u0432\u0430\u043b\u0434-\u0412\u0435\u043b\u0438\u043a\u0438\u0439"
    ],
    "name:und_x_variant":[
        "Wielki Lewa\u0142d",
        "Gross Lehwalde",
        "Lewa\u0142d"
    ],
    "name:vie_x_preferred":[
        "Lewa\u0142d Wielki"
    ],
    "wof:name":"Lewald Wielki",
    "wof:placetype":"locality"
},
  "geometry": {"coordinates":[19.98692,53.43691999999999],"type":"Point"}
}