{
  "type": "Feature",
  "properties": {
    "gn:admin1_code":"81.0",
    "gn:admin2_code":"2001.0",
    "gn:admin3_code":"200106.0",
    "gn:asciiname":"Strzelcowizna",
    "gn:country_code":"PL",
    "gn:dem":119,
    "gn:feature_class":"P",
    "gn:feature_code":"PPL",
    "gn:name":"Strzelcowizna",
    "gn:population":0,
    "gn:timezone":"Europe/Warsaw",
    "iso:country":"PL",
    "name:lit_x_preferred":[
        "St\u017eelcovizna"
    ],
    "name:pol_x_preferred":[
        "Strzelcowizna"
    ],
    "name:ukr_x_preferred":[
        "\u0421\u0442\u0448\u0435\u043b\u044c\u0446\u043e\u0432\u0456\u0437\u043d\u0430"
    ],
    "wof:name":"Strzelcowizna",
    "wof:placetype":"locality"
},
  "geometry": {"coordinates":[23.31474,53.94176],"type":"Point"}
}