{
  "type": "Feature",
  "properties": {
    "gn:admin1_code":"86.0",
    "gn:admin2_code":"3025.0",
    "gn:admin3_code":"302505.0",
    "gn:asciiname":"Bozydar",
    "gn:country_code":"PL",
    "gn:dem":79,
    "gn:feature_class":"P",
    "gn:feature_code":"PPL",
    "gn:name":"Bo\u017cydar",
    "gn:population":0,
    "gn:timezone":"Europe/Warsaw",
    "iso:country":"PL",
    "name:fra_x_preferred":[
        "Bo\u017cydar"
    ],
    "name:pol_x_preferred":[
        "Bo\u017cydar"
    ],
    "name:ukr_x_preferred":[
        "\u0411\u043e\u0436\u0438\u0434\u0430\u0440"
    ],
    "name:und_x_variant":[
        "Bo\u017cydar"
    ],
    "wof:name":"Bozydar",
    "wof:placetype":"locality"
},
  "geometry": {"coordinates":[17.1422,52.2121],"type":"Point"}
}