{
  "type": "Feature",
  "properties": {
    "gn:admin1_code":"86.0",
    "gn:admin2_code":"3009.0",
    "gn:admin3_code":"300906.0",
    "gn:asciiname":"Rycerzew",
    "gn:country_code":"PL",
    "gn:dem":117,
    "gn:feature_class":"P",
    "gn:feature_code":"PPL",
    "gn:name":"Rycerzew",
    "gn:population":0,
    "gn:timezone":"Europe/Warsaw",
    "iso:country":"PL",
    "name:pol_x_preferred":[
        "Rycerzew"
    ],
    "name:ukr_x_preferred":[
        "\u0420\u0438\u0446\u0435\u0436\u0435\u0432"
    ],
    "wof:name":"Rycerzew",
    "wof:placetype":"locality"
},
  "geometry": {"coordinates":[18.97081,52.21486],"type":"Point"}
}