{
  "type": "Feature",
  "properties": {
    "gn:gn_country":"PL",
    "gn:gn_fcode":"PPLA3",
    "gn:gn_pop":2988,
    "gn:population":2988,
    "iso:country":"PL",
    "name:csb_x_preferred":[
        "Sztutow\u00f2"
    ],
    "name:lit_x_preferred":[
        "\u0160tutovas"
    ],
    "name:ukr_x_preferred":[
        "\u0428\u0442\u0443\u0442\u043e\u0432\u043e"
    ],
    "qs_pg:aaroncc":"PL",
    "qs_pg:gn_country":"PL",
    "qs_pg:gn_fcode":"PPLA3",
    "qs_pg:gn_pop":2988,
    "qs_pg:name":"Sztutowo",
    "qs_pg:name_adm0":"Polska",
    "qs_pg:name_adm1":"Pomorskie",
    "qs_pg:photos":2,
    "qs_pg:photos_1k":1,
    "qs_pg:photos_9k":1,
    "qs_pg:photos_9r":5,
    "qs_pg:photos_all":313,
    "qs_pg:photos_sr":1,
    "qs_pg:pop_sr":4,
    "qs_pg:qs_pg_placetype":"localadmin",
    "qs_pg:qs_pg_placetype_gp":"LocalAdmin",
    "qs_pg:woe_adm0":23424923,
    "woe:adm0_id":23424923,
    "woe:name_adm0":"Polska",
    "woe:name_adm1":"Pomorskie",
    "woe:placetype":"LocalAdmin",
    "wof:name":"Sztutowo",
    "wof:placetype":"localadmin",
    "wof:population":2988
},
  "geometry": {"coordinates":[19.17921,54.32679],"type":"Point"}
}