{
  "type": "Feature",
  "properties": {
    "gn:admin1_code":"83.0",
    "gn:admin2_code":"2415.0",
    "gn:admin3_code":"241507.0",
    "gn:asciiname":"Trawniki",
    "gn:country_code":"PL",
    "gn:dem":187,
    "gn:feature_class":"P",
    "gn:feature_code":"PPL",
    "gn:name":"Trawniki",
    "gn:population":0,
    "gn:timezone":"Europe/Warsaw",
    "iso:country":"PL",
    "wof:name":"Trawniki",
    "wof:placetype":"locality"
},
  "geometry": {"coordinates":[18.26557,50.03816],"type":"Point"}
}