{
  "type": "Feature",
  "properties": {
    "gn:admin1_code":"72.0",
    "gn:admin2_code":"211.0",
    "gn:admin3_code":"21103.0",
    "gn:asciiname":"Stara Rudna",
    "gn:country_code":"PL",
    "gn:dem":133,
    "gn:feature_class":"P",
    "gn:feature_code":"PPL",
    "gn:name":"Stara Rudna",
    "gn:population":0,
    "gn:timezone":"Europe/Warsaw",
    "iso:country":"PL",
    "name:ceb_x_preferred":[
        "Stara Rudna"
    ],
    "name:deu_x_historical":[
        "Alt Raudten"
    ],
    "name:deu_x_preferred":[
        "Alt Raudten"
    ],
    "name:pol_x_preferred":[
        "Stara Rudna"
    ],
    "name:ukr_x_preferred":[
        "\u0421\u0442\u0430\u0440\u0430 \u0420\u0443\u0434\u043d\u0430"
    ],
    "wof:name":"Stara Rudna",
    "wof:placetype":"locality"
},
  "geometry": {"coordinates":[16.28358,51.49378],"type":"Point"}
}