{
  "type": "Feature",
  "properties": {
    "gn:admin1_code":"75.0",
    "gn:asciiname":"Liwki Szlacheckie",
    "gn:country_code":"PL",
    "gn:dem":160,
    "gn:feature_class":"P",
    "gn:feature_code":"PPL",
    "gn:name":"Liwki Szlacheckie",
    "gn:population":0,
    "gn:timezone":"Europe/Warsaw",
    "iso:country":"PL",
    "name:azb_x_preferred":[
        "\u0644\u06cc\u0648\u06a9\u06cc \u0634\u0644\u0627\u062e\u062a\u0633\u06a9\u06cc\u0647"
    ],
    "name:fas_x_preferred":[
        "\u0644\u06cc\u0648\u06a9\u06cc \u0634\u0644\u0627\u062e\u062a\u0633\u06a9\u06cc\u0647"
    ],
    "name:fra_x_preferred":[
        "Liwki Szlacheckie"
    ],
    "name:lit_x_preferred":[
        "Livki \u0160lacheckiai"
    ],
    "name:pol_x_preferred":[
        "Liwki Szlacheckie"
    ],
    "name:szl_x_preferred":[
        "Szlachecke Liwki"
    ],
    "name:ukr_x_preferred":[
        "\u041b\u0456\u0432\u043a\u0456-\u0428\u043b\u044f\u0445\u0435\u0446\u044c\u043a\u0456"
    ],
    "wof:name":"Liwki Szlacheckie",
    "wof:placetype":"locality"
},
  "geometry": {"coordinates":[22.80865,52.13054],"type":"Point"}
}