{
  "type": "Feature",
  "properties": {
    "gn:admin1_code":"79.0",
    "gn:admin2_code":"1607.0",
    "gn:admin3_code":"160706.0",
    "gn:asciiname":"Siedlec",
    "gn:country_code":"PL",
    "gn:dem":249,
    "gn:feature_class":"P",
    "gn:feature_code":"PPL",
    "gn:name":"Siedlec",
    "gn:population":0,
    "gn:timezone":"Europe/Warsaw",
    "iso:country":"PL",
    "name:ceb_x_preferred":[
        "Siedlec"
    ],
    "name:deu_x_preferred":[
        "Siedlec"
    ],
    "name:fra_x_preferred":[
        "Siedlec"
    ],
    "name:nld_x_preferred":[
        "Siedlec"
    ],
    "name:pol_x_preferred":[
        "Siedlec"
    ],
    "name:ukr_x_preferred":[
        "\u0421\u0435\u0434\u043b\u0435\u0446\u044c"
    ],
    "wof:name":"Siedlec",
    "wof:placetype":"locality"
},
  "geometry": {"coordinates":[17.19687,50.51943],"type":"Point"}
}