{
  "type": "Feature",
  "properties": {
    "gn:admin1_code":"78.0",
    "gn:admin2_code":"1437.0",
    "gn:admin3_code":"143701.0",
    "gn:asciiname":"Stanislawowo",
    "gn:country_code":"PL",
    "gn:dem":113,
    "gn:feature_class":"P",
    "gn:feature_code":"PPL",
    "gn:name":"Stanis\u0142awowo",
    "gn:population":0,
    "gn:timezone":"Europe/Warsaw",
    "iso:country":"PL",
    "name:und_x_variant":[
        "Stanis\u0142awowo"
    ],
    "wof:name":"Stanislawowo",
    "wof:placetype":"locality"
},
  "geometry": {"coordinates":[19.91595,52.92175],"type":"Point"}
}