{
  "type": "Feature",
  "properties": {
    "gn:admin1_code":"78.0",
    "gn:admin2_code":"1437.0",
    "gn:admin3_code":"143701.0",
    "gn:asciiname":"Stanislawowo",
    "gn:country_code":"PL",
    "gn:dem":113,
    "gn:feature_class":"P",
    "gn:feature_code":"PPL",
    "gn:name":"Stanis\u0142awowo",
    "gn:population":0,
    "gn:timezone":"Europe/Warsaw",
    "iso:country":"PL",
    "name:fra_x_preferred":[
        "Stanis\u0142awowo"
    ],
    "name:pol_x_preferred":[
        "Stanis\u0142awowo"
    ],
    "name:ukr_x_preferred":[
        "\u0421\u0442\u0430\u043d\u0456\u0441\u043b\u0430\u0432\u043e\u0432\u043e"
    ],
    "wof:name":"Stanislawowo",
    "wof:placetype":"locality"
},
  "geometry": {"coordinates":[19.91595,52.92175],"type":"Point"}
}