{
  "type": "Feature",
  "properties": {
    "gn:admin1_code":"85.0",
    "gn:admin2_code":"2813.0",
    "gn:admin3_code":"281304.0",
    "gn:asciiname":"Dobki",
    "gn:country_code":"PL",
    "gn:dem":164,
    "gn:feature_class":"P",
    "gn:feature_code":"PPL",
    "gn:name":"Dobki",
    "gn:population":0,
    "gn:timezone":"Europe/Warsaw",
    "iso:country":"PL",
    "name:deu_x_preferred":[
        "Dobki"
    ],
    "name:fra_x_preferred":[
        "Dobki"
    ],
    "name:pol_x_preferred":[
        "Dobki"
    ],
    "name:ukr_x_preferred":[
        "\u0414\u043e\u0431\u043a\u0456"
    ],
    "name:und_x_variant":[
        "Markgrafsfelde",
        "Dopken",
        "Dopki"
    ],
    "wof:name":"Dobki",
    "wof:placetype":"locality"
},
  "geometry": {"coordinates":[22.3996,54.03538],"type":"Point"}
}