{
  "type": "Feature",
  "properties": {
    "gn:admin1_code":"77.0",
    "gn:admin2_code":"1216.0",
    "gn:admin3_code":"121615.0",
    "gn:asciiname":"Otfinow",
    "gn:country_code":"PL",
    "gn:dem":176,
    "gn:feature_class":"P",
    "gn:feature_code":"PPL",
    "gn:name":"Otfin\u00f3w",
    "gn:population":0,
    "gn:timezone":"Europe/Warsaw",
    "iso:country":"PL",
    "name:pol_x_preferred":[
        "Otfin\u00f3w"
    ],
    "name:ukr_x_preferred":[
        "\u041e\u0442\u0444\u0456\u043d\u0443\u0432"
    ],
    "wof:name":"Otfinow",
    "wof:placetype":"locality"
},
  "geometry": {"coordinates":[20.81053,50.18434],"type":"Point"}
}