{
  "type": "Feature",
  "properties": {
    "gn:country":"PL",
    "gn:fcode":"PPL",
    "gn:population":0,
    "iso:country":"PL",
    "name:ast_x_preferred":[
        "Winniki"
    ],
    "name:eng_x_preferred":[
        "Winniki"
    ],
    "name:fra_x_preferred":[
        "Winniki"
    ],
    "name:pol_x_preferred":[
        "Winniki"
    ],
    "name:ukr_x_preferred":[
        "\u0412\u0456\u043d\u043d\u0438\u043a\u0438"
    ],
    "qs_pg:aaroncc":"PL",
    "qs_pg:gn_country":"PL",
    "qs_pg:gn_fcode":"PPL",
    "qs_pg:gn_pop":0,
    "qs_pg:name":"Winniki",
    "qs_pg:name_adm0":"Polska",
    "qs_pg:name_adm1":"Zachodniopomorskie",
    "qs_pg:photos_9r":0,
    "qs_pg:photos_sr":0,
    "qs_pg:pop_sr":0,
    "qs_pg:qs_pg_placetype":"locality",
    "qs_pg:qs_pg_placetype_gp":"Town",
    "qs_pg:woe_adm0":23424923,
    "woe:adm0_id":23424923,
    "woe:name_adm0":"Polska",
    "woe:name_adm1":"Zachodniopomorskie",
    "woe:placetype":"Town",
    "wof:name":"Winniki",
    "wof:placetype":"locality"
},
  "geometry": {"coordinates":[15.49695,53.52295],"type":"Point"}
}