{
  "type": "Feature",
  "properties": {
    "gn:admin1_code":"78.0",
    "gn:admin2_code":"1416.0",
    "gn:admin3_code":"141610.0",
    "gn:asciiname":"Rynek",
    "gn:country_code":"PL",
    "gn:dem":122,
    "gn:feature_class":"P",
    "gn:feature_code":"PPL",
    "gn:name":"Rynek",
    "gn:population":0,
    "gn:timezone":"Europe/Warsaw",
    "iso:country":"PL",
    "name:fra_x_preferred":[
        "Rynek"
    ],
    "name:pol_x_preferred":[
        "Rynek"
    ],
    "name:ukr_x_preferred":[
        "\u0420\u0438\u043d\u0435\u043a"
    ],
    "wof:name":"Rynek",
    "wof:placetype":"locality"
},
  "geometry": {"coordinates":[21.75178,52.85602],"type":"Point"}
}