{
  "type": "Feature",
  "properties": {
    "gn:admin1_code":"80.0",
    "gn:admin2_code":"1820.0",
    "gn:admin3_code":"182002.0",
    "gn:asciiname":"Pasternik",
    "gn:country_code":"PL",
    "gn:dem":140,
    "gn:feature_class":"P",
    "gn:feature_code":"PPL",
    "gn:name":"Pasternik",
    "gn:population":0,
    "gn:timezone":"Europe/Warsaw",
    "iso:country":"PL",
    "name:fra_x_preferred":[
        "Pasternik"
    ],
    "name:pol_x_preferred":[
        "Pasternik"
    ],
    "name:ukr_x_preferred":[
        "\u041f\u0430\u0441\u0442\u0435\u0440\u043d\u0438\u043a"
    ],
    "wof:name":"Pasternik",
    "wof:placetype":"locality"
},
  "geometry": {"coordinates":[21.85647,50.72029000000001],"type":"Point"}
}