{
  "type": "Feature",
  "properties": {
    "iso:country":"PL",
    "name:bel_x_preferred":[
        "\u0411\u0436\u044d\u0437\u0456\u043d\u044b"
    ],
    "name:bul_x_preferred":[
        "\u0411\u0436\u0435\u0436\u0438\u043d\u0438"
    ],
    "name:ceb_x_preferred":[
        "Brzeziny"
    ],
    "name:deu_x_preferred":[
        "Brzeziny"
    ],
    "name:dsb_x_preferred":[
        "Brzeziny"
    ],
    "name:epo_x_preferred":[
        "Brzeziny"
    ],
    "name:eus_x_preferred":[
        "Brzeziny"
    ],
    "name:fas_x_preferred":[
        "\u0628\u0698\u0698\u06cc\u0646\u0647"
    ],
    "name:fin_x_preferred":[
        "Brzeziny"
    ],
    "name:fra_x_preferred":[
        "Brzeziny"
    ],
    "name:heb_x_preferred":[
        "\u05d1\u05d6'\u05d6'\u05d9\u05e0\u05d9"
    ],
    "name:ind_x_preferred":[
        "Brzeziny"
    ],
    "name:ita_x_preferred":[
        "Brzeziny"
    ],
    "name:jav_x_preferred":[
        "Brzeziny"
    ],
    "name:kor_x_preferred":[
        "\ube0c\uc170\uc9c0\ub2c8"
    ],
    "name:lav_x_preferred":[
        "B\u017eezini"
    ],
    "name:msa_x_preferred":[
        "Brzeziny"
    ],
    "name:nld_x_preferred":[
        "Brzeziny"
    ],
    "name:pol_x_preferred":[
        "Brzeziny"
    ],
    "name:por_x_preferred":[
        "Brzeziny"
    ],
    "name:ron_x_preferred":[
        "Brzeziny"
    ],
    "name:rus_x_preferred":[
        "\u0411\u0436\u0435\u0437\u0438\u043d\u044b"
    ],
    "name:slk_x_preferred":[
        "Brzeziny"
    ],
    "name:srp_x_preferred":[
        "\u0411\u0436\u0435\u0437\u0438\u043d\u0438"
    ],
    "name:ukr_x_preferred":[
        "\u0411\u0436\u0435\u0437\u0456\u043d\u0438"
    ],
    "name:urd_x_preferred":[
        "\u0628\u0631\u0632\u0632\u0646\u0646\u06d2"
    ],
    "name:vie_x_preferred":[
        "Brzeziny"
    ],
    "name:war_x_preferred":[
        "Brzeziny"
    ],
    "name:zho_x_preferred":[
        "\u5e03\u672d\u5e0c\u5c3c"
    ],
    "wof:name":"Brzeziny",
    "wof:placetype":"neighbourhood"
},
  "geometry": {"coordinates":[21.05185580070049,52.31160044120517],"type":"Point"}
}