{
  "type": "Feature",
  "properties": {
    "iso:country":"PL",
    "wof:name":"Brzeziny",
    "wof:placetype":"neighbourhood"
},
  "geometry": {"coordinates":[21.05185580070049,52.31160044120517],"type":"Point"}
}