{
  "type": "Feature",
  "properties": {
    "gn:admin1_code":"82.0",
    "gn:admin2_code":"2216.0",
    "gn:admin3_code":"221601.0",
    "gn:asciiname":"Spalonki",
    "gn:country_code":"PL",
    "gn:dem":6,
    "gn:feature_class":"P",
    "gn:feature_code":"PPL",
    "gn:name":"Spalonki",
    "gn:population":0,
    "gn:timezone":"Europe/Warsaw",
    "iso:country":"PL",
    "name:pol_x_preferred":[
        "Spalonki"
    ],
    "wof:name":"Spalonki",
    "wof:placetype":"locality"
},
  "geometry": {"coordinates":[19.34212,53.9999],"type":"Point"}
}