{
  "type": "Feature",
  "properties": {
    "gn:admin1_code":"75.0",
    "gn:admin2_code":"604.0",
    "gn:admin3_code":"60402.0",
    "gn:asciiname":"Podhajczyki",
    "gn:country_code":"PL",
    "gn:dem":203,
    "gn:feature_class":"P",
    "gn:feature_code":"PPL",
    "gn:name":"Podhajczyki",
    "gn:population":0,
    "gn:timezone":"Europe/Warsaw",
    "iso:country":"PL",
    "name:fra_x_preferred":[
        "Podhajczyki"
    ],
    "name:pol_x_preferred":[
        "Podhajczyki"
    ],
    "name:ukr_x_preferred":[
        "\u041f\u043e\u0434\u0433\u0430\u0439\u0447\u0438\u043a\u0456"
    ],
    "wof:name":"Podhajczyki",
    "wof:placetype":"locality"
},
  "geometry": {"coordinates":[23.99524,50.60257],"type":"Point"}
}