{
  "type": "Feature",
  "properties": {
    "gn:admin1_code":"75.0",
    "gn:admin2_code":"616.0",
    "gn:admin3_code":"61605.0",
    "gn:asciiname":"Kolonia Brzesce",
    "gn:country_code":"PL",
    "gn:dem":114,
    "gn:feature_class":"P",
    "gn:feature_code":"PPL",
    "gn:name":"Kolonia Brze\u015bce",
    "gn:population":0,
    "gn:timezone":"Europe/Warsaw",
    "iso:country":"PL",
    "wof:name":"Kolonia Brzesce",
    "wof:placetype":"locality"
},
  "geometry": {"coordinates":[21.71362,51.58871],"type":"Point"}
}