{
  "type": "Feature",
  "properties": {
    "gn:gn_country":"PL",
    "gn:gn_fcode":"PPLA3",
    "gn:gn_pop":4716,
    "gn:population":4716,
    "iso:country":"PL",
    "name:lav_x_preferred":[
        "Kci\u0146a"
    ],
    "name:rus_x_preferred":[
        "\u041a\u0446\u044b\u043d\u044f"
    ],
    "name:srp_x_preferred":[
        "\u041a\u0446\u0438\u045a\u0430"
    ],
    "name:ukr_x_preferred":[
        "\u041a\u0446\u0438\u043d\u044f"
    ],
    "name:zho_x_preferred":[
        "\u514b\u9f4a\u5c3c\u4e9e"
    ],
    "qs_pg:aaroncc":"PL",
    "qs_pg:gn_country":"PL",
    "qs_pg:gn_fcode":"PPLA3",
    "qs_pg:gn_pop":4716,
    "qs_pg:name":"Kcynia",
    "qs_pg:name_adm0":"Polska",
    "qs_pg:name_adm1":"Kujawsko-Pomorskie",
    "qs_pg:photos":2,
    "qs_pg:photos_1k":1,
    "qs_pg:photos_9k":1,
    "qs_pg:photos_9r":1,
    "qs_pg:photos_all":2,
    "qs_pg:photos_sr":1,
    "qs_pg:pop_sr":6,
    "qs_pg:qs_pg_placetype":"localadmin",
    "qs_pg:qs_pg_placetype_gp":"LocalAdmin",
    "qs_pg:woe_adm0":23424923,
    "woe:adm0_id":23424923,
    "woe:name_adm0":"Polska",
    "woe:name_adm1":"Kujawsko-Pomorskie",
    "woe:placetype":"LocalAdmin",
    "wof:name":"Kcynia",
    "wof:placetype":"localadmin",
    "wof:population":4716
},
  "geometry": {"coordinates":[17.4883,52.99192],"type":"Point"}
}