{
  "type": "Feature",
  "properties": {
    "gn:admin1_code":"78.0",
    "gn:admin2_code":"1420.0",
    "gn:admin3_code":"142012.0",
    "gn:asciiname":"Falbogi Wielkie",
    "gn:country_code":"PL",
    "gn:dem":111,
    "gn:feature_class":"P",
    "gn:feature_code":"PPL",
    "gn:name":"Falbogi Wielkie",
    "gn:population":0,
    "gn:timezone":"Europe/Warsaw",
    "iso:country":"PL",
    "name:azb_x_preferred":[
        "\u0641\u0627\u0644\u0628\u0648\u0642\u06cc \u0648\u06cc\u0644\u06a9\u06cc\u0647"
    ],
    "name:fas_x_preferred":[
        "\u0641\u0627\u0644\u0628\u0648\u06af\u06cc \u0648\u06cc\u0644\u06a9\u06cc\u0647"
    ],
    "name:fra_x_preferred":[
        "Falbogi Wielkie"
    ],
    "name:pol_x_preferred":[
        "Falbogi Wielkie"
    ],
    "name:ukr_x_preferred":[
        "\u0424\u0430\u043b\u044c\u0431\u043e\u0491\u0456-\u0412\u0435\u043b\u0438\u043a\u0456"
    ],
    "name:urd_x_preferred":[
        "\u0641\u0627\u0644\u0628\u0648\u06af\u06cc \u0648\u06cc\u0644\u06a9\u06cc"
    ],
    "wof:name":"Falbogi Wielkie",
    "wof:placetype":"locality"
},
  "geometry": {"coordinates":[20.57648,52.50827],"type":"Point"}
}