{
  "type": "Feature",
  "properties": {
    "gn:admin1_code":"82.0",
    "gn:admin2_code":"2215.0",
    "gn:admin3_code":"221507.0",
    "gn:asciiname":"Tepcz",
    "gn:country_code":"PL",
    "gn:dem":176,
    "gn:feature_class":"P",
    "gn:feature_code":"PPL",
    "gn:name":"T\u0119pcz",
    "gn:population":0,
    "gn:timezone":"Europe/Warsaw",
    "iso:country":"PL",
    "name:azb_x_preferred":[
        "\u062a\u067e\u0686"
    ],
    "name:ceb_x_preferred":[
        "T\u0119pcz"
    ],
    "name:csb_x_preferred":[
        "T\u00e3pcz"
    ],
    "name:fas_x_preferred":[
        "\u062a\u067e\u0686"
    ],
    "name:pol_x_preferred":[
        "T\u0119pcz"
    ],
    "name:ukr_x_preferred":[
        "\u0422\u0435\u043c\u043f\u0447"
    ],
    "wof:name":"Tepcz",
    "wof:placetype":"locality"
},
  "geometry": {"coordinates":[18.03873,54.50637],"type":"Point"}
}