{
  "type": "Feature",
  "properties": {
    "gn:admin1_code":"77.0",
    "gn:admin2_code":"1217.0",
    "gn:admin3_code":"121701.0",
    "gn:asciiname":"Furmanowa",
    "gn:country_code":"PL",
    "gn:dem":1015,
    "gn:feature_class":"P",
    "gn:feature_code":"PPL",
    "gn:name":"Furmanowa",
    "gn:population":0,
    "gn:timezone":"Europe/Warsaw",
    "iso:country":"PL",
    "wof:name":"Furmanowa",
    "wof:placetype":"locality"
},
  "geometry": {"coordinates":[19.9485,49.32095],"type":"Point"}
}