{
  "type": "Feature",
  "properties": {
    "gn:admin1_code":"81.0",
    "gn:admin2_code":"2014.0",
    "gn:admin3_code":"201405.0",
    "gn:asciiname":"Osowiec",
    "gn:country_code":"PL",
    "gn:dem":130,
    "gn:feature_class":"P",
    "gn:feature_code":"PPL",
    "gn:name":"Osowiec",
    "gn:population":0,
    "gn:timezone":"Europe/Warsaw",
    "iso:country":"PL",
    "name:lit_x_preferred":[
        "Osoviecas"
    ],
    "name:pol_x_preferred":[
        "Osowiec"
    ],
    "name:ukr_x_preferred":[
        "\u041e\u0441\u043e\u0432\u0435\u0446\u044c"
    ],
    "wof:name":"Osowiec",
    "wof:placetype":"locality"
},
  "geometry": {"coordinates":[22.26036,52.92753],"type":"Point"}
}