{
  "type": "Feature",
  "properties": {
    "gn:admin1_code":"82.0",
    "gn:admin2_code":"2211.0",
    "gn:admin3_code":"221106.0",
    "gn:asciiname":"Lubocino",
    "gn:country_code":"PL",
    "gn:dem":91,
    "gn:feature_class":"P",
    "gn:feature_code":"PPL",
    "gn:name":"Lubocino",
    "gn:population":0,
    "gn:timezone":"Europe/Warsaw",
    "iso:country":"PL",
    "wof:name":"Lubocino",
    "wof:placetype":"locality"
},
  "geometry": {"coordinates":[18.14127,54.72655],"type":"Point"}
}