{
  "type": "Feature",
  "properties": {
    "gn:admin1_code":"82.0",
    "gn:admin2_code":"2211.0",
    "gn:admin3_code":"221106.0",
    "gn:asciiname":"Lubocino",
    "gn:country_code":"PL",
    "gn:dem":91,
    "gn:feature_class":"P",
    "gn:feature_code":"PPL",
    "gn:name":"Lubocino",
    "gn:population":0,
    "gn:timezone":"Europe/Warsaw",
    "iso:country":"PL",
    "name:azb_x_preferred":[
        "\u0644\u0648\u0628\u0648\u0686\u06cc\u0646\u0648"
    ],
    "name:ceb_x_preferred":[
        "Lubocino"
    ],
    "name:csb_x_preferred":[
        "L\u00ebb\u00f2c\u00ebno"
    ],
    "name:fas_x_preferred":[
        "\u0644\u0648\u0628\u0648\u0686\u06cc\u0646\u0648"
    ],
    "name:fra_x_preferred":[
        "Lubocino"
    ],
    "name:nld_x_preferred":[
        "Lubocino"
    ],
    "name:pol_x_preferred":[
        "Lubocino"
    ],
    "name:ukr_x_preferred":[
        "\u041b\u044e\u0431\u043e\u0446\u0438\u043d\u043e"
    ],
    "wof:name":"Lubocino",
    "wof:placetype":"locality"
},
  "geometry": {"coordinates":[18.14127,54.72655],"type":"Point"}
}