{
  "type": "Feature",
  "properties": {
    "gn:country":"PL",
    "gn:fcode":"PPL",
    "gn:population":0,
    "iso:country":"PL",
    "name:ast_x_preferred":[
        "Legb\u0105d"
    ],
    "name:ceb_x_preferred":[
        "Legb\u0105d"
    ],
    "name:eng_x_preferred":[
        "Legb\u0105d"
    ],
    "name:fra_x_preferred":[
        "Legb\u0105d"
    ],
    "name:nan_x_preferred":[
        "Legb\u0105d"
    ],
    "name:nld_x_preferred":[
        "Legb\u0105d"
    ],
    "name:pol_x_preferred":[
        "Legb\u0105d"
    ],
    "name:ukr_x_preferred":[
        "\u041b\u0435\u0491\u0431\u043e\u043d\u0434"
    ],
    "qs_pg:aaroncc":"PL",
    "qs_pg:gn_country":"PL",
    "qs_pg:gn_fcode":"PPL",
    "qs_pg:gn_pop":0,
    "qs_pg:name":"Legb\u0105d",
    "qs_pg:name_adm0":"Polska",
    "qs_pg:name_adm1":"Kujawsko-Pomorskie",
    "qs_pg:photos":39,
    "qs_pg:photos_1k":8,
    "qs_pg:photos_9k":1,
    "qs_pg:photos_9r":2,
    "qs_pg:photos_all":39,
    "qs_pg:photos_sr":2,
    "qs_pg:pop_sr":0,
    "qs_pg:qs_pg_placetype":"locality",
    "qs_pg:qs_pg_placetype_gp":"Town",
    "qs_pg:woe_adm0":23424923,
    "woe:adm0_id":23424923,
    "woe:name_adm0":"Polska",
    "woe:name_adm1":"Kujawsko-Pomorskie",
    "woe:placetype":"Town",
    "wof:name":"Legb\u0105d",
    "wof:placetype":"locality"
},
  "geometry": {"coordinates":[17.94085,53.71083],"type":"Point"}
}