{
  "type": "Feature",
  "properties": {
    "gn:admin1_code":"75.0",
    "gn:admin2_code":"618.0",
    "gn:admin3_code":"61807.0",
    "gn:asciiname":"Sielec",
    "gn:country_code":"PL",
    "gn:dem":257,
    "gn:feature_class":"P",
    "gn:feature_code":"PPL",
    "gn:name":"Sielec",
    "gn:population":0,
    "gn:timezone":"Europe/Warsaw",
    "iso:country":"PL",
    "name:bel_x_preferred":[
        "\u0421\u044f\u043b\u0435\u0446"
    ],
    "name:ceb_x_preferred":[
        "Sielec"
    ],
    "name:deu_x_preferred":[
        "Sielec"
    ],
    "name:fra_x_preferred":[
        "Sielec"
    ],
    "name:pol_x_preferred":[
        "Sielec"
    ],
    "name:rus_x_preferred":[
        "\u0421\u0435\u043b\u0435\u0446"
    ],
    "name:ukr_x_preferred":[
        "\u0421\u0435\u043b\u0435\u0446\u044c"
    ],
    "wof:name":"Sielec",
    "wof:placetype":"locality"
},
  "geometry": {"coordinates":[23.48333,50.58333],"type":"Point"}
}