{
  "type": "Feature",
  "properties": {
    "gn:admin1_code":"74.0",
    "gn:admin2_code":"1018.0",
    "gn:admin3_code":"101801.0",
    "gn:asciiname":"Kamionka",
    "gn:country_code":"PL",
    "gn:dem":181,
    "gn:feature_class":"P",
    "gn:feature_code":"PPL",
    "gn:name":"Kamionka",
    "gn:population":0,
    "gn:timezone":"Europe/Warsaw",
    "iso:country":"PL",
    "name:pol_x_preferred":[
        "Kamionka"
    ],
    "name:ukr_x_preferred":[
        "\u041a\u0430\u043c\u0439\u043e\u043d\u043a\u0430"
    ],
    "wof:name":"Kamionka",
    "wof:placetype":"locality"
},
  "geometry": {"coordinates":[18.21001,51.22506],"type":"Point"}
}