{
  "type": "Feature",
  "properties": {
    "gn:admin1_code":"80.0",
    "gn:admin2_code":"1813.0",
    "gn:admin3_code":"181310.0",
    "gn:asciiname":"Kosienice",
    "gn:country_code":"PL",
    "gn:dem":238,
    "gn:feature_class":"P",
    "gn:feature_code":"PPL",
    "gn:name":"Kosienice",
    "gn:population":0,
    "gn:timezone":"Europe/Warsaw",
    "iso:country":"PL",
    "name:pol_x_preferred":[
        "Kosienice"
    ],
    "name:ukr_x_preferred":[
        "\u041a\u043e\u0441\u0435\u043d\u0456\u0446\u0435"
    ],
    "wof:name":"Kosienice",
    "wof:placetype":"locality"
},
  "geometry": {"coordinates":[22.7005,49.88158],"type":"Point"}
}