{
  "type": "Feature",
  "properties": {
    "gn:admin1_code":"78.0",
    "gn:admin2_code":"1419.0",
    "gn:admin3_code":"141901.0",
    "gn:asciiname":"Machcino",
    "gn:country_code":"PL",
    "gn:dem":117,
    "gn:feature_class":"P",
    "gn:feature_code":"PPL",
    "gn:name":"Machcino",
    "gn:population":0,
    "gn:timezone":"Europe/Warsaw",
    "iso:country":"PL",
    "name:fra_x_preferred":[
        "Machcino"
    ],
    "name:pol_x_preferred":[
        "Machcino"
    ],
    "name:ukr_x_preferred":[
        "\u041c\u0430\u0445\u0446\u0438\u043d\u043e"
    ],
    "wof:name":"Machcino",
    "wof:placetype":"locality"
},
  "geometry": {"coordinates":[19.74348,52.62436999999999],"type":"Point"}
}