{
  "type": "Feature",
  "properties": {
    "gn:admin1_code":"79.0",
    "gn:admin2_code":"1601.0",
    "gn:admin3_code":"160106.0",
    "gn:asciiname":"Jankowice Wielkie",
    "gn:country_code":"PL",
    "gn:dem":163,
    "gn:feature_class":"P",
    "gn:feature_code":"PPL",
    "gn:name":"Jankowice Wielkie",
    "gn:population":0,
    "gn:timezone":"Europe/Warsaw",
    "iso:country":"PL",
    "name:und_x_variant":[
        "Gross Jenkwitz",
        "Jankowice Wielkie"
    ],
    "wof:name":"Jankowice Wielkie",
    "wof:placetype":"locality"
},
  "geometry": {"coordinates":[17.44047,50.76702],"type":"Point"}
}