{
  "type": "Feature",
  "properties": {
    "gn:admin1_code":"79.0",
    "gn:admin2_code":"1601.0",
    "gn:admin3_code":"160106.0",
    "gn:asciiname":"Jankowice Wielkie",
    "gn:country_code":"PL",
    "gn:dem":163,
    "gn:feature_class":"P",
    "gn:feature_code":"PPL",
    "gn:name":"Jankowice Wielkie",
    "gn:population":0,
    "gn:timezone":"Europe/Warsaw",
    "iso:country":"PL",
    "name:ceb_x_preferred":[
        "Jankowice Wielkie"
    ],
    "name:deu_x_preferred":[
        "Jankowice Wielkie"
    ],
    "name:pol_x_preferred":[
        "Jankowice Wielkie"
    ],
    "name:ukr_x_preferred":[
        "\u042f\u043d\u043a\u043e\u0432\u0456\u0446\u0435-\u0412\u0435\u043b\u0438\u043a\u0456"
    ],
    "name:und_x_variant":[
        "Gross Jenkwitz",
        "Jankowice Wielkie"
    ],
    "name:urd_x_preferred":[
        "\u062c\u0646\u06a9\u0648\u0648\u06a9\u06d2 \u0648\u06cc\u0644\u06a9\u0626\u06cc"
    ],
    "wof:name":"Jankowice Wielkie",
    "wof:placetype":"locality"
},
  "geometry": {"coordinates":[17.44047,50.76702],"type":"Point"}
}