{
  "type": "Feature",
  "properties": {
    "gn:admin1_code":"72.0",
    "gn:admin2_code":"202.0",
    "gn:admin3_code":"20205.0",
    "gn:asciiname":"Kolaczow",
    "gn:country_code":"PL",
    "gn:dem":288,
    "gn:feature_class":"P",
    "gn:feature_code":"PPL",
    "gn:name":"Ko\u0142aczow",
    "gn:population":0,
    "gn:timezone":"Europe/Warsaw",
    "iso:country":"PL",
    "name:pol_x_preferred":[
        "Ko\u0142acz\u00f3w"
    ],
    "name:und_x_variant":[
        "Ko\u0142aczow"
    ],
    "wof:name":"Kolaczow",
    "wof:placetype":"locality"
},
  "geometry": {"coordinates":[16.72331,50.76469],"type":"Point"}
}