{
  "type": "Feature",
  "properties": {
    "gn:admin1_code":"75.0",
    "gn:admin2_code":"609.0",
    "gn:admin3_code":"60911.0",
    "gn:asciiname":"Wola Krasieninska",
    "gn:country_code":"PL",
    "gn:dem":190,
    "gn:feature_class":"P",
    "gn:feature_code":"PPL",
    "gn:name":"Wola Krasieni\u0144ska",
    "gn:population":0,
    "gn:timezone":"Europe/Warsaw",
    "iso:country":"PL",
    "wof:name":"Wola Krasieninska",
    "wof:placetype":"locality"
},
  "geometry": {"coordinates":[22.48163,51.36471],"type":"Point"}
}