{
  "type": "Feature",
  "properties": {
    "gn:admin1_code":"79.0",
    "gn:admin2_code":"1607.0",
    "gn:admin3_code":"160705.0",
    "gn:asciiname":"Podkamien",
    "gn:country_code":"PL",
    "gn:dem":206,
    "gn:feature_class":"P",
    "gn:feature_code":"PPL",
    "gn:name":"Podkamie\u0144",
    "gn:population":0,
    "gn:timezone":"Europe/Warsaw",
    "iso:country":"PL",
    "name:pol_x_preferred":[
        "Podkamie\u0144"
    ],
    "name:ukr_x_preferred":[
        "\u041f\u043e\u0434\u043a\u0430\u043c\u0435\u043d\u044c"
    ],
    "wof:name":"Podkamien",
    "wof:placetype":"locality"
},
  "geometry": {"coordinates":[17.34089,50.43531],"type":"Point"}
}