{
  "type": "Feature",
  "properties": {
    "gn:admin1_code":"82.0",
    "gn:admin2_code":"2201.0",
    "gn:admin3_code":"220107.0",
    "gn:asciiname":"Sylczno",
    "gn:country_code":"PL",
    "gn:dem":198,
    "gn:feature_class":"P",
    "gn:feature_code":"PPL",
    "gn:name":"Sylczno",
    "gn:population":0,
    "gn:timezone":"Europe/Warsaw",
    "iso:country":"PL",
    "name:ceb_x_preferred":[
        "Sylczno"
    ],
    "name:csb_x_preferred":[
        "S\u00e9lczno"
    ],
    "name:pol_x_preferred":[
        "Sylczno"
    ],
    "name:ukr_x_preferred":[
        "\u0421\u0438\u043b\u044c\u0447\u043d\u043e"
    ],
    "wof:name":"Sylczno",
    "wof:placetype":"locality"
},
  "geometry": {"coordinates":[17.73587999999999,54.16726],"type":"Point"}
}