{
  "type": "Feature",
  "properties": {
    "gn:admin1_code":"72.0",
    "gn:admin2_code":"221.0",
    "gn:admin3_code":"22105.0",
    "gn:asciiname":"Sierpnica",
    "gn:country_code":"PL",
    "gn:dem":595,
    "gn:feature_class":"P",
    "gn:feature_code":"PPL",
    "gn:name":"Sierpnica",
    "gn:population":0,
    "gn:timezone":"Europe/Warsaw",
    "iso:country":"PL",
    "name:ceb_x_preferred":[
        "Sierpnica"
    ],
    "name:pol_x_preferred":[
        "Sierpnica"
    ],
    "name:ukr_x_preferred":[
        "\u0421\u0435\u0440\u043f\u043d\u0438\u0446\u044f"
    ],
    "wof:name":"Sierpnica",
    "wof:placetype":"locality"
},
  "geometry": {"coordinates":[16.43074,50.66154],"type":"Point"}
}