{
  "type": "Feature",
  "properties": {
    "iso:country":"PL",
    "name:azb_x_preferred":[
        "\u0642\u0645\u06cc\u0646\u0627 \u0633\u0627\u0646\u0648\u06a9"
    ],
    "name:bel_x_preferred":[
        "\u0421\u0430\u043d\u0430\u043a"
    ],
    "name:deu_x_preferred":[
        "Sanok"
    ],
    "name:eus_x_preferred":[
        "Sanok landa-udalerria"
    ],
    "name:fas_x_preferred":[
        "\u06af\u0645\u06cc\u0646\u0627 \u0633\u0627\u0646\u0648\u06a9"
    ],
    "name:fra_x_preferred":[
        "Sanok"
    ],
    "name:ita_x_preferred":[
        "Sanok"
    ],
    "name:nld_x_preferred":[
        "Sanok"
    ],
    "name:pol_x_preferred":[
        "Sanok"
    ],
    "name:rus_x_preferred":[
        "\u0421\u0430\u043d\u043e\u043a"
    ],
    "name:slk_x_preferred":[
        "Gmina Sanok"
    ],
    "name:ukr_x_preferred":[
        "\u0413\u043c\u0456\u043d\u0430 \u0421\u044f\u043d\u0456\u043a"
    ],
    "name:war_x_preferred":[
        "Gmina Sanok"
    ],
    "qs_pg:aaroncc":"PL",
    "qs_pg:name":"Gmina Sanok",
    "qs_pg:name_adm0":"Polska",
    "qs_pg:name_adm1":"Podkarpackie",
    "qs_pg:photos":1,
    "qs_pg:photos_1k":1,
    "qs_pg:photos_9k":1,
    "qs_pg:photos_9r":1,
    "qs_pg:photos_all":1,
    "qs_pg:photos_sr":1,
    "qs_pg:pop_sr":0,
    "qs_pg:qs_pg_placetype":"localadmin",
    "qs_pg:qs_pg_placetype_gp":"LocalAdmin",
    "qs_pg:woe_adm0":23424923,
    "woe:adm0_id":23424923,
    "woe:name_adm0":"Polska",
    "woe:name_adm1":"Podkarpackie",
    "woe:placetype":"LocalAdmin",
    "wof:name":"Gmina Sanok",
    "wof:placetype":"localadmin"
},
  "geometry": {"coordinates":[22.120971,49.468124],"type":"Point"}
}