{
  "type": "Feature",
  "properties": {
    "gn:admin1_code":"74.0",
    "gn:admin2_code":"1021.0",
    "gn:admin3_code":"102103.0",
    "gn:asciiname":"Gozd",
    "gn:country_code":"PL",
    "gn:dem":151,
    "gn:feature_class":"P",
    "gn:feature_code":"PPL",
    "gn:name":"Gozd",
    "gn:population":0,
    "gn:timezone":"Europe/Warsaw",
    "iso:country":"PL",
    "name:bos_x_preferred":[
        "Gozd"
    ],
    "name:ceb_x_preferred":[
        "Gozd"
    ],
    "name:nld_x_preferred":[
        "Gozd"
    ],
    "name:pol_x_preferred":[
        "Gozd"
    ],
    "name:slv_x_preferred":[
        "Gozd"
    ],
    "name:srp_x_preferred":[
        "\u0413\u043e\u0437\u0434"
    ],
    "name:swe_x_preferred":[
        "Gozd"
    ],
    "wof:name":"Gozd",
    "wof:placetype":"locality"
},
  "geometry": {"coordinates":[19.77884,51.94111],"type":"Point"}
}