{
  "type": "Feature",
  "properties": {
    "gn:admin1_code":"74.0",
    "gn:admin2_code":"1005.0",
    "gn:admin3_code":"100502.0",
    "gn:asciiname":"Zakrzew",
    "gn:country_code":"PL",
    "gn:dem":104,
    "gn:feature_class":"P",
    "gn:feature_code":"PPL",
    "gn:name":"Zakrzew",
    "gn:population":0,
    "gn:timezone":"Europe/Warsaw",
    "iso:country":"PL",
    "wof:name":"Zakrzew",
    "wof:placetype":"locality"
},
  "geometry": {"coordinates":[19.67734,52.13739],"type":"Point"}
}