{
  "type": "Feature",
  "properties": {
    "gn:admin1_code":"86.0",
    "gn:admin2_code":"3026.0",
    "gn:admin3_code":"302603.0",
    "gn:asciiname":"Wlosciejewice",
    "gn:country_code":"PL",
    "gn:dem":97,
    "gn:feature_class":"P",
    "gn:feature_code":"PPL",
    "gn:name":"W\u0142o\u015bciejewice",
    "gn:population":0,
    "gn:timezone":"Europe/Warsaw",
    "iso:country":"PL",
    "name:ceb_x_preferred":[
        "W\u0142o\u015bciejewice"
    ],
    "name:fra_x_preferred":[
        "W\u0142o\u015bciejewice"
    ],
    "name:pol_x_preferred":[
        "W\u0142o\u015bciejewice"
    ],
    "name:ukr_x_preferred":[
        "\u0412\u043b\u043e\u0441\u0446\u0454\u0454\u0432\u0456\u0446\u0435"
    ],
    "wof:name":"Wlosciejewice",
    "wof:placetype":"locality"
},
  "geometry": {"coordinates":[17.17705,52.00553],"type":"Point"}
}