{
  "type": "Feature",
  "properties": {
    "iso:country":"PL",
    "name:fra_x_preferred":[
        "Batowice"
    ],
    "name:pol_x_preferred":[
        "Batowice"
    ],
    "name:rus_x_preferred":[
        "\u0411\u0430\u0442\u043e\u0432\u0438\u0446\u0435"
    ],
    "name:ukr_x_preferred":[
        "\u0411\u0430\u0442\u043e\u0432\u0456\u0446\u0435"
    ],
    "wof:name":"Batowice",
    "wof:placetype":"neighbourhood"
},
  "geometry": {"coordinates":[19.99497674297053,50.10505339874403],"type":"Point"}
}