{
  "type": "Feature",
  "properties": {
    "iso:country":"PL",
    "wof:name":"Batowice",
    "wof:placetype":"neighbourhood"
},
  "geometry": {"coordinates":[19.99497674297053,50.10505339874403],"type":"Point"}
}