{
  "type": "Feature",
  "properties": {
    "gn:admin1_code":"81.0",
    "gn:admin2_code":"2008.0",
    "gn:admin3_code":"200805.0",
    "gn:asciiname":"Zygmunty",
    "gn:country_code":"PL",
    "gn:dem":111,
    "gn:feature_class":"P",
    "gn:feature_code":"PPL",
    "gn:name":"Zygmunty",
    "gn:population":0,
    "gn:timezone":"Europe/Warsaw",
    "iso:country":"PL",
    "wof:name":"Zygmunty",
    "wof:placetype":"locality"
},
  "geometry": {"coordinates":[22.82906,53.24697],"type":"Point"}
}