{
  "type": "Feature",
  "properties": {
    "gn:admin1_code":"75.0",
    "gn:admin2_code":"604.0",
    "gn:admin3_code":"60407.0",
    "gn:asciiname":"Wladzin",
    "gn:cc2":"PL",
    "gn:country_code":"PL",
    "gn:dem":214,
    "gn:feature_class":"P",
    "gn:feature_code":"PPL",
    "gn:name":"W\u0142adzin",
    "gn:population":0,
    "gn:timezone":"Europe/Warsaw",
    "iso:country":"PL",
    "name:und_x_variant":[
        "Kolonia W\u0142adzin",
        "W\u0142adzin"
    ],
    "wof:name":"Wladzin",
    "wof:placetype":"locality"
},
  "geometry": {"coordinates":[23.66667,50.91667],"type":"Point"}
}