{
  "type": "Feature",
  "properties": {
    "gn:admin1_code":"78.0",
    "gn:admin2_code":"1413.0",
    "gn:admin3_code":"141307.0",
    "gn:asciiname":"Mostowo",
    "gn:country_code":"PL",
    "gn:dem":122,
    "gn:feature_class":"P",
    "gn:feature_code":"PPL",
    "gn:name":"Mostowo",
    "gn:population":0,
    "gn:timezone":"Europe/Warsaw",
    "iso:country":"PL",
    "name:ceb_x_preferred":[
        "Mostowo"
    ],
    "name:fra_x_preferred":[
        "Mostowo"
    ],
    "name:pol_x_preferred":[
        "Mostowo"
    ],
    "name:ukr_x_preferred":[
        "\u041c\u043e\u0441\u0442\u043e\u0432\u043e"
    ],
    "wof:name":"Mostowo",
    "wof:placetype":"locality"
},
  "geometry": {"coordinates":[20.1211,53.05826999999999],"type":"Point"}
}