{
  "type": "Feature",
  "properties": {
    "gn:admin1_code":"82.0",
    "gn:admin2_code":"2207.0",
    "gn:admin3_code":"220705.0",
    "gn:asciiname":"Szadowko",
    "gn:country_code":"PL",
    "gn:dem":9,
    "gn:feature_class":"P",
    "gn:feature_code":"PPL",
    "gn:name":"Szad\u00f3wko",
    "gn:population":0,
    "gn:timezone":"Europe/Warsaw",
    "iso:country":"PL",
    "name:und_x_variant":[
        "Schadewinkel",
        "Sza\u0142winek",
        "Szad\u00f3wko"
    ],
    "wof:name":"Szadowko",
    "wof:placetype":"locality"
},
  "geometry": {"coordinates":[18.87788,53.84921],"type":"Point"}
}