{
  "type": "Feature",
  "properties": {
    "gn:admin1_code":"85.0",
    "gn:admin2_code":"2817.0",
    "gn:admin3_code":"281702.0",
    "gn:asciiname":"Linowo",
    "gn:country_code":"PL",
    "gn:dem":149,
    "gn:feature_class":"P",
    "gn:feature_code":"PPL",
    "gn:name":"Linowo",
    "gn:population":0,
    "gn:timezone":"Europe/Warsaw",
    "iso:country":"PL",
    "name:eng_x_preferred":[
        "Linowo"
    ],
    "name:rus_x_preferred":[
        "\u041b\u0438\u043d\u043e\u0432\u043e"
    ],
    "name:und_x_variant":[
        "Leynau Kreis Ortelsburg",
        "Leinau",
        "Leynau",
        "Linowo"
    ],
    "wof:name":"Linowo",
    "wof:placetype":"locality"
},
  "geometry": {"coordinates":[20.96202000000001,53.64729000000001],"type":"Point"}
}