{
  "type": "Feature",
  "properties": {
    "gn:admin1_code":"78.0",
    "gn:admin2_code":"1412.0",
    "gn:admin3_code":"141206.0",
    "gn:asciiname":"Modecin",
    "gn:country_code":"PL",
    "gn:dem":146,
    "gn:feature_class":"P",
    "gn:feature_code":"PPL",
    "gn:name":"Modecin",
    "gn:population":0,
    "gn:timezone":"Europe/Warsaw",
    "iso:country":"PL",
    "name:fra_x_preferred":[
        "Modecin"
    ],
    "name:pol_x_preferred":[
        "Modecin"
    ],
    "name:spa_x_preferred":[
        "Modecin"
    ],
    "name:ukr_x_preferred":[
        "\u041c\u043e\u0434\u0435\u0446\u0438\u043d"
    ],
    "name:und_x_variant":[
        "Modesin"
    ],
    "wof:name":"Modecin",
    "wof:placetype":"locality"
},
  "geometry": {"coordinates":[21.73007,52.36478],"type":"Point"}
}