{
  "type": "Feature",
  "properties": {
    "gn:admin1_code":"85.0",
    "gn:admin2_code":"2816.0",
    "gn:admin3_code":"281603.0",
    "gn:asciiname":"Lipa Przednia",
    "gn:country_code":"PL",
    "gn:dem":134,
    "gn:feature_class":"P",
    "gn:feature_code":"PPL",
    "gn:name":"Lipa Przednia",
    "gn:population":0,
    "gn:timezone":"Europe/Warsaw",
    "iso:country":"PL",
    "name:und_x_variant":[
        "Vorder Oppendorf",
        "Vorder Lippa",
        "Lipa Przednia"
    ],
    "wof:name":"Lipa Przednia",
    "wof:placetype":"locality"
},
  "geometry": {"coordinates":[21.68333,53.56667],"type":"Point"}
}