{
  "type": "Feature",
  "properties": {
    "gn:country":"PL",
    "gn:fcode":"PPL",
    "gn:population":166,
    "iso:country":"PL",
    "name:fra_x_preferred":[
        "Przybys\u0142awice"
    ],
    "name:pol_x_preferred":[
        "Przybys\u0142awice"
    ],
    "name:rus_x_preferred":[
        "\u041f\u0448\u0438\u0431\u044b\u0441\u043b\u0430\u0432\u0438\u0446\u0435"
    ],
    "name:ukr_x_preferred":[
        "\u041f\u0448\u0438\u0431\u0438\u0441\u043b\u0430\u0432\u0456\u0446\u0435"
    ],
    "qs_pg:aaroncc":"PL",
    "qs_pg:gn_country":"PL",
    "qs_pg:gn_fcode":"PPL",
    "qs_pg:gn_pop":166,
    "qs_pg:name":"Przybys\u0142awice",
    "qs_pg:name_adm0":"Polska",
    "qs_pg:name_adm1":"Ma\u0142opolskie",
    "qs_pg:photos_9k":1,
    "qs_pg:photos_9r":1,
    "qs_pg:photos_all":1,
    "qs_pg:photos_sr":0,
    "qs_pg:pop_sr":1,
    "qs_pg:qs_pg_placetype":"locality",
    "qs_pg:qs_pg_placetype_gp":"Town",
    "qs_pg:woe_adm0":23424923,
    "woe:adm0_id":23424923,
    "woe:name_adm0":"Polska",
    "woe:name_adm1":"Ma\u0142opolskie",
    "woe:placetype":"Town",
    "wof:name":"Przybys\u0142awice",
    "wof:placetype":"locality",
    "wof:population":166
},
  "geometry": {"coordinates":[20.34084,50.15166],"type":"Point"}
}