{
  "type": "Feature",
  "properties": {
    "gn:admin1_code":"72.0",
    "gn:admin2_code":"223.0",
    "gn:admin3_code":"22307.0",
    "gn:asciiname":"Tworzyjanow",
    "gn:cc2":"PL",
    "gn:country_code":"PL",
    "gn:dem":297,
    "gn:feature_class":"P",
    "gn:feature_code":"PPL",
    "gn:name":"Tworzyjan\u00f3w",
    "gn:population":0,
    "gn:timezone":"Europe/Warsaw",
    "iso:country":"PL",
    "name:deu_x_preferred":[
        "Floriansdorf"
    ],
    "name:pol_x_preferred":[
        "Tworzyjan\u00f3w"
    ],
    "name:ukr_x_preferred":[
        "\u0422\u0432\u043e\u0436\u0438\u044f\u043d\u0443\u0432"
    ],
    "wof:name":"Tworzyjanow",
    "wof:placetype":"locality"
},
  "geometry": {"coordinates":[16.71667,50.88333],"type":"Point"}
}