{
  "type": "Feature",
  "properties": {
    "gn:admin1_code":"78.0",
    "gn:admin2_code":"1415.0",
    "gn:admin3_code":"141511.0",
    "gn:asciiname":"Latczyn",
    "gn:cc2":"PL",
    "gn:country_code":"PL",
    "gn:dem":109,
    "gn:feature_class":"P",
    "gn:feature_code":"PPL",
    "gn:name":"\u0141\u0105tczyn",
    "gn:population":0,
    "gn:timezone":"Europe/Warsaw",
    "iso:country":"PL",
    "name:und_x_variant":[
        "L\u0105czyn",
        "\u0141\u0105tczyn Szlachecki",
        "\u0141\u0105tczyn W\u0142o\u015bcia\u0144ski",
        "\u0141\u0105tczyn"
    ],
    "wof:name":"Latczyn",
    "wof:placetype":"locality"
},
  "geometry": {"coordinates":[21.79619,53.0981],"type":"Point"}
}