{
  "type": "Feature",
  "properties": {
    "gn:admin1_code":"75.0",
    "gn:admin2_code":"611.0",
    "gn:admin3_code":"61110.0",
    "gn:asciiname":"Ciezkie",
    "gn:country_code":"PL",
    "gn:dem":164,
    "gn:feature_class":"P",
    "gn:feature_code":"PPL",
    "gn:name":"Ci\u0119\u017ckie",
    "gn:population":0,
    "gn:timezone":"Europe/Warsaw",
    "iso:country":"PL",
    "name:fra_x_preferred":[
        "Ci\u0119\u017ckie"
    ],
    "name:pol_x_preferred":[
        "Ci\u0119\u017ckie"
    ],
    "name:ukr_x_preferred":[
        "\u0426\u0435\u043d\u0436\u043a\u0435"
    ],
    "wof:name":"Ciezkie",
    "wof:placetype":"locality"
},
  "geometry": {"coordinates":[22.38531,51.79663],"type":"Point"}
}