{
  "type": "Feature",
  "properties": {
    "gn:admin1_code":"79.0",
    "gn:admin2_code":"1610.0",
    "gn:admin3_code":"161002.0",
    "gn:asciiname":"Golczowice",
    "gn:country_code":"PL",
    "gn:dem":191,
    "gn:feature_class":"P",
    "gn:feature_code":"PPL",
    "gn:name":"Golczowice",
    "gn:population":0,
    "gn:timezone":"Europe/Warsaw",
    "iso:country":"PL",
    "name:pol_x_preferred":[
        "Golczowice"
    ],
    "name:ukr_x_preferred":[
        "\u0490\u043e\u043b\u044c\u0447\u043e\u0432\u0456\u0446\u0435"
    ],
    "wof:name":"Golczowice",
    "wof:placetype":"locality"
},
  "geometry": {"coordinates":[17.79614,50.39603],"type":"Point"}
}