{
  "type": "Feature",
  "properties": {
    "gn:admin1_code":"82.0",
    "gn:admin2_code":"2261.0",
    "gn:admin3_code":"226101.0",
    "gn:asciiname":"Zaspa-Mlyniec",
    "gn:country_code":"PL",
    "gn:dem":14,
    "gn:feature_class":"P",
    "gn:feature_code":"PPL",
    "gn:name":"Zaspa-M\u0142yniec",
    "gn:population":0,
    "gn:timezone":"Europe/Warsaw",
    "iso:country":"PL",
    "name:csb_x_preferred":[
        "Zaspa-M\u0142i\u0144c"
    ],
    "name:ita_x_preferred":[
        "Zaspa-M\u0142yniec"
    ],
    "name:pol_x_preferred":[
        "Zaspa-M\u0142yniec"
    ],
    "wof:name":"Zaspa-Mlyniec",
    "wof:placetype":"locality"
},
  "geometry": {"coordinates":[18.59848,54.39127],"type":"Point"}
}