{
  "type": "Feature",
  "properties": {
    "gn:admin1_code":"72",
    "gn:admin2_code":"0204",
    "gn:admin3_code":"20401.0",
    "gn:asciiname":"Wierzowice Male",
    "gn:country_code":"PL",
    "gn:dem":85,
    "gn:feature_class":"P",
    "gn:feature_code":"PPL",
    "gn:name":"Wierzowice Ma\u0142e",
    "gn:population":0,
    "gn:timezone":"Europe/Warsaw",
    "iso:country":"PL",
    "name:deu_x_historical":[
        "Klein Wiersewitz"
    ],
    "name:deu_x_preferred":[
        "Klein Wiersewitz"
    ],
    "wof:name":"Wierzowice Male",
    "wof:placetype":"locality"
},
  "geometry": {"coordinates":[16.56957,51.59427],"type":"Point"}
}