{
  "type": "Feature",
  "properties": {
    "gn:admin1_code":"74.0",
    "gn:admin2_code":"1010.0",
    "gn:admin3_code":"101003.0",
    "gn:asciiname":"Goscinna",
    "gn:country_code":"PL",
    "gn:dem":203,
    "gn:feature_class":"P",
    "gn:feature_code":"PPL",
    "gn:name":"Go\u015bcinna",
    "gn:population":0,
    "gn:timezone":"Europe/Warsaw",
    "iso:country":"PL",
    "name:fra_x_preferred":[
        "Go\u015bcinna"
    ],
    "name:pol_x_preferred":[
        "Go\u015bcinna"
    ],
    "name:ukr_x_preferred":[
        "\u0490\u043e\u0441\u0446\u0438\u043d\u043d\u0430"
    ],
    "wof:name":"Goscinna",
    "wof:placetype":"locality"
},
  "geometry": {"coordinates":[19.61995,51.24665],"type":"Point"}
}