{
  "type": "Feature",
  "properties": {
    "gn:admin1_code":"75.0",
    "gn:admin2_code":"604.0",
    "gn:admin3_code":"60408.0",
    "gn:asciiname":"Hostynne",
    "gn:country_code":"PL",
    "gn:dem":199,
    "gn:feature_class":"P",
    "gn:feature_code":"PPL",
    "gn:name":"Hostynne",
    "gn:population":0,
    "gn:timezone":"Europe/Warsaw",
    "iso:country":"PL",
    "name:azb_x_preferred":[
        "\u062e\u0648\u0633\u062a\u0646\u0646\u0647"
    ],
    "name:fas_x_preferred":[
        "\u062e\u0648\u0633\u062a\u0646\u0646\u0647"
    ],
    "name:fra_x_preferred":[
        "Hostynne"
    ],
    "name:pol_x_preferred":[
        "Hostynne"
    ],
    "name:ukr_x_preferred":[
        "\u0413\u043e\u0441\u0442\u0438\u043d\u043d\u0435"
    ],
    "wof:name":"Hostynne",
    "wof:placetype":"locality"
},
  "geometry": {"coordinates":[23.70428,50.74692],"type":"Point"}
}