{
  "type": "Feature",
  "properties": {
    "gn:admin1_code":"85.0",
    "gn:admin2_code":"2812.0",
    "gn:admin3_code":"281204.0",
    "gn:asciiname":"Marzecice",
    "gn:country_code":"PL",
    "gn:dem":154,
    "gn:feature_class":"P",
    "gn:feature_code":"PPL",
    "gn:name":"Marz\u0119cice",
    "gn:population":0,
    "gn:timezone":"Europe/Warsaw",
    "iso:country":"PL",
    "name:pol_x_preferred":[
        "Marz\u0119cice"
    ],
    "name:ukr_x_preferred":[
        "\u041c\u0430\u0436\u0435\u043d\u0446\u0438\u0446\u0435"
    ],
    "wof:name":"Marzecice",
    "wof:placetype":"locality"
},
  "geometry": {"coordinates":[19.5413,53.42881],"type":"Point"}
}