{
  "type": "Feature",
  "properties": {
    "gn:admin1_code":"83.0",
    "gn:admin2_code":"2404.0",
    "gn:admin3_code":"240405.0",
    "gn:asciiname":"Chmielarze",
    "gn:country_code":"PL",
    "gn:dem":224,
    "gn:feature_class":"P",
    "gn:feature_code":"PPL",
    "gn:name":"Chmielarze",
    "gn:population":0,
    "gn:timezone":"Europe/Warsaw",
    "iso:country":"PL",
    "name:ceb_x_preferred":[
        "Chmielarze"
    ],
    "name:pol_x_preferred":[
        "Chmielarze"
    ],
    "name:ukr_x_preferred":[
        "\u0425\u043c\u0435\u043b\u044f\u0436\u0435"
    ],
    "name:und_x_variant":[
        "Chmielarze Rak\u00f3w",
        "Chmielarze"
    ],
    "wof:name":"Chmielarze",
    "wof:placetype":"locality"
},
  "geometry": {"coordinates":[19.4252,50.86883],"type":"Point"}
}