{
  "type": "Feature",
  "properties": {
    "gn:admin1_code":"83.0",
    "gn:admin2_code":"2404.0",
    "gn:admin3_code":"240403.0",
    "gn:asciiname":"Sokole Pole",
    "gn:country_code":"PL",
    "gn:dem":261,
    "gn:feature_class":"P",
    "gn:feature_code":"PPL",
    "gn:name":"Sokole Pole",
    "gn:population":0,
    "gn:timezone":"Europe/Warsaw",
    "iso:country":"PL",
    "name:ceb_x_preferred":[
        "Sokole Pole"
    ],
    "name:pol_x_preferred":[
        "Sokole Pole"
    ],
    "wof:name":"Sokole Pole",
    "wof:placetype":"locality"
},
  "geometry": {"coordinates":[19.54789,50.71024],"type":"Point"}
}