{
  "type": "Feature",
  "properties": {
    "gn:admin1_code":"85.0",
    "gn:admin2_code":"2814.0",
    "gn:admin3_code":"281412.0",
    "gn:asciiname":"Wlodowo",
    "gn:country_code":"PL",
    "gn:dem":128,
    "gn:feature_class":"P",
    "gn:feature_code":"PPL",
    "gn:name":"W\u0142odowo",
    "gn:population":0,
    "gn:timezone":"Europe/Warsaw",
    "iso:country":"PL",
    "name:ceb_x_preferred":[
        "W\u0142odowo"
    ],
    "name:pol_x_preferred":[
        "W\u0142odowo"
    ],
    "name:ukr_x_preferred":[
        "\u0412\u043b\u043e\u0434\u043e\u0432\u043e"
    ],
    "name:und_x_variant":[
        "Waltersdorf",
        "W\u0142adowo"
    ],
    "wof:name":"Wlodowo",
    "wof:placetype":"locality"
},
  "geometry": {"coordinates":[20.15458,53.94232],"type":"Point"}
}