{
  "type": "Feature",
  "properties": {
    "gn:gn_country":"PL",
    "gn:gn_fcode":"PPL",
    "gn:gn_pop":752,
    "gn:population":752,
    "iso:country":"PL",
    "name:ast_x_preferred":[
        "Wola Wi\u015bniowa"
    ],
    "name:ceb_x_preferred":[
        "Wola Wi\u015bniowa"
    ],
    "name:eng_x_preferred":[
        "Wola Wi\u015bniowa"
    ],
    "name:fra_x_preferred":[
        "Wola Wi\u015bniowa"
    ],
    "name:nld_x_preferred":[
        "Wola Wi\u015bniowa"
    ],
    "name:pol_x_preferred":[
        "Wola Wi\u015bniowa"
    ],
    "name:ukr_x_preferred":[
        "\u0412\u043e\u043b\u044f-\u0412\u0456\u0441\u043d\u044c\u043e\u0432\u0430"
    ],
    "qs_pg:aaroncc":"PL",
    "qs_pg:gn_country":"PL",
    "qs_pg:gn_fcode":"PPL",
    "qs_pg:gn_pop":752,
    "qs_pg:name":"Wola Wi\u015bniowa",
    "qs_pg:name_adm0":"Polska",
    "qs_pg:name_adm1":"Swi\u0119tokrzyskie",
    "qs_pg:photos_9k":1,
    "qs_pg:photos_9r":1,
    "qs_pg:photos_all":1,
    "qs_pg:photos_sr":0,
    "qs_pg:pop_sr":2,
    "qs_pg:qs_pg_placetype":"locality",
    "qs_pg:qs_pg_placetype_gp":"Town",
    "qs_pg:woe_adm0":23424923,
    "woe:adm0_id":23424923,
    "woe:name_adm0":"Polska",
    "woe:name_adm1":"Swi\u0119tokrzyskie",
    "woe:placetype":"Town",
    "wof:name":"Wola Wi\u015bniowa",
    "wof:placetype":"locality",
    "wof:population":752
},
  "geometry": {"coordinates":[19.99718,50.82464],"type":"Point"}
}