{
  "type": "Feature",
  "properties": {
    "gn:admin1_code":"75.0",
    "gn:admin2_code":"618.0",
    "gn:admin3_code":"61802.0",
    "gn:asciiname":"Chyze",
    "gn:country_code":"PL",
    "gn:dem":300,
    "gn:feature_class":"P",
    "gn:feature_code":"PPL",
    "gn:name":"Chy\u017ce",
    "gn:population":0,
    "gn:timezone":"Europe/Warsaw",
    "iso:country":"PL",
    "name:und_x_variant":[
        "Chy\u017ce"
    ],
    "wof:name":"Chyze",
    "wof:placetype":"locality"
},
  "geometry": {"coordinates":[23.3906,50.39678],"type":"Point"}
}