{
  "type": "Feature",
  "properties": {
    "gn:admin1_code":"80.0",
    "gn:admin2_code":"1812.0",
    "gn:admin3_code":"181207.0",
    "gn:asciiname":"Huta Deregowska",
    "gn:country_code":"PL",
    "gn:dem":187,
    "gn:feature_class":"P",
    "gn:feature_code":"PPL",
    "gn:name":"Huta Der\u0119gowska",
    "gn:population":0,
    "gn:timezone":"Europe/Warsaw",
    "iso:country":"PL",
    "name:pol_x_preferred":[
        "Huta Der\u0119gowska"
    ],
    "name:ukr_x_preferred":[
        "\u0413\u0443\u0442\u0430 \u0414\u0435\u0440\u0435\u043d\u0433\u0456\u0432\u0441\u044c\u043a\u0430"
    ],
    "wof:name":"Huta Deregowska",
    "wof:placetype":"locality"
},
  "geometry": {"coordinates":[22.25153,50.53856],"type":"Point"}
}