{
  "type": "Feature",
  "properties": {
    "gn:admin1_code":"75.0",
    "gn:admin2_code":"615.0",
    "gn:admin3_code":"61508.0",
    "gn:asciiname":"Lisia Wolka",
    "gn:country_code":"PL",
    "gn:dem":145,
    "gn:feature_class":"P",
    "gn:feature_code":"PPL",
    "gn:name":"Lisia W\u00f3lka",
    "gn:population":0,
    "gn:timezone":"Europe/Warsaw",
    "iso:country":"PL",
    "name:und_x_variant":[
        "Lisiow\u00f3lka",
        "Lisia W\u00f3lka"
    ],
    "wof:name":"Lisia Wolka",
    "wof:placetype":"locality"
},
  "geometry": {"coordinates":[22.75942,51.80298],"type":"Point"}
}