{
  "type": "Feature",
  "properties": {
    "gn:admin1_code":"75.0",
    "gn:admin2_code":"615.0",
    "gn:admin3_code":"61508.0",
    "gn:asciiname":"Lisia Wolka",
    "gn:country_code":"PL",
    "gn:dem":145,
    "gn:feature_class":"P",
    "gn:feature_code":"PPL",
    "gn:name":"Lisia W\u00f3lka",
    "gn:population":0,
    "gn:timezone":"Europe/Warsaw",
    "iso:country":"PL",
    "name:azb_x_preferred":[
        "\u0644\u06cc\u0634\u0648\u0648\u0648\u0644\u06a9\u0627"
    ],
    "name:fas_x_preferred":[
        "\u0644\u06cc\u0634\u0648\u0648\u0648\u0644\u06a9\u0627"
    ],
    "name:fra_x_preferred":[
        "Lisiow\u00f3lka"
    ],
    "name:lit_x_preferred":[
        "Lisiovulka"
    ],
    "name:pol_x_preferred":[
        "Lisiow\u00f3lka"
    ],
    "name:ukr_x_preferred":[
        "\u041b\u0456\u0441\u044c\u043e\u0432\u0443\u043b\u044c\u043a\u0430"
    ],
    "name:und_x_variant":[
        "Lisia W\u00f3lka"
    ],
    "wof:name":"Lisia Wolka",
    "wof:placetype":"locality"
},
  "geometry": {"coordinates":[22.75942,51.80298],"type":"Point"}
}