{
  "type": "Feature",
  "properties": {
    "gn:admin1_code":"74.0",
    "gn:admin2_code":"1017.0",
    "gn:admin3_code":"101705.0",
    "gn:asciiname":"Kuznica Strobinska",
    "gn:country_code":"PL",
    "gn:dem":164,
    "gn:feature_class":"P",
    "gn:feature_code":"PPL",
    "gn:name":"Ku\u017anica Strobi\u0144ska",
    "gn:population":0,
    "gn:timezone":"Europe/Warsaw",
    "iso:country":"PL",
    "name:ceb_x_preferred":[
        "Ku\u017anica Strobi\u0144ska"
    ],
    "name:pol_x_preferred":[
        "Ku\u017anica Strobi\u0144ska"
    ],
    "name:ukr_x_preferred":[
        "\u041a\u0443\u0437\u044c\u043d\u0438\u0446\u044f-\u0421\u0442\u0440\u043e\u0431\u0456\u043d\u0441\u044c\u043a\u0430"
    ],
    "wof:name":"Kuznica Strobinska",
    "wof:placetype":"locality"
},
  "geometry": {"coordinates":[18.83612,51.29312],"type":"Point"}
}