{
  "type": "Feature",
  "properties": {
    "gn:admin1_code":"74.0",
    "gn:admin2_code":"1017.0",
    "gn:admin3_code":"101705.0",
    "gn:asciiname":"Kuznica Strobinska",
    "gn:country_code":"PL",
    "gn:dem":164,
    "gn:feature_class":"P",
    "gn:feature_code":"PPL",
    "gn:name":"Ku\u017anica Strobi\u0144ska",
    "gn:population":0,
    "gn:timezone":"Europe/Warsaw",
    "iso:country":"PL",
    "name:und_x_variant":[
        "Ku\u017anica Strobi\u0144ska"
    ],
    "wof:name":"Kuznica Strobinska",
    "wof:placetype":"locality"
},
  "geometry": {"coordinates":[18.83612,51.29312],"type":"Point"}
}