{
  "type": "Feature",
  "properties": {
    "gn:admin1_code":"77.0",
    "gn:admin2_code":"1208.0",
    "gn:admin3_code":"120807.0",
    "gn:asciiname":"Sladow",
    "gn:country_code":"PL",
    "gn:dem":243,
    "gn:feature_class":"P",
    "gn:feature_code":"PPL",
    "gn:name":"\u015alad\u00f3w",
    "gn:population":0,
    "gn:timezone":"Europe/Warsaw",
    "iso:country":"PL",
    "name:ceb_x_preferred":[
        "\u015alad\u00f3w"
    ],
    "name:pol_x_preferred":[
        "\u015alad\u00f3w"
    ],
    "name:rus_x_preferred":[
        "\u0421\u043b\u044f\u0434\u0443\u0432"
    ],
    "name:ukr_x_preferred":[
        "\u0421\u043b\u044f\u0434\u0443\u0432"
    ],
    "name:und_x_variant":[
        "\u015alad\u00f3w"
    ],
    "wof:name":"Sladow",
    "wof:placetype":"locality"
},
  "geometry": {"coordinates":[20.18427,50.38431],"type":"Point"}
}