{
  "type": "Feature",
  "properties": {
    "gn:admin1_code":"82.0",
    "gn:admin2_code":"2216.0",
    "gn:admin3_code":"221601.0",
    "gn:asciiname":"Bruk",
    "gn:country_code":"PL",
    "gn:dem":48,
    "gn:feature_class":"P",
    "gn:feature_code":"PPL",
    "gn:name":"Bruk",
    "gn:population":0,
    "gn:timezone":"Europe/Warsaw",
    "iso:country":"PL",
    "wof:name":"Bruk",
    "wof:placetype":"locality"
},
  "geometry": {"coordinates":[19.29524,53.96541],"type":"Point"}
}