{
  "type": "Feature",
  "properties": {
    "gn:admin1_code":"82.0",
    "gn:admin2_code":"2216.0",
    "gn:admin3_code":"221601.0",
    "gn:asciiname":"Bruk",
    "gn:country_code":"PL",
    "gn:dem":48,
    "gn:feature_class":"P",
    "gn:feature_code":"PPL",
    "gn:name":"Bruk",
    "gn:population":0,
    "gn:timezone":"Europe/Warsaw",
    "iso:country":"PL",
    "name:azb_x_preferred":[
        "\u0628\u0631\u0648\u06a9"
    ],
    "name:ceb_x_preferred":[
        "Bruk"
    ],
    "name:deu_x_preferred":[
        "Bruk"
    ],
    "name:fas_x_preferred":[
        "\u0628\u0631\u0648\u06a9"
    ],
    "name:nld_x_preferred":[
        "Bruk"
    ],
    "name:pol_x_preferred":[
        "Bruk"
    ],
    "name:ukr_x_preferred":[
        "\u0411\u0440\u0443\u043a"
    ],
    "wof:name":"Bruk",
    "wof:placetype":"locality"
},
  "geometry": {"coordinates":[19.29524,53.96541],"type":"Point"}
}