{
  "type": "Feature",
  "properties": {
    "gn:admin1_code":"85.0",
    "gn:admin2_code":"2803.0",
    "gn:admin3_code":"280302.0",
    "gn:asciiname":"Ruszkowo",
    "gn:country_code":"PL",
    "gn:dem":175,
    "gn:feature_class":"P",
    "gn:feature_code":"PPL",
    "gn:name":"Ruszkowo",
    "gn:population":0,
    "gn:timezone":"Europe/Warsaw",
    "iso:country":"PL",
    "name:ceb_x_preferred":[
        "Ruszkowo"
    ],
    "name:pol_x_preferred":[
        "Ruszkowo"
    ],
    "name:ukr_x_preferred":[
        "\u0420\u0443\u0448\u043a\u043e\u0432\u043e"
    ],
    "name:und_x_variant":[
        "Rauschken"
    ],
    "wof:name":"Ruszkowo",
    "wof:placetype":"locality"
},
  "geometry": {"coordinates":[20.12451,53.38264],"type":"Point"}
}