{
  "type": "Feature",
  "properties": {
    "gn:admin1_code":"77.0",
    "gn:admin2_code":"1214.0",
    "gn:admin3_code":"121406.0",
    "gn:asciiname":"Wrocimowice",
    "gn:country_code":"PL",
    "gn:dem":255,
    "gn:feature_class":"P",
    "gn:feature_code":"PPL",
    "gn:name":"Wrocimowice",
    "gn:population":0,
    "gn:timezone":"Europe/Warsaw",
    "iso:country":"PL",
    "name:pol_x_preferred":[
        "Wrocimowice"
    ],
    "name:ukr_x_preferred":[
        "\u0412\u0440\u043e\u0446\u0438\u043c\u043e\u0432\u0456\u0446\u0435"
    ],
    "wof:name":"Wrocimowice",
    "wof:placetype":"locality"
},
  "geometry": {"coordinates":[20.24162,50.29421],"type":"Point"}
}