{
  "type": "Feature",
  "properties": {
    "gn:admin1_code":"78.0",
    "gn:admin2_code":"1402.0",
    "gn:admin3_code":"140208.0",
    "gn:asciiname":"Kozdroje",
    "gn:cc2":"PL",
    "gn:country_code":"PL",
    "gn:dem":132,
    "gn:feature_class":"P",
    "gn:feature_code":"PPL",
    "gn:name":"Kozdroje",
    "gn:population":0,
    "gn:timezone":"Europe/Warsaw",
    "iso:country":"PL",
    "name:azb_x_preferred":[
        "\u06a9\u0648\u0632\u062f\u0631\u0648\u06cc\u0647"
    ],
    "name:fas_x_preferred":[
        "\u06a9\u0648\u0632\u062f\u0631\u0648\u06cc\u0647"
    ],
    "name:fra_x_preferred":[
        "Kozdroje"
    ],
    "name:pol_x_preferred":[
        "Kozdroje"
    ],
    "name:spa_x_preferred":[
        "Kozdroje"
    ],
    "name:ukr_x_preferred":[
        "\u041a\u043e\u0437\u0434\u0440\u043e\u0454"
    ],
    "name:und_x_variant":[
        "Kosdroje"
    ],
    "wof:name":"Kozdroje",
    "wof:placetype":"locality"
},
  "geometry": {"coordinates":[20.61027,52.95464000000001],"type":"Point"}
}