{
  "type": "Feature",
  "properties": {
    "gn:admin1_code":"81.0",
    "gn:admin2_code":"2012.0",
    "gn:admin3_code":"201201.0",
    "gn:asciiname":"Zdreby",
    "gn:country_code":"PL",
    "gn:dem":194,
    "gn:feature_class":"P",
    "gn:feature_code":"PPL",
    "gn:name":"Zdr\u0119by",
    "gn:population":0,
    "gn:timezone":"Europe/Warsaw",
    "iso:country":"PL",
    "name:fra_x_preferred":[
        "Zdr\u0119by"
    ],
    "name:lit_x_preferred":[
        "Zdrembiai"
    ],
    "name:pol_x_preferred":[
        "Zdr\u0119by"
    ],
    "name:ukr_x_preferred":[
        "\u0417\u0434\u0440\u0435\u043c\u0431\u0438"
    ],
    "name:und_x_variant":[
        "Zdr\u0119by"
    ],
    "wof:name":"Zdreby",
    "wof:placetype":"locality"
},
  "geometry": {"coordinates":[22.71406,54.11463000000001],"type":"Point"}
}