{
  "type": "Feature",
  "properties": {
    "gn:admin1_code":"75.0",
    "gn:admin2_code":"618.0",
    "gn:admin3_code":"61811.0",
    "gn:asciiname":"Kolonia Podhorce",
    "gn:country_code":"PL",
    "gn:dem":234,
    "gn:feature_class":"P",
    "gn:feature_code":"PPL",
    "gn:name":"Kolonia Podhorce",
    "gn:population":0,
    "gn:timezone":"Europe/Warsaw",
    "iso:country":"PL",
    "wof:name":"Kolonia Podhorce",
    "wof:placetype":"locality"
},
  "geometry": {"coordinates":[23.51714,50.48327000000001],"type":"Point"}
}