{
  "type": "Feature",
  "properties": {
    "gn:admin1_code":"78.0",
    "gn:admin2_code":"1425.0",
    "gn:admin3_code":"142506.0",
    "gn:asciiname":"Slupica",
    "gn:country_code":"PL",
    "gn:dem":170,
    "gn:feature_class":"P",
    "gn:feature_code":"PPL",
    "gn:name":"S\u0142upica",
    "gn:population":0,
    "gn:timezone":"Europe/Warsaw",
    "iso:country":"PL",
    "name:ceb_x_preferred":[
        "S\u0142upica"
    ],
    "name:fra_x_preferred":[
        "S\u0142upica"
    ],
    "name:pol_x_preferred":[
        "S\u0142upica"
    ],
    "name:ukr_x_preferred":[
        "\u0421\u043b\u0443\u043f\u0438\u0446\u044f"
    ],
    "wof:name":"Slupica",
    "wof:placetype":"locality"
},
  "geometry": {"coordinates":[21.39029,51.41172],"type":"Point"}
}