{
  "type": "Feature",
  "properties": {
    "gn:admin1_code":"75.0",
    "gn:admin2_code":"616.0",
    "gn:admin3_code":"61603.0",
    "gn:asciiname":"Grabow Rycki",
    "gn:country_code":"PL",
    "gn:dem":161,
    "gn:feature_class":"P",
    "gn:feature_code":"PPL",
    "gn:name":"Grab\u00f3w Rycki",
    "gn:population":0,
    "gn:timezone":"Europe/Warsaw",
    "iso:country":"PL",
    "name:fra_x_preferred":[
        "Grab\u00f3w Rycki"
    ],
    "name:pol_x_preferred":[
        "Grab\u00f3w Rycki"
    ],
    "name:ukr_x_preferred":[
        "\u0490\u0440\u0430\u0431\u0443\u0432-\u0420\u0438\u0446\u044c\u043a\u0438\u0439"
    ],
    "name:und_x_variant":[
        "Grab\u00f3w Rycki"
    ],
    "wof:name":"Grabow Rycki",
    "wof:placetype":"locality"
},
  "geometry": {"coordinates":[22.08506,51.67476],"type":"Point"}
}