{
  "type": "Feature",
  "properties": {
    "gn:admin1_code":"86.0",
    "gn:admin2_code":"3010.0",
    "gn:admin3_code":"301013.0",
    "gn:asciiname":"Janowice",
    "gn:country_code":"PL",
    "gn:dem":96,
    "gn:feature_class":"P",
    "gn:feature_code":"PPL",
    "gn:name":"Janowice",
    "gn:population":0,
    "gn:timezone":"Europe/Warsaw",
    "iso:country":"PL",
    "name:ceb_x_preferred":[
        "Janowice"
    ],
    "name:deu_x_preferred":[
        "Janowice"
    ],
    "name:fra_x_preferred":[
        "Janowice"
    ],
    "name:pol_x_preferred":[
        "Janowice"
    ],
    "name:ukr_x_preferred":[
        "\u042f\u043d\u043e\u0432\u0456\u0446\u0435"
    ],
    "wof:name":"Janowice",
    "wof:placetype":"locality"
},
  "geometry": {"coordinates":[18.51573,52.47255],"type":"Point"}
}