{
  "type": "Feature",
  "properties": {
    "gn:admin1_code":"74.0",
    "gn:admin2_code":"1017.0",
    "gn:admin3_code":"101702.0",
    "gn:asciiname":"Gromadzice",
    "gn:country_code":"PL",
    "gn:dem":172,
    "gn:feature_class":"P",
    "gn:feature_code":"PPL",
    "gn:name":"Gromadzice",
    "gn:population":0,
    "gn:timezone":"Europe/Warsaw",
    "iso:country":"PL",
    "name:ceb_x_preferred":[
        "Gromadzice"
    ],
    "name:pol_x_preferred":[
        "Gromadzice"
    ],
    "name:ukr_x_preferred":[
        "\u0490\u0440\u043e\u043c\u0430\u0434\u0437\u0456\u0446\u0435"
    ],
    "wof:name":"Gromadzice",
    "wof:placetype":"locality"
},
  "geometry": {"coordinates":[18.61609,51.28726],"type":"Point"}
}