{
  "type": "Feature",
  "properties": {
    "gn:country":"PL",
    "gn:fcode":"PPL",
    "gn:population":554,
    "iso:country":"PL",
    "name:ast_x_preferred":[
        "Hucisko Nienadowskie"
    ],
    "name:ceb_x_preferred":[
        "Hucisko Nienadowskie"
    ],
    "name:eng_x_preferred":[
        "Hucisko Nienadowskie"
    ],
    "name:fra_x_preferred":[
        "Hucisko Nienadowskie"
    ],
    "name:nan_x_preferred":[
        "Hucisko Nienadowskie"
    ],
    "name:nld_x_preferred":[
        "Hucisko Nienadowskie"
    ],
    "name:pol_x_preferred":[
        "Hucisko Nienadowskie"
    ],
    "name:ukr_x_preferred":[
        "\u0413\u0443\u0442\u0438\u0441\u044c\u043a\u043e-\u041d\u0435\u043d\u0430\u0434\u043e\u0432\u0441\u043a\u0435"
    ],
    "name:und_x_variant":[
        "Hucisko Nienarowskie"
    ],
    "qs_pg:aaroncc":"PL",
    "qs_pg:gn_country":"PL",
    "qs_pg:gn_fcode":"PPL",
    "qs_pg:gn_pop":554,
    "qs_pg:name":"Hucisko Nienadowskie",
    "qs_pg:name_adm0":"Polska",
    "qs_pg:name_adm1":"Podkarpackie",
    "qs_pg:photos_9r":0,
    "qs_pg:photos_sr":0,
    "qs_pg:pop_sr":2,
    "qs_pg:qs_pg_placetype":"locality",
    "qs_pg:qs_pg_placetype_gp":"Town",
    "qs_pg:woe_adm0":23424923,
    "woe:adm0_id":23424923,
    "woe:name_adm0":"Polska",
    "woe:name_adm1":"Podkarpackie",
    "woe:placetype":"Town",
    "wof:name":"Hucisko Nienadowskie",
    "wof:placetype":"locality",
    "wof:population":554
},
  "geometry": {"coordinates":[22.41777,49.87716],"type":"Point"}
}