{
  "type": "Feature",
  "properties": {
    "gn:admin1_code":"85.0",
    "gn:admin2_code":"2807.0",
    "gn:admin3_code":"280707.0",
    "gn:asciiname":"Surbajny",
    "gn:country_code":"PL",
    "gn:dem":116,
    "gn:feature_class":"P",
    "gn:feature_code":"PPL",
    "gn:name":"Surbajny",
    "gn:population":0,
    "gn:timezone":"Europe/Warsaw",
    "iso:country":"PL",
    "name:deu_x_preferred":[
        "Surbajny"
    ],
    "name:pol_x_preferred":[
        "Surbajny"
    ],
    "name:ukr_x_preferred":[
        "\u0421\u0443\u0440\u0431\u0430\u0439\u043d\u0438"
    ],
    "name:und_x_variant":[
        "Sorbehnen",
        "Surbajny"
    ],
    "name:vie_x_preferred":[
        "Surbajny"
    ],
    "wof:name":"Surbajny",
    "wof:placetype":"locality"
},
  "geometry": {"coordinates":[19.66727,53.81723],"type":"Point"}
}