{
  "type": "Feature",
  "properties": {
    "gn:admin1_code":"72.0",
    "gn:admin2_code":"225.0",
    "gn:admin3_code":"22507.0",
    "gn:asciiname":"Kozlice",
    "gn:country_code":"PL",
    "gn:dem":199,
    "gn:feature_class":"P",
    "gn:feature_code":"PPL",
    "gn:name":"Ko\u017alice",
    "gn:population":0,
    "gn:timezone":"Europe/Warsaw",
    "iso:country":"PL",
    "name:azb_x_preferred":[
        "\u06a9\u0648\u0698\u0644\u06cc\u062a\u0633\u0647"
    ],
    "name:ceb_x_preferred":[
        "Ko\u017alice"
    ],
    "name:deu_x_historical":[
        "K\u00f6slitz"
    ],
    "name:deu_x_preferred":[
        "K\u00f6slitz"
    ],
    "name:deu_x_variant":[
        "Ko\u017alice"
    ],
    "name:fas_x_preferred":[
        "\u06a9\u0648\u0698\u0644\u06cc\u062a\u0633\u0647"
    ],
    "name:pol_x_preferred":[
        "Ko\u017alice"
    ],
    "name:ukr_x_preferred":[
        "\u041a\u043e\u0437\u043b\u0456\u0446\u0435"
    ],
    "wof:name":"Kozlice",
    "wof:placetype":"locality"
},
  "geometry": {"coordinates":[14.98672,51.10476],"type":"Point"}
}