{
  "type": "Feature",
  "properties": {
    "gn:admin1_code":"85.0",
    "gn:admin2_code":"2810.0",
    "gn:admin3_code":"281003.0",
    "gn:asciiname":"Wierzbowo",
    "gn:country_code":"PL",
    "gn:dem":133,
    "gn:feature_class":"P",
    "gn:feature_code":"PPL",
    "gn:name":"Wierzbowo",
    "gn:population":0,
    "gn:timezone":"Europe/Warsaw",
    "iso:country":"PL",
    "name:und_x_variant":[
        "Lockwinnen",
        "Wiersbau",
        "Wierzbowo"
    ],
    "wof:name":"Wierzbowo",
    "wof:placetype":"locality"
},
  "geometry": {"coordinates":[21.32829,53.81445],"type":"Point"}
}