{
  "type": "Feature",
  "properties": {
    "gn:population":3325,
    "iso:country":"PL",
    "name:ast_x_preferred":[
        "Gromnik"
    ],
    "name:azb_x_preferred":[
        "\u0642\u0631\u0648\u0645\u0646\u0642\u06a9"
    ],
    "name:bre_x_preferred":[
        "Gromnik"
    ],
    "name:deu_x_preferred":[
        "Gromnik"
    ],
    "name:eng_x_preferred":[
        "Gromnik"
    ],
    "name:fas_x_preferred":[
        "\u06af\u0631\u0648\u0645\u0646\u06af\u06a9"
    ],
    "name:fra_x_preferred":[
        "Gromnik"
    ],
    "name:nld_x_preferred":[
        "Gromnik"
    ],
    "name:pol_x_preferred":[
        "Gromnik"
    ],
    "name:rus_x_preferred":[
        "\u0413\u0440\u043e\u043c\u043d\u0438\u043a"
    ],
    "name:swe_x_preferred":[
        "Gromnik"
    ],
    "name:ukr_x_preferred":[
        "\u0490\u0440\u043e\u043c\u043d\u0438\u043a"
    ],
    "qs:a0":"Rzeczpospolita Polska",
    "qs:a1":"*Malopolskie",
    "qs:a1r":"0",
    "qs:a2":"Tarnowski",
    "qs:adm0":"Rzeczpospolita Polska",
    "qs:la":"Gromnik",
    "qs:la_lc":"*PL1216022",
    "qs:level":"locality",
    "qs:loc":"Gromnik",
    "qs:loc_alt":"Gromnik",
    "qs:pop":0,
    "qs:type":"rural point-in-poly",
    "wd:wordcount":96,
    "wof:name":"Gromnik",
    "wof:placetype":"locality",
    "wof:population":3325
},
  "geometry": {"coordinates":[20.9365581214174,49.8436860556458],"type":"Point"}
}