{
  "type": "Feature",
  "properties": {
    "gn:country":"PL",
    "gn:fcode":"PPL",
    "gn:population":0,
    "iso:country":"PL",
    "name:ast_x_preferred":[
        "Wola Maradzka"
    ],
    "name:ces_x_preferred":[
        "Wola Maradzka"
    ],
    "name:deu_x_preferred":[
        "Wola Maradzka"
    ],
    "name:eng_x_preferred":[
        "Wola Maradzka"
    ],
    "name:fra_x_preferred":[
        "Wola Maradzka"
    ],
    "name:nan_x_preferred":[
        "Wola Maradzka"
    ],
    "name:pol_x_preferred":[
        "Wola Maradzka"
    ],
    "name:und_x_variant":[
        "Maradtken Abbau"
    ],
    "qs_pg:aaroncc":"PL",
    "qs_pg:gn_country":"PL",
    "qs_pg:gn_fcode":"PPL",
    "qs_pg:gn_pop":0,
    "qs_pg:name":"Wola Maradzka",
    "qs_pg:name_adm0":"Polska",
    "qs_pg:name_adm1":"Warminsko-Mazurskie",
    "qs_pg:photos":63,
    "qs_pg:photos_1k":13,
    "qs_pg:photos_9k":1,
    "qs_pg:photos_9r":2,
    "qs_pg:photos_all":63,
    "qs_pg:photos_sr":2,
    "qs_pg:pop_sr":0,
    "qs_pg:qs_pg_placetype":"locality",
    "qs_pg:qs_pg_placetype_gp":"Town",
    "qs_pg:woe_adm0":23424923,
    "woe:adm0_id":23424923,
    "woe:name_adm0":"Polska",
    "woe:name_adm1":"Warminsko-Mazurskie",
    "woe:placetype":"Town",
    "wof:name":"Wola Maradzka",
    "wof:placetype":"locality"
},
  "geometry": {"coordinates":[21.17063,53.78901],"type":"Point"}
}