{
  "type": "Feature",
  "properties": {
    "gn:admin1_code":"85.0",
    "gn:admin2_code":"2814.0",
    "gn:admin3_code":"281410.0",
    "gn:asciiname":"Silice",
    "gn:country_code":"PL",
    "gn:dem":114,
    "gn:feature_class":"P",
    "gn:feature_code":"PPL",
    "gn:name":"Silice",
    "gn:population":0,
    "gn:timezone":"Europe/Warsaw",
    "iso:country":"PL",
    "name:pol_x_preferred":[
        "Silice"
    ],
    "name:ukr_x_preferred":[
        "\u0421\u0456\u043b\u0456\u0446\u0435"
    ],
    "name:und_x_variant":[
        "Quidlitz"
    ],
    "wof:name":"Silice",
    "wof:placetype":"locality"
},
  "geometry": {"coordinates":[20.63262000000001,53.75496],"type":"Point"}
}