{
  "type": "Feature",
  "properties": {
    "gn:admin1_code":"79.0",
    "gn:admin2_code":"1608.0",
    "gn:admin3_code":"160802.0",
    "gn:asciiname":"Pawlowice Gorzowskie",
    "gn:country_code":"PL",
    "gn:dem":198,
    "gn:feature_class":"P",
    "gn:feature_code":"PPL",
    "gn:name":"Paw\u0142owice Gorzowskie",
    "gn:population":0,
    "gn:timezone":"Europe/Warsaw",
    "iso:country":"PL",
    "name:ceb_x_preferred":[
        "Paw\u0142owice Gorzowskie"
    ],
    "name:deu_x_preferred":[
        "Paw\u0142owice"
    ],
    "name:pol_x_preferred":[
        "Paw\u0142owice"
    ],
    "name:rus_x_preferred":[
        "\u041f\u0430\u0432\u043b\u043e\u0432\u0438\u0446\u0435"
    ],
    "name:ukr_x_preferred":[
        "\u041f\u0430\u0432\u043b\u043e\u0432\u0456\u0446\u0435"
    ],
    "wof:name":"Pawlowice Gorzowskie",
    "wof:placetype":"locality"
},
  "geometry": {"coordinates":[18.39176,51.00356],"type":"Point"}
}