{
  "type": "Feature",
  "properties": {
    "gn:admin1_code":"78.0",
    "gn:admin2_code":"1436.0",
    "gn:admin3_code":"143602.0",
    "gn:asciiname":"Stary Grodek",
    "gn:country_code":"PL",
    "gn:dem":156,
    "gn:feature_class":"P",
    "gn:feature_code":"PPL",
    "gn:name":"Stary Gr\u00f3dek",
    "gn:population":0,
    "gn:timezone":"Europe/Warsaw",
    "iso:country":"PL",
    "wof:name":"Stary Grodek",
    "wof:placetype":"locality"
},
  "geometry": {"coordinates":[21.67464,51.46066],"type":"Point"}
}