{
  "type": "Feature",
  "properties": {
    "gn:admin1_code":"84.0",
    "gn:admin2_code":"2604.0",
    "gn:admin3_code":"260408.0",
    "gn:asciiname":"Czalczyn",
    "gn:country_code":"PL",
    "gn:dem":242,
    "gn:feature_class":"P",
    "gn:feature_code":"PPL",
    "gn:name":"Cza\u0142czyn",
    "gn:population":0,
    "gn:timezone":"Europe/Warsaw",
    "iso:country":"PL",
    "name:ceb_x_preferred":[
        "Cza\u0142czyn"
    ],
    "name:nld_x_preferred":[
        "Cza\u0142czyn"
    ],
    "name:pol_x_preferred":[
        "Cza\u0142czyn"
    ],
    "name:ukr_x_preferred":[
        "\u0427\u0430\u043b\u0447\u0438\u043d"
    ],
    "name:und_x_variant":[
        "Cza\u0142czyn"
    ],
    "wof:name":"Czalczyn",
    "wof:placetype":"locality"
},
  "geometry": {"coordinates":[20.24202,50.97265],"type":"Point"}
}