{
  "type": "Feature",
  "properties": {
    "gn:admin1_code":"80.0",
    "gn:admin2_code":"1806.0",
    "gn:admin3_code":"180601.0",
    "gn:asciiname":"Izdebnik",
    "gn:country_code":"PL",
    "gn:dem":209,
    "gn:feature_class":"P",
    "gn:feature_code":"PPL",
    "gn:name":"Izdebnik",
    "gn:population":0,
    "gn:timezone":"Europe/Warsaw",
    "iso:country":"PL",
    "wof:name":"Izdebnik",
    "wof:placetype":"locality"
},
  "geometry": {"coordinates":[21.68943,50.27361],"type":"Point"}
}