{
  "type": "Feature",
  "properties": {
    "gn:admin1_code":"74.0",
    "gn:admin2_code":"1001.0",
    "gn:admin3_code":"100105.0",
    "gn:asciiname":"Kolonia Strzyzewice",
    "gn:country_code":"PL",
    "gn:dem":181,
    "gn:feature_class":"P",
    "gn:feature_code":"PPL",
    "gn:name":"Kolonia Strzy\u017cewice",
    "gn:population":0,
    "gn:timezone":"Europe/Warsaw",
    "iso:country":"PL",
    "wof:name":"Kolonia Strzyzewice",
    "wof:placetype":"locality"
},
  "geometry": {"coordinates":[19.23333,51.41667],"type":"Point"}
}