{
  "type": "Feature",
  "properties": {
    "gn:admin1_code":"73.0",
    "gn:admin2_code":"409.0",
    "gn:admin3_code":"40904.0",
    "gn:asciiname":"Mlyny",
    "gn:country_code":"PL",
    "gn:dem":99,
    "gn:feature_class":"P",
    "gn:feature_code":"PPL",
    "gn:name":"M\u0142yny",
    "gn:population":0,
    "gn:timezone":"Europe/Warsaw",
    "iso:country":"PL",
    "name:pol_x_preferred":[
        "M\u0142yny"
    ],
    "name:ukr_x_preferred":[
        "\u041c\u043b\u0438\u043d\u0438"
    ],
    "name:und_x_variant":[
        "M\u0142yny"
    ],
    "wof:name":"Mlyny",
    "wof:placetype":"locality"
},
  "geometry": {"coordinates":[18.21718,52.60511999999999],"type":"Point"}
}