{
  "type": "Feature",
  "properties": {
    "iso:country":"PL",
    "name:ceb_x_preferred":[
        "Moszczenica"
    ],
    "name:deu_x_preferred":[
        "Moszczenica"
    ],
    "name:fra_x_preferred":[
        "Moszczenica"
    ],
    "name:ita_x_preferred":[
        "Moszczenica"
    ],
    "name:nld_x_preferred":[
        "Moszczenica"
    ],
    "name:pol_x_preferred":[
        "Moszczenica"
    ],
    "name:rus_x_preferred":[
        "\u041c\u043e\u0449\u0435\u043d\u0438\u0446\u0430"
    ],
    "name:ukr_x_preferred":[
        "\u041c\u043e\u0449\u0435\u043d\u0438\u0446\u044f"
    ],
    "wof:coterminous":[
        1125306255
    ],
    "wof:name":"Moszczenica",
    "wof:placetype":"locality"
},
  "geometry": {"coordinates":[19.6937498294715,51.496804431767],"type":"Point"}
}