{
  "type": "Feature",
  "properties": {
    "gn:admin1_code":"74.0",
    "gn:admin2_code":"1010.0",
    "gn:admin3_code":"101006.0",
    "gn:asciiname":"Pomykow",
    "gn:country_code":"PL",
    "gn:dem":199,
    "gn:feature_class":"P",
    "gn:feature_code":"PPL",
    "gn:name":"Pomyk\u00f3w",
    "gn:population":0,
    "gn:timezone":"Europe/Warsaw",
    "iso:country":"PL",
    "name:fra_x_preferred":[
        "Pomyk\u00f3w"
    ],
    "name:pol_x_preferred":[
        "Pomyk\u00f3w"
    ],
    "name:ukr_x_preferred":[
        "\u041f\u043e\u043c\u0438\u043a\u0443\u0432"
    ],
    "wof:name":"Pomykow",
    "wof:placetype":"locality"
},
  "geometry": {"coordinates":[19.72715,51.51964],"type":"Point"}
}