{
  "type": "Feature",
  "properties": {
    "gn:country":"PL",
    "gn:fcode":"PPL",
    "gn:population":20,
    "iso:country":"PL",
    "name:deu_x_preferred":[
        "Mielno"
    ],
    "name:epo_x_preferred":[
        "Mielno"
    ],
    "name:fra_x_preferred":[
        "Mielno"
    ],
    "name:ita_x_preferred":[
        "Mielno"
    ],
    "name:nld_x_preferred":[
        "Mielno"
    ],
    "name:pol_x_preferred":[
        "Mielno"
    ],
    "name:ukr_x_preferred":[
        "\u041c\u0435\u043b\u044c\u043d\u043e"
    ],
    "name:vie_x_preferred":[
        "Mielno"
    ],
    "qs_pg:aaroncc":"PL",
    "qs_pg:gn_country":"PL",
    "qs_pg:gn_fcode":"PPL",
    "qs_pg:gn_pop":20,
    "qs_pg:name":"Mielno",
    "qs_pg:photos_9r":0,
    "qs_pg:photos_sr":0,
    "qs_pg:pop_sr":1,
    "qs_pg:qs_pg_placetype":"locality",
    "wof:name":"Mielno",
    "wof:placetype":"locality",
    "wof:population":20
},
  "geometry": {"coordinates":[17.82128,52.67763],"type":"Point"}
}