{
  "type": "Feature",
  "properties": {
    "gn:admin1_code":"86.0",
    "gn:admin2_code":"3017.0",
    "gn:admin3_code":"301701.0",
    "gn:asciiname":"Wenecja",
    "gn:country_code":"PL",
    "gn:dem":127,
    "gn:feature_class":"P",
    "gn:feature_code":"PPL",
    "gn:name":"Wenecja",
    "gn:population":0,
    "gn:timezone":"Europe/Warsaw",
    "iso:country":"PL",
    "name:ceb_x_preferred":[
        "Wenecja"
    ],
    "name:deu_x_preferred":[
        "Wenecja"
    ],
    "name:pol_x_preferred":[
        "Wenecja"
    ],
    "name:rus_x_preferred":[
        "\u0412\u0435\u043d\u0435\u0446\u044c\u044f"
    ],
    "name:ukr_x_preferred":[
        "\u0412\u0435\u043d\u0435\u0446\u044f"
    ],
    "name:und_x_variant":[
        "Wenecia"
    ],
    "wof:name":"Wenecja",
    "wof:placetype":"neighbourhood"
},
  "geometry": {"coordinates":[17.82591,51.66493],"type":"Point"}
}