{
  "type": "Feature",
  "properties": {
    "gn:admin1_code":"87.0",
    "gn:admin2_code":"3213.0",
    "gn:admin3_code":"321305.0",
    "gn:asciiname":"Chudaczewo",
    "gn:country_code":"PL",
    "gn:dem":17,
    "gn:feature_class":"P",
    "gn:feature_code":"PPL",
    "gn:name":"Chudaczewo",
    "gn:population":0,
    "gn:timezone":"Europe/Warsaw",
    "iso:country":"PL",
    "name:azb_x_preferred":[
        "\u062e\u0648\u062f\u0627\u0686\u0648\u0648"
    ],
    "name:ceb_x_preferred":[
        "Chudaczewo"
    ],
    "name:deu_x_preferred":[
        "Chudaczewo"
    ],
    "name:fas_x_preferred":[
        "\u062e\u0648\u062f\u0627\u0686\u0648\u0648"
    ],
    "name:nld_x_preferred":[
        "Chudaczewo"
    ],
    "name:pol_x_preferred":[
        "Chudaczewo"
    ],
    "name:ukr_x_preferred":[
        "\u0425\u0443\u0434\u0430\u0447\u0435\u0432\u043e"
    ],
    "name:vie_x_preferred":[
        "Chudaczewo"
    ],
    "wof:name":"Chudaczewo",
    "wof:placetype":"locality"
},
  "geometry": {"coordinates":[16.65096,54.47863],"type":"Point"}
}