{
  "type": "Feature",
  "properties": {
    "gn:admin1_code":"85.0",
    "gn:admin2_code":"2815.0",
    "gn:admin3_code":"281503.0",
    "gn:asciiname":"Pacoltowo",
    "gn:country_code":"PL",
    "gn:dem":191,
    "gn:feature_class":"P",
    "gn:feature_code":"PPL",
    "gn:name":"Pac\u00f3\u0142towo",
    "gn:population":0,
    "gn:timezone":"Europe/Warsaw",
    "iso:country":"PL",
    "name:und_x_variant":[
        "P\u00f6tzdorf",
        "Gross P\u00f6tzdorf",
        "Pac\u00f3\u0142towo"
    ],
    "wof:name":"Pacoltowo",
    "wof:placetype":"locality"
},
  "geometry": {"coordinates":[20.14204,53.53275],"type":"Point"}
}