{
  "type": "Feature",
  "properties": {
    "gn:admin1_code":"86.0",
    "gn:admin2_code":"3011.0",
    "gn:admin3_code":"301104.0",
    "gn:asciiname":"Zbechy",
    "gn:country_code":"PL",
    "gn:dem":79,
    "gn:feature_class":"P",
    "gn:feature_code":"PPL",
    "gn:name":"Zb\u0119chy",
    "gn:population":0,
    "gn:timezone":"Europe/Warsaw",
    "iso:country":"PL",
    "name:fra_x_preferred":[
        "Zb\u0119chy"
    ],
    "name:pol_x_preferred":[
        "Zb\u0119chy"
    ],
    "name:ukr_x_preferred":[
        "\u0417\u0431\u0435\u043d\u0445\u0438"
    ],
    "name:und_x_variant":[
        "Zb\u0119chy"
    ],
    "wof:name":"Zbechy",
    "wof:placetype":"locality"
},
  "geometry": {"coordinates":[16.90096,52.00791],"type":"Point"}
}