{
  "type": "Feature",
  "properties": {
    "gn:admin1_code":"76.0",
    "gn:admin2_code":"805.0",
    "gn:admin3_code":"80502.0",
    "gn:asciiname":"Laski Lubuskie",
    "gn:country_code":"PL",
    "gn:dem":62,
    "gn:feature_class":"P",
    "gn:feature_code":"PPL",
    "gn:name":"Laski Lubuskie",
    "gn:population":0,
    "gn:timezone":"Europe/Warsaw",
    "iso:country":"PL",
    "name:deu_x_preferred":[
        "Lassig"
    ],
    "name:fra_x_preferred":[
        "Laski Lubuskie"
    ],
    "name:pol_x_preferred":[
        "Laski Lubuskie"
    ],
    "name:ukr_x_preferred":[
        "\u041b\u044f\u0441\u043a\u0456-\u041b\u044e\u0431\u0443\u0441\u044c\u043a\u0456"
    ],
    "wof:name":"Laski Lubuskie",
    "wof:placetype":"locality"
},
  "geometry": {"coordinates":[14.6913,52.46229],"type":"Point"}
}