{
  "type": "Feature",
  "properties": {
    "gn:country":"PL",
    "gn:fcode":"PPL",
    "gn:population":0,
    "iso:country":"PL",
    "name:ast_x_preferred":[
        "Wola Mokrzeska"
    ],
    "name:ces_x_preferred":[
        "Wola Mokrzeska"
    ],
    "name:che_x_preferred":[
        "\u0412\u043e\u043b\u044f-\u041c\u043e\u043a\u0448\u0435\u0441\u043a\u0430"
    ],
    "name:eng_x_preferred":[
        "Wola Mokrzeska"
    ],
    "name:fra_x_preferred":[
        "Wola Mokrzeska"
    ],
    "name:nan_x_preferred":[
        "Wola Mokrzeska"
    ],
    "name:pol_x_preferred":[
        "Wola Mokrzeska"
    ],
    "name:tat_x_preferred":[
        "\u0412\u043e\u043b\u044f-\u041c\u043e\u043a\u0448\u0435\u0441\u043a\u0430"
    ],
    "name:ukr_x_preferred":[
        "\u0412\u043e\u043b\u044f-\u041c\u043e\u043a\u0448\u0435\u0441\u044c\u043a\u0430"
    ],
    "name:und_x_variant":[
        "Wola Mokrzewska"
    ],
    "qs_pg:aaroncc":"PL",
    "qs_pg:gn_country":"PL",
    "qs_pg:gn_fcode":"PPL",
    "qs_pg:gn_pop":0,
    "qs_pg:name":"Wola Mokrzeska",
    "qs_pg:name_adm0":"Polska",
    "qs_pg:name_adm1":"Sl\u0105skie",
    "qs_pg:photos":6,
    "qs_pg:photos_1k":1,
    "qs_pg:photos_9k":1,
    "qs_pg:photos_9r":1,
    "qs_pg:photos_all":6,
    "qs_pg:photos_sr":1,
    "qs_pg:pop_sr":0,
    "qs_pg:qs_pg_placetype":"locality",
    "qs_pg:qs_pg_placetype_gp":"Town",
    "qs_pg:woe_adm0":23424923,
    "woe:adm0_id":23424923,
    "woe:name_adm0":"Polska",
    "woe:name_adm1":"Sl\u0105skie",
    "woe:placetype":"Town",
    "wof:name":"Wola Mokrzeska",
    "wof:placetype":"locality"
},
  "geometry": {"coordinates":[19.45745,50.82615],"type":"Point"}
}