{
  "type": "Feature",
  "properties": {
    "gn:admin1_code":"74.0",
    "gn:admin2_code":"1012.0",
    "gn:admin3_code":"101213.0",
    "gn:asciiname":"Niedospielin",
    "gn:country_code":"PL",
    "gn:dem":225,
    "gn:feature_class":"P",
    "gn:feature_code":"PPL",
    "gn:name":"Niedo\u015bpielin",
    "gn:population":0,
    "gn:timezone":"Europe/Warsaw",
    "iso:country":"PL",
    "name:ceb_x_preferred":[
        "Niedo\u015bpielin"
    ],
    "name:fra_x_preferred":[
        "Niedo\u015bpielin"
    ],
    "name:pol_x_preferred":[
        "Niedo\u015bpielin"
    ],
    "name:szl_x_preferred":[
        "\u0143ydo\u015bpjelin"
    ],
    "name:ukr_x_preferred":[
        "\u041d\u0435\u0434\u043e\u0441\u044c\u043f\u0435\u043b\u0456\u043d"
    ],
    "wof:name":"Niedospielin",
    "wof:placetype":"locality"
},
  "geometry": {"coordinates":[19.73474,51.01693],"type":"Point"}
}