{
  "type": "Feature",
  "properties": {
    "iso:country":"PL",
    "name:azb_x_preferred":[
        "\u0642\u0645\u06cc\u0646\u0627 \u0645\u06cc\u0644\u06cc\u0686"
    ],
    "name:bel_x_preferred":[
        "\u041c\u0456\u043b\u0456\u0447"
    ],
    "name:eus_x_preferred":[
        "Milicz udalerria"
    ],
    "name:fas_x_preferred":[
        "\u06af\u0645\u06cc\u0646\u0627 \u0645\u06cc\u0644\u06cc\u0686"
    ],
    "name:fra_x_preferred":[
        "Milicz"
    ],
    "name:ita_x_preferred":[
        "Milicz"
    ],
    "name:nld_x_preferred":[
        "Milicz"
    ],
    "name:pol_x_preferred":[
        "Milicz"
    ],
    "name:rus_x_preferred":[
        "\u041c\u0438\u043b\u0438\u0447"
    ],
    "name:slk_x_preferred":[
        "Gmina Milicz"
    ],
    "name:ukr_x_preferred":[
        "\u0413\u043c\u0456\u043d\u0430 \u041c\u0456\u043b\u0438\u0447"
    ],
    "name:vie_x_preferred":[
        "Milicz"
    ],
    "name:war_x_preferred":[
        "Gmina Milicz"
    ],
    "qs_pg:aaroncc":"PL",
    "qs_pg:name":"Gmina Milicz",
    "qs_pg:name_adm0":"Polska",
    "qs_pg:name_adm1":"Dolnosl\u0105skie",
    "qs_pg:photos":12,
    "qs_pg:photos_1k":2,
    "qs_pg:photos_9k":1,
    "qs_pg:photos_9r":2,
    "qs_pg:photos_all":48,
    "qs_pg:photos_sr":1,
    "qs_pg:pop_sr":0,
    "qs_pg:qs_pg_placetype":"localadmin",
    "qs_pg:qs_pg_placetype_gp":"LocalAdmin",
    "qs_pg:woe_adm0":23424923,
    "woe:adm0_id":23424923,
    "woe:name_adm0":"Polska",
    "woe:name_adm1":"Dolnosl\u0105skie",
    "woe:placetype":"LocalAdmin",
    "wof:name":"Gmina Milicz",
    "wof:placetype":"localadmin"
},
  "geometry": {"coordinates":[17.331962,51.543239],"type":"Point"}
}