{
  "type": "Feature",
  "properties": {
    "gn:gn_country":"PL",
    "gn:gn_fcode":"PPL",
    "gn:gn_pop":259,
    "gn:population":259,
    "iso:country":"PL",
    "name:eng_x_preferred":[
        "Opoczka Ma\u0142a"
    ],
    "name:fra_x_preferred":[
        "Opoczka Ma\u0142a"
    ],
    "name:pol_x_preferred":[
        "Opoczka Ma\u0142a"
    ],
    "name:unk_x_variant":[
        "Opoczka"
    ],
    "qs_pg:aaroncc":"PL",
    "qs_pg:gn_country":"PL",
    "qs_pg:gn_fcode":"PPL",
    "qs_pg:gn_pop":259,
    "qs_pg:name":"Opoczka Ma\u0142a",
    "qs_pg:name_adm0":"Polska",
    "qs_pg:name_adm1":"Lubelskie",
    "qs_pg:photos_9r":0,
    "qs_pg:photos_sr":0,
    "qs_pg:pop_sr":2,
    "qs_pg:qs_pg_placetype":"locality",
    "qs_pg:qs_pg_placetype_gp":"Town",
    "qs_pg:woe_adm0":23424923,
    "woe:adm0_id":23424923,
    "woe:name_adm0":"Polska",
    "woe:name_adm1":"Lubelskie",
    "woe:placetype":"Town",
    "wof:name":"Opoczka Ma\u0142a",
    "wof:placetype":"locality",
    "wof:population":259
},
  "geometry": {"coordinates":[21.84211,50.88181],"type":"Point"}
}