{
  "type": "Feature",
  "properties": {
    "gn:admin1_code":"86.0",
    "gn:admin2_code":"3004.0",
    "gn:admin3_code":"300402.0",
    "gn:asciiname":"Kosowo",
    "gn:country_code":"PL",
    "gn:dem":111,
    "gn:feature_class":"P",
    "gn:feature_code":"PPL",
    "gn:name":"Kosowo",
    "gn:population":0,
    "gn:timezone":"Europe/Warsaw",
    "iso:country":"PL",
    "name:fra_x_preferred":[
        "Kosowo"
    ],
    "name:pol_x_preferred":[
        "Kosowo"
    ],
    "wof:name":"Kosowo",
    "wof:placetype":"locality"
},
  "geometry": {"coordinates":[16.91064,51.89579000000001],"type":"Point"}
}