{
  "type": "Feature",
  "properties": {
    "gn:admin1_code":"74.0",
    "gn:admin2_code":"1002.0",
    "gn:admin3_code":"100210.0",
    "gn:asciiname":"Rejmontow",
    "gn:country_code":"PL",
    "gn:dem":119,
    "gn:feature_class":"P",
    "gn:feature_code":"PPL",
    "gn:name":"Rejmont\u00f3w",
    "gn:population":0,
    "gn:timezone":"Europe/Warsaw",
    "iso:country":"PL",
    "name:fra_x_preferred":[
        "Rejmont\u00f3w"
    ],
    "name:pol_x_preferred":[
        "Rejmont\u00f3w"
    ],
    "name:ukr_x_preferred":[
        "\u0420\u0435\u0439\u043c\u043e\u043d\u0442\u0443\u0432"
    ],
    "wof:name":"Rejmontow",
    "wof:placetype":"locality"
},
  "geometry": {"coordinates":[19.42606,52.29945],"type":"Point"}
}