{
  "type": "Feature",
  "properties": {
    "gn:gn_country":"PL",
    "gn:gn_fcode":"PPLA3",
    "gn:gn_pop":990,
    "gn:population":990,
    "iso:country":"PL",
    "name:azb_x_preferred":[
        "\u0645\u0648\u0642\u06cc\u0648"
    ],
    "name:ceb_x_preferred":[
        "Me\u0142giew"
    ],
    "name:fas_x_preferred":[
        "\u0645\u0648\u06af\u06cc\u0648"
    ],
    "name:fra_x_preferred":[
        "Me\u0142giew"
    ],
    "name:nld_x_preferred":[
        "Me\u0142giew"
    ],
    "name:pol_x_preferred":[
        "Me\u0142giew"
    ],
    "name:ukr_x_preferred":[
        "\u041c\u0435\u043b\u0491\u0435\u0432"
    ],
    "name:unk_x_variant":[
        "Metgiew"
    ],
    "qs_pg:aaroncc":"PL",
    "qs_pg:gn_country":"PL",
    "qs_pg:gn_fcode":"PPLA3",
    "qs_pg:gn_pop":990,
    "qs_pg:name":"Me\u0142giew",
    "qs_pg:name_adm0":"Polska",
    "qs_pg:name_adm1":"Lubelskie",
    "qs_pg:photos_9k":1,
    "qs_pg:photos_9r":2,
    "qs_pg:photos_all":75,
    "qs_pg:photos_sr":0,
    "qs_pg:pop_sr":2,
    "qs_pg:qs_pg_placetype":"localadmin",
    "qs_pg:qs_pg_placetype_gp":"LocalAdmin",
    "qs_pg:woe_adm0":23424923,
    "woe:adm0_id":23424923,
    "woe:name_adm0":"Polska",
    "woe:name_adm1":"Lubelskie",
    "woe:placetype":"LocalAdmin",
    "wof:name":"Me\u0142giew",
    "wof:placetype":"localadmin",
    "wof:population":990
},
  "geometry": {"coordinates":[22.78414,51.22519],"type":"Point"}
}