{
  "type": "Feature",
  "properties": {
    "gn:admin1_code":"87.0",
    "gn:admin2_code":"3202.0",
    "gn:admin3_code":"320201.0",
    "gn:asciiname":"Strumienno",
    "gn:country_code":"PL",
    "gn:dem":66,
    "gn:feature_class":"P",
    "gn:feature_code":"PPL",
    "gn:name":"Strumienno",
    "gn:population":0,
    "gn:timezone":"Europe/Warsaw",
    "iso:country":"PL",
    "name:deu_x_preferred":[
        "Strumienno"
    ],
    "name:fra_x_preferred":[
        "Strumienno"
    ],
    "name:pol_x_preferred":[
        "Strumienno"
    ],
    "name:vie_x_preferred":[
        "Strumienno"
    ],
    "wof:name":"Strumienno",
    "wof:placetype":"locality"
},
  "geometry": {"coordinates":[15.71431,53.03543000000001],"type":"Point"}
}