{
  "type": "Feature",
  "properties": {
    "gn:admin1_code":"74.0",
    "gn:admin2_code":"1005.0",
    "gn:admin3_code":"100510.0",
    "gn:asciiname":"Bogoria Dolna",
    "gn:cc2":"PL",
    "gn:country_code":"PL",
    "gn:dem":95,
    "gn:feature_class":"P",
    "gn:feature_code":"PPL",
    "gn:name":"Bogoria Dolna",
    "gn:population":0,
    "gn:timezone":"Europe/Warsaw",
    "iso:country":"PL",
    "name:fra_x_preferred":[
        "Bogoria Dolna"
    ],
    "name:pol_x_preferred":[
        "Bogoria Dolna"
    ],
    "name:ukr_x_preferred":[
        "\u0411\u043e\u0491\u043e\u0440\u0456\u044f-\u0414\u043e\u043b\u044c\u043d\u0430"
    ],
    "name:und_x_variant":[
        "Bogorja Dolna"
    ],
    "wof:name":"Bogoria Dolna",
    "wof:placetype":"locality"
},
  "geometry": {"coordinates":[19.76784,52.1396],"type":"Point"}
}