{
  "type": "Feature",
  "properties": {
    "gn:admin1_code":"74.0",
    "gn:admin2_code":"1005.0",
    "gn:admin3_code":"100510.0",
    "gn:asciiname":"Bogoria Dolna",
    "gn:cc2":"PL",
    "gn:country_code":"PL",
    "gn:dem":95,
    "gn:feature_class":"P",
    "gn:feature_code":"PPL",
    "gn:name":"Bogoria Dolna",
    "gn:population":0,
    "gn:timezone":"Europe/Warsaw",
    "iso:country":"PL",
    "name:und_x_variant":[
        "Bogorja Dolna",
        "Bogoria Dolna"
    ],
    "wof:name":"Bogoria Dolna",
    "wof:placetype":"locality"
},
  "geometry": {"coordinates":[19.76784,52.1396],"type":"Point"}
}