{
  "type": "Feature",
  "properties": {
    "gn:admin1_code":"80.0",
    "gn:admin2_code":"1817.0",
    "gn:admin3_code":"181703.0",
    "gn:asciiname":"Belchowka",
    "gn:country_code":"PL",
    "gn:dem":450,
    "gn:feature_class":"P",
    "gn:feature_code":"PPL",
    "gn:name":"Be\u0142ch\u00f3wka",
    "gn:population":0,
    "gn:timezone":"Europe/Warsaw",
    "iso:country":"PL",
    "name:und_x_variant":[
        "Blchowka",
        "Be\u0142ch\u00f3wka"
    ],
    "wof:name":"Belchowka",
    "wof:placetype":"locality"
},
  "geometry": {"coordinates":[22.10876,49.48819],"type":"Point"}
}