{
  "type": "Feature",
  "properties": {
    "gn:admin1_code":"80.0",
    "gn:admin2_code":"1817.0",
    "gn:admin3_code":"181703.0",
    "gn:asciiname":"Belchowka",
    "gn:country_code":"PL",
    "gn:dem":450,
    "gn:feature_class":"P",
    "gn:feature_code":"PPL",
    "gn:name":"Be\u0142ch\u00f3wka",
    "gn:population":0,
    "gn:timezone":"Europe/Warsaw",
    "iso:country":"PL",
    "name:pol_x_preferred":[
        "Be\u0142ch\u00f3wka"
    ],
    "name:rue_x_preferred":[
        "\u0411\u0435\u043b\u0445\u0456\u0432\u043a\u0430"
    ],
    "name:ukr_x_preferred":[
        "\u0411\u0435\u043b\u0445\u0456\u0432\u043a\u0430"
    ],
    "name:und_x_variant":[
        "Blchowka"
    ],
    "wof:name":"Belchowka",
    "wof:placetype":"locality"
},
  "geometry": {"coordinates":[22.10876,49.48819],"type":"Point"}
}