{
  "type": "Feature",
  "properties": {
    "gn:admin1_code":"85.0",
    "gn:admin2_code":"2817.0",
    "gn:admin3_code":"281706.0",
    "gn:asciiname":"Stare Kiejkuty",
    "gn:country_code":"PL",
    "gn:dem":173,
    "gn:feature_class":"P",
    "gn:feature_code":"PPL",
    "gn:name":"Stare Kiejkuty",
    "gn:population":0,
    "gn:timezone":"Europe/Warsaw",
    "iso:country":"PL",
    "name:deu_x_preferred":[
        "Stare Kiejkuty"
    ],
    "name:fra_x_preferred":[
        "Stare Kiejkuty"
    ],
    "name:pol_x_preferred":[
        "Stare Kiejkuty"
    ],
    "name:ukr_x_preferred":[
        "\u0421\u0442\u0430\u0440\u0435 \u041a\u0435\u0439\u043a\u0443\u0442\u0438"
    ],
    "name:und_x_variant":[
        "Alt Keykuth"
    ],
    "wof:name":"Stare Kiejkuty",
    "wof:placetype":"locality"
},
  "geometry": {"coordinates":[21.06656,53.63477],"type":"Point"}
}