{
  "type": "Feature",
  "properties": {
    "gn:admin1_code":"76.0",
    "gn:admin2_code":"810.0",
    "gn:admin3_code":"81009.0",
    "gn:asciiname":"Mlynisko",
    "gn:country_code":"PL",
    "gn:dem":83,
    "gn:feature_class":"P",
    "gn:feature_code":"PPL",
    "gn:name":"M\u0142ynisko",
    "gn:population":0,
    "gn:timezone":"Europe/Warsaw",
    "iso:country":"PL",
    "wof:name":"Mlynisko",
    "wof:placetype":"locality"
},
  "geometry": {"coordinates":[15.26231,51.73637],"type":"Point"}
}