{
  "type": "Feature",
  "properties": {
    "gn:admin1_code":"86.0",
    "gn:admin2_code":"3010.0",
    "gn:admin3_code":"301007.0",
    "gn:asciiname":"Kuchary Koscielne",
    "gn:country_code":"PL",
    "gn:dem":94,
    "gn:feature_class":"P",
    "gn:feature_code":"PPL",
    "gn:name":"Kuchary Ko\u015bcielne",
    "gn:population":0,
    "gn:timezone":"Europe/Warsaw",
    "iso:country":"PL",
    "name:fra_x_preferred":[
        "Kuchary Ko\u015bcielne"
    ],
    "name:pol_x_preferred":[
        "Kuchary Ko\u015bcielne"
    ],
    "name:ukr_x_preferred":[
        "\u041a\u0443\u0445\u0430\u0440\u0438-\u041a\u043e\u0441\u044c\u0446\u0435\u043b\u044c\u043d\u0435"
    ],
    "wof:name":"Kuchary Koscielne",
    "wof:placetype":"locality"
},
  "geometry": {"coordinates":[18.13753,52.13581],"type":"Point"}
}