{
  "type": "Feature",
  "properties": {
    "gn:admin1_code":"79.0",
    "gn:admin2_code":"1601.0",
    "gn:admin3_code":"160102.0",
    "gn:asciiname":"Bierzow",
    "gn:country_code":"PL",
    "gn:dem":158,
    "gn:feature_class":"P",
    "gn:feature_code":"PPL",
    "gn:name":"Bierz\u00f3w",
    "gn:population":0,
    "gn:timezone":"Europe/Warsaw",
    "iso:country":"PL",
    "name:ceb_x_preferred":[
        "Bierz\u00f3w"
    ],
    "name:pol_x_preferred":[
        "Bierz\u00f3w"
    ],
    "name:ukr_x_preferred":[
        "\u0411\u0435\u0436\u0443\u0432"
    ],
    "wof:name":"Bierzow",
    "wof:placetype":"locality"
},
  "geometry": {"coordinates":[17.34398,50.8209],"type":"Point"}
}