{
  "type": "Feature",
  "properties": {
    "gn:gn_country":"PL",
    "gn:gn_fcode":"PPL",
    "gn:gn_pop":107,
    "gn:population":107,
    "iso:country":"PL",
    "qs_pg:aaroncc":"PL",
    "qs_pg:gn_country":"PL",
    "qs_pg:gn_fcode":"PPL",
    "qs_pg:gn_pop":107,
    "qs_pg:name":"Stanis\u0142aw\u00f3w",
    "qs_pg:photos_9r":0,
    "qs_pg:photos_sr":0,
    "qs_pg:pop_sr":1,
    "qs_pg:qs_pg_placetype":"locality",
    "wof:name":"Stanis\u0142aw\u00f3w",
    "wof:placetype":"locality",
    "wof:population":107
},
  "geometry": {"coordinates":[20.03215,51.07171],"type":"Point"}
}