{
  "type": "Feature",
  "properties": {
    "gn:gn_country":"PL",
    "gn:gn_fcode":"PPL",
    "gn:gn_pop":0,
    "iso:country":"PL",
    "name:ast_x_preferred":[
        "B\u0105kowiec"
    ],
    "name:ceb_x_preferred":[
        "B\u0105kowiec"
    ],
    "name:eng_x_preferred":[
        "B\u0105kowiec"
    ],
    "name:fra_x_preferred":[
        "B\u0105kowiec"
    ],
    "name:nld_x_preferred":[
        "B\u0105kowiec"
    ],
    "name:pol_x_preferred":[
        "B\u0105kowiec"
    ],
    "name:ukr_x_preferred":[
        "\u0411\u043e\u043d\u043a\u043e\u0432\u0435\u0446\u044c"
    ],
    "qs_pg:aaroncc":"PL",
    "qs_pg:gn_country":"PL",
    "qs_pg:gn_fcode":"PPL",
    "qs_pg:gn_pop":0,
    "qs_pg:name":"B\u0105kowiec",
    "qs_pg:name_adm0":"Polska",
    "qs_pg:name_adm1":"Mazowieckie",
    "qs_pg:photos_9k":1,
    "qs_pg:photos_9r":1,
    "qs_pg:photos_all":1,
    "qs_pg:photos_sr":0,
    "qs_pg:pop_sr":0,
    "qs_pg:qs_pg_placetype":"locality",
    "qs_pg:qs_pg_placetype_gp":"Town",
    "qs_pg:woe_adm0":23424923,
    "woe:adm0_id":23424923,
    "woe:name_adm0":"Polska",
    "woe:name_adm1":"Mazowieckie",
    "woe:placetype":"Town",
    "wof:name":"B\u0105kowiec",
    "wof:placetype":"locality"
},
  "geometry": {"coordinates":[21.70603,51.50175],"type":"Point"}
}