{
  "type": "Feature",
  "properties": {
    "gn:gn_country":"PL",
    "gn:gn_fcode":"PPLA3",
    "gn:gn_pop":2067,
    "gn:population":2067,
    "iso:country":"PL",
    "name:csb_x_preferred":[
        "Stobnica"
    ],
    "name:srp_x_preferred":[
        "\u0421\u0442\u0435\u043f\u045a\u0438\u0446\u0430"
    ],
    "name:unk_x_variant":[
        "Gross Stepenitz"
    ],
    "qs_pg:aaroncc":"PL",
    "qs_pg:gn_country":"PL",
    "qs_pg:gn_fcode":"PPLA3",
    "qs_pg:gn_pop":2067,
    "qs_pg:name":"Stepnica",
    "qs_pg:name_adm0":"Polska",
    "qs_pg:name_adm1":"Zachodniopomorskie",
    "qs_pg:photos":2,
    "qs_pg:photos_1k":1,
    "qs_pg:photos_9k":1,
    "qs_pg:photos_9r":2,
    "qs_pg:photos_all":59,
    "qs_pg:photos_sr":1,
    "qs_pg:pop_sr":4,
    "qs_pg:qs_pg_placetype":"localadmin",
    "qs_pg:qs_pg_placetype_gp":"LocalAdmin",
    "qs_pg:woe_adm0":23424923,
    "woe:adm0_id":23424923,
    "woe:name_adm0":"Polska",
    "woe:name_adm1":"Zachodniopomorskie",
    "woe:placetype":"LocalAdmin",
    "wof:name":"Stepnica",
    "wof:placetype":"localadmin",
    "wof:population":2067
},
  "geometry": {"coordinates":[14.62555,53.65187],"type":"Point"}
}