{
  "type": "Feature",
  "properties": {
    "gn:admin1_code":"75.0",
    "gn:admin2_code":"605.0",
    "gn:admin3_code":"60506.0",
    "gn:asciiname":"Borownica-Kopce",
    "gn:country_code":"PL",
    "gn:dem":220,
    "gn:feature_class":"P",
    "gn:feature_code":"PPL",
    "gn:name":"Borownica-Kopce",
    "gn:population":0,
    "gn:timezone":"Europe/Warsaw",
    "iso:country":"PL",
    "wof:name":"Borownica-Kopce",
    "wof:placetype":"locality"
},
  "geometry": {"coordinates":[22.35,50.73333],"type":"Point"}
}