{
  "type": "Feature",
  "properties": {
    "gn:country":"PL",
    "gn:fcode":"PPL",
    "gn:population":256,
    "iso:country":"PL",
    "name:ceb_x_preferred":[
        "Chom\u0119towo"
    ],
    "name:deu_x_preferred":[
        "Chom\u0119towo"
    ],
    "name:fra_x_preferred":[
        "Chom\u0119towo"
    ],
    "name:pol_x_preferred":[
        "Chom\u0119towo"
    ],
    "name:ukr_x_preferred":[
        "\u0425\u043e\u043c\u0435\u043d\u0442\u043e\u0432\u043e"
    ],
    "qs_pg:aaroncc":"PL",
    "qs_pg:gn_country":"PL",
    "qs_pg:gn_fcode":"PPL",
    "qs_pg:gn_pop":256,
    "qs_pg:name":"Chom\u0119towo",
    "qs_pg:name_adm0":"Polska",
    "qs_pg:name_adm1":"Zachodniopomorskie",
    "qs_pg:photos_9r":0,
    "qs_pg:photos_sr":0,
    "qs_pg:pop_sr":2,
    "qs_pg:qs_pg_placetype":"locality",
    "qs_pg:qs_pg_placetype_gp":"Town",
    "qs_pg:woe_adm0":23424923,
    "woe:adm0_id":23424923,
    "woe:name_adm0":"Polska",
    "woe:name_adm1":"Zachodniopomorskie",
    "woe:placetype":"Town",
    "wof:name":"Chom\u0119towo",
    "wof:placetype":"locality",
    "wof:population":256
},
  "geometry": {"coordinates":[15.17384,54.03706],"type":"Point"}
}