{
  "type": "Feature",
  "properties": {
    "gn:admin1_code":"78.0",
    "gn:admin2_code":"1406.0",
    "gn:admin3_code":"140602.0",
    "gn:asciiname":"Wolka Dankowska",
    "gn:country_code":"PL",
    "gn:dem":147,
    "gn:feature_class":"P",
    "gn:feature_code":"PPL",
    "gn:name":"W\u00f3lka Dankowska",
    "gn:population":0,
    "gn:timezone":"Europe/Warsaw",
    "iso:country":"PL",
    "name:fra_x_preferred":[
        "W\u00f3lka Da\u0144kowska"
    ],
    "name:pol_x_preferred":[
        "W\u00f3lka Da\u0144kowska"
    ],
    "name:ukr_x_preferred":[
        "\u0412\u0443\u043b\u044c\u043a\u0430-\u0414\u0430\u043d\u044c\u043a\u043e\u0432\u0441\u044c\u043a\u0430"
    ],
    "name:und_x_variant":[
        "W\u00f3lka Dankowska"
    ],
    "wof:name":"Wolka Dankowska",
    "wof:placetype":"locality"
},
  "geometry": {"coordinates":[20.71882,51.74879],"type":"Point"}
}