{
  "type": "Feature",
  "properties": {
    "gn:admin1_code":"82.0",
    "gn:admin2_code":"2210.0",
    "gn:admin3_code":"221002.0",
    "gn:asciiname":"Laczki Myszewskie",
    "gn:country_code":"PL",
    "gn:dem":-3,
    "gn:feature_class":"P",
    "gn:feature_code":"PPL",
    "gn:name":"\u0141\u0105czki Myszewskie",
    "gn:population":0,
    "gn:timezone":"Europe/Warsaw",
    "iso:country":"PL",
    "name:und_x_variant":[
        "Klein Mausdorferweide",
        "\u0141\u0105czki Myszewskie"
    ],
    "wof:name":"Laczki Myszewskie",
    "wof:placetype":"locality"
},
  "geometry": {"coordinates":[19.23517,54.21833],"type":"Point"}
}