{
  "type": "Feature",
  "properties": {
    "gn:admin1_code":"82.0",
    "gn:admin2_code":"2216.0",
    "gn:admin3_code":"221604.0",
    "gn:asciiname":"Jurkowice",
    "gn:country_code":"PL",
    "gn:dem":20,
    "gn:feature_class":"P",
    "gn:feature_code":"PPL",
    "gn:name":"Jurkowice",
    "gn:population":0,
    "gn:timezone":"Europe/Warsaw",
    "iso:country":"PL",
    "name:pol_x_preferred":[
        "Jurkowice"
    ],
    "name:ukr_x_preferred":[
        "\u042e\u0440\u043a\u043e\u0432\u0456\u0446\u0435"
    ],
    "name:und_x_variant":[
        "Georgensdorf"
    ],
    "wof:name":"Jurkowice",
    "wof:placetype":"locality"
},
  "geometry": {"coordinates":[19.13201,53.95939],"type":"Point"}
}