{
  "type": "Feature",
  "properties": {
    "gn:admin1_code":"72",
    "gn:admin2_code":"0214",
    "gn:admin3_code":"21403.0",
    "gn:asciiname":"Strzelce",
    "gn:country_code":"PL",
    "gn:dem":162,
    "gn:feature_class":"P",
    "gn:feature_code":"PPL",
    "gn:name":"Strzelce",
    "gn:population":0,
    "gn:timezone":"Europe/Warsaw",
    "iso:country":"PL",
    "name:deu_x_historical":[
        "Strehlitz"
    ],
    "name:deu_x_preferred":[
        "Strehlitz"
    ],
    "wof:name":"Strzelce",
    "wof:placetype":"locality"
},
  "geometry": {"coordinates":[17.32407000000001,51.28541],"type":"Point"}
}