{
  "type": "Feature",
  "properties": {
    "gn:admin1_code":"81.0",
    "gn:admin2_code":"2005.0",
    "gn:admin3_code":"200508.0",
    "gn:asciiname":"Waniewo",
    "gn:country_code":"PL",
    "gn:dem":138,
    "gn:feature_class":"P",
    "gn:feature_code":"PPL",
    "gn:name":"Waniewo",
    "gn:population":0,
    "gn:timezone":"Europe/Warsaw",
    "iso:country":"PL",
    "name:lit_x_preferred":[
        "Vanevas"
    ],
    "name:pol_x_preferred":[
        "Waniewo"
    ],
    "name:ukr_x_preferred":[
        "\u0412\u0430\u043d\u0435\u0432\u043e"
    ],
    "wof:name":"Waniewo",
    "wof:placetype":"locality"
},
  "geometry": {"coordinates":[23.55399,52.94299],"type":"Point"}
}