{
  "type": "Feature",
  "properties": {
    "gn:admin1_code":"82.0",
    "gn:admin2_code":"2213.0",
    "gn:admin3_code":"221303.0",
    "gn:asciiname":"Krag",
    "gn:country_code":"PL",
    "gn:dem":108,
    "gn:feature_class":"P",
    "gn:feature_code":"PPL",
    "gn:name":"Kr\u0105g",
    "gn:population":0,
    "gn:timezone":"Europe/Warsaw",
    "iso:country":"PL",
    "name:und_x_variant":[
        "Kr\u0105g"
    ],
    "wof:name":"Krag",
    "wof:placetype":"locality"
},
  "geometry": {"coordinates":[18.44078,54.00296],"type":"Point"}
}