{
  "type": "Feature",
  "properties": {
    "gn:admin1_code":"78.0",
    "gn:admin2_code":"1433.0",
    "gn:admin3_code":"143304.0",
    "gn:asciiname":"Jarnice",
    "gn:country_code":"PL",
    "gn:dem":122,
    "gn:feature_class":"P",
    "gn:feature_code":"PPL",
    "gn:name":"Jarnice",
    "gn:population":0,
    "gn:timezone":"Europe/Warsaw",
    "iso:country":"PL",
    "name:azb_x_preferred":[
        "\u06cc\u0627\u0631\u0646\u0642\u062a\u0633\u0647"
    ],
    "name:fas_x_preferred":[
        "\u06cc\u0627\u0631\u0646\u06af\u062a\u0633\u0647"
    ],
    "name:fra_x_preferred":[
        "Jarnice"
    ],
    "name:lit_x_preferred":[
        "Jarnic\u0117"
    ],
    "name:pol_x_preferred":[
        "Jarnice"
    ],
    "name:ukr_x_preferred":[
        "\u042f\u0440\u043d\u0456\u0446\u0435"
    ],
    "name:urd_x_preferred":[
        "\u062c\u0631\u06ba \u06a9\u06d2"
    ],
    "wof:name":"Jarnice",
    "wof:placetype":"locality"
},
  "geometry": {"coordinates":[21.98566,52.35857],"type":"Point"}
}