{
  "type": "Feature",
  "properties": {
    "gn:admin1_code":"74.0",
    "gn:admin2_code":"1016.0",
    "gn:admin3_code":"101603.0",
    "gn:asciiname":"Adamow",
    "gn:country_code":"PL",
    "gn:dem":197,
    "gn:feature_class":"P",
    "gn:feature_code":"PPL",
    "gn:name":"Adam\u00f3w",
    "gn:population":65,
    "gn:timezone":"Europe/Warsaw",
    "iso:country":"PL",
    "wof:name":"Adamow",
    "wof:placetype":"locality",
    "wof:population":65
},
  "geometry": {"coordinates":[19.97211,51.66574],"type":"Point"}
}