{
  "type": "Feature",
  "properties": {
    "gn:admin1_code":"79.0",
    "gn:admin2_code":"1601.0",
    "gn:admin3_code":"160103.0",
    "gn:asciiname":"Lipowa",
    "gn:country_code":"PL",
    "gn:dem":169,
    "gn:feature_class":"P",
    "gn:feature_code":"PPL",
    "gn:name":"Lipowa",
    "gn:population":0,
    "gn:timezone":"Europe/Warsaw",
    "iso:country":"PL",
    "name:und_x_variant":[
        "Deutsch Leippe",
        "Lipowa"
    ],
    "wof:name":"Lipowa",
    "wof:placetype":"locality"
},
  "geometry": {"coordinates":[17.43485,50.7295],"type":"Point"}
}