{
  "type": "Feature",
  "properties": {
    "gn:admin1_code":"85.0",
    "gn:admin2_code":"2809.0",
    "gn:admin3_code":"280903.0",
    "gn:asciiname":"Swietnik",
    "gn:country_code":"PL",
    "gn:dem":103,
    "gn:feature_class":"P",
    "gn:feature_code":"PPL",
    "gn:name":"\u015awi\u0119tnik",
    "gn:population":0,
    "gn:timezone":"Europe/Warsaw",
    "iso:country":"PL",
    "name:fra_x_preferred":[
        "\u015awi\u0119tnik"
    ],
    "name:pol_x_preferred":[
        "\u015awi\u0119tnik"
    ],
    "name:ukr_x_preferred":[
        "\u0421\u044c\u0432\u0435\u043d\u0442\u043d\u0438\u043a"
    ],
    "name:und_x_variant":[
        "Heiligenfelde"
    ],
    "wof:name":"Swietnik",
    "wof:placetype":"locality"
},
  "geometry": {"coordinates":[20.63305,54.09124],"type":"Point"}
}