{
  "type": "Feature",
  "properties": {
    "gn:country":"PL",
    "gn:fcode":"PPL",
    "gn:population":496,
    "iso:country":"PL",
    "name:fra_x_preferred":[
        "P\u0119c\u0142aw"
    ],
    "name:pol_x_preferred":[
        "P\u0119c\u0142aw"
    ],
    "name:ukr_x_preferred":[
        "\u041f\u0435\u043d\u0446\u043b\u0430\u0432"
    ],
    "qs_pg:aaroncc":"PL",
    "qs_pg:gn_country":"PL",
    "qs_pg:gn_fcode":"PPL",
    "qs_pg:gn_pop":496,
    "qs_pg:name":"P\u0119c\u0142aw",
    "qs_pg:name_adm0":"Polska",
    "qs_pg:name_adm1":"Dolnosl\u0105skie",
    "qs_pg:photos_9k":1,
    "qs_pg:photos_9r":1,
    "qs_pg:photos_all":2,
    "qs_pg:photos_sr":0,
    "qs_pg:pop_sr":2,
    "qs_pg:qs_pg_placetype":"locality",
    "qs_pg:qs_pg_placetype_gp":"Town",
    "qs_pg:woe_adm0":23424923,
    "woe:adm0_id":23424923,
    "woe:name_adm0":"Polska",
    "woe:name_adm1":"Dolnosl\u0105skie",
    "woe:placetype":"Town",
    "wof:coterminous":[
        1477752007
    ],
    "wof:name":"P\u0119c\u0142aw",
    "wof:placetype":"locality",
    "wof:population":496
},
  "geometry": {"coordinates":[16.24071,51.64247],"type":"Point"}
}