{
  "type": "Feature",
  "properties": {
    "gn:admin1_code":"86.0",
    "gn:admin2_code":"3062.0",
    "gn:admin3_code":"306201.0",
    "gn:asciiname":"Morzyslaw",
    "gn:country_code":"PL",
    "gn:dem":95,
    "gn:feature_class":"P",
    "gn:feature_code":"PPL",
    "gn:name":"Morzys\u0142aw",
    "gn:population":0,
    "gn:timezone":"Europe/Warsaw",
    "iso:country":"PL",
    "wof:name":"Morzyslaw",
    "wof:placetype":"locality"
},
  "geometry": {"coordinates":[18.28332,52.23172],"type":"Point"}
}