{
  "type": "Feature",
  "properties": {
    "gn:country":"PL",
    "gn:fcode":"PPL",
    "gn:population":172,
    "iso:country":"PL",
    "name:ast_x_preferred":[
        "Nowa Dzierz\u0105\u017cnia"
    ],
    "name:ceb_x_preferred":[
        "Nowa Dzierz\u0105\u017cnia"
    ],
    "name:eng_x_preferred":[
        "Nowa Dzierz\u0105\u017cnia"
    ],
    "name:fra_x_preferred":[
        "Nowa Dzierz\u0105\u017cnia"
    ],
    "name:pol_x_preferred":[
        "Nowa Dzierz\u0105\u017cnia"
    ],
    "name:ukr_x_preferred":[
        "\u041d\u043e\u0432\u0430 \u0414\u0437\u0435\u0436\u043e\u043d\u0436\u043d\u044f"
    ],
    "qs_pg:aaroncc":"PL",
    "qs_pg:gn_country":"PL",
    "qs_pg:gn_fcode":"PPL",
    "qs_pg:gn_pop":172,
    "qs_pg:name":"Nowa Dzierz\u0105\u017cnia",
    "qs_pg:photos_9r":0,
    "qs_pg:photos_sr":0,
    "qs_pg:pop_sr":1,
    "qs_pg:qs_pg_placetype":"locality",
    "wof:name":"Nowa Dzierz\u0105\u017cnia",
    "wof:placetype":"locality",
    "wof:population":172
},
  "geometry": {"coordinates":[20.20806,52.62113],"type":"Point"}
}