{
  "type": "Feature",
  "properties": {
    "gn:gn_country":"PL",
    "gn:gn_fcode":"PPL",
    "gn:gn_pop":662,
    "gn:population":662,
    "iso:country":"PL",
    "name:ceb_x_preferred":[
        "Kamionka"
    ],
    "name:deu_x_preferred":[
        "Kamionka"
    ],
    "name:fra_x_preferred":[
        "Kamionka"
    ],
    "name:lit_x_preferred":[
        "Kamionka"
    ],
    "name:pol_x_preferred":[
        "Kamionka"
    ],
    "name:swe_x_preferred":[
        "Kamionka"
    ],
    "name:ukr_x_preferred":[
        "\u041a\u0430\u043c\u0439\u043e\u043d\u043a\u0430"
    ],
    "qs_pg:aaroncc":"PL",
    "qs_pg:gn_country":"PL",
    "qs_pg:gn_fcode":"PPL",
    "qs_pg:gn_pop":662,
    "qs_pg:name":"Kamionka",
    "qs_pg:name_adm0":"Polska",
    "qs_pg:name_adm1":"Mazowieckie",
    "qs_pg:photos_9r":0,
    "qs_pg:photos_sr":0,
    "qs_pg:pop_sr":2,
    "qs_pg:qs_pg_placetype":"locality",
    "qs_pg:qs_pg_placetype_gp":"Town",
    "qs_pg:woe_adm0":23424923,
    "woe:adm0_id":23424923,
    "woe:name_adm0":"Polska",
    "woe:name_adm1":"Mazowieckie",
    "woe:placetype":"Town",
    "wof:name":"Kamionka",
    "wof:placetype":"locality",
    "wof:population":662
},
  "geometry": {"coordinates":[20.98166,52.05819],"type":"Point"}
}