{
  "type": "Feature",
  "properties": {
    "gn:admin1_code":"74.0",
    "gn:admin2_code":"1001.0",
    "gn:admin3_code":"100104.0",
    "gn:asciiname":"Karolow",
    "gn:country_code":"PL",
    "gn:dem":193,
    "gn:feature_class":"P",
    "gn:feature_code":"PPL",
    "gn:name":"Karol\u00f3w",
    "gn:population":0,
    "gn:timezone":"Europe/Warsaw",
    "iso:country":"PL",
    "name:fra_x_preferred":[
        "Karol\u00f3w"
    ],
    "name:pol_x_preferred":[
        "Karol\u00f3w"
    ],
    "name:ukr_x_preferred":[
        "\u041a\u0430\u0440\u043e\u043b\u044e\u0432"
    ],
    "wof:name":"Karolow",
    "wof:placetype":"locality"
},
  "geometry": {"coordinates":[19.23809,51.25579000000001],"type":"Point"}
}