{
  "type": "Feature",
  "properties": {
    "gn:admin1_code":"82.0",
    "gn:admin2_code":"2205.0",
    "gn:admin3_code":"220504.0",
    "gn:asciiname":"Mierucin",
    "gn:country_code":"PL",
    "gn:dem":195,
    "gn:feature_class":"P",
    "gn:feature_code":"PPL",
    "gn:name":"Mierucin",
    "gn:population":0,
    "gn:timezone":"Europe/Warsaw",
    "iso:country":"PL",
    "name:pol_x_preferred":[
        "Mierucin"
    ],
    "name:ukr_x_preferred":[
        "\u041c\u0435\u0440\u0443\u0446\u0438\u043d"
    ],
    "wof:name":"Mierucin",
    "wof:placetype":"locality"
},
  "geometry": {"coordinates":[17.71667,54.31667],"type":"Point"}
}