{
  "type": "Feature",
  "properties": {
    "gn:admin1_code":"73.0",
    "gn:admin2_code":"419.0",
    "gn:admin3_code":"41906.0",
    "gn:asciiname":"Murczyn",
    "gn:country_code":"PL",
    "gn:dem":99,
    "gn:feature_class":"P",
    "gn:feature_code":"PPL",
    "gn:name":"Murczyn",
    "gn:population":0,
    "gn:timezone":"Europe/Warsaw",
    "iso:country":"PL",
    "name:pol_x_preferred":[
        "Murczyn"
    ],
    "name:spa_x_preferred":[
        "Murczyn"
    ],
    "name:ukr_x_preferred":[
        "\u041c\u0443\u0440\u0447\u0438\u043d"
    ],
    "wof:name":"Murczyn",
    "wof:placetype":"locality"
},
  "geometry": {"coordinates":[17.79553,52.86856],"type":"Point"}
}