{
  "type": "Feature",
  "properties": {
    "gn:admin1_code":"82.0",
    "gn:admin2_code":"2211.0",
    "gn:admin3_code":"221107.0",
    "gn:asciiname":"Wielka Piasnica",
    "gn:cc2":"PL",
    "gn:country_code":"PL",
    "gn:dem":42,
    "gn:feature_class":"P",
    "gn:feature_code":"PPL",
    "gn:name":"Wielka Pia\u015bnica",
    "gn:population":0,
    "gn:timezone":"Europe/Warsaw",
    "iso:country":"PL",
    "name:und_x_variant":[
        "Pia\u015bnica Wielka",
        "Wielka Pia\u015bnica"
    ],
    "wof:name":"Wielka Piasnica",
    "wof:placetype":"locality"
},
  "geometry": {"coordinates":[18.19405,54.68475],"type":"Point"}
}