{
  "type": "Feature",
  "properties": {
    "gn:admin1_code":"82.0",
    "gn:admin2_code":"2211.0",
    "gn:admin3_code":"221107.0",
    "gn:asciiname":"Wielka Piasnica",
    "gn:cc2":"PL",
    "gn:country_code":"PL",
    "gn:dem":42,
    "gn:feature_class":"P",
    "gn:feature_code":"PPL",
    "gn:name":"Wielka Pia\u015bnica",
    "gn:population":0,
    "gn:timezone":"Europe/Warsaw",
    "iso:country":"PL",
    "name:azb_x_preferred":[
        "\u0648\u06cc\u0644\u06a9\u0627 \u067e\u06cc\u0627\u0634\u0646\u0642\u062a\u0633\u0627"
    ],
    "name:csb_x_preferred":[
        "Wi\u00f4lg\u00f4 Pi\u00f4sznica"
    ],
    "name:deu_x_preferred":[
        "Wielka Pia\u015bnica"
    ],
    "name:fas_x_preferred":[
        "\u0648\u06cc\u0644\u06a9\u0627 \u067e\u06cc\u0627\u0634\u0646\u06af\u062a\u0633\u0627"
    ],
    "name:nld_x_preferred":[
        "Wielka Pia\u015bnica"
    ],
    "name:pol_x_preferred":[
        "Wielka Pia\u015bnica"
    ],
    "name:rus_x_preferred":[
        "\u041f\u044f\u0448\u043d\u0438\u0446\u0430 \u0412\u0435\u043b\u044c\u043a\u0430"
    ],
    "name:swe_x_preferred":[
        "Pia\u015bnica"
    ],
    "name:ukr_x_preferred":[
        "\u0412\u0435\u043b\u0438\u043a\u0430 \u041f\u044f\u0441\u044c\u043d\u0438\u0446\u044f"
    ],
    "name:und_x_variant":[
        "Pia\u015bnica Wielka"
    ],
    "name:vie_x_preferred":[
        "Wielka Pia\u015bnica"
    ],
    "wof:name":"Wielka Piasnica",
    "wof:placetype":"locality"
},
  "geometry": {"coordinates":[18.19405,54.68475],"type":"Point"}
}