{
  "type": "Feature",
  "properties": {
    "gn:admin1_code":"78.0",
    "gn:admin2_code":"1404.0",
    "gn:admin3_code":"140403.0",
    "gn:asciiname":"Rakowiec",
    "gn:country_code":"PL",
    "gn:dem":93,
    "gn:feature_class":"P",
    "gn:feature_code":"PPL",
    "gn:name":"Rakowiec",
    "gn:population":0,
    "gn:timezone":"Europe/Warsaw",
    "iso:country":"PL",
    "name:fra_x_preferred":[
        "Rakowiec"
    ],
    "name:pol_x_preferred":[
        "Rakowiec"
    ],
    "wof:name":"Rakowiec",
    "wof:placetype":"locality"
},
  "geometry": {"coordinates":[19.64073,52.26446],"type":"Point"}
}