{
  "type": "Feature",
  "properties": {
    "gn:admin1_code":"78.0",
    "gn:admin2_code":"1420.0",
    "gn:admin3_code":"142010.0",
    "gn:asciiname":"Lempino",
    "gn:cc2":"PL",
    "gn:country_code":"PL",
    "gn:dem":107,
    "gn:feature_class":"P",
    "gn:feature_code":"PPL",
    "gn:name":"\u0141empino",
    "gn:population":0,
    "gn:timezone":"Europe/Warsaw",
    "iso:country":"PL",
    "name:fra_x_preferred":[
        "\u0141empino"
    ],
    "name:pol_x_preferred":[
        "\u0141empino"
    ],
    "name:ukr_x_preferred":[
        "\u041b\u0435\u043c\u043f\u0456\u043d\u043e"
    ],
    "name:und_x_variant":[
        "\u0141empin"
    ],
    "wof:name":"Lempino",
    "wof:placetype":"locality"
},
  "geometry": {"coordinates":[20.10241,52.76684],"type":"Point"}
}