{
  "type": "Feature",
  "properties": {
    "gn:admin1_code":"82.0",
    "gn:asciiname":"Janikow",
    "gn:country_code":"PL",
    "gn:dem":359,
    "gn:feature_class":"P",
    "gn:feature_code":"PPL",
    "gn:name":"Janik\u00f3w",
    "gn:population":0,
    "gn:timezone":"Europe/Warsaw",
    "iso:country":"PL",
    "wof:name":"Janikow",
    "wof:placetype":"locality"
},
  "geometry": {"coordinates":[16.41667,50.55],"type":"Point"}
}