{
  "type": "Feature",
  "properties": {
    "gn:admin1_code":"75.0",
    "gn:admin2_code":"612.0",
    "gn:admin3_code":"61207.0",
    "gn:asciiname":"Kepa Chotecka",
    "gn:country_code":"PL",
    "gn:dem":122,
    "gn:feature_class":"P",
    "gn:feature_code":"PPL",
    "gn:name":"K\u0119pa Chotecka",
    "gn:population":0,
    "gn:timezone":"Europe/Warsaw",
    "iso:country":"PL",
    "name:ceb_x_preferred":[
        "K\u0119pa Chotecka"
    ],
    "name:fra_x_preferred":[
        "K\u0119pa Chotecka"
    ],
    "name:pol_x_preferred":[
        "K\u0119pa Chotecka"
    ],
    "name:ukr_x_preferred":[
        "\u041a\u0435\u043c\u043f\u0430-\u0425\u043e\u0442\u0435\u0446\u044c\u043a\u0430"
    ],
    "wof:name":"Kepa Chotecka",
    "wof:placetype":"locality"
},
  "geometry": {"coordinates":[21.82846,51.2415],"type":"Point"}
}