{
  "type": "Feature",
  "properties": {
    "gn:admin1_code":"81.0",
    "gn:admin2_code":"2008.0",
    "gn:admin3_code":"200803.0",
    "gn:asciiname":"Mikicin",
    "gn:country_code":"PL",
    "gn:dem":126,
    "gn:feature_class":"P",
    "gn:feature_code":"PPL",
    "gn:name":"Mikicin",
    "gn:population":0,
    "gn:timezone":"Europe/Warsaw",
    "iso:country":"PL",
    "name:azb_x_preferred":[
        "\u0645\u06cc\u06a9\u06cc\u0686\u06cc\u0646"
    ],
    "name:ceb_x_preferred":[
        "Mikicin"
    ],
    "name:fas_x_preferred":[
        "\u0645\u06cc\u06a9\u06cc\u0686\u06cc\u0646"
    ],
    "name:fra_x_preferred":[
        "Mikicin"
    ],
    "name:lit_x_preferred":[
        "Mikicinas"
    ],
    "name:nld_x_preferred":[
        "Mikicin"
    ],
    "name:pol_x_preferred":[
        "Mikicin"
    ],
    "name:rus_x_preferred":[
        "\u041c\u0438\u043a\u0438\u0446\u0438\u043d"
    ],
    "name:ukr_x_preferred":[
        "\u041c\u0456\u043a\u0456\u0446\u0438\u043d"
    ],
    "wof:name":"Mikicin",
    "wof:placetype":"locality"
},
  "geometry": {"coordinates":[22.99337,53.51034],"type":"Point"}
}