{
  "type": "Feature",
  "properties": {
    "gn:admin1_code":"79.0",
    "gn:admin2_code":"1610.0",
    "gn:admin3_code":"161001.0",
    "gn:asciiname":"Nowa Wies Prudnicka",
    "gn:country_code":"PL",
    "gn:dem":195,
    "gn:feature_class":"P",
    "gn:feature_code":"PPL",
    "gn:name":"Nowa Wie\u015b Prudnicka",
    "gn:population":0,
    "gn:timezone":"Europe/Warsaw",
    "iso:country":"PL",
    "name:azb_x_preferred":[
        "\u0646\u0648\u0648\u0627 \u0648\u06cc\u0634 \u067e\u0631\u0648\u062f\u0646\u0642\u062a\u0633\u06a9\u0627"
    ],
    "name:deu_x_preferred":[
        "Neudorf"
    ],
    "name:fas_x_preferred":[
        "\u0646\u0648\u0648\u0627 \u0648\u06cc\u0634 \u067e\u0631\u0648\u062f\u0646\u06af\u062a\u0633\u06a9\u0627"
    ],
    "name:pol_x_preferred":[
        "Nowa Wie\u015b Prudnicka"
    ],
    "name:ukr_x_preferred":[
        "\u041d\u043e\u0432\u0430 \u0412\u0435\u0441\u044c-\u041f\u0440\u0443\u0434\u043d\u0456\u0446\u044c\u043a\u0430"
    ],
    "wof:name":"Nowa Wies Prudnicka",
    "wof:placetype":"locality"
},
  "geometry": {"coordinates":[17.75816,50.4057],"type":"Point"}
}