{
  "type": "Feature",
  "properties": {
    "gn:admin1_code":"79.0",
    "gn:admin2_code":"1610.0",
    "gn:admin3_code":"161001.0",
    "gn:asciiname":"Nowa Wies Prudnicka",
    "gn:country_code":"PL",
    "gn:dem":195,
    "gn:feature_class":"P",
    "gn:feature_code":"PPL",
    "gn:name":"Nowa Wie\u015b Prudnicka",
    "gn:population":0,
    "gn:timezone":"Europe/Warsaw",
    "iso:country":"PL",
    "name:und_x_variant":[
        "Nowa Wie\u015b Prudnicka"
    ],
    "wof:name":"Nowa Wies Prudnicka",
    "wof:placetype":"locality"
},
  "geometry": {"coordinates":[17.75816,50.4057],"type":"Point"}
}