{
  "type": "Feature",
  "properties": {
    "gn:admin1_code":"87.0",
    "gn:admin2_code":"3207.0",
    "gn:admin3_code":"320706.0",
    "gn:asciiname":"Unin",
    "gn:country_code":"PL",
    "gn:dem":4,
    "gn:feature_class":"P",
    "gn:feature_code":"PPL",
    "gn:name":"Unin",
    "gn:population":0,
    "gn:timezone":"Europe/Warsaw",
    "iso:country":"PL",
    "name:ceb_x_preferred":[
        "Unin"
    ],
    "name:pol_x_preferred":[
        "Unin"
    ],
    "name:ukr_x_preferred":[
        "\u0423\u043d\u0456\u043d"
    ],
    "wof:name":"Unin",
    "wof:placetype":"locality"
},
  "geometry": {"coordinates":[14.63199,53.89389],"type":"Point"}
}