{
  "type": "Feature",
  "properties": {
    "gn:admin1_code":"86.0",
    "gn:admin2_code":"3031.0",
    "gn:admin3_code":"303108.0",
    "gn:asciiname":"Skic",
    "gn:country_code":"PL",
    "gn:dem":108,
    "gn:feature_class":"P",
    "gn:feature_code":"PPL",
    "gn:name":"Skic",
    "gn:population":0,
    "gn:timezone":"Europe/Warsaw",
    "iso:country":"PL",
    "name:ceb_x_preferred":[
        "Skic"
    ],
    "name:fra_x_preferred":[
        "Skic"
    ],
    "name:pol_x_preferred":[
        "Skic"
    ],
    "name:ukr_x_preferred":[
        "\u0421\u043a\u0456\u0446\u044c"
    ],
    "wof:name":"Skic",
    "wof:placetype":"locality"
},
  "geometry": {"coordinates":[17.17249,53.31539],"type":"Point"}
}