{
  "type": "Feature",
  "properties": {
    "gn:admin1_code":"73.0",
    "gn:admin2_code":"462.0",
    "gn:admin3_code":"46201.0",
    "gn:asciiname":"Rzadz",
    "gn:country_code":"PL",
    "gn:dem":40,
    "gn:feature_class":"P",
    "gn:feature_code":"PPL",
    "gn:name":"Rz\u0105dz",
    "gn:population":0,
    "gn:timezone":"Europe/Warsaw",
    "iso:country":"PL",
    "name:und_x_variant":[
        "Rondsen",
        "Rondgen",
        "Rz\u0105dz"
    ],
    "wof:name":"Rzadz",
    "wof:placetype":"locality"
},
  "geometry": {"coordinates":[18.71738,53.45364],"type":"Point"}
}