{
  "type": "Feature",
  "properties": {
    "gn:admin1_code":"77.0",
    "gn:admin2_code":"1219.0",
    "gn:admin3_code":"121901.0",
    "gn:asciiname":"Zablocie",
    "gn:country_code":"PL",
    "gn:dem":269,
    "gn:feature_class":"P",
    "gn:feature_code":"PPL",
    "gn:name":"Zab\u0142ocie",
    "gn:population":0,
    "gn:timezone":"Europe/Warsaw",
    "iso:country":"PL",
    "name:fra_x_preferred":[
        "Zab\u0142ocie"
    ],
    "name:pol_x_preferred":[
        "Zab\u0142ocie"
    ],
    "name:ukr_x_preferred":[
        "\u0417\u0430\u0431\u043b\u043e\u0446\u0435"
    ],
    "name:urd_x_preferred":[
        "\u0636\u0627\u0628\u0648\u0627\u06a9\u06d2"
    ],
    "wof:name":"Zablocie",
    "wof:placetype":"locality"
},
  "geometry": {"coordinates":[20.1764,49.97318],"type":"Point"}
}