{
  "type": "Feature",
  "properties": {
    "gn:country":"PL",
    "gn:fcode":"PPL",
    "gn:population":487,
    "iso:country":"PL",
    "name:ceb_x_preferred":[
        "Ostrowice"
    ],
    "name:deu_x_preferred":[
        "Ostrowice"
    ],
    "name:pol_x_preferred":[
        "Ostrowice"
    ],
    "name:ukr_x_preferred":[
        "\u041e\u0441\u0442\u0440\u043e\u0432\u0456\u0446\u0435"
    ],
    "name:vie_x_preferred":[
        "Ostrowice"
    ],
    "qs_pg:aaroncc":"PL",
    "qs_pg:gn_country":"PL",
    "qs_pg:gn_fcode":"PPL",
    "qs_pg:gn_pop":487,
    "qs_pg:name":"Ostrowice",
    "qs_pg:name_adm0":"Polska",
    "qs_pg:name_adm1":"Zachodniopomorskie",
    "qs_pg:photos_9r":0,
    "qs_pg:photos_sr":0,
    "qs_pg:pop_sr":2,
    "qs_pg:qs_pg_placetype":"locality",
    "qs_pg:qs_pg_placetype_gp":"Town",
    "qs_pg:woe_adm0":23424923,
    "woe:adm0_id":23424923,
    "woe:name_adm0":"Polska",
    "woe:name_adm1":"Zachodniopomorskie",
    "woe:placetype":"Town",
    "wof:name":"Ostrowice",
    "wof:placetype":"locality",
    "wof:population":487
},
  "geometry": {"coordinates":[15.97652,53.63924],"type":"Point"}
}