{
  "type": "Feature",
  "properties": {
    "gn:country":"PL",
    "gn:fcode":"PPL",
    "gn:population":2054,
    "iso:country":"PL",
    "name:ast_x_preferred":[
        "Izdebnik"
    ],
    "name:azb_x_preferred":[
        "\u0627\u06cc\u0632\u062f\u0628\u0646\u0642\u06a9"
    ],
    "name:ceb_x_preferred":[
        "Izdebnik"
    ],
    "name:deu_x_preferred":[
        "Izdebnik"
    ],
    "name:eng_x_preferred":[
        "Izdebnik"
    ],
    "name:fas_x_preferred":[
        "\u0627\u06cc\u0632\u062f\u0628\u0646\u06af\u06a9"
    ],
    "name:fra_x_preferred":[
        "Izdebnik"
    ],
    "name:nld_x_preferred":[
        "Izdebnik"
    ],
    "name:pol_x_preferred":[
        "Izdebnik"
    ],
    "name:ukr_x_preferred":[
        "\u0406\u0437\u0434\u0435\u0431\u043d\u0438\u043a"
    ],
    "qs_pg:aaroncc":"PL",
    "qs_pg:gn_country":"PL",
    "qs_pg:gn_fcode":"PPL",
    "qs_pg:gn_pop":2054,
    "qs_pg:name":"Izdebnik",
    "qs_pg:name_adm0":"Polska",
    "qs_pg:name_adm1":"Ma\u0142opolskie",
    "qs_pg:photos_9k":1,
    "qs_pg:photos_9r":1,
    "qs_pg:photos_all":1,
    "qs_pg:photos_sr":0,
    "qs_pg:pop_sr":4,
    "qs_pg:qs_pg_placetype":"locality",
    "qs_pg:qs_pg_placetype_gp":"Town",
    "qs_pg:woe_adm0":23424923,
    "woe:adm0_id":23424923,
    "woe:name_adm0":"Polska",
    "woe:name_adm1":"Ma\u0142opolskie",
    "woe:placetype":"Town",
    "wof:name":"Izdebnik",
    "wof:placetype":"locality",
    "wof:population":2054
},
  "geometry": {"coordinates":[19.76801,49.87218],"type":"Point"}
}