{
  "type": "Feature",
  "properties": {
    "gn:admin1_code":"87.0",
    "gn:admin2_code":"3202.0",
    "gn:admin3_code":"320205.0",
    "gn:asciiname":"Nadarzyn",
    "gn:country_code":"PL",
    "gn:dem":46,
    "gn:feature_class":"P",
    "gn:feature_code":"PPL",
    "gn:name":"Nadarzyn",
    "gn:population":0,
    "gn:timezone":"Europe/Warsaw",
    "iso:country":"PL",
    "wof:name":"Nadarzyn",
    "wof:placetype":"locality"
},
  "geometry": {"coordinates":[15.32463,53.11761],"type":"Point"}
}