{
  "type": "Feature",
  "properties": {
    "iso:country":"PL",
    "name:eng_x_preferred":[
        "Chwaliszewo"
    ],
    "name:pol_x_preferred":[
        "Chwaliszewo"
    ],
    "wof:name":"Chwaliszewo",
    "wof:placetype":"neighbourhood"
},
  "geometry": {"coordinates":[16.94183964419363,52.40761948144742],"type":"Point"}
}