{
  "type": "Feature",
  "properties": {
    "gn:admin1_code":"78",
    "gn:admin2_code":"1438",
    "gn:admin3_code":"143802.0",
    "gn:asciiname":"Czekaj",
    "gn:country_code":"PL",
    "gn:dem":155,
    "gn:feature_class":"P",
    "gn:feature_code":"PPL",
    "gn:name":"Czekaj",
    "gn:population":0,
    "gn:timezone":"Europe/Warsaw",
    "iso:country":"PL",
    "name:deu_x_preferred":[
        "Czekaj"
    ],
    "name:fra_x_preferred":[
        "Czekaj"
    ],
    "name:pol_x_preferred":[
        "Czekaj"
    ],
    "name:ukr_x_preferred":[
        "\u0427\u0435\u043a\u0430\u0439"
    ],
    "wof:name":"Czekaj",
    "wof:placetype":"locality"
},
  "geometry": {"coordinates":[20.48869,51.98163],"type":"Point"}
}