{
  "type": "Feature",
  "properties": {
    "gn:admin1_code":"78.0",
    "gn:admin2_code":"1434.0",
    "gn:admin3_code":"143410.0",
    "gn:asciiname":"Zofinin",
    "gn:country_code":"PL",
    "gn:dem":122,
    "gn:feature_class":"P",
    "gn:feature_code":"PPL",
    "gn:name":"Zofinin",
    "gn:population":0,
    "gn:timezone":"Europe/Warsaw",
    "iso:country":"PL",
    "name:fra_x_preferred":[
        "Zofinin"
    ],
    "name:pol_x_preferred":[
        "Zofinin"
    ],
    "name:ukr_x_preferred":[
        "\u0417\u043e\u0444\u0456\u043d\u0456\u043d"
    ],
    "wof:name":"Zofinin",
    "wof:placetype":"locality"
},
  "geometry": {"coordinates":[21.65508,52.41268],"type":"Point"}
}