{
  "type": "Feature",
  "properties": {
    "gn:gn_country":"PL",
    "gn:gn_fcode":"PPL",
    "gn:gn_pop":883,
    "gn:population":883,
    "iso:country":"PL",
    "name:pol_x_preferred":[
        "Witniczka"
    ],
    "name:unk_x_variant":[
        "Vietnitz"
    ],
    "name:vie_x_preferred":[
        "Witniczka"
    ],
    "qs_pg:aaroncc":"PL",
    "qs_pg:gn_country":"PL",
    "qs_pg:gn_fcode":"PPL",
    "qs_pg:gn_pop":883,
    "qs_pg:name":"Witniczka",
    "qs_pg:name_adm0":"Polska",
    "qs_pg:name_adm1":"Zachodniopomorskie",
    "qs_pg:photos_9r":0,
    "qs_pg:photos_sr":0,
    "qs_pg:pop_sr":2,
    "qs_pg:qs_pg_placetype":"locality",
    "qs_pg:qs_pg_placetype_gp":"Town",
    "qs_pg:woe_adm0":23424923,
    "woe:adm0_id":23424923,
    "woe:name_adm0":"Polska",
    "woe:name_adm1":"Zachodniopomorskie",
    "woe:placetype":"Town",
    "wof:name":"Witniczka",
    "wof:placetype":"locality",
    "wof:population":883
},
  "geometry": {"coordinates":[14.47438,52.87052],"type":"Point"}
}