{
  "type": "Feature",
  "properties": {
    "gn:gn_country":"PL",
    "gn:gn_fcode":"PPLA3",
    "gn:gn_pop":29231,
    "gn:population":29231,
    "iso:country":"PL",
    "name:bel_x_preferred":[
        "\u0413\u043e\u0440\u0430\u0434 \u041a\u0440\u0430\u0442\u043e\u0448\u044b\u043d"
    ],
    "name:bul_x_preferred":[
        "\u041a\u0440\u043e\u0442\u043e\u0448\u0438\u043d"
    ],
    "name:lav_x_preferred":[
        "Kroto\u0161ina"
    ],
    "name:lit_x_preferred":[
        "Kroto\u0161ynas"
    ],
    "name:rus_x_preferred":[
        "\u041a\u0440\u043e\u0442\u043e\u0448\u0438\u043d"
    ],
    "name:srp_x_preferred":[
        "\u041a\u0440\u043e\u0442\u043e\u0448\u0438\u043d"
    ],
    "name:ukr_x_preferred":[
        "\u041a\u0440\u043e\u0442\u043e\u0448\u0438\u043d"
    ],
    "name:unk_x_variant":[
        "Krotoshin"
    ],
    "name:zho_x_preferred":[
        "\u514b\u7f85\u6258\u7533"
    ],
    "qs_pg:aaroncc":"PL",
    "qs_pg:gn_country":"PL",
    "qs_pg:gn_fcode":"PPLA3",
    "qs_pg:gn_pop":29231,
    "qs_pg:name":"Krotoszyn",
    "qs_pg:name_adm0":"Polska",
    "qs_pg:name_adm1":"Wielkopolskie",
    "qs_pg:photos":3,
    "qs_pg:photos_1k":1,
    "qs_pg:photos_9k":1,
    "qs_pg:photos_9r":1,
    "qs_pg:photos_all":3,
    "qs_pg:photos_sr":1,
    "qs_pg:pop_sr":7,
    "qs_pg:qs_pg_placetype":"localadmin",
    "qs_pg:qs_pg_placetype_gp":"LocalAdmin",
    "qs_pg:woe_adm0":23424923,
    "woe:adm0_id":23424923,
    "woe:name_adm0":"Polska",
    "woe:name_adm1":"Wielkopolskie",
    "woe:placetype":"LocalAdmin",
    "wof:name":"Krotoszyn",
    "wof:placetype":"localadmin",
    "wof:population":29231
},
  "geometry": {"coordinates":[17.43738,51.69868],"type":"Point"}
}