{
  "type": "Feature",
  "properties": {
    "gn:admin1_code":"84.0",
    "gn:admin2_code":"2609.0",
    "gn:admin3_code":"260905.0",
    "gn:asciiname":"Bazow",
    "gn:country_code":"PL",
    "gn:dem":172,
    "gn:feature_class":"P",
    "gn:feature_code":"PPL",
    "gn:name":"Ba\u017c\u00f3w",
    "gn:population":0,
    "gn:timezone":"Europe/Warsaw",
    "iso:country":"PL",
    "name:nld_x_preferred":[
        "Baz\u00f3w"
    ],
    "name:pol_x_preferred":[
        "Baz\u00f3w"
    ],
    "name:ukr_x_preferred":[
        "\u0411\u0430\u0437\u0443\u0432"
    ],
    "name:und_x_variant":[
        "Ba\u017c\u00f3w"
    ],
    "wof:name":"Bazow",
    "wof:placetype":"locality"
},
  "geometry": {"coordinates":[21.44829,50.59496],"type":"Point"}
}