{
  "type": "Feature",
  "properties": {
    "gn:country":"PL",
    "gn:fcode":"PPLA3",
    "gn:population":760,
    "iso:country":"PL",
    "name:cat_x_preferred":[
        "Nur"
    ],
    "name:ceb_x_preferred":[
        "Nur"
    ],
    "name:deu_x_preferred":[
        "Nur"
    ],
    "name:eng_x_preferred":[
        "Nur"
    ],
    "name:epo_x_preferred":[
        "Nur"
    ],
    "name:eus_x_preferred":[
        "Nur"
    ],
    "name:fra_x_preferred":[
        "Nur"
    ],
    "name:hye_x_preferred":[
        "\u0546\u0578\u0582\u0580"
    ],
    "name:nld_x_preferred":[
        "Nur"
    ],
    "name:por_x_preferred":[
        "Nur"
    ],
    "name:rus_x_preferred":[
        "\u041d\u0443\u0440"
    ],
    "name:swe_x_preferred":[
        "Nur"
    ],
    "name:tur_x_preferred":[
        "Nur"
    ],
    "name:ukr_x_preferred":[
        "\u041d\u0443\u0440"
    ],
    "name:uzb_x_preferred":[
        "Nur"
    ],
    "qs_pg:aaroncc":"PL",
    "qs_pg:gn_country":"PL",
    "qs_pg:gn_fcode":"PPLA3",
    "qs_pg:gn_pop":760,
    "qs_pg:name":"Nur",
    "qs_pg:name_adm0":"Polska",
    "qs_pg:name_adm1":"Mazowieckie",
    "qs_pg:photos":1,
    "qs_pg:photos_1k":1,
    "qs_pg:photos_9k":1,
    "qs_pg:photos_9r":1,
    "qs_pg:photos_all":1,
    "qs_pg:photos_sr":1,
    "qs_pg:pop_sr":2,
    "qs_pg:qs_pg_placetype":"localadmin",
    "qs_pg:qs_pg_placetype_gp":"LocalAdmin",
    "qs_pg:woe_adm0":23424923,
    "woe:adm0_id":23424923,
    "woe:name_adm0":"Polska",
    "woe:name_adm1":"Mazowieckie",
    "woe:placetype":"LocalAdmin",
    "wof:name":"Nur",
    "wof:placetype":"localadmin",
    "wof:population":760
},
  "geometry": {"coordinates":[22.32207,52.66826],"type":"Point"}
}