{
  "type": "Feature",
  "properties": {
    "gn:country":"PL",
    "gn:fcode":"PPL",
    "gn:population":1300,
    "iso:country":"PL",
    "name:ast_x_preferred":[
        "Ostrowite"
    ],
    "name:eng_x_preferred":[
        "Ostrowite"
    ],
    "name:fra_x_preferred":[
        "Ostrowite"
    ],
    "name:pol_x_preferred":[
        "Ostrowite"
    ],
    "name:rus_x_preferred":[
        "\u041e\u0441\u0442\u0440\u043e\u0432\u0438\u0442\u0435"
    ],
    "name:ukr_x_preferred":[
        "\u041e\u0441\u0442\u0440\u043e\u0432\u0456\u0442\u0435"
    ],
    "qs:a0":"Rzeczpospolita Polska",
    "qs:a1":"*Kujawsko-pomorskie",
    "qs:a1r":"0",
    "qs:a2":"Rypinski",
    "qs:adm0":"Rzeczpospolita Polska",
    "qs:la_lc":"*",
    "qs:level":"locality",
    "qs:loc":"Ostrowite",
    "qs:loc_alt":"Ostrowite",
    "qs:pop":0,
    "qs:type":"buffered point",
    "qs_pg:aaroncc":"PL",
    "qs_pg:gn_country":"PL",
    "qs_pg:gn_fcode":"PPL",
    "qs_pg:gn_pop":1300,
    "qs_pg:name":"Ostrowite",
    "qs_pg:name_adm0":"Polska",
    "qs_pg:name_adm1":"Kujawsko-Pomorskie",
    "qs_pg:photos_9r":0,
    "qs_pg:photos_sr":0,
    "qs_pg:pop_sr":3,
    "qs_pg:qs_pg_placetype":"locality",
    "qs_pg:qs_pg_placetype_gp":"Town",
    "qs_pg:woe_adm0":23424923,
    "wd:wordcount":90,
    "wof:name":"Ostrowite",
    "wof:placetype":"locality",
    "wof:population":1300
},
  "geometry": {"coordinates":[19.289667,53.066971],"type":"Point"}
}