{
  "type": "Feature",
  "properties": {
    "gn:admin1_code":"73.0",
    "gn:admin2_code":"412.0",
    "gn:admin3_code":"41202.0",
    "gn:asciiname":"Laczonek",
    "gn:country_code":"PL",
    "gn:dem":121,
    "gn:feature_class":"P",
    "gn:feature_code":"PPL",
    "gn:name":"\u0141\u0105czonek",
    "gn:population":0,
    "gn:timezone":"Europe/Warsaw",
    "iso:country":"PL",
    "name:fra_x_preferred":[
        "\u0141\u0105czonek"
    ],
    "name:pol_x_preferred":[
        "\u0141\u0105czonek"
    ],
    "name:ukr_x_preferred":[
        "\u041b\u043e\u043d\u0447\u043e\u043d\u0435\u043a"
    ],
    "wof:name":"Laczonek",
    "wof:placetype":"locality"
},
  "geometry": {"coordinates":[19.31219,53.07706],"type":"Point"}
}