{
  "type": "Feature",
  "properties": {
    "gn:country":"PL",
    "gn:fcode":"PPLA3",
    "gn:population":831,
    "iso:country":"PL",
    "name:ast_x_preferred":[
        "Lutocin"
    ],
    "name:ceb_x_preferred":[
        "Lutocin"
    ],
    "name:deu_x_preferred":[
        "Lutocin"
    ],
    "name:eng_x_preferred":[
        "Lutocin"
    ],
    "name:fas_x_preferred":[
        "\u0644\u0648\u062a\u0648\u0686\u06cc\u0646"
    ],
    "name:fra_x_preferred":[
        "Lutocin"
    ],
    "name:nan_x_preferred":[
        "Lutocin"
    ],
    "name:nld_x_preferred":[
        "Lutocin"
    ],
    "name:pol_x_preferred":[
        "Lutocin"
    ],
    "name:ukr_x_preferred":[
        "\u041b\u044e\u0442\u043e\u0446\u0438\u043d"
    ],
    "qs_pg:aaroncc":"PL",
    "qs_pg:gn_country":"PL",
    "qs_pg:gn_fcode":"PPLA3",
    "qs_pg:gn_pop":831,
    "qs_pg:name":"Lutocin",
    "qs_pg:photos_9r":0,
    "qs_pg:photos_sr":0,
    "qs_pg:pop_sr":2,
    "qs_pg:qs_pg_placetype":"locality",
    "wof:name":"Lutocin",
    "wof:placetype":"locality",
    "wof:population":831
},
  "geometry": {"coordinates":[19.76655,52.98152],"type":"Point"}
}