{
  "type": "Feature",
  "properties": {
    "gn:admin1_code":"74.0",
    "gn:admin2_code":"1002.0",
    "gn:admin3_code":"100204.0",
    "gn:asciiname":"Szubsk Towarzystwo",
    "gn:country_code":"PL",
    "gn:dem":119,
    "gn:feature_class":"P",
    "gn:feature_code":"PPL",
    "gn:name":"Szubsk Towarzystwo",
    "gn:population":0,
    "gn:timezone":"Europe/Warsaw",
    "iso:country":"PL",
    "name:fra_x_preferred":[
        "Szubsk-Towarzystwo"
    ],
    "name:pol_x_preferred":[
        "Szubsk-Towarzystwo"
    ],
    "wof:name":"Szubsk Towarzystwo",
    "wof:placetype":"locality"
},
  "geometry": {"coordinates":[19.23849,52.21486],"type":"Point"}
}