{
  "type": "Feature",
  "properties": {
    "iso:country":"PL",
    "name:pol_x_preferred":[
        "Kobylnica"
    ],
    "wof:coterminous":[
        1125307905
    ],
    "wof:name":"Kobylnica",
    "wof:placetype":"locality"
},
  "geometry": {"coordinates":[16.9629264628489,54.3747187369319],"type":"Point"}
}