{
  "type": "Feature",
  "properties": {
    "iso:country":"PL",
    "name:ceb_x_preferred":[
        "Kobylnica"
    ],
    "name:deu_x_preferred":[
        "Kobylnica"
    ],
    "name:fra_x_preferred":[
        "Kobylnica"
    ],
    "name:nld_x_preferred":[
        "Kobylnica"
    ],
    "name:pol_x_preferred":[
        "Kobylnica"
    ],
    "name:ukr_x_preferred":[
        "\u041a\u043e\u0431\u0438\u043b\u044c\u043d\u0438\u0446\u044f"
    ],
    "wof:coterminous":[
        1125307905
    ],
    "wof:name":"Kobylnica",
    "wof:placetype":"locality"
},
  "geometry": {"coordinates":[16.9629264628489,54.3747187369319],"type":"Point"}
}