{
  "type": "Feature",
  "properties": {
    "gn:admin1_code":"75.0",
    "gn:admin2_code":"606.0",
    "gn:admin3_code":"60603.0",
    "gn:asciiname":"Bobrowe",
    "gn:country_code":"PL",
    "gn:dem":223,
    "gn:feature_class":"P",
    "gn:feature_code":"PPL",
    "gn:name":"Bobrowe",
    "gn:population":0,
    "gn:timezone":"Europe/Warsaw",
    "iso:country":"PL",
    "name:fra_x_preferred":[
        "Bobrowe"
    ],
    "name:pol_x_preferred":[
        "Bobrowe"
    ],
    "name:ukr_x_preferred":[
        "\u0411\u043e\u0431\u0440\u043e\u0432\u0435"
    ],
    "wof:name":"Bobrowe",
    "wof:placetype":"locality"
},
  "geometry": {"coordinates":[22.995,50.98083],"type":"Point"}
}