{
  "type": "Feature",
  "properties": {
    "gn:admin1_code":"87.0",
    "gn:admin2_code":"3210.0",
    "gn:admin3_code":"321004.0",
    "gn:asciiname":"Kruszwin",
    "gn:country_code":"PL",
    "gn:dem":64,
    "gn:feature_class":"P",
    "gn:feature_code":"PPL",
    "gn:name":"Kruszwin",
    "gn:population":0,
    "gn:timezone":"Europe/Warsaw",
    "iso:country":"PL",
    "name:pol_x_preferred":[
        "Kruszwin"
    ],
    "name:tur_x_preferred":[
        "Kruszwin"
    ],
    "name:ukr_x_preferred":[
        "\u041a\u0440\u0443\u0448\u0432\u0456\u043d"
    ],
    "name:und_x_variant":[
        "Simonsdorf"
    ],
    "wof:name":"Kruszwin",
    "wof:placetype":"locality"
},
  "geometry": {"coordinates":[14.83958,52.94873000000001],"type":"Point"}
}