{
  "type": "Feature",
  "properties": {
    "gn:admin1_code":"80.0",
    "gn:admin2_code":"1803.0",
    "gn:admin3_code":"180307.0",
    "gn:asciiname":"Swiercze",
    "gn:country_code":"PL",
    "gn:dem":214,
    "gn:feature_class":"P",
    "gn:feature_code":"PPL",
    "gn:name":"\u015awiercze",
    "gn:population":0,
    "gn:timezone":"Europe/Warsaw",
    "iso:country":"PL",
    "wof:name":"Swiercze",
    "wof:placetype":"locality"
},
  "geometry": {"coordinates":[21.32667,50.07724],"type":"Point"}
}