{
  "type": "Feature",
  "properties": {
    "gn:admin1_code":"77.0",
    "gn:admin2_code":"1212.0",
    "gn:admin3_code":"121207.0",
    "gn:asciiname":"Boza Wola",
    "gn:country_code":"PL",
    "gn:dem":408,
    "gn:feature_class":"P",
    "gn:feature_code":"PPL",
    "gn:name":"Bo\u017ca Wola",
    "gn:population":0,
    "gn:timezone":"Europe/Warsaw",
    "iso:country":"PL",
    "name:pol_x_preferred":[
        "Bo\u017ca Wola"
    ],
    "name:ukr_x_preferred":[
        "\u0411\u043e\u0436\u0430-\u0412\u043e\u043b\u044f"
    ],
    "wof:name":"Boza Wola",
    "wof:placetype":"locality"
},
  "geometry": {"coordinates":[19.79662,50.41917],"type":"Point"}
}