{
  "type": "Feature",
  "properties": {
    "gn:admin1_code":"78.0",
    "gn:admin2_code":"1438.0",
    "gn:admin3_code":"143805.0",
    "gn:asciiname":"Tomaszew Nowy",
    "gn:country_code":"PL",
    "gn:dem":99,
    "gn:feature_class":"P",
    "gn:feature_code":"PPL",
    "gn:name":"Tomaszew Nowy",
    "gn:population":0,
    "gn:timezone":"Europe/Warsaw",
    "iso:country":"PL",
    "wof:name":"Tomaszew Nowy",
    "wof:placetype":"locality"
},
  "geometry": {"coordinates":[20.35,52.06667],"type":"Point"}
}