{
  "type": "Feature",
  "properties": {
    "gn:admin1_code":"85",
    "gn:admin2_code":"2808",
    "gn:admin3_code":"280804.0",
    "gn:asciiname":"Podgorzyn",
    "gn:country_code":"PL",
    "gn:dem":46,
    "gn:feature_class":"P",
    "gn:feature_code":"PPL",
    "gn:name":"Podg\u00f3rzyn",
    "gn:population":0,
    "gn:timezone":"Europe/Warsaw",
    "iso:country":"PL",
    "name:deu_x_historical":[
        "Lumienen"
    ],
    "name:deu_x_preferred":[
        "Lumienen"
    ],
    "name:deu_x_variant":[
        "Podg\u00f3rzyn"
    ],
    "name:pol_x_preferred":[
        "Podg\u00f3rzyn"
    ],
    "wof:name":"Podgorzyn",
    "wof:placetype":"locality"
},
  "geometry": {"coordinates":[21.25164,54.14921999999999],"type":"Point"}
}