{
  "type": "Feature",
  "properties": {
    "gn:admin1_code":"81.0",
    "gn:admin2_code":"2004.0",
    "gn:admin3_code":"200402.0",
    "gn:asciiname":"Okol",
    "gn:country_code":"PL",
    "gn:dem":122,
    "gn:feature_class":"P",
    "gn:feature_code":"PPL",
    "gn:name":"Ok\u00f3\u0142",
    "gn:population":0,
    "gn:timezone":"Europe/Warsaw",
    "iso:country":"PL",
    "name:fra_x_preferred":[
        "Ok\u00f3\u0142"
    ],
    "name:lit_x_preferred":[
        "Okulas"
    ],
    "name:pol_x_preferred":[
        "Ok\u00f3\u0142"
    ],
    "name:ukr_x_preferred":[
        "\u041e\u043a\u0443\u043b"
    ],
    "name:und_x_variant":[
        "Ok\u00f3\u0142"
    ],
    "wof:name":"Okol",
    "wof:placetype":"locality"
},
  "geometry": {"coordinates":[22.47951,53.56836],"type":"Point"}
}