{
  "type": "Feature",
  "properties": {
    "gn:admin1_code":"74.0",
    "gn:admin2_code":"1016.0",
    "gn:admin3_code":"101606.0",
    "gn:asciiname":"Dabrowa",
    "gn:country_code":"PL",
    "gn:dem":176,
    "gn:feature_class":"P",
    "gn:feature_code":"PPL",
    "gn:name":"D\u0105browa",
    "gn:population":0,
    "gn:timezone":"Europe/Warsaw",
    "iso:country":"PL",
    "wof:name":"Dabrowa",
    "wof:placetype":"locality"
},
  "geometry": {"coordinates":[20.10458,51.56678],"type":"Point"}
}