{
  "type": "Feature",
  "properties": {
    "gn:admin1_code":"78.0",
    "gn:admin2_code":"1432.0",
    "gn:admin3_code":"143203.0",
    "gn:asciiname":"Szczytno",
    "gn:country_code":"PL",
    "gn:dem":86,
    "gn:feature_class":"P",
    "gn:feature_code":"PPL",
    "gn:name":"Szczytno",
    "gn:population":0,
    "gn:timezone":"Europe/Warsaw",
    "iso:country":"PL",
    "name:ceb_x_preferred":[
        "Szczytno"
    ],
    "name:fra_x_preferred":[
        "Szczytno"
    ],
    "name:pol_x_preferred":[
        "Szczytno"
    ],
    "name:rus_x_preferred":[
        "\u0429\u0438\u0442\u043d\u043e"
    ],
    "name:ukr_x_preferred":[
        "\u0429\u0438\u0442\u043d\u043e"
    ],
    "wof:name":"Szczytno",
    "wof:placetype":"locality"
},
  "geometry": {"coordinates":[20.35449,52.24919000000001],"type":"Point"}
}