{
  "type": "Feature",
  "properties": {
    "gn:country":"PL",
    "gn:fcode":"PPL",
    "gn:population":501,
    "iso:country":"PL",
    "name:ast_x_preferred":[
        "Hrebenne"
    ],
    "name:ceb_x_preferred":[
        "Hrebenne"
    ],
    "name:eng_x_preferred":[
        "Hrebenne"
    ],
    "name:fra_x_preferred":[
        "Hrebenne"
    ],
    "name:pol_x_preferred":[
        "Hrebenne"
    ],
    "name:ukr_x_preferred":[
        "\u0413\u0440\u0435\u0431\u0435\u043d\u043d\u0435"
    ],
    "qs_pg:aaroncc":"PL",
    "qs_pg:gn_country":"PL",
    "qs_pg:gn_fcode":"PPL",
    "qs_pg:gn_pop":501,
    "qs_pg:name":"Hrebenne",
    "qs_pg:name_adm0":"Polska",
    "qs_pg:name_adm1":"Lubelskie",
    "qs_pg:photos_9r":0,
    "qs_pg:photos_sr":0,
    "qs_pg:pop_sr":2,
    "qs_pg:qs_pg_placetype":"locality",
    "qs_pg:qs_pg_placetype_gp":"Town",
    "qs_pg:woe_adm0":23424923,
    "woe:adm0_id":23424923,
    "woe:name_adm0":"Polska",
    "woe:name_adm1":"Lubelskie",
    "woe:placetype":"Town",
    "wof:name":"Hrebenne",
    "wof:placetype":"locality",
    "wof:population":501
},
  "geometry": {"coordinates":[24.01431,50.8732],"type":"Point"}
}