{
  "type": "Feature",
  "properties": {
    "gn:admin1_code":"79.0",
    "gn:admin2_code":"1601.0",
    "gn:admin3_code":"160102.0",
    "gn:asciiname":"Zielecice",
    "gn:country_code":"PL",
    "gn:dem":148,
    "gn:feature_class":"P",
    "gn:feature_code":"PPL",
    "gn:name":"Ziel\u0119cice",
    "gn:population":0,
    "gn:timezone":"Europe/Warsaw",
    "iso:country":"PL",
    "name:deu_x_historical":[
        "Gr\u00fcningen"
    ],
    "name:deu_x_preferred":[
        "Gr\u00fcningen"
    ],
    "wof:name":"Zielecice",
    "wof:placetype":"locality"
},
  "geometry": {"coordinates":[17.4135,50.86784],"type":"Point"}
}