{
  "type": "Feature",
  "properties": {
    "gn:admin1_code":"83.0",
    "gn:admin2_code":"2416.0",
    "gn:admin3_code":"241601.0",
    "gn:asciiname":"Dziechciarze",
    "gn:country_code":"PL",
    "gn:dem":308,
    "gn:feature_class":"P",
    "gn:feature_code":"PPL",
    "gn:name":"Dziechciarze",
    "gn:population":0,
    "gn:timezone":"Europe/Warsaw",
    "iso:country":"PL",
    "wof:name":"Dziechciarze",
    "wof:placetype":"locality"
},
  "geometry": {"coordinates":[19.31542,50.49162000000001],"type":"Point"}
}