{
  "type": "Feature",
  "properties": {
    "gn:admin1_code":"81.0",
    "gn:admin2_code":"2012.0",
    "gn:admin3_code":"201205.0",
    "gn:asciiname":"Rabalina",
    "gn:country_code":"PL",
    "gn:dem":166,
    "gn:feature_class":"P",
    "gn:feature_code":"PPL",
    "gn:name":"Rabalina",
    "gn:population":0,
    "gn:timezone":"Europe/Warsaw",
    "iso:country":"PL",
    "name:lit_x_preferred":[
        "Rabalina"
    ],
    "name:pol_x_preferred":[
        "Rabalina"
    ],
    "name:ukr_x_preferred":[
        "\u0420\u0430\u0431\u0430\u043b\u0456\u043d\u0430"
    ],
    "name:und_x_variant":[
        "Rabalin"
    ],
    "wof:name":"Rabalina",
    "wof:placetype":"locality"
},
  "geometry": {"coordinates":[22.73804,54.03854000000001],"type":"Point"}
}