{
  "type": "Feature",
  "properties": {
    "gn:admin1_code":"72.0",
    "gn:admin2_code":"211.0",
    "gn:admin3_code":"21104.0",
    "gn:asciiname":"Dluzyce",
    "gn:country_code":"PL",
    "gn:dem":107,
    "gn:feature_class":"P",
    "gn:feature_code":"PPL",
    "gn:name":"D\u0142u\u017cyce",
    "gn:population":0,
    "gn:timezone":"Europe/Warsaw",
    "iso:country":"PL",
    "name:azb_x_preferred":[
        "\u062f\u0648\u0648\u0698\u062a\u0633\u0647"
    ],
    "name:ceb_x_preferred":[
        "D\u0142u\u017cyce"
    ],
    "name:deu_x_historical":[
        "Gro\u00dfendorf"
    ],
    "name:deu_x_preferred":[
        "Gro\u00dfendorf"
    ],
    "name:fas_x_preferred":[
        "\u062f\u0648\u0648\u0698\u062a\u0633\u0647"
    ],
    "name:nld_x_preferred":[
        "D\u0142u\u017cyce"
    ],
    "name:pol_x_preferred":[
        "D\u0142u\u017cyce"
    ],
    "name:ukr_x_preferred":[
        "\u0414\u043b\u0443\u0436\u0438\u0446\u0435"
    ],
    "wof:name":"Dluzyce",
    "wof:placetype":"locality"
},
  "geometry": {"coordinates":[16.44027,51.37441],"type":"Point"}
}