{
  "type": "Feature",
  "properties": {
    "gn:admin1_code":"87.0",
    "gn:admin2_code":"3201.0",
    "gn:admin3_code":"320103.0",
    "gn:asciiname":"Kowancz",
    "gn:country_code":"PL",
    "gn:dem":26,
    "gn:feature_class":"P",
    "gn:feature_code":"PPL",
    "gn:name":"Kowa\u0144cz",
    "gn:population":0,
    "gn:timezone":"Europe/Warsaw",
    "iso:country":"PL",
    "name:deu_x_preferred":[
        "Kowa\u0144cz"
    ],
    "name:pol_x_preferred":[
        "Kowa\u0144cz"
    ],
    "name:ukr_x_preferred":[
        "\u041a\u043e\u0432\u0430\u043d\u044c\u0447"
    ],
    "name:vie_x_preferred":[
        "Kowa\u0144cz"
    ],
    "wof:name":"Kowancz",
    "wof:placetype":"locality"
},
  "geometry": {"coordinates":[15.83978,54.03659],"type":"Point"}
}