{
  "type": "Feature",
  "properties": {
    "gn:admin1_code":"85.0",
    "gn:admin2_code":"2804.0",
    "gn:admin3_code":"280406.0",
    "gn:asciiname":"Kraskowo",
    "gn:country_code":"PL",
    "gn:dem":31,
    "gn:feature_class":"P",
    "gn:feature_code":"PPL",
    "gn:name":"Kraskowo",
    "gn:population":0,
    "gn:timezone":"Europe/Warsaw",
    "iso:country":"PL",
    "name:pol_x_preferred":[
        "Kraskowo"
    ],
    "name:ukr_x_preferred":[
        "\u041a\u0440\u0430\u0441\u043a\u043e\u0432\u043e"
    ],
    "name:und_x_variant":[
        "Sch\u00f6nfliess"
    ],
    "wof:name":"Kraskowo",
    "wof:placetype":"locality"
},
  "geometry": {"coordinates":[19.74058,54.22125],"type":"Point"}
}