{
  "type": "Feature",
  "properties": {
    "gn:admin1_code":"73.0",
    "gn:admin2_code":"403.0",
    "gn:admin3_code":"40304.0",
    "gn:asciiname":"Salno",
    "gn:country_code":"PL",
    "gn:dem":112,
    "gn:feature_class":"P",
    "gn:feature_code":"PPL",
    "gn:name":"Salno",
    "gn:population":0,
    "gn:timezone":"Europe/Warsaw",
    "iso:country":"PL",
    "name:ita_x_preferred":[
        "Salno"
    ],
    "name:nld_x_preferred":[
        "Salno"
    ],
    "name:pol_x_preferred":[
        "Salno"
    ],
    "name:ukr_x_preferred":[
        "\u0421\u0430\u043b\u044c\u043d\u043e"
    ],
    "wof:name":"Salno",
    "wof:placetype":"locality"
},
  "geometry": {"coordinates":[17.85287000000001,53.29261999999999],"type":"Point"}
}