{
  "type": "Feature",
  "properties": {
    "gn:country":"PL",
    "gn:fcode":"PPL",
    "gn:population":750,
    "iso:country":"PL",
    "name:ast_x_preferred":[
        "Dobra"
    ],
    "name:azb_x_preferred":[
        "\u062f\u0648\u0628\u0631\u0627"
    ],
    "name:ceb_x_preferred":[
        "Dobra"
    ],
    "name:deu_x_preferred":[
        "Dobrau"
    ],
    "name:eng_x_preferred":[
        "Dobra"
    ],
    "name:fas_x_preferred":[
        "\u062f\u0648\u0628\u0631\u0627"
    ],
    "name:fra_x_preferred":[
        "Dobra"
    ],
    "name:nan_x_preferred":[
        "Dobra"
    ],
    "name:pol_x_preferred":[
        "Dobra"
    ],
    "name:ukr_x_preferred":[
        "\u0414\u043e\u0431\u0440\u0430"
    ],
    "qs_pg:aaroncc":"PL",
    "qs_pg:gn_country":"PL",
    "qs_pg:gn_fcode":"PPL",
    "qs_pg:gn_pop":750,
    "qs_pg:name":"Dobra",
    "qs_pg:name_adm0":"Polska",
    "qs_pg:name_adm1":"Opolskie",
    "qs_pg:photos_9k":1,
    "qs_pg:photos_9r":1,
    "qs_pg:photos_all":1,
    "qs_pg:photos_sr":0,
    "qs_pg:pop_sr":2,
    "qs_pg:qs_pg_placetype":"locality",
    "qs_pg:qs_pg_placetype_gp":"Town",
    "qs_pg:woe_adm0":23424923,
    "woe:adm0_id":23424923,
    "woe:name_adm0":"Polska",
    "woe:name_adm1":"Opolskie",
    "woe:placetype":"Town",
    "wof:name":"Dobra",
    "wof:placetype":"locality",
    "wof:population":750
},
  "geometry": {"coordinates":[17.90737,50.45177],"type":"Point"}
}