{
  "type": "Feature",
  "properties": {
    "gn:admin1_code":"77.0",
    "gn:admin2_code":"1219.0",
    "gn:admin3_code":"121902.0",
    "gn:asciiname":"Stryszowa",
    "gn:country_code":"PL",
    "gn:dem":324,
    "gn:feature_class":"P",
    "gn:feature_code":"PPL",
    "gn:name":"Stryszowa",
    "gn:population":0,
    "gn:timezone":"Europe/Warsaw",
    "iso:country":"PL",
    "name:ceb_x_preferred":[
        "Stryszowa"
    ],
    "name:pol_x_preferred":[
        "Stryszowa"
    ],
    "name:ukr_x_preferred":[
        "\u0421\u0442\u0440\u0438\u0448\u043e\u0432\u0430"
    ],
    "wof:name":"Stryszowa",
    "wof:placetype":"locality"
},
  "geometry": {"coordinates":[20.18789,49.88446],"type":"Point"}
}