{
  "type": "Feature",
  "properties": {
    "gn:admin1_code":"83.0",
    "gn:admin2_code":"2404.0",
    "gn:admin3_code":"240403.0",
    "gn:asciiname":"Teodorow",
    "gn:country_code":"PL",
    "gn:dem":254,
    "gn:feature_class":"P",
    "gn:feature_code":"PPL",
    "gn:name":"Teodor\u00f3w",
    "gn:population":0,
    "gn:timezone":"Europe/Warsaw",
    "iso:country":"PL",
    "wof:name":"Teodorow",
    "wof:placetype":"locality"
},
  "geometry": {"coordinates":[19.56033,50.72946],"type":"Point"}
}