{
  "type": "Feature",
  "properties": {
    "gn:admin1_code":"84.0",
    "gn:admin2_code":"2609.0",
    "gn:admin3_code":"260903.0",
    "gn:asciiname":"Gozlice",
    "gn:country_code":"PL",
    "gn:dem":266,
    "gn:feature_class":"P",
    "gn:feature_code":"PPL",
    "gn:name":"Go\u017clice",
    "gn:population":0,
    "gn:timezone":"Europe/Warsaw",
    "iso:country":"PL",
    "name:pol_x_preferred":[
        "Go\u017alice"
    ],
    "name:ukr_x_preferred":[
        "\u0490\u043e\u0437\u043b\u0456\u0446\u0435"
    ],
    "wof:name":"Gozlice",
    "wof:placetype":"locality"
},
  "geometry": {"coordinates":[21.47741,50.69711],"type":"Point"}
}