{
  "type": "Feature",
  "properties": {
    "gn:admin1_code":"82.0",
    "gn:admin2_code":"2214.0",
    "gn:admin3_code":"221404.0",
    "gn:asciiname":"Rozental",
    "gn:country_code":"PL",
    "gn:dem":48,
    "gn:feature_class":"P",
    "gn:feature_code":"PPL",
    "gn:name":"Ro\u017cental",
    "gn:population":0,
    "gn:timezone":"Europe/Warsaw",
    "iso:country":"PL",
    "name:und_x_variant":[
        "Ro\u017cental"
    ],
    "wof:name":"Rozental",
    "wof:placetype":"locality"
},
  "geometry": {"coordinates":[18.68943,53.91082],"type":"Point"}
}