{
  "type": "Feature",
  "properties": {
    "gn:admin1_code":"86.0",
    "gn:admin2_code":"3003.0",
    "gn:admin3_code":"300303.0",
    "gn:asciiname":"Strzyzewo Smykowe",
    "gn:country_code":"PL",
    "gn:dem":110,
    "gn:feature_class":"P",
    "gn:feature_code":"PPL",
    "gn:name":"Strzy\u017cewo Smykowe",
    "gn:population":0,
    "gn:timezone":"Europe/Warsaw",
    "iso:country":"PL",
    "name:azb_x_preferred":[
        "\u0633\u062a\u0698\u0698\u0648\u0648 \u0633\u0645\u06a9\u0648\u0648\u0647"
    ],
    "name:fas_x_preferred":[
        "\u0633\u062a\u0698\u0698\u0648\u0648 \u0633\u0645\u06a9\u0648\u0648\u0647"
    ],
    "name:fra_x_preferred":[
        "Strzy\u017cewo Smykowe"
    ],
    "name:pol_x_preferred":[
        "Strzy\u017cewo Smykowe"
    ],
    "name:ukr_x_preferred":[
        "\u0421\u0442\u0448\u0438\u0436\u0435\u0432\u043e-\u0421\u043c\u0438\u043a\u043e\u0432\u0435"
    ],
    "wof:name":"Strzyzewo Smykowe",
    "wof:placetype":"locality"
},
  "geometry": {"coordinates":[17.69683,52.59083],"type":"Point"}
}