{
  "type": "Feature",
  "properties": {
    "gn:admin1_code":"84.0",
    "gn:admin2_code":"2604.0",
    "gn:admin3_code":"260404.0",
    "gn:asciiname":"Sladkow Maly",
    "gn:country_code":"PL",
    "gn:dem":225,
    "gn:feature_class":"P",
    "gn:feature_code":"PPL",
    "gn:name":"\u015aladk\u00f3w Ma\u0142y",
    "gn:population":0,
    "gn:timezone":"Europe/Warsaw",
    "iso:country":"PL",
    "name:ceb_x_preferred":[
        "\u015aladk\u00f3w Ma\u0142y"
    ],
    "name:pol_x_preferred":[
        "\u015aladk\u00f3w Ma\u0142y"
    ],
    "name:ukr_x_preferred":[
        "\u0421\u043b\u044f\u0434\u043a\u0443\u0432-\u041c\u0430\u043b\u0438\u0439"
    ],
    "wof:name":"Sladkow Maly",
    "wof:placetype":"locality"
},
  "geometry": {"coordinates":[20.744,50.57953],"type":"Point"}
}