{
  "type": "Feature",
  "properties": {
    "gn:admin1_code":"75.0",
    "gn:admin2_code":"614.0",
    "gn:admin3_code":"61408.0",
    "gn:asciiname":"Bronice",
    "gn:country_code":"PL",
    "gn:dem":199,
    "gn:feature_class":"P",
    "gn:feature_code":"PPL",
    "gn:name":"Bronice",
    "gn:population":0,
    "gn:timezone":"Europe/Warsaw",
    "iso:country":"PL",
    "name:fra_x_preferred":[
        "Bronice"
    ],
    "name:pol_x_preferred":[
        "Bronice"
    ],
    "name:ukr_x_preferred":[
        "\u0411\u0440\u043e\u043d\u0456\u0446\u0435"
    ],
    "name:und_x_variant":[
        "Bronica"
    ],
    "wof:name":"Bronice",
    "wof:placetype":"locality"
},
  "geometry": {"coordinates":[22.21915,51.34239],"type":"Point"}
}