{
  "type": "Feature",
  "properties": {
    "gn:admin1_code":"78.0",
    "gn:admin2_code":"1425.0",
    "gn:admin3_code":"142513.0",
    "gn:asciiname":"Kozinki",
    "gn:country_code":"PL",
    "gn:dem":178,
    "gn:feature_class":"P",
    "gn:feature_code":"PPL",
    "gn:name":"Kozinki",
    "gn:population":0,
    "gn:timezone":"Europe/Warsaw",
    "iso:country":"PL",
    "name:fra_x_preferred":[
        "Kozinki"
    ],
    "name:pol_x_preferred":[
        "Kozinki"
    ],
    "name:ukr_x_preferred":[
        "\u041a\u043e\u0437\u0456\u043d\u043a\u0456"
    ],
    "wof:name":"Kozinki",
    "wof:placetype":"locality"
},
  "geometry": {"coordinates":[21.05719,51.44673],"type":"Point"}
}