{
  "type": "Feature",
  "properties": {
    "gn:admin1_code":"78.0",
    "gn:admin2_code":"1409.0",
    "gn:admin3_code":"140902.0",
    "gn:asciiname":"Ciepielow Stary",
    "gn:country_code":"PL",
    "gn:dem":141,
    "gn:feature_class":"P",
    "gn:feature_code":"PPL",
    "gn:name":"Ciepiel\u00f3w Stary",
    "gn:population":0,
    "gn:timezone":"Europe/Warsaw",
    "iso:country":"PL",
    "wof:name":"Ciepielow Stary",
    "wof:placetype":"locality"
},
  "geometry": {"coordinates":[21.6002,51.25172],"type":"Point"}
}