{
  "type": "Feature",
  "properties": {
    "gn:admin1_code":"77.0",
    "gn:admin2_code":"1204.0",
    "gn:admin3_code":"120401.0",
    "gn:asciiname":"Strojcow",
    "gn:country_code":"PL",
    "gn:dem":165,
    "gn:feature_class":"P",
    "gn:feature_code":"PPL",
    "gn:name":"Strojc\u00f3w",
    "gn:population":0,
    "gn:timezone":"Europe/Warsaw",
    "iso:country":"PL",
    "name:pol_x_preferred":[
        "Strojc\u00f3w"
    ],
    "name:ukr_x_preferred":[
        "\u0421\u0442\u0440\u043e\u0439\u0446\u0443\u0432"
    ],
    "wof:name":"Strojcow",
    "wof:placetype":"locality"
},
  "geometry": {"coordinates":[20.89634,50.29614],"type":"Point"}
}