{
  "type": "Feature",
  "properties": {
    "gn:admin1_code":"73.0",
    "gn:admin2_code":"403.0",
    "gn:admin3_code":"40306.0",
    "gn:asciiname":"Niwy",
    "gn:country_code":"PL",
    "gn:dem":93,
    "gn:feature_class":"P",
    "gn:feature_code":"PPL",
    "gn:name":"Niwy",
    "gn:population":0,
    "gn:timezone":"Europe/Warsaw",
    "iso:country":"PL",
    "name:bel_x_preferred":[
        "\u041d\u0456\u0432\u044b"
    ],
    "name:deu_x_preferred":[
        "Niwy"
    ],
    "name:fra_x_preferred":[
        "Niwy"
    ],
    "name:pol_x_preferred":[
        "Niwy"
    ],
    "name:rus_x_preferred":[
        "\u041d\u0438\u0432\u044b"
    ],
    "name:ukr_x_preferred":[
        "\u041d\u0456\u0432\u0438"
    ],
    "wof:name":"Niwy",
    "wof:placetype":"locality"
},
  "geometry": {"coordinates":[18.10035,53.19693],"type":"Point"}
}