{
  "type": "Feature",
  "properties": {
    "gn:gn_country":"PL",
    "gn:gn_fcode":"PPL",
    "gn:gn_pop":121,
    "gn:population":121,
    "iso:country":"PL",
    "name:ast_x_preferred":[
        "Brze\u017anica"
    ],
    "name:ceb_x_preferred":[
        "Brze\u017anica"
    ],
    "name:eng_x_preferred":[
        "Brze\u017anica"
    ],
    "name:fra_x_preferred":[
        "Brze\u017anica"
    ],
    "name:pol_x_preferred":[
        "Brze\u017anica"
    ],
    "name:ukr_x_preferred":[
        "\u0411\u0436\u0435\u0437\u044c\u043d\u0438\u0446\u044f"
    ],
    "name:urd_x_preferred":[
        "\u0628\u0631\u0632\u06d2\u0632\u0646\u06a9\u0627\u060c \u0633\u0648\u06cc\u06cc\u0679\u0648\u06a9\u0631\u0632\u06cc\u0633\u06a9\u0626\u06cc \u0635\u0648\u0628\u06c1"
    ],
    "name:urd_x_variant":[
        "\u0628\u0631\u0632\u06d2\u0632\u0646\u06a9\u0627"
    ],
    "qs_pg:aaroncc":"PL",
    "qs_pg:gn_country":"PL",
    "qs_pg:gn_fcode":"PPL",
    "qs_pg:gn_pop":121,
    "qs_pg:name":"Brze\u017anica",
    "qs_pg:name_adm0":"Polska",
    "qs_pg:name_adm1":"Swi\u0119tokrzyskie",
    "qs_pg:photos_9r":0,
    "qs_pg:photos_sr":0,
    "qs_pg:pop_sr":1,
    "qs_pg:qs_pg_placetype":"locality",
    "qs_pg:qs_pg_placetype_gp":"Town",
    "qs_pg:woe_adm0":23424923,
    "woe:adm0_id":23424923,
    "woe:name_adm0":"Polska",
    "woe:name_adm1":"Swi\u0119tokrzyskie",
    "woe:placetype":"Town",
    "wof:name":"Brze\u017anica",
    "wof:placetype":"locality",
    "wof:population":121
},
  "geometry": {"coordinates":[20.48169,51.26959],"type":"Point"}
}