{
  "type": "Feature",
  "properties": {
    "gn:admin1_code":"85.0",
    "gn:admin2_code":"2805.0",
    "gn:admin3_code":"280502.0",
    "gn:asciiname":"Kaleczyny",
    "gn:country_code":"PL",
    "gn:dem":128,
    "gn:feature_class":"P",
    "gn:feature_code":"PPL",
    "gn:name":"Ka\u0142\u0119czyny",
    "gn:population":0,
    "gn:timezone":"Europe/Warsaw",
    "iso:country":"PL",
    "name:azb_x_preferred":[
        "\u06a9\u0627\u0648\u0646\u0686\u0646\u0647"
    ],
    "name:deu_x_preferred":[
        "Ka\u0142\u0119czyny"
    ],
    "name:fas_x_preferred":[
        "\u06a9\u0627\u0648\u0646\u0686\u0646\u0647"
    ],
    "name:fra_x_preferred":[
        "Ka\u0142\u0119czyny"
    ],
    "name:pol_x_preferred":[
        "Ka\u0142\u0119czyny"
    ],
    "name:ukr_x_preferred":[
        "\u041a\u0430\u043b\u0435\u043d\u0447\u0438\u043d\u0438"
    ],
    "name:und_x_variant":[
        "Lenzendorf",
        "Kallenczynnen",
        "Kallenczinnen",
        "Kalenczynnen"
    ],
    "wof:name":"Kaleczyny",
    "wof:placetype":"locality"
},
  "geometry": {"coordinates":[22.48451,53.78746999999999],"type":"Point"}
}