{
  "type": "Feature",
  "properties": {
    "gn:admin1_code":"75.0",
    "gn:admin2_code":"620.0",
    "gn:admin3_code":"62008.0",
    "gn:asciiname":"Wolka Czarnystok",
    "gn:country_code":"PL",
    "gn:dem":222,
    "gn:feature_class":"P",
    "gn:feature_code":"PPL",
    "gn:name":"W\u00f3lka Czarnystok",
    "gn:population":0,
    "gn:timezone":"Europe/Warsaw",
    "iso:country":"PL",
    "wof:name":"Wolka Czarnystok",
    "wof:placetype":"locality"
},
  "geometry": {"coordinates":[22.85382,50.66547],"type":"Point"}
}