{
  "type": "Feature",
  "properties": {
    "gn:admin1_code":"81.0",
    "gn:admin2_code":"2007.0",
    "gn:admin3_code":"200701.0",
    "gn:asciiname":"Makowskie",
    "gn:country_code":"PL",
    "gn:dem":118,
    "gn:feature_class":"P",
    "gn:feature_code":"PPL",
    "gn:name":"Makowskie",
    "gn:population":0,
    "gn:timezone":"Europe/Warsaw",
    "iso:country":"PL",
    "name:lit_x_preferred":[
        "Makovskiai"
    ],
    "name:pol_x_preferred":[
        "Makowskie"
    ],
    "name:ukr_x_preferred":[
        "\u041c\u0430\u043a\u043e\u0432\u0441\u044c\u043a\u0435"
    ],
    "wof:name":"Makowskie",
    "wof:placetype":"locality"
},
  "geometry": {"coordinates":[22.40608,53.27462],"type":"Point"}
}