{
  "type": "Feature",
  "properties": {
    "gn:gn_country":"PL",
    "gn:gn_fcode":"PPL",
    "gn:gn_pop":1667,
    "gn:population":1667,
    "iso:country":"PL",
    "name:dut_x_preferred":[
        "Sopotnia Wielka"
    ],
    "name:eng_x_preferred":[
        "Sopotnia Wielka"
    ],
    "name:fre_x_preferred":[
        "Sopotnia Wielka"
    ],
    "name:ger_x_preferred":[
        "Sopotnia Wielka"
    ],
    "name:pol_x_preferred":[
        "Sopotnia Wielka"
    ],
    "qs_pg:aaroncc":"PL",
    "qs_pg:gn_country":"PL",
    "qs_pg:gn_fcode":"PPL",
    "qs_pg:gn_pop":1667,
    "qs_pg:name":"Sopotnia Wielka",
    "qs_pg:name_adm0":"Polska",
    "qs_pg:name_adm1":"Sl\u0105skie",
    "qs_pg:photos_9k":1,
    "qs_pg:photos_9r":1,
    "qs_pg:photos_all":3,
    "qs_pg:photos_sr":0,
    "qs_pg:pop_sr":3,
    "qs_pg:qs_pg_placetype":"locality",
    "qs_pg:qs_pg_placetype_gp":"Town",
    "qs_pg:woe_adm0":23424923,
    "woe:adm0_id":23424923,
    "woe:name_adm0":"Polska",
    "woe:name_adm1":"Sl\u0105skie",
    "woe:placetype":"Town",
    "wof:name":"Sopotnia Wielka",
    "wof:placetype":"locality",
    "wof:population":1667
},
  "geometry": {"coordinates":[19.28289,49.56853],"type":"Point"}
}