{
  "type": "Feature",
  "properties": {
    "gn:admin1_code":"86.0",
    "gn:admin2_code":"3009.0",
    "gn:admin3_code":"300906.0",
    "gn:asciiname":"Gory",
    "gn:country_code":"PL",
    "gn:dem":124,
    "gn:feature_class":"P",
    "gn:feature_code":"PPL",
    "gn:name":"G\u00f3ry",
    "gn:population":0,
    "gn:timezone":"Europe/Warsaw",
    "iso:country":"PL",
    "name:ceb_x_preferred":[
        "Gory"
    ],
    "name:deu_x_preferred":[
        "G\u00f3ry"
    ],
    "name:fra_x_preferred":[
        "Gory"
    ],
    "name:ita_x_preferred":[
        "Gory"
    ],
    "name:lit_x_preferred":[
        "Gurai"
    ],
    "name:swe_x_preferred":[
        "Gory"
    ],
    "wof:name":"Gory",
    "wof:placetype":"locality"
},
  "geometry": {"coordinates":[18.91667,52.31667],"type":"Point"}
}