{
  "type": "Feature",
  "properties": {
    "gn:admin1_code":"74.0",
    "gn:admin2_code":"1004.0",
    "gn:admin3_code":"100406.0",
    "gn:asciiname":"Lubnica",
    "gn:country_code":"PL",
    "gn:dem":107,
    "gn:feature_class":"P",
    "gn:feature_code":"PPL",
    "gn:name":"\u0141ubnica",
    "gn:population":0,
    "gn:timezone":"Europe/Warsaw",
    "iso:country":"PL",
    "name:fra_x_preferred":[
        "\u0141ubnica"
    ],
    "name:pol_x_preferred":[
        "\u0141ubnica"
    ],
    "name:ukr_x_preferred":[
        "\u041b\u0443\u0431\u043d\u0438\u0446\u044f"
    ],
    "wof:name":"Lubnica",
    "wof:placetype":"locality"
},
  "geometry": {"coordinates":[19.42042,52.06572],"type":"Point"}
}