{
  "type": "Feature",
  "properties": {
    "gn:admin1_code":"80.0",
    "gn:admin2_code":"1818.0",
    "gn:admin3_code":"181805.0",
    "gn:asciiname":"Karkowka",
    "gn:country_code":"PL",
    "gn:dem":235,
    "gn:feature_class":"P",
    "gn:feature_code":"PPL",
    "gn:name":"Kark\u00f3wka",
    "gn:population":0,
    "gn:timezone":"Europe/Warsaw",
    "iso:country":"PL",
    "wof:name":"Karkowka",
    "wof:placetype":"locality"
},
  "geometry": {"coordinates":[22.14552,50.79498],"type":"Point"}
}