{
  "type": "Feature",
  "properties": {
    "iso:country":"PL",
    "name:pol_x_preferred":[
        "\u0141ysa G\u00f3ra"
    ],
    "wof:name":"Lysa Gora",
    "wof:placetype":"neighbourhood"
},
  "geometry": {"coordinates":[19.93435163617296,49.98792865886725],"type":"Point"}
}