{
  "type": "Feature",
  "properties": {
    "gn:admin1_code":"84.0",
    "gn:admin2_code":"2605.0",
    "gn:admin3_code":"260504.0",
    "gn:asciiname":"Kapalow",
    "gn:country_code":"PL",
    "gn:dem":243,
    "gn:feature_class":"P",
    "gn:feature_code":"PPL",
    "gn:name":"Kapa\u0142\u00f3w",
    "gn:population":0,
    "gn:timezone":"Europe/Warsaw",
    "iso:country":"PL",
    "name:ceb_x_preferred":[
        "Kapa\u0142\u00f3w"
    ],
    "name:nld_x_preferred":[
        "Kapa\u0142\u00f3w"
    ],
    "name:pol_x_preferred":[
        "Kapa\u0142\u00f3w"
    ],
    "name:ukr_x_preferred":[
        "\u041a\u0430\u043f\u0430\u043b\u0443\u0432"
    ],
    "wof:name":"Kapalow",
    "wof:placetype":"locality"
},
  "geometry": {"coordinates":[20.28179,51.04976],"type":"Point"}
}