{
  "type": "Feature",
  "properties": {
    "gn:country":"PL",
    "gn:fcode":"PPLA3",
    "gn:population":2600,
    "iso:country":"PL",
    "name:azb_x_preferred":[
        "\u0628\u06cc\u0627\u0648\u0648\u0634\u0644\u06cc\u0648\u06cc\u0647"
    ],
    "name:ceb_x_preferred":[
        "Bia\u0142o\u015bliwie"
    ],
    "name:deu_x_preferred":[
        "Bia\u0142o\u015bliwie"
    ],
    "name:fas_x_preferred":[
        "\u0628\u06cc\u0627\u0648\u0648\u0634\u0644\u06cc\u0648\u06cc\u0647"
    ],
    "name:fra_x_preferred":[
        "Bia\u0142o\u015bliwie"
    ],
    "name:nld_x_preferred":[
        "Bia\u0142o\u015bliwie"
    ],
    "name:pol_x_preferred":[
        "Bia\u0142o\u015bliwie"
    ],
    "name:ukr_x_preferred":[
        "\u0411\u044f\u043b\u043e\u0441\u043b\u0456\u0432\u0435"
    ],
    "qs_pg:aaroncc":"PL",
    "qs_pg:gn_country":"PL",
    "qs_pg:gn_fcode":"PPLA3",
    "qs_pg:gn_pop":2600,
    "qs_pg:name":"Bia\u0142o\u015bliwie",
    "qs_pg:name_adm0":"Polska",
    "qs_pg:name_adm1":"Wielkopolskie",
    "qs_pg:photos_9r":0,
    "qs_pg:photos_sr":0,
    "qs_pg:pop_sr":4,
    "qs_pg:qs_pg_placetype":"localadmin",
    "qs_pg:qs_pg_placetype_gp":"LocalAdmin",
    "qs_pg:woe_adm0":23424923,
    "woe:adm0_id":23424923,
    "woe:name_adm0":"Polska",
    "woe:name_adm1":"Wielkopolskie",
    "woe:placetype":"LocalAdmin",
    "wof:name":"Bia\u0142o\u015bliwie",
    "wof:placetype":"localadmin",
    "wof:population":2600
},
  "geometry": {"coordinates":[17.12533,53.10461],"type":"Point"}
}