{
  "type": "Feature",
  "properties": {
    "gn:admin1_code":"82.0",
    "gn:admin2_code":"2205.0",
    "gn:admin3_code":"220503.0",
    "gn:asciiname":"Pomieczyno",
    "gn:country_code":"PL",
    "gn:dem":204,
    "gn:feature_class":"P",
    "gn:feature_code":"PPL",
    "gn:name":"Pomieczyno",
    "gn:population":0,
    "gn:timezone":"Europe/Warsaw",
    "iso:country":"PL",
    "wof:name":"Pomieczyno",
    "wof:placetype":"locality"
},
  "geometry": {"coordinates":[18.20219,54.41524],"type":"Point"}
}