{
  "type": "Feature",
  "properties": {
    "gn:admin1_code":"78.0",
    "gn:admin2_code":"1430.0",
    "gn:admin3_code":"143005.0",
    "gn:asciiname":"Jankowice",
    "gn:country_code":"PL",
    "gn:dem":187,
    "gn:feature_class":"P",
    "gn:feature_code":"PPL",
    "gn:name":"Jankowice",
    "gn:population":0,
    "gn:timezone":"Europe/Warsaw",
    "iso:country":"PL",
    "name:ceb_x_preferred":[
        "Jankowice"
    ],
    "name:fra_x_preferred":[
        "Jankowice"
    ],
    "name:pol_x_preferred":[
        "Jankowice"
    ],
    "name:ukr_x_preferred":[
        "\u042f\u043d\u043a\u043e\u0432\u0456\u0446\u0435"
    ],
    "name:urd_x_preferred":[
        "\u062c\u0646\u06a9\u0648\u0648\u06a9\u06d2"
    ],
    "wof:name":"Jankowice",
    "wof:placetype":"locality"
},
  "geometry": {"coordinates":[20.87334,51.27534],"type":"Point"}
}