{
  "type": "Feature",
  "properties": {
    "gn:admin1_code":"74.0",
    "gn:admin2_code":"1012.0",
    "gn:admin3_code":"101208.0",
    "gn:asciiname":"Brudzice",
    "gn:country_code":"PL",
    "gn:dem":214,
    "gn:feature_class":"P",
    "gn:feature_code":"PPL",
    "gn:name":"Brudzice",
    "gn:population":0,
    "gn:timezone":"Europe/Warsaw",
    "iso:country":"PL",
    "name:azb_x_preferred":[
        "\u0628\u0631\u0648\u062c\u062a\u0633\u0647"
    ],
    "name:ceb_x_preferred":[
        "Brudzice"
    ],
    "name:fas_x_preferred":[
        "\u0628\u0631\u0648\u062c\u062a\u0633\u0647"
    ],
    "name:fra_x_preferred":[
        "Brudzice"
    ],
    "name:nld_x_preferred":[
        "Brudzice"
    ],
    "name:pol_x_preferred":[
        "Brudzice"
    ],
    "name:ukr_x_preferred":[
        "\u0411\u0440\u0443\u0434\u0437\u0456\u0446\u0435"
    ],
    "wof:name":"Brudzice",
    "wof:placetype":"locality"
},
  "geometry": {"coordinates":[19.33731,51.17278],"type":"Point"}
}