{
  "type": "Feature",
  "properties": {
    "gn:admin1_code":"72.0",
    "gn:admin2_code":"208.0",
    "gn:admin3_code":"20811.0",
    "gn:asciiname":"Sciborow",
    "gn:country_code":"PL",
    "gn:dem":517,
    "gn:feature_class":"P",
    "gn:feature_code":"PPL",
    "gn:name":"Sciborow",
    "gn:population":0,
    "gn:timezone":"Europe/Warsaw",
    "iso:country":"PL",
    "wof:name":"Sciborow",
    "wof:placetype":"locality"
},
  "geometry": {"coordinates":[16.58333,50.58333],"type":"Point"}
}