{
  "type": "Feature",
  "properties": {
    "gn:gn_country":"PL",
    "gn:gn_fcode":"PPL",
    "gn:gn_pop":1014,
    "gn:population":1014,
    "iso:country":"PL",
    "name:eng_x_preferred":[
        "Sulbiny G\u00f3rne"
    ],
    "name:fre_x_preferred":[
        "Sulbiny G\u00f3rne"
    ],
    "name:per_x_preferred":[
        "\u0633\u0648\u0644\u0628\u06cc\u0646 \u06af\u0648\u0631\u0646\u0647"
    ],
    "name:pol_x_preferred":[
        "Sulbiny"
    ],
    "name:spa_x_preferred":[
        "Sulbiny G\u00f3rne"
    ],
    "qs_pg:aaroncc":"PL",
    "qs_pg:gn_country":"PL",
    "qs_pg:gn_fcode":"PPL",
    "qs_pg:gn_pop":1014,
    "qs_pg:name":"Sulbiny G\u00f3rne",
    "qs_pg:photos_9r":0,
    "qs_pg:photos_sr":0,
    "qs_pg:pop_sr":3,
    "qs_pg:qs_pg_placetype":"locality",
    "wof:name":"Sulbiny G\u00f3rne",
    "wof:placetype":"locality",
    "wof:population":1014
},
  "geometry": {"coordinates":[21.63174,51.87321],"type":"Point"}
}