{
  "type": "Feature",
  "properties": {
    "gn:admin1_code":"74.0",
    "gn:admin2_code":"1014.0",
    "gn:admin3_code":"101409.0",
    "gn:asciiname":"Rozdzaly",
    "gn:country_code":"PL",
    "gn:dem":129,
    "gn:feature_class":"P",
    "gn:feature_code":"PPL",
    "gn:name":"Ro\u017cd\u017ca\u0142y",
    "gn:population":0,
    "gn:timezone":"Europe/Warsaw",
    "iso:country":"PL",
    "name:pol_x_preferred":[
        "Ro\u017cd\u017ca\u0142y"
    ],
    "name:ukr_x_preferred":[
        "\u0420\u043e\u0436\u0434\u0436\u0430\u043b\u0438"
    ],
    "name:und_x_variant":[
        "Ro\u017cd\u017ca\u0142y"
    ],
    "wof:name":"Rozdzaly",
    "wof:placetype":"locality"
},
  "geometry": {"coordinates":[18.80711,51.7323],"type":"Point"}
}