{
  "type": "Feature",
  "properties": {
    "gn:admin1_code":"75.0",
    "gn:admin2_code":"601.0",
    "gn:admin3_code":"60111.0",
    "gn:asciiname":"Zalutyn",
    "gn:country_code":"PL",
    "gn:dem":137,
    "gn:feature_class":"P",
    "gn:feature_code":"PPL",
    "gn:name":"Zaluty\u0144",
    "gn:population":0,
    "gn:timezone":"Europe/Warsaw",
    "iso:country":"PL",
    "name:azb_x_preferred":[
        "\u0632\u0627\u0644\u0648\u062a\u0646\u0642"
    ],
    "name:fas_x_preferred":[
        "\u0632\u0627\u0644\u0648\u062a\u0646\u06af"
    ],
    "name:fra_x_preferred":[
        "Zaluty\u0144"
    ],
    "name:lit_x_preferred":[
        "Zalutinas"
    ],
    "name:pol_x_preferred":[
        "Zaluty\u0144"
    ],
    "name:ukr_x_preferred":[
        "\u0417\u0430\u043b\u044e\u0442\u0438\u043d\u044c"
    ],
    "name:und_x_variant":[
        "Zaluty\u0144"
    ],
    "wof:name":"Zalutyn",
    "wof:placetype":"locality"
},
  "geometry": {"coordinates":[23.34977,51.98853],"type":"Point"}
}