{
  "type": "Feature",
  "properties": {
    "gn:admin1_code":"83.0",
    "gn:admin2_code":"2404.0",
    "gn:admin3_code":"240411.0",
    "gn:asciiname":"Kuznica Kiedrzynska",
    "gn:country_code":"PL",
    "gn:dem":225,
    "gn:feature_class":"P",
    "gn:feature_code":"PPL",
    "gn:name":"Ku\u017anica Kiedrzy\u0144ska",
    "gn:population":0,
    "gn:timezone":"Europe/Warsaw",
    "iso:country":"PL",
    "name:und_x_variant":[
        "Ku\u017anica Kiedrzy\u0144ska"
    ],
    "wof:name":"Kuznica Kiedrzynska",
    "wof:placetype":"locality"
},
  "geometry": {"coordinates":[19.07782000000001,50.91351],"type":"Point"}
}