{
  "type": "Feature",
  "properties": {
    "gn:country":"PL",
    "gn:fcode":"PPL",
    "gn:population":890,
    "iso:country":"PL",
    "name:ast_x_preferred":[
        "Lipnica Murowana"
    ],
    "name:azb_x_preferred":[
        "\u0644\u06cc\u067e\u06cc\u0646\u0633\u0627 \u0645\u0648\u0631\u0648\u0648\u0627\u0646\u0627"
    ],
    "name:ceb_x_preferred":[
        "Lipnica Murowana"
    ],
    "name:deu_x_preferred":[
        "Lipnica Murowana"
    ],
    "name:eng_x_preferred":[
        "Lipnica Murowana"
    ],
    "name:fas_x_preferred":[
        "\u0644\u06cc\u067e\u06cc\u0646\u0633\u0627 \u0645\u0648\u0631\u0648\u0648\u0627\u0646\u0627"
    ],
    "name:fra_x_preferred":[
        "Lipnica Murowana"
    ],
    "name:jpn_x_preferred":[
        "\u30ea\u30d7\u30cb\u30c4\u30a1\u30fb\u30e0\u30ed\u30f4\u30a1\u30ca"
    ],
    "name:nan_x_preferred":[
        "Lipnica Murowana"
    ],
    "name:nld_x_preferred":[
        "Lipnica Murowana"
    ],
    "name:pol_x_preferred":[
        "Lipnica Murowana"
    ],
    "name:rus_x_preferred":[
        "\u041b\u0438\u043f\u043d\u0438\u0446\u0430-\u041c\u0443\u0440\u043e\u0432\u0430\u043d\u0430"
    ],
    "name:swe_x_preferred":[
        "Lipnica Murowana"
    ],
    "name:ukr_x_preferred":[
        "\u041b\u0456\u043f\u043d\u0438\u0446\u044f-\u041c\u0443\u0440\u043e\u0432\u0430\u043d\u0430"
    ],
    "name:und_x_variant":[
        "Lipnica"
    ],
    "name:vie_x_preferred":[
        "Lipnica Murowana"
    ],
    "qs_pg:aaroncc":"PL",
    "qs_pg:gn_country":"PL",
    "qs_pg:gn_fcode":"PPL",
    "qs_pg:gn_pop":890,
    "qs_pg:name":"Lipnica Murowana",
    "qs_pg:name_adm0":"Polska",
    "qs_pg:name_adm1":"Ma\u0142opolskie",
    "qs_pg:photos":195,
    "qs_pg:photos_1k":40,
    "qs_pg:photos_9k":1,
    "qs_pg:photos_9r":4,
    "qs_pg:photos_all":195,
    "qs_pg:photos_sr":4,
    "qs_pg:pop_sr":2,
    "qs_pg:qs_pg_placetype":"locality",
    "qs_pg:qs_pg_placetype_gp":"Town",
    "qs_pg:woe_adm0":23424923,
    "woe:adm0_id":23424923,
    "woe:name_adm0":"Polska",
    "woe:name_adm1":"Ma\u0142opolskie",
    "woe:placetype":"Town",
    "wof:coterminous":[
        1125292917
    ],
    "wof:name":"Lipnica Murowana",
    "wof:placetype":"locality",
    "wof:population":890
},
  "geometry": {"coordinates":[20.52619,49.85928],"type":"Point"}
}