{
  "type": "Feature",
  "properties": {
    "gn:admin1_code":"86.0",
    "gn:admin2_code":"3019.0",
    "gn:admin3_code":"301907.0",
    "gn:asciiname":"Nowawies Ujska",
    "gn:country_code":"PL",
    "gn:dem":99,
    "gn:feature_class":"P",
    "gn:feature_code":"PPL",
    "gn:name":"Nowawie\u015b Ujska",
    "gn:population":0,
    "gn:timezone":"Europe/Warsaw",
    "iso:country":"PL",
    "name:fra_x_preferred":[
        "Nowa Wie\u015b Ujska"
    ],
    "name:pol_x_preferred":[
        "Nowa Wie\u015b Ujska"
    ],
    "name:ukr_x_preferred":[
        "\u041d\u043e\u0432\u0430 \u0412\u0435\u0441\u044c-\u0423\u0439\u0441\u044c\u043a\u0430"
    ],
    "name:und_x_variant":[
        "Nowawie\u015b Ujska"
    ],
    "wof:name":"Nowawies Ujska",
    "wof:placetype":"locality"
},
  "geometry": {"coordinates":[16.74679,53.03369],"type":"Point"}
}