{
  "type": "Feature",
  "properties": {
    "gn:country":"PL",
    "gn:fcode":"PPLA3",
    "gn:population":185,
    "iso:country":"PL",
    "name:ceb_x_preferred":[
        "Kowiesy"
    ],
    "name:fra_x_preferred":[
        "Kowiesy"
    ],
    "name:nld_x_preferred":[
        "Kowiesy"
    ],
    "name:pol_x_preferred":[
        "Kowiesy"
    ],
    "name:ukr_x_preferred":[
        "\u041a\u043e\u0432\u0435\u0441\u0438"
    ],
    "qs_pg:aaroncc":"PL",
    "qs_pg:gn_country":"PL",
    "qs_pg:gn_fcode":"PPLA3",
    "qs_pg:gn_pop":185,
    "qs_pg:name":"Kowiesy",
    "qs_pg:name_adm0":"Polska",
    "qs_pg:name_adm1":"\u0141\u00f3dzkie",
    "qs_pg:photos":1,
    "qs_pg:photos_1k":1,
    "qs_pg:photos_9k":1,
    "qs_pg:photos_9r":1,
    "qs_pg:photos_all":1,
    "qs_pg:photos_sr":1,
    "qs_pg:pop_sr":1,
    "qs_pg:qs_pg_placetype":"localadmin",
    "qs_pg:qs_pg_placetype_gp":"LocalAdmin",
    "qs_pg:woe_adm0":23424923,
    "woe:adm0_id":23424923,
    "woe:name_adm0":"Polska",
    "woe:name_adm1":"\u0141\u00f3dzkie",
    "woe:placetype":"LocalAdmin",
    "wof:name":"Kowiesy",
    "wof:placetype":"localadmin",
    "wof:population":185
},
  "geometry": {"coordinates":[20.41929,51.88942],"type":"Point"}
}