{
  "type": "Feature",
  "properties": {
    "gn:admin1_code":"86.0",
    "gn:admin2_code":"3021.0",
    "gn:admin3_code":"302112.0",
    "gn:asciiname":"Pomarzanowice",
    "gn:country_code":"PL",
    "gn:dem":110,
    "gn:feature_class":"P",
    "gn:feature_code":"PPL",
    "gn:name":"Pomarzanowice",
    "gn:population":0,
    "gn:timezone":"Europe/Warsaw",
    "iso:country":"PL",
    "wof:name":"Pomarzanowice",
    "wof:placetype":"locality"
},
  "geometry": {"coordinates":[17.27762,52.50476],"type":"Point"}
}