{
  "type": "Feature",
  "properties": {
    "gn:admin1_code":"86.0",
    "gn:admin2_code":"3021.0",
    "gn:admin3_code":"302112.0",
    "gn:asciiname":"Pomarzanowice",
    "gn:country_code":"PL",
    "gn:dem":110,
    "gn:feature_class":"P",
    "gn:feature_code":"PPL",
    "gn:name":"Pomarzanowice",
    "gn:population":0,
    "gn:timezone":"Europe/Warsaw",
    "iso:country":"PL",
    "name:azb_x_preferred":[
        "\u067e\u0648\u0645\u0627\u0698\u0627\u0646\u0648\u0648\u06cc\u062a\u0633\u0647"
    ],
    "name:deu_x_preferred":[
        "Pomarzanowice"
    ],
    "name:fas_x_preferred":[
        "\u067e\u0648\u0645\u0627\u0698\u0627\u0646\u0648\u0648\u06cc\u062a\u0633\u0647"
    ],
    "name:fra_x_preferred":[
        "Pomarzanowice"
    ],
    "name:pol_x_preferred":[
        "Pomarzanowice"
    ],
    "name:ukr_x_preferred":[
        "\u041f\u043e\u043c\u0430\u0436\u0430\u043d\u043e\u0432\u0456\u0446\u0435"
    ],
    "wof:name":"Pomarzanowice",
    "wof:placetype":"locality"
},
  "geometry": {"coordinates":[17.27762,52.50476],"type":"Point"}
}