{
  "type": "Feature",
  "properties": {
    "gn:gn_country":"PL",
    "gn:gn_fcode":"PPL",
    "gn:gn_pop":507,
    "gn:population":507,
    "iso:country":"PL",
    "name:eng_x_preferred":[
        "Borkowo \u0141ostowickie"
    ],
    "name:fra_x_preferred":[
        "Borkowo"
    ],
    "name:pol_x_preferred":[
        "Borkowo"
    ],
    "name:unk_x_variant":[
        "Borgfeld"
    ],
    "qs_pg:aaroncc":"PL",
    "qs_pg:gn_country":"PL",
    "qs_pg:gn_fcode":"PPL",
    "qs_pg:gn_pop":507,
    "qs_pg:name":"Borkowo \u0141ostowickie",
    "qs_pg:photos_9r":0,
    "qs_pg:photos_sr":0,
    "qs_pg:pop_sr":2,
    "qs_pg:qs_pg_placetype":"locality",
    "wof:name":"Borkowo \u0141ostowickie",
    "wof:placetype":"locality",
    "wof:population":507
},
  "geometry": {"coordinates":[18.59539,54.2991],"type":"Point"}
}