{
  "type": "Feature",
  "properties": {
    "gn:admin1_code":"74.0",
    "gn:admin2_code":"1016.0",
    "gn:admin3_code":"101611.0",
    "gn:asciiname":"Teklin",
    "gn:country_code":"PL",
    "gn:dem":161,
    "gn:feature_class":"P",
    "gn:feature_code":"PPL",
    "gn:name":"Teklin",
    "gn:population":0,
    "gn:timezone":"Europe/Warsaw",
    "iso:country":"PL",
    "name:fra_x_preferred":[
        "Teklin"
    ],
    "name:pol_x_preferred":[
        "Teklin"
    ],
    "name:ukr_x_preferred":[
        "\u0422\u0435\u043a\u043b\u0456\u043d"
    ],
    "wof:name":"Teklin",
    "wof:placetype":"locality"
},
  "geometry": {"coordinates":[20.10904,51.72441],"type":"Point"}
}