{
  "type": "Feature",
  "properties": {
    "gn:admin1_code":"74.0",
    "gn:admin2_code":"1010.0",
    "gn:admin3_code":"101009.0",
    "gn:asciiname":"Lazy Dabrowa",
    "gn:country_code":"PL",
    "gn:dem":196,
    "gn:feature_class":"P",
    "gn:feature_code":"PPL",
    "gn:name":"\u0141azy D\u0105browa",
    "gn:population":0,
    "gn:timezone":"Europe/Warsaw",
    "iso:country":"PL",
    "name:fra_x_preferred":[
        "\u0141azy-D\u0105browa"
    ],
    "name:pol_x_preferred":[
        "\u0141azy-D\u0105browa"
    ],
    "name:ukr_x_preferred":[
        "\u041b\u0430\u0437\u0438-\u0414\u043e\u043c\u0431\u0440\u043e\u0432\u0430"
    ],
    "name:und_x_variant":[
        "\u0141azy D\u0105browa"
    ],
    "wof:name":"Lazy Dabrowa",
    "wof:placetype":"locality"
},
  "geometry": {"coordinates":[19.76831,51.31408],"type":"Point"}
}