{
  "type": "Feature",
  "properties": {
    "gn:admin1_code":"75.0",
    "gn:admin2_code":"604.0",
    "gn:admin3_code":"60408.0",
    "gn:asciiname":"Lysa Gora",
    "gn:country_code":"PL",
    "gn:dem":198,
    "gn:feature_class":"P",
    "gn:feature_code":"PPL",
    "gn:name":"\u0141ysa G\u00f3ra",
    "gn:population":0,
    "gn:timezone":"Europe/Warsaw",
    "iso:country":"PL",
    "name:fra_x_preferred":[
        "\u0141ysa G\u00f3ra"
    ],
    "name:pol_x_preferred":[
        "\u0141ysa G\u00f3ra"
    ],
    "name:ukr_x_preferred":[
        "\u041b\u0438\u0441\u0430 \u0413\u0443\u0440\u0430"
    ],
    "name:und_x_variant":[
        "\u0141ysa Goro"
    ],
    "wof:name":"Lysa Gora",
    "wof:placetype":"locality"
},
  "geometry": {"coordinates":[23.7676,50.72283],"type":"Point"}
}