{
  "type": "Feature",
  "properties": {
    "gn:admin1_code":"74.0",
    "gn:admin2_code":"1012.0",
    "gn:admin3_code":"101203.0",
    "gn:asciiname":"Wojnowice",
    "gn:country_code":"PL",
    "gn:dem":218,
    "gn:feature_class":"P",
    "gn:feature_code":"PPL",
    "gn:name":"Wojnowice",
    "gn:population":0,
    "gn:timezone":"Europe/Warsaw",
    "iso:country":"PL",
    "name:fra_x_preferred":[
        "Wojnowice"
    ],
    "name:pol_x_preferred":[
        "Wojnowice"
    ],
    "name:ukr_x_preferred":[
        "\u0412\u043e\u0439\u043d\u043e\u0432\u0456\u0446\u0435"
    ],
    "wof:name":"Wojnowice",
    "wof:placetype":"locality"
},
  "geometry": {"coordinates":[19.51948,50.94454],"type":"Point"}
}