{
  "type": "Feature",
  "properties": {
    "gn:admin1_code":"72.0",
    "gn:admin2_code":"222.0",
    "gn:admin3_code":"22201.0",
    "gn:asciiname":"Jodlowice",
    "gn:country_code":"PL",
    "gn:dem":118,
    "gn:feature_class":"P",
    "gn:feature_code":"PPL",
    "gn:name":"Jod\u0142owice",
    "gn:population":0,
    "gn:timezone":"Europe/Warsaw",
    "iso:country":"PL",
    "name:und_x_variant":[
        "Jod\u0142owice"
    ],
    "wof:name":"Jodlowice",
    "wof:placetype":"locality"
},
  "geometry": {"coordinates":[16.79346,51.28084000000001],"type":"Point"}
}