{
  "type": "Feature",
  "properties": {
    "gn:admin1_code":"81.0",
    "gn:admin2_code":"2003.0",
    "gn:admin3_code":"200306.0",
    "gn:asciiname":"Czechy Zablotne",
    "gn:country_code":"PL",
    "gn:dem":148,
    "gn:feature_class":"P",
    "gn:feature_code":"PPL",
    "gn:name":"Czechy Zab\u0142otne",
    "gn:population":0,
    "gn:timezone":"Europe/Warsaw",
    "iso:country":"PL",
    "name:azb_x_preferred":[
        "\u0686\u062e \u0632\u0627\u0628\u0648\u0648\u062a\u0646\u0647"
    ],
    "name:fas_x_preferred":[
        "\u0686\u062e \u0632\u0627\u0628\u0648\u0648\u062a\u0646\u0647"
    ],
    "name:lit_x_preferred":[
        "\u010cechi Zablotn\u0117"
    ],
    "name:pol_x_preferred":[
        "Czechy Zab\u0142otne"
    ],
    "name:ukr_x_preferred":[
        "\u0427\u0435\u0445\u0438-\u0417\u0430\u0431\u043b\u043e\u0442\u043d\u0435"
    ],
    "wof:name":"Czechy Zablotne",
    "wof:placetype":"locality"
},
  "geometry": {"coordinates":[23.19772,52.6269],"type":"Point"}
}