{
  "type": "Feature",
  "properties": {
    "gn:admin1_code":"81.0",
    "gn:admin2_code":"2003.0",
    "gn:admin3_code":"200306.0",
    "gn:asciiname":"Czechy Zablotne",
    "gn:country_code":"PL",
    "gn:dem":148,
    "gn:feature_class":"P",
    "gn:feature_code":"PPL",
    "gn:name":"Czechy Zab\u0142otne",
    "gn:population":0,
    "gn:timezone":"Europe/Warsaw",
    "iso:country":"PL",
    "name:und_x_variant":[
        "Czechy Zab\u0142otne"
    ],
    "wof:name":"Czechy Zablotne",
    "wof:placetype":"locality"
},
  "geometry": {"coordinates":[23.19772,52.6269],"type":"Point"}
}