{
  "type": "Feature",
  "properties": {
    "gn:admin1_code":"79.0",
    "gn:admin2_code":"1602.0",
    "gn:admin3_code":"160203.0",
    "gn:asciiname":"Krasne Pole",
    "gn:country_code":"PL",
    "gn:dem":355,
    "gn:feature_class":"P",
    "gn:feature_code":"PPL",
    "gn:name":"Krasne Pole",
    "gn:population":0,
    "gn:timezone":"Europe/Warsaw",
    "iso:country":"PL",
    "name:ces_x_preferred":[
        "Kr\u00e1sn\u00e9 Pole"
    ],
    "name:slk_x_preferred":[
        "Kr\u00e1sn\u00e9 Pole"
    ],
    "name:und_x_variant":[
        "Sch\u00f6nwiese",
        "Krasne Pole"
    ],
    "wof:name":"Krasne Pole",
    "wof:placetype":"locality"
},
  "geometry": {"coordinates":[17.64653,50.1263],"type":"Point"}
}