{
  "type": "Feature",
  "properties": {
    "gn:admin1_code":"75.0",
    "gn:admin2_code":"616.0",
    "gn:admin3_code":"61602.0",
    "gn:asciiname":"Wola Zadybska",
    "gn:country_code":"PL",
    "gn:dem":168,
    "gn:feature_class":"P",
    "gn:feature_code":"PPL",
    "gn:name":"Wola Zadybska",
    "gn:population":0,
    "gn:timezone":"Europe/Warsaw",
    "iso:country":"PL",
    "name:ceb_x_preferred":[
        "Wola Zadybska"
    ],
    "name:fra_x_preferred":[
        "Wola Zadybska"
    ],
    "name:pol_x_preferred":[
        "Wola Zadybska"
    ],
    "name:ukr_x_preferred":[
        "\u0412\u043e\u043b\u044f-\u0417\u0430\u0434\u0438\u0431\u0441\u044c\u043a\u0430"
    ],
    "wof:name":"Wola Zadybska",
    "wof:placetype":"locality"
},
  "geometry": {"coordinates":[21.86125,51.74776],"type":"Point"}
}