{
  "type": "Feature",
  "properties": {
    "gn:admin1_code":"81.0",
    "gn:admin2_code":"2013.0",
    "gn:admin3_code":"201310.0",
    "gn:asciiname":"Osipy Kolonia",
    "gn:country_code":"PL",
    "gn:dem":148,
    "gn:feature_class":"P",
    "gn:feature_code":"PPL",
    "gn:name":"Osipy Kolonia",
    "gn:population":0,
    "gn:timezone":"Europe/Warsaw",
    "iso:country":"PL",
    "name:lit_x_preferred":[
        "Osipi Kolonija"
    ],
    "name:pol_x_preferred":[
        "Osipy-Kolonia"
    ],
    "name:ukr_x_preferred":[
        "\u041e\u0441\u0456\u043f\u0438-\u041a\u043e\u043b\u044c\u043e\u043d\u0456\u044f"
    ],
    "name:und_x_variant":[
        "Osipy Kolonja",
        "Osipy Kolonia"
    ],
    "wof:name":"Osipy Kolonia",
    "wof:placetype":"locality"
},
  "geometry": {"coordinates":[22.46655,52.93304000000001],"type":"Point"}
}