{
  "type": "Feature",
  "properties": {
    "iso:country":"PL",
    "name:eng_x_preferred":[
        "Zerniki"
    ],
    "name:pol_x_preferred":[
        "\u017berniki"
    ],
    "wof:name":"Zerniki",
    "wof:placetype":"neighbourhood"
},
  "geometry": {"coordinates":[16.9175362999281,51.12400835106871],"type":"Point"}
}