{
  "type": "Feature",
  "properties": {
    "gn:admin1_code":"85.0",
    "gn:admin2_code":"2811.0",
    "gn:admin3_code":"281104.0",
    "gn:asciiname":"Piatki",
    "gn:country_code":"PL",
    "gn:dem":169,
    "gn:feature_class":"P",
    "gn:feature_code":"PPL",
    "gn:name":"Pi\u0105tki",
    "gn:population":0,
    "gn:timezone":"Europe/Warsaw",
    "iso:country":"PL",
    "name:fra_x_preferred":[
        "Pi\u0105tki"
    ],
    "name:pol_x_preferred":[
        "Pi\u0105tki"
    ],
    "name:ukr_x_preferred":[
        "\u041f\u0439\u043e\u043d\u0442\u043a\u0456"
    ],
    "name:und_x_variant":[
        "Freidorf",
        "Piontken"
    ],
    "wof:name":"Piatki",
    "wof:placetype":"locality"
},
  "geometry": {"coordinates":[20.40838,53.34486],"type":"Point"}
}