{
  "type": "Feature",
  "properties": {
    "gn:admin1_code":"81.0",
    "gn:admin2_code":"2014.0",
    "gn:admin3_code":"201405.0",
    "gn:asciiname":"Lady Borowe",
    "gn:country_code":"PL",
    "gn:dem":103,
    "gn:feature_class":"P",
    "gn:feature_code":"PPL",
    "gn:name":"\u0141ady Borowe",
    "gn:population":0,
    "gn:timezone":"Europe/Warsaw",
    "iso:country":"PL",
    "name:lit_x_preferred":[
        "Ladi Borov\u0117"
    ],
    "name:pol_x_preferred":[
        "\u0141ady-Borowe"
    ],
    "name:ukr_x_preferred":[
        "\u041b\u0430\u0434\u0438-\u0411\u043e\u0440\u043e\u0432\u0435"
    ],
    "name:und_x_variant":[
        "\u0141ady Borowe"
    ],
    "wof:name":"Lady Borowe",
    "wof:placetype":"locality"
},
  "geometry": {"coordinates":[22.25509,53.06157],"type":"Point"}
}