{
  "type": "Feature",
  "properties": {
    "gn:admin1_code":"80.0",
    "gn:admin2_code":"1803.0",
    "gn:admin3_code":"180302.0",
    "gn:asciiname":"Smarzowa",
    "gn:country_code":"PL",
    "gn:dem":250,
    "gn:feature_class":"P",
    "gn:feature_code":"PPL",
    "gn:name":"Smarzowa",
    "gn:population":0,
    "gn:timezone":"Europe/Warsaw",
    "iso:country":"PL",
    "name:azb_x_preferred":[
        "\u0633\u0645\u0627\u0631\u0698\u0648\u0648\u0627"
    ],
    "name:deu_x_preferred":[
        "Smar\u017cowa"
    ],
    "name:fas_x_preferred":[
        "\u0633\u0645\u0627\u0631\u0698\u0648\u0648\u0627"
    ],
    "name:nld_x_preferred":[
        "Smar\u017cowa"
    ],
    "name:pol_x_preferred":[
        "Smar\u017cowa"
    ],
    "name:ukr_x_preferred":[
        "\u0421\u043c\u0430\u0440\u0436\u043e\u0432\u0430"
    ],
    "name:und_x_variant":[
        "Smarzoma",
        "Smarzowa"
    ],
    "wof:name":"Smarzowa",
    "wof:placetype":"locality"
},
  "geometry": {"coordinates":[21.42916,49.91677],"type":"Point"}
}