{
  "type": "Feature",
  "properties": {
    "gn:admin1_code":"73.0",
    "gn:admin2_code":"409.0",
    "gn:admin3_code":"40904.0",
    "gn:asciiname":"Ciechrz",
    "gn:country_code":"PL",
    "gn:dem":94,
    "gn:feature_class":"P",
    "gn:feature_code":"PPL",
    "gn:name":"Ciechrz",
    "gn:population":0,
    "gn:timezone":"Europe/Warsaw",
    "iso:country":"PL",
    "name:nld_x_preferred":[
        "Ciechrz"
    ],
    "name:pol_x_preferred":[
        "Ciechrz"
    ],
    "name:ukr_x_preferred":[
        "\u0426\u0435\u0445\u0448"
    ],
    "wof:name":"Ciechrz",
    "wof:placetype":"locality"
},
  "geometry": {"coordinates":[18.17095,52.6719],"type":"Point"}
}