{
  "type": "Feature",
  "properties": {
    "gn:admin1_code":"84.0",
    "gn:admin2_code":"2607.0",
    "gn:admin3_code":"260701.0",
    "gn:asciiname":"Koszary",
    "gn:country_code":"PL",
    "gn:dem":195,
    "gn:feature_class":"P",
    "gn:feature_code":"PPL",
    "gn:name":"Koszary",
    "gn:population":0,
    "gn:timezone":"Europe/Warsaw",
    "iso:country":"PL",
    "name:fra_x_preferred":[
        "Koszary"
    ],
    "wof:name":"Koszary",
    "wof:placetype":"locality"
},
  "geometry": {"coordinates":[21.43389,50.96096],"type":"Point"}
}