{
  "type": "Feature",
  "properties": {
    "gn:admin1_code":"78.0",
    "gn:admin2_code":"1420.0",
    "gn:admin3_code":"142007.0",
    "gn:asciiname":"Sobanice",
    "gn:country_code":"PL",
    "gn:dem":127,
    "gn:feature_class":"P",
    "gn:feature_code":"PPL",
    "gn:name":"Sobanice",
    "gn:population":0,
    "gn:timezone":"Europe/Warsaw",
    "iso:country":"PL",
    "name:fra_x_preferred":[
        "Sobanice"
    ],
    "name:pol_x_preferred":[
        "Sobanice"
    ],
    "name:ukr_x_preferred":[
        "\u0421\u043e\u0431\u0430\u043d\u0456\u0446\u0435"
    ],
    "wof:name":"Sobanice",
    "wof:placetype":"locality"
},
  "geometry": {"coordinates":[20.27347,52.48472],"type":"Point"}
}