{
  "type": "Feature",
  "properties": {
    "gn:admin1_code":"84.0",
    "gn:admin2_code":"2604.0",
    "gn:admin3_code":"260413.0",
    "gn:asciiname":"Jeziorko",
    "gn:country_code":"PL",
    "gn:dem":265,
    "gn:feature_class":"P",
    "gn:feature_code":"PPL",
    "gn:name":"Jeziorko",
    "gn:population":0,
    "gn:timezone":"Europe/Warsaw",
    "iso:country":"PL",
    "wof:name":"Jeziorko",
    "wof:placetype":"locality"
},
  "geometry": {"coordinates":[21.02483,50.89345],"type":"Point"}
}