{
  "type": "Feature",
  "properties": {
    "gn:population":4979,
    "iso:country":"PL",
    "name:azb_x_preferred":[
        "\u06a9\u0627\u0631\u067e\u0627\u0686"
    ],
    "name:bul_x_preferred":[
        "\u041a\u0430\u0440\u043f\u0430\u0447"
    ],
    "name:cat_x_preferred":[
        "Karpacz"
    ],
    "name:ceb_x_preferred":[
        "Karpacz"
    ],
    "name:ces_x_preferred":[
        "Karpacz"
    ],
    "name:deu_x_preferred":[
        "Karpacz"
    ],
    "name:eng_x_preferred":[
        "Karpacz"
    ],
    "name:epo_x_preferred":[
        "Karpacz"
    ],
    "name:eus_x_preferred":[
        "Karpacz"
    ],
    "name:fas_x_preferred":[
        "\u06a9\u0627\u0631\u067e\u0627\u0686"
    ],
    "name:fra_x_preferred":[
        "Karpacz"
    ],
    "name:heb_x_preferred":[
        "\u05e7\u05e8\u05e4\u05e5'"
    ],
    "name:hsb_x_preferred":[
        "Karpacz"
    ],
    "name:ita_x_preferred":[
        "Karpacz"
    ],
    "name:jav_x_preferred":[
        "Karpacz"
    ],
    "name:jpn_x_preferred":[
        "\u30ab\u30eb\u30d1\u30c1\u30e5"
    ],
    "name:lav_x_preferred":[
        "Karpa\u010da"
    ],
    "name:msa_x_preferred":[
        "Karpacz"
    ],
    "name:nan_x_preferred":[
        "Karpacz"
    ],
    "name:nld_x_preferred":[
        "Karpacz"
    ],
    "name:nob_x_preferred":[
        "Karpacz"
    ],
    "name:nor_x_preferred":[
        "Karpacz"
    ],
    "name:pol_x_preferred":[
        "Karpacz"
    ],
    "name:por_x_preferred":[
        "Karpacz"
    ],
    "name:ron_x_preferred":[
        "Karpacz"
    ],
    "name:rus_x_preferred":[
        "\u041a\u0430\u0440\u043f\u0430\u0447"
    ],
    "name:slk_x_preferred":[
        "Karpacz"
    ],
    "name:spa_x_preferred":[
        "Karpacz"
    ],
    "name:srp_x_preferred":[
        "\u041a\u0430\u0440\u043f\u0430\u0447"
    ],
    "name:swe_x_preferred":[
        "Karpacz"
    ],
    "name:tat_x_preferred":[
        "\u041a\u0430\u0440\u043f\u0430\u0447"
    ],
    "name:ukr_x_preferred":[
        "\u041a\u0430\u0440\u043f\u0430\u0447"
    ],
    "name:und_x_variant":[
        "Krummh\u00fcbel"
    ],
    "name:vie_x_preferred":[
        "Karpacz"
    ],
    "name:war_x_preferred":[
        "Karpacz"
    ],
    "name:zho_min_nan_x_preferred":[
        "Karpacz"
    ],
    "name:zho_x_preferred":[
        "\u5361\u723e\u5e15\u5947"
    ],
    "qs:a0":"Rzeczpospolita Polska",
    "qs:a1":"*Dolnoslaskie",
    "qs:a1r":"0",
    "qs:a2":"Jeleniog\u00f3rski",
    "qs:adm0":"Rzeczpospolita Polska",
    "qs:la":"Karpacz",
    "qs:la_lc":"*PL0206011",
    "qs:level":"locality",
    "qs:loc":"Karpacz",
    "qs:loc_alt":"Karpacz",
    "qs:pop":0,
    "qs:type":"rural point-in-poly",
    "wd:wordcount":432,
    "wof:coterminous":[
        1125342373
    ],
    "wof:name":"Karpacz",
    "wof:placetype":"locality",
    "wof:population":4979
},
  "geometry": {"coordinates":[15.7397859131416,50.7601913926547],"type":"Point"}
}