{
  "type": "Feature",
  "properties": {
    "gn:admin1_code":"74.0",
    "gn:admin2_code":"1004.0",
    "gn:admin3_code":"100403.0",
    "gn:asciiname":"Podgorzyce",
    "gn:country_code":"PL",
    "gn:dem":111,
    "gn:feature_class":"P",
    "gn:feature_code":"PPL",
    "gn:name":"Podg\u00f3rzyce",
    "gn:population":0,
    "gn:timezone":"Europe/Warsaw",
    "iso:country":"PL",
    "name:fra_x_preferred":[
        "Podg\u00f3rzyce"
    ],
    "name:pol_x_preferred":[
        "Podg\u00f3rzyce"
    ],
    "name:ukr_x_preferred":[
        "\u041f\u043e\u0434\u0491\u0443\u0436\u0438\u0446\u0435"
    ],
    "wof:name":"Podgorzyce",
    "wof:placetype":"locality"
},
  "geometry": {"coordinates":[19.30624,52.06336],"type":"Point"}
}