{
  "type": "Feature",
  "properties": {
    "gn:admin1_code":"81.0",
    "gn:admin2_code":"2011.0",
    "gn:admin3_code":"201103.0",
    "gn:asciiname":"Stok",
    "gn:country_code":"PL",
    "gn:dem":150,
    "gn:feature_class":"P",
    "gn:feature_code":"PPL",
    "gn:name":"Stok",
    "gn:population":0,
    "gn:timezone":"Europe/Warsaw",
    "iso:country":"PL",
    "name:lit_x_preferred":[
        "Stokas"
    ],
    "name:pol_x_preferred":[
        "Stok"
    ],
    "name:ukr_x_preferred":[
        "\u0421\u0442\u043e\u043a"
    ],
    "wof:name":"Stok",
    "wof:placetype":"locality"
},
  "geometry": {"coordinates":[23.11266,53.37601],"type":"Point"}
}