{
  "type": "Feature",
  "properties": {
    "gn:admin1_code":"86.0",
    "gn:admin2_code":"3010.0",
    "gn:admin3_code":"301007.0",
    "gn:asciiname":"Siaszyce",
    "gn:country_code":"PL",
    "gn:dem":108,
    "gn:feature_class":"P",
    "gn:feature_code":"PPL",
    "gn:name":"Si\u0105szyce",
    "gn:population":0,
    "gn:timezone":"Europe/Warsaw",
    "iso:country":"PL",
    "name:fra_x_preferred":[
        "Si\u0105szyce"
    ],
    "name:pol_x_preferred":[
        "Si\u0105szyce"
    ],
    "name:szl_x_preferred":[
        "\u015a\u016fnszycy"
    ],
    "name:ukr_x_preferred":[
        "\u0421\u044c\u043e\u043d\u0448\u0438\u0446\u0435"
    ],
    "wof:name":"Siaszyce",
    "wof:placetype":"locality"
},
  "geometry": {"coordinates":[18.16457,52.03981],"type":"Point"}
}