{
  "type": "Feature",
  "properties": {
    "gn:admin1_code":"86.0",
    "gn:admin2_code":"3010.0",
    "gn:admin3_code":"301007.0",
    "gn:asciiname":"Siaszyce",
    "gn:country_code":"PL",
    "gn:dem":108,
    "gn:feature_class":"P",
    "gn:feature_code":"PPL",
    "gn:name":"Si\u0105szyce",
    "gn:population":0,
    "gn:timezone":"Europe/Warsaw",
    "iso:country":"PL",
    "name:und_x_variant":[
        "Si\u0105szyce"
    ],
    "wof:name":"Siaszyce",
    "wof:placetype":"locality"
},
  "geometry": {"coordinates":[18.16457,52.03981],"type":"Point"}
}