{
  "type": "Feature",
  "properties": {
    "gn:admin1_code":"77.0",
    "gn:admin2_code":"1206.0",
    "gn:admin3_code":"120611.0",
    "gn:asciiname":"Jaskowice",
    "gn:country_code":"PL",
    "gn:dem":233,
    "gn:feature_class":"P",
    "gn:feature_code":"PPL",
    "gn:name":"Ja\u015bkowice",
    "gn:population":0,
    "gn:timezone":"Europe/Warsaw",
    "iso:country":"PL",
    "name:azb_x_preferred":[
        "\u06cc\u0627\u0634\u06a9\u0648\u0648\u06cc\u062a\u0633\u0647"
    ],
    "name:ceb_x_preferred":[
        "Ja\u015bkowice"
    ],
    "name:deu_x_preferred":[
        "Ja\u015bkowice"
    ],
    "name:fas_x_preferred":[
        "\u06cc\u0627\u0634\u06a9\u0648\u0648\u06cc\u062a\u0633\u0647"
    ],
    "name:pol_x_preferred":[
        "Ja\u015bkowice"
    ],
    "name:rus_x_preferred":[
        "\u042f\u0441\u044c\u043a\u043e\u0432\u0438\u0446\u0435"
    ],
    "name:ukr_x_preferred":[
        "\u042f\u0441\u044c\u043a\u043e\u0432\u0456\u0446\u0435"
    ],
    "name:urd_x_preferred":[
        "\u062c\u0627\u0633\u06a9\u0648\u06a9\u06d2"
    ],
    "wof:name":"Jaskowice",
    "wof:placetype":"locality"
},
  "geometry": {"coordinates":[19.66656,49.96017],"type":"Point"}
}