{
  "type": "Feature",
  "properties": {
    "gn:admin1_code":"79.0",
    "gn:admin2_code":"1661.0",
    "gn:admin3_code":"166101.0",
    "gn:asciiname":"Polwies",
    "gn:country_code":"PL",
    "gn:dem":151,
    "gn:feature_class":"P",
    "gn:feature_code":"PPL",
    "gn:name":"P\u00f3\u0142wie\u015b",
    "gn:population":0,
    "gn:timezone":"Europe/Warsaw",
    "iso:country":"PL",
    "wof:name":"Polwies",
    "wof:placetype":"locality"
},
  "geometry": {"coordinates":[17.88682,50.67896],"type":"Point"}
}