{
  "type": "Feature",
  "properties": {
    "iso:country":"PL",
    "name:deu_x_preferred":[
        "Paluch"
    ],
    "name:pol_x_preferred":[
        "Paluch"
    ],
    "name:slk_x_preferred":[
        "Paluch"
    ],
    "wof:name":"Paluch",
    "wof:placetype":"neighbourhood"
},
  "geometry": {"coordinates":[20.96293516269814,52.15512692905502],"type":"Point"}
}