{
  "type": "Feature",
  "properties": {
    "gn:admin1_code":"72.0",
    "gn:admin2_code":"215.0",
    "gn:admin3_code":"21504.0",
    "gn:asciiname":"Jakubowice",
    "gn:country_code":"PL",
    "gn:dem":137,
    "gn:feature_class":"P",
    "gn:feature_code":"PPL",
    "gn:name":"Jakubowice",
    "gn:population":0,
    "gn:timezone":"Europe/Warsaw",
    "iso:country":"PL",
    "name:pol_x_preferred":[
        "Jakubowice"
    ],
    "name:urd_x_preferred":[
        "\u062c\u06a9\u0628\u0648\u0648\u06a9\u06d2"
    ],
    "wof:name":"Jakubowice",
    "wof:placetype":"locality"
},
  "geometry": {"coordinates":[17.24356,50.88506],"type":"Point"}
}