{
  "type": "Feature",
  "properties": {
    "gn:admin1_code":"81.0",
    "gn:admin2_code":"2014.0",
    "gn:admin3_code":"201404.0",
    "gn:asciiname":"Radwany",
    "gn:country_code":"PL",
    "gn:dem":122,
    "gn:feature_class":"P",
    "gn:feature_code":"PPL",
    "gn:name":"Radwany",
    "gn:population":0,
    "gn:timezone":"Europe/Warsaw",
    "iso:country":"PL",
    "name:lit_x_preferred":[
        "Radvani Zao\u017e\u0117"
    ],
    "name:pol_x_preferred":[
        "Radwany-Zaorze"
    ],
    "name:ukr_x_preferred":[
        "\u0420\u0430\u0434\u0432\u0430\u043d\u0438-\u0417\u0430\u043e\u0436\u0435"
    ],
    "name:und_x_variant":[
        "Radwany-Zaorze",
        "Radwany"
    ],
    "wof:name":"Radwany",
    "wof:placetype":"locality"
},
  "geometry": {"coordinates":[22.02356,52.89724],"type":"Point"}
}