{
  "type": "Feature",
  "properties": {
    "gn:admin1_code":"75.0",
    "gn:admin2_code":"618.0",
    "gn:admin3_code":"61806.0",
    "gn:asciiname":"Kmiczyn",
    "gn:country_code":"PL",
    "gn:dem":208,
    "gn:feature_class":"P",
    "gn:feature_code":"PPL",
    "gn:name":"Kmiczyn",
    "gn:population":0,
    "gn:timezone":"Europe/Warsaw",
    "iso:country":"PL",
    "name:azb_x_preferred":[
        "\u06a9\u0645\u06cc\u0686\u0646"
    ],
    "name:ceb_x_preferred":[
        "Kmiczyn"
    ],
    "name:fas_x_preferred":[
        "\u06a9\u0645\u06cc\u0686\u0646"
    ],
    "name:fra_x_preferred":[
        "Kmiczyn"
    ],
    "name:nld_x_preferred":[
        "Kmiczyn"
    ],
    "name:pol_x_preferred":[
        "Kmiczyn"
    ],
    "name:ukr_x_preferred":[
        "\u041a\u043c\u0456\u0447\u0438\u043d"
    ],
    "name:und_x_variant":[
        "Kniczyn"
    ],
    "wof:name":"Kmiczyn",
    "wof:placetype":"locality"
},
  "geometry": {"coordinates":[23.77836,50.54785],"type":"Point"}
}