{
  "type": "Feature",
  "properties": {
    "gn:country":"PL",
    "gn:fcode":"PPLA3",
    "gn:population":310,
    "iso:country":"PL",
    "name:ast_x_preferred":[
        "Kuczbork-Osada"
    ],
    "name:azb_x_preferred":[
        "\u06a9\u0648\u0686\u0628\u0648\u0631\u06a9-\u0627\u0648\u0633\u0627\u062f\u0627"
    ],
    "name:ceb_x_preferred":[
        "Kuczbork-Osada"
    ],
    "name:deu_x_preferred":[
        "Kuczbork-Osada"
    ],
    "name:eng_x_preferred":[
        "Kuczbork-Osada"
    ],
    "name:fas_x_preferred":[
        "\u06a9\u0648\u0686\u0628\u0648\u0631\u06a9-\u0627\u0648\u0633\u0627\u062f\u0627"
    ],
    "name:fra_x_preferred":[
        "Kuczbork-Osada"
    ],
    "name:nan_x_preferred":[
        "Kuczbork-Osada"
    ],
    "name:nld_x_preferred":[
        "Kuczbork-Osada"
    ],
    "name:pol_x_preferred":[
        "Kuczbork-Osada"
    ],
    "name:ukr_x_preferred":[
        "\u041a\u0443\u0447\u0431\u043e\u0440\u043a-\u041e\u0441\u0430\u0434\u0430"
    ],
    "qs_pg:aaroncc":"PL",
    "qs_pg:gn_country":"PL",
    "qs_pg:gn_fcode":"PPLA3",
    "qs_pg:gn_pop":310,
    "qs_pg:name":"Kuczbork-Osada",
    "qs_pg:photos_9r":0,
    "qs_pg:photos_sr":0,
    "qs_pg:pop_sr":2,
    "qs_pg:qs_pg_placetype":"locality",
    "wof:coterminous":[
        1477751505
    ],
    "wof:name":"Kuczbork-Osada",
    "wof:placetype":"locality",
    "wof:population":310
},
  "geometry": {"coordinates":[20.04782,53.08619],"type":"Point"}
}