{
  "type": "Feature",
  "properties": {
    "gn:gn_country":"PL",
    "gn:gn_fcode":"PPL",
    "gn:gn_pop":0,
    "iso:country":"PL",
    "name:ast_x_preferred":[
        "Studziany Las"
    ],
    "name:eng_x_preferred":[
        "Studziany Las"
    ],
    "name:fra_x_preferred":[
        "Studziany Las"
    ],
    "name:lit_x_preferred":[
        "Studziani Lasas"
    ],
    "name:pol_x_preferred":[
        "Studziany Las"
    ],
    "name:ukr_x_preferred":[
        "\u0421\u0442\u0443\u0434\u0437\u044f\u043d\u0438-\u041b\u044f\u0441"
    ],
    "qs_pg:aaroncc":"PL",
    "qs_pg:gn_country":"PL",
    "qs_pg:gn_fcode":"PPL",
    "qs_pg:gn_pop":0,
    "qs_pg:name":"Studziany Las",
    "qs_pg:name_adm0":"Polska",
    "qs_pg:name_adm1":"Podlaskie",
    "qs_pg:photos":25,
    "qs_pg:photos_1k":5,
    "qs_pg:photos_9k":1,
    "qs_pg:photos_9r":1,
    "qs_pg:photos_all":25,
    "qs_pg:photos_sr":1,
    "qs_pg:pop_sr":0,
    "qs_pg:qs_pg_placetype":"locality",
    "qs_pg:qs_pg_placetype_gp":"Town",
    "qs_pg:woe_adm0":23424923,
    "woe:adm0_id":23424923,
    "woe:name_adm0":"Polska",
    "woe:name_adm1":"Podlaskie",
    "woe:placetype":"Town",
    "wof:name":"Studziany Las",
    "wof:placetype":"locality"
},
  "geometry": {"coordinates":[23.23044,54.01959],"type":"Point"}
}