{
  "type": "Feature",
  "properties": {
    "gn:admin1_code":"84.0",
    "gn:admin2_code":"2610.0",
    "gn:admin3_code":"261002.0",
    "gn:asciiname":"Soltykow",
    "gn:country_code":"PL",
    "gn:dem":279,
    "gn:feature_class":"P",
    "gn:feature_code":"PPL",
    "gn:name":"So\u0142tyk\u00f3w",
    "gn:population":0,
    "gn:timezone":"Europe/Warsaw",
    "iso:country":"PL",
    "name:ceb_x_preferred":[
        "So\u0142tyk\u00f3w"
    ],
    "name:pol_x_preferred":[
        "So\u0142tyk\u00f3w"
    ],
    "name:szl_x_preferred":[
        "So\u0142tyk\u016fw"
    ],
    "name:ukr_x_preferred":[
        "\u0421\u043e\u043b\u0442\u0438\u043a\u0443\u0432"
    ],
    "wof:name":"Soltykow",
    "wof:placetype":"locality"
},
  "geometry": {"coordinates":[20.68511,51.14156],"type":"Point"}
}