{
  "type": "Feature",
  "properties": {
    "gn:admin1_code":"84.0",
    "gn:admin2_code":"2610.0",
    "gn:admin3_code":"261002.0",
    "gn:asciiname":"Soltykow",
    "gn:country_code":"PL",
    "gn:dem":279,
    "gn:feature_class":"P",
    "gn:feature_code":"PPL",
    "gn:name":"So\u0142tyk\u00f3w",
    "gn:population":0,
    "gn:timezone":"Europe/Warsaw",
    "iso:country":"PL",
    "wof:name":"Soltykow",
    "wof:placetype":"locality"
},
  "geometry": {"coordinates":[20.68511,51.14156],"type":"Point"}
}