{
  "type": "Feature",
  "properties": {
    "gn:admin1_code":"75.0",
    "gn:admin2_code":"603.0",
    "gn:admin3_code":"60306.0",
    "gn:asciiname":"Kolonia Ignatow",
    "gn:country_code":"PL",
    "gn:dem":183,
    "gn:feature_class":"P",
    "gn:feature_code":"PPL",
    "gn:name":"Kolonia Ignat\u00f3w",
    "gn:population":0,
    "gn:timezone":"Europe/Warsaw",
    "iso:country":"PL",
    "name:fra_x_preferred":[
        "Ignat\u00f3w-Kolonia"
    ],
    "name:pol_x_preferred":[
        "Ignat\u00f3w-Kolonia"
    ],
    "name:und_x_variant":[
        "Kolonia Ignat\u00f3w"
    ],
    "wof:name":"Kolonia Ignatow",
    "wof:placetype":"locality"
},
  "geometry": {"coordinates":[23.59331,51.13931],"type":"Point"}
}