{
  "type": "Feature",
  "properties": {
    "gn:admin1_code":"85.0",
    "gn:admin2_code":"2814.0",
    "gn:admin3_code":"281401.0",
    "gn:asciiname":"Szynowo",
    "gn:country_code":"PL",
    "gn:dem":142,
    "gn:feature_class":"P",
    "gn:feature_code":"PPL",
    "gn:name":"Szynowo",
    "gn:population":0,
    "gn:timezone":"Europe/Warsaw",
    "iso:country":"PL",
    "name:pol_x_preferred":[
        "Szynowo"
    ],
    "name:und_x_variant":[
        "Sch\u00f6nau",
        "Szynowy"
    ],
    "name:vie_x_preferred":[
        "Szynowo"
    ],
    "wof:name":"Szynowo",
    "wof:placetype":"locality"
},
  "geometry": {"coordinates":[20.6459,53.88311],"type":"Point"}
}