{
  "type": "Feature",
  "properties": {
    "gn:admin1_code":"78.0",
    "gn:admin2_code":"1410.0",
    "gn:admin3_code":"141004.0",
    "gn:asciiname":"Czuchow",
    "gn:country_code":"PL",
    "gn:dem":149,
    "gn:feature_class":"P",
    "gn:feature_code":"PPL",
    "gn:name":"Czuch\u00f3w",
    "gn:population":0,
    "gn:timezone":"Europe/Warsaw",
    "iso:country":"PL",
    "wof:name":"Czuchow",
    "wof:placetype":"locality"
},
  "geometry": {"coordinates":[22.7944,52.28165],"type":"Point"}
}