{
  "type": "Feature",
  "properties": {
    "gn:admin1_code":"73.0",
    "gn:admin2_code":"414.0",
    "gn:admin3_code":"41411.0",
    "gn:asciiname":"Przewodnik",
    "gn:country_code":"PL",
    "gn:dem":98,
    "gn:feature_class":"P",
    "gn:feature_code":"PPL",
    "gn:name":"Przewodnik",
    "gn:population":0,
    "gn:timezone":"Europe/Warsaw",
    "iso:country":"PL",
    "wof:name":"Przewodnik",
    "wof:placetype":"locality"
},
  "geometry": {"coordinates":[18.48038,53.67576],"type":"Point"}
}