{
  "type": "Feature",
  "properties": {
    "gn:admin1_code":"76.0",
    "gn:admin2_code":"862.0",
    "gn:admin3_code":"86201.0",
    "gn:asciiname":"Przyjazni",
    "gn:country_code":"PL",
    "gn:dem":156,
    "gn:feature_class":"P",
    "gn:feature_code":"PPL",
    "gn:name":"Przyja\u017ani",
    "gn:population":0,
    "gn:timezone":"Europe/Warsaw",
    "iso:country":"PL",
    "wof:name":"Przyjazni",
    "wof:placetype":"locality"
},
  "geometry": {"coordinates":[15.47536,51.93524],"type":"Point"}
}