{
  "type": "Feature",
  "properties": {
    "gn:admin1_code":"74.0",
    "gn:admin2_code":"1014.0",
    "gn:admin3_code":"101409.0",
    "gn:asciiname":"Lasek",
    "gn:country_code":"PL",
    "gn:dem":128,
    "gn:feature_class":"P",
    "gn:feature_code":"PPL",
    "gn:name":"Lasek",
    "gn:population":0,
    "gn:timezone":"Europe/Warsaw",
    "iso:country":"PL",
    "name:pol_x_preferred":[
        "Lasek"
    ],
    "name:ukr_x_preferred":[
        "\u041b\u044f\u0441\u0435\u043a"
    ],
    "wof:name":"Lasek",
    "wof:placetype":"locality"
},
  "geometry": {"coordinates":[18.76528,51.71333],"type":"Point"}
}