{
  "type": "Feature",
  "properties": {
    "gn:admin1_code":"77.0",
    "gn:asciiname":"Dobrojewo",
    "gn:country_code":"PL",
    "gn:dem":26,
    "gn:feature_class":"P",
    "gn:feature_code":"PPL",
    "gn:name":"Dobrojewo",
    "gn:population":0,
    "gn:timezone":"Europe/Warsaw",
    "iso:country":"PL",
    "name:fra_x_preferred":[
        "Dobrojewo"
    ],
    "name:pol_x_preferred":[
        "Dobrojewo"
    ],
    "name:ukr_x_preferred":[
        "\u0414\u043e\u0431\u0440\u043e\u0454\u0432\u043e"
    ],
    "name:und_x_variant":[
        "Johanneswunsch"
    ],
    "wof:name":"Dobrojewo",
    "wof:placetype":"locality"
},
  "geometry": {"coordinates":[15.46257,52.68502],"type":"Point"}
}