{
  "type": "Feature",
  "properties": {
    "gn:admin1_code":"74.0",
    "gn:admin2_code":"1012.0",
    "gn:admin3_code":"101206.0",
    "gn:asciiname":"Jasien",
    "gn:country_code":"PL",
    "gn:dem":234,
    "gn:feature_class":"P",
    "gn:feature_code":"PPL",
    "gn:name":"Jasie\u0144",
    "gn:population":0,
    "gn:timezone":"Europe/Warsaw",
    "iso:country":"PL",
    "wof:name":"Jasien",
    "wof:placetype":"locality"
},
  "geometry": {"coordinates":[19.57154,51.00185],"type":"Point"}
}