{
  "type": "Feature",
  "properties": {
    "gn:admin1_code":"83.0",
    "gn:admin2_code":"2411.0",
    "gn:admin3_code":"241104.0",
    "gn:asciiname":"Owsiszcze",
    "gn:country_code":"PL",
    "gn:dem":215,
    "gn:feature_class":"P",
    "gn:feature_code":"PPL",
    "gn:name":"Owsiszcze",
    "gn:population":0,
    "gn:timezone":"Europe/Warsaw",
    "iso:country":"PL",
    "name:ceb_x_preferred":[
        "Owsiszcze"
    ],
    "name:ces_x_preferred":[
        "Ovsi\u0161t\u011b"
    ],
    "name:deu_x_preferred":[
        "Owsiszcze"
    ],
    "name:epo_x_preferred":[
        "Owsiszcze"
    ],
    "name:pol_x_preferred":[
        "Owsiszcze"
    ],
    "name:ukr_x_preferred":[
        "\u041e\u0432\u0441\u0456\u0449\u0435"
    ],
    "name:und_x_variant":[
        "Habergrund",
        "Ovsi\u0161t\u011b",
        "Owsch\u00fctz",
        "Owsiszcze"
    ],
    "wof:name":"Owsiszcze",
    "wof:placetype":"locality"
},
  "geometry": {"coordinates":[18.22093,49.97601],"type":"Point"}
}