{
  "type": "Feature",
  "properties": {
    "gn:admin1_code":"77.0",
    "gn:admin2_code":"1204.0",
    "gn:admin3_code":"120401.0",
    "gn:asciiname":"Samocice",
    "gn:country_code":"PL",
    "gn:dem":169,
    "gn:feature_class":"P",
    "gn:feature_code":"PPL",
    "gn:name":"Samocice",
    "gn:population":0,
    "gn:timezone":"Europe/Warsaw",
    "iso:country":"PL",
    "name:pol_x_preferred":[
        "Samocice"
    ],
    "name:ukr_x_preferred":[
        "\u0421\u0430\u043c\u043e\u0446\u0438\u0446\u0435"
    ],
    "wof:name":"Samocice",
    "wof:placetype":"locality"
},
  "geometry": {"coordinates":[20.85291,50.26904],"type":"Point"}
}