{
  "type": "Feature",
  "properties": {
    "gn:admin1_code":"79.0",
    "gn:admin2_code":"1606.0",
    "gn:admin3_code":"160604.0",
    "gn:asciiname":"Gola",
    "gn:country_code":"PL",
    "gn:dem":153,
    "gn:feature_class":"P",
    "gn:feature_code":"PPL",
    "gn:name":"Gola",
    "gn:population":0,
    "gn:timezone":"Europe/Warsaw",
    "iso:country":"PL",
    "name:pol_x_preferred":[
        "Gola"
    ],
    "name:ukr_x_preferred":[
        "\u0490\u043e\u043b\u044f"
    ],
    "wof:name":"Gola",
    "wof:placetype":"locality"
},
  "geometry": {"coordinates":[17.70032999999999,50.95134],"type":"Point"}
}