{
  "type": "Feature",
  "properties": {
    "gn:admin1_code":"86.0",
    "gn:admin2_code":"3027.0",
    "gn:admin3_code":"302708.0",
    "gn:asciiname":"Szadow Ksiezy",
    "gn:country_code":"PL",
    "gn:dem":103,
    "gn:feature_class":"P",
    "gn:feature_code":"PPL",
    "gn:name":"Szad\u00f3w Ksi\u0119\u017cy",
    "gn:population":0,
    "gn:timezone":"Europe/Warsaw",
    "iso:country":"PL",
    "name:ceb_x_preferred":[
        "Szad\u00f3w Ksi\u0119\u017cy"
    ],
    "name:nld_x_preferred":[
        "Szad\u00f3w Ksi\u0119\u017cy"
    ],
    "name:pol_x_preferred":[
        "Szad\u00f3w Ksi\u0119\u017cy"
    ],
    "name:ukr_x_preferred":[
        "\u0428\u0430\u0434\u0443\u0432-\u041a\u0441\u0435\u043d\u0436\u0438"
    ],
    "name:und_x_variant":[
        "Szad\u00f3w Ksi\u0119\u017cy"
    ],
    "wof:name":"Szadow Ksiezy",
    "wof:placetype":"locality"
},
  "geometry": {"coordinates":[18.54771,52.04127],"type":"Point"}
}