{
  "type": "Feature",
  "properties": {
    "gn:admin1_code":"83.0",
    "gn:admin2_code":"2405.0",
    "gn:admin3_code":"240507.0",
    "gn:asciiname":"Pluzniczka",
    "gn:country_code":"PL",
    "gn:dem":241,
    "gn:feature_class":"P",
    "gn:feature_code":"PPL",
    "gn:name":"P\u0142u\u017cniczka",
    "gn:population":0,
    "gn:timezone":"Europe/Warsaw",
    "iso:country":"PL",
    "name:ceb_x_preferred":[
        "P\u0142u\u017cniczka"
    ],
    "name:deu_x_preferred":[
        "P\u0142u\u017cniczka"
    ],
    "name:pol_x_preferred":[
        "P\u0142u\u017cniczka"
    ],
    "name:ukr_x_preferred":[
        "\u041f\u043b\u0443\u0436\u043d\u0456\u0447\u043a\u0430"
    ],
    "wof:name":"Pluzniczka",
    "wof:placetype":"locality"
},
  "geometry": {"coordinates":[18.48587,50.4734],"type":"Point"}
}