{
  "type": "Feature",
  "properties": {
    "gn:admin1_code":"78.0",
    "gn:admin2_code":"1427.0",
    "gn:admin3_code":"142703.0",
    "gn:asciiname":"Zalszyn",
    "gn:country_code":"PL",
    "gn:dem":117,
    "gn:feature_class":"P",
    "gn:feature_code":"PPL",
    "gn:name":"Za\u0142szyn",
    "gn:population":0,
    "gn:timezone":"Europe/Warsaw",
    "iso:country":"PL",
    "name:fra_x_preferred":[
        "Za\u0142szyn"
    ],
    "name:pol_x_preferred":[
        "Za\u0142szyn"
    ],
    "name:ukr_x_preferred":[
        "\u0417\u0430\u043b\u0448\u0438\u043d"
    ],
    "wof:name":"Zalszyn",
    "wof:placetype":"locality"
},
  "geometry": {"coordinates":[19.60416,52.74913000000001],"type":"Point"}
}