{
  "type": "Feature",
  "properties": {
    "gn:admin1_code":"74.0",
    "gn:admin2_code":"1015.0",
    "gn:admin3_code":"101507.0",
    "gn:asciiname":"Franciszkany",
    "gn:country_code":"PL",
    "gn:dem":143,
    "gn:feature_class":"P",
    "gn:feature_code":"PPL",
    "gn:name":"Franciszkany",
    "gn:population":0,
    "gn:timezone":"Europe/Warsaw",
    "iso:country":"PL",
    "name:pol_x_preferred":[
        "Franciszkany"
    ],
    "name:ukr_x_preferred":[
        "\u0424\u0440\u0430\u043d\u0446\u0438\u0448\u043a\u0430\u043d\u0438"
    ],
    "wof:name":"Franciszkany",
    "wof:placetype":"locality"
},
  "geometry": {"coordinates":[20.21502000000001,51.89569],"type":"Point"}
}