{
  "type": "Feature",
  "properties": {
    "gn:admin1_code":"78.0",
    "gn:admin2_code":"1425.0",
    "gn:admin3_code":"142505.0",
    "gn:asciiname":"Piaseczno",
    "gn:country_code":"PL",
    "gn:dem":132,
    "gn:feature_class":"P",
    "gn:feature_code":"PPL",
    "gn:name":"Piaseczno",
    "gn:population":0,
    "gn:timezone":"Europe/Warsaw",
    "iso:country":"PL",
    "name:fra_x_preferred":[
        "Piaseczno"
    ],
    "name:pol_x_preferred":[
        "Piaseczno"
    ],
    "name:ukr_x_preferred":[
        "\u041f\u044f\u0441\u0435\u0447\u043d\u043e"
    ],
    "wof:name":"Piaseczno",
    "wof:placetype":"locality"
},
  "geometry": {"coordinates":[21.14611,51.51195],"type":"Point"}
}