{
  "type": "Feature",
  "properties": {
    "gn:admin1_code":"73.0",
    "gn:admin2_code":"408.0",
    "gn:admin3_code":"40806.0",
    "gn:asciiname":"Barany",
    "gn:country_code":"PL",
    "gn:dem":97,
    "gn:feature_class":"P",
    "gn:feature_code":"PPL",
    "gn:name":"Barany",
    "gn:population":0,
    "gn:timezone":"Europe/Warsaw",
    "iso:country":"PL",
    "name:pol_x_preferred":[
        "Barany"
    ],
    "name:ukr_x_preferred":[
        "\u0411\u0430\u0440\u0430\u043d\u0438"
    ],
    "wof:name":"Barany",
    "wof:placetype":"locality"
},
  "geometry": {"coordinates":[19.08175,52.79699],"type":"Point"}
}