{
  "type": "Feature",
  "properties": {
    "gn:admin1_code":"84.0",
    "gn:admin2_code":"2604.0",
    "gn:admin3_code":"260411.0",
    "gn:asciiname":"Kontrewers",
    "gn:country_code":"PL",
    "gn:dem":296,
    "gn:feature_class":"P",
    "gn:feature_code":"PPL",
    "gn:name":"Kontrewers",
    "gn:population":0,
    "gn:timezone":"Europe/Warsaw",
    "iso:country":"PL",
    "name:pol_x_preferred":[
        "Kontrewers"
    ],
    "name:ukr_x_preferred":[
        "\u041a\u043e\u043d\u0442\u0440\u0435\u0432\u0435\u0440\u0441"
    ],
    "wof:name":"Kontrewers",
    "wof:placetype":"locality"
},
  "geometry": {"coordinates":[20.51221,51.05463],"type":"Point"}
}