{
  "type": "Feature",
  "properties": {
    "gn:admin1_code":"74.0",
    "gn:admin2_code":"1008.0",
    "gn:admin3_code":"100807.0",
    "gn:asciiname":"Swiatniki",
    "gn:country_code":"PL",
    "gn:dem":176,
    "gn:feature_class":"P",
    "gn:feature_code":"PPL",
    "gn:name":"\u015awi\u0105tniki",
    "gn:population":0,
    "gn:timezone":"Europe/Warsaw",
    "iso:country":"PL",
    "wof:name":"Swiatniki",
    "wof:placetype":"locality"
},
  "geometry": {"coordinates":[19.30849,51.70445],"type":"Point"}
}