{
  "type": "Feature",
  "properties": {
    "gn:admin1_code":"86.0",
    "gn:admin2_code":"3018.0",
    "gn:admin3_code":"301804.0",
    "gn:asciiname":"Bierzow",
    "gn:country_code":"PL",
    "gn:dem":209,
    "gn:feature_class":"P",
    "gn:feature_code":"PPL",
    "gn:name":"Bierz\u00f3w",
    "gn:population":0,
    "gn:timezone":"Europe/Warsaw",
    "iso:country":"PL",
    "name:pol_x_preferred":[
        "Bierz\u00f3w"
    ],
    "name:ukr_x_preferred":[
        "\u0411\u0435\u0436\u0443\u0432"
    ],
    "wof:name":"Bierzow",
    "wof:placetype":"locality"
},
  "geometry": {"coordinates":[17.84761,51.401],"type":"Point"}
}