{
  "type": "Feature",
  "properties": {
    "gn:admin1_code":"75.0",
    "gn:admin2_code":"609.0",
    "gn:admin3_code":"60915.0",
    "gn:asciiname":"Gielczew",
    "gn:country_code":"PL",
    "gn:dem":254,
    "gn:feature_class":"P",
    "gn:feature_code":"PPL",
    "gn:name":"Gie\u0142czew",
    "gn:population":0,
    "gn:timezone":"Europe/Warsaw",
    "iso:country":"PL",
    "wof:name":"Gielczew",
    "wof:placetype":"locality"
},
  "geometry": {"coordinates":[22.67853,50.95756],"type":"Point"}
}