{
  "type": "Feature",
  "properties": {
    "gn:admin1_code":"81.0",
    "gn:admin2_code":"2011.0",
    "gn:admin3_code":"201103.0",
    "gn:asciiname":"Szumowo",
    "gn:country_code":"PL",
    "gn:dem":149,
    "gn:feature_class":"P",
    "gn:feature_code":"PPL",
    "gn:name":"Szumowo",
    "gn:population":0,
    "gn:timezone":"Europe/Warsaw",
    "iso:country":"PL",
    "name:lit_x_preferred":[
        "\u0160umovas"
    ],
    "name:pol_x_preferred":[
        "Szumowo"
    ],
    "name:ukr_x_preferred":[
        "\u0428\u0443\u043c\u043e\u0432\u043e"
    ],
    "wof:name":"Szumowo",
    "wof:placetype":"locality"
},
  "geometry": {"coordinates":[23.15836,53.45228],"type":"Point"}
}