{
  "type": "Feature",
  "properties": {
    "gn:admin1_code":"76.0",
    "gn:admin2_code":"808.0",
    "gn:admin3_code":"80805.0",
    "gn:asciiname":"Rzeczyca",
    "gn:country_code":"PL",
    "gn:dem":88,
    "gn:feature_class":"P",
    "gn:feature_code":"PPL",
    "gn:name":"Rzeczyca",
    "gn:population":0,
    "gn:timezone":"Europe/Warsaw",
    "iso:country":"PL",
    "name:deu_x_historical":[
        "Rietsch\u00fctz"
    ],
    "name:deu_x_preferred":[
        "Rietsch\u00fctz"
    ],
    "wof:name":"Rzeczyca",
    "wof:placetype":"locality"
},
  "geometry": {"coordinates":[15.60485,52.27745],"type":"Point"}
}