{
  "type": "Feature",
  "properties": {
    "gn:admin1_code":"86.0",
    "gn:admin2_code":"3019.0",
    "gn:admin3_code":"301903.0",
    "gn:asciiname":"Pilsko",
    "gn:country_code":"PL",
    "gn:dem":93,
    "gn:feature_class":"P",
    "gn:feature_code":"PPL",
    "gn:name":"Pilsko",
    "gn:population":0,
    "gn:timezone":"Europe/Warsaw",
    "iso:country":"PL",
    "name:ceb_x_preferred":[
        "Pilsko"
    ],
    "name:ces_x_preferred":[
        "Pilsko"
    ],
    "name:deu_x_preferred":[
        "Pilsko"
    ],
    "name:kat_x_preferred":[
        "\u10de\u10d8\u10da\u10e1\u10d9\u10dd"
    ],
    "name:nno_x_preferred":[
        "Pilsko"
    ],
    "name:pol_x_preferred":[
        "Pilsko"
    ],
    "name:slk_x_preferred":[
        "Pilsko"
    ],
    "name:spa_x_preferred":[
        "Pilsko"
    ],
    "name:vie_x_preferred":[
        "Pilsko"
    ],
    "wof:name":"Pilsko",
    "wof:placetype":"locality"
},
  "geometry": {"coordinates":[16.90699,53.17375],"type":"Point"}
}