{
  "type": "Feature",
  "properties": {
    "gn:gn_country":"PL",
    "gn:gn_fcode":"PPLA3",
    "gn:gn_pop":540,
    "gn:population":540,
    "iso:country":"PL",
    "name:azb_x_preferred":[
        "\u0631\u0648\u0642\u0648\u0648\u0648"
    ],
    "name:deu_x_preferred":[
        "Rogowo"
    ],
    "name:fas_x_preferred":[
        "\u0631\u0648\u06af\u0648\u0648\u0648"
    ],
    "name:nld_x_preferred":[
        "Rogowo"
    ],
    "name:pol_x_preferred":[
        "Rogowo"
    ],
    "name:ukr_x_preferred":[
        "\u0420\u043e\u0491\u043e\u0432\u043e"
    ],
    "qs_pg:aaroncc":"PL",
    "qs_pg:gn_country":"PL",
    "qs_pg:gn_fcode":"PPLA3",
    "qs_pg:gn_pop":540,
    "qs_pg:name":"Rogowo",
    "qs_pg:name_adm0":"Polska",
    "qs_pg:name_adm1":"Kujawsko-Pomorskie",
    "qs_pg:photos":4,
    "qs_pg:photos_1k":1,
    "qs_pg:photos_9k":1,
    "qs_pg:photos_9r":1,
    "qs_pg:photos_all":4,
    "qs_pg:photos_sr":1,
    "qs_pg:pop_sr":2,
    "qs_pg:qs_pg_placetype":"localadmin",
    "qs_pg:qs_pg_placetype_gp":"LocalAdmin",
    "qs_pg:woe_adm0":23424923,
    "woe:adm0_id":23424923,
    "woe:name_adm0":"Polska",
    "woe:name_adm1":"Kujawsko-Pomorskie",
    "woe:placetype":"LocalAdmin",
    "wof:name":"Rogowo",
    "wof:placetype":"localadmin",
    "wof:population":540
},
  "geometry": {"coordinates":[19.38486,52.97712],"type":"Point"}
}