{
  "type": "Feature",
  "properties": {
    "gn:admin1_code":"75.0",
    "gn:admin2_code":"611.0",
    "gn:admin3_code":"61107.0",
    "gn:asciiname":"Jonik",
    "gn:country_code":"PL",
    "gn:dem":164,
    "gn:feature_class":"P",
    "gn:feature_code":"PPL",
    "gn:name":"Jonik",
    "gn:population":0,
    "gn:timezone":"Europe/Warsaw",
    "iso:country":"PL",
    "name:fra_x_preferred":[
        "Jonnik"
    ],
    "name:pol_x_preferred":[
        "Jonnik"
    ],
    "name:ukr_x_preferred":[
        "\u0419\u043e\u043d\u043d\u0438\u043a"
    ],
    "name:und_x_variant":[
        "Jonik"
    ],
    "wof:name":"Jonik",
    "wof:placetype":"locality"
},
  "geometry": {"coordinates":[22.23528,51.84609],"type":"Point"}
}