{
  "type": "Feature",
  "properties": {
    "gn:country":"PL",
    "gn:fcode":"PPL",
    "gn:population":0,
    "iso:country":"PL",
    "name:ast_x_preferred":[
        "Gaj"
    ],
    "name:azb_x_preferred":[
        "\u0642\u0627\u06cc"
    ],
    "name:ceb_x_preferred":[
        "Gaj"
    ],
    "name:ces_x_preferred":[
        "Gaj"
    ],
    "name:che_x_preferred":[
        "\u0413\u0430\u0439"
    ],
    "name:deu_x_preferred":[
        "Gaj"
    ],
    "name:eng_x_preferred":[
        "Gaj"
    ],
    "name:fas_x_preferred":[
        "\u06af\u0627\u06cc"
    ],
    "name:fra_x_preferred":[
        "Gaj"
    ],
    "name:nan_x_preferred":[
        "Gaj"
    ],
    "name:pol_x_preferred":[
        "Gaj"
    ],
    "name:rus_x_preferred":[
        "\u0413\u0430\u0439"
    ],
    "name:tat_x_preferred":[
        "\u0413\u0430\u0439"
    ],
    "name:ukr_x_preferred":[
        "\u0490\u0430\u0439"
    ],
    "qs_pg:aaroncc":"PL",
    "qs_pg:gn_country":"PL",
    "qs_pg:gn_fcode":"PPL",
    "qs_pg:gn_pop":0,
    "qs_pg:name":"Gaj",
    "qs_pg:name_adm0":"Polska",
    "qs_pg:name_adm1":"Ma\u0142opolskie",
    "qs_pg:photos_9k":1,
    "qs_pg:photos_9r":1,
    "qs_pg:photos_all":2,
    "qs_pg:photos_sr":0,
    "qs_pg:pop_sr":0,
    "qs_pg:qs_pg_placetype":"locality",
    "qs_pg:qs_pg_placetype_gp":"Town",
    "qs_pg:woe_adm0":23424923,
    "woe:adm0_id":23424923,
    "woe:name_adm0":"Polska",
    "woe:name_adm1":"Ma\u0142opolskie",
    "woe:placetype":"Town",
    "wof:name":"Gaj",
    "wof:placetype":"locality"
},
  "geometry": {"coordinates":[19.89988,49.96178],"type":"Point"}
}