{
  "type": "Feature",
  "properties": {
    "gn:admin1_code":"86.0",
    "gn:admin2_code":"3030.0",
    "gn:admin3_code":"303002.0",
    "gn:asciiname":"Nowa Wies Podgorna",
    "gn:country_code":"PL",
    "gn:dem":86,
    "gn:feature_class":"P",
    "gn:feature_code":"PPL",
    "gn:name":"Nowa Wie\u015b Podg\u00f3rna",
    "gn:population":0,
    "gn:timezone":"Europe/Warsaw",
    "iso:country":"PL",
    "name:und_x_variant":[
        "Nowa Wie\u015b Podg\u00f3rna"
    ],
    "wof:name":"Nowa Wies Podgorna",
    "wof:placetype":"locality"
},
  "geometry": {"coordinates":[17.60095,52.15477],"type":"Point"}
}