{
  "type": "Feature",
  "properties": {
    "gn:admin1_code":"79.0",
    "gn:admin2_code":"1609.0",
    "gn:admin3_code":"160909.0",
    "gn:asciiname":"Stary Popielow",
    "gn:country_code":"PL",
    "gn:dem":142,
    "gn:feature_class":"P",
    "gn:feature_code":"PPL",
    "gn:name":"Stary Popiel\u00f3w",
    "gn:population":0,
    "gn:timezone":"Europe/Warsaw",
    "iso:country":"PL",
    "name:und_x_variant":[
        "Alt Popelau",
        "Alt Poppelau",
        "Stary Popiel\u00f3w"
    ],
    "wof:name":"Stary Popielow",
    "wof:placetype":"locality"
},
  "geometry": {"coordinates":[17.74198999999999,50.8245],"type":"Point"}
}