{
  "type": "Feature",
  "properties": {
    "gn:admin1_code":"86.0",
    "gn:admin2_code":"3027.0",
    "gn:admin3_code":"302706.0",
    "gn:asciiname":"Ewinow",
    "gn:country_code":"PL",
    "gn:dem":100,
    "gn:feature_class":"P",
    "gn:feature_code":"PPL",
    "gn:name":"Ewin\u00f3w",
    "gn:population":0,
    "gn:timezone":"Europe/Warsaw",
    "iso:country":"PL",
    "name:pol_x_preferred":[
        "Ewin\u00f3w"
    ],
    "name:ukr_x_preferred":[
        "\u0415\u0432\u0456\u043d\u0443\u0432"
    ],
    "wof:name":"Ewinow",
    "wof:placetype":"locality"
},
  "geometry": {"coordinates":[18.70594,51.97854],"type":"Point"}
}