{
  "type": "Feature",
  "properties": {
    "gn:admin1_code":"74.0",
    "gn:admin2_code":"1017.0",
    "gn:admin3_code":"101704.0",
    "gn:asciiname":"Jasna Gora",
    "gn:country_code":"PL",
    "gn:dem":215,
    "gn:feature_class":"P",
    "gn:feature_code":"PPL",
    "gn:name":"Jasna G\u00f3ra",
    "gn:population":0,
    "gn:timezone":"Europe/Warsaw",
    "iso:country":"PL",
    "wof:name":"Jasna Gora",
    "wof:placetype":"locality"
},
  "geometry": {"coordinates":[18.45643,51.14834000000001],"type":"Point"}
}