{
  "type": "Feature",
  "properties": {
    "gn:admin1_code":"72.0",
    "gn:admin2_code":"214.0",
    "gn:admin3_code":"21402.0",
    "gn:asciiname":"Wabienice",
    "gn:country_code":"PL",
    "gn:dem":185,
    "gn:feature_class":"P",
    "gn:feature_code":"PPL",
    "gn:name":"Wabienice",
    "gn:population":0,
    "gn:timezone":"Europe/Warsaw",
    "iso:country":"PL",
    "name:pol_x_preferred":[
        "Wabienice"
    ],
    "name:ukr_x_preferred":[
        "\u0412\u0430\u0431\u0435\u043d\u0456\u0446\u0435"
    ],
    "name:und_x_variant":[
        "Ober Wabnitz",
        "Wabnitz"
    ],
    "wof:name":"Wabienice",
    "wof:placetype":"locality"
},
  "geometry": {"coordinates":[17.58705,51.1816],"type":"Point"}
}