{
  "type": "Feature",
  "properties": {
    "gn:admin1_code":"72.0",
    "gn:admin2_code":"214.0",
    "gn:admin3_code":"21402.0",
    "gn:asciiname":"Wabienice",
    "gn:country_code":"PL",
    "gn:dem":185,
    "gn:feature_class":"P",
    "gn:feature_code":"PPL",
    "gn:name":"Wabienice",
    "gn:population":0,
    "gn:timezone":"Europe/Warsaw",
    "iso:country":"PL",
    "name:und_x_variant":[
        "Ober Wabnitz",
        "Wabnitz",
        "Wabienice"
    ],
    "wof:name":"Wabienice",
    "wof:placetype":"locality"
},
  "geometry": {"coordinates":[17.58705,51.1816],"type":"Point"}
}