{
  "type": "Feature",
  "properties": {
    "gn:country":"PL",
    "gn:fcode":"PPL",
    "gn:population":130,
    "iso:country":"PL",
    "name:ast_x_preferred":[
        "My\u015blakowice"
    ],
    "name:ceb_x_preferred":[
        "My\u015blakowice"
    ],
    "name:eng_x_preferred":[
        "My\u015blakowice"
    ],
    "name:fra_x_preferred":[
        "My\u015blakowice"
    ],
    "name:pol_x_preferred":[
        "My\u015blakowice"
    ],
    "name:ukr_x_preferred":[
        "\u041c\u0438\u0441\u043b\u044f\u043a\u043e\u0432\u0456\u0446\u0435"
    ],
    "qs_pg:aaroncc":"PL",
    "qs_pg:gn_country":"PL",
    "qs_pg:gn_fcode":"PPL",
    "qs_pg:gn_pop":130,
    "qs_pg:name":"My\u015blakowice",
    "qs_pg:name_adm0":"Polska",
    "qs_pg:name_adm1":"Mazowieckie",
    "qs_pg:photos_9r":0,
    "qs_pg:photos_sr":0,
    "qs_pg:pop_sr":1,
    "qs_pg:qs_pg_placetype":"locality",
    "qs_pg:qs_pg_placetype_gp":"Town",
    "qs_pg:woe_adm0":23424923,
    "woe:adm0_id":23424923,
    "woe:name_adm0":"Polska",
    "woe:name_adm1":"Mazowieckie",
    "woe:placetype":"Town",
    "wof:name":"My\u015blakowice",
    "wof:placetype":"locality",
    "wof:population":130
},
  "geometry": {"coordinates":[20.47122,51.60192],"type":"Point"}
}