{
  "type": "Feature",
  "properties": {
    "gn:admin1_code":"81.0",
    "gn:admin2_code":"2003.0",
    "gn:admin3_code":"200305.0",
    "gn:asciiname":"Lubieszcze",
    "gn:country_code":"PL",
    "gn:dem":131,
    "gn:feature_class":"P",
    "gn:feature_code":"PPL",
    "gn:name":"Lubieszcze",
    "gn:population":0,
    "gn:timezone":"Europe/Warsaw",
    "iso:country":"PL",
    "name:azb_x_preferred":[
        "\u0644\u0648\u0628\u06cc\u0634\u0686\u0647"
    ],
    "name:ceb_x_preferred":[
        "Lubieszcze"
    ],
    "name:fas_x_preferred":[
        "\u0644\u0648\u0628\u06cc\u0634\u0686\u0647"
    ],
    "name:fra_x_preferred":[
        "Lubieszcze"
    ],
    "name:lit_x_preferred":[
        "Lubie\u0161\u010d\u0117"
    ],
    "name:pol_x_preferred":[
        "Lubieszcze"
    ],
    "name:ukr_x_preferred":[
        "\u041b\u044e\u0431\u0435\u0449\u0435"
    ],
    "name:und_x_variant":[
        "Lubiszcze",
        "Lubieszcze"
    ],
    "wof:name":"Lubieszcze",
    "wof:placetype":"locality"
},
  "geometry": {"coordinates":[22.78208,52.71595],"type":"Point"}
}