{
  "type": "Feature",
  "properties": {
    "gn:admin1_code":"75.0",
    "gn:admin2_code":"619.0",
    "gn:admin3_code":"61904.0",
    "gn:asciiname":"Kolacze",
    "gn:country_code":"PL",
    "gn:dem":164,
    "gn:feature_class":"P",
    "gn:feature_code":"PPL",
    "gn:name":"Ko\u0142acze",
    "gn:population":0,
    "gn:timezone":"Europe/Warsaw",
    "iso:country":"PL",
    "name:azb_x_preferred":[
        "\u06a9\u0648\u0648\u0627\u0686\u0647"
    ],
    "name:fas_x_preferred":[
        "\u06a9\u0648\u0648\u0627\u0686\u0647"
    ],
    "name:fra_x_preferred":[
        "Ko\u0142acze"
    ],
    "name:lit_x_preferred":[
        "Kola\u010d\u0117"
    ],
    "name:pol_x_preferred":[
        "Ko\u0142acze"
    ],
    "name:ukr_x_preferred":[
        "\u041a\u043e\u043b\u0430\u0447\u0435"
    ],
    "wof:name":"Kolacze",
    "wof:placetype":"locality"
},
  "geometry": {"coordinates":[23.32346,51.47155],"type":"Point"}
}