{
  "type": "Feature",
  "properties": {
    "gn:admin1_code":"74.0",
    "gn:admin2_code":"1010.0",
    "gn:admin3_code":"101008.0",
    "gn:asciiname":"Stara Wies",
    "gn:country_code":"PL",
    "gn:dem":192,
    "gn:feature_class":"P",
    "gn:feature_code":"PPL",
    "gn:name":"Stara Wie\u015b",
    "gn:population":0,
    "gn:timezone":"Europe/Warsaw",
    "iso:country":"PL",
    "name:fra_x_preferred":[
        "Stara Wie\u015b"
    ],
    "name:pol_x_preferred":[
        "Stara Wie\u015b"
    ],
    "name:ukr_x_preferred":[
        "\u0421\u0442\u0430\u0440\u0430 \u0412\u0435\u0441\u044c"
    ],
    "wof:name":"Stara Wies",
    "wof:placetype":"locality"
},
  "geometry": {"coordinates":[19.64613,51.28098],"type":"Point"}
}