{
  "type": "Feature",
  "properties": {
    "gn:admin1_code":"74.0",
    "gn:admin2_code":"1013.0",
    "gn:admin3_code":"101302.0",
    "gn:asciiname":"Teodozjow",
    "gn:country_code":"PL",
    "gn:dem":138,
    "gn:feature_class":"P",
    "gn:feature_code":"PPL",
    "gn:name":"Teodozj\u00f3w",
    "gn:population":0,
    "gn:timezone":"Europe/Warsaw",
    "iso:country":"PL",
    "name:ceb_x_preferred":[
        "Teodozj\u00f3w"
    ],
    "name:pol_x_preferred":[
        "Teodozj\u00f3w"
    ],
    "name:ukr_x_preferred":[
        "\u0422\u0435\u043e\u0434\u043e\u0437\u044e\u0432"
    ],
    "wof:name":"Teodozjow",
    "wof:placetype":"locality"
},
  "geometry": {"coordinates":[20.36513,51.80465],"type":"Point"}
}