{
  "type": "Feature",
  "properties": {
    "gn:admin1_code":"78.0",
    "gn:admin2_code":"1413.0",
    "gn:admin3_code":"141308.0",
    "gn:asciiname":"Giednia",
    "gn:country_code":"PL",
    "gn:dem":143,
    "gn:feature_class":"P",
    "gn:feature_code":"PPL",
    "gn:name":"Giednia",
    "gn:population":0,
    "gn:timezone":"Europe/Warsaw",
    "iso:country":"PL",
    "name:ara_x_preferred":[
        "\u063a\u064a\u064a\u062f\u0646\u0627"
    ],
    "name:fra_x_preferred":[
        "Giednia"
    ],
    "name:pol_x_preferred":[
        "Giednia"
    ],
    "name:ukr_x_preferred":[
        "\u0490\u0435\u0434\u043d\u044f"
    ],
    "wof:name":"Giednia",
    "wof:placetype":"locality"
},
  "geometry": {"coordinates":[20.46785,53.06304],"type":"Point"}
}