{
  "type": "Feature",
  "properties": {
    "gn:admin1_code":"73.0",
    "gn:admin2_code":"417.0",
    "gn:admin3_code":"41705.0",
    "gn:asciiname":"Male Radowiska",
    "gn:country_code":"PL",
    "gn:dem":96,
    "gn:feature_class":"P",
    "gn:feature_code":"PPL",
    "gn:name":"Ma\u0142e Radowiska",
    "gn:population":0,
    "gn:timezone":"Europe/Warsaw",
    "iso:country":"PL",
    "name:und_x_variant":[
        "Radowiska Ma\u0142e",
        "Radowska Ma\u0142e",
        "Ma\u0142e Radowiska"
    ],
    "wof:name":"Male Radowiska",
    "wof:placetype":"locality"
},
  "geometry": {"coordinates":[18.97215,53.21564],"type":"Point"}
}