{
  "type": "Feature",
  "properties": {
    "gn:admin1_code":"78.0",
    "gn:admin2_code":"1430.0",
    "gn:admin3_code":"143001.0",
    "gn:asciiname":"Borki",
    "gn:country_code":"PL",
    "gn:dem":375,
    "gn:feature_class":"P",
    "gn:feature_code":"PPL",
    "gn:name":"Borki",
    "gn:population":0,
    "gn:timezone":"Europe/Warsaw",
    "iso:country":"PL",
    "wof:name":"Borki",
    "wof:placetype":"locality"
},
  "geometry": {"coordinates":[20.71963,51.18447000000001],"type":"Point"}
}