{
  "type": "Feature",
  "properties": {
    "gn:admin1_code":"78.0",
    "gn:admin2_code":"1402.0",
    "gn:admin3_code":"140209.0",
    "gn:asciiname":"Bienki Karkuty",
    "gn:country_code":"PL",
    "gn:dem":107,
    "gn:feature_class":"P",
    "gn:feature_code":"PPL",
    "gn:name":"Bie\u0144ki Karkuty",
    "gn:population":0,
    "gn:timezone":"Europe/Warsaw",
    "iso:country":"PL",
    "name:ceb_x_preferred":[
        "Bie\u0144ki Karkuty"
    ],
    "name:fra_x_preferred":[
        "Bie\u0144ki-Karkuty"
    ],
    "name:pol_x_preferred":[
        "Bie\u0144ki-Karkuty"
    ],
    "name:ukr_x_preferred":[
        "\u0411\u0435\u043d\u044c\u043a\u0456-\u041a\u0430\u0440\u043a\u0443\u0442\u0438"
    ],
    "wof:name":"Bienki Karkuty",
    "wof:placetype":"locality"
},
  "geometry": {"coordinates":[20.67528,52.8093],"type":"Point"}
}