{
  "type": "Feature",
  "properties": {
    "gn:admin1_code":"78.0",
    "gn:admin2_code":"1402.0",
    "gn:admin3_code":"140209.0",
    "gn:asciiname":"Bienki Karkuty",
    "gn:country_code":"PL",
    "gn:dem":107,
    "gn:feature_class":"P",
    "gn:feature_code":"PPL",
    "gn:name":"Bie\u0144ki Karkuty",
    "gn:population":0,
    "gn:timezone":"Europe/Warsaw",
    "iso:country":"PL",
    "name:und_x_variant":[
        "Bie\u0144ki Karkuty"
    ],
    "wof:name":"Bienki Karkuty",
    "wof:placetype":"locality"
},
  "geometry": {"coordinates":[20.67528,52.8093],"type":"Point"}
}