{
  "type": "Feature",
  "properties": {
    "gn:admin1_code":"75.0",
    "gn:admin2_code":"612.0",
    "gn:admin3_code":"61202.0",
    "gn:asciiname":"Stefanowka",
    "gn:country_code":"PL",
    "gn:dem":172,
    "gn:feature_class":"P",
    "gn:feature_code":"PPL",
    "gn:name":"Stefan\u00f3wka",
    "gn:population":0,
    "gn:timezone":"Europe/Warsaw",
    "iso:country":"PL",
    "name:fra_x_preferred":[
        "Stefan\u00f3wka"
    ],
    "name:pol_x_preferred":[
        "Stefan\u00f3wka"
    ],
    "name:ukr_x_preferred":[
        "\u0421\u0442\u0435\u0444\u0430\u043d\u0443\u0432\u043a\u0430"
    ],
    "wof:name":"Stefanowka",
    "wof:placetype":"locality"
},
  "geometry": {"coordinates":[21.93764,50.9828],"type":"Point"}
}