{
  "type": "Feature",
  "properties": {
    "gn:admin1_code":"75.0",
    "gn:admin2_code":"620.0",
    "gn:admin3_code":"62004.0",
    "gn:asciiname":"Majdan Wielki",
    "gn:country_code":"PL",
    "gn:dem":265,
    "gn:feature_class":"P",
    "gn:feature_code":"PPL",
    "gn:name":"Majdan Wielki",
    "gn:population":0,
    "gn:timezone":"Europe/Warsaw",
    "iso:country":"PL",
    "name:ceb_x_preferred":[
        "Majdan Wielki"
    ],
    "name:pol_x_preferred":[
        "Majdan Wielki"
    ],
    "name:ukr_x_preferred":[
        "\u041c\u0430\u0439\u0434\u0430\u043d-\u0412\u0435\u043b\u0438\u043a\u0438\u0439"
    ],
    "wof:name":"Majdan Wielki",
    "wof:placetype":"locality"
},
  "geometry": {"coordinates":[23.27217000000001,50.5433],"type":"Point"}
}