{
  "type": "Feature",
  "properties": {
    "gn:country":"PL",
    "gn:fcode":"PPL",
    "gn:population":135,
    "iso:country":"PL",
    "name:ceb_x_preferred":[
        "Zabrodzie"
    ],
    "name:deu_x_preferred":[
        "Zabrodzie"
    ],
    "name:fra_x_preferred":[
        "Zabrodzie"
    ],
    "name:nld_x_preferred":[
        "Zabrodzie"
    ],
    "name:pol_x_preferred":[
        "Zabrodzie"
    ],
    "name:ukr_x_preferred":[
        "\u0417\u0430\u0431\u0440\u043e\u0434\u0437\u0435"
    ],
    "qs_pg:aaroncc":"PL",
    "qs_pg:gn_country":"PL",
    "qs_pg:gn_fcode":"PPL",
    "qs_pg:gn_pop":135,
    "qs_pg:name":"Zabrodzie",
    "qs_pg:name_adm0":"Polska",
    "qs_pg:name_adm1":"Sl\u0105skie",
    "qs_pg:photos_9r":0,
    "qs_pg:photos_sr":0,
    "qs_pg:pop_sr":1,
    "qs_pg:qs_pg_placetype":"locality",
    "qs_pg:qs_pg_placetype_gp":"Town",
    "qs_pg:woe_adm0":23424923,
    "woe:adm0_id":23424923,
    "woe:name_adm0":"Polska",
    "woe:name_adm1":"Sl\u0105skie",
    "woe:placetype":"Town",
    "wof:name":"Zabrodzie",
    "wof:placetype":"locality",
    "wof:population":135
},
  "geometry": {"coordinates":[19.87341,50.49224],"type":"Point"}
}