{
  "type": "Feature",
  "properties": {
    "gn:admin1_code":"78.0",
    "gn:admin2_code":"1419.0",
    "gn:admin3_code":"141903.0",
    "gn:asciiname":"Krzyzanowo",
    "gn:country_code":"PL",
    "gn:dem":88,
    "gn:feature_class":"P",
    "gn:feature_code":"PPL",
    "gn:name":"Krzy\u017canowo",
    "gn:population":0,
    "gn:timezone":"Europe/Warsaw",
    "iso:country":"PL",
    "name:ceb_x_preferred":[
        "Krzy\u017canowo"
    ],
    "name:fra_x_preferred":[
        "Krzy\u017canowo"
    ],
    "name:nld_x_preferred":[
        "Krzy\u017canowo"
    ],
    "name:pol_x_preferred":[
        "Krzy\u017canowo"
    ],
    "name:ukr_x_preferred":[
        "\u041a\u0448\u0438\u0436\u0430\u043d\u043e\u0432\u043e"
    ],
    "wof:name":"Krzyzanowo",
    "wof:placetype":"locality"
},
  "geometry": {"coordinates":[19.53884,52.66186],"type":"Point"}
}