{
  "type": "Feature",
  "properties": {
    "gn:admin1_code":"75.0",
    "gn:admin2_code":"609.0",
    "gn:admin3_code":"60901.0",
    "gn:asciiname":"Matczyn",
    "gn:cc2":"PL",
    "gn:country_code":"PL",
    "gn:dem":213,
    "gn:feature_class":"P",
    "gn:feature_code":"PPL",
    "gn:name":"Matczyn",
    "gn:population":0,
    "gn:timezone":"Europe/Warsaw",
    "iso:country":"PL",
    "name:fra_x_preferred":[
        "Matczyn"
    ],
    "name:pol_x_preferred":[
        "Matczyn"
    ],
    "name:ukr_x_preferred":[
        "\u041c\u0430\u0442\u0447\u0438\u043d"
    ],
    "name:und_x_variant":[
        "Matyczn"
    ],
    "wof:name":"Matczyn",
    "wof:placetype":"locality"
},
  "geometry": {"coordinates":[22.31598,51.20237],"type":"Point"}
}