{
  "type": "Feature",
  "properties": {
    "iso:country":"PL",
    "name:azb_x_preferred":[
        "\u0642\u0645\u06cc\u0646\u0627 \u0648\u0627\u062f\u0648\u0648\u06cc\u062a\u0633\u0647"
    ],
    "name:bel_x_preferred":[
        "\u0412\u0430\u0434\u0430\u0432\u0456\u0446\u044b"
    ],
    "name:deu_x_preferred":[
        "Gmina Wadowice"
    ],
    "name:eus_x_preferred":[
        "Wadowice udalerria"
    ],
    "name:fas_x_preferred":[
        "\u06af\u0645\u06cc\u0646\u0627 \u0648\u0627\u062f\u0648\u0648\u06cc\u062a\u0633\u0647"
    ],
    "name:fra_x_preferred":[
        "Wadowice"
    ],
    "name:nld_x_preferred":[
        "Wadowice"
    ],
    "name:pol_x_preferred":[
        "Wadowice"
    ],
    "name:rus_x_preferred":[
        "\u0412\u0430\u0434\u043e\u0432\u0438\u0446\u0435"
    ],
    "name:slk_x_preferred":[
        "Gmina Wadowice"
    ],
    "name:ukr_x_preferred":[
        "\u0413\u043c\u0456\u043d\u0430 \u0412\u0430\u0434\u043e\u0432\u0456\u0446\u0435"
    ],
    "name:war_x_preferred":[
        "Gmina Wadowice"
    ],
    "qs_pg:aaroncc":"PL",
    "qs_pg:name":"Gmina Wadowice",
    "qs_pg:name_adm0":"Polska",
    "qs_pg:name_adm1":"Ma\u0142opolskie",
    "qs_pg:photos":3,
    "qs_pg:photos_1k":1,
    "qs_pg:photos_9k":1,
    "qs_pg:photos_9r":1,
    "qs_pg:photos_all":3,
    "qs_pg:photos_sr":1,
    "qs_pg:pop_sr":0,
    "qs_pg:qs_pg_placetype":"localadmin",
    "qs_pg:qs_pg_placetype_gp":"LocalAdmin",
    "qs_pg:woe_adm0":23424923,
    "woe:adm0_id":23424923,
    "woe:name_adm0":"Polska",
    "woe:name_adm1":"Ma\u0142opolskie",
    "woe:placetype":"LocalAdmin",
    "wof:name":"Gmina Wadowice",
    "wof:placetype":"localadmin"
},
  "geometry": {"coordinates":[19.533333,49.866667],"type":"Point"}
}