{
  "type": "Feature",
  "properties": {
    "gn:admin1_code":"80.0",
    "gn:admin2_code":"1809.0",
    "gn:admin3_code":"180908.0",
    "gn:asciiname":"Zmijowiska",
    "gn:country_code":"PL",
    "gn:dem":241,
    "gn:feature_class":"P",
    "gn:feature_code":"PPL",
    "gn:name":"\u017bmijowiska",
    "gn:population":0,
    "gn:timezone":"Europe/Warsaw",
    "iso:country":"PL",
    "name:pol_x_preferred":[
        "\u017bmijowiska"
    ],
    "name:ukr_x_preferred":[
        "\u0417\u043c\u0456\u0454\u0432\u0438\u0441\u044c\u043a\u0430"
    ],
    "wof:name":"Zmijowiska",
    "wof:placetype":"locality"
},
  "geometry": {"coordinates":[23.19334,50.02631],"type":"Point"}
}