{
  "type": "Feature",
  "properties": {
    "gn:admin1_code":"80.0",
    "gn:admin2_code":"1809.0",
    "gn:admin3_code":"180908.0",
    "gn:asciiname":"Zmijowiska",
    "gn:country_code":"PL",
    "gn:dem":241,
    "gn:feature_class":"P",
    "gn:feature_code":"PPL",
    "gn:name":"\u017bmijowiska",
    "gn:population":0,
    "gn:timezone":"Europe/Warsaw",
    "iso:country":"PL",
    "name:und_x_variant":[
        "\u017bmijowiska"
    ],
    "wof:name":"Zmijowiska",
    "wof:placetype":"locality"
},
  "geometry": {"coordinates":[23.19334,50.02631],"type":"Point"}
}