{
  "type": "Feature",
  "properties": {
    "gn:admin1_code":"74.0",
    "gn:admin2_code":"1004.0",
    "gn:admin3_code":"100404.0",
    "gn:asciiname":"Pieczew",
    "gn:country_code":"PL",
    "gn:dem":110,
    "gn:feature_class":"P",
    "gn:feature_code":"PPL",
    "gn:name":"Pieczew",
    "gn:population":0,
    "gn:timezone":"Europe/Warsaw",
    "iso:country":"PL",
    "name:fra_x_preferred":[
        "Pieczew"
    ],
    "name:pol_x_preferred":[
        "Pieczew"
    ],
    "name:ukr_x_preferred":[
        "\u041f\u0435\u0447\u0435\u0432"
    ],
    "wof:name":"Pieczew",
    "wof:placetype":"locality"
},
  "geometry": {"coordinates":[18.92223,52.1356],"type":"Point"}
}