{
  "type": "Feature",
  "properties": {
    "gn:admin1_code":"74.0",
    "gn:admin2_code":"1016.0",
    "gn:admin3_code":"101608.0",
    "gn:asciiname":"Jeziorzec",
    "gn:country_code":"PL",
    "gn:dem":168,
    "gn:feature_class":"P",
    "gn:feature_code":"PPL",
    "gn:name":"Jeziorzec",
    "gn:population":0,
    "gn:timezone":"Europe/Warsaw",
    "iso:country":"PL",
    "name:pol_x_preferred":[
        "Jeziorzec"
    ],
    "name:ukr_x_preferred":[
        "\u0404\u0437\u044c\u043e\u0436\u0435\u0446\u044c"
    ],
    "wof:name":"Jeziorzec",
    "wof:placetype":"locality"
},
  "geometry": {"coordinates":[20.39406,51.63134],"type":"Point"}
}