{
  "type": "Feature",
  "properties": {
    "gn:admin1_code":"78.0",
    "gn:admin2_code":"1422.0",
    "gn:admin3_code":"142203.0",
    "gn:asciiname":"Borkowo Falenta",
    "gn:country_code":"PL",
    "gn:dem":152,
    "gn:feature_class":"P",
    "gn:feature_code":"PPL",
    "gn:name":"Borkowo Falenta",
    "gn:population":0,
    "gn:timezone":"Europe/Warsaw",
    "iso:country":"PL",
    "name:ceb_x_preferred":[
        "Borkowo Falenta"
    ],
    "name:fra_x_preferred":[
        "Borkowo-Falenta"
    ],
    "name:pol_x_preferred":[
        "Borkowo-Falenta"
    ],
    "name:ukr_x_preferred":[
        "\u0411\u043e\u0440\u043a\u043e\u0432\u043e-\u0424\u0430\u043b\u0435\u043d\u0442\u0430"
    ],
    "name:und_x_variant":[
        "Borkowo Fal\u0119ta",
        "Borkowo Falenta"
    ],
    "wof:name":"Borkowo Falenta",
    "wof:placetype":"locality"
},
  "geometry": {"coordinates":[20.761,53.08223],"type":"Point"}
}