{
  "type": "Feature",
  "properties": {
    "gn:admin1_code":"86.0",
    "gn:admin2_code":"3020.0",
    "gn:admin3_code":"302005.0",
    "gn:asciiname":"Czechel",
    "gn:country_code":"PL",
    "gn:dem":122,
    "gn:feature_class":"P",
    "gn:feature_code":"PPL",
    "gn:name":"Czechel",
    "gn:population":0,
    "gn:timezone":"Europe/Warsaw",
    "iso:country":"PL",
    "name:ceb_x_preferred":[
        "Czechel"
    ],
    "name:nld_x_preferred":[
        "Czechel"
    ],
    "name:pol_x_preferred":[
        "Czechel"
    ],
    "name:ukr_x_preferred":[
        "\u0427\u0435\u0445\u0435\u043b\u044c"
    ],
    "wof:name":"Czechel",
    "wof:placetype":"locality"
},
  "geometry": {"coordinates":[17.92463,51.79059],"type":"Point"}
}