{
  "type": "Feature",
  "properties": {
    "gn:admin1_code":"72.0",
    "gn:admin2_code":"217.0",
    "gn:admin3_code":"21705.0",
    "gn:asciiname":"Wawrzyszow",
    "gn:country_code":"PL",
    "gn:dem":197,
    "gn:feature_class":"P",
    "gn:feature_code":"PPL",
    "gn:name":"Wawrzysz\u00f3w",
    "gn:population":0,
    "gn:timezone":"Europe/Warsaw",
    "iso:country":"PL",
    "name:deu_x_historical":[
        "Lorenzberg"
    ],
    "name:deu_x_preferred":[
        "Lorenzberg"
    ],
    "wof:name":"Wawrzyszow",
    "wof:placetype":"locality"
},
  "geometry": {"coordinates":[17.236,50.73157],"type":"Point"}
}