{
  "type": "Feature",
  "properties": {
    "gn:admin1_code":"72.0",
    "gn:admin2_code":"223.0",
    "gn:admin3_code":"22305.0",
    "gn:asciiname":"Damianowice",
    "gn:country_code":"PL",
    "gn:dem":155,
    "gn:feature_class":"P",
    "gn:feature_code":"PPL",
    "gn:name":"Damianowice",
    "gn:population":0,
    "gn:timezone":"Europe/Warsaw",
    "iso:country":"PL",
    "name:pol_x_preferred":[
        "Damianowice"
    ],
    "name:ukr_x_preferred":[
        "\u0414\u0430\u043c\u044f\u043d\u043e\u0432\u0456\u0446\u0435"
    ],
    "wof:name":"Damianowice",
    "wof:placetype":"locality"
},
  "geometry": {"coordinates":[16.85338,50.91911],"type":"Point"}
}