{
  "type": "Feature",
  "properties": {
    "gn:admin1_code":"72.0",
    "gn:admin2_code":"223.0",
    "gn:admin3_code":"22305.0",
    "gn:asciiname":"Damianowice",
    "gn:country_code":"PL",
    "gn:dem":155,
    "gn:feature_class":"P",
    "gn:feature_code":"PPL",
    "gn:name":"Damianowice",
    "gn:population":0,
    "gn:timezone":"Europe/Warsaw",
    "iso:country":"PL",
    "wof:name":"Damianowice",
    "wof:placetype":"locality"
},
  "geometry": {"coordinates":[16.85338,50.91911],"type":"Point"}
}