{
  "type": "Feature",
  "properties": {
    "gn:admin1_code":"83.0",
    "gn:admin2_code":"2411.0",
    "gn:admin3_code":"241108.0",
    "gn:asciiname":"Strzybnik",
    "gn:country_code":"PL",
    "gn:dem":220,
    "gn:feature_class":"P",
    "gn:feature_code":"PPL",
    "gn:name":"Strzybnik",
    "gn:population":0,
    "gn:timezone":"Europe/Warsaw",
    "iso:country":"PL",
    "name:ceb_x_preferred":[
        "Strzybnik"
    ],
    "name:deu_x_preferred":[
        "Strzybnik"
    ],
    "name:pol_x_preferred":[
        "Strzybnik"
    ],
    "name:ukr_x_preferred":[
        "\u0421\u0442\u0448\u0438\u0431\u043d\u0438\u043a"
    ],
    "wof:name":"Strzybnik",
    "wof:placetype":"locality"
},
  "geometry": {"coordinates":[18.16623,50.13509000000001],"type":"Point"}
}