{
  "type": "Feature",
  "properties": {
    "gn:admin1_code":"75.0",
    "gn:admin2_code":"615.0",
    "gn:admin3_code":"61506.0",
    "gn:asciiname":"Pludy",
    "gn:country_code":"PL",
    "gn:dem":154,
    "gn:feature_class":"P",
    "gn:feature_code":"PPL",
    "gn:name":"P\u0142udy",
    "gn:population":0,
    "gn:timezone":"Europe/Warsaw",
    "iso:country":"PL",
    "name:ceb_x_preferred":[
        "P\u0142udy"
    ],
    "name:fra_x_preferred":[
        "P\u0142udy"
    ],
    "name:pol_x_preferred":[
        "P\u0142udy"
    ],
    "name:ukr_x_preferred":[
        "\u041f\u043b\u0443\u0434\u0438"
    ],
    "wof:name":"Pludy",
    "wof:placetype":"locality"
},
  "geometry": {"coordinates":[22.62228,51.83631],"type":"Point"}
}