{
  "type": "Feature",
  "properties": {
    "gn:country":"PL",
    "gn:fcode":"PPL",
    "gn:population":0,
    "iso:country":"PL",
    "name:ast_x_preferred":[
        "Pr\u0105dnik Korzkiewski"
    ],
    "name:ces_x_preferred":[
        "Pr\u0105dnik Korzkiewski"
    ],
    "name:che_x_preferred":[
        "\u041f\u0440\u043e\u043d\u0434\u043d\u0438\u043a-\u041a\u043e\u0436\u043a\u0435\u0432\u0441\u043a\u0438\u0439"
    ],
    "name:eng_x_preferred":[
        "Pr\u0105dnik Korzkiewski"
    ],
    "name:fra_x_preferred":[
        "Pr\u0105dnik Korzkiewski"
    ],
    "name:nan_x_preferred":[
        "Pr\u0105dnik Korzkiewski"
    ],
    "name:pol_x_preferred":[
        "Pr\u0105dnik Korzkiewski"
    ],
    "name:rus_x_preferred":[
        "\u041f\u0440\u043e\u043d\u0434\u043d\u0438\u043a-\u041a\u043e\u0436\u043a\u0435\u0432\u0441\u043a\u0438\u0439"
    ],
    "name:tat_x_preferred":[
        "\u041f\u0440\u043e\u043d\u0434\u043d\u0438\u043a-\u041a\u043e\u0436\u043a\u0435\u0432\u0441\u043a\u0438\u0439"
    ],
    "name:ukr_x_preferred":[
        "\u041f\u0440\u043e\u043d\u0434\u043d\u0438\u043a-\u041a\u043e\u0436\u043a\u0435\u0432\u0441\u044c\u043a\u0438\u0439"
    ],
    "qs_pg:aaroncc":"PL",
    "qs_pg:gn_country":"PL",
    "qs_pg:gn_fcode":"PPL",
    "qs_pg:gn_pop":0,
    "qs_pg:name":"Pr\u0105dnik Korzkiewski",
    "qs_pg:name_adm0":"Polska",
    "qs_pg:name_adm1":"Ma\u0142opolskie",
    "qs_pg:photos_9r":0,
    "qs_pg:photos_sr":0,
    "qs_pg:pop_sr":0,
    "qs_pg:qs_pg_placetype":"locality",
    "qs_pg:qs_pg_placetype_gp":"Town",
    "qs_pg:woe_adm0":23424923,
    "woe:adm0_id":23424923,
    "woe:name_adm0":"Polska",
    "woe:name_adm1":"Ma\u0142opolskie",
    "woe:placetype":"Town",
    "wof:name":"Pr\u0105dnik Korzkiewski",
    "wof:placetype":"locality"
},
  "geometry": {"coordinates":[19.8559,50.17014],"type":"Point"}
}