{
  "type": "Feature",
  "properties": {
    "gn:admin1_code":"82.0",
    "gn:admin2_code":"2213.0",
    "gn:admin3_code":"221304.0",
    "gn:asciiname":"Grabowiec",
    "gn:country_code":"PL",
    "gn:dem":65,
    "gn:feature_class":"P",
    "gn:feature_code":"PPL",
    "gn:name":"Grabowiec",
    "gn:population":0,
    "gn:timezone":"Europe/Warsaw",
    "iso:country":"PL",
    "name:ceb_x_preferred":[
        "Grabowiec"
    ],
    "name:deu_x_preferred":[
        "Grabowiec"
    ],
    "name:fra_x_preferred":[
        "Grabowiec"
    ],
    "name:lit_x_preferred":[
        "Graboviecas"
    ],
    "name:nld_x_preferred":[
        "Grabowiec"
    ],
    "name:pol_x_preferred":[
        "Grabowiec"
    ],
    "name:ukr_x_preferred":[
        "\u0490\u0440\u0430\u0431\u043e\u0432\u0435\u0446\u044c"
    ],
    "wof:name":"Grabowiec",
    "wof:placetype":"locality"
},
  "geometry": {"coordinates":[18.61001,53.905],"type":"Point"}
}