{
  "type": "Feature",
  "properties": {
    "gn:admin1_code":"82.0",
    "gn:admin2_code":"2213.0",
    "gn:admin3_code":"221304.0",
    "gn:asciiname":"Grabowiec",
    "gn:country_code":"PL",
    "gn:dem":65,
    "gn:feature_class":"P",
    "gn:feature_code":"PPL",
    "gn:name":"Grabowiec",
    "gn:population":0,
    "gn:timezone":"Europe/Warsaw",
    "iso:country":"PL",
    "wof:name":"Grabowiec",
    "wof:placetype":"locality"
},
  "geometry": {"coordinates":[18.61001,53.905],"type":"Point"}
}