{
  "type": "Feature",
  "properties": {
    "gn:admin1_code":"75.0",
    "gn:admin2_code":"611.0",
    "gn:admin3_code":"61107.0",
    "gn:asciiname":"Kosuty",
    "gn:country_code":"PL",
    "gn:dem":167,
    "gn:feature_class":"P",
    "gn:feature_code":"PPL",
    "gn:name":"Kosuty",
    "gn:population":0,
    "gn:timezone":"Europe/Warsaw",
    "iso:country":"PL",
    "name:ceb_x_preferred":[
        "Kosuty"
    ],
    "name:fra_x_preferred":[
        "Kosuty"
    ],
    "name:pol_x_preferred":[
        "Kosuty"
    ],
    "name:ukr_x_preferred":[
        "\u041a\u043e\u0441\u0443\u0442\u0438"
    ],
    "wof:name":"Kosuty",
    "wof:placetype":"locality"
},
  "geometry": {"coordinates":[22.1634,51.87383],"type":"Point"}
}