{
  "type": "Feature",
  "properties": {
    "gn:admin1_code":"77.0",
    "gn:admin2_code":"1210.0",
    "gn:admin3_code":"121006.0",
    "gn:asciiname":"Posadowa",
    "gn:country_code":"PL",
    "gn:dem":442,
    "gn:feature_class":"P",
    "gn:feature_code":"PPL",
    "gn:name":"Posadowa",
    "gn:population":0,
    "gn:timezone":"Europe/Warsaw",
    "iso:country":"PL",
    "wof:name":"Posadowa",
    "wof:placetype":"locality"
},
  "geometry": {"coordinates":[20.85,49.66667],"type":"Point"}
}