{
  "type": "Feature",
  "properties": {
    "gn:admin1_code":"82.0",
    "gn:admin2_code":"2205.0",
    "gn:admin3_code":"220501.0",
    "gn:asciiname":"Reskowo",
    "gn:country_code":"PL",
    "gn:dem":168,
    "gn:feature_class":"P",
    "gn:feature_code":"PPL",
    "gn:name":"Reskowo",
    "gn:population":0,
    "gn:timezone":"Europe/Warsaw",
    "iso:country":"PL",
    "name:ceb_x_preferred":[
        "Reskowo"
    ],
    "name:csb_x_preferred":[
        "Resk\u00f2w\u00f2"
    ],
    "name:pol_x_preferred":[
        "Reskowo"
    ],
    "name:ukr_x_preferred":[
        "\u0420\u0435\u0441\u043a\u043e\u0432\u043e"
    ],
    "wof:name":"Reskowo",
    "wof:placetype":"locality"
},
  "geometry": {"coordinates":[18.06194,54.33727],"type":"Point"}
}