{
  "type": "Feature",
  "properties": {
    "gn:gn_country":"PL",
    "gn:gn_fcode":"ADM4",
    "gn:gn_pop":165610,
    "gn:population":165610,
    "iso:country":"PL",
    "qs_pg:aaroncc":"PL",
    "qs_pg:gn_country":"PL",
    "qs_pg:gn_fcode":"ADM4",
    "qs_pg:gn_pop":165610,
    "qs_pg:name":"Krzyki",
    "qs_pg:photos_9r":0,
    "qs_pg:photos_sr":0,
    "qs_pg:pop_sr":9,
    "qs_pg:qs_pg_placetype":"localadmin",
    "wof:name":"Krzyki",
    "wof:placetype":"localadmin",
    "wof:population":165610
},
  "geometry": {"coordinates":[17.05336,51.07845],"type":"Point"}
}