{
  "type": "Feature",
  "properties": {
    "gn:admin1_code":"81.0",
    "gn:admin2_code":"2010.0",
    "gn:admin3_code":"201003.0",
    "gn:asciiname":"Zareby",
    "gn:country_code":"PL",
    "gn:dem":165,
    "gn:feature_class":"P",
    "gn:feature_code":"PPL",
    "gn:name":"Zar\u0119by",
    "gn:population":0,
    "gn:timezone":"Europe/Warsaw",
    "iso:country":"PL",
    "name:fra_x_preferred":[
        "Zar\u0119by"
    ],
    "name:lit_x_preferred":[
        "Zarembai"
    ],
    "name:pol_x_preferred":[
        "Zar\u0119by"
    ],
    "name:ukr_x_preferred":[
        "\u0417\u0430\u0440\u0435\u043c\u0431\u0438"
    ],
    "name:und_x_variant":[
        "Zar\u0119by"
    ],
    "wof:name":"Zareby",
    "wof:placetype":"locality"
},
  "geometry": {"coordinates":[22.88179,52.56435],"type":"Point"}
}