{
  "type": "Feature",
  "properties": {
    "gn:country":"PL",
    "gn:fcode":"PPL",
    "gn:population":580,
    "iso:country":"PL",
    "name:azb_x_preferred":[
        "\u06cc\u0627\u0634\u0648\u06cc\u0648\u0647"
    ],
    "name:eng_x_preferred":[
        "Ja\u015bwi\u0142y"
    ],
    "name:fas_x_preferred":[
        "\u06cc\u0627\u0634\u0648\u06cc\u0648\u0647"
    ],
    "name:fra_x_preferred":[
        "Ja\u015bwi\u0142y"
    ],
    "name:lit_x_preferred":[
        "Ja\u0161viliai"
    ],
    "name:nld_x_preferred":[
        "Ja\u015bwi\u0142y"
    ],
    "name:pol_x_preferred":[
        "Ja\u015bwi\u0142y"
    ],
    "name:rus_x_preferred":[
        "\u042f\u0441\u0432\u0438\u043b\u044b"
    ],
    "name:szl_x_preferred":[
        "Ja\u015bwi\u0142y"
    ],
    "name:ukr_x_preferred":[
        "\u042f\u0441\u044c\u0432\u0456\u043b\u0438"
    ],
    "name:und_x_variant":[
        "Ja\u015bwity"
    ],
    "name:urd_x_preferred":[
        "\u062c\u0627\u0633\u0648\u06cc\u0648\u06cc"
    ],
    "qs_pg:aaroncc":"PL",
    "qs_pg:gn_country":"PL",
    "qs_pg:gn_fcode":"PPL",
    "qs_pg:gn_pop":580,
    "qs_pg:name":"Ja\u015bwi\u0142y",
    "qs_pg:name_adm0":"Polska",
    "qs_pg:name_adm1":"Podlaskie",
    "qs_pg:photos_9r":0,
    "qs_pg:photos_sr":0,
    "qs_pg:pop_sr":2,
    "qs_pg:qs_pg_placetype":"locality",
    "qs_pg:qs_pg_placetype_gp":"Town",
    "qs_pg:woe_adm0":23424923,
    "woe:adm0_id":23424923,
    "woe:name_adm0":"Polska",
    "woe:name_adm1":"Podlaskie",
    "woe:placetype":"Town",
    "wof:coterminous":[
        1125385667
    ],
    "wof:name":"Ja\u015bwi\u0142y",
    "wof:placetype":"locality",
    "wof:population":580
},
  "geometry": {"coordinates":[22.94941,53.47977],"type":"Point"}
}