{
  "type": "Feature",
  "properties": {
    "gn:admin1_code":"81.0",
    "gn:admin2_code":"2014.0",
    "gn:admin3_code":"201404.0",
    "gn:asciiname":"Wyszomierz Wielki",
    "gn:country_code":"PL",
    "gn:dem":132,
    "gn:feature_class":"P",
    "gn:feature_code":"PPL",
    "gn:name":"Wyszomierz Wielki",
    "gn:population":0,
    "gn:timezone":"Europe/Warsaw",
    "iso:country":"PL",
    "name:und_x_variant":[
        "Wyszomierz",
        "Wyszomierz Wielki"
    ],
    "wof:name":"Wyszomierz Wielki",
    "wof:placetype":"locality"
},
  "geometry": {"coordinates":[22.05868,52.88554],"type":"Point"}
}