{
  "type": "Feature",
  "properties": {
    "gn:admin1_code":"78.0",
    "gn:admin2_code":"1425.0",
    "gn:admin3_code":"142503.0",
    "gn:asciiname":"Alojzow",
    "gn:country_code":"PL",
    "gn:dem":195,
    "gn:feature_class":"P",
    "gn:feature_code":"PPL",
    "gn:name":"Alojz\u00f3w",
    "gn:population":0,
    "gn:timezone":"Europe/Warsaw",
    "iso:country":"PL",
    "name:azb_x_preferred":[
        "\u0627\u0644\u0648\u06cc\u0632\u0627\u0648"
    ],
    "name:ceb_x_preferred":[
        "Alojz\u00f3w"
    ],
    "name:fas_x_preferred":[
        "\u0627\u0644\u0648\u06cc\u0632\u0627\u0648"
    ],
    "name:fra_x_preferred":[
        "Alojz\u00f3w"
    ],
    "name:pol_x_preferred":[
        "Alojz\u00f3w"
    ],
    "name:ukr_x_preferred":[
        "\u0410\u043b\u044c\u043e\u0439\u0437\u0443\u0432"
    ],
    "wof:name":"Alojzow",
    "wof:placetype":"locality"
},
  "geometry": {"coordinates":[21.25163,51.22429],"type":"Point"}
}