{
  "type": "Feature",
  "properties": {
    "gn:country":"PL",
    "gn:fcode":"PPL",
    "gn:population":232,
    "iso:country":"PL",
    "name:ceb_x_preferred":[
        "Wysoka"
    ],
    "name:csb_x_preferred":[
        "W\u00ebsok\u00f4"
    ],
    "name:deu_x_preferred":[
        "Wysoka"
    ],
    "name:epo_x_preferred":[
        "Wysoka"
    ],
    "name:fra_x_preferred":[
        "Wysoka"
    ],
    "name:lav_x_preferred":[
        "Visoka"
    ],
    "name:msa_x_preferred":[
        "Wysoka"
    ],
    "name:nld_x_preferred":[
        "Wysoka"
    ],
    "name:pol_x_preferred":[
        "Wysoka"
    ],
    "name:por_x_preferred":[
        "Wysoka"
    ],
    "name:ron_x_preferred":[
        "Wysoka"
    ],
    "name:rus_x_preferred":[
        "\u0412\u044b\u0441\u043e\u043a\u0430"
    ],
    "name:slk_x_preferred":[
        "Wysoka"
    ],
    "name:srp_x_preferred":[
        "\u0412\u0438\u0441\u043e\u043a\u0430"
    ],
    "name:swe_x_preferred":[
        "Wysoka"
    ],
    "name:ukr_x_preferred":[
        "\u0412\u0438\u0441\u043e\u043a\u0430"
    ],
    "name:vie_x_preferred":[
        "Wysoka"
    ],
    "name:zho_x_preferred":[
        "\u7dad\u7d22\u5361"
    ],
    "qs_pg:aaroncc":"PL",
    "qs_pg:gn_country":"PL",
    "qs_pg:gn_fcode":"PPL",
    "qs_pg:gn_pop":232,
    "qs_pg:name":"Wysoka",
    "qs_pg:name_adm0":"Polska",
    "qs_pg:name_adm1":"Lubuskie",
    "qs_pg:photos":50,
    "qs_pg:photos_1k":10,
    "qs_pg:photos_9k":1,
    "qs_pg:photos_9r":2,
    "qs_pg:photos_all":50,
    "qs_pg:photos_sr":2,
    "qs_pg:pop_sr":2,
    "qs_pg:qs_pg_placetype":"locality",
    "qs_pg:qs_pg_placetype_gp":"Town",
    "qs_pg:woe_adm0":23424923,
    "woe:adm0_id":23424923,
    "woe:name_adm0":"Polska",
    "woe:name_adm1":"Lubuskie",
    "woe:placetype":"Town",
    "wof:name":"Wysoka",
    "wof:placetype":"locality",
    "wof:population":232
},
  "geometry": {"coordinates":[15.46214,52.37586],"type":"Point"}
}