{
  "type": "Feature",
  "properties": {
    "gn:admin1_code":"82.0",
    "gn:admin2_code":"2212.0",
    "gn:admin3_code":"221208.0",
    "gn:asciiname":"Wlynkowo",
    "gn:country_code":"PL",
    "gn:dem":26,
    "gn:feature_class":"P",
    "gn:feature_code":"PPL",
    "gn:name":"W\u0142ynkowo",
    "gn:population":0,
    "gn:timezone":"Europe/Warsaw",
    "iso:country":"PL",
    "name:und_x_variant":[
        "W\u0142ynkowo"
    ],
    "wof:name":"Wlynkowo",
    "wof:placetype":"locality"
},
  "geometry": {"coordinates":[17.00959,54.51772],"type":"Point"}
}