{
  "type": "Feature",
  "properties": {
    "gn:admin1_code":"85.0",
    "gn:admin2_code":"2814.0",
    "gn:admin3_code":"281408.0",
    "gn:asciiname":"Kruzy",
    "gn:cc2":"PL",
    "gn:country_code":"PL",
    "gn:dem":176,
    "gn:feature_class":"P",
    "gn:feature_code":"PPL",
    "gn:name":"Kruzy",
    "gn:population":0,
    "gn:timezone":"Europe/Warsaw",
    "iso:country":"PL",
    "name:pol_x_preferred":[
        "Kruzy"
    ],
    "name:ukr_x_preferred":[
        "\u041a\u0440\u0443\u0437\u0438"
    ],
    "name:und_x_variant":[
        "Krausen"
    ],
    "wof:name":"Kruzy",
    "wof:placetype":"locality"
},
  "geometry": {"coordinates":[20.94664,53.96245],"type":"Point"}
}