{
  "type": "Feature",
  "properties": {
    "gn:admin1_code":"78.0",
    "gn:admin2_code":"1411.0",
    "gn:admin3_code":"141110.0",
    "gn:asciiname":"Makowica",
    "gn:country_code":"PL",
    "gn:dem":104,
    "gn:feature_class":"P",
    "gn:feature_code":"PPL",
    "gn:name":"Makowica",
    "gn:population":0,
    "gn:timezone":"Europe/Warsaw",
    "iso:country":"PL",
    "name:fra_x_preferred":[
        "Makowica"
    ],
    "name:pol_x_preferred":[
        "Makowica"
    ],
    "name:ukr_x_preferred":[
        "\u041c\u0430\u043a\u043e\u0432\u0438\u0446\u044f"
    ],
    "name:und_x_variant":[
        "Markowica"
    ],
    "wof:name":"Makowica",
    "wof:placetype":"locality"
},
  "geometry": {"coordinates":[21.13924,52.86085],"type":"Point"}
}