{
  "type": "Feature",
  "properties": {
    "gn:admin1_code":"82.0",
    "gn:admin2_code":"2209.0",
    "gn:admin3_code":"220906.0",
    "gn:asciiname":"Gnojewo",
    "gn:country_code":"PL",
    "gn:dem":4,
    "gn:feature_class":"P",
    "gn:feature_code":"PPL",
    "gn:name":"Gnojewo",
    "gn:population":0,
    "gn:timezone":"Europe/Warsaw",
    "iso:country":"PL",
    "name:ceb_x_preferred":[
        "Gnojewo"
    ],
    "name:nld_x_preferred":[
        "Gnojewo"
    ],
    "name:pol_x_preferred":[
        "Gnojewo"
    ],
    "name:ukr_x_preferred":[
        "\u0490\u043d\u043e\u0454\u0432\u043e"
    ],
    "wof:name":"Gnojewo",
    "wof:placetype":"locality"
},
  "geometry": {"coordinates":[18.90487000000001,54.05391],"type":"Point"}
}