{
  "type": "Feature",
  "properties": {
    "gn:admin1_code":"75.0",
    "gn:admin2_code":"604.0",
    "gn:admin3_code":"60402.0",
    "gn:asciiname":"Zabcze",
    "gn:country_code":"PL",
    "gn:dem":240,
    "gn:feature_class":"P",
    "gn:feature_code":"PPL",
    "gn:name":"Zabcze",
    "gn:population":0,
    "gn:timezone":"Europe/Warsaw",
    "iso:country":"PL",
    "name:azb_x_preferred":[
        "\u0698\u0627\u0628\u0686\u0647"
    ],
    "name:fas_x_preferred":[
        "\u0698\u0627\u0628\u0686\u0647"
    ],
    "name:fra_x_preferred":[
        "\u017babcze"
    ],
    "name:pol_x_preferred":[
        "\u017babcze"
    ],
    "name:ukr_x_preferred":[
        "\u0416\u0430\u0431\u0447\u0435"
    ],
    "name:urd_x_preferred":[
        "\u0632\u0627\u067e\u062a\u0633 \u0632\u06d2"
    ],
    "wof:name":"Zabcze",
    "wof:placetype":"locality"
},
  "geometry": {"coordinates":[23.98787,50.54902],"type":"Point"}
}