{
  "type": "Feature",
  "properties": {
    "gn:admin1_code":"75.0",
    "gn:admin2_code":"604.0",
    "gn:admin3_code":"60402.0",
    "gn:asciiname":"Zabcze",
    "gn:country_code":"PL",
    "gn:dem":240,
    "gn:feature_class":"P",
    "gn:feature_code":"PPL",
    "gn:name":"Zabcze",
    "gn:population":0,
    "gn:timezone":"Europe/Warsaw",
    "iso:country":"PL",
    "wof:name":"Zabcze",
    "wof:placetype":"locality"
},
  "geometry": {"coordinates":[23.98787,50.54902],"type":"Point"}
}