{
  "type": "Feature",
  "properties": {
    "gn:country":"PL",
    "gn:fcode":"PPLA3",
    "gn:population":4000,
    "iso:country":"PL",
    "name:azb_x_preferred":[
        "\u062a\u0633\u0645\u0648\u0644\u0627\u0633"
    ],
    "name:ceb_x_preferred":[
        "Cmolas"
    ],
    "name:fas_x_preferred":[
        "\u062a\u0633\u0645\u0648\u0644\u0627\u0633"
    ],
    "name:nld_x_preferred":[
        "Cmolas"
    ],
    "name:pol_x_preferred":[
        "Cmolas"
    ],
    "name:szl_x_preferred":[
        "Cmolas"
    ],
    "name:ukr_x_preferred":[
        "\u0426\u043c\u043e\u043b\u044f\u0441"
    ],
    "qs_pg:aaroncc":"PL",
    "qs_pg:gn_country":"PL",
    "qs_pg:gn_fcode":"PPLA3",
    "qs_pg:gn_pop":4000,
    "qs_pg:name":"Cmolas",
    "qs_pg:name_adm0":"Polska",
    "qs_pg:name_adm1":"Podkarpackie",
    "qs_pg:photos_9k":1,
    "qs_pg:photos_9r":1,
    "qs_pg:photos_all":11,
    "qs_pg:photos_sr":0,
    "qs_pg:pop_sr":4,
    "qs_pg:qs_pg_placetype":"localadmin",
    "qs_pg:qs_pg_placetype_gp":"LocalAdmin",
    "qs_pg:woe_adm0":23424923,
    "woe:adm0_id":23424923,
    "woe:name_adm0":"Polska",
    "woe:name_adm1":"Podkarpackie",
    "woe:placetype":"LocalAdmin",
    "wof:name":"Cmolas",
    "wof:placetype":"localadmin",
    "wof:population":4000
},
  "geometry": {"coordinates":[21.74417,50.29526],"type":"Point"}
}