{
  "type": "Feature",
  "properties": {
    "gn:admin1_code":"87.0",
    "gn:admin2_code":"3211.0",
    "gn:admin3_code":"321104.0",
    "gn:asciiname":"Dobieszczyn",
    "gn:country_code":"PL",
    "gn:dem":24,
    "gn:feature_class":"P",
    "gn:feature_code":"PPL",
    "gn:name":"Dobieszczyn",
    "gn:population":0,
    "gn:timezone":"Europe/Warsaw",
    "iso:country":"PL",
    "name:azb_x_preferred":[
        "\u062f\u0648\u0628\u06cc\u0634\u0686\u0646"
    ],
    "name:deu_x_preferred":[
        "Dobieszczyn"
    ],
    "name:fas_x_preferred":[
        "\u062f\u0648\u0628\u06cc\u0634\u0686\u0646"
    ],
    "name:pol_x_preferred":[
        "Dobieszczyn"
    ],
    "name:und_x_variant":[
        "Entep\u00f6l"
    ],
    "name:vie_x_preferred":[
        "Dobieszczyn"
    ],
    "wof:name":"Dobieszczyn",
    "wof:placetype":"locality"
},
  "geometry": {"coordinates":[14.33394,53.60041],"type":"Point"}
}