{
  "type": "Feature",
  "properties": {
    "gn:admin1_code":"74.0",
    "gn:admin2_code":"1008.0",
    "gn:admin3_code":"100807.0",
    "gn:asciiname":"Porszewice",
    "gn:country_code":"PL",
    "gn:dem":174,
    "gn:feature_class":"P",
    "gn:feature_code":"PPL",
    "gn:name":"Porszewice",
    "gn:population":0,
    "gn:timezone":"Europe/Warsaw",
    "iso:country":"PL",
    "name:ceb_x_preferred":[
        "Porszewice"
    ],
    "name:fra_x_preferred":[
        "Porszewice"
    ],
    "name:pol_x_preferred":[
        "Porszewice"
    ],
    "name:ukr_x_preferred":[
        "\u041f\u043e\u0440\u0448\u0435\u0432\u0456\u0446\u0435"
    ],
    "wof:name":"Porszewice",
    "wof:placetype":"locality"
},
  "geometry": {"coordinates":[19.29108,51.71467],"type":"Point"}
}