{
  "type": "Feature",
  "properties": {
    "gn:admin1_code":"84.0",
    "gn:admin2_code":"2603.0",
    "gn:admin3_code":"260301.0",
    "gn:asciiname":"Piotrkowice",
    "gn:country_code":"PL",
    "gn:dem":229,
    "gn:feature_class":"P",
    "gn:feature_code":"PPL",
    "gn:name":"Piotrkowice",
    "gn:population":0,
    "gn:timezone":"Europe/Warsaw",
    "iso:country":"PL",
    "wof:name":"Piotrkowice",
    "wof:placetype":"locality"
},
  "geometry": {"coordinates":[20.64709,50.2359],"type":"Point"}
}