{
  "type": "Feature",
  "properties": {
    "gn:admin1_code":"76.0",
    "gn:admin2_code":"862.0",
    "gn:admin3_code":"86201.0",
    "gn:asciiname":"Rybaki",
    "gn:country_code":"PL",
    "gn:dem":48,
    "gn:feature_class":"P",
    "gn:feature_code":"PPL",
    "gn:name":"Rybaki",
    "gn:population":0,
    "gn:timezone":"Europe/Warsaw",
    "iso:country":"PL",
    "name:fra_x_preferred":[
        "Rybaki"
    ],
    "name:lit_x_preferred":[
        "Ribakai"
    ],
    "name:pol_x_preferred":[
        "Rybaki"
    ],
    "name:ukr_x_preferred":[
        "\u0420\u0438\u0431\u0430\u043a\u0456"
    ],
    "wof:name":"Rybaki",
    "wof:placetype":"locality"
},
  "geometry": {"coordinates":[15.55,52.01667],"type":"Point"}
}