{
  "type": "Feature",
  "properties": {
    "gn:admin1_code":"73.0",
    "gn:admin2_code":"401.0",
    "gn:admin3_code":"40105.0",
    "gn:asciiname":"Lowkowice",
    "gn:country_code":"PL",
    "gn:dem":95,
    "gn:feature_class":"P",
    "gn:feature_code":"PPL",
    "gn:name":"\u0141\u00f3wkowice",
    "gn:population":0,
    "gn:timezone":"Europe/Warsaw",
    "iso:country":"PL",
    "wof:name":"Lowkowice",
    "wof:placetype":"locality"
},
  "geometry": {"coordinates":[18.81271,52.75468000000001],"type":"Point"}
}