{
  "type": "Feature",
  "properties": {
    "gn:admin1_code":"83.0",
    "gn:admin2_code":"2464.0",
    "gn:admin3_code":"246401.0",
    "gn:asciiname":"Kuznica Marianowa Druga",
    "gn:country_code":"PL",
    "gn:dem":265,
    "gn:feature_class":"P",
    "gn:feature_code":"PPL",
    "gn:name":"Ku\u017anica Marianowa Druga",
    "gn:population":0,
    "gn:timezone":"Europe/Warsaw",
    "iso:country":"PL",
    "wof:name":"Kuznica Marianowa Druga",
    "wof:placetype":"locality"
},
  "geometry": {"coordinates":[19.08333,50.75],"type":"Point"}
}