{
  "type": "Feature",
  "properties": {
    "gn:admin1_code":"75.0",
    "gn:admin2_code":"620.0",
    "gn:admin3_code":"62003.0",
    "gn:asciiname":"Szczerbiki",
    "gn:country_code":"PL",
    "gn:dem":204,
    "gn:feature_class":"P",
    "gn:feature_code":"PPL",
    "gn:name":"Szczerbiki",
    "gn:population":0,
    "gn:timezone":"Europe/Warsaw",
    "iso:country":"PL",
    "wof:name":"Szczerbiki",
    "wof:placetype":"locality"
},
  "geometry": {"coordinates":[23.56667,50.63333],"type":"Point"}
}