{
  "type": "Feature",
  "properties": {
    "gn:admin1_code":"76.0",
    "gn:admin2_code":"802.0",
    "gn:admin3_code":"80205.0",
    "gn:asciiname":"Zawada",
    "gn:country_code":"PL",
    "gn:dem":55,
    "gn:feature_class":"P",
    "gn:feature_code":"PPL",
    "gn:name":"Zawada",
    "gn:population":0,
    "gn:timezone":"Europe/Warsaw",
    "iso:country":"PL",
    "name:ceb_x_preferred":[
        "Zawada"
    ],
    "name:ces_x_preferred":[
        "Z\u00e1vada"
    ],
    "name:deu_x_preferred":[
        "Zawada"
    ],
    "name:fra_x_preferred":[
        "Zawada"
    ],
    "name:pol_x_preferred":[
        "Zawada"
    ],
    "name:slk_x_preferred":[
        "Z\u00e1vada"
    ],
    "wof:name":"Zawada",
    "wof:placetype":"locality"
},
  "geometry": {"coordinates":[14.80923,51.92648],"type":"Point"}
}