{
  "type": "Feature",
  "properties": {
    "gn:admin1_code":"86.0",
    "gn:admin2_code":"3028.0",
    "gn:admin3_code":"302802.0",
    "gn:asciiname":"Gruntowice",
    "gn:country_code":"PL",
    "gn:dem":101,
    "gn:feature_class":"P",
    "gn:feature_code":"PPL",
    "gn:name":"Gruntowice",
    "gn:population":0,
    "gn:timezone":"Europe/Warsaw",
    "iso:country":"PL",
    "name:azb_x_preferred":[
        "\u0642\u0631\u0648\u0646\u062a\u0648\u0648\u06cc\u062a\u0633\u0647"
    ],
    "name:fas_x_preferred":[
        "\u06af\u0631\u0648\u0646\u062a\u0648\u0648\u06cc\u062a\u0633\u0647"
    ],
    "name:fra_x_preferred":[
        "Gruntowice"
    ],
    "name:pol_x_preferred":[
        "Gruntowice"
    ],
    "name:ukr_x_preferred":[
        "\u0490\u0440\u0443\u043d\u0442\u043e\u0432\u0456\u0446\u0435"
    ],
    "wof:name":"Gruntowice",
    "wof:placetype":"locality"
},
  "geometry": {"coordinates":[17.42809,52.79726],"type":"Point"}
}