{
  "type": "Feature",
  "properties": {
    "gn:admin1_code":"74.0",
    "gn:admin2_code":"1005.0",
    "gn:admin3_code":"100502.0",
    "gn:asciiname":"Augustowo",
    "gn:country_code":"PL",
    "gn:dem":105,
    "gn:feature_class":"P",
    "gn:feature_code":"PPL",
    "gn:name":"Augustowo",
    "gn:population":0,
    "gn:timezone":"Europe/Warsaw",
    "iso:country":"PL",
    "name:fra_x_preferred":[
        "Augustowo"
    ],
    "name:pol_x_preferred":[
        "Augustowo"
    ],
    "name:rus_x_preferred":[
        "\u0410\u0443\u0433\u0443\u0441\u0442\u043e\u0432\u043e"
    ],
    "name:ukr_x_preferred":[
        "\u0410\u0443\u0491\u0443\u0441\u0442\u043e\u0432\u043e"
    ],
    "wof:name":"Augustowo",
    "wof:placetype":"locality"
},
  "geometry": {"coordinates":[19.59904,52.0566],"type":"Point"}
}