{
  "type": "Feature",
  "properties": {
    "iso:country":"PL",
    "name:ceb_x_preferred":[
        "Kurak"
    ],
    "wof:name":"Kurak",
    "wof:placetype":"neighbourhood"
},
  "geometry": {"coordinates":[19.46046965178871,51.72833973439586],"type":"Point"}
}