{
  "type": "Feature",
  "properties": {
    "gn:admin1_code":"81.0",
    "gn:admin2_code":"2007.0",
    "gn:admin3_code":"200704.0",
    "gn:asciiname":"Jankowo-Mlodzianowo",
    "gn:country_code":"PL",
    "gn:dem":106,
    "gn:feature_class":"P",
    "gn:feature_code":"PPL",
    "gn:name":"Jankowo-M\u0142odzianowo",
    "gn:population":0,
    "gn:timezone":"Europe/Warsaw",
    "iso:country":"PL",
    "name:und_x_variant":[
        "Jankowo-M\u0142odzianowo"
    ],
    "wof:name":"Jankowo-Mlodzianowo",
    "wof:placetype":"locality"
},
  "geometry": {"coordinates":[21.82453,53.20283000000001],"type":"Point"}
}