{
  "type": "Feature",
  "properties": {
    "gn:admin1_code":"81.0",
    "gn:admin2_code":"2007.0",
    "gn:admin3_code":"200704.0",
    "gn:asciiname":"Jankowo-Mlodzianowo",
    "gn:country_code":"PL",
    "gn:dem":106,
    "gn:feature_class":"P",
    "gn:feature_code":"PPL",
    "gn:name":"Jankowo-M\u0142odzianowo",
    "gn:population":0,
    "gn:timezone":"Europe/Warsaw",
    "iso:country":"PL",
    "name:azb_x_preferred":[
        "\u06cc\u0627\u0646\u06a9\u0648\u0648\u0648-\u0645\u0648\u0648\u062c\u0627\u0646\u0648\u0648\u0648"
    ],
    "name:ceb_x_preferred":[
        "Jankowo-M\u0142odzianowo"
    ],
    "name:fas_x_preferred":[
        "\u06cc\u0627\u0646\u06a9\u0648\u0648\u0648-\u0645\u0648\u0648\u062c\u0627\u0646\u0648\u0648\u0648"
    ],
    "name:lit_x_preferred":[
        "Jankovo Mlodzianovas"
    ],
    "name:nld_x_preferred":[
        "Jankowo-M\u0142odzianowo"
    ],
    "name:pol_x_preferred":[
        "Jankowo-M\u0142odzianowo"
    ],
    "name:ukr_x_preferred":[
        "\u042f\u043d\u043a\u043e\u0432\u043e-\u041c\u043b\u043e\u0434\u0437\u044f\u043d\u043e\u0432\u043e"
    ],
    "name:urd_x_preferred":[
        "\u062c\u0627\u0646\u06a9\u0648\u0648-\u0645\u0648\u0648\u062f\u0632\u06cc\u0646\u0648\u0648\u0648"
    ],
    "wof:name":"Jankowo-Mlodzianowo",
    "wof:placetype":"locality"
},
  "geometry": {"coordinates":[21.82453,53.20283000000001],"type":"Point"}
}