{
  "type": "Feature",
  "properties": {
    "gn:admin1_code":"78.0",
    "gn:admin2_code":"1418.0",
    "gn:admin3_code":"141801.0",
    "gn:asciiname":"Dobiesz",
    "gn:country_code":"PL",
    "gn:dem":114,
    "gn:feature_class":"P",
    "gn:feature_code":"PPL",
    "gn:name":"Dobiesz",
    "gn:population":0,
    "gn:timezone":"Europe/Warsaw",
    "iso:country":"PL",
    "name:fra_x_preferred":[
        "Dobiesz"
    ],
    "name:pol_x_preferred":[
        "Dobiesz"
    ],
    "name:ukr_x_preferred":[
        "\u0414\u043e\u0431\u0435\u0448"
    ],
    "wof:name":"Dobiesz",
    "wof:placetype":"locality"
},
  "geometry": {"coordinates":[21.09887,52.00111],"type":"Point"}
}