{
  "type": "Feature",
  "properties": {
    "gn:country":"PL",
    "gn:fcode":"PPL",
    "gn:population":666,
    "iso:country":"PL",
    "name:ast_x_preferred":[
        "Kamienica"
    ],
    "name:ceb_x_preferred":[
        "Kamienica"
    ],
    "name:eng_x_preferred":[
        "Kamienica"
    ],
    "name:fra_x_preferred":[
        "Kamienica"
    ],
    "name:pol_x_preferred":[
        "Kamienica"
    ],
    "name:ukr_x_preferred":[
        "\u041a\u0430\u043c\u0435\u043d\u0438\u0446\u044f"
    ],
    "qs_pg:aaroncc":"PL",
    "qs_pg:gn_country":"PL",
    "qs_pg:gn_fcode":"PPL",
    "qs_pg:gn_pop":666,
    "qs_pg:name":"Kamienica",
    "qs_pg:name_adm0":"Polska",
    "qs_pg:name_adm1":"Sl\u0105skie",
    "qs_pg:photos_9r":0,
    "qs_pg:photos_sr":0,
    "qs_pg:pop_sr":2,
    "qs_pg:qs_pg_placetype":"locality",
    "qs_pg:qs_pg_placetype_gp":"Town",
    "qs_pg:woe_adm0":23424923,
    "woe:adm0_id":23424923,
    "woe:name_adm0":"Polska",
    "woe:name_adm1":"Sl\u0105skie",
    "woe:placetype":"Town",
    "wof:name":"Kamienica",
    "wof:placetype":"locality",
    "wof:population":666
},
  "geometry": {"coordinates":[18.99304,50.63569],"type":"Point"}
}