{
  "type": "Feature",
  "properties": {
    "gn:admin1_code":"82.0",
    "gn:admin2_code":"2216.0",
    "gn:admin3_code":"221603.0",
    "gn:asciiname":"Skolwity",
    "gn:cc2":"PL",
    "gn:country_code":"PL",
    "gn:dem":103,
    "gn:feature_class":"P",
    "gn:feature_code":"PPL",
    "gn:name":"Skolwity",
    "gn:population":0,
    "gn:timezone":"Europe/Warsaw",
    "iso:country":"PL",
    "name:ceb_x_preferred":[
        "Skolwity"
    ],
    "name:pol_x_preferred":[
        "Skolwity"
    ],
    "name:ukr_x_preferred":[
        "\u0421\u043a\u043e\u043b\u044c\u0432\u0456\u0442\u0438"
    ],
    "name:und_x_variant":[
        "Skolwitten",
        "Skollwitten"
    ],
    "wof:name":"Skolwity",
    "wof:placetype":"locality"
},
  "geometry": {"coordinates":[19.55034,53.93962],"type":"Point"}
}