{
  "type": "Feature",
  "properties": {
    "gn:country":"PL",
    "gn:fcode":"PPLA3",
    "gn:population":1800,
    "iso:country":"PL",
    "name:deu_x_preferred":[
        "Lipinki \u0141u\u017cyckie"
    ],
    "name:fas_x_preferred":[
        "\u0644\u06cc\u067e\u06cc\u0646\u06a9\u06cc \u0648\u0648\u0698\u062a\u0633\u06a9\u06cc\u0647"
    ],
    "name:fra_x_preferred":[
        "Lipinki \u0141u\u017cyckie"
    ],
    "name:hsb_x_preferred":[
        "Lindroz"
    ],
    "name:nld_x_preferred":[
        "Lipinki \u0141u\u017cyckie"
    ],
    "name:pol_x_preferred":[
        "Lipinki \u0141u\u017cyckie"
    ],
    "name:ukr_x_preferred":[
        "\u041b\u0456\u043f\u0456\u043d\u043a\u0456-\u041b\u0443\u0436\u0438\u0446\u044c\u043a\u0456"
    ],
    "qs_pg:aaroncc":"PL",
    "qs_pg:gn_country":"PL",
    "qs_pg:gn_fcode":"PPLA3",
    "qs_pg:gn_pop":1800,
    "qs_pg:name":"Lipinki \u0141u\u017cyckie",
    "qs_pg:name_adm0":"Polska",
    "qs_pg:name_adm1":"Lubuskie",
    "qs_pg:photos":1,
    "qs_pg:photos_1k":1,
    "qs_pg:photos_9k":1,
    "qs_pg:photos_9r":1,
    "qs_pg:photos_all":1,
    "qs_pg:photos_sr":1,
    "qs_pg:pop_sr":3,
    "qs_pg:qs_pg_placetype":"localadmin",
    "qs_pg:qs_pg_placetype_gp":"LocalAdmin",
    "qs_pg:woe_adm0":23424923,
    "woe:adm0_id":23424923,
    "woe:name_adm0":"Polska",
    "woe:name_adm1":"Lubuskie",
    "woe:placetype":"LocalAdmin",
    "wof:name":"Lipinki \u0141u\u017cyckie",
    "wof:placetype":"localadmin",
    "wof:population":1800
},
  "geometry": {"coordinates":[14.99874,51.63954],"type":"Point"}
}