{
  "type": "Feature",
  "properties": {
    "gn:admin1_code":"85.0",
    "gn:admin2_code":"2806.0",
    "gn:admin3_code":"280604.0",
    "gn:asciiname":"Kozin",
    "gn:country_code":"PL",
    "gn:dem":117,
    "gn:feature_class":"P",
    "gn:feature_code":"PPL",
    "gn:name":"Kozin",
    "gn:population":0,
    "gn:timezone":"Europe/Warsaw",
    "iso:country":"PL",
    "name:deu_x_preferred":[
        "Kozin"
    ],
    "name:fra_x_preferred":[
        "Kozin"
    ],
    "name:pol_x_preferred":[
        "Kozin"
    ],
    "name:ukr_x_preferred":[
        "\u041a\u043e\u0437\u0456\u043d"
    ],
    "name:und_x_variant":[
        "Rodenau",
        "Koszinnen",
        "Kozinowa",
        "Koszinnen Kreis L\u00f6tzen"
    ],
    "wof:name":"Kozin",
    "wof:placetype":"locality"
},
  "geometry": {"coordinates":[21.71952000000001,53.94657],"type":"Point"}
}