{
  "type": "Feature",
  "properties": {
    "gn:admin1_code":"72.0",
    "gn:admin2_code":"219.0",
    "gn:admin3_code":"21904.0",
    "gn:asciiname":"Nowice",
    "gn:country_code":"PL",
    "gn:dem":216,
    "gn:feature_class":"P",
    "gn:feature_code":"PPL",
    "gn:name":"Nowice",
    "gn:population":0,
    "gn:timezone":"Europe/Warsaw",
    "iso:country":"PL",
    "name:deu_x_preferred":[
        "Nowice"
    ],
    "name:pol_x_preferred":[
        "Nowice"
    ],
    "name:spa_x_preferred":[
        "Nowice"
    ],
    "name:ukr_x_preferred":[
        "\u041d\u043e\u0432\u0456\u0446\u0435"
    ],
    "wof:name":"Nowice",
    "wof:placetype":"locality"
},
  "geometry": {"coordinates":[16.46885,50.91148],"type":"Point"}
}