{
  "type": "Feature",
  "properties": {
    "gn:admin1_code":"86.0",
    "gn:admin2_code":"3002.0",
    "gn:admin3_code":"300208.0",
    "gn:asciiname":"Wrzeszczyna",
    "gn:country_code":"PL",
    "gn:dem":46,
    "gn:feature_class":"P",
    "gn:feature_code":"PPL",
    "gn:name":"Wrzeszczyna",
    "gn:population":0,
    "gn:timezone":"Europe/Warsaw",
    "iso:country":"PL",
    "name:ceb_x_preferred":[
        "Wrzeszczyna"
    ],
    "name:fra_x_preferred":[
        "Wrzeszczyna"
    ],
    "name:pol_x_preferred":[
        "Wrzeszczyna"
    ],
    "name:ukr_x_preferred":[
        "\u0412\u0436\u0435\u0449\u0438\u043d\u0430"
    ],
    "wof:name":"Wrzeszczyna",
    "wof:placetype":"locality"
},
  "geometry": {"coordinates":[16.23627999999999,52.8747],"type":"Point"}
}