{
  "type": "Feature",
  "properties": {
    "gn:country":"PL",
    "gn:fcode":"PPL",
    "gn:population":0,
    "iso:country":"PL",
    "name:ast_x_preferred":[
        "Krzydlina Ma\u0142a"
    ],
    "name:eng_x_preferred":[
        "Krzydlina Ma\u0142a"
    ],
    "name:fra_x_preferred":[
        "Krzydlina Ma\u0142a"
    ],
    "name:nan_x_preferred":[
        "Krzydlina Ma\u0142a"
    ],
    "name:pol_x_preferred":[
        "Krzydlina Ma\u0142a"
    ],
    "name:ukr_x_preferred":[
        "\u041a\u0448\u0438\u0434\u043b\u0456\u043d\u0430-\u041c\u0430\u043b\u0430"
    ],
    "qs_pg:aaroncc":"PL",
    "qs_pg:gn_country":"PL",
    "qs_pg:gn_fcode":"PPL",
    "qs_pg:gn_pop":0,
    "qs_pg:name":"Krzydlina Ma\u0142a",
    "qs_pg:name_adm0":"Polska",
    "qs_pg:name_adm1":"Dolnosl\u0105skie",
    "qs_pg:photos_9r":0,
    "qs_pg:photos_sr":0,
    "qs_pg:pop_sr":0,
    "qs_pg:qs_pg_placetype":"locality",
    "qs_pg:qs_pg_placetype_gp":"Town",
    "qs_pg:woe_adm0":23424923,
    "woe:adm0_id":23424923,
    "woe:name_adm0":"Polska",
    "woe:name_adm1":"Dolnosl\u0105skie",
    "woe:placetype":"Town",
    "wof:name":"Krzydlina Ma\u0142a",
    "wof:placetype":"locality"
},
  "geometry": {"coordinates":[16.53952,51.30024],"type":"Point"}
}