{
  "type": "Feature",
  "properties": {
    "gn:admin1_code":"79.0",
    "gn:admin2_code":"1606.0",
    "gn:admin3_code":"160602.0",
    "gn:asciiname":"Niwki",
    "gn:country_code":"PL",
    "gn:dem":148,
    "gn:feature_class":"P",
    "gn:feature_code":"PPL",
    "gn:name":"Niwki",
    "gn:population":0,
    "gn:timezone":"Europe/Warsaw",
    "iso:country":"PL",
    "name:pol_x_preferred":[
        "Niwki"
    ],
    "name:ukr_x_preferred":[
        "\u041d\u0456\u0432\u043a\u0456"
    ],
    "wof:name":"Niwki",
    "wof:placetype":"locality"
},
  "geometry": {"coordinates":[17.5668,51.05607],"type":"Point"}
}