{
  "type": "Feature",
  "properties": {
    "gn:admin1_code":"75.0",
    "gn:admin2_code":"606.0",
    "gn:admin3_code":"60604.0",
    "gn:asciiname":"Topola",
    "gn:country_code":"PL",
    "gn:dem":193,
    "gn:feature_class":"P",
    "gn:feature_code":"PPL",
    "gn:name":"Topola",
    "gn:population":0,
    "gn:timezone":"Europe/Warsaw",
    "iso:country":"PL",
    "name:fra_x_preferred":[
        "Topola"
    ],
    "name:pol_x_preferred":[
        "Topola"
    ],
    "name:ukr_x_preferred":[
        "\u0422\u043e\u043f\u043e\u043b\u044f"
    ],
    "wof:name":"Topola",
    "wof:placetype":"locality"
},
  "geometry": {"coordinates":[23.20444,50.91399000000001],"type":"Point"}
}