{
  "type": "Feature",
  "properties": {
    "iso:country":"PL",
    "name:dut_x_preferred":[
        "Krajno Pierwsze"
    ],
    "name:eng_x_preferred":[
        "Krajno Pierwsze"
    ],
    "name:fre_x_preferred":[
        "Krajno Pierwsze"
    ],
    "name:nan_x_preferred":[
        "Krajno Pierwsze"
    ],
    "name:pol_x_preferred":[
        "Krajno Pierwsze"
    ],
    "qs_pg:aaroncc":"PL",
    "qs_pg:name":"Krajno Pierwsze",
    "qs_pg:name_adm0":"Polska",
    "qs_pg:name_adm1":"Swi\u0119tokrzyskie",
    "qs_pg:photos":34,
    "qs_pg:photos_1k":7,
    "qs_pg:photos_9k":1,
    "qs_pg:photos_9r":2,
    "qs_pg:photos_all":34,
    "qs_pg:photos_sr":2,
    "qs_pg:pop_sr":0,
    "qs_pg:qs_pg_placetype":"locality",
    "qs_pg:qs_pg_placetype_gp":"Town",
    "qs_pg:woe_adm0":23424923,
    "woe:adm0_id":23424923,
    "woe:name_adm0":"Polska",
    "woe:name_adm1":"Swi\u0119tokrzyskie",
    "woe:placetype":"Town",
    "wof:name":"Krajno Pierwsze",
    "wof:placetype":"locality"
},
  "geometry": {"coordinates":[20.901575,50.893938],"type":"Point"}
}