{
  "type": "Feature",
  "properties": {
    "gn:admin1_code":"85.0",
    "gn:admin2_code":"2808.0",
    "gn:admin3_code":"280802.0",
    "gn:asciiname":"Piskorze",
    "gn:country_code":"PL",
    "gn:dem":46,
    "gn:feature_class":"P",
    "gn:feature_code":"PPL",
    "gn:name":"Piskorze",
    "gn:population":0,
    "gn:timezone":"Europe/Warsaw",
    "iso:country":"PL",
    "name:deu_x_preferred":[
        "Piskorze"
    ],
    "name:pol_x_preferred":[
        "Piskorze"
    ],
    "name:vie_x_preferred":[
        "Piskorze"
    ],
    "wof:name":"Piskorze",
    "wof:placetype":"locality"
},
  "geometry": {"coordinates":[21.24567,54.3028],"type":"Point"}
}