{
  "type": "Feature",
  "properties": {
    "gn:admin1_code":"75.0",
    "gn:admin2_code":"604.0",
    "gn:admin3_code":"60406.0",
    "gn:asciiname":"Molodziatycze",
    "gn:country_code":"PL",
    "gn:dem":216,
    "gn:feature_class":"P",
    "gn:feature_code":"PPL",
    "gn:name":"Mo\u0142odziatycze",
    "gn:population":0,
    "gn:timezone":"Europe/Warsaw",
    "iso:country":"PL",
    "name:fra_x_preferred":[
        "Mo\u0142odiatycze"
    ],
    "name:pol_x_preferred":[
        "Mo\u0142odiatycze"
    ],
    "name:ukr_x_preferred":[
        "\u041c\u043e\u043b\u043e\u0434\u044f\u0442\u0438\u0447\u0435"
    ],
    "name:und_x_variant":[
        "Mo\u0142odziatycze"
    ],
    "wof:name":"Molodziatycze",
    "wof:placetype":"locality"
},
  "geometry": {"coordinates":[23.69337,50.8154],"type":"Point"}
}