{
  "type": "Feature",
  "properties": {
    "gn:admin1_code":"86.0",
    "gn:admin2_code":"3015.0",
    "gn:admin3_code":"301502.0",
    "gn:asciiname":"Zgierzynka",
    "gn:country_code":"PL",
    "gn:dem":98,
    "gn:feature_class":"P",
    "gn:feature_code":"PPL",
    "gn:name":"Zgierzynka",
    "gn:population":0,
    "gn:timezone":"Europe/Warsaw",
    "iso:country":"PL",
    "name:ceb_x_preferred":[
        "Zgierzynka"
    ],
    "name:fra_x_preferred":[
        "Zgierzynka"
    ],
    "name:pol_x_preferred":[
        "Zgierzynka"
    ],
    "name:ukr_x_preferred":[
        "\u0417\u0491\u0435\u0436\u0438\u043d\u043a\u0430"
    ],
    "wof:name":"Zgierzynka",
    "wof:placetype":"locality"
},
  "geometry": {"coordinates":[16.24334,52.46369],"type":"Point"}
}