{
  "type": "Feature",
  "properties": {
    "gn:admin1_code":"74.0",
    "gn:admin2_code":"1002.0",
    "gn:admin3_code":"100211.0",
    "gn:asciiname":"Brzeziny",
    "gn:country_code":"PL",
    "gn:dem":102,
    "gn:feature_class":"P",
    "gn:feature_code":"PPL",
    "gn:name":"Brzeziny",
    "gn:population":0,
    "gn:timezone":"Europe/Warsaw",
    "iso:country":"PL",
    "name:fra_x_preferred":[
        "Brzeziny"
    ],
    "name:pol_x_preferred":[
        "Brzeziny"
    ],
    "name:ukr_x_preferred":[
        "\u0411\u0436\u0435\u0437\u0456\u043d\u0438"
    ],
    "name:und_x_variant":[
        "Brzezinki"
    ],
    "name:urd_x_preferred":[
        "\u0628\u0631\u0632\u0632\u0646\u0646\u06d2"
    ],
    "wof:name":"Brzeziny",
    "wof:placetype":"locality"
},
  "geometry": {"coordinates":[19.66398,52.21181],"type":"Point"}
}