{
  "type": "Feature",
  "properties": {
    "gn:admin1_code":"78.0",
    "gn:admin2_code":"1462.0",
    "gn:admin3_code":"146201.0",
    "gn:asciiname":"Podolszyce",
    "gn:country_code":"PL",
    "gn:dem":98,
    "gn:feature_class":"P",
    "gn:feature_code":"PPL",
    "gn:name":"Podolszyce",
    "gn:population":0,
    "gn:timezone":"Europe/Warsaw",
    "iso:country":"PL",
    "wof:name":"Podolszyce",
    "wof:placetype":"neighbourhood"
},
  "geometry": {"coordinates":[19.75,52.53333000000001],"type":"Point"}
}