{
  "type": "Feature",
  "properties": {
    "gn:admin1_code":"85.0",
    "gn:admin2_code":"2802.0",
    "gn:admin3_code":"280202.0",
    "gn:asciiname":"Krzewno",
    "gn:country_code":"PL",
    "gn:dem":77,
    "gn:feature_class":"P",
    "gn:feature_code":"PPL",
    "gn:name":"Krzewno",
    "gn:population":0,
    "gn:timezone":"Europe/Warsaw",
    "iso:country":"PL",
    "name:ceb_x_preferred":[
        "Krzewno"
    ],
    "name:fra_x_preferred":[
        "Krzewno"
    ],
    "name:pol_x_preferred":[
        "Krzewno"
    ],
    "name:ukr_x_preferred":[
        "\u041a\u0448\u0435\u0432\u043d\u043e"
    ],
    "name:vie_x_preferred":[
        "Krzewno"
    ],
    "wof:name":"Krzewno",
    "wof:placetype":"locality"
},
  "geometry": {"coordinates":[20.02773,54.36606],"type":"Point"}
}