{
  "type": "Feature",
  "properties": {
    "gn:gn_country":"PL",
    "gn:gn_fcode":"PPL",
    "gn:gn_pop":459,
    "gn:population":459,
    "iso:country":"PL",
    "name:eng_x_preferred":[
        "Pojawie"
    ],
    "name:fra_x_preferred":[
        "Pojawie"
    ],
    "name:pol_x_preferred":[
        "Pojawie"
    ],
    "qs_pg:aaroncc":"PL",
    "qs_pg:gn_country":"PL",
    "qs_pg:gn_fcode":"PPL",
    "qs_pg:gn_pop":459,
    "qs_pg:name":"Pojawie",
    "qs_pg:name_adm0":"Polska",
    "qs_pg:name_adm1":"Ma\u0142opolskie",
    "qs_pg:photos_9r":0,
    "qs_pg:photos_sr":0,
    "qs_pg:pop_sr":2,
    "qs_pg:qs_pg_placetype":"locality",
    "qs_pg:qs_pg_placetype_gp":"Town",
    "qs_pg:woe_adm0":23424923,
    "woe:adm0_id":23424923,
    "woe:name_adm0":"Polska",
    "woe:name_adm1":"Ma\u0142opolskie",
    "woe:placetype":"Town",
    "wof:name":"Pojawie",
    "wof:placetype":"locality",
    "wof:population":459
},
  "geometry": {"coordinates":[20.71678,50.14974],"type":"Point"}
}