{
  "type": "Feature",
  "properties": {
    "iso:country":"PL",
    "name:ceb_x_preferred":[
        "Ko\u015bcielec"
    ],
    "name:deu_x_preferred":[
        "Ko\u015bcielec"
    ],
    "name:nld_x_preferred":[
        "Ko\u015bcielec"
    ],
    "name:pol_x_preferred":[
        "Ko\u015bcielec"
    ],
    "name:ukr_x_preferred":[
        "\u041a\u043e\u0441\u044c\u0446\u0435\u043b\u0435\u0446\u044c"
    ],
    "wof:coterminous":[
        1125354045
    ],
    "wof:name":"Ko\u015bcielec",
    "wof:placetype":"locality"
},
  "geometry": {"coordinates":[18.5695375960411,52.1642192027949],"type":"Point"}
}