{
  "type": "Feature",
  "properties": {
    "iso:country":"PL",
    "name:pol_x_preferred":[
        "Ko\u015bcielec"
    ],
    "wof:name":"Ko\u015bcielec",
    "wof:placetype":"locality"
},
  "geometry": {"coordinates":[18.5695375960411,52.1642192027949],"type":"Point"}
}