{
  "type": "Feature",
  "properties": {
    "gn:admin1_code":"76.0",
    "gn:admin2_code":"804.0",
    "gn:admin3_code":"80404.0",
    "gn:asciiname":"Mirocin Dolny",
    "gn:cc2":"PL",
    "gn:country_code":"PL",
    "gn:dem":77,
    "gn:feature_class":"P",
    "gn:feature_code":"PPL",
    "gn:name":"Mirocin Dolny",
    "gn:population":0,
    "gn:timezone":"Europe/Warsaw",
    "iso:country":"PL",
    "name:ceb_x_preferred":[
        "Mirocin Dolny"
    ],
    "name:fra_x_preferred":[
        "Mirocin Dolny"
    ],
    "name:nld_x_preferred":[
        "Mirocin Dolny"
    ],
    "name:pol_x_preferred":[
        "Mirocin Dolny"
    ],
    "name:ukr_x_preferred":[
        "\u041c\u0456\u0440\u043e\u0446\u0438\u043d-\u0414\u043e\u043b\u044c\u043d\u0438"
    ],
    "name:und_x_variant":[
        "Nieder Herzogswaldau",
        "Nieder-Herzogswalde"
    ],
    "wof:name":"Mirocin Dolny",
    "wof:placetype":"locality"
},
  "geometry": {"coordinates":[15.54806,51.78547],"type":"Point"}
}