{
  "type": "Feature",
  "properties": {
    "gn:admin1_code":"83.0",
    "gn:admin2_code":"2417.0",
    "gn:admin3_code":"241712.0",
    "gn:asciiname":"Kocon",
    "gn:country_code":"PL",
    "gn:dem":503,
    "gn:feature_class":"P",
    "gn:feature_code":"PPL",
    "gn:name":"Koco\u0144",
    "gn:population":0,
    "gn:timezone":"Europe/Warsaw",
    "iso:country":"PL",
    "name:ceb_x_preferred":[
        "Koco\u0144"
    ],
    "name:nld_x_preferred":[
        "Koco\u0144"
    ],
    "name:pol_x_preferred":[
        "Koco\u0144"
    ],
    "name:ukr_x_preferred":[
        "\u041a\u043e\u0446\u043e\u043d\u044c"
    ],
    "wof:name":"Kocon",
    "wof:placetype":"locality"
},
  "geometry": {"coordinates":[19.39699,49.72442],"type":"Point"}
}