{
  "type": "Feature",
  "properties": {
    "gn:admin1_code":"73.0",
    "gn:admin2_code":"401.0",
    "gn:admin3_code":"40107.0",
    "gn:asciiname":"Siarzewo",
    "gn:country_code":"PL",
    "gn:dem":42,
    "gn:feature_class":"P",
    "gn:feature_code":"PPL",
    "gn:name":"Siarzewo",
    "gn:population":0,
    "gn:timezone":"Europe/Warsaw",
    "iso:country":"PL",
    "name:pol_x_preferred":[
        "Siarzewo"
    ],
    "name:ukr_x_preferred":[
        "\u0421\u044f\u0436\u0435\u0432\u043e"
    ],
    "wof:name":"Siarzewo",
    "wof:placetype":"locality"
},
  "geometry": {"coordinates":[18.85178,52.86331],"type":"Point"}
}