{
  "type": "Feature",
  "properties": {
    "gn:admin1_code":"75.0",
    "gn:admin2_code":"605.0",
    "gn:admin3_code":"60507.0",
    "gn:asciiname":"Maliniec Swidry",
    "gn:country_code":"PL",
    "gn:dem":186,
    "gn:feature_class":"P",
    "gn:feature_code":"PPL",
    "gn:name":"Maliniec \u015awidry",
    "gn:population":0,
    "gn:timezone":"Europe/Warsaw",
    "iso:country":"PL",
    "name:fra_x_preferred":[
        "Maliniec"
    ],
    "name:pol_x_preferred":[
        "Maliniec"
    ],
    "name:ukr_x_preferred":[
        "\u041c\u0430\u043b\u0456\u043d\u0435\u0446\u044c"
    ],
    "name:und_x_variant":[
        "Maliniec",
        "Maliniec \u015awidry"
    ],
    "wof:name":"Maliniec Swidry",
    "wof:placetype":"locality"
},
  "geometry": {"coordinates":[22.19724,50.70895],"type":"Point"}
}