{
  "type": "Feature",
  "properties": {
    "gn:admin1_code":"86.0",
    "gn:admin2_code":"3015.0",
    "gn:admin3_code":"301501.0",
    "gn:asciiname":"Michorzewko",
    "gn:country_code":"PL",
    "gn:dem":92,
    "gn:feature_class":"P",
    "gn:feature_code":"PPL",
    "gn:name":"Michorzewko",
    "gn:population":0,
    "gn:timezone":"Europe/Warsaw",
    "iso:country":"PL",
    "name:fra_x_preferred":[
        "Michorzewko"
    ],
    "name:pol_x_preferred":[
        "Michorzewko"
    ],
    "name:ukr_x_preferred":[
        "\u041c\u0456\u0445\u043e\u0436\u0435\u0432\u043a\u043e"
    ],
    "wof:name":"Michorzewko",
    "wof:placetype":"locality"
},
  "geometry": {"coordinates":[16.33993,52.35463],"type":"Point"}
}