{
  "type": "Feature",
  "properties": {
    "gn:admin1_code":"81.0",
    "gn:admin2_code":"2011.0",
    "gn:admin3_code":"201105.0",
    "gn:asciiname":"Wojnowce",
    "gn:country_code":"PL",
    "gn:dem":171,
    "gn:feature_class":"P",
    "gn:feature_code":"PPL",
    "gn:name":"Wojnowce",
    "gn:population":0,
    "gn:timezone":"Europe/Warsaw",
    "iso:country":"PL",
    "name:azb_x_preferred":[
        "\u0648\u0648\u06cc\u0646\u0648\u0648\u062a\u0633\u0647"
    ],
    "name:bel_x_preferred":[
        "\u0412\u043e\u0439\u043d\u0430\u045e\u0446\u044b"
    ],
    "name:fas_x_preferred":[
        "\u0648\u0648\u06cc\u0646\u0648\u0648\u062a\u0633\u0647"
    ],
    "name:lit_x_preferred":[
        "Vojnovc\u0117"
    ],
    "name:pol_x_preferred":[
        "Wojnowce"
    ],
    "name:ukr_x_preferred":[
        "\u0412\u043e\u0439\u043d\u043e\u0432\u0446\u0435"
    ],
    "wof:name":"Wojnowce",
    "wof:placetype":"locality"
},
  "geometry": {"coordinates":[23.61151,53.50816],"type":"Point"}
}