{
  "type": "Feature",
  "properties": {
    "gn:admin1_code":"83.0",
    "gn:admin2_code":"2414.0",
    "gn:admin3_code":"241402.0",
    "gn:asciiname":"Pasieczki",
    "gn:country_code":"PL",
    "gn:dem":294,
    "gn:feature_class":"P",
    "gn:feature_code":"PPL",
    "gn:name":"Pasieczki",
    "gn:population":0,
    "gn:timezone":"Europe/Warsaw",
    "iso:country":"PL",
    "wof:name":"Pasieczki",
    "wof:placetype":"locality"
},
  "geometry": {"coordinates":[19.20187,50.15386],"type":"Point"}
}