{
  "type": "Feature",
  "properties": {
    "gn:admin1_code":"82.0",
    "gn:admin2_code":"2206.0",
    "gn:admin3_code":"220607.0",
    "gn:asciiname":"Luban",
    "gn:country_code":"PL",
    "gn:dem":183,
    "gn:feature_class":"P",
    "gn:feature_code":"PPL",
    "gn:name":"Luba\u0144",
    "gn:population":0,
    "gn:timezone":"Europe/Warsaw",
    "iso:country":"PL",
    "name:ceb_x_preferred":[
        "Luba\u0144"
    ],
    "name:csb_x_preferred":[
        "Luba\u0144"
    ],
    "name:pol_x_preferred":[
        "Luba\u0144"
    ],
    "name:ukr_x_preferred":[
        "\u041b\u044e\u0431\u0430\u043d\u044c"
    ],
    "name:und_x_variant":[
        "Luba\u0144"
    ],
    "wof:name":"Luban",
    "wof:placetype":"locality"
},
  "geometry": {"coordinates":[18.16115,54.11743000000001],"type":"Point"}
}