{
  "type": "Feature",
  "properties": {
    "gn:admin1_code":"81.0",
    "gn:admin2_code":"2006.0",
    "gn:admin3_code":"200602.0",
    "gn:asciiname":"Suraly",
    "gn:country_code":"PL",
    "gn:dem":164,
    "gn:feature_class":"P",
    "gn:feature_code":"PPL",
    "gn:name":"Sura\u0142y",
    "gn:population":0,
    "gn:timezone":"Europe/Warsaw",
    "iso:country":"PL",
    "name:ceb_x_preferred":[
        "Sura\u0142y"
    ],
    "name:fra_x_preferred":[
        "Sura\u0142y"
    ],
    "name:lit_x_preferred":[
        "Suralai"
    ],
    "name:pol_x_preferred":[
        "Sura\u0142y"
    ],
    "name:ukr_x_preferred":[
        "\u0421\u0443\u0440\u0430\u043b\u0438"
    ],
    "wof:name":"Suraly",
    "wof:placetype":"locality"
},
  "geometry": {"coordinates":[22.21335,53.5028],"type":"Point"}
}