{
  "type": "Feature",
  "properties": {
    "gn:admin1_code":"85.0",
    "gn:admin2_code":"2801.0",
    "gn:admin3_code":"280105.0",
    "gn:asciiname":"Robity",
    "gn:country_code":"PL",
    "gn:dem":125,
    "gn:feature_class":"P",
    "gn:feature_code":"PPL",
    "gn:name":"Robity",
    "gn:population":0,
    "gn:timezone":"Europe/Warsaw",
    "iso:country":"PL",
    "name:fra_x_preferred":[
        "Robity"
    ],
    "name:pol_x_preferred":[
        "Robity"
    ],
    "wof:name":"Robity",
    "wof:placetype":"locality"
},
  "geometry": {"coordinates":[20.36625,54.39215],"type":"Point"}
}