{
  "type": "Feature",
  "properties": {
    "gn:admin1_code":"75.0",
    "gn:admin2_code":"603.0",
    "gn:admin3_code":"60305.0",
    "gn:asciiname":"Zagornik",
    "gn:country_code":"PL",
    "gn:dem":181,
    "gn:feature_class":"P",
    "gn:feature_code":"PPL",
    "gn:name":"Zag\u00f3rnik",
    "gn:population":0,
    "gn:timezone":"Europe/Warsaw",
    "iso:country":"PL",
    "name:und_x_variant":[
        "Kolonia Zag\u00f3rnik",
        "Zag\u00f3rnik"
    ],
    "wof:name":"Zagornik",
    "wof:placetype":"locality"
},
  "geometry": {"coordinates":[23.93467,50.98378],"type":"Point"}
}