{
  "type": "Feature",
  "properties": {
    "gn:admin1_code":"75.0",
    "gn:admin2_code":"603.0",
    "gn:admin3_code":"60305.0",
    "gn:asciiname":"Zagornik",
    "gn:country_code":"PL",
    "gn:dem":181,
    "gn:feature_class":"P",
    "gn:feature_code":"PPL",
    "gn:name":"Zag\u00f3rnik",
    "gn:population":0,
    "gn:timezone":"Europe/Warsaw",
    "iso:country":"PL",
    "name:azb_x_preferred":[
        "\u0632\u0627\u0642\u0648\u0631\u0646\u0642\u06a9"
    ],
    "name:fas_x_preferred":[
        "\u0632\u0627\u06af\u0648\u0631\u0646\u06af\u06a9"
    ],
    "name:fra_x_preferred":[
        "Zag\u00f3rnik"
    ],
    "name:pol_x_preferred":[
        "Zag\u00f3rnik"
    ],
    "name:ukr_x_preferred":[
        "\u0417\u0430\u0491\u0443\u0440\u043d\u0438\u043a"
    ],
    "name:und_x_variant":[
        "Kolonia Zag\u00f3rnik"
    ],
    "name:urd_x_preferred":[
        "\u0632\u06af\u0648\u0631\u0646\u06a9"
    ],
    "wof:name":"Zagornik",
    "wof:placetype":"locality"
},
  "geometry": {"coordinates":[23.93467,50.98378],"type":"Point"}
}