{
  "type": "Feature",
  "properties": {
    "gn:gn_country":"PL",
    "gn:gn_fcode":"PPL",
    "gn:gn_pop":354,
    "gn:population":354,
    "iso:country":"PL",
    "name:ast_x_preferred":[
        "Rzucewo"
    ],
    "name:ceb_x_preferred":[
        "Rzucewo"
    ],
    "name:csb_x_preferred":[
        "Rzucew\u00f2"
    ],
    "name:deu_x_preferred":[
        "Rzucewo"
    ],
    "name:eng_x_preferred":[
        "Rzucewo"
    ],
    "name:fra_x_preferred":[
        "Rzucewo"
    ],
    "name:nld_x_preferred":[
        "Rzucewo"
    ],
    "name:pol_x_preferred":[
        "Rzucewo"
    ],
    "name:swe_x_preferred":[
        "Rzucewo"
    ],
    "name:ukr_x_preferred":[
        "\u0416\u0443\u0446\u0435\u0432\u043e"
    ],
    "qs_pg:aaroncc":"PL",
    "qs_pg:gn_country":"PL",
    "qs_pg:gn_fcode":"PPL",
    "qs_pg:gn_pop":354,
    "qs_pg:name":"Rzucewo",
    "qs_pg:photos_9r":0,
    "qs_pg:photos_sr":0,
    "qs_pg:pop_sr":2,
    "qs_pg:qs_pg_placetype":"locality",
    "wof:name":"Rzucewo",
    "wof:placetype":"locality",
    "wof:population":354
},
  "geometry": {"coordinates":[18.46287,54.68782],"type":"Point"}
}