{
  "type": "Feature",
  "properties": {
    "gn:admin1_code":"82.0",
    "gn:admin2_code":"2215.0",
    "gn:admin3_code":"221504.0",
    "gn:asciiname":"Ciekocino",
    "gn:country_code":"PL",
    "gn:dem":50,
    "gn:feature_class":"P",
    "gn:feature_code":"PPL",
    "gn:name":"Ciekocino",
    "gn:population":0,
    "gn:timezone":"Europe/Warsaw",
    "iso:country":"PL",
    "name:deu_x_preferred":[
        "Ciekocino"
    ],
    "name:pol_x_preferred":[
        "Ciekocino"
    ],
    "name:ukr_x_preferred":[
        "\u0426\u0435\u043a\u043e\u0446\u0438\u043d\u043e"
    ],
    "wof:name":"Ciekocino",
    "wof:placetype":"locality"
},
  "geometry": {"coordinates":[17.79847999999999,54.74612],"type":"Point"}
}