{
  "type": "Feature",
  "properties": {
    "iso:country":"PL",
    "name:azb_x_preferred":[
        "\u0627\u06cc\u0632\u0628\u06cc\u062a\u0633\u0627"
    ],
    "name:deu_x_preferred":[
        "Izbica"
    ],
    "name:fas_x_preferred":[
        "\u0627\u06cc\u0632\u0628\u06cc\u062a\u0633\u0627"
    ],
    "name:fra_x_preferred":[
        "Izbica"
    ],
    "name:fry_x_preferred":[
        "Izbika"
    ],
    "name:heb_x_preferred":[
        "\u05d0\u05d9\u05d6\u05d1\u05d9\u05e6\u05d4"
    ],
    "name:ita_x_preferred":[
        "Izbica"
    ],
    "name:nld_x_preferred":[
        "Izbica"
    ],
    "name:pol_x_preferred":[
        "Izbica"
    ],
    "name:swe_x_preferred":[
        "Izbica"
    ],
    "name:szl_x_preferred":[
        "Izbica"
    ],
    "name:yid_x_preferred":[
        "\u05d0\u05d9\u05d6\u05e9\u05d1\u05d9\u05e6\u05e2"
    ],
    "wof:coterminous":[
        1125304377
    ],
    "wof:name":"Izbica",
    "wof:placetype":"locality"
},
  "geometry": {"coordinates":[23.10938398144,50.8896481670172],"type":"Point"}
}