{
  "type": "Feature",
  "properties": {
    "gn:admin1_code":"85.0",
    "gn:admin2_code":"2803.0",
    "gn:admin3_code":"280306.0",
    "gn:asciiname":"Rumian",
    "gn:country_code":"PL",
    "gn:dem":162,
    "gn:feature_class":"P",
    "gn:feature_code":"PPL",
    "gn:name":"Rumian",
    "gn:population":0,
    "gn:timezone":"Europe/Warsaw",
    "iso:country":"PL",
    "wof:name":"Rumian",
    "wof:placetype":"locality"
},
  "geometry": {"coordinates":[19.93057,53.41952],"type":"Point"}
}