{
  "type": "Feature",
  "properties": {
    "gn:gn_country":"PL",
    "gn:gn_fcode":"PPLA3",
    "gn:gn_pop":4056,
    "gn:population":4056,
    "iso:country":"PL",
    "name:eng_x_preferred":[
        "G\u0105bin"
    ],
    "name:heb_x_preferred":[
        "\u05d2\u05d5\u05de\u05d1\u05d9\u05df"
    ],
    "name:lav_x_preferred":[
        "Gombina"
    ],
    "name:rus_x_preferred":[
        "\u0413\u043e\u043c\u0431\u0438\u043d"
    ],
    "name:srp_x_preferred":[
        "\u0413\u043e\u043c\u0431\u0438\u043d"
    ],
    "name:ukr_x_preferred":[
        "\u0413\u043e\u043c\u0431\u0456\u043d"
    ],
    "name:zho_x_preferred":[
        "\u8ca2\u8cd3"
    ],
    "qs_pg:aaroncc":"PL",
    "qs_pg:gn_country":"PL",
    "qs_pg:gn_fcode":"PPLA3",
    "qs_pg:gn_pop":4056,
    "qs_pg:name":"G\u0105bin",
    "qs_pg:name_adm0":"Polska",
    "qs_pg:name_adm1":"Mazowieckie",
    "qs_pg:photos":11,
    "qs_pg:photos_1k":2,
    "qs_pg:photos_9k":1,
    "qs_pg:photos_9r":1,
    "qs_pg:photos_all":11,
    "qs_pg:photos_sr":1,
    "qs_pg:pop_sr":7,
    "qs_pg:qs_pg_placetype":"localadmin",
    "qs_pg:qs_pg_placetype_gp":"LocalAdmin",
    "qs_pg:woe_adm0":23424923,
    "woe:adm0_id":23424923,
    "woe:name_adm0":"Polska",
    "woe:name_adm1":"Mazowieckie",
    "woe:placetype":"LocalAdmin",
    "wof:name":"G\u0105bin",
    "wof:placetype":"localadmin",
    "wof:population":4056
},
  "geometry": {"coordinates":[19.73509,52.39849],"type":"Point"}
}