{
  "type": "Feature",
  "properties": {
    "gn:admin1_code":"74.0",
    "gn:admin2_code":"1010.0",
    "gn:admin3_code":"101005.0",
    "gn:asciiname":"Kolonia Zerechowa",
    "gn:country_code":"PL",
    "gn:dem":232,
    "gn:feature_class":"P",
    "gn:feature_code":"PPL",
    "gn:name":"Kolonia Zerechowa",
    "gn:population":0,
    "gn:timezone":"Europe/Warsaw",
    "iso:country":"PL",
    "name:fra_x_preferred":[
        "Kolonia \u017berechowa"
    ],
    "name:pol_x_preferred":[
        "\u017berechowa-Kolonia"
    ],
    "wof:name":"Kolonia Zerechowa",
    "wof:placetype":"locality"
},
  "geometry": {"coordinates":[19.73474,51.2409],"type":"Point"}
}