{
  "type": "Feature",
  "properties": {
    "gn:admin1_code":"84.0",
    "gn:admin2_code":"2606.0",
    "gn:admin3_code":"260605.0",
    "gn:asciiname":"Potok",
    "gn:country_code":"PL",
    "gn:dem":191,
    "gn:feature_class":"P",
    "gn:feature_code":"PPL",
    "gn:name":"Potok",
    "gn:population":0,
    "gn:timezone":"Europe/Warsaw",
    "iso:country":"PL",
    "name:bos_x_preferred":[
        "Potok"
    ],
    "name:ceb_x_preferred":[
        "Potok"
    ],
    "name:deu_x_preferred":[
        "Potok"
    ],
    "name:epo_x_preferred":[
        "Potok"
    ],
    "name:fra_x_preferred":[
        "Potok"
    ],
    "name:hrv_x_preferred":[
        "Potok"
    ],
    "name:hun_x_preferred":[
        "Potok"
    ],
    "name:ita_x_preferred":[
        "Potok"
    ],
    "name:nld_x_preferred":[
        "Potok"
    ],
    "name:pol_x_preferred":[
        "Potok"
    ],
    "name:rue_x_preferred":[
        "\u041f\u043e\u0442\u043e\u043a"
    ],
    "name:sco_x_preferred":[
        "Potok"
    ],
    "name:slk_x_preferred":[
        "Potok"
    ],
    "name:slv_x_preferred":[
        "Potok"
    ],
    "name:swe_x_preferred":[
        "Potok"
    ],
    "name:ukr_x_preferred":[
        "\u041f\u043e\u0442\u043e\u043a"
    ],
    "wof:name":"Potok",
    "wof:placetype":"locality"
},
  "geometry": {"coordinates":[21.64991,50.94600000000001],"type":"Point"}
}