{
  "type": "Feature",
  "properties": {
    "gn:admin1_code":"84.0",
    "gn:admin2_code":"2604.0",
    "gn:admin3_code":"260417.0",
    "gn:asciiname":"Wola Murowana",
    "gn:country_code":"PL",
    "gn:dem":234,
    "gn:feature_class":"P",
    "gn:feature_code":"PPL",
    "gn:name":"Wola Murowana",
    "gn:population":0,
    "gn:timezone":"Europe/Warsaw",
    "iso:country":"PL",
    "wof:name":"Wola Murowana",
    "wof:placetype":"locality"
},
  "geometry": {"coordinates":[20.53267,50.79503],"type":"Point"}
}