{
  "type": "Feature",
  "properties": {
    "gn:admin1_code":"78.0",
    "gn:admin2_code":"1407.0",
    "gn:admin3_code":"140704.0",
    "gn:asciiname":"Budy Augustowskie",
    "gn:country_code":"PL",
    "gn:dem":127,
    "gn:feature_class":"P",
    "gn:feature_code":"PPL",
    "gn:name":"Budy Augustowskie",
    "gn:population":0,
    "gn:timezone":"Europe/Warsaw",
    "iso:country":"PL",
    "name:azb_x_preferred":[
        "\u0628\u0648\u062f \u0627\u0648\u0642\u0648\u0633\u062a\u0648\u0648\u0633\u06a9\u06cc\u0647"
    ],
    "name:fas_x_preferred":[
        "\u0628\u0648\u062f \u0627\u0648\u06af\u0648\u0633\u062a\u0648\u0648\u0633\u06a9\u06cc\u0647"
    ],
    "name:fra_x_preferred":[
        "Budy Augustowskie"
    ],
    "name:nld_x_preferred":[
        "Budy Augustowskie"
    ],
    "name:pol_x_preferred":[
        "Budy Augustowskie"
    ],
    "name:ukr_x_preferred":[
        "\u0411\u0443\u0434\u0438-\u0410\u0443\u0491\u0443\u0441\u0442\u043e\u0432\u0441\u044c\u043a\u0456"
    ],
    "wof:name":"Budy Augustowskie",
    "wof:placetype":"locality"
},
  "geometry": {"coordinates":[21.18971,51.66979],"type":"Point"}
}