{
  "type": "Feature",
  "properties": {
    "gn:admin1_code":"78.0",
    "gn:admin2_code":"1407.0",
    "gn:admin3_code":"140704.0",
    "gn:asciiname":"Budy Augustowskie",
    "gn:country_code":"PL",
    "gn:dem":127,
    "gn:feature_class":"P",
    "gn:feature_code":"PPL",
    "gn:name":"Budy Augustowskie",
    "gn:population":0,
    "gn:timezone":"Europe/Warsaw",
    "iso:country":"PL",
    "wof:name":"Budy Augustowskie",
    "wof:placetype":"locality"
},
  "geometry": {"coordinates":[21.18971,51.66979],"type":"Point"}
}