{
  "type": "Feature",
  "properties": {
    "gn:population":4474,
    "iso:country":"PL",
    "name:azb_x_preferred":[
        "\u0631\u06cc\u0648\u0648\u06cc\u062a\u0633 \u0641\u0627\u0628\u0631\u0686\u0646\u0647"
    ],
    "name:ceb_x_preferred":[
        "Rejowiec Fabryczny"
    ],
    "name:deu_x_preferred":[
        "Rejowiec Fabryczny"
    ],
    "name:dsb_x_preferred":[
        "Rejowiec Fabryczny"
    ],
    "name:eng_x_preferred":[
        "Rejowiec Fabryczny"
    ],
    "name:epo_x_preferred":[
        "Rejowiec Fabryczny"
    ],
    "name:eus_x_preferred":[
        "Rejowiec Fabryczny"
    ],
    "name:fas_x_preferred":[
        "\u0631\u06cc\u0648\u0648\u06cc\u062a\u0633 \u0641\u0627\u0628\u0631\u0686\u0646\u0647"
    ],
    "name:fra_x_preferred":[
        "Rejowiec Fabryczny"
    ],
    "name:ita_x_preferred":[
        "Rejowiec Fabryczny"
    ],
    "name:jav_x_preferred":[
        "Rejowiec Fabryczny"
    ],
    "name:lav_x_preferred":[
        "Rejovecfabri\u010dni"
    ],
    "name:msa_x_preferred":[
        "Rejowiec Fabryczny"
    ],
    "name:nan_x_preferred":[
        "Rejowiec Fabryczny"
    ],
    "name:nld_x_preferred":[
        "Rejowiec Fabryczny"
    ],
    "name:pol_x_preferred":[
        "Rejowiec Fabryczny"
    ],
    "name:por_x_preferred":[
        "Rejowiec Fabryczny"
    ],
    "name:ron_x_preferred":[
        "Rejowiec Fabryczny"
    ],
    "name:rus_x_preferred":[
        "\u0420\u0435\u0451\u0432\u0435\u0446-\u0424\u0430\u0431\u0440\u044b\u0447\u043d\u044b"
    ],
    "name:slk_x_preferred":[
        "Rejowiec Fabryczny"
    ],
    "name:srp_x_preferred":[
        "\u0420\u0435\u0458\u043e\u0432\u0458\u0435\u0446 \u0424\u0430\u0431\u0440\u0438\u0447\u043d\u0438"
    ],
    "name:tat_x_preferred":[
        "\u0420\u0435\u0439\u043e\u0432\u0435\u0442\u0441-\u0424\u0430\u0431\u0440\u044b\u0447\u043d\u044b"
    ],
    "name:ukr_x_preferred":[
        "\u0420\u0435\u0439\u043e\u0432\u0435\u0446\u044c-\u0424\u0430\u0431\u0440\u0438\u0447\u043d\u0438\u0439"
    ],
    "name:vie_x_preferred":[
        "Rejowiec Fabryczny"
    ],
    "name:war_x_preferred":[
        "Rejowiec Fabryczny"
    ],
    "name:zho_min_nan_x_preferred":[
        "Rejowiec Fabryczny"
    ],
    "name:zho_x_preferred":[
        "\u96f7\u7d04\u7dad\u8328\u6cd5\u5e03\u91cc\u5947\u5167"
    ],
    "qs:a0":"Rzeczpospolita Polska",
    "qs:a1":"*Lubelskie",
    "qs:a1r":"0",
    "qs:a2":"Chelmski",
    "qs:adm0":"Rzeczpospolita Polska",
    "qs:la":"Rejowiec Fabryczny",
    "qs:la_lc":"*PL0603011",
    "qs:level":"locality",
    "qs:loc":"Rejowiec Fabryczny",
    "qs:loc_alt":"Rejowiec Fabryczny",
    "qs:pop":0,
    "qs:type":"rural point-in-poly",
    "wd:wordcount":279,
    "wof:name":"Rejowiec Fabryczny",
    "wof:placetype":"locality",
    "wof:population":4474
},
  "geometry": {"coordinates":[23.2534071643239,51.1199875584238],"type":"Point"}
}