{
  "type": "Feature",
  "properties": {
    "gn:admin1_code":"87.0",
    "gn:admin2_code":"3209.0",
    "gn:admin3_code":"320906.0",
    "gn:asciiname":"Garbno",
    "gn:country_code":"PL",
    "gn:dem":120,
    "gn:feature_class":"P",
    "gn:feature_code":"PPL",
    "gn:name":"Garbno",
    "gn:population":0,
    "gn:timezone":"Europe/Warsaw",
    "iso:country":"PL",
    "name:ceb_x_preferred":[
        "Garbno"
    ],
    "name:deu_x_preferred":[
        "Garbno"
    ],
    "name:pol_x_preferred":[
        "Garbno"
    ],
    "name:ukr_x_preferred":[
        "\u0490\u0430\u0440\u0431\u043d\u043e"
    ],
    "name:vie_x_preferred":[
        "Garbno"
    ],
    "wof:name":"Garbno",
    "wof:placetype":"locality"
},
  "geometry": {"coordinates":[16.53844,54.11061],"type":"Point"}
}