{
  "type": "Feature",
  "properties": {
    "gn:admin1_code":"81.0",
    "gn:admin2_code":"2002.0",
    "gn:admin3_code":"200204.0",
    "gn:asciiname":"Przechody",
    "gn:country_code":"PL",
    "gn:dem":138,
    "gn:feature_class":"P",
    "gn:feature_code":"PPL",
    "gn:name":"Przechody",
    "gn:population":0,
    "gn:timezone":"Europe/Warsaw",
    "iso:country":"PL",
    "name:azb_x_preferred":[
        "\u067e\u0698\u062e\u0648\u062f\u0647"
    ],
    "name:fas_x_preferred":[
        "\u067e\u0698\u062e\u0648\u062f\u0647"
    ],
    "name:fra_x_preferred":[
        "Przechody"
    ],
    "name:lit_x_preferred":[
        "P\u017eechodai"
    ],
    "name:pol_x_preferred":[
        "Przechody"
    ],
    "name:ukr_x_preferred":[
        "\u041f\u0448\u0435\u0445\u043e\u0434\u0438"
    ],
    "wof:name":"Przechody",
    "wof:placetype":"locality"
},
  "geometry": {"coordinates":[23.46245,53.13675],"type":"Point"}
}