{
  "type": "Feature",
  "properties": {
    "gn:admin1_code":"78.0",
    "gn:admin2_code":"1411.0",
    "gn:admin3_code":"141106.0",
    "gn:asciiname":"Szlasy Lozino",
    "gn:cc2":"PL",
    "gn:country_code":"PL",
    "gn:dem":101,
    "gn:feature_class":"P",
    "gn:feature_code":"PPL",
    "gn:name":"Szlasy \u0141ozino",
    "gn:population":0,
    "gn:timezone":"Europe/Warsaw",
    "iso:country":"PL",
    "name:und_x_variant":[
        "Szlasy \u0141osino",
        "Szlasy \u0141ozino"
    ],
    "wof:name":"Szlasy Lozino",
    "wof:placetype":"locality"
},
  "geometry": {"coordinates":[21.01667,52.93333000000001],"type":"Point"}
}