{
  "type": "Feature",
  "properties": {
    "gn:gn_country":"PL",
    "gn:gn_fcode":"PPL",
    "gn:gn_pop":128,
    "gn:population":128,
    "iso:country":"PL",
    "name:csb_x_preferred":[
        "S\u0142\u00ebpi\u00f4"
    ],
    "name:deu_x_preferred":[
        "S\u0142upia"
    ],
    "name:fra_x_preferred":[
        "Slupia"
    ],
    "name:hun_x_preferred":[
        "S\u0142upia"
    ],
    "name:ita_x_preferred":[
        "S\u0142upia"
    ],
    "name:nno_x_preferred":[
        "S\u0142upia"
    ],
    "name:pol_x_preferred":[
        "S\u0142upia"
    ],
    "name:ron_x_preferred":[
        "R\u00e2ul S\u0142upia"
    ],
    "name:spa_x_preferred":[
        "R\u00edo S\u0142upia"
    ],
    "name:ukr_x_preferred":[
        "\u0421\u043b\u0443\u043f\u044f"
    ],
    "name:zho_x_preferred":[
        "\u65af\u6b66\u76ae\u4e9a\u6cb3"
    ],
    "qs_pg:aaroncc":"PL",
    "qs_pg:gn_country":"PL",
    "qs_pg:gn_fcode":"PPL",
    "qs_pg:gn_pop":128,
    "qs_pg:name":"S\u0142upia",
    "qs_pg:name_adm0":"Polska",
    "qs_pg:name_adm1":"Mazowieckie",
    "qs_pg:photos_9k":1,
    "qs_pg:photos_9r":1,
    "qs_pg:photos_all":7,
    "qs_pg:photos_sr":0,
    "qs_pg:pop_sr":1,
    "qs_pg:qs_pg_placetype":"locality",
    "qs_pg:qs_pg_placetype_gp":"Town",
    "qs_pg:woe_adm0":23424923,
    "woe:adm0_id":23424923,
    "woe:name_adm0":"Polska",
    "woe:name_adm1":"Mazowieckie",
    "woe:placetype":"Town",
    "wof:name":"S\u0142upia",
    "wof:placetype":"locality",
    "wof:population":128
},
  "geometry": {"coordinates":[19.5954,52.96451],"type":"Point"}
}