{
  "type": "Feature",
  "properties": {
    "gn:admin1_code":"73.0",
    "gn:admin2_code":"461.0",
    "gn:admin3_code":"46101.0",
    "gn:asciiname":"Wyzyny",
    "gn:country_code":"PL",
    "gn:dem":68,
    "gn:feature_class":"P",
    "gn:feature_code":"PPL",
    "gn:name":"Wy\u017cyny",
    "gn:population":0,
    "gn:timezone":"Europe/Warsaw",
    "iso:country":"PL",
    "wof:name":"Wyzyny",
    "wof:placetype":"neighbourhood"
},
  "geometry": {"coordinates":[18.02745,53.10396],"type":"Point"}
}