{
  "type": "Feature",
  "properties": {
    "gn:admin1_code":"77.0",
    "gn:admin2_code":"1202.0",
    "gn:admin3_code":"120207.0",
    "gn:asciiname":"Jaksice",
    "gn:country_code":"PL",
    "gn:dem":177,
    "gn:feature_class":"P",
    "gn:feature_code":"PPL",
    "gn:name":"Jaksice",
    "gn:population":0,
    "gn:timezone":"Europe/Warsaw",
    "iso:country":"PL",
    "name:pol_x_preferred":[
        "Jaksice"
    ],
    "name:ukr_x_preferred":[
        "\u042f\u043a\u0441\u0456\u0446\u0435"
    ],
    "wof:name":"Jaksice",
    "wof:placetype":"locality"
},
  "geometry": {"coordinates":[20.51667,50.13333],"type":"Point"}
}