{
  "type": "Feature",
  "properties": {
    "gn:admin1_code":"85.0",
    "gn:admin2_code":"2808.0",
    "gn:admin3_code":"280802.0",
    "gn:asciiname":"Aptynty",
    "gn:country_code":"PL",
    "gn:dem":48,
    "gn:feature_class":"P",
    "gn:feature_code":"PPL",
    "gn:name":"Aptynty",
    "gn:population":0,
    "gn:timezone":"Europe/Warsaw",
    "iso:country":"PL",
    "name:azb_x_preferred":[
        "\u0627\u067e\u062a\u0646\u062a\u0647"
    ],
    "name:ceb_x_preferred":[
        "Aptynty"
    ],
    "name:deu_x_preferred":[
        "Aptynty"
    ],
    "name:fas_x_preferred":[
        "\u0627\u067e\u062a\u0646\u062a\u0647"
    ],
    "name:nld_x_preferred":[
        "Aptynty"
    ],
    "name:pol_x_preferred":[
        "Aptynty"
    ],
    "name:vie_x_preferred":[
        "Aptynty"
    ],
    "wof:name":"Aptynty",
    "wof:placetype":"locality"
},
  "geometry": {"coordinates":[21.29889,54.30411],"type":"Point"}
}