{
  "type": "Feature",
  "properties": {
    "gn:gn_country":"PL",
    "gn:gn_fcode":"PPLA3",
    "gn:gn_pop":1800,
    "gn:population":1800,
    "iso:country":"PL",
    "name:azb_x_preferred":[
        "\u0628\u0627\u0628\u0648\u0634\u0648\u0648"
    ],
    "name:ceb_x_preferred":[
        "Baboszewo"
    ],
    "name:deu_x_preferred":[
        "Baboszewo"
    ],
    "name:eng_x_preferred":[
        "Baboszewo"
    ],
    "name:fas_x_preferred":[
        "\u0628\u0627\u0628\u0648\u0634\u0648\u0648"
    ],
    "name:fra_x_preferred":[
        "Baboszewo"
    ],
    "name:nld_x_preferred":[
        "Baboszewo"
    ],
    "name:pol_x_preferred":[
        "Baboszewo"
    ],
    "name:rus_x_preferred":[
        "\u0411\u0430\u0431\u043e\u0448\u0435\u0432\u043e"
    ],
    "name:ukr_x_preferred":[
        "\u0411\u0430\u0431\u043e\u0448\u0435\u0432\u043e"
    ],
    "qs_pg:aaroncc":"PL",
    "qs_pg:gn_country":"PL",
    "qs_pg:gn_fcode":"PPLA3",
    "qs_pg:gn_pop":1800,
    "qs_pg:name":"Baboszewo",
    "qs_pg:name_adm0":"Polska",
    "qs_pg:name_adm1":"Mazowieckie",
    "qs_pg:photos_9k":1,
    "qs_pg:photos_9r":1,
    "qs_pg:photos_all":20,
    "qs_pg:photos_sr":0,
    "qs_pg:pop_sr":3,
    "qs_pg:qs_pg_placetype":"localadmin",
    "qs_pg:qs_pg_placetype_gp":"LocalAdmin",
    "qs_pg:woe_adm0":23424923,
    "woe:adm0_id":23424923,
    "woe:name_adm0":"Polska",
    "woe:name_adm1":"Mazowieckie",
    "woe:placetype":"LocalAdmin",
    "wof:name":"Baboszewo",
    "wof:placetype":"localadmin",
    "wof:population":1800
},
  "geometry": {"coordinates":[20.25527,52.6807],"type":"Point"}
}