{
  "type": "Feature",
  "properties": {
    "gn:admin1_code":"75.0",
    "gn:admin2_code":"609.0",
    "gn:admin3_code":"60912.0",
    "gn:asciiname":"Kajetanowka",
    "gn:country_code":"PL",
    "gn:dem":221,
    "gn:feature_class":"P",
    "gn:feature_code":"PPL",
    "gn:name":"Kajetan\u00f3wka",
    "gn:population":0,
    "gn:timezone":"Europe/Warsaw",
    "iso:country":"PL",
    "name:und_x_variant":[
        "Kajetan\u00f3wka"
    ],
    "wof:name":"Kajetanowka",
    "wof:placetype":"locality"
},
  "geometry": {"coordinates":[22.42287,51.07723],"type":"Point"}
}