{
  "type": "Feature",
  "properties": {
    "gn:admin1_code":"86.0",
    "gn:asciiname":"Leszno",
    "gn:country_code":"PL",
    "gn:dem":96,
    "gn:feature_class":"P",
    "gn:feature_code":"PPL",
    "gn:name":"Leszno",
    "gn:population":0,
    "gn:timezone":"Europe/Warsaw",
    "iso:country":"PL",
    "name:ast_x_preferred":[
        "Leszno"
    ],
    "name:bel_x_preferred":[
        "\u041b\u0435\u0448\u043d\u0430"
    ],
    "name:bul_x_preferred":[
        "\u041b\u0435\u0448\u043d\u043e"
    ],
    "name:cat_x_preferred":[
        "Leszno"
    ],
    "name:ceb_x_preferred":[
        "Leszno"
    ],
    "name:ces_x_preferred":[
        "Le\u0161no"
    ],
    "name:deu_x_preferred":[
        "Leszno"
    ],
    "name:epo_x_preferred":[
        "Leszno"
    ],
    "name:est_x_preferred":[
        "Leszno"
    ],
    "name:eus_x_preferred":[
        "Leszno"
    ],
    "name:fas_x_preferred":[
        "\u0644\u0634\u0646\u0648"
    ],
    "name:fin_x_preferred":[
        "Leszno"
    ],
    "name:fra_x_preferred":[
        "Leszno"
    ],
    "name:heb_x_preferred":[
        "\u05dc\u05e9\u05e0\u05d5"
    ],
    "name:hun_x_preferred":[
        "Leszno"
    ],
    "name:ind_x_preferred":[
        "Leszno"
    ],
    "name:ita_x_preferred":[
        "Leszno"
    ],
    "name:jav_x_preferred":[
        "Leszno"
    ],
    "name:jpn_x_preferred":[
        "\u30ec\u30b7\u30e5\u30ce"
    ],
    "name:kor_x_preferred":[
        "\ub808\uc288\ub178"
    ],
    "name:lav_x_preferred":[
        "Le\u0161no"
    ],
    "name:lit_x_preferred":[
        "Le\u0161nas"
    ],
    "name:mkd_x_preferred":[
        "\u041b\u0435\u0448\u043d\u043e"
    ],
    "name:msa_x_preferred":[
        "Leszno"
    ],
    "name:nld_x_preferred":[
        "Leszno"
    ],
    "name:nor_x_preferred":[
        "Leszno"
    ],
    "name:pol_x_preferred":[
        "Leszno"
    ],
    "name:por_x_preferred":[
        "Leszno"
    ],
    "name:ron_x_preferred":[
        "Leszno"
    ],
    "name:rus_x_preferred":[
        "\u041b\u0435\u0448\u043d\u043e"
    ],
    "name:slk_x_preferred":[
        "Leszno"
    ],
    "name:spa_x_preferred":[
        "Leszno"
    ],
    "name:srp_x_preferred":[
        "\u041b\u0435\u0448\u043d\u043e"
    ],
    "name:swe_x_preferred":[
        "Leszno"
    ],
    "name:szl_x_preferred":[
        "Leszno"
    ],
    "name:tat_x_preferred":[
        "\u041b\u0435\u0448\u043d\u043e"
    ],
    "name:tur_x_preferred":[
        "Leszno"
    ],
    "name:ukr_x_preferred":[
        "\u041b\u0435\u0448\u043d\u043e"
    ],
    "name:vie_x_preferred":[
        "Leszno"
    ],
    "name:war_x_preferred":[
        "Leszno"
    ],
    "name:yid_x_preferred":[
        "\u05dc\u05d9\u05e1\u05d0"
    ],
    "name:zho_x_preferred":[
        "\u83b1\u4ec0\u8bfa"
    ],
    "wof:name":"Leszno",
    "wof:placetype":"locality"
},
  "geometry": {"coordinates":[18.94833,52.09037],"type":"Point"}
}