{
  "type": "Feature",
  "properties": {
    "gn:admin1_code":"86.0",
    "gn:asciiname":"Leszno",
    "gn:country_code":"PL",
    "gn:dem":96,
    "gn:feature_class":"P",
    "gn:feature_code":"PPL",
    "gn:name":"Leszno",
    "gn:population":0,
    "gn:timezone":"Europe/Warsaw",
    "iso:country":"PL",
    "wof:name":"Leszno",
    "wof:placetype":"locality"
},
  "geometry": {"coordinates":[18.94833,52.09037],"type":"Point"}
}