{
  "type": "Feature",
  "properties": {
    "gn:admin1_code":"85.0",
    "gn:admin2_code":"2801.0",
    "gn:admin3_code":"280103.0",
    "gn:asciiname":"Kiersity",
    "gn:country_code":"PL",
    "gn:dem":82,
    "gn:feature_class":"P",
    "gn:feature_code":"PPL",
    "gn:name":"Kiersity",
    "gn:population":0,
    "gn:timezone":"Europe/Warsaw",
    "iso:country":"PL",
    "name:fra_x_preferred":[
        "Kiersity"
    ],
    "name:pol_x_preferred":[
        "Kiersity"
    ],
    "name:ukr_x_preferred":[
        "\u041a\u0435\u0440\u0441\u0456\u0442\u0438"
    ],
    "name:und_x_variant":[
        "Kirschitten"
    ],
    "name:vie_x_preferred":[
        "Kiersity"
    ],
    "wof:name":"Kiersity",
    "wof:placetype":"locality"
},
  "geometry": {"coordinates":[20.69632,54.22673],"type":"Point"}
}