{
  "type": "Feature",
  "properties": {
    "gn:admin1_code":"74.0",
    "gn:admin2_code":"1014.0",
    "gn:admin3_code":"101410.0",
    "gn:asciiname":"Kobierzycko",
    "gn:country_code":"PL",
    "gn:dem":153,
    "gn:feature_class":"P",
    "gn:feature_code":"PPL",
    "gn:name":"Kobierzycko",
    "gn:population":0,
    "gn:timezone":"Europe/Warsaw",
    "iso:country":"PL",
    "name:pol_x_preferred":[
        "Kobierzycko"
    ],
    "name:ukr_x_preferred":[
        "\u041a\u043e\u0431\u0435\u0436\u0438\u0446\u044c\u043a\u043e"
    ],
    "wof:name":"Kobierzycko",
    "wof:placetype":"locality"
},
  "geometry": {"coordinates":[18.60328,51.62539],"type":"Point"}
}