{
  "type": "Feature",
  "properties": {
    "gn:admin1_code":"80.0",
    "gn:admin2_code":"1810.0",
    "gn:admin3_code":"181003.0",
    "gn:asciiname":"Zalesie",
    "gn:country_code":"PL",
    "gn:dem":248,
    "gn:feature_class":"P",
    "gn:feature_code":"PPL",
    "gn:name":"Zalesie",
    "gn:population":0,
    "gn:timezone":"Europe/Warsaw",
    "iso:country":"PL",
    "wof:name":"Zalesie",
    "wof:placetype":"locality"
},
  "geometry": {"coordinates":[22.16048,50.15295],"type":"Point"}
}