{
  "type": "Feature",
  "properties": {
    "iso:country":"PL",
    "name:eng_x_preferred":[
        "Osiedle Przemyslawa"
    ],
    "name:pol_x_preferred":[
        "Osiedle Przemys\u0142awa"
    ],
    "wof:name":"Osiedle Przemyslawa",
    "wof:placetype":"neighbourhood"
},
  "geometry": {"coordinates":[17.00320861733233,52.38883563807121],"type":"Point"}
}