{
  "type": "Feature",
  "properties": {
    "gn:admin1_code":"74.0",
    "gn:admin2_code":"1017.0",
    "gn:admin3_code":"101703.0",
    "gn:asciiname":"Szynkielow",
    "gn:country_code":"PL",
    "gn:dem":165,
    "gn:feature_class":"P",
    "gn:feature_code":"PPL",
    "gn:name":"Szynkiel\u00f3w",
    "gn:population":0,
    "gn:timezone":"Europe/Warsaw",
    "iso:country":"PL",
    "name:ceb_x_preferred":[
        "Szynkiel\u00f3w"
    ],
    "name:pol_x_preferred":[
        "Szynkiel\u00f3w"
    ],
    "name:ukr_x_preferred":[
        "\u0428\u0438\u043d\u043a\u0435\u043b\u044e\u0432"
    ],
    "name:und_x_variant":[
        "Szynkielew"
    ],
    "wof:name":"Szynkielow",
    "wof:placetype":"locality"
},
  "geometry": {"coordinates":[18.75757,51.35131],"type":"Point"}
}