{
  "type": "Feature",
  "properties": {
    "gn:admin1_code":"78.0",
    "gn:admin2_code":"1416.0",
    "gn:admin3_code":"141606.0",
    "gn:asciiname":"Slepowrony",
    "gn:country_code":"PL",
    "gn:dem":118,
    "gn:feature_class":"P",
    "gn:feature_code":"PPL",
    "gn:name":"\u015alepowrony",
    "gn:population":0,
    "gn:timezone":"Europe/Warsaw",
    "iso:country":"PL",
    "name:fra_x_preferred":[
        "\u015alepowrony"
    ],
    "name:pol_x_preferred":[
        "\u015alepowrony"
    ],
    "name:ukr_x_preferred":[
        "\u0421\u044c\u043b\u0435\u043f\u043e\u0432\u0440\u043e\u043d\u0438"
    ],
    "wof:name":"Slepowrony",
    "wof:placetype":"locality"
},
  "geometry": {"coordinates":[22.41168,52.61841999999999],"type":"Point"}
}