{
  "type": "Feature",
  "properties": {
    "gn:admin1_code":"78.0",
    "gn:admin2_code":"1416.0",
    "gn:admin3_code":"141606.0",
    "gn:asciiname":"Slepowrony",
    "gn:country_code":"PL",
    "gn:dem":118,
    "gn:feature_class":"P",
    "gn:feature_code":"PPL",
    "gn:name":"\u015alepowrony",
    "gn:population":0,
    "gn:timezone":"Europe/Warsaw",
    "iso:country":"PL",
    "wof:name":"Slepowrony",
    "wof:placetype":"locality"
},
  "geometry": {"coordinates":[22.41168,52.61841999999999],"type":"Point"}
}