{
  "type": "Feature",
  "properties": {
    "gn:admin1_code":"79",
    "gn:admin2_code":"1604",
    "gn:admin3_code":"160404.0",
    "gn:asciiname":"Wasice",
    "gn:country_code":"PL",
    "gn:dem":166,
    "gn:feature_class":"P",
    "gn:feature_code":"PPL",
    "gn:name":"W\u0105sice",
    "gn:population":0,
    "gn:timezone":"Europe/Warsaw",
    "iso:country":"PL",
    "name:deu_x_historical":[
        "Wundsch\u00fctz"
    ],
    "name:deu_x_preferred":[
        "Wundsch\u00fctz"
    ],
    "wof:name":"Wasice",
    "wof:placetype":"locality"
},
  "geometry": {"coordinates":[18.0185,50.98519],"type":"Point"}
}