{
  "type": "Feature",
  "properties": {
    "gn:admin1_code":"81.0",
    "gn:admin2_code":"2001.0",
    "gn:admin3_code":"200104.0",
    "gn:asciiname":"Bohatery Lesne",
    "gn:country_code":"PL",
    "gn:dem":116,
    "gn:feature_class":"P",
    "gn:feature_code":"PPL",
    "gn:name":"Bohatery Le\u015bne",
    "gn:population":0,
    "gn:timezone":"Europe/Warsaw",
    "iso:country":"PL",
    "name:und_x_variant":[
        "Bohatyry Le\u015bne",
        "Bohatery Le\u015bne"
    ],
    "wof:name":"Bohatery Lesne",
    "wof:placetype":"locality"
},
  "geometry": {"coordinates":[23.53383,53.79657],"type":"Point"}
}