{
  "type": "Feature",
  "properties": {
    "gn:admin1_code":"75.0",
    "gn:admin2_code":"612.0",
    "gn:admin3_code":"61202.0",
    "gn:asciiname":"Nieszawa",
    "gn:country_code":"PL",
    "gn:dem":130,
    "gn:feature_class":"P",
    "gn:feature_code":"PPL",
    "gn:name":"Nieszawa",
    "gn:population":0,
    "gn:timezone":"Europe/Warsaw",
    "iso:country":"PL",
    "name:fra_x_preferred":[
        "Nieszawa"
    ],
    "name:pol_x_preferred":[
        "Nieszawa"
    ],
    "name:ukr_x_preferred":[
        "\u041d\u0435\u0448\u0430\u0432\u0430"
    ],
    "wof:name":"Nieszawa",
    "wof:placetype":"locality"
},
  "geometry": {"coordinates":[21.82898,51.01581],"type":"Point"}
}