{
  "type": "Feature",
  "properties": {
    "gn:admin1_code":"74.0",
    "gn:admin2_code":"1061.0",
    "gn:admin3_code":"106101.0",
    "gn:asciiname":"Lublinek-Pienista",
    "gn:country_code":"PL",
    "gn:dem":182,
    "gn:feature_class":"P",
    "gn:feature_code":"PPL",
    "gn:name":"Lublinek-Pienista",
    "gn:population":0,
    "gn:timezone":"Europe/Warsaw",
    "iso:country":"PL",
    "wof:name":"Lublinek-Pienista",
    "wof:placetype":"locality"
},
  "geometry": {"coordinates":[19.42211,51.73752],"type":"Point"}
}