{
  "type": "Feature",
  "properties": {
    "gn:admin1_code":"85.0",
    "gn:admin2_code":"2813.0",
    "gn:admin3_code":"281304.0",
    "gn:asciiname":"Doliwy Male",
    "gn:country_code":"PL",
    "gn:dem":160,
    "gn:feature_class":"P",
    "gn:feature_code":"PPL",
    "gn:name":"Doliwy Ma\u0142e",
    "gn:population":0,
    "gn:timezone":"Europe/Warsaw",
    "iso:country":"PL",
    "wof:name":"Doliwy Male",
    "wof:placetype":"locality"
},
  "geometry": {"coordinates":[22.35628,54.06003000000001],"type":"Point"}
}