{
  "type": "Feature",
  "properties": {
    "gn:admin1_code":"87.0",
    "gn:admin2_code":"3209.0",
    "gn:admin3_code":"320906.0",
    "gn:asciiname":"Sowinko",
    "gn:country_code":"PL",
    "gn:dem":97,
    "gn:feature_class":"P",
    "gn:feature_code":"PPL",
    "gn:name":"Sowinko",
    "gn:population":0,
    "gn:timezone":"Europe/Warsaw",
    "iso:country":"PL",
    "name:deu_x_preferred":[
        "Sowinko"
    ],
    "name:pol_x_preferred":[
        "Sowinko"
    ],
    "name:ukr_x_preferred":[
        "\u0421\u043e\u0432\u0456\u043d\u043a\u043e"
    ],
    "name:und_x_variant":[
        "Neu Zowen"
    ],
    "name:vie_x_preferred":[
        "Sowinko"
    ],
    "wof:name":"Sowinko",
    "wof:placetype":"locality"
},
  "geometry": {"coordinates":[16.51142,54.1724],"type":"Point"}
}