{
  "type": "Feature",
  "properties": {
    "gn:admin1_code":"86.0",
    "gn:admin2_code":"3031.0",
    "gn:admin3_code":"303108.0",
    "gn:asciiname":"Radawnica",
    "gn:country_code":"PL",
    "gn:dem":122,
    "gn:feature_class":"P",
    "gn:feature_code":"PPL",
    "gn:name":"Radawnica",
    "gn:population":0,
    "gn:timezone":"Europe/Warsaw",
    "iso:country":"PL",
    "wof:name":"Radawnica",
    "wof:placetype":"locality"
},
  "geometry": {"coordinates":[16.98077,53.4469],"type":"Point"}
}