{
  "type": "Feature",
  "properties": {
    "gn:admin1_code":"86.0",
    "gn:admin2_code":"3031.0",
    "gn:admin3_code":"303108.0",
    "gn:asciiname":"Radawnica",
    "gn:country_code":"PL",
    "gn:dem":122,
    "gn:feature_class":"P",
    "gn:feature_code":"PPL",
    "gn:name":"Radawnica",
    "gn:population":0,
    "gn:timezone":"Europe/Warsaw",
    "iso:country":"PL",
    "name:ceb_x_preferred":[
        "Radawnica"
    ],
    "name:deu_x_preferred":[
        "Radawnica"
    ],
    "name:fra_x_preferred":[
        "Radawnica"
    ],
    "name:pol_x_preferred":[
        "Radawnica"
    ],
    "name:ukr_x_preferred":[
        "\u0420\u0430\u0434\u0430\u0432\u043d\u0438\u0446\u044f"
    ],
    "wof:name":"Radawnica",
    "wof:placetype":"locality"
},
  "geometry": {"coordinates":[16.98077,53.4469],"type":"Point"}
}