{
  "type": "Feature",
  "properties": {
    "gn:admin1_code":"76.0",
    "gn:admin2_code":"804.0",
    "gn:admin3_code":"80404.0",
    "gn:asciiname":"Drwalewice",
    "gn:cc2":"PL",
    "gn:country_code":"PL",
    "gn:dem":87,
    "gn:feature_class":"P",
    "gn:feature_code":"PPL",
    "gn:name":"Drwalewice",
    "gn:population":0,
    "gn:timezone":"Europe/Warsaw",
    "iso:country":"PL",
    "name:fra_x_preferred":[
        "Drwalewice"
    ],
    "name:pol_x_preferred":[
        "Drwalewice"
    ],
    "name:ukr_x_preferred":[
        "\u0414\u0440\u0432\u0430\u043b\u0435\u0432\u0456\u0446\u0435"
    ],
    "name:und_x_variant":[
        "Drwalowice"
    ],
    "wof:name":"Drwalewice",
    "wof:placetype":"locality"
},
  "geometry": {"coordinates":[15.66925,51.74138],"type":"Point"}
}