{
  "type": "Feature",
  "properties": {
    "gn:admin1_code":"86.0",
    "gn:admin2_code":"3014.0",
    "gn:admin3_code":"301403.0",
    "gn:asciiname":"Wielowies",
    "gn:country_code":"PL",
    "gn:dem":52,
    "gn:feature_class":"P",
    "gn:feature_code":"PPL",
    "gn:name":"Wielowie\u015b",
    "gn:population":0,
    "gn:timezone":"Europe/Warsaw",
    "iso:country":"PL",
    "name:ceb_x_preferred":[
        "Wielowie\u015b"
    ],
    "name:fra_x_preferred":[
        "Wielowie\u015b"
    ],
    "name:pol_x_preferred":[
        "Wielowie\u015b"
    ],
    "name:ukr_x_preferred":[
        "\u0412\u0435\u043b\u044c\u043e\u0432\u0435\u0441\u044c"
    ],
    "wof:name":"Wielowies",
    "wof:placetype":"locality"
},
  "geometry": {"coordinates":[15.8973,52.58443000000001],"type":"Point"}
}