{
  "type": "Feature",
  "properties": {
    "gn:admin1_code":"73.0",
    "gn:admin2_code":"413.0",
    "gn:admin3_code":"41302.0",
    "gn:asciiname":"Waldowo",
    "gn:country_code":"PL",
    "gn:dem":132,
    "gn:feature_class":"P",
    "gn:feature_code":"PPL",
    "gn:name":"Wa\u0142dowo",
    "gn:population":0,
    "gn:timezone":"Europe/Warsaw",
    "iso:country":"PL",
    "wof:name":"Waldowo",
    "wof:placetype":"locality"
},
  "geometry": {"coordinates":[17.68693,53.47826],"type":"Point"}
}