{
  "type": "Feature",
  "properties": {
    "gn:admin1_code":"83.0",
    "gn:admin2_code":"2406.0",
    "gn:admin3_code":"240603.0",
    "gn:asciiname":"Rebielice Szlacheckie",
    "gn:country_code":"PL",
    "gn:dem":205,
    "gn:feature_class":"P",
    "gn:feature_code":"PPL",
    "gn:name":"R\u0119bielice Szlacheckie",
    "gn:population":0,
    "gn:timezone":"Europe/Warsaw",
    "iso:country":"PL",
    "name:ceb_x_preferred":[
        "R\u0119bielice Szlacheckie"
    ],
    "name:pol_x_preferred":[
        "R\u0119bielice Szlacheckie"
    ],
    "name:und_x_variant":[
        "R\u0119bielice Szlacheckie"
    ],
    "wof:name":"Rebielice Szlacheckie",
    "wof:placetype":"locality"
},
  "geometry": {"coordinates":[18.85433,51.02109],"type":"Point"}
}