{
  "type": "Feature",
  "properties": {
    "iso:country":"PL",
    "name:nld_x_preferred":[
        "Jelitkowo"
    ],
    "name:pol_x_preferred":[
        "Jelitkowo"
    ],
    "name:pol_x_variant":[
        "Glettkau"
    ],
    "name:ukr_x_preferred":[
        "\u0404\u043b\u0456\u0442\u043a\u043e\u0432\u043e"
    ],
    "name:unk_x_variant":[
        "Glettkau",
        "Jelitkowo"
    ],
    "qs:gn_adm0_cc":"PL",
    "qs:gn_fcode":"PPLX",
    "qs:gn_local":3085151,
    "qs:gn_nam_loc":"Sopot, Sopot, Sopot, Pomorskie, PL",
    "qs:gn_namadm1":"82",
    "qs:gn_name":"Jelitkowo",
    "qs:local_max":3579,
    "qs:local_sum":3579,
    "qs:localhoods":1,
    "qs:name":"Jelitkowo",
    "qs:name_adm0":"Polska",
    "qs:name_adm1":"Pomorskie",
    "qs:name_adm2":"Sopot",
    "qs:name_lau":"Sopot",
    "qs:name_local":"Sopot",
    "qs:photo_max":412,
    "qs:photo_sum":3579,
    "qs:placetype":"Suburb",
    "qs:quad_count":211,
    "qs:woe_adm0":23424923,
    "qs:woe_adm1":12577945,
    "qs:woe_adm2":12591380,
    "qs:woe_lau":12618711,
    "qs:woe_local":519349,
    "qs:woe_ver":"7.10.0",
    "wd:wordcount":123,
    "wof:lang":[
        "pol"
    ],
    "wof:name":"Jelitkowo",
    "wof:placetype":"neighbourhood"
},
  "geometry": {"coordinates":[18.576456,54.422182],"type":"Point"}
}