{
  "type": "Feature",
  "properties": {
    "gn:admin1_code":"86.0",
    "gn:admin2_code":"3010.0",
    "gn:admin3_code":"301007.0",
    "gn:asciiname":"Rybie",
    "gn:country_code":"PL",
    "gn:dem":114,
    "gn:feature_class":"P",
    "gn:feature_code":"PPL",
    "gn:name":"Rybie",
    "gn:population":0,
    "gn:timezone":"Europe/Warsaw",
    "iso:country":"PL",
    "name:fra_x_preferred":[
        "Rybie"
    ],
    "name:pol_x_preferred":[
        "Rybie"
    ],
    "name:ukr_x_preferred":[
        "\u0420\u0438\u0431\u0435"
    ],
    "wof:name":"Rybie",
    "wof:placetype":"locality"
},
  "geometry": {"coordinates":[18.19036,52.01521],"type":"Point"}
}