{
  "type": "Feature",
  "properties": {
    "gn:admin1_code":"78.0",
    "gn:admin2_code":"1433.0",
    "gn:admin3_code":"143307.0",
    "gn:asciiname":"Sokolka",
    "gn:country_code":"PL",
    "gn:dem":102,
    "gn:feature_class":"P",
    "gn:feature_code":"PPL",
    "gn:name":"Sok\u00f3\u0142ka",
    "gn:population":0,
    "gn:timezone":"Europe/Warsaw",
    "iso:country":"PL",
    "name:ceb_x_preferred":[
        "Sok\u00f3\u0142ka"
    ],
    "name:fra_x_preferred":[
        "Sok\u00f3\u0142ka"
    ],
    "name:lit_x_preferred":[
        "Sokulka"
    ],
    "name:pol_x_preferred":[
        "Sok\u00f3\u0142ka"
    ],
    "name:ukr_x_preferred":[
        "\u0421\u043e\u043a\u0443\u043b\u043a\u0430"
    ],
    "wof:name":"Sokolka",
    "wof:placetype":"locality"
},
  "geometry": {"coordinates":[21.88735,52.61064],"type":"Point"}
}