{
  "type": "Feature",
  "properties": {
    "gn:admin1_code":"75.0",
    "gn:admin2_code":"615.0",
    "gn:admin3_code":"61506.0",
    "gn:asciiname":"Siedlanow",
    "gn:country_code":"PL",
    "gn:dem":148,
    "gn:feature_class":"P",
    "gn:feature_code":"PPL",
    "gn:name":"Siedlan\u00f3w",
    "gn:population":0,
    "gn:timezone":"Europe/Warsaw",
    "iso:country":"PL",
    "name:fra_x_preferred":[
        "Siedlan\u00f3w"
    ],
    "name:pol_x_preferred":[
        "Siedlan\u00f3w"
    ],
    "name:ukr_x_preferred":[
        "\u0421\u0435\u0434\u043b\u044f\u043d\u0443\u0432"
    ],
    "name:und_x_variant":[
        "Siedlan\u00f3w"
    ],
    "wof:name":"Siedlanow",
    "wof:placetype":"locality"
},
  "geometry": {"coordinates":[22.70571,51.81675],"type":"Point"}
}