{
  "type": "Feature",
  "properties": {
    "gn:admin1_code":"83.0",
    "gn:admin2_code":"2464.0",
    "gn:admin3_code":"246401.0",
    "gn:asciiname":"Rzasawy",
    "gn:country_code":"PL",
    "gn:dem":250,
    "gn:feature_class":"P",
    "gn:feature_code":"PPL",
    "gn:name":"Rz\u0105sawy",
    "gn:population":0,
    "gn:timezone":"Europe/Warsaw",
    "iso:country":"PL",
    "wof:name":"Rzasawy",
    "wof:placetype":"neighbourhood"
},
  "geometry": {"coordinates":[19.16965,50.87242],"type":"Point"}
}