{
  "type": "Feature",
  "properties": {
    "gn:admin1_code":"73.0",
    "gn:admin2_code":"414.0",
    "gn:admin3_code":"41401.0",
    "gn:asciiname":"Branica",
    "gn:country_code":"PL",
    "gn:dem":98,
    "gn:feature_class":"P",
    "gn:feature_code":"PPL",
    "gn:name":"Branica",
    "gn:population":0,
    "gn:timezone":"Europe/Warsaw",
    "iso:country":"PL",
    "name:pol_x_preferred":[
        "Branica"
    ],
    "name:ukr_x_preferred":[
        "\u0411\u0440\u0430\u043d\u0438\u0446\u044f"
    ],
    "wof:name":"Branica",
    "wof:placetype":"locality"
},
  "geometry": {"coordinates":[18.20101,53.44484],"type":"Point"}
}