{
  "type": "Feature",
  "properties": {
    "gn:admin1_code":"84.0",
    "gn:admin2_code":"2603.0",
    "gn:admin3_code":"260303.0",
    "gn:asciiname":"Stradlice",
    "gn:country_code":"PL",
    "gn:dem":186,
    "gn:feature_class":"P",
    "gn:feature_code":"PPL",
    "gn:name":"Stradlice",
    "gn:population":0,
    "gn:timezone":"Europe/Warsaw",
    "iso:country":"PL",
    "name:pol_x_preferred":[
        "Stradlice"
    ],
    "name:ukr_x_preferred":[
        "\u0421\u0442\u0440\u0430\u0434\u043b\u0456\u0446\u0435"
    ],
    "wof:name":"Stradlice",
    "wof:placetype":"locality"
},
  "geometry": {"coordinates":[20.54058,50.24879],"type":"Point"}
}