{
  "type": "Feature",
  "properties": {
    "gn:admin1_code":"83.0",
    "gn:admin2_code":"2404.0",
    "gn:admin3_code":"240412.0",
    "gn:asciiname":"Przymilowice",
    "gn:country_code":"PL",
    "gn:dem":320,
    "gn:feature_class":"P",
    "gn:feature_code":"PPL",
    "gn:name":"Przymi\u0142owice",
    "gn:population":0,
    "gn:timezone":"Europe/Warsaw",
    "iso:country":"PL",
    "name:ceb_x_preferred":[
        "Przymi\u0142owice"
    ],
    "name:pol_x_preferred":[
        "Przymi\u0142owice"
    ],
    "name:ukr_x_preferred":[
        "\u041f\u0448\u0438\u043c\u0456\u043b\u043e\u0432\u0456\u0446\u0435"
    ],
    "name:und_x_variant":[
        "Przemi\u0142owice",
        "Przymi\u0142owice"
    ],
    "wof:name":"Przymilowice",
    "wof:placetype":"locality"
},
  "geometry": {"coordinates":[19.30725,50.75273],"type":"Point"}
}