{
  "type": "Feature",
  "properties": {
    "gn:admin1_code":"83.0",
    "gn:admin2_code":"2410.0",
    "gn:admin3_code":"241006.0",
    "gn:asciiname":"Konradowo",
    "gn:country_code":"PL",
    "gn:dem":255,
    "gn:feature_class":"P",
    "gn:feature_code":"PPL",
    "gn:name":"Konradowo",
    "gn:population":0,
    "gn:timezone":"Europe/Warsaw",
    "iso:country":"PL",
    "wof:name":"Konradowo",
    "wof:placetype":"locality"
},
  "geometry": {"coordinates":[18.77609,49.98155],"type":"Point"}
}