{
  "type": "Feature",
  "properties": {
    "gn:admin1_code":"78.0",
    "gn:admin2_code":"1403.0",
    "gn:admin3_code":"140306.0",
    "gn:asciiname":"Stary Pilczyn",
    "gn:country_code":"PL",
    "gn:dem":139,
    "gn:feature_class":"P",
    "gn:feature_code":"PPL",
    "gn:name":"Stary Pilczyn",
    "gn:population":0,
    "gn:timezone":"Europe/Warsaw",
    "iso:country":"PL",
    "wof:name":"Stary Pilczyn",
    "wof:placetype":"locality"
},
  "geometry": {"coordinates":[21.6238,51.7977],"type":"Point"}
}