{
  "type": "Feature",
  "properties": {
    "gn:admin1_code":"78.0",
    "gn:admin2_code":"1403.0",
    "gn:admin3_code":"140306.0",
    "gn:asciiname":"Stary Pilczyn",
    "gn:country_code":"PL",
    "gn:dem":139,
    "gn:feature_class":"P",
    "gn:feature_code":"PPL",
    "gn:name":"Stary Pilczyn",
    "gn:population":0,
    "gn:timezone":"Europe/Warsaw",
    "iso:country":"PL",
    "name:fra_x_preferred":[
        "Stary Pilczyn"
    ],
    "name:pol_x_preferred":[
        "Stary Pilczyn"
    ],
    "name:spa_x_preferred":[
        "Stary Pilczyn"
    ],
    "name:ukr_x_preferred":[
        "\u0421\u0442\u0430\u0440\u0438\u0439 \u041f\u0456\u043b\u044c\u0447\u0438\u043d"
    ],
    "wof:name":"Stary Pilczyn",
    "wof:placetype":"locality"
},
  "geometry": {"coordinates":[21.6238,51.7977],"type":"Point"}
}