{
  "type": "Feature",
  "properties": {
    "gn:admin1_code":"77.0",
    "gn:admin2_code":"1219.0",
    "gn:admin3_code":"121905.0",
    "gn:asciiname":"Dobranowice",
    "gn:country_code":"PL",
    "gn:dem":347,
    "gn:feature_class":"P",
    "gn:feature_code":"PPL",
    "gn:name":"Dobranowice",
    "gn:population":0,
    "gn:timezone":"Europe/Warsaw",
    "iso:country":"PL",
    "name:pol_x_preferred":[
        "Dobranowice"
    ],
    "name:ukr_x_preferred":[
        "\u0414\u043e\u0431\u0440\u0430\u043d\u043e\u0432\u0456\u0446\u0435"
    ],
    "wof:name":"Dobranowice",
    "wof:placetype":"locality"
},
  "geometry": {"coordinates":[20.11477,49.94404],"type":"Point"}
}