{
  "type": "Feature",
  "properties": {
    "gn:admin1_code":"75.0",
    "gn:admin2_code":"607.0",
    "gn:admin3_code":"60709.0",
    "gn:asciiname":"Zalesie",
    "gn:country_code":"PL",
    "gn:dem":219,
    "gn:feature_class":"P",
    "gn:feature_code":"PPL",
    "gn:name":"Zalesie",
    "gn:population":0,
    "gn:timezone":"Europe/Warsaw",
    "iso:country":"PL",
    "wof:name":"Zalesie",
    "wof:placetype":"locality"
},
  "geometry": {"coordinates":[22.27934,51.00544],"type":"Point"}
}