{
  "type": "Feature",
  "properties": {
    "gn:admin1_code":"82.0",
    "gn:admin2_code":"2216.0",
    "gn:admin3_code":"221601.0",
    "gn:asciiname":"Andrzejewo",
    "gn:country_code":"PL",
    "gn:dem":46,
    "gn:feature_class":"P",
    "gn:feature_code":"PPL",
    "gn:name":"Andrzejewo",
    "gn:population":0,
    "gn:timezone":"Europe/Warsaw",
    "iso:country":"PL",
    "name:ceb_x_preferred":[
        "Andrzejewo"
    ],
    "name:deu_x_preferred":[
        "Andrzejewo"
    ],
    "name:fra_x_preferred":[
        "Andrzejewo"
    ],
    "name:lit_x_preferred":[
        "Andrejavas"
    ],
    "name:nld_x_preferred":[
        "Andrzejewo"
    ],
    "name:pol_x_preferred":[
        "Andrzejewo"
    ],
    "name:swe_x_preferred":[
        "Andrzejewo"
    ],
    "name:ukr_x_preferred":[
        "\u0410\u043d\u0434\u0436\u0435\u0454\u0432\u043e"
    ],
    "name:und_x_variant":[
        "Reichandres",
        "Reichandreas"
    ],
    "wof:name":"Andrzejewo",
    "wof:placetype":"locality"
},
  "geometry": {"coordinates":[19.27344,53.91748000000001],"type":"Point"}
}