{
  "type": "Feature",
  "properties": {
    "gn:admin1_code":"82.0",
    "gn:admin2_code":"2216.0",
    "gn:admin3_code":"221601.0",
    "gn:asciiname":"Andrzejewo",
    "gn:country_code":"PL",
    "gn:dem":46,
    "gn:feature_class":"P",
    "gn:feature_code":"PPL",
    "gn:name":"Andrzejewo",
    "gn:population":0,
    "gn:timezone":"Europe/Warsaw",
    "iso:country":"PL",
    "name:und_x_variant":[
        "Reichandres",
        "Reichandreas",
        "Andrzejewo"
    ],
    "wof:name":"Andrzejewo",
    "wof:placetype":"locality"
},
  "geometry": {"coordinates":[19.27344,53.91748000000001],"type":"Point"}
}