{
  "type": "Feature",
  "properties": {
    "gn:gn_country":"PL",
    "gn:gn_fcode":"PPL",
    "gn:gn_pop":145,
    "gn:population":145,
    "iso:country":"PL",
    "name:ast_x_preferred":[
        "Zbere\u017ce"
    ],
    "name:ceb_x_preferred":[
        "Zbere\u017ce"
    ],
    "name:deu_x_preferred":[
        "Zbere\u017ce"
    ],
    "name:eng_x_preferred":[
        "Zbere\u017ce"
    ],
    "name:fra_x_preferred":[
        "Zbere\u017ce"
    ],
    "name:nld_x_preferred":[
        "Zbere\u017ce"
    ],
    "name:pol_x_preferred":[
        "Zbere\u017ce"
    ],
    "name:ukr_x_preferred":[
        "\u0417\u0431\u0435\u0440\u0435\u0436\u0435"
    ],
    "qs_pg:aaroncc":"PL",
    "qs_pg:gn_country":"PL",
    "qs_pg:gn_fcode":"PPL",
    "qs_pg:gn_pop":145,
    "qs_pg:name":"Zbere\u017ce",
    "qs_pg:name_adm0":"Polska",
    "qs_pg:name_adm1":"Lubelskie",
    "qs_pg:photos_9r":0,
    "qs_pg:photos_sr":0,
    "qs_pg:pop_sr":1,
    "qs_pg:qs_pg_placetype":"locality",
    "qs_pg:qs_pg_placetype_gp":"Town",
    "qs_pg:woe_adm0":23424923,
    "woe:adm0_id":23424923,
    "woe:name_adm0":"Polska",
    "woe:name_adm1":"Lubelskie",
    "woe:placetype":"Town",
    "wof:name":"Zbere\u017ce",
    "wof:placetype":"locality",
    "wof:population":145
},
  "geometry": {"coordinates":[23.67425,51.3961],"type":"Point"}
}