{
  "type": "Feature",
  "properties": {
    "gn:admin1_code":"78.0",
    "gn:admin2_code":"1412.0",
    "gn:admin3_code":"141206.0",
    "gn:asciiname":"Nowa Rynia",
    "gn:country_code":"PL",
    "gn:dem":139,
    "gn:feature_class":"P",
    "gn:feature_code":"PPL",
    "gn:name":"Nowa Rynia",
    "gn:population":0,
    "gn:timezone":"Europe/Warsaw",
    "iso:country":"PL",
    "name:und_x_variant":[
        "Rynia Nowa",
        "Biedula",
        "Nowa Rynia"
    ],
    "wof:name":"Nowa Rynia",
    "wof:placetype":"locality"
},
  "geometry": {"coordinates":[21.6762,52.36672],"type":"Point"}
}