{
  "type": "Feature",
  "properties": {
    "gn:admin1_code":"83.0",
    "gn:admin2_code":"2403.0",
    "gn:admin3_code":"240301.0",
    "gn:asciiname":"Bobrek",
    "gn:country_code":"PL",
    "gn:dem":342,
    "gn:feature_class":"P",
    "gn:feature_code":"PPL",
    "gn:name":"Bobrek",
    "gn:population":0,
    "gn:timezone":"Europe/Warsaw",
    "iso:country":"PL",
    "wof:name":"Bobrek",
    "wof:placetype":"locality"
},
  "geometry": {"coordinates":[18.65992,49.76488],"type":"Point"}
}