{
  "type": "Feature",
  "properties": {
    "gn:admin1_code":"86.0",
    "gn:admin2_code":"3010.0",
    "gn:admin3_code":"301013.0",
    "gn:asciiname":"Krzymowo",
    "gn:country_code":"PL",
    "gn:dem":96,
    "gn:feature_class":"P",
    "gn:feature_code":"PPL",
    "gn:name":"Krzymowo",
    "gn:population":0,
    "gn:timezone":"Europe/Warsaw",
    "iso:country":"PL",
    "name:pol_x_preferred":[
        "Krzymowo"
    ],
    "name:ukr_x_preferred":[
        "\u041a\u0448\u0438\u043c\u043e\u0432\u043e"
    ],
    "wof:name":"Krzymowo",
    "wof:placetype":"locality"
},
  "geometry": {"coordinates":[18.52776,52.49543000000001],"type":"Point"}
}