{
  "type": "Feature",
  "properties": {
    "gn:admin1_code":"81.0",
    "gn:admin2_code":"2010.0",
    "gn:admin3_code":"201007.0",
    "gn:asciiname":"Telatycze",
    "gn:country_code":"PL",
    "gn:dem":156,
    "gn:feature_class":"P",
    "gn:feature_code":"PPL",
    "gn:name":"Telatycze",
    "gn:population":0,
    "gn:timezone":"Europe/Warsaw",
    "iso:country":"PL",
    "name:azb_x_preferred":[
        "\u062a\u0644\u0627\u062a\u0686\u0647"
    ],
    "name:fas_x_preferred":[
        "\u062a\u0644\u0627\u062a\u0686\u0647"
    ],
    "name:fra_x_preferred":[
        "Telatycze"
    ],
    "name:lit_x_preferred":[
        "Telati\u010d\u0117"
    ],
    "name:pol_x_preferred":[
        "Telatycze"
    ],
    "wof:name":"Telatycze",
    "wof:placetype":"locality"
},
  "geometry": {"coordinates":[23.21699,52.42705],"type":"Point"}
}