{
  "type": "Feature",
  "properties": {
    "gn:admin1_code":"78.0",
    "gn:admin2_code":"1435.0",
    "gn:admin3_code":"143501.0",
    "gn:asciiname":"Budykierz",
    "gn:country_code":"PL",
    "gn:dem":107,
    "gn:feature_class":"P",
    "gn:feature_code":"PPL",
    "gn:name":"Budykierz",
    "gn:population":0,
    "gn:timezone":"Europe/Warsaw",
    "iso:country":"PL",
    "name:azb_x_preferred":[
        "\u0628\u0648\u062f\u06a9\u06cc\u0698"
    ],
    "name:ceb_x_preferred":[
        "Budykierz"
    ],
    "name:fas_x_preferred":[
        "\u0628\u0648\u062f\u06a9\u06cc\u0698"
    ],
    "name:fra_x_preferred":[
        "Budykierz"
    ],
    "name:nld_x_preferred":[
        "Budykierz"
    ],
    "name:pol_x_preferred":[
        "Budykierz"
    ],
    "name:ukr_x_preferred":[
        "\u0411\u0443\u0434\u0438\u043a\u0435\u0436"
    ],
    "wof:name":"Budykierz",
    "wof:placetype":"locality"
},
  "geometry": {"coordinates":[21.63187000000001,52.67867],"type":"Point"}
}