{
  "type": "Feature",
  "properties": {
    "gn:country":"PL",
    "gn:fcode":"PPL",
    "gn:population":569,
    "iso:country":"PL",
    "name:ast_x_preferred":[
        "Ksi\u0105\u017cenice"
    ],
    "name:ceb_x_preferred":[
        "Ksi\u0105\u017cenice"
    ],
    "name:eng_x_preferred":[
        "Ksi\u0105\u017cenice"
    ],
    "name:fra_x_preferred":[
        "Ksi\u0105\u017cenice"
    ],
    "name:pol_x_preferred":[
        "Ksi\u0105\u017cenice"
    ],
    "name:szl_x_preferred":[
        "K\u015b\u016fn\u017cy\u0144icy"
    ],
    "name:ukr_x_preferred":[
        "\u041a\u0441\u044c\u043e\u043d\u0436\u0435\u043d\u0456\u0446\u0435"
    ],
    "qs_pg:aaroncc":"PL",
    "qs_pg:gn_country":"PL",
    "qs_pg:gn_fcode":"PPL",
    "qs_pg:gn_pop":569,
    "qs_pg:name":"Ksi\u0105\u017cenice",
    "qs_pg:name_adm0":"Polska",
    "qs_pg:name_adm1":"Mazowieckie",
    "qs_pg:photos_9r":0,
    "qs_pg:photos_sr":0,
    "qs_pg:pop_sr":2,
    "qs_pg:qs_pg_placetype":"locality",
    "qs_pg:qs_pg_placetype_gp":"Town",
    "qs_pg:woe_adm0":23424923,
    "woe:adm0_id":23424923,
    "woe:name_adm0":"Polska",
    "woe:name_adm1":"Mazowieckie",
    "woe:placetype":"Town",
    "wof:name":"Ksi\u0105\u017cenice",
    "wof:placetype":"locality",
    "wof:population":569
},
  "geometry": {"coordinates":[20.69661,52.07766],"type":"Point"}
}