{
  "type": "Feature",
  "properties": {
    "gn:admin1_code":"86.0",
    "gn:admin2_code":"3010.0",
    "gn:admin3_code":"301002.0",
    "gn:asciiname":"Lipice",
    "gn:country_code":"PL",
    "gn:dem":99,
    "gn:feature_class":"P",
    "gn:feature_code":"PPL",
    "gn:name":"Lipice",
    "gn:population":0,
    "gn:timezone":"Europe/Warsaw",
    "iso:country":"PL",
    "name:fra_x_preferred":[
        "Lipice"
    ],
    "name:hrv_x_preferred":[
        "Lipice"
    ],
    "name:pol_x_preferred":[
        "Lipice"
    ],
    "name:ukr_x_preferred":[
        "\u041b\u0456\u043f\u0456\u0446\u0435"
    ],
    "wof:name":"Lipice",
    "wof:placetype":"locality"
},
  "geometry": {"coordinates":[18.02534,52.02485],"type":"Point"}
}