{
  "type": "Feature",
  "properties": {
    "gn:admin1_code":"75.0",
    "gn:admin2_code":"605.0",
    "gn:admin3_code":"60505.0",
    "gn:asciiname":"Lazek",
    "gn:country_code":"PL",
    "gn:dem":176,
    "gn:feature_class":"P",
    "gn:feature_code":"PPL",
    "gn:name":"\u0141\u0105\u017cek",
    "gn:population":0,
    "gn:timezone":"Europe/Warsaw",
    "iso:country":"PL",
    "name:ceb_x_preferred":[
        "Lazek"
    ],
    "name:deu_x_preferred":[
        "Lazek"
    ],
    "name:swe_x_preferred":[
        "Lazek"
    ],
    "wof:name":"Lazek",
    "wof:placetype":"locality"
},
  "geometry": {"coordinates":[22.28333,50.63333],"type":"Point"}
}