{
  "type": "Feature",
  "properties": {
    "gn:admin1_code":"75.0",
    "gn:admin2_code":"601.0",
    "gn:admin3_code":"60113.0",
    "gn:asciiname":"Rossosz",
    "gn:country_code":"PL",
    "gn:dem":145,
    "gn:feature_class":"P",
    "gn:feature_code":"PPLA3",
    "gn:name":"Rossosz",
    "gn:population":0,
    "gn:timezone":"Europe/Warsaw",
    "iso:country":"PL",
    "wof:name":"Rossosz",
    "wof:placetype":"locality"
},
  "geometry": {"coordinates":[23.1374,51.85836],"type":"Point"}
}