{
  "type": "Feature",
  "properties": {
    "gn:admin1_code":"75.0",
    "gn:admin2_code":"601.0",
    "gn:admin3_code":"60113.0",
    "gn:asciiname":"Rossosz",
    "gn:country_code":"PL",
    "gn:dem":145,
    "gn:feature_class":"P",
    "gn:feature_code":"PPLA3",
    "gn:name":"Rossosz",
    "gn:population":0,
    "gn:timezone":"Europe/Warsaw",
    "iso:country":"PL",
    "name:azb_x_preferred":[
        "\u0642\u0645\u06cc\u0646\u0627 \u0631\u0648\u0633\u0633\u0648\u0634"
    ],
    "name:bel_x_preferred":[
        "\u0420\u043e\u0441\u0441\u0430\u0448"
    ],
    "name:deu_x_preferred":[
        "Gmina Rossosz"
    ],
    "name:eus_x_preferred":[
        "Rossosz udalerria"
    ],
    "name:fas_x_preferred":[
        "\u06af\u0645\u06cc\u0646\u0627 \u0631\u0648\u0633\u0633\u0648\u0634"
    ],
    "name:fra_x_preferred":[
        "Rossosz"
    ],
    "name:ita_x_preferred":[
        "Rossosz"
    ],
    "name:lit_x_preferred":[
        "Roso\u0161o vals\u010dius"
    ],
    "name:nld_x_preferred":[
        "Rossosz"
    ],
    "name:pol_x_preferred":[
        "Rossosz"
    ],
    "name:ron_x_preferred":[
        "Comuna Rossosz"
    ],
    "name:rus_x_preferred":[
        "\u0420\u043e\u0441\u0441\u043e\u0448"
    ],
    "name:slk_x_preferred":[
        "Gmina Rossosz"
    ],
    "name:ukr_x_preferred":[
        "\u0413\u043c\u0456\u043d\u0430 \u0420\u043e\u0441\u0441\u043e\u0448"
    ],
    "name:war_x_preferred":[
        "Gmina Rossosz"
    ],
    "wof:coterminous":[
        1477751491
    ],
    "wof:name":"Rossosz",
    "wof:placetype":"locality"
},
  "geometry": {"coordinates":[23.1374,51.85836],"type":"Point"}
}