{
  "type": "Feature",
  "properties": {
    "gn:admin1_code":"80.0",
    "gn:admin2_code":"1803.0",
    "gn:admin3_code":"180304.0",
    "gn:asciiname":"Stobierna",
    "gn:country_code":"PL",
    "gn:dem":275,
    "gn:feature_class":"P",
    "gn:feature_code":"PPL",
    "gn:name":"Stobierna",
    "gn:population":0,
    "gn:timezone":"Europe/Warsaw",
    "iso:country":"PL",
    "name:ceb_x_preferred":[
        "Stobierna"
    ],
    "name:pol_x_preferred":[
        "Stobierna"
    ],
    "name:ukr_x_preferred":[
        "\u0421\u0442\u043e\u0431\u0435\u0440\u043d\u0430"
    ],
    "wof:name":"Stobierna",
    "wof:placetype":"locality"
},
  "geometry": {"coordinates":[21.48685,50.02772],"type":"Point"}
}