{
  "type": "Feature",
  "properties": {
    "gn:admin1_code":"75.0",
    "gn:admin2_code":"663.0",
    "gn:admin3_code":"66301.0",
    "gn:asciiname":"Jezuickie",
    "gn:country_code":"PL",
    "gn:dem":183,
    "gn:feature_class":"P",
    "gn:feature_code":"PPL",
    "gn:name":"Jezuickie",
    "gn:population":0,
    "gn:timezone":"Europe/Warsaw",
    "iso:country":"PL",
    "wof:name":"Jezuickie",
    "wof:placetype":"locality"
},
  "geometry": {"coordinates":[22.53333,51.21667],"type":"Point"}
}