{
  "type": "Feature",
  "properties": {
    "gn:admin1_code":"78.0",
    "gn:admin2_code":"1414.0",
    "gn:admin3_code":"141403.0",
    "gn:asciiname":"Teofile",
    "gn:country_code":"PL",
    "gn:dem":70,
    "gn:feature_class":"P",
    "gn:feature_code":"PPL",
    "gn:name":"Teofile",
    "gn:population":0,
    "gn:timezone":"Europe/Warsaw",
    "iso:country":"PL",
    "name:fra_x_preferred":[
        "Teofile"
    ],
    "name:pol_x_preferred":[
        "Teofile"
    ],
    "name:ukr_x_preferred":[
        "\u0422\u0435\u043e\u0444\u0456\u043b\u0435"
    ],
    "wof:name":"Teofile",
    "wof:placetype":"locality"
},
  "geometry": {"coordinates":[20.53509,52.38800000000001],"type":"Point"}
}