{
  "type": "Feature",
  "properties": {
    "gn:admin1_code":"72.0",
    "gn:admin2_code":"223.0",
    "gn:admin3_code":"22304.0",
    "gn:asciiname":"Pelcznica",
    "gn:cc2":"PL",
    "gn:country_code":"PL",
    "gn:dem":139,
    "gn:feature_class":"P",
    "gn:feature_code":"PPL",
    "gn:name":"Pe\u0142cznica",
    "gn:population":0,
    "gn:timezone":"Europe/Warsaw",
    "iso:country":"PL",
    "name:und_x_variant":[
        "Polsnitz",
        "Br\u00fcckenfelde",
        "Pe\u0142cznica"
    ],
    "wof:name":"Pelcznica",
    "wof:placetype":"locality"
},
  "geometry": {"coordinates":[16.73801,51.04183],"type":"Point"}
}