{
  "type": "Feature",
  "properties": {
    "gn:admin1_code":"85.0",
    "gn:asciiname":"Plowez",
    "gn:country_code":"PL",
    "gn:dem":78,
    "gn:feature_class":"P",
    "gn:feature_code":"PPL",
    "gn:name":"P\u0142ow\u0119\u017c",
    "gn:population":0,
    "gn:timezone":"Europe/Warsaw",
    "iso:country":"PL",
    "name:und_x_variant":[
        "P\u0142ow\u0119\u017c"
    ],
    "wof:name":"Plowez",
    "wof:placetype":"locality"
},
  "geometry": {"coordinates":[19.23093,53.43595],"type":"Point"}
}