{
  "type": "Feature",
  "properties": {
    "gn:admin1_code":"85.0",
    "gn:asciiname":"Plowez",
    "gn:country_code":"PL",
    "gn:dem":78,
    "gn:feature_class":"P",
    "gn:feature_code":"PPL",
    "gn:name":"P\u0142ow\u0119\u017c",
    "gn:population":0,
    "gn:timezone":"Europe/Warsaw",
    "iso:country":"PL",
    "name:pol_x_preferred":[
        "P\u0142ow\u0119\u017c"
    ],
    "name:ukr_x_preferred":[
        "\u041f\u043b\u043e\u0432\u0435\u043d\u0436"
    ],
    "wof:name":"Plowez",
    "wof:placetype":"locality"
},
  "geometry": {"coordinates":[19.23093,53.43595],"type":"Point"}
}