{
  "type": "Feature",
  "properties": {
    "gn:gn_country":"PL",
    "gn:gn_fcode":"PPL",
    "gn:gn_pop":552,
    "gn:population":552,
    "iso:country":"PL",
    "name:ast_x_preferred":[
        "Jod\u0142ownik"
    ],
    "name:ceb_x_preferred":[
        "Jod\u0142ownik"
    ],
    "name:eng_x_preferred":[
        "Jod\u0142ownik"
    ],
    "name:fra_x_preferred":[
        "Jod\u0142ownik"
    ],
    "name:pol_x_preferred":[
        "Jod\u0142ownik"
    ],
    "qs_pg:aaroncc":"PL",
    "qs_pg:gn_country":"PL",
    "qs_pg:gn_fcode":"PPL",
    "qs_pg:gn_pop":552,
    "qs_pg:name":"Jod\u0142ownik",
    "qs_pg:name_adm0":"Polska",
    "qs_pg:name_adm1":"Dolnosl\u0105skie",
    "qs_pg:photos_9k":1,
    "qs_pg:photos_9r":1,
    "qs_pg:photos_all":10,
    "qs_pg:photos_sr":0,
    "qs_pg:pop_sr":2,
    "qs_pg:qs_pg_placetype":"locality",
    "qs_pg:qs_pg_placetype_gp":"Town",
    "qs_pg:woe_adm0":23424923,
    "woe:adm0_id":23424923,
    "woe:name_adm0":"Polska",
    "woe:name_adm1":"Dolnosl\u0105skie",
    "woe:placetype":"Town",
    "wof:name":"Jod\u0142ownik",
    "wof:placetype":"locality",
    "wof:population":552
},
  "geometry": {"coordinates":[16.61296,50.64549],"type":"Point"}
}