{
  "type": "Feature",
  "properties": {
    "gn:admin1_code":"87.0",
    "gn:admin2_code":"3218.0",
    "gn:admin3_code":"321803.0",
    "gn:asciiname":"Maliniec",
    "gn:country_code":"PL",
    "gn:dem":59,
    "gn:feature_class":"P",
    "gn:feature_code":"PPL",
    "gn:name":"Maliniec",
    "gn:population":0,
    "gn:timezone":"Europe/Warsaw",
    "iso:country":"PL",
    "name:ceb_x_preferred":[
        "Maliniec"
    ],
    "name:pol_x_preferred":[
        "Maliniec"
    ],
    "name:vie_x_preferred":[
        "Maliniec"
    ],
    "wof:name":"Maliniec",
    "wof:placetype":"locality"
},
  "geometry": {"coordinates":[15.36045,53.70267],"type":"Point"}
}