{
  "type": "Feature",
  "properties": {
    "gn:admin1_code":"77.0",
    "gn:admin2_code":"1204.0",
    "gn:admin3_code":"120405.0",
    "gn:asciiname":"Niwki",
    "gn:country_code":"PL",
    "gn:dem":172,
    "gn:feature_class":"P",
    "gn:feature_code":"PPL",
    "gn:name":"Niwki",
    "gn:population":0,
    "gn:timezone":"Europe/Warsaw",
    "iso:country":"PL",
    "name:ceb_x_preferred":[
        "Niwki"
    ],
    "name:pol_x_preferred":[
        "Niwki"
    ],
    "name:ukr_x_preferred":[
        "\u041d\u0456\u0432\u043a\u0456"
    ],
    "wof:name":"Niwki",
    "wof:placetype":"locality"
},
  "geometry": {"coordinates":[20.85504,50.21809],"type":"Point"}
}