{
  "type": "Feature",
  "properties": {
    "gn:admin1_code":"75.0",
    "gn:admin2_code":"612.0",
    "gn:admin3_code":"61204.0",
    "gn:asciiname":"Kopanina Kamienska",
    "gn:country_code":"PL",
    "gn:dem":171,
    "gn:feature_class":"P",
    "gn:feature_code":"PPL",
    "gn:name":"Kopanina Kamienska",
    "gn:population":0,
    "gn:timezone":"Europe/Warsaw",
    "iso:country":"PL",
    "wof:name":"Kopanina Kamienska",
    "wof:placetype":"locality"
},
  "geometry": {"coordinates":[21.85211,51.11686],"type":"Point"}
}