{
  "type": "Feature",
  "properties": {
    "gn:admin1_code":"86.0",
    "gn:admin2_code":"3017.0",
    "gn:admin3_code":"301702.0",
    "gn:asciiname":"Boczkow",
    "gn:country_code":"PL",
    "gn:dem":136,
    "gn:feature_class":"P",
    "gn:feature_code":"PPL",
    "gn:name":"Boczk\u00f3w",
    "gn:population":0,
    "gn:timezone":"Europe/Warsaw",
    "iso:country":"PL",
    "name:azb_x_preferred":[
        "\u0628\u0648\u0686\u06a9\u0648\u0648"
    ],
    "name:ceb_x_preferred":[
        "Boczk\u00f3w"
    ],
    "name:fas_x_preferred":[
        "\u0628\u0648\u0686\u06a9\u0648\u0648"
    ],
    "name:nld_x_preferred":[
        "Boczk\u00f3w"
    ],
    "name:pol_x_preferred":[
        "Boczk\u00f3w"
    ],
    "name:ukr_x_preferred":[
        "\u0411\u043e\u0447\u043a\u0443\u0432"
    ],
    "wof:name":"Boczkow",
    "wof:placetype":"locality"
},
  "geometry": {"coordinates":[17.99047000000001,51.73098],"type":"Point"}
}