{
  "type": "Feature",
  "properties": {
    "gn:admin1_code":"86.0",
    "gn:admin2_code":"3017.0",
    "gn:admin3_code":"301702.0",
    "gn:asciiname":"Boczkow",
    "gn:country_code":"PL",
    "gn:dem":136,
    "gn:feature_class":"P",
    "gn:feature_code":"PPL",
    "gn:name":"Boczk\u00f3w",
    "gn:population":0,
    "gn:timezone":"Europe/Warsaw",
    "iso:country":"PL",
    "name:und_x_variant":[
        "Boczk\u00f3w"
    ],
    "wof:name":"Boczkow",
    "wof:placetype":"locality"
},
  "geometry": {"coordinates":[17.99047000000001,51.73098],"type":"Point"}
}