{
  "type": "Feature",
  "properties": {
    "gn:admin1_code":"78.0",
    "gn:admin2_code":"1404.0",
    "gn:admin3_code":"140402.0",
    "gn:asciiname":"Boleslawow",
    "gn:country_code":"PL",
    "gn:dem":117,
    "gn:feature_class":"P",
    "gn:feature_code":"PPL",
    "gn:name":"Boles\u0142aw\u00f3w",
    "gn:population":0,
    "gn:timezone":"Europe/Warsaw",
    "iso:country":"PL",
    "name:ceb_x_preferred":[
        "Boles\u0142aw\u00f3w"
    ],
    "name:fra_x_preferred":[
        "Boles\u0142aw\u00f3w"
    ],
    "name:pol_x_preferred":[
        "Boles\u0142aw\u00f3w"
    ],
    "name:ukr_x_preferred":[
        "\u0411\u043e\u043b\u0435\u0441\u043b\u0430\u0432\u0443\u0432"
    ],
    "wof:name":"Boleslawow",
    "wof:placetype":"locality"
},
  "geometry": {"coordinates":[19.54245,52.44638000000001],"type":"Point"}
}