{
  "type": "Feature",
  "properties": {
    "gn:admin1_code":"79.0",
    "gn:admin2_code":"1608.0",
    "gn:admin3_code":"160807.0",
    "gn:asciiname":"Pruskow",
    "gn:country_code":"PL",
    "gn:dem":229,
    "gn:feature_class":"P",
    "gn:feature_code":"PPL",
    "gn:name":"Prusk\u00f3w",
    "gn:population":0,
    "gn:timezone":"Europe/Warsaw",
    "iso:country":"PL",
    "name:deu_x_preferred":[
        "Pruskau"
    ],
    "name:pol_x_preferred":[
        "Prusk\u00f3w"
    ],
    "name:ukr_x_preferred":[
        "\u041f\u0440\u0443\u0441\u043a\u0443\u0432"
    ],
    "wof:name":"Pruskow",
    "wof:placetype":"locality"
},
  "geometry": {"coordinates":[18.34024,50.78529],"type":"Point"}
}