{
  "type": "Feature",
  "properties": {
    "gn:admin1_code":"82.0",
    "gn:admin2_code":"2216.0",
    "gn:admin3_code":"221605.0",
    "gn:asciiname":"Grzepa",
    "gn:country_code":"PL",
    "gn:dem":46,
    "gn:feature_class":"P",
    "gn:feature_code":"PPL",
    "gn:name":"Grz\u0119pa",
    "gn:population":0,
    "gn:timezone":"Europe/Warsaw",
    "iso:country":"PL",
    "name:pol_x_preferred":[
        "Grz\u0119pa"
    ],
    "name:und_x_variant":[
        "Neuhakenberg"
    ],
    "wof:name":"Grzepa",
    "wof:placetype":"locality"
},
  "geometry": {"coordinates":[19.00897,53.95443],"type":"Point"}
}