{
  "type": "Feature",
  "properties": {
    "gn:admin1_code":"86.0",
    "gn:admin2_code":"3012.0",
    "gn:admin3_code":"301205.0",
    "gn:asciiname":"Nowa Wies",
    "gn:country_code":"PL",
    "gn:dem":147,
    "gn:feature_class":"P",
    "gn:feature_code":"PPL",
    "gn:name":"Nowa Wie\u015b",
    "gn:population":0,
    "gn:timezone":"Europe/Warsaw",
    "iso:country":"PL",
    "wof:name":"Nowa Wies",
    "wof:placetype":"locality"
},
  "geometry": {"coordinates":[17.56843,51.81278],"type":"Point"}
}