{
  "type": "Feature",
  "properties": {
    "gn:admin1_code":"85.0",
    "gn:admin2_code":"2808.0",
    "gn:admin3_code":"280805.0",
    "gn:asciiname":"Pasterzewo",
    "gn:country_code":"PL",
    "gn:dem":132,
    "gn:feature_class":"P",
    "gn:feature_code":"PPL",
    "gn:name":"Pasterzewo",
    "gn:population":0,
    "gn:timezone":"Europe/Warsaw",
    "iso:country":"PL",
    "name:und_x_variant":[
        "Pastern",
        "Pasterzewo"
    ],
    "wof:name":"Pasterzewo",
    "wof:placetype":"locality"
},
  "geometry": {"coordinates":[21.1841,53.99381999999999],"type":"Point"}
}