{
  "type": "Feature",
  "properties": {
    "gn:admin1_code":"85.0",
    "gn:admin2_code":"2815.0",
    "gn:admin3_code":"281508.0",
    "gn:asciiname":"Borzymowo",
    "gn:country_code":"PL",
    "gn:dem":172,
    "gn:feature_class":"P",
    "gn:feature_code":"PPL",
    "gn:name":"Borzymowo",
    "gn:population":0,
    "gn:timezone":"Europe/Warsaw",
    "iso:country":"PL",
    "name:fra_x_preferred":[
        "Borzymowo"
    ],
    "name:pol_x_preferred":[
        "Borzymowo"
    ],
    "name:und_x_variant":[
        "Abrahamsheide"
    ],
    "wof:name":"Borzymowo",
    "wof:placetype":"locality"
},
  "geometry": {"coordinates":[19.92354,53.98455],"type":"Point"}
}