{
  "type": "Feature",
  "properties": {
    "gn:admin1_code":"75.0",
    "gn:admin2_code":"607.0",
    "gn:admin3_code":"60707.0",
    "gn:asciiname":"Olbiecin",
    "gn:country_code":"PL",
    "gn:dem":203,
    "gn:feature_class":"P",
    "gn:feature_code":"PPL",
    "gn:name":"Olbi\u0119cin",
    "gn:population":0,
    "gn:timezone":"Europe/Warsaw",
    "iso:country":"PL",
    "name:fra_x_preferred":[
        "Olbi\u0119cin"
    ],
    "name:pol_x_preferred":[
        "Olbi\u0119cin"
    ],
    "name:szl_x_preferred":[
        "Uolbjy\u0144\u0107in"
    ],
    "name:ukr_x_preferred":[
        "\u041e\u043b\u044c\u0431\u0435\u043d\u0446\u0438\u043d"
    ],
    "name:und_x_variant":[
        "Olbi\u0119cin"
    ],
    "wof:name":"Olbiecin",
    "wof:placetype":"locality"
},
  "geometry": {"coordinates":[22.12504,50.89456],"type":"Point"}
}