{
  "type": "Feature",
  "properties": {
    "gn:country":"PL",
    "gn:fcode":"PPLA3",
    "gn:population":1000,
    "iso:country":"PL",
    "name:ceb_x_preferred":[
        "Or\u0142y"
    ],
    "name:fra_x_preferred":[
        "Or\u0142y"
    ],
    "name:nld_x_preferred":[
        "Or\u0142y"
    ],
    "qs_pg:aaroncc":"PL",
    "qs_pg:gn_country":"PL",
    "qs_pg:gn_fcode":"PPLA3",
    "qs_pg:gn_pop":1000,
    "qs_pg:name":"Or\u0142y",
    "qs_pg:name_adm0":"Polska",
    "qs_pg:name_adm1":"Podkarpackie",
    "qs_pg:photos_9k":1,
    "qs_pg:photos_9r":1,
    "qs_pg:photos_all":3,
    "qs_pg:photos_sr":0,
    "qs_pg:pop_sr":2,
    "qs_pg:qs_pg_placetype":"localadmin",
    "qs_pg:qs_pg_placetype_gp":"LocalAdmin",
    "qs_pg:woe_adm0":23424923,
    "woe:adm0_id":23424923,
    "woe:name_adm0":"Polska",
    "woe:name_adm1":"Podkarpackie",
    "woe:placetype":"LocalAdmin",
    "wof:name":"Or\u0142y",
    "wof:placetype":"localadmin",
    "wof:population":1000
},
  "geometry": {"coordinates":[22.80298,49.87107],"type":"Point"}
}