{
  "type": "Feature",
  "properties": {
    "gn:admin1_code":"78.0",
    "gn:admin2_code":"1403.0",
    "gn:admin3_code":"140311.0",
    "gn:asciiname":"Kolonia Sobolew",
    "gn:country_code":"PL",
    "gn:dem":159,
    "gn:feature_class":"P",
    "gn:feature_code":"PPL",
    "gn:name":"Kolonia Sobolew",
    "gn:population":0,
    "gn:timezone":"Europe/Warsaw",
    "iso:country":"PL",
    "wof:name":"Kolonia Sobolew",
    "wof:placetype":"locality"
},
  "geometry": {"coordinates":[21.67129,51.71919000000001],"type":"Point"}
}