{
  "type": "Feature",
  "properties": {
    "gn:admin1_code":"74.0",
    "gn:admin2_code":"1011.0",
    "gn:admin3_code":"101106.0",
    "gn:asciiname":"Rzeczyca",
    "gn:country_code":"PL",
    "gn:dem":134,
    "gn:feature_class":"P",
    "gn:feature_code":"PPL",
    "gn:name":"Rzeczyca",
    "gn:population":0,
    "gn:timezone":"Europe/Warsaw",
    "iso:country":"PL",
    "name:bel_x_preferred":[
        "\u0420\u044d\u0447\u044b\u0446\u0430"
    ],
    "name:ceb_x_preferred":[
        "Rzeczyca"
    ],
    "name:deu_x_preferred":[
        "Rzeczyca"
    ],
    "name:fra_x_preferred":[
        "Rzeczyca"
    ],
    "name:nld_x_preferred":[
        "Rzeczyca"
    ],
    "name:pol_x_preferred":[
        "Rzeczyca"
    ],
    "name:ukr_x_preferred":[
        "\u0416\u0435\u0447\u0438\u0446\u044f"
    ],
    "wof:name":"Rzeczyca",
    "wof:placetype":"locality"
},
  "geometry": {"coordinates":[18.8424,51.73903],"type":"Point"}
}