{
  "type": "Feature",
  "properties": {
    "gn:admin1_code":"86.0",
    "gn:admin2_code":"3010.0",
    "gn:admin3_code":"301001.0",
    "gn:asciiname":"Kolno",
    "gn:country_code":"PL",
    "gn:dem":81,
    "gn:feature_class":"P",
    "gn:feature_code":"PPL",
    "gn:name":"Kolno",
    "gn:population":0,
    "gn:timezone":"Europe/Warsaw",
    "iso:country":"PL",
    "name:fra_x_preferred":[
        "Kolno"
    ],
    "name:pol_x_preferred":[
        "Kolno"
    ],
    "name:ukr_x_preferred":[
        "\u041a\u043e\u043b\u044c\u043d\u043e"
    ],
    "wof:name":"Kolno",
    "wof:placetype":"locality"
},
  "geometry": {"coordinates":[18.10496,52.22362],"type":"Point"}
}