{
  "type": "Feature",
  "properties": {
    "gn:admin1_code":"72.0",
    "gn:admin2_code":"215.0",
    "gn:admin3_code":"21502.0",
    "gn:asciiname":"Swojkow",
    "gn:country_code":"PL",
    "gn:dem":136,
    "gn:feature_class":"P",
    "gn:feature_code":"PPL",
    "gn:name":"Swojk\u00f3w",
    "gn:population":0,
    "gn:timezone":"Europe/Warsaw",
    "iso:country":"PL",
    "name:pol_x_preferred":[
        "Swojk\u00f3w"
    ],
    "name:ukr_x_preferred":[
        "\u0421\u0432\u043e\u0439\u043a\u0443\u0432"
    ],
    "name:und_x_variant":[
        "Swojk\u00f3w"
    ],
    "wof:name":"Swojkow",
    "wof:placetype":"locality"
},
  "geometry": {"coordinates":[17.13235,50.94252],"type":"Point"}
}