{
  "type": "Feature",
  "properties": {
    "gn:admin1_code":"74.0",
    "gn:admin2_code":"1001.0",
    "gn:admin3_code":"100104.0",
    "gn:asciiname":"Antoniowka",
    "gn:country_code":"PL",
    "gn:dem":200,
    "gn:feature_class":"P",
    "gn:feature_code":"PPL",
    "gn:name":"Antoni\u00f3wka",
    "gn:population":0,
    "gn:timezone":"Europe/Warsaw",
    "iso:country":"PL",
    "name:fra_x_preferred":[
        "Antoni\u00f3wka"
    ],
    "name:pol_x_preferred":[
        "Antoni\u00f3wka"
    ],
    "name:srp_x_preferred":[
        "\u0410\u043d\u0442\u043e\u045a\u0438\u043d\u043e\u0432\u043a\u0430"
    ],
    "name:ukr_x_preferred":[
        "\u0410\u043d\u0442\u043e\u043d\u044e\u0432\u043a\u0430"
    ],
    "wof:name":"Antoniowka",
    "wof:placetype":"locality"
},
  "geometry": {"coordinates":[19.2556,51.20597],"type":"Point"}
}