{
  "type": "Feature",
  "properties": {
    "gn:admin1_code":"78.0",
    "gn:admin2_code":"1428.0",
    "gn:admin3_code":"142808.0",
    "gn:asciiname":"Lisice",
    "gn:country_code":"PL",
    "gn:dem":82,
    "gn:feature_class":"P",
    "gn:feature_code":"PPL",
    "gn:name":"Lisice",
    "gn:population":0,
    "gn:timezone":"Europe/Warsaw",
    "iso:country":"PL",
    "name:fra_x_preferred":[
        "Lisice"
    ],
    "name:pol_x_preferred":[
        "Lisice"
    ],
    "name:ukr_x_preferred":[
        "\u041b\u0456\u0441\u0456\u0446\u0435"
    ],
    "wof:name":"Lisice",
    "wof:placetype":"locality"
},
  "geometry": {"coordinates":[20.47839,52.20794],"type":"Point"}
}