{
  "type": "Feature",
  "properties": {
    "gn:gn_country":"PL",
    "gn:gn_fcode":"PPLA3",
    "gn:gn_pop":600,
    "gn:population":600,
    "iso:country":"PL",
    "name:ceb_x_preferred":[
        "Sadowie"
    ],
    "name:deu_x_preferred":[
        "Sadowie"
    ],
    "name:eng_x_preferred":[
        "Gmina Sadowie"
    ],
    "name:fra_x_preferred":[
        "Sadowie"
    ],
    "name:pol_x_preferred":[
        "Sadowie"
    ],
    "name:por_x_preferred":[
        "Comuna de Sadowie"
    ],
    "name:rus_x_preferred":[
        "\u0421\u0430\u0434\u043e\u0432\u0435"
    ],
    "name:slk_x_preferred":[
        "Gmina Sadowie"
    ],
    "name:ukr_x_preferred":[
        "\u0490\u043c\u0456\u043d\u0430 \u0421\u0430\u0434\u043e\u0432\u0435"
    ],
    "name:war_x_preferred":[
        "Gmina Sadowie"
    ],
    "qs_pg:aaroncc":"PL",
    "qs_pg:gn_country":"PL",
    "qs_pg:gn_fcode":"PPLA3",
    "qs_pg:gn_pop":600,
    "qs_pg:name":"Sadowie",
    "qs_pg:name_adm0":"Polska",
    "qs_pg:name_adm1":"Swi\u0119tokrzyskie",
    "qs_pg:photos_9k":1,
    "qs_pg:photos_9r":1,
    "qs_pg:photos_all":1,
    "qs_pg:photos_sr":0,
    "qs_pg:pop_sr":2,
    "qs_pg:qs_pg_placetype":"localadmin",
    "qs_pg:qs_pg_placetype_gp":"LocalAdmin",
    "qs_pg:woe_adm0":23424923,
    "woe:adm0_id":23424923,
    "woe:name_adm0":"Polska",
    "woe:name_adm1":"Swi\u0119tokrzyskie",
    "woe:placetype":"LocalAdmin",
    "wof:name":"Sadowie",
    "wof:placetype":"localadmin",
    "wof:population":600
},
  "geometry": {"coordinates":[21.36884,50.85261],"type":"Point"}
}