{
  "type": "Feature",
  "properties": {
    "gn:admin1_code":"85.0",
    "gn:admin2_code":"2814.0",
    "gn:admin3_code":"281401.0",
    "gn:asciiname":"Jedzbark",
    "gn:country_code":"PL",
    "gn:dem":135,
    "gn:feature_class":"P",
    "gn:feature_code":"PPL",
    "gn:name":"Jedzbark",
    "gn:population":0,
    "gn:timezone":"Europe/Warsaw",
    "iso:country":"PL",
    "name:ceb_x_preferred":[
        "Jedzbark"
    ],
    "name:deu_x_preferred":[
        "Jedzbark"
    ],
    "name:pol_x_preferred":[
        "Jedzbark"
    ],
    "name:ukr_x_preferred":[
        "\u0404\u0434\u0437\u0431\u0430\u0440\u043a"
    ],
    "name:und_x_variant":[
        "Hirschberg",
        "Jecpark"
    ],
    "name:vie_x_preferred":[
        "Jedzbark"
    ],
    "wof:name":"Jedzbark",
    "wof:placetype":"locality"
},
  "geometry": {"coordinates":[20.75645,53.78596],"type":"Point"}
}