{
  "type": "Feature",
  "properties": {
    "gn:admin1_code":"85.0",
    "gn:admin2_code":"2805.0",
    "gn:admin3_code":"280504.0",
    "gn:asciiname":"Kosinowo",
    "gn:country_code":"PL",
    "gn:dem":170,
    "gn:feature_class":"P",
    "gn:feature_code":"PPL",
    "gn:name":"Kosinowo",
    "gn:population":0,
    "gn:timezone":"Europe/Warsaw",
    "iso:country":"PL",
    "name:azb_x_preferred":[
        "\u06a9\u0648\u0634\u0646\u0648\u0648\u0648"
    ],
    "name:deu_x_preferred":[
        "Kosinowo"
    ],
    "name:fas_x_preferred":[
        "\u06a9\u0648\u0634\u0646\u0648\u0648\u0648"
    ],
    "name:fra_x_preferred":[
        "Kosinowo"
    ],
    "name:pol_x_preferred":[
        "Kosinowo"
    ],
    "wof:name":"Kosinowo",
    "wof:placetype":"locality"
},
  "geometry": {"coordinates":[22.22714,53.72866],"type":"Point"}
}