{
  "type": "Feature",
  "properties": {
    "gn:admin1_code":"74.0",
    "gn:admin2_code":"1002.0",
    "gn:admin3_code":"100206.0",
    "gn:asciiname":"Golebiow",
    "gn:country_code":"PL",
    "gn:dem":112,
    "gn:feature_class":"P",
    "gn:feature_code":"PPL",
    "gn:name":"Go\u0142\u0119bi\u00f3w",
    "gn:population":0,
    "gn:timezone":"Europe/Warsaw",
    "iso:country":"PL",
    "name:und_x_variant":[
        "Go\u0142\u0119bie",
        "Go\u0142\u0119bi\u00f3w"
    ],
    "wof:name":"Golebiow",
    "wof:placetype":"locality"
},
  "geometry": {"coordinates":[19.34271,52.26328],"type":"Point"}
}