{
  "type": "Feature",
  "properties": {
    "gn:admin1_code":"81.0",
    "gn:admin2_code":"2007.0",
    "gn:admin3_code":"200705.0",
    "gn:asciiname":"Kosaki",
    "gn:country_code":"PL",
    "gn:dem":118,
    "gn:feature_class":"P",
    "gn:feature_code":"PPL",
    "gn:name":"Kosaki",
    "gn:population":0,
    "gn:timezone":"Europe/Warsaw",
    "iso:country":"PL",
    "name:ceb_x_preferred":[
        "Kosaki"
    ],
    "name:lit_x_preferred":[
        "Kosakai"
    ],
    "name:pol_x_preferred":[
        "Kosaki"
    ],
    "name:ukr_x_preferred":[
        "\u041a\u043e\u0441\u0430\u043a\u0456"
    ],
    "wof:name":"Kosaki",
    "wof:placetype":"locality"
},
  "geometry": {"coordinates":[22.26603,53.15583],"type":"Point"}
}