{
  "type": "Feature",
  "properties": {
    "gn:admin1_code":"78.0",
    "gn:admin2_code":"1403.0",
    "gn:admin3_code":"140306.0",
    "gn:asciiname":"Krzywda",
    "gn:country_code":"PL",
    "gn:dem":126,
    "gn:feature_class":"P",
    "gn:feature_code":"PPL",
    "gn:name":"Krzywda",
    "gn:population":0,
    "gn:timezone":"Europe/Warsaw",
    "iso:country":"PL",
    "name:ceb_x_preferred":[
        "Krzywda"
    ],
    "name:deu_x_preferred":[
        "Krzywda"
    ],
    "name:fra_x_preferred":[
        "Krzywda"
    ],
    "name:nld_x_preferred":[
        "Krzywda"
    ],
    "name:pol_x_preferred":[
        "Krzywda"
    ],
    "name:spa_x_preferred":[
        "Krzywda"
    ],
    "name:ukr_x_preferred":[
        "\u041a\u0448\u0438\u0432\u0434\u0430"
    ],
    "wof:name":"Krzywda",
    "wof:placetype":"locality"
},
  "geometry": {"coordinates":[21.52028,51.81843],"type":"Point"}
}