{
  "type": "Feature",
  "properties": {
    "gn:admin1_code":"76.0",
    "gn:admin2_code":"808.0",
    "gn:admin3_code":"80805.0",
    "gn:asciiname":"Rosin",
    "gn:country_code":"PL",
    "gn:dem":102,
    "gn:feature_class":"P",
    "gn:feature_code":"PPL",
    "gn:name":"Rosin",
    "gn:population":0,
    "gn:timezone":"Europe/Warsaw",
    "iso:country":"PL",
    "name:deu_x_historical":[
        "Rissen"
    ],
    "name:deu_x_preferred":[
        "Rissen"
    ],
    "name:fra_x_preferred":[
        "Rosin"
    ],
    "name:pol_x_preferred":[
        "Rosin"
    ],
    "name:ukr_x_preferred":[
        "\u0420\u043e\u0441\u0456\u043d"
    ],
    "wof:name":"Rosin",
    "wof:placetype":"locality"
},
  "geometry": {"coordinates":[15.5786,52.1657],"type":"Point"}
}