{
  "type": "Feature",
  "properties": {
    "gn:admin1_code":"81.0",
    "gn:admin2_code":"2009.0",
    "gn:admin3_code":"200905.0",
    "gn:asciiname":"Posejanka",
    "gn:country_code":"PL",
    "gn:dem":129,
    "gn:feature_class":"P",
    "gn:feature_code":"PPL",
    "gn:name":"Posejanka",
    "gn:population":0,
    "gn:timezone":"Europe/Warsaw",
    "iso:country":"PL",
    "name:lit_x_preferred":[
        "Posejanka"
    ],
    "name:pol_x_preferred":[
        "Posejanka"
    ],
    "name:ukr_x_preferred":[
        "\u041f\u043e\u0441\u0435\u044f\u043d\u043a\u0430"
    ],
    "wof:name":"Posejanka",
    "wof:placetype":"locality"
},
  "geometry": {"coordinates":[23.3569,54.07357],"type":"Point"}
}