{
  "type": "Feature",
  "properties": {
    "gn:admin1_code":"74.0",
    "gn:admin2_code":"1020.0",
    "gn:admin3_code":"102003.0",
    "gn:asciiname":"Stepowizna",
    "gn:country_code":"PL",
    "gn:dem":200,
    "gn:feature_class":"P",
    "gn:feature_code":"PPL",
    "gn:name":"St\u0119powizna",
    "gn:population":0,
    "gn:timezone":"Europe/Warsaw",
    "iso:country":"PL",
    "wof:name":"Stepowizna",
    "wof:placetype":"locality"
},
  "geometry": {"coordinates":[19.43839,51.86244],"type":"Point"}
}