{
  "type": "Feature",
  "properties": {
    "gn:admin1_code":"83.0",
    "gn:admin2_code":"2412.0",
    "gn:admin3_code":"241204.0",
    "gn:asciiname":"Dzimierz",
    "gn:country_code":"PL",
    "gn:dem":236,
    "gn:feature_class":"P",
    "gn:feature_code":"PPL",
    "gn:name":"Dzimierz",
    "gn:population":0,
    "gn:timezone":"Europe/Warsaw",
    "iso:country":"PL",
    "name:pol_x_preferred":[
        "Dzimierz"
    ],
    "name:ukr_x_preferred":[
        "\u0414\u0437\u0456\u043c\u0435\u0436"
    ],
    "wof:name":"Dzimierz",
    "wof:placetype":"locality"
},
  "geometry": {"coordinates":[18.35219,50.1068],"type":"Point"}
}