{
  "type": "Feature",
  "properties": {
    "gn:admin1_code":"82.0",
    "gn:admin2_code":"2208.0",
    "gn:admin3_code":"220804.0",
    "gn:asciiname":"Ledziechowo",
    "gn:country_code":"PL",
    "gn:dem":30,
    "gn:feature_class":"P",
    "gn:feature_code":"PPL",
    "gn:name":"L\u0119dziechowo",
    "gn:population":0,
    "gn:timezone":"Europe/Warsaw",
    "iso:country":"PL",
    "name:ceb_x_preferred":[
        "L\u0119dziechowo"
    ],
    "name:nld_x_preferred":[
        "L\u0119dziechowo"
    ],
    "name:pol_x_preferred":[
        "L\u0119dziechowo"
    ],
    "wof:name":"Ledziechowo",
    "wof:placetype":"locality"
},
  "geometry": {"coordinates":[17.68524,54.64682],"type":"Point"}
}