{
  "type": "Feature",
  "properties": {
    "gn:admin1_code":"86.0",
    "gn:admin2_code":"3010.0",
    "gn:admin3_code":"301007.0",
    "gn:asciiname":"Siaszyce Czwarte",
    "gn:country_code":"PL",
    "gn:dem":112,
    "gn:feature_class":"P",
    "gn:feature_code":"PPL",
    "gn:name":"Si\u0105szyce Czwarte",
    "gn:population":0,
    "gn:timezone":"Europe/Warsaw",
    "iso:country":"PL",
    "wof:name":"Siaszyce Czwarte",
    "wof:placetype":"locality"
},
  "geometry": {"coordinates":[18.16667,52.03333],"type":"Point"}
}