{
  "type": "Feature",
  "properties": {
    "gn:admin1_code":"80.0",
    "gn:admin2_code":"1803.0",
    "gn:admin3_code":"180303.0",
    "gn:asciiname":"Borowa",
    "gn:country_code":"PL",
    "gn:dem":214,
    "gn:feature_class":"P",
    "gn:feature_code":"PPL",
    "gn:name":"Borowa",
    "gn:population":0,
    "gn:timezone":"Europe/Warsaw",
    "iso:country":"PL",
    "name:bel_x_preferred":[
        "\u0411\u0430\u0440\u0430\u0432\u0430\u044f"
    ],
    "name:bos_x_preferred":[
        "Borova"
    ],
    "name:ceb_x_preferred":[
        "Borowa"
    ],
    "name:deu_x_preferred":[
        "Borowa"
    ],
    "name:fra_x_preferred":[
        "Borowa"
    ],
    "name:heb_x_preferred":[
        "\u05d1\u05d5\u05e8\u05d5\u05d1\u05d4"
    ],
    "name:hye_x_preferred":[
        "\u0532\u0578\u0580\u0578\u057e\u0561\u0575\u0561"
    ],
    "name:nld_x_preferred":[
        "Borowa"
    ],
    "name:pol_x_preferred":[
        "Borowa"
    ],
    "name:rus_x_preferred":[
        "\u0411\u043e\u0440\u043e\u0432\u0430\u044f"
    ],
    "name:srp_x_preferred":[
        "\u0411\u043e\u0440\u043e\u0432\u0430"
    ],
    "name:swe_x_preferred":[
        "Borowa"
    ],
    "name:ukr_x_preferred":[
        "\u0411\u043e\u0440\u043e\u0432\u0430"
    ],
    "wof:name":"Borowa",
    "wof:placetype":"locality"
},
  "geometry": {"coordinates":[21.28706,50.08533],"type":"Point"}
}