{
  "type": "Feature",
  "properties": {
    "gn:admin1_code":"78",
    "gn:admin2_code":"1438",
    "gn:admin3_code":"143805.0",
    "gn:asciiname":"Janowek",
    "gn:country_code":"PL",
    "gn:dem":95,
    "gn:feature_class":"P",
    "gn:feature_code":"PPL",
    "gn:name":"Jan\u00f3wek",
    "gn:population":0,
    "gn:timezone":"Europe/Warsaw",
    "iso:country":"PL",
    "wof:name":"Janowek",
    "wof:placetype":"locality"
},
  "geometry": {"coordinates":[20.37123,52.11502],"type":"Point"}
}