{
  "type": "Feature",
  "properties": {
    "gn:admin1_code":"77.0",
    "gn:admin2_code":"1210.0",
    "gn:admin3_code":"121011.0",
    "gn:asciiname":"Andrzejowka",
    "gn:country_code":"PL",
    "gn:dem":452,
    "gn:feature_class":"P",
    "gn:feature_code":"PPL",
    "gn:name":"Andrzej\u00f3wka",
    "gn:population":0,
    "gn:timezone":"Europe/Warsaw",
    "iso:country":"PL",
    "name:azb_x_preferred":[
        "\u0627\u0646\u062f\u0698\u06cc\u0648\u0648\u06a9\u0627"
    ],
    "name:fas_x_preferred":[
        "\u0627\u0646\u062f\u0698\u06cc\u0648\u0648\u06a9\u0627"
    ],
    "name:heb_x_preferred":[
        "\u05d0\u05e0\u05d3\u05d6'\u05d9\u05d9\u05d5\u05d1\u05e7\u05d4"
    ],
    "name:pol_x_preferred":[
        "Andrzej\u00f3wka"
    ],
    "name:rue_x_preferred":[
        "\u0410\u043d\u0434\u0440\u0435\u0457\u0432\u043a\u0430"
    ],
    "name:ukr_x_preferred":[
        "\u0410\u043d\u0434\u0440\u0456\u0457\u0432\u043a\u0430"
    ],
    "wof:name":"Andrzejowka",
    "wof:placetype":"locality"
},
  "geometry": {"coordinates":[20.82411,49.34185],"type":"Point"}
}