{
  "type": "Feature",
  "properties": {
    "gn:admin1_code":"77.0",
    "gn:admin2_code":"1210.0",
    "gn:admin3_code":"121011.0",
    "gn:asciiname":"Andrzejowka",
    "gn:country_code":"PL",
    "gn:dem":452,
    "gn:feature_class":"P",
    "gn:feature_code":"PPL",
    "gn:name":"Andrzej\u00f3wka",
    "gn:population":0,
    "gn:timezone":"Europe/Warsaw",
    "iso:country":"PL",
    "name:und_x_variant":[
        "Andrzej\u00f3wka"
    ],
    "wof:name":"Andrzejowka",
    "wof:placetype":"locality"
},
  "geometry": {"coordinates":[20.82411,49.34185],"type":"Point"}
}