{
  "type": "Feature",
  "properties": {
    "gn:admin1_code":"74.0",
    "gn:admin2_code":"1011.0",
    "gn:admin3_code":"101106.0",
    "gn:asciiname":"Skeczno",
    "gn:country_code":"PL",
    "gn:dem":124,
    "gn:feature_class":"P",
    "gn:feature_code":"PPL",
    "gn:name":"Sk\u0119czno",
    "gn:population":0,
    "gn:timezone":"Europe/Warsaw",
    "iso:country":"PL",
    "name:und_x_variant":[
        "Sk\u0119czno"
    ],
    "wof:name":"Skeczno",
    "wof:placetype":"locality"
},
  "geometry": {"coordinates":[18.78541,51.75181],"type":"Point"}
}