{
  "type": "Feature",
  "properties": {
    "gn:admin1_code":"87.0",
    "gn:admin2_code":"3210.0",
    "gn:admin3_code":"321004.0",
    "gn:asciiname":"Otanow",
    "gn:country_code":"PL",
    "gn:dem":67,
    "gn:feature_class":"P",
    "gn:feature_code":"PPL",
    "gn:name":"Otan\u00f3w",
    "gn:population":0,
    "gn:timezone":"Europe/Warsaw",
    "iso:country":"PL",
    "name:und_x_variant":[
        "Wuthenow",
        "Otan\u00f3w"
    ],
    "wof:name":"Otanow",
    "wof:placetype":"locality"
},
  "geometry": {"coordinates":[14.87548,52.99771],"type":"Point"}
}