{
  "type": "Feature",
  "properties": {
    "gn:admin1_code":"77.0",
    "gn:admin2_code":"1216.0",
    "gn:admin3_code":"121606.0",
    "gn:asciiname":"Przymiarki",
    "gn:cc2":"PL",
    "gn:country_code":"PL",
    "gn:dem":334,
    "gn:feature_class":"P",
    "gn:feature_code":"PPL",
    "gn:name":"Przymiarki",
    "gn:population":0,
    "gn:timezone":"Europe/Warsaw",
    "iso:country":"PL",
    "name:und_x_variant":[
        "Przymiarek",
        "Przymiarki"
    ],
    "wof:name":"Przymiarki",
    "wof:placetype":"locality"
},
  "geometry": {"coordinates":[21.16667,49.91667],"type":"Point"}
}