{
  "type": "Feature",
  "properties": {
    "gn:admin1_code":"78.0",
    "gn:admin2_code":"1416.0",
    "gn:admin3_code":"141606.0",
    "gn:asciiname":"Godlewo Mierniki",
    "gn:country_code":"PL",
    "gn:dem":117,
    "gn:feature_class":"P",
    "gn:feature_code":"PPL",
    "gn:name":"Godlewo Mierniki",
    "gn:population":0,
    "gn:timezone":"Europe/Warsaw",
    "iso:country":"PL",
    "name:fra_x_preferred":[
        "Godlewo Mierniki"
    ],
    "name:pol_x_preferred":[
        "Godlewo-Mierniki"
    ],
    "name:ukr_x_preferred":[
        "\u0490\u043e\u0434\u043b\u0435\u0432\u043e-\u041c\u0435\u0440\u043d\u0438\u043a\u0438"
    ],
    "wof:name":"Godlewo Mierniki",
    "wof:placetype":"locality"
},
  "geometry": {"coordinates":[22.29615,52.72261999999999],"type":"Point"}
}