{
  "type": "Feature",
  "properties": {
    "gn:admin1_code":"83.0",
    "gn:admin2_code":"2416.0",
    "gn:admin3_code":"241604.0",
    "gn:asciiname":"Szypowice",
    "gn:country_code":"PL",
    "gn:dem":343,
    "gn:feature_class":"P",
    "gn:feature_code":"PPL",
    "gn:name":"Szypowice",
    "gn:population":0,
    "gn:timezone":"Europe/Warsaw",
    "iso:country":"PL",
    "wof:name":"Szypowice",
    "wof:placetype":"locality"
},
  "geometry": {"coordinates":[19.62192000000001,50.51454],"type":"Point"}
}