{
  "type": "Feature",
  "properties": {
    "gn:admin1_code":"78.0",
    "gn:admin2_code":"1425.0",
    "gn:admin3_code":"142508.0",
    "gn:asciiname":"Jaroszki",
    "gn:country_code":"PL",
    "gn:dem":140,
    "gn:feature_class":"P",
    "gn:feature_code":"PPL",
    "gn:name":"Jaroszki",
    "gn:population":0,
    "gn:timezone":"Europe/Warsaw",
    "iso:country":"PL",
    "name:fra_x_preferred":[
        "Jaroszki"
    ],
    "name:pol_x_preferred":[
        "Jaroszki"
    ],
    "name:ukr_x_preferred":[
        "\u042f\u0440\u043e\u0448\u043a\u0456"
    ],
    "name:urd_x_preferred":[
        "\u062c\u0631\u0648\u0633\u0632\u06a9\u06cc"
    ],
    "wof:name":"Jaroszki",
    "wof:placetype":"locality"
},
  "geometry": {"coordinates":[21.34624,51.49274000000001],"type":"Point"}
}