{
  "type": "Feature",
  "properties": {
    "gn:admin1_code":"78.0",
    "gn:admin2_code":"1425.0",
    "gn:admin3_code":"142508.0",
    "gn:asciiname":"Jaroszki",
    "gn:country_code":"PL",
    "gn:dem":140,
    "gn:feature_class":"P",
    "gn:feature_code":"PPL",
    "gn:name":"Jaroszki",
    "gn:population":0,
    "gn:timezone":"Europe/Warsaw",
    "iso:country":"PL",
    "wof:name":"Jaroszki",
    "wof:placetype":"locality"
},
  "geometry": {"coordinates":[21.34624,51.49274000000001],"type":"Point"}
}