{
  "type": "Feature",
  "properties": {
    "gn:admin1_code":"86.0",
    "gn:admin2_code":"3010.0",
    "gn:admin3_code":"301013.0",
    "gn:asciiname":"Tomislawice",
    "gn:country_code":"PL",
    "gn:dem":100,
    "gn:feature_class":"P",
    "gn:feature_code":"PPL",
    "gn:name":"Tomis\u0142awice",
    "gn:population":0,
    "gn:timezone":"Europe/Warsaw",
    "iso:country":"PL",
    "name:pol_x_preferred":[
        "Tomis\u0142awice"
    ],
    "name:ukr_x_preferred":[
        "\u0422\u043e\u043c\u0456\u0441\u043b\u0430\u0432\u0456\u0446\u0435"
    ],
    "wof:name":"Tomislawice",
    "wof:placetype":"locality"
},
  "geometry": {"coordinates":[18.50252,52.48477],"type":"Point"}
}