{
  "type": "Feature",
  "properties": {
    "gn:admin1_code":"85.0",
    "gn:admin2_code":"2816.0",
    "gn:admin3_code":"281603.0",
    "gn:asciiname":"Rostki",
    "gn:country_code":"PL",
    "gn:dem":119,
    "gn:feature_class":"P",
    "gn:feature_code":"PPL",
    "gn:name":"Rostki",
    "gn:population":0,
    "gn:timezone":"Europe/Warsaw",
    "iso:country":"PL",
    "name:deu_x_preferred":[
        "Rostki"
    ],
    "name:fra_x_preferred":[
        "Rostki"
    ],
    "name:lit_x_preferred":[
        "Rostkai"
    ],
    "name:pol_x_preferred":[
        "Rostki"
    ],
    "name:ukr_x_preferred":[
        "\u0420\u043e\u0441\u0442\u043a\u0456"
    ],
    "name:und_x_variant":[
        "Rostken"
    ],
    "wof:name":"Rostki",
    "wof:placetype":"locality"
},
  "geometry": {"coordinates":[21.90139,53.702],"type":"Point"}
}