{
  "type": "Feature",
  "properties": {
    "iso:country":"PL",
    "name:eng_x_preferred":[
        "Blonia"
    ],
    "name:pol_x_preferred":[
        "B\u0142onia"
    ],
    "wof:name":"Blonia",
    "wof:placetype":"neighbourhood"
},
  "geometry": {"coordinates":[18.71520068609227,54.35074457470712],"type":"Point"}
}