{
  "type": "Feature",
  "properties": {
    "gn:gn_country":"PL",
    "gn:gn_fcode":"PPL",
    "gn:gn_pop":0,
    "iso:country":"PL",
    "name:ast_x_preferred":[
        "Wierzenica"
    ],
    "name:azb_x_preferred":[
        "\u0648\u06cc\u0698\u0646\u0642\u062a\u0633\u0627"
    ],
    "name:ceb_x_preferred":[
        "Wierzenica"
    ],
    "name:eng_x_preferred":[
        "Wierzenica"
    ],
    "name:fas_x_preferred":[
        "\u0648\u06cc\u0698\u0646\u06af\u062a\u0633\u0627"
    ],
    "name:fra_x_preferred":[
        "Wierzenica"
    ],
    "name:nld_x_preferred":[
        "Wierzenica"
    ],
    "name:pol_x_preferred":[
        "Wierzenica"
    ],
    "name:ukr_x_preferred":[
        "\u0412\u0435\u0436\u0435\u043d\u0438\u0446\u044f"
    ],
    "qs_pg:aaroncc":"PL",
    "qs_pg:gn_country":"PL",
    "qs_pg:gn_fcode":"PPL",
    "qs_pg:gn_pop":0,
    "qs_pg:name":"Wierzenica",
    "qs_pg:name_adm0":"Polska",
    "qs_pg:name_adm1":"Wielkopolskie",
    "qs_pg:photos_9k":1,
    "qs_pg:photos_9r":1,
    "qs_pg:photos_all":2,
    "qs_pg:photos_sr":0,
    "qs_pg:pop_sr":0,
    "qs_pg:qs_pg_placetype":"locality",
    "qs_pg:qs_pg_placetype_gp":"Town",
    "qs_pg:woe_adm0":23424923,
    "woe:adm0_id":23424923,
    "woe:name_adm0":"Polska",
    "woe:name_adm1":"Wielkopolskie",
    "woe:placetype":"Town",
    "wof:name":"Wierzenica",
    "wof:placetype":"locality"
},
  "geometry": {"coordinates":[17.06977,52.46191],"type":"Point"}
}