{
  "type": "Feature",
  "properties": {
    "gn:country":"PL",
    "gn:fcode":"PPLA3",
    "gn:population":995,
    "iso:country":"PL",
    "name:ceb_x_preferred":[
        "Lubrza"
    ],
    "name:deu_x_historical":[
        "Liebenau bei Schwiebus",
        "Liebenau"
    ],
    "name:deu_x_preferred":[
        "Liebenau bei Schwiebus"
    ],
    "name:deu_x_variant":[
        "Liebenau",
        "Lubrza"
    ],
    "name:fra_x_preferred":[
        "Lubrza"
    ],
    "name:ita_x_preferred":[
        "Lubrza"
    ],
    "name:nld_x_preferred":[
        "Lubrza"
    ],
    "name:pol_x_preferred":[
        "Lubrza"
    ],
    "name:ukr_x_preferred":[
        "\u041b\u044e\u0431\u0436\u0430"
    ],
    "name:und_x_variant":[
        "Lubna"
    ],
    "qs_pg:aaroncc":"PL",
    "qs_pg:gn_country":"PL",
    "qs_pg:gn_fcode":"PPLA3",
    "qs_pg:gn_pop":995,
    "qs_pg:name":"Lubrza",
    "qs_pg:photos_9r":0,
    "qs_pg:photos_sr":0,
    "qs_pg:pop_sr":2,
    "qs_pg:qs_pg_placetype":"locality",
    "wof:coterminous":[
        1477751209
    ],
    "wof:name":"Lubrza",
    "wof:placetype":"locality",
    "wof:population":995
},
  "geometry": {"coordinates":[15.44317,52.30418],"type":"Point"}
}