{
  "type": "Feature",
  "properties": {
    "gn:admin1_code":"74.0",
    "gn:admin2_code":"1010.0",
    "gn:admin3_code":"101004.0",
    "gn:asciiname":"Zychlin",
    "gn:country_code":"PL",
    "gn:dem":212,
    "gn:feature_class":"P",
    "gn:feature_code":"PPL",
    "gn:name":"\u017bychlin",
    "gn:population":0,
    "gn:timezone":"Europe/Warsaw",
    "iso:country":"PL",
    "name:fra_x_preferred":[
        "\u017bychlin"
    ],
    "name:pol_x_preferred":[
        "\u017bychlin"
    ],
    "name:ukr_x_preferred":[
        "\u0416\u0438\u0445\u043b\u0456\u043d"
    ],
    "wof:name":"Zychlin",
    "wof:placetype":"locality"
},
  "geometry": {"coordinates":[19.62064,51.46101],"type":"Point"}
}