{
  "type": "Feature",
  "properties": {
    "gn:admin1_code":"75.0",
    "gn:admin2_code":"601.0",
    "gn:admin3_code":"60103.0",
    "gn:asciiname":"Zlamany Most",
    "gn:country_code":"PL",
    "gn:dem":143,
    "gn:feature_class":"P",
    "gn:feature_code":"PPL",
    "gn:name":"Z\u0142amany Most",
    "gn:population":0,
    "gn:timezone":"Europe/Warsaw",
    "iso:country":"PL",
    "name:und_x_variant":[
        "Kolonia Z\u0142amany Most",
        "Z\u0142amany Most"
    ],
    "wof:name":"Zlamany Most",
    "wof:placetype":"locality"
},
  "geometry": {"coordinates":[23.08932,51.95858],"type":"Point"}
}