{
  "type": "Feature",
  "properties": {
    "iso:country":"PL",
    "name:pol_x_preferred":[
        "Gr\u00f3dek"
    ],
    "wof:coterminous":[
        1477753025
    ],
    "wof:name":"Gr\u00f3dek",
    "wof:placetype":"locality"
},
  "geometry": {"coordinates":[23.7213529121293,53.0897849038942],"type":"Point"}
}