{
  "type": "Feature",
  "properties": {
    "iso:country":"PL",
    "name:ceb_x_preferred":[
        "Gr\u00f3dek"
    ],
    "name:deu_x_preferred":[
        "Gr\u00f3dek"
    ],
    "name:fra_x_preferred":[
        "Gr\u00f3dek"
    ],
    "name:heb_x_preferred":[
        "\u05d2\u05e8\u05d5\u05d3\u05e7"
    ],
    "name:ita_x_preferred":[
        "Grodek"
    ],
    "name:lit_x_preferred":[
        "Grudekas"
    ],
    "name:nld_x_preferred":[
        "Gr\u00f3dek"
    ],
    "name:pol_x_preferred":[
        "Gr\u00f3dek"
    ],
    "name:rus_x_preferred":[
        "\u0413\u0440\u0443\u0434\u0435\u043a"
    ],
    "name:ukr_x_preferred":[
        "\u0490\u0440\u0443\u0434\u0435\u043a"
    ],
    "wof:coterminous":[
        1477753025
    ],
    "wof:name":"Gr\u00f3dek",
    "wof:placetype":"locality"
},
  "geometry": {"coordinates":[23.7213529121293,53.0897849038942],"type":"Point"}
}