{
  "type": "Feature",
  "properties": {
    "gn:admin1_code":"78.0",
    "gn:admin2_code":"1430.0",
    "gn:admin3_code":"143004.0",
    "gn:asciiname":"Dobrut",
    "gn:country_code":"PL",
    "gn:dem":178,
    "gn:feature_class":"P",
    "gn:feature_code":"PPL",
    "gn:name":"Dobrut",
    "gn:population":0,
    "gn:timezone":"Europe/Warsaw",
    "iso:country":"PL",
    "name:azb_x_preferred":[
        "\u062f\u0648\u0628\u0631\u0648\u062a"
    ],
    "name:ceb_x_preferred":[
        "Dobrut"
    ],
    "name:fas_x_preferred":[
        "\u062f\u0648\u0628\u0631\u0648\u062a"
    ],
    "name:fra_x_preferred":[
        "Dobrut"
    ],
    "name:nld_x_preferred":[
        "Dobrut"
    ],
    "name:pol_x_preferred":[
        "Dobrut"
    ],
    "name:ukr_x_preferred":[
        "\u0414\u043e\u0431\u0440\u0443\u0442"
    ],
    "wof:name":"Dobrut",
    "wof:placetype":"locality"
},
  "geometry": {"coordinates":[20.96687,51.29581],"type":"Point"}
}