{
  "type": "Feature",
  "properties": {
    "gn:admin1_code":"78.0",
    "gn:admin2_code":"1430.0",
    "gn:admin3_code":"143004.0",
    "gn:asciiname":"Dobrut",
    "gn:country_code":"PL",
    "gn:dem":178,
    "gn:feature_class":"P",
    "gn:feature_code":"PPL",
    "gn:name":"Dobrut",
    "gn:population":0,
    "gn:timezone":"Europe/Warsaw",
    "iso:country":"PL",
    "wof:name":"Dobrut",
    "wof:placetype":"locality"
},
  "geometry": {"coordinates":[20.96687,51.29581],"type":"Point"}
}