{
  "type": "Feature",
  "properties": {
    "gn:admin1_code":"77.0",
    "gn:admin2_code":"1205.0",
    "gn:admin3_code":"120510.0",
    "gn:asciiname":"Brunary",
    "gn:country_code":"PL",
    "gn:dem":414,
    "gn:feature_class":"P",
    "gn:feature_code":"PPL",
    "gn:name":"Brunary",
    "gn:population":0,
    "gn:timezone":"Europe/Warsaw",
    "iso:country":"PL",
    "wof:name":"Brunary",
    "wof:placetype":"locality"
},
  "geometry": {"coordinates":[21.02609,49.53994],"type":"Point"}
}