{
  "type": "Feature",
  "properties": {
    "gn:admin1_code":"85.0",
    "gn:admin2_code":"2805.0",
    "gn:admin3_code":"280502.0",
    "gn:asciiname":"Straduny",
    "gn:country_code":"PL",
    "gn:dem":127,
    "gn:feature_class":"P",
    "gn:feature_code":"PPL",
    "gn:name":"Straduny",
    "gn:population":0,
    "gn:timezone":"Europe/Warsaw",
    "iso:country":"PL",
    "name:azb_x_preferred":[
        "\u0633\u062a\u0631\u0627\u062f\u0648\u0646\u0647"
    ],
    "name:ceb_x_preferred":[
        "Straduny"
    ],
    "name:deu_x_preferred":[
        "Straduny"
    ],
    "name:eng_x_preferred":[
        "Straduny"
    ],
    "name:fas_x_preferred":[
        "\u0633\u062a\u0631\u0627\u062f\u0648\u0646\u0647"
    ],
    "name:fra_x_preferred":[
        "Straduny"
    ],
    "name:pol_x_preferred":[
        "Straduny"
    ],
    "name:rus_x_preferred":[
        "\u0421\u0442\u0440\u0430\u0434\u0443\u043d\u044b"
    ],
    "name:ukr_x_preferred":[
        "\u0421\u0442\u0440\u0430\u0434\u0443\u043d\u0438"
    ],
    "name:und_x_variant":[
        "Wielkie (Wlk.) Straduny",
        "Stradaupen",
        "Stradaunen",
        "Stradauen"
    ],
    "wof:name":"Straduny",
    "wof:placetype":"locality"
},
  "geometry": {"coordinates":[22.34414,53.89088],"type":"Point"}
}