{
  "type": "Feature",
  "properties": {
    "gn:admin1_code":"73.0",
    "gn:admin2_code":"414.0",
    "gn:admin3_code":"41408.0",
    "gn:asciiname":"Grabowko",
    "gn:country_code":"PL",
    "gn:dem":25,
    "gn:feature_class":"P",
    "gn:feature_code":"PPL",
    "gn:name":"Grab\u00f3wko",
    "gn:population":0,
    "gn:timezone":"Europe/Warsaw",
    "iso:country":"PL",
    "name:pol_x_preferred":[
        "Grab\u00f3wko"
    ],
    "name:ukr_x_preferred":[
        "\u0490\u0440\u0430\u0431\u0443\u0432\u043a\u043e"
    ],
    "wof:name":"Grabowko",
    "wof:placetype":"locality"
},
  "geometry": {"coordinates":[18.29858,53.26966],"type":"Point"}
}