{
  "type": "Feature",
  "properties": {
    "gn:admin1_code":"80.0",
    "gn:admin2_code":"1863.0",
    "gn:admin3_code":"186301.0",
    "gn:asciiname":"Slocina",
    "gn:country_code":"PL",
    "gn:dem":207,
    "gn:feature_class":"P",
    "gn:feature_code":"PPL",
    "gn:name":"S\u0142ocina",
    "gn:population":0,
    "gn:timezone":"Europe/Warsaw",
    "iso:country":"PL",
    "wof:name":"Slocina",
    "wof:placetype":"neighbourhood"
},
  "geometry": {"coordinates":[22.05133,50.02762],"type":"Point"}
}