{
  "type": "Feature",
  "properties": {
    "gn:admin1_code":"78.0",
    "gn:admin2_code":"1425.0",
    "gn:admin3_code":"142504.0",
    "gn:asciiname":"Bartodzieje",
    "gn:country_code":"PL",
    "gn:dem":133,
    "gn:feature_class":"P",
    "gn:feature_code":"PPL",
    "gn:name":"Bartodzieje",
    "gn:population":0,
    "gn:timezone":"Europe/Warsaw",
    "iso:country":"PL",
    "name:fra_x_preferred":[
        "Bartodzieje"
    ],
    "name:pol_x_preferred":[
        "Bartodzieje"
    ],
    "name:ukr_x_preferred":[
        "\u0411\u0430\u0440\u0442\u043e\u0434\u0437\u0454\u0454"
    ],
    "wof:name":"Bartodzieje",
    "wof:placetype":"locality"
},
  "geometry": {"coordinates":[21.2043,51.5253],"type":"Point"}
}