{
  "type": "Feature",
  "properties": {
    "gn:admin1_code":"78.0",
    "gn:admin2_code":"1425.0",
    "gn:admin3_code":"142504.0",
    "gn:asciiname":"Bartodzieje",
    "gn:country_code":"PL",
    "gn:dem":133,
    "gn:feature_class":"P",
    "gn:feature_code":"PPL",
    "gn:name":"Bartodzieje",
    "gn:population":0,
    "gn:timezone":"Europe/Warsaw",
    "iso:country":"PL",
    "wof:name":"Bartodzieje",
    "wof:placetype":"locality"
},
  "geometry": {"coordinates":[21.2043,51.5253],"type":"Point"}
}