{
  "type": "Feature",
  "properties": {
    "gn:admin1_code":"81.0",
    "gn:admin2_code":"2002.0",
    "gn:admin3_code":"200210.0",
    "gn:asciiname":"Zimnochy Susly",
    "gn:country_code":"PL",
    "gn:dem":153,
    "gn:feature_class":"P",
    "gn:feature_code":"PPL",
    "gn:name":"Zimnochy Sus\u0142y",
    "gn:population":0,
    "gn:timezone":"Europe/Warsaw",
    "iso:country":"PL",
    "name:lit_x_preferred":[
        "Zimnochi Suslai"
    ],
    "name:pol_x_preferred":[
        "Zimnochy-Sus\u0142y"
    ],
    "name:ukr_x_preferred":[
        "\u0417\u0456\u043c\u043d\u043e\u0445\u0438-\u0421\u0443\u0441\u043b\u0438"
    ],
    "name:und_x_variant":[
        "Zimnochy Sus\u0142y"
    ],
    "wof:name":"Zimnochy Susly",
    "wof:placetype":"neighbourhood"
},
  "geometry": {"coordinates":[23.07042,52.94285],"type":"Point"}
}