{
  "type": "Feature",
  "properties": {
    "gn:admin1_code":"84.0",
    "gn:admin2_code":"2601.0",
    "gn:admin3_code":"260106.0",
    "gn:asciiname":"Mariampol",
    "gn:country_code":"PL",
    "gn:dem":241,
    "gn:feature_class":"P",
    "gn:feature_code":"PPL",
    "gn:name":"Mariampol",
    "gn:population":0,
    "gn:timezone":"Europe/Warsaw",
    "iso:country":"PL",
    "name:pol_x_preferred":[
        "Mariampol"
    ],
    "name:ukr_x_preferred":[
        "\u041c\u0430\u0440\u044f\u043c\u043f\u043e\u043b\u044c"
    ],
    "wof:name":"Mariampol",
    "wof:placetype":"locality"
},
  "geometry": {"coordinates":[20.95049,50.4199],"type":"Point"}
}