{
  "type": "Feature",
  "properties": {
    "gn:admin1_code":"74.0",
    "gn:admin2_code":"1010.0",
    "gn:admin3_code":"101004.0",
    "gn:asciiname":"Kociolki",
    "gn:country_code":"PL",
    "gn:dem":200,
    "gn:feature_class":"P",
    "gn:feature_code":"PPL",
    "gn:name":"Kocio\u0142ki",
    "gn:population":0,
    "gn:timezone":"Europe/Warsaw",
    "iso:country":"PL",
    "name:fra_x_preferred":[
        "Kocio\u0142ki"
    ],
    "name:pol_x_preferred":[
        "Kocio\u0142ki"
    ],
    "name:und_x_variant":[
        "Dw\u00f3r Kocio\u0142ki"
    ],
    "wof:name":"Kociolki",
    "wof:placetype":"locality"
},
  "geometry": {"coordinates":[19.44243,51.51892],"type":"Point"}
}