{
  "type": "Feature",
  "properties": {
    "gn:admin1_code":"86.0",
    "gn:admin2_code":"3028.0",
    "gn:admin3_code":"302803.0",
    "gn:asciiname":"Mala Laskownica",
    "gn:country_code":"PL",
    "gn:dem":90,
    "gn:feature_class":"P",
    "gn:feature_code":"PPL",
    "gn:name":"Ma\u0142a Laskownica",
    "gn:population":0,
    "gn:timezone":"Europe/Warsaw",
    "iso:country":"PL",
    "name:fra_x_preferred":[
        "Laskownica Ma\u0142a"
    ],
    "name:pol_x_preferred":[
        "Laskownica Ma\u0142a"
    ],
    "name:ukr_x_preferred":[
        "\u041b\u044f\u0441\u043a\u043e\u0432\u043d\u0438\u0446\u044f-\u041c\u0430\u043b\u0430"
    ],
    "name:und_x_variant":[
        "Ma\u0142a Laskownica"
    ],
    "wof:name":"Mala Laskownica",
    "wof:placetype":"locality"
},
  "geometry": {"coordinates":[17.25474,52.91741],"type":"Point"}
}