{
  "type": "Feature",
  "properties": {
    "gn:admin1_code":"78.0",
    "gn:admin2_code":"1406.0",
    "gn:admin3_code":"140611.0",
    "gn:asciiname":"Wola Palczewska",
    "gn:country_code":"PL",
    "gn:dem":126,
    "gn:feature_class":"P",
    "gn:feature_code":"PPL",
    "gn:name":"Wola Palczewska",
    "gn:population":0,
    "gn:timezone":"Europe/Warsaw",
    "iso:country":"PL",
    "wof:name":"Wola Palczewska",
    "wof:placetype":"locality"
},
  "geometry": {"coordinates":[21.04345,51.7502],"type":"Point"}
}