{
  "type": "Feature",
  "properties": {
    "gn:admin1_code":"78.0",
    "gn:admin2_code":"1424.0",
    "gn:admin3_code":"142405.0",
    "gn:asciiname":"Swierkowo",
    "gn:country_code":"PL",
    "gn:dem":107,
    "gn:feature_class":"P",
    "gn:feature_code":"PPL",
    "gn:name":"\u015awierkowo",
    "gn:population":0,
    "gn:timezone":"Europe/Warsaw",
    "iso:country":"PL",
    "name:fra_x_preferred":[
        "\u015awierkowo"
    ],
    "name:pol_x_preferred":[
        "\u015awierkowo"
    ],
    "name:ukr_x_preferred":[
        "\u0421\u044c\u0432\u0435\u0440\u043a\u043e\u0432\u043e"
    ],
    "wof:name":"Swierkowo",
    "wof:placetype":"locality"
},
  "geometry": {"coordinates":[20.72124,52.62597],"type":"Point"}
}