{
  "type": "Feature",
  "properties": {
    "gn:admin1_code":"78.0",
    "gn:admin2_code":"1424.0",
    "gn:admin3_code":"142405.0",
    "gn:asciiname":"Swierkowo",
    "gn:country_code":"PL",
    "gn:dem":107,
    "gn:feature_class":"P",
    "gn:feature_code":"PPL",
    "gn:name":"\u015awierkowo",
    "gn:population":0,
    "gn:timezone":"Europe/Warsaw",
    "iso:country":"PL",
    "name:und_x_variant":[
        "\u015awierkowo"
    ],
    "wof:name":"Swierkowo",
    "wof:placetype":"locality"
},
  "geometry": {"coordinates":[20.72124,52.62597],"type":"Point"}
}