{
  "type": "Feature",
  "properties": {
    "gn:admin1_code":"86.0",
    "gn:admin2_code":"3020.0",
    "gn:admin3_code":"302003.0",
    "gn:asciiname":"Zurawieniec",
    "gn:country_code":"PL",
    "gn:dem":152,
    "gn:feature_class":"P",
    "gn:feature_code":"PPL",
    "gn:name":"\u017burawieniec",
    "gn:population":0,
    "gn:timezone":"Europe/Warsaw",
    "iso:country":"PL",
    "wof:name":"Zurawieniec",
    "wof:placetype":"locality"
},
  "geometry": {"coordinates":[17.63332999999999,51.83333],"type":"Point"}
}