{
  "type": "Feature",
  "properties": {
    "gn:admin1_code":"85.0",
    "gn:admin2_code":"2802.0",
    "gn:admin3_code":"280204.0",
    "gn:asciiname":"Wyszkowo",
    "gn:cc2":"PL",
    "gn:country_code":"PL",
    "gn:dem":98,
    "gn:feature_class":"P",
    "gn:feature_code":"PPL",
    "gn:name":"Wyszkowo",
    "gn:population":0,
    "gn:timezone":"Europe/Warsaw",
    "iso:country":"PL",
    "name:azb_x_preferred":[
        "\u0648\u0634\u06a9\u0648\u0648\u0648"
    ],
    "name:deu_x_preferred":[
        "Wyszkowo"
    ],
    "name:fas_x_preferred":[
        "\u0648\u0634\u06a9\u0648\u0648\u0648"
    ],
    "name:fra_x_preferred":[
        "Wyszkowo"
    ],
    "name:pol_x_preferred":[
        "Wyszkowo"
    ],
    "name:und_x_variant":[
        "Hohenf\u00fcrst"
    ],
    "wof:name":"Wyszkowo",
    "wof:placetype":"locality"
},
  "geometry": {"coordinates":[20.11442000000001,54.34145],"type":"Point"}
}