{
  "type": "Feature",
  "properties": {
    "gn:admin1_code":"78.0",
    "gn:admin2_code":"1415.0",
    "gn:admin3_code":"141509.0",
    "gn:asciiname":"Kordowo",
    "gn:country_code":"PL",
    "gn:dem":97,
    "gn:feature_class":"P",
    "gn:feature_code":"PPL",
    "gn:name":"Kordowo",
    "gn:population":0,
    "gn:timezone":"Europe/Warsaw",
    "iso:country":"PL",
    "name:fra_x_preferred":[
        "Kordowo"
    ],
    "name:pol_x_preferred":[
        "Kordowo"
    ],
    "name:ukr_x_preferred":[
        "\u041a\u043e\u0440\u0434\u043e\u0432\u043e"
    ],
    "wof:name":"Kordowo",
    "wof:placetype":"locality"
},
  "geometry": {"coordinates":[21.51106,53.04741],"type":"Point"}
}