{
  "type": "Feature",
  "properties": {
    "gn:admin1_code":"80.0",
    "gn:admin2_code":"1818.0",
    "gn:admin3_code":"181801.0",
    "gn:asciiname":"Charzewice",
    "gn:country_code":"PL",
    "gn:dem":150,
    "gn:feature_class":"P",
    "gn:feature_code":"PPL",
    "gn:name":"Charzewice",
    "gn:population":0,
    "gn:timezone":"Europe/Warsaw",
    "iso:country":"PL",
    "name:deu_x_preferred":[
        "Charzewice"
    ],
    "name:pol_x_preferred":[
        "Charzewice"
    ],
    "name:ukr_x_preferred":[
        "\u0425\u0430\u0436\u0435\u0432\u0456\u0446\u0435"
    ],
    "wof:name":"Charzewice",
    "wof:placetype":"locality"
},
  "geometry": {"coordinates":[22.03747000000001,50.59837],"type":"Point"}
}