{
  "type": "Feature",
  "properties": {
    "gn:country":"PL",
    "gn:fcode":"PPL",
    "gn:population":0,
    "iso:country":"PL",
    "name:ast_x_preferred":[
        "Serpelice"
    ],
    "name:ceb_x_preferred":[
        "Serpelice"
    ],
    "name:deu_x_preferred":[
        "Serpelice"
    ],
    "name:eng_x_preferred":[
        "Serpelice"
    ],
    "name:fra_x_preferred":[
        "Serpelice"
    ],
    "name:lit_x_preferred":[
        "Serpelic\u0117"
    ],
    "name:nld_x_preferred":[
        "Serpelice"
    ],
    "name:pol_x_preferred":[
        "Serpelice"
    ],
    "name:ukr_x_preferred":[
        "\u0421\u0435\u0440\u043f\u0435\u043b\u0456\u0446\u0435"
    ],
    "qs_pg:aaroncc":"PL",
    "qs_pg:gn_country":"PL",
    "qs_pg:gn_fcode":"PPL",
    "qs_pg:gn_pop":0,
    "qs_pg:name":"Serpelice",
    "qs_pg:name_adm0":"Polska",
    "qs_pg:name_adm1":"Mazowieckie",
    "qs_pg:photos":13,
    "qs_pg:photos_1k":3,
    "qs_pg:photos_9k":1,
    "qs_pg:photos_9r":1,
    "qs_pg:photos_all":13,
    "qs_pg:photos_sr":1,
    "qs_pg:pop_sr":0,
    "qs_pg:qs_pg_placetype":"locality",
    "qs_pg:qs_pg_placetype_gp":"Town",
    "qs_pg:woe_adm0":23424923,
    "woe:adm0_id":23424923,
    "woe:name_adm0":"Polska",
    "woe:name_adm1":"Mazowieckie",
    "woe:placetype":"Town",
    "wof:name":"Serpelice",
    "wof:placetype":"locality"
},
  "geometry": {"coordinates":[23.05292,52.27593],"type":"Point"}
}