{
  "type": "Feature",
  "properties": {
    "gn:admin1_code":"82.0",
    "gn:admin2_code":"2201.0",
    "gn:admin3_code":"220105.0",
    "gn:asciiname":"Karpno",
    "gn:country_code":"PL",
    "gn:dem":145,
    "gn:feature_class":"P",
    "gn:feature_code":"PPL",
    "gn:name":"Karpno",
    "gn:population":0,
    "gn:timezone":"Europe/Warsaw",
    "iso:country":"PL",
    "name:deu_x_preferred":[
        "Karpno"
    ],
    "name:nld_x_preferred":[
        "Karpno"
    ],
    "name:pol_x_preferred":[
        "Karpno"
    ],
    "name:ukr_x_preferred":[
        "\u041a\u0430\u0440\u043f\u043d\u043e"
    ],
    "wof:name":"Karpno",
    "wof:placetype":"locality"
},
  "geometry": {"coordinates":[17.42277,53.95013],"type":"Point"}
}