{
  "type": "Feature",
  "properties": {
    "gn:admin1_code":"72",
    "gn:admin2_code":"0201",
    "gn:admin3_code":"20104.0",
    "gn:asciiname":"Bieniec",
    "gn:country_code":"PL",
    "gn:dem":201,
    "gn:feature_class":"P",
    "gn:feature_code":"PPL",
    "gn:name":"Bieniec",
    "gn:population":0,
    "gn:timezone":"Europe/Warsaw",
    "iso:country":"PL",
    "name:pol_x_preferred":[
        "Bieniec"
    ],
    "name:ukr_x_preferred":[
        "\u0411\u0435\u043d\u0435\u0446\u044c"
    ],
    "wof:name":"Bieniec",
    "wof:placetype":"locality"
},
  "geometry": {"coordinates":[15.39567,51.27749],"type":"Point"}
}