{
  "type": "Feature",
  "properties": {
    "gn:country":"PL",
    "gn:fcode":"PPLA3",
    "gn:population":417,
    "iso:country":"PL",
    "name:ceb_x_preferred":[
        "D\u0105bie"
    ],
    "name:deu_x_preferred":[
        "D\u0105bie"
    ],
    "name:epo_x_preferred":[
        "D\u0105bie"
    ],
    "name:fra_x_preferred":[
        "D\u0105bie"
    ],
    "name:ita_x_preferred":[
        "D\u0105bie"
    ],
    "name:nld_x_preferred":[
        "D\u0105bie"
    ],
    "name:pol_x_preferred":[
        "D\u0105bie"
    ],
    "name:rus_x_preferred":[
        "\u0414\u043e\u043c\u0431\u0435"
    ],
    "name:srp_x_preferred":[
        "\u0414\u043e\u043c\u0431\u0458\u0435"
    ],
    "name:swe_x_preferred":[
        "D\u0105bie"
    ],
    "name:ukr_x_preferred":[
        "\u0414\u043e\u043c\u0431'\u0454"
    ],
    "qs_pg:aaroncc":"PL",
    "qs_pg:gn_country":"PL",
    "qs_pg:gn_fcode":"PPLA3",
    "qs_pg:gn_pop":417,
    "qs_pg:name":"D\u0105bie",
    "qs_pg:name_adm0":"Polska",
    "qs_pg:name_adm1":"Lubuskie",
    "qs_pg:photos":1,
    "qs_pg:photos_1k":1,
    "qs_pg:photos_9k":1,
    "qs_pg:photos_9r":1,
    "qs_pg:photos_all":1,
    "qs_pg:photos_sr":1,
    "qs_pg:pop_sr":2,
    "qs_pg:qs_pg_placetype":"localadmin",
    "qs_pg:qs_pg_placetype_gp":"LocalAdmin",
    "qs_pg:woe_adm0":23424923,
    "woe:adm0_id":23424923,
    "woe:name_adm0":"Polska",
    "woe:name_adm1":"Lubuskie",
    "woe:placetype":"LocalAdmin",
    "wof:name":"D\u0105bie",
    "wof:placetype":"localadmin",
    "wof:population":417
},
  "geometry": {"coordinates":[15.15221,52.01056],"type":"Point"}
}