{
  "type": "Feature",
  "properties": {
    "gn:admin1_code":"80.0",
    "gn:admin2_code":"1813.0",
    "gn:admin3_code":"181301.0",
    "gn:asciiname":"Kuzmina",
    "gn:country_code":"PL",
    "gn:dem":453,
    "gn:feature_class":"P",
    "gn:feature_code":"PPL",
    "gn:name":"Ku\u017cmina",
    "gn:population":0,
    "gn:timezone":"Europe/Warsaw",
    "iso:country":"PL",
    "name:azb_x_preferred":[
        "\u06a9\u0648\u0698\u0645\u06cc\u0646\u0627"
    ],
    "name:fas_x_preferred":[
        "\u06a9\u0648\u0698\u0645\u06cc\u0646\u0627"
    ],
    "name:hun_x_preferred":[
        "Ku\u017amina"
    ],
    "name:nld_x_preferred":[
        "Ku\u017amina"
    ],
    "name:pol_x_preferred":[
        "Ku\u017amina"
    ],
    "name:ukr_x_preferred":[
        "\u041a\u0443\u0437\u044c\u043c\u0438\u043d\u0430"
    ],
    "wof:name":"Kuzmina",
    "wof:placetype":"locality"
},
  "geometry": {"coordinates":[22.4291,49.61683],"type":"Point"}
}