{
  "type": "Feature",
  "properties": {
    "gn:admin1_code":"75.0",
    "gn:admin2_code":"602.0",
    "gn:admin3_code":"60205.0",
    "gn:asciiname":"Radziecin",
    "gn:country_code":"PL",
    "gn:dem":250,
    "gn:feature_class":"P",
    "gn:feature_code":"PPL",
    "gn:name":"Radzi\u0119cin",
    "gn:population":0,
    "gn:timezone":"Europe/Warsaw",
    "iso:country":"PL",
    "name:ceb_x_preferred":[
        "Radzi\u0119cin"
    ],
    "name:fra_x_preferred":[
        "Radzi\u0119cin"
    ],
    "name:pol_x_preferred":[
        "Radzi\u0119cin"
    ],
    "name:rus_x_preferred":[
        "\u0420\u0430\u0434\u0437\u0435\u043d\u0446\u0438\u043d"
    ],
    "name:ukr_x_preferred":[
        "\u0420\u0430\u0434\u0437\u0435\u043d\u0446\u0438\u043d"
    ],
    "wof:name":"Radziecin",
    "wof:placetype":"locality"
},
  "geometry": {"coordinates":[22.70977,50.67819],"type":"Point"}
}