{
  "type": "Feature",
  "properties": {
    "gn:admin1_code":"86.0",
    "gn:admin2_code":"3021.0",
    "gn:admin3_code":"302108.0",
    "gn:asciiname":"Trzek",
    "gn:country_code":"PL",
    "gn:dem":88,
    "gn:feature_class":"P",
    "gn:feature_code":"PPL",
    "gn:name":"Trzek",
    "gn:population":0,
    "gn:timezone":"Europe/Warsaw",
    "iso:country":"PL",
    "wof:name":"Trzek",
    "wof:placetype":"locality"
},
  "geometry": {"coordinates":[17.17238,52.35105],"type":"Point"}
}