{
  "type": "Feature",
  "properties": {
    "gn:admin1_code":"72.0",
    "gn:admin2_code":"224.0",
    "gn:admin3_code":"22406.0",
    "gn:asciiname":"Jasienica",
    "gn:country_code":"PL",
    "gn:dem":254,
    "gn:feature_class":"P",
    "gn:feature_code":"PPL",
    "gn:name":"Jasienica",
    "gn:population":70,
    "gn:timezone":"Europe/Warsaw",
    "iso:country":"PL",
    "name:pol_x_preferred":[
        "Jasienica"
    ],
    "name:ukr_x_preferred":[
        "\u042f\u0441\u0435\u043d\u0438\u0446\u044f"
    ],
    "name:urd_x_preferred":[
        "\u062c\u0633\u06cc\u0646\u06cc\u06a9\u0627"
    ],
    "wof:name":"Jasienica",
    "wof:placetype":"locality",
    "wof:population":70
},
  "geometry": {"coordinates":[17.07945,50.65893],"type":"Point"}
}