{
  "type": "Feature",
  "properties": {
    "gn:admin1_code":"72.0",
    "gn:admin2_code":"203.0",
    "gn:admin3_code":"20306.0",
    "gn:asciiname":"Kloda",
    "gn:country_code":"PL",
    "gn:dem":114,
    "gn:feature_class":"P",
    "gn:feature_code":"PPL",
    "gn:name":"K\u0142oda",
    "gn:population":0,
    "gn:timezone":"Europe/Warsaw",
    "iso:country":"PL",
    "name:pol_x_preferred":[
        "K\u0142oda"
    ],
    "name:ukr_x_preferred":[
        "\u041a\u043b\u043e\u0434\u0430"
    ],
    "wof:name":"Kloda",
    "wof:placetype":"locality"
},
  "geometry": {"coordinates":[15.95695,51.65978],"type":"Point"}
}