{
  "type": "Feature",
  "properties": {
    "gn:admin1_code":"72.0",
    "gn:admin2_code":"215.0",
    "gn:admin3_code":"21504.0",
    "gn:asciiname":"Janikow",
    "gn:country_code":"PL",
    "gn:dem":129,
    "gn:feature_class":"P",
    "gn:feature_code":"PPL",
    "gn:name":"Janik\u00f3w",
    "gn:population":0,
    "gn:timezone":"Europe/Warsaw",
    "iso:country":"PL",
    "name:deu_x_historical":[
        "Gr\u00fcntanne"
    ],
    "name:deu_x_preferred":[
        "Gr\u00fcntanne"
    ],
    "name:pol_x_preferred":[
        "Janik\u00f3w"
    ],
    "name:ukr_x_preferred":[
        "\u042f\u043d\u0456\u043a\u0443\u0432"
    ],
    "name:urd_x_preferred":[
        "\u062c\u0646\u06a9\u0648\u0648"
    ],
    "wof:name":"Janikow",
    "wof:placetype":"locality"
},
  "geometry": {"coordinates":[17.37436,50.97021],"type":"Point"}
}