{
  "type": "Feature",
  "properties": {
    "gn:admin1_code":"74.0",
    "gn:admin2_code":"1001.0",
    "gn:admin3_code":"100102.0",
    "gn:asciiname":"Kielchinow",
    "gn:country_code":"PL",
    "gn:dem":217,
    "gn:feature_class":"P",
    "gn:feature_code":"PPL",
    "gn:name":"Kielchin\u00f3w",
    "gn:population":0,
    "gn:timezone":"Europe/Warsaw",
    "iso:country":"PL",
    "name:fra_x_preferred":[
        "Kielchin\u00f3w"
    ],
    "name:pol_x_preferred":[
        "Kielchin\u00f3w"
    ],
    "name:szl_x_preferred":[
        "Kelchin\u016fw"
    ],
    "name:ukr_x_preferred":[
        "\u041a\u0435\u043b\u044c\u0445\u0456\u043d\u0443\u0432"
    ],
    "wof:name":"Kielchinow",
    "wof:placetype":"locality"
},
  "geometry": {"coordinates":[19.43866,51.34017],"type":"Point"}
}