{
  "type": "Feature",
  "properties": {
    "gn:gn_country":"PL",
    "gn:gn_fcode":"ADM3",
    "gn:gn_pop":0,
    "iso:country":"PL",
    "name:pol_x_preferred":[
        "Powiat w\u0142oc\u0142awski"
    ],
    "name:pol_x_variant":[
        "W\u0142oc\u0142awek"
    ],
    "qs_pg:aaroncc":"PL",
    "qs_pg:gn_country":"PL",
    "qs_pg:gn_fcode":"ADM3",
    "qs_pg:gn_pop":0,
    "qs_pg:name":"W\u0142oc\u0142awek",
    "qs_pg:name_adm0":"Polska",
    "qs_pg:name_adm1":"Kujawsko-Pomorskie",
    "qs_pg:photos":22,
    "qs_pg:photos_1k":4,
    "qs_pg:photos_9k":1,
    "qs_pg:photos_9r":1,
    "qs_pg:photos_all":22,
    "qs_pg:photos_sr":1,
    "qs_pg:pop_sr":0,
    "qs_pg:qs_pg_placetype":"localadmin",
    "qs_pg:qs_pg_placetype_gp":"LocalAdmin",
    "qs_pg:woe_adm0":23424923,
    "woe:adm0_id":23424923,
    "woe:name_adm0":"Polska",
    "woe:name_adm1":"Kujawsko-Pomorskie",
    "woe:placetype":"LocalAdmin",
    "wof:name":"W\u0142oc\u0142awek",
    "wof:placetype":"localadmin"
},
  "geometry": {"coordinates":[19.0608,52.6653],"type":"Point"}
}