{
  "type": "Feature",
  "properties": {
    "gn:admin1_code":"78.0",
    "gn:admin2_code":"1427.0",
    "gn:admin3_code":"142707.0",
    "gn:asciiname":"Kosmaczewo",
    "gn:country_code":"PL",
    "gn:dem":123,
    "gn:feature_class":"P",
    "gn:feature_code":"PPL",
    "gn:name":"Kosmaczewo",
    "gn:population":0,
    "gn:timezone":"Europe/Warsaw",
    "iso:country":"PL",
    "name:azb_x_preferred":[
        "\u06a9\u0648\u0633\u0645\u0627\u0686\u0648\u0648"
    ],
    "name:ceb_x_preferred":[
        "Kosmaczewo"
    ],
    "name:fas_x_preferred":[
        "\u06a9\u0648\u0633\u0645\u0627\u0686\u0648\u0648"
    ],
    "name:fra_x_preferred":[
        "Kosmaczewo"
    ],
    "name:pol_x_preferred":[
        "Kosmaczewo"
    ],
    "name:ukr_x_preferred":[
        "\u041a\u043e\u0441\u043c\u0430\u0447\u0435\u0432\u043e"
    ],
    "wof:name":"Kosmaczewo",
    "wof:placetype":"locality"
},
  "geometry": {"coordinates":[19.89242,52.75564],"type":"Point"}
}