{
  "type": "Feature",
  "properties": {
    "gn:admin1_code":"81.0",
    "gn:admin2_code":"2001.0",
    "gn:admin3_code":"200105.0",
    "gn:asciiname":"Osinska Buda",
    "gn:country_code":"PL",
    "gn:dem":154,
    "gn:feature_class":"P",
    "gn:feature_code":"PPL",
    "gn:name":"Osi\u0144ska Buda",
    "gn:population":0,
    "gn:timezone":"Europe/Warsaw",
    "iso:country":"PL",
    "name:lit_x_preferred":[
        "Osinska B\u016bda"
    ],
    "name:pol_x_preferred":[
        "Osi\u0144ska Buda"
    ],
    "name:ukr_x_preferred":[
        "\u041e\u0441\u0456\u043d\u0441\u044c\u043a\u0430-\u0411\u0443\u0434\u0430"
    ],
    "wof:name":"Osinska Buda",
    "wof:placetype":"locality"
},
  "geometry": {"coordinates":[22.89406,53.99439],"type":"Point"}
}