{
  "type": "Feature",
  "properties": {
    "gn:admin1_code":"81.0",
    "gn:admin2_code":"2001.0",
    "gn:admin3_code":"200105.0",
    "gn:asciiname":"Osinska Buda",
    "gn:country_code":"PL",
    "gn:dem":154,
    "gn:feature_class":"P",
    "gn:feature_code":"PPL",
    "gn:name":"Osi\u0144ska Buda",
    "gn:population":0,
    "gn:timezone":"Europe/Warsaw",
    "iso:country":"PL",
    "name:und_x_variant":[
        "Osi\u0144ska Buda"
    ],
    "wof:name":"Osinska Buda",
    "wof:placetype":"locality"
},
  "geometry": {"coordinates":[22.89406,53.99439],"type":"Point"}
}