{
  "type": "Feature",
  "properties": {
    "gn:admin1_code":"81.0",
    "gn:admin2_code":"2013.0",
    "gn:admin3_code":"201310.0",
    "gn:asciiname":"Tybory Jeziornia",
    "gn:country_code":"PL",
    "gn:dem":142,
    "gn:feature_class":"P",
    "gn:feature_code":"PPL",
    "gn:name":"Tybory Jeziornia",
    "gn:population":0,
    "gn:timezone":"Europe/Warsaw",
    "iso:country":"PL",
    "wof:name":"Tybory Jeziornia",
    "wof:placetype":"locality"
},
  "geometry": {"coordinates":[22.40772,52.94779000000001],"type":"Point"}
}