{
  "type": "Feature",
  "properties": {
    "iso:country":"PL",
    "name:pol_x_preferred":[
        "Lubiszyn"
    ],
    "wof:coterminous":[
        1125399495
    ],
    "wof:name":"Lubiszyn",
    "wof:placetype":"locality"
},
  "geometry": {"coordinates":[15.0232592228626,52.7961284245749],"type":"Point"}
}