{
  "type": "Feature",
  "properties": {
    "iso:country":"PL",
    "name:azb_x_preferred":[
        "\u0644\u0648\u0628\u06cc\u0634\u0646"
    ],
    "name:ceb_x_preferred":[
        "Lubiszyn"
    ],
    "name:deu_x_preferred":[
        "Lubiszyn"
    ],
    "name:fas_x_preferred":[
        "\u0644\u0648\u0628\u06cc\u0634\u0646"
    ],
    "name:fra_x_preferred":[
        "Lubiszyn"
    ],
    "name:nld_x_preferred":[
        "Lubiszyn"
    ],
    "name:pol_x_preferred":[
        "Lubiszyn"
    ],
    "name:ukr_x_preferred":[
        "\u041b\u044e\u0431\u0456\u0448\u0438\u043d"
    ],
    "wof:coterminous":[
        1125399495
    ],
    "wof:name":"Lubiszyn",
    "wof:placetype":"locality"
},
  "geometry": {"coordinates":[15.0232592228626,52.7961284245749],"type":"Point"}
}