{
  "type": "Feature",
  "properties": {
    "gn:admin1_code":"84.0",
    "gn:admin2_code":"2610.0",
    "gn:admin3_code":"261005.0",
    "gn:asciiname":"Ostojow",
    "gn:country_code":"PL",
    "gn:dem":296,
    "gn:feature_class":"P",
    "gn:feature_code":"PPL",
    "gn:name":"Ostoj\u00f3w",
    "gn:population":0,
    "gn:timezone":"Europe/Warsaw",
    "iso:country":"PL",
    "name:ceb_x_preferred":[
        "Ostoj\u00f3w"
    ],
    "name:pol_x_preferred":[
        "Ostoj\u00f3w"
    ],
    "name:ukr_x_preferred":[
        "\u041e\u0441\u0442\u043e\u044e\u0432"
    ],
    "wof:name":"Ostojow",
    "wof:placetype":"locality"
},
  "geometry": {"coordinates":[20.82029,51.01872],"type":"Point"}
}