{
  "type": "Feature",
  "properties": {
    "gn:admin1_code":"74.0",
    "gn:admin2_code":"1003.0",
    "gn:admin3_code":"100304.0",
    "gn:asciiname":"Ruda",
    "gn:country_code":"PL",
    "gn:dem":152,
    "gn:feature_class":"P",
    "gn:feature_code":"PPL",
    "gn:name":"Ruda",
    "gn:population":0,
    "gn:timezone":"Europe/Warsaw",
    "iso:country":"PL",
    "name:fra_x_preferred":[
        "Ruda"
    ],
    "name:pol_x_preferred":[
        "Ruda"
    ],
    "name:ukr_x_preferred":[
        "\u0420\u0443\u0434\u0430"
    ],
    "wof:name":"Ruda",
    "wof:placetype":"locality"
},
  "geometry": {"coordinates":[19.00299,51.41249000000001],"type":"Point"}
}