{
  "type": "Feature",
  "properties": {
    "gn:admin1_code":"86.0",
    "gn:admin2_code":"3029.0",
    "gn:admin3_code":"302902.0",
    "gn:asciiname":"Kopanica",
    "gn:country_code":"PL",
    "gn:dem":56,
    "gn:feature_class":"P",
    "gn:feature_code":"PPL",
    "gn:name":"Kopanica",
    "gn:population":0,
    "gn:timezone":"Europe/Warsaw",
    "iso:country":"PL",
    "name:ceb_x_preferred":[
        "Kopanica"
    ],
    "name:fra_x_preferred":[
        "Kopanica"
    ],
    "name:pol_x_preferred":[
        "Kopanica"
    ],
    "name:ukr_x_preferred":[
        "\u041a\u043e\u043f\u0430\u043d\u0438\u0446\u044f"
    ],
    "wof:name":"Kopanica",
    "wof:placetype":"locality"
},
  "geometry": {"coordinates":[15.91948,52.09528],"type":"Point"}
}