{
  "type": "Feature",
  "properties": {
    "gn:admin1_code":"76.0",
    "gn:admin2_code":"811.0",
    "gn:admin3_code":"81110.0",
    "gn:asciiname":"Kadlubia",
    "gn:country_code":"PL",
    "gn:dem":150,
    "gn:feature_class":"P",
    "gn:feature_code":"PPL",
    "gn:name":"Kad\u0142ubia",
    "gn:population":0,
    "gn:timezone":"Europe/Warsaw",
    "iso:country":"PL",
    "name:ceb_x_preferred":[
        "Kad\u0142ubia"
    ],
    "name:fra_x_preferred":[
        "Kad\u0142ubia"
    ],
    "name:pol_x_preferred":[
        "Kad\u0142ubia"
    ],
    "name:ukr_x_preferred":[
        "\u041a\u0430\u0434\u043b\u0443\u0431\u044f"
    ],
    "wof:name":"Kadlubia",
    "wof:placetype":"locality"
},
  "geometry": {"coordinates":[15.17109,51.65557],"type":"Point"}
}