{
  "type": "Feature",
  "properties": {
    "gn:gn_country":"PL",
    "gn:gn_fcode":"PPL",
    "gn:gn_pop":1091,
    "gn:population":1091,
    "iso:country":"PL",
    "name:ast_x_preferred":[
        "Zdziechowice Drugie"
    ],
    "name:ceb_x_preferred":[
        "Zdziechowice Drugie"
    ],
    "name:eng_x_preferred":[
        "Zdziechowice Drugie"
    ],
    "name:fra_x_preferred":[
        "Zdziechowice Drugie"
    ],
    "name:pol_x_preferred":[
        "Zdziechowice Drugie"
    ],
    "name:ukr_x_preferred":[
        "\u0417\u0434\u0437\u0435\u0445\u043e\u0432\u0456\u0446\u0435-\u0414\u0440\u0443\u0433\u0456"
    ],
    "qs_pg:aaroncc":"PL",
    "qs_pg:gn_country":"PL",
    "qs_pg:gn_fcode":"PPL",
    "qs_pg:gn_pop":1091,
    "qs_pg:name":"Zdziechowice Drugie",
    "qs_pg:name_adm0":"Polska",
    "qs_pg:name_adm1":"Podkarpackie",
    "qs_pg:photos_9r":0,
    "qs_pg:photos_sr":0,
    "qs_pg:pop_sr":3,
    "qs_pg:qs_pg_placetype":"locality",
    "qs_pg:qs_pg_placetype_gp":"Town",
    "qs_pg:woe_adm0":23424923,
    "woe:adm0_id":23424923,
    "woe:name_adm0":"Polska",
    "woe:name_adm1":"Podkarpackie",
    "woe:placetype":"Town",
    "wof:name":"Zdziechowice Drugie",
    "wof:placetype":"locality",
    "wof:population":1091
},
  "geometry": {"coordinates":[22.10999,50.78478],"type":"Point"}
}