{
  "type": "Feature",
  "properties": {
    "gn:admin1_code":"74.0",
    "gn:admin2_code":"1009.0",
    "gn:admin3_code":"100902.0",
    "gn:asciiname":"Brutus",
    "gn:country_code":"PL",
    "gn:dem":173,
    "gn:feature_class":"P",
    "gn:feature_code":"PPL",
    "gn:name":"Brutus",
    "gn:population":0,
    "gn:timezone":"Europe/Warsaw",
    "iso:country":"PL",
    "name:fra_x_preferred":[
        "Brutus"
    ],
    "name:pol_x_preferred":[
        "Brutus"
    ],
    "name:ukr_x_preferred":[
        "\u0411\u0440\u0443\u0442\u0443\u0441"
    ],
    "wof:name":"Brutus",
    "wof:placetype":"locality"
},
  "geometry": {"coordinates":[19.02733,51.24629],"type":"Point"}
}