{
  "type": "Feature",
  "properties": {
    "gn:admin1_code":"86.0",
    "gn:admin2_code":"3022.0",
    "gn:admin3_code":"302201.0",
    "gn:asciiname":"Sowiny",
    "gn:country_code":"PL",
    "gn:dem":96,
    "gn:feature_class":"P",
    "gn:feature_code":"PPL",
    "gn:name":"Sowiny",
    "gn:population":0,
    "gn:timezone":"Europe/Warsaw",
    "iso:country":"PL",
    "name:fra_x_preferred":[
        "Sowiny"
    ],
    "name:pol_x_preferred":[
        "Sowiny"
    ],
    "name:ukr_x_preferred":[
        "\u0421\u043e\u0432\u0456\u043d\u0438"
    ],
    "wof:name":"Sowiny",
    "wof:placetype":"locality"
},
  "geometry": {"coordinates":[16.8302,51.7249],"type":"Point"}
}