{
  "type": "Feature",
  "properties": {
    "gn:admin1_code":"72.0",
    "gn:admin2_code":"208.0",
    "gn:admin3_code":"20811.0",
    "gn:asciiname":"Czerwieczyce",
    "gn:country_code":"PL",
    "gn:dem":379,
    "gn:feature_class":"P",
    "gn:feature_code":"PPL",
    "gn:name":"Czerwieczyce",
    "gn:population":0,
    "gn:timezone":"Europe/Warsaw",
    "iso:country":"PL",
    "wof:name":"Czerwieczyce",
    "wof:placetype":"locality"
},
  "geometry": {"coordinates":[16.60577,50.53078],"type":"Point"}
}