{
  "type": "Feature",
  "properties": {
    "gn:admin1_code":"85.0",
    "gn:admin2_code":"2861.0",
    "gn:admin3_code":"286101.0",
    "gn:asciiname":"Prochnik",
    "gn:cc2":"PL",
    "gn:country_code":"PL",
    "gn:dem":129,
    "gn:feature_class":"P",
    "gn:feature_code":"PPL",
    "gn:name":"Pr\u00f3chnik",
    "gn:population":0,
    "gn:timezone":"Europe/Warsaw",
    "iso:country":"PL",
    "name:und_x_variant":[
        "D\u00f6rbeck",
        "Pr\u00f3chnik"
    ],
    "wof:name":"Prochnik",
    "wof:placetype":"neighbourhood"
},
  "geometry": {"coordinates":[19.45318,54.24296],"type":"Point"}
}