{
  "type": "Feature",
  "properties": {
    "gn:admin1_code":"80.0",
    "gn:admin2_code":"1805.0",
    "gn:admin3_code":"180507.0",
    "gn:asciiname":"Toki",
    "gn:country_code":"PL",
    "gn:dem":275,
    "gn:feature_class":"P",
    "gn:feature_code":"PPL",
    "gn:name":"Toki",
    "gn:population":0,
    "gn:timezone":"Europe/Warsaw",
    "iso:country":"PL",
    "name:pol_x_preferred":[
        "Toki"
    ],
    "name:ukr_x_preferred":[
        "\u0422\u043e\u043a\u0456"
    ],
    "wof:name":"Toki",
    "wof:placetype":"locality"
},
  "geometry": {"coordinates":[21.53973,49.62233],"type":"Point"}
}