{
  "type": "Feature",
  "properties": {
    "gn:admin1_code":"75.0",
    "gn:admin2_code":"618.0",
    "gn:admin3_code":"61806.0",
    "gn:asciiname":"Pukarzow",
    "gn:country_code":"PL",
    "gn:dem":227,
    "gn:feature_class":"P",
    "gn:feature_code":"PPL",
    "gn:name":"Pukarz\u00f3w",
    "gn:population":0,
    "gn:timezone":"Europe/Warsaw",
    "iso:country":"PL",
    "name:fra_x_preferred":[
        "Pukarz\u00f3w"
    ],
    "name:pol_x_preferred":[
        "Pukarz\u00f3w"
    ],
    "name:ukr_x_preferred":[
        "\u041f\u0443\u043a\u0430\u0436\u0443\u0432"
    ],
    "wof:name":"Pukarzow",
    "wof:placetype":"locality"
},
  "geometry": {"coordinates":[23.66652,50.54532],"type":"Point"}
}