{
  "type": "Feature",
  "properties": {
    "gn:admin1_code":"74.0",
    "gn:admin2_code":"1004.0",
    "gn:admin3_code":"100406.0",
    "gn:asciiname":"Jasionna",
    "gn:country_code":"PL",
    "gn:dem":112,
    "gn:feature_class":"P",
    "gn:feature_code":"PPL",
    "gn:name":"Jasionna",
    "gn:population":0,
    "gn:timezone":"Europe/Warsaw",
    "iso:country":"PL",
    "name:fra_x_preferred":[
        "Jasionna"
    ],
    "name:pol_x_preferred":[
        "Jasionna"
    ],
    "name:ukr_x_preferred":[
        "\u042f\u0441\u044c\u043e\u043d\u043d\u0430"
    ],
    "wof:name":"Jasionna",
    "wof:placetype":"locality"
},
  "geometry": {"coordinates":[19.55243,52.03645],"type":"Point"}
}