{
  "type": "Feature",
  "properties": {
    "gn:admin1_code":"83.0",
    "gn:admin2_code":"2411.0",
    "gn:admin3_code":"241101.0",
    "gn:asciiname":"Sudol",
    "gn:country_code":"PL",
    "gn:dem":198,
    "gn:feature_class":"P",
    "gn:feature_code":"PPL",
    "gn:name":"Sud\u00f3\u0142",
    "gn:population":0,
    "gn:timezone":"Europe/Warsaw",
    "iso:country":"PL",
    "name:deu_x_preferred":[
        "Sudol"
    ],
    "wof:name":"Sudol",
    "wof:placetype":"locality"
},
  "geometry": {"coordinates":[18.19353,50.05439000000001],"type":"Point"}
}