{
  "type": "Feature",
  "properties": {
    "gn:admin1_code":"79.0",
    "gn:admin2_code":"1609.0",
    "gn:admin3_code":"160912.0",
    "gn:asciiname":"Ligota Tulowicka",
    "gn:country_code":"PL",
    "gn:dem":172,
    "gn:feature_class":"P",
    "gn:feature_code":"PPL",
    "gn:name":"Ligota Tu\u0142owicka",
    "gn:population":0,
    "gn:timezone":"Europe/Warsaw",
    "iso:country":"PL",
    "name:deu_x_preferred":[
        "Ligota Tu\u0142owicka"
    ],
    "name:pol_x_preferred":[
        "Ligota Tu\u0142owicka"
    ],
    "name:ukr_x_preferred":[
        "\u041b\u0456\u0491\u043e\u0442\u0430-\u0422\u0443\u043b\u043e\u0432\u0456\u0446\u044c\u043a\u0430"
    ],
    "wof:name":"Ligota Tulowicka",
    "wof:placetype":"locality"
},
  "geometry": {"coordinates":[17.65317000000001,50.5819],"type":"Point"}
}