{
  "type": "Feature",
  "properties": {
    "gn:admin1_code":"74.0",
    "gn:admin2_code":"1010.0",
    "gn:admin3_code":"101004.0",
    "gn:asciiname":"Lutoslawice",
    "gn:country_code":"PL",
    "gn:dem":221,
    "gn:feature_class":"P",
    "gn:feature_code":"PPL",
    "gn:name":"Lutos\u0142awice",
    "gn:population":0,
    "gn:timezone":"Europe/Warsaw",
    "iso:country":"PL",
    "name:fra_x_preferred":[
        "Lutos\u0142awice Rz\u0105dowe"
    ],
    "name:pol_x_preferred":[
        "Lutos\u0142awice Rz\u0105dowe"
    ],
    "name:ukr_x_preferred":[
        "\u041b\u044e\u0442\u043e\u0441\u043b\u0430\u0432\u0456\u0446\u0435-\u0416\u043e\u043d\u0434\u043e\u0432\u0435"
    ],
    "name:und_x_variant":[
        "Lutos\u0142awice Rzad",
        "Lutos\u0142awice Rz\u0105dowe",
        "Lutos\u0142awice"
    ],
    "wof:name":"Lutoslawice",
    "wof:placetype":"locality"
},
  "geometry": {"coordinates":[19.57562,51.50043],"type":"Point"}
}