{
  "type": "Feature",
  "properties": {
    "gn:country":"PL",
    "gn:fcode":"PPL",
    "gn:population":806,
    "iso:country":"PL",
    "name:ast_x_preferred":[
        "Kluczewsko"
    ],
    "name:azb_x_preferred":[
        "\u06a9\u0644\u0648\u0686\u0648\u0633\u06a9\u0648"
    ],
    "name:deu_x_preferred":[
        "Kluczewsko"
    ],
    "name:eng_x_preferred":[
        "Kluczewsko"
    ],
    "name:fas_x_preferred":[
        "\u06a9\u0644\u0648\u0686\u0648\u0633\u06a9\u0648"
    ],
    "name:fra_x_preferred":[
        "Kluczewsko"
    ],
    "name:nan_x_preferred":[
        "Kluczewsko"
    ],
    "name:nld_x_preferred":[
        "Kluczewsko"
    ],
    "name:pol_x_preferred":[
        "Kluczewsko"
    ],
    "name:rus_x_preferred":[
        "\u041a\u043b\u044e\u0447\u0435\u0432\u0441\u043a\u043e"
    ],
    "name:swe_x_preferred":[
        "Kluczewsko"
    ],
    "name:ukr_x_preferred":[
        "\u041a\u043b\u044e\u0447\u0435\u0432\u0441\u044c\u043a\u043e"
    ],
    "qs_pg:aaroncc":"PL",
    "qs_pg:gn_country":"PL",
    "qs_pg:gn_fcode":"PPL",
    "qs_pg:gn_pop":806,
    "qs_pg:name":"Kluczewsko",
    "qs_pg:name_adm0":"Polska",
    "qs_pg:name_adm1":"Swi\u0119tokrzyskie",
    "qs_pg:photos_9r":0,
    "qs_pg:photos_sr":0,
    "qs_pg:pop_sr":2,
    "qs_pg:qs_pg_placetype":"locality",
    "qs_pg:qs_pg_placetype_gp":"Town",
    "qs_pg:woe_adm0":23424923,
    "woe:adm0_id":23424923,
    "woe:name_adm0":"Polska",
    "woe:name_adm1":"Swi\u0119tokrzyskie",
    "woe:placetype":"Town",
    "wof:name":"Kluczewsko",
    "wof:placetype":"locality",
    "wof:population":806
},
  "geometry": {"coordinates":[19.91881,50.92771],"type":"Point"}
}