{
  "type": "Feature",
  "properties": {
    "gn:admin1_code":"78.0",
    "gn:admin2_code":"1437.0",
    "gn:admin3_code":"143703.0",
    "gn:asciiname":"Ruda",
    "gn:country_code":"PL",
    "gn:dem":133,
    "gn:feature_class":"P",
    "gn:feature_code":"PPL",
    "gn:name":"Ruda",
    "gn:population":0,
    "gn:timezone":"Europe/Warsaw",
    "iso:country":"PL",
    "name:bos_x_preferred":[
        "Ruda"
    ],
    "name:ceb_x_preferred":[
        "Ruda"
    ],
    "name:ces_x_preferred":[
        "Ruda"
    ],
    "name:deu_x_preferred":[
        "Ruda"
    ],
    "name:epo_x_preferred":[
        "Ruda"
    ],
    "name:fra_x_preferred":[
        "Ruda"
    ],
    "name:glg_x_preferred":[
        "Ruda"
    ],
    "name:hrv_x_preferred":[
        "Ruda"
    ],
    "name:hun_x_preferred":[
        "Ruda"
    ],
    "name:ita_x_preferred":[
        "Ruda"
    ],
    "name:lit_x_preferred":[
        "Ruda"
    ],
    "name:nld_x_preferred":[
        "Ruda"
    ],
    "name:oci_x_preferred":[
        "Ruda"
    ],
    "name:pol_x_preferred":[
        "Ruda"
    ],
    "name:ron_x_preferred":[
        "Ruda"
    ],
    "name:slk_x_preferred":[
        "Ruda"
    ],
    "name:slv_x_preferred":[
        "Ruda"
    ],
    "name:spa_x_preferred":[
        "Ruda"
    ],
    "name:swe_x_preferred":[
        "Ruda"
    ],
    "name:uzb_x_preferred":[
        "Ruda"
    ],
    "wof:name":"Ruda",
    "wof:placetype":"locality"
},
  "geometry": {"coordinates":[19.85842,53.15344],"type":"Point"}
}