{
  "type": "Feature",
  "properties": {
    "gn:admin1_code":"84.0",
    "gn:admin2_code":"2606.0",
    "gn:admin3_code":"260602.0",
    "gn:asciiname":"Haliszka",
    "gn:country_code":"PL",
    "gn:dem":287,
    "gn:feature_class":"P",
    "gn:feature_code":"PPL",
    "gn:name":"Haliszka",
    "gn:population":0,
    "gn:timezone":"Europe/Warsaw",
    "iso:country":"PL",
    "name:pol_x_preferred":[
        "Haliszka"
    ],
    "wof:name":"Haliszka",
    "wof:placetype":"locality"
},
  "geometry": {"coordinates":[21.29399,50.71825],"type":"Point"}
}