{
  "type": "Feature",
  "properties": {
    "gn:admin1_code":"86.0",
    "gn:admin2_code":"3002.0",
    "gn:admin3_code":"300202.0",
    "gn:asciiname":"Radosiew",
    "gn:country_code":"PL",
    "gn:dem":60,
    "gn:feature_class":"P",
    "gn:feature_code":"PPL",
    "gn:name":"Radosiew",
    "gn:population":0,
    "gn:timezone":"Europe/Warsaw",
    "iso:country":"PL",
    "name:fra_x_preferred":[
        "Radosiew"
    ],
    "name:pol_x_preferred":[
        "Radosiew"
    ],
    "name:ukr_x_preferred":[
        "\u0420\u0430\u0434\u043e\u0441\u0435\u0432"
    ],
    "wof:name":"Radosiew",
    "wof:placetype":"locality"
},
  "geometry": {"coordinates":[16.48217,52.96271],"type":"Point"}
}