{
  "type": "Feature",
  "properties": {
    "gn:admin1_code":"73.0",
    "gn:admin2_code":"413.0",
    "gn:admin3_code":"41304.0",
    "gn:asciiname":"Zakrzewska Osada",
    "gn:country_code":"PL",
    "gn:dem":110,
    "gn:feature_class":"P",
    "gn:feature_code":"PPL",
    "gn:name":"Zakrzewska Osada",
    "gn:population":0,
    "gn:timezone":"Europe/Warsaw",
    "iso:country":"PL",
    "name:und_x_variant":[
        "Zakrzewska",
        "Zakrzewska Osada"
    ],
    "wof:name":"Zakrzewska Osada",
    "wof:placetype":"locality"
},
  "geometry": {"coordinates":[17.41864,53.36316],"type":"Point"}
}