{
  "type": "Feature",
  "properties": {
    "gn:admin1_code":"73.0",
    "gn:admin2_code":"413.0",
    "gn:admin3_code":"41304.0",
    "gn:asciiname":"Zakrzewska Osada",
    "gn:country_code":"PL",
    "gn:dem":110,
    "gn:feature_class":"P",
    "gn:feature_code":"PPL",
    "gn:name":"Zakrzewska Osada",
    "gn:population":0,
    "gn:timezone":"Europe/Warsaw",
    "iso:country":"PL",
    "name:pol_x_preferred":[
        "Zakrzewska Osada"
    ],
    "name:ukr_x_preferred":[
        "\u0417\u0430\u043a\u0448\u0435\u0432\u0441\u044c\u043a\u0430-\u041e\u0441\u0430\u0434\u0430"
    ],
    "name:und_x_variant":[
        "Zakrzewska",
        "Zakrzewska Osada"
    ],
    "wof:name":"Zakrzewska Osada",
    "wof:placetype":"locality"
},
  "geometry": {"coordinates":[17.41864,53.36316],"type":"Point"}
}