{
  "type": "Feature",
  "properties": {
    "gn:admin1_code":"78.0",
    "gn:admin2_code":"1404.0",
    "gn:admin3_code":"140403.0",
    "gn:asciiname":"Remki",
    "gn:country_code":"PL",
    "gn:dem":104,
    "gn:feature_class":"P",
    "gn:feature_code":"PPL",
    "gn:name":"Remki",
    "gn:population":0,
    "gn:timezone":"Europe/Warsaw",
    "iso:country":"PL",
    "name:ceb_x_preferred":[
        "Remki"
    ],
    "name:fra_x_preferred":[
        "Remki"
    ],
    "name:pol_x_preferred":[
        "Remki"
    ],
    "name:ukr_x_preferred":[
        "\u0420\u0435\u043c\u043a\u0456"
    ],
    "wof:name":"Remki",
    "wof:placetype":"locality"
},
  "geometry": {"coordinates":[19.77352,52.3039],"type":"Point"}
}