{
  "type": "Feature",
  "properties": {
    "gn:admin1_code":"78.0",
    "gn:admin2_code":"1404.0",
    "gn:admin3_code":"140401.0",
    "gn:asciiname":"Rataje",
    "gn:country_code":"PL",
    "gn:dem":93,
    "gn:feature_class":"P",
    "gn:feature_code":"PPL",
    "gn:name":"Rataje",
    "gn:population":0,
    "gn:timezone":"Europe/Warsaw",
    "iso:country":"PL",
    "name:ceb_x_preferred":[
        "Rataje"
    ],
    "name:ces_x_preferred":[
        "Rataje"
    ],
    "name:deu_x_preferred":[
        "Rataje"
    ],
    "name:fra_x_preferred":[
        "Rataje"
    ],
    "name:ita_x_preferred":[
        "Rataje"
    ],
    "name:nld_x_preferred":[
        "Rataje"
    ],
    "name:oci_x_preferred":[
        "Rataje"
    ],
    "name:pol_x_preferred":[
        "Rataje"
    ],
    "name:slk_x_preferred":[
        "Rataje"
    ],
    "name:srp_x_preferred":[
        "\u0420\u0430\u0442\u0430\u0458\u0435"
    ],
    "name:swe_x_preferred":[
        "Rataje"
    ],
    "name:ukr_x_preferred":[
        "\u0420\u0430\u0442\u0430\u0454"
    ],
    "wof:name":"Rataje",
    "wof:placetype":"locality"
},
  "geometry": {"coordinates":[19.44088,52.42686],"type":"Point"}
}