{
  "type": "Feature",
  "properties": {
    "gn:admin1_code":"85.0",
    "gn:admin2_code":"2814.0",
    "gn:admin3_code":"281408.0",
    "gn:asciiname":"Tarniny",
    "gn:cc2":"PL",
    "gn:country_code":"PL",
    "gn:dem":92,
    "gn:feature_class":"P",
    "gn:feature_code":"PPL",
    "gn:name":"Tarniny",
    "gn:population":0,
    "gn:timezone":"Europe/Warsaw",
    "iso:country":"PL",
    "name:deu_x_preferred":[
        "Tarniny"
    ],
    "name:pol_x_preferred":[
        "Tarniny"
    ],
    "name:ukr_x_preferred":[
        "\u0422\u0430\u0440\u043d\u0456\u043d\u0438"
    ],
    "name:und_x_variant":[
        "Tornienen"
    ],
    "wof:name":"Tarniny",
    "wof:placetype":"locality"
},
  "geometry": {"coordinates":[21.04208,54.04326],"type":"Point"}
}