{
  "type": "Feature",
  "properties": {
    "gn:admin1_code":"73.0",
    "gn:admin2_code":"404.0",
    "gn:admin3_code":"40405.0",
    "gn:asciiname":"Folgowo",
    "gn:country_code":"PL",
    "gn:dem":81,
    "gn:feature_class":"P",
    "gn:feature_code":"PPL",
    "gn:name":"Folgowo",
    "gn:population":0,
    "gn:timezone":"Europe/Warsaw",
    "iso:country":"PL",
    "name:afr_x_preferred":[
        "Folgowo"
    ],
    "name:azb_x_preferred":[
        "\u0641\u0648\u0644\u0642\u0648\u0648\u0648"
    ],
    "name:deu_x_preferred":[
        "Folgowo"
    ],
    "name:epo_x_preferred":[
        "Folgowo"
    ],
    "name:fas_x_preferred":[
        "\u0641\u0648\u0644\u06af\u0648\u0648\u0648"
    ],
    "name:fra_x_preferred":[
        "Folgowo"
    ],
    "name:hun_x_preferred":[
        "Folgowo"
    ],
    "name:ita_x_preferred":[
        "Folgowo"
    ],
    "name:pol_x_preferred":[
        "Folgowo"
    ],
    "name:szl_x_preferred":[
        "Folgowo"
    ],
    "name:ukr_x_preferred":[
        "\u0424\u043e\u043b\u044c\u0491\u043e\u0432\u043e"
    ],
    "wof:name":"Folgowo",
    "wof:placetype":"locality"
},
  "geometry": {"coordinates":[18.56304,53.27265],"type":"Point"}
}