{
  "type": "Feature",
  "properties": {
    "gn:admin1_code":"82.0",
    "gn:admin2_code":"2262.0",
    "gn:admin3_code":"226201.0",
    "gn:asciiname":"Maly Kack",
    "gn:cc2":"PL",
    "gn:country_code":"PL",
    "gn:dem":93,
    "gn:feature_class":"P",
    "gn:feature_code":"PPL",
    "gn:name":"Ma\u0142y Kack",
    "gn:population":0,
    "gn:timezone":"Europe/Warsaw",
    "iso:country":"PL",
    "name:deu_x_historical":[
        "Gross Katz"
    ],
    "name:deu_x_preferred":[
        "Gross Katz"
    ],
    "name:und_x_variant":[
        "Kack Ma\u0142y",
        "Ma\u0142y Kack"
    ],
    "wof:name":"Maly Kack",
    "wof:placetype":"locality"
},
  "geometry": {"coordinates":[18.52072,54.48121],"type":"Point"}
}