{
  "type": "Feature",
  "properties": {
    "gn:admin1_code":"86.0",
    "gn:admin2_code":"3007.0",
    "gn:admin3_code":"300701.0",
    "gn:asciiname":"Bogucice",
    "gn:country_code":"PL",
    "gn:dem":122,
    "gn:feature_class":"P",
    "gn:feature_code":"PPL",
    "gn:name":"Bogucice",
    "gn:population":0,
    "gn:timezone":"Europe/Warsaw",
    "iso:country":"PL",
    "name:pol_x_preferred":[
        "Bogucice"
    ],
    "name:ukr_x_preferred":[
        "\u0411\u043e\u0491\u0443\u0446\u0438\u0446\u0435"
    ],
    "wof:name":"Bogucice",
    "wof:placetype":"locality"
},
  "geometry": {"coordinates":[18.0653,51.86122],"type":"Point"}
}