{
  "type": "Feature",
  "properties": {
    "gn:admin1_code":"79.0",
    "gn:admin2_code":"1607.0",
    "gn:admin3_code":"160703.0",
    "gn:asciiname":"Gryzow",
    "gn:country_code":"PL",
    "gn:dem":252,
    "gn:feature_class":"P",
    "gn:feature_code":"PPL",
    "gn:name":"Gry\u017c\u00f3w",
    "gn:population":0,
    "gn:timezone":"Europe/Warsaw",
    "iso:country":"PL",
    "name:und_x_variant":[
        "Krzesz\u00f3w",
        "Greisau",
        "Gry\u017c\u00f3w"
    ],
    "wof:name":"Gryzow",
    "wof:placetype":"locality"
},
  "geometry": {"coordinates":[17.50183,50.40487],"type":"Point"}
}