{
  "type": "Feature",
  "properties": {
    "gn:admin1_code":"80.0",
    "gn:admin2_code":"1864.0",
    "gn:admin3_code":"186401.0",
    "gn:asciiname":"Radowaz",
    "gn:country_code":"PL",
    "gn:dem":163,
    "gn:feature_class":"P",
    "gn:feature_code":"PPL",
    "gn:name":"Radow\u0105\u017c",
    "gn:population":0,
    "gn:timezone":"Europe/Warsaw",
    "iso:country":"PL",
    "wof:name":"Radowaz",
    "wof:placetype":"neighbourhood"
},
  "geometry": {"coordinates":[21.66667,50.56667],"type":"Point"}
}