{
  "type": "Feature",
  "properties": {
    "gn:admin1_code":"84.0",
    "gn:admin2_code":"2604.0",
    "gn:admin3_code":"260415.0",
    "gn:asciiname":"Strojnow",
    "gn:country_code":"PL",
    "gn:dem":298,
    "gn:feature_class":"P",
    "gn:feature_code":"PPL",
    "gn:name":"Strojn\u00f3w",
    "gn:population":0,
    "gn:timezone":"Europe/Warsaw",
    "iso:country":"PL",
    "wof:name":"Strojnow",
    "wof:placetype":"locality"
},
  "geometry": {"coordinates":[20.79592,50.65675],"type":"Point"}
}