{
  "type": "Feature",
  "properties": {
    "iso:country":"PL",
    "name:ast_x_preferred":[
        "Grabowo"
    ],
    "name:deu_x_preferred":[
        "Grabowo"
    ],
    "name:deu_x_variant":[
        "Grabow"
    ],
    "name:eng_x_preferred":[
        "Grabowo"
    ],
    "name:fra_x_preferred":[
        "Grabowo"
    ],
    "name:heb_x_preferred":[
        "\u05d2\u05e8\u05d1\u05d5\u05d1\u05d5"
    ],
    "name:pol_x_preferred":[
        "Grabowo"
    ],
    "name:pol_x_variant":[
        "Grabow",
        "Stettin-Grabow"
    ],
    "qs:gn_adm0_cc":"PL",
    "qs:gn_fcode":"PPLX",
    "qs:gn_local":3083829,
    "qs:gn_nam_loc":"Szczecin, Szczecin, Zachodniopomorskie, PL",
    "qs:gn_namadm1":"87",
    "qs:gn_name":"Grabowo",
    "qs:local_max":2463,
    "qs:local_sum":5955,
    "qs:localhoods":11,
    "qs:name":"Grabowo",
    "qs:name_adm0":"Polska",
    "qs:name_adm1":"Zachodniopomorskie",
    "qs:name_adm2":"Szczecin",
    "qs:name_lau":"Szczecin",
    "qs:name_local":"Szczecin",
    "qs:photo_max":402,
    "qs:photo_sum":2463,
    "qs:placetype":"Suburb",
    "qs:quad_count":111,
    "qs:woe_adm0":23424923,
    "qs:woe_adm1":12577950,
    "qs:woe_adm2":12591505,
    "qs:woe_lau":12618080,
    "qs:woe_local":521598,
    "qs:woe_ver":"7.10.0",
    "wd:wordcount":106,
    "wof:lang":[
        "pol"
    ],
    "wof:name":"Grabowo",
    "wof:placetype":"neighbourhood"
},
  "geometry": {"coordinates":[14.557146,53.430077],"type":"Point"}
}