{
  "type": "Feature",
  "properties": {
    "gn:admin1_code":"72",
    "gn:admin2_code":"0225",
    "gn:admin3_code":"22505.0",
    "gn:asciiname":"Wilka-Bory",
    "gn:country_code":"PL",
    "gn:dem":249,
    "gn:feature_class":"P",
    "gn:feature_code":"PPL",
    "gn:name":"Wilka-Bory",
    "gn:population":0,
    "gn:timezone":"Europe/Warsaw",
    "iso:country":"PL",
    "name:deu_x_historical":[
        "Bohra"
    ],
    "name:deu_x_preferred":[
        "Bohra"
    ],
    "name:pol_x_preferred":[
        "Wilka-Bory"
    ],
    "wof:name":"Wilka-Bory",
    "wof:placetype":"locality"
},
  "geometry": {"coordinates":[14.99694,51.04474],"type":"Point"}
}