{
  "type": "Feature",
  "properties": {
    "gn:admin1_code":"83.0",
    "gn:admin2_code":"2407.0",
    "gn:admin3_code":"240702.0",
    "gn:asciiname":"Doly",
    "gn:country_code":"PL",
    "gn:dem":274,
    "gn:feature_class":"P",
    "gn:feature_code":"PPL",
    "gn:name":"Do\u0142y",
    "gn:population":0,
    "gn:timezone":"Europe/Warsaw",
    "iso:country":"PL",
    "name:nld_x_preferred":[
        "Do\u0142y"
    ],
    "name:pol_x_preferred":[
        "Do\u0142y"
    ],
    "wof:name":"Doly",
    "wof:placetype":"locality"
},
  "geometry": {"coordinates":[18.88144,50.68008],"type":"Point"}
}