{
  "type": "Feature",
  "properties": {
    "gn:admin1_code":"80.0",
    "gn:admin2_code":"1814.0",
    "gn:admin3_code":"181404.0",
    "gn:asciiname":"Kanczuckie",
    "gn:country_code":"PL",
    "gn:dem":247,
    "gn:feature_class":"P",
    "gn:feature_code":"PPL",
    "gn:name":"Ka\u0144czuckie",
    "gn:population":0,
    "gn:timezone":"Europe/Warsaw",
    "iso:country":"PL",
    "wof:name":"Kanczuckie",
    "wof:placetype":"locality"
},
  "geometry": {"coordinates":[22.29982,49.91532],"type":"Point"}
}