{
  "type": "Feature",
  "properties": {
    "gn:admin1_code":"81.0",
    "gn:admin2_code":"2012.0",
    "gn:admin3_code":"201209.0",
    "gn:asciiname":"Maszutkinie",
    "gn:country_code":"PL",
    "gn:dem":208,
    "gn:feature_class":"P",
    "gn:feature_code":"PPL",
    "gn:name":"Maszutkinie",
    "gn:population":0,
    "gn:timezone":"Europe/Warsaw",
    "iso:country":"PL",
    "name:lit_x_preferred":[
        "Ma\u0161utkiniai"
    ],
    "name:pol_x_preferred":[
        "Maszutkinie"
    ],
    "name:ukr_x_preferred":[
        "\u041c\u0430\u0448\u0443\u0442\u043a\u0456\u043d\u0435"
    ],
    "name:und_x_variant":[
        "Maszutkina"
    ],
    "wof:name":"Maszutkinie",
    "wof:placetype":"locality"
},
  "geometry": {"coordinates":[22.94766,54.37643000000001],"type":"Point"}
}