{
  "type": "Feature",
  "properties": {
    "gn:admin1_code":"85.0",
    "gn:admin2_code":"2862.0",
    "gn:admin3_code":"286201.0",
    "gn:asciiname":"Zatorze",
    "gn:country_code":"PL",
    "gn:dem":123,
    "gn:feature_class":"P",
    "gn:feature_code":"PPL",
    "gn:name":"Zatorze",
    "gn:population":0,
    "gn:timezone":"Europe/Warsaw",
    "iso:country":"PL",
    "wof:name":"Zatorze",
    "wof:placetype":"locality"
},
  "geometry": {"coordinates":[20.48427,53.78887],"type":"Point"}
}