{
  "type": "Feature",
  "properties": {
    "gn:admin1_code":"77.0",
    "gn:admin2_code":"1217.0",
    "gn:admin3_code":"121705.0",
    "gn:asciiname":"Ligasowka",
    "gn:country_code":"PL",
    "gn:dem":984,
    "gn:feature_class":"P",
    "gn:feature_code":"PPL",
    "gn:name":"Ligas\u00f3wka",
    "gn:population":0,
    "gn:timezone":"Europe/Warsaw",
    "iso:country":"PL",
    "wof:name":"Ligasowka",
    "wof:placetype":"locality"
},
  "geometry": {"coordinates":[19.95,49.33333],"type":"Point"}
}