{
  "type": "Feature",
  "properties": {
    "iso:country":"PL",
    "name:eng_x_preferred":[
        "Rodojewo"
    ],
    "name:pol_x_preferred":[
        "Rodojewo"
    ],
    "wof:name":"Rodojewo",
    "wof:placetype":"neighbourhood"
},
  "geometry": {"coordinates":[16.94565911175261,52.49762188636935],"type":"Point"}
}