{
  "type": "Feature",
  "properties": {
    "gn:admin1_code":"78.0",
    "gn:admin2_code":"1415.0",
    "gn:admin3_code":"141501.0",
    "gn:asciiname":"Adamczycha",
    "gn:country_code":"PL",
    "gn:dem":113,
    "gn:feature_class":"P",
    "gn:feature_code":"PPL",
    "gn:name":"Adamczycha",
    "gn:population":0,
    "gn:timezone":"Europe/Warsaw",
    "iso:country":"PL",
    "wof:name":"Adamczycha",
    "wof:placetype":"locality"
},
  "geometry": {"coordinates":[21.26324,53.10686],"type":"Point"}
}