{
  "type": "Feature",
  "properties": {
    "gn:admin1_code":"85.0",
    "gn:admin2_code":"2801.0",
    "gn:admin3_code":"280103.0",
    "gn:asciiname":"Nalikajmy",
    "gn:country_code":"PL",
    "gn:dem":74,
    "gn:feature_class":"P",
    "gn:feature_code":"PPL",
    "gn:name":"Nalikajmy",
    "gn:population":0,
    "gn:timezone":"Europe/Warsaw",
    "iso:country":"PL",
    "name:fra_x_preferred":[
        "Nalikajmy"
    ],
    "name:pol_x_preferred":[
        "Nalikajmy"
    ],
    "name:ukr_x_preferred":[
        "\u041d\u0430\u043b\u0456\u043a\u0430\u0439\u043c\u0438"
    ],
    "name:und_x_variant":[
        "Liekeim"
    ],
    "name:vie_x_preferred":[
        "Nalikajmy"
    ],
    "wof:name":"Nalikajmy",
    "wof:placetype":"locality"
},
  "geometry": {"coordinates":[20.80275,54.29406],"type":"Point"}
}