{
  "type": "Feature",
  "properties": {
    "gn:admin1_code":"86.0",
    "gn:admin2_code":"3012.0",
    "gn:admin3_code":"301205.0",
    "gn:asciiname":"Debowiec",
    "gn:country_code":"PL",
    "gn:dem":148,
    "gn:feature_class":"P",
    "gn:feature_code":"PPL",
    "gn:name":"D\u0119bowiec",
    "gn:population":0,
    "gn:timezone":"Europe/Warsaw",
    "iso:country":"PL",
    "name:pol_x_preferred":[
        "D\u0119bowiec"
    ],
    "wof:name":"Debowiec",
    "wof:placetype":"locality"
},
  "geometry": {"coordinates":[17.46323,51.77813],"type":"Point"}
}