{
  "type": "Feature",
  "properties": {
    "gn:population":2503,
    "iso:country":"PL",
    "name:ast_x_preferred":[
        "Grzechynia"
    ],
    "name:ceb_x_preferred":[
        "Grzechynia"
    ],
    "name:deu_x_preferred":[
        "Grzechynia"
    ],
    "name:eng_x_preferred":[
        "Grzechynia"
    ],
    "name:fra_x_preferred":[
        "Grzechynia"
    ],
    "name:ita_x_preferred":[
        "Grzechynia"
    ],
    "name:nan_x_preferred":[
        "Grzechynia"
    ],
    "name:pol_x_preferred":[
        "Grzechynia"
    ],
    "name:ukr_x_preferred":[
        "\u0490\u0436\u0435\u0445\u0438\u043d\u044f"
    ],
    "name:zho_min_nan_x_preferred":[
        "Grzechynia"
    ],
    "qs:a0":"Rzeczpospolita Polska",
    "qs:a1":"*Malopolskie",
    "qs:a1r":"0",
    "qs:a2":"Suski",
    "qs:adm0":"Rzeczpospolita Polska",
    "qs:la_lc":"*",
    "qs:level":"locality",
    "qs:loc":"Grzechynia",
    "qs:loc_alt":"Grzechynia",
    "qs:pop":0,
    "qs:type":"buffered point",
    "wd:wordcount":98,
    "wof:name":"Grzechynia",
    "wof:placetype":"locality",
    "wof:population":2503
},
  "geometry": {"coordinates":[19.663555,49.720458],"type":"Point"}
}