{
  "type": "Feature",
  "properties": {
    "gn:admin1_code":"86.0",
    "gn:admin2_code":"3007.0",
    "gn:admin3_code":"300703.0",
    "gn:asciiname":"Kuznica",
    "gn:country_code":"PL",
    "gn:dem":118,
    "gn:feature_class":"P",
    "gn:feature_code":"PPL",
    "gn:name":"Ku\u017anica",
    "gn:population":0,
    "gn:timezone":"Europe/Warsaw",
    "iso:country":"PL",
    "name:pol_x_preferred":[
        "Ku\u017anica"
    ],
    "name:ukr_x_preferred":[
        "\u041a\u0443\u0437\u044c\u043d\u0438\u0446\u044f"
    ],
    "name:und_x_variant":[
        "Ku\u017anice"
    ],
    "wof:name":"Kuznica",
    "wof:placetype":"locality"
},
  "geometry": {"coordinates":[18.29686,51.86381],"type":"Point"}
}