{
  "type": "Feature",
  "properties": {
    "gn:admin1_code":"73.0",
    "gn:admin2_code":"402.0",
    "gn:admin3_code":"40210.0",
    "gn:asciiname":"Lipowiec",
    "gn:country_code":"PL",
    "gn:dem":115,
    "gn:feature_class":"P",
    "gn:feature_code":"PPL",
    "gn:name":"Lipowiec",
    "gn:population":0,
    "gn:timezone":"Europe/Warsaw",
    "iso:country":"PL",
    "name:pol_x_preferred":[
        "Lipowiec"
    ],
    "name:ukr_x_preferred":[
        "\u041b\u0456\u043f\u043e\u0432\u0435\u0446\u044c"
    ],
    "wof:name":"Lipowiec",
    "wof:placetype":"locality"
},
  "geometry": {"coordinates":[19.49713,53.35311],"type":"Point"}
}