{
  "type": "Feature",
  "properties": {
    "gn:admin1_code":"82.0",
    "gn:admin2_code":"2202.0",
    "gn:admin3_code":"220203.0",
    "gn:asciiname":"Nowa Cerkiew",
    "gn:country_code":"PL",
    "gn:dem":158,
    "gn:feature_class":"P",
    "gn:feature_code":"PPL",
    "gn:name":"Nowa Cerkiew",
    "gn:population":0,
    "gn:timezone":"Europe/Warsaw",
    "iso:country":"PL",
    "name:deu_x_preferred":[
        "Nowa Cerkiew"
    ],
    "name:pol_x_preferred":[
        "Nowa Cerkiew"
    ],
    "name:ukr_x_preferred":[
        "\u041d\u043e\u0432\u0430 \u0426\u0435\u0440\u043a\u0435\u0432"
    ],
    "wof:name":"Nowa Cerkiew",
    "wof:placetype":"locality"
},
  "geometry": {"coordinates":[17.68437,53.70126],"type":"Point"}
}