{
  "type": "Feature",
  "properties": {
    "gn:admin1_code":"78.0",
    "gn:admin2_code":"1426.0",
    "gn:admin3_code":"142603.0",
    "gn:asciiname":"Koszewnica",
    "gn:country_code":"PL",
    "gn:dem":137,
    "gn:feature_class":"P",
    "gn:feature_code":"PPL",
    "gn:name":"Koszewnica",
    "gn:population":0,
    "gn:timezone":"Europe/Warsaw",
    "iso:country":"PL",
    "wof:name":"Koszewnica",
    "wof:placetype":"locality"
},
  "geometry": {"coordinates":[21.98656,52.1689],"type":"Point"}
}