{
  "type": "Feature",
  "properties": {
    "gn:admin1_code":"74.0",
    "gn:admin2_code":"1011.0",
    "gn:admin3_code":"101105.0",
    "gn:asciiname":"Plewnik",
    "gn:country_code":"PL",
    "gn:dem":123,
    "gn:feature_class":"P",
    "gn:feature_code":"PPL",
    "gn:name":"Plewnik",
    "gn:population":0,
    "gn:timezone":"Europe/Warsaw",
    "iso:country":"PL",
    "name:fra_x_preferred":[
        "Plewnik Drugi"
    ],
    "name:pol_x_preferred":[
        "Plewnik"
    ],
    "name:ukr_x_preferred":[
        "\u041f\u043b\u0435\u0432\u043d\u0438\u043a"
    ],
    "wof:name":"Plewnik",
    "wof:placetype":"locality"
},
  "geometry": {"coordinates":[19.04376,51.93414],"type":"Point"}
}