{
  "type": "Feature",
  "properties": {
    "gn:admin1_code":"84.0",
    "gn:admin2_code":"2611.0",
    "gn:admin3_code":"261101.0",
    "gn:asciiname":"Krzyzowa Wola",
    "gn:country_code":"PL",
    "gn:dem":250,
    "gn:feature_class":"P",
    "gn:feature_code":"PPL",
    "gn:name":"Krzy\u017cowa Wola",
    "gn:population":0,
    "gn:timezone":"Europe/Warsaw",
    "iso:country":"PL",
    "wof:name":"Krzyzowa Wola",
    "wof:placetype":"neighbourhood"
},
  "geometry": {"coordinates":[21.05525,51.03853],"type":"Point"}
}