{
  "type": "Feature",
  "properties": {
    "gn:admin1_code":"78.0",
    "gn:admin2_code":"1413.0",
    "gn:admin3_code":"141302.0",
    "gn:asciiname":"Zawady",
    "gn:country_code":"PL",
    "gn:dem":169,
    "gn:feature_class":"P",
    "gn:feature_code":"PPL",
    "gn:name":"Zawady",
    "gn:population":0,
    "gn:timezone":"Europe/Warsaw",
    "iso:country":"PL",
    "name:ceb_x_preferred":[
        "Zawady"
    ],
    "name:deu_x_preferred":[
        "Zawady"
    ],
    "name:fra_x_preferred":[
        "Zawady"
    ],
    "name:lit_x_preferred":[
        "Zavadai"
    ],
    "name:nld_x_preferred":[
        "Zawady"
    ],
    "name:pol_x_preferred":[
        "Zawady"
    ],
    "name:rus_x_preferred":[
        "\u0417\u0430\u0432\u0430\u0434\u044b"
    ],
    "name:ukr_x_preferred":[
        "\u0417\u0430\u0432\u0430\u0434\u0438"
    ],
    "wof:name":"Zawady",
    "wof:placetype":"locality"
},
  "geometry": {"coordinates":[20.64401,53.10549],"type":"Point"}
}