{
  "type": "Feature",
  "properties": {
    "gn:admin1_code":"83.0",
    "gn:admin2_code":"2478.0",
    "gn:admin3_code":"247801.0",
    "gn:asciiname":"Borzykow",
    "gn:cc2":"PL",
    "gn:country_code":"PL",
    "gn:dem":281,
    "gn:feature_class":"P",
    "gn:feature_code":"PPL",
    "gn:name":"Borzyk\u00f3w",
    "gn:population":0,
    "gn:timezone":"Europe/Warsaw",
    "iso:country":"PL",
    "name:und_x_variant":[
        "Borsigwerke",
        "Borsigwerk",
        "Borzyk\u00f3w"
    ],
    "wof:name":"Borzykow",
    "wof:placetype":"locality"
},
  "geometry": {"coordinates":[18.83333,50.33333],"type":"Point"}
}