{
  "type": "Feature",
  "properties": {
    "gn:population":460,
    "iso:country":"PL",
    "name:ast_x_preferred":[
        "Cisna"
    ],
    "name:ceb_x_preferred":[
        "Cisna"
    ],
    "name:deu_x_preferred":[
        "Cisna"
    ],
    "name:eng_x_preferred":[
        "Cisna"
    ],
    "name:fas_x_preferred":[
        "\u0686\u06cc\u0633\u0646\u0627"
    ],
    "name:hun_x_preferred":[
        "Cisna"
    ],
    "name:nan_x_preferred":[
        "Cisna"
    ],
    "name:nld_x_preferred":[
        "Cisna"
    ],
    "name:pol_x_preferred":[
        "Cisna"
    ],
    "name:ukr_x_preferred":[
        "\u0422\u0456\u0441\u043d\u0430"
    ],
    "name:vie_x_preferred":[
        "Cisna"
    ],
    "name:zho_min_nan_x_preferred":[
        "Cisna"
    ],
    "qs:a0":"Rzeczpospolita Polska",
    "qs:a1":"*Podkarpackie",
    "qs:a1r":"6",
    "qs:a2":"Leski",
    "qs:adm0":"Rzeczpospolita Polska",
    "qs:la":"Cisna",
    "qs:la_lc":"*PL1821022",
    "qs:level":"locality",
    "qs:loc":"Cisna",
    "qs:pop":0,
    "qs:type":"rural hamlet perfect local_admin match geoplanet",
    "wd:wordcount":249,
    "wof:name":"Cisna",
    "wof:placetype":"locality",
    "wof:population":460
},
  "geometry": {"coordinates":[22.4084417407544,49.1987600755315],"type":"Point"}
}