{
  "type": "Feature",
  "properties": {
    "gn:admin1_code":"81.0",
    "gn:admin2_code":"2009.0",
    "gn:admin3_code":"200902.0",
    "gn:asciiname":"Pokrowsk",
    "gn:country_code":"PL",
    "gn:dem":131,
    "gn:feature_class":"P",
    "gn:feature_code":"PPL",
    "gn:name":"Pokrowsk",
    "gn:population":0,
    "gn:timezone":"Europe/Warsaw",
    "iso:country":"PL",
    "wof:name":"Pokrowsk",
    "wof:placetype":"locality"
},
  "geometry": {"coordinates":[23.26148,54.05304],"type":"Point"}
}