{
  "type": "Feature",
  "properties": {
    "gn:admin1_code":"83.0",
    "gn:admin2_code":"2413.0",
    "gn:admin3_code":"241308.0",
    "gn:asciiname":"Wojska",
    "gn:country_code":"PL",
    "gn:dem":264,
    "gn:feature_class":"P",
    "gn:feature_code":"PPL",
    "gn:name":"Wojska",
    "gn:population":0,
    "gn:timezone":"Europe/Warsaw",
    "iso:country":"PL",
    "name:ceb_x_preferred":[
        "Wojska"
    ],
    "name:deu_x_preferred":[
        "Wojska"
    ],
    "name:pol_x_preferred":[
        "Wojska"
    ],
    "name:ukr_x_preferred":[
        "\u0412\u043e\u0439\u0441\u044c\u043a\u0430"
    ],
    "wof:name":"Wojska",
    "wof:placetype":"locality"
},
  "geometry": {"coordinates":[18.66626,50.48518],"type":"Point"}
}