{
  "type": "Feature",
  "properties": {
    "gn:admin1_code":"83.0",
    "gn:admin2_code":"2413.0",
    "gn:admin3_code":"241308.0",
    "gn:asciiname":"Wojska",
    "gn:country_code":"PL",
    "gn:dem":264,
    "gn:feature_class":"P",
    "gn:feature_code":"PPL",
    "gn:name":"Wojska",
    "gn:population":0,
    "gn:timezone":"Europe/Warsaw",
    "iso:country":"PL",
    "wof:name":"Wojska",
    "wof:placetype":"locality"
},
  "geometry": {"coordinates":[18.66626,50.48518],"type":"Point"}
}