{
  "type": "Feature",
  "properties": {
    "gn:gn_country":"PL",
    "gn:gn_fcode":"PPL",
    "gn:gn_pop":295,
    "gn:population":295,
    "iso:country":"PL",
    "name:eng_x_preferred":[
        "Za\u0142uski"
    ],
    "name:fre_x_preferred":[
        "Za\u0142uski"
    ],
    "name:pol_x_preferred":[
        "Za\u0142uski"
    ],
    "name:unk_x_variant":[
        "Kniprode"
    ],
    "qs_pg:aaroncc":"PL",
    "qs_pg:gn_country":"PL",
    "qs_pg:gn_fcode":"PPL",
    "qs_pg:gn_pop":295,
    "qs_pg:name":"Za\u0142uski",
    "qs_pg:name_adm0":"Polska",
    "qs_pg:name_adm1":"Warminsko-Mazurskie",
    "qs_pg:photos_9r":0,
    "qs_pg:photos_sr":0,
    "qs_pg:pop_sr":2,
    "qs_pg:qs_pg_placetype":"locality",
    "qs_pg:qs_pg_placetype_gp":"Town",
    "qs_pg:woe_adm0":23424923,
    "woe:adm0_id":23424923,
    "woe:name_adm0":"Polska",
    "woe:name_adm1":"Warminsko-Mazurskie",
    "woe:placetype":"Town",
    "wof:name":"Za\u0142uski",
    "wof:placetype":"locality",
    "wof:population":295
},
  "geometry": {"coordinates":[20.35715,53.39321],"type":"Point"}
}