{
  "type": "Feature",
  "properties": {
    "gn:admin1_code":"84.0",
    "gn:admin2_code":"2604.0",
    "gn:admin3_code":"260414.0",
    "gn:asciiname":"Micigozd",
    "gn:country_code":"PL",
    "gn:dem":270,
    "gn:feature_class":"P",
    "gn:feature_code":"PPL",
    "gn:name":"Micig\u00f3zd",
    "gn:population":0,
    "gn:timezone":"Europe/Warsaw",
    "iso:country":"PL",
    "name:ceb_x_preferred":[
        "Micig\u00f3zd"
    ],
    "name:nld_x_preferred":[
        "Micig\u00f3zd"
    ],
    "name:pol_x_preferred":[
        "Micig\u00f3zd"
    ],
    "name:ukr_x_preferred":[
        "\u041c\u0456\u0446\u0438\u0491\u0443\u0437\u0434"
    ],
    "wof:name":"Micigozd",
    "wof:placetype":"locality"
},
  "geometry": {"coordinates":[20.45376,50.90141],"type":"Point"}
}