{
  "type": "Feature",
  "properties": {
    "gn:admin1_code":"82.0",
    "gn:admin2_code":"2206.0",
    "gn:admin3_code":"220607.0",
    "gn:asciiname":"Skrzydlowo",
    "gn:country_code":"PL",
    "gn:dem":167,
    "gn:feature_class":"P",
    "gn:feature_code":"PPL",
    "gn:name":"Skrzyd\u0142owo",
    "gn:population":0,
    "gn:timezone":"Europe/Warsaw",
    "iso:country":"PL",
    "name:pol_x_preferred":[
        "Skrzyd\u0142owo"
    ],
    "name:ukr_x_preferred":[
        "\u0421\u043a\u0448\u0438\u0434\u043b\u043e\u0432\u043e"
    ],
    "wof:name":"Skrzydlowo",
    "wof:placetype":"locality"
},
  "geometry": {"coordinates":[18.26476,54.12753000000001],"type":"Point"}
}