{
  "type": "Feature",
  "properties": {
    "gn:admin1_code":"78.0",
    "gn:admin2_code":"1426.0",
    "gn:admin3_code":"142613.0",
    "gn:asciiname":"Krzesk Krolowa Niwa",
    "gn:country_code":"PL",
    "gn:dem":159,
    "gn:feature_class":"P",
    "gn:feature_code":"PPL",
    "gn:name":"Krzesk Kr\u00f3lowa Niwa",
    "gn:population":0,
    "gn:timezone":"Europe/Warsaw",
    "iso:country":"PL",
    "name:azb_x_preferred":[
        "\u06a9\u0698\u0633\u06a9-\u06a9\u0631\u0648\u0644\u0648\u0648\u0627 \u0646\u0642\u0648\u0627"
    ],
    "name:fas_x_preferred":[
        "\u06a9\u0698\u0633\u06a9-\u06a9\u0631\u0648\u0644\u0648\u0648\u0627 \u0646\u06af\u0648\u0627"
    ],
    "name:fra_x_preferred":[
        "Krzesk-Kr\u00f3lowa Niwa"
    ],
    "name:pol_x_preferred":[
        "Krzesk-Kr\u00f3lowa Niwa"
    ],
    "name:ukr_x_preferred":[
        "\u041a\u0448\u0435\u0441\u044c\u043a-\u041a\u0440\u0443\u043b\u044c\u043e\u0432\u0430-\u041d\u0456\u0432\u0430"
    ],
    "name:und_x_variant":[
        "Krzesk",
        "Krzesk Kr\u00f3lowa Niwa"
    ],
    "wof:name":"Krzesk Krolowa Niwa",
    "wof:placetype":"locality"
},
  "geometry": {"coordinates":[22.61494,52.06731],"type":"Point"}
}