{
  "type": "Feature",
  "properties": {
    "gn:admin1_code":"78.0",
    "gn:admin2_code":"1426.0",
    "gn:admin3_code":"142613.0",
    "gn:asciiname":"Krzesk Krolowa Niwa",
    "gn:country_code":"PL",
    "gn:dem":159,
    "gn:feature_class":"P",
    "gn:feature_code":"PPL",
    "gn:name":"Krzesk Kr\u00f3lowa Niwa",
    "gn:population":0,
    "gn:timezone":"Europe/Warsaw",
    "iso:country":"PL",
    "name:und_x_variant":[
        "Krzesk",
        "Krzesk Kr\u00f3lowa Niwa"
    ],
    "wof:name":"Krzesk Krolowa Niwa",
    "wof:placetype":"locality"
},
  "geometry": {"coordinates":[22.61494,52.06731],"type":"Point"}
}