{
  "type": "Feature",
  "properties": {
    "gn:admin1_code":"78.0",
    "gn:admin2_code":"1429.0",
    "gn:admin3_code":"142902.0",
    "gn:asciiname":"Ruciany",
    "gn:country_code":"PL",
    "gn:dem":156,
    "gn:feature_class":"P",
    "gn:feature_code":"PPL",
    "gn:name":"Ruciany",
    "gn:population":0,
    "gn:timezone":"Europe/Warsaw",
    "iso:country":"PL",
    "wof:name":"Ruciany",
    "wof:placetype":"locality"
},
  "geometry": {"coordinates":[22.265,52.31638],"type":"Point"}
}