{
  "type": "Feature",
  "properties": {
    "gn:admin1_code":"78.0",
    "gn:admin2_code":"1429.0",
    "gn:admin3_code":"142902.0",
    "gn:asciiname":"Ruciany",
    "gn:country_code":"PL",
    "gn:dem":156,
    "gn:feature_class":"P",
    "gn:feature_code":"PPL",
    "gn:name":"Ruciany",
    "gn:population":0,
    "gn:timezone":"Europe/Warsaw",
    "iso:country":"PL",
    "name:azb_x_preferred":[
        "\u0631\u0648\u0686\u06cc\u0627\u0646\u0647"
    ],
    "name:fas_x_preferred":[
        "\u0631\u0648\u0686\u06cc\u0627\u0646\u0647"
    ],
    "name:fra_x_preferred":[
        "Ruciany"
    ],
    "name:lit_x_preferred":[
        "Rucianai"
    ],
    "name:pol_x_preferred":[
        "Ruciany"
    ],
    "name:szl_x_preferred":[
        "Ru\u0107any"
    ],
    "name:ukr_x_preferred":[
        "\u0420\u0443\u0446\u044f\u043d\u0438"
    ],
    "wof:name":"Ruciany",
    "wof:placetype":"locality"
},
  "geometry": {"coordinates":[22.265,52.31638],"type":"Point"}
}