{
  "type": "Feature",
  "properties": {
    "gn:country":"PL",
    "gn:fcode":"PPL",
    "gn:population":1539,
    "iso:country":"PL",
    "name:ceb_x_preferred":[
        "Paprotnia"
    ],
    "name:deu_x_preferred":[
        "Paprotnia"
    ],
    "name:eng_x_preferred":[
        "Paprotnia"
    ],
    "name:fra_x_preferred":[
        "Paprotnia"
    ],
    "name:nld_x_preferred":[
        "Paprotnia"
    ],
    "name:pol_x_preferred":[
        "Paprotnia"
    ],
    "name:rus_x_preferred":[
        "\u041f\u0430\u043f\u0440\u043e\u0442\u043d\u044f"
    ],
    "name:ukr_x_preferred":[
        "\u041f\u0430\u043f\u0440\u043e\u0442\u043d\u044f"
    ],
    "qs_pg:aaroncc":"PL",
    "qs_pg:gn_country":"PL",
    "qs_pg:gn_fcode":"PPL",
    "qs_pg:gn_pop":1539,
    "qs_pg:name":"Paprotnia",
    "qs_pg:name_adm0":"Polska",
    "qs_pg:name_adm1":"Mazowieckie",
    "qs_pg:photos_9r":0,
    "qs_pg:photos_sr":0,
    "qs_pg:pop_sr":3,
    "qs_pg:qs_pg_placetype":"locality",
    "qs_pg:qs_pg_placetype_gp":"Town",
    "qs_pg:woe_adm0":23424923,
    "woe:adm0_id":23424923,
    "woe:name_adm0":"Polska",
    "woe:name_adm1":"Mazowieckie",
    "woe:placetype":"Town",
    "wof:name":"Paprotnia",
    "wof:placetype":"locality",
    "wof:population":1539
},
  "geometry": {"coordinates":[20.4232,52.20513],"type":"Point"}
}