{
  "type": "Feature",
  "properties": {
    "gn:admin1_code":"78.0",
    "gn:admin2_code":"1428.0",
    "gn:admin3_code":"142803.0",
    "gn:asciiname":"Piotrow",
    "gn:country_code":"PL",
    "gn:dem":82,
    "gn:feature_class":"P",
    "gn:feature_code":"PPL",
    "gn:name":"Piotr\u00f3w",
    "gn:population":0,
    "gn:timezone":"Europe/Warsaw",
    "iso:country":"PL",
    "name:pol_x_preferred":[
        "Piotr\u00f3w"
    ],
    "name:ukr_x_preferred":[
        "\u041f\u0439\u043e\u0442\u0440\u0443\u0432"
    ],
    "name:und_x_variant":[
        "Piotr\u00f3w"
    ],
    "wof:name":"Piotrow",
    "wof:placetype":"locality"
},
  "geometry": {"coordinates":[20.07532,52.30199],"type":"Point"}
}