{
  "type": "Feature",
  "properties": {
    "gn:admin1_code":"77.0",
    "gn:admin2_code":"1210.0",
    "gn:admin3_code":"121007.0",
    "gn:asciiname":"Czyrna",
    "gn:country_code":"PL",
    "gn:dem":528,
    "gn:feature_class":"P",
    "gn:feature_code":"PPL",
    "gn:name":"Czyrna",
    "gn:population":0,
    "gn:timezone":"Europe/Warsaw",
    "iso:country":"PL",
    "name:pol_x_preferred":[
        "Czyrna"
    ],
    "name:rue_x_preferred":[
        "\u0427\u0438\u0440\u043d\u0430"
    ],
    "name:ukr_x_preferred":[
        "\u0427\u0438\u0440\u043d\u0430"
    ],
    "name:und_x_variant":[
        "Czarna",
        "Czyrna"
    ],
    "wof:name":"Czyrna",
    "wof:placetype":"locality"
},
  "geometry": {"coordinates":[21.02086,49.48052],"type":"Point"}
}