{
  "type": "Feature",
  "properties": {
    "gn:admin1_code":"73.0",
    "gn:admin2_code":"418.0",
    "gn:admin3_code":"41804.0",
    "gn:asciiname":"Wolica Stara",
    "gn:country_code":"PL",
    "gn:dem":79,
    "gn:feature_class":"P",
    "gn:feature_code":"PPL",
    "gn:name":"Wolica Stara",
    "gn:population":0,
    "gn:timezone":"Europe/Warsaw",
    "iso:country":"PL",
    "wof:name":"Wolica Stara",
    "wof:placetype":"locality"
},
  "geometry": {"coordinates":[18.87784,52.64986999999999],"type":"Point"}
}