{
  "type": "Feature",
  "properties": {
    "gn:admin1_code":"83.0",
    "gn:admin2_code":"2404.0",
    "gn:admin3_code":"240408.0",
    "gn:asciiname":"Widzowek",
    "gn:country_code":"PL",
    "gn:dem":213,
    "gn:feature_class":"P",
    "gn:feature_code":"PPL",
    "gn:name":"Widz\u00f3wek",
    "gn:population":0,
    "gn:timezone":"Europe/Warsaw",
    "iso:country":"PL",
    "name:ceb_x_preferred":[
        "Widz\u00f3wek"
    ],
    "name:pol_x_preferred":[
        "Widz\u00f3wek"
    ],
    "name:ukr_x_preferred":[
        "\u0412\u0456\u0434\u0437\u0443\u0432\u0435\u043a"
    ],
    "wof:name":"Widzowek",
    "wof:placetype":"locality"
},
  "geometry": {"coordinates":[19.38623,50.98361],"type":"Point"}
}