{
  "type": "Feature",
  "properties": {
    "gn:admin1_code":"82.0",
    "gn:admin2_code":"2204.0",
    "gn:admin3_code":"220407.0",
    "gn:asciiname":"Kozliny",
    "gn:country_code":"PL",
    "gn:dem":3,
    "gn:feature_class":"P",
    "gn:feature_code":"PPL",
    "gn:name":"Ko\u017aliny",
    "gn:population":0,
    "gn:timezone":"Europe/Warsaw",
    "iso:country":"PL",
    "name:ceb_x_preferred":[
        "Ko\u017aliny"
    ],
    "name:eng_x_preferred":[
        "Ko\u017aliny"
    ],
    "name:nld_x_preferred":[
        "Ko\u017aliny"
    ],
    "name:pol_x_preferred":[
        "Ko\u017aliny"
    ],
    "name:rus_x_preferred":[
        "\u041a\u043e\u0436\u043b\u0438\u043d\u044b"
    ],
    "name:ukr_x_preferred":[
        "\u041a\u043e\u0437\u043b\u0456\u043d\u0438"
    ],
    "name:und_x_variant":[
        "G\u00fcttland"
    ],
    "wof:name":"Kozliny",
    "wof:placetype":"locality"
},
  "geometry": {"coordinates":[18.80152,54.16134],"type":"Point"}
}