{
  "type": "Feature",
  "properties": {
    "gn:admin1_code":"78.0",
    "gn:admin2_code":"1410.0",
    "gn:admin3_code":"141004.0",
    "gn:asciiname":"Zaborze",
    "gn:country_code":"PL",
    "gn:dem":133,
    "gn:feature_class":"P",
    "gn:feature_code":"PPL",
    "gn:name":"Zaborze",
    "gn:population":0,
    "gn:timezone":"Europe/Warsaw",
    "iso:country":"PL",
    "name:azb_x_preferred":[
        "\u0632\u0627\u0628\u0648\u0698\u0647"
    ],
    "name:ceb_x_preferred":[
        "Zaborze"
    ],
    "name:fas_x_preferred":[
        "\u0632\u0627\u0628\u0648\u0698\u0647"
    ],
    "name:fra_x_preferred":[
        "Zaborze"
    ],
    "name:lit_x_preferred":[
        "Zabo\u017e\u0117"
    ],
    "name:pol_x_preferred":[
        "Zaborze"
    ],
    "name:ukr_x_preferred":[
        "\u0417\u0430\u0431\u043e\u0436\u0435"
    ],
    "name:urd_x_preferred":[
        "\u0632\u0628\u0648\u0631\u0632\u06d2"
    ],
    "wof:name":"Zaborze",
    "wof:placetype":"locality"
},
  "geometry": {"coordinates":[22.75217,52.28691],"type":"Point"}
}