{
  "type": "Feature",
  "properties": {
    "gn:gn_country":"PL",
    "gn:gn_fcode":"PPL",
    "gn:gn_pop":220,
    "gn:population":220,
    "iso:country":"PL",
    "name:eng_x_preferred":[
        "Bedo\u0144-Wie\u015b"
    ],
    "name:fra_x_preferred":[
        "Bedo\u0144-Wie\u015b"
    ],
    "name:nld_x_preferred":[
        "Bedo\u0144-Wie\u015b"
    ],
    "name:pol_x_preferred":[
        "Bedo\u0144-Wie\u015b"
    ],
    "qs_pg:aaroncc":"PL",
    "qs_pg:gn_country":"PL",
    "qs_pg:gn_fcode":"PPL",
    "qs_pg:gn_pop":220,
    "qs_pg:name":"Bedo\u0144 Wie\u015b",
    "qs_pg:photos_9r":0,
    "qs_pg:photos_sr":0,
    "qs_pg:pop_sr":2,
    "qs_pg:qs_pg_placetype":"locality",
    "wof:name":"Bedo\u0144 Wie\u015b",
    "wof:placetype":"locality",
    "wof:population":220
},
  "geometry": {"coordinates":[19.64433,51.74441],"type":"Point"}
}