{
  "type": "Feature",
  "properties": {
    "gn:admin1_code":"75.0",
    "gn:admin2_code":"608.0",
    "gn:admin3_code":"60809.0",
    "gn:asciiname":"Zabiele",
    "gn:country_code":"PL",
    "gn:dem":158,
    "gn:feature_class":"P",
    "gn:feature_code":"PPL",
    "gn:name":"Zabiele",
    "gn:population":0,
    "gn:timezone":"Europe/Warsaw",
    "iso:country":"PL",
    "name:deu_x_preferred":[
        "Zabiele"
    ],
    "name:fra_x_preferred":[
        "Zabiele"
    ],
    "name:lit_x_preferred":[
        "Zabiel\u0117"
    ],
    "name:pol_x_preferred":[
        "Zabiele"
    ],
    "name:ukr_x_preferred":[
        "\u0417\u0430\u0431\u0435\u043b\u0435"
    ],
    "wof:name":"Zabiele",
    "wof:placetype":"locality"
},
  "geometry": {"coordinates":[22.77022,51.53627],"type":"Point"}
}