{
  "type": "Feature",
  "properties": {
    "iso:country":"PL",
    "name:eng_x_preferred":[
        "Biskupin"
    ],
    "name:pol_x_preferred":[
        "Biskupin"
    ],
    "wof:name":"Biskupin",
    "wof:placetype":"neighbourhood"
},
  "geometry": {"coordinates":[17.10170882777755,51.10146902773751],"type":"Point"}
}