{
  "type": "Feature",
  "properties": {
    "iso:country":"PL",
    "name:afr_x_preferred":[
        "Biskupin"
    ],
    "name:ceb_x_preferred":[
        "Biskupin"
    ],
    "name:deu_x_preferred":[
        "Biskupin"
    ],
    "name:eng_x_preferred":[
        "Biskupin"
    ],
    "name:fin_x_preferred":[
        "Biskupin"
    ],
    "name:hye_x_preferred":[
        "\u0532\u056b\u057d\u056f\u0578\u0582\u057a\u056b\u0576"
    ],
    "name:ita_x_preferred":[
        "Biskupin"
    ],
    "name:kor_x_preferred":[
        "\ube44\uc2a4\ucfe0\ud540 \uc720\uc801"
    ],
    "name:lav_x_preferred":[
        "Biskupina"
    ],
    "name:lit_x_preferred":[
        "Biskupino gyvenviet\u0117"
    ],
    "name:nor_x_preferred":[
        "Biskupin"
    ],
    "name:oci_x_preferred":[
        "Biskupin"
    ],
    "name:pol_x_preferred":[
        "Biskupin"
    ],
    "name:rus_x_preferred":[
        "\u0411\u0438\u0441\u043a\u0443\u043f\u0438\u043d"
    ],
    "name:spa_x_preferred":[
        "Biskupin"
    ],
    "name:swe_x_preferred":[
        "Biskupin"
    ],
    "name:ukr_x_preferred":[
        "\u0411\u0456\u0441\u043a\u0443\u043f\u0438\u043d\u0441\u044c\u043a\u0435 \u0433\u043e\u0440\u043e\u0434\u0438\u0449\u0435"
    ],
    "name:vie_x_preferred":[
        "Biskupin"
    ],
    "name:vol_x_preferred":[
        "Biskupin"
    ],
    "wof:name":"Biskupin",
    "wof:placetype":"neighbourhood"
},
  "geometry": {"coordinates":[17.10170882777755,51.10146902773751],"type":"Point"}
}