{
  "type": "Feature",
  "properties": {
    "gn:admin1_code":"78.0",
    "gn:admin2_code":"1438.0",
    "gn:admin3_code":"143803.0",
    "gn:asciiname":"Wyczesniak",
    "gn:country_code":"PL",
    "gn:dem":128,
    "gn:feature_class":"P",
    "gn:feature_code":"PPL",
    "gn:name":"Wycze\u015bniak",
    "gn:population":0,
    "gn:timezone":"Europe/Warsaw",
    "iso:country":"PL",
    "name:fra_x_preferred":[
        "Wycze\u015bniak"
    ],
    "name:pol_x_preferred":[
        "Wycze\u015bniak"
    ],
    "name:ukr_x_preferred":[
        "\u0412\u0438\u0447\u0435\u0441\u043d\u044f\u043a"
    ],
    "wof:name":"Wyczesniak",
    "wof:placetype":"locality"
},
  "geometry": {"coordinates":[20.31715,51.93749],"type":"Point"}
}