{
  "type": "Feature",
  "properties": {
    "gn:admin1_code":"75.0",
    "gn:admin2_code":"611.0",
    "gn:admin3_code":"61105.0",
    "gn:asciiname":"Szczygly Dolne",
    "gn:country_code":"PL",
    "gn:dem":158,
    "gn:feature_class":"P",
    "gn:feature_code":"PPL",
    "gn:name":"Szczyg\u0142y Dolne",
    "gn:population":0,
    "gn:timezone":"Europe/Warsaw",
    "iso:country":"PL",
    "name:fra_x_preferred":[
        "Szczyg\u0142y Dolne"
    ],
    "name:pol_x_preferred":[
        "Szczyg\u0142y Dolne"
    ],
    "name:ukr_x_preferred":[
        "\u0429\u0438\u0491\u043b\u0438-\u0414\u043e\u043b\u044c\u043d\u0435"
    ],
    "wof:name":"Szczygly Dolne",
    "wof:placetype":"locality"
},
  "geometry": {"coordinates":[22.3154,51.86151],"type":"Point"}
}