{
  "type": "Feature",
  "properties": {
    "gn:admin1_code":"79.0",
    "gn:admin2_code":"1661.0",
    "gn:admin3_code":"166101.0",
    "gn:asciiname":"Zakrzow",
    "gn:country_code":"PL",
    "gn:dem":161,
    "gn:feature_class":"P",
    "gn:feature_code":"PPL",
    "gn:name":"Zakrz\u00f3w",
    "gn:population":0,
    "gn:timezone":"Europe/Warsaw",
    "iso:country":"PL",
    "wof:name":"Zakrzow",
    "wof:placetype":"locality"
},
  "geometry": {"coordinates":[17.91939,50.69335],"type":"Point"}
}