{
  "type": "Feature",
  "properties": {
    "gn:gn_country":"PL",
    "gn:gn_fcode":"PPLA3",
    "gn:gn_pop":380,
    "gn:population":380,
    "iso:country":"PL",
    "name:ceb_x_preferred":[
        "Wierzbinek"
    ],
    "name:deu_x_preferred":[
        "Wierzbinek"
    ],
    "name:pol_x_preferred":[
        "Wierzbinek"
    ],
    "name:ukr_x_preferred":[
        "\u0412\u0435\u0436\u0431\u0456\u043d\u0435\u043a"
    ],
    "qs_pg:aaroncc":"PL",
    "qs_pg:gn_country":"PL",
    "qs_pg:gn_fcode":"PPLA3",
    "qs_pg:gn_pop":380,
    "qs_pg:name":"Wierzbinek",
    "qs_pg:name_adm0":"Polska",
    "qs_pg:name_adm1":"Wielkopolskie",
    "qs_pg:photos":1,
    "qs_pg:photos_1k":1,
    "qs_pg:photos_9k":1,
    "qs_pg:photos_9r":1,
    "qs_pg:photos_all":1,
    "qs_pg:photos_sr":1,
    "qs_pg:pop_sr":2,
    "qs_pg:qs_pg_placetype":"localadmin",
    "qs_pg:qs_pg_placetype_gp":"LocalAdmin",
    "qs_pg:woe_adm0":23424923,
    "woe:adm0_id":23424923,
    "woe:name_adm0":"Polska",
    "woe:name_adm1":"Wielkopolskie",
    "woe:placetype":"LocalAdmin",
    "wof:name":"Wierzbinek",
    "wof:placetype":"localadmin",
    "wof:population":380
},
  "geometry": {"coordinates":[18.51085,52.44026],"type":"Point"}
}