{
  "type": "Feature",
  "properties": {
    "gn:admin1_code":"82.0",
    "gn:admin2_code":"2207.0",
    "gn:admin3_code":"220702.0",
    "gn:asciiname":"Cygany",
    "gn:country_code":"PL",
    "gn:dem":98,
    "gn:feature_class":"P",
    "gn:feature_code":"PPL",
    "gn:name":"Cygany",
    "gn:population":0,
    "gn:timezone":"Europe/Warsaw",
    "iso:country":"PL",
    "name:ceb_x_preferred":[
        "Cygany"
    ],
    "name:pol_x_preferred":[
        "Cygany"
    ],
    "name:ukr_x_preferred":[
        "\u0426\u0438\u0491\u0430\u043d\u0438"
    ],
    "name:und_x_variant":[
        "Zigahnen",
        "Dietmarsdorf",
        "Cigany"
    ],
    "wof:name":"Cygany",
    "wof:placetype":"locality"
},
  "geometry": {"coordinates":[19.00769,53.65156999999999],"type":"Point"}
}