{
  "type": "Feature",
  "properties": {
    "gn:admin1_code":"79.0",
    "gn:admin2_code":"1607.0",
    "gn:admin3_code":"160703.0",
    "gn:asciiname":"Ulianowka",
    "gn:country_code":"PL",
    "gn:dem":194,
    "gn:feature_class":"P",
    "gn:feature_code":"PPL",
    "gn:name":"Ulianowka",
    "gn:population":0,
    "gn:timezone":"Europe/Warsaw",
    "iso:country":"PL",
    "wof:name":"Ulianowka",
    "wof:placetype":"locality"
},
  "geometry": {"coordinates":[17.59126,50.49746],"type":"Point"}
}