{
  "type": "Feature",
  "properties": {
    "gn:admin1_code":"86.0",
    "gn:admin2_code":"3027.0",
    "gn:admin3_code":"302702.0",
    "gn:asciiname":"Cichow",
    "gn:country_code":"PL",
    "gn:dem":95,
    "gn:feature_class":"P",
    "gn:feature_code":"PPL",
    "gn:name":"Cich\u00f3w",
    "gn:population":0,
    "gn:timezone":"Europe/Warsaw",
    "iso:country":"PL",
    "name:ceb_x_preferred":[
        "Cich\u00f3w"
    ],
    "name:nld_x_preferred":[
        "Cich\u00f3w"
    ],
    "name:pol_x_preferred":[
        "Cich\u00f3w"
    ],
    "name:ukr_x_preferred":[
        "\u0426\u0438\u0445\u0443\u0432"
    ],
    "wof:name":"Cichow",
    "wof:placetype":"locality"
},
  "geometry": {"coordinates":[18.63169,52.11595],"type":"Point"}
}