{
  "type": "Feature",
  "properties": {
    "gn:admin1_code":"75.0",
    "gn:admin2_code":"606.0",
    "gn:admin3_code":"60611.0",
    "gn:asciiname":"Chlaniow",
    "gn:country_code":"PL",
    "gn:dem":217,
    "gn:feature_class":"P",
    "gn:feature_code":"PPL",
    "gn:name":"Ch\u0142ani\u00f3w",
    "gn:population":0,
    "gn:timezone":"Europe/Warsaw",
    "iso:country":"PL",
    "name:und_x_variant":[
        "Ch\u0142ani\u00f3w"
    ],
    "wof:name":"Chlaniow",
    "wof:placetype":"locality"
},
  "geometry": {"coordinates":[22.87036,50.83693],"type":"Point"}
}