{
  "type": "Feature",
  "properties": {
    "gn:admin1_code":"74.0",
    "gn:admin2_code":"1014.0",
    "gn:admin3_code":"101411.0",
    "gn:asciiname":"Wandalin",
    "gn:country_code":"PL",
    "gn:dem":167,
    "gn:feature_class":"P",
    "gn:feature_code":"PPL",
    "gn:name":"Wandalin",
    "gn:population":0,
    "gn:timezone":"Europe/Warsaw",
    "iso:country":"PL",
    "name:pol_x_preferred":[
        "Wandalin"
    ],
    "name:ukr_x_preferred":[
        "\u0412\u0430\u043d\u0434\u0430\u043b\u0456\u043d"
    ],
    "wof:name":"Wandalin",
    "wof:placetype":"locality"
},
  "geometry": {"coordinates":[18.52707,51.39566],"type":"Point"}
}