{
  "type": "Feature",
  "properties": {
    "gn:admin1_code":"78.0",
    "gn:admin2_code":"1427.0",
    "gn:admin3_code":"142704.0",
    "gn:asciiname":"Babiec Piaseczny",
    "gn:country_code":"PL",
    "gn:dem":111,
    "gn:feature_class":"P",
    "gn:feature_code":"PPL",
    "gn:name":"Babiec Piaseczny",
    "gn:population":0,
    "gn:timezone":"Europe/Warsaw",
    "iso:country":"PL",
    "wof:name":"Babiec Piaseczny",
    "wof:placetype":"locality"
},
  "geometry": {"coordinates":[19.70502,52.89436],"type":"Point"}
}