{
  "type": "Feature",
  "properties": {
    "gn:admin1_code":"78.0",
    "gn:admin2_code":"1424.0",
    "gn:admin3_code":"142404.0",
    "gn:asciiname":"Lipniki Nowe",
    "gn:country_code":"PL",
    "gn:dem":104,
    "gn:feature_class":"P",
    "gn:feature_code":"PPL",
    "gn:name":"Lipniki Nowe",
    "gn:population":0,
    "gn:timezone":"Europe/Warsaw",
    "iso:country":"PL",
    "name:fra_x_preferred":[
        "Lipniki Nowe"
    ],
    "name:pol_x_preferred":[
        "Lipniki Nowe"
    ],
    "name:ukr_x_preferred":[
        "\u041b\u0456\u043f\u043d\u0438\u043a\u0438-\u041d\u043e\u0432\u0456"
    ],
    "wof:name":"Lipniki Nowe",
    "wof:placetype":"locality"
},
  "geometry": {"coordinates":[21.03683,52.70884],"type":"Point"}
}