{
  "type": "Feature",
  "properties": {
    "gn:admin1_code":"77.0",
    "gn:admin2_code":"1217.0",
    "gn:admin3_code":"121705.0",
    "gn:asciiname":"Kule",
    "gn:country_code":"PL",
    "gn:dem":908,
    "gn:feature_class":"P",
    "gn:feature_code":"PPL",
    "gn:name":"Kule",
    "gn:population":0,
    "gn:timezone":"Europe/Warsaw",
    "iso:country":"PL",
    "name:fra_x_preferred":[
        "Kule"
    ],
    "name:ita_x_preferred":[
        "Kule"
    ],
    "name:mlg_x_preferred":[
        "Kule"
    ],
    "name:nld_x_preferred":[
        "Kule"
    ],
    "name:pol_x_preferred":[
        "Kule"
    ],
    "name:swa_x_preferred":[
        "Kule"
    ],
    "name:swe_x_preferred":[
        "Kule"
    ],
    "name:tsn_x_preferred":[
        "Kule"
    ],
    "wof:name":"Kule",
    "wof:placetype":"locality"
},
  "geometry": {"coordinates":[19.91667,49.33333],"type":"Point"}
}