{
  "type": "Feature",
  "properties": {
    "gn:admin1_code":"86.0",
    "gn:admin2_code":"3009.0",
    "gn:admin3_code":"300908.0",
    "gn:asciiname":"Bialkow Gorny",
    "gn:country_code":"PL",
    "gn:dem":117,
    "gn:feature_class":"P",
    "gn:feature_code":"PPL",
    "gn:name":"Bia\u0142k\u00f3w G\u00f3rny",
    "gn:population":0,
    "gn:timezone":"Europe/Warsaw",
    "iso:country":"PL",
    "name:pol_x_preferred":[
        "Bia\u0142k\u00f3w G\u00f3rny"
    ],
    "name:ukr_x_preferred":[
        "\u0411\u044f\u043b\u043a\u0443\u0432-\u0490\u0443\u0440\u043d\u0438"
    ],
    "wof:name":"Bialkow Gorny",
    "wof:placetype":"locality"
},
  "geometry": {"coordinates":[18.56003,52.1574],"type":"Point"}
}