{
  "type": "Feature",
  "properties": {
    "gn:admin1_code":"81.0",
    "gn:admin2_code":"2010.0",
    "gn:admin3_code":"201009.0",
    "gn:asciiname":"Cecele",
    "gn:country_code":"PL",
    "gn:dem":153,
    "gn:feature_class":"P",
    "gn:feature_code":"PPL",
    "gn:name":"Cecele",
    "gn:population":0,
    "gn:timezone":"Europe/Warsaw",
    "iso:country":"PL",
    "name:azb_x_preferred":[
        "\u062a\u0633\u062a\u0633\u0644\u0647"
    ],
    "name:fas_x_preferred":[
        "\u062a\u0633\u062a\u0633\u0644\u0647"
    ],
    "name:lit_x_preferred":[
        "Cecel\u0117"
    ],
    "name:pol_x_preferred":[
        "Cecele"
    ],
    "name:por_x_preferred":[
        "Cecele"
    ],
    "name:ukr_x_preferred":[
        "\u0426\u0435\u0446\u0435\u043b\u0435"
    ],
    "wof:name":"Cecele",
    "wof:placetype":"locality"
},
  "geometry": {"coordinates":[22.76641,52.46628000000001],"type":"Point"}
}