{
  "type": "Feature",
  "properties": {
    "gn:admin1_code":"80.0",
    "gn:admin2_code":"1805.0",
    "gn:admin3_code":"180502.0",
    "gn:asciiname":"Dabrowka",
    "gn:country_code":"PL",
    "gn:dem":263,
    "gn:feature_class":"P",
    "gn:feature_code":"PPL",
    "gn:name":"D\u0105br\u00f3wka",
    "gn:population":0,
    "gn:timezone":"Europe/Warsaw",
    "iso:country":"PL",
    "wof:name":"Dabrowka",
    "wof:placetype":"locality"
},
  "geometry": {"coordinates":[21.39401,49.77467],"type":"Point"}
}