{
  "type": "Feature",
  "properties": {
    "gn:admin1_code":"82.0",
    "gn:admin2_code":"2212.0",
    "gn:admin3_code":"221204.0",
    "gn:asciiname":"Gorzyslaw",
    "gn:country_code":"PL",
    "gn:dem":84,
    "gn:feature_class":"P",
    "gn:feature_code":"PPL",
    "gn:name":"Gorzys\u0142aw",
    "gn:population":0,
    "gn:timezone":"Europe/Warsaw",
    "iso:country":"PL",
    "name:und_x_variant":[
        "Gorzys\u0142aw"
    ],
    "wof:name":"Gorzyslaw",
    "wof:placetype":"locality"
},
  "geometry": {"coordinates":[17.42067,54.554],"type":"Point"}
}