{
  "type": "Feature",
  "properties": {
    "gn:admin1_code":"81.0",
    "gn:admin2_code":"2002.0",
    "gn:admin3_code":"200206.0",
    "gn:asciiname":"Gasowka Skwarki",
    "gn:country_code":"PL",
    "gn:dem":129,
    "gn:feature_class":"P",
    "gn:feature_code":"PPL",
    "gn:name":"G\u0105s\u00f3wka Skwarki",
    "gn:population":0,
    "gn:timezone":"Europe/Warsaw",
    "iso:country":"PL",
    "name:und_x_variant":[
        "G\u0105s\u00f3wka-Skwarki",
        "G\u0105s\u00f3wka Skwarki"
    ],
    "wof:name":"Gasowka Skwarki",
    "wof:placetype":"locality"
},
  "geometry": {"coordinates":[22.8013,52.98362],"type":"Point"}
}