{
  "type": "Feature",
  "properties": {
    "gn:admin1_code":"78.0",
    "gn:admin2_code":"1415.0",
    "gn:admin3_code":"141503.0",
    "gn:asciiname":"Laski Szlacheckie",
    "gn:country_code":"PL",
    "gn:dem":122,
    "gn:feature_class":"P",
    "gn:feature_code":"PPL",
    "gn:name":"Laski Szlacheckie",
    "gn:population":0,
    "gn:timezone":"Europe/Warsaw",
    "iso:country":"PL",
    "name:fra_x_preferred":[
        "Laski Szlacheckie"
    ],
    "name:pol_x_preferred":[
        "Laski Szlacheckie"
    ],
    "name:ukr_x_preferred":[
        "\u041b\u044f\u0441\u043a\u0456-\u0428\u043b\u044f\u0445\u0435\u0446\u044c\u043a\u0456"
    ],
    "wof:name":"Laski Szlacheckie",
    "wof:placetype":"locality"
},
  "geometry": {"coordinates":[21.79554,52.932],"type":"Point"}
}