{
  "type": "Feature",
  "properties": {
    "gn:admin1_code":"75.0",
    "gn:admin2_code":"606.0",
    "gn:admin3_code":"60609.0",
    "gn:asciiname":"Suszen",
    "gn:country_code":"PL",
    "gn:dem":277,
    "gn:feature_class":"P",
    "gn:feature_code":"PPL",
    "gn:name":"Susze\u0144",
    "gn:population":0,
    "gn:timezone":"Europe/Warsaw",
    "iso:country":"PL",
    "name:fra_x_preferred":[
        "Susze\u0144"
    ],
    "name:pol_x_preferred":[
        "Susze\u0144"
    ],
    "name:ukr_x_preferred":[
        "\u0421\u0443\u0448\u0435\u043d\u044c"
    ],
    "wof:name":"Suszen",
    "wof:placetype":"locality"
},
  "geometry": {"coordinates":[22.99281,50.90422],"type":"Point"}
}