{
  "type": "Feature",
  "properties": {
    "gn:admin1_code":"79.0",
    "gn:admin2_code":"1611.0",
    "gn:admin3_code":"161106.0",
    "gn:asciiname":"Nogowczyce",
    "gn:country_code":"PL",
    "gn:dem":254,
    "gn:feature_class":"P",
    "gn:feature_code":"PPL",
    "gn:name":"Nogowczyce",
    "gn:population":0,
    "gn:timezone":"Europe/Warsaw",
    "iso:country":"PL",
    "name:azb_x_preferred":[
        "\u0646\u0648\u0642\u0648\u0648\u0686\u062a\u0633\u0647"
    ],
    "name:deu_x_preferred":[
        "Nogowsch\u00fctz"
    ],
    "name:fas_x_preferred":[
        "\u0646\u0648\u06af\u0648\u0648\u0686\u062a\u0633\u0647"
    ],
    "name:pol_x_preferred":[
        "Nogowczyce"
    ],
    "name:ukr_x_preferred":[
        "\u041d\u043e\u0491\u043e\u0432\u0447\u0438\u0446\u0435"
    ],
    "wof:name":"Nogowczyce",
    "wof:placetype":"locality"
},
  "geometry": {"coordinates":[18.37086,50.44176],"type":"Point"}
}