{
  "type": "Feature",
  "properties": {
    "gn:admin1_code":"79.0",
    "gn:admin2_code":"1611.0",
    "gn:admin3_code":"161106.0",
    "gn:asciiname":"Nogowczyce",
    "gn:country_code":"PL",
    "gn:dem":254,
    "gn:feature_class":"P",
    "gn:feature_code":"PPL",
    "gn:name":"Nogowczyce",
    "gn:population":0,
    "gn:timezone":"Europe/Warsaw",
    "iso:country":"PL",
    "wof:name":"Nogowczyce",
    "wof:placetype":"locality"
},
  "geometry": {"coordinates":[18.37086,50.44176],"type":"Point"}
}