{
  "type": "Feature",
  "properties": {
    "gn:admin1_code":"78.0",
    "gn:admin2_code":"1423.0",
    "gn:admin3_code":"142301.0",
    "gn:asciiname":"Bryzgow",
    "gn:country_code":"PL",
    "gn:dem":242,
    "gn:feature_class":"P",
    "gn:feature_code":"PPL",
    "gn:name":"Bryzg\u00f3w",
    "gn:population":0,
    "gn:timezone":"Europe/Warsaw",
    "iso:country":"PL",
    "name:azb_x_preferred":[
        "\u0628\u0631\u0632\u0642\u0648\u0648"
    ],
    "name:fas_x_preferred":[
        "\u0628\u0631\u0632\u06af\u0648\u0648"
    ],
    "name:fra_x_preferred":[
        "Bryzg\u00f3w"
    ],
    "name:pol_x_preferred":[
        "Bryzg\u00f3w"
    ],
    "name:ukr_x_preferred":[
        "\u0411\u0440\u0438\u0437\u0491\u0443\u0432"
    ],
    "name:urd_x_preferred":[
        "\u0628\u0631\u06cc\u0632\u06af\u0648\u0648"
    ],
    "wof:name":"Bryzgow",
    "wof:placetype":"locality"
},
  "geometry": {"coordinates":[20.66077,51.27953],"type":"Point"}
}