{
  "type": "Feature",
  "properties": {
    "gn:admin1_code":"78.0",
    "gn:admin2_code":"1423.0",
    "gn:admin3_code":"142301.0",
    "gn:asciiname":"Bryzgow",
    "gn:country_code":"PL",
    "gn:dem":242,
    "gn:feature_class":"P",
    "gn:feature_code":"PPL",
    "gn:name":"Bryzg\u00f3w",
    "gn:population":0,
    "gn:timezone":"Europe/Warsaw",
    "iso:country":"PL",
    "name:und_x_variant":[
        "Bryzg\u00f3w"
    ],
    "wof:name":"Bryzgow",
    "wof:placetype":"locality"
},
  "geometry": {"coordinates":[20.66077,51.27953],"type":"Point"}
}