{
  "type": "Feature",
  "properties": {
    "gn:admin1_code":"85.0",
    "gn:admin2_code":"2816.0",
    "gn:admin3_code":"281601.0",
    "gn:asciiname":"Konopki",
    "gn:country_code":"PL",
    "gn:dem":137,
    "gn:feature_class":"P",
    "gn:feature_code":"PPL",
    "gn:name":"Konopki",
    "gn:population":0,
    "gn:timezone":"Europe/Warsaw",
    "iso:country":"PL",
    "name:ceb_x_preferred":[
        "Konopki"
    ],
    "name:deu_x_preferred":[
        "Konopki"
    ],
    "name:fra_x_preferred":[
        "Konopki"
    ],
    "name:pol_x_preferred":[
        "Konopki"
    ],
    "name:ukr_x_preferred":[
        "\u041a\u043e\u043d\u043e\u043f\u043a\u0456"
    ],
    "name:und_x_variant":[
        "M\u00fchlengrund Ostpreussen",
        "Konopken",
        "M\u00fchlengrund"
    ],
    "wof:name":"Konopki",
    "wof:placetype":"locality"
},
  "geometry": {"coordinates":[22.08579,53.62458],"type":"Point"}
}