{
  "type": "Feature",
  "properties": {
    "gn:admin1_code":"74.0",
    "gn:admin2_code":"1001.0",
    "gn:admin3_code":"100103.0",
    "gn:asciiname":"Glupice",
    "gn:country_code":"PL",
    "gn:dem":204,
    "gn:feature_class":"P",
    "gn:feature_code":"PPL",
    "gn:name":"G\u0142upice",
    "gn:population":0,
    "gn:timezone":"Europe/Warsaw",
    "iso:country":"PL",
    "name:fra_x_preferred":[
        "G\u0142upice"
    ],
    "name:pol_x_preferred":[
        "G\u0142upice"
    ],
    "name:ukr_x_preferred":[
        "\u0490\u043b\u0443\u043f\u0456\u0446\u0435"
    ],
    "wof:name":"Glupice",
    "wof:placetype":"locality"
},
  "geometry": {"coordinates":[19.3636,51.47351],"type":"Point"}
}