{
  "type": "Feature",
  "properties": {
    "gn:gn_country":"PL",
    "gn:gn_fcode":"PPL",
    "gn:gn_pop":343,
    "gn:population":343,
    "iso:country":"PL",
    "name:eng_x_preferred":[
        "\u015awiniary"
    ],
    "name:fas_x_preferred":[
        "\u0634\u0648\u06cc\u0646\u06af\u0627\u0631\u0647"
    ],
    "name:fra_x_preferred":[
        "\u015awiniary"
    ],
    "name:nan_x_preferred":[
        "\u015awiniary"
    ],
    "name:pol_x_preferred":[
        "\u015awiniary"
    ],
    "qs_pg:aaroncc":"PL",
    "qs_pg:gn_country":"PL",
    "qs_pg:gn_fcode":"PPL",
    "qs_pg:gn_pop":343,
    "qs_pg:name":"\u015awiniary",
    "qs_pg:name_adm0":"Polska",
    "qs_pg:name_adm1":"Wielkopolskie",
    "qs_pg:photos_9r":0,
    "qs_pg:photos_sr":0,
    "qs_pg:pop_sr":2,
    "qs_pg:qs_pg_placetype":"locality",
    "qs_pg:qs_pg_placetype_gp":"Town",
    "qs_pg:woe_adm0":23424923,
    "woe:adm0_id":23424923,
    "woe:name_adm0":"Polska",
    "woe:name_adm1":"Wielkopolskie",
    "woe:placetype":"Town",
    "wof:name":"\u015awiniary",
    "wof:placetype":"locality",
    "wof:population":343
},
  "geometry": {"coordinates":[17.43084,52.66139],"type":"Point"}
}