{
  "type": "Feature",
  "properties": {
    "iso:country":"PL",
    "name:azb_x_preferred":[
        "\u062a\u0644\u0627\u062a\u0646"
    ],
    "name:fas_x_preferred":[
        "\u062a\u0644\u0627\u062a\u0646"
    ],
    "name:fra_x_preferred":[
        "Telatyn"
    ],
    "name:nld_x_preferred":[
        "Telatyn"
    ],
    "name:pol_x_preferred":[
        "Telatyn"
    ],
    "name:ukr_x_preferred":[
        "\u0422\u0435\u043b\u044f\u0442\u0438\u043d"
    ],
    "wof:coterminous":[
        1125289361
    ],
    "wof:name":"Telatyn",
    "wof:placetype":"locality"
},
  "geometry": {"coordinates":[23.8802081306565,50.5171272161371],"type":"Point"}
}