{
  "type": "Feature",
  "properties": {
    "iso:country":"PL",
    "name:pol_x_preferred":[
        "Telatyn"
    ],
    "wof:name":"Telatyn",
    "wof:placetype":"locality"
},
  "geometry": {"coordinates":[23.8802081306565,50.5171272161371],"type":"Point"}
}