{
  "type": "Feature",
  "properties": {
    "gn:admin1_code":"81.0",
    "gn:admin2_code":"2011.0",
    "gn:admin3_code":"201106.0",
    "gn:asciiname":"Choruzowce",
    "gn:country_code":"PL",
    "gn:dem":140,
    "gn:feature_class":"P",
    "gn:feature_code":"PPL",
    "gn:name":"Choru\u017cowce",
    "gn:population":0,
    "gn:timezone":"Europe/Warsaw",
    "iso:country":"PL",
    "name:azb_x_preferred":[
        "\u062e\u0648\u0631\u0648\u0698\u0648\u0648\u062a\u0633\u0647"
    ],
    "name:ceb_x_preferred":[
        "Choru\u017cowce"
    ],
    "name:fas_x_preferred":[
        "\u062e\u0648\u0631\u0648\u0698\u0648\u0648\u062a\u0633\u0647"
    ],
    "name:fra_x_preferred":[
        "Choru\u017cowce"
    ],
    "name:lit_x_preferred":[
        "Choru\u017eovc\u0117"
    ],
    "name:nld_x_preferred":[
        "Choru\u017cowce"
    ],
    "name:pol_x_preferred":[
        "Choru\u017cowce"
    ],
    "name:ukr_x_preferred":[
        "\u0425\u043e\u0440\u0443\u0436\u043e\u0432\u0446\u0435"
    ],
    "name:und_x_variant":[
        "Choro\u017cowce",
        "Choru\u017cowec"
    ],
    "wof:name":"Choruzowce",
    "wof:placetype":"locality"
},
  "geometry": {"coordinates":[23.54889,53.70114],"type":"Point"}
}