{
  "type": "Feature",
  "properties": {
    "gn:admin1_code":"81.0",
    "gn:admin2_code":"2011.0",
    "gn:admin3_code":"201106.0",
    "gn:asciiname":"Choruzowce",
    "gn:country_code":"PL",
    "gn:dem":140,
    "gn:feature_class":"P",
    "gn:feature_code":"PPL",
    "gn:name":"Choru\u017cowce",
    "gn:population":0,
    "gn:timezone":"Europe/Warsaw",
    "iso:country":"PL",
    "name:und_x_variant":[
        "Choro\u017cowce",
        "Choru\u017cowec",
        "Choru\u017cowce"
    ],
    "wof:name":"Choruzowce",
    "wof:placetype":"locality"
},
  "geometry": {"coordinates":[23.54889,53.70114],"type":"Point"}
}