{
  "type": "Feature",
  "properties": {
    "gn:admin1_code":"81.0",
    "gn:admin2_code":"2004.0",
    "gn:admin3_code":"200403.0",
    "gn:asciiname":"Mscichy",
    "gn:country_code":"PL",
    "gn:dem":112,
    "gn:feature_class":"P",
    "gn:feature_code":"PPL",
    "gn:name":"M\u015bcichy",
    "gn:population":0,
    "gn:timezone":"Europe/Warsaw",
    "iso:country":"PL",
    "name:eng_x_preferred":[
        "M\u015bcichy"
    ],
    "name:lit_x_preferred":[
        "M\u0161cichai"
    ],
    "name:pol_x_preferred":[
        "M\u015bcichy"
    ],
    "name:rus_x_preferred":[
        "\u041c\u0441\u044c\u0446\u0438\u0445\u044b"
    ],
    "name:ukr_x_preferred":[
        "\u041c\u0441\u0446\u0438\u0445\u0438"
    ],
    "wof:name":"Mscichy",
    "wof:placetype":"locality"
},
  "geometry": {"coordinates":[22.48455,53.42916999999999],"type":"Point"}
}