{
  "type": "Feature",
  "properties": {
    "gn:admin1_code":"80.0",
    "gn:admin2_code":"1811.0",
    "gn:admin3_code":"181105.0",
    "gn:asciiname":"Boza Wola",
    "gn:country_code":"PL",
    "gn:dem":174,
    "gn:feature_class":"P",
    "gn:feature_code":"PPL",
    "gn:name":"Bo\u017ca Wola",
    "gn:population":0,
    "gn:timezone":"Europe/Warsaw",
    "iso:country":"PL",
    "name:ceb_x_preferred":[
        "Bo\u017ca Wola"
    ],
    "name:nld_x_preferred":[
        "Bo\u017ca Wola"
    ],
    "name:pol_x_preferred":[
        "Bo\u017ca Wola"
    ],
    "name:ukr_x_preferred":[
        "\u0411\u043e\u0436\u0430-\u0412\u043e\u043b\u044f"
    ],
    "name:und_x_variant":[
        "Bo\u017ca Wola"
    ],
    "wof:name":"Boza Wola",
    "wof:placetype":"locality"
},
  "geometry": {"coordinates":[21.41667,50.25],"type":"Point"}
}