{
  "type": "Feature",
  "properties": {
    "gn:admin1_code":"77.0",
    "gn:admin2_code":"1210.0",
    "gn:admin3_code":"121002.0",
    "gn:asciiname":"Swiniarsko",
    "gn:country_code":"PL",
    "gn:dem":288,
    "gn:feature_class":"P",
    "gn:feature_code":"PPL",
    "gn:name":"\u015awiniarsko",
    "gn:population":0,
    "gn:timezone":"Europe/Warsaw",
    "iso:country":"PL",
    "name:und_x_variant":[
        "\u015awiniarsko"
    ],
    "wof:name":"Swiniarsko",
    "wof:placetype":"locality"
},
  "geometry": {"coordinates":[20.6554,49.60661],"type":"Point"}
}