{
  "type": "Feature",
  "properties": {
    "gn:admin1_code":"77.0",
    "gn:admin2_code":"1210.0",
    "gn:admin3_code":"121002.0",
    "gn:asciiname":"Swiniarsko",
    "gn:country_code":"PL",
    "gn:dem":288,
    "gn:feature_class":"P",
    "gn:feature_code":"PPL",
    "gn:name":"\u015awiniarsko",
    "gn:population":0,
    "gn:timezone":"Europe/Warsaw",
    "iso:country":"PL",
    "name:azb_x_preferred":[
        "\u0634\u0648\u06cc\u0646\u0642\u0627\u0631\u0633\u06a9\u0648"
    ],
    "name:ceb_x_preferred":[
        "\u015awiniarsko"
    ],
    "name:deu_x_preferred":[
        "\u015awiniarsko"
    ],
    "name:fas_x_preferred":[
        "\u0634\u0648\u06cc\u0646\u06af\u0627\u0631\u0633\u06a9\u0648"
    ],
    "name:fra_x_preferred":[
        "\u015awiniarsko"
    ],
    "name:pol_x_preferred":[
        "\u015awiniarsko"
    ],
    "name:szl_x_preferred":[
        "\u015awi\u0144arsko"
    ],
    "name:ukr_x_preferred":[
        "\u0421\u044c\u0432\u0456\u043d\u044f\u0440\u0441\u044c\u043a\u043e"
    ],
    "wof:name":"Swiniarsko",
    "wof:placetype":"locality"
},
  "geometry": {"coordinates":[20.6554,49.60661],"type":"Point"}
}