{
  "type": "Feature",
  "properties": {
    "gn:admin1_code":"77.0",
    "gn:admin2_code":"1208.0",
    "gn:admin3_code":"120805.0",
    "gn:asciiname":"Poradow",
    "gn:country_code":"PL",
    "gn:dem":306,
    "gn:feature_class":"P",
    "gn:feature_code":"PPL",
    "gn:name":"Porad\u00f3w",
    "gn:population":0,
    "gn:timezone":"Europe/Warsaw",
    "iso:country":"PL",
    "name:und_x_variant":[
        "Porad\u00f3w"
    ],
    "wof:name":"Poradow",
    "wof:placetype":"locality"
},
  "geometry": {"coordinates":[20.0438,50.33934],"type":"Point"}
}