{
  "type": "Feature",
  "properties": {
    "gn:admin1_code":"78.0",
    "gn:admin2_code":"1422.0",
    "gn:admin3_code":"142207.0",
    "gn:asciiname":"Kot",
    "gn:country_code":"PL",
    "gn:dem":120,
    "gn:feature_class":"P",
    "gn:feature_code":"PPL",
    "gn:name":"Kot",
    "gn:population":0,
    "gn:timezone":"Europe/Warsaw",
    "iso:country":"PL",
    "name:und_x_variant":[
        "Zakocie",
        "Kot"
    ],
    "wof:name":"Kot",
    "wof:placetype":"locality"
},
  "geometry": {"coordinates":[20.90744,53.07341],"type":"Point"}
}