{
  "type": "Feature",
  "properties": {
    "gn:admin1_code":"78.0",
    "gn:admin2_code":"1412.0",
    "gn:admin3_code":"141214.0",
    "gn:asciiname":"Cisowka",
    "gn:country_code":"PL",
    "gn:dem":122,
    "gn:feature_class":"P",
    "gn:feature_code":"PPL",
    "gn:name":"Cis\u00f3wka",
    "gn:population":0,
    "gn:timezone":"Europe/Warsaw",
    "iso:country":"PL",
    "name:fra_x_preferred":[
        "Cis\u00f3wka"
    ],
    "name:pol_x_preferred":[
        "Cis\u00f3wka"
    ],
    "name:ukr_x_preferred":[
        "\u0426\u0438\u0441\u0443\u0432\u043a\u0430"
    ],
    "wof:name":"Cisowka",
    "wof:placetype":"locality"
},
  "geometry": {"coordinates":[21.45523,52.29666],"type":"Point"}
}