{
  "type": "Feature",
  "properties": {
    "gn:admin1_code":"85.0",
    "gn:admin2_code":"2817.0",
    "gn:admin3_code":"281708.0",
    "gn:asciiname":"Baranowo",
    "gn:cc2":"PL",
    "gn:country_code":"PL",
    "gn:dem":129,
    "gn:feature_class":"P",
    "gn:feature_code":"PPL",
    "gn:name":"Baranowo",
    "gn:population":152,
    "gn:timezone":"Europe/Warsaw",
    "iso:country":"PL",
    "name:ceb_x_preferred":[
        "Baranowo"
    ],
    "name:pol_x_preferred":[
        "Baranowo"
    ],
    "name:ukr_x_preferred":[
        "\u0411\u0430\u0440\u0430\u043d\u043e\u0432\u043e"
    ],
    "name:und_x_variant":[
        "Neufliess",
        "Barranowen",
        "Baranowen",
        "Baranowo"
    ],
    "wof:name":"Baranowo",
    "wof:placetype":"locality",
    "wof:population":152
},
  "geometry": {"coordinates":[20.82725,53.31442],"type":"Point"}
}