{
  "type": "Feature",
  "properties": {
    "gn:admin1_code":"78.0",
    "gn:admin2_code":"1424.0",
    "gn:admin3_code":"142406.0",
    "gn:asciiname":"Poniaty Keczki",
    "gn:country_code":"PL",
    "gn:dem":122,
    "gn:feature_class":"P",
    "gn:feature_code":"PPL",
    "gn:name":"Poniaty Keczki",
    "gn:population":0,
    "gn:timezone":"Europe/Warsaw",
    "iso:country":"PL",
    "wof:name":"Poniaty Keczki",
    "wof:placetype":"locality"
},
  "geometry": {"coordinates":[20.88333,52.61666999999999],"type":"Point"}
}