{
  "type": "Feature",
  "properties": {
    "gn:population":5860,
    "iso:country":"PL",
    "name:azb_x_preferred":[
        "\u0634\u0686\u0631\u06a9"
    ],
    "name:bul_x_preferred":[
        "\u0428\u0447\u0438\u0440\u043a"
    ],
    "name:ces_x_preferred":[
        "Szczyrk"
    ],
    "name:deu_x_preferred":[
        "Szczyrk"
    ],
    "name:eng_x_preferred":[
        "Szczyrk"
    ],
    "name:epo_x_preferred":[
        "Szczyrk"
    ],
    "name:est_x_preferred":[
        "Szczyrk"
    ],
    "name:eus_x_preferred":[
        "Szczyrk"
    ],
    "name:fas_x_preferred":[
        "\u0634\u0686\u0631\u06a9"
    ],
    "name:fin_x_preferred":[
        "Szczyrk"
    ],
    "name:fra_x_preferred":[
        "Szczyrk"
    ],
    "name:heb_x_preferred":[
        "\u05e9\u05e6'\u05d9\u05e8\u05e7"
    ],
    "name:ita_x_preferred":[
        "Szczyrk"
    ],
    "name:jav_x_preferred":[
        "Szczyrk"
    ],
    "name:jpn_x_preferred":[
        "\u30b7\u30c1\u30a3\u30eb\u30af"
    ],
    "name:lav_x_preferred":[
        "\u0160\u010dirka"
    ],
    "name:mkd_x_preferred":[
        "\u0428\u0447\u0438\u0440\u043a"
    ],
    "name:msa_x_preferred":[
        "Szczyrk"
    ],
    "name:nan_x_preferred":[
        "Szczyrk"
    ],
    "name:nld_x_preferred":[
        "Szczyrk"
    ],
    "name:nob_x_preferred":[
        "Szczyrk"
    ],
    "name:nor_x_preferred":[
        "Szczyrk"
    ],
    "name:pol_x_preferred":[
        "Szczyrk"
    ],
    "name:por_x_preferred":[
        "Szczyrk"
    ],
    "name:ron_x_preferred":[
        "Szczyrk"
    ],
    "name:rus_x_preferred":[
        "\u0429\u0438\u0440\u043a"
    ],
    "name:slk_x_preferred":[
        "Szczyrk"
    ],
    "name:spa_x_preferred":[
        "Szczyrk"
    ],
    "name:srp_x_preferred":[
        "\u0428\u0447\u0438\u0440\u043a"
    ],
    "name:swe_x_preferred":[
        "Szczyrk"
    ],
    "name:szl_x_preferred":[
        "Szczyrk"
    ],
    "name:tat_x_preferred":[
        "\u0428\u0447\u044b\u0440\u043a"
    ],
    "name:ukr_x_preferred":[
        "\u0429\u0438\u0440\u043a"
    ],
    "name:vie_x_preferred":[
        "Szczyrk"
    ],
    "name:war_x_preferred":[
        "Szczyrk"
    ],
    "name:zho_min_nan_x_preferred":[
        "Szczyrk"
    ],
    "name:zho_x_preferred":[
        "\u4ec0\u5207\u723e\u514b"
    ],
    "qs:a0":"Rzeczpospolita Polska",
    "qs:a1":"*Slaskie",
    "qs:a1r":"0",
    "qs:a2":"Bielski",
    "qs:adm0":"Rzeczpospolita Polska",
    "qs:la":"Szczyrk",
    "qs:la_lc":"*PL2402011",
    "qs:level":"locality",
    "qs:loc":"Szczyrk",
    "qs:loc_alt":"Szczyrk",
    "qs:pop":0,
    "qs:type":"rural point-in-poly",
    "wd:wordcount":272,
    "wof:coterminous":[
        1125295937
    ],
    "wof:name":"Szczyrk",
    "wof:placetype":"locality",
    "wof:population":5860
},
  "geometry": {"coordinates":[19.016065019166,49.7025490083906],"type":"Point"}
}