{
  "type": "Feature",
  "properties": {
    "gn:admin1_code":"74.0",
    "gn:admin2_code":"1012.0",
    "gn:admin3_code":"101205.0",
    "gn:asciiname":"Barczkowice",
    "gn:country_code":"PL",
    "gn:dem":214,
    "gn:feature_class":"P",
    "gn:feature_code":"PPL",
    "gn:name":"Barczkowice",
    "gn:population":0,
    "gn:timezone":"Europe/Warsaw",
    "iso:country":"PL",
    "name:fra_x_preferred":[
        "Barczkowice"
    ],
    "name:pol_x_preferred":[
        "Barczkowice"
    ],
    "name:ukr_x_preferred":[
        "\u0411\u0430\u0440\u0447\u043a\u043e\u0432\u0456\u0446\u0435"
    ],
    "wof:name":"Barczkowice",
    "wof:placetype":"locality"
},
  "geometry": {"coordinates":[19.51376,51.20238],"type":"Point"}
}