{
  "type": "Feature",
  "properties": {
    "gn:country":"PL",
    "gn:fcode":"PPLA3",
    "gn:population":1248,
    "iso:country":"PL",
    "name:azb_x_preferred":[
        "\u0628\u0631\u0648\u06cc\u062a\u0633\u0647"
    ],
    "name:ceb_x_preferred":[
        "Brojce"
    ],
    "name:fas_x_preferred":[
        "\u0628\u0631\u0648\u06cc\u062a\u0633\u0647"
    ],
    "name:nld_x_preferred":[
        "Brojce"
    ],
    "name:pol_x_preferred":[
        "Brojce"
    ],
    "name:ukr_x_preferred":[
        "\u0411\u0440\u043e\u0439\u0446\u0435"
    ],
    "name:vie_x_preferred":[
        "Brojce"
    ],
    "qs_pg:aaroncc":"PL",
    "qs_pg:gn_country":"PL",
    "qs_pg:gn_fcode":"PPLA3",
    "qs_pg:gn_pop":1248,
    "qs_pg:name":"Brojce",
    "qs_pg:name_adm0":"Polska",
    "qs_pg:name_adm1":"Zachodniopomorskie",
    "qs_pg:photos_9k":1,
    "qs_pg:photos_9r":1,
    "qs_pg:photos_all":2,
    "qs_pg:photos_sr":0,
    "qs_pg:pop_sr":3,
    "qs_pg:qs_pg_placetype":"localadmin",
    "qs_pg:qs_pg_placetype_gp":"LocalAdmin",
    "qs_pg:woe_adm0":23424923,
    "woe:adm0_id":23424923,
    "woe:name_adm0":"Polska",
    "woe:name_adm1":"Zachodniopomorskie",
    "woe:placetype":"LocalAdmin",
    "wof:name":"Brojce",
    "wof:placetype":"localadmin",
    "wof:population":1248
},
  "geometry": {"coordinates":[15.35975,53.95705],"type":"Point"}
}