{
  "type": "Feature",
  "properties": {
    "gn:admin1_code":"78.0",
    "gn:admin2_code":"1403.0",
    "gn:admin3_code":"140314.0",
    "gn:asciiname":"Keblow",
    "gn:country_code":"PL",
    "gn:dem":177,
    "gn:feature_class":"P",
    "gn:feature_code":"PPL",
    "gn:name":"K\u0119b\u0142\u00f3w",
    "gn:population":0,
    "gn:timezone":"Europe/Warsaw",
    "iso:country":"PL",
    "wof:name":"Keblow",
    "wof:placetype":"locality"
},
  "geometry": {"coordinates":[21.86324,51.7917],"type":"Point"}
}