{
  "type": "Feature",
  "properties": {
    "gn:admin1_code":"86.0",
    "gn:admin2_code":"3019.0",
    "gn:admin3_code":"301902.0",
    "gn:asciiname":"Kleszczyna",
    "gn:country_code":"PL",
    "gn:dem":87,
    "gn:feature_class":"P",
    "gn:feature_code":"PPL",
    "gn:name":"Kleszczyna",
    "gn:population":0,
    "gn:timezone":"Europe/Warsaw",
    "iso:country":"PL",
    "name:fra_x_preferred":[
        "Kleszczyna"
    ],
    "name:pol_x_preferred":[
        "Kleszczyna"
    ],
    "name:ukr_x_preferred":[
        "\u041a\u043b\u0435\u0449\u0438\u043d\u0430"
    ],
    "wof:name":"Kleszczyna",
    "wof:placetype":"locality"
},
  "geometry": {"coordinates":[17.11667000000001,53.13333000000001],"type":"Point"}
}