{
  "type": "Feature",
  "properties": {
    "iso:country":"PL",
    "name:azb_x_preferred":[
        "\u0648\u0627\u0648\u0631"
    ],
    "name:ceb_x_preferred":[
        "Wawer"
    ],
    "name:ces_x_preferred":[
        "Wawer"
    ],
    "name:deu_x_preferred":[
        "Wawer"
    ],
    "name:epo_x_preferred":[
        "Wawer"
    ],
    "name:fas_x_preferred":[
        "\u0648\u0627\u0648\u0631"
    ],
    "name:fra_x_preferred":[
        "Wawer"
    ],
    "name:heb_x_preferred":[
        "\u05d5\u05d0\u05d5\u05d5\u05e8"
    ],
    "name:ita_x_preferred":[
        "Wawer"
    ],
    "name:nld_x_preferred":[
        "Wawer"
    ],
    "name:pol_x_preferred":[
        "Wawer"
    ],
    "name:rus_x_preferred":[
        "\u0412\u0430\u0432\u0435\u0440"
    ],
    "name:slk_x_preferred":[
        "Wawer"
    ],
    "name:spa_x_preferred":[
        "Wawer"
    ],
    "name:swe_x_preferred":[
        "Wawer"
    ],
    "name:ukr_x_preferred":[
        "\u0412\u0430\u0432\u0435\u0440"
    ],
    "name:vie_x_preferred":[
        "Wawer"
    ],
    "name:zho_x_preferred":[
        "\u74e6\u6c83\u5340"
    ],
    "wof:name":"Wawer",
    "wof:placetype":"neighbourhood"
},
  "geometry": {"coordinates":[21.14519672138343,52.21970181745348],"type":"Point"}
}