{
  "type": "Feature",
  "properties": {
    "iso:country":"PL",
    "wof:name":"Wawer",
    "wof:placetype":"neighbourhood"
},
  "geometry": {"coordinates":[21.14519672138343,52.21970181745348],"type":"Point"}
}