{
  "type": "Feature",
  "properties": {
    "gn:admin1_code":"73.0",
    "gn:admin2_code":"404.0",
    "gn:admin3_code":"40403.0",
    "gn:asciiname":"Bajerze",
    "gn:country_code":"PL",
    "gn:dem":88,
    "gn:feature_class":"P",
    "gn:feature_code":"PPL",
    "gn:name":"Bajerze",
    "gn:population":0,
    "gn:timezone":"Europe/Warsaw",
    "iso:country":"PL",
    "name:pol_x_preferred":[
        "Bajerze"
    ],
    "name:ukr_x_preferred":[
        "\u0411\u0430\u0454\u0436\u0435"
    ],
    "wof:name":"Bajerze",
    "wof:placetype":"locality"
},
  "geometry": {"coordinates":[18.45873,53.2463],"type":"Point"}
}