{
  "type": "Feature",
  "properties": {
    "gn:admin1_code":"86.0",
    "gn:admin2_code":"3006.0",
    "gn:admin3_code":"300604.0",
    "gn:asciiname":"Lgow",
    "gn:country_code":"PL",
    "gn:dem":73,
    "gn:feature_class":"P",
    "gn:feature_code":"PPL",
    "gn:name":"Lg\u00f3w",
    "gn:population":0,
    "gn:timezone":"Europe/Warsaw",
    "iso:country":"PL",
    "name:und_x_variant":[
        "Lg\u00f3w"
    ],
    "wof:name":"Lgow",
    "wof:placetype":"locality"
},
  "geometry": {"coordinates":[17.53533,52.10333],"type":"Point"}
}