{
  "type": "Feature",
  "properties": {
    "gn:admin1_code":"86.0",
    "gn:admin2_code":"3006.0",
    "gn:admin3_code":"300604.0",
    "gn:asciiname":"Lgow",
    "gn:country_code":"PL",
    "gn:dem":73,
    "gn:feature_class":"P",
    "gn:feature_code":"PPL",
    "gn:name":"Lg\u00f3w",
    "gn:population":0,
    "gn:timezone":"Europe/Warsaw",
    "iso:country":"PL",
    "name:ceb_x_preferred":[
        "Lg\u00f3w"
    ],
    "name:fas_x_preferred":[
        "\u0644\u06af\u0648\u0648"
    ],
    "name:fra_x_preferred":[
        "Lg\u00f3w"
    ],
    "name:pol_x_preferred":[
        "Lg\u00f3w"
    ],
    "name:ukr_x_preferred":[
        "\u041b\u044c\u0491\u0443\u0432"
    ],
    "wof:name":"Lgow",
    "wof:placetype":"locality"
},
  "geometry": {"coordinates":[17.53533,52.10333],"type":"Point"}
}