{
  "type": "Feature",
  "properties": {
    "gn:admin1_code":"72.0",
    "gn:admin2_code":"206.0",
    "gn:admin3_code":"20602.0",
    "gn:asciiname":"Kowary Gorne",
    "gn:country_code":"PL",
    "gn:dem":509,
    "gn:feature_class":"P",
    "gn:feature_code":"PPL",
    "gn:name":"Kowary G\u00f3rne",
    "gn:population":0,
    "gn:timezone":"Europe/Warsaw",
    "iso:country":"PL",
    "wof:name":"Kowary Gorne",
    "wof:placetype":"neighbourhood"
},
  "geometry": {"coordinates":[15.85,50.78333],"type":"Point"}
}