{
  "type": "Feature",
  "properties": {
    "gn:admin1_code":"82.0",
    "gn:admin2_code":"2205.0",
    "gn:admin3_code":"220507.0",
    "gn:asciiname":"Msciszewice",
    "gn:country_code":"PL",
    "gn:dem":208,
    "gn:feature_class":"P",
    "gn:feature_code":"PPL",
    "gn:name":"M\u015bciszewice",
    "gn:population":0,
    "gn:timezone":"Europe/Warsaw",
    "iso:country":"PL",
    "name:azb_x_preferred":[
        "\u0645\u0634\u0686\u06cc\u0634\u0648\u06cc\u062a\u0633\u0647"
    ],
    "name:ceb_x_preferred":[
        "M\u015bciszewice"
    ],
    "name:csb_x_preferred":[
        "Msc\u00ebszejce"
    ],
    "name:fas_x_preferred":[
        "\u0645\u0634\u0686\u06cc\u0634\u0648\u06cc\u062a\u0633\u0647"
    ],
    "name:nld_x_preferred":[
        "M\u015bciszewice"
    ],
    "name:pol_x_preferred":[
        "M\u015bciszewice"
    ],
    "name:ukr_x_preferred":[
        "\u041c\u0441\u0446\u0438\u0448\u0435\u0432\u0456\u0446\u0435"
    ],
    "name:und_x_variant":[
        "M\u015bciszewice"
    ],
    "wof:name":"Msciszewice",
    "wof:placetype":"locality"
},
  "geometry": {"coordinates":[17.85473,54.26158],"type":"Point"}
}