{
  "type": "Feature",
  "properties": {
    "gn:admin1_code":"73.0",
    "gn:admin2_code":"412.0",
    "gn:admin3_code":"41203.0",
    "gn:asciiname":"Wierzchowiska",
    "gn:country_code":"PL",
    "gn:dem":128,
    "gn:feature_class":"P",
    "gn:feature_code":"PPL",
    "gn:name":"Wierzchowiska",
    "gn:population":0,
    "gn:timezone":"Europe/Warsaw",
    "iso:country":"PL",
    "wof:name":"Wierzchowiska",
    "wof:placetype":"locality"
},
  "geometry": {"coordinates":[19.43877,52.9525],"type":"Point"}
}