{
  "type": "Feature",
  "properties": {
    "gn:admin1_code":"73.0",
    "gn:admin2_code":"412.0",
    "gn:admin3_code":"41203.0",
    "gn:asciiname":"Wierzchowiska",
    "gn:country_code":"PL",
    "gn:dem":128,
    "gn:feature_class":"P",
    "gn:feature_code":"PPL",
    "gn:name":"Wierzchowiska",
    "gn:population":0,
    "gn:timezone":"Europe/Warsaw",
    "iso:country":"PL",
    "name:pol_x_preferred":[
        "Wierzchowiska"
    ],
    "name:ukr_x_preferred":[
        "\u0412\u0435\u0436\u0445\u043e\u0432\u0438\u0441\u044c\u043a\u0430"
    ],
    "wof:name":"Wierzchowiska",
    "wof:placetype":"locality"
},
  "geometry": {"coordinates":[19.43877,52.9525],"type":"Point"}
}