{
  "type": "Feature",
  "properties": {
    "gn:gn_country":"PL",
    "gn:gn_fcode":"PPLA3",
    "gn:gn_pop":2110,
    "gn:population":2110,
    "iso:country":"PL",
    "name:eng_x_preferred":[
        "S\u0142ubice"
    ],
    "name:eng_x_variant":[
        "Gmina S\u0142ubice"
    ],
    "name:rus_x_preferred":[
        "\u0421\u043b\u0443\u0431\u0438\u0446\u0435"
    ],
    "name:slk_x_preferred":[
        "Gmina S\u0142ubice"
    ],
    "name:ukr_x_preferred":[
        "\u0490\u043c\u0456\u043d\u0430 \u0421\u043b\u0443\u0431\u0456\u0446\u0435"
    ],
    "name:war_x_preferred":[
        "Gmina S\u0142ubice"
    ],
    "qs_pg:aaroncc":"PL",
    "qs_pg:gn_country":"PL",
    "qs_pg:gn_fcode":"PPLA3",
    "qs_pg:gn_pop":2110,
    "qs_pg:name":"S\u0142ubice",
    "qs_pg:name_adm0":"Polska",
    "qs_pg:name_adm1":"Mazowieckie",
    "qs_pg:photos":1,
    "qs_pg:photos_1k":1,
    "qs_pg:photos_9k":1,
    "qs_pg:photos_9r":1,
    "qs_pg:photos_all":1,
    "qs_pg:photos_sr":1,
    "qs_pg:pop_sr":4,
    "qs_pg:qs_pg_placetype":"localadmin",
    "qs_pg:qs_pg_placetype_gp":"LocalAdmin",
    "qs_pg:woe_adm0":23424923,
    "woe:adm0_id":23424923,
    "woe:name_adm0":"Polska",
    "woe:name_adm1":"Mazowieckie",
    "woe:placetype":"LocalAdmin",
    "wof:name":"S\u0142ubice",
    "wof:placetype":"localadmin",
    "wof:population":2110
},
  "geometry": {"coordinates":[19.93881,52.36942],"type":"Point"}
}