{
  "type": "Feature",
  "properties": {
    "iso:country":"PL",
    "name:pol_x_preferred":[
        "Gorzk\u00f3w"
    ],
    "wof:coterminous":[
        1125385759
    ],
    "wof:name":"Gorzk\u00f3w",
    "wof:placetype":"locality"
},
  "geometry": {"coordinates":[22.9727845411159,50.9537965089555],"type":"Point"}
}