{
  "type": "Feature",
  "properties": {
    "gn:admin1_code":"78.0",
    "gn:admin2_code":"1426.0",
    "gn:admin3_code":"142613.0",
    "gn:asciiname":"Izdebki Blazeje",
    "gn:country_code":"PL",
    "gn:dem":157,
    "gn:feature_class":"P",
    "gn:feature_code":"PPL",
    "gn:name":"Izdebki B\u0142a\u017ceje",
    "gn:population":0,
    "gn:timezone":"Europe/Warsaw",
    "iso:country":"PL",
    "name:azb_x_preferred":[
        "\u0627\u06cc\u0632\u062f\u0628\u06a9\u06cc-\u0628\u0648\u0627\u0698\u06cc\u0647"
    ],
    "name:fas_x_preferred":[
        "\u0627\u06cc\u0632\u062f\u0628\u06a9\u06cc-\u0628\u0648\u0627\u0698\u06cc\u0647"
    ],
    "name:fra_x_preferred":[
        "Izdebki-B\u0142a\u017ceje"
    ],
    "name:pol_x_preferred":[
        "Izdebki-B\u0142a\u017ceje"
    ],
    "name:ukr_x_preferred":[
        "\u0406\u0437\u0434\u0435\u0431\u043a\u0456-\u0411\u043b\u0430\u0436\u0435\u0454"
    ],
    "wof:name":"Izdebki Blazeje",
    "wof:placetype":"locality"
},
  "geometry": {"coordinates":[22.59029,52.10998],"type":"Point"}
}