{
  "type": "Feature",
  "properties": {
    "gn:admin1_code":"75.0",
    "gn:admin2_code":"601.0",
    "gn:admin3_code":"60105.0",
    "gn:asciiname":"Jakowki",
    "gn:country_code":"PL",
    "gn:dem":140,
    "gn:feature_class":"P",
    "gn:feature_code":"PPL",
    "gn:name":"Jak\u00f3wki",
    "gn:population":0,
    "gn:timezone":"Europe/Warsaw",
    "iso:country":"PL",
    "name:azb_x_preferred":[
        "\u06cc\u0627\u06a9\u0648\u0648\u06a9\u06cc"
    ],
    "name:ceb_x_preferred":[
        "Jak\u00f3wki"
    ],
    "name:fas_x_preferred":[
        "\u06cc\u0627\u06a9\u0648\u0648\u06a9\u06cc"
    ],
    "name:fra_x_preferred":[
        "Jak\u00f3wki"
    ],
    "name:lit_x_preferred":[
        "Jakuvkai"
    ],
    "name:pol_x_preferred":[
        "Jak\u00f3wki"
    ],
    "name:ukr_x_preferred":[
        "\u042f\u043a\u0443\u0432\u043a\u0456"
    ],
    "name:urd_x_preferred":[
        "\u062c\u0627\u06a9\u0648\u0648\u06a9\u06cc"
    ],
    "wof:name":"Jakowki",
    "wof:placetype":"locality"
},
  "geometry": {"coordinates":[23.13189,52.19803],"type":"Point"}
}