{
  "type": "Feature",
  "properties": {
    "gn:admin1_code":"78.0",
    "gn:admin2_code":"1417.0",
    "gn:admin3_code":"141708.0",
    "gn:asciiname":"Dziechciniec",
    "gn:country_code":"PL",
    "gn:dem":115,
    "gn:feature_class":"P",
    "gn:feature_code":"PPL",
    "gn:name":"Dziechciniec",
    "gn:population":0,
    "gn:timezone":"Europe/Warsaw",
    "iso:country":"PL",
    "name:azb_x_preferred":[
        "\u062c\u062e\u0686\u06cc\u0646\u0642\u062a\u0633"
    ],
    "name:ceb_x_preferred":[
        "Dziechciniec"
    ],
    "name:fas_x_preferred":[
        "\u062c\u062e\u0686\u06cc\u0646\u06af\u062a\u0633"
    ],
    "name:fra_x_preferred":[
        "Dziechciniec"
    ],
    "name:nld_x_preferred":[
        "Dziechciniec"
    ],
    "name:pol_x_preferred":[
        "Dziechciniec"
    ],
    "name:ukr_x_preferred":[
        "\u0414\u0437\u0435\u0445\u0446\u0438\u043d\u0435\u0446\u044c"
    ],
    "wof:name":"Dziechciniec",
    "wof:placetype":"locality"
},
  "geometry": {"coordinates":[21.35528,52.14919],"type":"Point"}
}