{
  "type": "Feature",
  "properties": {
    "gn:admin1_code":"78.0",
    "gn:admin2_code":"1417.0",
    "gn:admin3_code":"141708.0",
    "gn:asciiname":"Dziechciniec",
    "gn:country_code":"PL",
    "gn:dem":115,
    "gn:feature_class":"P",
    "gn:feature_code":"PPL",
    "gn:name":"Dziechciniec",
    "gn:population":0,
    "gn:timezone":"Europe/Warsaw",
    "iso:country":"PL",
    "wof:name":"Dziechciniec",
    "wof:placetype":"locality"
},
  "geometry": {"coordinates":[21.35528,52.14919],"type":"Point"}
}