{
  "type": "Feature",
  "properties": {
    "gn:admin1_code":"78.0",
    "gn:admin2_code":"1426.0",
    "gn:admin3_code":"142606.0",
    "gn:asciiname":"Pliszki",
    "gn:country_code":"PL",
    "gn:dem":168,
    "gn:feature_class":"P",
    "gn:feature_code":"PPL",
    "gn:name":"Pliszki",
    "gn:population":0,
    "gn:timezone":"Europe/Warsaw",
    "iso:country":"PL",
    "name:azb_x_preferred":[
        "\u067e\u0644\u06cc\u0634\u06a9\u06cc"
    ],
    "name:fas_x_preferred":[
        "\u067e\u0644\u06cc\u0634\u06a9\u06cc"
    ],
    "name:fra_x_preferred":[
        "Pliszki"
    ],
    "name:lit_x_preferred":[
        "Pli\u0161kai"
    ],
    "name:pol_x_preferred":[
        "Pliszki"
    ],
    "name:szl_x_preferred":[
        "Pliszki"
    ],
    "name:ukr_x_preferred":[
        "\u041f\u043b\u0456\u0448\u043a\u0456"
    ],
    "wof:name":"Pliszki",
    "wof:placetype":"locality"
},
  "geometry": {"coordinates":[22.51545,52.26895],"type":"Point"}
}