{
  "type": "Feature",
  "properties": {
    "gn:admin1_code":"74.0",
    "gn:admin2_code":"1004.0",
    "gn:admin3_code":"100408.0",
    "gn:asciiname":"Rybitwy",
    "gn:country_code":"PL",
    "gn:dem":117,
    "gn:feature_class":"P",
    "gn:feature_code":"PPL",
    "gn:name":"Rybitwy",
    "gn:population":0,
    "gn:timezone":"Europe/Warsaw",
    "iso:country":"PL",
    "wof:name":"Rybitwy",
    "wof:placetype":"locality"
},
  "geometry": {"coordinates":[19.27335,52.10751],"type":"Point"}
}