{
  "type": "Feature",
  "properties": {
    "gn:admin1_code":"81.0",
    "gn:admin2_code":"2061.0",
    "gn:admin3_code":"206101.0",
    "gn:asciiname":"Starosielce",
    "gn:country_code":"PL",
    "gn:dem":140,
    "gn:feature_class":"P",
    "gn:feature_code":"PPL",
    "gn:name":"Starosielce",
    "gn:population":0,
    "gn:timezone":"Europe/Warsaw",
    "iso:country":"PL",
    "name:und_x_variant":[
        "Bialystok Starosielce",
        "Starosielce"
    ],
    "wof:name":"Starosielce",
    "wof:placetype":"neighbourhood"
},
  "geometry": {"coordinates":[23.08005,53.12099],"type":"Point"}
}