{
  "type": "Feature",
  "properties": {
    "gn:population":1737,
    "iso:country":"PL",
    "name:azb_x_preferred":[
        "\u0642\u0645\u06cc\u0646\u0627 \u0628\u0631\u0648\u062f\u0647"
    ],
    "name:ceb_x_preferred":[
        "Brody"
    ],
    "name:eng_x_preferred":[
        "Gmina Brody"
    ],
    "name:eus_x_preferred":[
        "Brody udalerria"
    ],
    "name:fas_x_preferred":[
        "\u06af\u0645\u06cc\u0646\u0627 \u0628\u0631\u0648\u062f\u0647"
    ],
    "name:fra_x_preferred":[
        "Brody"
    ],
    "name:ind_x_preferred":[
        "Gmina Brody"
    ],
    "name:ita_x_preferred":[
        "Brody"
    ],
    "name:nld_x_preferred":[
        "Brody"
    ],
    "name:pol_x_preferred":[
        "Brody"
    ],
    "name:rus_x_preferred":[
        "\u0411\u0440\u043e\u0434\u044b"
    ],
    "name:slk_x_preferred":[
        "Gmina Brody"
    ],
    "name:swe_x_preferred":[
        "Brody kommun"
    ],
    "name:ukr_x_preferred":[
        "\u0490\u043c\u0456\u043d\u0430 \u0411\u0440\u043e\u0434\u0438"
    ],
    "name:war_x_preferred":[
        "Gmina Brody"
    ],
    "qs:a0":"Rzeczpospolita Polska",
    "qs:a1":"*Swietokrzyskie",
    "qs:a1r":"0",
    "qs:a2":"Starachowicki",
    "qs:adm0":"Rzeczpospolita Polska",
    "qs:la":"Brody",
    "qs:la_lc":"*PL2611022",
    "qs:level":"locality",
    "qs:loc":"Brody",
    "qs:loc_alt":"Brody",
    "qs:pop":0,
    "qs:type":"rural point-in-poly",
    "wd:wordcount":134,
    "wof:coterminous":[
        1125363455
    ],
    "wof:name":"Brody",
    "wof:placetype":"locality",
    "wof:population":1737
},
  "geometry": {"coordinates":[21.2416676064433,51.0389761882768],"type":"Point"}
}