{
  "type": "Feature",
  "properties": {
    "gn:admin1_code":"78.0",
    "gn:admin2_code":"1416.0",
    "gn:admin3_code":"141607.0",
    "gn:asciiname":"Budy Grudzie",
    "gn:country_code":"PL",
    "gn:dem":124,
    "gn:feature_class":"P",
    "gn:feature_code":"PPL",
    "gn:name":"Budy Grudzie",
    "gn:population":0,
    "gn:timezone":"Europe/Warsaw",
    "iso:country":"PL",
    "name:ceb_x_preferred":[
        "Budy-Grudzie"
    ],
    "name:fra_x_preferred":[
        "Budy-Grudzie"
    ],
    "name:pol_x_preferred":[
        "Budy-Grudzie"
    ],
    "name:ukr_x_preferred":[
        "\u0411\u0443\u0434\u0438-\u0490\u0440\u0443\u0434\u0437\u0435"
    ],
    "name:und_x_variant":[
        "Grudzie",
        "Budy-Grodzie",
        "Budy Grudzie"
    ],
    "wof:name":"Budy Grudzie",
    "wof:placetype":"locality"
},
  "geometry": {"coordinates":[21.94666,52.85111],"type":"Point"}
}