{
  "type": "Feature",
  "properties": {
    "gn:admin1_code":"78.0",
    "gn:admin2_code":"1429.0",
    "gn:admin3_code":"142906.0",
    "gn:asciiname":"Wierzbice Gorne",
    "gn:country_code":"PL",
    "gn:dem":148,
    "gn:feature_class":"P",
    "gn:feature_code":"PPL",
    "gn:name":"Wierzbice G\u00f3rne",
    "gn:population":0,
    "gn:timezone":"Europe/Warsaw",
    "iso:country":"PL",
    "name:fra_x_preferred":[
        "Wierzbice G\u00f3rne"
    ],
    "name:lit_x_preferred":[
        "Ve\u017ebice Gurn\u0117"
    ],
    "name:pol_x_preferred":[
        "Wierzbice G\u00f3rne"
    ],
    "name:ukr_x_preferred":[
        "\u0412\u0435\u0436\u0431\u0456\u0446\u0435-\u0490\u0443\u0440\u043d\u0435"
    ],
    "name:und_x_variant":[
        "Wierzbie G\u00f3rne"
    ],
    "wof:name":"Wierzbice Gorne",
    "wof:placetype":"locality"
},
  "geometry": {"coordinates":[22.45751,52.38272],"type":"Point"}
}