{
  "type": "Feature",
  "properties": {
    "gn:admin1_code":"79.0",
    "gn:admin2_code":"1602.0",
    "gn:admin3_code":"160201.0",
    "gn:asciiname":"Sulkow",
    "gn:country_code":"PL",
    "gn:dem":237,
    "gn:feature_class":"P",
    "gn:feature_code":"PPL",
    "gn:name":"Su\u0142k\u00f3w",
    "gn:population":0,
    "gn:timezone":"Europe/Warsaw",
    "iso:country":"PL",
    "name:pol_x_preferred":[
        "Su\u0142k\u00f3w"
    ],
    "name:szl_x_preferred":[
        "Sulk\u016fw"
    ],
    "name:ukr_x_preferred":[
        "\u0421\u0443\u043b\u043a\u0443\u0432"
    ],
    "wof:name":"Sulkow",
    "wof:placetype":"locality"
},
  "geometry": {"coordinates":[17.95286,50.16392000000001],"type":"Point"}
}