{
  "type": "Feature",
  "properties": {
    "gn:admin1_code":"74.0",
    "gn:admin2_code":"1014.0",
    "gn:admin3_code":"101402.0",
    "gn:asciiname":"Naceslawice",
    "gn:country_code":"PL",
    "gn:dem":138,
    "gn:feature_class":"P",
    "gn:feature_code":"PPL",
    "gn:name":"Naces\u0142awice",
    "gn:population":0,
    "gn:timezone":"Europe/Warsaw",
    "iso:country":"PL",
    "name:pol_x_preferred":[
        "Naces\u0142awice"
    ],
    "name:ukr_x_preferred":[
        "\u041d\u0430\u0446\u0435\u0441\u043b\u0430\u0432\u0456\u0446\u0435"
    ],
    "wof:name":"Naceslawice",
    "wof:placetype":"locality"
},
  "geometry": {"coordinates":[18.42948,51.72995],"type":"Point"}
}