{
  "type": "Feature",
  "properties": {
    "gn:admin1_code":"86.0",
    "gn:admin2_code":"3028.0",
    "gn:admin3_code":"302805.0",
    "gn:asciiname":"Roscinno",
    "gn:country_code":"PL",
    "gn:dem":89,
    "gn:feature_class":"P",
    "gn:feature_code":"PPL",
    "gn:name":"Ro\u015bcinno",
    "gn:population":0,
    "gn:timezone":"Europe/Warsaw",
    "iso:country":"PL",
    "name:fra_x_preferred":[
        "Ro\u015bcinno"
    ],
    "name:pol_x_preferred":[
        "Ro\u015bcinno"
    ],
    "name:ukr_x_preferred":[
        "\u0420\u043e\u0441\u0446\u0438\u043d\u043d\u043e"
    ],
    "name:und_x_variant":[
        "Ro\u015bcinno"
    ],
    "wof:name":"Roscinno",
    "wof:placetype":"locality"
},
  "geometry": {"coordinates":[17.13832,52.68997],"type":"Point"}
}