{
  "type": "Feature",
  "properties": {
    "gn:admin1_code":"87.0",
    "gn:admin2_code":"3207.0",
    "gn:admin3_code":"320706.0",
    "gn:asciiname":"Jarzebowo",
    "gn:country_code":"PL",
    "gn:dem":5,
    "gn:feature_class":"P",
    "gn:feature_code":"PPL",
    "gn:name":"Jarz\u0119bowo",
    "gn:population":0,
    "gn:timezone":"Europe/Warsaw",
    "iso:country":"PL",
    "name:azb_x_preferred":[
        "\u06cc\u0627\u0698\u0646\u0628\u0648\u0648\u0648"
    ],
    "name:fas_x_preferred":[
        "\u06cc\u0627\u0698\u0646\u0628\u0648\u0648\u0648"
    ],
    "name:nld_x_preferred":[
        "Jarz\u0119bowo"
    ],
    "name:pol_x_preferred":[
        "Jarz\u0119bowo"
    ],
    "name:ukr_x_preferred":[
        "\u042f\u0436\u0435\u043c\u0431\u043e\u0432\u043e"
    ],
    "name:urd_x_preferred":[
        "\u062c\u0631\u0632\u06cc\u0628\u0648\u0648"
    ],
    "name:vie_x_preferred":[
        "Jarz\u0119bowo"
    ],
    "wof:name":"Jarzebowo",
    "wof:placetype":"locality"
},
  "geometry": {"coordinates":[14.64563,53.9097],"type":"Point"}
}