{
  "type": "Feature",
  "properties": {
    "gn:admin1_code":"86.0",
    "gn:admin2_code":"3010.0",
    "gn:admin3_code":"301003.0",
    "gn:asciiname":"Stefanowo",
    "gn:country_code":"PL",
    "gn:dem":101,
    "gn:feature_class":"P",
    "gn:feature_code":"PPL",
    "gn:name":"Stefanowo",
    "gn:population":0,
    "gn:timezone":"Europe/Warsaw",
    "iso:country":"PL",
    "name:fra_x_preferred":[
        "Stefanowo"
    ],
    "wof:name":"Stefanowo",
    "wof:placetype":"locality"
},
  "geometry": {"coordinates":[18.12178,52.34698],"type":"Point"}
}