{
  "type": "Feature",
  "properties": {
    "gn:admin1_code":"78.0",
    "gn:admin2_code":"1432.0",
    "gn:admin3_code":"143204.0",
    "gn:asciiname":"Kepiaste",
    "gn:country_code":"PL",
    "gn:dem":86,
    "gn:feature_class":"P",
    "gn:feature_code":"PPL",
    "gn:name":"K\u0119piaste",
    "gn:population":0,
    "gn:timezone":"Europe/Warsaw",
    "iso:country":"PL",
    "name:ceb_x_preferred":[
        "K\u0119piaste"
    ],
    "name:fra_x_preferred":[
        "K\u0119piaste"
    ],
    "name:pol_x_preferred":[
        "K\u0119piaste"
    ],
    "name:ukr_x_preferred":[
        "\u041a\u0435\u043c\u043f\u044f\u0441\u0442\u0435"
    ],
    "wof:name":"Kepiaste",
    "wof:placetype":"locality"
},
  "geometry": {"coordinates":[20.60048,52.28407],"type":"Point"}
}