{
  "type": "Feature",
  "properties": {
    "gn:admin1_code":"78.0",
    "gn:admin2_code":"1415.0",
    "gn:admin3_code":"141503.0",
    "gn:asciiname":"Zochy Milen",
    "gn:country_code":"PL",
    "gn:dem":111,
    "gn:feature_class":"P",
    "gn:feature_code":"PPL",
    "gn:name":"\u017bochy Milen",
    "gn:population":0,
    "gn:timezone":"Europe/Warsaw",
    "iso:country":"PL",
    "name:und_x_variant":[
        "\u017bochy Milan",
        "Zochy",
        "\u017bochy Milen"
    ],
    "wof:name":"Zochy Milen",
    "wof:placetype":"locality"
},
  "geometry": {"coordinates":[21.82631,52.97057],"type":"Point"}
}