{
  "type": "Feature",
  "properties": {
    "gn:population":4364,
    "iso:country":"PL",
    "name:ces_x_preferred":[
        "Zawid\u00f3w"
    ],
    "name:deu_x_preferred":[
        "Zawid\u00f3w"
    ],
    "name:eng_x_preferred":[
        "Zawid\u00f3w"
    ],
    "name:epo_x_preferred":[
        "Zawid\u00f3w"
    ],
    "name:eus_x_preferred":[
        "Zawid\u00f3w"
    ],
    "name:fra_x_preferred":[
        "Zawid\u00f3w"
    ],
    "name:hsb_x_preferred":[
        "Zawidow"
    ],
    "name:ita_x_preferred":[
        "Zawid\u00f3w"
    ],
    "name:jav_x_preferred":[
        "Zawid\u00f3w"
    ],
    "name:lav_x_preferred":[
        "Zavidova"
    ],
    "name:msa_x_preferred":[
        "Zawid\u00f3w"
    ],
    "name:nan_x_preferred":[
        "Zawid\u00f3w"
    ],
    "name:nld_x_preferred":[
        "Zawid\u00f3w"
    ],
    "name:pol_x_preferred":[
        "Zawid\u00f3w"
    ],
    "name:por_x_preferred":[
        "Zawid\u00f3w"
    ],
    "name:ron_x_preferred":[
        "Zawid\u00f3w"
    ],
    "name:rus_x_preferred":[
        "\u0417\u0430\u0432\u0438\u0434\u0443\u0432"
    ],
    "name:slk_x_preferred":[
        "Zawid\u00f3w"
    ],
    "name:srp_x_preferred":[
        "\u0417\u0430\u0432\u0438\u0434\u043e\u0432"
    ],
    "name:swe_x_preferred":[
        "Zawid\u00f3w"
    ],
    "name:tat_x_preferred":[
        "\u0417\u0430\u0432\u0438\u0434\u0443\u0432"
    ],
    "name:ukr_x_preferred":[
        "\u0417\u0430\u0432\u0456\u0434\u0443\u0432"
    ],
    "name:und_x_variant":[
        "Seidenberg"
    ],
    "name:vie_x_preferred":[
        "Zawid\u00f3w"
    ],
    "name:war_x_preferred":[
        "Zawid\u00f3w"
    ],
    "name:zho_x_preferred":[
        "\u624e\u7dad\u675c\u592b"
    ],
    "qs:a0":"Rzeczpospolita Polska",
    "qs:a1":"*Dolnoslaskie",
    "qs:a1r":"0",
    "qs:a2":"Zgorzelecki",
    "qs:adm0":"Rzeczpospolita Polska",
    "qs:la":"Sulik\u00f3w",
    "qs:la_lc":"*PL0225052",
    "qs:level":"locality",
    "qs:loc":"Zawid\u00f3w",
    "qs:loc_alt":"Zawidow",
    "qs:pop":0,
    "qs:type":"rural point-in-poly",
    "wd:wordcount":93,
    "wof:coterminous":[
        1477752261
    ],
    "wof:name":"Zawid\u00f3w",
    "wof:placetype":"locality",
    "wof:population":4364
},
  "geometry": {"coordinates":[15.0458395214776,51.0240841745019],"type":"Point"}
}