{
  "type": "Feature",
  "properties": {
    "gn:country":"PL",
    "gn:fcode":"PPL",
    "gn:population":526,
    "iso:country":"PL",
    "name:ast_x_preferred":[
        "Nieboczowy"
    ],
    "name:eng_x_preferred":[
        "Nieboczowy"
    ],
    "name:fra_x_preferred":[
        "Nieboczowy"
    ],
    "name:pol_x_preferred":[
        "Nieboczowy"
    ],
    "qs_pg:aaroncc":"PL",
    "qs_pg:gn_country":"PL",
    "qs_pg:gn_fcode":"PPL",
    "qs_pg:gn_pop":526,
    "qs_pg:name":"Nieboczowy",
    "qs_pg:name_adm0":"Polska",
    "qs_pg:name_adm1":"Sl\u0105skie",
    "qs_pg:photos_9r":0,
    "qs_pg:photos_sr":0,
    "qs_pg:pop_sr":2,
    "qs_pg:qs_pg_placetype":"locality",
    "qs_pg:qs_pg_placetype_gp":"Town",
    "qs_pg:woe_adm0":23424923,
    "woe:adm0_id":23424923,
    "woe:name_adm0":"Polska",
    "woe:name_adm1":"Sl\u0105skie",
    "woe:placetype":"Town",
    "wof:name":"Nieboczowy",
    "wof:placetype":"locality",
    "wof:population":526
},
  "geometry": {"coordinates":[18.25928,50.04364],"type":"Point"}
}