{
  "type": "Feature",
  "properties": {
    "gn:admin1_code":"74.0",
    "gn:admin2_code":"1011.0",
    "gn:admin3_code":"101103.0",
    "gn:asciiname":"Baldrzychowska Gora",
    "gn:cc2":"PL",
    "gn:country_code":"PL",
    "gn:dem":125,
    "gn:feature_class":"P",
    "gn:feature_code":"PPL",
    "gn:name":"Ba\u0142drzychowska G\u00f3ra",
    "gn:population":0,
    "gn:timezone":"Europe/Warsaw",
    "iso:country":"PL",
    "name:und_x_variant":[
        "G\u00f3ra Ba\u0142drzych\u00f3wska",
        "Ba\u0142drzychowska G\u00f3ra"
    ],
    "wof:name":"Baldrzychowska Gora",
    "wof:placetype":"locality"
},
  "geometry": {"coordinates":[18.97116,51.84866],"type":"Point"}
}