{
  "type": "Feature",
  "properties": {
    "gn:admin1_code":"81.0",
    "gn:admin2_code":"2010.0",
    "gn:admin3_code":"201004.0",
    "gn:asciiname":"Stadniki",
    "gn:country_code":"PL",
    "gn:dem":154,
    "gn:feature_class":"P",
    "gn:feature_code":"PPL",
    "gn:name":"Stadniki",
    "gn:population":0,
    "gn:timezone":"Europe/Warsaw",
    "iso:country":"PL",
    "name:ceb_x_preferred":[
        "Stadniki"
    ],
    "name:lit_x_preferred":[
        "Stadnikai"
    ],
    "name:pol_x_preferred":[
        "Stadniki"
    ],
    "name:ukr_x_preferred":[
        "\u0421\u0442\u0430\u0434\u043d\u0438\u043a\u0438"
    ],
    "wof:name":"Stadniki",
    "wof:placetype":"locality"
},
  "geometry": {"coordinates":[22.71567000000001,52.52526],"type":"Point"}
}