{
  "type": "Feature",
  "properties": {
    "gn:admin1_code":"80.0",
    "gn:admin2_code":"1811.0",
    "gn:admin3_code":"181110.0",
    "gn:asciiname":"Bor",
    "gn:country_code":"PL",
    "gn:dem":165,
    "gn:feature_class":"P",
    "gn:feature_code":"PPL",
    "gn:name":"B\u00f3r",
    "gn:population":0,
    "gn:timezone":"Europe/Warsaw",
    "iso:country":"PL",
    "name:bel_x_preferred":[
        "\u0411\u043e\u0440"
    ],
    "name:bos_x_preferred":[
        "Bor"
    ],
    "name:bul_x_preferred":[
        "\u0411\u043e\u0440"
    ],
    "name:cat_x_preferred":[
        "Bor"
    ],
    "name:ceb_x_preferred":[
        "Bor"
    ],
    "name:ces_x_preferred":[
        "Bor"
    ],
    "name:dan_x_preferred":[
        "Bor"
    ],
    "name:deu_x_preferred":[
        "Bor"
    ],
    "name:fin_x_preferred":[
        "Bor"
    ],
    "name:fra_x_preferred":[
        "Bor"
    ],
    "name:frr_x_preferred":[
        "Bor"
    ],
    "name:heb_x_preferred":[
        "\u05d1\u05d5\u05e8"
    ],
    "name:hrv_x_preferred":[
        "Bor"
    ],
    "name:hun_x_preferred":[
        "Bor"
    ],
    "name:hye_x_preferred":[
        "\u0532\u0578\u0580"
    ],
    "name:kaz_x_preferred":[
        "\u0411\u043e\u0440"
    ],
    "name:mkd_x_preferred":[
        "\u0411\u043e\u0440"
    ],
    "name:myv_x_preferred":[
        "\u041a\u0430\u043b\u0433\u043e\u0434\u043e \u043c\u0430\u0440\u044c"
    ],
    "name:nds_x_preferred":[
        "Bor"
    ],
    "name:nld_x_preferred":[
        "Bor"
    ],
    "name:nno_x_preferred":[
        "Bor"
    ],
    "name:nor_x_preferred":[
        "Bor"
    ],
    "name:oci_x_preferred":[
        "Bor"
    ],
    "name:pol_x_preferred":[
        "Bor"
    ],
    "name:por_x_preferred":[
        "Bor"
    ],
    "name:ron_x_preferred":[
        "Bor"
    ],
    "name:rus_x_preferred":[
        "\u0411\u043e\u0440"
    ],
    "name:sco_x_preferred":[
        "Bor"
    ],
    "name:slk_x_preferred":[
        "Bor"
    ],
    "name:slv_x_preferred":[
        "Bor"
    ],
    "name:spa_x_preferred":[
        "Bor"
    ],
    "name:srp_x_preferred":[
        "\u0411\u043e\u0440"
    ],
    "name:swe_x_preferred":[
        "Bor"
    ],
    "name:tur_x_preferred":[
        "Bor"
    ],
    "name:ukr_x_preferred":[
        "\u0411\u043e\u0440"
    ],
    "name:vep_x_preferred":[
        "Bor"
    ],
    "wof:name":"Bor",
    "wof:placetype":"locality"
},
  "geometry": {"coordinates":[21.1961,50.25582],"type":"Point"}
}