{
  "type": "Feature",
  "properties": {
    "gn:admin1_code":"73.0",
    "gn:admin2_code":"418.0",
    "gn:admin3_code":"41807.0",
    "gn:asciiname":"Cyprianka",
    "gn:country_code":"PL",
    "gn:dem":93,
    "gn:feature_class":"P",
    "gn:feature_code":"PPL",
    "gn:name":"Cyprianka",
    "gn:population":0,
    "gn:timezone":"Europe/Warsaw",
    "iso:country":"PL",
    "name:eng_x_preferred":[
        "Cyprianka"
    ],
    "name:rus_x_preferred":[
        "\u0426\u044b\u043f\u0440\u044f\u043d\u043a\u0430"
    ],
    "name:und_x_variant":[
        "Cyprjanka",
        "Cyprianka"
    ],
    "wof:name":"Cyprianka",
    "wof:placetype":"locality"
},
  "geometry": {"coordinates":[19.10285,52.73446],"type":"Point"}
}