{
  "type": "Feature",
  "properties": {
    "gn:admin1_code":"82.0",
    "gn:admin2_code":"2204.0",
    "gn:admin3_code":"220405.0",
    "gn:asciiname":"Zabrsko Gorne",
    "gn:country_code":"PL",
    "gn:dem":229,
    "gn:feature_class":"P",
    "gn:feature_code":"PPL",
    "gn:name":"Z\u0105brsko G\u00f3rne",
    "gn:population":0,
    "gn:timezone":"Europe/Warsaw",
    "iso:country":"PL",
    "name:und_x_variant":[
        "Ober Sommerkau",
        "Z\u0105brsko G\u00f3rne"
    ],
    "wof:name":"Zabrsko Gorne",
    "wof:placetype":"locality"
},
  "geometry": {"coordinates":[18.34457,54.24686],"type":"Point"}
}