{
  "type": "Feature",
  "properties": {
    "gn:admin1_code":"82.0",
    "gn:admin2_code":"2204.0",
    "gn:admin3_code":"220405.0",
    "gn:asciiname":"Zabrsko Gorne",
    "gn:country_code":"PL",
    "gn:dem":229,
    "gn:feature_class":"P",
    "gn:feature_code":"PPL",
    "gn:name":"Z\u0105brsko G\u00f3rne",
    "gn:population":0,
    "gn:timezone":"Europe/Warsaw",
    "iso:country":"PL",
    "name:ceb_x_preferred":[
        "Z\u0105brsko G\u00f3rne"
    ],
    "name:pol_x_preferred":[
        "Z\u0105brsko G\u00f3rne"
    ],
    "name:ukr_x_preferred":[
        "\u0417\u043e\u043c\u0431\u0440\u0441\u044c\u043a\u043e-\u0490\u0443\u0440\u043d\u0435"
    ],
    "name:und_x_variant":[
        "Ober Sommerkau"
    ],
    "name:urd_x_preferred":[
        "\u0632\u0648\u0628\u0631\u0633\u06a9\u0648 \u06af\u0648\u0631\u0646\u06d2"
    ],
    "wof:name":"Zabrsko Gorne",
    "wof:placetype":"locality"
},
  "geometry": {"coordinates":[18.34457,54.24686],"type":"Point"}
}