{
  "type": "Feature",
  "properties": {
    "gn:admin1_code":"75.0",
    "gn:admin2_code":"619.0",
    "gn:admin3_code":"61903.0",
    "gn:asciiname":"Budki",
    "gn:country_code":"PL",
    "gn:dem":169,
    "gn:feature_class":"P",
    "gn:feature_code":"PPL",
    "gn:name":"Budki",
    "gn:population":0,
    "gn:timezone":"Europe/Warsaw",
    "iso:country":"PL",
    "name:deu_x_preferred":[
        "Budki"
    ],
    "name:fra_x_preferred":[
        "Budki"
    ],
    "name:nld_x_preferred":[
        "Budki"
    ],
    "name:pol_x_preferred":[
        "Budki"
    ],
    "name:ukr_x_preferred":[
        "\u0411\u0443\u0434\u043a\u0456"
    ],
    "wof:name":"Budki",
    "wof:placetype":"locality"
},
  "geometry": {"coordinates":[23.45303,51.41801],"type":"Point"}
}