{
  "type": "Feature",
  "properties": {
    "gn:admin1_code":"85.0",
    "gn:admin2_code":"2801.0",
    "gn:admin3_code":"280104.0",
    "gn:asciiname":"Lablawki",
    "gn:country_code":"PL",
    "gn:dem":59,
    "gn:feature_class":"P",
    "gn:feature_code":"PPL",
    "gn:name":"\u0141ab\u0142awki",
    "gn:population":0,
    "gn:timezone":"Europe/Warsaw",
    "iso:country":"PL",
    "name:und_x_variant":[
        "Lablack",
        "\u0141ab\u0142awki"
    ],
    "wof:name":"Lablawki",
    "wof:placetype":"locality"
},
  "geometry": {"coordinates":[21.0216,54.14928000000001],"type":"Point"}
}