{
  "type": "Feature",
  "properties": {
    "gn:admin1_code":"74.0",
    "gn:admin2_code":"1020.0",
    "gn:admin3_code":"102007.0",
    "gn:asciiname":"Skorka",
    "gn:country_code":"PL",
    "gn:dem":135,
    "gn:feature_class":"P",
    "gn:feature_code":"PPL",
    "gn:name":"Skorka",
    "gn:population":0,
    "gn:timezone":"Europe/Warsaw",
    "iso:country":"PL",
    "name:pol_x_preferred":[
        "Sk\u00f3rka"
    ],
    "name:ukr_x_preferred":[
        "\u0421\u043a\u0443\u0440\u043a\u0430"
    ],
    "wof:name":"Skorka",
    "wof:placetype":"locality"
},
  "geometry": {"coordinates":[19.14824,51.92591],"type":"Point"}
}