{
  "type": "Feature",
  "properties": {
    "gn:admin1_code":"74.0",
    "gn:admin2_code":"1010.0",
    "gn:admin3_code":"101009.0",
    "gn:asciiname":"Przyglow",
    "gn:country_code":"PL",
    "gn:dem":173,
    "gn:feature_class":"P",
    "gn:feature_code":"PPL",
    "gn:name":"Przyg\u0142\u00f3w",
    "gn:population":0,
    "gn:timezone":"Europe/Warsaw",
    "iso:country":"PL",
    "wof:name":"Przyglow",
    "wof:placetype":"locality"
},
  "geometry": {"coordinates":[19.8171,51.37757],"type":"Point"}
}