{
  "type": "Feature",
  "properties": {
    "gn:admin1_code":"72.0",
    "gn:admin2_code":"223.0",
    "gn:admin3_code":"22307.0",
    "gn:asciiname":"Gorka",
    "gn:country_code":"PL",
    "gn:dem":202,
    "gn:feature_class":"P",
    "gn:feature_code":"PPL",
    "gn:name":"G\u00f3rka",
    "gn:population":0,
    "gn:timezone":"Europe/Warsaw",
    "iso:country":"PL",
    "wof:name":"Gorka",
    "wof:placetype":"locality"
},
  "geometry": {"coordinates":[16.70692,50.89204],"type":"Point"}
}