{
  "type": "Feature",
  "properties": {
    "gn:admin1_code":"74.0",
    "gn:admin2_code":"1008.0",
    "gn:admin3_code":"100807.0",
    "gn:asciiname":"Janowice",
    "gn:country_code":"PL",
    "gn:dem":183,
    "gn:feature_class":"P",
    "gn:feature_code":"PPL",
    "gn:name":"Janowice",
    "gn:population":0,
    "gn:timezone":"Europe/Warsaw",
    "iso:country":"PL",
    "name:ceb_x_preferred":[
        "Janowice"
    ],
    "name:fra_x_preferred":[
        "Janowice"
    ],
    "name:pol_x_preferred":[
        "Janowice"
    ],
    "name:ukr_x_preferred":[
        "\u042f\u043d\u043e\u0432\u0456\u0446\u0435"
    ],
    "name:urd_x_preferred":[
        "\u062c\u0646\u0648\u0648\u06a9\u06d2"
    ],
    "wof:name":"Janowice",
    "wof:placetype":"locality"
},
  "geometry": {"coordinates":[19.20891,51.69299],"type":"Point"}
}