{
  "type": "Feature",
  "properties": {
    "iso:country":"PL",
    "name:ast_x_preferred":[
        "Pisarzowa"
    ],
    "name:eng_x_preferred":[
        "Pisarzowa"
    ],
    "name:fra_x_preferred":[
        "Pisarzowa"
    ],
    "name:pol_x_preferred":[
        "Pisarzowa"
    ],
    "name:ukr_x_preferred":[
        "\u041f\u0456\u0441\u0430\u0436\u043e\u0432\u0430"
    ],
    "qs:a0":"Rzeczpospolita Polska",
    "qs:a1":"*Malopolskie",
    "qs:a1r":"0",
    "qs:a2":"Limanowski",
    "qs:adm0":"Rzeczpospolita Polska",
    "qs:la_lc":"*",
    "qs:level":"locality",
    "qs:loc":"Pisarzowa",
    "qs:loc_alt":"Pisarzowa",
    "qs:pop":0,
    "qs:type":"buffered point",
    "wd:wordcount":60,
    "wof:name":"Pisarzowa",
    "wof:placetype":"locality"
},
  "geometry": {"coordinates":[20.507337,49.68906],"type":"Point"}
}