{
  "type": "Feature",
  "properties": {
    "gn:admin1_code":"77.0",
    "gn:admin2_code":"1207.0",
    "gn:admin3_code":"120709.0",
    "gn:asciiname":"Przyslop",
    "gn:country_code":"PL",
    "gn:dem":741,
    "gn:feature_class":"P",
    "gn:feature_code":"PPL",
    "gn:name":"Przys\u0142op",
    "gn:population":0,
    "gn:timezone":"Europe/Warsaw",
    "iso:country":"PL",
    "wof:name":"Przyslop",
    "wof:placetype":"locality"
},
  "geometry": {"coordinates":[20.22677,49.594],"type":"Point"}
}