{
  "type": "Feature",
  "properties": {
    "gn:admin1_code":"76.0",
    "gn:admin2_code":"803.0",
    "gn:admin3_code":"80303.0",
    "gn:asciiname":"Krasne Dlusko",
    "gn:country_code":"PL",
    "gn:dem":29,
    "gn:feature_class":"P",
    "gn:feature_code":"PPL",
    "gn:name":"Krasne D\u0142usko",
    "gn:population":0,
    "gn:timezone":"Europe/Warsaw",
    "iso:country":"PL",
    "name:ceb_x_preferred":[
        "Krasne D\u0142usko"
    ],
    "name:fra_x_preferred":[
        "Krasne D\u0142usko"
    ],
    "name:pol_x_preferred":[
        "Krasne D\u0142usko"
    ],
    "name:ukr_x_preferred":[
        "\u041a\u0440\u0430\u0441\u043d\u0435-\u0414\u043b\u0443\u0441\u044c\u043a\u043e"
    ],
    "wof:name":"Krasne Dlusko",
    "wof:placetype":"locality"
},
  "geometry": {"coordinates":[15.61939,52.6131],"type":"Point"}
}