{
  "type": "Feature",
  "properties": {
    "gn:admin1_code":"76.0",
    "gn:admin2_code":"803.0",
    "gn:admin3_code":"80303.0",
    "gn:asciiname":"Krasne Dlusko",
    "gn:country_code":"PL",
    "gn:dem":29,
    "gn:feature_class":"P",
    "gn:feature_code":"PPL",
    "gn:name":"Krasne D\u0142usko",
    "gn:population":0,
    "gn:timezone":"Europe/Warsaw",
    "iso:country":"PL",
    "name:und_x_variant":[
        "Krasne D\u0142usko"
    ],
    "wof:name":"Krasne Dlusko",
    "wof:placetype":"locality"
},
  "geometry": {"coordinates":[15.61939,52.6131],"type":"Point"}
}