{
  "type": "Feature",
  "properties": {
    "iso:country":"PL",
    "name:eng_x_preferred":[
        "Ziemica"
    ],
    "name:pol_x_preferred":[
        "Ziemica"
    ],
    "wof:name":"Ziemica",
    "wof:placetype":"neighbourhood"
},
  "geometry": {"coordinates":[18.62366527615747,54.35270558804123],"type":"Point"}
}