{
  "type": "Feature",
  "properties": {
    "gn:admin1_code":"86.0",
    "gn:admin2_code":"3007.0",
    "gn:admin3_code":"300706.0",
    "gn:asciiname":"Swoboda",
    "gn:country_code":"PL",
    "gn:dem":143,
    "gn:feature_class":"P",
    "gn:feature_code":"PPL",
    "gn:name":"Swoboda",
    "gn:population":0,
    "gn:timezone":"Europe/Warsaw",
    "iso:country":"PL",
    "wof:name":"Swoboda",
    "wof:placetype":"locality"
},
  "geometry": {"coordinates":[18.45411,51.83206],"type":"Point"}
}