{
  "type": "Feature",
  "properties": {
    "gn:admin1_code":"78.0",
    "gn:admin2_code":"1428.0",
    "gn:admin3_code":"142803.0",
    "gn:asciiname":"Wszeliwy",
    "gn:country_code":"PL",
    "gn:dem":103,
    "gn:feature_class":"P",
    "gn:feature_code":"PPL",
    "gn:name":"Wszeliwy",
    "gn:population":0,
    "gn:timezone":"Europe/Warsaw",
    "iso:country":"PL",
    "name:fra_x_preferred":[
        "Wszeliwy"
    ],
    "name:pol_x_preferred":[
        "Wszeliwy"
    ],
    "name:ukr_x_preferred":[
        "\u0412\u0448\u0435\u043b\u0456\u0432\u0438"
    ],
    "wof:name":"Wszeliwy",
    "wof:placetype":"locality"
},
  "geometry": {"coordinates":[19.96389,52.29692],"type":"Point"}
}