{
  "type": "Feature",
  "properties": {
    "gn:admin1_code":"85.0",
    "gn:admin2_code":"2811.0",
    "gn:admin3_code":"281102.0",
    "gn:asciiname":"Wieckowo",
    "gn:country_code":"PL",
    "gn:dem":151,
    "gn:feature_class":"P",
    "gn:feature_code":"PPL",
    "gn:name":"Wi\u0119ckowo",
    "gn:population":0,
    "gn:timezone":"Europe/Warsaw",
    "iso:country":"PL",
    "name:fra_x_preferred":[
        "Wi\u0119ckowo"
    ],
    "name:pol_x_preferred":[
        "Wi\u0119ckowo"
    ],
    "name:ukr_x_preferred":[
        "\u0412\u0435\u043d\u0446\u043a\u043e\u0432\u043e"
    ],
    "name:und_x_variant":[
        "Winsken",
        "Wientzkowen"
    ],
    "wof:name":"Wieckowo",
    "wof:placetype":"locality"
},
  "geometry": {"coordinates":[20.58942,53.37555],"type":"Point"}
}