{
  "type": "Feature",
  "properties": {
    "gn:admin1_code":"87.0",
    "gn:admin2_code":"3211.0",
    "gn:admin3_code":"321102.0",
    "gn:asciiname":"Bedargowo",
    "gn:country_code":"PL",
    "gn:dem":41,
    "gn:feature_class":"P",
    "gn:feature_code":"PPL",
    "gn:name":"B\u0119dargowo",
    "gn:population":0,
    "gn:timezone":"Europe/Warsaw",
    "iso:country":"PL",
    "name:und_x_variant":[
        "B\u0119dargowo"
    ],
    "wof:name":"Bedargowo",
    "wof:placetype":"locality"
},
  "geometry": {"coordinates":[14.4413,53.39158000000001],"type":"Point"}
}