{
  "type": "Feature",
  "properties": {
    "gn:admin1_code":"87.0",
    "gn:admin2_code":"3211.0",
    "gn:admin3_code":"321102.0",
    "gn:asciiname":"Bedargowo",
    "gn:country_code":"PL",
    "gn:dem":41,
    "gn:feature_class":"P",
    "gn:feature_code":"PPL",
    "gn:name":"B\u0119dargowo",
    "gn:population":0,
    "gn:timezone":"Europe/Warsaw",
    "iso:country":"PL",
    "name:azb_x_preferred":[
        "\u0628\u0646\u062f\u0627\u0631\u0642\u0648\u0648\u0648"
    ],
    "name:ceb_x_preferred":[
        "B\u0119dargowo"
    ],
    "name:deu_x_preferred":[
        "B\u0119dargowo"
    ],
    "name:fas_x_preferred":[
        "\u0628\u0646\u062f\u0627\u0631\u06af\u0648\u0648\u0648"
    ],
    "name:nld_x_preferred":[
        "B\u0119dargowo"
    ],
    "name:pol_x_preferred":[
        "B\u0119dargowo"
    ],
    "name:ukr_x_preferred":[
        "\u0411\u0435\u043d\u0434\u0430\u0440\u0491\u043e\u0432\u043e"
    ],
    "name:vie_x_preferred":[
        "B\u0119dargowo"
    ],
    "wof:name":"Bedargowo",
    "wof:placetype":"locality"
},
  "geometry": {"coordinates":[14.4413,53.39158000000001],"type":"Point"}
}