{
  "type": "Feature",
  "properties": {
    "gn:admin1_code":"87.0",
    "gn:admin2_code":"3216.0",
    "gn:admin3_code":"321604.0",
    "gn:asciiname":"Gaskow",
    "gn:country_code":"PL",
    "gn:dem":61,
    "gn:feature_class":"P",
    "gn:feature_code":"PPL",
    "gn:name":"G\u0105sk\u00f3w",
    "gn:population":0,
    "gn:timezone":"Europe/Warsaw",
    "iso:country":"PL",
    "name:azb_x_preferred":[
        "\u0642\u0627\u0646\u0633\u06a9\u0648\u0648"
    ],
    "name:deu_x_preferred":[
        "G\u0105sk\u00f3w"
    ],
    "name:fas_x_preferred":[
        "\u06af\u0627\u0646\u0633\u06a9\u0648\u0648"
    ],
    "name:pol_x_preferred":[
        "G\u0105sk\u00f3w"
    ],
    "name:ukr_x_preferred":[
        "\u0490\u043e\u043d\u0441\u043a\u0443\u0432"
    ],
    "name:und_x_variant":[
        "Ganzkow",
        "G\u0105sk\u00f3w"
    ],
    "name:vie_x_preferred":[
        "G\u0105sk\u00f3w"
    ],
    "wof:name":"Gaskow",
    "wof:placetype":"locality"
},
  "geometry": {"coordinates":[15.94776,53.90087],"type":"Point"}
}