{
  "type": "Feature",
  "properties": {
    "gn:gn_country":"PL",
    "gn:gn_fcode":"PPL",
    "gn:gn_pop":110,
    "gn:population":110,
    "iso:country":"PL",
    "name:ceb_x_preferred":[
        "Ostr\u00f3wek"
    ],
    "name:deu_x_preferred":[
        "Ostr\u00f3wek"
    ],
    "name:fra_x_preferred":[
        "Ostr\u00f3wek"
    ],
    "name:ita_x_preferred":[
        "Ostr\u00f3wek"
    ],
    "name:lit_x_preferred":[
        "Ostruvekas"
    ],
    "name:nld_x_preferred":[
        "Ostr\u00f3wek"
    ],
    "name:pol_x_preferred":[
        "Ostr\u00f3wek"
    ],
    "name:rus_x_preferred":[
        "\u041e\u0441\u0442\u0440\u0443\u0432\u0435\u043a"
    ],
    "name:ukr_x_preferred":[
        "\u041e\u0441\u0442\u0440\u0443\u0432\u0435\u043a"
    ],
    "qs_pg:aaroncc":"PL",
    "qs_pg:gn_country":"PL",
    "qs_pg:gn_fcode":"PPL",
    "qs_pg:gn_pop":110,
    "qs_pg:name":"Ostr\u00f3wek",
    "qs_pg:name_adm0":"Polska",
    "qs_pg:name_adm1":"Podlaskie",
    "qs_pg:photos_9r":0,
    "qs_pg:photos_sr":0,
    "qs_pg:pop_sr":1,
    "qs_pg:qs_pg_placetype":"locality",
    "qs_pg:qs_pg_placetype_gp":"Town",
    "qs_pg:woe_adm0":23424923,
    "woe:adm0_id":23424923,
    "woe:name_adm0":"Polska",
    "woe:name_adm1":"Podlaskie",
    "woe:placetype":"Town",
    "wof:name":"Ostr\u00f3wek",
    "wof:placetype":"locality",
    "wof:population":110
},
  "geometry": {"coordinates":[23.70008,53.28302],"type":"Point"}
}