{
  "type": "Feature",
  "properties": {
    "gn:admin1_code":"81.0",
    "gn:admin2_code":"2013.0",
    "gn:admin3_code":"201309.0",
    "gn:asciiname":"Szepietowo-Janowka",
    "gn:country_code":"PL",
    "gn:dem":146,
    "gn:feature_class":"P",
    "gn:feature_code":"PPL",
    "gn:name":"Szepietowo-Jan\u00f3wka",
    "gn:population":0,
    "gn:timezone":"Europe/Warsaw",
    "iso:country":"PL",
    "name:lit_x_preferred":[
        "\u0160epetovo Januvka"
    ],
    "name:pol_x_preferred":[
        "Szepietowo-Jan\u00f3wka"
    ],
    "name:ukr_x_preferred":[
        "\u0428\u0435\u043f\u0435\u0442\u043e\u0432\u043e-\u042f\u043d\u0443\u0432\u043a\u0430"
    ],
    "wof:name":"Szepietowo-Janowka",
    "wof:placetype":"locality"
},
  "geometry": {"coordinates":[22.51159,52.8554],"type":"Point"}
}