{
  "type": "Feature",
  "properties": {
    "gn:admin1_code":"74.0",
    "gn:admin2_code":"1004.0",
    "gn:admin3_code":"100402.0",
    "gn:asciiname":"Krezelewice",
    "gn:country_code":"PL",
    "gn:dem":122,
    "gn:feature_class":"P",
    "gn:feature_code":"PPL",
    "gn:name":"Kr\u0119\u017celewice",
    "gn:population":0,
    "gn:timezone":"Europe/Warsaw",
    "iso:country":"PL",
    "name:fra_x_preferred":[
        "Kr\u0119\u017celewice"
    ],
    "name:pol_x_preferred":[
        "Kr\u0119\u017celewice"
    ],
    "wof:name":"Krezelewice",
    "wof:placetype":"locality"
},
  "geometry": {"coordinates":[19.18814,52.12542],"type":"Point"}
}