{
  "type": "Feature",
  "properties": {
    "gn:admin1_code":"78.0",
    "gn:admin2_code":"1403.0",
    "gn:admin3_code":"140303.0",
    "gn:asciiname":"Gosciewicz",
    "gn:country_code":"PL",
    "gn:dem":188,
    "gn:feature_class":"P",
    "gn:feature_code":"PPL",
    "gn:name":"Go\u015bciewicz",
    "gn:population":0,
    "gn:timezone":"Europe/Warsaw",
    "iso:country":"PL",
    "name:azb_x_preferred":[
        "\u0642\u0648\u0634\u0686\u06cc\u0648\u06cc\u0686"
    ],
    "name:ceb_x_preferred":[
        "Go\u015bciewicz"
    ],
    "name:fas_x_preferred":[
        "\u06af\u0648\u0634\u0686\u06cc\u0648\u06cc\u0686"
    ],
    "name:fra_x_preferred":[
        "Go\u015bciewicz"
    ],
    "name:pol_x_preferred":[
        "Go\u015bciewicz"
    ],
    "name:spa_x_preferred":[
        "Go\u015bciewicz"
    ],
    "name:ukr_x_preferred":[
        "\u0490\u043e\u0441\u044c\u0446\u0435\u0432\u0438\u0447"
    ],
    "wof:name":"Gosciewicz",
    "wof:placetype":"locality"
},
  "geometry": {"coordinates":[21.84546,51.93823],"type":"Point"}
}