{
  "type": "Feature",
  "properties": {
    "gn:admin1_code":"73.0",
    "gn:admin2_code":"409.0",
    "gn:admin3_code":"40901.0",
    "gn:asciiname":"Broniewiaki",
    "gn:country_code":"PL",
    "gn:dem":108,
    "gn:feature_class":"P",
    "gn:feature_code":"PPL",
    "gn:name":"Broniewiaki",
    "gn:population":0,
    "gn:timezone":"Europe/Warsaw",
    "iso:country":"PL",
    "wof:name":"Broniewiaki",
    "wof:placetype":"locality"
},
  "geometry": {"coordinates":[17.99723999999999,52.72095],"type":"Point"}
}