{
  "type": "Feature",
  "properties": {
    "gn:admin1_code":"77.0",
    "gn:admin2_code":"1207.0",
    "gn:admin3_code":"120708.0",
    "gn:asciiname":"Stronie",
    "gn:country_code":"PL",
    "gn:dem":441,
    "gn:feature_class":"P",
    "gn:feature_code":"PPL",
    "gn:name":"Stronie",
    "gn:population":0,
    "gn:timezone":"Europe/Warsaw",
    "iso:country":"PL",
    "name:ceb_x_preferred":[
        "Stronie"
    ],
    "name:pol_x_preferred":[
        "Stronie"
    ],
    "name:ukr_x_preferred":[
        "\u0421\u0442\u0440\u043e\u043d\u0435"
    ],
    "wof:name":"Stronie",
    "wof:placetype":"locality"
},
  "geometry": {"coordinates":[20.53203,49.61227],"type":"Point"}
}