{
  "type": "Feature",
  "properties": {
    "gn:admin1_code":"74.0",
    "gn:admin2_code":"1006.0",
    "gn:admin3_code":"100608.0",
    "gn:asciiname":"Moskiew",
    "gn:country_code":"PL",
    "gn:dem":245,
    "gn:feature_class":"P",
    "gn:feature_code":"PPL",
    "gn:name":"Moskiew",
    "gn:population":0,
    "gn:timezone":"Europe/Warsaw",
    "iso:country":"PL",
    "wof:name":"Moskiew",
    "wof:placetype":"locality"
},
  "geometry": {"coordinates":[19.66667,51.81667],"type":"Point"}
}