{
  "type": "Feature",
  "properties": {
    "gn:admin1_code":"83.0",
    "gn:admin2_code":"2417.0",
    "gn:admin3_code":"241705.0",
    "gn:asciiname":"Jalowiec",
    "gn:country_code":"PL",
    "gn:dem":735,
    "gn:feature_class":"P",
    "gn:feature_code":"PPL",
    "gn:name":"Ja\u0142owiec",
    "gn:population":0,
    "gn:timezone":"Europe/Warsaw",
    "iso:country":"PL",
    "wof:name":"Jalowiec",
    "wof:placetype":"locality"
},
  "geometry": {"coordinates":[19.455,49.67156],"type":"Point"}
}