{
  "type": "Feature",
  "properties": {
    "gn:gn_country":"PL",
    "gn:gn_fcode":"PPLA3",
    "gn:gn_pop":2335,
    "gn:population":2335,
    "iso:country":"PL",
    "name:eng_x_preferred":[
        "Szepietowo"
    ],
    "name:lav_x_preferred":[
        "\u0160epetovo"
    ],
    "name:lit_x_preferred":[
        "\u0160epetovas"
    ],
    "name:rus_x_preferred":[
        "\u0428\u0435\u043f\u0435\u0442\u043e\u0432\u043e-\u0421\u0442\u0430\u0446\u044c\u044f"
    ],
    "name:rus_x_variant":[
        "\u0428\u0435\u043f\u0435\u0442\u043e\u0432\u043e"
    ],
    "name:srp_x_preferred":[
        "\u0428\u0435\u043f\u0458\u0435\u0442\u043e\u0432\u043e"
    ],
    "name:unk_x_variant":[
        "Szepetowo"
    ],
    "qs_pg:aaroncc":"PL",
    "qs_pg:gn_country":"PL",
    "qs_pg:gn_fcode":"PPLA3",
    "qs_pg:gn_pop":2335,
    "qs_pg:name":"Szepietowo",
    "qs_pg:name_adm0":"Polska",
    "qs_pg:name_adm1":"Podlaskie",
    "qs_pg:photos_9k":1,
    "qs_pg:photos_9r":1,
    "qs_pg:photos_all":4,
    "qs_pg:photos_sr":0,
    "qs_pg:pop_sr":4,
    "qs_pg:qs_pg_placetype":"localadmin",
    "qs_pg:qs_pg_placetype_gp":"LocalAdmin",
    "qs_pg:woe_adm0":23424923,
    "woe:adm0_id":23424923,
    "woe:name_adm0":"Polska",
    "woe:name_adm1":"Podlaskie",
    "woe:placetype":"LocalAdmin",
    "wof:name":"Szepietowo",
    "wof:placetype":"localadmin",
    "wof:population":2335
},
  "geometry": {"coordinates":[22.54392,52.87032],"type":"Point"}
}