{
  "type": "Feature",
  "properties": {
    "gn:admin1_code":"73.0",
    "gn:admin2_code":"418.0",
    "gn:admin3_code":"41806.0",
    "gn:asciiname":"Pyszkowo",
    "gn:country_code":"PL",
    "gn:dem":110,
    "gn:feature_class":"P",
    "gn:feature_code":"PPL",
    "gn:name":"Pyszkowo",
    "gn:population":0,
    "gn:timezone":"Europe/Warsaw",
    "iso:country":"PL",
    "name:pol_x_preferred":[
        "Pyszkowo"
    ],
    "name:ukr_x_preferred":[
        "\u041f\u0438\u0448\u043a\u043e\u0432\u043e"
    ],
    "wof:name":"Pyszkowo",
    "wof:placetype":"locality"
},
  "geometry": {"coordinates":[18.9489,52.43913000000001],"type":"Point"}
}