{
  "type": "Feature",
  "properties": {
    "gn:admin1_code":"73.0",
    "gn:admin2_code":"410.0",
    "gn:admin3_code":"41003.0",
    "gn:asciiname":"Suchary",
    "gn:country_code":"PL",
    "gn:dem":106,
    "gn:feature_class":"P",
    "gn:feature_code":"PPL",
    "gn:name":"Suchary",
    "gn:population":0,
    "gn:timezone":"Europe/Warsaw",
    "iso:country":"PL",
    "name:ceb_x_preferred":[
        "Suchary"
    ],
    "name:pol_x_preferred":[
        "Suchary"
    ],
    "name:ukr_x_preferred":[
        "\u0421\u0443\u0445\u0430\u0440\u0438"
    ],
    "wof:name":"Suchary",
    "wof:placetype":"locality"
},
  "geometry": {"coordinates":[17.64725,53.18894],"type":"Point"}
}