{
  "type": "Feature",
  "properties": {
    "gn:admin1_code":"83.0",
    "gn:admin2_code":"2401.0",
    "gn:admin3_code":"240102.0",
    "gn:asciiname":"Piaski",
    "gn:country_code":"PL",
    "gn:dem":285,
    "gn:feature_class":"P",
    "gn:feature_code":"PPL",
    "gn:name":"Piaski",
    "gn:population":0,
    "gn:timezone":"Europe/Warsaw",
    "iso:country":"PL",
    "name:deu_x_preferred":[
        "Piaski"
    ],
    "name:dsb_x_preferred":[
        "Piaski"
    ],
    "name:epo_x_preferred":[
        "Piaski"
    ],
    "name:est_x_preferred":[
        "Piaski"
    ],
    "name:fra_x_preferred":[
        "Piaski"
    ],
    "name:heb_x_preferred":[
        "\u05e4\u05d9\u05d0\u05e1\u05e7\u05d9"
    ],
    "name:lav_x_preferred":[
        "Pjaski"
    ],
    "name:msa_x_preferred":[
        "Piaski"
    ],
    "name:nld_x_preferred":[
        "Piaski"
    ],
    "name:pol_x_preferred":[
        "Piaski"
    ],
    "name:por_x_preferred":[
        "Piaski"
    ],
    "name:ron_x_preferred":[
        "Piaski"
    ],
    "name:rus_x_preferred":[
        "\u041f\u044f\u0441\u043a\u0438"
    ],
    "name:slk_x_preferred":[
        "Piaski"
    ],
    "name:srp_x_preferred":[
        "\u041f\u0458\u0430\u0441\u043a\u0438"
    ],
    "name:ukr_x_preferred":[
        "\u041f\u044f\u0441\u043a\u0456"
    ],
    "name:vie_x_preferred":[
        "Piaski"
    ],
    "name:zho_x_preferred":[
        "\u76ae\u4e9e\u65af\u57fa"
    ],
    "wof:name":"Piaski",
    "wof:placetype":"neighbourhood"
},
  "geometry": {"coordinates":[19.09083,50.30575],"type":"Point"}
}