{
  "type": "Feature",
  "properties": {
    "gn:admin1_code":"77.0",
    "gn:admin2_code":"1206.0",
    "gn:admin3_code":"120611.0",
    "gn:asciiname":"Goluchowice",
    "gn:country_code":"PL",
    "gn:dem":296,
    "gn:feature_class":"P",
    "gn:feature_code":"PPL",
    "gn:name":"Go\u0142uchowice",
    "gn:population":0,
    "gn:timezone":"Europe/Warsaw",
    "iso:country":"PL",
    "name:pol_x_preferred":[
        "Go\u0142uchowice"
    ],
    "name:rus_x_preferred":[
        "\u0413\u043e\u043b\u0443\u0445\u043e\u0432\u0438\u0446\u0435"
    ],
    "name:ukr_x_preferred":[
        "\u0490\u043e\u043b\u0443\u0445\u043e\u0432\u0456\u0446\u0435"
    ],
    "wof:name":"Goluchowice",
    "wof:placetype":"locality"
},
  "geometry": {"coordinates":[19.77179,49.94062],"type":"Point"}
}