{
  "type": "Feature",
  "properties": {
    "gn:admin1_code":"87.0",
    "gn:admin2_code":"3202.0",
    "gn:admin3_code":"320205.0",
    "gn:asciiname":"Boguszyny",
    "gn:country_code":"PL",
    "gn:dem":64,
    "gn:feature_class":"P",
    "gn:feature_code":"PPL",
    "gn:name":"Boguszyny",
    "gn:population":0,
    "gn:timezone":"Europe/Warsaw",
    "iso:country":"PL",
    "name:pol_x_preferred":[
        "Boguszyny"
    ],
    "name:ukr_x_preferred":[
        "\u0411\u043e\u0491\u0443\u0448\u0438\u043d\u0438"
    ],
    "name:vie_x_preferred":[
        "Boguszyny"
    ],
    "wof:name":"Boguszyny",
    "wof:placetype":"locality"
},
  "geometry": {"coordinates":[15.35131,53.08462],"type":"Point"}
}