{
  "type": "Feature",
  "properties": {
    "gn:admin1_code":"74.0",
    "gn:admin2_code":"1001.0",
    "gn:admin3_code":"100107.0",
    "gn:asciiname":"Kuznica Lubiecka",
    "gn:country_code":"PL",
    "gn:dem":174,
    "gn:feature_class":"P",
    "gn:feature_code":"PPL",
    "gn:name":"Ku\u017anica Lubiecka",
    "gn:population":0,
    "gn:timezone":"Europe/Warsaw",
    "iso:country":"PL",
    "name:fra_x_preferred":[
        "Ku\u017anica Lubiecka"
    ],
    "name:pol_x_preferred":[
        "Ku\u017anica Lubiecka"
    ],
    "name:ukr_x_preferred":[
        "\u041a\u0443\u0437\u044c\u043d\u0438\u0446\u044f-\u041b\u044e\u0431\u0435\u0446\u044c\u043a\u0430"
    ],
    "wof:name":"Kuznica Lubiecka",
    "wof:placetype":"locality"
},
  "geometry": {"coordinates":[19.17145,51.3724],"type":"Point"}
}