{
  "type": "Feature",
  "properties": {
    "gn:admin1_code":"83.0",
    "gn:admin2_code":"2404.0",
    "gn:admin3_code":"240411.0",
    "gn:asciiname":"Wola Hankowska",
    "gn:country_code":"PL",
    "gn:dem":230,
    "gn:feature_class":"P",
    "gn:feature_code":"PPL",
    "gn:name":"Wola Hankowska",
    "gn:population":0,
    "gn:timezone":"Europe/Warsaw",
    "iso:country":"PL",
    "name:ceb_x_preferred":[
        "Wola Hankowska"
    ],
    "name:pol_x_preferred":[
        "Wola Hankowska"
    ],
    "name:ukr_x_preferred":[
        "\u0412\u043e\u043b\u044f-\u0413\u0430\u043d\u043a\u043e\u0432\u0441\u044c\u043a\u0430"
    ],
    "name:und_x_variant":[
        "Jankowska Wola",
        "Wola Hankowska"
    ],
    "wof:name":"Wola Hankowska",
    "wof:placetype":"locality"
},
  "geometry": {"coordinates":[19.10067,50.88333],"type":"Point"}
}