{
  "type": "Feature",
  "properties": {
    "gn:admin1_code":"75.0",
    "gn:admin2_code":"607.0",
    "gn:admin3_code":"60702.0",
    "gn:asciiname":"Zychowki",
    "gn:country_code":"PL",
    "gn:dem":172,
    "gn:feature_class":"P",
    "gn:feature_code":"PPL",
    "gn:name":"\u017bych\u00f3wki",
    "gn:population":0,
    "gn:timezone":"Europe/Warsaw",
    "iso:country":"PL",
    "name:fra_x_preferred":[
        "\u015awieciech\u00f3w Poduchowny-Zych\u00f3wki"
    ],
    "name:pol_x_preferred":[
        "Zych\u00f3wki"
    ],
    "name:und_x_variant":[
        "\u017bych\u00f3wki"
    ],
    "wof:name":"Zychowki",
    "wof:placetype":"locality"
},
  "geometry": {"coordinates":[21.87496,50.92209],"type":"Point"}
}