{
  "type": "Feature",
  "properties": {
    "gn:admin1_code":"87.0",
    "gn:admin2_code":"3208.0",
    "gn:admin3_code":"320806.0",
    "gn:asciiname":"Bialokury",
    "gn:country_code":"PL",
    "gn:dem":35,
    "gn:feature_class":"P",
    "gn:feature_code":"PPL",
    "gn:name":"Bia\u0142okury",
    "gn:population":0,
    "gn:timezone":"Europe/Warsaw",
    "iso:country":"PL",
    "name:deu_x_preferred":[
        "Bia\u0142okury"
    ],
    "name:pol_x_preferred":[
        "Bia\u0142okury"
    ],
    "name:ukr_x_preferred":[
        "\u0411\u044f\u043b\u043e\u043a\u0443\u0440\u0438"
    ],
    "name:vie_x_preferred":[
        "Bia\u0142okury"
    ],
    "wof:name":"Bialokury",
    "wof:placetype":"locality"
},
  "geometry": {"coordinates":[15.51638,54.01523],"type":"Point"}
}