{
  "type": "Feature",
  "properties": {
    "gn:admin1_code":"85.0",
    "gn:admin2_code":"2814.0",
    "gn:admin3_code":"281411.0",
    "gn:asciiname":"Rybaki",
    "gn:country_code":"PL",
    "gn:dem":145,
    "gn:feature_class":"P",
    "gn:feature_code":"PPL",
    "gn:name":"Rybaki",
    "gn:population":0,
    "gn:timezone":"Europe/Warsaw",
    "iso:country":"PL",
    "name:fra_x_preferred":[
        "Rybaki"
    ],
    "name:lit_x_preferred":[
        "Ribakai"
    ],
    "name:pol_x_preferred":[
        "Rybaki"
    ],
    "name:ukr_x_preferred":[
        "\u0420\u0438\u0431\u0430\u043a\u0456"
    ],
    "name:und_x_variant":[
        "Lansk"
    ],
    "wof:name":"Rybaki",
    "wof:placetype":"locality"
},
  "geometry": {"coordinates":[20.4642,53.5877],"type":"Point"}
}