{
  "type": "Feature",
  "properties": {
    "gn:admin1_code":"86.0",
    "gn:admin2_code":"3016.0",
    "gn:admin3_code":"301603.0",
    "gn:asciiname":"Boruchowo",
    "gn:country_code":"PL",
    "gn:dem":71,
    "gn:feature_class":"P",
    "gn:feature_code":"PPL",
    "gn:name":"Boruchowo",
    "gn:population":0,
    "gn:timezone":"Europe/Warsaw",
    "iso:country":"PL",
    "wof:name":"Boruchowo",
    "wof:placetype":"locality"
},
  "geometry": {"coordinates":[16.88833,52.75893000000001],"type":"Point"}
}