{
  "type": "Feature",
  "properties": {
    "gn:admin1_code":"78.0",
    "gn:admin2_code":"1413.0",
    "gn:admin3_code":"141305.0",
    "gn:asciiname":"Gizynek",
    "gn:country_code":"PL",
    "gn:dem":104,
    "gn:feature_class":"P",
    "gn:feature_code":"PPL",
    "gn:name":"Gi\u017cynek",
    "gn:population":0,
    "gn:timezone":"Europe/Warsaw",
    "iso:country":"PL",
    "name:und_x_variant":[
        "Gi\u017cynek"
    ],
    "wof:name":"Gizynek",
    "wof:placetype":"locality"
},
  "geometry": {"coordinates":[20.30742,52.85388],"type":"Point"}
}