{
  "type": "Feature",
  "properties": {
    "gn:admin1_code":"75.0",
    "gn:admin2_code":"602.0",
    "gn:admin3_code":"60211.0",
    "gn:asciiname":"Zagrodki",
    "gn:country_code":"PL",
    "gn:dem":189,
    "gn:feature_class":"P",
    "gn:feature_code":"PPL",
    "gn:name":"Zagr\u00f3dki",
    "gn:population":0,
    "gn:timezone":"Europe/Warsaw",
    "iso:country":"PL",
    "name:ceb_x_preferred":[
        "Zagr\u00f3dki"
    ],
    "name:fra_x_preferred":[
        "Zagr\u00f3dki"
    ],
    "name:pol_x_preferred":[
        "Zagr\u00f3dki"
    ],
    "name:rus_x_preferred":[
        "\u0417\u0430\u0433\u0440\u0443\u0434\u043a\u0438"
    ],
    "name:ukr_x_preferred":[
        "\u0417\u0430\u0491\u0440\u0443\u0434\u043a\u0456"
    ],
    "name:urd_x_preferred":[
        "\u0632\u0627\u06af\u0631\u0648\u062f\u06a9\u06cc"
    ],
    "wof:name":"Zagrodki",
    "wof:placetype":"locality"
},
  "geometry": {"coordinates":[22.56602,50.3622],"type":"Point"}
}