{
  "type": "Feature",
  "properties": {
    "gn:admin1_code":"75.0",
    "gn:admin2_code":"602.0",
    "gn:admin3_code":"60211.0",
    "gn:asciiname":"Zagrodki",
    "gn:country_code":"PL",
    "gn:dem":189,
    "gn:feature_class":"P",
    "gn:feature_code":"PPL",
    "gn:name":"Zagr\u00f3dki",
    "gn:population":0,
    "gn:timezone":"Europe/Warsaw",
    "iso:country":"PL",
    "name:und_x_variant":[
        "Zagr\u00f3dki"
    ],
    "wof:name":"Zagrodki",
    "wof:placetype":"locality"
},
  "geometry": {"coordinates":[22.56602,50.3622],"type":"Point"}
}