{
  "type": "Feature",
  "properties": {
    "gn:admin1_code":"72.0",
    "gn:admin2_code":"223.0",
    "gn:admin3_code":"22307.0",
    "gn:asciiname":"Strachow",
    "gn:cc2":"PL",
    "gn:country_code":"PL",
    "gn:dem":152,
    "gn:feature_class":"P",
    "gn:feature_code":"PPL",
    "gn:name":"Strach\u00f3w",
    "gn:population":0,
    "gn:timezone":"Europe/Warsaw",
    "iso:country":"PL",
    "name:und_x_variant":[
        "Silingau",
        "Strachau",
        "Strachau bei Zobten",
        "Strach\u00f3w"
    ],
    "wof:name":"Strachow",
    "wof:placetype":"locality"
},
  "geometry": {"coordinates":[16.7872,50.90866],"type":"Point"}
}