{
  "type": "Feature",
  "properties": {
    "gn:admin1_code":"86.0",
    "gn:admin2_code":"3025.0",
    "gn:admin3_code":"302504.0",
    "gn:asciiname":"Annopole",
    "gn:country_code":"PL",
    "gn:dem":80,
    "gn:feature_class":"P",
    "gn:feature_code":"PPL",
    "gn:name":"Annopole",
    "gn:population":0,
    "gn:timezone":"Europe/Warsaw",
    "iso:country":"PL",
    "name:fra_x_preferred":[
        "Annopole"
    ],
    "name:pol_x_preferred":[
        "Annopole"
    ],
    "name:ukr_x_preferred":[
        "\u0410\u043d\u043d\u043e\u043f\u043e\u043b\u0435"
    ],
    "wof:name":"Annopole",
    "wof:placetype":"locality"
},
  "geometry": {"coordinates":[17.19669,52.20966],"type":"Point"}
}