{
  "type": "Feature",
  "properties": {
    "gn:admin1_code":"82.0",
    "gn:admin2_code":"2202.0",
    "gn:admin3_code":"220204.0",
    "gn:asciiname":"Zle Mieso",
    "gn:country_code":"PL",
    "gn:dem":117,
    "gn:feature_class":"P",
    "gn:feature_code":"PPL",
    "gn:name":"Z\u0142e Mi\u0119so",
    "gn:population":0,
    "gn:timezone":"Europe/Warsaw",
    "iso:country":"PL",
    "name:ceb_x_preferred":[
        "Z\u0142e Mi\u0119so"
    ],
    "name:pol_x_preferred":[
        "Z\u0142e Mi\u0119so"
    ],
    "name:szl_x_preferred":[
        "Z\u0142e Mjynso"
    ],
    "name:ukr_x_preferred":[
        "\u0417\u043b\u0435-\u041c\u0435\u043d\u0441\u043e"
    ],
    "wof:name":"Zle Mieso",
    "wof:placetype":"locality"
},
  "geometry": {"coordinates":[18.1087,53.8267],"type":"Point"}
}