{
  "type": "Feature",
  "properties": {
    "gn:gn_country":"PL",
    "gn:gn_fcode":"PPLA3",
    "gn:gn_pop":4200,
    "gn:population":4200,
    "iso:country":"PL",
    "name:azb_x_preferred":[
        "\u0633\u0648\u0648\u0648\u0634\u0648\u0648\u0627"
    ],
    "name:fas_x_preferred":[
        "\u0633\u0648\u0648\u0648\u0634\u0648\u0648\u0627"
    ],
    "name:nld_x_preferred":[
        "Su\u0142oszowa"
    ],
    "name:pol_x_preferred":[
        "Su\u0142oszowa"
    ],
    "name:rus_x_preferred":[
        "\u0421\u0443\u043b\u043e\u0448\u043e\u0432\u0430"
    ],
    "name:ukr_x_preferred":[
        "\u0421\u0443\u043b\u043e\u0448\u043e\u0432\u0430"
    ],
    "qs_pg:aaroncc":"PL",
    "qs_pg:gn_country":"PL",
    "qs_pg:gn_fcode":"PPLA3",
    "qs_pg:gn_pop":4200,
    "qs_pg:name":"Su\u0142oszowa",
    "qs_pg:name_adm0":"Polska",
    "qs_pg:name_adm1":"Ma\u0142opolskie",
    "qs_pg:photos":8,
    "qs_pg:photos_1k":2,
    "qs_pg:photos_9k":1,
    "qs_pg:photos_9r":4,
    "qs_pg:photos_all":200,
    "qs_pg:photos_sr":1,
    "qs_pg:pop_sr":4,
    "qs_pg:qs_pg_placetype":"localadmin",
    "qs_pg:qs_pg_placetype_gp":"LocalAdmin",
    "qs_pg:woe_adm0":23424923,
    "woe:adm0_id":23424923,
    "woe:name_adm0":"Polska",
    "woe:name_adm1":"Ma\u0142opolskie",
    "woe:placetype":"LocalAdmin",
    "wof:name":"Su\u0142oszowa",
    "wof:placetype":"localadmin",
    "wof:population":4200
},
  "geometry": {"coordinates":[19.73282,50.26789],"type":"Point"}
}