{
  "type": "Feature",
  "properties": {
    "gn:admin1_code":"87.0",
    "gn:admin2_code":"3213.0",
    "gn:admin3_code":"321306.0",
    "gn:asciiname":"Letowo",
    "gn:country_code":"PL",
    "gn:dem":38,
    "gn:feature_class":"P",
    "gn:feature_code":"PPL",
    "gn:name":"\u0141\u0119towo",
    "gn:population":0,
    "gn:timezone":"Europe/Warsaw",
    "iso:country":"PL",
    "name:ceb_x_preferred":[
        "\u0141\u0119towo"
    ],
    "name:deu_x_preferred":[
        "\u0141\u0119towo"
    ],
    "name:pol_x_preferred":[
        "\u0141\u0119towo"
    ],
    "name:ukr_x_preferred":[
        "\u041b\u0435\u043d\u0442\u043e\u0432\u043e"
    ],
    "wof:name":"Letowo",
    "wof:placetype":"locality"
},
  "geometry": {"coordinates":[16.81484,54.28194000000001],"type":"Point"}
}