{
  "type": "Feature",
  "properties": {
    "gn:admin1_code":"78.0",
    "gn:admin2_code":"1426.0",
    "gn:admin3_code":"142613.0",
    "gn:asciiname":"Plewki",
    "gn:cc2":"PL",
    "gn:country_code":"PL",
    "gn:dem":160,
    "gn:feature_class":"P",
    "gn:feature_code":"PPL",
    "gn:name":"Plewki",
    "gn:population":0,
    "gn:timezone":"Europe/Warsaw",
    "iso:country":"PL",
    "name:ceb_x_preferred":[
        "Plewki"
    ],
    "name:fra_x_preferred":[
        "Tch\u00f3rzew-Plewki"
    ],
    "name:pol_x_preferred":[
        "Tch\u00f3rzew-Plewki"
    ],
    "name:ukr_x_preferred":[
        "\u0422\u0445\u0443\u0436\u0435\u0432-\u041f\u043b\u0435\u0432\u043a\u0456"
    ],
    "name:und_x_variant":[
        "Tchorzew Plewki",
        "Plewki"
    ],
    "wof:name":"Plewki",
    "wof:placetype":"locality"
},
  "geometry": {"coordinates":[22.50635,52.07655],"type":"Point"}
}