{
  "type": "Feature",
  "properties": {
    "gn:admin1_code":"75.0",
    "gn:admin2_code":"613.0",
    "gn:admin3_code":"61305.0",
    "gn:asciiname":"Antopol",
    "gn:country_code":"PL",
    "gn:dem":155,
    "gn:feature_class":"P",
    "gn:feature_code":"PPL",
    "gn:name":"Antopol",
    "gn:population":0,
    "gn:timezone":"Europe/Warsaw",
    "iso:country":"PL",
    "name:bel_x_preferred":[
        "\u0410\u043d\u0442\u043e\u043f\u0430\u043b\u044c"
    ],
    "name:deu_x_preferred":[
        "Antopol"
    ],
    "name:fra_x_preferred":[
        "Antopol"
    ],
    "name:hye_x_preferred":[
        "\u0531\u0576\u057f\u0578\u057a\u0578\u056c"
    ],
    "name:pol_x_preferred":[
        "Antopol"
    ],
    "name:rus_x_preferred":[
        "\u0410\u043d\u0442\u043e\u043f\u043e\u043b\u044c"
    ],
    "name:ukr_x_preferred":[
        "\u0410\u043d\u0442\u043e\u043f\u0456\u043b\u044c"
    ],
    "name:und_x_variant":[
        "Kolonia Antopol"
    ],
    "wof:name":"Antopol",
    "wof:placetype":"locality"
},
  "geometry": {"coordinates":[23.2441,51.65376],"type":"Point"}
}