{
  "type": "Feature",
  "properties": {
    "gn:admin1_code":"75.0",
    "gn:admin2_code":"613.0",
    "gn:admin3_code":"61305.0",
    "gn:asciiname":"Antopol",
    "gn:country_code":"PL",
    "gn:dem":155,
    "gn:feature_class":"P",
    "gn:feature_code":"PPL",
    "gn:name":"Antopol",
    "gn:population":0,
    "gn:timezone":"Europe/Warsaw",
    "iso:country":"PL",
    "name:und_x_variant":[
        "Kolonia Antopol",
        "Antopol"
    ],
    "wof:name":"Antopol",
    "wof:placetype":"locality"
},
  "geometry": {"coordinates":[23.2441,51.65376],"type":"Point"}
}