{
  "type": "Feature",
  "properties": {
    "gn:admin1_code":"80.0",
    "gn:admin2_code":"1816.0",
    "gn:admin3_code":"181605.0",
    "gn:asciiname":"Dylagowa",
    "gn:cc2":"PL",
    "gn:country_code":"PL",
    "gn:dem":350,
    "gn:feature_class":"P",
    "gn:feature_code":"PPL",
    "gn:name":"Dyl\u0105gowa",
    "gn:population":0,
    "gn:timezone":"Europe/Warsaw",
    "iso:country":"PL",
    "name:ceb_x_preferred":[
        "Dyl\u0105gowa"
    ],
    "name:nld_x_preferred":[
        "Dyl\u0105gowa"
    ],
    "name:pol_x_preferred":[
        "Dyl\u0105gowa"
    ],
    "name:ukr_x_preferred":[
        "\u0414\u0438\u043b\u044c\u043e\u043d\u0491\u043e\u0432\u0430"
    ],
    "name:und_x_variant":[
        "Dyl\u0105grwa"
    ],
    "wof:name":"Dylagowa",
    "wof:placetype":"locality"
},
  "geometry": {"coordinates":[22.29658,49.78126],"type":"Point"}
}