{
  "type": "Feature",
  "properties": {
    "gn:admin1_code":"86.0",
    "gn:admin2_code":"3009.0",
    "gn:admin3_code":"300906.0",
    "gn:asciiname":"Kolonia Rysiny",
    "gn:country_code":"PL",
    "gn:dem":121,
    "gn:feature_class":"P",
    "gn:feature_code":"PPL",
    "gn:name":"Kolonia Rysiny",
    "gn:population":0,
    "gn:timezone":"Europe/Warsaw",
    "iso:country":"PL",
    "name:und_x_variant":[
        "Rysiny Kolonia",
        "Kolonia Rysiny"
    ],
    "wof:name":"Kolonia Rysiny",
    "wof:placetype":"locality"
},
  "geometry": {"coordinates":[18.81526,52.31149],"type":"Point"}
}