{
  "type": "Feature",
  "properties": {
    "gn:admin1_code":"78.0",
    "gn:admin2_code":"1429.0",
    "gn:admin3_code":"142908.0",
    "gn:asciiname":"Budy Kupietynskie",
    "gn:country_code":"PL",
    "gn:dem":156,
    "gn:feature_class":"P",
    "gn:feature_code":"PPL",
    "gn:name":"Budy Kupi\u0119ty\u0144skie",
    "gn:population":0,
    "gn:timezone":"Europe/Warsaw",
    "iso:country":"PL",
    "name:und_x_variant":[
        "Budy",
        "Budy Kupi\u0119ty\u0144skie"
    ],
    "wof:name":"Budy Kupietynskie",
    "wof:placetype":"locality"
},
  "geometry": {"coordinates":[22.22436,52.44434],"type":"Point"}
}