{
  "type": "Feature",
  "properties": {
    "gn:admin1_code":"72.0",
    "gn:admin2_code":"223.0",
    "gn:admin3_code":"22305.0",
    "gn:asciiname":"Wierzbice",
    "gn:country_code":"PL",
    "gn:dem":147,
    "gn:feature_class":"P",
    "gn:feature_code":"PPL",
    "gn:name":"Wierzbice",
    "gn:population":0,
    "gn:timezone":"Europe/Warsaw",
    "iso:country":"PL",
    "wof:name":"Wierzbice",
    "wof:placetype":"locality"
},
  "geometry": {"coordinates":[16.89182000000001,50.95529000000001],"type":"Point"}
}