{
  "type": "Feature",
  "properties": {
    "gn:admin1_code":"86.0",
    "gn:admin2_code":"3010.0",
    "gn:admin3_code":"301006.0",
    "gn:asciiname":"Nowe Brzezno",
    "gn:country_code":"PL",
    "gn:dem":113,
    "gn:feature_class":"P",
    "gn:feature_code":"PPL",
    "gn:name":"Nowe Brze\u017ano",
    "gn:population":0,
    "gn:timezone":"Europe/Warsaw",
    "iso:country":"PL",
    "wof:name":"Nowe Brzezno",
    "wof:placetype":"locality"
},
  "geometry": {"coordinates":[18.33246,52.19036],"type":"Point"}
}