{
  "type": "Feature",
  "properties": {
    "gn:admin1_code":"75.0",
    "gn:admin2_code":"604.0",
    "gn:admin3_code":"60407.0",
    "gn:asciiname":"Kolonia Staszic",
    "gn:country_code":"PL",
    "gn:dem":233,
    "gn:feature_class":"P",
    "gn:feature_code":"PPL",
    "gn:name":"Kolonia Staszic",
    "gn:population":0,
    "gn:timezone":"Europe/Warsaw",
    "iso:country":"PL",
    "name:fra_x_preferred":[
        "Staszic"
    ],
    "name:pol_x_preferred":[
        "Staszic"
    ],
    "name:ukr_x_preferred":[
        "\u0421\u0442\u0430\u0448\u0456\u0446"
    ],
    "name:und_x_variant":[
        "Kolonja Staszie",
        "Kolonia Staszic"
    ],
    "wof:name":"Kolonia Staszic",
    "wof:placetype":"locality"
},
  "geometry": {"coordinates":[23.67236,50.88387],"type":"Point"}
}