{
  "type": "Feature",
  "properties": {
    "gn:admin1_code":"78.0",
    "gn:admin2_code":"1426.0",
    "gn:admin3_code":"142606.0",
    "gn:asciiname":"Strusy",
    "gn:country_code":"PL",
    "gn:dem":154,
    "gn:feature_class":"P",
    "gn:feature_code":"PPL",
    "gn:name":"Strusy",
    "gn:population":0,
    "gn:timezone":"Europe/Warsaw",
    "iso:country":"PL",
    "wof:name":"Strusy",
    "wof:placetype":"locality"
},
  "geometry": {"coordinates":[22.3758,52.26117],"type":"Point"}
}