{
  "type": "Feature",
  "properties": {
    "gn:admin1_code":"78.0",
    "gn:admin2_code":"1426.0",
    "gn:admin3_code":"142606.0",
    "gn:asciiname":"Strusy",
    "gn:country_code":"PL",
    "gn:dem":154,
    "gn:feature_class":"P",
    "gn:feature_code":"PPL",
    "gn:name":"Strusy",
    "gn:population":0,
    "gn:timezone":"Europe/Warsaw",
    "iso:country":"PL",
    "name:azb_x_preferred":[
        "\u0633\u062a\u0631\u0648\u0633\u0647"
    ],
    "name:fas_x_preferred":[
        "\u0633\u062a\u0631\u0648\u0633\u0647"
    ],
    "name:fra_x_preferred":[
        "Strusy"
    ],
    "name:lit_x_preferred":[
        "Strusai"
    ],
    "name:pol_x_preferred":[
        "Strusy"
    ],
    "name:szl_x_preferred":[
        "Strusy"
    ],
    "name:ukr_x_preferred":[
        "\u0421\u0442\u0440\u0443\u0441\u0438"
    ],
    "wof:name":"Strusy",
    "wof:placetype":"locality"
},
  "geometry": {"coordinates":[22.3758,52.26117],"type":"Point"}
}