{
  "type": "Feature",
  "properties": {
    "gn:population":1253,
    "iso:country":"PL",
    "name:ast_x_preferred":[
        "Stara Kamienica"
    ],
    "name:azb_x_preferred":[
        "\u0633\u062a\u0627\u0631\u0627 \u06a9\u0627\u0645\u06cc\u0646\u0642\u062a\u0633\u0627"
    ],
    "name:ceb_x_preferred":[
        "Stara Kamienica"
    ],
    "name:deu_x_preferred":[
        "Stara Kamienica"
    ],
    "name:eng_x_preferred":[
        "Stara Kamienica"
    ],
    "name:fas_x_preferred":[
        "\u0633\u062a\u0627\u0631\u0627 \u06a9\u0627\u0645\u06cc\u0646\u06af\u062a\u0633\u0627"
    ],
    "name:fra_x_preferred":[
        "Stara Kamienica"
    ],
    "name:nld_x_preferred":[
        "Stara Kamienica"
    ],
    "name:pol_x_preferred":[
        "Stara Kamienica"
    ],
    "name:rus_x_preferred":[
        "\u0421\u0442\u0430\u0440\u0430-\u041a\u0430\u043c\u0435\u043d\u0438\u0446\u0430"
    ],
    "name:swe_x_preferred":[
        "Stara Kamienica"
    ],
    "name:szl_x_preferred":[
        "Staro Kamjy\u0144ica"
    ],
    "name:ukr_x_preferred":[
        "\u0421\u0442\u0430\u0440\u0430 \u041a\u0430\u043c\u0435\u043d\u0438\u0446\u044f"
    ],
    "name:und_x_variant":[
        "Stara Kamienice"
    ],
    "qs:a0":"Rzeczpospolita Polska",
    "qs:a1":"*Dolnoslaskie",
    "qs:a1r":"0",
    "qs:a2":"Jeleniog\u00f3rski",
    "qs:adm0":"Rzeczpospolita Polska",
    "qs:la":"Stara Kamienica",
    "qs:la_lc":"*PL0206092",
    "qs:level":"locality",
    "qs:loc":"Stara Kamienica",
    "qs:loc_alt":"Stara Kamienica",
    "qs:pop":0,
    "qs:type":"rural point-in-poly",
    "wd:wordcount":118,
    "wof:coterminous":[
        1125283461
    ],
    "wof:name":"Stara Kamienica",
    "wof:placetype":"locality",
    "wof:population":1253
},
  "geometry": {"coordinates":[15.5430173134022,50.9042119784338],"type":"Point"}
}