{
  "type": "Feature",
  "properties": {
    "gn:admin1_code":"86.0",
    "gn:admin2_code":"3015.0",
    "gn:admin3_code":"301502.0",
    "gn:asciiname":"Zebowo",
    "gn:country_code":"PL",
    "gn:dem":88,
    "gn:feature_class":"P",
    "gn:feature_code":"PPL",
    "gn:name":"Z\u0119bowo",
    "gn:population":0,
    "gn:timezone":"Europe/Warsaw",
    "iso:country":"PL",
    "name:azb_x_preferred":[
        "\u0632\u0646\u0628\u0648\u0648\u0648"
    ],
    "name:ceb_x_preferred":[
        "Z\u0119bowo"
    ],
    "name:fas_x_preferred":[
        "\u0632\u0646\u0628\u0648\u0648\u0648"
    ],
    "name:fra_x_preferred":[
        "Z\u0119bowo"
    ],
    "name:nld_x_preferred":[
        "Z\u0119bowo"
    ],
    "name:pol_x_preferred":[
        "Z\u0119bowo"
    ],
    "name:ukr_x_preferred":[
        "\u0417\u0435\u043c\u0431\u043e\u0432\u043e"
    ],
    "wof:name":"Zebowo",
    "wof:placetype":"locality"
},
  "geometry": {"coordinates":[16.08547,52.46806],"type":"Point"}
}