{
  "type": "Feature",
  "properties": {
    "gn:admin1_code":"86.0",
    "gn:admin2_code":"3015.0",
    "gn:admin3_code":"301502.0",
    "gn:asciiname":"Zebowo",
    "gn:country_code":"PL",
    "gn:dem":88,
    "gn:feature_class":"P",
    "gn:feature_code":"PPL",
    "gn:name":"Z\u0119bowo",
    "gn:population":0,
    "gn:timezone":"Europe/Warsaw",
    "iso:country":"PL",
    "name:und_x_variant":[
        "Z\u0119bowo"
    ],
    "wof:name":"Zebowo",
    "wof:placetype":"locality"
},
  "geometry": {"coordinates":[16.08547,52.46806],"type":"Point"}
}