{
  "type": "Feature",
  "properties": {
    "iso:country":"PL",
    "name:azb_x_preferred":[
        "\u0642\u0645\u06cc\u0646\u0627 \u0627\u0648\u0644\u0634\u062a\u0646\u06a9"
    ],
    "name:bel_x_preferred":[
        "\u0410\u043b\u044c\u0448\u0442\u044b\u043d\u0430\u043a"
    ],
    "name:deu_x_preferred":[
        "Olsztynek#Gemeinde"
    ],
    "name:eus_x_preferred":[
        "Olsztynek udalerria"
    ],
    "name:fas_x_preferred":[
        "\u06af\u0645\u06cc\u0646\u0627 \u0627\u0648\u0644\u0634\u062a\u0646\u06a9"
    ],
    "name:fra_x_preferred":[
        "Olsztynek"
    ],
    "name:nld_x_preferred":[
        "Olsztynek"
    ],
    "name:pol_x_preferred":[
        "Olsztynek"
    ],
    "name:rus_x_preferred":[
        "\u041e\u043b\u044c\u0448\u0442\u044b\u043d\u0435\u043a"
    ],
    "name:sco_x_preferred":[
        "Gmina Olsztynek"
    ],
    "name:slk_x_preferred":[
        "Gmina Olsztynek"
    ],
    "name:ukr_x_preferred":[
        "\u0413\u043c\u0456\u043d\u0430 \u041e\u043b\u044c\u0448\u0442\u0438\u043d\u0435\u043a"
    ],
    "name:war_x_preferred":[
        "Gmina Olsztynek"
    ],
    "qs_pg:aaroncc":"PL",
    "qs_pg:name":"Gmina Olsztynek",
    "qs_pg:name_adm0":"Polska",
    "qs_pg:name_adm1":"Warminsko-Mazurskie",
    "qs_pg:photos":162,
    "qs_pg:photos_1k":33,
    "qs_pg:photos_9k":1,
    "qs_pg:photos_9r":4,
    "qs_pg:photos_all":170,
    "qs_pg:photos_sr":4,
    "qs_pg:pop_sr":0,
    "qs_pg:qs_pg_placetype":"localadmin",
    "qs_pg:qs_pg_placetype_gp":"LocalAdmin",
    "qs_pg:woe_adm0":23424923,
    "woe:adm0_id":23424923,
    "woe:name_adm0":"Polska",
    "woe:name_adm1":"Warminsko-Mazurskie",
    "woe:placetype":"LocalAdmin",
    "wof:name":"Gmina Olsztynek",
    "wof:placetype":"localadmin"
},
  "geometry": {"coordinates":[20.319557,53.480435],"type":"Point"}
}