{
  "type": "Feature",
  "properties": {
    "gn:admin1_code":"77.0",
    "gn:admin2_code":"1206.0",
    "gn:admin3_code":"120615.0",
    "gn:asciiname":"Gacki",
    "gn:country_code":"PL",
    "gn:dem":345,
    "gn:feature_class":"P",
    "gn:feature_code":"PPL",
    "gn:name":"Gacki",
    "gn:population":0,
    "gn:timezone":"Europe/Warsaw",
    "iso:country":"PL",
    "name:pol_x_preferred":[
        "Gacki"
    ],
    "name:ukr_x_preferred":[
        "\u0490\u0430\u0446\u043a\u0456"
    ],
    "wof:name":"Gacki",
    "wof:placetype":"locality"
},
  "geometry": {"coordinates":[19.81667,50.15],"type":"Point"}
}