{
  "type": "Feature",
  "properties": {
    "gn:admin1_code":"72.0",
    "gn:admin2_code":"211.0",
    "gn:admin3_code":"21102.0",
    "gn:asciiname":"Skladowice",
    "gn:country_code":"PL",
    "gn:dem":138,
    "gn:feature_class":"P",
    "gn:feature_code":"PPL",
    "gn:name":"Sk\u0142adowice",
    "gn:population":0,
    "gn:timezone":"Europe/Warsaw",
    "iso:country":"PL",
    "name:und_x_variant":[
        "Sk\u0142adowice"
    ],
    "wof:name":"Skladowice",
    "wof:placetype":"locality"
},
  "geometry": {"coordinates":[16.26153,51.43099],"type":"Point"}
}