{
  "type": "Feature",
  "properties": {
    "gn:admin1_code":"72.0",
    "gn:admin2_code":"211.0",
    "gn:admin3_code":"21102.0",
    "gn:asciiname":"Skladowice",
    "gn:country_code":"PL",
    "gn:dem":138,
    "gn:feature_class":"P",
    "gn:feature_code":"PPL",
    "gn:name":"Sk\u0142adowice",
    "gn:population":0,
    "gn:timezone":"Europe/Warsaw",
    "iso:country":"PL",
    "name:pol_x_preferred":[
        "Sk\u0142adowice"
    ],
    "name:ukr_x_preferred":[
        "\u0421\u043a\u043b\u0430\u0434\u043e\u0432\u0456\u0446\u0435"
    ],
    "wof:name":"Skladowice",
    "wof:placetype":"locality"
},
  "geometry": {"coordinates":[16.26153,51.43099],"type":"Point"}
}