{
  "type": "Feature",
  "properties": {
    "gn:admin1_code":"81.0",
    "gn:admin2_code":"2002.0",
    "gn:admin3_code":"200209.0",
    "gn:asciiname":"Karakule",
    "gn:country_code":"PL",
    "gn:dem":134,
    "gn:feature_class":"P",
    "gn:feature_code":"PPL",
    "gn:name":"Karakule",
    "gn:population":0,
    "gn:timezone":"Europe/Warsaw",
    "iso:country":"PL",
    "name:azb_x_preferred":[
        "\u06a9\u0627\u0631\u0627\u06a9\u0648\u0644\u0647"
    ],
    "name:ceb_x_preferred":[
        "Karakule"
    ],
    "name:fas_x_preferred":[
        "\u06a9\u0627\u0631\u0627\u06a9\u0648\u0644\u0647"
    ],
    "name:lit_x_preferred":[
        "Karakul\u0117"
    ],
    "name:pol_x_preferred":[
        "Karakule"
    ],
    "name:rus_x_preferred":[
        "\u041a\u0430\u0440\u0430\u043a\u0443\u043b\u0435"
    ],
    "name:ukr_x_preferred":[
        "\u041a\u0430\u0440\u0430\u043a\u0443\u043b\u0435"
    ],
    "wof:name":"Karakule",
    "wof:placetype":"locality"
},
  "geometry": {"coordinates":[23.26135,53.1744],"type":"Point"}
}