{
  "type": "Feature",
  "properties": {
    "gn:gn_country":"PL",
    "gn:gn_fcode":"PPL",
    "gn:gn_pop":240,
    "gn:population":240,
    "iso:country":"PL",
    "name:eng_x_preferred":[
        "Lipno"
    ],
    "name:fre_x_preferred":[
        "Lipno"
    ],
    "name:pol_x_preferred":[
        "Lipno"
    ],
    "qs_pg:aaroncc":"PL",
    "qs_pg:gn_country":"PL",
    "qs_pg:gn_fcode":"PPL",
    "qs_pg:gn_pop":240,
    "qs_pg:name":"Lipno",
    "qs_pg:name_adm0":"Polska",
    "qs_pg:name_adm1":"Mazowieckie",
    "qs_pg:photos_9r":0,
    "qs_pg:photos_sr":0,
    "qs_pg:pop_sr":2,
    "qs_pg:qs_pg_placetype":"locality",
    "qs_pg:qs_pg_placetype_gp":"Town",
    "qs_pg:woe_adm0":23424923,
    "woe:adm0_id":23424923,
    "woe:name_adm0":"Polska",
    "woe:name_adm1":"Mazowieckie",
    "woe:placetype":"Town",
    "wof:name":"Lipno",
    "wof:placetype":"locality",
    "wof:population":240
},
  "geometry": {"coordinates":[20.5955,51.36717],"type":"Point"}
}