{
  "type": "Feature",
  "properties": {
    "gn:admin1_code":"73.0",
    "gn:admin2_code":"403.0",
    "gn:admin3_code":"40302.0",
    "gn:asciiname":"Czarze",
    "gn:country_code":"PL",
    "gn:dem":29,
    "gn:feature_class":"P",
    "gn:feature_code":"PPL",
    "gn:name":"Czarze",
    "gn:population":0,
    "gn:timezone":"Europe/Warsaw",
    "iso:country":"PL",
    "wof:name":"Czarze",
    "wof:placetype":"locality"
},
  "geometry": {"coordinates":[18.27048,53.22315],"type":"Point"}
}