{
  "type": "Feature",
  "properties": {
    "gn:admin1_code":"83.0",
    "gn:admin2_code":"2416.0",
    "gn:admin3_code":"241608.0",
    "gn:asciiname":"Siedliska",
    "gn:country_code":"PL",
    "gn:dem":263,
    "gn:feature_class":"P",
    "gn:feature_code":"PPL",
    "gn:name":"Siedliska",
    "gn:population":0,
    "gn:timezone":"Europe/Warsaw",
    "iso:country":"PL",
    "name:pol_x_preferred":[
        "Siedliska"
    ],
    "name:ukr_x_preferred":[
        "\u0421\u0435\u0434\u043b\u0438\u0441\u044c\u043a\u0430"
    ],
    "wof:name":"Siedliska",
    "wof:placetype":"locality"
},
  "geometry": {"coordinates":[19.7475,50.63683],"type":"Point"}
}