{
  "type": "Feature",
  "properties": {
    "gn:admin1_code":"78.0",
    "gn:admin2_code":"1429.0",
    "gn:admin3_code":"142904.0",
    "gn:asciiname":"Molozew Wies",
    "gn:country_code":"PL",
    "gn:dem":124,
    "gn:feature_class":"P",
    "gn:feature_code":"PPL",
    "gn:name":"Mo\u0142o\u017cew Wie\u015b",
    "gn:population":0,
    "gn:timezone":"Europe/Warsaw",
    "iso:country":"PL",
    "wof:name":"Molozew Wies",
    "wof:placetype":"locality"
},
  "geometry": {"coordinates":[22.52536,52.45711],"type":"Point"}
}