{
  "type": "Feature",
  "properties": {
    "gn:admin1_code":"73.0",
    "gn:admin2_code":"419.0",
    "gn:admin3_code":"41902.0",
    "gn:asciiname":"Chomiaza Szlachecka",
    "gn:country_code":"PL",
    "gn:dem":89,
    "gn:feature_class":"P",
    "gn:feature_code":"PPL",
    "gn:name":"Chomi\u0105\u017ca Szlachecka",
    "gn:population":0,
    "gn:timezone":"Europe/Warsaw",
    "iso:country":"PL",
    "name:nld_x_preferred":[
        "Chomi\u0105\u017ca Szlachecka"
    ],
    "name:pol_x_preferred":[
        "Chomi\u0105\u017ca Szlachecka"
    ],
    "name:ukr_x_preferred":[
        "\u0425\u043e\u043c\u0439\u043e\u043d\u0436\u0430-\u0428\u043b\u044f\u0445\u0435\u0446\u044c\u043a\u0430"
    ],
    "name:und_x_variant":[
        "Chomi\u0105\u017ca",
        "Chomi\u0105\u017ca Szlachecka"
    ],
    "wof:name":"Chomiaza Szlachecka",
    "wof:placetype":"locality"
},
  "geometry": {"coordinates":[17.84179,52.7508],"type":"Point"}
}