{
  "type": "Feature",
  "properties": {
    "gn:admin1_code":"74.0",
    "gn:admin2_code":"1010.0",
    "gn:admin3_code":"101007.0",
    "gn:asciiname":"Kolonia Reczno",
    "gn:country_code":"PL",
    "gn:dem":199,
    "gn:feature_class":"P",
    "gn:feature_code":"PPL",
    "gn:name":"Kolonia R\u0119czno",
    "gn:population":0,
    "gn:timezone":"Europe/Warsaw",
    "iso:country":"PL",
    "name:fra_x_preferred":[
        "Kolonia R\u0119czno"
    ],
    "name:pol_x_preferred":[
        "Kolonia R\u0119czno"
    ],
    "name:ukr_x_preferred":[
        "\u041a\u043e\u043b\u044c\u043e\u043d\u0456\u044f-\u0420\u0435\u043d\u0447\u043d\u043e"
    ],
    "wof:name":"Kolonia Reczno",
    "wof:placetype":"locality"
},
  "geometry": {"coordinates":[19.87238,51.18435],"type":"Point"}
}