{
  "type": "Feature",
  "properties": {
    "gn:admin1_code":"73.0",
    "gn:admin2_code":"401.0",
    "gn:admin3_code":"40105.0",
    "gn:asciiname":"Jaranowo",
    "gn:country_code":"PL",
    "gn:dem":93,
    "gn:feature_class":"P",
    "gn:feature_code":"PPL",
    "gn:name":"Jaranowo",
    "gn:population":0,
    "gn:timezone":"Europe/Warsaw",
    "iso:country":"PL",
    "name:ita_x_preferred":[
        "Jaranowo"
    ],
    "name:pol_x_preferred":[
        "Jaranowo"
    ],
    "name:ukr_x_preferred":[
        "\u042f\u0440\u0430\u043d\u043e\u0432\u043e"
    ],
    "name:urd_x_preferred":[
        "\u062c\u0691\u0627\u0646\u0648\u0648\u0648"
    ],
    "wof:name":"Jaranowo",
    "wof:placetype":"locality"
},
  "geometry": {"coordinates":[18.8122,52.69719],"type":"Point"}
}