{
  "type": "Feature",
  "properties": {
    "iso:country":"PL",
    "name:eng_x_preferred":[
        "Gorczyn"
    ],
    "name:pol_x_preferred":[
        "G\u00f3rczyn"
    ],
    "wof:name":"Gorczyn",
    "wof:placetype":"neighbourhood"
},
  "geometry": {"coordinates":[16.88240050012482,52.38122206798906],"type":"Point"}
}