{
  "type": "Feature",
  "properties": {
    "iso:country":"PL",
    "name:eng_x_preferred":[
        "Gorczyn"
    ],
    "name:fra_x_preferred":[
        "Gorczyn"
    ],
    "name:pol_x_preferred":[
        "G\u00f3rczyn"
    ],
    "name:pol_x_variant":[
        "Gorczyn"
    ],
    "name:ukr_x_preferred":[
        "\u0490\u043e\u0440\u0447\u0438\u043d"
    ],
    "wof:name":"Gorczyn",
    "wof:placetype":"neighbourhood"
},
  "geometry": {"coordinates":[16.88240050012482,52.38122206798906],"type":"Point"}
}