{
  "type": "Feature",
  "properties": {
    "gn:admin1_code":"85.0",
    "gn:admin2_code":"2801.0",
    "gn:admin3_code":"280103.0",
    "gn:asciiname":"Spytajny",
    "gn:cc2":"PL",
    "gn:country_code":"PL",
    "gn:dem":65,
    "gn:feature_class":"P",
    "gn:feature_code":"PPL",
    "gn:name":"Spytajny",
    "gn:population":0,
    "gn:timezone":"Europe/Warsaw",
    "iso:country":"PL",
    "name:fra_x_preferred":[
        "Spytajny"
    ],
    "name:pol_x_preferred":[
        "Spytajny"
    ],
    "name:ukr_x_preferred":[
        "\u0421\u043f\u0438\u0442\u0430\u0439\u043d\u0438"
    ],
    "name:und_x_variant":[
        "Spittehnen"
    ],
    "name:vie_x_preferred":[
        "Spytajny"
    ],
    "wof:name":"Spytajny",
    "wof:placetype":"locality"
},
  "geometry": {"coordinates":[20.75778,54.25083000000001],"type":"Point"}
}