{
  "type": "Feature",
  "properties": {
    "gn:admin1_code":"85.0",
    "gn:admin2_code":"2801.0",
    "gn:admin3_code":"280103.0",
    "gn:asciiname":"Spytajny",
    "gn:cc2":"PL",
    "gn:country_code":"PL",
    "gn:dem":65,
    "gn:feature_class":"P",
    "gn:feature_code":"PPL",
    "gn:name":"Spytajny",
    "gn:population":0,
    "gn:timezone":"Europe/Warsaw",
    "iso:country":"PL",
    "name:und_x_variant":[
        "Spittehnen",
        "Spytajny"
    ],
    "wof:name":"Spytajny",
    "wof:placetype":"locality"
},
  "geometry": {"coordinates":[20.75778,54.25083000000001],"type":"Point"}
}