{
  "type": "Feature",
  "properties": {
    "gn:admin1_code":"75.0",
    "gn:admin2_code":"606.0",
    "gn:admin3_code":"60609.0",
    "gn:asciiname":"Majdan Kobylanski",
    "gn:country_code":"PL",
    "gn:dem":259,
    "gn:feature_class":"P",
    "gn:feature_code":"PPL",
    "gn:name":"Majdan Kobyla\u0144ski",
    "gn:population":0,
    "gn:timezone":"Europe/Warsaw",
    "iso:country":"PL",
    "name:fra_x_preferred":[
        "Majdan Kobyla\u0144ski"
    ],
    "name:pol_x_preferred":[
        "Majdan Kobyla\u0144ski"
    ],
    "name:ukr_x_preferred":[
        "\u041c\u0430\u0439\u0434\u0430\u043d-\u041a\u043e\u0431\u0438\u043b\u044f\u043d\u0441\u044c\u043a\u0438\u0439"
    ],
    "wof:name":"Majdan Kobylanski",
    "wof:placetype":"locality"
},
  "geometry": {"coordinates":[23.0159,50.89019],"type":"Point"}
}