{
  "type": "Feature",
  "properties": {
    "gn:admin1_code":"75.0",
    "gn:admin2_code":"606.0",
    "gn:admin3_code":"60609.0",
    "gn:asciiname":"Majdan Kobylanski",
    "gn:country_code":"PL",
    "gn:dem":259,
    "gn:feature_class":"P",
    "gn:feature_code":"PPL",
    "gn:name":"Majdan Kobyla\u0144ski",
    "gn:population":0,
    "gn:timezone":"Europe/Warsaw",
    "iso:country":"PL",
    "name:und_x_variant":[
        "Majdan Kobyla\u0144ski"
    ],
    "wof:name":"Majdan Kobylanski",
    "wof:placetype":"locality"
},
  "geometry": {"coordinates":[23.0159,50.89019],"type":"Point"}
}