{
  "type": "Feature",
  "properties": {
    "iso:country":"PL",
    "name:eng_x_preferred":[
        "Zacisze-Zalesie-Szczytniki"
    ],
    "name:pol_x_preferred":[
        "Zacisze-Zalesie-Szczytniki"
    ],
    "wof:name":"Zacisze-Zalesie-Szczytniki",
    "wof:placetype":"neighbourhood"
},
  "geometry": {"coordinates":[17.08492948991512,51.12092241586063],"type":"Point"}
}