{
  "type": "Feature",
  "properties": {
    "gn:gn_country":"PL",
    "gn:gn_fcode":"PPLA3",
    "gn:gn_pop":2955,
    "gn:population":2955,
    "iso:country":"PL",
    "name:ceb_x_preferred":[
        "Ka\u0142uszyn"
    ],
    "name:deu_x_preferred":[
        "Ka\u0142uszyn"
    ],
    "name:eng_x_preferred":[
        "Ka\u0142uszyn"
    ],
    "name:epo_x_preferred":[
        "Ka\u0142uszyn"
    ],
    "name:est_x_preferred":[
        "Ka\u0142uszyn"
    ],
    "name:fra_x_preferred":[
        "Ka\u0142uszyn"
    ],
    "name:heb_x_preferred":[
        "\u05e7\u05d0\u05dc\u05d5\u05e9\u05d9\u05df"
    ],
    "name:jav_x_preferred":[
        "Ka\u0142uszyn"
    ],
    "name:lav_x_preferred":[
        "Kalu\u0161ina"
    ],
    "name:msa_x_preferred":[
        "Ka\u0142uszyn"
    ],
    "name:nld_x_preferred":[
        "Ka\u0142uszyn"
    ],
    "name:pol_x_preferred":[
        "Ka\u0142uszyn"
    ],
    "name:por_x_preferred":[
        "Ka\u0142uszyn"
    ],
    "name:ron_x_preferred":[
        "Ka\u0142uszyn"
    ],
    "name:rus_x_preferred":[
        "\u041a\u0430\u043b\u0443\u0448\u0438\u043d"
    ],
    "name:slk_x_preferred":[
        "Ka\u0142uszyn"
    ],
    "name:spa_x_preferred":[
        "Ka\u0142uszyn"
    ],
    "name:srp_x_preferred":[
        "\u041a\u0430\u043b\u0443\u0448\u0438\u043d"
    ],
    "name:szl_x_preferred":[
        "Ka\u0142uszyn"
    ],
    "name:ukr_x_preferred":[
        "\u041a\u0430\u043b\u0443\u0448\u0438\u043d"
    ],
    "name:unk_x_variant":[
        "Kalushin"
    ],
    "name:uzb_x_preferred":[
        "Kalushin"
    ],
    "name:vie_x_preferred":[
        "Ka\u0142uszyn"
    ],
    "name:zho_x_preferred":[
        "\u5361\u6b66\u7533"
    ],
    "qs_pg:aaroncc":"PL",
    "qs_pg:gn_country":"PL",
    "qs_pg:gn_fcode":"PPLA3",
    "qs_pg:gn_pop":2955,
    "qs_pg:name":"Ka\u0142uszyn",
    "qs_pg:name_adm0":"Polska",
    "qs_pg:name_adm1":"Mazowieckie",
    "qs_pg:photos":1,
    "qs_pg:photos_1k":1,
    "qs_pg:photos_9k":1,
    "qs_pg:photos_9r":1,
    "qs_pg:photos_all":1,
    "qs_pg:photos_sr":1,
    "qs_pg:pop_sr":7,
    "qs_pg:qs_pg_placetype":"localadmin",
    "qs_pg:qs_pg_placetype_gp":"LocalAdmin",
    "qs_pg:woe_adm0":23424923,
    "woe:adm0_id":23424923,
    "woe:name_adm0":"Polska",
    "woe:name_adm1":"Mazowieckie",
    "woe:placetype":"LocalAdmin",
    "wof:name":"Ka\u0142uszyn",
    "wof:placetype":"localadmin",
    "wof:population":2955
},
  "geometry": {"coordinates":[21.80838,52.20669],"type":"Point"}
}