{
  "type": "Feature",
  "properties": {
    "gn:country":"PL",
    "gn:fcode":"PPL",
    "gn:population":480,
    "iso:country":"PL",
    "name:azb_x_preferred":[
        "\u06a9\u06cc\u06cc\u0648\u0648 \u06a9\u0631\u0648\u0644\u0648\u0633\u06a9\u06cc\u0647"
    ],
    "name:ceb_x_preferred":[
        "Kijewo Kr\u00f3lewskie"
    ],
    "name:deu_x_preferred":[
        "Kijewo Kr\u00f3lewskie"
    ],
    "name:fas_x_preferred":[
        "\u06a9\u06cc\u06cc\u0648\u0648 \u06a9\u0631\u0648\u0644\u0648\u0633\u06a9\u06cc\u0647"
    ],
    "name:nld_x_preferred":[
        "Kijewo Kr\u00f3lewskie"
    ],
    "name:pol_x_preferred":[
        "Kijewo Kr\u00f3lewskie"
    ],
    "name:ukr_x_preferred":[
        "\u041a\u0438\u0454\u0432\u043e-\u041a\u0440\u0443\u043b\u0435\u0432\u0441\u044c\u043a\u0435"
    ],
    "name:und_x_variant":[
        "Kijewo"
    ],
    "qs_pg:aaroncc":"PL",
    "qs_pg:gn_country":"PL",
    "qs_pg:gn_fcode":"PPL",
    "qs_pg:gn_pop":480,
    "qs_pg:name":"Kijewo Kr\u00f3lewskie",
    "qs_pg:name_adm0":"Polska",
    "qs_pg:name_adm1":"Kujawsko-Pomorskie",
    "qs_pg:photos_9k":1,
    "qs_pg:photos_9r":1,
    "qs_pg:photos_all":1,
    "qs_pg:photos_sr":0,
    "qs_pg:pop_sr":2,
    "qs_pg:qs_pg_placetype":"locality",
    "qs_pg:qs_pg_placetype_gp":"Town",
    "qs_pg:woe_adm0":23424923,
    "woe:adm0_id":23424923,
    "woe:name_adm0":"Polska",
    "woe:name_adm1":"Kujawsko-Pomorskie",
    "woe:placetype":"Town",
    "wof:coterminous":[
        1477751359
    ],
    "wof:name":"Kijewo Kr\u00f3lewskie",
    "wof:placetype":"locality",
    "wof:population":480
},
  "geometry": {"coordinates":[18.44407,53.27296],"type":"Point"}
}