{
  "type": "Feature",
  "properties": {
    "gn:admin1_code":"82.0",
    "gn:admin2_code":"2213.0",
    "gn:admin3_code":"221312.0",
    "gn:asciiname":"Brzezno Wielkie",
    "gn:country_code":"PL",
    "gn:dem":63,
    "gn:feature_class":"P",
    "gn:feature_code":"PPL",
    "gn:name":"Brze\u017ano Wielkie",
    "gn:population":0,
    "gn:timezone":"Europe/Warsaw",
    "iso:country":"PL",
    "name:azb_x_preferred":[
        "\u0628\u0698\u0698\u0646\u0648 \u0648\u06cc\u0644\u06a9\u06cc\u0647"
    ],
    "name:ceb_x_preferred":[
        "Brze\u017ano Wielkie"
    ],
    "name:fas_x_preferred":[
        "\u0628\u0698\u0698\u0646\u0648 \u0648\u06cc\u0644\u06a9\u06cc\u0647"
    ],
    "name:nld_x_preferred":[
        "Brze\u017ano Wielkie"
    ],
    "name:pol_x_preferred":[
        "Brze\u017ano Wielkie"
    ],
    "name:ukr_x_preferred":[
        "\u0411\u0436\u0435\u0437\u044c\u043d\u043e-\u0412\u0435\u043b\u0438\u043a\u0435"
    ],
    "name:urd_x_preferred":[
        "\u0628\u0631\u0632\u06d2\u0632\u0646\u0648 \u0648\u06cc\u0644\u06a9\u0626\u06cc"
    ],
    "wof:name":"Brzezno Wielkie",
    "wof:placetype":"locality"
},
  "geometry": {"coordinates":[18.64716,53.99029],"type":"Point"}
}