{
  "type": "Feature",
  "properties": {
    "gn:admin1_code":"86.0",
    "gn:admin2_code":"3030.0",
    "gn:admin3_code":"303001.0",
    "gn:asciiname":"Lagiewki",
    "gn:country_code":"PL",
    "gn:dem":94,
    "gn:feature_class":"P",
    "gn:feature_code":"PPL",
    "gn:name":"\u0141agiewki",
    "gn:population":0,
    "gn:timezone":"Europe/Warsaw",
    "iso:country":"PL",
    "name:fra_x_preferred":[
        "\u0141agiewki"
    ],
    "name:pol_x_preferred":[
        "\u0141agiewki"
    ],
    "name:ukr_x_preferred":[
        "\u041b\u0430\u0491\u0435\u0432\u043a\u0456"
    ],
    "wof:name":"Lagiewki",
    "wof:placetype":"locality"
},
  "geometry": {"coordinates":[17.59006,52.21003],"type":"Point"}
}