{
  "type": "Feature",
  "properties": {
    "gn:admin1_code":"74.0",
    "gn:admin2_code":"1002.0",
    "gn:admin3_code":"100202.0",
    "gn:asciiname":"Garbow",
    "gn:country_code":"PL",
    "gn:dem":98,
    "gn:feature_class":"P",
    "gn:feature_code":"PPL",
    "gn:name":"Garb\u00f3w",
    "gn:population":134,
    "gn:timezone":"Europe/Warsaw",
    "iso:country":"PL",
    "name:ceb_x_preferred":[
        "Garb\u00f3w"
    ],
    "name:fra_x_preferred":[
        "Garb\u00f3w"
    ],
    "name:pol_x_preferred":[
        "Garb\u00f3w"
    ],
    "name:ukr_x_preferred":[
        "\u0490\u0430\u0440\u0431\u0443\u0432"
    ],
    "wof:name":"Garbow",
    "wof:placetype":"locality",
    "wof:population":134
},
  "geometry": {"coordinates":[19.59034,52.15735],"type":"Point"}
}