{
  "type": "Feature",
  "properties": {
    "gn:admin1_code":"74.0",
    "gn:admin2_code":"1002.0",
    "gn:admin3_code":"100202.0",
    "gn:asciiname":"Garbow",
    "gn:country_code":"PL",
    "gn:dem":98,
    "gn:feature_class":"P",
    "gn:feature_code":"PPL",
    "gn:name":"Garb\u00f3w",
    "gn:population":134,
    "gn:timezone":"Europe/Warsaw",
    "iso:country":"PL",
    "wof:name":"Garbow",
    "wof:placetype":"locality",
    "wof:population":134
},
  "geometry": {"coordinates":[19.59034,52.15735],"type":"Point"}
}