{
  "type": "Feature",
  "properties": {
    "gn:admin1_code":"74.0",
    "gn:admin2_code":"1015.0",
    "gn:admin3_code":"101507.0",
    "gn:asciiname":"Esterka",
    "gn:country_code":"PL",
    "gn:dem":144,
    "gn:feature_class":"P",
    "gn:feature_code":"PPL",
    "gn:name":"Esterka",
    "gn:population":0,
    "gn:timezone":"Europe/Warsaw",
    "iso:country":"PL",
    "name:pol_x_preferred":[
        "Esterka"
    ],
    "name:ukr_x_preferred":[
        "\u0415\u0441\u0442\u0435\u0440\u043a\u0430"
    ],
    "wof:name":"Esterka",
    "wof:placetype":"locality"
},
  "geometry": {"coordinates":[20.32984,51.88875],"type":"Point"}
}