{
  "type": "Feature",
  "properties": {
    "gn:admin1_code":"86.0",
    "gn:admin2_code":"3025.0",
    "gn:admin3_code":"302502.0",
    "gn:asciiname":"Miaskowo",
    "gn:cc2":"PL",
    "gn:country_code":"PL",
    "gn:dem":68,
    "gn:feature_class":"P",
    "gn:feature_code":"PPL",
    "gn:name":"Mi\u0105skowo",
    "gn:population":0,
    "gn:timezone":"Europe/Warsaw",
    "iso:country":"PL",
    "name:fra_x_preferred":[
        "Mi\u0105skowo"
    ],
    "name:pol_x_preferred":[
        "Mi\u0105skowo"
    ],
    "name:ukr_x_preferred":[
        "\u041c\u0439\u043e\u043d\u0441\u043a\u043e\u0432\u043e"
    ],
    "name:und_x_variant":[
        "Miastkowo"
    ],
    "wof:name":"Miaskowo",
    "wof:placetype":"locality"
},
  "geometry": {"coordinates":[17.37968,52.16398],"type":"Point"}
}