{
  "type": "Feature",
  "properties": {
    "gn:admin1_code":"78.0",
    "gn:admin2_code":"1426.0",
    "gn:admin3_code":"142609.0",
    "gn:asciiname":"Ozorow",
    "gn:country_code":"PL",
    "gn:dem":170,
    "gn:feature_class":"P",
    "gn:feature_code":"PPL",
    "gn:name":"Ozor\u00f3w",
    "gn:population":0,
    "gn:timezone":"Europe/Warsaw",
    "iso:country":"PL",
    "name:ceb_x_preferred":[
        "Ozor\u00f3w"
    ],
    "name:fra_x_preferred":[
        "Ozor\u00f3w"
    ],
    "name:pol_x_preferred":[
        "Ozor\u00f3w"
    ],
    "name:ukr_x_preferred":[
        "\u041e\u0437\u043e\u0440\u0443\u0432"
    ],
    "wof:name":"Ozorow",
    "wof:placetype":"locality"
},
  "geometry": {"coordinates":[22.02785,52.12342],"type":"Point"}
}