{
  "type": "Feature",
  "properties": {
    "gn:admin1_code":"74.0",
    "gn:admin2_code":"1007.0",
    "gn:admin3_code":"100702.0",
    "gn:asciiname":"Strzeszkowice",
    "gn:country_code":"PL",
    "gn:dem":167,
    "gn:feature_class":"P",
    "gn:feature_code":"PPL",
    "gn:name":"Strzeszkowice",
    "gn:population":0,
    "gn:timezone":"Europe/Warsaw",
    "iso:country":"PL",
    "name:pol_x_preferred":[
        "Strzeszkowice"
    ],
    "name:ukr_x_preferred":[
        "\u0421\u0442\u0448\u0435\u0448\u043a\u043e\u0432\u0456\u0446\u0435"
    ],
    "wof:name":"Strzeszkowice",
    "wof:placetype":"locality"
},
  "geometry": {"coordinates":[20.36397,51.44249],"type":"Point"}
}