{
  "type": "Feature",
  "properties": {
    "gn:admin1_code":"86.0",
    "gn:admin2_code":"3009.0",
    "gn:admin3_code":"300906.0",
    "gn:asciiname":"Wolka Czepowa",
    "gn:cc2":"PL",
    "gn:country_code":"PL",
    "gn:dem":122,
    "gn:feature_class":"P",
    "gn:feature_code":"PPL",
    "gn:name":"W\u00f3lka Czepowa",
    "gn:population":0,
    "gn:timezone":"Europe/Warsaw",
    "iso:country":"PL",
    "name:und_x_variant":[
        "W\u00f3lka",
        "W\u00f3lka Czepowa"
    ],
    "wof:name":"Wolka Czepowa",
    "wof:placetype":"locality"
},
  "geometry": {"coordinates":[18.94077,52.23201],"type":"Point"}
}