{
  "type": "Feature",
  "properties": {
    "gn:country":"PL",
    "gn:fcode":"PPL",
    "gn:population":210,
    "iso:country":"PL",
    "name:ceb_x_preferred":[
        "Trzciana"
    ],
    "name:deu_x_preferred":[
        "Trzciana"
    ],
    "name:nld_x_preferred":[
        "Trzciana"
    ],
    "name:pol_x_preferred":[
        "Trzciana"
    ],
    "name:rus_x_preferred":[
        "\u0422\u0448\u0446\u044f\u043d\u0430"
    ],
    "name:ukr_x_preferred":[
        "\u0422\u0448\u0446\u044f\u043d\u0430"
    ],
    "name:urd_x_preferred":[
        "\u0686\u0686\u0627\u0646\u0627"
    ],
    "qs_pg:aaroncc":"PL",
    "qs_pg:gn_country":"PL",
    "qs_pg:gn_fcode":"PPL",
    "qs_pg:gn_pop":210,
    "qs_pg:name":"Trzciana",
    "qs_pg:name_adm0":"Polska",
    "qs_pg:name_adm1":"Podkarpackie",
    "qs_pg:photos_9r":0,
    "qs_pg:photos_sr":0,
    "qs_pg:pop_sr":2,
    "qs_pg:qs_pg_placetype":"locality",
    "qs_pg:qs_pg_placetype_gp":"Town",
    "qs_pg:woe_adm0":23424923,
    "woe:adm0_id":23424923,
    "woe:name_adm0":"Polska",
    "woe:name_adm1":"Podkarpackie",
    "woe:placetype":"Town",
    "wof:name":"Trzciana",
    "wof:placetype":"locality",
    "wof:population":210
},
  "geometry": {"coordinates":[21.69937,49.50147],"type":"Point"}
}