{
  "type": "Feature",
  "properties": {
    "iso:country":"PL",
    "name:pol_x_preferred":[
        "Ulh\u00f3wek"
    ],
    "wof:coterminous":[
        1125375727
    ],
    "wof:name":"Ulh\u00f3wek",
    "wof:placetype":"locality"
},
  "geometry": {"coordinates":[23.8005532393265,50.4456078677959],"type":"Point"}
}