{
  "type": "Feature",
  "properties": {
    "iso:country":"PL",
    "name:azb_x_preferred":[
        "\u0627\u0648\u0644\u062e\u0648\u0648\u06a9"
    ],
    "name:fas_x_preferred":[
        "\u0627\u0648\u0644\u062e\u0648\u0648\u06a9"
    ],
    "name:fra_x_preferred":[
        "Ulh\u00f3wek"
    ],
    "name:nld_x_preferred":[
        "Ulh\u00f3wek"
    ],
    "name:pol_x_preferred":[
        "Ulh\u00f3wek"
    ],
    "name:ukr_x_preferred":[
        "\u0423\u043b\u044c\u0433\u0456\u0432\u043e\u043a"
    ],
    "wof:coterminous":[
        1125375727
    ],
    "wof:name":"Ulh\u00f3wek",
    "wof:placetype":"locality"
},
  "geometry": {"coordinates":[23.8005532393265,50.4456078677959],"type":"Point"}
}