{
  "type": "Feature",
  "properties": {
    "gn:admin1_code":"72.0",
    "gn:admin2_code":"208.0",
    "gn:admin3_code":"20804.0",
    "gn:asciiname":"Zagorzno",
    "gn:country_code":"PL",
    "gn:dem":556,
    "gn:feature_class":"P",
    "gn:feature_code":"PPL",
    "gn:name":"Zag\u00f3rzno",
    "gn:population":0,
    "gn:timezone":"Europe/Warsaw",
    "iso:country":"PL",
    "wof:name":"Zagorzno",
    "wof:placetype":"locality"
},
  "geometry": {"coordinates":[16.53333,50.53333],"type":"Point"}
}