{
  "type": "Feature",
  "properties": {
    "gn:admin1_code":"75.0",
    "gn:admin2_code":"606.0",
    "gn:admin3_code":"60606.0",
    "gn:asciiname":"Surhow",
    "gn:country_code":"PL",
    "gn:dem":191,
    "gn:feature_class":"P",
    "gn:feature_code":"PPL",
    "gn:name":"Surh\u00f3w",
    "gn:population":0,
    "gn:timezone":"Europe/Warsaw",
    "iso:country":"PL",
    "name:fra_x_preferred":[
        "Surh\u00f3w"
    ],
    "name:pol_x_preferred":[
        "Surh\u00f3w"
    ],
    "name:ukr_x_preferred":[
        "\u0421\u0443\u0440\u0433\u0443\u0432"
    ],
    "name:und_x_variant":[
        "Surch\u00f3w"
    ],
    "wof:name":"Surhow",
    "wof:placetype":"locality"
},
  "geometry": {"coordinates":[23.25953,50.93494000000001],"type":"Point"}
}