{
  "type": "Feature",
  "properties": {
    "gn:admin1_code":"75.0",
    "gn:admin2_code":"620.0",
    "gn:admin3_code":"62007.0",
    "gn:asciiname":"Gruszka Duza",
    "gn:country_code":"PL",
    "gn:dem":204,
    "gn:feature_class":"P",
    "gn:feature_code":"PPL",
    "gn:name":"Gruszka Du\u017ca",
    "gn:population":0,
    "gn:timezone":"Europe/Warsaw",
    "iso:country":"PL",
    "name:und_x_variant":[
        "Du\u017ca",
        "Gruszka Wielka",
        "Gruszka Du\u017ca"
    ],
    "wof:name":"Gruszka Duza",
    "wof:placetype":"locality"
},
  "geometry": {"coordinates":[22.97081,50.8109],"type":"Point"}
}