{
  "type": "Feature",
  "properties": {
    "gn:admin1_code":"75.0",
    "gn:admin2_code":"620.0",
    "gn:admin3_code":"62007.0",
    "gn:asciiname":"Gruszka Duza",
    "gn:country_code":"PL",
    "gn:dem":204,
    "gn:feature_class":"P",
    "gn:feature_code":"PPL",
    "gn:name":"Gruszka Du\u017ca",
    "gn:population":0,
    "gn:timezone":"Europe/Warsaw",
    "iso:country":"PL",
    "name:azb_x_preferred":[
        "\u0642\u0631\u0648\u0634\u06a9\u0627 \u062f\u0648\u0698\u0627"
    ],
    "name:fas_x_preferred":[
        "\u06af\u0631\u0648\u0634\u06a9\u0627 \u062f\u0648\u0698\u0627"
    ],
    "name:fra_x_preferred":[
        "Gruszka Du\u017ca"
    ],
    "name:pol_x_preferred":[
        "Gruszka Du\u017ca"
    ],
    "name:rus_x_preferred":[
        "\u0413\u0440\u0443\u0448\u043a\u0430-\u0414\u0443\u0436\u0430"
    ],
    "name:ukr_x_preferred":[
        "\u0490\u0440\u0443\u0448\u043a\u0430-\u0414\u0443\u0436\u0430"
    ],
    "name:und_x_variant":[
        "Du\u017ca",
        "Gruszka Wielka"
    ],
    "wof:name":"Gruszka Duza",
    "wof:placetype":"locality"
},
  "geometry": {"coordinates":[22.97081,50.8109],"type":"Point"}
}