{
  "type": "Feature",
  "properties": {
    "gn:admin1_code":"82.0",
    "gn:admin2_code":"2210.0",
    "gn:admin3_code":"221002.0",
    "gn:asciiname":"Starocin",
    "gn:country_code":"PL",
    "gn:dem":-3,
    "gn:feature_class":"P",
    "gn:feature_code":"PPL",
    "gn:name":"Starocin",
    "gn:population":0,
    "gn:timezone":"Europe/Warsaw",
    "iso:country":"PL",
    "name:pol_x_preferred":[
        "Starocin"
    ],
    "name:szl_x_preferred":[
        "Staro\u0107in"
    ],
    "name:ukr_x_preferred":[
        "\u0421\u0442\u0430\u0440\u043e\u0446\u0438\u043d"
    ],
    "name:und_x_variant":[
        "Reiland",
        "Reinland"
    ],
    "wof:name":"Starocin",
    "wof:placetype":"locality"
},
  "geometry": {"coordinates":[19.15089,54.22039],"type":"Point"}
}