{
  "type": "Feature",
  "properties": {
    "gn:admin1_code":"82.0",
    "gn:admin2_code":"2210.0",
    "gn:admin3_code":"221002.0",
    "gn:asciiname":"Starocin",
    "gn:country_code":"PL",
    "gn:dem":-3,
    "gn:feature_class":"P",
    "gn:feature_code":"PPL",
    "gn:name":"Starocin",
    "gn:population":0,
    "gn:timezone":"Europe/Warsaw",
    "iso:country":"PL",
    "name:und_x_variant":[
        "Reiland",
        "Reinland",
        "Starocin"
    ],
    "wof:name":"Starocin",
    "wof:placetype":"locality"
},
  "geometry": {"coordinates":[19.15089,54.22039],"type":"Point"}
}