{
  "type": "Feature",
  "properties": {
    "gn:admin1_code":"82.0",
    "gn:admin2_code":"2209.0",
    "gn:admin3_code":"220907.0",
    "gn:asciiname":"Pregowo",
    "gn:country_code":"PL",
    "gn:dem":1,
    "gn:feature_class":"P",
    "gn:feature_code":"PPL",
    "gn:name":"Pr\u0119gowo",
    "gn:population":0,
    "gn:timezone":"Europe/Warsaw",
    "iso:country":"PL",
    "name:und_x_variant":[
        "Prangenau",
        "Pr\u0105gowo",
        "Pr\u0119gowo"
    ],
    "wof:name":"Pregowo",
    "wof:placetype":"locality"
},
  "geometry": {"coordinates":[18.92969,54.15754],"type":"Point"}
}