{
  "type": "Feature",
  "properties": {
    "iso:country":"PL",
    "name:pol_x_preferred":[
        "Konstantyn\u00f3w"
    ],
    "wof:name":"Konstantynow",
    "wof:placetype":"neighbourhood"
},
  "geometry": {"coordinates":[21.02816651876164,52.31635783386131],"type":"Point"}
}