{
  "type": "Feature",
  "properties": {
    "gn:admin1_code":"75.0",
    "gn:admin2_code":"608.0",
    "gn:admin3_code":"60808.0",
    "gn:asciiname":"Chudowola",
    "gn:country_code":"PL",
    "gn:dem":134,
    "gn:feature_class":"P",
    "gn:feature_code":"PPL",
    "gn:name":"Chudowola",
    "gn:population":0,
    "gn:timezone":"Europe/Warsaw",
    "iso:country":"PL",
    "name:fra_x_preferred":[
        "Chudowola"
    ],
    "name:pol_x_preferred":[
        "Chudowola"
    ],
    "name:ukr_x_preferred":[
        "\u0425\u0443\u0434\u043e\u0432\u043e\u043b\u044f"
    ],
    "wof:name":"Chudowola",
    "wof:placetype":"locality"
},
  "geometry": {"coordinates":[22.31358,51.56949],"type":"Point"}
}