{
  "type": "Feature",
  "properties": {
    "gn:admin1_code":"82.0",
    "gn:admin2_code":"2216.0",
    "gn:admin3_code":"221601.0",
    "gn:asciiname":"Minieta",
    "gn:country_code":"PL",
    "gn:dem":56,
    "gn:feature_class":"P",
    "gn:feature_code":"PPL",
    "gn:name":"Mini\u0119ta",
    "gn:population":0,
    "gn:timezone":"Europe/Warsaw",
    "iso:country":"PL",
    "name:und_x_variant":[
        "Menthen",
        "Mini\u0119ta"
    ],
    "wof:name":"Minieta",
    "wof:placetype":"locality"
},
  "geometry": {"coordinates":[19.33662,53.88704],"type":"Point"}
}