{
  "type": "Feature",
  "properties": {
    "gn:admin1_code":"74.0",
    "gn:admin2_code":"1014.0",
    "gn:admin3_code":"101405.0",
    "gn:asciiname":"Gronow",
    "gn:country_code":"PL",
    "gn:dem":174,
    "gn:feature_class":"P",
    "gn:feature_code":"PPL",
    "gn:name":"Gron\u00f3w",
    "gn:population":0,
    "gn:timezone":"Europe/Warsaw",
    "iso:country":"PL",
    "name:und_x_variant":[
        "Gron\u00f3w"
    ],
    "wof:name":"Gronow",
    "wof:placetype":"locality"
},
  "geometry": {"coordinates":[18.72252000000001,51.41298],"type":"Point"}
}