{
  "type": "Feature",
  "properties": {
    "gn:admin1_code":"86.0",
    "gn:admin2_code":"3002.0",
    "gn:admin3_code":"300207.0",
    "gn:asciiname":"Radolin",
    "gn:country_code":"PL",
    "gn:dem":51,
    "gn:feature_class":"P",
    "gn:feature_code":"PPL",
    "gn:name":"Radolin",
    "gn:population":0,
    "gn:timezone":"Europe/Warsaw",
    "iso:country":"PL",
    "wof:name":"Radolin",
    "wof:placetype":"locality"
},
  "geometry": {"coordinates":[16.54409,53.00864],"type":"Point"}
}