{
  "type": "Feature",
  "properties": {
    "gn:admin1_code":"86.0",
    "gn:admin2_code":"3002.0",
    "gn:admin3_code":"300207.0",
    "gn:asciiname":"Radolin",
    "gn:country_code":"PL",
    "gn:dem":51,
    "gn:feature_class":"P",
    "gn:feature_code":"PPL",
    "gn:name":"Radolin",
    "gn:population":0,
    "gn:timezone":"Europe/Warsaw",
    "iso:country":"PL",
    "name:azb_x_preferred":[
        "\u0631\u0627\u062f\u0648\u0644\u06cc\u0646"
    ],
    "name:deu_x_preferred":[
        "Radolin"
    ],
    "name:fas_x_preferred":[
        "\u0631\u0627\u062f\u0648\u0644\u06cc\u0646"
    ],
    "name:fra_x_preferred":[
        "Radolin"
    ],
    "name:pol_x_preferred":[
        "Radolin"
    ],
    "name:ukr_x_preferred":[
        "\u0420\u0430\u0434\u043e\u043b\u0456\u043d"
    ],
    "wof:name":"Radolin",
    "wof:placetype":"locality"
},
  "geometry": {"coordinates":[16.54409,53.00864],"type":"Point"}
}