{
  "type": "Feature",
  "properties": {
    "gn:admin1_code":"78.0",
    "gn:admin2_code":"1411.0",
    "gn:admin3_code":"141103.0",
    "gn:asciiname":"Romanowo",
    "gn:country_code":"PL",
    "gn:dem":118,
    "gn:feature_class":"P",
    "gn:feature_code":"PPL",
    "gn:name":"Romanowo",
    "gn:population":0,
    "gn:timezone":"Europe/Warsaw",
    "iso:country":"PL",
    "name:fra_x_preferred":[
        "Romanowo"
    ],
    "name:pol_x_preferred":[
        "Romanowo"
    ],
    "name:ukr_x_preferred":[
        "\u0420\u043e\u043c\u0430\u043d\u043e\u0432\u043e"
    ],
    "wof:name":"Romanowo",
    "wof:placetype":"locality"
},
  "geometry": {"coordinates":[21.02483,52.87664],"type":"Point"}
}