{
  "type": "Feature",
  "properties": {
    "gn:gn_country":"PL",
    "gn:gn_fcode":"PPL",
    "gn:gn_pop":720,
    "gn:population":720,
    "iso:country":"PL",
    "name:csb_x_preferred":[
        "Pr\u00e3g\u00f2w\u00f2"
    ],
    "name:eng_x_preferred":[
        "Pr\u0119gowo"
    ],
    "name:fre_x_preferred":[
        "Pr\u0119gowo"
    ],
    "name:pol_x_preferred":[
        "Pr\u0119gowo"
    ],
    "name:unk_x_variant":[
        "Nieder Prangenau"
    ],
    "qs_pg:aaroncc":"PL",
    "qs_pg:gn_country":"PL",
    "qs_pg:gn_fcode":"PPL",
    "qs_pg:gn_pop":720,
    "qs_pg:name":"Pr\u0119gowo",
    "qs_pg:photos_9r":0,
    "qs_pg:photos_sr":0,
    "qs_pg:pop_sr":2,
    "qs_pg:qs_pg_placetype":"locality",
    "wof:name":"Pr\u0119gowo",
    "wof:placetype":"locality",
    "wof:population":720
},
  "geometry": {"coordinates":[18.47969,54.25419],"type":"Point"}
}