{
  "type": "Feature",
  "properties": {
    "gn:admin1_code":"78.0",
    "gn:admin2_code":"1437.0",
    "gn:admin3_code":"143703.0",
    "gn:asciiname":"Dziwy",
    "gn:country_code":"PL",
    "gn:dem":134,
    "gn:feature_class":"P",
    "gn:feature_code":"PPL",
    "gn:name":"Dziwy",
    "gn:population":0,
    "gn:timezone":"Europe/Warsaw",
    "iso:country":"PL",
    "name:azb_x_preferred":[
        "\u062c\u0648\u0647"
    ],
    "name:fas_x_preferred":[
        "\u062c\u0648\u0647"
    ],
    "name:fra_x_preferred":[
        "Dziwy"
    ],
    "name:pol_x_preferred":[
        "Dziwy"
    ],
    "name:ukr_x_preferred":[
        "\u0414\u0437\u0456\u0432\u0438"
    ],
    "wof:name":"Dziwy",
    "wof:placetype":"locality"
},
  "geometry": {"coordinates":[19.8124,53.10891],"type":"Point"}
}