{
  "type": "Feature",
  "properties": {
    "iso:country":"PL",
    "name:pol_x_preferred":[
        "B\u0142onie"
    ],
    "wof:name":"Blonie",
    "wof:placetype":"neighbourhood"
},
  "geometry": {"coordinates":[20.17606528165631,50.07121305294559],"type":"Point"}
}