{
  "type": "Feature",
  "properties": {
    "gn:admin1_code":"81.0",
    "gn:admin2_code":"2002.0",
    "gn:admin3_code":"200215.0",
    "gn:asciiname":"Grabowo Nowe",
    "gn:country_code":"PL",
    "gn:dem":118,
    "gn:feature_class":"P",
    "gn:feature_code":"PPL",
    "gn:name":"Grabowo Nowe",
    "gn:population":0,
    "gn:timezone":"Europe/Warsaw",
    "iso:country":"PL",
    "wof:name":"Grabowo Nowe",
    "wof:placetype":"locality"
},
  "geometry": {"coordinates":[22.54993,53.13151],"type":"Point"}
}