{
  "type": "Feature",
  "properties": {
    "gn:admin1_code":"74.0",
    "gn:admin2_code":"1012.0",
    "gn:admin3_code":"101210.0",
    "gn:asciiname":"Strzelce Male",
    "gn:country_code":"PL",
    "gn:dem":210,
    "gn:feature_class":"P",
    "gn:feature_code":"PPL",
    "gn:name":"Strzelce Ma\u0142e",
    "gn:population":0,
    "gn:timezone":"Europe/Warsaw",
    "iso:country":"PL",
    "name:fra_x_preferred":[
        "Strzelce Ma\u0142e"
    ],
    "name:pol_x_preferred":[
        "Strzelce Ma\u0142e"
    ],
    "name:ukr_x_preferred":[
        "\u0421\u0442\u0448\u0435\u043b\u044c\u0446\u0435-\u041c\u0430\u043b\u0456"
    ],
    "wof:name":"Strzelce Male",
    "wof:placetype":"locality"
},
  "geometry": {"coordinates":[19.79648,51.0963],"type":"Point"}
}