{
  "type": "Feature",
  "properties": {
    "gn:admin1_code":"74.0",
    "gn:admin2_code":"1012.0",
    "gn:admin3_code":"101210.0",
    "gn:asciiname":"Strzelce Male",
    "gn:country_code":"PL",
    "gn:dem":210,
    "gn:feature_class":"P",
    "gn:feature_code":"PPL",
    "gn:name":"Strzelce Ma\u0142e",
    "gn:population":0,
    "gn:timezone":"Europe/Warsaw",
    "iso:country":"PL",
    "name:und_x_variant":[
        "Strzelce Ma\u0142e"
    ],
    "wof:name":"Strzelce Male",
    "wof:placetype":"locality"
},
  "geometry": {"coordinates":[19.79648,51.0963],"type":"Point"}
}