{
  "type": "Feature",
  "properties": {
    "gn:admin1_code":"84.0",
    "gn:admin2_code":"2604.0",
    "gn:admin3_code":"260410.0",
    "gn:asciiname":"Cminsk Kobylaki",
    "gn:country_code":"PL",
    "gn:dem":271,
    "gn:feature_class":"P",
    "gn:feature_code":"PPL",
    "gn:name":"\u0106mi\u0144sk Kobylaki",
    "gn:population":0,
    "gn:timezone":"Europe/Warsaw",
    "iso:country":"PL",
    "name:und_x_variant":[
        "Kobylaki",
        "\u0106mi\u0144sk Kobylaki"
    ],
    "wof:name":"Cminsk Kobylaki",
    "wof:placetype":"locality"
},
  "geometry": {"coordinates":[20.5358,50.97793],"type":"Point"}
}