{
  "type": "Feature",
  "properties": {
    "gn:admin1_code":"84.0",
    "gn:admin2_code":"2613.0",
    "gn:admin3_code":"261302.0",
    "gn:asciiname":"Ciesle",
    "gn:country_code":"PL",
    "gn:dem":339,
    "gn:feature_class":"P",
    "gn:feature_code":"PPL",
    "gn:name":"Cie\u015ble",
    "gn:population":0,
    "gn:timezone":"Europe/Warsaw",
    "iso:country":"PL",
    "name:und_x_variant":[
        "Cie\u015ble"
    ],
    "wof:name":"Ciesle",
    "wof:placetype":"locality"
},
  "geometry": {"coordinates":[20.2027,50.84202],"type":"Point"}
}