{
  "type": "Feature",
  "properties": {
    "gn:admin1_code":"86.0",
    "gn:admin2_code":"3021.0",
    "gn:admin3_code":"302114.0",
    "gn:asciiname":"Drozdzyce",
    "gn:country_code":"PL",
    "gn:dem":73,
    "gn:feature_class":"P",
    "gn:feature_code":"PPL",
    "gn:name":"Dro\u017cd\u017cyce",
    "gn:population":0,
    "gn:timezone":"Europe/Warsaw",
    "iso:country":"PL",
    "name:fra_x_preferred":[
        "Dro\u017cd\u017cyce"
    ],
    "name:pol_x_preferred":[
        "Dro\u017cd\u017cyce"
    ],
    "name:ukr_x_preferred":[
        "\u0414\u0440\u043e\u0436\u0434\u0436\u0438\u0446\u0435"
    ],
    "wof:name":"Drozdzyce",
    "wof:placetype":"locality"
},
  "geometry": {"coordinates":[16.60648,52.18449],"type":"Point"}
}