{
  "type": "Feature",
  "properties": {
    "gn:admin1_code":"76.0",
    "gn:admin2_code":"803.0",
    "gn:admin3_code":"80302.0",
    "gn:asciiname":"Kuligowo",
    "gn:country_code":"PL",
    "gn:dem":52,
    "gn:feature_class":"P",
    "gn:feature_code":"PPL",
    "gn:name":"Kuligowo",
    "gn:population":0,
    "gn:timezone":"Europe/Warsaw",
    "iso:country":"PL",
    "name:fra_x_preferred":[
        "Kuligowo"
    ],
    "name:nld_x_preferred":[
        "Kuligowo"
    ],
    "name:pol_x_preferred":[
        "Kuligowo"
    ],
    "name:ukr_x_preferred":[
        "\u041a\u0443\u043b\u0456\u0491\u043e\u0432\u043e"
    ],
    "wof:name":"Kuligowo",
    "wof:placetype":"locality"
},
  "geometry": {"coordinates":[15.65435,52.47396],"type":"Point"}
}