{
  "type": "Feature",
  "properties": {
    "gn:gn_country":"PL",
    "gn:gn_fcode":"ADM3",
    "gn:gn_pop":0,
    "iso:country":"PL",
    "name:bel_x_preferred":[
        "\u0422\u0447\u044d\u045e"
    ],
    "name:bul_x_preferred":[
        "\u0422\u0447\u0435\u0432"
    ],
    "name:ces_x_preferred":[
        "Tczew"
    ],
    "name:csb_x_preferred":[
        "D\u00ebrszew\u00f2"
    ],
    "name:deu_x_preferred":[
        "Tczew"
    ],
    "name:dsb_x_preferred":[
        "Tczew"
    ],
    "name:epo_x_preferred":[
        "Tczew"
    ],
    "name:est_x_preferred":[
        "Tczew"
    ],
    "name:eus_x_preferred":[
        "Tczew"
    ],
    "name:fas_x_preferred":[
        "\u062a\u0686\u0641"
    ],
    "name:fin_x_preferred":[
        "Tczew"
    ],
    "name:fra_x_preferred":[
        "Tczew"
    ],
    "name:glv_x_preferred":[
        "Tczew"
    ],
    "name:hak_x_preferred":[
        "Tczew"
    ],
    "name:hun_x_preferred":[
        "Tczew"
    ],
    "name:ind_x_preferred":[
        "Tczew"
    ],
    "name:ita_x_preferred":[
        "Tczew"
    ],
    "name:jav_x_preferred":[
        "Tczew"
    ],
    "name:jpn_x_preferred":[
        "\u30c8\u30c1\u30a7\u30d5"
    ],
    "name:kal_x_preferred":[
        "Tczew"
    ],
    "name:kor_x_preferred":[
        "\ud2b8\uccb4\ud504"
    ],
    "name:lav_x_preferred":[
        "T\u010deva"
    ],
    "name:lit_x_preferred":[
        "T\u010devas"
    ],
    "name:mkd_x_preferred":[
        "\u0422\u0447\u0435\u0432"
    ],
    "name:msa_x_preferred":[
        "Tczew"
    ],
    "name:nau_x_preferred":[
        "Tczew"
    ],
    "name:nld_x_preferred":[
        "Tczew"
    ],
    "name:nor_x_preferred":[
        "Tczew"
    ],
    "name:pol_x_preferred":[
        "Tczew"
    ],
    "name:por_x_preferred":[
        "Tczew"
    ],
    "name:ron_x_preferred":[
        "Tczew"
    ],
    "name:rus_x_preferred":[
        "\u0422\u0447\u0435\u0432"
    ],
    "name:sco_x_preferred":[
        "Tczew"
    ],
    "name:slk_x_preferred":[
        "Tczew"
    ],
    "name:spa_x_preferred":[
        "Tczew"
    ],
    "name:srp_x_preferred":[
        "\u0422\u0447\u0435\u0432"
    ],
    "name:swe_x_preferred":[
        "Tczew"
    ],
    "name:szl_x_preferred":[
        "Tczew"
    ],
    "name:tat_x_preferred":[
        "\u0422\u0447\u0435\u0432"
    ],
    "name:tha_x_preferred":[
        "\u0e15\u0e41\u0e0a\u0e1f"
    ],
    "name:tur_x_preferred":[
        "Tczew"
    ],
    "name:ukr_x_preferred":[
        "\u0422\u0447\u0435\u0432"
    ],
    "name:vie_x_preferred":[
        "Tczew"
    ],
    "name:war_x_preferred":[
        "Tczew"
    ],
    "name:zho_x_preferred":[
        "\u7279\u5207\u592b"
    ],
    "qs_pg:aaroncc":"PL",
    "qs_pg:gn_country":"PL",
    "qs_pg:gn_fcode":"ADM3",
    "qs_pg:gn_pop":0,
    "qs_pg:name":"Tczew",
    "qs_pg:photos_9r":0,
    "qs_pg:photos_sr":0,
    "qs_pg:pop_sr":0,
    "qs_pg:qs_pg_placetype":"localadmin",
    "wof:name":"Tczew",
    "wof:placetype":"localadmin"
},
  "geometry": {"coordinates":[18.6897,54.0853],"type":"Point"}
}