{
  "type": "Feature",
  "properties": {
    "gn:admin1_code":"87.0",
    "gn:admin2_code":"3213.0",
    "gn:admin3_code":"321304.0",
    "gn:asciiname":"Grabowo",
    "gn:cc2":"PL",
    "gn:country_code":"PL",
    "gn:dem":16,
    "gn:feature_class":"P",
    "gn:feature_code":"PPL",
    "gn:name":"Grabowo",
    "gn:population":121,
    "gn:timezone":"Europe/Warsaw",
    "iso:country":"PL",
    "name:ceb_x_preferred":[
        "Grabowo"
    ],
    "name:deu_x_preferred":[
        "Grabowo"
    ],
    "name:pol_x_preferred":[
        "Grabowo"
    ],
    "name:szl_x_preferred":[
        "Grabowo"
    ],
    "name:ukr_x_preferred":[
        "\u0490\u0440\u0430\u0431\u043e\u0432\u043e"
    ],
    "name:und_x_variant":[
        "Martinshagen",
        "Grabowo"
    ],
    "wof:name":"Grabowo",
    "wof:placetype":"locality",
    "wof:population":121
},
  "geometry": {"coordinates":[16.43443,54.29354],"type":"Point"}
}