{
  "type": "Feature",
  "properties": {
    "gn:admin1_code":"74.0",
    "gn:admin2_code":"1011.0",
    "gn:admin3_code":"101106.0",
    "gn:asciiname":"Bratkow Gorny",
    "gn:country_code":"PL",
    "gn:dem":135,
    "gn:feature_class":"P",
    "gn:feature_code":"PPL",
    "gn:name":"Bratk\u00f3w G\u00f3rny",
    "gn:population":0,
    "gn:timezone":"Europe/Warsaw",
    "iso:country":"PL",
    "name:und_x_variant":[
        "Kolonia Bratk\u00f3w G\u00f3rny",
        "Bratk\u00f3w G\u00f3rny"
    ],
    "wof:name":"Bratkow Gorny",
    "wof:placetype":"locality"
},
  "geometry": {"coordinates":[18.88664,51.8271],"type":"Point"}
}