{
  "type": "Feature",
  "properties": {
    "gn:admin1_code":"73.0",
    "gn:admin2_code":"417.0",
    "gn:admin3_code":"41704.0",
    "gn:asciiname":"Mgowo",
    "gn:country_code":"PL",
    "gn:dem":114,
    "gn:feature_class":"P",
    "gn:feature_code":"PPL",
    "gn:name":"Mgowo",
    "gn:population":0,
    "gn:timezone":"Europe/Warsaw",
    "iso:country":"PL",
    "name:pol_x_preferred":[
        "Mgowo"
    ],
    "name:ukr_x_preferred":[
        "\u041c\u0491\u043e\u0432\u043e"
    ],
    "wof:name":"Mgowo",
    "wof:placetype":"locality"
},
  "geometry": {"coordinates":[18.83189,53.34744],"type":"Point"}
}