{
  "type": "Feature",
  "properties": {
    "iso:country":"PL",
    "name:bel_x_preferred":[
        "\u0420\u0443\u0434\u043d\u0456\u043a\u0456"
    ],
    "name:ceb_x_preferred":[
        "Rudniki"
    ],
    "name:deu_x_preferred":[
        "Rudnyky"
    ],
    "name:eng_x_preferred":[
        "Rudniki"
    ],
    "name:fra_x_preferred":[
        "Rudniki"
    ],
    "name:hye_x_preferred":[
        "\u054c\u0578\u0582\u0564\u0576\u056b\u056f\u056b"
    ],
    "name:lit_x_preferred":[
        "Rudnikai"
    ],
    "name:nld_x_preferred":[
        "Rudniki"
    ],
    "name:pol_x_preferred":[
        "Rudniki"
    ],
    "name:rus_x_preferred":[
        "\u0420\u0443\u0434\u043d\u0438\u043a\u0438"
    ],
    "name:ukr_x_preferred":[
        "\u0420\u0443\u0434\u043d\u0438\u043a\u0438"
    ],
    "wof:name":"Rudniki",
    "wof:placetype":"neighbourhood"
},
  "geometry": {"coordinates":[18.72508348176655,54.34866733397206],"type":"Point"}
}