{
  "type": "Feature",
  "properties": {
    "iso:country":"PL",
    "name:eng_x_preferred":[
        "Rudniki"
    ],
    "name:pol_x_preferred":[
        "Rudniki"
    ],
    "wof:name":"Rudniki",
    "wof:placetype":"neighbourhood"
},
  "geometry": {"coordinates":[18.72508348176655,54.34866733397206],"type":"Point"}
}