{
  "type": "Feature",
  "properties": {
    "gn:admin1_code":"78.0",
    "gn:admin2_code":"1406.0",
    "gn:admin3_code":"140611.0",
    "gn:asciiname":"Debnowola",
    "gn:country_code":"PL",
    "gn:dem":123,
    "gn:feature_class":"P",
    "gn:feature_code":"PPL",
    "gn:name":"D\u0119bnowola",
    "gn:population":0,
    "gn:timezone":"Europe/Warsaw",
    "iso:country":"PL",
    "name:ceb_x_preferred":[
        "D\u0119bnowola"
    ],
    "name:fra_x_preferred":[
        "D\u0119bnowola"
    ],
    "name:pol_x_preferred":[
        "D\u0119bnowola"
    ],
    "name:ukr_x_preferred":[
        "\u0414\u0435\u043c\u0431\u043d\u043e\u0432\u043e\u043b\u044f"
    ],
    "wof:name":"Debnowola",
    "wof:placetype":"locality"
},
  "geometry": {"coordinates":[21.21271,51.84225],"type":"Point"}
}