{
  "type": "Feature",
  "properties": {
    "gn:admin1_code":"77.0",
    "gn:admin2_code":"1211.0",
    "gn:admin3_code":"121108.0",
    "gn:asciiname":"Lapszanka",
    "gn:country_code":"PL",
    "gn:dem":769,
    "gn:feature_class":"P",
    "gn:feature_code":"PPL",
    "gn:name":"\u0141apszanka",
    "gn:population":0,
    "gn:timezone":"Europe/Warsaw",
    "iso:country":"PL",
    "name:azb_x_preferred":[
        "\u0648\u0627\u067e\u0634\u0627\u0646\u06a9\u0627"
    ],
    "name:ceb_x_preferred":[
        "\u0141apszanka"
    ],
    "name:deu_x_preferred":[
        "\u0141apszanka"
    ],
    "name:fas_x_preferred":[
        "\u0648\u0627\u067e\u0634\u0627\u0646\u06a9\u0627"
    ],
    "name:nld_x_preferred":[
        "\u0141apszanka"
    ],
    "name:pol_x_preferred":[
        "\u0141apszanka"
    ],
    "name:slk_x_preferred":[
        "Lap\u0161anka"
    ],
    "name:ukr_x_preferred":[
        "\u041b\u0430\u043f\u0448\u0430\u043d\u043a\u0430"
    ],
    "name:und_x_variant":[
        "\u0141apszanka"
    ],
    "wof:name":"Lapszanka",
    "wof:placetype":"locality"
},
  "geometry": {"coordinates":[20.18386,49.36579],"type":"Point"}
}