{
  "type": "Feature",
  "properties": {
    "gn:admin1_code":"80.0",
    "gn:admin2_code":"1805.0",
    "gn:admin3_code":"180506.0",
    "gn:asciiname":"Myscowa",
    "gn:country_code":"PL",
    "gn:dem":354,
    "gn:feature_class":"P",
    "gn:feature_code":"PPL",
    "gn:name":"Myscowa",
    "gn:population":0,
    "gn:timezone":"Europe/Warsaw",
    "iso:country":"PL",
    "name:pol_x_preferred":[
        "Myscowa"
    ],
    "name:rus_x_preferred":[
        "\u041c\u044b\u0441\u0446\u043e\u0432\u0430"
    ],
    "name:ukr_x_preferred":[
        "\u041c\u0438\u0441\u0446\u043e\u0432\u0430"
    ],
    "wof:name":"Myscowa",
    "wof:placetype":"locality"
},
  "geometry": {"coordinates":[21.56391,49.52696],"type":"Point"}
}