{
  "type": "Feature",
  "properties": {
    "gn:admin1_code":"84.0",
    "gn:admin2_code":"2613.0",
    "gn:admin3_code":"261302.0",
    "gn:asciiname":"Brygidow",
    "gn:country_code":"PL",
    "gn:dem":225,
    "gn:feature_class":"P",
    "gn:feature_code":"PPL",
    "gn:name":"Brygid\u00f3w",
    "gn:population":0,
    "gn:timezone":"Europe/Warsaw",
    "iso:country":"PL",
    "name:und_x_variant":[
        "Brygid\u00f3w"
    ],
    "wof:name":"Brygidow",
    "wof:placetype":"locality"
},
  "geometry": {"coordinates":[20.12523,50.93169],"type":"Point"}
}