{
  "type": "Feature",
  "properties": {
    "gn:admin1_code":"75.0",
    "gn:admin2_code":"608.0",
    "gn:admin3_code":"60804.0",
    "gn:asciiname":"Kruszyna",
    "gn:country_code":"PL",
    "gn:dem":123,
    "gn:feature_class":"P",
    "gn:feature_code":"PPL",
    "gn:name":"Kruszyna",
    "gn:population":0,
    "gn:timezone":"Europe/Warsaw",
    "iso:country":"PL",
    "name:fra_x_preferred":[
        "Kruszyna"
    ],
    "name:pol_x_preferred":[
        "Kruszyna"
    ],
    "name:ukr_x_preferred":[
        "\u041a\u0440\u0443\u0448\u0438\u043d\u0430"
    ],
    "wof:name":"Kruszyna",
    "wof:placetype":"locality"
},
  "geometry": {"coordinates":[22.25,51.58333],"type":"Point"}
}