{
  "type": "Feature",
  "properties": {
    "gn:admin1_code":"73.0",
    "gn:admin2_code":"411.0",
    "gn:admin3_code":"41103.0",
    "gn:asciiname":"Ludwikowo",
    "gn:country_code":"PL",
    "gn:dem":89,
    "gn:feature_class":"P",
    "gn:feature_code":"PPL",
    "gn:name":"Ludwikowo",
    "gn:population":0,
    "gn:timezone":"Europe/Warsaw",
    "iso:country":"PL",
    "name:fra_x_preferred":[
        "Ludwikowo"
    ],
    "name:pol_x_preferred":[
        "Ludwikowo"
    ],
    "name:ukr_x_preferred":[
        "\u041b\u044e\u0434\u0432\u0456\u043a\u043e\u0432\u043e"
    ],
    "wof:name":"Ludwikowo",
    "wof:placetype":"locality"
},
  "geometry": {"coordinates":[18.64239,52.68511],"type":"Point"}
}