{
  "type": "Feature",
  "properties": {
    "gn:admin1_code":"86.0",
    "gn:admin2_code":"3021.0",
    "gn:admin3_code":"302110.0",
    "gn:asciiname":"Baranowko",
    "gn:cc2":"PL",
    "gn:country_code":"PL",
    "gn:dem":63,
    "gn:feature_class":"P",
    "gn:feature_code":"PPL",
    "gn:name":"Baran\u00f3wko",
    "gn:population":0,
    "gn:timezone":"Europe/Warsaw",
    "iso:country":"PL",
    "name:azb_x_preferred":[
        "\u0628\u0627\u0631\u0627\u0646\u0648\u0648\u06a9\u0648"
    ],
    "name:fas_x_preferred":[
        "\u0628\u0627\u0631\u0627\u0646\u0648\u0648\u06a9\u0648"
    ],
    "name:fra_x_preferred":[
        "Baran\u00f3wko"
    ],
    "name:nld_x_preferred":[
        "Baran\u00f3wko"
    ],
    "name:pol_x_preferred":[
        "Baran\u00f3wko"
    ],
    "name:ukr_x_preferred":[
        "\u0411\u0430\u0440\u0430\u043d\u0443\u0432\u043a\u043e"
    ],
    "name:und_x_variant":[
        "Baranowo"
    ],
    "wof:name":"Baranowko",
    "wof:placetype":"locality"
},
  "geometry": {"coordinates":[16.89654,52.20876],"type":"Point"}
}