{
  "type": "Feature",
  "properties": {
    "gn:admin1_code":"86.0",
    "gn:admin2_code":"3021.0",
    "gn:admin3_code":"302110.0",
    "gn:asciiname":"Baranowko",
    "gn:cc2":"PL",
    "gn:country_code":"PL",
    "gn:dem":63,
    "gn:feature_class":"P",
    "gn:feature_code":"PPL",
    "gn:name":"Baran\u00f3wko",
    "gn:population":0,
    "gn:timezone":"Europe/Warsaw",
    "iso:country":"PL",
    "name:und_x_variant":[
        "Baranowo",
        "Baran\u00f3wko"
    ],
    "wof:name":"Baranowko",
    "wof:placetype":"locality"
},
  "geometry": {"coordinates":[16.89654,52.20876],"type":"Point"}
}