{
  "type": "Feature",
  "properties": {
    "gn:admin1_code":"83.0",
    "gn:admin2_code":"2406.0",
    "gn:admin3_code":"240601.0",
    "gn:asciiname":"Zakrzew",
    "gn:country_code":"PL",
    "gn:dem":248,
    "gn:feature_class":"P",
    "gn:feature_code":"PPL",
    "gn:name":"Zakrzew",
    "gn:population":0,
    "gn:timezone":"Europe/Warsaw",
    "iso:country":"PL",
    "name:ceb_x_preferred":[
        "Zakrzew"
    ],
    "name:deu_x_preferred":[
        "Zakrzew"
    ],
    "name:fra_x_preferred":[
        "Zakrzew"
    ],
    "name:ita_x_preferred":[
        "Zakrzew"
    ],
    "name:nld_x_preferred":[
        "Zakrzew"
    ],
    "name:pol_x_preferred":[
        "Zakrzew"
    ],
    "name:rus_x_preferred":[
        "\u0417\u0430\u043a\u0448\u0435\u0432"
    ],
    "name:ukr_x_preferred":[
        "\u0417\u0430\u043a\u0448\u0435\u0432"
    ],
    "wof:name":"Zakrzew",
    "wof:placetype":"locality"
},
  "geometry": {"coordinates":[18.9075,50.89512],"type":"Point"}
}