{
  "type": "Feature",
  "properties": {
    "gn:admin1_code":"78.0",
    "gn:admin2_code":"1419.0",
    "gn:admin3_code":"141914.0",
    "gn:asciiname":"Zdziar Maly",
    "gn:country_code":"PL",
    "gn:dem":134,
    "gn:feature_class":"P",
    "gn:feature_code":"PPL",
    "gn:name":"Zdziar Ma\u0142y",
    "gn:population":0,
    "gn:timezone":"Europe/Warsaw",
    "iso:country":"PL",
    "name:fra_x_preferred":[
        "Zdziar Ma\u0142y"
    ],
    "name:pol_x_preferred":[
        "Zdziar Ma\u0142y"
    ],
    "name:ukr_x_preferred":[
        "\u0417\u0434\u0437\u044f\u0440-\u041c\u0430\u043b\u0438\u0439"
    ],
    "wof:name":"Zdziar Maly",
    "wof:placetype":"locality"
},
  "geometry": {"coordinates":[20.03203,52.62838000000001],"type":"Point"}
}