{
  "type": "Feature",
  "properties": {
    "gn:admin1_code":"81.0",
    "gn:admin2_code":"2008.0",
    "gn:admin3_code":"200803.0",
    "gn:asciiname":"Moniuszki",
    "gn:country_code":"PL",
    "gn:dem":129,
    "gn:feature_class":"P",
    "gn:feature_code":"PPL",
    "gn:name":"Moniuszki",
    "gn:population":0,
    "gn:timezone":"Europe/Warsaw",
    "iso:country":"PL",
    "name:fra_x_preferred":[
        "Moniuszki"
    ],
    "name:lit_x_preferred":[
        "Moniu\u0161kai"
    ],
    "name:pol_x_preferred":[
        "Moniuszki"
    ],
    "name:ukr_x_preferred":[
        "\u041c\u043e\u043d\u044e\u0448\u043a\u0456"
    ],
    "wof:name":"Moniuszki",
    "wof:placetype":"locality"
},
  "geometry": {"coordinates":[22.92469,53.51225],"type":"Point"}
}