{
  "type": "Feature",
  "properties": {
    "gn:admin1_code":"73.0",
    "gn:admin2_code":"412.0",
    "gn:admin3_code":"41203.0",
    "gn:asciiname":"Czumsk Duzy",
    "gn:country_code":"PL",
    "gn:dem":119,
    "gn:feature_class":"P",
    "gn:feature_code":"PPL",
    "gn:name":"Czumsk Du\u017cy",
    "gn:population":0,
    "gn:timezone":"Europe/Warsaw",
    "iso:country":"PL",
    "name:pol_x_preferred":[
        "Czumsk Du\u017cy"
    ],
    "name:ukr_x_preferred":[
        "\u0427\u0443\u043c\u0441\u044c\u043a-\u0414\u0443\u0436\u0438"
    ],
    "wof:name":"Czumsk Duzy",
    "wof:placetype":"locality"
},
  "geometry": {"coordinates":[19.4985,52.95908000000001],"type":"Point"}
}