{
  "type": "Feature",
  "properties": {
    "gn:admin1_code":"86.0",
    "gn:admin2_code":"3014.0",
    "gn:admin3_code":"301403.0",
    "gn:asciiname":"Drzewce",
    "gn:country_code":"PL",
    "gn:dem":45,
    "gn:feature_class":"P",
    "gn:feature_code":"PPL",
    "gn:name":"Drzewce",
    "gn:population":0,
    "gn:timezone":"Europe/Warsaw",
    "iso:country":"PL",
    "wof:name":"Drzewce",
    "wof:placetype":"locality"
},
  "geometry": {"coordinates":[15.8242,52.64988],"type":"Point"}
}