{
  "type": "Feature",
  "properties": {
    "gn:country":"PL",
    "gn:fcode":"PPL",
    "gn:population":217,
    "iso:country":"PL",
    "name:ceb_x_preferred":[
        "Jab\u0142onna"
    ],
    "name:deu_x_preferred":[
        "Jab\u0142onna"
    ],
    "name:fra_x_preferred":[
        "Jab\u0142onna"
    ],
    "name:ita_x_preferred":[
        "Jab\u0142onna"
    ],
    "name:nld_x_preferred":[
        "Jab\u0142onna"
    ],
    "name:pol_x_preferred":[
        "Jab\u0142onna"
    ],
    "name:rus_x_preferred":[
        "\u042f\u0431\u043b\u043e\u043d\u043d\u0430"
    ],
    "name:ukr_x_preferred":[
        "\u042f\u0431\u043b\u043e\u043d\u043d\u0430"
    ],
    "qs_pg:aaroncc":"PL",
    "qs_pg:gn_country":"PL",
    "qs_pg:gn_fcode":"PPL",
    "qs_pg:gn_pop":217,
    "qs_pg:name":"Jab\u0142onna",
    "qs_pg:photos_9r":0,
    "qs_pg:photos_sr":0,
    "qs_pg:pop_sr":2,
    "qs_pg:qs_pg_placetype":"locality",
    "wof:name":"Jab\u0142onna",
    "wof:placetype":"locality",
    "wof:population":217
},
  "geometry": {"coordinates":[20.85274,51.4709],"type":"Point"}
}