{
  "type": "Feature",
  "properties": {
    "gn:admin1_code":"78.0",
    "gn:admin2_code":"1407.0",
    "gn:admin3_code":"140702.0",
    "gn:asciiname":"Stanislawow",
    "gn:country_code":"PL",
    "gn:dem":154,
    "gn:feature_class":"P",
    "gn:feature_code":"PPL",
    "gn:name":"Stanis\u0142aw\u00f3w",
    "gn:population":0,
    "gn:timezone":"Europe/Warsaw",
    "iso:country":"PL",
    "wof:name":"Stanislawow",
    "wof:placetype":"locality"
},
  "geometry": {"coordinates":[21.39248,51.57178],"type":"Point"}
}