{
  "type": "Feature",
  "properties": {
    "gn:admin1_code":"78.0",
    "gn:admin2_code":"1402.0",
    "gn:admin3_code":"140203.0",
    "gn:asciiname":"Wkra",
    "gn:country_code":"PL",
    "gn:dem":102,
    "gn:feature_class":"P",
    "gn:feature_code":"PPL",
    "gn:name":"Wkra",
    "gn:population":0,
    "gn:timezone":"Europe/Warsaw",
    "iso:country":"PL",
    "name:fra_x_preferred":[
        "Wkra"
    ],
    "name:pol_x_preferred":[
        "Wkra"
    ],
    "name:ukr_x_preferred":[
        "\u0412\u043a\u0440\u0430"
    ],
    "wof:name":"Wkra",
    "wof:placetype":"locality"
},
  "geometry": {"coordinates":[20.29669,52.79059],"type":"Point"}
}