{
  "type": "Feature",
  "properties": {
    "gn:admin1_code":"78.0",
    "gn:admin2_code":"1415.0",
    "gn:admin3_code":"141511.0",
    "gn:asciiname":"Zyzniewo",
    "gn:country_code":"PL",
    "gn:dem":108,
    "gn:feature_class":"P",
    "gn:feature_code":"PPL",
    "gn:name":"\u017by\u017aniewo",
    "gn:population":0,
    "gn:timezone":"Europe/Warsaw",
    "iso:country":"PL",
    "name:fra_x_preferred":[
        "\u017by\u017aniewo"
    ],
    "name:pol_x_preferred":[
        "\u017by\u017aniewo"
    ],
    "name:srp_x_preferred":[
        "\u0416\u0438\u0437\u045a\u0435\u0432\u043e"
    ],
    "name:ukr_x_preferred":[
        "\u0416\u0438\u0437\u044c\u043d\u0435\u0432\u043e"
    ],
    "wof:name":"Zyzniewo",
    "wof:placetype":"locality"
},
  "geometry": {"coordinates":[21.87017,53.05731],"type":"Point"}
}