{
  "type": "Feature",
  "properties": {
    "gn:admin1_code":"75.0",
    "gn:admin2_code":"612.0",
    "gn:admin3_code":"61205.0",
    "gn:asciiname":"Darowne",
    "gn:country_code":"PL",
    "gn:dem":158,
    "gn:feature_class":"P",
    "gn:feature_code":"PPL",
    "gn:name":"Darowne",
    "gn:population":0,
    "gn:timezone":"Europe/Warsaw",
    "iso:country":"PL",
    "name:azb_x_preferred":[
        "\u062f\u0627\u0631\u0648\u0648\u0646\u0647"
    ],
    "name:fas_x_preferred":[
        "\u062f\u0627\u0631\u0648\u0648\u0646\u0647"
    ],
    "name:fra_x_preferred":[
        "Darowne"
    ],
    "name:pol_x_preferred":[
        "Darowne"
    ],
    "name:ukr_x_preferred":[
        "\u0414\u0430\u0440\u043e\u0432\u043d\u0435"
    ],
    "wof:name":"Darowne",
    "wof:placetype":"locality"
},
  "geometry": {"coordinates":[22.042,51.16295],"type":"Point"}
}