{
  "type": "Feature",
  "properties": {
    "gn:admin1_code":"81.0",
    "gn:admin2_code":"2001.0",
    "gn:admin3_code":"200107.0",
    "gn:asciiname":"Jastrzebna I",
    "gn:country_code":"PL",
    "gn:dem":124,
    "gn:feature_class":"P",
    "gn:feature_code":"PPL",
    "gn:name":"Jastrz\u0119bna I",
    "gn:population":0,
    "gn:timezone":"Europe/Warsaw",
    "iso:country":"PL",
    "wof:name":"Jastrzebna I",
    "wof:placetype":"locality"
},
  "geometry": {"coordinates":[23.23237,53.73023000000001],"type":"Point"}
}