{
  "type": "Feature",
  "properties": {
    "gn:admin1_code":"87.0",
    "gn:admin2_code":"3209.0",
    "gn:admin3_code":"320908.0",
    "gn:asciiname":"Konikowo",
    "gn:country_code":"PL",
    "gn:dem":36,
    "gn:feature_class":"P",
    "gn:feature_code":"PPL",
    "gn:name":"Konikowo",
    "gn:population":0,
    "gn:timezone":"Europe/Warsaw",
    "iso:country":"PL",
    "name:ceb_x_preferred":[
        "Konikowo"
    ],
    "name:deu_x_preferred":[
        "Konikowo"
    ],
    "name:pol_x_preferred":[
        "Konikowo"
    ],
    "name:ukr_x_preferred":[
        "\u041a\u043e\u043d\u0456\u043a\u043e\u0432\u043e"
    ],
    "wof:name":"Konikowo",
    "wof:placetype":"locality"
},
  "geometry": {"coordinates":[16.1786,54.1517],"type":"Point"}
}