{
  "type": "Feature",
  "properties": {
    "gn:admin1_code":"85.0",
    "gn:admin2_code":"2816.0",
    "gn:admin3_code":"281603.0",
    "gn:asciiname":"Lipniki",
    "gn:country_code":"PL",
    "gn:dem":133,
    "gn:feature_class":"P",
    "gn:feature_code":"PPL",
    "gn:name":"Lipniki",
    "gn:population":0,
    "gn:timezone":"Europe/Warsaw",
    "iso:country":"PL",
    "name:bel_x_preferred":[
        "\u041b\u0456\u043f\u043d\u0456\u043a\u0456"
    ],
    "name:fra_x_preferred":[
        "Lipniki"
    ],
    "name:lit_x_preferred":[
        "Lipnikai"
    ],
    "name:pol_x_preferred":[
        "Lipniki"
    ],
    "name:rus_x_preferred":[
        "\u041b\u0438\u043f\u043d\u0438\u043a\u0438"
    ],
    "name:ukr_x_preferred":[
        "\u041b\u0456\u043f\u043d\u0438\u043a\u0438"
    ],
    "name:und_x_variant":[
        "Lipniken"
    ],
    "wof:name":"Lipniki",
    "wof:placetype":"locality"
},
  "geometry": {"coordinates":[21.90927000000001,53.50823000000001],"type":"Point"}
}