{
  "type": "Feature",
  "properties": {
    "gn:admin1_code":"82.0",
    "gn:admin2_code":"2205.0",
    "gn:admin3_code":"220508.0",
    "gn:asciiname":"Glincz",
    "gn:country_code":"PL",
    "gn:dem":163,
    "gn:feature_class":"P",
    "gn:feature_code":"PPL",
    "gn:name":"Gli\u0144cz",
    "gn:population":0,
    "gn:timezone":"Europe/Warsaw",
    "iso:country":"PL",
    "name:ceb_x_preferred":[
        "Gli\u0144cz"
    ],
    "name:csb_x_preferred":[
        "Gli\u0144cz"
    ],
    "name:ita_x_preferred":[
        "Glincz"
    ],
    "name:pol_x_preferred":[
        "Glincz"
    ],
    "name:ukr_x_preferred":[
        "\u0490\u043b\u0456\u043d\u0447"
    ],
    "wof:name":"Glincz",
    "wof:placetype":"locality"
},
  "geometry": {"coordinates":[18.34507,54.32291],"type":"Point"}
}