{
  "type": "Feature",
  "properties": {
    "gn:admin1_code":"87.0",
    "gn:admin2_code":"3212.0",
    "gn:admin3_code":"321204.0",
    "gn:asciiname":"Przywodzie",
    "gn:country_code":"PL",
    "gn:dem":20,
    "gn:feature_class":"P",
    "gn:feature_code":"PPL",
    "gn:name":"Przywodzie",
    "gn:population":0,
    "gn:timezone":"Europe/Warsaw",
    "iso:country":"PL",
    "name:pol_x_preferred":[
        "Przywodzie"
    ],
    "wof:name":"Przywodzie",
    "wof:placetype":"locality"
},
  "geometry": {"coordinates":[15.15524,53.12924],"type":"Point"}
}