{
  "type": "Feature",
  "properties": {
    "gn:admin1_code":"81.0",
    "gn:admin2_code":"2006.0",
    "gn:admin3_code":"200605.0",
    "gn:asciiname":"Tafily",
    "gn:cc2":"PL",
    "gn:country_code":"PL",
    "gn:dem":152,
    "gn:feature_class":"P",
    "gn:feature_code":"PPL",
    "gn:name":"Tafi\u0142y",
    "gn:population":0,
    "gn:timezone":"Europe/Warsaw",
    "iso:country":"PL",
    "name:lit_x_preferred":[
        "Tafilai"
    ],
    "name:pol_x_preferred":[
        "Tafi\u0142y"
    ],
    "name:ukr_x_preferred":[
        "\u0422\u0430\u0444\u0456\u043b\u0438"
    ],
    "name:und_x_variant":[
        "Tafity"
    ],
    "wof:name":"Tafily",
    "wof:placetype":"locality"
},
  "geometry": {"coordinates":[22.1874,53.40247],"type":"Point"}
}