{
  "type": "Feature",
  "properties": {
    "gn:country":"PL",
    "gn:fcode":"PPL",
    "gn:population":554,
    "iso:country":"PL",
    "name:ast_x_preferred":[
        "Wierzbno"
    ],
    "name:ceb_x_preferred":[
        "Wierzbno"
    ],
    "name:ces_x_preferred":[
        "Wierzbno"
    ],
    "name:che_x_preferred":[
        "\u0412\u0435\u0436\u0431\u043d\u043e"
    ],
    "name:eng_x_preferred":[
        "Wierzbno"
    ],
    "name:fra_x_preferred":[
        "Wierzbno"
    ],
    "name:nan_x_preferred":[
        "Wierzbno"
    ],
    "name:pol_x_preferred":[
        "Wierzbno"
    ],
    "name:spa_x_preferred":[
        "Wierzbno"
    ],
    "name:tat_x_preferred":[
        "\u0412\u0435\u0436\u0431\u043d\u043e"
    ],
    "name:ukr_x_preferred":[
        "\u0412\u0435\u0436\u0431\u043d\u043e"
    ],
    "name:yid_x_preferred":[
        "\u05d0\u05dc\u05e2\u05e7\u05e1\u05d0\u05e0\u05d3\u05e2\u05e8"
    ],
    "qs_pg:aaroncc":"PL",
    "qs_pg:gn_country":"PL",
    "qs_pg:gn_fcode":"PPL",
    "qs_pg:gn_pop":554,
    "qs_pg:name":"Wierzbno",
    "qs_pg:name_adm0":"Polska",
    "qs_pg:name_adm1":"Wielkopolskie",
    "qs_pg:photos_9r":0,
    "qs_pg:photos_sr":0,
    "qs_pg:pop_sr":2,
    "qs_pg:qs_pg_placetype":"locality",
    "qs_pg:qs_pg_placetype_gp":"Town",
    "qs_pg:woe_adm0":23424923,
    "woe:adm0_id":23424923,
    "woe:name_adm0":"Polska",
    "woe:name_adm1":"Wielkopolskie",
    "woe:placetype":"Town",
    "wof:name":"Wierzbno",
    "wof:placetype":"locality",
    "wof:population":554
},
  "geometry": {"coordinates":[17.66782,51.63789],"type":"Point"}
}