{
  "type": "Feature",
  "properties": {
    "gn:admin1_code":"77.0",
    "gn:admin2_code":"1216.0",
    "gn:admin3_code":"121609.0",
    "gn:asciiname":"Lekawka",
    "gn:country_code":"PL",
    "gn:dem":263,
    "gn:feature_class":"P",
    "gn:feature_code":"PPL",
    "gn:name":"\u0141\u0119kawka",
    "gn:population":0,
    "gn:timezone":"Europe/Warsaw",
    "iso:country":"PL",
    "wof:name":"Lekawka",
    "wof:placetype":"locality"
},
  "geometry": {"coordinates":[21.03281,49.95034],"type":"Point"}
}