{
  "type": "Feature",
  "properties": {
    "gn:admin1_code":"85.0",
    "gn:admin2_code":"2805.0",
    "gn:admin3_code":"280505.0",
    "gn:asciiname":"Orzechowo",
    "gn:country_code":"PL",
    "gn:dem":135,
    "gn:feature_class":"P",
    "gn:feature_code":"PPL",
    "gn:name":"Orzechowo",
    "gn:population":0,
    "gn:timezone":"Europe/Warsaw",
    "iso:country":"PL",
    "name:deu_x_preferred":[
        "Orzechowo"
    ],
    "name:pol_x_preferred":[
        "Orzechowo"
    ],
    "name:ukr_x_preferred":[
        "\u041e\u0436\u0435\u0445\u043e\u0432\u043e"
    ],
    "name:und_x_variant":[
        "Orzechowen",
        "Nussberg"
    ],
    "wof:name":"Orzechowo",
    "wof:placetype":"locality"
},
  "geometry": {"coordinates":[22.15396,53.96228000000001],"type":"Point"}
}