{
  "type": "Feature",
  "properties": {
    "gn:admin1_code":"86.0",
    "gn:admin2_code":"3016.0",
    "gn:admin3_code":"301601.0",
    "gn:asciiname":"Slepuchowo",
    "gn:country_code":"PL",
    "gn:dem":78,
    "gn:feature_class":"P",
    "gn:feature_code":"PPL",
    "gn:name":"\u015alepuchowo",
    "gn:population":0,
    "gn:timezone":"Europe/Warsaw",
    "iso:country":"PL",
    "name:fra_x_preferred":[
        "\u015alepuchowo"
    ],
    "name:pol_x_preferred":[
        "\u015alepuchowo"
    ],
    "name:ukr_x_preferred":[
        "\u0421\u044c\u043b\u0435\u043f\u0443\u0445\u043e\u0432\u043e"
    ],
    "wof:name":"Slepuchowo",
    "wof:placetype":"locality"
},
  "geometry": {"coordinates":[16.72162,52.59533],"type":"Point"}
}