{
  "type": "Feature",
  "properties": {
    "gn:admin1_code":"75.0",
    "gn:admin2_code":"620.0",
    "gn:admin3_code":"62009.0",
    "gn:asciiname":"Stabrow",
    "gn:country_code":"PL",
    "gn:dem":225,
    "gn:feature_class":"P",
    "gn:feature_code":"PPL",
    "gn:name":"Stabr\u00f3w",
    "gn:population":0,
    "gn:timezone":"Europe/Warsaw",
    "iso:country":"PL",
    "name:und_x_variant":[
        "Stabr\u00f3w"
    ],
    "wof:name":"Stabrow",
    "wof:placetype":"locality"
},
  "geometry": {"coordinates":[23.39697,50.73206],"type":"Point"}
}