{
  "type": "Feature",
  "properties": {
    "gn:admin1_code":"72.0",
    "gn:admin2_code":"264.0",
    "gn:admin3_code":"26401.0",
    "gn:asciiname":"Przedmiescie Swidnickie",
    "gn:country_code":"PL",
    "gn:dem":122,
    "gn:feature_class":"P",
    "gn:feature_code":"PPL",
    "gn:name":"Przedmie\u015bcie \u015awidnickie",
    "gn:population":0,
    "gn:timezone":"Europe/Warsaw",
    "iso:country":"PL",
    "wof:name":"Przedmiescie Swidnickie",
    "wof:placetype":"locality"
},
  "geometry": {"coordinates":[17.03458,51.10083],"type":"Point"}
}