{
  "type": "Feature",
  "properties": {
    "gn:admin1_code":"87.0",
    "gn:admin2_code":"3205.0",
    "gn:admin3_code":"320508.0",
    "gn:asciiname":"Ostrowo",
    "gn:cc2":"PL",
    "gn:country_code":"PL",
    "gn:dem":-2,
    "gn:feature_class":"P",
    "gn:feature_code":"PPL",
    "gn:name":"Ostrowo",
    "gn:population":0,
    "gn:timezone":"Europe/Warsaw",
    "iso:country":"PL",
    "name:ceb_x_preferred":[
        "Ostrowo"
    ],
    "name:deu_x_preferred":[
        "Ostrowo"
    ],
    "name:fra_x_preferred":[
        "Ostrowo"
    ],
    "name:pol_x_preferred":[
        "Ostrowo"
    ],
    "name:ukr_x_preferred":[
        "\u041e\u0441\u0442\u0440\u043e\u0432\u043e"
    ],
    "name:und_x_variant":[
        "Wustrow"
    ],
    "wof:name":"Ostrowo",
    "wof:placetype":"locality"
},
  "geometry": {"coordinates":[15.35,54.13333000000001],"type":"Point"}
}