{
  "type": "Feature",
  "properties": {
    "gn:admin1_code":"74.0",
    "gn:admin2_code":"1020.0",
    "gn:admin3_code":"102009.0",
    "gn:asciiname":"Dabrowka Strumiany",
    "gn:country_code":"PL",
    "gn:dem":171,
    "gn:feature_class":"P",
    "gn:feature_code":"PPL",
    "gn:name":"D\u0105br\u00f3wka Strumiany",
    "gn:population":0,
    "gn:timezone":"Europe/Warsaw",
    "iso:country":"PL",
    "name:pol_x_preferred":[
        "D\u0105br\u00f3wka-Strumiany"
    ],
    "name:ukr_x_preferred":[
        "\u0414\u043e\u043c\u0431\u0440\u0443\u0432\u043a\u0430-\u0421\u0442\u0440\u0443\u043c\u044f\u043d\u0438"
    ],
    "name:und_x_variant":[
        "D\u0105br\u00f3wka Strumiany"
    ],
    "wof:name":"Dabrowka Strumiany",
    "wof:placetype":"locality"
},
  "geometry": {"coordinates":[19.4455,51.89813],"type":"Point"}
}