{
  "type": "Feature",
  "properties": {
    "gn:gn_country":"PL",
    "gn:gn_fcode":"PPLA3",
    "gn:gn_pop":1800,
    "gn:population":1800,
    "iso:country":"PL",
    "name:azb_x_preferred":[
        "\u0698\u06a9\u0648\u0646\u0642"
    ],
    "name:ceb_x_preferred":[
        "Rzeku\u0144"
    ],
    "name:deu_x_preferred":[
        "Rzeku\u0144"
    ],
    "name:eng_x_preferred":[
        "Rzeku\u0144"
    ],
    "name:fas_x_preferred":[
        "\u0698\u06a9\u0648\u0646\u06af"
    ],
    "name:fra_x_preferred":[
        "Rzeku\u0144"
    ],
    "name:nld_x_preferred":[
        "Rzeku\u0144"
    ],
    "name:pol_x_preferred":[
        "Rzeku\u0144"
    ],
    "name:rus_x_preferred":[
        "\u0416\u0435\u043a\u0443\u043d\u044c"
    ],
    "name:ukr_x_preferred":[
        "\u0416\u0435\u043a\u0443\u043d\u044c"
    ],
    "qs_pg:aaroncc":"PL",
    "qs_pg:gn_country":"PL",
    "qs_pg:gn_fcode":"PPLA3",
    "qs_pg:gn_pop":1800,
    "qs_pg:name":"Rzeku\u0144",
    "qs_pg:name_adm0":"Polska",
    "qs_pg:name_adm1":"Mazowieckie",
    "qs_pg:photos_9k":1,
    "qs_pg:photos_9r":2,
    "qs_pg:photos_all":35,
    "qs_pg:photos_sr":0,
    "qs_pg:pop_sr":3,
    "qs_pg:qs_pg_placetype":"localadmin",
    "qs_pg:qs_pg_placetype_gp":"LocalAdmin",
    "qs_pg:woe_adm0":23424923,
    "woe:adm0_id":23424923,
    "woe:name_adm0":"Polska",
    "woe:name_adm1":"Mazowieckie",
    "woe:placetype":"LocalAdmin",
    "wof:name":"Rzeku\u0144",
    "wof:placetype":"localadmin",
    "wof:population":1800
},
  "geometry": {"coordinates":[21.62069,53.04756],"type":"Point"}
}