{
  "type": "Feature",
  "properties": {
    "gn:admin1_code":"85.0",
    "gn:admin2_code":"2806.0",
    "gn:admin3_code":"280606.0",
    "gn:asciiname":"Staswiny",
    "gn:country_code":"PL",
    "gn:dem":131,
    "gn:feature_class":"P",
    "gn:feature_code":"PPL",
    "gn:name":"Sta\u015bwiny",
    "gn:population":0,
    "gn:timezone":"Europe/Warsaw",
    "iso:country":"PL",
    "name:deu_x_preferred":[
        "Sta\u015bwiny"
    ],
    "name:fra_x_preferred":[
        "Sta\u015bwiny"
    ],
    "name:pol_x_preferred":[
        "Sta\u015bwiny"
    ],
    "name:ukr_x_preferred":[
        "\u0421\u0442\u0430\u0441\u044c\u0432\u0456\u043d\u0438"
    ],
    "name:und_x_variant":[
        "Eiserm\u00fchl",
        "Stasswinen"
    ],
    "wof:name":"Staswiny",
    "wof:placetype":"locality"
},
  "geometry": {"coordinates":[21.86206,53.96545],"type":"Point"}
}