{
  "type": "Feature",
  "properties": {
    "gn:admin1_code":"81.0",
    "gn:admin2_code":"2011.0",
    "gn:admin3_code":"201101.0",
    "gn:asciiname":"Jaczno",
    "gn:country_code":"PL",
    "gn:dem":132,
    "gn:feature_class":"P",
    "gn:feature_code":"PPL",
    "gn:name":"Jaczno",
    "gn:population":0,
    "gn:timezone":"Europe/Warsaw",
    "iso:country":"PL",
    "name:azb_x_preferred":[
        "\u06cc\u0627\u0686\u0646\u0648"
    ],
    "name:fas_x_preferred":[
        "\u06cc\u0627\u0686\u0646\u0648"
    ],
    "name:fra_x_preferred":[
        "Jaczno"
    ],
    "name:lit_x_preferred":[
        "Ja\u010dnas"
    ],
    "name:nld_x_preferred":[
        "Jaczno"
    ],
    "name:pol_x_preferred":[
        "Jaczno"
    ],
    "name:ukr_x_preferred":[
        "\u042f\u0447\u043d\u043e"
    ],
    "name:urd_x_preferred":[
        "\u062c\u06a9\u0632\u0646\u0648"
    ],
    "wof:name":"Jaczno",
    "wof:placetype":"locality"
},
  "geometry": {"coordinates":[23.43365,53.64775],"type":"Point"}
}