{
  "type": "Feature",
  "properties": {
    "gn:admin1_code":"81.0",
    "gn:admin2_code":"2002.0",
    "gn:admin3_code":"200204.0",
    "gn:asciiname":"Zubry",
    "gn:country_code":"PL",
    "gn:dem":148,
    "gn:feature_class":"P",
    "gn:feature_code":"PPL",
    "gn:name":"\u017bubry",
    "gn:population":0,
    "gn:timezone":"Europe/Warsaw",
    "iso:country":"PL",
    "name:azb_x_preferred":[
        "\u0632\u0648\u0628\u0631\u0647"
    ],
    "name:fas_x_preferred":[
        "\u0632\u0648\u0628\u0631\u0647"
    ],
    "name:fra_x_preferred":[
        "Zubry"
    ],
    "name:lit_x_preferred":[
        "Zubrai"
    ],
    "name:pol_x_preferred":[
        "Zubry"
    ],
    "name:ukr_x_preferred":[
        "\u0417\u0443\u0431\u0440\u0438"
    ],
    "name:und_x_variant":[
        "\u017bubry"
    ],
    "wof:name":"Zubry",
    "wof:placetype":"locality"
},
  "geometry": {"coordinates":[23.81796,53.06746999999999],"type":"Point"}
}