{
  "type": "Feature",
  "properties": {
    "gn:admin1_code":"81.0",
    "gn:admin2_code":"2009.0",
    "gn:admin3_code":"200904.0",
    "gn:asciiname":"Boksze Nowe",
    "gn:country_code":"PL",
    "gn:dem":150,
    "gn:feature_class":"P",
    "gn:feature_code":"PPL",
    "gn:name":"Boksze Nowe",
    "gn:population":0,
    "gn:timezone":"Europe/Warsaw",
    "iso:country":"PL",
    "name:lit_x_preferred":[
        "Naujieji Bok\u0161iai"
    ],
    "name:pol_x_preferred":[
        "Boksze Nowe"
    ],
    "name:ukr_x_preferred":[
        "\u0411\u043e\u043a\u0448\u0435-\u041d\u043e\u0432\u0456"
    ],
    "wof:name":"Boksze Nowe",
    "wof:placetype":"locality"
},
  "geometry": {"coordinates":[23.16309,54.19269],"type":"Point"}
}