{
  "type": "Feature",
  "properties": {
    "gn:admin1_code":"86.0",
    "gn:admin2_code":"3009.0",
    "gn:admin3_code":"300905.0",
    "gn:asciiname":"Kielczewek",
    "gn:country_code":"PL",
    "gn:dem":103,
    "gn:feature_class":"P",
    "gn:feature_code":"PPL",
    "gn:name":"Kie\u0142czewek",
    "gn:population":0,
    "gn:timezone":"Europe/Warsaw",
    "iso:country":"PL",
    "name:pol_x_preferred":[
        "Kie\u0142czewek"
    ],
    "name:ukr_x_preferred":[
        "\u041a\u0435\u043b\u0447\u0435\u0432\u0435\u043a"
    ],
    "wof:name":"Kielczewek",
    "wof:placetype":"locality"
},
  "geometry": {"coordinates":[18.73145,52.23443],"type":"Point"}
}