{
  "type": "Feature",
  "properties": {
    "gn:admin1_code":"83.0",
    "gn:admin2_code":"2404.0",
    "gn:admin3_code":"240403.0",
    "gn:asciiname":"Zagorze",
    "gn:country_code":"PL",
    "gn:dem":298,
    "gn:feature_class":"P",
    "gn:feature_code":"PPL",
    "gn:name":"Zag\u00f3rze",
    "gn:population":0,
    "gn:timezone":"Europe/Warsaw",
    "iso:country":"PL",
    "wof:name":"Zagorze",
    "wof:placetype":"locality"
},
  "geometry": {"coordinates":[19.37527,50.77283],"type":"Point"}
}