{
  "type": "Feature",
  "properties": {
    "gn:admin1_code":"74.0",
    "gn:admin2_code":"1005.0",
    "gn:admin3_code":"100503.0",
    "gn:asciiname":"Przemyslow",
    "gn:country_code":"PL",
    "gn:dem":96,
    "gn:feature_class":"P",
    "gn:feature_code":"PPL",
    "gn:name":"Przemys\u0142\u00f3w",
    "gn:population":0,
    "gn:timezone":"Europe/Warsaw",
    "iso:country":"PL",
    "name:fra_x_preferred":[
        "Przemys\u0142\u00f3w"
    ],
    "name:pol_x_preferred":[
        "Przemys\u0142\u00f3w"
    ],
    "name:ukr_x_preferred":[
        "\u041f\u0448\u0435\u043c\u0438\u0441\u043b\u0443\u0432"
    ],
    "wof:name":"Przemyslow",
    "wof:placetype":"locality"
},
  "geometry": {"coordinates":[19.85538,52.19393],"type":"Point"}
}