{
  "type": "Feature",
  "properties": {
    "gn:country":"PL",
    "gn:fcode":"PPL",
    "gn:population":290,
    "iso:country":"PL",
    "name:ast_x_preferred":[
        "Gr\u0119bynice"
    ],
    "name:azb_x_preferred":[
        "\u0642\u0631\u0646\u0628\u0646\u0642\u062a\u0633\u0647"
    ],
    "name:ceb_x_preferred":[
        "Gr\u0119bynice"
    ],
    "name:eng_x_preferred":[
        "Gr\u0119bynice"
    ],
    "name:fas_x_preferred":[
        "\u06af\u0631\u0646\u0628\u0646\u06af\u062a\u0633\u0647"
    ],
    "name:fra_x_preferred":[
        "Gr\u0119bynice"
    ],
    "name:nan_x_preferred":[
        "Gr\u0119bynice"
    ],
    "name:nld_x_preferred":[
        "Gr\u0119bynice"
    ],
    "name:pol_x_preferred":[
        "Gr\u0119bynice"
    ],
    "name:rus_x_preferred":[
        "\u0413\u0440\u0435\u043c\u0431\u044b\u043d\u0438\u0446\u0435"
    ],
    "name:ukr_x_preferred":[
        "\u0490\u0440\u0435\u043c\u0431\u0438\u043d\u0456\u0446\u0435"
    ],
    "qs_pg:aaroncc":"PL",
    "qs_pg:gn_country":"PL",
    "qs_pg:gn_fcode":"PPL",
    "qs_pg:gn_pop":290,
    "qs_pg:name":"Gr\u0119bynice",
    "qs_pg:name_adm0":"Polska",
    "qs_pg:name_adm1":"Ma\u0142opolskie",
    "qs_pg:photos_9k":1,
    "qs_pg:photos_9r":1,
    "qs_pg:photos_all":1,
    "qs_pg:photos_sr":0,
    "qs_pg:pop_sr":2,
    "qs_pg:qs_pg_placetype":"locality",
    "qs_pg:qs_pg_placetype_gp":"Town",
    "qs_pg:woe_adm0":23424923,
    "woe:adm0_id":23424923,
    "woe:name_adm0":"Polska",
    "woe:name_adm1":"Ma\u0142opolskie",
    "woe:placetype":"Town",
    "wof:name":"Gr\u0119bynice",
    "wof:placetype":"locality",
    "wof:population":290
},
  "geometry": {"coordinates":[19.87324,50.16629],"type":"Point"}
}