{
  "type": "Feature",
  "properties": {
    "gn:admin1_code":"86.0",
    "gn:admin2_code":"3027.0",
    "gn:admin3_code":"302708.0",
    "gn:asciiname":"Warenka",
    "gn:country_code":"PL",
    "gn:dem":104,
    "gn:feature_class":"P",
    "gn:feature_code":"PPL",
    "gn:name":"Warenka",
    "gn:population":0,
    "gn:timezone":"Europe/Warsaw",
    "iso:country":"PL",
    "name:ceb_x_preferred":[
        "Warenka"
    ],
    "name:pol_x_preferred":[
        "Warenka"
    ],
    "name:ukr_x_preferred":[
        "\u0412\u0430\u0440\u0435\u043d\u043a\u0430"
    ],
    "wof:name":"Warenka",
    "wof:placetype":"locality"
},
  "geometry": {"coordinates":[18.60611,52.03477],"type":"Point"}
}