{
  "type": "Feature",
  "properties": {
    "iso:country":"PL",
    "name:pol_x_preferred":[
        "Obrowo"
    ],
    "wof:name":"Obrowo",
    "wof:placetype":"locality"
},
  "geometry": {"coordinates":[18.8387532696349,52.9732912442841],"type":"Point"}
}