{
  "type": "Feature",
  "properties": {
    "iso:country":"PL",
    "name:ceb_x_preferred":[
        "Obrowo"
    ],
    "name:fra_x_preferred":[
        "Obrowo"
    ],
    "name:nld_x_preferred":[
        "Obrowo"
    ],
    "name:pol_x_preferred":[
        "Obrowo"
    ],
    "name:ukr_x_preferred":[
        "\u041e\u0431\u0440\u043e\u0432\u043e"
    ],
    "wof:coterminous":[
        1125290563
    ],
    "wof:name":"Obrowo",
    "wof:placetype":"locality"
},
  "geometry": {"coordinates":[18.8387532696349,52.9732912442841],"type":"Point"}
}