{
  "type": "Feature",
  "properties": {
    "gn:admin1_code":"87.0",
    "gn:admin2_code":"3213.0",
    "gn:admin3_code":"321305.0",
    "gn:asciiname":"Wszedzien",
    "gn:country_code":"PL",
    "gn:dem":22,
    "gn:feature_class":"P",
    "gn:feature_code":"PPL",
    "gn:name":"Wszedzien",
    "gn:population":0,
    "gn:timezone":"Europe/Warsaw",
    "iso:country":"PL",
    "wof:name":"Wszedzien",
    "wof:placetype":"locality"
},
  "geometry": {"coordinates":[16.58377999999999,54.48741999999999],"type":"Point"}
}