{
  "type": "Feature",
  "properties": {
    "gn:admin1_code":"87.0",
    "gn:admin2_code":"3213.0",
    "gn:admin3_code":"321305.0",
    "gn:asciiname":"Wszedzien",
    "gn:country_code":"PL",
    "gn:dem":22,
    "gn:feature_class":"P",
    "gn:feature_code":"PPL",
    "gn:name":"Wszedzien",
    "gn:population":0,
    "gn:timezone":"Europe/Warsaw",
    "iso:country":"PL",
    "name:deu_x_preferred":[
        "Wszedzie\u0144"
    ],
    "name:pol_x_preferred":[
        "Wszedzie\u0144"
    ],
    "name:ukr_x_preferred":[
        "\u0412\u0448\u0435\u0434\u0437\u0435\u043d\u044c"
    ],
    "name:vie_x_preferred":[
        "Wszedzie\u0144"
    ],
    "wof:name":"Wszedzien",
    "wof:placetype":"locality"
},
  "geometry": {"coordinates":[16.58377999999999,54.48741999999999],"type":"Point"}
}