{
  "type": "Feature",
  "properties": {
    "gn:admin1_code":"74.0",
    "gn:admin2_code":"1013.0",
    "gn:admin3_code":"101304.0",
    "gn:asciiname":"Byliny Stare",
    "gn:country_code":"PL",
    "gn:dem":151,
    "gn:feature_class":"P",
    "gn:feature_code":"PPL",
    "gn:name":"Byliny Stare",
    "gn:population":0,
    "gn:timezone":"Europe/Warsaw",
    "iso:country":"PL",
    "name:pol_x_preferred":[
        "Stare Byliny"
    ],
    "name:ukr_x_preferred":[
        "\u0421\u0442\u0430\u0440\u0435 \u0411\u0438\u043b\u0456\u043d\u0438"
    ],
    "wof:name":"Byliny Stare",
    "wof:placetype":"locality"
},
  "geometry": {"coordinates":[20.15493,51.73756],"type":"Point"}
}