{
  "type": "Feature",
  "properties": {
    "gn:gn_country":"PL",
    "gn:gn_fcode":"PPL",
    "gn:gn_pop":0,
    "iso:country":"PL",
    "name:cat_x_preferred":[
        "Karniewek"
    ],
    "name:eng_x_preferred":[
        "Karniewek"
    ],
    "name:fas_x_preferred":[
        "\u06a9\u0627\u0631\u0646\u06af\u0648\u06a9"
    ],
    "name:fra_x_preferred":[
        "Karniewek"
    ],
    "name:nan_x_preferred":[
        "Karniewek"
    ],
    "name:nld_x_preferred":[
        "Karniewek"
    ],
    "name:oci_x_preferred":[
        "Karniewek"
    ],
    "name:pol_x_preferred":[
        "Karniewek"
    ],
    "name:unk_x_variant":[
        "Kurniewek"
    ],
    "qs_pg:aaroncc":"PL",
    "qs_pg:gn_country":"PL",
    "qs_pg:gn_fcode":"PPL",
    "qs_pg:gn_pop":0,
    "qs_pg:name":"Karniewek",
    "qs_pg:name_adm0":"Polska",
    "qs_pg:name_adm1":"Mazowieckie",
    "qs_pg:photos_9k":1,
    "qs_pg:photos_9r":1,
    "qs_pg:photos_all":1,
    "qs_pg:photos_sr":0,
    "qs_pg:pop_sr":0,
    "qs_pg:qs_pg_placetype":"locality",
    "qs_pg:qs_pg_placetype_gp":"Town",
    "qs_pg:woe_adm0":23424923,
    "woe:adm0_id":23424923,
    "woe:name_adm0":"Polska",
    "woe:name_adm1":"Mazowieckie",
    "woe:placetype":"Town",
    "wof:name":"Karniewek",
    "wof:placetype":"locality"
},
  "geometry": {"coordinates":[21.12056,52.59509],"type":"Point"}
}