{
  "type": "Feature",
  "properties": {
    "gn:admin1_code":"78.0",
    "gn:admin2_code":"1429.0",
    "gn:admin3_code":"142905.0",
    "gn:asciiname":"Wyszomierz",
    "gn:country_code":"PL",
    "gn:dem":161,
    "gn:feature_class":"P",
    "gn:feature_code":"PPL",
    "gn:name":"Wyszomierz",
    "gn:population":0,
    "gn:timezone":"Europe/Warsaw",
    "iso:country":"PL",
    "name:fra_x_preferred":[
        "Wyszomierz"
    ],
    "name:lit_x_preferred":[
        "Vi\u0161omie\u017eas"
    ],
    "name:nld_x_preferred":[
        "Wyszomierz"
    ],
    "name:pol_x_preferred":[
        "Wyszomierz"
    ],
    "name:ukr_x_preferred":[
        "\u0412\u0438\u0448\u043e\u043c\u0435\u0436"
    ],
    "wof:name":"Wyszomierz",
    "wof:placetype":"locality"
},
  "geometry": {"coordinates":[22.1193,52.52268],"type":"Point"}
}