{
  "type": "Feature",
  "properties": {
    "gn:admin1_code":"86.0",
    "gn:admin2_code":"3011.0",
    "gn:admin3_code":"301105.0",
    "gn:asciiname":"Bruszczewo",
    "gn:country_code":"PL",
    "gn:dem":85,
    "gn:feature_class":"P",
    "gn:feature_code":"PPL",
    "gn:name":"Bruszczewo",
    "gn:population":0,
    "gn:timezone":"Europe/Warsaw",
    "iso:country":"PL",
    "name:fra_x_preferred":[
        "Bruszczewo"
    ],
    "name:pol_x_preferred":[
        "Bruszczewo"
    ],
    "name:szl_x_preferred":[
        "Bruszczewo"
    ],
    "name:ukr_x_preferred":[
        "\u0411\u0440\u0443\u0449\u0435\u0432\u043e"
    ],
    "wof:name":"Bruszczewo",
    "wof:placetype":"locality"
},
  "geometry": {"coordinates":[16.57391,52.00924000000001],"type":"Point"}
}