{
  "type": "Feature",
  "properties": {
    "gn:admin1_code":"82.0",
    "gn:admin2_code":"2215.0",
    "gn:admin3_code":"221509.0",
    "gn:asciiname":"Zeblewo",
    "gn:country_code":"PL",
    "gn:dem":148,
    "gn:feature_class":"P",
    "gn:feature_code":"PPL",
    "gn:name":"Zeblewo",
    "gn:population":0,
    "gn:timezone":"Europe/Warsaw",
    "iso:country":"PL",
    "name:und_x_variant":[
        "Zeblowo",
        "Zeblewo"
    ],
    "wof:name":"Zeblewo",
    "wof:placetype":"locality"
},
  "geometry": {"coordinates":[18.11839,54.45638],"type":"Point"}
}