{
  "type": "Feature",
  "properties": {
    "gn:admin1_code":"81.0",
    "gn:admin2_code":"2007.0",
    "gn:admin3_code":"200701.0",
    "gn:asciiname":"Chyliny",
    "gn:country_code":"PL",
    "gn:dem":104,
    "gn:feature_class":"P",
    "gn:feature_code":"PPL",
    "gn:name":"Chyliny",
    "gn:population":0,
    "gn:timezone":"Europe/Warsaw",
    "iso:country":"PL",
    "name:lit_x_preferred":[
        "Chilinai"
    ],
    "name:pol_x_preferred":[
        "Chyliny"
    ],
    "name:ukr_x_preferred":[
        "\u0425\u0438\u043b\u0456\u043d\u0438"
    ],
    "wof:name":"Chyliny",
    "wof:placetype":"locality"
},
  "geometry": {"coordinates":[22.46052,53.33087],"type":"Point"}
}