{
  "type": "Feature",
  "properties": {
    "gn:admin1_code":"78.0",
    "gn:admin2_code":"1426.0",
    "gn:admin3_code":"142602.0",
    "gn:asciiname":"Zales",
    "gn:country_code":"PL",
    "gn:dem":128,
    "gn:feature_class":"P",
    "gn:feature_code":"PPL",
    "gn:name":"Zale\u015b",
    "gn:population":0,
    "gn:timezone":"Europe/Warsaw",
    "iso:country":"PL",
    "wof:name":"Zales",
    "wof:placetype":"locality"
},
  "geometry": {"coordinates":[22.55296,52.38089],"type":"Point"}
}