{
  "type": "Feature",
  "properties": {
    "gn:admin1_code":"85.0",
    "gn:admin2_code":"2810.0",
    "gn:admin3_code":"281004.0",
    "gn:asciiname":"Zyzdrojowa Wola",
    "gn:country_code":"PL",
    "gn:dem":135,
    "gn:feature_class":"P",
    "gn:feature_code":"PPL",
    "gn:name":"Zyzdrojowa Wola",
    "gn:population":0,
    "gn:timezone":"Europe/Warsaw",
    "iso:country":"PL",
    "name:und_x_variant":[
        "Kranzhausen",
        "Sysdroywolla",
        "Zyzdrojowa Wola"
    ],
    "wof:name":"Zyzdrojowa Wola",
    "wof:placetype":"locality"
},
  "geometry": {"coordinates":[21.28335,53.65834],"type":"Point"}
}