{
  "type": "Feature",
  "properties": {
    "gn:admin1_code":"84.0",
    "gn:admin2_code":"2607.0",
    "gn:admin3_code":"260704.0",
    "gn:asciiname":"Stoki Duze",
    "gn:country_code":"PL",
    "gn:dem":161,
    "gn:feature_class":"P",
    "gn:feature_code":"PPL",
    "gn:name":"Stoki Du\u017ce",
    "gn:population":0,
    "gn:timezone":"Europe/Warsaw",
    "iso:country":"PL",
    "name:pol_x_preferred":[
        "Stoki Du\u017ce"
    ],
    "name:ukr_x_preferred":[
        "\u0421\u0442\u043e\u043a\u0456-\u0414\u0443\u0436\u0435"
    ],
    "name:und_x_variant":[
        "Kolonia Stoki"
    ],
    "wof:name":"Stoki Duze",
    "wof:placetype":"locality"
},
  "geometry": {"coordinates":[21.56048,50.95524],"type":"Point"}
}