{
  "type": "Feature",
  "properties": {
    "gn:admin1_code":"86.0",
    "gn:admin2_code":"3027.0",
    "gn:admin3_code":"302703.0",
    "gn:asciiname":"Mikulice",
    "gn:country_code":"PL",
    "gn:dem":116,
    "gn:feature_class":"P",
    "gn:feature_code":"PPL",
    "gn:name":"Mikulice",
    "gn:population":0,
    "gn:timezone":"Europe/Warsaw",
    "iso:country":"PL",
    "name:ceb_x_preferred":[
        "Mikulice"
    ],
    "name:pol_x_preferred":[
        "Mikulice"
    ],
    "name:ukr_x_preferred":[
        "\u041c\u0456\u043a\u0443\u043b\u0456\u0446\u0435"
    ],
    "wof:name":"Mikulice",
    "wof:placetype":"locality"
},
  "geometry": {"coordinates":[18.58955,51.93432],"type":"Point"}
}