{
  "type": "Feature",
  "properties": {
    "gn:admin1_code":"78.0",
    "gn:admin2_code":"1401.0",
    "gn:admin3_code":"140103.0",
    "gn:asciiname":"Ratoszyn",
    "gn:country_code":"PL",
    "gn:dem":178,
    "gn:feature_class":"P",
    "gn:feature_code":"PPL",
    "gn:name":"Ratoszyn",
    "gn:population":0,
    "gn:timezone":"Europe/Warsaw",
    "iso:country":"PL",
    "wof:name":"Ratoszyn",
    "wof:placetype":"locality"
},
  "geometry": {"coordinates":[20.81129,51.55941],"type":"Point"}
}