{
  "type": "Feature",
  "properties": {
    "gn:gn_country":"PL",
    "gn:gn_fcode":"PPL",
    "gn:gn_pop":522,
    "gn:population":522,
    "iso:country":"PL",
    "name:eng_x_preferred":[
        "Bogus\u0142awice"
    ],
    "name:fre_x_preferred":[
        "Bogus\u0142awice"
    ],
    "name:pol_x_preferred":[
        "Bogus\u0142awice"
    ],
    "qs_pg:aaroncc":"PL",
    "qs_pg:gn_country":"PL",
    "qs_pg:gn_fcode":"PPL",
    "qs_pg:gn_pop":522,
    "qs_pg:name":"Bogus\u0142awice",
    "qs_pg:name_adm0":"Polska",
    "qs_pg:name_adm1":"Sl\u0105skie",
    "qs_pg:photos_9r":0,
    "qs_pg:photos_sr":0,
    "qs_pg:pop_sr":2,
    "qs_pg:qs_pg_placetype":"locality",
    "qs_pg:qs_pg_placetype_gp":"Town",
    "qs_pg:woe_adm0":23424923,
    "woe:adm0_id":23424923,
    "woe:name_adm0":"Polska",
    "woe:name_adm1":"Sl\u0105skie",
    "woe:placetype":"Town",
    "wof:name":"Bogus\u0142awice",
    "wof:placetype":"locality",
    "wof:population":522
},
  "geometry": {"coordinates":[19.2592,50.95605],"type":"Point"}
}