{
  "type": "Feature",
  "properties": {
    "gn:admin1_code":"73.0",
    "gn:admin2_code":"418.0",
    "gn:admin3_code":"41812.0",
    "gn:asciiname":"Turowo Nowe",
    "gn:country_code":"PL",
    "gn:dem":83,
    "gn:feature_class":"P",
    "gn:feature_code":"PPL",
    "gn:name":"Turowo Nowe",
    "gn:population":0,
    "gn:timezone":"Europe/Warsaw",
    "iso:country":"PL",
    "wof:name":"Turowo Nowe",
    "wof:placetype":"locality"
},
  "geometry": {"coordinates":[18.91667,52.55],"type":"Point"}
}