{
  "type": "Feature",
  "properties": {
    "gn:admin1_code":"78.0",
    "gn:admin2_code":"1428.0",
    "gn:admin3_code":"142803.0",
    "gn:asciiname":"Gizyce",
    "gn:country_code":"PL",
    "gn:dem":87,
    "gn:feature_class":"P",
    "gn:feature_code":"PPL",
    "gn:name":"Gi\u017cyce",
    "gn:population":0,
    "gn:timezone":"Europe/Warsaw",
    "iso:country":"PL",
    "name:und_x_variant":[
        "Gi\u017cyczki",
        "Gi\u017cyce"
    ],
    "wof:name":"Gizyce",
    "wof:placetype":"locality"
},
  "geometry": {"coordinates":[20.08388,52.28897],"type":"Point"}
}