{
  "type": "Feature",
  "properties": {
    "gn:admin1_code":"76.0",
    "gn:admin2_code":"862.0",
    "gn:admin3_code":"86201.0",
    "gn:asciiname":"Zatonie",
    "gn:country_code":"PL",
    "gn:dem":72,
    "gn:feature_class":"P",
    "gn:feature_code":"PPL",
    "gn:name":"Zatonie",
    "gn:population":0,
    "gn:timezone":"Europe/Warsaw",
    "iso:country":"PL",
    "name:ceb_x_preferred":[
        "Zatonie"
    ],
    "name:fra_x_preferred":[
        "Zatonie"
    ],
    "name:nld_x_preferred":[
        "Zatonie"
    ],
    "name:pol_x_preferred":[
        "Zatonie"
    ],
    "wof:name":"Zatonie",
    "wof:placetype":"locality"
},
  "geometry": {"coordinates":[15.55992,51.85708],"type":"Point"}
}