{
  "type": "Feature",
  "properties": {
    "gn:admin1_code":"81.0",
    "gn:admin2_code":"2007.0",
    "gn:admin3_code":"200709.0",
    "gn:asciiname":"Debniki",
    "gn:country_code":"PL",
    "gn:dem":107,
    "gn:feature_class":"P",
    "gn:feature_code":"PPL",
    "gn:name":"D\u0119bniki",
    "gn:population":0,
    "gn:timezone":"Europe/Warsaw",
    "iso:country":"PL",
    "name:lit_x_preferred":[
        "Dembnikai"
    ],
    "name:pol_x_preferred":[
        "D\u0119bniki"
    ],
    "name:ukr_x_preferred":[
        "\u0414\u0435\u043c\u0431\u043d\u0438\u043a\u0438"
    ],
    "wof:name":"Debniki",
    "wof:placetype":"locality"
},
  "geometry": {"coordinates":[21.82262,53.24426],"type":"Point"}
}