{
  "type": "Feature",
  "properties": {
    "gn:admin1_code":"84.0",
    "gn:admin2_code":"2604.0",
    "gn:admin3_code":"260411.0",
    "gn:asciiname":"Pepice",
    "gn:country_code":"PL",
    "gn:dem":293,
    "gn:feature_class":"P",
    "gn:feature_code":"PPL",
    "gn:name":"P\u0119pice",
    "gn:population":0,
    "gn:timezone":"Europe/Warsaw",
    "iso:country":"PL",
    "name:ceb_x_preferred":[
        "P\u0119pice"
    ],
    "name:pol_x_preferred":[
        "P\u0119pice"
    ],
    "name:ukr_x_preferred":[
        "\u041f\u0435\u043c\u043f\u0456\u0446\u0435"
    ],
    "wof:name":"Pepice",
    "wof:placetype":"locality"
},
  "geometry": {"coordinates":[20.49507,50.97465],"type":"Point"}
}