{
  "type": "Feature",
  "properties": {
    "gn:admin1_code":"86.0",
    "gn:admin2_code":"3030.0",
    "gn:admin3_code":"303001.0",
    "gn:asciiname":"Budzilowo",
    "gn:country_code":"PL",
    "gn:dem":95,
    "gn:feature_class":"P",
    "gn:feature_code":"PPL",
    "gn:name":"Budzi\u0142owo",
    "gn:population":0,
    "gn:timezone":"Europe/Warsaw",
    "iso:country":"PL",
    "name:fra_x_preferred":[
        "Budzi\u0142owo"
    ],
    "name:pol_x_preferred":[
        "Budzi\u0142owo"
    ],
    "name:ukr_x_preferred":[
        "\u0411\u0443\u0434\u0437\u0456\u043b\u043e\u0432\u043e"
    ],
    "name:und_x_variant":[
        "Budzi\u0142owo"
    ],
    "wof:name":"Budzilowo",
    "wof:placetype":"locality"
},
  "geometry": {"coordinates":[17.59067000000001,52.19772],"type":"Point"}
}