{
  "type": "Feature",
  "properties": {
    "gn:admin1_code":"75.0",
    "gn:admin2_code":"606.0",
    "gn:admin3_code":"60607.0",
    "gn:asciiname":"Borowica",
    "gn:country_code":"PL",
    "gn:dem":175,
    "gn:feature_class":"P",
    "gn:feature_code":"PPL",
    "gn:name":"Borowica",
    "gn:population":0,
    "gn:timezone":"Europe/Warsaw",
    "iso:country":"PL",
    "wof:name":"Borowica",
    "wof:placetype":"locality"
},
  "geometry": {"coordinates":[23.12836,51.0656],"type":"Point"}
}