{
  "type": "Feature",
  "properties": {
    "gn:admin1_code":"75.0",
    "gn:admin2_code":"606.0",
    "gn:admin3_code":"60607.0",
    "gn:asciiname":"Borowica",
    "gn:country_code":"PL",
    "gn:dem":175,
    "gn:feature_class":"P",
    "gn:feature_code":"PPL",
    "gn:name":"Borowica",
    "gn:population":0,
    "gn:timezone":"Europe/Warsaw",
    "iso:country":"PL",
    "name:azb_x_preferred":[
        "\u0628\u0648\u0631\u0648\u0648\u06cc\u062a\u0633\u0627"
    ],
    "name:fas_x_preferred":[
        "\u0628\u0648\u0631\u0648\u0648\u06cc\u062a\u0633\u0627"
    ],
    "name:fra_x_preferred":[
        "Borowica"
    ],
    "name:pol_x_preferred":[
        "Borowica"
    ],
    "name:swe_x_preferred":[
        "Borowica"
    ],
    "name:szl_x_preferred":[
        "Borowica"
    ],
    "name:ukr_x_preferred":[
        "\u0411\u043e\u0440\u043e\u0432\u0438\u0446\u044f"
    ],
    "wof:name":"Borowica",
    "wof:placetype":"locality"
},
  "geometry": {"coordinates":[23.12836,51.0656],"type":"Point"}
}