{
  "type": "Feature",
  "properties": {
    "gn:admin1_code":"76.0",
    "gn:admin2_code":"809.0",
    "gn:admin3_code":"80907.0",
    "gn:asciiname":"Wilkanowo",
    "gn:country_code":"PL",
    "gn:dem":157,
    "gn:feature_class":"P",
    "gn:feature_code":"PPL",
    "gn:name":"Wilkanowo",
    "gn:population":0,
    "gn:timezone":"Europe/Warsaw",
    "iso:country":"PL",
    "name:fra_x_preferred":[
        "Wilkanowo"
    ],
    "name:pol_x_preferred":[
        "Wilkanowo"
    ],
    "name:ukr_x_preferred":[
        "\u0412\u0456\u043b\u044c\u043a\u0430\u043d\u043e\u0432\u043e"
    ],
    "wof:name":"Wilkanowo",
    "wof:placetype":"locality"
},
  "geometry": {"coordinates":[15.43591,51.92071],"type":"Point"}
}