{
  "type": "Feature",
  "properties": {
    "iso:country":"PL",
    "name:pol_x_preferred":[
        "\u0141\u0105ck"
    ],
    "wof:name":"\u0141\u0105ck",
    "wof:placetype":"locality"
},
  "geometry": {"coordinates":[19.6302940509501,52.4566383029848],"type":"Point"}
}