{
  "type": "Feature",
  "properties": {
    "iso:country":"PL",
    "name:azb_x_preferred":[
        "\u0648\u0627\u0646\u062a\u0633\u06a9"
    ],
    "name:ceb_x_preferred":[
        "\u0141\u0105ck"
    ],
    "name:deu_x_preferred":[
        "\u0141\u0105ck"
    ],
    "name:fas_x_preferred":[
        "\u0648\u0627\u0646\u062a\u0633\u06a9"
    ],
    "name:fra_x_preferred":[
        "\u0141\u0105ck"
    ],
    "name:nld_x_preferred":[
        "\u0141\u0105ck"
    ],
    "name:pol_x_preferred":[
        "\u0141\u0105ck"
    ],
    "name:ukr_x_preferred":[
        "\u041b\u043e\u043d\u0446\u044c\u043a"
    ],
    "wof:coterminous":[
        1125295369
    ],
    "wof:name":"\u0141\u0105ck",
    "wof:placetype":"locality"
},
  "geometry": {"coordinates":[19.6302940509501,52.4566383029848],"type":"Point"}
}