{
  "type": "Feature",
  "properties": {
    "gn:admin1_code":"82.0",
    "gn:admin2_code":"2210.0",
    "gn:admin3_code":"221004.0",
    "gn:asciiname":"Chorazowka",
    "gn:country_code":"PL",
    "gn:dem":-1,
    "gn:feature_class":"P",
    "gn:feature_code":"PPL",
    "gn:name":"Chor\u0105\u017c\u00f3wka",
    "gn:population":0,
    "gn:timezone":"Europe/Warsaw",
    "iso:country":"PL",
    "name:und_x_variant":[
        "Junkertroyl",
        "Junkenrtroyl",
        "Chor\u0105\u017c\u00f3wka"
    ],
    "wof:name":"Chorazowka",
    "wof:placetype":"locality"
},
  "geometry": {"coordinates":[19.06933,54.2881],"type":"Point"}
}