{
  "type": "Feature",
  "properties": {
    "gn:admin1_code":"74.0",
    "gn:admin2_code":"1003.0",
    "gn:admin3_code":"100301.0",
    "gn:asciiname":"Petronelow",
    "gn:country_code":"PL",
    "gn:dem":188,
    "gn:feature_class":"P",
    "gn:feature_code":"PPL",
    "gn:name":"Petronel\u00f3w",
    "gn:population":0,
    "gn:timezone":"Europe/Warsaw",
    "iso:country":"PL",
    "name:fra_x_preferred":[
        "Petronel\u00f3w"
    ],
    "name:pol_x_preferred":[
        "Petronel\u00f3w"
    ],
    "name:ukr_x_preferred":[
        "\u041f\u0435\u0442\u0440\u043e\u043d\u0435\u043b\u044e\u0432"
    ],
    "name:und_x_variant":[
        "Petronel\u00f3w"
    ],
    "wof:name":"Petronelow",
    "wof:placetype":"locality"
},
  "geometry": {"coordinates":[19.13562,51.48086],"type":"Point"}
}