{
  "type": "Feature",
  "properties": {
    "gn:gn_country":"PL",
    "gn:gn_fcode":"PPL",
    "gn:gn_pop":433,
    "gn:population":433,
    "iso:country":"PL",
    "name:eng_x_preferred":[
        "Jurczyce"
    ],
    "name:fre_x_preferred":[
        "Jurczyce"
    ],
    "name:pol_x_preferred":[
        "Jurczyce"
    ],
    "name:rus_x_preferred":[
        "\u042e\u0440\u0447\u0438\u0446\u0435"
    ],
    "qs_pg:aaroncc":"PL",
    "qs_pg:gn_country":"PL",
    "qs_pg:gn_fcode":"PPL",
    "qs_pg:gn_pop":433,
    "qs_pg:name":"Jurczyce",
    "qs_pg:name_adm0":"Polska",
    "qs_pg:name_adm1":"Ma\u0142opolskie",
    "qs_pg:photos_9r":0,
    "qs_pg:photos_sr":0,
    "qs_pg:pop_sr":2,
    "qs_pg:qs_pg_placetype":"locality",
    "qs_pg:qs_pg_placetype_gp":"Town",
    "qs_pg:woe_adm0":23424923,
    "woe:adm0_id":23424923,
    "woe:name_adm0":"Polska",
    "woe:name_adm1":"Ma\u0142opolskie",
    "woe:placetype":"Town",
    "wof:name":"Jurczyce",
    "wof:placetype":"locality",
    "wof:population":433
},
  "geometry": {"coordinates":[19.78397,49.93852],"type":"Point"}
}