{
  "type": "Feature",
  "properties": {
    "gn:admin1_code":"78.0",
    "gn:admin2_code":"1415.0",
    "gn:admin3_code":"141503.0",
    "gn:asciiname":"Wojsze",
    "gn:country_code":"PL",
    "gn:dem":104,
    "gn:feature_class":"P",
    "gn:feature_code":"PPL",
    "gn:name":"Wojsze",
    "gn:population":0,
    "gn:timezone":"Europe/Warsaw",
    "iso:country":"PL",
    "name:fra_x_preferred":[
        "Wojsze"
    ],
    "name:pol_x_preferred":[
        "Wojsze"
    ],
    "name:ukr_x_preferred":[
        "\u0412\u043e\u0439\u0448\u0435"
    ],
    "wof:name":"Wojsze",
    "wof:placetype":"locality"
},
  "geometry": {"coordinates":[21.6962,52.97492],"type":"Point"}
}