{
  "type": "Feature",
  "properties": {
    "iso:country":"PL",
    "name:eng_x_preferred":[
        "Gorczynek"
    ],
    "name:pol_x_preferred":[
        "G\u00f3rczynek"
    ],
    "wof:name":"Gorczynek",
    "wof:placetype":"neighbourhood"
},
  "geometry": {"coordinates":[16.871544274962,52.37554595514437],"type":"Point"}
}