{
  "type": "Feature",
  "properties": {
    "gn:admin1_code":"85.0",
    "gn:admin2_code":"2807.0",
    "gn:admin3_code":"280703.0",
    "gn:asciiname":"Segnowy",
    "gn:country_code":"PL",
    "gn:dem":102,
    "gn:feature_class":"P",
    "gn:feature_code":"PPL",
    "gn:name":"Segnowy",
    "gn:population":0,
    "gn:timezone":"Europe/Warsaw",
    "iso:country":"PL",
    "name:pol_x_preferred":[
        "Segnowy"
    ],
    "name:ukr_x_preferred":[
        "\u0421\u0435\u0491\u043d\u043e\u0432\u0438"
    ],
    "wof:name":"Segnowy",
    "wof:placetype":"locality"
},
  "geometry": {"coordinates":[19.45425,53.62235],"type":"Point"}
}