{
  "type": "Feature",
  "properties": {
    "gn:admin1_code":"85.0",
    "gn:admin2_code":"2804.0",
    "gn:admin3_code":"280404.0",
    "gn:asciiname":"Zolwiniec",
    "gn:cc2":"PL",
    "gn:country_code":"PL",
    "gn:dem":-4,
    "gn:feature_class":"P",
    "gn:feature_code":"PPL",
    "gn:name":"\u017b\u00f3\u0142winiec",
    "gn:population":0,
    "gn:timezone":"Europe/Warsaw",
    "iso:country":"PL",
    "name:pol_x_preferred":[
        "\u017b\u00f3\u0142winiec"
    ],
    "name:ukr_x_preferred":[
        "\u0416\u0443\u043b\u0432\u0456\u043d\u0435\u0446\u044c"
    ],
    "name:und_x_variant":[
        "Wengenwalde",
        "Wengelwalde",
        "Wengelwald"
    ],
    "wof:name":"Zolwiniec",
    "wof:placetype":"locality"
},
  "geometry": {"coordinates":[19.43138,54.07611],"type":"Point"}
}