{
  "type": "Feature",
  "properties": {
    "gn:admin1_code":"86.0",
    "gn:admin2_code":"3017.0",
    "gn:admin3_code":"301706.0",
    "gn:asciiname":"Drogoslaw",
    "gn:country_code":"PL",
    "gn:dem":152,
    "gn:feature_class":"P",
    "gn:feature_code":"PPL",
    "gn:name":"Drogos\u0142aw",
    "gn:population":0,
    "gn:timezone":"Europe/Warsaw",
    "iso:country":"PL",
    "name:pol_x_preferred":[
        "Drogos\u0142aw"
    ],
    "name:ukr_x_preferred":[
        "\u0414\u0440\u043e\u0491\u043e\u0441\u043b\u0430\u0432"
    ],
    "name:und_x_variant":[
        "Drogos\u0142aw"
    ],
    "wof:name":"Drogoslaw",
    "wof:placetype":"locality"
},
  "geometry": {"coordinates":[17.66825,51.72911],"type":"Point"}
}