{
  "type": "Feature",
  "properties": {
    "gn:admin1_code":"87.0",
    "gn:admin2_code":"3209.0",
    "gn:admin3_code":"320906.0",
    "gn:asciiname":"Bukowo",
    "gn:country_code":"PL",
    "gn:dem":151,
    "gn:feature_class":"P",
    "gn:feature_code":"PPL",
    "gn:name":"Bukowo",
    "gn:population":0,
    "gn:timezone":"Europe/Warsaw",
    "iso:country":"PL",
    "name:ceb_x_preferred":[
        "Bukowo"
    ],
    "name:deu_x_preferred":[
        "Bukowo"
    ],
    "name:pol_x_preferred":[
        "Bukowo"
    ],
    "name:ukr_x_preferred":[
        "\u0411\u0443\u043a\u043e\u0432\u043e"
    ],
    "name:vie_x_preferred":[
        "Bukowo"
    ],
    "wof:name":"Bukowo",
    "wof:placetype":"locality"
},
  "geometry": {"coordinates":[16.59331,54.17345],"type":"Point"}
}