{
  "type": "Feature",
  "properties": {
    "gn:admin1_code":"81.0",
    "gn:admin2_code":"2002.0",
    "gn:admin3_code":"200214.0",
    "gn:asciiname":"Halickie",
    "gn:country_code":"PL",
    "gn:dem":158,
    "gn:feature_class":"P",
    "gn:feature_code":"PPL",
    "gn:name":"Halickie",
    "gn:population":0,
    "gn:timezone":"Europe/Warsaw",
    "iso:country":"PL",
    "name:lit_x_preferred":[
        "Halickiai"
    ],
    "name:pol_x_preferred":[
        "Halickie"
    ],
    "name:ukr_x_preferred":[
        "\u0413\u0430\u043b\u0456\u0446\u044c\u043a\u0435"
    ],
    "wof:name":"Halickie",
    "wof:placetype":"locality"
},
  "geometry": {"coordinates":[23.2332,53.06627],"type":"Point"}
}