{
  "type": "Feature",
  "properties": {
    "gn:admin1_code":"85.0",
    "gn:admin2_code":"2814.0",
    "gn:admin3_code":"281411.0",
    "gn:asciiname":"Bartazek",
    "gn:country_code":"PL",
    "gn:dem":120,
    "gn:feature_class":"P",
    "gn:feature_code":"PPL",
    "gn:name":"Bart\u0105\u017cek",
    "gn:population":0,
    "gn:timezone":"Europe/Warsaw",
    "iso:country":"PL",
    "name:nld_x_preferred":[
        "Bart\u0105\u017cek"
    ],
    "name:pol_x_preferred":[
        "Bart\u0105\u017cek"
    ],
    "name:und_x_variant":[
        "Klein Bertung"
    ],
    "wof:name":"Bartazek",
    "wof:placetype":"locality"
},
  "geometry": {"coordinates":[20.49358,53.70947],"type":"Point"}
}