{
  "type": "Feature",
  "properties": {
    "gn:admin1_code":"76.0",
    "gn:admin2_code":"806.0",
    "gn:admin3_code":"80602.0",
    "gn:asciiname":"Kosinek",
    "gn:country_code":"PL",
    "gn:dem":44,
    "gn:feature_class":"P",
    "gn:feature_code":"PPL",
    "gn:name":"Kosinek",
    "gn:population":0,
    "gn:timezone":"Europe/Warsaw",
    "iso:country":"PL",
    "name:pol_x_preferred":[
        "Kosinek"
    ],
    "name:und_x_variant":[
        "L\u00fccks Teerofen",
        "Kosinek"
    ],
    "name:vie_x_preferred":[
        "Kosinek"
    ],
    "wof:name":"Kosinek",
    "wof:placetype":"locality"
},
  "geometry": {"coordinates":[15.90295,52.90637],"type":"Point"}
}