{
  "type": "Feature",
  "properties": {
    "gn:country":"PL",
    "gn:fcode":"PPLA3",
    "gn:population":1213,
    "iso:country":"PL",
    "name:bul_x_preferred":[
        "\u041e\u043f\u0430\u0442\u043e\u0432"
    ],
    "name:ceb_x_preferred":[
        "Opat\u00f3w"
    ],
    "name:deu_x_preferred":[
        "Opat\u00f3w"
    ],
    "name:epo_x_preferred":[
        "Opat\u00f3w"
    ],
    "name:fra_x_preferred":[
        "Opat\u00f3w"
    ],
    "name:hak_x_preferred":[
        "Opat\u00f3w"
    ],
    "name:heb_x_preferred":[
        "\u05d0\u05e4\u05d8\u05d0"
    ],
    "name:jav_x_preferred":[
        "Opat\u00f3w"
    ],
    "name:lav_x_preferred":[
        "Opatova"
    ],
    "name:msa_x_preferred":[
        "Opat\u00f3w"
    ],
    "name:nld_x_preferred":[
        "Opat\u00f3w"
    ],
    "name:pol_x_preferred":[
        "Opat\u00f3w"
    ],
    "name:por_x_preferred":[
        "Opat\u00f3w"
    ],
    "name:ron_x_preferred":[
        "Opat\u00f3w"
    ],
    "name:rus_x_preferred":[
        "\u041e\u043f\u0430\u0442\u0443\u0432"
    ],
    "name:slk_x_preferred":[
        "Opat\u00f3w"
    ],
    "name:srp_x_preferred":[
        "\u041e\u043f\u0430\u0442\u043e\u0432"
    ],
    "name:szl_x_preferred":[
        "Uopat\u016fw"
    ],
    "name:ukr_x_preferred":[
        "\u041e\u043f\u0430\u0442\u0456\u0432"
    ],
    "name:vie_x_preferred":[
        "Opat\u00f3w"
    ],
    "name:war_x_preferred":[
        "Opat\u00f3w"
    ],
    "name:yid_x_preferred":[
        "\u05d0\u05e4\u05d8\u05d0"
    ],
    "name:zho_x_preferred":[
        "\u5967\u5e15\u5716\u592b"
    ],
    "qs_pg:aaroncc":"PL",
    "qs_pg:gn_country":"PL",
    "qs_pg:gn_fcode":"PPLA3",
    "qs_pg:gn_pop":1213,
    "qs_pg:name":"Opat\u00f3w",
    "qs_pg:name_adm0":"Polska",
    "qs_pg:name_adm1":"Sl\u0105skie",
    "qs_pg:photos_9r":0,
    "qs_pg:photos_sr":0,
    "qs_pg:pop_sr":3,
    "qs_pg:qs_pg_placetype":"localadmin",
    "qs_pg:qs_pg_placetype_gp":"LocalAdmin",
    "qs_pg:woe_adm0":23424923,
    "woe:adm0_id":23424923,
    "woe:name_adm0":"Polska",
    "woe:name_adm1":"Sl\u0105skie",
    "woe:placetype":"LocalAdmin",
    "wof:name":"Opat\u00f3w",
    "wof:placetype":"localadmin",
    "wof:population":1213
},
  "geometry": {"coordinates":[18.81941,50.95567],"type":"Point"}
}