{
  "type": "Feature",
  "properties": {
    "gn:admin1_code":"84.0",
    "gn:admin2_code":"2604.0",
    "gn:admin3_code":"260414.0",
    "gn:asciiname":"Galezice",
    "gn:country_code":"PL",
    "gn:dem":271,
    "gn:feature_class":"P",
    "gn:feature_code":"PPL",
    "gn:name":"Ga\u0142\u0119zice",
    "gn:population":0,
    "gn:timezone":"Europe/Warsaw",
    "iso:country":"PL",
    "name:und_x_variant":[
        "Ga\u0142\u0119zice"
    ],
    "wof:name":"Galezice",
    "wof:placetype":"locality"
},
  "geometry": {"coordinates":[20.41068,50.84472],"type":"Point"}
}