{
  "type": "Feature",
  "properties": {
    "gn:admin1_code":"84.0",
    "gn:admin2_code":"2604.0",
    "gn:admin3_code":"260414.0",
    "gn:asciiname":"Galezice",
    "gn:country_code":"PL",
    "gn:dem":271,
    "gn:feature_class":"P",
    "gn:feature_code":"PPL",
    "gn:name":"Ga\u0142\u0119zice",
    "gn:population":0,
    "gn:timezone":"Europe/Warsaw",
    "iso:country":"PL",
    "name:ceb_x_preferred":[
        "Ga\u0142\u0119zice"
    ],
    "name:nld_x_preferred":[
        "Ga\u0142\u0119zice"
    ],
    "name:pol_x_preferred":[
        "Ga\u0142\u0119zice"
    ],
    "name:ukr_x_preferred":[
        "\u0490\u0430\u043b\u0435\u043d\u0437\u0456\u0446\u0435"
    ],
    "wof:name":"Galezice",
    "wof:placetype":"locality"
},
  "geometry": {"coordinates":[20.41068,50.84472],"type":"Point"}
}