{
  "type": "Feature",
  "properties": {
    "gn:admin1_code":"78.0",
    "gn:admin2_code":"1402.0",
    "gn:admin3_code":"140207.0",
    "gn:asciiname":"Pomorze",
    "gn:country_code":"PL",
    "gn:dem":115,
    "gn:feature_class":"P",
    "gn:feature_code":"PPL",
    "gn:name":"Pomorze",
    "gn:population":0,
    "gn:timezone":"Europe/Warsaw",
    "iso:country":"PL",
    "name:fra_x_preferred":[
        "Pomorze"
    ],
    "name:pol_x_preferred":[
        "Pomorze"
    ],
    "name:ukr_x_preferred":[
        "\u041f\u043e\u043c\u043e\u0436\u0435"
    ],
    "wof:name":"Pomorze",
    "wof:placetype":"locality"
},
  "geometry": {"coordinates":[20.7025,52.86994],"type":"Point"}
}