{
  "type": "Feature",
  "properties": {
    "gn:admin1_code":"78.0",
    "gn:admin2_code":"1417.0",
    "gn:admin3_code":"141707.0",
    "gn:asciiname":"Warszowka",
    "gn:country_code":"PL",
    "gn:dem":94,
    "gn:feature_class":"P",
    "gn:feature_code":"PPL",
    "gn:name":"Warsz\u00f3wka",
    "gn:population":0,
    "gn:timezone":"Europe/Warsaw",
    "iso:country":"PL",
    "name:ceb_x_preferred":[
        "Warsz\u00f3wka"
    ],
    "name:fra_x_preferred":[
        "Warsz\u00f3wka"
    ],
    "name:pol_x_preferred":[
        "Warsz\u00f3wka"
    ],
    "name:ukr_x_preferred":[
        "\u0412\u0430\u0440\u0448\u0443\u0432\u043a\u0430"
    ],
    "wof:name":"Warszowka",
    "wof:placetype":"locality"
},
  "geometry": {"coordinates":[21.32747,51.98494],"type":"Point"}
}