{
  "type": "Feature",
  "properties": {
    "gn:admin1_code":"78.0",
    "gn:admin2_code":"1413.0",
    "gn:admin3_code":"141306.0",
    "gn:asciiname":"Zmijewo Kuce",
    "gn:country_code":"PL",
    "gn:dem":130,
    "gn:feature_class":"P",
    "gn:feature_code":"PPL",
    "gn:name":"\u017bmijewo Kuce",
    "gn:population":0,
    "gn:timezone":"Europe/Warsaw",
    "iso:country":"PL",
    "name:und_x_variant":[
        "\u017bmijewo Kuce"
    ],
    "wof:name":"Zmijewo Kuce",
    "wof:placetype":"locality"
},
  "geometry": {"coordinates":[20.52326,53.00141],"type":"Point"}
}