{
  "type": "Feature",
  "properties": {
    "gn:admin1_code":"78.0",
    "gn:admin2_code":"1423.0",
    "gn:admin3_code":"142307.0",
    "gn:asciiname":"Klonowa",
    "gn:country_code":"PL",
    "gn:dem":175,
    "gn:feature_class":"P",
    "gn:feature_code":"PPL",
    "gn:name":"Klonowa",
    "gn:population":0,
    "gn:timezone":"Europe/Warsaw",
    "iso:country":"PL",
    "wof:name":"Klonowa",
    "wof:placetype":"locality"
},
  "geometry": {"coordinates":[20.63333,51.41162],"type":"Point"}
}