{
  "type": "Feature",
  "properties": {
    "gn:admin1_code":"73.0",
    "gn:admin2_code":"418.0",
    "gn:admin3_code":"41813.0",
    "gn:asciiname":"Warzachewka Krolewska",
    "gn:country_code":"PL",
    "gn:dem":65,
    "gn:feature_class":"P",
    "gn:feature_code":"PPL",
    "gn:name":"Warz\u0105chewka Kr\u00f3lewska",
    "gn:population":0,
    "gn:timezone":"Europe/Warsaw",
    "iso:country":"PL",
    "name:und_x_variant":[
        "Warz\u0105chewka",
        "Warz\u0105chewka Kr\u00f3lewska"
    ],
    "wof:name":"Warzachewka Krolewska",
    "wof:placetype":"locality"
},
  "geometry": {"coordinates":[19.09235,52.58601],"type":"Point"}
}