{
  "type": "Feature",
  "properties": {
    "gn:admin1_code":"73.0",
    "gn:admin2_code":"418.0",
    "gn:admin3_code":"41813.0",
    "gn:asciiname":"Warzachewka Krolewska",
    "gn:country_code":"PL",
    "gn:dem":65,
    "gn:feature_class":"P",
    "gn:feature_code":"PPL",
    "gn:name":"Warz\u0105chewka Kr\u00f3lewska",
    "gn:population":0,
    "gn:timezone":"Europe/Warsaw",
    "iso:country":"PL",
    "name:pol_x_preferred":[
        "Warz\u0105chewka Kr\u00f3lewska"
    ],
    "name:szl_x_preferred":[
        "Kr\u016flewsko Warz\u016fnchewka"
    ],
    "name:ukr_x_preferred":[
        "\u0412\u0430\u0436\u043e\u043d\u0445\u0435\u0432\u043a\u0430-\u041a\u0440\u0443\u043b\u0435\u0432\u0441\u044c\u043a\u0430"
    ],
    "name:und_x_variant":[
        "Warz\u0105chewka",
        "Warz\u0105chewka Kr\u00f3lewska"
    ],
    "wof:name":"Warzachewka Krolewska",
    "wof:placetype":"locality"
},
  "geometry": {"coordinates":[19.09235,52.58601],"type":"Point"}
}