{
  "type": "Feature",
  "properties": {
    "gn:admin1_code":"73.0",
    "gn:admin2_code":"417.0",
    "gn:admin3_code":"41704.0",
    "gn:asciiname":"Plachawy",
    "gn:country_code":"PL",
    "gn:dem":97,
    "gn:feature_class":"P",
    "gn:feature_code":"PPL",
    "gn:name":"P\u0142\u0105chawy",
    "gn:population":0,
    "gn:timezone":"Europe/Warsaw",
    "iso:country":"PL",
    "name:pol_x_preferred":[
        "P\u0142\u0105chawy"
    ],
    "name:ukr_x_preferred":[
        "\u041f\u043b\u043e\u043d\u0445\u0430\u0432\u0438"
    ],
    "wof:name":"Plachawy",
    "wof:placetype":"locality"
},
  "geometry": {"coordinates":[18.74696,53.3526],"type":"Point"}
}