{
  "type": "Feature",
  "properties": {
    "gn:population":1300,
    "iso:country":"PL",
    "name:ast_x_preferred":[
        "So\u015bnie"
    ],
    "name:azb_x_preferred":[
        "\u0633\u0648\u0634\u0646\u0642\u0647"
    ],
    "name:deu_x_preferred":[
        "So\u015bnie"
    ],
    "name:eng_x_preferred":[
        "So\u015bnie"
    ],
    "name:fas_x_preferred":[
        "\u0633\u0648\u0634\u0646\u06af\u0647"
    ],
    "name:fra_x_preferred":[
        "So\u015bnie"
    ],
    "name:nld_x_preferred":[
        "So\u015bnie"
    ],
    "name:pol_x_preferred":[
        "So\u015bnie"
    ],
    "name:spa_x_preferred":[
        "So\u015bnie"
    ],
    "name:ukr_x_preferred":[
        "\u041b\u0456\u043f\u0446\u0435-\u0420\u0435\u0438\u043c\u043e\u043d\u0442\u043e\u0432\u0441\u044c\u043a\u0456"
    ],
    "name:ukr_x_variant":[
        "\u0421\u043e\u0441\u044c\u043d\u0435"
    ],
    "name:und_x_variant":[
        "So\u015bnie Na G\u00f3rach"
    ],
    "qs:a0":"Rzeczpospolita Polska",
    "qs:a1":"*Wielkopolskie",
    "qs:a1r":"0",
    "qs:a2":"Ostrowski",
    "qs:adm0":"Rzeczpospolita Polska",
    "qs:la":"So\u015bnie",
    "qs:la_lc":"*PL3017082",
    "qs:level":"locality",
    "qs:loc":"So\u015bnie",
    "qs:loc_alt":"Sosnie",
    "qs:pop":0,
    "qs:type":"rural point-in-poly",
    "wd:wordcount":93,
    "wof:coterminous":[
        1125380011
    ],
    "wof:name":"So\u015bnie",
    "wof:placetype":"locality",
    "wof:population":1300
},
  "geometry": {"coordinates":[17.6024148183535,51.4763326749494],"type":"Point"}
}