{
  "type": "Feature",
  "properties": {
    "gn:admin1_code":"78.0",
    "gn:admin2_code":"1435.0",
    "gn:admin3_code":"143505.0",
    "gn:asciiname":"Rybienko",
    "gn:country_code":"PL",
    "gn:dem":97,
    "gn:feature_class":"P",
    "gn:feature_code":"PPL",
    "gn:name":"Rybienko",
    "gn:population":0,
    "gn:timezone":"Europe/Warsaw",
    "iso:country":"PL",
    "name:pol_x_preferred":[
        "Rybienko"
    ],
    "name:rus_x_preferred":[
        "\u0420\u044b\u0431\u0435\u043d\u043a\u043e"
    ],
    "name:ukr_x_preferred":[
        "\u0420\u0438\u0431\u0435\u043d\u043a\u043e"
    ],
    "wof:name":"Rybienko",
    "wof:placetype":"neighbourhood"
},
  "geometry": {"coordinates":[21.46035,52.57624000000001],"type":"Point"}
}