{
  "type": "Feature",
  "properties": {
    "iso:country":"PL",
    "name:eng_x_preferred":[
        "Wydmy"
    ],
    "name:pol_x_preferred":[
        "Wydmy"
    ],
    "wof:name":"Wydmy",
    "wof:placetype":"neighbourhood"
},
  "geometry": {"coordinates":[16.83286322522611,52.4047046687185],"type":"Point"}
}