{
  "type": "Feature",
  "properties": {
    "gn:admin1_code":"80.0",
    "gn:admin2_code":"1813.0",
    "gn:admin3_code":"181302.0",
    "gn:asciiname":"Huta Drohobycka",
    "gn:country_code":"PL",
    "gn:dem":344,
    "gn:feature_class":"P",
    "gn:feature_code":"PPL",
    "gn:name":"Huta Drohobycka",
    "gn:population":0,
    "gn:timezone":"Europe/Warsaw",
    "iso:country":"PL",
    "wof:name":"Huta Drohobycka",
    "wof:placetype":"locality"
},
  "geometry": {"coordinates":[22.33934,49.87962],"type":"Point"}
}