{
  "type": "Feature",
  "properties": {
    "gn:admin1_code":"81.0",
    "gn:admin2_code":"2003.0",
    "gn:admin3_code":"200303.0",
    "gn:asciiname":"Lubin Koscielny",
    "gn:country_code":"PL",
    "gn:dem":140,
    "gn:feature_class":"P",
    "gn:feature_code":"PPL",
    "gn:name":"\u0141ubin Ko\u015bcielny",
    "gn:population":0,
    "gn:timezone":"Europe/Warsaw",
    "iso:country":"PL",
    "name:azb_x_preferred":[
        "\u0648\u0648\u0628\u06cc\u0646 \u06a9\u0648\u0634\u0686\u06cc\u0644\u0646\u0647"
    ],
    "name:fas_x_preferred":[
        "\u0648\u0648\u0628\u06cc\u0646 \u06a9\u0648\u0634\u0686\u06cc\u0644\u0646\u0647"
    ],
    "name:fra_x_preferred":[
        "\u0141ubin Ko\u015bcielny"
    ],
    "name:lit_x_preferred":[
        "Lubin Ko\u0161celnai"
    ],
    "name:pol_x_preferred":[
        "\u0141ubin Ko\u015bcielny"
    ],
    "name:ukr_x_preferred":[
        "\u041b\u0443\u0431\u0456\u043d-\u041a\u043e\u0441\u044c\u0446\u0435\u043b\u044c\u043d\u0438"
    ],
    "name:und_x_variant":[
        "\u0141ubin"
    ],
    "wof:name":"Lubin Koscielny",
    "wof:placetype":"locality"
},
  "geometry": {"coordinates":[23.00769,52.75997],"type":"Point"}
}