{
  "type": "Feature",
  "properties": {
    "gn:admin1_code":"76.0",
    "gn:admin2_code":"808.0",
    "gn:admin3_code":"80801.0",
    "gn:asciiname":"Nowa Wioska",
    "gn:country_code":"PL",
    "gn:dem":73,
    "gn:feature_class":"P",
    "gn:feature_code":"PPL",
    "gn:name":"Nowa Wioska",
    "gn:population":0,
    "gn:timezone":"Europe/Warsaw",
    "iso:country":"PL",
    "name:ceb_x_preferred":[
        "Nowa Wioska"
    ],
    "name:fra_x_preferred":[
        "Nowa Wioska"
    ],
    "name:pol_x_preferred":[
        "Nowa Wioska"
    ],
    "name:ukr_x_preferred":[
        "\u041d\u043e\u0432\u0430 \u0412\u0439\u043e\u0441\u044c\u043a\u0430"
    ],
    "name:und_x_variant":[
        "Neud\u00f6rfel",
        "Nowa Wroska"
    ],
    "wof:name":"Nowa Wioska",
    "wof:placetype":"locality"
},
  "geometry": {"coordinates":[15.43847,52.29121],"type":"Point"}
}