{
  "type": "Feature",
  "properties": {
    "gn:admin1_code":"84.0",
    "gn:admin2_code":"2604.0",
    "gn:admin3_code":"260412.0",
    "gn:asciiname":"Drochow Gorny",
    "gn:country_code":"PL",
    "gn:dem":278,
    "gn:feature_class":"P",
    "gn:feature_code":"PPL",
    "gn:name":"Droch\u00f3w G\u00f3rny",
    "gn:population":0,
    "gn:timezone":"Europe/Warsaw",
    "iso:country":"PL",
    "name:ceb_x_preferred":[
        "Droch\u00f3w G\u00f3rny"
    ],
    "name:nld_x_preferred":[
        "Droch\u00f3w G\u00f3rny"
    ],
    "name:pol_x_preferred":[
        "Droch\u00f3w G\u00f3rny"
    ],
    "name:ukr_x_preferred":[
        "\u0414\u0440\u043e\u0445\u0443\u0432-\u0490\u0443\u0440\u043d\u0438"
    ],
    "name:und_x_variant":[
        "Droch\u00f3w G\u00f3rny"
    ],
    "wof:name":"Drochow Gorny",
    "wof:placetype":"locality"
},
  "geometry": {"coordinates":[20.57277,50.69249],"type":"Point"}
}