{
  "type": "Feature",
  "properties": {
    "gn:country":"PL",
    "gn:fcode":"PPL",
    "gn:population":378,
    "iso:country":"PL",
    "name:ast_x_preferred":[
        "Domaszczyn"
    ],
    "name:ceb_x_preferred":[
        "Domaszczyn"
    ],
    "name:eng_x_preferred":[
        "Domaszczyn"
    ],
    "name:fra_x_preferred":[
        "Domaszczyn"
    ],
    "name:nan_x_preferred":[
        "Domaszczyn"
    ],
    "name:pol_x_preferred":[
        "Domaszczyn"
    ],
    "name:ukr_x_preferred":[
        "\u0414\u043e\u043c\u0430\u0449\u0438\u043d"
    ],
    "qs_pg:aaroncc":"PL",
    "qs_pg:gn_country":"PL",
    "qs_pg:gn_fcode":"PPL",
    "qs_pg:gn_pop":378,
    "qs_pg:name":"Domaszczyn",
    "qs_pg:name_adm0":"Polska",
    "qs_pg:name_adm1":"Dolnosl\u0105skie",
    "qs_pg:photos_9r":0,
    "qs_pg:photos_sr":0,
    "qs_pg:pop_sr":2,
    "qs_pg:qs_pg_placetype":"locality",
    "qs_pg:qs_pg_placetype_gp":"Town",
    "qs_pg:woe_adm0":23424923,
    "woe:adm0_id":23424923,
    "woe:name_adm0":"Polska",
    "woe:name_adm1":"Dolnosl\u0105skie",
    "woe:placetype":"Town",
    "wof:name":"Domaszczyn",
    "wof:placetype":"neighbourhood",
    "wof:population":378
},
  "geometry": {"coordinates":[17.16579,51.18849],"type":"Point"}
}