{
  "type": "Feature",
  "properties": {
    "gn:admin1_code":"73.0",
    "gn:admin2_code":"404.0",
    "gn:admin3_code":"40403.0",
    "gn:asciiname":"Trzebcz",
    "gn:country_code":"PL",
    "gn:dem":96,
    "gn:feature_class":"P",
    "gn:feature_code":"PPL",
    "gn:name":"Trzebcz",
    "gn:population":0,
    "gn:timezone":"Europe/Warsaw",
    "iso:country":"PL",
    "name:azb_x_preferred":[
        "\u0686\u0628\u06a9\u0633 \u0634\u0644\u0627\u062e\u062a\u0633\u06a9\u06cc"
    ],
    "name:fas_x_preferred":[
        "\u0686\u0628\u06a9\u0633 \u0634\u0644\u0627\u062e\u062a\u0633\u06a9\u06cc"
    ],
    "name:nld_x_preferred":[
        "Trzebcz Szlachecki"
    ],
    "name:pol_x_preferred":[
        "Trzebcz Szlachecki"
    ],
    "name:ukr_x_preferred":[
        "\u0422\u0448\u0435\u0431\u0447-\u0428\u043b\u044f\u0445\u0435\u0446\u044c\u043a\u0438\u0439"
    ],
    "name:und_x_variant":[
        "Trzebcz Szlachecki",
        "Trzebcz"
    ],
    "wof:name":"Trzebcz",
    "wof:placetype":"locality"
},
  "geometry": {"coordinates":[18.47368,53.22174],"type":"Point"}
}