{
  "type": "Feature",
  "properties": {
    "gn:admin1_code":"86.0",
    "gn:admin2_code":"3016.0",
    "gn:admin3_code":"301601.0",
    "gn:asciiname":"Maniewo",
    "gn:country_code":"PL",
    "gn:dem":94,
    "gn:feature_class":"P",
    "gn:feature_code":"PPL",
    "gn:name":"Maniewo",
    "gn:population":0,
    "gn:timezone":"Europe/Warsaw",
    "iso:country":"PL",
    "name:ceb_x_preferred":[
        "Maniewo"
    ],
    "name:fra_x_preferred":[
        "Maniewo"
    ],
    "name:pol_x_preferred":[
        "Maniewo"
    ],
    "name:ukr_x_preferred":[
        "\u041c\u0430\u043d\u0435\u0432\u043e"
    ],
    "wof:name":"Maniewo",
    "wof:placetype":"locality"
},
  "geometry": {"coordinates":[16.86625,52.59418],"type":"Point"}
}