{
  "type": "Feature",
  "properties": {
    "gn:admin1_code":"87.0",
    "gn:admin2_code":"3214.0",
    "gn:admin3_code":"321410.0",
    "gn:asciiname":"Malkocin",
    "gn:country_code":"PL",
    "gn:dem":37,
    "gn:feature_class":"P",
    "gn:feature_code":"PPL",
    "gn:name":"Ma\u0142kocin",
    "gn:population":0,
    "gn:timezone":"Europe/Warsaw",
    "iso:country":"PL",
    "name:ceb_x_preferred":[
        "Ma\u0142kocin"
    ],
    "name:deu_x_preferred":[
        "Ma\u0142kocin"
    ],
    "name:pol_x_preferred":[
        "Ma\u0142kocin"
    ],
    "name:ukr_x_preferred":[
        "\u041c\u0430\u043b\u043a\u043e\u0446\u0438\u043d"
    ],
    "name:vie_x_preferred":[
        "Ma\u0142kocin"
    ],
    "wof:name":"Malkocin",
    "wof:placetype":"locality"
},
  "geometry": {"coordinates":[15.02944,53.40632],"type":"Point"}
}