{
  "type": "Feature",
  "properties": {
    "gn:admin1_code":"76.0",
    "gn:admin2_code":"811.0",
    "gn:admin3_code":"81108.0",
    "gn:asciiname":"Przewozniki",
    "gn:country_code":"PL",
    "gn:dem":138,
    "gn:feature_class":"P",
    "gn:feature_code":"PPL",
    "gn:name":"Przewo\u017aniki",
    "gn:population":0,
    "gn:timezone":"Europe/Warsaw",
    "iso:country":"PL",
    "name:deu_x_preferred":[
        "Przewo\u017aniki"
    ],
    "name:fra_x_preferred":[
        "Przewo\u017aniki"
    ],
    "name:pol_x_preferred":[
        "Przewo\u017aniki"
    ],
    "name:ukr_x_preferred":[
        "\u041f\u0448\u0435\u0432\u043e\u0437\u044c\u043d\u0438\u043a\u0438"
    ],
    "wof:name":"Przewozniki",
    "wof:placetype":"locality"
},
  "geometry": {"coordinates":[14.80245,51.53839],"type":"Point"}
}