{
  "type": "Feature",
  "properties": {
    "gn:admin1_code":"87.0",
    "gn:admin2_code":"3211.0",
    "gn:admin3_code":"321102.0",
    "gn:asciiname":"Osiedle Kresy",
    "gn:country_code":"PL",
    "gn:dem":24,
    "gn:feature_class":"P",
    "gn:feature_code":"PPL",
    "gn:name":"Osiedle Kresy",
    "gn:population":0,
    "gn:timezone":"Europe/Warsaw",
    "iso:country":"PL",
    "wof:name":"Osiedle Kresy",
    "wof:placetype":"locality"
},
  "geometry": {"coordinates":[14.48075,53.38678],"type":"Point"}
}