{
  "type": "Feature",
  "properties": {
    "gn:country":"PL",
    "gn:fcode":"PPLA3",
    "gn:population":400,
    "iso:country":"PL",
    "name:eng_x_preferred":[
        "Gmina Chyn\u00f3w"
    ],
    "name:por_x_preferred":[
        "Comuna de Chyn\u00f3w"
    ],
    "name:rus_x_preferred":[
        "\u0425\u044b\u043d\u0443\u0432"
    ],
    "name:slk_x_preferred":[
        "Gmina Chyn\u00f3w"
    ],
    "name:ukr_x_preferred":[
        "\u0490\u043c\u0456\u043d\u0430 \u0425\u0438\u043d\u0443\u0432"
    ],
    "name:war_x_preferred":[
        "Gmina Chyn\u00f3w"
    ],
    "qs_pg:aaroncc":"PL",
    "qs_pg:gn_country":"PL",
    "qs_pg:gn_fcode":"PPLA3",
    "qs_pg:gn_pop":400,
    "qs_pg:name":"Chyn\u00f3w",
    "qs_pg:name_adm0":"Polska",
    "qs_pg:name_adm1":"Mazowieckie",
    "qs_pg:photos_9k":1,
    "qs_pg:photos_9r":1,
    "qs_pg:photos_all":5,
    "qs_pg:photos_sr":0,
    "qs_pg:pop_sr":2,
    "qs_pg:qs_pg_placetype":"localadmin",
    "qs_pg:qs_pg_placetype_gp":"LocalAdmin",
    "qs_pg:woe_adm0":23424923,
    "woe:adm0_id":23424923,
    "woe:name_adm0":"Polska",
    "woe:name_adm1":"Mazowieckie",
    "woe:placetype":"LocalAdmin",
    "wof:name":"Chyn\u00f3w",
    "wof:placetype":"localadmin",
    "wof:population":400
},
  "geometry": {"coordinates":[21.08208,51.90425],"type":"Point"}
}