{
  "type": "Feature",
  "properties": {
    "gn:admin1_code":"78.0",
    "gn:admin2_code":"1426.0",
    "gn:admin3_code":"142612.0",
    "gn:asciiname":"Lomnica",
    "gn:country_code":"PL",
    "gn:dem":153,
    "gn:feature_class":"P",
    "gn:feature_code":"PPL",
    "gn:name":"\u0141omnica",
    "gn:population":0,
    "gn:timezone":"Europe/Warsaw",
    "iso:country":"PL",
    "name:fas_x_preferred":[
        "\u0644\u0648\u0645\u0646\u06cc\u062a\u0633\u0627"
    ],
    "name:fra_x_preferred":[
        "Lomnica"
    ],
    "name:msa_x_preferred":[
        "Lomnica"
    ],
    "name:por_x_preferred":[
        "Lomnica"
    ],
    "name:slv_x_preferred":[
        "Lomnica"
    ],
    "name:srp_x_preferred":[
        "\u041b\u043e\u043c\u043d\u0438\u0446\u0430"
    ],
    "wof:name":"Lomnica",
    "wof:placetype":"locality"
},
  "geometry": {"coordinates":[21.92595,52.03274],"type":"Point"}
}