{
  "type": "Feature",
  "properties": {
    "gn:admin1_code":"84.0",
    "gn:admin2_code":"2606.0",
    "gn:admin3_code":"260607.0",
    "gn:asciiname":"Tadeuszow",
    "gn:country_code":"PL",
    "gn:dem":191,
    "gn:feature_class":"P",
    "gn:feature_code":"PPL",
    "gn:name":"Tadeusz\u00f3w",
    "gn:population":0,
    "gn:timezone":"Europe/Warsaw",
    "iso:country":"PL",
    "name:und_x_variant":[
        "Tadeusz\u00f3",
        "Tadeusz\u00f3w"
    ],
    "wof:name":"Tadeuszow",
    "wof:placetype":"locality"
},
  "geometry": {"coordinates":[21.76324,50.94981],"type":"Point"}
}