{
  "type": "Feature",
  "properties": {
    "gn:admin1_code":"73.0",
    "gn:admin2_code":"402.0",
    "gn:admin3_code":"40203.0",
    "gn:asciiname":"Cieleta",
    "gn:country_code":"PL",
    "gn:dem":126,
    "gn:feature_class":"P",
    "gn:feature_code":"PPL",
    "gn:name":"Ciel\u0119ta",
    "gn:population":0,
    "gn:timezone":"Europe/Warsaw",
    "iso:country":"PL",
    "name:pol_x_preferred":[
        "Ciel\u0119ta"
    ],
    "name:ukr_x_preferred":[
        "\u0426\u0435\u043b\u0435\u043d\u0442\u0430"
    ],
    "wof:name":"Cieleta",
    "wof:placetype":"locality"
},
  "geometry": {"coordinates":[19.46427000000001,53.24623],"type":"Point"}
}