{
  "type": "Feature",
  "properties": {
    "gn:admin1_code":"83.0",
    "gn:admin2_code":"2408.0",
    "gn:admin3_code":"240802.0",
    "gn:asciiname":"Kotulowiec",
    "gn:country_code":"PL",
    "gn:dem":302,
    "gn:feature_class":"P",
    "gn:feature_code":"PPL",
    "gn:name":"Kotulowiec",
    "gn:population":0,
    "gn:timezone":"Europe/Warsaw",
    "iso:country":"PL",
    "wof:name":"Kotulowiec",
    "wof:placetype":"locality"
},
  "geometry": {"coordinates":[18.88333,50.18333],"type":"Point"}
}