{
  "type": "Feature",
  "properties": {
    "gn:admin1_code":"85.0",
    "gn:admin2_code":"2801.0",
    "gn:admin3_code":"280106.0",
    "gn:asciiname":"Ostre Bardo",
    "gn:cc2":"PL",
    "gn:country_code":"PL",
    "gn:dem":46,
    "gn:feature_class":"P",
    "gn:feature_code":"PPL",
    "gn:name":"Ostre Bardo",
    "gn:population":0,
    "gn:timezone":"Europe/Warsaw",
    "iso:country":"PL",
    "name:und_x_variant":[
        "Klingenberg",
        "Ostre Bardo"
    ],
    "wof:name":"Ostre Bardo",
    "wof:placetype":"locality"
},
  "geometry": {"coordinates":[20.98715,54.34625],"type":"Point"}
}