{
  "type": "Feature",
  "properties": {
    "gn:admin1_code":"85.0",
    "gn:admin2_code":"2801.0",
    "gn:admin3_code":"280106.0",
    "gn:asciiname":"Ostre Bardo",
    "gn:cc2":"PL",
    "gn:country_code":"PL",
    "gn:dem":46,
    "gn:feature_class":"P",
    "gn:feature_code":"PPL",
    "gn:name":"Ostre Bardo",
    "gn:population":0,
    "gn:timezone":"Europe/Warsaw",
    "iso:country":"PL",
    "name:azb_x_preferred":[
        "\u0627\u0648\u0633\u062a\u0631\u0647 \u0628\u0627\u0631\u062f\u0648"
    ],
    "name:deu_x_preferred":[
        "Ostre Bardo"
    ],
    "name:fas_x_preferred":[
        "\u0627\u0648\u0633\u062a\u0631\u0647 \u0628\u0627\u0631\u062f\u0648"
    ],
    "name:fra_x_preferred":[
        "Ostre Bardo"
    ],
    "name:pol_x_preferred":[
        "Ostre Bardo"
    ],
    "name:ukr_x_preferred":[
        "\u041e\u0441\u0442\u0440\u0435-\u0411\u0430\u0440\u0434\u043e"
    ],
    "name:und_x_variant":[
        "Klingenberg"
    ],
    "wof:name":"Ostre Bardo",
    "wof:placetype":"locality"
},
  "geometry": {"coordinates":[20.98715,54.34625],"type":"Point"}
}