{
  "type": "Feature",
  "properties": {
    "iso:country":"PL",
    "name:eng_x_preferred":[
        "Morz\u0119cin Ma\u0142y"
    ],
    "name:fra_x_preferred":[
        "Morz\u0119cin Ma\u0142y"
    ],
    "name:pol_x_preferred":[
        "Morz\u0119cin Ma\u0142y"
    ],
    "qs_pg:aaroncc":"PL",
    "qs_pg:name":"Morz\u0119cin Ma\u0142y",
    "qs_pg:name_adm0":"Polska",
    "qs_pg:name_adm1":"Dolnosl\u0105skie",
    "qs_pg:photos":48,
    "qs_pg:photos_1k":10,
    "qs_pg:photos_9k":1,
    "qs_pg:photos_9r":2,
    "qs_pg:photos_all":48,
    "qs_pg:photos_sr":2,
    "qs_pg:pop_sr":0,
    "qs_pg:qs_pg_placetype":"locality",
    "qs_pg:qs_pg_placetype_gp":"Town",
    "qs_pg:woe_adm0":23424923,
    "woe:adm0_id":23424923,
    "woe:name_adm0":"Polska",
    "woe:name_adm1":"Dolnosl\u0105skie",
    "woe:placetype":"Town",
    "wof:name":"Morz\u0119cin Ma\u0142y",
    "wof:placetype":"locality"
},
  "geometry": {"coordinates":[16.870279,51.349002],"type":"Point"}
}