{
  "type": "Feature",
  "properties": {
    "gn:admin1_code":"78.0",
    "gn:admin2_code":"1402.0",
    "gn:admin3_code":"140202.0",
    "gn:asciiname":"Kanigowek",
    "gn:country_code":"PL",
    "gn:dem":111,
    "gn:feature_class":"P",
    "gn:feature_code":"PPL",
    "gn:name":"Kanig\u00f3wek",
    "gn:population":0,
    "gn:timezone":"Europe/Warsaw",
    "iso:country":"PL",
    "name:und_x_variant":[
        "Kanig\u00f3wek"
    ],
    "wof:name":"Kanigowek",
    "wof:placetype":"locality"
},
  "geometry": {"coordinates":[20.47444,52.8423],"type":"Point"}
}