{
  "type": "Feature",
  "properties": {
    "gn:admin1_code":"78.0",
    "gn:admin2_code":"1402.0",
    "gn:admin3_code":"140202.0",
    "gn:asciiname":"Kanigowek",
    "gn:country_code":"PL",
    "gn:dem":111,
    "gn:feature_class":"P",
    "gn:feature_code":"PPL",
    "gn:name":"Kanig\u00f3wek",
    "gn:population":0,
    "gn:timezone":"Europe/Warsaw",
    "iso:country":"PL",
    "name:azb_x_preferred":[
        "\u06a9\u0627\u0646\u0642\u0642\u0648\u0648\u06a9"
    ],
    "name:fas_x_preferred":[
        "\u06a9\u0627\u0646\u06af\u06af\u0648\u0648\u06a9"
    ],
    "name:fra_x_preferred":[
        "Kanig\u00f3wek"
    ],
    "name:pol_x_preferred":[
        "Kanig\u00f3wek"
    ],
    "name:spa_x_preferred":[
        "Kanig\u00f3wek"
    ],
    "name:ukr_x_preferred":[
        "\u041a\u0430\u043d\u0456\u0491\u0443\u0432\u0435\u043a"
    ],
    "wof:name":"Kanigowek",
    "wof:placetype":"locality"
},
  "geometry": {"coordinates":[20.47444,52.8423],"type":"Point"}
}