{
  "type": "Feature",
  "properties": {
    "gn:admin1_code":"75.0",
    "gn:admin2_code":"620.0",
    "gn:admin3_code":"62002.0",
    "gn:asciiname":"Szystowice",
    "gn:country_code":"PL",
    "gn:dem":222,
    "gn:feature_class":"P",
    "gn:feature_code":"PPL",
    "gn:name":"Szystowice",
    "gn:population":0,
    "gn:timezone":"Europe/Warsaw",
    "iso:country":"PL",
    "name:fra_x_preferred":[
        "Szystowice"
    ],
    "name:pol_x_preferred":[
        "Szystowice"
    ],
    "name:ukr_x_preferred":[
        "\u0428\u0438\u0441\u0442\u043e\u0432\u0456\u0446\u0435"
    ],
    "name:und_x_variant":[
        "Szys\u0142owice"
    ],
    "wof:name":"Szystowice",
    "wof:placetype":"locality"
},
  "geometry": {"coordinates":[23.60532000000001,50.83079],"type":"Point"}
}