{
  "type": "Feature",
  "properties": {
    "gn:admin1_code":"76",
    "gn:admin2_code":"0808",
    "gn:admin3_code":"80801.0",
    "gn:asciiname":"Zagaje",
    "gn:country_code":"PL",
    "gn:dem":100,
    "gn:feature_class":"P",
    "gn:feature_code":"PPL",
    "gn:name":"Zagaje",
    "gn:population":0,
    "gn:timezone":"Europe/Warsaw",
    "iso:country":"PL",
    "name:deu_x_historical":[
        "Grunwald"
    ],
    "name:deu_x_preferred":[
        "Grunwald"
    ],
    "name:fra_x_preferred":[
        "Zagaje"
    ],
    "name:pol_x_preferred":[
        "Zagaje"
    ],
    "name:ukr_x_preferred":[
        "\u0417\u0430\u0491\u0430\u0454"
    ],
    "name:urd_x_preferred":[
        "\u0632\u06af\u0627\u062c\u06d2"
    ],
    "wof:name":"Zagaje",
    "wof:placetype":"locality"
},
  "geometry": {"coordinates":[15.40084,52.32683],"type":"Point"}
}