{
  "type": "Feature",
  "properties": {
    "iso:country":"PL",
    "name:bul_x_preferred":[
        "\u041f\u0448\u0447\u0438\u043d\u0430"
    ],
    "name:ceb_x_preferred":[
        "Pszczyna"
    ],
    "name:ces_x_preferred":[
        "Pszczyna"
    ],
    "name:deu_x_preferred":[
        "Pszczyna"
    ],
    "name:epo_x_preferred":[
        "Pszczyna"
    ],
    "name:fas_x_preferred":[
        "\u067e\u0634\u0686\u0646\u0627"
    ],
    "name:fra_x_preferred":[
        "Pszczyna"
    ],
    "name:hrv_x_preferred":[
        "Pszczyna"
    ],
    "name:ita_x_preferred":[
        "Pszczyna"
    ],
    "name:jav_x_preferred":[
        "Pszczyna"
    ],
    "name:lav_x_preferred":[
        "P\u0161\u010dina"
    ],
    "name:lit_x_preferred":[
        "P\u0161\u010dyna"
    ],
    "name:msa_x_preferred":[
        "Pszczyna"
    ],
    "name:nld_x_preferred":[
        "Pszczyna"
    ],
    "name:pol_x_preferred":[
        "Pszczyna"
    ],
    "name:por_x_preferred":[
        "Pszczyna"
    ],
    "name:ron_x_preferred":[
        "Pszczyna"
    ],
    "name:rus_x_preferred":[
        "\u041f\u0449\u0438\u043d\u0430"
    ],
    "name:slk_x_preferred":[
        "Pszczyna"
    ],
    "name:sot_x_preferred":[
        "Pszczyna"
    ],
    "name:srp_x_preferred":[
        "\u041f\u0448\u0447\u0438\u043d\u0430"
    ],
    "name:szl_x_preferred":[
        "Pszczyna"
    ],
    "name:ukr_x_preferred":[
        "\u041f\u0449\u0438\u043d\u0430"
    ],
    "name:vie_x_preferred":[
        "Pszczyna"
    ],
    "name:war_x_preferred":[
        "Pszczyna"
    ],
    "name:zho_x_preferred":[
        "\u666e\u4ec0\u5947\u7d0d"
    ],
    "qs_pg:aaroncc":"PL",
    "qs_pg:name":"Pszczyna",
    "qs_pg:name_adm0":"Polska",
    "qs_pg:name_adm1":"Sl\u0105skie",
    "qs_pg:photos":184,
    "qs_pg:photos_1k":37,
    "qs_pg:photos_9k":1,
    "qs_pg:photos_9r":4,
    "qs_pg:photos_all":184,
    "qs_pg:photos_sr":4,
    "qs_pg:pop_sr":0,
    "qs_pg:qs_pg_placetype":"localadmin",
    "qs_pg:qs_pg_placetype_gp":"LocalAdmin",
    "qs_pg:woe_adm0":23424923,
    "woe:adm0_id":23424923,
    "woe:name_adm0":"Polska",
    "woe:name_adm1":"Sl\u0105skie",
    "woe:placetype":"LocalAdmin",
    "wof:name":"Pszczyna",
    "wof:placetype":"localadmin"
},
  "geometry": {"coordinates":[18.940987,49.982578],"type":"Point"}
}