{
  "type": "Feature",
  "properties": {
    "gn:admin1_code":"84.0",
    "gn:admin2_code":"2609.0",
    "gn:admin3_code":"260905.0",
    "gn:asciiname":"Skrzypaczowice",
    "gn:country_code":"PL",
    "gn:dem":159,
    "gn:feature_class":"P",
    "gn:feature_code":"PPL",
    "gn:name":"Skrzypaczowice",
    "gn:population":0,
    "gn:timezone":"Europe/Warsaw",
    "iso:country":"PL",
    "name:pol_x_preferred":[
        "Skrzypaczowice"
    ],
    "name:ukr_x_preferred":[
        "\u0421\u043a\u0448\u0438\u043f\u0430\u0447\u043e\u0432\u0456\u0446\u0435"
    ],
    "wof:name":"Skrzypaczowice",
    "wof:placetype":"locality"
},
  "geometry": {"coordinates":[21.55638,50.57146],"type":"Point"}
}