{
  "type": "Feature",
  "properties": {
    "gn:admin1_code":"81.0",
    "gn:admin2_code":"2004.0",
    "gn:admin3_code":"200405.0",
    "gn:asciiname":"Chojnowo",
    "gn:country_code":"PL",
    "gn:dem":149,
    "gn:feature_class":"P",
    "gn:feature_code":"PPL",
    "gn:name":"Chojnowo",
    "gn:population":0,
    "gn:timezone":"Europe/Warsaw",
    "iso:country":"PL",
    "name:fra_x_preferred":[
        "Chojnowo"
    ],
    "name:lit_x_preferred":[
        "Chojnovas"
    ],
    "name:pol_x_preferred":[
        "Chojnowo"
    ],
    "name:ukr_x_preferred":[
        "\u0425\u043e\u0439\u043d\u043e\u0432\u043e"
    ],
    "wof:name":"Chojnowo",
    "wof:placetype":"locality"
},
  "geometry": {"coordinates":[22.2353,53.56876],"type":"Point"}
}