{
  "type": "Feature",
  "properties": {
    "gn:admin1_code":"82.0",
    "gn:admin2_code":"2211.0",
    "gn:admin3_code":"221107.0",
    "gn:asciiname":"Zdrada",
    "gn:country_code":"PL",
    "gn:dem":18,
    "gn:feature_class":"P",
    "gn:feature_code":"PPL",
    "gn:name":"Zdrada",
    "gn:population":0,
    "gn:timezone":"Europe/Warsaw",
    "iso:country":"PL",
    "name:ceb_x_preferred":[
        "Zdrada"
    ],
    "name:csb_x_preferred":[
        "Zdrada"
    ],
    "name:pol_x_preferred":[
        "Zdrada"
    ],
    "name:ukr_x_preferred":[
        "\u0417\u0434\u0440\u0430\u0434\u0430"
    ],
    "wof:name":"Zdrada",
    "wof:placetype":"locality"
},
  "geometry": {"coordinates":[18.31624,54.72012],"type":"Point"}
}