{
  "type": "Feature",
  "properties": {
    "gn:admin1_code":"83.0",
    "gn:admin2_code":"2479.0",
    "gn:admin3_code":"247901.0",
    "gn:asciiname":"Kleszczowka",
    "gn:country_code":"PL",
    "gn:dem":254,
    "gn:feature_class":"P",
    "gn:feature_code":"PPL",
    "gn:name":"Kleszcz\u00f3wka",
    "gn:population":0,
    "gn:timezone":"Europe/Warsaw",
    "iso:country":"PL",
    "wof:name":"Kleszczowka",
    "wof:placetype":"locality"
},
  "geometry": {"coordinates":[18.7123,50.05278],"type":"Point"}
}