{
  "type": "Feature",
  "properties": {
    "gn:admin1_code":"78.0",
    "gn:admin2_code":"1437.0",
    "gn:admin3_code":"143703.0",
    "gn:asciiname":"Straszewy",
    "gn:cc2":"PL",
    "gn:country_code":"PL",
    "gn:dem":154,
    "gn:feature_class":"P",
    "gn:feature_code":"PPL",
    "gn:name":"Straszewy",
    "gn:population":0,
    "gn:timezone":"Europe/Warsaw",
    "iso:country":"PL",
    "name:und_x_variant":[
        "Straszewo",
        "Straszewy"
    ],
    "wof:name":"Straszewy",
    "wof:placetype":"locality"
},
  "geometry": {"coordinates":[19.93504,53.15243],"type":"Point"}
}