{
  "type": "Feature",
  "properties": {
    "gn:admin1_code":"78.0",
    "gn:admin2_code":"1437.0",
    "gn:admin3_code":"143703.0",
    "gn:asciiname":"Straszewy",
    "gn:cc2":"PL",
    "gn:country_code":"PL",
    "gn:dem":154,
    "gn:feature_class":"P",
    "gn:feature_code":"PPL",
    "gn:name":"Straszewy",
    "gn:population":0,
    "gn:timezone":"Europe/Warsaw",
    "iso:country":"PL",
    "name:azb_x_preferred":[
        "\u0633\u062a\u0631\u0627\u0634\u0648\u0647"
    ],
    "name:fas_x_preferred":[
        "\u0633\u062a\u0631\u0627\u0634\u0648\u0647"
    ],
    "name:fra_x_preferred":[
        "Straszewy"
    ],
    "name:pol_x_preferred":[
        "Straszewy"
    ],
    "name:ukr_x_preferred":[
        "\u0421\u0442\u0440\u0430\u0448\u0435\u0432\u0438"
    ],
    "name:und_x_variant":[
        "Straszewo"
    ],
    "wof:name":"Straszewy",
    "wof:placetype":"locality"
},
  "geometry": {"coordinates":[19.93504,53.15243],"type":"Point"}
}