{
  "type": "Feature",
  "properties": {
    "gn:admin1_code":"83.0",
    "gn:admin2_code":"2417.0",
    "gn:admin3_code":"241711.0",
    "gn:asciiname":"Kolonia",
    "gn:cc2":"PL",
    "gn:country_code":"PL",
    "gn:dem":996,
    "gn:feature_class":"P",
    "gn:feature_code":"PPL",
    "gn:name":"Kolonia",
    "gn:population":0,
    "gn:timezone":"Europe/Warsaw",
    "iso:country":"PL",
    "name:und_x_variant":[
        "Kolonja",
        "Kolonia"
    ],
    "wof:name":"Kolonia",
    "wof:placetype":"locality"
},
  "geometry": {"coordinates":[19.03333,49.43333],"type":"Point"}
}