{
  "type": "Feature",
  "properties": {
    "gn:admin1_code":"75.0",
    "gn:admin2_code":"603.0",
    "gn:admin3_code":"60310.0",
    "gn:asciiname":"Czulczyce",
    "gn:country_code":"PL",
    "gn:dem":179,
    "gn:feature_class":"P",
    "gn:feature_code":"PPL",
    "gn:name":"Czu\u0142czyce",
    "gn:population":0,
    "gn:timezone":"Europe/Warsaw",
    "iso:country":"PL",
    "name:azb_x_preferred":[
        "\u0686\u0648\u0648\u0686\u062a\u0633\u0647"
    ],
    "name:fas_x_preferred":[
        "\u0686\u0648\u0648\u0686\u062a\u0633\u0647"
    ],
    "name:fra_x_preferred":[
        "Czu\u0142czyce"
    ],
    "name:pol_x_preferred":[
        "Czu\u0142czyce"
    ],
    "name:ukr_x_preferred":[
        "\u0427\u0443\u043b\u044c\u0447\u0438\u0446\u0456"
    ],
    "wof:name":"Czulczyce",
    "wof:placetype":"locality"
},
  "geometry": {"coordinates":[23.45289,51.22387],"type":"Point"}
}