{
  "type": "Feature",
  "properties": {
    "gn:country":"PL",
    "gn:fcode":"PPLA3",
    "gn:population":732,
    "iso:country":"PL",
    "name:bel_x_preferred":[
        "\u0411\u043e\u0440\u043a\u0456"
    ],
    "name:bos_x_preferred":[
        "Borki"
    ],
    "name:ceb_x_preferred":[
        "Borki"
    ],
    "name:crh_x_preferred":[
        "Birk\u0131"
    ],
    "name:deu_x_preferred":[
        "Borki"
    ],
    "name:fra_x_preferred":[
        "Borki"
    ],
    "name:hye_x_preferred":[
        "\u0532\u0578\u0580\u056f\u056b"
    ],
    "name:lit_x_preferred":[
        "Borkai"
    ],
    "name:nld_x_preferred":[
        "Borki"
    ],
    "name:pol_x_preferred":[
        "Borki"
    ],
    "name:rus_x_preferred":[
        "\u0411\u043e\u0440\u043a\u0438"
    ],
    "name:ukr_x_preferred":[
        "\u0411\u043e\u0440\u043a\u0438"
    ],
    "qs_pg:aaroncc":"PL",
    "qs_pg:gn_country":"PL",
    "qs_pg:gn_fcode":"PPLA3",
    "qs_pg:gn_pop":732,
    "qs_pg:name":"Borki",
    "qs_pg:name_adm0":"Polska",
    "qs_pg:name_adm1":"Lubelskie",
    "qs_pg:photos_9k":1,
    "qs_pg:photos_9r":1,
    "qs_pg:photos_all":8,
    "qs_pg:photos_sr":0,
    "qs_pg:pop_sr":2,
    "qs_pg:qs_pg_placetype":"localadmin",
    "qs_pg:qs_pg_placetype_gp":"LocalAdmin",
    "qs_pg:woe_adm0":23424923,
    "woe:adm0_id":23424923,
    "woe:name_adm0":"Polska",
    "woe:name_adm1":"Lubelskie",
    "woe:placetype":"LocalAdmin",
    "wof:name":"Borki",
    "wof:placetype":"localadmin",
    "wof:population":732
},
  "geometry": {"coordinates":[22.52129,51.72161],"type":"Point"}
}