{
  "type": "Feature",
  "properties": {
    "gn:admin1_code":"75.0",
    "gn:admin2_code":"605.0",
    "gn:admin3_code":"60505.0",
    "gn:asciiname":"Pikule",
    "gn:country_code":"PL",
    "gn:dem":192,
    "gn:feature_class":"P",
    "gn:feature_code":"PPL",
    "gn:name":"Pikule",
    "gn:population":0,
    "gn:timezone":"Europe/Warsaw",
    "iso:country":"PL",
    "name:fra_x_preferred":[
        "Pikule"
    ],
    "name:pol_x_preferred":[
        "Pikule"
    ],
    "name:ukr_x_preferred":[
        "\u041f\u0456\u043a\u0443\u043b\u0435"
    ],
    "wof:name":"Pikule",
    "wof:placetype":"locality"
},
  "geometry": {"coordinates":[22.33171,50.67762000000001],"type":"Point"}
}