{
  "type": "Feature",
  "properties": {
    "gn:admin1_code":"81.0",
    "gn:admin2_code":"2012.0",
    "gn:admin3_code":"201204.0",
    "gn:asciiname":"Bucki",
    "gn:country_code":"PL",
    "gn:dem":229,
    "gn:feature_class":"P",
    "gn:feature_code":"PPL",
    "gn:name":"Bucki",
    "gn:population":0,
    "gn:timezone":"Europe/Warsaw",
    "iso:country":"PL",
    "name:lit_x_preferred":[
        "Bu\u010dkai"
    ],
    "name:pol_x_preferred":[
        "Bu\u0107ki"
    ],
    "name:szl_x_preferred":[
        "Bu\u0107ki"
    ],
    "name:ukr_x_preferred":[
        "\u0411\u0443\u0446\u044c\u043a\u0456"
    ],
    "wof:name":"Bucki",
    "wof:placetype":"locality"
},
  "geometry": {"coordinates":[22.75869,54.26783],"type":"Point"}
}