{
  "type": "Feature",
  "properties": {
    "gn:admin1_code":"76.0",
    "gn:admin2_code":"862.0",
    "gn:admin3_code":"86201.0",
    "gn:asciiname":"Chynow",
    "gn:country_code":"PL",
    "gn:dem":92,
    "gn:feature_class":"P",
    "gn:feature_code":"PPL",
    "gn:name":"Chyn\u00f3w",
    "gn:population":0,
    "gn:timezone":"Europe/Warsaw",
    "iso:country":"PL",
    "wof:name":"Chynow",
    "wof:placetype":"locality"
},
  "geometry": {"coordinates":[15.53243,51.96679],"type":"Point"}
}