{
  "type": "Feature",
  "properties": {
    "iso:country":"PL",
    "name:ceb_x_preferred":[
        "Wielka Wie\u015b"
    ],
    "name:deu_x_preferred":[
        "Wielka Wie\u015b"
    ],
    "name:fra_x_preferred":[
        "Wielka Wie\u015b"
    ],
    "name:nld_x_preferred":[
        "Wielka Wie\u015b"
    ],
    "name:pol_x_preferred":[
        "Wielka Wie\u015b"
    ],
    "name:rus_x_preferred":[
        "\u0412\u0435\u043b\u044c\u043a\u0430-\u0412\u0435\u0441\u044c"
    ],
    "name:ukr_x_preferred":[
        "\u0412\u0435\u043b\u0438\u043a\u0430 \u0412\u0435\u0441\u044c"
    ],
    "qs_pg:aaroncc":"PL",
    "qs_pg:name":"Wielka Wie\u015b",
    "qs_pg:name_adm0":"Polska",
    "qs_pg:name_adm1":"Ma\u0142opolskie",
    "qs_pg:photos":2,
    "qs_pg:photos_1k":1,
    "qs_pg:photos_9k":1,
    "qs_pg:photos_9r":5,
    "qs_pg:photos_all":320,
    "qs_pg:photos_sr":1,
    "qs_pg:pop_sr":0,
    "qs_pg:qs_pg_placetype":"localadmin",
    "qs_pg:qs_pg_placetype_gp":"LocalAdmin",
    "qs_pg:woe_adm0":23424923,
    "woe:adm0_id":23424923,
    "woe:name_adm0":"Polska",
    "woe:name_adm1":"Ma\u0142opolskie",
    "woe:placetype":"LocalAdmin",
    "wof:name":"Wielka Wie\u015b",
    "wof:placetype":"localadmin"
},
  "geometry": {"coordinates":[19.82706,50.192945],"type":"Point"}
}