{
  "type": "Feature",
  "properties": {
    "gn:admin1_code":"84.0",
    "gn:admin2_code":"2603.0",
    "gn:admin3_code":"260303.0",
    "gn:asciiname":"Chruszczyna",
    "gn:country_code":"PL",
    "gn:dem":255,
    "gn:feature_class":"P",
    "gn:feature_code":"PPL",
    "gn:name":"Chruszczyna",
    "gn:population":0,
    "gn:timezone":"Europe/Warsaw",
    "iso:country":"PL",
    "wof:name":"Chruszczyna",
    "wof:placetype":"locality"
},
  "geometry": {"coordinates":[20.4675,50.2354],"type":"Point"}
}