{
  "type": "Feature",
  "properties": {
    "iso:country":"PL",
    "name:ara_x_preferred":[
        "\u0648\u064a\u0633\u062a\u0631\u0628\u0644\u0627\u062a"
    ],
    "name:bul_x_preferred":[
        "\u0412\u0435\u0441\u0442\u0435\u0440\u043f\u043b\u0430\u0442\u0435"
    ],
    "name:ceb_x_preferred":[
        "Westerplatte"
    ],
    "name:ces_x_preferred":[
        "Westerplatte"
    ],
    "name:deu_x_preferred":[
        "Westerplatte"
    ],
    "name:eng_x_preferred":[
        "Westerplatte"
    ],
    "name:est_x_preferred":[
        "Westerplatte poolsaar"
    ],
    "name:fin_x_preferred":[
        "Westerplatte"
    ],
    "name:fra_x_preferred":[
        "Westerplatte"
    ],
    "name:ita_x_preferred":[
        "Westerplatte"
    ],
    "name:jpn_x_preferred":[
        "\u30f4\u30a7\u30b9\u30c6\u30eb\u30d7\u30e9\u30c3\u30c6"
    ],
    "name:kor_x_preferred":[
        "\ubca0\uc2a4\ud14c\ub974\ud50c\ub77c\ud14c"
    ],
    "name:lit_x_preferred":[
        "Vesterplat\u0117"
    ],
    "name:nld_x_preferred":[
        "Westerplatte"
    ],
    "name:nno_x_preferred":[
        "Westerplatte"
    ],
    "name:nor_x_preferred":[
        "Westerplatte"
    ],
    "name:pol_x_preferred":[
        "Westerplatte"
    ],
    "name:ron_x_preferred":[
        "Westerplatte"
    ],
    "name:spa_x_preferred":[
        "Westerplatte"
    ],
    "name:swe_x_preferred":[
        "Westerplatte"
    ],
    "name:tur_x_preferred":[
        "Westerplatte"
    ],
    "name:ukr_x_preferred":[
        "\u0412\u0435\u0441\u0442\u0435\u0440\u043f\u043b\u0430\u0442\u0442\u0435"
    ],
    "name:zho_x_preferred":[
        "\u897f\u76e4\u534a\u5cf6"
    ],
    "wof:name":"Westerplatte",
    "wof:placetype":"neighbourhood"
},
  "geometry": {"coordinates":[18.67951720024842,54.40552502839154],"type":"Point"}
}