{
  "type": "Feature",
  "properties": {
    "iso:country":"PL",
    "name:eng_x_preferred":[
        "Westerplatte"
    ],
    "name:pol_x_preferred":[
        "Westerplatte"
    ],
    "wof:name":"Westerplatte",
    "wof:placetype":"neighbourhood"
},
  "geometry": {"coordinates":[18.67951720024842,54.40552502839154],"type":"Point"}
}