{
  "type": "Feature",
  "properties": {
    "gn:admin1_code":"86.0",
    "gn:admin2_code":"3008.0",
    "gn:admin3_code":"300802.0",
    "gn:asciiname":"Weronikopole",
    "gn:country_code":"PL",
    "gn:dem":189,
    "gn:feature_class":"P",
    "gn:feature_code":"PPL",
    "gn:name":"Weronikopole",
    "gn:population":0,
    "gn:timezone":"Europe/Warsaw",
    "iso:country":"PL",
    "name:pol_x_preferred":[
        "Weronikopole"
    ],
    "name:ukr_x_preferred":[
        "\u0412\u0435\u0440\u043e\u043d\u0456\u043a\u043e\u043f\u043e\u043b\u0435"
    ],
    "name:und_x_variant":[
        "Weronikopol",
        "Weronikopole"
    ],
    "wof:name":"Weronikopole",
    "wof:placetype":"locality"
},
  "geometry": {"coordinates":[17.88312,51.32712],"type":"Point"}
}