{
  "type": "Feature",
  "properties": {
    "gn:admin1_code":"73.0",
    "gn:admin2_code":"414.0",
    "gn:admin3_code":"41401.0",
    "gn:asciiname":"Krupocin",
    "gn:country_code":"PL",
    "gn:dem":101,
    "gn:feature_class":"P",
    "gn:feature_code":"PPL",
    "gn:name":"Krupocin",
    "gn:population":0,
    "gn:timezone":"Europe/Warsaw",
    "iso:country":"PL",
    "name:pol_x_preferred":[
        "Krupocin"
    ],
    "name:ukr_x_preferred":[
        "\u041a\u0440\u0443\u043f\u043e\u0446\u0438\u043d"
    ],
    "wof:name":"Krupocin",
    "wof:placetype":"locality"
},
  "geometry": {"coordinates":[18.19929,53.45222],"type":"Point"}
}