{
  "type": "Feature",
  "properties": {
    "gn:admin1_code":"81.0",
    "gn:admin2_code":"2003.0",
    "gn:admin3_code":"200306.0",
    "gn:asciiname":"Koszki",
    "gn:country_code":"PL",
    "gn:dem":150,
    "gn:feature_class":"P",
    "gn:feature_code":"PPL",
    "gn:name":"Koszki",
    "gn:population":0,
    "gn:timezone":"Europe/Warsaw",
    "iso:country":"PL",
    "name:lit_x_preferred":[
        "Ko\u0161kai"
    ],
    "name:pol_x_preferred":[
        "Koszki"
    ],
    "name:ukr_x_preferred":[
        "\u041a\u043e\u0448\u043a\u0456"
    ],
    "wof:name":"Koszki",
    "wof:placetype":"locality"
},
  "geometry": {"coordinates":[23.22605,52.68346999999999],"type":"Point"}
}