{
  "type": "Feature",
  "properties": {
    "gn:admin1_code":"82.0",
    "gn:admin2_code":"2216.0",
    "gn:admin3_code":"221605.0",
    "gn:asciiname":"Pieklo",
    "gn:country_code":"PL",
    "gn:dem":15,
    "gn:feature_class":"P",
    "gn:feature_code":"PPL",
    "gn:name":"Piek\u0142o",
    "gn:population":0,
    "gn:timezone":"Europe/Warsaw",
    "iso:country":"PL",
    "name:ceb_x_preferred":[
        "Piek\u0142o"
    ],
    "name:pol_x_preferred":[
        "Piek\u0142o"
    ],
    "name:ukr_x_preferred":[
        "\u041f\u0435\u043a\u043b\u043e"
    ],
    "name:und_x_variant":[
        "Pieckel",
        "Piek\u0142o"
    ],
    "wof:name":"Pieklo",
    "wof:placetype":"locality"
},
  "geometry": {"coordinates":[18.8667,53.93202],"type":"Point"}
}