{
  "type": "Feature",
  "properties": {
    "gn:admin1_code":"78.0",
    "gn:admin2_code":"1424.0",
    "gn:admin3_code":"142404.0",
    "gn:asciiname":"Szygowek",
    "gn:country_code":"PL",
    "gn:dem":80,
    "gn:feature_class":"P",
    "gn:feature_code":"PPL",
    "gn:name":"Szyg\u00f3wek",
    "gn:population":0,
    "gn:timezone":"Europe/Warsaw",
    "iso:country":"PL",
    "name:fra_x_preferred":[
        "Szyg\u00f3wek"
    ],
    "name:pol_x_preferred":[
        "Szyg\u00f3wek"
    ],
    "name:ukr_x_preferred":[
        "\u0428\u0438\u0491\u0443\u0432\u0435\u043a"
    ],
    "wof:name":"Szygowek",
    "wof:placetype":"locality"
},
  "geometry": {"coordinates":[21.1334,52.76369],"type":"Point"}
}