{
  "type": "Feature",
  "properties": {
    "gn:admin1_code":"74.0",
    "gn:admin2_code":"1002.0",
    "gn:admin3_code":"100205.0",
    "gn:asciiname":"Kaszewy Tarnowskie",
    "gn:country_code":"PL",
    "gn:dem":108,
    "gn:feature_class":"P",
    "gn:feature_code":"PPL",
    "gn:name":"Kaszewy Tarnowskie",
    "gn:population":0,
    "gn:timezone":"Europe/Warsaw",
    "iso:country":"PL",
    "name:fra_x_preferred":[
        "Kaszewy Tarnowskie"
    ],
    "name:pol_x_preferred":[
        "Kaszewy Tarnowskie"
    ],
    "name:ukr_x_preferred":[
        "\u041a\u0430\u0448\u0435\u0432\u0438-\u0422\u0430\u0440\u043d\u043e\u0432\u0441\u044c\u043a\u0456"
    ],
    "wof:name":"Kaszewy Tarnowskie",
    "wof:placetype":"locality"
},
  "geometry": {"coordinates":[19.49095,52.21308],"type":"Point"}
}