{
  "type": "Feature",
  "properties": {
    "gn:admin1_code":"72.0",
    "gn:admin2_code":"217.0",
    "gn:admin3_code":"21703.0",
    "gn:asciiname":"Krzywina",
    "gn:country_code":"PL",
    "gn:dem":185,
    "gn:feature_class":"P",
    "gn:feature_code":"PPL",
    "gn:name":"Krzywina",
    "gn:population":0,
    "gn:timezone":"Europe/Warsaw",
    "iso:country":"PL",
    "name:pol_x_preferred":[
        "Krzywina"
    ],
    "name:ukr_x_preferred":[
        "\u041a\u0448\u0438\u0432\u0456\u043d\u0430"
    ],
    "wof:name":"Krzywina",
    "wof:placetype":"locality"
},
  "geometry": {"coordinates":[17.1567,50.71255],"type":"Point"}
}