{
  "type": "Feature",
  "properties": {
    "gn:admin1_code":"74.0",
    "gn:admin2_code":"1013.0",
    "gn:admin3_code":"101306.0",
    "gn:asciiname":"Trebaczew",
    "gn:country_code":"PL",
    "gn:dem":165,
    "gn:feature_class":"P",
    "gn:feature_code":"PPL",
    "gn:name":"Tr\u0119baczew",
    "gn:population":0,
    "gn:timezone":"Europe/Warsaw",
    "iso:country":"PL",
    "name:azb_x_preferred":[
        "\u062a\u0631\u0645\u0628\u0627\u0686\u0641"
    ],
    "name:ceb_x_preferred":[
        "Tr\u0119baczew"
    ],
    "name:fas_x_preferred":[
        "\u062a\u0631\u0645\u0628\u0627\u0686\u0641"
    ],
    "name:pol_x_preferred":[
        "Tr\u0119baczew"
    ],
    "name:ukr_x_preferred":[
        "\u0422\u0440\u0435\u043c\u0431\u0430\u0447\u0435\u0432"
    ],
    "name:und_x_variant":[
        "Tr\u0119baczew"
    ],
    "wof:name":"Trebaczew",
    "wof:placetype":"locality"
},
  "geometry": {"coordinates":[20.58697,51.70505],"type":"Point"}
}