{
  "type": "Feature",
  "properties": {
    "gn:admin1_code":"80.0",
    "gn:admin2_code":"1814.0",
    "gn:admin3_code":"181405.0",
    "gn:asciiname":"Lopuszka Mala",
    "gn:country_code":"PL",
    "gn:dem":208,
    "gn:feature_class":"P",
    "gn:feature_code":"PPL",
    "gn:name":"\u0141opuszka Ma\u0142a",
    "gn:population":0,
    "gn:timezone":"Europe/Warsaw",
    "iso:country":"PL",
    "name:und_x_variant":[
        "\u0141opuszka Ma\u0142a"
    ],
    "wof:name":"Lopuszka Mala",
    "wof:placetype":"locality"
},
  "geometry": {"coordinates":[22.4163,49.96762],"type":"Point"}
}