{
  "type": "Feature",
  "properties": {
    "gn:admin1_code":"80.0",
    "gn:admin2_code":"1814.0",
    "gn:admin3_code":"181405.0",
    "gn:asciiname":"Lopuszka Mala",
    "gn:country_code":"PL",
    "gn:dem":208,
    "gn:feature_class":"P",
    "gn:feature_code":"PPL",
    "gn:name":"\u0141opuszka Ma\u0142a",
    "gn:population":0,
    "gn:timezone":"Europe/Warsaw",
    "iso:country":"PL",
    "name:pol_x_preferred":[
        "\u0141opuszka Ma\u0142a"
    ],
    "name:ukr_x_preferred":[
        "\u041b\u043e\u043f\u0443\u0448\u043a\u0430 \u041c\u0430\u043b\u0430"
    ],
    "wof:name":"Lopuszka Mala",
    "wof:placetype":"locality"
},
  "geometry": {"coordinates":[22.4163,49.96762],"type":"Point"}
}