{
  "type": "Feature",
  "properties": {
    "gn:admin1_code":"77.0",
    "gn:admin2_code":"1202.0",
    "gn:admin3_code":"120207.0",
    "gn:asciiname":"Barczkow",
    "gn:country_code":"PL",
    "gn:dem":178,
    "gn:feature_class":"P",
    "gn:feature_code":"PPL",
    "gn:name":"Barczk\u00f3w",
    "gn:population":0,
    "gn:timezone":"Europe/Warsaw",
    "iso:country":"PL",
    "name:pol_x_preferred":[
        "Barczk\u00f3w"
    ],
    "name:ukr_x_preferred":[
        "\u0411\u0430\u0440\u0447\u043a\u0443\u0432"
    ],
    "wof:name":"Barczkow",
    "wof:placetype":"locality"
},
  "geometry": {"coordinates":[20.5491,50.13494],"type":"Point"}
}