{
  "type": "Feature",
  "properties": {
    "gn:admin1_code":"79.0",
    "gn:admin2_code":"1611.0",
    "gn:admin3_code":"161106.0",
    "gn:asciiname":"Niezdrowice",
    "gn:country_code":"PL",
    "gn:dem":200,
    "gn:feature_class":"P",
    "gn:feature_code":"PPL",
    "gn:name":"Niezdrowice",
    "gn:population":0,
    "gn:timezone":"Europe/Warsaw",
    "iso:country":"PL",
    "wof:name":"Niezdrowice",
    "wof:placetype":"locality"
},
  "geometry": {"coordinates":[18.3626,50.37511],"type":"Point"}
}