{
  "type": "Feature",
  "properties": {
    "gn:admin1_code":"79.0",
    "gn:admin2_code":"1611.0",
    "gn:admin3_code":"161106.0",
    "gn:asciiname":"Niezdrowice",
    "gn:country_code":"PL",
    "gn:dem":200,
    "gn:feature_class":"P",
    "gn:feature_code":"PPL",
    "gn:name":"Niezdrowice",
    "gn:population":0,
    "gn:timezone":"Europe/Warsaw",
    "iso:country":"PL",
    "name:azb_x_preferred":[
        "\u0646\u0642\u0632\u062f\u0631\u0648\u0648\u06cc\u062a\u0633\u0647"
    ],
    "name:ceb_x_preferred":[
        "Niezdrowice"
    ],
    "name:deu_x_preferred":[
        "Niesdrowitz"
    ],
    "name:fas_x_preferred":[
        "\u0646\u06af\u0632\u062f\u0631\u0648\u0648\u06cc\u062a\u0633\u0647"
    ],
    "name:pol_x_preferred":[
        "Niezdrowice"
    ],
    "name:ukr_x_preferred":[
        "\u041d\u0435\u0437\u0434\u0440\u043e\u0432\u0456\u0446\u0435"
    ],
    "wof:name":"Niezdrowice",
    "wof:placetype":"locality"
},
  "geometry": {"coordinates":[18.3626,50.37511],"type":"Point"}
}