{
  "type": "Feature",
  "properties": {
    "gn:admin1_code":"78.0",
    "gn:admin2_code":"1422.0",
    "gn:admin3_code":"142206.0",
    "gn:asciiname":"Goski Wasosze",
    "gn:country_code":"PL",
    "gn:dem":127,
    "gn:feature_class":"P",
    "gn:feature_code":"PPL",
    "gn:name":"Goski W\u0105sosze",
    "gn:population":0,
    "gn:timezone":"Europe/Warsaw",
    "iso:country":"PL",
    "name:azb_x_preferred":[
        "\u0642\u0627\u0646\u0633\u06a9\u06cc-\u0648\u0627\u0646\u0633\u0648\u0634\u0647"
    ],
    "name:fas_x_preferred":[
        "\u06af\u0627\u0646\u0633\u06a9\u06cc-\u0648\u0627\u0646\u0633\u0648\u0634\u0647"
    ],
    "name:fra_x_preferred":[
        "G\u0105ski-W\u0105sosze"
    ],
    "name:nld_x_preferred":[
        "G\u0105ski-W\u0105sosze"
    ],
    "name:pol_x_preferred":[
        "Goski-W\u0105sosze"
    ],
    "name:ukr_x_preferred":[
        "\u0490\u043e\u0441\u043a\u0456-\u0412\u043e\u043d\u0441\u043e\u0448\u0435"
    ],
    "name:und_x_variant":[
        "Goski W\u0105sosze"
    ],
    "wof:name":"Goski Wasosze",
    "wof:placetype":"locality"
},
  "geometry": {"coordinates":[20.85,53.15],"type":"Point"}
}