{
  "type": "Feature",
  "properties": {
    "gn:admin1_code":"78.0",
    "gn:admin2_code":"1422.0",
    "gn:admin3_code":"142206.0",
    "gn:asciiname":"Goski Wasosze",
    "gn:country_code":"PL",
    "gn:dem":127,
    "gn:feature_class":"P",
    "gn:feature_code":"PPL",
    "gn:name":"Goski W\u0105sosze",
    "gn:population":0,
    "gn:timezone":"Europe/Warsaw",
    "iso:country":"PL",
    "name:und_x_variant":[
        "Goski W\u0105sosze"
    ],
    "wof:name":"Goski Wasosze",
    "wof:placetype":"locality"
},
  "geometry": {"coordinates":[20.85,53.15],"type":"Point"}
}