{
  "type": "Feature",
  "properties": {
    "gn:admin1_code":"78.0",
    "gn:admin2_code":"1406.0",
    "gn:admin3_code":"140611.0",
    "gn:asciiname":"Borowe",
    "gn:cc2":"PL",
    "gn:country_code":"PL",
    "gn:dem":126,
    "gn:feature_class":"P",
    "gn:feature_code":"PPL",
    "gn:name":"Borowe",
    "gn:population":0,
    "gn:timezone":"Europe/Warsaw",
    "iso:country":"PL",
    "name:fra_x_preferred":[
        "Borowe"
    ],
    "name:pol_x_preferred":[
        "Borowe"
    ],
    "name:ukr_x_preferred":[
        "\u0411\u043e\u0440\u043e\u0432\u0435"
    ],
    "name:und_x_variant":[
        "Borowo",
        "Borowe"
    ],
    "wof:name":"Borowe",
    "wof:placetype":"locality"
},
  "geometry": {"coordinates":[21.1607,51.85826],"type":"Point"}
}