{
  "type": "Feature",
  "properties": {
    "gn:admin1_code":"78.0",
    "gn:admin2_code":"1420.0",
    "gn:admin3_code":"142012.0",
    "gn:asciiname":"Karolinowo",
    "gn:country_code":"PL",
    "gn:dem":106,
    "gn:feature_class":"P",
    "gn:feature_code":"PPL",
    "gn:name":"Karolinowo",
    "gn:population":0,
    "gn:timezone":"Europe/Warsaw",
    "iso:country":"PL",
    "name:fra_x_preferred":[
        "Karolinowo"
    ],
    "name:pol_x_preferred":[
        "Karolinowo"
    ],
    "name:ukr_x_preferred":[
        "\u041a\u0430\u0440\u043e\u043b\u0456\u043d\u043e\u0432\u043e"
    ],
    "wof:name":"Karolinowo",
    "wof:placetype":"locality"
},
  "geometry": {"coordinates":[20.53908,52.55081],"type":"Point"}
}