{
  "type": "Feature",
  "properties": {
    "gn:admin1_code":"81.0",
    "gn:admin2_code":"2013.0",
    "gn:admin3_code":"201307.0",
    "gn:asciiname":"Krasowo Czestki",
    "gn:cc2":"PL",
    "gn:country_code":"PL",
    "gn:dem":133,
    "gn:feature_class":"P",
    "gn:feature_code":"PPL",
    "gn:name":"Krasowo Cz\u0119stki",
    "gn:population":0,
    "gn:timezone":"Europe/Warsaw",
    "iso:country":"PL",
    "name:lit_x_preferred":[
        "Krasovo \u010cestkai"
    ],
    "name:pol_x_preferred":[
        "Krasowo-Cz\u0119stki"
    ],
    "name:ukr_x_preferred":[
        "\u041a\u0440\u0430\u0441\u043e\u0432\u043e-\u0427\u0435\u043d\u0441\u0442\u043a\u0456"
    ],
    "name:und_x_variant":[
        "Krasowo Cz\u0105stki",
        "Krasowo Cz\u0119stki"
    ],
    "wof:name":"Krasowo Czestki",
    "wof:placetype":"locality"
},
  "geometry": {"coordinates":[22.68239,52.85255],"type":"Point"}
}