{
  "type": "Feature",
  "properties": {
    "gn:admin1_code":"76.0",
    "gn:admin2_code":"808.0",
    "gn:admin3_code":"80805.0",
    "gn:asciiname":"Kepsko",
    "gn:country_code":"PL",
    "gn:dem":83,
    "gn:feature_class":"P",
    "gn:feature_code":"PPL",
    "gn:name":"K\u0119psko",
    "gn:population":0,
    "gn:timezone":"Europe/Warsaw",
    "iso:country":"PL",
    "name:deu_x_historical":[
        "Sch\u00f6nborn"
    ],
    "name:deu_x_preferred":[
        "Sch\u00f6nborn"
    ],
    "name:fra_x_preferred":[
        "K\u0119psko"
    ],
    "name:pol_x_preferred":[
        "K\u0119psko"
    ],
    "name:ukr_x_preferred":[
        "\u041a\u0435\u043c\u043f\u0441\u044c\u043a\u043e"
    ],
    "wof:name":"Kepsko",
    "wof:placetype":"locality"
},
  "geometry": {"coordinates":[15.56488,52.1435],"type":"Point"}
}