{
  "type": "Feature",
  "properties": {
    "gn:population":1200,
    "iso:country":"PL",
    "name:ast_x_preferred":[
        "Bojan\u00f3w"
    ],
    "name:azb_x_preferred":[
        "\u0628\u0648\u06cc\u0627\u0646\u0648\u0648"
    ],
    "name:deu_x_preferred":[
        "Bojan\u00f3w"
    ],
    "name:eng_x_preferred":[
        "Bojan\u00f3w"
    ],
    "name:fas_x_preferred":[
        "\u0628\u0648\u06cc\u0627\u0646\u0648\u0648"
    ],
    "name:fra_x_preferred":[
        "Bojan\u00f3w"
    ],
    "name:nld_x_preferred":[
        "Bojan\u00f3w"
    ],
    "name:pol_x_preferred":[
        "Bojan\u00f3w"
    ],
    "name:ukr_x_preferred":[
        "\u0411\u043e\u044f\u043d\u0443\u0432"
    ],
    "name:und_x_variant":[
        "Boyanuv"
    ],
    "qs:a0":"Rzeczpospolita Polska",
    "qs:a1":"*Podkarpackie",
    "qs:a1r":"0",
    "qs:a2":"Stalowowolski",
    "qs:adm0":"Rzeczpospolita Polska",
    "qs:la":"Bojan\u00f3w",
    "qs:la_lc":"*PL1818022",
    "qs:level":"locality",
    "qs:loc":"Bojan\u00f3w",
    "qs:loc_alt":"Bojanow",
    "qs:pop":0,
    "qs:type":"rural point-in-poly",
    "wd:wordcount":90,
    "wof:coterminous":[
        1125304759
    ],
    "wof:name":"Bojan\u00f3w",
    "wof:placetype":"locality",
    "wof:population":1200
},
  "geometry": {"coordinates":[21.9771150298511,50.4484070608801],"type":"Point"}
}