{
  "type": "Feature",
  "properties": {
    "gn:admin1_code":"82.0",
    "gn:admin2_code":"2215.0",
    "gn:admin3_code":"221505.0",
    "gn:asciiname":"Dabrowka Mala",
    "gn:country_code":"PL",
    "gn:dem":107,
    "gn:feature_class":"P",
    "gn:feature_code":"PPL",
    "gn:name":"D\u0105br\u00f3wka Ma\u0142a",
    "gn:population":0,
    "gn:timezone":"Europe/Warsaw",
    "iso:country":"PL",
    "wof:name":"Dabrowka Mala",
    "wof:placetype":"locality"
},
  "geometry": {"coordinates":[17.96636,54.66067],"type":"Point"}
}