{
  "type": "Feature",
  "properties": {
    "gn:admin1_code":"85.0",
    "gn:admin2_code":"2812.0",
    "gn:admin3_code":"281203.0",
    "gn:asciiname":"Straszewo",
    "gn:country_code":"PL",
    "gn:dem":161,
    "gn:feature_class":"P",
    "gn:feature_code":"PPL",
    "gn:name":"Straszewo",
    "gn:population":0,
    "gn:timezone":"Europe/Warsaw",
    "iso:country":"PL",
    "wof:name":"Straszewo",
    "wof:placetype":"locality"
},
  "geometry": {"coordinates":[19.78333,53.35],"type":"Point"}
}