{
  "type": "Feature",
  "properties": {
    "gn:admin1_code":"85.0",
    "gn:admin2_code":"2812.0",
    "gn:admin3_code":"281203.0",
    "gn:asciiname":"Straszewo",
    "gn:country_code":"PL",
    "gn:dem":161,
    "gn:feature_class":"P",
    "gn:feature_code":"PPL",
    "gn:name":"Straszewo",
    "gn:population":0,
    "gn:timezone":"Europe/Warsaw",
    "iso:country":"PL",
    "name:pol_x_preferred":[
        "Straszewo"
    ],
    "name:ukr_x_preferred":[
        "\u0421\u0442\u0440\u0430\u0448\u0435\u0432\u043e"
    ],
    "wof:name":"Straszewo",
    "wof:placetype":"locality"
},
  "geometry": {"coordinates":[19.78333,53.35],"type":"Point"}
}