{
  "type": "Feature",
  "properties": {
    "gn:admin1_code":"82.0",
    "gn:admin2_code":"2204.0",
    "gn:admin3_code":"220406.0",
    "gn:asciiname":"Rebielcz",
    "gn:country_code":"PL",
    "gn:dem":39,
    "gn:feature_class":"P",
    "gn:feature_code":"PPL",
    "gn:name":"R\u0119bielcz",
    "gn:population":0,
    "gn:timezone":"Europe/Warsaw",
    "iso:country":"PL",
    "name:und_x_variant":[
        "Rambeltsch",
        "R\u0119bielcz"
    ],
    "wof:name":"Rebielcz",
    "wof:placetype":"locality"
},
  "geometry": {"coordinates":[18.67009,54.15505],"type":"Point"}
}