{
  "type": "Feature",
  "properties": {
    "gn:admin1_code":"82.0",
    "gn:admin2_code":"2207.0",
    "gn:admin3_code":"220704.0",
    "gn:asciiname":"Gorowychy",
    "gn:country_code":"PL",
    "gn:dem":99,
    "gn:feature_class":"P",
    "gn:feature_code":"PPL",
    "gn:name":"Gorowychy",
    "gn:population":0,
    "gn:timezone":"Europe/Warsaw",
    "iso:country":"PL",
    "name:ceb_x_preferred":[
        "Gorowychy"
    ],
    "name:ita_x_preferred":[
        "G\u00f3rowychy"
    ],
    "name:pol_x_preferred":[
        "G\u00f3rowychy"
    ],
    "name:ukr_x_preferred":[
        "\u0490\u0443\u0440\u043e\u0432\u0438\u0445\u0438"
    ],
    "name:und_x_variant":[
        "Sonnenberg",
        "Sonnenberg in Westpreussen"
    ],
    "wof:name":"Gorowychy",
    "wof:placetype":"locality"
},
  "geometry": {"coordinates":[19.21427000000001,53.79299],"type":"Point"}
}