{
  "type": "Feature",
  "properties": {
    "gn:admin1_code":"82.0",
    "gn:admin2_code":"2207.0",
    "gn:admin3_code":"220704.0",
    "gn:asciiname":"Gorowychy",
    "gn:country_code":"PL",
    "gn:dem":99,
    "gn:feature_class":"P",
    "gn:feature_code":"PPL",
    "gn:name":"Gorowychy",
    "gn:population":0,
    "gn:timezone":"Europe/Warsaw",
    "iso:country":"PL",
    "name:und_x_variant":[
        "Sonnenberg",
        "Sonnenberg in Westpreussen",
        "Gorowychy"
    ],
    "wof:name":"Gorowychy",
    "wof:placetype":"locality"
},
  "geometry": {"coordinates":[19.21427000000001,53.79299],"type":"Point"}
}