{
  "type": "Feature",
  "properties": {
    "gn:admin1_code":"77.0",
    "gn:asciiname":"Dalechowice",
    "gn:country_code":"PL",
    "gn:dem":228,
    "gn:feature_class":"P",
    "gn:feature_code":"PPL",
    "gn:name":"Dalechowice",
    "gn:population":0,
    "gn:timezone":"Europe/Warsaw",
    "iso:country":"PL",
    "wof:name":"Dalechowice",
    "wof:placetype":"locality"
},
  "geometry": {"coordinates":[20.44882,50.20218],"type":"Point"}
}