{
  "type": "Feature",
  "properties": {
    "gn:admin1_code":"77.0",
    "gn:asciiname":"Dalechowice",
    "gn:country_code":"PL",
    "gn:dem":228,
    "gn:feature_class":"P",
    "gn:feature_code":"PPL",
    "gn:name":"Dalechowice",
    "gn:population":0,
    "gn:timezone":"Europe/Warsaw",
    "iso:country":"PL",
    "name:pol_x_preferred":[
        "Dalechowice"
    ],
    "name:ukr_x_preferred":[
        "\u0414\u0430\u043b\u0435\u0445\u043e\u0432\u0456\u0446\u0435"
    ],
    "wof:name":"Dalechowice",
    "wof:placetype":"locality"
},
  "geometry": {"coordinates":[20.44882,50.20218],"type":"Point"}
}