{
  "type": "Feature",
  "properties": {
    "gn:admin1_code":"82.0",
    "gn:admin2_code":"2213.0",
    "gn:admin3_code":"221305.0",
    "gn:asciiname":"Frank",
    "gn:country_code":"PL",
    "gn:dem":141,
    "gn:feature_class":"P",
    "gn:feature_code":"PPL",
    "gn:name":"Frank",
    "gn:population":0,
    "gn:timezone":"Europe/Warsaw",
    "iso:country":"PL",
    "wof:name":"Frank",
    "wof:placetype":"locality"
},
  "geometry": {"coordinates":[18.23307,53.89962],"type":"Point"}
}