{
  "type": "Feature",
  "properties": {
    "gn:admin1_code":"78.0",
    "gn:admin2_code":"1409.0",
    "gn:admin3_code":"140901.0",
    "gn:asciiname":"Baranow",
    "gn:country_code":"PL",
    "gn:dem":133,
    "gn:feature_class":"P",
    "gn:feature_code":"PPL",
    "gn:name":"Baran\u00f3w",
    "gn:population":0,
    "gn:timezone":"Europe/Warsaw",
    "iso:country":"PL",
    "name:ceb_x_preferred":[
        "Baranow"
    ],
    "name:deu_x_preferred":[
        "Baranow"
    ],
    "name:fra_x_preferred":[
        "Baran\u00f3w"
    ],
    "name:heb_x_preferred":[
        "\u05d1\u05e8\u05e0\u05d5\u05d1"
    ],
    "name:ita_x_preferred":[
        "Baran\u00f3w"
    ],
    "name:nld_x_preferred":[
        "Baran\u00f3w"
    ],
    "name:pol_x_preferred":[
        "Baran\u00f3w"
    ],
    "name:ukr_x_preferred":[
        "\u0411\u0430\u0440\u0430\u043d\u0443\u0432"
    ],
    "wof:name":"Baranow",
    "wof:placetype":"locality"
},
  "geometry": {"coordinates":[21.7379,51.21944000000001],"type":"Point"}
}