{
  "type": "Feature",
  "properties": {
    "gn:country":"PL",
    "gn:fcode":"PPLA3",
    "gn:population":535,
    "iso:country":"PL",
    "name:ceb_x_preferred":[
        "D\u0105br\u00f3wka"
    ],
    "name:deu_x_preferred":[
        "D\u0105br\u00f3wka"
    ],
    "name:fra_x_preferred":[
        "D\u0105br\u00f3wka"
    ],
    "name:lit_x_preferred":[
        "Dambruvka"
    ],
    "name:nld_x_preferred":[
        "D\u0105br\u00f3wka"
    ],
    "name:pol_x_preferred":[
        "D\u0105br\u00f3wka"
    ],
    "name:rus_x_preferred":[
        "\u0414\u043e\u043c\u0431\u0440\u0443\u0432\u043a\u0430"
    ],
    "name:ukr_x_preferred":[
        "\u0414\u043e\u043c\u0431\u0440\u0443\u0432\u043a\u0430"
    ],
    "qs_pg:aaroncc":"PL",
    "qs_pg:gn_country":"PL",
    "qs_pg:gn_fcode":"PPLA3",
    "qs_pg:gn_pop":535,
    "qs_pg:name":"D\u0105br\u00f3wka",
    "qs_pg:name_adm0":"Polska",
    "qs_pg:name_adm1":"Mazowieckie",
    "qs_pg:photos_9k":1,
    "qs_pg:photos_9r":2,
    "qs_pg:photos_all":29,
    "qs_pg:photos_sr":0,
    "qs_pg:pop_sr":2,
    "qs_pg:qs_pg_placetype":"localadmin",
    "qs_pg:qs_pg_placetype_gp":"LocalAdmin",
    "qs_pg:woe_adm0":23424923,
    "woe:adm0_id":23424923,
    "woe:name_adm0":"Polska",
    "woe:name_adm1":"Mazowieckie",
    "woe:placetype":"LocalAdmin",
    "wof:name":"D\u0105br\u00f3wka",
    "wof:placetype":"localadmin",
    "wof:population":535
},
  "geometry": {"coordinates":[21.29794,52.48388],"type":"Point"}
}