{
  "type": "Feature",
  "properties": {
    "gn:admin1_code":"75.0",
    "gn:admin2_code":"607.0",
    "gn:admin3_code":"60706.0",
    "gn:asciiname":"Brzozowka",
    "gn:country_code":"PL",
    "gn:dem":293,
    "gn:feature_class":"P",
    "gn:feature_code":"PPL",
    "gn:name":"Brzoz\u00f3wka",
    "gn:population":0,
    "gn:timezone":"Europe/Warsaw",
    "iso:country":"PL",
    "wof:name":"Brzozowka",
    "wof:placetype":"locality"
},
  "geometry": {"coordinates":[22.35486,50.83809],"type":"Point"}
}