{
  "type": "Feature",
  "properties": {
    "gn:admin1_code":"84.0",
    "gn:admin2_code":"2601.0",
    "gn:admin3_code":"260105.0",
    "gn:asciiname":"Piestrzec",
    "gn:country_code":"PL",
    "gn:dem":198,
    "gn:feature_class":"P",
    "gn:feature_code":"PPL",
    "gn:name":"Piestrzec",
    "gn:population":0,
    "gn:timezone":"Europe/Warsaw",
    "iso:country":"PL",
    "name:pol_x_preferred":[
        "Piestrzec"
    ],
    "name:ukr_x_preferred":[
        "\u041f\u0435\u0441\u0442\u0448\u0435\u0446\u044c"
    ],
    "wof:name":"Piestrzec",
    "wof:placetype":"locality"
},
  "geometry": {"coordinates":[20.94586,50.38893],"type":"Point"}
}