{
  "type": "Feature",
  "properties": {
    "gn:admin1_code":"85.0",
    "gn:admin2_code":"2805.0",
    "gn:admin3_code":"280503.0",
    "gn:asciiname":"Skrzypki",
    "gn:country_code":"PL",
    "gn:dem":121,
    "gn:feature_class":"P",
    "gn:feature_code":"PPL",
    "gn:name":"Skrzypki",
    "gn:population":0,
    "gn:timezone":"Europe/Warsaw",
    "iso:country":"PL",
    "name:und_x_variant":[
        "Geigenau",
        "Skrzypken",
        "Skrzypki"
    ],
    "wof:name":"Skrzypki",
    "wof:placetype":"locality"
},
  "geometry": {"coordinates":[22.68917,53.78209],"type":"Point"}
}