{
  "type": "Feature",
  "properties": {
    "gn:admin1_code":"85.0",
    "gn:admin2_code":"2805.0",
    "gn:admin3_code":"280503.0",
    "gn:asciiname":"Skrzypki",
    "gn:country_code":"PL",
    "gn:dem":121,
    "gn:feature_class":"P",
    "gn:feature_code":"PPL",
    "gn:name":"Skrzypki",
    "gn:population":0,
    "gn:timezone":"Europe/Warsaw",
    "iso:country":"PL",
    "name:azb_x_preferred":[
        "\u0633\u06a9\u0698\u067e\u06a9\u06cc"
    ],
    "name:deu_x_preferred":[
        "Skrzypki"
    ],
    "name:fas_x_preferred":[
        "\u0633\u06a9\u0698\u067e\u06a9\u06cc"
    ],
    "name:fra_x_preferred":[
        "Skrzypki"
    ],
    "name:pol_x_preferred":[
        "Skrzypki"
    ],
    "name:ukr_x_preferred":[
        "\u0421\u043a\u0448\u0438\u043f\u043a\u0456"
    ],
    "name:und_x_variant":[
        "Geigenau",
        "Skrzypken"
    ],
    "wof:name":"Skrzypki",
    "wof:placetype":"locality"
},
  "geometry": {"coordinates":[22.68917,53.78209],"type":"Point"}
}