{
  "type": "Feature",
  "properties": {
    "gn:admin1_code":"86.0",
    "gn:admin2_code":"3025.0",
    "gn:admin3_code":"302505.0",
    "gn:asciiname":"Luboniec",
    "gn:country_code":"PL",
    "gn:dem":77,
    "gn:feature_class":"P",
    "gn:feature_code":"PPL",
    "gn:name":"Luboniec",
    "gn:population":0,
    "gn:timezone":"Europe/Warsaw",
    "iso:country":"PL",
    "wof:name":"Luboniec",
    "wof:placetype":"locality"
},
  "geometry": {"coordinates":[17.19754,52.16286],"type":"Point"}
}