{
  "type": "Feature",
  "properties": {
    "gn:admin1_code":"86.0",
    "gn:admin2_code":"3025.0",
    "gn:admin3_code":"302505.0",
    "gn:asciiname":"Luboniec",
    "gn:country_code":"PL",
    "gn:dem":77,
    "gn:feature_class":"P",
    "gn:feature_code":"PPL",
    "gn:name":"Luboniec",
    "gn:population":0,
    "gn:timezone":"Europe/Warsaw",
    "iso:country":"PL",
    "name:azb_x_preferred":[
        "\u0644\u0648\u0628\u0648\u0646\u0642\u062a\u0633"
    ],
    "name:ceb_x_preferred":[
        "Luboniec"
    ],
    "name:fas_x_preferred":[
        "\u0644\u0648\u0628\u0648\u0646\u06af\u062a\u0633"
    ],
    "name:fra_x_preferred":[
        "Luboniec"
    ],
    "name:nld_x_preferred":[
        "Luboniec"
    ],
    "name:pol_x_preferred":[
        "Luboniec"
    ],
    "name:ukr_x_preferred":[
        "\u041b\u044e\u0431\u043e\u043d\u0435\u0446\u044c"
    ],
    "wof:name":"Luboniec",
    "wof:placetype":"locality"
},
  "geometry": {"coordinates":[17.19754,52.16286],"type":"Point"}
}