{
  "type": "Feature",
  "properties": {
    "iso:country":"PL",
    "name:deu_x_preferred":[
        "Jelonki"
    ],
    "name:fra_x_preferred":[
        "Jelonki"
    ],
    "name:pol_x_preferred":[
        "Jelonki"
    ],
    "name:ukr_x_preferred":[
        "\u0404\u043b\u044c\u043e\u043d\u043a\u0456"
    ],
    "wof:name":"Jelonki",
    "wof:placetype":"neighbourhood"
},
  "geometry": {"coordinates":[20.90920512467742,52.22836841901061],"type":"Point"}
}