{
  "type": "Feature",
  "properties": {
    "iso:country":"PL",
    "wof:name":"Jelonki",
    "wof:placetype":"neighbourhood"
},
  "geometry": {"coordinates":[20.90920512467742,52.22836841901061],"type":"Point"}
}