{
  "type": "Feature",
  "properties": {
    "gn:gn_country":"PL",
    "gn:gn_fcode":"PPLA3",
    "gn:gn_pop":2939,
    "gn:population":2939,
    "iso:country":"PL",
    "name:eng_x_preferred":[
        "Gmina Lw\u00f3wek"
    ],
    "name:por_x_preferred":[
        "Comuna de Lw\u00f3wek"
    ],
    "name:rus_x_preferred":[
        "\u041b\u044c\u0432\u0443\u0432\u0435\u043a"
    ],
    "name:slk_x_preferred":[
        "Gmina Lw\u00f3wek"
    ],
    "name:ukr_x_preferred":[
        "\u0490\u043c\u0456\u043d\u0430 \u041b\u044c\u0432\u0443\u0432\u0435\u043a"
    ],
    "name:unk_x_variant":[
        "Neustadt bei Pinne"
    ],
    "name:war_x_preferred":[
        "Gmina Lw\u00f3wek"
    ],
    "qs_pg:aaroncc":"PL",
    "qs_pg:gn_country":"PL",
    "qs_pg:gn_fcode":"PPLA3",
    "qs_pg:gn_pop":2939,
    "qs_pg:name":"Lw\u00f3wek",
    "qs_pg:name_adm0":"Polska",
    "qs_pg:name_adm1":"Wielkopolskie",
    "qs_pg:photos":1,
    "qs_pg:photos_1k":1,
    "qs_pg:photos_9k":1,
    "qs_pg:photos_9r":1,
    "qs_pg:photos_all":1,
    "qs_pg:photos_sr":1,
    "qs_pg:pop_sr":4,
    "qs_pg:qs_pg_placetype":"localadmin",
    "qs_pg:qs_pg_placetype_gp":"LocalAdmin",
    "qs_pg:woe_adm0":23424923,
    "woe:adm0_id":23424923,
    "woe:name_adm0":"Polska",
    "woe:name_adm1":"Wielkopolskie",
    "woe:placetype":"LocalAdmin",
    "wof:name":"Lw\u00f3wek",
    "wof:placetype":"localadmin",
    "wof:population":2939
},
  "geometry": {"coordinates":[16.18106,52.44798],"type":"Point"}
}