{
  "type": "Feature",
  "properties": {
    "gn:admin1_code":"78.0",
    "gn:admin2_code":"1407.0",
    "gn:admin3_code":"140703.0",
    "gn:asciiname":"Boguszowka",
    "gn:country_code":"PL",
    "gn:dem":131,
    "gn:feature_class":"P",
    "gn:feature_code":"PPL",
    "gn:name":"Bogusz\u00f3wka",
    "gn:population":0,
    "gn:timezone":"Europe/Warsaw",
    "iso:country":"PL",
    "wof:name":"Boguszowka",
    "wof:placetype":"locality"
},
  "geometry": {"coordinates":[21.82812,51.44588],"type":"Point"}
}