{
  "type": "Feature",
  "properties": {
    "gn:admin1_code":"72.0",
    "gn:admin2_code":"213.0",
    "gn:admin3_code":"21303.0",
    "gn:asciiname":"Koleda",
    "gn:country_code":"PL",
    "gn:dem":122,
    "gn:feature_class":"P",
    "gn:feature_code":"PPL",
    "gn:name":"Kol\u0119da",
    "gn:population":0,
    "gn:timezone":"Europe/Warsaw",
    "iso:country":"PL",
    "name:und_x_variant":[
        "Kol\u0119da"
    ],
    "wof:name":"Koleda",
    "wof:placetype":"locality"
},
  "geometry": {"coordinates":[17.52929,51.58393],"type":"Point"}
}