{
  "type": "Feature",
  "properties": {
    "gn:admin1_code":"75.0",
    "gn:admin2_code":"615.0",
    "gn:admin3_code":"61504.0",
    "gn:asciiname":"Kakolewnica Poludniowa",
    "gn:country_code":"PL",
    "gn:dem":152,
    "gn:feature_class":"P",
    "gn:feature_code":"PPL",
    "gn:name":"K\u0105kolewnica Po\u0142udniowa",
    "gn:population":0,
    "gn:timezone":"Europe/Warsaw",
    "iso:country":"PL",
    "wof:name":"Kakolewnica Poludniowa",
    "wof:placetype":"locality"
},
  "geometry": {"coordinates":[22.6878,51.89413],"type":"Point"}
}