{
  "type": "Feature",
  "properties": {
    "gn:admin1_code":"85.0",
    "gn:admin2_code":"2816.0",
    "gn:admin3_code":"281603.0",
    "gn:asciiname":"Anuszewo",
    "gn:country_code":"PL",
    "gn:dem":118,
    "gn:feature_class":"P",
    "gn:feature_code":"PPL",
    "gn:name":"Anuszewo",
    "gn:population":0,
    "gn:timezone":"Europe/Warsaw",
    "iso:country":"PL",
    "name:deu_x_preferred":[
        "Anuszewo"
    ],
    "name:pol_x_preferred":[
        "Anuszewo"
    ],
    "name:srp_x_preferred":[
        "\u0410\u043d\u0443\u0448\u0435\u0432\u043e"
    ],
    "name:und_x_variant":[
        "Annussewen",
        "Annusewen",
        "Brennerheim"
    ],
    "wof:name":"Anuszewo",
    "wof:placetype":"locality"
},
  "geometry": {"coordinates":[21.68866,53.52441],"type":"Point"}
}