{
  "type": "Feature",
  "properties": {
    "gn:admin1_code":"75.0",
    "gn:admin2_code":"611.0",
    "gn:admin3_code":"61108.0",
    "gn:asciiname":"Roza Stara",
    "gn:country_code":"PL",
    "gn:dem":173,
    "gn:feature_class":"P",
    "gn:feature_code":"PPL",
    "gn:name":"R\u00f3\u017ca Stara",
    "gn:population":0,
    "gn:timezone":"Europe/Warsaw",
    "iso:country":"PL",
    "name:und_x_variant":[
        "R\u00f3\u017ca",
        "R\u00f3\u017ca Stara"
    ],
    "wof:name":"Roza Stara",
    "wof:placetype":"locality"
},
  "geometry": {"coordinates":[22.07996,51.97876],"type":"Point"}
}