{
  "type": "Feature",
  "properties": {
    "gn:admin1_code":"81.0",
    "gn:admin2_code":"2007.0",
    "gn:admin3_code":"200709.0",
    "gn:asciiname":"Laski",
    "gn:country_code":"PL",
    "gn:dem":106,
    "gn:feature_class":"P",
    "gn:feature_code":"PPL",
    "gn:name":"Laski",
    "gn:population":0,
    "gn:timezone":"Europe/Warsaw",
    "iso:country":"PL",
    "name:lit_x_preferred":[
        "Laskai"
    ],
    "name:pol_x_preferred":[
        "Laski"
    ],
    "name:ukr_x_preferred":[
        "\u041b\u044f\u0441\u043a\u0456"
    ],
    "wof:name":"Laski",
    "wof:placetype":"locality"
},
  "geometry": {"coordinates":[21.71276,53.23789],"type":"Point"}
}