{
  "type": "Feature",
  "properties": {
    "gn:admin1_code":"84.0",
    "gn:admin2_code":"2604.0",
    "gn:admin3_code":"260419.0",
    "gn:asciiname":"Samsonow",
    "gn:country_code":"PL",
    "gn:dem":290,
    "gn:feature_class":"P",
    "gn:feature_code":"PPL",
    "gn:name":"Samson\u00f3w",
    "gn:population":0,
    "gn:timezone":"Europe/Warsaw",
    "iso:country":"PL",
    "name:und_x_variant":[
        "Samson\u00f3w"
    ],
    "wof:name":"Samsonow",
    "wof:placetype":"locality"
},
  "geometry": {"coordinates":[20.62542,50.99161],"type":"Point"}
}