{
  "type": "Feature",
  "properties": {
    "gn:admin1_code":"84.0",
    "gn:admin2_code":"2604.0",
    "gn:admin3_code":"260419.0",
    "gn:asciiname":"Samsonow",
    "gn:country_code":"PL",
    "gn:dem":290,
    "gn:feature_class":"P",
    "gn:feature_code":"PPL",
    "gn:name":"Samson\u00f3w",
    "gn:population":0,
    "gn:timezone":"Europe/Warsaw",
    "iso:country":"PL",
    "name:ceb_x_preferred":[
        "Samson\u00f3w"
    ],
    "name:pol_x_preferred":[
        "Samson\u00f3w"
    ],
    "name:ukr_x_preferred":[
        "\u0421\u0430\u043c\u0441\u043e\u043d\u0443\u0432"
    ],
    "wof:name":"Samsonow",
    "wof:placetype":"locality"
},
  "geometry": {"coordinates":[20.62542,50.99161],"type":"Point"}
}