{
  "type": "Feature",
  "properties": {
    "gn:admin1_code":"78.0",
    "gn:admin2_code":"1429.0",
    "gn:admin3_code":"142904.0",
    "gn:asciiname":"Bujaly Gniewosze",
    "gn:country_code":"PL",
    "gn:dem":151,
    "gn:feature_class":"P",
    "gn:feature_code":"PPL",
    "gn:name":"Buja\u0142y Gniewosze",
    "gn:population":0,
    "gn:timezone":"Europe/Warsaw",
    "iso:country":"PL",
    "name:und_x_variant":[
        "Buja\u0142y-Gniewosze"
    ],
    "wof:name":"Bujaly Gniewosze",
    "wof:placetype":"locality"
},
  "geometry": {"coordinates":[22.35598,52.46299000000001],"type":"Point"}
}