{
  "type": "Feature",
  "properties": {
    "gn:admin1_code":"78.0",
    "gn:admin2_code":"1429.0",
    "gn:admin3_code":"142904.0",
    "gn:asciiname":"Bujaly Gniewosze",
    "gn:country_code":"PL",
    "gn:dem":151,
    "gn:feature_class":"P",
    "gn:feature_code":"PPL",
    "gn:name":"Buja\u0142y Gniewosze",
    "gn:population":0,
    "gn:timezone":"Europe/Warsaw",
    "iso:country":"PL",
    "name:azb_x_preferred":[
        "\u0628\u0648\u06cc\u0627\u0648-\u0642\u0646\u0642\u0648\u0648\u0634\u0647"
    ],
    "name:fas_x_preferred":[
        "\u0628\u0648\u06cc\u0627\u0648-\u06af\u0646\u06af\u0648\u0648\u0634\u0647"
    ],
    "name:fra_x_preferred":[
        "Buja\u0142y-Gniewosze"
    ],
    "name:lit_x_preferred":[
        "Bujali Gnevo\u0161\u0117"
    ],
    "name:pol_x_preferred":[
        "Buja\u0142y-Gniewosze"
    ],
    "name:ukr_x_preferred":[
        "\u0411\u0443\u044f\u043b\u0438-\u0490\u043d\u0435\u0432\u043e\u0448\u0435"
    ],
    "name:und_x_variant":[
        "Buja\u0142y-Gniewosze"
    ],
    "wof:name":"Bujaly Gniewosze",
    "wof:placetype":"locality"
},
  "geometry": {"coordinates":[22.35598,52.46299000000001],"type":"Point"}
}