{
  "type": "Feature",
  "properties": {
    "gn:admin1_code":"85.0",
    "gn:admin2_code":"2802.0",
    "gn:admin3_code":"280202.0",
    "gn:asciiname":"Szyleny",
    "gn:country_code":"PL",
    "gn:dem":23,
    "gn:feature_class":"P",
    "gn:feature_code":"PPL",
    "gn:name":"Szyleny",
    "gn:population":0,
    "gn:timezone":"Europe/Warsaw",
    "iso:country":"PL",
    "name:fra_x_preferred":[
        "Szyleny"
    ],
    "name:pol_x_preferred":[
        "Szyleny"
    ],
    "name:ukr_x_preferred":[
        "\u0428\u0438\u043b\u0435\u043d\u0438"
    ],
    "name:und_x_variant":[
        "Schillgehnen"
    ],
    "name:vie_x_preferred":[
        "Szyleny"
    ],
    "wof:name":"Szyleny",
    "wof:placetype":"locality"
},
  "geometry": {"coordinates":[19.87067,54.3382],"type":"Point"}
}