{
  "type": "Feature",
  "properties": {
    "gn:admin1_code":"87.0",
    "gn:admin2_code":"3214.0",
    "gn:admin3_code":"321410.0",
    "gn:asciiname":"Krapiel",
    "gn:country_code":"PL",
    "gn:dem":50,
    "gn:feature_class":"P",
    "gn:feature_code":"PPL",
    "gn:name":"Kr\u0105piel",
    "gn:population":0,
    "gn:timezone":"Europe/Warsaw",
    "iso:country":"PL",
    "wof:name":"Krapiel",
    "wof:placetype":"locality"
},
  "geometry": {"coordinates":[15.17861,53.29948],"type":"Point"}
}