{
  "type": "Feature",
  "properties": {
    "gn:admin1_code":"75.0",
    "gn:admin2_code":"603.0",
    "gn:admin3_code":"60311.0",
    "gn:asciiname":"Dobromysl",
    "gn:country_code":"PL",
    "gn:dem":178,
    "gn:feature_class":"P",
    "gn:feature_code":"PPL",
    "gn:name":"Dobromy\u015bl",
    "gn:population":0,
    "gn:timezone":"Europe/Warsaw",
    "iso:country":"PL",
    "name:und_x_variant":[
        "Dobromy\u015bl"
    ],
    "wof:name":"Dobromysl",
    "wof:placetype":"locality"
},
  "geometry": {"coordinates":[23.18552,51.22836],"type":"Point"}
}