{
  "type": "Feature",
  "properties": {
    "gn:admin1_code":"75.0",
    "gn:admin2_code":"603.0",
    "gn:admin3_code":"60311.0",
    "gn:asciiname":"Dobromysl",
    "gn:country_code":"PL",
    "gn:dem":178,
    "gn:feature_class":"P",
    "gn:feature_code":"PPL",
    "gn:name":"Dobromy\u015bl",
    "gn:population":0,
    "gn:timezone":"Europe/Warsaw",
    "iso:country":"PL",
    "name:fra_x_preferred":[
        "Dobromy\u015bl"
    ],
    "name:pol_x_preferred":[
        "Dobromy\u015bl"
    ],
    "name:ukr_x_preferred":[
        "\u0414\u043e\u0431\u0440\u043e\u043c\u0438\u0441\u043b\u044c"
    ],
    "wof:name":"Dobromysl",
    "wof:placetype":"locality"
},
  "geometry": {"coordinates":[23.18552,51.22836],"type":"Point"}
}