{
  "type": "Feature",
  "properties": {
    "gn:admin1_code":"78.0",
    "gn:admin2_code":"1423.0",
    "gn:admin3_code":"142304.0",
    "gn:asciiname":"Ceten",
    "gn:country_code":"PL",
    "gn:dem":145,
    "gn:feature_class":"P",
    "gn:feature_code":"PPL",
    "gn:name":"Cete\u0144",
    "gn:population":0,
    "gn:timezone":"Europe/Warsaw",
    "iso:country":"PL",
    "name:fra_x_preferred":[
        "Cete\u0144"
    ],
    "name:pol_x_preferred":[
        "Cete\u0144"
    ],
    "name:ukr_x_preferred":[
        "\u0426\u0435\u0442\u0435\u043d\u044c"
    ],
    "wof:name":"Ceten",
    "wof:placetype":"neighbourhood"
},
  "geometry": {"coordinates":[20.55927,51.53016],"type":"Point"}
}