{
  "type": "Feature",
  "properties": {
    "gn:admin1_code":"77.0",
    "gn:admin2_code":"1214.0",
    "gn:admin3_code":"121406.0",
    "gn:asciiname":"Zielenice",
    "gn:country_code":"PL",
    "gn:dem":285,
    "gn:feature_class":"P",
    "gn:feature_code":"PPL",
    "gn:name":"Zielenice",
    "gn:population":0,
    "gn:timezone":"Europe/Warsaw",
    "iso:country":"PL",
    "name:und_x_variant":[
        "Zieleniec",
        "Zielenice"
    ],
    "wof:name":"Zielenice",
    "wof:placetype":"locality"
},
  "geometry": {"coordinates":[20.18778,50.28707],"type":"Point"}
}