{
  "type": "Feature",
  "properties": {
    "gn:admin1_code":"78.0",
    "gn:admin2_code":"1403.0",
    "gn:admin3_code":"140311.0",
    "gn:asciiname":"Mazurki",
    "gn:country_code":"PL",
    "gn:dem":177,
    "gn:feature_class":"P",
    "gn:feature_code":"PPL",
    "gn:name":"Mazurki",
    "gn:population":0,
    "gn:timezone":"Europe/Warsaw",
    "iso:country":"PL",
    "name:fra_x_preferred":[
        "Mazurki"
    ],
    "name:pol_x_preferred":[
        "Mazurki"
    ],
    "wof:name":"Mazurki",
    "wof:placetype":"locality"
},
  "geometry": {"coordinates":[21.72425,51.79145],"type":"Point"}
}