{
  "type": "Feature",
  "properties": {
    "gn:admin1_code":"80.0",
    "gn:admin2_code":"1814.0",
    "gn:admin3_code":"181402.0",
    "gn:asciiname":"Osowka",
    "gn:country_code":"PL",
    "gn:dem":226,
    "gn:feature_class":"P",
    "gn:feature_code":"PPL",
    "gn:name":"Os\u00f3wka",
    "gn:population":0,
    "gn:timezone":"Europe/Warsaw",
    "iso:country":"PL",
    "wof:name":"Osowka",
    "wof:placetype":"locality"
},
  "geometry": {"coordinates":[22.75,50.28333],"type":"Point"}
}