{
  "type": "Feature",
  "properties": {
    "gn:admin1_code":"86.0",
    "gn:admin2_code":"3005.0",
    "gn:admin3_code":"300502.0",
    "gn:asciiname":"Ujazdek",
    "gn:country_code":"PL",
    "gn:dem":72,
    "gn:feature_class":"P",
    "gn:feature_code":"PPL",
    "gn:name":"Ujazdek",
    "gn:population":0,
    "gn:timezone":"Europe/Warsaw",
    "iso:country":"PL",
    "name:pol_x_preferred":[
        "Ujazdek"
    ],
    "name:ukr_x_preferred":[
        "\u0423\u044f\u0437\u0434\u0435\u043a"
    ],
    "name:und_x_variant":[
        "Ujazdek Zdr\u00f3j"
    ],
    "wof:name":"Ujazdek",
    "wof:placetype":"locality"
},
  "geometry": {"coordinates":[16.44705,52.19553],"type":"Point"}
}