{
  "type": "Feature",
  "properties": {
    "gn:admin1_code":"78.0",
    "gn:admin2_code":"1430.0",
    "gn:admin3_code":"143005.0",
    "gn:asciiname":"Wola Korzeniowa",
    "gn:country_code":"PL",
    "gn:dem":236,
    "gn:feature_class":"P",
    "gn:feature_code":"PPL",
    "gn:name":"Wola Korzeniowa",
    "gn:population":0,
    "gn:timezone":"Europe/Warsaw",
    "iso:country":"PL",
    "name:ceb_x_preferred":[
        "Wola Korzeniowa"
    ],
    "name:fra_x_preferred":[
        "Wola Korzeniowa"
    ],
    "name:pol_x_preferred":[
        "Wola Korzeniowa"
    ],
    "name:ukr_x_preferred":[
        "\u0412\u043e\u043b\u044f-\u041a\u043e\u0436\u0435\u043d\u044c\u043e\u0432\u0430"
    ],
    "wof:name":"Wola Korzeniowa",
    "wof:placetype":"locality"
},
  "geometry": {"coordinates":[20.85,51.20076],"type":"Point"}
}