{
  "type": "Feature",
  "properties": {
    "iso:country":"PL",
    "wof:name":"Azory",
    "wof:placetype":"neighbourhood"
},
  "geometry": {"coordinates":[19.90860851110657,50.08626144139335],"type":"Point"}
}