{
  "type": "Feature",
  "properties": {
    "gn:admin1_code":"79.0",
    "gn:admin2_code":"1610.0",
    "gn:admin3_code":"161001.0",
    "gn:asciiname":"Fracki",
    "gn:country_code":"PL",
    "gn:dem":184,
    "gn:feature_class":"P",
    "gn:feature_code":"PPL",
    "gn:name":"Fracki",
    "gn:population":0,
    "gn:timezone":"Europe/Warsaw",
    "iso:country":"PL",
    "name:pol_x_preferred":[
        "Fr\u0105cki"
    ],
    "wof:name":"Fracki",
    "wof:placetype":"locality"
},
  "geometry": {"coordinates":[17.69096,50.45549000000001],"type":"Point"}
}