{
  "type": "Feature",
  "properties": {
    "gn:admin1_code":"74.0",
    "gn:admin2_code":"1010.0",
    "gn:admin3_code":"101009.0",
    "gn:asciiname":"Barkowice Mokre",
    "gn:country_code":"PL",
    "gn:dem":175,
    "gn:feature_class":"P",
    "gn:feature_code":"PPL",
    "gn:name":"Barkowice Mokre",
    "gn:population":0,
    "gn:timezone":"Europe/Warsaw",
    "iso:country":"PL",
    "name:azb_x_preferred":[
        "\u0628\u0627\u0631\u06a9\u0648\u0648\u06cc\u062a\u0633\u0647 \u0645\u0648\u06a9\u0631\u0647"
    ],
    "name:ceb_x_preferred":[
        "Barkowice Mokre"
    ],
    "name:deu_x_preferred":[
        "Barkowice Mokre"
    ],
    "name:fas_x_preferred":[
        "\u0628\u0627\u0631\u06a9\u0648\u0648\u06cc\u062a\u0633\u0647 \u0645\u0648\u06a9\u0631\u0647"
    ],
    "name:fra_x_preferred":[
        "Barkowice Mokre"
    ],
    "name:nld_x_preferred":[
        "Barkowice Mokre"
    ],
    "name:pol_x_preferred":[
        "Barkowice Mokre"
    ],
    "name:ukr_x_preferred":[
        "\u0411\u0430\u0440\u043a\u043e\u0432\u0456\u0446\u0435-\u041c\u043e\u043a\u0440\u0435"
    ],
    "wof:name":"Barkowice Mokre",
    "wof:placetype":"locality"
},
  "geometry": {"coordinates":[19.8777,51.4097],"type":"Point"}
}