{
  "type": "Feature",
  "properties": {
    "gn:gn_country":"PL",
    "gn:gn_fcode":"PPL",
    "gn:gn_pop":663,
    "gn:population":663,
    "iso:country":"PL",
    "name:eng_x_preferred":[
        "Gmina \u017bmud\u017a"
    ],
    "name:por_x_preferred":[
        "Comuna de \u017bmud\u017a"
    ],
    "name:rus_x_preferred":[
        "\u0416\u043c\u0443\u0434\u0437\u044c"
    ],
    "name:slk_x_preferred":[
        "Gmina \u017bmud\u017a"
    ],
    "name:ukr_x_preferred":[
        "\u0490\u043c\u0456\u043d\u0430 \u0416\u043c\u0443\u0434\u0437\u044c"
    ],
    "name:war_x_preferred":[
        "Gmina \u017bmud\u017a"
    ],
    "qs_pg:aaroncc":"PL",
    "qs_pg:gn_country":"PL",
    "qs_pg:gn_fcode":"PPL",
    "qs_pg:gn_pop":663,
    "qs_pg:name":"\u017bmud\u017a",
    "qs_pg:name_adm0":"Polska",
    "qs_pg:name_adm1":"Lubelskie",
    "qs_pg:photos_9k":1,
    "qs_pg:photos_9r":1,
    "qs_pg:photos_all":2,
    "qs_pg:photos_sr":0,
    "qs_pg:pop_sr":2,
    "qs_pg:qs_pg_placetype":"locality",
    "qs_pg:qs_pg_placetype_gp":"Town",
    "qs_pg:woe_adm0":23424923,
    "woe:adm0_id":23424923,
    "woe:name_adm0":"Polska",
    "woe:name_adm1":"Lubelskie",
    "woe:placetype":"Town",
    "wof:name":"\u017bmud\u017a",
    "wof:placetype":"locality",
    "wof:population":663
},
  "geometry": {"coordinates":[23.67588,51.01829],"type":"Point"}
}