{
  "type": "Feature",
  "properties": {
    "gn:admin1_code":"81.0",
    "gn:admin2_code":"2011.0",
    "gn:admin3_code":"201101.0",
    "gn:asciiname":"Harasimowicze",
    "gn:country_code":"PL",
    "gn:dem":124,
    "gn:feature_class":"P",
    "gn:feature_code":"PPL",
    "gn:name":"Harasimowicze",
    "gn:population":0,
    "gn:timezone":"Europe/Warsaw",
    "iso:country":"PL",
    "wof:name":"Harasimowicze",
    "wof:placetype":"locality"
},
  "geometry": {"coordinates":[23.42138,53.66153000000001],"type":"Point"}
}