{
  "type": "Feature",
  "properties": {
    "gn:admin1_code":"78.0",
    "gn:admin2_code":"1402.0",
    "gn:admin3_code":"140207.0",
    "gn:asciiname":"Wladyslawow",
    "gn:country_code":"PL",
    "gn:dem":120,
    "gn:feature_class":"P",
    "gn:feature_code":"PPL",
    "gn:name":"W\u0142adys\u0142aw\u00f3w",
    "gn:population":0,
    "gn:timezone":"Europe/Warsaw",
    "iso:country":"PL",
    "wof:name":"Wladyslawow",
    "wof:placetype":"locality"
},
  "geometry": {"coordinates":[20.67512,52.88516],"type":"Point"}
}