{
  "type": "Feature",
  "properties": {
    "gn:admin1_code":"85.0",
    "gn:admin2_code":"2804.0",
    "gn:admin3_code":"280403.0",
    "gn:asciiname":"Kopanka Druga",
    "gn:cc2":"PL",
    "gn:country_code":"PL",
    "gn:dem":-2,
    "gn:feature_class":"P",
    "gn:feature_code":"PPL",
    "gn:name":"Kopanka Druga",
    "gn:population":0,
    "gn:timezone":"Europe/Warsaw",
    "iso:country":"PL",
    "name:ceb_x_preferred":[
        "Kopanka Druga"
    ],
    "name:nld_x_preferred":[
        "Kopanka Druga"
    ],
    "name:pol_x_preferred":[
        "Kopanka Druga"
    ],
    "name:und_x_variant":[
        "Hoppenau",
        "Kopanka"
    ],
    "wof:name":"Kopanka Druga",
    "wof:placetype":"locality"
},
  "geometry": {"coordinates":[19.24135,54.1197],"type":"Point"}
}