{
  "type": "Feature",
  "properties": {
    "gn:admin1_code":"86.0",
    "gn:admin2_code":"3027.0",
    "gn:admin3_code":"302704.0",
    "gn:asciiname":"Borek",
    "gn:country_code":"PL",
    "gn:dem":116,
    "gn:feature_class":"P",
    "gn:feature_code":"PPL",
    "gn:name":"Borek",
    "gn:population":0,
    "gn:timezone":"Europe/Warsaw",
    "iso:country":"PL",
    "name:ceb_x_preferred":[
        "Borek"
    ],
    "name:ces_x_preferred":[
        "Borek"
    ],
    "name:deu_x_preferred":[
        "Borek"
    ],
    "name:epo_x_preferred":[
        "Borek"
    ],
    "name:fra_x_preferred":[
        "Borek"
    ],
    "name:ita_x_preferred":[
        "Borek"
    ],
    "name:lit_x_preferred":[
        "Borekas"
    ],
    "name:nld_x_preferred":[
        "Borek"
    ],
    "name:pol_x_preferred":[
        "Borek"
    ],
    "name:por_x_preferred":[
        "Borek"
    ],
    "name:rus_x_preferred":[
        "\u0411\u043e\u0440\u0435\u043a"
    ],
    "name:slk_x_preferred":[
        "Borek"
    ],
    "name:srp_x_preferred":[
        "\u0411\u043e\u0440\u0435\u043a"
    ],
    "name:swe_x_preferred":[
        "Borek"
    ],
    "name:ukr_x_preferred":[
        "\u0411\u043e\u0440\u0435\u043a"
    ],
    "wof:name":"Borek",
    "wof:placetype":"locality"
},
  "geometry": {"coordinates":[18.56667,51.86667],"type":"Point"}
}