{
  "type": "Feature",
  "properties": {
    "gn:admin1_code":"73.0",
    "gn:admin2_code":"416.0",
    "gn:admin3_code":"41605.0",
    "gn:asciiname":"Lisiny",
    "gn:country_code":"PL",
    "gn:dem":116,
    "gn:feature_class":"P",
    "gn:feature_code":"PPL",
    "gn:name":"Lisiny",
    "gn:population":0,
    "gn:timezone":"Europe/Warsaw",
    "iso:country":"PL",
    "name:deu_x_preferred":[
        "Lisiny"
    ],
    "name:fra_x_preferred":[
        "Lisiny"
    ],
    "name:pol_x_preferred":[
        "Lisiny"
    ],
    "name:ukr_x_preferred":[
        "\u041b\u0456\u0441\u0456\u043d\u0438"
    ],
    "wof:name":"Lisiny",
    "wof:placetype":"locality"
},
  "geometry": {"coordinates":[18.14594,53.6652],"type":"Point"}
}