{
  "type": "Feature",
  "properties": {
    "gn:admin1_code":"86.0",
    "gn:admin2_code":"3021.0",
    "gn:admin3_code":"302116.0",
    "gn:asciiname":"Sokolniki Gwiazdowskie",
    "gn:country_code":"PL",
    "gn:dem":101,
    "gn:feature_class":"P",
    "gn:feature_code":"PPL",
    "gn:name":"Sokolniki Gwiazdowskie",
    "gn:population":0,
    "gn:timezone":"Europe/Warsaw",
    "iso:country":"PL",
    "name:und_x_variant":[
        "Sokolniki",
        "Sokolniki Gwiazdowskie"
    ],
    "wof:name":"Sokolniki Gwiazdowskie",
    "wof:placetype":"locality"
},
  "geometry": {"coordinates":[17.17142999999999,52.41417],"type":"Point"}
}