{
  "type": "Feature",
  "properties": {
    "gn:admin1_code":"86.0",
    "gn:admin2_code":"3021.0",
    "gn:admin3_code":"302116.0",
    "gn:asciiname":"Sokolniki Gwiazdowskie",
    "gn:country_code":"PL",
    "gn:dem":101,
    "gn:feature_class":"P",
    "gn:feature_code":"PPL",
    "gn:name":"Sokolniki Gwiazdowskie",
    "gn:population":0,
    "gn:timezone":"Europe/Warsaw",
    "iso:country":"PL",
    "name:fra_x_preferred":[
        "Sokolniki Gwiazdowskie"
    ],
    "name:pol_x_preferred":[
        "Sokolniki Gwiazdowskie"
    ],
    "name:ukr_x_preferred":[
        "\u0421\u043e\u043a\u043e\u043b\u044c\u043d\u0438\u043a\u0438-\u0490\u0432\u044f\u0437\u0434\u043e\u0432\u0441\u044c\u043a\u0456"
    ],
    "name:und_x_variant":[
        "Sokolniki"
    ],
    "wof:name":"Sokolniki Gwiazdowskie",
    "wof:placetype":"locality"
},
  "geometry": {"coordinates":[17.17142999999999,52.41417],"type":"Point"}
}