{
  "type": "Feature",
  "properties": {
    "gn:country":"PL",
    "gn:fcode":"PPL",
    "gn:population":900,
    "iso:country":"PL",
    "name:ast_x_preferred":[
        "Biertowice"
    ],
    "name:ceb_x_preferred":[
        "Biertowice"
    ],
    "name:deu_x_preferred":[
        "Biertowice"
    ],
    "name:eng_x_preferred":[
        "Biertowice"
    ],
    "name:fra_x_preferred":[
        "Biertowice"
    ],
    "name:nld_x_preferred":[
        "Biertowice"
    ],
    "name:pol_x_preferred":[
        "Biertowice"
    ],
    "name:ukr_x_preferred":[
        "\u0411\u0435\u0440\u0442\u043e\u0432\u0456\u0446\u0435"
    ],
    "qs_pg:aaroncc":"PL",
    "qs_pg:gn_country":"PL",
    "qs_pg:gn_fcode":"PPL",
    "qs_pg:gn_pop":900,
    "qs_pg:name":"Biertowice",
    "qs_pg:name_adm0":"Polska",
    "qs_pg:name_adm1":"Ma\u0142opolskie",
    "qs_pg:photos_9k":1,
    "qs_pg:photos_9r":1,
    "qs_pg:photos_all":1,
    "qs_pg:photos_sr":0,
    "qs_pg:pop_sr":2,
    "qs_pg:qs_pg_placetype":"locality",
    "qs_pg:qs_pg_placetype_gp":"Town",
    "qs_pg:woe_adm0":23424923,
    "woe:adm0_id":23424923,
    "woe:name_adm0":"Polska",
    "woe:name_adm1":"Ma\u0142opolskie",
    "woe:placetype":"Town",
    "wof:name":"Biertowice",
    "wof:placetype":"locality",
    "wof:population":900
},
  "geometry": {"coordinates":[19.7929,49.87207],"type":"Point"}
}