{
  "type": "Feature",
  "properties": {
    "iso:country":"PL",
    "name:ceb_x_preferred":[
        "Ligota"
    ],
    "name:ces_x_preferred":[
        "Ligota"
    ],
    "name:deu_x_preferred":[
        "Ligota"
    ],
    "name:eng_x_preferred":[
        "Ligota"
    ],
    "name:fra_x_preferred":[
        "Ligota"
    ],
    "name:pol_x_preferred":[
        "Ligota"
    ],
    "name:ukr_x_preferred":[
        "\u041b\u0456\u0491\u043e\u0442\u0430"
    ],
    "wof:name":"Ligota",
    "wof:placetype":"neighbourhood"
},
  "geometry": {"coordinates":[17.02739522708275,51.15163137225603],"type":"Point"}
}