{
  "type": "Feature",
  "properties": {
    "iso:country":"PL",
    "name:eng_x_preferred":[
        "Ligota"
    ],
    "name:pol_x_preferred":[
        "Ligota"
    ],
    "wof:name":"Ligota",
    "wof:placetype":"neighbourhood"
},
  "geometry": {"coordinates":[17.02739522708275,51.15163137225603],"type":"Point"}
}