{
  "type": "Feature",
  "properties": {
    "gn:admin1_code":"76.0",
    "gn:admin2_code":"810.0",
    "gn:admin3_code":"81009.0",
    "gn:asciiname":"Dzietrzychowice",
    "gn:country_code":"PL",
    "gn:dem":133,
    "gn:feature_class":"P",
    "gn:feature_code":"PPL",
    "gn:name":"Dzietrzychowice",
    "gn:population":0,
    "gn:timezone":"Europe/Warsaw",
    "iso:country":"PL",
    "name:ceb_x_preferred":[
        "Dzietrzychowice"
    ],
    "name:dan_x_preferred":[
        "Dzietrzychowice"
    ],
    "name:fas_x_preferred":[
        "\u062c\u062a\u0698\u062e\u0648\u0648\u06cc\u062a\u0633\u0647"
    ],
    "name:fra_x_preferred":[
        "Dzietrzychowice"
    ],
    "name:nld_x_preferred":[
        "Dzietrzychowice"
    ],
    "name:pol_x_preferred":[
        "Dzietrzychowice"
    ],
    "name:ukr_x_preferred":[
        "\u0414\u0437\u0435\u0442\u0448\u0438\u0445\u043e\u0432\u0456\u0446\u0435"
    ],
    "wof:name":"Dzietrzychowice",
    "wof:placetype":"locality"
},
  "geometry": {"coordinates":[15.35416,51.66372],"type":"Point"}
}