{
  "type": "Feature",
  "properties": {
    "gn:admin1_code":"85.0",
    "gn:admin2_code":"2813.0",
    "gn:admin3_code":"281303.0",
    "gn:asciiname":"Gorczyce",
    "gn:country_code":"PL",
    "gn:dem":211,
    "gn:feature_class":"P",
    "gn:feature_code":"PPL",
    "gn:name":"Gorczyce",
    "gn:population":0,
    "gn:timezone":"Europe/Warsaw",
    "iso:country":"PL",
    "name:und_x_variant":[
        "Gartenberg",
        "Gorczyce"
    ],
    "wof:name":"Gorczyce",
    "wof:placetype":"locality"
},
  "geometry": {"coordinates":[22.47198,54.13896999999999],"type":"Point"}
}