{
  "type": "Feature",
  "properties": {
    "gn:admin1_code":"73.0",
    "gn:admin2_code":"407.0",
    "gn:admin3_code":"40709.0",
    "gn:asciiname":"Tuczno",
    "gn:country_code":"PL",
    "gn:dem":83,
    "gn:feature_class":"P",
    "gn:feature_code":"PPL",
    "gn:name":"Tuczno",
    "gn:population":0,
    "gn:timezone":"Europe/Warsaw",
    "iso:country":"PL",
    "name:bel_x_preferred":[
        "\u0422\u0443\u0447\u043d\u0430"
    ],
    "name:csb_x_preferred":[
        "T\u00ebczno"
    ],
    "name:deu_x_preferred":[
        "Tuczno"
    ],
    "name:epo_x_preferred":[
        "Tuczno"
    ],
    "name:fra_x_preferred":[
        "Tuczno"
    ],
    "name:ita_x_preferred":[
        "Tuczno"
    ],
    "name:jav_x_preferred":[
        "Tuczno"
    ],
    "name:lav_x_preferred":[
        "Tu\u010dno"
    ],
    "name:msa_x_preferred":[
        "Tuczno"
    ],
    "name:nld_x_preferred":[
        "Tuczno"
    ],
    "name:pol_x_preferred":[
        "Tuczno"
    ],
    "name:por_x_preferred":[
        "Tuczno"
    ],
    "name:ron_x_preferred":[
        "Tuczno"
    ],
    "name:rus_x_preferred":[
        "\u0422\u0443\u0447\u043d\u043e"
    ],
    "name:slk_x_preferred":[
        "Tuczno"
    ],
    "name:srp_x_preferred":[
        "\u0422\u0443\u0447\u043d\u043e"
    ],
    "name:swe_x_preferred":[
        "Tuczno"
    ],
    "name:ukr_x_preferred":[
        "\u0422\u0443\u0447\u043d\u043e"
    ],
    "name:vie_x_preferred":[
        "Tuczno"
    ],
    "name:zho_x_preferred":[
        "\u5716\u5947\u8afe"
    ],
    "wof:name":"Tuczno",
    "wof:placetype":"locality"
},
  "geometry": {"coordinates":[18.13655,52.86167],"type":"Point"}
}