{
  "type": "Feature",
  "properties": {
    "gn:admin1_code":"86.0",
    "gn:admin2_code":"3027.0",
    "gn:admin3_code":"302709.0",
    "gn:asciiname":"Przemyslawow",
    "gn:country_code":"PL",
    "gn:dem":129,
    "gn:feature_class":"P",
    "gn:feature_code":"PPL",
    "gn:name":"Przemys\u0142aw\u00f3w",
    "gn:population":0,
    "gn:timezone":"Europe/Warsaw",
    "iso:country":"PL",
    "name:pol_x_preferred":[
        "Przemys\u0142aw\u00f3w"
    ],
    "wof:name":"Przemyslawow",
    "wof:placetype":"locality"
},
  "geometry": {"coordinates":[18.48204,52.07308],"type":"Point"}
}