{
  "type": "Feature",
  "properties": {
    "gn:country":"PL",
    "gn:fcode":"PPL",
    "gn:population":556,
    "iso:country":"PL",
    "name:ast_x_preferred":[
        "\u017barki Wielkie"
    ],
    "name:azb_x_preferred":[
        "\u0698\u0627\u0631\u06a9\u06cc \u0648\u06cc\u0644\u06a9\u06cc\u0647"
    ],
    "name:ceb_x_preferred":[
        "\u017barki Wielkie"
    ],
    "name:ces_x_preferred":[
        "\u017barki Wielkie"
    ],
    "name:che_x_preferred":[
        "\u0416\u0430\u0440\u043a\u0438-\u0412\u0435\u043b\u0438\u043a\u0438"
    ],
    "name:dan_x_preferred":[
        "\u017barki Wielkie"
    ],
    "name:deu_x_preferred":[
        "\u017barki Wielkie"
    ],
    "name:dsb_x_preferred":[
        "\u017dark\u0142"
    ],
    "name:dsb_x_variant":[
        "Zd\u017aary"
    ],
    "name:eng_x_preferred":[
        "\u017barki Wielkie"
    ],
    "name:fas_x_preferred":[
        "\u0698\u0627\u0631\u06a9\u06cc \u0648\u06cc\u0644\u06a9\u06cc\u0647"
    ],
    "name:fra_x_preferred":[
        "\u017barki Wielkie"
    ],
    "name:gle_x_preferred":[
        "\u017barki Wielkie"
    ],
    "name:hsb_x_preferred":[
        "Zd\u017aary"
    ],
    "name:ita_x_preferred":[
        "\u017barki Wielkie"
    ],
    "name:nan_x_preferred":[
        "\u017barki Wielkie"
    ],
    "name:nld_x_preferred":[
        "\u017barki Wielkie"
    ],
    "name:pol_x_preferred":[
        "\u017barki Wielkie"
    ],
    "name:rus_x_preferred":[
        "\u0417\u0430\u0440\u043a\u0438-\u0412\u0435\u043b\u043a\u0438"
    ],
    "name:rus_x_variant":[
        "\u0416\u0430\u0440\u043a\u0438-\u0412\u0435\u043b\u044c\u043a\u0435"
    ],
    "name:slv_x_preferred":[
        "\u017barki Wielkie"
    ],
    "name:tat_x_preferred":[
        "\u0416\u0430\u0440\u043a\u0438-\u0412\u0435\u043b\u0438\u043a\u0438"
    ],
    "name:ukr_x_preferred":[
        "\u0416\u0430\u0440\u043a\u0456-\u0412\u0435\u043b\u0438\u043a\u0456"
    ],
    "name:und_x_variant":[
        "Gross S\u00e4rchen"
    ],
    "qs_pg:aaroncc":"PL",
    "qs_pg:gn_country":"PL",
    "qs_pg:gn_fcode":"PPL",
    "qs_pg:gn_pop":556,
    "qs_pg:name":"\u017barki Wielkie",
    "qs_pg:name_adm0":"Polska",
    "qs_pg:name_adm1":"Lubuskie",
    "qs_pg:photos_9k":1,
    "qs_pg:photos_9r":1,
    "qs_pg:photos_all":1,
    "qs_pg:photos_sr":0,
    "qs_pg:pop_sr":2,
    "qs_pg:qs_pg_placetype":"locality",
    "qs_pg:qs_pg_placetype_gp":"Town",
    "qs_pg:woe_adm0":23424923,
    "woe:adm0_id":23424923,
    "woe:name_adm0":"Polska",
    "woe:name_adm1":"Lubuskie",
    "woe:placetype":"Town",
    "wof:name":"\u017barki Wielkie",
    "wof:placetype":"locality",
    "wof:population":556
},
  "geometry": {"coordinates":[14.7603,51.59382],"type":"Point"}
}