{
  "type": "Feature",
  "properties": {
    "gn:admin1_code":"86.0",
    "gn:admin2_code":"3016.0",
    "gn:admin3_code":"301603.0",
    "gn:asciiname":"Wiardunki",
    "gn:country_code":"PL",
    "gn:dem":77,
    "gn:feature_class":"P",
    "gn:feature_code":"PPL",
    "gn:name":"Wiardunki",
    "gn:population":0,
    "gn:timezone":"Europe/Warsaw",
    "iso:country":"PL",
    "name:fra_x_preferred":[
        "Wiardunki"
    ],
    "name:pol_x_preferred":[
        "Wiardunki"
    ],
    "name:ukr_x_preferred":[
        "\u0412\u044f\u0440\u0434\u0443\u043d\u043a\u0456"
    ],
    "wof:name":"Wiardunki",
    "wof:placetype":"locality"
},
  "geometry": {"coordinates":[16.88286,52.78451999999999],"type":"Point"}
}