{
  "type": "Feature",
  "properties": {
    "gn:population":1519,
    "iso:country":"PL",
    "name:ast_x_preferred":[
        "Bystra"
    ],
    "name:ceb_x_preferred":[
        "Bystra"
    ],
    "name:eng_x_preferred":[
        "Bystra"
    ],
    "name:fra_x_preferred":[
        "Bystra"
    ],
    "name:pol_x_preferred":[
        "Bystra"
    ],
    "name:ukr_x_preferred":[
        "\u0411\u0438\u0441\u0442\u0440\u0430"
    ],
    "qs:a0":"Rzeczpospolita Polska",
    "qs:a1":"*Malopolskie",
    "qs:a1r":"0",
    "qs:a2":"Gorlicki",
    "qs:adm0":"Rzeczpospolita Polska",
    "qs:la_lc":"*",
    "qs:level":"locality",
    "qs:loc":"Bystra",
    "qs:loc_alt":"Bystra",
    "qs:pop":0,
    "qs:type":"buffered point",
    "wd:wordcount":76,
    "wof:name":"Bystra",
    "wof:placetype":"locality",
    "wof:population":1519
},
  "geometry": {"coordinates":[21.093839,49.655151],"type":"Point"}
}