{
  "type": "Feature",
  "properties": {
    "gn:admin1_code":"86.0",
    "gn:admin2_code":"3026.0",
    "gn:admin3_code":"302604.0",
    "gn:asciiname":"Grodzewo",
    "gn:country_code":"PL",
    "gn:dem":78,
    "gn:feature_class":"P",
    "gn:feature_code":"PPL",
    "gn:name":"Grodzewo",
    "gn:population":0,
    "gn:timezone":"Europe/Warsaw",
    "iso:country":"PL",
    "name:azb_x_preferred":[
        "\u0642\u0631\u0648\u0632\u0648\u0648"
    ],
    "name:fas_x_preferred":[
        "\u06af\u0631\u0648\u0632\u0648\u0648"
    ],
    "name:fra_x_preferred":[
        "Grodzewo"
    ],
    "name:nld_x_preferred":[
        "Grodzewo"
    ],
    "name:pol_x_preferred":[
        "Grodzewo"
    ],
    "name:ukr_x_preferred":[
        "\u0490\u0440\u043e\u0434\u0437\u0435\u0432\u043e"
    ],
    "wof:name":"Grodzewo",
    "wof:placetype":"locality"
},
  "geometry": {"coordinates":[17.13348,52.11524],"type":"Point"}
}