{
  "type": "Feature",
  "properties": {
    "gn:admin1_code":"75.0",
    "gn:admin2_code":"609.0",
    "gn:admin3_code":"60910.0",
    "gn:asciiname":"Kolonia Sobieszczany",
    "gn:country_code":"PL",
    "gn:dem":228,
    "gn:feature_class":"P",
    "gn:feature_code":"PPL",
    "gn:name":"Kolonia Sobieszczany",
    "gn:population":0,
    "gn:timezone":"Europe/Warsaw",
    "iso:country":"PL",
    "name:und_x_variant":[
        "Kolonja Sobieszczany",
        "Kolonia Sobieszczany",
        "Sobieszczany-Kolonia"
    ],
    "wof:name":"Kolonia Sobieszczany",
    "wof:placetype":"locality"
},
  "geometry": {"coordinates":[22.38371,51.06248],"type":"Point"}
}