{
  "type": "Feature",
  "properties": {
    "gn:admin1_code":"82.0",
    "gn:admin2_code":"2201.0",
    "gn:admin3_code":"220107.0",
    "gn:asciiname":"Bylina",
    "gn:country_code":"PL",
    "gn:dem":127,
    "gn:feature_class":"P",
    "gn:feature_code":"PPL",
    "gn:name":"Bylina",
    "gn:population":0,
    "gn:timezone":"Europe/Warsaw",
    "iso:country":"PL",
    "name:csb_x_preferred":[
        "B\u00ebl\u00ebno"
    ],
    "name:pol_x_preferred":[
        "Bylina"
    ],
    "name:ukr_x_preferred":[
        "\u0411\u0438\u043b\u0456\u043d\u0430"
    ],
    "wof:name":"Bylina",
    "wof:placetype":"locality"
},
  "geometry": {"coordinates":[17.61103,54.24666],"type":"Point"}
}