{
  "type": "Feature",
  "properties": {
    "gn:admin1_code":"85.0",
    "gn:admin2_code":"2802.0",
    "gn:admin3_code":"280205.0",
    "gn:asciiname":"Posady",
    "gn:country_code":"PL",
    "gn:dem":101,
    "gn:feature_class":"P",
    "gn:feature_code":"PPL",
    "gn:name":"Posady",
    "gn:population":0,
    "gn:timezone":"Europe/Warsaw",
    "iso:country":"PL",
    "name:und_x_variant":[
        "Palten",
        "Posady"
    ],
    "wof:name":"Posady",
    "wof:placetype":"locality"
},
  "geometry": {"coordinates":[20.07106,54.29676],"type":"Point"}
}