{
  "type": "Feature",
  "properties": {
    "gn:admin1_code":"85.0",
    "gn:admin2_code":"2802.0",
    "gn:admin3_code":"280205.0",
    "gn:asciiname":"Posady",
    "gn:country_code":"PL",
    "gn:dem":101,
    "gn:feature_class":"P",
    "gn:feature_code":"PPL",
    "gn:name":"Posady",
    "gn:population":0,
    "gn:timezone":"Europe/Warsaw",
    "iso:country":"PL",
    "name:fra_x_preferred":[
        "Posady"
    ],
    "name:pol_x_preferred":[
        "Posady"
    ],
    "name:ukr_x_preferred":[
        "\u041f\u043e\u0441\u0430\u0434\u0438"
    ],
    "name:und_x_variant":[
        "Palten"
    ],
    "wof:name":"Posady",
    "wof:placetype":"locality"
},
  "geometry": {"coordinates":[20.07106,54.29676],"type":"Point"}
}