{
  "type": "Feature",
  "properties": {
    "gn:admin1_code":"78.0",
    "gn:admin2_code":"1406.0",
    "gn:admin3_code":"140609.0",
    "gn:asciiname":"Cychry",
    "gn:country_code":"PL",
    "gn:dem":169,
    "gn:feature_class":"P",
    "gn:feature_code":"PPL",
    "gn:name":"Cychry",
    "gn:population":0,
    "gn:timezone":"Europe/Warsaw",
    "iso:country":"PL",
    "name:fra_x_preferred":[
        "Cychry"
    ],
    "name:pol_x_preferred":[
        "Cychry"
    ],
    "name:ukr_x_preferred":[
        "\u0426\u0438\u0445\u0440\u0438"
    ],
    "wof:name":"Cychry",
    "wof:placetype":"locality"
},
  "geometry": {"coordinates":[20.65537,51.89026],"type":"Point"}
}