{
  "type": "Feature",
  "properties": {
    "gn:admin1_code":"74.0",
    "gn:admin2_code":"1009.0",
    "gn:admin3_code":"100905.0",
    "gn:asciiname":"Kolonia Suchowola",
    "gn:country_code":"PL",
    "gn:dem":207,
    "gn:feature_class":"P",
    "gn:feature_code":"PPL",
    "gn:name":"Kolonia Suchowola",
    "gn:population":0,
    "gn:timezone":"Europe/Warsaw",
    "iso:country":"PL",
    "name:fra_x_preferred":[
        "Suchowola-Maj\u0105tek"
    ],
    "name:pol_x_preferred":[
        "Kolonia Suchowola"
    ],
    "wof:name":"Kolonia Suchowola",
    "wof:placetype":"locality"
},
  "geometry": {"coordinates":[19.08738,51.19323],"type":"Point"}
}