{
  "type": "Feature",
  "properties": {
    "gn:admin1_code":"75.0",
    "gn:admin2_code":"601.0",
    "gn:admin3_code":"60103.0",
    "gn:asciiname":"Jazwiny",
    "gn:country_code":"PL",
    "gn:dem":145,
    "gn:feature_class":"P",
    "gn:feature_code":"PPL",
    "gn:name":"Ja\u017awiny",
    "gn:population":0,
    "gn:timezone":"Europe/Warsaw",
    "iso:country":"PL",
    "name:ceb_x_preferred":[
        "Ja\u017awiny"
    ],
    "name:fra_x_preferred":[
        "Ja\u017awiny"
    ],
    "name:lit_x_preferred":[
        "Ja\u017evinai"
    ],
    "name:pol_x_preferred":[
        "Ja\u017awiny"
    ],
    "name:ukr_x_preferred":[
        "\u042f\u0437\u044c\u0432\u0456\u043d\u0438"
    ],
    "wof:name":"Jazwiny",
    "wof:placetype":"locality"
},
  "geometry": {"coordinates":[23.03082,51.9884],"type":"Point"}
}