{
  "type": "Feature",
  "properties": {
    "gn:admin1_code":"78.0",
    "gn:admin2_code":"1426.0",
    "gn:admin3_code":"142606.0",
    "gn:asciiname":"Podawce",
    "gn:country_code":"PL",
    "gn:dem":167,
    "gn:feature_class":"P",
    "gn:feature_code":"PPL",
    "gn:name":"Podawce",
    "gn:population":0,
    "gn:timezone":"Europe/Warsaw",
    "iso:country":"PL",
    "name:azb_x_preferred":[
        "\u067e\u0648\u062f\u0627\u0648\u062a\u0633\u0647"
    ],
    "name:ceb_x_preferred":[
        "Podawce"
    ],
    "name:fas_x_preferred":[
        "\u067e\u0648\u062f\u0627\u0648\u062a\u0633\u0647"
    ],
    "name:fra_x_preferred":[
        "Podawce"
    ],
    "name:lit_x_preferred":[
        "Podavc\u0117"
    ],
    "name:pol_x_preferred":[
        "Podawce"
    ],
    "name:szl_x_preferred":[
        "Podawce"
    ],
    "name:ukr_x_preferred":[
        "\u041f\u043e\u0434\u0430\u0432\u0446\u0435"
    ],
    "wof:name":"Podawce",
    "wof:placetype":"locality"
},
  "geometry": {"coordinates":[22.46318,52.29153],"type":"Point"}
}