{
  "type": "Feature",
  "properties": {
    "gn:admin1_code":"80.0",
    "gn:admin2_code":"1809.0",
    "gn:admin3_code":"180908.0",
    "gn:asciiname":"Mielniki",
    "gn:country_code":"PL",
    "gn:dem":194,
    "gn:feature_class":"P",
    "gn:feature_code":"PPL",
    "gn:name":"Mielniki",
    "gn:population":0,
    "gn:timezone":"Europe/Warsaw",
    "iso:country":"PL",
    "name:pol_x_preferred":[
        "Mielniki"
    ],
    "name:und_x_variant":[
        "Melniki"
    ],
    "wof:name":"Mielniki",
    "wof:placetype":"locality"
},
  "geometry": {"coordinates":[23.05526,49.98943],"type":"Point"}
}