{
  "type": "Feature",
  "properties": {
    "gn:admin1_code":"82.0",
    "gn:admin2_code":"2212.0",
    "gn:admin3_code":"221209.0",
    "gn:asciiname":"Zelazo",
    "gn:country_code":"PL",
    "gn:dem":8,
    "gn:feature_class":"P",
    "gn:feature_code":"PPL",
    "gn:name":"\u017belazo",
    "gn:population":0,
    "gn:timezone":"Europe/Warsaw",
    "iso:country":"PL",
    "name:deu_x_historical":[
        "Selesen"
    ],
    "name:deu_x_preferred":[
        "Selesen"
    ],
    "wof:name":"Zelazo",
    "wof:placetype":"locality"
},
  "geometry": {"coordinates":[17.2554,54.6497],"type":"Point"}
}