{
  "type": "Feature",
  "properties": {
    "gn:admin1_code":"86.0",
    "gn:admin2_code":"3023.0",
    "gn:admin3_code":"302303.0",
    "gn:asciiname":"Linowiec",
    "gn:country_code":"PL",
    "gn:dem":105,
    "gn:feature_class":"P",
    "gn:feature_code":"PPL",
    "gn:name":"Linowiec",
    "gn:population":0,
    "gn:timezone":"Europe/Warsaw",
    "iso:country":"PL",
    "name:fra_x_preferred":[
        "Lin\u00f3wiec"
    ],
    "name:pol_x_preferred":[
        "Lin\u00f3wiec"
    ],
    "name:ukr_x_preferred":[
        "\u041b\u0456\u043d\u0443\u0432\u0435\u0446\u044c"
    ],
    "wof:name":"Linowiec",
    "wof:placetype":"locality"
},
  "geometry": {"coordinates":[18.08857,52.5079],"type":"Point"}
}