{
  "type": "Feature",
  "properties": {
    "gn:admin1_code":"86.0",
    "gn:admin2_code":"3024.0",
    "gn:admin3_code":"302406.0",
    "gn:asciiname":"Nojewo",
    "gn:country_code":"PL",
    "gn:dem":87,
    "gn:feature_class":"P",
    "gn:feature_code":"PPL",
    "gn:name":"Nojewo",
    "gn:population":0,
    "gn:timezone":"Europe/Warsaw",
    "iso:country":"PL",
    "name:ceb_x_preferred":[
        "Nojewo"
    ],
    "name:fra_x_preferred":[
        "Nojewo"
    ],
    "name:pol_x_preferred":[
        "Nojewo"
    ],
    "name:ukr_x_preferred":[
        "\u041d\u043e\u0454\u0432\u043e"
    ],
    "wof:name":"Nojewo",
    "wof:placetype":"locality"
},
  "geometry": {"coordinates":[16.31219,52.60638],"type":"Point"}
}