{
  "type": "Feature",
  "properties": {
    "gn:admin1_code":"76.0",
    "gn:admin2_code":"809.0",
    "gn:admin3_code":"80908.0",
    "gn:asciiname":"Radowice",
    "gn:country_code":"PL",
    "gn:dem":64,
    "gn:feature_class":"P",
    "gn:feature_code":"PPL",
    "gn:name":"Radowice",
    "gn:population":0,
    "gn:timezone":"Europe/Warsaw",
    "iso:country":"PL",
    "name:fra_x_preferred":[
        "Radowice"
    ],
    "name:pol_x_preferred":[
        "Radowice"
    ],
    "name:ukr_x_preferred":[
        "\u0420\u0430\u0434\u043e\u0432\u0456\u0446\u0435"
    ],
    "wof:name":"Radowice",
    "wof:placetype":"locality"
},
  "geometry": {"coordinates":[15.69363,52.04426],"type":"Point"}
}