{
  "type": "Feature",
  "properties": {
    "iso:country":"PL",
    "name:ceb_x_preferred":[
        "Nysa"
    ],
    "name:deu_x_preferred":[
        "Nysa"
    ],
    "name:ell_x_preferred":[
        "\u039d\u03cd\u03c3\u03c3\u03b1"
    ],
    "name:fas_x_preferred":[
        "\u0646\u06cc\u0633\u0627"
    ],
    "name:fra_x_preferred":[
        "Nysa"
    ],
    "name:hun_x_preferred":[
        "Nysa"
    ],
    "name:ita_x_preferred":[
        "Nysa"
    ],
    "name:lat_x_preferred":[
        "Nysa"
    ],
    "name:nds_x_preferred":[
        "Nysa"
    ],
    "name:nld_x_preferred":[
        "Nysa"
    ],
    "name:nor_x_preferred":[
        "Nysa"
    ],
    "name:pol_x_preferred":[
        "Nysa"
    ],
    "name:por_x_preferred":[
        "Nysa"
    ],
    "name:rus_x_preferred":[
        "\u041d\u044b\u0441\u0430"
    ],
    "name:slk_x_preferred":[
        "Nysa"
    ],
    "qs_pg:aaroncc":"PL",
    "qs_pg:name":"Nysa",
    "qs_pg:name_adm0":"Polska",
    "qs_pg:name_adm1":"Opolskie",
    "qs_pg:photos":680,
    "qs_pg:photos_1k":138,
    "qs_pg:photos_9k":3,
    "qs_pg:photos_9r":5,
    "qs_pg:photos_all":680,
    "qs_pg:photos_sr":8,
    "qs_pg:pop_sr":0,
    "qs_pg:qs_pg_placetype":"localadmin",
    "qs_pg:qs_pg_placetype_gp":"LocalAdmin",
    "qs_pg:woe_adm0":23424923,
    "woe:adm0_id":23424923,
    "woe:name_adm0":"Polska",
    "woe:name_adm1":"Opolskie",
    "woe:placetype":"LocalAdmin",
    "wof:name":"Nysa",
    "wof:placetype":"localadmin"
},
  "geometry": {"coordinates":[17.333738,50.474414],"type":"Point"}
}