{
  "type": "Feature",
  "properties": {
    "iso:country":"PL",
    "qs_pg:aaroncc":"PL",
    "qs_pg:name":"Nysa",
    "qs_pg:name_adm0":"Polska",
    "qs_pg:name_adm1":"Opolskie",
    "qs_pg:photos":680,
    "qs_pg:photos_1k":138,
    "qs_pg:photos_9k":3,
    "qs_pg:photos_9r":5,
    "qs_pg:photos_all":680,
    "qs_pg:photos_sr":8,
    "qs_pg:pop_sr":0,
    "qs_pg:qs_pg_placetype":"localadmin",
    "qs_pg:qs_pg_placetype_gp":"LocalAdmin",
    "qs_pg:woe_adm0":23424923,
    "woe:adm0_id":23424923,
    "woe:name_adm0":"Polska",
    "woe:name_adm1":"Opolskie",
    "woe:placetype":"LocalAdmin",
    "wof:name":"Nysa",
    "wof:placetype":"localadmin"
},
  "geometry": {"coordinates":[17.333738,50.474414],"type":"Point"}
}