{
  "type": "Feature",
  "properties": {
    "gn:admin1_code":"77.0",
    "gn:admin2_code":"1213.0",
    "gn:admin3_code":"121309.0",
    "gn:asciiname":"Smolice",
    "gn:country_code":"PL",
    "gn:dem":222,
    "gn:feature_class":"P",
    "gn:feature_code":"PPL",
    "gn:name":"Smolice",
    "gn:population":0,
    "gn:timezone":"Europe/Warsaw",
    "iso:country":"PL",
    "name:deu_x_preferred":[
        "Smolice"
    ],
    "name:pol_x_preferred":[
        "Smolice"
    ],
    "name:ukr_x_preferred":[
        "\u0421\u043c\u043e\u043b\u0456\u0446\u0435"
    ],
    "wof:name":"Smolice",
    "wof:placetype":"locality"
},
  "geometry": {"coordinates":[19.4573,50.02737],"type":"Point"}
}