{
  "type": "Feature",
  "properties": {
    "gn:admin1_code":"86.0",
    "gn:admin2_code":"3062.0",
    "gn:admin3_code":"306201.0",
    "gn:asciiname":"Grojec",
    "gn:country_code":"PL",
    "gn:dem":90,
    "gn:feature_class":"P",
    "gn:feature_code":"PPL",
    "gn:name":"Gr\u00f3jec",
    "gn:population":0,
    "gn:timezone":"Europe/Warsaw",
    "iso:country":"PL",
    "name:ceb_x_preferred":[
        "Grojec"
    ],
    "name:deu_x_preferred":[
        "Grojec"
    ],
    "name:fra_x_preferred":[
        "Grojec"
    ],
    "name:pol_x_preferred":[
        "Grojec"
    ],
    "name:ukr_x_preferred":[
        "\u0490\u0440\u043e\u0454\u0446\u044c"
    ],
    "wof:name":"Grojec",
    "wof:placetype":"neighbourhood"
},
  "geometry": {"coordinates":[18.31648,52.22296],"type":"Point"}
}