{
  "type": "Feature",
  "properties": {
    "gn:admin1_code":"74.0",
    "gn:admin2_code":"1002.0",
    "gn:admin3_code":"100202.0",
    "gn:asciiname":"Antoniew",
    "gn:country_code":"PL",
    "gn:dem":101,
    "gn:feature_class":"P",
    "gn:feature_code":"PPL",
    "gn:name":"Antoniew",
    "gn:population":0,
    "gn:timezone":"Europe/Warsaw",
    "iso:country":"PL",
    "name:fra_x_preferred":[
        "Antoniew"
    ],
    "name:pol_x_preferred":[
        "Antoniew"
    ],
    "name:ukr_x_preferred":[
        "\u0410\u043d\u0442\u043e\u043d\u0435\u0432"
    ],
    "wof:name":"Antoniew",
    "wof:placetype":"locality"
},
  "geometry": {"coordinates":[19.66209,52.17214],"type":"Point"}
}