{
  "type": "Feature",
  "properties": {
    "gn:admin1_code":"86.0",
    "gn:admin2_code":"3017.0",
    "gn:admin3_code":"301702.0",
    "gn:asciiname":"Gostyczyna",
    "gn:country_code":"PL",
    "gn:dem":131,
    "gn:feature_class":"P",
    "gn:feature_code":"PPL",
    "gn:name":"Gostyczyna",
    "gn:population":0,
    "gn:timezone":"Europe/Warsaw",
    "iso:country":"PL",
    "name:azb_x_preferred":[
        "\u0642\u0648\u0633\u062a\u0686\u0646\u0627"
    ],
    "name:fas_x_preferred":[
        "\u06af\u0648\u0633\u062a\u0686\u0646\u0627"
    ],
    "name:nld_x_preferred":[
        "Gostyczyna"
    ],
    "name:pol_x_preferred":[
        "Gostyczyna"
    ],
    "name:ukr_x_preferred":[
        "\u0490\u043e\u0441\u0442\u0438\u0447\u0438\u043d\u0430"
    ],
    "name:und_x_variant":[
        "Gustyczyna"
    ],
    "wof:name":"Gostyczyna",
    "wof:placetype":"locality"
},
  "geometry": {"coordinates":[18.07555,51.67672],"type":"Point"}
}