{
  "type": "Feature",
  "properties": {
    "gn:admin1_code":"86.0",
    "gn:admin2_code":"3017.0",
    "gn:admin3_code":"301705.0",
    "gn:asciiname":"Smardow",
    "gn:country_code":"PL",
    "gn:dem":138,
    "gn:feature_class":"P",
    "gn:feature_code":"PPL",
    "gn:name":"Smard\u00f3w",
    "gn:population":0,
    "gn:timezone":"Europe/Warsaw",
    "iso:country":"PL",
    "name:pol_x_preferred":[
        "Smard\u00f3w"
    ],
    "name:ukr_x_preferred":[
        "\u0421\u043c\u0430\u0440\u0434\u0443\u0432"
    ],
    "wof:name":"Smardow",
    "wof:placetype":"neighbourhood"
},
  "geometry": {"coordinates":[17.85587,51.60554000000001],"type":"Point"}
}