{
  "type": "Feature",
  "properties": {
    "gn:admin1_code":"85.0",
    "gn:admin2_code":"2815.0",
    "gn:admin3_code":"281508.0",
    "gn:asciiname":"Winiec",
    "gn:cc2":"PL",
    "gn:country_code":"PL",
    "gn:dem":98,
    "gn:feature_class":"P",
    "gn:feature_code":"PPL",
    "gn:name":"Winiec",
    "gn:population":0,
    "gn:timezone":"Europe/Warsaw",
    "iso:country":"PL",
    "name:und_x_variant":[
        "Wieniec",
        "Winkenhagen",
        "Winiec"
    ],
    "wof:name":"Winiec",
    "wof:placetype":"locality"
},
  "geometry": {"coordinates":[19.85,53.81667],"type":"Point"}
}