{
  "type": "Feature",
  "properties": {
    "gn:admin1_code":"82.0",
    "gn:admin2_code":"2211.0",
    "gn:admin3_code":"221106.0",
    "gn:asciiname":"Klanino",
    "gn:country_code":"PL",
    "gn:dem":29,
    "gn:feature_class":"P",
    "gn:feature_code":"PPL",
    "gn:name":"K\u0142anino",
    "gn:population":0,
    "gn:timezone":"Europe/Warsaw",
    "iso:country":"PL",
    "name:ceb_x_preferred":[
        "K\u0142anino"
    ],
    "name:csb_x_preferred":[
        "K\u0142anino"
    ],
    "name:fra_x_preferred":[
        "K\u0142anino"
    ],
    "name:pol_x_preferred":[
        "K\u0142anino"
    ],
    "name:ukr_x_preferred":[
        "\u041a\u043b\u0430\u043d\u0456\u043d\u043e"
    ],
    "wof:name":"Klanino",
    "wof:placetype":"locality"
},
  "geometry": {"coordinates":[18.24636,54.76436],"type":"Point"}
}