{
  "type": "Feature",
  "properties": {
    "gn:admin1_code":"75.0",
    "gn:admin2_code":"603.0",
    "gn:admin3_code":"60307.0",
    "gn:asciiname":"Teresin",
    "gn:country_code":"PL",
    "gn:dem":249,
    "gn:feature_class":"P",
    "gn:feature_code":"PPL",
    "gn:name":"Teresin",
    "gn:population":0,
    "gn:timezone":"Europe/Warsaw",
    "iso:country":"PL",
    "name:fra_x_preferred":[
        "Teresin"
    ],
    "name:pol_x_preferred":[
        "Teresin"
    ],
    "name:ukr_x_preferred":[
        "\u0422\u0435\u0440\u0435\u0441\u0456\u043d"
    ],
    "wof:name":"Teresin",
    "wof:placetype":"locality"
},
  "geometry": {"coordinates":[23.55014,50.97178],"type":"Point"}
}