{
  "type": "Feature",
  "properties": {
    "iso:country":"PL",
    "wof:name":"Nad Nerem",
    "wof:placetype":"neighbourhood"
},
  "geometry": {"coordinates":[19.3842376569505,51.71026964440568],"type":"Point"}
}