{
  "type": "Feature",
  "properties": {
    "gn:admin1_code":"86.0",
    "gn:admin2_code":"3009.0",
    "gn:admin3_code":"300910.0",
    "gn:asciiname":"Smulniki Racieckie",
    "gn:country_code":"PL",
    "gn:dem":91,
    "gn:feature_class":"P",
    "gn:feature_code":"PPL",
    "gn:name":"Smulniki Raci\u0119ckie",
    "gn:population":0,
    "gn:timezone":"Europe/Warsaw",
    "iso:country":"PL",
    "wof:name":"Smulniki Racieckie",
    "wof:placetype":"locality"
},
  "geometry": {"coordinates":[18.50685,52.26549],"type":"Point"}
}