{
  "type": "Feature",
  "properties": {
    "gn:country":"PL",
    "gn:fcode":"PPLA3",
    "gn:population":4340,
    "iso:country":"PL",
    "name:bul_x_preferred":[
        "\u0421\u043b\u043e\u043c\u043d\u0438\u043a\u0438"
    ],
    "name:epo_x_preferred":[
        "S\u0142omniki"
    ],
    "name:est_x_preferred":[
        "S\u0142omniki"
    ],
    "name:fra_x_preferred":[
        "S\u0142omniki"
    ],
    "name:heb_x_preferred":[
        "\u05e1\u05dc\u05d5\u05de\u05e0\u05d9\u05e7\u05d9"
    ],
    "name:jav_x_preferred":[
        "S\u0142omniki"
    ],
    "name:lav_x_preferred":[
        "Slom\u0146iki"
    ],
    "name:msa_x_preferred":[
        "S\u0142omniki"
    ],
    "name:nld_x_preferred":[
        "S\u0142omniki"
    ],
    "name:pol_x_preferred":[
        "S\u0142omniki"
    ],
    "name:por_x_preferred":[
        "S\u0142omniki"
    ],
    "name:ron_x_preferred":[
        "S\u0142omniki"
    ],
    "name:rus_x_preferred":[
        "\u0421\u043b\u043e\u043c\u043d\u0438\u043a\u0438"
    ],
    "name:slk_x_preferred":[
        "S\u0142omniki"
    ],
    "name:srp_x_preferred":[
        "\u0421\u043b\u043e\u043c\u045a\u0438\u043a\u0438"
    ],
    "name:ukr_x_preferred":[
        "\u0421\u043b\u043e\u043c\u043d\u0438\u043a\u0438"
    ],
    "name:vie_x_preferred":[
        "S\u0142omniki"
    ],
    "qs_pg:aaroncc":"PL",
    "qs_pg:gn_country":"PL",
    "qs_pg:gn_fcode":"PPLA3",
    "qs_pg:gn_pop":4340,
    "qs_pg:name":"S\u0142omniki",
    "qs_pg:name_adm0":"Polska",
    "qs_pg:name_adm1":"Ma\u0142opolskie",
    "qs_pg:photos":1,
    "qs_pg:photos_1k":1,
    "qs_pg:photos_9k":1,
    "qs_pg:photos_9r":1,
    "qs_pg:photos_all":1,
    "qs_pg:photos_sr":1,
    "qs_pg:pop_sr":6,
    "qs_pg:qs_pg_placetype":"localadmin",
    "qs_pg:qs_pg_placetype_gp":"LocalAdmin",
    "qs_pg:woe_adm0":23424923,
    "woe:adm0_id":23424923,
    "woe:name_adm0":"Polska",
    "woe:name_adm1":"Ma\u0142opolskie",
    "woe:placetype":"LocalAdmin",
    "wof:name":"S\u0142omniki",
    "wof:placetype":"localadmin",
    "wof:population":4340
},
  "geometry": {"coordinates":[20.08224,50.24012],"type":"Point"}
}