{
  "type": "Feature",
  "properties": {
    "gn:admin1_code":"78.0",
    "gn:admin2_code":"1428.0",
    "gn:admin3_code":"142803.0",
    "gn:asciiname":"Pieczyska Ilowskie",
    "gn:country_code":"PL",
    "gn:dem":63,
    "gn:feature_class":"P",
    "gn:feature_code":"PPL",
    "gn:name":"Pieczyska I\u0142owskie",
    "gn:population":0,
    "gn:timezone":"Europe/Warsaw",
    "iso:country":"PL",
    "name:fra_x_preferred":[
        "Pieczyska I\u0142owskie"
    ],
    "name:pol_x_preferred":[
        "Pieczyska I\u0142owskie"
    ],
    "name:ukr_x_preferred":[
        "\u041f\u0435\u0447\u0438\u0441\u044c\u043a\u0430-\u0406\u043b\u043e\u0432\u0441\u044c\u043a\u0435"
    ],
    "wof:name":"Pieczyska Ilowskie",
    "wof:placetype":"locality"
},
  "geometry": {"coordinates":[20.01687,52.37319],"type":"Point"}
}