{
  "type": "Feature",
  "properties": {
    "gn:admin1_code":"75.0",
    "gn:admin2_code":"615.0",
    "gn:admin3_code":"61502.0",
    "gn:asciiname":"Tchorzewek",
    "gn:country_code":"PL",
    "gn:dem":132,
    "gn:feature_class":"P",
    "gn:feature_code":"PPL",
    "gn:name":"Tch\u00f3rzewek",
    "gn:population":0,
    "gn:timezone":"Europe/Warsaw",
    "iso:country":"PL",
    "wof:name":"Tchorzewek",
    "wof:placetype":"locality"
},
  "geometry": {"coordinates":[22.55,51.71667],"type":"Point"}
}