{
  "type": "Feature",
  "properties": {
    "gn:admin1_code":"73.0",
    "gn:admin2_code":"409.0",
    "gn:admin3_code":"40904.0",
    "gn:asciiname":"Stodoly",
    "gn:country_code":"PL",
    "gn:dem":92,
    "gn:feature_class":"P",
    "gn:feature_code":"PPL",
    "gn:name":"Stodo\u0142y",
    "gn:population":0,
    "gn:timezone":"Europe/Warsaw",
    "iso:country":"PL",
    "name:ceb_x_preferred":[
        "Stodo\u0142y"
    ],
    "name:pol_x_preferred":[
        "Stodo\u0142y"
    ],
    "name:ukr_x_preferred":[
        "\u0421\u0442\u043e\u0434\u043e\u043b\u0438"
    ],
    "name:und_x_variant":[
        "Stodo\u0142y"
    ],
    "wof:name":"Stodoly",
    "wof:placetype":"locality"
},
  "geometry": {"coordinates":[18.22813,52.65038000000001],"type":"Point"}
}