{
  "type": "Feature",
  "properties": {
    "gn:admin1_code":"78.0",
    "gn:admin2_code":"1412.0",
    "gn:admin3_code":"141215.0",
    "gn:asciiname":"Milosna",
    "gn:cc2":"PL",
    "gn:country_code":"PL",
    "gn:dem":108,
    "gn:feature_class":"P",
    "gn:feature_code":"PPL",
    "gn:name":"Mi\u0142osna",
    "gn:population":0,
    "gn:timezone":"Europe/Warsaw",
    "iso:country":"PL",
    "name:und_x_variant":[
        "Cech\u00f3wka"
    ],
    "wof:name":"Milosna",
    "wof:placetype":"neighbourhood"
},
  "geometry": {"coordinates":[21.30335,52.23968],"type":"Point"}
}