{
  "type": "Feature",
  "properties": {
    "gn:admin1_code":"78.0",
    "gn:admin2_code":"1413.0",
    "gn:admin3_code":"141306.0",
    "gn:asciiname":"Zdroje",
    "gn:country_code":"PL",
    "gn:dem":133,
    "gn:feature_class":"P",
    "gn:feature_code":"PPL",
    "gn:name":"Zdroje",
    "gn:population":0,
    "gn:timezone":"Europe/Warsaw",
    "iso:country":"PL",
    "name:fra_x_preferred":[
        "Zdroje"
    ],
    "name:pol_x_preferred":[
        "Zdroje"
    ],
    "name:ukr_x_preferred":[
        "\u0417\u0434\u0440\u043e\u0454"
    ],
    "wof:name":"Zdroje",
    "wof:placetype":"locality"
},
  "geometry": {"coordinates":[20.39273,53.03061],"type":"Point"}
}