{
  "type": "Feature",
  "properties": {
    "gn:admin1_code":"74.0",
    "gn:admin2_code":"1018.0",
    "gn:admin3_code":"101803.0",
    "gn:asciiname":"Konaty",
    "gn:country_code":"PL",
    "gn:dem":158,
    "gn:feature_class":"P",
    "gn:feature_code":"PPL",
    "gn:name":"Konaty",
    "gn:population":0,
    "gn:timezone":"Europe/Warsaw",
    "iso:country":"PL",
    "name:pol_x_preferred":[
        "Konaty"
    ],
    "wof:name":"Konaty",
    "wof:placetype":"locality"
},
  "geometry": {"coordinates":[18.30123,51.37916],"type":"Point"}
}