{
  "type": "Feature",
  "properties": {
    "gn:country":"PL",
    "gn:fcode":"PPL",
    "gn:population":0,
    "iso:country":"PL",
    "name:ast_x_preferred":[
        "Ewelin"
    ],
    "name:azb_x_preferred":[
        "\u0627\u0648\u0644\u06cc\u0646"
    ],
    "name:deu_x_preferred":[
        "Ewelin"
    ],
    "name:eng_x_preferred":[
        "Ewelin"
    ],
    "name:fas_x_preferred":[
        "\u0627\u0648\u0644\u06cc\u0646"
    ],
    "name:fra_x_preferred":[
        "Ewelin"
    ],
    "name:nan_x_preferred":[
        "Ewelin"
    ],
    "name:nld_x_preferred":[
        "Ewelin"
    ],
    "name:pol_x_preferred":[
        "Ewelin"
    ],
    "name:spa_x_preferred":[
        "Ewelin"
    ],
    "name:ukr_x_preferred":[
        "\u0415\u0432\u0435\u043b\u0456\u043d"
    ],
    "qs_pg:aaroncc":"PL",
    "qs_pg:gn_country":"PL",
    "qs_pg:gn_fcode":"PPL",
    "qs_pg:gn_pop":0,
    "qs_pg:name":"Ewelin",
    "qs_pg:name_adm0":"Polska",
    "qs_pg:name_adm1":"Mazowieckie",
    "qs_pg:photos_9k":1,
    "qs_pg:photos_9r":1,
    "qs_pg:photos_all":1,
    "qs_pg:photos_sr":0,
    "qs_pg:pop_sr":0,
    "qs_pg:qs_pg_placetype":"locality",
    "qs_pg:qs_pg_placetype_gp":"Town",
    "qs_pg:woe_adm0":23424923,
    "woe:adm0_id":23424923,
    "woe:name_adm0":"Polska",
    "woe:name_adm1":"Mazowieckie",
    "woe:placetype":"Town",
    "wof:name":"Ewelin",
    "wof:placetype":"locality"
},
  "geometry": {"coordinates":[21.51881,51.88476],"type":"Point"}
}