{
  "type": "Feature",
  "properties": {
    "gn:admin1_code":"75.0",
    "gn:admin2_code":"609.0",
    "gn:admin3_code":"60909.0",
    "gn:asciiname":"Krzczonow-Wojtostwo",
    "gn:cc2":"PL",
    "gn:country_code":"PL",
    "gn:dem":260,
    "gn:feature_class":"P",
    "gn:feature_code":"PPL",
    "gn:name":"Krzczon\u00f3w-W\u00f3jtostwo",
    "gn:population":0,
    "gn:timezone":"Europe/Warsaw",
    "iso:country":"PL",
    "name:und_x_variant":[
        "Krzczon\u00f3w",
        "Krzczon\u00f3w-W\u00f3jtostwo"
    ],
    "wof:name":"Krzczonow-Wojtostwo",
    "wof:placetype":"locality"
},
  "geometry": {"coordinates":[22.70565,51.01451],"type":"Point"}
}