{
  "type": "Feature",
  "properties": {
    "gn:gn_country":"PL",
    "gn:gn_fcode":"ADM3",
    "gn:gn_pop":0,
    "iso:country":"PL",
    "name:pol_x_preferred":[
        "Gniezno"
    ],
    "qs_pg:aaroncc":"PL",
    "qs_pg:gn_country":"PL",
    "qs_pg:gn_fcode":"ADM3",
    "qs_pg:gn_pop":0,
    "qs_pg:name":"Gniezno",
    "qs_pg:photos_9r":0,
    "qs_pg:photos_sr":0,
    "qs_pg:pop_sr":0,
    "qs_pg:qs_pg_placetype":"localadmin",
    "wof:name":"Gniezno",
    "wof:placetype":"localadmin"
},
  "geometry": {"coordinates":[17.6302,52.5687],"type":"Point"}
}