{
  "type": "Feature",
  "properties": {
    "gn:admin1_code":"81.0",
    "gn:admin2_code":"2012.0",
    "gn:admin3_code":"201204.0",
    "gn:asciiname":"Przerosl Nowa",
    "gn:country_code":"PL",
    "gn:dem":206,
    "gn:feature_class":"P",
    "gn:feature_code":"PPL",
    "gn:name":"Przero\u015bl Nowa",
    "gn:population":0,
    "gn:timezone":"Europe/Warsaw",
    "iso:country":"PL",
    "name:lit_x_preferred":[
        "Nova Prieraslis"
    ],
    "name:pol_x_preferred":[
        "Nowa Przero\u015bl"
    ],
    "name:ukr_x_preferred":[
        "\u041d\u043e\u0432\u0430 \u041f\u0448\u0435\u0440\u043e\u0441\u043b\u044c"
    ],
    "wof:name":"Przerosl Nowa",
    "wof:placetype":"locality"
},
  "geometry": {"coordinates":[22.63433,54.26507],"type":"Point"}
}