{
  "type": "Feature",
  "properties": {
    "gn:admin1_code":"76.0",
    "gn:admin2_code":"806.0",
    "gn:admin3_code":"80604.0",
    "gn:asciiname":"Gilow",
    "gn:country_code":"PL",
    "gn:dem":92,
    "gn:feature_class":"P",
    "gn:feature_code":"PPL",
    "gn:name":"Gil\u00f3w",
    "gn:population":0,
    "gn:timezone":"Europe/Warsaw",
    "iso:country":"PL",
    "wof:name":"Gilow",
    "wof:placetype":"locality"
},
  "geometry": {"coordinates":[15.5496,52.99789000000001],"type":"Point"}
}