{
  "type": "Feature",
  "properties": {
    "gn:admin1_code":"74.0",
    "gn:admin2_code":"1061.0",
    "gn:admin3_code":"106101.0",
    "gn:asciiname":"Olechow-Janow",
    "gn:country_code":"PL",
    "gn:dem":221,
    "gn:feature_class":"P",
    "gn:feature_code":"PPL",
    "gn:name":"Olech\u00f3w-Jan\u00f3w",
    "gn:population":0,
    "gn:timezone":"Europe/Warsaw",
    "iso:country":"PL",
    "wof:name":"Olechow-Janow",
    "wof:placetype":"neighbourhood"
},
  "geometry": {"coordinates":[19.567,51.7494],"type":"Point"}
}