{
  "type": "Feature",
  "properties": {
    "gn:admin1_code":"85.0",
    "gn:admin2_code":"2816.0",
    "gn:admin3_code":"281603.0",
    "gn:asciiname":"Jaskowo",
    "gn:country_code":"PL",
    "gn:dem":121,
    "gn:feature_class":"P",
    "gn:feature_code":"PPL",
    "gn:name":"Ja\u015bkowo",
    "gn:population":0,
    "gn:timezone":"Europe/Warsaw",
    "iso:country":"PL",
    "name:und_x_variant":[
        "Reiherswalde",
        "Jaschkowen",
        "Ja\u015bkowo"
    ],
    "wof:name":"Jaskowo",
    "wof:placetype":"locality"
},
  "geometry": {"coordinates":[21.66542,53.58189],"type":"Point"}
}