{
  "type": "Feature",
  "properties": {
    "gn:admin1_code":"86.0",
    "gn:admin2_code":"3061.0",
    "gn:admin3_code":"306101.0",
    "gn:asciiname":"Rajskow",
    "gn:country_code":"PL",
    "gn:dem":103,
    "gn:feature_class":"P",
    "gn:feature_code":"PPL",
    "gn:name":"Rajsk\u00f3w",
    "gn:population":0,
    "gn:timezone":"Europe/Warsaw",
    "iso:country":"PL",
    "wof:name":"Rajskow",
    "wof:placetype":"locality"
},
  "geometry": {"coordinates":[18.1157,51.74542],"type":"Point"}
}