{
  "type": "Feature",
  "properties": {
    "iso:country":"PL",
    "name:pol_x_preferred":[
        "\u0141obz\u00f3w"
    ],
    "wof:name":"Lobzow",
    "wof:placetype":"neighbourhood"
},
  "geometry": {"coordinates":[19.91156715478339,50.074826966909],"type":"Point"}
}