{
  "type": "Feature",
  "properties": {
    "gn:admin1_code":"77.0",
    "gn:admin2_code":"1261.0",
    "gn:admin3_code":"126101.0",
    "gn:asciiname":"Lobzow",
    "gn:country_code":"PL",
    "gn:dem":213,
    "gn:feature_class":"P",
    "gn:feature_code":"PPL",
    "gn:name":"\u0141obz\u00f3w",
    "gn:population":0,
    "gn:timezone":"Europe/Warsaw",
    "iso:country":"PL",
    "name:pol_x_preferred":[
        "\u0141obz\u00f3w"
    ],
    "wof:name":"Lobzow",
    "wof:placetype":"neighbourhood"
},
  "geometry": {"coordinates":[19.911567,50.074827],"type":"Point"}
}