{
  "type": "Feature",
  "properties": {
    "gn:admin1_code":"75.0",
    "gn:admin2_code":"601.0",
    "gn:admin3_code":"60111.0",
    "gn:asciiname":"Wolka Koscieniewicka",
    "gn:country_code":"PL",
    "gn:dem":143,
    "gn:feature_class":"P",
    "gn:feature_code":"PPL",
    "gn:name":"W\u00f3lka Ko\u015bcieniewicka",
    "gn:population":0,
    "gn:timezone":"Europe/Warsaw",
    "iso:country":"PL",
    "name:fra_x_preferred":[
        "W\u00f3lka Ko\u015bcieniewicka"
    ],
    "name:lit_x_preferred":[
        "Vulka Ko\u0161cenevicka"
    ],
    "name:pol_x_preferred":[
        "W\u00f3lka Ko\u015bcieniewicka"
    ],
    "name:ukr_x_preferred":[
        "\u0412\u0443\u043b\u044c\u043a\u0430-\u041a\u043e\u0441\u044c\u0446\u0435\u043d\u0435\u0432\u0456\u0446\u044c\u043a\u0430"
    ],
    "name:und_x_variant":[
        "Ko\u015bcieniewicka W\u00f3lka"
    ],
    "wof:name":"Wolka Koscieniewicka",
    "wof:placetype":"locality"
},
  "geometry": {"coordinates":[23.33762,51.9322],"type":"Point"}
}