{
  "type": "Feature",
  "properties": {
    "gn:country":"PL",
    "gn:fcode":"PPL",
    "gn:population":710,
    "iso:country":"PL",
    "name:ast_x_preferred":[
        "Mikoszewo"
    ],
    "name:ceb_x_preferred":[
        "Mikoszewo"
    ],
    "name:ces_x_preferred":[
        "Mikoszewo"
    ],
    "name:che_x_preferred":[
        "\u041c\u0438\u043a\u043e\u0448\u0435\u0432\u043e"
    ],
    "name:deu_x_preferred":[
        "Mikoszewo"
    ],
    "name:eng_x_preferred":[
        "Mikoszewo"
    ],
    "name:fra_x_preferred":[
        "Mikoszewo"
    ],
    "name:ita_x_preferred":[
        "Mikoszewo"
    ],
    "name:nan_x_preferred":[
        "Mikoszewo"
    ],
    "name:nld_x_preferred":[
        "Mikoszewo"
    ],
    "name:pol_x_preferred":[
        "Mikoszewo"
    ],
    "name:szl_x_preferred":[
        "Mikoszewo"
    ],
    "name:tat_x_preferred":[
        "\u041c\u0438\u043a\u043e\u0448\u0435\u0432\u043e"
    ],
    "name:ukr_x_preferred":[
        "\u041c\u0456\u043a\u043e\u0448\u0435\u0432\u043e"
    ],
    "name:und_x_variant":[
        "Nickelswalde"
    ],
    "qs_pg:aaroncc":"PL",
    "qs_pg:gn_country":"PL",
    "qs_pg:gn_fcode":"PPL",
    "qs_pg:gn_pop":710,
    "qs_pg:name":"Mikoszewo",
    "qs_pg:name_adm0":"Polska",
    "qs_pg:name_adm1":"Pomorskie",
    "qs_pg:photos":33,
    "qs_pg:photos_1k":7,
    "qs_pg:photos_9k":1,
    "qs_pg:photos_9r":2,
    "qs_pg:photos_all":33,
    "qs_pg:photos_sr":2,
    "qs_pg:pop_sr":2,
    "qs_pg:qs_pg_placetype":"locality",
    "qs_pg:qs_pg_placetype_gp":"Town",
    "qs_pg:woe_adm0":23424923,
    "woe:adm0_id":23424923,
    "woe:name_adm0":"Polska",
    "woe:name_adm1":"Pomorskie",
    "woe:placetype":"Town",
    "wof:name":"Mikoszewo",
    "wof:placetype":"locality",
    "wof:population":710
},
  "geometry": {"coordinates":[18.96679,54.33344],"type":"Point"}
}