{
  "type": "Feature",
  "properties": {
    "gn:admin1_code":"82.0",
    "gn:admin2_code":"2201.0",
    "gn:admin3_code":"220103.0",
    "gn:asciiname":"Lupawsko",
    "gn:country_code":"PL",
    "gn:dem":119,
    "gn:feature_class":"P",
    "gn:feature_code":"PPL",
    "gn:name":"\u0141upawsko",
    "gn:population":0,
    "gn:timezone":"Europe/Warsaw",
    "iso:country":"PL",
    "name:csb_x_preferred":[
        "\u0141\u00ebpawsk\u00f2"
    ],
    "name:nld_x_preferred":[
        "\u0141upawsko"
    ],
    "name:pol_x_preferred":[
        "\u0141upawsko"
    ],
    "name:ukr_x_preferred":[
        "\u041b\u0443\u043f\u0430\u0432\u0441\u044c\u043a\u043e"
    ],
    "wof:name":"Lupawsko",
    "wof:placetype":"locality"
},
  "geometry": {"coordinates":[17.58911,54.27655],"type":"Point"}
}