{
  "type": "Feature",
  "properties": {
    "gn:admin1_code":"85.0",
    "gn:admin2_code":"2817.0",
    "gn:admin3_code":"281705.0",
    "gn:asciiname":"Faryny",
    "gn:country_code":"PL",
    "gn:dem":143,
    "gn:feature_class":"P",
    "gn:feature_code":"PPL",
    "gn:name":"Faryny",
    "gn:population":0,
    "gn:timezone":"Europe/Warsaw",
    "iso:country":"PL",
    "name:ceb_x_preferred":[
        "Faryny"
    ],
    "name:pol_x_preferred":[
        "Faryny"
    ],
    "name:ukr_x_preferred":[
        "\u0424\u0430\u0440\u0438\u043d\u0438"
    ],
    "name:und_x_variant":[
        "Farienen"
    ],
    "wof:name":"Faryny",
    "wof:placetype":"locality"
},
  "geometry": {"coordinates":[21.38751,53.52999000000001],"type":"Point"}
}