{
  "type": "Feature",
  "properties": {
    "gn:admin1_code":"80.0",
    "gn:admin2_code":"1809.0",
    "gn:admin3_code":"180908.0",
    "gn:asciiname":"Kobylnica Woloska",
    "gn:country_code":"PL",
    "gn:dem":206,
    "gn:feature_class":"P",
    "gn:feature_code":"PPL",
    "gn:name":"Kobylnica Wo\u0142oska",
    "gn:population":0,
    "gn:timezone":"Europe/Warsaw",
    "iso:country":"PL",
    "name:pol_x_preferred":[
        "Kobylnica Wo\u0142oska"
    ],
    "name:ukr_x_preferred":[
        "\u041a\u043e\u0431\u0438\u043b\u044c\u043d\u0438\u0446\u044f \u0412\u043e\u043b\u043e\u0441\u044c\u043a\u0430"
    ],
    "wof:name":"Kobylnica Woloska",
    "wof:placetype":"locality"
},
  "geometry": {"coordinates":[23.10525,50.00384],"type":"Point"}
}