{
  "type": "Feature",
  "properties": {
    "gn:admin1_code":"77.0",
    "gn:admin2_code":"1210.0",
    "gn:admin3_code":"121010.0",
    "gn:asciiname":"Swidnik",
    "gn:country_code":"PL",
    "gn:dem":340,
    "gn:feature_class":"P",
    "gn:feature_code":"PPL",
    "gn:name":"\u015awidnik",
    "gn:population":0,
    "gn:timezone":"Europe/Warsaw",
    "iso:country":"PL",
    "name:pol_x_preferred":[
        "\u015awidnik"
    ],
    "name:ukr_x_preferred":[
        "\u0421\u044c\u0432\u0456\u0434\u043d\u0438\u043a"
    ],
    "wof:name":"Swidnik",
    "wof:placetype":"locality"
},
  "geometry": {"coordinates":[20.61361,49.71749000000001],"type":"Point"}
}