{
  "type": "Feature",
  "properties": {
    "gn:admin1_code":"78.0",
    "gn:admin2_code":"1434.0",
    "gn:admin3_code":"143410.0",
    "gn:asciiname":"Szamocin",
    "gn:country_code":"PL",
    "gn:dem":133,
    "gn:feature_class":"P",
    "gn:feature_code":"PPL",
    "gn:name":"Szamocin",
    "gn:population":0,
    "gn:timezone":"Europe/Warsaw",
    "iso:country":"PL",
    "name:fra_x_preferred":[
        "Szamocin"
    ],
    "name:pol_x_preferred":[
        "Szamocin"
    ],
    "name:ukr_x_preferred":[
        "\u0428\u0430\u043c\u043e\u0446\u0438\u043d"
    ],
    "wof:name":"Szamocin",
    "wof:placetype":"locality"
},
  "geometry": {"coordinates":[21.71109,52.39923],"type":"Point"}
}