{
  "type": "Feature",
  "properties": {
    "gn:admin1_code":"81.0",
    "gn:admin2_code":"2014.0",
    "gn:admin3_code":"201405.0",
    "gn:asciiname":"Cieciorki",
    "gn:country_code":"PL",
    "gn:dem":118,
    "gn:feature_class":"P",
    "gn:feature_code":"PPL",
    "gn:name":"Cieciorki",
    "gn:population":0,
    "gn:timezone":"Europe/Warsaw",
    "iso:country":"PL",
    "wof:name":"Cieciorki",
    "wof:placetype":"locality"
},
  "geometry": {"coordinates":[22.25633,53.01651999999999],"type":"Point"}
}