{
  "type": "Feature",
  "properties": {
    "gn:admin1_code":"75.0",
    "gn:admin2_code":"601.0",
    "gn:admin3_code":"60110.0",
    "gn:asciiname":"Przychody",
    "gn:country_code":"PL",
    "gn:dem":150,
    "gn:feature_class":"P",
    "gn:feature_code":"PPL",
    "gn:name":"Przychody",
    "gn:population":0,
    "gn:timezone":"Europe/Warsaw",
    "iso:country":"PL",
    "name:ceb_x_preferred":[
        "Przychody"
    ],
    "name:fra_x_preferred":[
        "Przychody"
    ],
    "name:lit_x_preferred":[
        "P\u017eichodai"
    ],
    "name:pol_x_preferred":[
        "Przychody"
    ],
    "name:ukr_x_preferred":[
        "\u041f\u0448\u0438\u0445\u043e\u0434\u0438"
    ],
    "wof:name":"Przychody",
    "wof:placetype":"locality"
},
  "geometry": {"coordinates":[22.67527,51.9503],"type":"Point"}
}