{
  "type": "Feature",
  "properties": {
    "gn:admin1_code":"75.0",
    "gn:admin2_code":"614.0",
    "gn:admin3_code":"61402.0",
    "gn:asciiname":"Wola Czolnowska",
    "gn:country_code":"PL",
    "gn:dem":163,
    "gn:feature_class":"P",
    "gn:feature_code":"PPL",
    "gn:name":"Wola Czo\u0142nowska",
    "gn:population":0,
    "gn:timezone":"Europe/Warsaw",
    "iso:country":"PL",
    "name:fra_x_preferred":[
        "Wola Czo\u0142nowska"
    ],
    "name:pol_x_preferred":[
        "Wola Czo\u0142nowska"
    ],
    "name:ukr_x_preferred":[
        "\u0412\u043e\u043b\u044f-\u0427\u043e\u043b\u043d\u043e\u0432\u0441\u044c\u043a\u0430"
    ],
    "wof:name":"Wola Czolnowska",
    "wof:placetype":"locality"
},
  "geometry": {"coordinates":[22.16203,51.54351],"type":"Point"}
}