{
  "type": "Feature",
  "properties": {
    "gn:admin1_code":"81.0",
    "gn:admin2_code":"2010.0",
    "gn:admin3_code":"201005.0",
    "gn:asciiname":"Radziwillowka",
    "gn:country_code":"PL",
    "gn:dem":157,
    "gn:feature_class":"P",
    "gn:feature_code":"PPL",
    "gn:name":"Radziwi\u0142\u0142\u00f3wka",
    "gn:population":0,
    "gn:timezone":"Europe/Warsaw",
    "iso:country":"PL",
    "name:eng_x_preferred":[
        "Radziwi\u0142\u0142\u00f3wka"
    ],
    "name:lit_x_preferred":[
        "Radziviluvka"
    ],
    "name:pol_x_preferred":[
        "Radziwi\u0142\u0142\u00f3wka"
    ],
    "name:rus_x_preferred":[
        "\u0420\u0430\u0434\u0437\u0438\u0432\u0438\u043b\u043b\u0443\u0432\u043a\u0430"
    ],
    "name:ukr_x_preferred":[
        "\u0420\u0430\u0434\u0437\u0456\u0432\u0456\u043b\u043b\u0443\u0432\u043a\u0430"
    ],
    "name:und_x_variant":[
        "Radziwi\u0142\u00f3wka"
    ],
    "wof:name":"Radziwillowka",
    "wof:placetype":"locality"
},
  "geometry": {"coordinates":[23.0388,52.37461],"type":"Point"}
}