{
  "type": "Feature",
  "properties": {
    "iso:country":"PL",
    "name:ast_x_preferred":[
        "Uszew"
    ],
    "name:ceb_x_preferred":[
        "Uszew"
    ],
    "name:eng_x_preferred":[
        "Uszew"
    ],
    "name:fra_x_preferred":[
        "Uszew"
    ],
    "name:nld_x_preferred":[
        "Uszew"
    ],
    "name:pol_x_preferred":[
        "Uszew"
    ],
    "name:ukr_x_preferred":[
        "\u0423\u0448\u0435\u0432"
    ],
    "qs:a0":"Rzeczpospolita Polska",
    "qs:a1":"*Malopolskie",
    "qs:a1r":"0",
    "qs:a2":"Brzeski",
    "qs:adm0":"Rzeczpospolita Polska",
    "qs:la_lc":"*",
    "qs:level":"locality",
    "qs:loc":"Uszew",
    "qs:loc_alt":"Uszew",
    "qs:pop":0,
    "qs:type":"buffered point",
    "wd:wordcount":90,
    "wof:name":"Uszew",
    "wof:placetype":"locality"
},
  "geometry": {"coordinates":[20.604195,49.917473],"type":"Point"}
}