{
  "type": "Feature",
  "properties": {
    "gn:admin1_code":"78.0",
    "gn:admin2_code":"1416.0",
    "gn:admin3_code":"141610.0",
    "gn:asciiname":"Jarzabka",
    "gn:country_code":"PL",
    "gn:dem":113,
    "gn:feature_class":"P",
    "gn:feature_code":"PPL",
    "gn:name":"Jarz\u0105bka",
    "gn:population":0,
    "gn:timezone":"Europe/Warsaw",
    "iso:country":"PL",
    "name:und_x_variant":[
        "Jarz\u0105bka"
    ],
    "wof:name":"Jarzabka",
    "wof:placetype":"locality"
},
  "geometry": {"coordinates":[21.70334,52.80584],"type":"Point"}
}