{
  "type": "Feature",
  "properties": {
    "gn:admin1_code":"78.0",
    "gn:admin2_code":"1416.0",
    "gn:admin3_code":"141610.0",
    "gn:asciiname":"Jarzabka",
    "gn:country_code":"PL",
    "gn:dem":113,
    "gn:feature_class":"P",
    "gn:feature_code":"PPL",
    "gn:name":"Jarz\u0105bka",
    "gn:population":0,
    "gn:timezone":"Europe/Warsaw",
    "iso:country":"PL",
    "name:azb_x_preferred":[
        "\u06cc\u0627\u0698\u0627\u0646\u0628\u06a9\u0627"
    ],
    "name:fas_x_preferred":[
        "\u06cc\u0627\u0698\u0627\u0646\u0628\u06a9\u0627"
    ],
    "name:fra_x_preferred":[
        "Jarz\u0105bka"
    ],
    "name:pol_x_preferred":[
        "Jarz\u0105bka"
    ],
    "name:ukr_x_preferred":[
        "\u042f\u0436\u043e\u043c\u0431\u043a\u0430"
    ],
    "name:urd_x_preferred":[
        "\u062c\u0631\u0632\u0648\u0628\u06a9\u0627"
    ],
    "wof:name":"Jarzabka",
    "wof:placetype":"locality"
},
  "geometry": {"coordinates":[21.70334,52.80584],"type":"Point"}
}