{
  "type": "Feature",
  "properties": {
    "gn:admin1_code":"86.0",
    "gn:admin2_code":"3007.0",
    "gn:admin3_code":"300710.0",
    "gn:asciiname":"Posrednik",
    "gn:country_code":"PL",
    "gn:dem":123,
    "gn:feature_class":"P",
    "gn:feature_code":"PPL",
    "gn:name":"Po\u015brednik",
    "gn:population":0,
    "gn:timezone":"Europe/Warsaw",
    "iso:country":"PL",
    "name:pol_x_preferred":[
        "Po\u015brednik"
    ],
    "name:ukr_x_preferred":[
        "\u041f\u043e\u0441\u044c\u0440\u0435\u0434\u043d\u0438\u043a"
    ],
    "wof:name":"Posrednik",
    "wof:placetype":"locality"
},
  "geometry": {"coordinates":[18.25614,51.66224],"type":"Point"}
}