{
  "type": "Feature",
  "properties": {
    "gn:admin1_code":"87.0",
    "gn:admin2_code":"3211.0",
    "gn:admin3_code":"321104.0",
    "gn:asciiname":"Przesocin",
    "gn:country_code":"PL",
    "gn:dem":94,
    "gn:feature_class":"P",
    "gn:feature_code":"PPL",
    "gn:name":"Prz\u0119socin",
    "gn:population":0,
    "gn:timezone":"Europe/Warsaw",
    "iso:country":"PL",
    "name:azb_x_preferred":[
        "\u067e\u0698\u0646\u0633\u0648\u0686\u06cc\u0646"
    ],
    "name:dan_x_preferred":[
        "Prz\u0119socin"
    ],
    "name:deu_x_preferred":[
        "Prz\u0119socin"
    ],
    "name:fas_x_preferred":[
        "\u067e\u0698\u0646\u0633\u0648\u0686\u06cc\u0646"
    ],
    "name:fra_x_preferred":[
        "Prz\u0119socin"
    ],
    "name:pol_x_preferred":[
        "Prz\u0119socin"
    ],
    "name:ukr_x_preferred":[
        "\u041f\u0448\u0435\u043d\u0441\u043e\u0446\u0438\u043d"
    ],
    "name:vie_x_preferred":[
        "Prz\u0119socin"
    ],
    "wof:name":"Przesocin",
    "wof:placetype":"locality"
},
  "geometry": {"coordinates":[14.56064,53.51205],"type":"Point"}
}