{
  "type": "Feature",
  "properties": {
    "gn:admin1_code":"86.0",
    "gn:admin2_code":"3006.0",
    "gn:admin3_code":"300603.0",
    "gn:asciiname":"Slupia",
    "gn:country_code":"PL",
    "gn:dem":120,
    "gn:feature_class":"P",
    "gn:feature_code":"PPL",
    "gn:name":"S\u0142upia",
    "gn:population":0,
    "gn:timezone":"Europe/Warsaw",
    "iso:country":"PL",
    "wof:name":"Slupia",
    "wof:placetype":"locality"
},
  "geometry": {"coordinates":[17.58333,51.96667],"type":"Point"}
}