{
  "type": "Feature",
  "properties": {
    "gn:admin1_code":"79.0",
    "gn:admin2_code":"1604.0",
    "gn:admin3_code":"160401.0",
    "gn:asciiname":"Jozefowka",
    "gn:country_code":"PL",
    "gn:dem":175,
    "gn:feature_class":"P",
    "gn:feature_code":"PPL",
    "gn:name":"J\u00f3zef\u00f3wka",
    "gn:population":0,
    "gn:timezone":"Europe/Warsaw",
    "iso:country":"PL",
    "name:und_x_variant":[
        "Osada J\u00f3zef\u00f3wka",
        "J\u00f3zef\u00f3wka"
    ],
    "wof:name":"Jozefowka",
    "wof:placetype":"locality"
},
  "geometry": {"coordinates":[18.0991,51.15284000000001],"type":"Point"}
}