{
  "type": "Feature",
  "properties": {
    "gn:admin1_code":"75.0",
    "gn:admin2_code":"603.0",
    "gn:admin3_code":"60310.0",
    "gn:asciiname":"Sajczyce",
    "gn:country_code":"PL",
    "gn:dem":170,
    "gn:feature_class":"P",
    "gn:feature_code":"PPL",
    "gn:name":"Sajczyce",
    "gn:population":0,
    "gn:timezone":"Europe/Warsaw",
    "iso:country":"PL",
    "name:ces_x_preferred":[
        "Sajczyce"
    ],
    "name:fra_x_preferred":[
        "Sajczyce"
    ],
    "name:pol_x_preferred":[
        "Sajczyce"
    ],
    "name:ukr_x_preferred":[
        "\u0421\u0430\u0439\u0447\u0438\u0446\u0435"
    ],
    "wof:name":"Sajczyce",
    "wof:placetype":"locality"
},
  "geometry": {"coordinates":[23.46169,51.25185],"type":"Point"}
}