{
  "type": "Feature",
  "properties": {
    "gn:admin1_code":"72.0",
    "gn:admin2_code":"217.0",
    "gn:admin3_code":"21702.0",
    "gn:asciiname":"Blotnica",
    "gn:country_code":"PL",
    "gn:dem":250,
    "gn:feature_class":"P",
    "gn:feature_code":"PPL",
    "gn:name":"B\u0142otnica",
    "gn:population":0,
    "gn:timezone":"Europe/Warsaw",
    "iso:country":"PL",
    "name:pol_x_preferred":[
        "B\u0142otnica"
    ],
    "name:ukr_x_preferred":[
        "\u0411\u043b\u043e\u0442\u043d\u0438\u0446\u044f"
    ],
    "wof:name":"Blotnica",
    "wof:placetype":"locality"
},
  "geometry": {"coordinates":[16.91242,50.71277],"type":"Point"}
}