{
  "type": "Feature",
  "properties": {
    "iso:country":"PL",
    "name:pol_x_preferred":[
        "Baran\u00f3w"
    ],
    "wof:coterminous":[
        1125317803
    ],
    "wof:name":"Baran\u00f3w",
    "wof:placetype":"locality"
},
  "geometry": {"coordinates":[17.9754314509501,51.2382748227387],"type":"Point"}
}