{
  "type": "Feature",
  "properties": {
    "gn:country":"PL",
    "gn:fcode":"PPL",
    "gn:population":840,
    "iso:country":"PL",
    "name:ast_x_preferred":[
        "Drewnica"
    ],
    "name:ceb_x_preferred":[
        "Drewnica"
    ],
    "name:eng_x_preferred":[
        "Drewnica"
    ],
    "name:fra_x_preferred":[
        "Drewnica"
    ],
    "name:nld_x_preferred":[
        "Drewnica"
    ],
    "name:pol_x_preferred":[
        "Drewnica"
    ],
    "name:ukr_x_preferred":[
        "\u0414\u0440\u0435\u0432\u043d\u0438\u0446\u044f"
    ],
    "name:und_x_variant":[
        "Sch\u00f6nbaum"
    ],
    "qs_pg:aaroncc":"PL",
    "qs_pg:gn_country":"PL",
    "qs_pg:gn_fcode":"PPL",
    "qs_pg:gn_pop":840,
    "qs_pg:name":"Drewnica",
    "qs_pg:name_adm0":"Polska",
    "qs_pg:name_adm1":"Pomorskie",
    "qs_pg:photos":29,
    "qs_pg:photos_1k":6,
    "qs_pg:photos_9k":1,
    "qs_pg:photos_9r":2,
    "qs_pg:photos_all":29,
    "qs_pg:photos_sr":2,
    "qs_pg:pop_sr":2,
    "qs_pg:qs_pg_placetype":"locality",
    "qs_pg:qs_pg_placetype_gp":"Town",
    "qs_pg:woe_adm0":23424923,
    "woe:adm0_id":23424923,
    "woe:name_adm0":"Polska",
    "woe:name_adm1":"Pomorskie",
    "woe:placetype":"Town",
    "wof:name":"Drewnica",
    "wof:placetype":"locality",
    "wof:population":840
},
  "geometry": {"coordinates":[18.95665,54.28758],"type":"Point"}
}