{
  "type": "Feature",
  "properties": {
    "gn:admin1_code":"82.0",
    "gn:admin2_code":"2202.0",
    "gn:admin3_code":"220202.0",
    "gn:asciiname":"Kruszyn",
    "gn:country_code":"PL",
    "gn:dem":144,
    "gn:feature_class":"P",
    "gn:feature_code":"PPL",
    "gn:name":"Kruszyn",
    "gn:population":0,
    "gn:timezone":"Europe/Warsaw",
    "iso:country":"PL",
    "name:csb_x_preferred":[
        "Kr\u00ebsz\u00ebni\u00f4"
    ],
    "name:pol_x_preferred":[
        "Kruszyn"
    ],
    "name:ukr_x_preferred":[
        "\u041a\u0440\u0443\u0448\u0438\u043d"
    ],
    "wof:name":"Kruszyn",
    "wof:placetype":"locality"
},
  "geometry": {"coordinates":[17.59802999999999,53.9807],"type":"Point"}
}