{
  "type": "Feature",
  "properties": {
    "gn:admin1_code":"81.0",
    "gn:admin2_code":"2006.0",
    "gn:admin3_code":"200603.0",
    "gn:asciiname":"Zabiele",
    "gn:country_code":"PL",
    "gn:dem":113,
    "gn:feature_class":"P",
    "gn:feature_code":"PPL",
    "gn:name":"Zabiele",
    "gn:population":0,
    "gn:timezone":"Europe/Warsaw",
    "iso:country":"PL",
    "name:eng_x_preferred":[
        "Zabiele"
    ],
    "name:rus_x_preferred":[
        "\u0417\u0430\u0431\u0435\u043b\u0435"
    ],
    "wof:name":"Zabiele",
    "wof:placetype":"locality"
},
  "geometry": {"coordinates":[21.86255,53.38779],"type":"Point"}
}