{
  "type": "Feature",
  "properties": {
    "gn:admin1_code":"81.0",
    "gn:admin2_code":"2012.0",
    "gn:admin3_code":"201201.0",
    "gn:asciiname":"Klonowa Gora",
    "gn:country_code":"PL",
    "gn:dem":174,
    "gn:feature_class":"P",
    "gn:feature_code":"PPL",
    "gn:name":"Klonowa G\u00f3ra",
    "gn:population":0,
    "gn:timezone":"Europe/Warsaw",
    "iso:country":"PL",
    "name:und_x_variant":[
        "Klonowa G\u00f3ra"
    ],
    "wof:name":"Klonowa Gora",
    "wof:placetype":"locality"
},
  "geometry": {"coordinates":[22.71546,54.0947],"type":"Point"}
}