{
  "type": "Feature",
  "properties": {
    "gn:admin1_code":"81.0",
    "gn:admin2_code":"2012.0",
    "gn:admin3_code":"201201.0",
    "gn:asciiname":"Klonowa Gora",
    "gn:country_code":"PL",
    "gn:dem":174,
    "gn:feature_class":"P",
    "gn:feature_code":"PPL",
    "gn:name":"Klonowa G\u00f3ra",
    "gn:population":0,
    "gn:timezone":"Europe/Warsaw",
    "iso:country":"PL",
    "name:azb_x_preferred":[
        "\u06a9\u0644\u0648\u0646\u0648\u0648\u0627 \u0642\u0648\u0631\u0627"
    ],
    "name:fas_x_preferred":[
        "\u06a9\u0644\u0648\u0646\u0648\u0648\u0627 \u06af\u0648\u0631\u0627"
    ],
    "name:fra_x_preferred":[
        "Klonowa G\u00f3ra"
    ],
    "name:lit_x_preferred":[
        "Klonova Gura"
    ],
    "name:pol_x_preferred":[
        "Klonowa G\u00f3ra"
    ],
    "name:ukr_x_preferred":[
        "\u041a\u043b\u044c\u043e\u043d\u043e\u0432\u0430-\u0490\u0443\u0440\u0430"
    ],
    "wof:name":"Klonowa Gora",
    "wof:placetype":"locality"
},
  "geometry": {"coordinates":[22.71546,54.0947],"type":"Point"}
}