{
  "type": "Feature",
  "properties": {
    "gn:admin1_code":"72.0",
    "gn:admin2_code":"203.0",
    "gn:admin3_code":"20306.0",
    "gn:asciiname":"Brzeg Glogowski",
    "gn:country_code":"PL",
    "gn:dem":81,
    "gn:feature_class":"P",
    "gn:feature_code":"PPL",
    "gn:name":"Brzeg G\u0142ogowski",
    "gn:population":0,
    "gn:timezone":"Europe/Warsaw",
    "iso:country":"PL",
    "name:deu_x_historical":[
        "Brieg"
    ],
    "name:deu_x_preferred":[
        "Brieg"
    ],
    "wof:name":"Brzeg Glogowski",
    "wof:placetype":"locality"
},
  "geometry": {"coordinates":[15.91541,51.69746],"type":"Point"}
}