{
  "type": "Feature",
  "properties": {
    "gn:admin1_code":"72.0",
    "gn:admin2_code":"203.0",
    "gn:admin3_code":"20306.0",
    "gn:asciiname":"Brzeg Glogowski",
    "gn:country_code":"PL",
    "gn:dem":81,
    "gn:feature_class":"P",
    "gn:feature_code":"PPL",
    "gn:name":"Brzeg G\u0142ogowski",
    "gn:population":0,
    "gn:timezone":"Europe/Warsaw",
    "iso:country":"PL",
    "name:azb_x_preferred":[
        "\u0628\u0698\u0642 \u0642\u0648\u0648\u0642\u0648\u0648\u0633\u06a9\u06cc"
    ],
    "name:ceb_x_preferred":[
        "Brzeg G\u0142ogowski"
    ],
    "name:deu_x_historical":[
        "Brieg"
    ],
    "name:deu_x_preferred":[
        "Brieg"
    ],
    "name:fas_x_preferred":[
        "\u0628\u0698\u06af \u06af\u0648\u0648\u06af\u0648\u0648\u0633\u06a9\u06cc"
    ],
    "name:nld_x_preferred":[
        "Brzeg G\u0142ogowski"
    ],
    "name:pol_x_preferred":[
        "Brzeg G\u0142ogowski"
    ],
    "name:ukr_x_preferred":[
        "\u0411\u0436\u0435\u0491-\u0490\u043b\u043e\u0491\u043e\u0432\u0441\u044c\u043a\u0438\u0439"
    ],
    "name:urd_x_preferred":[
        "\u0628\u0631\u0632\u06af \u06af\u0648\u0648\u06af\u0648\u0648\u0633\u06a9\u06cc"
    ],
    "wof:name":"Brzeg Glogowski",
    "wof:placetype":"locality"
},
  "geometry": {"coordinates":[15.91541,51.69746],"type":"Point"}
}