{
  "type": "Feature",
  "properties": {
    "gn:admin1_code":"86.0",
    "gn:admin2_code":"3010.0",
    "gn:admin3_code":"301008.0",
    "gn:asciiname":"Kurow",
    "gn:country_code":"PL",
    "gn:dem":90,
    "gn:feature_class":"P",
    "gn:feature_code":"PPL",
    "gn:name":"Kur\u00f3w",
    "gn:population":0,
    "gn:timezone":"Europe/Warsaw",
    "iso:country":"PL",
    "name:ceb_x_preferred":[
        "Kurow"
    ],
    "name:cym_x_preferred":[
        "Kurow"
    ],
    "name:deu_x_preferred":[
        "Kurow"
    ],
    "name:fra_x_preferred":[
        "Kurow"
    ],
    "name:msa_x_preferred":[
        "Kurow"
    ],
    "name:nld_x_preferred":[
        "Kurow"
    ],
    "name:pol_x_preferred":[
        "Kurow"
    ],
    "name:ron_x_preferred":[
        "Kurow"
    ],
    "name:swa_x_preferred":[
        "Kurow"
    ],
    "name:war_x_preferred":[
        "Kurow"
    ],
    "wof:name":"Kurow",
    "wof:placetype":"locality"
},
  "geometry": {"coordinates":[18.01229,52.11134000000001],"type":"Point"}
}