{
  "type": "Feature",
  "properties": {
    "gn:admin1_code":"74.0",
    "gn:admin2_code":"1010.0",
    "gn:admin3_code":"101002.0",
    "gn:asciiname":"Zawodzie",
    "gn:country_code":"PL",
    "gn:dem":185,
    "gn:feature_class":"P",
    "gn:feature_code":"PPL",
    "gn:name":"Zawodzie",
    "gn:population":0,
    "gn:timezone":"Europe/Warsaw",
    "iso:country":"PL",
    "wof:name":"Zawodzie",
    "wof:placetype":"locality"
},
  "geometry": {"coordinates":[19.68452000000001,51.61239000000001],"type":"Point"}
}