{
  "type": "Feature",
  "properties": {
    "gn:admin1_code":"84.0",
    "gn:admin2_code":"2608.0",
    "gn:admin3_code":"260801.0",
    "gn:asciiname":"Sypow",
    "gn:country_code":"PL",
    "gn:dem":296,
    "gn:feature_class":"P",
    "gn:feature_code":"PPL",
    "gn:name":"Syp\u00f3w",
    "gn:population":0,
    "gn:timezone":"Europe/Warsaw",
    "iso:country":"PL",
    "name:pol_x_preferred":[
        "Syp\u00f3w"
    ],
    "name:ukr_x_preferred":[
        "\u0421\u0438\u043f\u0443\u0432"
    ],
    "name:und_x_variant":[
        "Syp\u00f3w"
    ],
    "wof:name":"Sypow",
    "wof:placetype":"locality"
},
  "geometry": {"coordinates":[20.43226,50.40496],"type":"Point"}
}