{
  "type": "Feature",
  "properties": {
    "gn:population":5100,
    "iso:country":"PL",
    "name:ast_x_preferred":[
        "Mys\u0142akowice"
    ],
    "name:azb_x_preferred":[
        "\u0645\u0633\u0648\u0627\u06a9\u0648\u0648\u06cc\u062a\u0633\u0647"
    ],
    "name:ceb_x_preferred":[
        "Mys\u0142akowice"
    ],
    "name:deu_x_preferred":[
        "Mys\u0142akowice"
    ],
    "name:deu_x_variant":[
        "Zillerthal-Erdmannsdorf"
    ],
    "name:eng_x_preferred":[
        "Mys\u0142akowice"
    ],
    "name:fas_x_preferred":[
        "\u0645\u0633\u0648\u0627\u06a9\u0648\u0648\u06cc\u062a\u0633\u0647"
    ],
    "name:fra_x_preferred":[
        "Mys\u0142akowice"
    ],
    "name:ger_x_historical":[
        "Zillerthal-Erdmannsdorf"
    ],
    "name:jpn_x_preferred":[
        "\u30df\u30b9\u30ef\u30b3\u30f4\u30a3\u30c4\u30a7"
    ],
    "name:nld_x_preferred":[
        "Mys\u0142akowice"
    ],
    "name:pol_x_preferred":[
        "Mys\u0142akowice"
    ],
    "name:rus_x_preferred":[
        "\u041c\u044b\u0441\u043b\u0430\u043a\u043e\u0432\u0438\u0446\u0435"
    ],
    "name:swe_x_preferred":[
        "Mys\u0142akowice"
    ],
    "name:ukr_x_preferred":[
        "\u041c\u0438\u0441\u043b\u0430\u043a\u043e\u0432\u0456\u0446\u0435"
    ],
    "qs:a0":"Rzeczpospolita Polska",
    "qs:a1":"*Dolnoslaskie",
    "qs:a1r":"0",
    "qs:a2":"Jeleniog\u00f3rski",
    "qs:adm0":"Rzeczpospolita Polska",
    "qs:la":"Mys\u0142akowice",
    "qs:la_lc":"*PL0206072",
    "qs:level":"locality",
    "qs:loc":"Mys\u0142akowice",
    "qs:loc_alt":"Myslakowice",
    "qs:pop":0,
    "qs:type":"rural point-near-poly",
    "wd:wordcount":133,
    "wof:name":"Mys\u0142akowice",
    "wof:placetype":"locality",
    "wof:population":5100
},
  "geometry": {"coordinates":[15.8228369041019,50.8512632869116],"type":"Point"}
}