{
  "type": "Feature",
  "properties": {
    "gn:admin1_code":"73.0",
    "gn:admin2_code":"410.0",
    "gn:admin3_code":"41005.0",
    "gn:asciiname":"Retkowo",
    "gn:country_code":"PL",
    "gn:dem":101,
    "gn:feature_class":"P",
    "gn:feature_code":"PPL",
    "gn:name":"Retkowo",
    "gn:population":0,
    "gn:timezone":"Europe/Warsaw",
    "iso:country":"PL",
    "name:ceb_x_preferred":[
        "Retkowo"
    ],
    "name:pol_x_preferred":[
        "Retkowo"
    ],
    "name:ukr_x_preferred":[
        "\u0420\u0435\u0442\u043a\u043e\u0432\u043e"
    ],
    "wof:name":"Retkowo",
    "wof:placetype":"locality"
},
  "geometry": {"coordinates":[17.62365,52.93013000000001],"type":"Point"}
}