{
  "type": "Feature",
  "properties": {
    "gn:admin1_code":"85.0",
    "gn:admin2_code":"2818.0",
    "gn:admin3_code":"281802.0",
    "gn:asciiname":"Barcie",
    "gn:country_code":"PL",
    "gn:dem":188,
    "gn:feature_class":"P",
    "gn:feature_code":"PPL",
    "gn:name":"Barcie",
    "gn:population":0,
    "gn:timezone":"Europe/Warsaw",
    "iso:country":"PL",
    "name:azb_x_preferred":[
        "\u0628\u0627\u0631\u0686\u06cc\u0647"
    ],
    "name:deu_x_preferred":[
        "Barcie"
    ],
    "name:fas_x_preferred":[
        "\u0628\u0627\u0631\u0686\u06cc\u0647"
    ],
    "name:lit_x_preferred":[
        "T\u0117velkiemis"
    ],
    "name:nld_x_preferred":[
        "Barcie"
    ],
    "name:pol_x_preferred":[
        "Barcie"
    ],
    "name:ukr_x_preferred":[
        "\u0411\u0430\u0440\u0446\u0435"
    ],
    "name:und_x_variant":[
        "Thowelkehmen",
        "Thewelkehmen",
        "Tulkeim"
    ],
    "wof:name":"Barcie",
    "wof:placetype":"locality"
},
  "geometry": {"coordinates":[22.58892,54.28697],"type":"Point"}
}