{
  "type": "Feature",
  "properties": {
    "gn:admin1_code":"84.0",
    "gn:admin2_code":"2601.0",
    "gn:admin3_code":"260106.0",
    "gn:asciiname":"Czyzow",
    "gn:country_code":"PL",
    "gn:dem":196,
    "gn:feature_class":"P",
    "gn:feature_code":"PPL",
    "gn:name":"Czy\u017c\u00f3w",
    "gn:population":0,
    "gn:timezone":"Europe/Warsaw",
    "iso:country":"PL",
    "name:ceb_x_preferred":[
        "Czy\u017c\u00f3w"
    ],
    "name:pol_x_preferred":[
        "Czy\u017c\u00f3w"
    ],
    "name:ukr_x_preferred":[
        "\u0427\u0438\u0436\u0443\u0432"
    ],
    "wof:name":"Czyzow",
    "wof:placetype":"locality"
},
  "geometry": {"coordinates":[20.99607,50.4751],"type":"Point"}
}