{
  "type": "Feature",
  "properties": {
    "gn:admin1_code":"76.0",
    "gn:admin2_code":"811.0",
    "gn:admin3_code":"81103.0",
    "gn:asciiname":"Grodziszcze",
    "gn:country_code":"PL",
    "gn:dem":63,
    "gn:feature_class":"P",
    "gn:feature_code":"PPL",
    "gn:name":"Grodziszcze",
    "gn:population":0,
    "gn:timezone":"Europe/Warsaw",
    "iso:country":"PL",
    "wof:name":"Grodziszcze",
    "wof:placetype":"locality"
},
  "geometry": {"coordinates":[14.82742,51.82432],"type":"Point"}
}