{
  "type": "Feature",
  "properties": {
    "gn:admin1_code":"82.0",
    "gn:admin2_code":"2202.0",
    "gn:admin3_code":"220204.0",
    "gn:asciiname":"Stare Prusy",
    "gn:country_code":"PL",
    "gn:dem":124,
    "gn:feature_class":"P",
    "gn:feature_code":"PPL",
    "gn:name":"Stare Prusy",
    "gn:population":0,
    "gn:timezone":"Europe/Warsaw",
    "iso:country":"PL",
    "name:pol_x_preferred":[
        "Stare Prusy"
    ],
    "name:ukr_x_preferred":[
        "\u0421\u0442\u0430\u0440\u0435 \u041f\u0440\u0443\u0441\u0438"
    ],
    "wof:name":"Stare Prusy",
    "wof:placetype":"locality"
},
  "geometry": {"coordinates":[18.05263,53.84899],"type":"Point"}
}