{
  "type": "Feature",
  "properties": {
    "gn:admin1_code":"84.0",
    "gn:admin2_code":"2606.0",
    "gn:admin3_code":"260602.0",
    "gn:asciiname":"Wojnowice",
    "gn:country_code":"PL",
    "gn:dem":269,
    "gn:feature_class":"P",
    "gn:feature_code":"PPL",
    "gn:name":"Wojnowice",
    "gn:population":0,
    "gn:timezone":"Europe/Warsaw",
    "iso:country":"PL",
    "name:ceb_x_preferred":[
        "Wojnowice"
    ],
    "name:deu_x_preferred":[
        "Wojnowice"
    ],
    "name:fra_x_preferred":[
        "Wojnowice"
    ],
    "name:nld_x_preferred":[
        "Wojnowice"
    ],
    "name:pol_x_preferred":[
        "Wojnowice"
    ],
    "name:ukr_x_preferred":[
        "\u0412\u043e\u0439\u043d\u043e\u0432\u0456\u0446\u0435"
    ],
    "wof:name":"Wojnowice",
    "wof:placetype":"locality"
},
  "geometry": {"coordinates":[21.27838,50.75048],"type":"Point"}
}