{
  "type": "Feature",
  "properties": {
    "gn:admin1_code":"75.0",
    "gn:admin2_code":"606.0",
    "gn:admin3_code":"60604.0",
    "gn:asciiname":"Szajowka",
    "gn:country_code":"PL",
    "gn:dem":205,
    "gn:feature_class":"P",
    "gn:feature_code":"PPL",
    "gn:name":"Szaj\u00f3wka",
    "gn:population":0,
    "gn:timezone":"Europe/Warsaw",
    "iso:country":"PL",
    "wof:name":"Szajowka",
    "wof:placetype":"locality"
},
  "geometry": {"coordinates":[23.14018,50.86462],"type":"Point"}
}