{
  "type": "Feature",
  "properties": {
    "gn:gn_country":"PL",
    "gn:gn_fcode":"PPL",
    "gn:gn_pop":728,
    "gn:population":728,
    "iso:country":"PL",
    "name:ast_x_preferred":[
        "Dojazd\u00f3w"
    ],
    "name:ceb_x_preferred":[
        "Dojazd\u00f3w"
    ],
    "name:eng_x_preferred":[
        "Dojazd\u00f3w"
    ],
    "name:fra_x_preferred":[
        "Dojazd\u00f3w"
    ],
    "name:nan_x_preferred":[
        "Dojazd\u00f3w"
    ],
    "name:pol_x_preferred":[
        "Dojazd\u00f3w"
    ],
    "name:rus_x_preferred":[
        "\u0414\u043e\u044f\u0437\u0434\u0443\u0432"
    ],
    "name:ukr_x_preferred":[
        "\u0414\u043e\u044f\u0437\u0434\u0443\u0432"
    ],
    "qs_pg:aaroncc":"PL",
    "qs_pg:gn_country":"PL",
    "qs_pg:gn_fcode":"PPL",
    "qs_pg:gn_pop":728,
    "qs_pg:name":"Dojazd\u00f3w",
    "qs_pg:name_adm0":"Polska",
    "qs_pg:name_adm1":"Ma\u0142opolskie",
    "qs_pg:photos_9k":1,
    "qs_pg:photos_9r":1,
    "qs_pg:photos_all":1,
    "qs_pg:photos_sr":0,
    "qs_pg:pop_sr":2,
    "qs_pg:qs_pg_placetype":"locality",
    "qs_pg:qs_pg_placetype_gp":"Town",
    "qs_pg:woe_adm0":23424923,
    "woe:adm0_id":23424923,
    "woe:name_adm0":"Polska",
    "woe:name_adm1":"Ma\u0142opolskie",
    "woe:placetype":"Town",
    "wof:name":"Dojazd\u00f3w",
    "wof:placetype":"locality",
    "wof:population":728
},
  "geometry": {"coordinates":[20.11236,50.12201],"type":"Point"}
}