{
  "type": "Feature",
  "properties": {
    "gn:admin1_code":"86.0",
    "gn:admin2_code":"3007.0",
    "gn:admin3_code":"300706.0",
    "gn:asciiname":"Strzalkow",
    "gn:country_code":"PL",
    "gn:dem":139,
    "gn:feature_class":"P",
    "gn:feature_code":"PPL",
    "gn:name":"Strza\u0142k\u00f3w",
    "gn:population":0,
    "gn:timezone":"Europe/Warsaw",
    "iso:country":"PL",
    "name:pol_x_preferred":[
        "Strza\u0142k\u00f3w"
    ],
    "name:ukr_x_preferred":[
        "\u0421\u0442\u0448\u0430\u043b\u043a\u0443\u0432"
    ],
    "wof:name":"Strzalkow",
    "wof:placetype":"locality"
},
  "geometry": {"coordinates":[18.4251,51.86239000000001],"type":"Point"}
}