{
  "type": "Feature",
  "properties": {
    "gn:admin1_code":"78.0",
    "gn:admin2_code":"1463.0",
    "gn:admin3_code":"146301.0",
    "gn:asciiname":"osiedle Nad Potokiem",
    "gn:country_code":"PL",
    "gn:dem":171,
    "gn:feature_class":"P",
    "gn:feature_code":"PPL",
    "gn:name":"osiedle Nad Potokiem",
    "gn:population":0,
    "gn:timezone":"Europe/Warsaw",
    "iso:country":"PL",
    "wof:name":"osiedle Nad Potokiem",
    "wof:placetype":"neighbourhood"
},
  "geometry": {"coordinates":[21.1734,51.40689],"type":"Point"}
}