{
  "type": "Feature",
  "properties": {
    "gn:admin1_code":"86.0",
    "gn:admin2_code":"3022.0",
    "gn:admin3_code":"302201.0",
    "gn:asciiname":"Kawcze",
    "gn:country_code":"PL",
    "gn:dem":96,
    "gn:feature_class":"P",
    "gn:feature_code":"PPL",
    "gn:name":"Kawcze",
    "gn:population":0,
    "gn:timezone":"Europe/Warsaw",
    "iso:country":"PL",
    "name:azb_x_preferred":[
        "\u06a9\u0627\u0648\u0686\u0647"
    ],
    "name:fas_x_preferred":[
        "\u06a9\u0627\u0648\u0686\u0647"
    ],
    "name:fra_x_preferred":[
        "Kawcze"
    ],
    "name:ita_x_preferred":[
        "Kawcze"
    ],
    "name:pol_x_preferred":[
        "Kawcze"
    ],
    "name:ukr_x_preferred":[
        "\u041a\u0430\u0432\u0447\u0435"
    ],
    "wof:name":"Kawcze",
    "wof:placetype":"locality"
},
  "geometry": {"coordinates":[16.85363,51.69283],"type":"Point"}
}