{
  "type": "Feature",
  "properties": {
    "gn:admin1_code":"72.0",
    "gn:admin2_code":"218.0",
    "gn:admin3_code":"21801.0",
    "gn:asciiname":"Bogdanow",
    "gn:country_code":"PL",
    "gn:dem":173,
    "gn:feature_class":"P",
    "gn:feature_code":"PPL",
    "gn:name":"Bogdan\u00f3w",
    "gn:population":0,
    "gn:timezone":"Europe/Warsaw",
    "iso:country":"PL",
    "name:pol_x_preferred":[
        "Bogdan\u00f3w"
    ],
    "name:ukr_x_preferred":[
        "\u0411\u043e\u0491\u0434\u0430\u043d\u0443\u0432"
    ],
    "wof:name":"Bogdanow",
    "wof:placetype":"locality"
},
  "geometry": {"coordinates":[16.57631,51.0076],"type":"Point"}
}