{
  "type": "Feature",
  "properties": {
    "iso:country":"PL",
    "name:ast_x_preferred":[
        "G\u00f3rczyca"
    ],
    "name:eng_x_preferred":[
        "G\u00f3rczyca"
    ],
    "name:fra_x_preferred":[
        "G\u00f3rczyca"
    ],
    "name:nan_x_preferred":[
        "G\u00f3rczyca"
    ],
    "name:nld_x_preferred":[
        "G\u00f3rczyca"
    ],
    "name:pol_x_preferred":[
        "G\u00f3rczyca"
    ],
    "name:ukr_x_preferred":[
        "\u0490\u0443\u0440\u0447\u0438\u0446\u044f"
    ],
    "qs_pg:aaroncc":"PL",
    "qs_pg:name":"G\u00f3rczyca",
    "qs_pg:name_adm0":"Polska",
    "qs_pg:name_adm1":"Dolnosl\u0105skie",
    "qs_pg:photos":20,
    "qs_pg:photos_1k":4,
    "qs_pg:photos_9k":1,
    "qs_pg:photos_9r":1,
    "qs_pg:photos_all":20,
    "qs_pg:photos_sr":1,
    "qs_pg:pop_sr":0,
    "qs_pg:qs_pg_placetype":"locality",
    "qs_pg:qs_pg_placetype_gp":"Town",
    "qs_pg:woe_adm0":23424923,
    "woe:adm0_id":23424923,
    "woe:name_adm0":"Polska",
    "woe:name_adm1":"Dolnosl\u0105skie",
    "woe:placetype":"Town",
    "wof:name":"G\u00f3rczyca",
    "wof:placetype":"locality"
},
  "geometry": {"coordinates":[15.6691215,51.051133],"type":"Point"}
}