{
  "type": "Feature",
  "properties": {
    "iso:country":"PL",
    "name:pol_x_preferred":[
        "Piekie\u0142ko"
    ],
    "wof:name":"Piekielko",
    "wof:placetype":"neighbourhood"
},
  "geometry": {"coordinates":[20.11792926607696,50.05532637905387],"type":"Point"}
}