{
  "type": "Feature",
  "properties": {
    "gn:admin1_code":"78.0",
    "gn:admin2_code":"1415.0",
    "gn:admin3_code":"141504.0",
    "gn:asciiname":"Jawory",
    "gn:country_code":"PL",
    "gn:dem":107,
    "gn:feature_class":"P",
    "gn:feature_code":"PPL",
    "gn:name":"Jawory",
    "gn:population":0,
    "gn:timezone":"Europe/Warsaw",
    "iso:country":"PL",
    "name:fra_x_preferred":[
        "Jawory"
    ],
    "name:pol_x_preferred":[
        "Jawory"
    ],
    "name:ukr_x_preferred":[
        "\u042f\u0432\u043e\u0440\u0438"
    ],
    "wof:name":"Jawory",
    "wof:placetype":"locality"
},
  "geometry": {"coordinates":[21.50464,52.91752],"type":"Point"}
}