{
  "type": "Feature",
  "properties": {
    "gn:admin1_code":"86.0",
    "gn:admin2_code":"3017.0",
    "gn:admin3_code":"301708.0",
    "gn:asciiname":"Konradow",
    "gn:country_code":"PL",
    "gn:dem":128,
    "gn:feature_class":"P",
    "gn:feature_code":"PPL",
    "gn:name":"Konrad\u00f3w",
    "gn:population":0,
    "gn:timezone":"Europe/Warsaw",
    "iso:country":"PL",
    "name:pol_x_preferred":[
        "Konrad\u00f3w"
    ],
    "name:spa_x_preferred":[
        "Konrad\u00f3w"
    ],
    "name:ukr_x_preferred":[
        "\u041a\u043e\u043d\u0440\u0430\u0434\u0443\u0432"
    ],
    "wof:name":"Konradow",
    "wof:placetype":"locality"
},
  "geometry": {"coordinates":[17.55333,51.44428],"type":"Point"}
}