{
  "type": "Feature",
  "properties": {
    "gn:admin1_code":"75.0",
    "gn:admin2_code":"614.0",
    "gn:admin3_code":"61411.0",
    "gn:asciiname":"Borysow",
    "gn:country_code":"PL",
    "gn:dem":134,
    "gn:feature_class":"P",
    "gn:feature_code":"PPL",
    "gn:name":"Borys\u00f3w",
    "gn:population":0,
    "gn:timezone":"Europe/Warsaw",
    "iso:country":"PL",
    "name:fra_x_preferred":[
        "Borys\u00f3w"
    ],
    "name:pol_x_preferred":[
        "Borys\u00f3w"
    ],
    "name:ukr_x_preferred":[
        "\u0411\u043e\u0440\u0438\u0441\u0443\u0432"
    ],
    "name:und_x_variant":[
        "Borys\u00f3w"
    ],
    "wof:name":"Borysow",
    "wof:placetype":"locality"
},
  "geometry": {"coordinates":[22.03824,51.51152],"type":"Point"}
}