{
  "type": "Feature",
  "properties": {
    "gn:admin1_code":"81.0",
    "gn:admin2_code":"2013.0",
    "gn:admin3_code":"201307.0",
    "gn:asciiname":"Jablon Zarzeckie",
    "gn:country_code":"PL",
    "gn:dem":145,
    "gn:feature_class":"P",
    "gn:feature_code":"PPL",
    "gn:name":"Jab\u0142o\u0144 Zarzeckie",
    "gn:population":0,
    "gn:timezone":"Europe/Warsaw",
    "iso:country":"PL",
    "name:und_x_variant":[
        "Jab\u0142o\u0144 Zarzeckie"
    ],
    "wof:name":"Jablon Zarzeckie",
    "wof:placetype":"locality"
},
  "geometry": {"coordinates":[22.65264,52.9356],"type":"Point"}
}