{
  "type": "Feature",
  "properties": {
    "gn:admin1_code":"81.0",
    "gn:admin2_code":"2013.0",
    "gn:admin3_code":"201307.0",
    "gn:asciiname":"Jablon Zarzeckie",
    "gn:country_code":"PL",
    "gn:dem":145,
    "gn:feature_class":"P",
    "gn:feature_code":"PPL",
    "gn:name":"Jab\u0142o\u0144 Zarzeckie",
    "gn:population":0,
    "gn:timezone":"Europe/Warsaw",
    "iso:country":"PL",
    "name:azb_x_preferred":[
        "\u06cc\u0627\u0628\u0648\u0648\u0646\u0642-\u0632\u0627\u0698\u062a\u0633\u06a9\u06cc\u0647"
    ],
    "name:fas_x_preferred":[
        "\u06cc\u0627\u0628\u0648\u0648\u0646\u06af-\u0632\u0627\u0698\u062a\u0633\u06a9\u06cc\u0647"
    ],
    "name:lit_x_preferred":[
        "Jablon Za\u017eeckiai"
    ],
    "name:pol_x_preferred":[
        "Jab\u0142o\u0144-Zarzeckie"
    ],
    "name:ukr_x_preferred":[
        "\u042f\u0431\u043b\u043e\u043d\u044c-\u0417\u0430\u0436\u0435\u0446\u044c\u043a\u0435"
    ],
    "name:und_x_variant":[
        "Jab\u0142o\u0144 Zarzeckie"
    ],
    "name:urd_x_preferred":[
        "\u062c\u0628\u0648\u0648\u0646-\u0632\u0631\u0632\u06a9\u06a9\u0626\u06cc"
    ],
    "wof:name":"Jablon Zarzeckie",
    "wof:placetype":"locality"
},
  "geometry": {"coordinates":[22.65264,52.9356],"type":"Point"}
}