{
  "type": "Feature",
  "properties": {
    "gn:admin1_code":"73.0",
    "gn:admin2_code":"410.0",
    "gn:admin3_code":"41005.0",
    "gn:asciiname":"Zazdrosc",
    "gn:country_code":"PL",
    "gn:dem":66,
    "gn:feature_class":"P",
    "gn:feature_code":"PPL",
    "gn:name":"Zazdro\u015b\u0107",
    "gn:population":0,
    "gn:timezone":"Europe/Warsaw",
    "iso:country":"PL",
    "wof:name":"Zazdrosc",
    "wof:placetype":"locality"
},
  "geometry": {"coordinates":[17.80473,53.01563],"type":"Point"}
}