{
  "type": "Feature",
  "properties": {
    "gn:admin1_code":"85.0",
    "gn:admin2_code":"2801.0",
    "gn:admin3_code":"280103.0",
    "gn:asciiname":"Wardomy",
    "gn:country_code":"PL",
    "gn:dem":52,
    "gn:feature_class":"P",
    "gn:feature_code":"PPL",
    "gn:name":"Wardomy",
    "gn:population":0,
    "gn:timezone":"Europe/Warsaw",
    "iso:country":"PL",
    "name:fra_x_preferred":[
        "Wardomy"
    ],
    "name:pol_x_preferred":[
        "Wardomy"
    ],
    "name:ukr_x_preferred":[
        "\u0412\u0430\u0440\u0434\u043e\u043c\u0438"
    ],
    "name:und_x_variant":[
        "Wordommen",
        "Wardomy"
    ],
    "name:vie_x_preferred":[
        "Wardomy"
    ],
    "wof:name":"Wardomy",
    "wof:placetype":"locality"
},
  "geometry": {"coordinates":[20.90089,54.20659000000001],"type":"Point"}
}