{
  "type": "Feature",
  "properties": {
    "gn:admin1_code":"77.0",
    "gn:admin2_code":"1210.0",
    "gn:admin3_code":"121013.0",
    "gn:asciiname":"Mlodow",
    "gn:country_code":"PL",
    "gn:dem":361,
    "gn:feature_class":"P",
    "gn:feature_code":"PPL",
    "gn:name":"M\u0142od\u00f3w",
    "gn:population":0,
    "gn:timezone":"Europe/Warsaw",
    "iso:country":"PL",
    "name:pol_x_preferred":[
        "M\u0142od\u00f3w"
    ],
    "name:ukr_x_preferred":[
        "\u041c\u043b\u043e\u0434\u0443\u0432"
    ],
    "wof:name":"Mlodow",
    "wof:placetype":"locality"
},
  "geometry": {"coordinates":[20.69417,49.46858],"type":"Point"}
}