{
  "type": "Feature",
  "properties": {
    "gn:admin1_code":"81.0",
    "gn:admin2_code":"2006.0",
    "gn:admin3_code":"200605.0",
    "gn:asciiname":"Wilczewo",
    "gn:country_code":"PL",
    "gn:dem":139,
    "gn:feature_class":"P",
    "gn:feature_code":"PPL",
    "gn:name":"Wilczewo",
    "gn:population":0,
    "gn:timezone":"Europe/Warsaw",
    "iso:country":"PL",
    "name:ceb_x_preferred":[
        "Wilczewo"
    ],
    "name:lit_x_preferred":[
        "Vil\u010devas"
    ],
    "name:pol_x_preferred":[
        "Wilczewo"
    ],
    "name:ukr_x_preferred":[
        "\u0412\u0456\u043b\u044c\u0447\u0435\u0432\u043e"
    ],
    "wof:name":"Wilczewo",
    "wof:placetype":"locality"
},
  "geometry": {"coordinates":[22.10314,53.3437],"type":"Point"}
}