{
  "type": "Feature",
  "properties": {
    "gn:admin1_code":"75.0",
    "gn:admin2_code":"613.0",
    "gn:admin3_code":"61302.0",
    "gn:asciiname":"Kalinka",
    "gn:country_code":"PL",
    "gn:dem":153,
    "gn:feature_class":"P",
    "gn:feature_code":"PPL",
    "gn:name":"Kalinka",
    "gn:population":0,
    "gn:timezone":"Europe/Warsaw",
    "iso:country":"PL",
    "name:fra_x_preferred":[
        "Kalinka"
    ],
    "name:lit_x_preferred":[
        "Kalinka"
    ],
    "name:pol_x_preferred":[
        "Kalinka"
    ],
    "name:ukr_x_preferred":[
        "\u041a\u0430\u043b\u0456\u043d\u043a\u0430"
    ],
    "wof:name":"Kalinka",
    "wof:placetype":"locality"
},
  "geometry": {"coordinates":[23.112,51.67482],"type":"Point"}
}