{
  "type": "Feature",
  "properties": {
    "gn:admin1_code":"75.0",
    "gn:admin2_code":"611.0",
    "gn:admin3_code":"61109.0",
    "gn:asciiname":"Poplawy",
    "gn:country_code":"PL",
    "gn:dem":153,
    "gn:feature_class":"P",
    "gn:feature_code":"PPL",
    "gn:name":"Pop\u0142awy",
    "gn:population":0,
    "gn:timezone":"Europe/Warsaw",
    "iso:country":"PL",
    "wof:name":"Poplawy",
    "wof:placetype":"locality"
},
  "geometry": {"coordinates":[22.51869,51.99286],"type":"Point"}
}