{
  "type": "Feature",
  "properties": {
    "gn:admin1_code":"81.0",
    "gn:admin2_code":"2002.0",
    "gn:admin3_code":"200205.0",
    "gn:asciiname":"Baranki",
    "gn:country_code":"PL",
    "gn:dem":151,
    "gn:feature_class":"P",
    "gn:feature_code":"PPL",
    "gn:name":"Baranki",
    "gn:population":0,
    "gn:timezone":"Europe/Warsaw",
    "iso:country":"PL",
    "name:lit_x_preferred":[
        "Barankai"
    ],
    "name:pol_x_preferred":[
        "Baranki"
    ],
    "name:ukr_x_preferred":[
        "\u0411\u0430\u0440\u0430\u043d\u043a\u0456"
    ],
    "wof:name":"Baranki",
    "wof:placetype":"locality"
},
  "geometry": {"coordinates":[23.11345,52.94598000000001],"type":"Point"}
}