{
  "type": "Feature",
  "properties": {
    "gn:admin1_code":"83.0",
    "gn:admin2_code":"2407.0",
    "gn:admin3_code":"240706.0",
    "gn:asciiname":"Pilka",
    "gn:country_code":"PL",
    "gn:dem":260,
    "gn:feature_class":"P",
    "gn:feature_code":"PPL",
    "gn:name":"Pi\u0142ka",
    "gn:population":0,
    "gn:timezone":"Europe/Warsaw",
    "iso:country":"PL",
    "wof:name":"Pilka",
    "wof:placetype":"locality"
},
  "geometry": {"coordinates":[18.7662,50.62244000000001],"type":"Point"}
}