{
  "type": "Feature",
  "properties": {
    "gn:admin1_code":"78.0",
    "gn:admin2_code":"1409.0",
    "gn:admin3_code":"140903.0",
    "gn:asciiname":"Lipa Krepa",
    "gn:country_code":"PL",
    "gn:dem":156,
    "gn:feature_class":"P",
    "gn:feature_code":"PPL",
    "gn:name":"Lipa Kr\u0119pa",
    "gn:population":0,
    "gn:timezone":"Europe/Warsaw",
    "iso:country":"PL",
    "name:fra_x_preferred":[
        "Lipa-Kr\u0119pa"
    ],
    "name:pol_x_preferred":[
        "Lipa-Kr\u0119pa"
    ],
    "name:ukr_x_preferred":[
        "\u041b\u0456\u043f\u0430-\u041a\u0440\u0435\u043c\u043f\u0430"
    ],
    "name:und_x_variant":[
        "Lipa-Kr\u0119pa",
        "Lipa Kr\u0119pa"
    ],
    "wof:name":"Lipa Krepa",
    "wof:placetype":"locality"
},
  "geometry": {"coordinates":[21.60696,51.14915],"type":"Point"}
}