{
  "type": "Feature",
  "properties": {
    "gn:admin1_code":"87.0",
    "gn:admin2_code":"3202.0",
    "gn:admin3_code":"320205.0",
    "gn:asciiname":"Sarnik",
    "gn:country_code":"PL",
    "gn:dem":91,
    "gn:feature_class":"P",
    "gn:feature_code":"PPL",
    "gn:name":"Sarnik",
    "gn:population":0,
    "gn:timezone":"Europe/Warsaw",
    "iso:country":"PL",
    "name:und_x_variant":[
        "Rehfeld",
        "Sarnik"
    ],
    "wof:name":"Sarnik",
    "wof:placetype":"locality"
},
  "geometry": {"coordinates":[15.3067,53.00026999999999],"type":"Point"}
}