{
  "type": "Feature",
  "properties": {
    "gn:country":"PL",
    "gn:fcode":"PPLA3",
    "gn:population":1871,
    "iso:country":"PL",
    "name:azb_x_preferred":[
        "\u0644\u0633\u06a9\u06cc"
    ],
    "name:ceb_x_preferred":[
        "Lyski"
    ],
    "name:deu_x_preferred":[
        "Lyski"
    ],
    "name:fas_x_preferred":[
        "\u0644\u0633\u06a9\u06cc"
    ],
    "name:fra_x_preferred":[
        "Lyski"
    ],
    "name:nld_x_preferred":[
        "Lyski"
    ],
    "name:pol_x_preferred":[
        "Lyski"
    ],
    "name:ron_x_preferred":[
        "Lyski"
    ],
    "name:ukr_x_preferred":[
        "\u041b\u0438\u0441\u043a\u0456"
    ],
    "qs_pg:aaroncc":"PL",
    "qs_pg:gn_country":"PL",
    "qs_pg:gn_fcode":"PPLA3",
    "qs_pg:gn_pop":1871,
    "qs_pg:name":"Lyski",
    "qs_pg:name_adm0":"Polska",
    "qs_pg:name_adm1":"Sl\u0105skie",
    "qs_pg:photos_9k":1,
    "qs_pg:photos_9r":2,
    "qs_pg:photos_all":40,
    "qs_pg:photos_sr":0,
    "qs_pg:pop_sr":3,
    "qs_pg:qs_pg_placetype":"localadmin",
    "qs_pg:qs_pg_placetype_gp":"LocalAdmin",
    "qs_pg:woe_adm0":23424923,
    "woe:adm0_id":23424923,
    "woe:name_adm0":"Polska",
    "woe:name_adm1":"Sl\u0105skie",
    "woe:placetype":"LocalAdmin",
    "wof:name":"Lyski",
    "wof:placetype":"localadmin",
    "wof:population":1871
},
  "geometry": {"coordinates":[18.39146,50.11992],"type":"Point"}
}