{
  "type": "Feature",
  "properties": {
    "gn:admin1_code":"77.0",
    "gn:admin2_code":"1210.0",
    "gn:admin3_code":"121004.0",
    "gn:asciiname":"Kruzlowa",
    "gn:country_code":"PL",
    "gn:dem":364,
    "gn:feature_class":"P",
    "gn:feature_code":"PPL",
    "gn:name":"Kru\u017clowa",
    "gn:population":0,
    "gn:timezone":"Europe/Warsaw",
    "iso:country":"PL",
    "wof:name":"Kruzlowa",
    "wof:placetype":"locality"
},
  "geometry": {"coordinates":[20.88713,49.64628],"type":"Point"}
}