{
  "type": "Feature",
  "properties": {
    "gn:admin1_code":"74.0",
    "gn:admin2_code":"1061.0",
    "gn:admin3_code":"106101.0",
    "gn:asciiname":"Wiaczyn",
    "gn:country_code":"PL",
    "gn:dem":219,
    "gn:feature_class":"P",
    "gn:feature_code":"PPL",
    "gn:name":"Wi\u0105czyn",
    "gn:population":0,
    "gn:timezone":"Europe/Warsaw",
    "iso:country":"PL",
    "wof:name":"Wiaczyn",
    "wof:placetype":"neighbourhood"
},
  "geometry": {"coordinates":[19.61758,51.76703],"type":"Point"}
}