{
  "type": "Feature",
  "properties": {
    "gn:country":"PL",
    "gn:fcode":"PPL",
    "gn:population":0,
    "iso:country":"PL",
    "name:ast_x_preferred":[
        "Rzeczka"
    ],
    "name:eng_x_preferred":[
        "Rzeczka"
    ],
    "name:fra_x_preferred":[
        "Rzeczka"
    ],
    "name:nld_x_preferred":[
        "Rzeczka"
    ],
    "name:pol_x_preferred":[
        "Rzeczka"
    ],
    "name:ukr_x_preferred":[
        "\u0416\u0435\u0447\u043a\u0430"
    ],
    "qs_pg:aaroncc":"PL",
    "qs_pg:gn_country":"PL",
    "qs_pg:gn_fcode":"PPL",
    "qs_pg:gn_pop":0,
    "qs_pg:name":"Rzeczka",
    "qs_pg:name_adm0":"Polska",
    "qs_pg:name_adm1":"Dolnosl\u0105skie",
    "qs_pg:photos":29,
    "qs_pg:photos_1k":6,
    "qs_pg:photos_9k":1,
    "qs_pg:photos_9r":2,
    "qs_pg:photos_all":29,
    "qs_pg:photos_sr":2,
    "qs_pg:pop_sr":0,
    "qs_pg:qs_pg_placetype":"locality",
    "qs_pg:qs_pg_placetype_gp":"Town",
    "qs_pg:woe_adm0":23424923,
    "woe:adm0_id":23424923,
    "woe:name_adm0":"Polska",
    "woe:name_adm1":"Dolnosl\u0105skie",
    "woe:placetype":"Town",
    "wof:name":"Rzeczka",
    "wof:placetype":"locality"
},
  "geometry": {"coordinates":[16.45735,50.66927],"type":"Point"}
}