{
  "type": "Feature",
  "properties": {
    "gn:admin1_code":"83.0",
    "gn:admin2_code":"2411.0",
    "gn:admin3_code":"241108.0",
    "gn:asciiname":"Modzurow",
    "gn:country_code":"PL",
    "gn:dem":270,
    "gn:feature_class":"P",
    "gn:feature_code":"PPL",
    "gn:name":"Modzur\u00f3w",
    "gn:population":0,
    "gn:timezone":"Europe/Warsaw",
    "iso:country":"PL",
    "name:azb_x_preferred":[
        "\u0645\u0648\u0632\u0648\u0631\u0648\u0648"
    ],
    "name:ceb_x_preferred":[
        "Modzur\u00f3w"
    ],
    "name:deu_x_preferred":[
        "Modzur\u00f3w"
    ],
    "name:fas_x_preferred":[
        "\u0645\u0648\u0632\u0648\u0631\u0648\u0648"
    ],
    "name:nld_x_preferred":[
        "Modzur\u00f3w"
    ],
    "name:pol_x_preferred":[
        "Modzur\u00f3w"
    ],
    "name:ukr_x_preferred":[
        "\u041c\u043e\u0434\u0437\u0443\u0440\u0443\u0432"
    ],
    "wof:name":"Modzurow",
    "wof:placetype":"locality"
},
  "geometry": {"coordinates":[18.13202,50.15592],"type":"Point"}
}