{
  "type": "Feature",
  "properties": {
    "gn:admin1_code":"83.0",
    "gn:admin2_code":"2411.0",
    "gn:admin3_code":"241108.0",
    "gn:asciiname":"Modzurow",
    "gn:country_code":"PL",
    "gn:dem":270,
    "gn:feature_class":"P",
    "gn:feature_code":"PPL",
    "gn:name":"Modzur\u00f3w",
    "gn:population":0,
    "gn:timezone":"Europe/Warsaw",
    "iso:country":"PL",
    "name:und_x_variant":[
        "Modzur\u00f3w"
    ],
    "wof:name":"Modzurow",
    "wof:placetype":"locality"
},
  "geometry": {"coordinates":[18.13202,50.15592],"type":"Point"}
}