{
  "type": "Feature",
  "properties": {
    "gn:admin1_code":"81.0",
    "gn:admin2_code":"2012.0",
    "gn:admin3_code":"201209.0",
    "gn:asciiname":"Wysokie",
    "gn:country_code":"PL",
    "gn:dem":233,
    "gn:feature_class":"P",
    "gn:feature_code":"PPL",
    "gn:name":"Wysokie",
    "gn:population":49,
    "gn:timezone":"Europe/Warsaw",
    "iso:country":"PL",
    "wof:name":"Wysokie",
    "wof:placetype":"locality",
    "wof:population":49
},
  "geometry": {"coordinates":[22.92761,54.37066],"type":"Point"}
}