{
  "type": "Feature",
  "properties": {
    "gn:admin1_code":"86.0",
    "gn:admin2_code":"3022.0",
    "gn:admin3_code":"302202.0",
    "gn:asciiname":"Szymonki",
    "gn:country_code":"PL",
    "gn:dem":112,
    "gn:feature_class":"P",
    "gn:feature_code":"PPL",
    "gn:name":"Szymonki",
    "gn:population":0,
    "gn:timezone":"Europe/Warsaw",
    "iso:country":"PL",
    "name:fra_x_preferred":[
        "Szymonki"
    ],
    "name:pol_x_preferred":[
        "Szymonki"
    ],
    "name:ukr_x_preferred":[
        "\u0428\u0438\u043c\u043e\u043d\u043a\u0456"
    ],
    "wof:name":"Szymonki",
    "wof:placetype":"locality"
},
  "geometry": {"coordinates":[17.17032,51.6369],"type":"Point"}
}