{
  "type": "Feature",
  "properties": {
    "gn:admin1_code":"87.0",
    "gn:admin2_code":"3217.0",
    "gn:admin3_code":"321704.0",
    "gn:asciiname":"Strzaliny",
    "gn:country_code":"PL",
    "gn:dem":90,
    "gn:feature_class":"P",
    "gn:feature_code":"PPL",
    "gn:name":"Strzaliny",
    "gn:population":0,
    "gn:timezone":"Europe/Warsaw",
    "iso:country":"PL",
    "name:ceb_x_preferred":[
        "Strzaliny"
    ],
    "name:fra_x_preferred":[
        "Strzaliny"
    ],
    "name:pol_x_preferred":[
        "Strzaliny"
    ],
    "name:ukr_x_preferred":[
        "\u0421\u0442\u0448\u0430\u043b\u0456\u043d\u0438"
    ],
    "name:vie_x_preferred":[
        "Strzaliny"
    ],
    "wof:name":"Strzaliny",
    "wof:placetype":"locality"
},
  "geometry": {"coordinates":[16.21154,53.19149],"type":"Point"}
}