{
  "type": "Feature",
  "properties": {
    "gn:admin1_code":"85.0",
    "gn:admin2_code":"2815.0",
    "gn:admin3_code":"281505.0",
    "gn:asciiname":"Wilamowo",
    "gn:country_code":"PL",
    "gn:dem":109,
    "gn:feature_class":"P",
    "gn:feature_code":"PPL",
    "gn:name":"Wilamowo",
    "gn:population":0,
    "gn:timezone":"Europe/Warsaw",
    "iso:country":"PL",
    "name:fra_x_preferred":[
        "Wilamowo"
    ],
    "name:pol_x_preferred":[
        "Wilamowo"
    ],
    "name:ukr_x_preferred":[
        "\u0412\u0456\u043b\u044f\u043c\u043e\u0432\u043e"
    ],
    "name:und_x_variant":[
        "Gross Wilmsdorf",
        "Wilamowo"
    ],
    "wof:name":"Wilamowo",
    "wof:placetype":"locality"
},
  "geometry": {"coordinates":[19.77458,53.90176999999999],"type":"Point"}
}