{
  "type": "Feature",
  "properties": {
    "gn:admin1_code":"77.0",
    "gn:admin2_code":"1216.0",
    "gn:admin3_code":"121616.0",
    "gn:asciiname":"Podlesie",
    "gn:country_code":"PL",
    "gn:dem":350,
    "gn:feature_class":"P",
    "gn:feature_code":"PPL",
    "gn:name":"Podlesie",
    "gn:population":0,
    "gn:timezone":"Europe/Warsaw",
    "iso:country":"PL",
    "wof:name":"Podlesie",
    "wof:placetype":"locality"
},
  "geometry": {"coordinates":[21.22695,49.78458],"type":"Point"}
}