{
  "type": "Feature",
  "properties": {
    "gn:admin1_code":"78.0",
    "gn:admin2_code":"1415.0",
    "gn:admin3_code":"141510.0",
    "gn:asciiname":"Korczaki",
    "gn:country_code":"PL",
    "gn:dem":94,
    "gn:feature_class":"P",
    "gn:feature_code":"PPL",
    "gn:name":"Korczaki",
    "gn:population":0,
    "gn:timezone":"Europe/Warsaw",
    "iso:country":"PL",
    "name:fra_x_preferred":[
        "Korczaki"
    ],
    "name:pol_x_preferred":[
        "Korczaki"
    ],
    "name:ukr_x_preferred":[
        "\u041a\u043e\u0440\u0447\u0430\u043a\u0456"
    ],
    "wof:name":"Korczaki",
    "wof:placetype":"locality"
},
  "geometry": {"coordinates":[21.54282000000001,53.03543000000001],"type":"Point"}
}