{
  "type": "Feature",
  "properties": {
    "gn:admin1_code":"78.0",
    "gn:admin2_code":"1425.0",
    "gn:admin3_code":"142509.0",
    "gn:asciiname":"Kaszewska Wola",
    "gn:country_code":"PL",
    "gn:dem":157,
    "gn:feature_class":"P",
    "gn:feature_code":"PPL",
    "gn:name":"Kaszewska Wola",
    "gn:population":0,
    "gn:timezone":"Europe/Warsaw",
    "iso:country":"PL",
    "name:fra_x_preferred":[
        "Kaszewska Wola"
    ],
    "name:pol_x_preferred":[
        "Kaszewska Wola"
    ],
    "name:ukr_x_preferred":[
        "\u041a\u0430\u0448\u0435\u0432\u0441\u044c\u043a\u0430-\u0412\u043e\u043b\u044f"
    ],
    "name:und_x_variant":[
        "Kaszowska Wola"
    ],
    "wof:name":"Kaszewska Wola",
    "wof:placetype":"locality"
},
  "geometry": {"coordinates":[20.92572,51.51201],"type":"Point"}
}