{
  "type": "Feature",
  "properties": {
    "gn:admin1_code":"78.0",
    "gn:admin2_code":"1418.0",
    "gn:admin3_code":"141801.0",
    "gn:asciiname":"Sobikow",
    "gn:country_code":"PL",
    "gn:dem":106,
    "gn:feature_class":"P",
    "gn:feature_code":"PPL",
    "gn:name":"Sobik\u00f3w",
    "gn:population":0,
    "gn:timezone":"Europe/Warsaw",
    "iso:country":"PL",
    "name:fra_x_preferred":[
        "Sobik\u00f3w"
    ],
    "name:pol_x_preferred":[
        "Sobik\u00f3w"
    ],
    "name:ukr_x_preferred":[
        "\u0421\u043e\u0431\u0456\u043a\u0443\u0432"
    ],
    "wof:name":"Sobikow",
    "wof:placetype":"locality"
},
  "geometry": {"coordinates":[21.15383,51.97098],"type":"Point"}
}