{
  "type": "Feature",
  "properties": {
    "gn:admin1_code":"72.0",
    "gn:admin2_code":"214.0",
    "gn:admin3_code":"21402.0",
    "gn:asciiname":"Radzieszyn",
    "gn:country_code":"PL",
    "gn:dem":147,
    "gn:feature_class":"P",
    "gn:feature_code":"PPL",
    "gn:name":"Radzieszyn",
    "gn:population":0,
    "gn:timezone":"Europe/Warsaw",
    "iso:country":"PL",
    "name:pol_x_preferred":[
        "Radzieszyn"
    ],
    "name:ukr_x_preferred":[
        "\u0420\u0430\u0434\u0437\u0435\u0448\u0438\u043d"
    ],
    "wof:name":"Radzieszyn",
    "wof:placetype":"locality"
},
  "geometry": {"coordinates":[17.50809,51.05828],"type":"Point"}
}