{
  "type": "Feature",
  "properties": {
    "gn:admin1_code":"76.0",
    "gn:admin2_code":"801.0",
    "gn:admin3_code":"80103.0",
    "gn:asciiname":"Dzierzow",
    "gn:country_code":"PL",
    "gn:dem":18,
    "gn:feature_class":"P",
    "gn:feature_code":"PPL",
    "gn:name":"Dzierz\u00f3w",
    "gn:population":0,
    "gn:timezone":"Europe/Warsaw",
    "iso:country":"PL",
    "name:fra_x_preferred":[
        "Dzier\u017c\u00f3w"
    ],
    "name:pol_x_preferred":[
        "Dzier\u017c\u00f3w"
    ],
    "name:ukr_x_preferred":[
        "\u0414\u0437\u0435\u0440\u0436\u0443\u0432"
    ],
    "name:und_x_variant":[
        "Derschau",
        "Dzierz\u00f3w",
        "Dzier\u017c\u00f3w"
    ],
    "wof:name":"Dzierzow",
    "wof:placetype":"locality"
},
  "geometry": {"coordinates":[15.20451,52.66088000000001],"type":"Point"}
}