{
  "type": "Feature",
  "properties": {
    "gn:admin1_code":"75.0",
    "gn:admin2_code":"615.0",
    "gn:admin3_code":"61507.0",
    "gn:asciiname":"Gasiory",
    "gn:country_code":"PL",
    "gn:dem":157,
    "gn:feature_class":"P",
    "gn:feature_code":"PPL",
    "gn:name":"G\u0105siory",
    "gn:population":0,
    "gn:timezone":"Europe/Warsaw",
    "iso:country":"PL",
    "name:fra_x_preferred":[
        "G\u0105siory"
    ],
    "name:pol_x_preferred":[
        "G\u0105siory"
    ],
    "name:ukr_x_preferred":[
        "\u0490\u043e\u043d\u0441\u044c\u043e\u0440\u0438"
    ],
    "wof:name":"Gasiory",
    "wof:placetype":"locality"
},
  "geometry": {"coordinates":[22.53201,51.85989],"type":"Point"}
}