{
  "type": "Feature",
  "properties": {
    "gn:gn_country":"PL",
    "gn:gn_fcode":"PPLA3",
    "gn:gn_pop":528,
    "gn:population":528,
    "iso:country":"PL",
    "name:azb_x_preferred":[
        "\u06a9\u0644\u0648\u0648\u0648"
    ],
    "name:ceb_x_preferred":[
        "Klw\u00f3w"
    ],
    "name:deu_x_preferred":[
        "Klw\u00f3w"
    ],
    "name:fas_x_preferred":[
        "\u06a9\u0644\u0648\u0648\u0648"
    ],
    "name:fra_x_preferred":[
        "Klw\u00f3w"
    ],
    "name:heb_x_preferred":[
        "\u05e7\u05dc\u05d1\u05d5\u05d1"
    ],
    "name:nld_x_preferred":[
        "Klw\u00f3w"
    ],
    "name:pol_x_preferred":[
        "Klw\u00f3w"
    ],
    "name:ukr_x_preferred":[
        "\u041a\u043b\u044c\u0432\u0443\u0432"
    ],
    "qs_pg:aaroncc":"PL",
    "qs_pg:gn_country":"PL",
    "qs_pg:gn_fcode":"PPLA3",
    "qs_pg:gn_pop":528,
    "qs_pg:name":"Klw\u00f3w",
    "qs_pg:name_adm0":"Polska",
    "qs_pg:name_adm1":"Mazowieckie",
    "qs_pg:photos_9r":0,
    "qs_pg:photos_sr":0,
    "qs_pg:pop_sr":2,
    "qs_pg:qs_pg_placetype":"localadmin",
    "qs_pg:qs_pg_placetype_gp":"LocalAdmin",
    "qs_pg:woe_adm0":23424923,
    "woe:adm0_id":23424923,
    "woe:name_adm0":"Polska",
    "woe:name_adm1":"Mazowieckie",
    "woe:placetype":"LocalAdmin",
    "wof:name":"Klw\u00f3w",
    "wof:placetype":"localadmin",
    "wof:population":528
},
  "geometry": {"coordinates":[20.63644,51.53448],"type":"Point"}
}