{
  "type": "Feature",
  "properties": {
    "gn:admin1_code":"80.0",
    "gn:admin2_code":"1805.0",
    "gn:admin3_code":"180511.0",
    "gn:asciiname":"Umieszcz",
    "gn:country_code":"PL",
    "gn:dem":260,
    "gn:feature_class":"P",
    "gn:feature_code":"PPL",
    "gn:name":"Umieszcz",
    "gn:population":0,
    "gn:timezone":"Europe/Warsaw",
    "iso:country":"PL",
    "wof:name":"Umieszcz",
    "wof:placetype":"locality"
},
  "geometry": {"coordinates":[21.55409,49.71381],"type":"Point"}
}