{
  "type": "Feature",
  "properties": {
    "gn:admin1_code":"86.0",
    "gn:admin2_code":"3010.0",
    "gn:admin3_code":"301013.0",
    "gn:asciiname":"Romanowo",
    "gn:country_code":"PL",
    "gn:dem":108,
    "gn:feature_class":"P",
    "gn:feature_code":"PPL",
    "gn:name":"Romanowo",
    "gn:population":0,
    "gn:timezone":"Europe/Warsaw",
    "iso:country":"PL",
    "name:deu_x_preferred":[
        "Romanowo"
    ],
    "name:fra_x_preferred":[
        "Romanowo"
    ],
    "name:nld_x_preferred":[
        "Romanowo"
    ],
    "name:pol_x_preferred":[
        "Romanowo"
    ],
    "name:ukr_x_preferred":[
        "\u0420\u043e\u043c\u0430\u043d\u043e\u0432\u043e"
    ],
    "wof:name":"Romanowo",
    "wof:placetype":"locality"
},
  "geometry": {"coordinates":[18.61667000000001,52.45],"type":"Point"}
}