{
  "type": "Feature",
  "properties": {
    "gn:admin1_code":"82.0",
    "gn:admin2_code":"2211.0",
    "gn:admin3_code":"221106.0",
    "gn:asciiname":"Sulicice",
    "gn:country_code":"PL",
    "gn:dem":31,
    "gn:feature_class":"P",
    "gn:feature_code":"PPL",
    "gn:name":"Sulicice",
    "gn:population":0,
    "gn:timezone":"Europe/Warsaw",
    "iso:country":"PL",
    "name:ceb_x_preferred":[
        "Sulicice"
    ],
    "name:csb_x_preferred":[
        "S\u00ebl\u00ebc\u00ebce"
    ],
    "name:fra_x_preferred":[
        "Sulicice"
    ],
    "name:pol_x_preferred":[
        "Sulicice"
    ],
    "name:ukr_x_preferred":[
        "\u0421\u0443\u043b\u0456\u0446\u0438\u0446\u0435"
    ],
    "wof:name":"Sulicice",
    "wof:placetype":"locality"
},
  "geometry": {"coordinates":[18.21739,54.77352],"type":"Point"}
}