{
  "type": "Feature",
  "properties": {
    "gn:admin1_code":"81.0",
    "gn:admin2_code":"2002.0",
    "gn:admin3_code":"200207.0",
    "gn:asciiname":"Planty",
    "gn:country_code":"PL",
    "gn:dem":146,
    "gn:feature_class":"P",
    "gn:feature_code":"PPL",
    "gn:name":"Planty",
    "gn:population":0,
    "gn:timezone":"Europe/Warsaw",
    "iso:country":"PL",
    "name:lit_x_preferred":[
        "Plantai"
    ],
    "name:pol_x_preferred":[
        "Planty"
    ],
    "name:ukr_x_preferred":[
        "\u041f\u043b\u044f\u043d\u0442\u0438"
    ],
    "wof:name":"Planty",
    "wof:placetype":"locality"
},
  "geometry": {"coordinates":[23.66104,52.96446],"type":"Point"}
}