{
  "type": "Feature",
  "properties": {
    "gn:admin1_code":"73.0",
    "gn:admin2_code":"410.0",
    "gn:admin3_code":"41003.0",
    "gn:asciiname":"Karnowko",
    "gn:country_code":"PL",
    "gn:dem":106,
    "gn:feature_class":"P",
    "gn:feature_code":"PPL",
    "gn:name":"Karn\u00f3wko",
    "gn:population":0,
    "gn:timezone":"Europe/Warsaw",
    "iso:country":"PL",
    "name:pol_x_preferred":[
        "Karn\u00f3wko"
    ],
    "name:ukr_x_preferred":[
        "\u041a\u0430\u0440\u043d\u0443\u0432\u043a\u043e"
    ],
    "name:und_x_variant":[
        "Altlinden",
        "Karn\u00f3wko"
    ],
    "wof:name":"Karnowko",
    "wof:placetype":"locality"
},
  "geometry": {"coordinates":[17.61731,53.18688],"type":"Point"}
}