{
  "type": "Feature",
  "properties": {
    "gn:gn_country":"PL",
    "gn:gn_fcode":"PPLA3",
    "gn:gn_pop":452,
    "gn:population":452,
    "iso:country":"PL",
    "name:eng_x_preferred":[
        "Gmina Kije"
    ],
    "name:glv_x_preferred":[
        "Baljaght Kije"
    ],
    "name:por_x_preferred":[
        "Comuna de Kije"
    ],
    "name:rus_x_preferred":[
        "\u041a\u0438\u0439\u0435"
    ],
    "name:slk_x_preferred":[
        "Gmina Kije"
    ],
    "name:ukr_x_preferred":[
        "\u0490\u043c\u0456\u043d\u0430 \u041a\u0456\u0454"
    ],
    "name:war_x_preferred":[
        "Gmina Kije"
    ],
    "qs_pg:aaroncc":"PL",
    "qs_pg:gn_country":"PL",
    "qs_pg:gn_fcode":"PPLA3",
    "qs_pg:gn_pop":452,
    "qs_pg:name":"Kije",
    "qs_pg:name_adm0":"Polska",
    "qs_pg:name_adm1":"Swi\u0119tokrzyskie",
    "qs_pg:photos_9k":1,
    "qs_pg:photos_9r":1,
    "qs_pg:photos_all":4,
    "qs_pg:photos_sr":0,
    "qs_pg:pop_sr":2,
    "qs_pg:qs_pg_placetype":"localadmin",
    "qs_pg:qs_pg_placetype_gp":"LocalAdmin",
    "qs_pg:woe_adm0":23424923,
    "woe:adm0_id":23424923,
    "woe:name_adm0":"Polska",
    "woe:name_adm1":"Swi\u0119tokrzyskie",
    "woe:placetype":"LocalAdmin",
    "wof:name":"Kije",
    "wof:placetype":"localadmin",
    "wof:population":452
},
  "geometry": {"coordinates":[20.57121,50.60721],"type":"Point"}
}