{
  "type": "Feature",
  "properties": {
    "gn:admin1_code":"85.0",
    "gn:admin2_code":"2815.0",
    "gn:admin3_code":"281505.0",
    "gn:asciiname":"Surzyki Wielkie",
    "gn:country_code":"PL",
    "gn:dem":117,
    "gn:feature_class":"P",
    "gn:feature_code":"PPL",
    "gn:name":"Surzyki Wielkie",
    "gn:population":0,
    "gn:timezone":"Europe/Warsaw",
    "iso:country":"PL",
    "name:fra_x_preferred":[
        "Surzyki Wielkie"
    ],
    "name:pol_x_preferred":[
        "Surzyki Wielkie"
    ],
    "name:ukr_x_preferred":[
        "\u0421\u0443\u0436\u0438\u043a\u0456-\u0412\u0435\u043b\u0438\u043a\u0456"
    ],
    "name:und_x_variant":[
        "Gross Sauerken"
    ],
    "wof:name":"Surzyki Wielkie",
    "wof:placetype":"locality"
},
  "geometry": {"coordinates":[19.76215,53.82673000000001],"type":"Point"}
}