{
  "type": "Feature",
  "properties": {
    "gn:admin1_code":"87.0",
    "gn:admin2_code":"3216.0",
    "gn:admin3_code":"321604.0",
    "gn:asciiname":"Batyn",
    "gn:country_code":"PL",
    "gn:dem":122,
    "gn:feature_class":"P",
    "gn:feature_code":"PPL",
    "gn:name":"Baty\u0144",
    "gn:population":0,
    "gn:timezone":"Europe/Warsaw",
    "iso:country":"PL",
    "name:azb_x_preferred":[
        "\u0628\u0627\u062a\u0646\u0642"
    ],
    "name:ceb_x_preferred":[
        "Baty\u0144"
    ],
    "name:deu_x_preferred":[
        "Baty\u0144"
    ],
    "name:fas_x_preferred":[
        "\u0628\u0627\u062a\u0646\u06af"
    ],
    "name:nld_x_preferred":[
        "Baty\u0144"
    ],
    "name:pol_x_preferred":[
        "Baty\u0144"
    ],
    "name:ukr_x_preferred":[
        "\u0411\u0430\u0442\u0438\u043d\u044c"
    ],
    "name:vie_x_preferred":[
        "Baty\u0144"
    ],
    "wof:name":"Batyn",
    "wof:placetype":"locality"
},
  "geometry": {"coordinates":[15.88927,53.88091],"type":"Point"}
}