{
  "type": "Feature",
  "properties": {
    "gn:gn_country":"PL",
    "gn:gn_fcode":"PPL",
    "gn:gn_pop":560,
    "gn:population":560,
    "iso:country":"PL",
    "name:eng_x_preferred":[
        "Trute"
    ],
    "name:fra_x_preferred":[
        "Trute"
    ],
    "name:pol_x_preferred":[
        "Trute"
    ],
    "name:urd_x_preferred":[
        "\u062a\u0631\u0648\u062a\u06d2"
    ],
    "qs_pg:aaroncc":"PL",
    "qs_pg:gn_country":"PL",
    "qs_pg:gn_fcode":"PPL",
    "qs_pg:gn_pop":560,
    "qs_pg:name":"Trute",
    "qs_pg:photos_9r":0,
    "qs_pg:photos_sr":0,
    "qs_pg:pop_sr":2,
    "qs_pg:qs_pg_placetype":"locality",
    "wof:name":"Trute",
    "wof:placetype":"locality",
    "wof:population":560
},
  "geometry": {"coordinates":[19.96808,49.49188],"type":"Point"}
}