{
  "type": "Feature",
  "properties": {
    "gn:admin1_code":"81.0",
    "gn:admin2_code":"2009.0",
    "gn:admin3_code":"200905.0",
    "gn:asciiname":"Sumowo",
    "gn:country_code":"PL",
    "gn:dem":140,
    "gn:feature_class":"P",
    "gn:feature_code":"PPL",
    "gn:name":"Sumowo",
    "gn:population":0,
    "gn:timezone":"Europe/Warsaw",
    "iso:country":"PL",
    "wof:name":"Sumowo",
    "wof:placetype":"locality"
},
  "geometry": {"coordinates":[23.28617,54.08134],"type":"Point"}
}