{
  "type": "Feature",
  "properties": {
    "gn:admin1_code":"81.0",
    "gn:admin2_code":"2009.0",
    "gn:admin3_code":"200905.0",
    "gn:asciiname":"Sumowo",
    "gn:country_code":"PL",
    "gn:dem":140,
    "gn:feature_class":"P",
    "gn:feature_code":"PPL",
    "gn:name":"Sumowo",
    "gn:population":0,
    "gn:timezone":"Europe/Warsaw",
    "iso:country":"PL",
    "name:deu_x_preferred":[
        "Sumowo"
    ],
    "name:lit_x_preferred":[
        "Sumavas"
    ],
    "name:nld_x_preferred":[
        "Sumowo"
    ],
    "name:pol_x_preferred":[
        "Sumowo"
    ],
    "name:ukr_x_preferred":[
        "\u0421\u0443\u043c\u043e\u0432\u043e"
    ],
    "wof:name":"Sumowo",
    "wof:placetype":"locality"
},
  "geometry": {"coordinates":[23.28617,54.08134],"type":"Point"}
}