{
  "type": "Feature",
  "properties": {
    "gn:admin1_code":"82.0",
    "gn:admin2_code":"2204.0",
    "gn:admin3_code":"220405.0",
    "gn:asciiname":"Marszewo",
    "gn:cc2":"PL",
    "gn:country_code":"PL",
    "gn:dem":212,
    "gn:feature_class":"P",
    "gn:feature_code":"PPL",
    "gn:name":"Marszewo",
    "gn:population":0,
    "gn:timezone":"Europe/Warsaw",
    "iso:country":"PL",
    "name:pol_x_preferred":[
        "Marszewo"
    ],
    "name:ukr_x_preferred":[
        "\u041c\u0430\u0440\u0448\u0435\u0432\u043e"
    ],
    "name:und_x_variant":[
        "Marschau"
    ],
    "wof:name":"Marszewo",
    "wof:placetype":"locality"
},
  "geometry": {"coordinates":[18.38333,54.26667],"type":"Point"}
}