{
  "type": "Feature",
  "properties": {
    "gn:admin1_code":"74.0",
    "gn:admin2_code":"1001.0",
    "gn:admin3_code":"100103.0",
    "gn:asciiname":"Rozniatowice",
    "gn:country_code":"PL",
    "gn:dem":213,
    "gn:feature_class":"P",
    "gn:feature_code":"PPL",
    "gn:name":"Ro\u017cniatowice",
    "gn:population":0,
    "gn:timezone":"Europe/Warsaw",
    "iso:country":"PL",
    "name:und_x_variant":[
        "Ro\u017cniatowice"
    ],
    "wof:name":"Rozniatowice",
    "wof:placetype":"locality"
},
  "geometry": {"coordinates":[19.32938,51.43858],"type":"Point"}
}