{
  "type": "Feature",
  "properties": {
    "gn:admin1_code":"85.0",
    "gn:admin2_code":"2816.0",
    "gn:admin3_code":"281602.0",
    "gn:asciiname":"Okartowo",
    "gn:country_code":"PL",
    "gn:dem":122,
    "gn:feature_class":"P",
    "gn:feature_code":"PPL",
    "gn:name":"Okartowo",
    "gn:population":0,
    "gn:timezone":"Europe/Warsaw",
    "iso:country":"PL",
    "name:deu_x_preferred":[
        "Okartowo"
    ],
    "name:pol_x_preferred":[
        "Okartowo"
    ],
    "name:ukr_x_preferred":[
        "\u041e\u043a\u0430\u0440\u0442\u043e\u0432\u043e"
    ],
    "name:und_x_variant":[
        "Eckersberg"
    ],
    "name:vie_x_preferred":[
        "Okartowo"
    ],
    "wof:name":"Okartowo",
    "wof:placetype":"locality"
},
  "geometry": {"coordinates":[21.85715,53.80566],"type":"Point"}
}