{
  "type": "Feature",
  "properties": {
    "gn:admin1_code":"78.0",
    "gn:admin2_code":"1433.0",
    "gn:admin3_code":"143309.0",
    "gn:asciiname":"Strupiechow",
    "gn:country_code":"PL",
    "gn:dem":128,
    "gn:feature_class":"P",
    "gn:feature_code":"PPL",
    "gn:name":"Strupiech\u00f3w",
    "gn:population":0,
    "gn:timezone":"Europe/Warsaw",
    "iso:country":"PL",
    "name:ceb_x_preferred":[
        "Strupiech\u00f3w"
    ],
    "name:fra_x_preferred":[
        "Strupiech\u00f3w"
    ],
    "name:pol_x_preferred":[
        "Strupiech\u00f3w"
    ],
    "name:ukr_x_preferred":[
        "\u0421\u0442\u0440\u0443\u043f\u0435\u0445\u0443\u0432"
    ],
    "wof:name":"Strupiechow",
    "wof:placetype":"locality"
},
  "geometry": {"coordinates":[21.92514,52.33664],"type":"Point"}
}