{
  "type": "Feature",
  "properties": {
    "gn:country":"PL",
    "gn:fcode":"PPL",
    "gn:population":52,
    "iso:country":"PL",
    "name:ceb_x_preferred":[
        "Ostrowite"
    ],
    "name:deu_x_preferred":[
        "Ostrowite"
    ],
    "name:fra_x_preferred":[
        "Ostrowite"
    ],
    "name:nld_x_preferred":[
        "Ostrowite"
    ],
    "name:pol_x_preferred":[
        "Ostrowite"
    ],
    "name:ukr_x_preferred":[
        "\u041e\u0441\u0442\u0440\u043e\u0432\u0456\u0442\u0435"
    ],
    "qs_pg:aaroncc":"PL",
    "qs_pg:gn_country":"PL",
    "qs_pg:gn_fcode":"PPL",
    "qs_pg:gn_pop":52,
    "qs_pg:name":"Ostrowite",
    "qs_pg:name_adm0":"Polska",
    "qs_pg:name_adm1":"Pomorskie",
    "qs_pg:photos_9k":1,
    "qs_pg:photos_9r":1,
    "qs_pg:photos_all":11,
    "qs_pg:photos_sr":0,
    "qs_pg:pop_sr":1,
    "qs_pg:qs_pg_placetype":"locality",
    "qs_pg:qs_pg_placetype_gp":"Town",
    "qs_pg:woe_adm0":23424923,
    "woe:adm0_id":23424923,
    "woe:name_adm0":"Polska",
    "woe:name_adm1":"Pomorskie",
    "woe:placetype":"Town",
    "wof:name":"Ostrowite",
    "wof:placetype":"locality",
    "wof:population":52
},
  "geometry": {"coordinates":[18.03148,53.75054],"type":"Point"}
}