{
  "type": "Feature",
  "properties": {
    "gn:admin1_code":"84.0",
    "gn:admin2_code":"2601.0",
    "gn:admin3_code":"260101.0",
    "gn:asciiname":"Skotniki",
    "gn:country_code":"PL",
    "gn:dem":228,
    "gn:feature_class":"P",
    "gn:feature_code":"PPL",
    "gn:name":"Skotniki",
    "gn:population":0,
    "gn:timezone":"Europe/Warsaw",
    "iso:country":"PL",
    "name:dan_x_preferred":[
        "Skotniki"
    ],
    "name:fra_x_preferred":[
        "Skotniki"
    ],
    "name:pol_x_preferred":[
        "Skotniki"
    ],
    "name:ukr_x_preferred":[
        "\u0421\u043a\u043e\u0442\u043d\u0438\u043a\u0438"
    ],
    "wof:name":"Skotniki",
    "wof:placetype":"locality"
},
  "geometry": {"coordinates":[20.78333,50.43333],"type":"Point"}
}