{
  "type": "Feature",
  "properties": {
    "gn:admin1_code":"79.0",
    "gn:admin2_code":"1609.0",
    "gn:admin3_code":"160910.0",
    "gn:asciiname":"Folwark",
    "gn:country_code":"PL",
    "gn:dem":157,
    "gn:feature_class":"P",
    "gn:feature_code":"PPL",
    "gn:name":"Folwark",
    "gn:population":0,
    "gn:timezone":"Europe/Warsaw",
    "iso:country":"PL",
    "name:azb_x_preferred":[
        "\u0641\u0648\u0644\u0648\u0627\u0631\u06a9"
    ],
    "name:deu_x_preferred":[
        "Follwark"
    ],
    "name:fas_x_preferred":[
        "\u0641\u0648\u0644\u0648\u0627\u0631\u06a9"
    ],
    "name:pol_x_preferred":[
        "Folwark"
    ],
    "name:ukr_x_preferred":[
        "\u0424\u043e\u043b\u044c\u0432\u0430\u0440\u043a"
    ],
    "wof:name":"Folwark",
    "wof:placetype":"locality"
},
  "geometry": {"coordinates":[17.92602,50.62256],"type":"Point"}
}