{
  "type": "Feature",
  "properties": {
    "gn:admin1_code":"81.0",
    "gn:admin2_code":"2002.0",
    "gn:admin3_code":"200214.0",
    "gn:asciiname":"Zacisze",
    "gn:country_code":"PL",
    "gn:dem":155,
    "gn:feature_class":"P",
    "gn:feature_code":"PPL",
    "gn:name":"Zacisze",
    "gn:population":0,
    "gn:timezone":"Europe/Warsaw",
    "iso:country":"PL",
    "name:fra_x_preferred":[
        "Zacisze"
    ],
    "name:lit_x_preferred":[
        "Zaci\u0161\u0117"
    ],
    "name:pol_x_preferred":[
        "Zacisze"
    ],
    "name:ukr_x_preferred":[
        "\u0417\u0430\u0446\u0438\u0448\u0435"
    ],
    "wof:name":"Zacisze",
    "wof:placetype":"locality"
},
  "geometry": {"coordinates":[23.37198,53.07328],"type":"Point"}
}