{
  "type": "Feature",
  "properties": {
    "gn:admin1_code":"85.0",
    "gn:admin2_code":"2813.0",
    "gn:admin3_code":"281306.0",
    "gn:asciiname":"Kleszczewo",
    "gn:country_code":"PL",
    "gn:dem":141,
    "gn:feature_class":"P",
    "gn:feature_code":"PPL",
    "gn:name":"Kleszczewo",
    "gn:population":0,
    "gn:timezone":"Europe/Warsaw",
    "iso:country":"PL",
    "name:deu_x_preferred":[
        "Kleszczewo"
    ],
    "name:pol_x_preferred":[
        "Kleszczewo"
    ],
    "name:ukr_x_preferred":[
        "\u041a\u043b\u0435\u0449\u0435\u0432\u043e"
    ],
    "name:und_x_variant":[
        "Klesz\u00f6wen",
        "Klesch\u00f6wen",
        "Kleschen",
        "Kleszczewo"
    ],
    "wof:name":"Kleszczewo",
    "wof:placetype":"locality"
},
  "geometry": {"coordinates":[22.55692,53.92669],"type":"Point"}
}