{
  "type": "Feature",
  "properties": {
    "gn:admin1_code":"81.0",
    "gn:admin2_code":"2011.0",
    "gn:admin3_code":"201109.0",
    "gn:asciiname":"Sucha Gora",
    "gn:country_code":"PL",
    "gn:dem":170,
    "gn:feature_class":"P",
    "gn:feature_code":"PPL",
    "gn:name":"Sucha G\u00f3ra",
    "gn:population":0,
    "gn:timezone":"Europe/Warsaw",
    "iso:country":"PL",
    "name:lit_x_preferred":[
        "Sucha Gura"
    ],
    "name:pol_x_preferred":[
        "Sucha G\u00f3ra"
    ],
    "name:ukr_x_preferred":[
        "\u0421\u0443\u0445\u0430-\u0490\u0443\u0440\u0430"
    ],
    "wof:name":"Sucha Gora",
    "wof:placetype":"locality"
},
  "geometry": {"coordinates":[23.24769,53.53382],"type":"Point"}
}