{
  "type": "Feature",
  "properties": {
    "gn:admin1_code":"78.0",
    "gn:admin2_code":"1419.0",
    "gn:admin3_code":"141901.0",
    "gn:asciiname":"Jozinek",
    "gn:country_code":"PL",
    "gn:dem":149,
    "gn:feature_class":"P",
    "gn:feature_code":"PPL",
    "gn:name":"J\u00f3zinek",
    "gn:population":0,
    "gn:timezone":"Europe/Warsaw",
    "iso:country":"PL",
    "name:und_x_variant":[
        "J\u00f3zinek"
    ],
    "wof:name":"Jozinek",
    "wof:placetype":"locality"
},
  "geometry": {"coordinates":[19.84224,52.61639],"type":"Point"}
}