{
  "type": "Feature",
  "properties": {
    "gn:admin1_code":"82.0",
    "gn:admin2_code":"2212.0",
    "gn:admin3_code":"221204.0",
    "gn:asciiname":"Gorzyno",
    "gn:country_code":"PL",
    "gn:dem":52,
    "gn:feature_class":"P",
    "gn:feature_code":"PPL",
    "gn:name":"Gorzyno",
    "gn:population":0,
    "gn:timezone":"Europe/Warsaw",
    "iso:country":"PL",
    "name:ceb_x_preferred":[
        "Gorzyno"
    ],
    "name:csb_x_preferred":[
        "G\u00f3rz\u00ebno"
    ],
    "name:deu_x_preferred":[
        "G\u00f3rzyno"
    ],
    "name:nld_x_preferred":[
        "G\u00f3rzyno"
    ],
    "name:pol_x_preferred":[
        "Gorzyno"
    ],
    "name:ukr_x_preferred":[
        "\u0490\u043e\u0436\u0438\u043d\u043e"
    ],
    "wof:name":"Gorzyno",
    "wof:placetype":"locality"
},
  "geometry": {"coordinates":[17.49387999999999,54.55509],"type":"Point"}
}