{
  "type": "Feature",
  "properties": {
    "gn:admin1_code":"78.0",
    "gn:admin2_code":"1419.0",
    "gn:admin3_code":"141906.0",
    "gn:asciiname":"Jadwigow",
    "gn:country_code":"PL",
    "gn:dem":107,
    "gn:feature_class":"P",
    "gn:feature_code":"PPL",
    "gn:name":"Jadwig\u00f3w",
    "gn:population":0,
    "gn:timezone":"Europe/Warsaw",
    "iso:country":"PL",
    "wof:name":"Jadwigow",
    "wof:placetype":"locality"
},
  "geometry": {"coordinates":[19.77244,52.36536],"type":"Point"}
}