{
  "type": "Feature",
  "properties": {
    "gn:admin1_code":"72.0",
    "gn:admin2_code":"204.0",
    "gn:admin3_code":"20401.0",
    "gn:asciiname":"Osetno",
    "gn:country_code":"PL",
    "gn:dem":93,
    "gn:feature_class":"P",
    "gn:feature_code":"PPL",
    "gn:name":"Osetno",
    "gn:population":0,
    "gn:timezone":"Europe/Warsaw",
    "iso:country":"PL",
    "name:ceb_x_preferred":[
        "Osetno"
    ],
    "name:pol_x_preferred":[
        "Osetno"
    ],
    "name:ukr_x_preferred":[
        "\u041e\u0441\u0435\u0442\u043d\u043e"
    ],
    "wof:name":"Osetno",
    "wof:placetype":"locality"
},
  "geometry": {"coordinates":[16.45577999999999,51.63655],"type":"Point"}
}