{
  "type": "Feature",
  "properties": {
    "gn:admin1_code":"85.0",
    "gn:admin2_code":"2819.0",
    "gn:admin3_code":"281901.0",
    "gn:asciiname":"Zabrost Wielki",
    "gn:country_code":"PL",
    "gn:dem":99,
    "gn:feature_class":"P",
    "gn:feature_code":"PPL",
    "gn:name":"Zabrost Wielki",
    "gn:population":0,
    "gn:timezone":"Europe/Warsaw",
    "iso:country":"PL",
    "name:deu_x_preferred":[
        "Zabrost Wielki"
    ],
    "name:pol_x_preferred":[
        "Zabrost Wielki"
    ],
    "name:ukr_x_preferred":[
        "\u0417\u0430\u0431\u0440\u043e\u0441\u0442-\u0412\u0435\u043b\u0438\u043a\u0438\u0439"
    ],
    "name:und_x_variant":[
        "Gross Sobrost",
        "Zabrost Wielkie",
        "Sobrost Wielki"
    ],
    "name:urd_x_preferred":[
        "\u0632\u0628\u0631\u0648\u0633\u0679 \u0648\u06cc\u0644\u06a9\u06cc"
    ],
    "name:vie_x_preferred":[
        "Zabrost Wielki"
    ],
    "wof:name":"Zabrost Wielki",
    "wof:placetype":"locality"
},
  "geometry": {"coordinates":[21.92459,54.32704],"type":"Point"}
}