{
  "type": "Feature",
  "properties": {
    "gn:admin1_code":"85.0",
    "gn:admin2_code":"2819.0",
    "gn:admin3_code":"281901.0",
    "gn:asciiname":"Zabrost Wielki",
    "gn:country_code":"PL",
    "gn:dem":99,
    "gn:feature_class":"P",
    "gn:feature_code":"PPL",
    "gn:name":"Zabrost Wielki",
    "gn:population":0,
    "gn:timezone":"Europe/Warsaw",
    "iso:country":"PL",
    "name:und_x_variant":[
        "Gross Sobrost",
        "Zabrost Wielkie",
        "Sobrost Wielki",
        "Zabrost Wielki"
    ],
    "wof:name":"Zabrost Wielki",
    "wof:placetype":"locality"
},
  "geometry": {"coordinates":[21.92459,54.32704],"type":"Point"}
}