{
  "type": "Feature",
  "properties": {
    "gn:admin1_code":"81.0",
    "gn:admin2_code":"2003.0",
    "gn:admin3_code":"200308.0",
    "gn:asciiname":"Niewino Lesne",
    "gn:country_code":"PL",
    "gn:dem":138,
    "gn:feature_class":"P",
    "gn:feature_code":"PPL",
    "gn:name":"Niewino Le\u015bne",
    "gn:population":0,
    "gn:timezone":"Europe/Warsaw",
    "iso:country":"PL",
    "name:lit_x_preferred":[
        "Nevino Le\u0161n\u0117"
    ],
    "name:pol_x_preferred":[
        "Niewino Le\u015bne"
    ],
    "name:ukr_x_preferred":[
        "\u041d\u0435\u0432\u0456\u043d\u043e-\u041b\u0435\u0441\u044c\u043d\u0435"
    ],
    "name:und_x_variant":[
        "Niewino Le\u015bne"
    ],
    "wof:name":"Niewino Lesne",
    "wof:placetype":"locality"
},
  "geometry": {"coordinates":[23.04786,52.81948000000001],"type":"Point"}
}