{
  "type": "Feature",
  "properties": {
    "iso:country":"PL",
    "name:deu_x_historical":[
        "Burgweide bei Breslau"
    ],
    "name:deu_x_preferred":[
        "Burgweide bei Breslau"
    ],
    "name:pol_x_colloquial":[
        "Soltysowice"
    ],
    "name:pol_x_preferred":[
        "Sotysowice"
    ],
    "name:pol_x_variant":[
        "Burgweide",
        "Schottwitz"
    ],
    "qs:gn_adm0_cc":"PL",
    "qs:gn_fcode":"PPL",
    "qs:gn_local":3081368,
    "qs:gn_namadm1":"72",
    "qs:gn_name":"So\u0142tysowice",
    "qs:local_max":3187,
    "qs:local_sum":10994,
    "qs:localhoods":7,
    "qs:name":"Sotysowice",
    "qs:name_adm0":"Polska",
    "qs:name_adm1":"Dolnosl\u0105skie",
    "qs:name_adm2":"Wroclaw",
    "qs:name_lau":"Wroclaw",
    "qs:name_local":"Wroclaw",
    "qs:photo_max":103,
    "qs:photo_sum":1270,
    "qs:placetype":"Suburb",
    "qs:quad_count":123,
    "qs:woe_adm0":23424923,
    "qs:woe_adm1":12577935,
    "qs:woe_adm2":12591160,
    "qs:woe_lau":12618090,
    "qs:woe_local":12618090,
    "qs:woe_ver":"7.10.0",
    "wof:name":"Sotysowice",
    "wof:placetype":"neighbourhood"
},
  "geometry": {"coordinates":[17.073785,51.152716],"type":"Point"}
}