{
  "type": "Feature",
  "properties": {
    "gn:admin1_code":"83.0",
    "gn:admin2_code":"2406.0",
    "gn:admin3_code":"240603.0",
    "gn:asciiname":"Brzozki",
    "gn:country_code":"PL",
    "gn:dem":236,
    "gn:feature_class":"P",
    "gn:feature_code":"PPL",
    "gn:name":"Brz\u00f3zki",
    "gn:population":0,
    "gn:timezone":"Europe/Warsaw",
    "iso:country":"PL",
    "name:pol_x_preferred":[
        "Brz\u00f3zki"
    ],
    "name:urd_x_preferred":[
        "\u0628\u0631\u0636\u0648\u0632\u06a9\u06cc"
    ],
    "wof:name":"Brzozki",
    "wof:placetype":"locality"
},
  "geometry": {"coordinates":[18.74559,51.01429],"type":"Point"}
}