{
  "type": "Feature",
  "properties": {
    "gn:admin1_code":"84.0",
    "gn:admin2_code":"2661.0",
    "gn:admin3_code":"266101.0",
    "gn:asciiname":"Sloneczne Wzgorze",
    "gn:country_code":"PL",
    "gn:dem":320,
    "gn:feature_class":"P",
    "gn:feature_code":"PPL",
    "gn:name":"S\u0142oneczne Wzg\u00f3rze",
    "gn:population":0,
    "gn:timezone":"Europe/Warsaw",
    "iso:country":"PL",
    "wof:name":"Sloneczne Wzgorze",
    "wof:placetype":"neighbourhood"
},
  "geometry": {"coordinates":[20.65541,50.88718],"type":"Point"}
}