{
  "type": "Feature",
  "properties": {
    "gn:admin1_code":"82.0",
    "gn:admin2_code":"2212.0",
    "gn:admin3_code":"221206.0",
    "gn:asciiname":"Kuleszewo",
    "gn:country_code":"PL",
    "gn:dem":41,
    "gn:feature_class":"P",
    "gn:feature_code":"PPL",
    "gn:name":"Kuleszewo",
    "gn:population":0,
    "gn:timezone":"Europe/Warsaw",
    "iso:country":"PL",
    "name:ceb_x_preferred":[
        "Kuleszewo"
    ],
    "name:csb_x_preferred":[
        "K\u00f9leszew\u00f2"
    ],
    "name:deu_x_preferred":[
        "Kuleszewo"
    ],
    "name:nld_x_preferred":[
        "Kuleszewo"
    ],
    "name:pol_x_preferred":[
        "Kuleszewo"
    ],
    "name:ukr_x_preferred":[
        "\u041a\u0443\u043b\u0435\u0448\u0435\u0432\u043e"
    ],
    "wof:name":"Kuleszewo",
    "wof:placetype":"locality"
},
  "geometry": {"coordinates":[16.96825,54.35367],"type":"Point"}
}