{
  "type": "Feature",
  "properties": {
    "gn:admin1_code":"77.0",
    "gn:admin2_code":"1205.0",
    "gn:admin3_code":"120510.0",
    "gn:asciiname":"Czertyzne",
    "gn:country_code":"PL",
    "gn:dem":675,
    "gn:feature_class":"P",
    "gn:feature_code":"PPL",
    "gn:name":"Czerty\u017cne",
    "gn:population":0,
    "gn:timezone":"Europe/Warsaw",
    "iso:country":"PL",
    "wof:name":"Czertyzne",
    "wof:placetype":"locality"
},
  "geometry": {"coordinates":[21.08333,49.48333],"type":"Point"}
}