{
  "type": "Feature",
  "properties": {
    "gn:admin1_code":"76.0",
    "gn:admin2_code":"811.0",
    "gn:admin3_code":"81110.0",
    "gn:asciiname":"Bogumilow",
    "gn:country_code":"PL",
    "gn:dem":153,
    "gn:feature_class":"P",
    "gn:feature_code":"PPL",
    "gn:name":"Bogumi\u0142\u00f3w",
    "gn:population":0,
    "gn:timezone":"Europe/Warsaw",
    "iso:country":"PL",
    "name:ceb_x_preferred":[
        "Bogumi\u0142\u00f3w"
    ],
    "name:fra_x_preferred":[
        "Bogumi\u0142\u00f3w"
    ],
    "name:pol_x_preferred":[
        "Bogumi\u0142\u00f3w"
    ],
    "name:ukr_x_preferred":[
        "\u0411\u043e\u0491\u0443\u043c\u0456\u043b\u0443\u0432"
    ],
    "wof:name":"Bogumilow",
    "wof:placetype":"locality"
},
  "geometry": {"coordinates":[15.00938,51.57366],"type":"Point"}
}