{
  "type": "Feature",
  "properties": {
    "gn:admin1_code":"73.0",
    "gn:admin2_code":"408.0",
    "gn:admin3_code":"40804.0",
    "gn:asciiname":"Kochon",
    "gn:country_code":"PL",
    "gn:dem":104,
    "gn:feature_class":"P",
    "gn:feature_code":"PPL",
    "gn:name":"Kocho\u0144",
    "gn:population":0,
    "gn:timezone":"Europe/Warsaw",
    "iso:country":"PL",
    "name:pol_x_preferred":[
        "Kocho\u0144"
    ],
    "name:ukr_x_preferred":[
        "\u041a\u043e\u0445\u043e\u043d\u044c"
    ],
    "wof:name":"Kochon",
    "wof:placetype":"locality"
},
  "geometry": {"coordinates":[19.33708,52.6981],"type":"Point"}
}