{
  "type": "Feature",
  "properties": {
    "gn:admin1_code":"78.0",
    "gn:admin2_code":"1409.0",
    "gn:admin3_code":"140906.0",
    "gn:asciiname":"Sluszczyn",
    "gn:country_code":"PL",
    "gn:dem":177,
    "gn:feature_class":"P",
    "gn:feature_code":"PPL",
    "gn:name":"S\u0142uszczyn",
    "gn:population":0,
    "gn:timezone":"Europe/Warsaw",
    "iso:country":"PL",
    "name:fra_x_preferred":[
        "S\u0142uszczyn"
    ],
    "name:pol_x_preferred":[
        "S\u0142uszczyn"
    ],
    "name:ukr_x_preferred":[
        "\u0421\u043b\u0443\u0449\u0438\u043d"
    ],
    "wof:name":"Sluszczyn",
    "wof:placetype":"locality"
},
  "geometry": {"coordinates":[21.68191,51.11229],"type":"Point"}
}