{
  "type": "Feature",
  "properties": {
    "gn:admin1_code":"86.0",
    "gn:admin2_code":"3014.0",
    "gn:admin3_code":"301401.0",
    "gn:asciiname":"Lezeczki",
    "gn:country_code":"PL",
    "gn:dem":65,
    "gn:feature_class":"P",
    "gn:feature_code":"PPL",
    "gn:name":"\u0141\u0119\u017ceczki",
    "gn:population":0,
    "gn:timezone":"Europe/Warsaw",
    "iso:country":"PL",
    "name:azb_x_preferred":[
        "\u0648\u0646\u0698\u0686\u06a9\u06cc"
    ],
    "name:fas_x_preferred":[
        "\u0648\u0646\u0698\u0686\u06a9\u06cc"
    ],
    "name:fra_x_preferred":[
        "\u0141\u0119\u017ceczki"
    ],
    "name:pol_x_preferred":[
        "\u0141\u0119\u017ceczki"
    ],
    "name:ukr_x_preferred":[
        "\u041b\u0435\u043d\u0436\u0435\u0447\u043a\u0456"
    ],
    "wof:name":"Lezeczki",
    "wof:placetype":"locality"
},
  "geometry": {"coordinates":[16.212,52.60915],"type":"Point"}
}