{
  "type": "Feature",
  "properties": {
    "gn:gn_country":"PL",
    "gn:gn_fcode":"PPL",
    "gn:gn_pop":70,
    "gn:population":70,
    "iso:country":"PL",
    "name:dut_x_preferred":[
        "Dro\u017c\u00f3w"
    ],
    "name:eng_x_preferred":[
        "Dro\u017c\u00f3w"
    ],
    "name:fre_x_preferred":[
        "Dro\u017c\u00f3w"
    ],
    "name:nan_x_preferred":[
        "Dro\u017c\u00f3w"
    ],
    "name:pol_x_preferred":[
        "Dro\u017c\u00f3w"
    ],
    "qs_pg:aaroncc":"PL",
    "qs_pg:gn_country":"PL",
    "qs_pg:gn_fcode":"PPL",
    "qs_pg:gn_pop":70,
    "qs_pg:name":"Dro\u017c\u00f3w",
    "qs_pg:name_adm0":"Polska",
    "qs_pg:name_adm1":"Dolnosl\u0105skie",
    "qs_pg:photos_9r":0,
    "qs_pg:photos_sr":0,
    "qs_pg:pop_sr":1,
    "qs_pg:qs_pg_placetype":"locality",
    "qs_pg:qs_pg_placetype_gp":"Town",
    "qs_pg:woe_adm0":23424923,
    "woe:adm0_id":23424923,
    "woe:name_adm0":"Polska",
    "woe:name_adm1":"Dolnosl\u0105skie",
    "woe:placetype":"Town",
    "wof:name":"Dro\u017c\u00f3w",
    "wof:placetype":"locality",
    "wof:population":70
},
  "geometry": {"coordinates":[15.97116,51.6085],"type":"Point"}
}