{
  "type": "Feature",
  "properties": {
    "gn:admin1_code":"86.0",
    "gn:admin2_code":"3031.0",
    "gn:admin3_code":"303105.0",
    "gn:asciiname":"Brokecino",
    "gn:country_code":"PL",
    "gn:dem":153,
    "gn:feature_class":"P",
    "gn:feature_code":"PPL",
    "gn:name":"Brok\u0119cino",
    "gn:population":0,
    "gn:timezone":"Europe/Warsaw",
    "iso:country":"PL",
    "name:und_x_variant":[
        "Brok\u0119cino"
    ],
    "wof:name":"Brokecino",
    "wof:placetype":"locality"
},
  "geometry": {"coordinates":[16.81507,53.55998],"type":"Point"}
}