{
  "type": "Feature",
  "properties": {
    "gn:admin1_code":"86.0",
    "gn:admin2_code":"3031.0",
    "gn:admin3_code":"303105.0",
    "gn:asciiname":"Brokecino",
    "gn:country_code":"PL",
    "gn:dem":153,
    "gn:feature_class":"P",
    "gn:feature_code":"PPL",
    "gn:name":"Brok\u0119cino",
    "gn:population":0,
    "gn:timezone":"Europe/Warsaw",
    "iso:country":"PL",
    "name:azb_x_preferred":[
        "\u0628\u0631\u0648\u06a9\u0646\u0686\u06cc\u0646\u0648"
    ],
    "name:ceb_x_preferred":[
        "Brok\u0119cino"
    ],
    "name:fas_x_preferred":[
        "\u0628\u0631\u0648\u06a9\u0646\u0686\u06cc\u0646\u0648"
    ],
    "name:fra_x_preferred":[
        "Brok\u0119cino"
    ],
    "name:nld_x_preferred":[
        "Brok\u0119cino"
    ],
    "name:pol_x_preferred":[
        "Brok\u0119cino"
    ],
    "name:ukr_x_preferred":[
        "\u0411\u0440\u043e\u043a\u0435\u043d\u0446\u0438\u043d\u043e"
    ],
    "wof:name":"Brokecino",
    "wof:placetype":"locality"
},
  "geometry": {"coordinates":[16.81507,53.55998],"type":"Point"}
}