{
  "type": "Feature",
  "properties": {
    "iso:country":"PL",
    "name:pol_x_preferred":[
        "Wi\u015bniew"
    ],
    "wof:name":"Wi\u015bniew",
    "wof:placetype":"locality"
},
  "geometry": {"coordinates":[22.287448126377,52.0744105012507],"type":"Point"}
}