{
  "type": "Feature",
  "properties": {
    "gn:admin1_code":"74.0",
    "gn:admin2_code":"1011.0",
    "gn:admin3_code":"101102.0",
    "gn:asciiname":"Rudniki",
    "gn:country_code":"PL",
    "gn:dem":121,
    "gn:feature_class":"P",
    "gn:feature_code":"PPL",
    "gn:name":"Rudniki",
    "gn:population":0,
    "gn:timezone":"Europe/Warsaw",
    "iso:country":"PL",
    "name:fra_x_preferred":[
        "Rudniki"
    ],
    "name:pol_x_preferred":[
        "Rudniki"
    ],
    "name:ukr_x_preferred":[
        "\u0420\u0443\u0434\u043d\u0438\u043a\u0438"
    ],
    "wof:name":"Rudniki",
    "wof:placetype":"locality"
},
  "geometry": {"coordinates":[18.76757000000001,51.79715],"type":"Point"}
}