{
  "type": "Feature",
  "properties": {
    "gn:admin1_code":"74.0",
    "gn:admin2_code":"1020.0",
    "gn:admin3_code":"102008.0",
    "gn:asciiname":"Kielmina",
    "gn:country_code":"PL",
    "gn:dem":193,
    "gn:feature_class":"P",
    "gn:feature_code":"PPL",
    "gn:name":"Kie\u0142mina",
    "gn:population":0,
    "gn:timezone":"Europe/Warsaw",
    "iso:country":"PL",
    "name:mkd_x_preferred":[
        "\u041a\u0438\u0435\u043b\u043c\u0438\u043d\u0430"
    ],
    "name:pol_x_preferred":[
        "Kie\u0142mina"
    ],
    "name:ukr_x_preferred":[
        "\u041a\u0435\u043b\u043c\u0456\u043d\u0430"
    ],
    "name:und_x_variant":[
        "Kie\u0142mina"
    ],
    "wof:name":"Kielmina",
    "wof:placetype":"locality"
},
  "geometry": {"coordinates":[19.53256,51.86563],"type":"Point"}
}