{
  "type": "Feature",
  "properties": {
    "gn:admin1_code":"75.0",
    "gn:admin2_code":"601.0",
    "gn:admin3_code":"60109.0",
    "gn:asciiname":"Bielany",
    "gn:country_code":"PL",
    "gn:dem":144,
    "gn:feature_class":"P",
    "gn:feature_code":"PPL",
    "gn:name":"Bielany",
    "gn:population":0,
    "gn:timezone":"Europe/Warsaw",
    "iso:country":"PL",
    "wof:name":"Bielany",
    "wof:placetype":"locality"
},
  "geometry": {"coordinates":[23.13496,51.93243],"type":"Point"}
}