{
  "type": "Feature",
  "properties": {
    "gn:admin1_code":"80.0",
    "gn:admin2_code":"1809.0",
    "gn:admin3_code":"180903.0",
    "gn:asciiname":"Halanie",
    "gn:country_code":"PL",
    "gn:dem":274,
    "gn:feature_class":"P",
    "gn:feature_code":"PPL",
    "gn:name":"Ha\u0142anie",
    "gn:population":0,
    "gn:timezone":"Europe/Warsaw",
    "iso:country":"PL",
    "wof:name":"Halanie",
    "wof:placetype":"locality"
},
  "geometry": {"coordinates":[23.40296,50.19443],"type":"Point"}
}