{
  "type": "Feature",
  "properties": {
    "gn:admin1_code":"87.0",
    "gn:admin2_code":"3207.0",
    "gn:admin3_code":"320705.0",
    "gn:asciiname":"Gostyniec",
    "gn:cc2":"PL",
    "gn:country_code":"PL",
    "gn:dem":18,
    "gn:feature_class":"P",
    "gn:feature_code":"PPL",
    "gn:name":"Gostyniec",
    "gn:population":0,
    "gn:timezone":"Europe/Warsaw",
    "iso:country":"PL",
    "name:und_x_variant":[
        "Klein Justin",
        "Gostyniec"
    ],
    "wof:name":"Gostyniec",
    "wof:placetype":"locality"
},
  "geometry": {"coordinates":[14.9699,53.99516],"type":"Point"}
}