{
  "type": "Feature",
  "properties": {
    "iso:country":"PL",
    "name:eng_x_preferred":[
        "Gadow Maly"
    ],
    "name:pol_x_preferred":[
        "G\u0105d\u00f3w Ma\u0142y"
    ],
    "wof:name":"Gadow Maly",
    "wof:placetype":"neighbourhood"
},
  "geometry": {"coordinates":[16.96499438457234,51.1258764071576],"type":"Point"}
}