{
  "type": "Feature",
  "properties": {
    "gn:admin1_code":"77.0",
    "gn:admin2_code":"1208.0",
    "gn:admin3_code":"120804.0",
    "gn:asciiname":"Lazy",
    "gn:country_code":"PL",
    "gn:dem":348,
    "gn:feature_class":"P",
    "gn:feature_code":"PPL",
    "gn:name":"\u0141azy",
    "gn:population":0,
    "gn:timezone":"Europe/Warsaw",
    "iso:country":"PL",
    "name:ceb_x_preferred":[
        "\u0141azy"
    ],
    "name:ita_x_preferred":[
        "\u0141azy"
    ],
    "name:pol_x_preferred":[
        "\u0141azy"
    ],
    "name:rus_x_preferred":[
        "\u041b\u0430\u0437\u044b"
    ],
    "name:ukr_x_preferred":[
        "\u041b\u0430\u0437\u0438"
    ],
    "wof:name":"Lazy",
    "wof:placetype":"locality"
},
  "geometry": {"coordinates":[20.07048,50.42914],"type":"Point"}
}