{
  "type": "Feature",
  "properties": {
    "gn:admin1_code":"72.0",
    "gn:admin2_code":"208.0",
    "gn:admin3_code":"20808.0",
    "gn:asciiname":"Lutynia",
    "gn:country_code":"PL",
    "gn:dem":535,
    "gn:feature_class":"P",
    "gn:feature_code":"PPL",
    "gn:name":"Lutynia",
    "gn:population":0,
    "gn:timezone":"Europe/Warsaw",
    "iso:country":"PL",
    "name:deu_x_preferred":[
        "Deutsch Leuthen"
    ],
    "name:deu_x_variant":[
        "Lutynia"
    ],
    "name:pol_x_preferred":[
        "Lutynia"
    ],
    "name:ukr_x_preferred":[
        "\u041b\u044e\u0442\u0438\u043d\u044f"
    ],
    "wof:name":"Lutynia",
    "wof:placetype":"locality"
},
  "geometry": {"coordinates":[16.90435,50.36457],"type":"Point"}
}