{
  "type": "Feature",
  "properties": {
    "gn:admin1_code":"81.0",
    "gn:admin2_code":"2010.0",
    "gn:admin3_code":"201002.0",
    "gn:asciiname":"Sytki",
    "gn:country_code":"PL",
    "gn:dem":149,
    "gn:feature_class":"P",
    "gn:feature_code":"PPL",
    "gn:name":"Sytki",
    "gn:population":0,
    "gn:timezone":"Europe/Warsaw",
    "iso:country":"PL",
    "name:fra_x_preferred":[
        "Sytki"
    ],
    "name:lit_x_preferred":[
        "Sitkai"
    ],
    "name:pol_x_preferred":[
        "Sytki"
    ],
    "name:ukr_x_preferred":[
        "\u0421\u0438\u0442\u043a\u0456"
    ],
    "wof:name":"Sytki",
    "wof:placetype":"locality"
},
  "geometry": {"coordinates":[22.72089,52.43587],"type":"Point"}
}