{
  "type": "Feature",
  "properties": {
    "gn:admin1_code":"75.0",
    "gn:admin2_code":"612.0",
    "gn:admin3_code":"61204.0",
    "gn:asciiname":"Piotrawin",
    "gn:country_code":"PL",
    "gn:dem":154,
    "gn:feature_class":"P",
    "gn:feature_code":"PPL",
    "gn:name":"Piotrawin",
    "gn:population":0,
    "gn:timezone":"Europe/Warsaw",
    "iso:country":"PL",
    "name:fra_x_preferred":[
        "Piotrawin"
    ],
    "name:pol_x_preferred":[
        "Piotrawin"
    ],
    "name:ukr_x_preferred":[
        "\u041f\u0439\u043e\u0442\u0440\u0430\u0432\u0456\u043d"
    ],
    "wof:name":"Piotrawin",
    "wof:placetype":"locality"
},
  "geometry": {"coordinates":[21.79945,51.10131],"type":"Point"}
}