{
  "type": "Feature",
  "properties": {
    "gn:admin1_code":"83.0",
    "gn:admin2_code":"2413.0",
    "gn:admin3_code":"241302.0",
    "gn:asciiname":"Zyglin",
    "gn:country_code":"PL",
    "gn:dem":306,
    "gn:feature_class":"P",
    "gn:feature_code":"PPL",
    "gn:name":"Zyglin",
    "gn:population":0,
    "gn:timezone":"Europe/Warsaw",
    "iso:country":"PL",
    "wof:name":"Zyglin",
    "wof:placetype":"locality"
},
  "geometry": {"coordinates":[18.94577,50.48532],"type":"Point"}
}