{
  "type": "Feature",
  "properties": {
    "gn:admin1_code":"87.0",
    "gn:admin2_code":"3204.0",
    "gn:admin3_code":"320405.0",
    "gn:asciiname":"Kikorze",
    "gn:country_code":"PL",
    "gn:dem":44,
    "gn:feature_class":"P",
    "gn:feature_code":"PPL",
    "gn:name":"Kikorze",
    "gn:population":0,
    "gn:timezone":"Europe/Warsaw",
    "iso:country":"PL",
    "name:ceb_x_preferred":[
        "Kikorze"
    ],
    "name:pol_x_preferred":[
        "Kikorze"
    ],
    "name:ukr_x_preferred":[
        "\u041a\u0456\u043a\u043e\u0436\u0435"
    ],
    "name:vie_x_preferred":[
        "Kikorze"
    ],
    "wof:name":"Kikorze",
    "wof:placetype":"locality"
},
  "geometry": {"coordinates":[15.01762,53.63077],"type":"Point"}
}