{
  "type": "Feature",
  "properties": {
    "gn:admin1_code":"78.0",
    "gn:admin2_code":"1437.0",
    "gn:admin3_code":"143704.0",
    "gn:asciiname":"Zimolza",
    "gn:country_code":"PL",
    "gn:dem":119,
    "gn:feature_class":"P",
    "gn:feature_code":"PPL",
    "gn:name":"Zimolza",
    "gn:population":0,
    "gn:timezone":"Europe/Warsaw",
    "iso:country":"PL",
    "name:ara_x_preferred":[
        "\u0632\u064a\u0645\u0648\u0644\u0632\u0627"
    ],
    "name:fra_x_preferred":[
        "Zimolza"
    ],
    "name:pol_x_preferred":[
        "Zimolza"
    ],
    "name:ukr_x_preferred":[
        "\u0417\u0456\u043c\u043e\u043b\u044c\u0437\u0430"
    ],
    "wof:name":"Zimolza",
    "wof:placetype":"locality"
},
  "geometry": {"coordinates":[19.83241,52.96985],"type":"Point"}
}