{
  "type": "Feature",
  "properties": {
    "iso:country":"PL",
    "name:pol_x_preferred":[
        "\u0141agiewniki"
    ],
    "wof:name":"Lagiewniki",
    "wof:placetype":"neighbourhood"
},
  "geometry": {"coordinates":[19.94017768862913,50.02140553513605],"type":"Point"}
}