{
  "type": "Feature",
  "properties": {
    "gn:admin1_code":"74.0",
    "gn:admin2_code":"1016.0",
    "gn:admin3_code":"101606.0",
    "gn:asciiname":"Malecz",
    "gn:country_code":"PL",
    "gn:dem":187,
    "gn:feature_class":"P",
    "gn:feature_code":"PPL",
    "gn:name":"Ma\u0142ecz",
    "gn:population":0,
    "gn:timezone":"Europe/Warsaw",
    "iso:country":"PL",
    "name:azb_x_preferred":[
        "\u0645\u0627\u0648\u0686"
    ],
    "name:ceb_x_preferred":[
        "Ma\u0142ecz"
    ],
    "name:epo_x_preferred":[
        "Ma\u0142ecz"
    ],
    "name:fas_x_preferred":[
        "\u0645\u0627\u0648\u0686"
    ],
    "name:fra_x_preferred":[
        "Ma\u0142ecz"
    ],
    "name:nld_x_preferred":[
        "Ma\u0142ecz"
    ],
    "name:pol_x_preferred":[
        "Ma\u0142ecz"
    ],
    "name:szl_x_preferred":[
        "Ma\u0142ecz"
    ],
    "name:ukr_x_preferred":[
        "\u041c\u0430\u043b\u0435\u0447"
    ],
    "name:und_x_variant":[
        "Ma\u0142ecz"
    ],
    "wof:name":"Malecz",
    "wof:placetype":"locality"
},
  "geometry": {"coordinates":[20.00845,51.61796],"type":"Point"}
}