{
  "type": "Feature",
  "properties": {
    "gn:admin1_code":"78.0",
    "gn:admin2_code":"1428.0",
    "gn:admin3_code":"142803.0",
    "gn:asciiname":"Uderz",
    "gn:country_code":"PL",
    "gn:dem":68,
    "gn:feature_class":"P",
    "gn:feature_code":"PPL",
    "gn:name":"Uderz",
    "gn:population":0,
    "gn:timezone":"Europe/Warsaw",
    "iso:country":"PL",
    "name:azb_x_preferred":[
        "\u0627\u0648\u062f\u0698"
    ],
    "name:fas_x_preferred":[
        "\u0627\u0648\u062f\u0698"
    ],
    "name:fra_x_preferred":[
        "Uderz"
    ],
    "name:pol_x_preferred":[
        "Uderz"
    ],
    "name:ukr_x_preferred":[
        "\u0423\u0434\u0435\u0436"
    ],
    "name:urd_x_preferred":[
        "\u0627\u0648\u062f\u06cc\u0634"
    ],
    "wof:name":"Uderz",
    "wof:placetype":"locality"
},
  "geometry": {"coordinates":[20.05812,52.35374],"type":"Point"}
}