{
  "type": "Feature",
  "properties": {
    "gn:admin1_code":"81.0",
    "gn:admin2_code":"2013.0",
    "gn:admin3_code":"201306.0",
    "gn:asciiname":"Litwa",
    "gn:country_code":"PL",
    "gn:dem":131,
    "gn:feature_class":"P",
    "gn:feature_code":"PPL",
    "gn:name":"Litwa",
    "gn:population":0,
    "gn:timezone":"Europe/Warsaw",
    "iso:country":"PL",
    "name:und_x_variant":[
        "Litwa Stara",
        "Litwa"
    ],
    "wof:name":"Litwa",
    "wof:placetype":"locality"
},
  "geometry": {"coordinates":[22.52179,53.03341999999999],"type":"Point"}
}