{
  "type": "Feature",
  "properties": {
    "gn:admin1_code":"87.0",
    "gn:admin2_code":"3208.0",
    "gn:admin3_code":"320804.0",
    "gn:asciiname":"Wiecemino",
    "gn:cc2":"PL",
    "gn:country_code":"PL",
    "gn:dem":2,
    "gn:feature_class":"P",
    "gn:feature_code":"PPL",
    "gn:name":"Wi\u0119cemino",
    "gn:population":0,
    "gn:timezone":"Europe/Warsaw",
    "iso:country":"PL",
    "name:und_x_variant":[
        "Karlsberger",
        "Karlsberg",
        "Wi\u0119cemino"
    ],
    "wof:name":"Wiecemino",
    "wof:placetype":"locality"
},
  "geometry": {"coordinates":[15.58333,54.15],"type":"Point"}
}