{
  "type": "Feature",
  "properties": {
    "gn:admin1_code":"87.0",
    "gn:admin2_code":"3214.0",
    "gn:admin3_code":"321408.0",
    "gn:asciiname":"Sulino",
    "gn:country_code":"PL",
    "gn:dem":66,
    "gn:feature_class":"P",
    "gn:feature_code":"PPL",
    "gn:name":"Sulino",
    "gn:population":0,
    "gn:timezone":"Europe/Warsaw",
    "iso:country":"PL",
    "name:pol_x_preferred":[
        "Sulino"
    ],
    "name:ukr_x_preferred":[
        "\u0421\u0443\u043b\u0456\u043d\u043e"
    ],
    "wof:name":"Sulino",
    "wof:placetype":"locality"
},
  "geometry": {"coordinates":[15.3137,53.33794],"type":"Point"}
}