{
  "type": "Feature",
  "properties": {
    "gn:admin1_code":"78.0",
    "gn:admin2_code":"1406.0",
    "gn:admin3_code":"140611.0",
    "gn:asciiname":"Grzegorzewice",
    "gn:country_code":"PL",
    "gn:dem":109,
    "gn:feature_class":"P",
    "gn:feature_code":"PPL",
    "gn:name":"Grzegorzewice",
    "gn:population":0,
    "gn:timezone":"Europe/Warsaw",
    "iso:country":"PL",
    "name:ceb_x_preferred":[
        "Grzegorzewice"
    ],
    "name:fra_x_preferred":[
        "Grzegorzewice"
    ],
    "name:pol_x_preferred":[
        "Grzegorzewice"
    ],
    "name:ukr_x_preferred":[
        "\u0490\u0436\u0435\u0491\u043e\u0436\u0435\u0432\u0456\u0446\u0435"
    ],
    "wof:name":"Grzegorzewice",
    "wof:placetype":"locality"
},
  "geometry": {"coordinates":[21.12379,51.76263],"type":"Point"}
}