{
  "type": "Feature",
  "properties": {
    "gn:admin1_code":"74.0",
    "gn:admin2_code":"1009.0",
    "gn:admin3_code":"100908.0",
    "gn:asciiname":"Bogumilowice",
    "gn:country_code":"PL",
    "gn:dem":205,
    "gn:feature_class":"P",
    "gn:feature_code":"PPL",
    "gn:name":"Bogumi\u0142owice",
    "gn:population":0,
    "gn:timezone":"Europe/Warsaw",
    "iso:country":"PL",
    "name:fra_x_preferred":[
        "Bogumi\u0142owice"
    ],
    "name:pol_x_preferred":[
        "Bogumi\u0142owice"
    ],
    "name:ukr_x_preferred":[
        "\u0411\u043e\u0491\u0443\u043c\u0456\u043b\u043e\u0432\u0456\u0446\u0435"
    ],
    "wof:name":"Bogumilowice",
    "wof:placetype":"locality"
},
  "geometry": {"coordinates":[19.13148,51.19],"type":"Point"}
}