{
  "type": "Feature",
  "properties": {
    "gn:admin1_code":"81.0",
    "gn:admin2_code":"2008.0",
    "gn:admin3_code":"200804.0",
    "gn:asciiname":"Nowiny Kasjerskie",
    "gn:country_code":"PL",
    "gn:dem":135,
    "gn:feature_class":"P",
    "gn:feature_code":"PPL",
    "gn:name":"Nowiny Kasjerskie",
    "gn:population":0,
    "gn:timezone":"Europe/Warsaw",
    "iso:country":"PL",
    "wof:name":"Nowiny Kasjerskie",
    "wof:placetype":"locality"
},
  "geometry": {"coordinates":[23.03132,53.32871],"type":"Point"}
}