{
  "type": "Feature",
  "properties": {
    "gn:admin1_code":"73.0",
    "gn:admin2_code":"418.0",
    "gn:admin3_code":"41813.0",
    "gn:asciiname":"Smolnik",
    "gn:country_code":"PL",
    "gn:dem":60,
    "gn:feature_class":"P",
    "gn:feature_code":"PPL",
    "gn:name":"Smolnik",
    "gn:population":0,
    "gn:timezone":"Europe/Warsaw",
    "iso:country":"PL",
    "name:eng_x_preferred":[
        "Smolnik"
    ],
    "name:pol_x_preferred":[
        "Sm\u00f3lnik"
    ],
    "name:rus_x_preferred":[
        "\u0421\u043c\u043e\u043b\u044c\u043d\u0438\u043a"
    ],
    "name:ukr_x_preferred":[
        "\u0421\u043c\u0443\u043b\u044c\u043d\u0438\u043a"
    ],
    "wof:name":"Smolnik",
    "wof:placetype":"locality"
},
  "geometry": {"coordinates":[19.25211,52.60375],"type":"Point"}
}