{
  "type": "Feature",
  "properties": {
    "gn:admin1_code":"83.0",
    "gn:admin2_code":"2409.0",
    "gn:admin3_code":"240903.0",
    "gn:asciiname":"Mzurow",
    "gn:country_code":"PL",
    "gn:dem":353,
    "gn:feature_class":"P",
    "gn:feature_code":"PPL",
    "gn:name":"Mzur\u00f3w",
    "gn:population":0,
    "gn:timezone":"Europe/Warsaw",
    "iso:country":"PL",
    "wof:name":"Mzurow",
    "wof:placetype":"locality"
},
  "geometry": {"coordinates":[19.50726,50.66285],"type":"Point"}
}