{
  "type": "Feature",
  "properties": {
    "gn:admin1_code":"79.0",
    "gn:admin2_code":"1609.0",
    "gn:admin3_code":"160902.0",
    "gn:asciiname":"Lipowa",
    "gn:country_code":"PL",
    "gn:dem":173,
    "gn:feature_class":"P",
    "gn:feature_code":"PPL",
    "gn:name":"Lipowa",
    "gn:population":0,
    "gn:timezone":"Europe/Warsaw",
    "iso:country":"PL",
    "name:ceb_x_preferred":[
        "Lipowa"
    ],
    "name:deu_x_preferred":[
        "Lipowa"
    ],
    "name:fra_x_preferred":[
        "Lipowa"
    ],
    "name:nld_x_preferred":[
        "Lipowa"
    ],
    "name:pol_x_preferred":[
        "Lipowa"
    ],
    "wof:name":"Lipowa",
    "wof:placetype":"locality"
},
  "geometry": {"coordinates":[17.67387,50.70446],"type":"Point"}
}