{
  "type": "Feature",
  "properties": {
    "gn:admin1_code":"85.0",
    "gn:admin2_code":"2809.0",
    "gn:admin3_code":"280902.0",
    "gn:asciiname":"Napraty",
    "gn:country_code":"PL",
    "gn:dem":103,
    "gn:feature_class":"P",
    "gn:feature_code":"PPL",
    "gn:name":"Napraty",
    "gn:population":0,
    "gn:timezone":"Europe/Warsaw",
    "iso:country":"PL",
    "name:und_x_variant":[
        "Napratten",
        "Napraty"
    ],
    "wof:name":"Napraty",
    "wof:placetype":"locality"
},
  "geometry": {"coordinates":[20.70209,54.15325],"type":"Point"}
}