{
  "type": "Feature",
  "properties": {
    "gn:admin1_code":"74.0",
    "gn:admin2_code":"1010.0",
    "gn:admin3_code":"101004.0",
    "gn:asciiname":"Wola Kamocka",
    "gn:country_code":"PL",
    "gn:dem":226,
    "gn:feature_class":"P",
    "gn:feature_code":"PPL",
    "gn:name":"Wola Kamocka",
    "gn:population":0,
    "gn:timezone":"Europe/Warsaw",
    "iso:country":"PL",
    "name:fra_x_preferred":[
        "Wola Kamocka"
    ],
    "name:pol_x_preferred":[
        "Wola Kamocka"
    ],
    "name:ukr_x_preferred":[
        "\u0412\u043e\u043b\u044f-\u041a\u0430\u043c\u043e\u0446\u044c\u043a\u0430"
    ],
    "wof:name":"Wola Kamocka",
    "wof:placetype":"locality"
},
  "geometry": {"coordinates":[19.57234,51.48166],"type":"Point"}
}