{
  "type": "Feature",
  "properties": {
    "gn:admin1_code":"78.0",
    "gn:admin2_code":"1422.0",
    "gn:admin3_code":"142202.0",
    "gn:asciiname":"Macice",
    "gn:cc2":"PL",
    "gn:country_code":"PL",
    "gn:dem":122,
    "gn:feature_class":"P",
    "gn:feature_code":"PPL",
    "gn:name":"M\u0105cice",
    "gn:population":0,
    "gn:timezone":"Europe/Warsaw",
    "iso:country":"PL",
    "name:und_x_variant":[
        "Montwitz",
        "M\u0105cice"
    ],
    "wof:name":"Macice",
    "wof:placetype":"locality"
},
  "geometry": {"coordinates":[20.98543,53.32298],"type":"Point"}
}