{
  "type": "Feature",
  "properties": {
    "iso:country":"PL",
    "name:ast_x_preferred":[
        "Stare Babice"
    ],
    "name:azb_x_preferred":[
        "\u0633\u062a\u0627\u0631\u0647 \u0628\u0627\u0628\u06cc\u062a\u0633\u0647"
    ],
    "name:ces_x_preferred":[
        "Stare Babice"
    ],
    "name:deu_x_preferred":[
        "Stare Babice"
    ],
    "name:eng_x_preferred":[
        "Stare Babice"
    ],
    "name:fas_x_preferred":[
        "\u0633\u062a\u0627\u0631\u0647 \u0628\u0627\u0628\u06cc\u062a\u0633\u0647"
    ],
    "name:fra_x_preferred":[
        "Stare Babice"
    ],
    "name:nld_x_preferred":[
        "Stare Babice"
    ],
    "name:pol_x_preferred":[
        "Stare Babice"
    ],
    "name:ukr_x_preferred":[
        "\u0421\u0442\u0430\u0440\u0435 \u0411\u0430\u0431\u0456\u0446\u0435"
    ],
    "qs_pg:aaroncc":"PL",
    "qs_pg:name":"Stare Babice",
    "qs_pg:name_adm0":"Polska",
    "qs_pg:name_adm1":"Mazowieckie",
    "qs_pg:photos":8,
    "qs_pg:photos_1k":2,
    "qs_pg:photos_9k":1,
    "qs_pg:photos_9r":1,
    "qs_pg:photos_all":8,
    "qs_pg:photos_sr":1,
    "qs_pg:pop_sr":0,
    "qs_pg:qs_pg_placetype":"locality",
    "qs_pg:qs_pg_placetype_gp":"Town",
    "qs_pg:woe_adm0":23424923,
    "woe:adm0_id":23424923,
    "woe:name_adm0":"Polska",
    "woe:name_adm1":"Mazowieckie",
    "woe:placetype":"Town",
    "wof:coterminous":[
        1125370853
    ],
    "wof:name":"Stare Babice",
    "wof:placetype":"locality"
},
  "geometry": {"coordinates":[20.8250995,52.255969],"type":"Point"}
}