{
  "type": "Feature",
  "properties": {
    "gn:admin1_code":"78.0",
    "gn:admin2_code":"1425.0",
    "gn:admin3_code":"142513.0",
    "gn:asciiname":"Zakrzewska Wola",
    "gn:country_code":"PL",
    "gn:dem":154,
    "gn:feature_class":"P",
    "gn:feature_code":"PPL",
    "gn:name":"Zakrzewska Wola",
    "gn:population":0,
    "gn:timezone":"Europe/Warsaw",
    "iso:country":"PL",
    "wof:name":"Zakrzewska Wola",
    "wof:placetype":"locality"
},
  "geometry": {"coordinates":[20.96835,51.44926],"type":"Point"}
}