{
  "type": "Feature",
  "properties": {
    "gn:admin1_code":"84.0",
    "gn:admin2_code":"2613.0",
    "gn:admin3_code":"261302.0",
    "gn:asciiname":"Lipia Gora",
    "gn:country_code":"PL",
    "gn:dem":228,
    "gn:feature_class":"P",
    "gn:feature_code":"PPL",
    "gn:name":"Lipia G\u00f3ra",
    "gn:population":0,
    "gn:timezone":"Europe/Warsaw",
    "iso:country":"PL",
    "name:ceb_x_preferred":[
        "Lipia G\u00f3ra"
    ],
    "name:pol_x_preferred":[
        "Lipia G\u00f3ra"
    ],
    "name:ukr_x_preferred":[
        "\u041b\u0456\u043f\u044f-\u0490\u0443\u0440\u0430"
    ],
    "wof:name":"Lipia Gora",
    "wof:placetype":"locality"
},
  "geometry": {"coordinates":[20.1473,50.92699],"type":"Point"}
}