{
  "type": "Feature",
  "properties": {
    "gn:admin1_code":"83.0",
    "gn:admin2_code":"2476.0",
    "gn:admin3_code":"247601.0",
    "gn:asciiname":"Chropaczow",
    "gn:country_code":"PL",
    "gn:dem":289,
    "gn:feature_class":"P",
    "gn:feature_code":"PPL",
    "gn:name":"Chropacz\u00f3w",
    "gn:population":0,
    "gn:timezone":"Europe/Warsaw",
    "iso:country":"PL",
    "wof:name":"Chropaczow",
    "wof:placetype":"locality"
},
  "geometry": {"coordinates":[18.91637,50.3096],"type":"Point"}
}