{
  "type": "Feature",
  "properties": {
    "gn:admin1_code":"73.0",
    "gn:admin2_code":"416.0",
    "gn:admin3_code":"41601.0",
    "gn:asciiname":"Ostrowo",
    "gn:country_code":"PL",
    "gn:dem":111,
    "gn:feature_class":"P",
    "gn:feature_code":"PPL",
    "gn:name":"Ostrowo",
    "gn:population":0,
    "gn:timezone":"Europe/Warsaw",
    "iso:country":"PL",
    "name:ceb_x_preferred":[
        "Ostrowo"
    ],
    "name:deu_x_preferred":[
        "Ostrowo"
    ],
    "name:fra_x_preferred":[
        "Ostrowo"
    ],
    "name:pol_x_preferred":[
        "Ostrowo"
    ],
    "name:ukr_x_preferred":[
        "\u041e\u0441\u0442\u0440\u043e\u0432\u043e"
    ],
    "wof:name":"Ostrowo",
    "wof:placetype":"locality"
},
  "geometry": {"coordinates":[18.05192000000001,53.55093000000001],"type":"Point"}
}