{
  "type": "Feature",
  "properties": {
    "gn:admin1_code":"86.0",
    "gn:admin2_code":"3010.0",
    "gn:admin3_code":"301004.0",
    "gn:asciiname":"Slowiki",
    "gn:country_code":"PL",
    "gn:dem":104,
    "gn:feature_class":"P",
    "gn:feature_code":"PPL",
    "gn:name":"S\u0142owiki",
    "gn:population":0,
    "gn:timezone":"Europe/Warsaw",
    "iso:country":"PL",
    "name:und_x_variant":[
        "S\u0142owiki"
    ],
    "wof:name":"Slowiki",
    "wof:placetype":"locality"
},
  "geometry": {"coordinates":[18.07304,52.42867],"type":"Point"}
}