{
  "type": "Feature",
  "properties": {
    "gn:admin1_code":"81.0",
    "gn:admin2_code":"2009.0",
    "gn:admin3_code":"200904.0",
    "gn:asciiname":"Pelele",
    "gn:country_code":"PL",
    "gn:dem":156,
    "gn:feature_class":"P",
    "gn:feature_code":"PPL",
    "gn:name":"Pe\u0142ele",
    "gn:population":0,
    "gn:timezone":"Europe/Warsaw",
    "iso:country":"PL",
    "name:lit_x_preferred":[
        "Peleliai"
    ],
    "name:pol_x_preferred":[
        "Pe\u0142ele"
    ],
    "name:ukr_x_preferred":[
        "\u041f\u0435\u043b\u0435\u043b\u0435"
    ],
    "wof:name":"Pelele",
    "wof:placetype":"locality"
},
  "geometry": {"coordinates":[23.27188,54.22164],"type":"Point"}
}