{
  "type": "Feature",
  "properties": {
    "gn:admin1_code":"87.0",
    "gn:admin2_code":"3205.0",
    "gn:admin3_code":"320508.0",
    "gn:asciiname":"Glebokie",
    "gn:cc2":"PL",
    "gn:country_code":"PL",
    "gn:dem":-1,
    "gn:feature_class":"P",
    "gn:feature_code":"PPL",
    "gn:name":"G\u0142\u0119bokie",
    "gn:population":0,
    "gn:timezone":"Europe/Warsaw",
    "iso:country":"PL",
    "name:und_x_variant":[
        "Westdeep",
        "G\u0142\u0119bokie"
    ],
    "wof:name":"Glebokie",
    "wof:placetype":"locality"
},
  "geometry": {"coordinates":[15.28333,54.13333000000001],"type":"Point"}
}