{
  "type": "Feature",
  "properties": {
    "gn:admin1_code":"78.0",
    "gn:admin2_code":"1410.0",
    "gn:admin3_code":"141003.0",
    "gn:asciiname":"Bolesty",
    "gn:country_code":"PL",
    "gn:dem":160,
    "gn:feature_class":"P",
    "gn:feature_code":"PPL",
    "gn:name":"Bolesty",
    "gn:population":0,
    "gn:timezone":"Europe/Warsaw",
    "iso:country":"PL",
    "name:fra_x_preferred":[
        "Bolesty"
    ],
    "name:lit_x_preferred":[
        "Bolestai"
    ],
    "name:pol_x_preferred":[
        "Bolesty"
    ],
    "name:ukr_x_preferred":[
        "\u0411\u043e\u043b\u0435\u0441\u0442\u0438"
    ],
    "wof:name":"Bolesty",
    "wof:placetype":"locality"
},
  "geometry": {"coordinates":[22.69672000000001,52.17348],"type":"Point"}
}