{
  "type": "Feature",
  "properties": {
    "gn:admin1_code":"76",
    "gn:admin2_code":"0808",
    "gn:admin3_code":"80801.0",
    "gn:asciiname":"Janislawiec",
    "gn:country_code":"PL",
    "gn:dem":103,
    "gn:feature_class":"P",
    "gn:feature_code":"PPL",
    "gn:name":"Janis\u0142awiec",
    "gn:population":0,
    "gn:timezone":"Europe/Warsaw",
    "iso:country":"PL",
    "name:fra_x_preferred":[
        "Janis\u0142awiec"
    ],
    "name:pol_x_preferred":[
        "Janis\u0142awiec"
    ],
    "name:urd_x_preferred":[
        "\u062c\u0646\u0633\u0648\u0627\u0648\u06cc\u06a9"
    ],
    "wof:name":"Janislawiec",
    "wof:placetype":"locality"
},
  "geometry": {"coordinates":[15.42092,52.25699],"type":"Point"}
}