{
  "type": "Feature",
  "properties": {
    "gn:gn_country":"PL",
    "gn:gn_fcode":"PPLA3",
    "gn:gn_pop":560,
    "gn:population":560,
    "iso:country":"PL",
    "name:deu_x_preferred":[
        "Gmina Bielice"
    ],
    "name:eng_x_preferred":[
        "Gmina Bielice"
    ],
    "name:por_x_preferred":[
        "Comuna de Bielice"
    ],
    "name:rus_x_preferred":[
        "\u0411\u0435\u043b\u0438\u0446\u0435"
    ],
    "name:slk_x_preferred":[
        "Gmina Bielice"
    ],
    "name:ukr_x_preferred":[
        "\u0490\u043c\u0456\u043d\u0430 \u0411\u0435\u043b\u0456\u0446\u0435"
    ],
    "name:unk_x_variant":[
        "Beelitz in Pommern"
    ],
    "name:war_x_preferred":[
        "Gmina Bielice"
    ],
    "qs_pg:aaroncc":"PL",
    "qs_pg:gn_country":"PL",
    "qs_pg:gn_fcode":"PPLA3",
    "qs_pg:gn_pop":560,
    "qs_pg:name":"Bielice",
    "qs_pg:name_adm0":"Polska",
    "qs_pg:name_adm1":"Zachodniopomorskie",
    "qs_pg:photos_9k":1,
    "qs_pg:photos_9r":1,
    "qs_pg:photos_all":1,
    "qs_pg:photos_sr":0,
    "qs_pg:pop_sr":2,
    "qs_pg:qs_pg_placetype":"localadmin",
    "qs_pg:qs_pg_placetype_gp":"LocalAdmin",
    "qs_pg:woe_adm0":23424923,
    "woe:adm0_id":23424923,
    "woe:name_adm0":"Polska",
    "woe:name_adm1":"Zachodniopomorskie",
    "woe:placetype":"LocalAdmin",
    "wof:name":"Bielice",
    "wof:placetype":"localadmin",
    "wof:population":560
},
  "geometry": {"coordinates":[14.7276,53.20022],"type":"Point"}
}