{
  "type": "Feature",
  "properties": {
    "gn:admin1_code":"72.0",
    "gn:admin2_code":"214.0",
    "gn:admin3_code":"21408.0",
    "gn:asciiname":"Kuznia Goszczanska",
    "gn:country_code":"PL",
    "gn:dem":139,
    "gn:feature_class":"P",
    "gn:feature_code":"PPL",
    "gn:name":"Ku\u017ania Goszcza\u0144ska",
    "gn:population":0,
    "gn:timezone":"Europe/Warsaw",
    "iso:country":"PL",
    "name:pol_x_preferred":[
        "Ku\u017ania Goszcza\u0144ska"
    ],
    "name:und_x_variant":[
        "Althammer Gosch\u00fctz",
        "Heinrichsh\u00fctte"
    ],
    "wof:name":"Kuznia Goszczanska",
    "wof:placetype":"locality"
},
  "geometry": {"coordinates":[17.45929,51.40107],"type":"Point"}
}