{
  "type": "Feature",
  "properties": {
    "gn:admin1_code":"84.0",
    "gn:admin2_code":"2602.0",
    "gn:admin3_code":"260201.0",
    "gn:asciiname":"Borszowice",
    "gn:country_code":"PL",
    "gn:dem":201,
    "gn:feature_class":"P",
    "gn:feature_code":"PPL",
    "gn:name":"Borszowice",
    "gn:population":0,
    "gn:timezone":"Europe/Warsaw",
    "iso:country":"PL",
    "name:pol_x_preferred":[
        "Borszowice"
    ],
    "name:ukr_x_preferred":[
        "\u0411\u043e\u0440\u0448\u043e\u0432\u0456\u0446\u0435"
    ],
    "wof:name":"Borszowice",
    "wof:placetype":"locality"
},
  "geometry": {"coordinates":[20.48607,50.63182000000001],"type":"Point"}
}