{
  "type": "Feature",
  "properties": {
    "gn:admin1_code":"86.0",
    "gn:admin2_code":"3021.0",
    "gn:admin3_code":"302110.0",
    "gn:asciiname":"Nowinki",
    "gn:country_code":"PL",
    "gn:dem":63,
    "gn:feature_class":"P",
    "gn:feature_code":"PPL",
    "gn:name":"Nowinki",
    "gn:population":0,
    "gn:timezone":"Europe/Warsaw",
    "iso:country":"PL",
    "name:ceb_x_preferred":[
        "Nowinki"
    ],
    "name:fra_x_preferred":[
        "Nowinki"
    ],
    "name:pol_x_preferred":[
        "Nowinki"
    ],
    "name:ukr_x_preferred":[
        "\u041d\u043e\u0432\u0456\u043d\u043a\u0456"
    ],
    "wof:name":"Nowinki",
    "wof:placetype":"locality"
},
  "geometry": {"coordinates":[16.82496,52.19919],"type":"Point"}
}