{
  "type": "Feature",
  "properties": {
    "gn:admin1_code":"78.0",
    "gn:admin2_code":"1411.0",
    "gn:admin3_code":"141107.0",
    "gn:asciiname":"Mroczki Rebiszewo",
    "gn:country_code":"PL",
    "gn:dem":101,
    "gn:feature_class":"P",
    "gn:feature_code":"PPL",
    "gn:name":"Mroczki R\u0119biszewo",
    "gn:population":0,
    "gn:timezone":"Europe/Warsaw",
    "iso:country":"PL",
    "wof:name":"Mroczki Rebiszewo",
    "wof:placetype":"locality"
},
  "geometry": {"coordinates":[21.3977,52.85303],"type":"Point"}
}