{
  "type": "Feature",
  "properties": {
    "gn:admin1_code":"78.0",
    "gn:admin2_code":"1403.0",
    "gn:admin3_code":"140314.0",
    "gn:asciiname":"Ostrozen C",
    "gn:country_code":"PL",
    "gn:dem":181,
    "gn:feature_class":"P",
    "gn:feature_code":"PPL",
    "gn:name":"Ostro\u017ce\u0144 C",
    "gn:population":0,
    "gn:timezone":"Europe/Warsaw",
    "iso:country":"PL",
    "wof:name":"Ostrozen C",
    "wof:placetype":"locality"
},
  "geometry": {"coordinates":[21.79472,51.77352],"type":"Point"}
}