{
  "type": "Feature",
  "properties": {
    "gn:admin1_code":"74.0",
    "gn:admin2_code":"1002.0",
    "gn:admin3_code":"100204.0",
    "gn:asciiname":"Kajew",
    "gn:country_code":"PL",
    "gn:dem":123,
    "gn:feature_class":"P",
    "gn:feature_code":"PPL",
    "gn:name":"Kajew",
    "gn:population":0,
    "gn:timezone":"Europe/Warsaw",
    "iso:country":"PL",
    "name:fra_x_preferred":[
        "Kajew"
    ],
    "name:pol_x_preferred":[
        "Kajew"
    ],
    "name:ukr_x_preferred":[
        "\u041a\u0430\u0454\u0432"
    ],
    "wof:name":"Kajew",
    "wof:placetype":"locality"
},
  "geometry": {"coordinates":[19.16471,52.27562],"type":"Point"}
}