{
  "type": "Feature",
  "properties": {
    "gn:admin1_code":"86.0",
    "gn:admin2_code":"3014.0",
    "gn:admin3_code":"301404.0",
    "gn:asciiname":"Lawica",
    "gn:country_code":"PL",
    "gn:dem":63,
    "gn:feature_class":"P",
    "gn:feature_code":"PPL",
    "gn:name":"\u0141awica",
    "gn:population":0,
    "gn:timezone":"Europe/Warsaw",
    "iso:country":"PL",
    "name:und_x_variant":[
        "\u0141awica"
    ],
    "wof:name":"Lawica",
    "wof:placetype":"locality"
},
  "geometry": {"coordinates":[16.00911,52.61448000000001],"type":"Point"}
}