{
  "type": "Feature",
  "properties": {
    "gn:admin1_code":"81.0",
    "gn:admin2_code":"2007.0",
    "gn:admin3_code":"200702.0",
    "gn:asciiname":"Puchaly",
    "gn:country_code":"PL",
    "gn:dem":118,
    "gn:feature_class":"P",
    "gn:feature_code":"PPL",
    "gn:name":"Pucha\u0142y",
    "gn:population":0,
    "gn:timezone":"Europe/Warsaw",
    "iso:country":"PL",
    "name:lit_x_preferred":[
        "Puchalai"
    ],
    "name:pol_x_preferred":[
        "Pucha\u0142y"
    ],
    "name:ukr_x_preferred":[
        "\u041f\u0443\u0445\u0430\u043b\u0438"
    ],
    "wof:name":"Puchaly",
    "wof:placetype":"locality"
},
  "geometry": {"coordinates":[22.22479,53.07617],"type":"Point"}
}