{
  "type": "Feature",
  "properties": {
    "gn:admin1_code":"86.0",
    "gn:admin2_code":"3014.0",
    "gn:admin3_code":"301403.0",
    "gn:asciiname":"Zatom Stary",
    "gn:country_code":"PL",
    "gn:dem":46,
    "gn:feature_class":"P",
    "gn:feature_code":"PPL",
    "gn:name":"Zatom Stary",
    "gn:population":0,
    "gn:timezone":"Europe/Warsaw",
    "iso:country":"PL",
    "wof:name":"Zatom Stary",
    "wof:placetype":"locality"
},
  "geometry": {"coordinates":[15.9682,52.63344],"type":"Point"}
}