{
  "type": "Feature",
  "properties": {
    "gn:admin1_code":"86.0",
    "gn:admin2_code":"3014.0",
    "gn:admin3_code":"301403.0",
    "gn:asciiname":"Zatom Stary",
    "gn:country_code":"PL",
    "gn:dem":46,
    "gn:feature_class":"P",
    "gn:feature_code":"PPL",
    "gn:name":"Zatom Stary",
    "gn:population":0,
    "gn:timezone":"Europe/Warsaw",
    "iso:country":"PL",
    "name:azb_x_preferred":[
        "\u0632\u0627\u062a\u0648\u0645 \u0633\u062a\u0627\u0631\u0647"
    ],
    "name:ceb_x_preferred":[
        "Zatom Stary"
    ],
    "name:fas_x_preferred":[
        "\u0632\u0627\u062a\u0648\u0645 \u0633\u062a\u0627\u0631\u0647"
    ],
    "name:fra_x_preferred":[
        "Zatom Stary"
    ],
    "name:pol_x_preferred":[
        "Zatom Stary"
    ],
    "name:ukr_x_preferred":[
        "\u0417\u0430\u0442\u043e\u043c-\u0421\u0442\u0430\u0440\u0438\u0439"
    ],
    "wof:name":"Zatom Stary",
    "wof:placetype":"locality"
},
  "geometry": {"coordinates":[15.9682,52.63344],"type":"Point"}
}