{
  "type": "Feature",
  "properties": {
    "gn:admin1_code":"74.0",
    "gn:admin2_code":"1001.0",
    "gn:admin3_code":"100107.0",
    "gn:asciiname":"Marcelow",
    "gn:country_code":"PL",
    "gn:dem":166,
    "gn:feature_class":"P",
    "gn:feature_code":"PPL",
    "gn:name":"Marcel\u00f3w",
    "gn:population":0,
    "gn:timezone":"Europe/Warsaw",
    "iso:country":"PL",
    "wof:name":"Marcelow",
    "wof:placetype":"locality"
},
  "geometry": {"coordinates":[19.11249,51.37522],"type":"Point"}
}