{
  "type": "Feature",
  "properties": {
    "gn:country":"PL",
    "gn:fcode":"PPL",
    "gn:population":290,
    "iso:country":"PL",
    "name:ast_x_preferred":[
        "Stare Miasto"
    ],
    "name:ceb_x_preferred":[
        "Stare Miasto"
    ],
    "name:deu_x_preferred":[
        "Stare Miasto in Stary Dzierzgo\u0144"
    ],
    "name:eng_x_preferred":[
        "Stare Miasto"
    ],
    "name:fra_x_preferred":[
        "Stare Miasto"
    ],
    "name:pol_x_preferred":[
        "Stare Miasto"
    ],
    "name:rus_x_preferred":[
        "\u0421\u0442\u0430\u0440\u0435-\u041c\u044f\u0441\u0442\u043e"
    ],
    "name:ukr_x_preferred":[
        "\u0421\u0442\u0430\u0440\u0435 \u041c\u044f\u0441\u0442\u043e"
    ],
    "name:und_x_variant":[
        "Alstadt"
    ],
    "qs_pg:aaroncc":"PL",
    "qs_pg:gn_country":"PL",
    "qs_pg:gn_fcode":"PPL",
    "qs_pg:gn_pop":290,
    "qs_pg:name":"Stare Miasto",
    "qs_pg:name_adm0":"Polska",
    "qs_pg:name_adm1":"Pomorskie",
    "qs_pg:photos_9k":1,
    "qs_pg:photos_9r":1,
    "qs_pg:photos_all":1,
    "qs_pg:photos_sr":0,
    "qs_pg:pop_sr":2,
    "qs_pg:qs_pg_placetype":"locality",
    "qs_pg:qs_pg_placetype_gp":"Town",
    "qs_pg:woe_adm0":23424923,
    "woe:adm0_id":23424923,
    "woe:name_adm0":"Polska",
    "woe:name_adm1":"Pomorskie",
    "woe:placetype":"Town",
    "wof:name":"Stare Miasto",
    "wof:placetype":"locality",
    "wof:population":290
},
  "geometry": {"coordinates":[19.36581,53.88775],"type":"Point"}
}