{
  "type": "Feature",
  "properties": {
    "gn:admin1_code":"86.0",
    "gn:admin2_code":"3027.0",
    "gn:admin3_code":"302707.0",
    "gn:asciiname":"Sarbicko",
    "gn:country_code":"PL",
    "gn:dem":110,
    "gn:feature_class":"P",
    "gn:feature_code":"PPL",
    "gn:name":"Sarbicko",
    "gn:population":0,
    "gn:timezone":"Europe/Warsaw",
    "iso:country":"PL",
    "name:ceb_x_preferred":[
        "Sarbicko"
    ],
    "name:deu_x_preferred":[
        "Sarbicko"
    ],
    "name:pol_x_preferred":[
        "Sarbicko"
    ],
    "name:ukr_x_preferred":[
        "\u0421\u0430\u0440\u0431\u0456\u0446\u044c\u043a\u043e"
    ],
    "wof:name":"Sarbicko",
    "wof:placetype":"locality"
},
  "geometry": {"coordinates":[18.27381,52.05723],"type":"Point"}
}