{
  "type": "Feature",
  "properties": {
    "gn:admin1_code":"80.0",
    "gn:admin2_code":"1808.0",
    "gn:admin3_code":"180804.0",
    "gn:asciiname":"Wygnanki",
    "gn:country_code":"PL",
    "gn:dem":169,
    "gn:feature_class":"P",
    "gn:feature_code":"PPL",
    "gn:name":"Wygnanki",
    "gn:population":0,
    "gn:timezone":"Europe/Warsaw",
    "iso:country":"PL",
    "name:azb_x_preferred":[
        "\u0648\u0642\u0646\u0627\u0646\u06a9\u06cc"
    ],
    "name:ceb_x_preferred":[
        "Wygnanki"
    ],
    "name:fas_x_preferred":[
        "\u0648\u06af\u0646\u0627\u0646\u06a9\u06cc"
    ],
    "name:fra_x_preferred":[
        "Wygnanki"
    ],
    "name:lit_x_preferred":[
        "Vignankai"
    ],
    "name:pol_x_preferred":[
        "Wygnanki"
    ],
    "name:ukr_x_preferred":[
        "\u0412\u0438\u0491\u043d\u0430\u043d\u043a\u0456"
    ],
    "wof:name":"Wygnanki",
    "wof:placetype":"locality"
},
  "geometry": {"coordinates":[22.51071,50.245],"type":"Point"}
}