{
  "type": "Feature",
  "properties": {
    "gn:admin1_code":"75.0",
    "gn:admin2_code":"618.0",
    "gn:admin3_code":"61804.0",
    "gn:asciiname":"Karolowka",
    "gn:country_code":"PL",
    "gn:dem":264,
    "gn:feature_class":"P",
    "gn:feature_code":"PPL",
    "gn:name":"Karol\u00f3wka",
    "gn:population":0,
    "gn:timezone":"Europe/Warsaw",
    "iso:country":"PL",
    "name:und_x_variant":[
        "Korol\u00f3wka",
        "Karol\u00f3wka"
    ],
    "wof:name":"Karolowka",
    "wof:placetype":"locality"
},
  "geometry": {"coordinates":[23.46955,50.58838],"type":"Point"}
}