{
  "type": "Feature",
  "properties": {
    "gn:admin1_code":"75.0",
    "gn:admin2_code":"619.0",
    "gn:admin3_code":"61905.0",
    "gn:asciiname":"Wielkopole",
    "gn:cc2":"PL",
    "gn:country_code":"PL",
    "gn:dem":196,
    "gn:feature_class":"P",
    "gn:feature_code":"PPL",
    "gn:name":"Wielkopole",
    "gn:population":0,
    "gn:timezone":"Europe/Warsaw",
    "iso:country":"PL",
    "name:fra_x_preferred":[
        "Wielkopole"
    ],
    "name:pol_x_preferred":[
        "Wielkopole"
    ],
    "name:ukr_x_preferred":[
        "\u0412\u0435\u043b\u044c\u043a\u043e\u043f\u043e\u043b\u0435"
    ],
    "name:und_x_variant":[
        "Kolonia Wielkopole",
        "Wielkopole"
    ],
    "wof:name":"Wielkopole",
    "wof:placetype":"locality"
},
  "geometry": {"coordinates":[23.24707,51.34289],"type":"Point"}
}