{
  "type": "Feature",
  "properties": {
    "gn:admin1_code":"85.0",
    "gn:admin2_code":"2815.0",
    "gn:admin3_code":"281504.0",
    "gn:asciiname":"Wynki",
    "gn:cc2":"PL",
    "gn:country_code":"PL",
    "gn:dem":99,
    "gn:feature_class":"P",
    "gn:feature_code":"PPL",
    "gn:name":"Wynki",
    "gn:population":0,
    "gn:timezone":"Europe/Warsaw",
    "iso:country":"PL",
    "name:ceb_x_preferred":[
        "Wynki"
    ],
    "name:fra_x_preferred":[
        "Wynki"
    ],
    "name:pol_x_preferred":[
        "Wynki"
    ],
    "name:ukr_x_preferred":[
        "\u0412\u0438\u043d\u043a\u0456"
    ],
    "name:und_x_variant":[
        "Wonicken"
    ],
    "wof:name":"Wynki",
    "wof:placetype":"locality"
},
  "geometry": {"coordinates":[20.10017,53.77154],"type":"Point"}
}