{
  "type": "Feature",
  "properties": {
    "gn:admin1_code":"85.0",
    "gn:admin2_code":"2808.0",
    "gn:admin3_code":"280805.0",
    "gn:asciiname":"Worplawki",
    "gn:country_code":"PL",
    "gn:dem":125,
    "gn:feature_class":"P",
    "gn:feature_code":"PPL",
    "gn:name":"Worp\u0142awki",
    "gn:population":0,
    "gn:timezone":"Europe/Warsaw",
    "iso:country":"PL",
    "name:deu_x_preferred":[
        "Worp\u0142awki"
    ],
    "name:pol_x_preferred":[
        "Worp\u0142awki"
    ],
    "name:ukr_x_preferred":[
        "\u0412\u043e\u0440\u043f\u043b\u0430\u0432\u043a\u0456"
    ],
    "wof:name":"Worplawki",
    "wof:placetype":"locality"
},
  "geometry": {"coordinates":[21.17123,54.08508000000001],"type":"Point"}
}