{
  "type": "Feature",
  "properties": {
    "gn:admin1_code":"86.0",
    "gn:admin2_code":"3009.0",
    "gn:admin3_code":"300906.0",
    "gn:asciiname":"Podgajew",
    "gn:country_code":"PL",
    "gn:dem":116,
    "gn:feature_class":"P",
    "gn:feature_code":"PPL",
    "gn:name":"Podgajew",
    "gn:population":0,
    "gn:timezone":"Europe/Warsaw",
    "iso:country":"PL",
    "name:pol_x_preferred":[
        "Podgajew"
    ],
    "name:ukr_x_preferred":[
        "\u041f\u043e\u0434\u0491\u0430\u0454\u0432"
    ],
    "wof:name":"Podgajew",
    "wof:placetype":"locality"
},
  "geometry": {"coordinates":[18.95494,52.21055],"type":"Point"}
}