{
  "type": "Feature",
  "properties": {
    "gn:admin1_code":"73.0",
    "gn:admin2_code":"419.0",
    "gn:admin3_code":"41901.0",
    "gn:asciiname":"Pturek",
    "gn:country_code":"PL",
    "gn:dem":77,
    "gn:feature_class":"P",
    "gn:feature_code":"PPL",
    "gn:name":"Pturek",
    "gn:population":0,
    "gn:timezone":"Europe/Warsaw",
    "iso:country":"PL",
    "name:pol_x_preferred":[
        "Pturek"
    ],
    "name:ukr_x_preferred":[
        "\u041f\u0442\u0443\u0440\u0435\u043a"
    ],
    "wof:name":"Pturek",
    "wof:placetype":"locality"
},
  "geometry": {"coordinates":[17.87819,52.88198000000001],"type":"Point"}
}