{
  "type": "Feature",
  "properties": {
    "gn:admin1_code":"85.0",
    "gn:admin2_code":"2811.0",
    "gn:admin3_code":"281104.0",
    "gn:asciiname":"Orlowo",
    "gn:country_code":"PL",
    "gn:dem":160,
    "gn:feature_class":"P",
    "gn:feature_code":"PPL",
    "gn:name":"Or\u0142owo",
    "gn:population":0,
    "gn:timezone":"Europe/Warsaw",
    "iso:country":"PL",
    "name:und_x_variant":[
        "Orlau",
        "Or\u0142owo"
    ],
    "wof:name":"Orlowo",
    "wof:placetype":"locality"
},
  "geometry": {"coordinates":[20.45531,53.4488],"type":"Point"}
}