{
  "type": "Feature",
  "properties": {
    "gn:admin1_code":"75.0",
    "gn:admin2_code":"613.0",
    "gn:admin3_code":"61306.0",
    "gn:asciiname":"Juliopol",
    "gn:country_code":"PL",
    "gn:dem":154,
    "gn:feature_class":"P",
    "gn:feature_code":"PPL",
    "gn:name":"Juliopol",
    "gn:population":0,
    "gn:timezone":"Europe/Warsaw",
    "iso:country":"PL",
    "name:fra_x_preferred":[
        "Juliopol"
    ],
    "name:pol_x_preferred":[
        "Juliopol"
    ],
    "name:ukr_x_preferred":[
        "\u042e\u043b\u044c\u043e\u043f\u043e\u043b\u044c"
    ],
    "name:und_x_variant":[
        "Juljopol",
        "Juliopol"
    ],
    "wof:name":"Juliopol",
    "wof:placetype":"locality"
},
  "geometry": {"coordinates":[22.70943,51.59068],"type":"Point"}
}