{
  "type": "Feature",
  "properties": {
    "gn:admin1_code":"74.0",
    "gn:admin2_code":"1003.0",
    "gn:admin3_code":"100303.0",
    "gn:asciiname":"Przymilow",
    "gn:country_code":"PL",
    "gn:dem":155,
    "gn:feature_class":"P",
    "gn:feature_code":"PPL",
    "gn:name":"Przymi\u0142\u00f3w",
    "gn:population":0,
    "gn:timezone":"Europe/Warsaw",
    "iso:country":"PL",
    "name:und_x_variant":[
        "Przymi\u0142\u00f3w"
    ],
    "wof:name":"Przymilow",
    "wof:placetype":"locality"
},
  "geometry": {"coordinates":[19.00835,51.53115],"type":"Point"}
}