{
  "type": "Feature",
  "properties": {
    "gn:admin1_code":"72.0",
    "gn:admin2_code":"222.0",
    "gn:admin3_code":"22203.0",
    "gn:asciiname":"Slawowice",
    "gn:country_code":"PL",
    "gn:dem":154,
    "gn:feature_class":"P",
    "gn:feature_code":"PPL",
    "gn:name":"S\u0142awowice",
    "gn:population":0,
    "gn:timezone":"Europe/Warsaw",
    "iso:country":"PL",
    "name:pol_x_preferred":[
        "S\u0142awowice"
    ],
    "name:ukr_x_preferred":[
        "\u0421\u043b\u0430\u0432\u043e\u0432\u0456\u0446\u0435"
    ],
    "name:und_x_variant":[
        "S\u0142awowice"
    ],
    "wof:name":"Slawowice",
    "wof:placetype":"locality"
},
  "geometry": {"coordinates":[16.73733,51.36289],"type":"Point"}
}