{
  "type": "Feature",
  "properties": {
    "gn:admin1_code":"86.0",
    "gn:admin2_code":"3011.0",
    "gn:admin3_code":"301102.0",
    "gn:asciiname":"Stary Golebin",
    "gn:country_code":"PL",
    "gn:dem":81,
    "gn:feature_class":"P",
    "gn:feature_code":"PPL",
    "gn:name":"Stary Go\u0142\u0119bin",
    "gn:population":0,
    "gn:timezone":"Europe/Warsaw",
    "iso:country":"PL",
    "name:fra_x_preferred":[
        "Stary Go\u0142\u0119bin"
    ],
    "name:pol_x_preferred":[
        "Stary Go\u0142\u0119bin"
    ],
    "name:ukr_x_preferred":[
        "\u0421\u0442\u0430\u0440\u0438\u0439 \u0490\u043e\u043b\u0435\u043c\u0431\u0456\u043d"
    ],
    "name:und_x_variant":[
        "Go\u0142\u0119bin Stary"
    ],
    "wof:name":"Stary Golebin",
    "wof:placetype":"locality"
},
  "geometry": {"coordinates":[16.78866,52.08257],"type":"Point"}
}