{
  "type": "Feature",
  "properties": {
    "gn:admin1_code":"86.0",
    "gn:admin2_code":"3011.0",
    "gn:admin3_code":"301102.0",
    "gn:asciiname":"Stary Golebin",
    "gn:country_code":"PL",
    "gn:dem":81,
    "gn:feature_class":"P",
    "gn:feature_code":"PPL",
    "gn:name":"Stary Go\u0142\u0119bin",
    "gn:population":0,
    "gn:timezone":"Europe/Warsaw",
    "iso:country":"PL",
    "name:und_x_variant":[
        "Go\u0142\u0119bin Stary",
        "Stary Go\u0142\u0119bin"
    ],
    "wof:name":"Stary Golebin",
    "wof:placetype":"locality"
},
  "geometry": {"coordinates":[16.78866,52.08257],"type":"Point"}
}