{
  "type": "Feature",
  "properties": {
    "gn:gn_country":"PL",
    "gn:gn_fcode":"PPL",
    "gn:gn_pop":1935,
    "gn:population":1935,
    "iso:country":"PL",
    "name:eng_x_preferred":[
        "Ostrowy nad Oksz\u0105"
    ],
    "name:fra_x_preferred":[
        "Ostrowy nad Oksz\u0105"
    ],
    "name:pol_x_preferred":[
        "Ostrowy nad Oksz\u0105"
    ],
    "qs_pg:aaroncc":"PL",
    "qs_pg:gn_country":"PL",
    "qs_pg:gn_fcode":"PPL",
    "qs_pg:gn_pop":1935,
    "qs_pg:name":"Ostrowy nad Oksz\u0105",
    "qs_pg:name_adm0":"Polska",
    "qs_pg:name_adm1":"Sl\u0105skie",
    "qs_pg:photos":10,
    "qs_pg:photos_1k":2,
    "qs_pg:photos_9k":1,
    "qs_pg:photos_9r":1,
    "qs_pg:photos_all":10,
    "qs_pg:photos_sr":1,
    "qs_pg:pop_sr":3,
    "qs_pg:qs_pg_placetype":"locality",
    "qs_pg:qs_pg_placetype_gp":"Town",
    "qs_pg:woe_adm0":23424923,
    "woe:adm0_id":23424923,
    "woe:name_adm0":"Polska",
    "woe:name_adm1":"Sl\u0105skie",
    "woe:placetype":"Town",
    "wof:name":"Ostrowy nad Oksz\u0105",
    "wof:placetype":"locality",
    "wof:population":1935
},
  "geometry": {"coordinates":[19.05355,50.97799],"type":"Point"}
}