{
  "type": "Feature",
  "properties": {
    "gn:admin1_code":"74.0",
    "gn:admin2_code":"1017.0",
    "gn:admin3_code":"101701.0",
    "gn:asciiname":"Biala",
    "gn:country_code":"PL",
    "gn:dem":183,
    "gn:feature_class":"P",
    "gn:feature_code":"PPL",
    "gn:name":"Bia\u0142a",
    "gn:population":0,
    "gn:timezone":"Europe/Warsaw",
    "iso:country":"PL",
    "name:pol_x_preferred":[
        "Bia\u0142a"
    ],
    "wof:coterminous":[
        1477751317
    ],
    "wof:name":"Biala",
    "wof:placetype":"locality"
},
  "geometry": {"coordinates":[18.43343,51.28302],"type":"Point"}
}