{
  "type": "Feature",
  "properties": {
    "gn:admin1_code":"75.0",
    "gn:admin2_code":"601.0",
    "gn:admin3_code":"60115.0",
    "gn:asciiname":"Przechod",
    "gn:country_code":"PL",
    "gn:dem":159,
    "gn:feature_class":"P",
    "gn:feature_code":"PPL",
    "gn:name":"Przech\u00f3d",
    "gn:population":0,
    "gn:timezone":"Europe/Warsaw",
    "iso:country":"PL",
    "name:und_x_variant":[
        "Przech\u00f3d"
    ],
    "wof:name":"Przechod",
    "wof:placetype":"locality"
},
  "geometry": {"coordinates":[23.35578,51.80159],"type":"Point"}
}