{
  "type": "Feature",
  "properties": {
    "iso:country":"PL",
    "name:eng_x_preferred":[
        "Sypniewo"
    ],
    "name:pol_x_preferred":[
        "Sypniewo"
    ],
    "wof:name":"Sypniewo",
    "wof:placetype":"neighbourhood"
},
  "geometry": {"coordinates":[16.98197981636779,52.30865269082928],"type":"Point"}
}