{
  "type": "Feature",
  "properties": {
    "gn:admin1_code":"78.0",
    "gn:admin2_code":"1420.0",
    "gn:admin3_code":"142004.0",
    "gn:asciiname":"Parlin",
    "gn:country_code":"PL",
    "gn:dem":102,
    "gn:feature_class":"P",
    "gn:feature_code":"PPL",
    "gn:name":"Parlin",
    "gn:population":0,
    "gn:timezone":"Europe/Warsaw",
    "iso:country":"PL",
    "name:fra_x_preferred":[
        "Parlin"
    ],
    "name:pol_x_preferred":[
        "Parlin"
    ],
    "name:ukr_x_preferred":[
        "\u041f\u0430\u0440\u043b\u0456\u043d"
    ],
    "wof:name":"Parlin",
    "wof:placetype":"locality"
},
  "geometry": {"coordinates":[20.32694,52.42043],"type":"Point"}
}