{
  "type": "Feature",
  "properties": {
    "gn:admin1_code":"86.0",
    "gn:admin2_code":"3004.0",
    "gn:admin3_code":"300405.0",
    "gn:asciiname":"Grabonog",
    "gn:country_code":"PL",
    "gn:dem":119,
    "gn:feature_class":"P",
    "gn:feature_code":"PPL",
    "gn:name":"Grabon\u00f3g",
    "gn:population":0,
    "gn:timezone":"Europe/Warsaw",
    "iso:country":"PL",
    "name:azb_x_preferred":[
        "\u0642\u0631\u0627\u0628\u0648\u0646\u0648\u0642"
    ],
    "name:ceb_x_preferred":[
        "Grabon\u00f3g"
    ],
    "name:fas_x_preferred":[
        "\u06af\u0631\u0627\u0628\u0648\u0646\u0648\u06af"
    ],
    "name:fra_x_preferred":[
        "Grabon\u00f3g"
    ],
    "name:nld_x_preferred":[
        "Grabon\u00f3g"
    ],
    "name:pol_x_preferred":[
        "Grabon\u00f3g"
    ],
    "name:ukr_x_preferred":[
        "\u0490\u0440\u0430\u0431\u043e\u043d\u0443\u0491"
    ],
    "wof:name":"Grabonog",
    "wof:placetype":"locality"
},
  "geometry": {"coordinates":[17.0483,51.8716],"type":"Point"}
}