{
  "type": "Feature",
  "properties": {
    "gn:admin1_code":"86.0",
    "gn:admin2_code":"3004.0",
    "gn:admin3_code":"300405.0",
    "gn:asciiname":"Grabonog",
    "gn:country_code":"PL",
    "gn:dem":119,
    "gn:feature_class":"P",
    "gn:feature_code":"PPL",
    "gn:name":"Grabon\u00f3g",
    "gn:population":0,
    "gn:timezone":"Europe/Warsaw",
    "iso:country":"PL",
    "name:und_x_variant":[
        "Grabon\u00f3g"
    ],
    "wof:name":"Grabonog",
    "wof:placetype":"locality"
},
  "geometry": {"coordinates":[17.0483,51.8716],"type":"Point"}
}