{
  "type": "Feature",
  "properties": {
    "gn:admin1_code":"78.0",
    "gn:admin2_code":"1424.0",
    "gn:admin3_code":"142407.0",
    "gn:asciiname":"Wolka Zatorska",
    "gn:cc2":"PL",
    "gn:country_code":"PL",
    "gn:dem":104,
    "gn:feature_class":"P",
    "gn:feature_code":"PPL",
    "gn:name":"W\u00f3lka Zatorska",
    "gn:population":0,
    "gn:timezone":"Europe/Warsaw",
    "iso:country":"PL",
    "name:und_x_variant":[
        "Zatorska W\u00f3lka",
        "W\u00f3lka Zatorska"
    ],
    "wof:name":"Wolka Zatorska",
    "wof:placetype":"locality"
},
  "geometry": {"coordinates":[21.191,52.57984],"type":"Point"}
}