{
  "type": "Feature",
  "properties": {
    "gn:gn_country":"PL",
    "gn:gn_fcode":"PPL",
    "gn:gn_pop":1300,
    "gn:population":1300,
    "iso:country":"PL",
    "name:eng_x_preferred":[
        "Stanis\u0142awice"
    ],
    "name:fra_x_preferred":[
        "Stanis\u0142awice"
    ],
    "name:pol_x_preferred":[
        "Stanis\u0142awice"
    ],
    "qs_pg:aaroncc":"PL",
    "qs_pg:gn_country":"PL",
    "qs_pg:gn_fcode":"PPL",
    "qs_pg:gn_pop":1300,
    "qs_pg:name":"Stanis\u0142awice",
    "qs_pg:name_adm0":"Polska",
    "qs_pg:name_adm1":"Ma\u0142opolskie",
    "qs_pg:photos_9k":1,
    "qs_pg:photos_9r":1,
    "qs_pg:photos_all":7,
    "qs_pg:photos_sr":0,
    "qs_pg:pop_sr":3,
    "qs_pg:qs_pg_placetype":"locality",
    "qs_pg:qs_pg_placetype_gp":"Town",
    "qs_pg:woe_adm0":23424923,
    "woe:adm0_id":23424923,
    "woe:name_adm0":"Polska",
    "woe:name_adm1":"Ma\u0142opolskie",
    "woe:placetype":"Town",
    "wof:name":"Stanis\u0142awice",
    "wof:placetype":"locality",
    "wof:population":1300
},
  "geometry": {"coordinates":[20.35123,49.9855],"type":"Point"}
}