{
  "type": "Feature",
  "properties": {
    "gn:admin1_code":"85.0",
    "gn:admin2_code":"2806.0",
    "gn:admin3_code":"280610.0",
    "gn:asciiname":"Czarnowka",
    "gn:country_code":"PL",
    "gn:dem":132,
    "gn:feature_class":"P",
    "gn:feature_code":"PPL",
    "gn:name":"Czarn\u00f3wka",
    "gn:population":0,
    "gn:timezone":"Europe/Warsaw",
    "iso:country":"PL",
    "name:deu_x_preferred":[
        "Czarn\u00f3wka"
    ],
    "name:fra_x_preferred":[
        "Czarn\u00f3wka"
    ],
    "name:pol_x_preferred":[
        "Czarn\u00f3wka"
    ],
    "name:ukr_x_preferred":[
        "\u0427\u0430\u0440\u043d\u0443\u0432\u043a\u0430"
    ],
    "name:und_x_variant":[
        "Grundensee",
        "Czarnowken",
        "Czarnowken Kreis L\u00f6tzen"
    ],
    "wof:name":"Czarnowka",
    "wof:placetype":"locality"
},
  "geometry": {"coordinates":[22.12841,53.99683],"type":"Point"}
}