{
  "type": "Feature",
  "properties": {
    "gn:admin1_code":"74.0",
    "gn:admin2_code":"1010.0",
    "gn:admin3_code":"101004.0",
    "gn:asciiname":"Zeronie",
    "gn:country_code":"PL",
    "gn:dem":215,
    "gn:feature_class":"P",
    "gn:feature_code":"PPL",
    "gn:name":"\u017beronie",
    "gn:population":0,
    "gn:timezone":"Europe/Warsaw",
    "iso:country":"PL",
    "name:fra_x_preferred":[
        "\u017beronie"
    ],
    "name:pol_x_preferred":[
        "\u017beronie"
    ],
    "name:ukr_x_preferred":[
        "\u0416\u0435\u0440\u043e\u043d\u0435"
    ],
    "wof:name":"Zeronie",
    "wof:placetype":"locality"
},
  "geometry": {"coordinates":[19.46799,51.52434],"type":"Point"}
}