{
  "type": "Feature",
  "properties": {
    "gn:country":"PL",
    "gn:fcode":"PPL",
    "gn:population":781,
    "iso:country":"PL",
    "name:ast_x_preferred":[
        "Kleszcz\u00f3w"
    ],
    "name:ceb_x_preferred":[
        "Kleszcz\u00f3w"
    ],
    "name:deu_x_preferred":[
        "Kl\u00fcschau"
    ],
    "name:eng_x_preferred":[
        "Kleszcz\u00f3w"
    ],
    "name:fra_x_preferred":[
        "Kleszcz\u00f3w"
    ],
    "name:pol_x_preferred":[
        "Kleszcz\u00f3w"
    ],
    "name:ukr_x_preferred":[
        "\u041a\u043b\u0435\u0449\u0443\u0432"
    ],
    "name:und_x_variant":[
        "Kleszczowice"
    ],
    "qs_pg:aaroncc":"PL",
    "qs_pg:gn_country":"PL",
    "qs_pg:gn_fcode":"PPL",
    "qs_pg:gn_pop":781,
    "qs_pg:name":"Kleszcz\u00f3w",
    "qs_pg:name_adm0":"Polska",
    "qs_pg:name_adm1":"Sl\u0105skie",
    "qs_pg:photos_9r":0,
    "qs_pg:photos_sr":0,
    "qs_pg:pop_sr":2,
    "qs_pg:qs_pg_placetype":"locality",
    "qs_pg:qs_pg_placetype_gp":"Town",
    "qs_pg:woe_adm0":23424923,
    "woe:adm0_id":23424923,
    "woe:name_adm0":"Polska",
    "woe:name_adm1":"Sl\u0105skie",
    "woe:placetype":"Town",
    "wof:name":"Kleszcz\u00f3w",
    "wof:placetype":"locality",
    "wof:population":781
},
  "geometry": {"coordinates":[18.52724,50.34787],"type":"Point"}
}