{
  "type": "Feature",
  "properties": {
    "gn:admin1_code":"75.0",
    "gn:admin2_code":"607.0",
    "gn:admin3_code":"60708.0",
    "gn:asciiname":"Skorczyce",
    "gn:country_code":"PL",
    "gn:dem":192,
    "gn:feature_class":"P",
    "gn:feature_code":"PPL",
    "gn:name":"Skorczyce",
    "gn:population":0,
    "gn:timezone":"Europe/Warsaw",
    "iso:country":"PL",
    "wof:name":"Skorczyce",
    "wof:placetype":"locality"
},
  "geometry": {"coordinates":[22.1981,51.01],"type":"Point"}
}