{
  "type": "Feature",
  "properties": {
    "gn:admin1_code":"75.0",
    "gn:admin2_code":"618.0",
    "gn:admin3_code":"61805.0",
    "gn:asciiname":"Zatyle",
    "gn:country_code":"PL",
    "gn:dem":258,
    "gn:feature_class":"P",
    "gn:feature_code":"PPL",
    "gn:name":"Zatyle",
    "gn:population":0,
    "gn:timezone":"Europe/Warsaw",
    "iso:country":"PL",
    "name:fra_x_preferred":[
        "Zatyle"
    ],
    "name:pol_x_preferred":[
        "Zatyle"
    ],
    "name:ukr_x_preferred":[
        "\u0417\u0430\u0442\u0438\u043b\u043b\u044f"
    ],
    "wof:name":"Zatyle",
    "wof:placetype":"locality"
},
  "geometry": {"coordinates":[23.49539,50.35909],"type":"Point"}
}