{
  "type": "Feature",
  "properties": {
    "gn:admin1_code":"82.0",
    "gn:admin2_code":"2216.0",
    "gn:admin3_code":"221602.0",
    "gn:asciiname":"Dabrowka Pruska",
    "gn:country_code":"PL",
    "gn:dem":77,
    "gn:feature_class":"P",
    "gn:feature_code":"PPL",
    "gn:name":"D\u0105br\u00f3wka Pruska",
    "gn:population":0,
    "gn:timezone":"Europe/Warsaw",
    "iso:country":"PL",
    "name:nld_x_preferred":[
        "D\u0105br\u00f3wka Pruska"
    ],
    "name:pol_x_preferred":[
        "D\u0105br\u00f3wka Pruska"
    ],
    "name:ukr_x_preferred":[
        "\u0414\u043e\u043c\u0431\u0440\u0443\u0432\u043a\u0430-\u041f\u0440\u0443\u0441\u044c\u043a\u0430"
    ],
    "name:und_x_variant":[
        "Preussisch Damerau"
    ],
    "wof:name":"Dabrowka Pruska",
    "wof:placetype":"locality"
},
  "geometry": {"coordinates":[19.13029,53.85689],"type":"Point"}
}