{
  "type": "Feature",
  "properties": {
    "gn:country":"PL",
    "gn:fcode":"PPL",
    "gn:population":497,
    "iso:country":"PL",
    "name:ast_x_preferred":[
        "Boles\u0142aw"
    ],
    "name:azb_x_preferred":[
        "\u0628\u0648\u0644\u0633\u0648\u0627\u0648"
    ],
    "name:ces_x_preferred":[
        "Boles\u0142aw"
    ],
    "name:deu_x_preferred":[
        "Boleslau"
    ],
    "name:eng_x_preferred":[
        "Boles\u0142aw"
    ],
    "name:epo_x_preferred":[
        "Boles\u0142aw"
    ],
    "name:fas_x_preferred":[
        "\u0628\u0648\u0644\u0633\u0648\u0627\u0648"
    ],
    "name:fra_x_preferred":[
        "Boles\u0142aw"
    ],
    "name:nld_x_preferred":[
        "Boles\u0142aw"
    ],
    "name:pol_x_preferred":[
        "Boles\u0142aw"
    ],
    "name:ukr_x_preferred":[
        "\u0411\u043e\u043b\u0435\u0441\u043b\u0430\u0432"
    ],
    "qs_pg:aaroncc":"PL",
    "qs_pg:gn_country":"PL",
    "qs_pg:gn_fcode":"PPL",
    "qs_pg:gn_pop":497,
    "qs_pg:name":"Boles\u0142aw",
    "qs_pg:name_adm0":"Polska",
    "qs_pg:name_adm1":"Sl\u0105skie",
    "qs_pg:photos_9r":0,
    "qs_pg:photos_sr":0,
    "qs_pg:pop_sr":2,
    "qs_pg:qs_pg_placetype":"locality",
    "qs_pg:qs_pg_placetype_gp":"Town",
    "qs_pg:woe_adm0":23424923,
    "woe:adm0_id":23424923,
    "woe:name_adm0":"Polska",
    "woe:name_adm1":"Sl\u0105skie",
    "woe:placetype":"Town",
    "wof:name":"Boles\u0142aw",
    "wof:placetype":"locality",
    "wof:population":497
},
  "geometry": {"coordinates":[18.20203,50.00653],"type":"Point"}
}