{
  "type": "Feature",
  "properties": {
    "gn:gn_country":"PL",
    "gn:gn_fcode":"PPL",
    "gn:gn_pop":1373,
    "gn:population":1373,
    "iso:country":"PL",
    "name:csb_x_preferred":[
        "\u00d2rl\u00e9"
    ],
    "name:eng_x_preferred":[
        "Orle"
    ],
    "name:fas_x_preferred":[
        "\u0627\u0648\u0631\u0644\u0647"
    ],
    "name:fra_x_preferred":[
        "Orle"
    ],
    "name:nld_x_preferred":[
        "Orle"
    ],
    "name:pol_x_preferred":[
        "Orle"
    ],
    "name:slk_x_preferred":[
        "Orle"
    ],
    "name:unk_x_variant":[
        "Worle"
    ],
    "qs_pg:aaroncc":"PL",
    "qs_pg:gn_country":"PL",
    "qs_pg:gn_fcode":"PPL",
    "qs_pg:gn_pop":1373,
    "qs_pg:name":"Orle",
    "qs_pg:name_adm0":"Polska",
    "qs_pg:name_adm1":"Pomorskie",
    "qs_pg:photos_9k":1,
    "qs_pg:photos_9r":1,
    "qs_pg:photos_all":2,
    "qs_pg:photos_sr":0,
    "qs_pg:pop_sr":3,
    "qs_pg:qs_pg_placetype":"locality",
    "qs_pg:qs_pg_placetype_gp":"Town",
    "qs_pg:woe_adm0":23424923,
    "woe:adm0_id":23424923,
    "woe:name_adm0":"Polska",
    "woe:name_adm1":"Pomorskie",
    "woe:placetype":"Town",
    "wof:name":"Orle",
    "wof:placetype":"locality",
    "wof:population":1373
},
  "geometry": {"coordinates":[18.17057,54.64022],"type":"Point"}
}