{
  "type": "Feature",
  "properties": {
    "gn:admin1_code":"76.0",
    "gn:admin2_code":"809.0",
    "gn:admin3_code":"80906.0",
    "gn:asciiname":"Gorki Male",
    "gn:country_code":"PL",
    "gn:dem":70,
    "gn:feature_class":"P",
    "gn:feature_code":"PPL",
    "gn:name":"G\u00f3rki Ma\u0142e",
    "gn:population":193,
    "gn:timezone":"Europe/Warsaw",
    "iso:country":"PL",
    "name:ceb_x_preferred":[
        "G\u00f3rki Ma\u0142e"
    ],
    "name:fra_x_preferred":[
        "G\u00f3rki Ma\u0142e"
    ],
    "name:pol_x_preferred":[
        "G\u00f3rki Ma\u0142e"
    ],
    "name:ukr_x_preferred":[
        "\u0490\u0443\u0440\u043a\u0456-\u041c\u0430\u043b\u0435"
    ],
    "wof:name":"Gorki Male",
    "wof:placetype":"locality",
    "wof:population":193
},
  "geometry": {"coordinates":[15.5932,52.03966],"type":"Point"}
}