{
  "type": "Feature",
  "properties": {
    "gn:admin1_code":"74.0",
    "gn:admin2_code":"1017.0",
    "gn:admin3_code":"101708.0",
    "gn:asciiname":"Smugi",
    "gn:country_code":"PL",
    "gn:dem":195,
    "gn:feature_class":"P",
    "gn:feature_code":"PPL",
    "gn:name":"Smugi",
    "gn:population":0,
    "gn:timezone":"Europe/Warsaw",
    "iso:country":"PL",
    "name:pol_x_preferred":[
        "Smugi"
    ],
    "name:ukr_x_preferred":[
        "\u0421\u043c\u0443\u0491\u0456"
    ],
    "wof:name":"Smugi",
    "wof:placetype":"locality"
},
  "geometry": {"coordinates":[18.43351,51.13908],"type":"Point"}
}