{
  "type": "Feature",
  "properties": {
    "gn:admin1_code":"74.0",
    "gn:admin2_code":"1002.0",
    "gn:admin3_code":"100206.0",
    "gn:asciiname":"Wroczyny",
    "gn:country_code":"PL",
    "gn:dem":121,
    "gn:feature_class":"P",
    "gn:feature_code":"PPL",
    "gn:name":"Wroczyny",
    "gn:population":0,
    "gn:timezone":"Europe/Warsaw",
    "iso:country":"PL",
    "name:fra_x_preferred":[
        "Wroczyny"
    ],
    "name:pol_x_preferred":[
        "Wroczyny"
    ],
    "name:ukr_x_preferred":[
        "\u0412\u0440\u043e\u0447\u0438\u043d\u0438"
    ],
    "wof:name":"Wroczyny",
    "wof:placetype":"locality"
},
  "geometry": {"coordinates":[19.26955,52.21009],"type":"Point"}
}