{
  "type": "Feature",
  "properties": {
    "gn:admin1_code":"75.0",
    "gn:admin2_code":"620.0",
    "gn:admin3_code":"62008.0",
    "gn:asciiname":"Zaburze",
    "gn:country_code":"PL",
    "gn:dem":225,
    "gn:feature_class":"P",
    "gn:feature_code":"PPL",
    "gn:name":"Zaburze",
    "gn:population":0,
    "gn:timezone":"Europe/Warsaw",
    "iso:country":"PL",
    "wof:name":"Zaburze",
    "wof:placetype":"locality"
},
  "geometry": {"coordinates":[22.85055,50.72397],"type":"Point"}
}