{
  "type": "Feature",
  "properties": {
    "gn:admin1_code":"75.0",
    "gn:admin2_code":"620.0",
    "gn:admin3_code":"62008.0",
    "gn:asciiname":"Zaburze",
    "gn:country_code":"PL",
    "gn:dem":225,
    "gn:feature_class":"P",
    "gn:feature_code":"PPL",
    "gn:name":"Zaburze",
    "gn:population":0,
    "gn:timezone":"Europe/Warsaw",
    "iso:country":"PL",
    "name:azb_x_preferred":[
        "\u0632\u0627\u0628\u0648\u0698\u0647"
    ],
    "name:fas_x_preferred":[
        "\u0632\u0627\u0628\u0648\u0698\u0647"
    ],
    "name:fra_x_preferred":[
        "Zaburze"
    ],
    "name:ita_x_preferred":[
        "Zaburze"
    ],
    "name:nld_x_preferred":[
        "Zaburze"
    ],
    "name:pol_x_preferred":[
        "Zaburze"
    ],
    "name:ukr_x_preferred":[
        "\u0417\u0430\u0431\u0443\u0436\u0435"
    ],
    "wof:name":"Zaburze",
    "wof:placetype":"locality"
},
  "geometry": {"coordinates":[22.85055,50.72397],"type":"Point"}
}