{
  "type": "Feature",
  "properties": {
    "gn:admin1_code":"77.0",
    "gn:admin2_code":"1208.0",
    "gn:admin3_code":"120807.0",
    "gn:asciiname":"Ilkowice",
    "gn:country_code":"PL",
    "gn:dem":227,
    "gn:feature_class":"P",
    "gn:feature_code":"PPL",
    "gn:name":"Ilkowice",
    "gn:population":0,
    "gn:timezone":"Europe/Warsaw",
    "iso:country":"PL",
    "wof:name":"Ilkowice",
    "wof:placetype":"locality"
},
  "geometry": {"coordinates":[20.23079,50.38967],"type":"Point"}
}