{
  "type": "Feature",
  "properties": {
    "gn:admin1_code":"78.0",
    "gn:admin2_code":"1423.0",
    "gn:admin3_code":"142308.0",
    "gn:asciiname":"Zawady",
    "gn:country_code":"PL",
    "gn:dem":161,
    "gn:feature_class":"P",
    "gn:feature_code":"PPL",
    "gn:name":"Zawady",
    "gn:population":0,
    "gn:timezone":"Europe/Warsaw",
    "iso:country":"PL",
    "name:fra_x_preferred":[
        "Zawady"
    ],
    "name:pol_x_preferred":[
        "Zawady"
    ],
    "name:ukr_x_preferred":[
        "\u0417\u0430\u0432\u0430\u0434\u0438"
    ],
    "wof:name":"Zawady",
    "wof:placetype":"locality"
},
  "geometry": {"coordinates":[20.8281,51.3504],"type":"Point"}
}