{
  "type": "Feature",
  "properties": {
    "gn:admin1_code":"85.0",
    "gn:admin2_code":"2804.0",
    "gn:admin3_code":"280406.0",
    "gn:asciiname":"Plonne",
    "gn:country_code":"PL",
    "gn:dem":43,
    "gn:feature_class":"P",
    "gn:feature_code":"PPL",
    "gn:name":"P\u0142onne",
    "gn:population":0,
    "gn:timezone":"Europe/Warsaw",
    "iso:country":"PL",
    "name:pol_x_preferred":[
        "P\u0142onne"
    ],
    "name:ukr_x_preferred":[
        "\u041f\u043b\u043e\u043d\u043d\u0435"
    ],
    "name:und_x_variant":[
        "Lohberg"
    ],
    "wof:name":"Plonne",
    "wof:placetype":"locality"
},
  "geometry": {"coordinates":[19.70315,54.19925],"type":"Point"}
}