{
  "type": "Feature",
  "properties": {
    "gn:country":"PL",
    "gn:fcode":"PPL",
    "gn:population":0,
    "iso:country":"PL",
    "name:ast_x_preferred":[
        "Arciech\u00f3w"
    ],
    "name:ces_x_preferred":[
        "Arciech\u00f3w"
    ],
    "name:che_x_preferred":[
        "\u0410\u0440\u0446\u0435\u0445\u0443\u0432"
    ],
    "name:deu_x_preferred":[
        "Arciech\u00f3w"
    ],
    "name:eng_x_preferred":[
        "Arciech\u00f3w"
    ],
    "name:fas_x_preferred":[
        "\u0622\u0631\u0686\u06cc\u0647\u200c\u062e\u0648\u0641"
    ],
    "name:fra_x_preferred":[
        "Arciech\u00f3w"
    ],
    "name:nan_x_preferred":[
        "Arciech\u00f3w"
    ],
    "name:nld_x_preferred":[
        "Arciech\u00f3w"
    ],
    "name:pol_x_preferred":[
        "Arciech\u00f3w"
    ],
    "name:szl_x_preferred":[
        "Ar\u0107ech\u016fw"
    ],
    "name:tat_x_preferred":[
        "\u0410\u0440\u0446\u0435\u0445\u0443\u0432"
    ],
    "name:ukr_x_preferred":[
        "\u0410\u0440\u0446\u0435\u0445\u0443\u0432"
    ],
    "qs_pg:aaroncc":"PL",
    "qs_pg:gn_country":"PL",
    "qs_pg:gn_fcode":"PPL",
    "qs_pg:gn_pop":0,
    "qs_pg:name":"Arciech\u00f3w",
    "qs_pg:name_adm0":"Polska",
    "qs_pg:name_adm1":"Mazowieckie",
    "qs_pg:photos":30,
    "qs_pg:photos_1k":6,
    "qs_pg:photos_9k":1,
    "qs_pg:photos_9r":2,
    "qs_pg:photos_all":30,
    "qs_pg:photos_sr":2,
    "qs_pg:pop_sr":0,
    "qs_pg:qs_pg_placetype":"locality",
    "qs_pg:qs_pg_placetype_gp":"Town",
    "qs_pg:woe_adm0":23424923,
    "woe:adm0_id":23424923,
    "woe:name_adm0":"Polska",
    "woe:name_adm1":"Mazowieckie",
    "woe:placetype":"Town",
    "wof:name":"Arciech\u00f3w",
    "wof:placetype":"locality"
},
  "geometry": {"coordinates":[21.08354,52.48801],"type":"Point"}
}