{
  "type": "Feature",
  "properties": {
    "gn:admin1_code":"79.0",
    "gn:admin2_code":"1602.0",
    "gn:admin3_code":"160202.0",
    "gn:asciiname":"Wodka",
    "gn:country_code":"PL",
    "gn:dem":323,
    "gn:feature_class":"P",
    "gn:feature_code":"PPL",
    "gn:name":"W\u00f3dka",
    "gn:population":0,
    "gn:timezone":"Europe/Warsaw",
    "iso:country":"PL",
    "name:ceb_x_preferred":[
        "W\u00f3dka"
    ],
    "name:fra_x_preferred":[
        "W\u00f3dka"
    ],
    "name:pol_x_preferred":[
        "W\u00f3dka"
    ],
    "name:ukr_x_preferred":[
        "\u0412\u0443\u0434\u043a\u0430"
    ],
    "wof:name":"Wodka",
    "wof:placetype":"locality"
},
  "geometry": {"coordinates":[17.84454,50.06485],"type":"Point"}
}