{
  "type": "Feature",
  "properties": {
    "gn:admin1_code":"86.0",
    "gn:admin2_code":"3009.0",
    "gn:admin3_code":"300903.0",
    "gn:asciiname":"Koserz",
    "gn:country_code":"PL",
    "gn:dem":125,
    "gn:feature_class":"P",
    "gn:feature_code":"PPL",
    "gn:name":"Koserz",
    "gn:population":0,
    "gn:timezone":"Europe/Warsaw",
    "iso:country":"PL",
    "name:pol_x_preferred":[
        "Koserz"
    ],
    "name:ukr_x_preferred":[
        "\u041a\u043e\u0441\u0435\u0436"
    ],
    "wof:name":"Koserz",
    "wof:placetype":"locality"
},
  "geometry": {"coordinates":[19.06591,52.2712],"type":"Point"}
}