{
  "type": "Feature",
  "properties": {
    "gn:admin1_code":"73.0",
    "gn:admin2_code":"401.0",
    "gn:admin3_code":"40104.0",
    "gn:asciiname":"Debicze",
    "gn:country_code":"PL",
    "gn:dem":80,
    "gn:feature_class":"P",
    "gn:feature_code":"PPL",
    "gn:name":"Debicze",
    "gn:population":0,
    "gn:timezone":"Europe/Warsaw",
    "iso:country":"PL",
    "wof:name":"Debicze",
    "wof:placetype":"locality"
},
  "geometry": {"coordinates":[18.61637,52.81326],"type":"Point"}
}