{
  "type": "Feature",
  "properties": {
    "gn:admin1_code":"77.0",
    "gn:admin2_code":"1261.0",
    "gn:admin3_code":"126101.0",
    "gn:asciiname":"Grebalow",
    "gn:country_code":"PL",
    "gn:dem":236,
    "gn:feature_class":"P",
    "gn:feature_code":"PPL",
    "gn:name":"Gr\u0119ba\u0142\u00f3w",
    "gn:population":0,
    "gn:timezone":"Europe/Warsaw",
    "iso:country":"PL",
    "wof:name":"Grebalow",
    "wof:placetype":"locality"
},
  "geometry": {"coordinates":[20.07268,50.10021],"type":"Point"}
}