{
  "type": "Feature",
  "properties": {
    "gn:admin1_code":"77.0",
    "gn:admin2_code":"1210.0",
    "gn:admin3_code":"121004.0",
    "gn:asciiname":"Wawrzka",
    "gn:country_code":"PL",
    "gn:dem":532,
    "gn:feature_class":"P",
    "gn:feature_code":"PPL",
    "gn:name":"Wawrzka",
    "gn:population":0,
    "gn:timezone":"Europe/Warsaw",
    "iso:country":"PL",
    "name:pol_x_preferred":[
        "Wawrzka"
    ],
    "name:ukr_x_preferred":[
        "\u0412\u0430\u0444\u043a\u0430"
    ],
    "wof:name":"Wawrzka",
    "wof:placetype":"locality"
},
  "geometry": {"coordinates":[21.00174,49.57432],"type":"Point"}
}