{
  "type": "Feature",
  "properties": {
    "gn:admin1_code":"78.0",
    "gn:admin2_code":"1411.0",
    "gn:admin3_code":"141108.0",
    "gn:asciiname":"Brzuze",
    "gn:country_code":"PL",
    "gn:dem":94,
    "gn:feature_class":"P",
    "gn:feature_code":"PPL",
    "gn:name":"Brzuze",
    "gn:population":0,
    "gn:timezone":"Europe/Warsaw",
    "iso:country":"PL",
    "wof:name":"Brzuze",
    "wof:placetype":"locality"
},
  "geometry": {"coordinates":[21.46333,52.81959000000001],"type":"Point"}
}