{
  "type": "Feature",
  "properties": {
    "gn:admin1_code":"78.0",
    "gn:admin2_code":"1416.0",
    "gn:admin3_code":"141607.0",
    "gn:asciiname":"Grabownica Stara",
    "gn:country_code":"PL",
    "gn:dem":110,
    "gn:feature_class":"P",
    "gn:feature_code":"PPL",
    "gn:name":"Grabownica Stara",
    "gn:population":0,
    "gn:timezone":"Europe/Warsaw",
    "iso:country":"PL",
    "name:und_x_variant":[
        "Stara Grabownica",
        "Grabownica Stara"
    ],
    "wof:name":"Grabownica Stara",
    "wof:placetype":"locality"
},
  "geometry": {"coordinates":[21.88189,52.76901],"type":"Point"}
}