{
  "type": "Feature",
  "properties": {
    "gn:admin1_code":"78.0",
    "gn:admin2_code":"1416.0",
    "gn:admin3_code":"141607.0",
    "gn:asciiname":"Grabownica Stara",
    "gn:country_code":"PL",
    "gn:dem":110,
    "gn:feature_class":"P",
    "gn:feature_code":"PPL",
    "gn:name":"Grabownica Stara",
    "gn:population":0,
    "gn:timezone":"Europe/Warsaw",
    "iso:country":"PL",
    "name:fra_x_preferred":[
        "Stara Grabownica"
    ],
    "name:pol_x_preferred":[
        "Stara Grabownica"
    ],
    "name:ukr_x_preferred":[
        "\u0421\u0442\u0430\u0440\u0430 \u0490\u0440\u0430\u0431\u043e\u0432\u043d\u0438\u0446\u044f"
    ],
    "name:und_x_variant":[
        "Grabownica Stara"
    ],
    "wof:name":"Grabownica Stara",
    "wof:placetype":"locality"
},
  "geometry": {"coordinates":[21.88189,52.76901],"type":"Point"}
}