{
  "type": "Feature",
  "properties": {
    "gn:admin1_code":"78.0",
    "gn:admin2_code":"1406.0",
    "gn:admin3_code":"140602.0",
    "gn:asciiname":"Gludna",
    "gn:country_code":"PL",
    "gn:dem":171,
    "gn:feature_class":"P",
    "gn:feature_code":"PPL",
    "gn:name":"G\u0142udna",
    "gn:population":0,
    "gn:timezone":"Europe/Warsaw",
    "iso:country":"PL",
    "name:fra_x_preferred":[
        "G\u0142udna"
    ],
    "name:pol_x_preferred":[
        "G\u0142udna"
    ],
    "name:ukr_x_preferred":[
        "\u0490\u043b\u0443\u0434\u043d\u0430"
    ],
    "wof:name":"Gludna",
    "wof:placetype":"locality"
},
  "geometry": {"coordinates":[20.72433,51.81075],"type":"Point"}
}