{
  "type": "Feature",
  "properties": {
    "gn:admin1_code":"74.0",
    "gn:admin2_code":"1004.0",
    "gn:admin3_code":"100402.0",
    "gn:asciiname":"Ogrodzona",
    "gn:country_code":"PL",
    "gn:dem":127,
    "gn:feature_class":"P",
    "gn:feature_code":"PPL",
    "gn:name":"Ogrodzona",
    "gn:population":0,
    "gn:timezone":"Europe/Warsaw",
    "iso:country":"PL",
    "name:deu_x_preferred":[
        "Ogrodzona"
    ],
    "name:fra_x_preferred":[
        "Ogrodzona"
    ],
    "name:nld_x_preferred":[
        "Ogrodzona"
    ],
    "name:pol_x_preferred":[
        "Ogrodzona"
    ],
    "name:ukr_x_preferred":[
        "\u041e\u0491\u0440\u043e\u0434\u0437\u043e\u043d\u0430"
    ],
    "wof:name":"Ogrodzona",
    "wof:placetype":"locality"
},
  "geometry": {"coordinates":[19.18432,52.1977],"type":"Point"}
}