{
  "type": "Feature",
  "properties": {
    "gn:admin1_code":"75.0",
    "gn:admin2_code":"612.0",
    "gn:admin3_code":"61202.0",
    "gn:asciiname":"Kolczyn",
    "gn:country_code":"PL",
    "gn:dem":157,
    "gn:feature_class":"P",
    "gn:feature_code":"PPL",
    "gn:name":"Kolczyn",
    "gn:population":0,
    "gn:timezone":"Europe/Warsaw",
    "iso:country":"PL",
    "wof:name":"Kolczyn",
    "wof:placetype":"locality"
},
  "geometry": {"coordinates":[21.83842000000001,51.0565],"type":"Point"}
}