{
  "type": "Feature",
  "properties": {
    "gn:admin1_code":"82.0",
    "gn:admin2_code":"2215.0",
    "gn:admin3_code":"221504.0",
    "gn:asciiname":"Kierzkowo",
    "gn:country_code":"PL",
    "gn:dem":36,
    "gn:feature_class":"P",
    "gn:feature_code":"PPL",
    "gn:name":"Kierzkowo",
    "gn:population":0,
    "gn:timezone":"Europe/Warsaw",
    "iso:country":"PL",
    "wof:name":"Kierzkowo",
    "wof:placetype":"locality"
},
  "geometry": {"coordinates":[17.87167,54.76723000000001],"type":"Point"}
}