{
  "type": "Feature",
  "properties": {
    "gn:admin1_code":"82.0",
    "gn:admin2_code":"2261.0",
    "gn:admin3_code":"226101.0",
    "gn:asciiname":"Sidlice",
    "gn:cc2":"PL",
    "gn:country_code":"PL",
    "gn:dem":18,
    "gn:feature_class":"P",
    "gn:feature_code":"PPL",
    "gn:name":"Sidlice",
    "gn:population":0,
    "gn:timezone":"Europe/Warsaw",
    "iso:country":"PL",
    "name:und_x_variant":[
        "Schidlitz",
        "Sidlice"
    ],
    "wof:name":"Sidlice",
    "wof:placetype":"neighbourhood"
},
  "geometry": {"coordinates":[18.63333,54.35],"type":"Point"}
}