{
  "type": "Feature",
  "properties": {
    "gn:admin1_code":"75.0",
    "gn:admin2_code":"603.0",
    "gn:admin3_code":"60303.0",
    "gn:asciiname":"Nowiny",
    "gn:country_code":"PL",
    "gn:dem":178,
    "gn:feature_class":"P",
    "gn:feature_code":"PPL",
    "gn:name":"Nowiny",
    "gn:population":0,
    "gn:timezone":"Europe/Warsaw",
    "iso:country":"PL",
    "wof:name":"Nowiny",
    "wof:placetype":"locality"
},
  "geometry": {"coordinates":[23.50421,51.17055],"type":"Point"}
}