{
  "type": "Feature",
  "properties": {
    "gn:admin1_code":"82.0",
    "gn:admin2_code":"2209.0",
    "gn:admin3_code":"220907.0",
    "gn:asciiname":"Myszewo",
    "gn:country_code":"PL",
    "gn:dem":0,
    "gn:feature_class":"P",
    "gn:feature_code":"PPL",
    "gn:name":"Myszewo",
    "gn:population":0,
    "gn:timezone":"Europe/Warsaw",
    "iso:country":"PL",
    "name:ceb_x_preferred":[
        "Myszewo"
    ],
    "name:nld_x_preferred":[
        "Myszewo"
    ],
    "name:pol_x_preferred":[
        "Myszewo"
    ],
    "name:ukr_x_preferred":[
        "\u041c\u0438\u0448\u0435\u0432\u043e"
    ],
    "name:und_x_variant":[
        "Gross Mausdorf"
    ],
    "wof:name":"Myszewo",
    "wof:placetype":"locality"
},
  "geometry": {"coordinates":[19.16153,54.13066],"type":"Point"}
}