{
  "type": "Feature",
  "properties": {
    "gn:admin1_code":"78.0",
    "gn:admin2_code":"1415.0",
    "gn:admin3_code":"141506.0",
    "gn:asciiname":"Olszewka",
    "gn:country_code":"PL",
    "gn:dem":103,
    "gn:feature_class":"P",
    "gn:feature_code":"PPL",
    "gn:name":"Olszewka",
    "gn:population":0,
    "gn:timezone":"Europe/Warsaw",
    "iso:country":"PL",
    "name:fra_x_preferred":[
        "Olszewka"
    ],
    "name:pol_x_preferred":[
        "Olszewka"
    ],
    "name:ukr_x_preferred":[
        "\u041e\u043b\u044c\u0448\u0435\u0432\u043a\u0430"
    ],
    "wof:name":"Olszewka",
    "wof:placetype":"locality"
},
  "geometry": {"coordinates":[21.46828,53.12791],"type":"Point"}
}