{
  "type": "Feature",
  "properties": {
    "gn:admin1_code":"75.0",
    "gn:admin2_code":"614.0",
    "gn:admin3_code":"61404.0",
    "gn:asciiname":"Dabrowka",
    "gn:country_code":"PL",
    "gn:dem":188,
    "gn:feature_class":"P",
    "gn:feature_code":"PPL",
    "gn:name":"D\u0105br\u00f3wka",
    "gn:population":0,
    "gn:timezone":"Europe/Warsaw",
    "iso:country":"PL",
    "name:ceb_x_preferred":[
        "D\u0105br\u00f3wka"
    ],
    "name:deu_x_preferred":[
        "D\u0105br\u00f3wka"
    ],
    "name:fra_x_preferred":[
        "D\u0105br\u00f3wka"
    ],
    "name:lit_x_preferred":[
        "Dambruvka"
    ],
    "name:nld_x_preferred":[
        "D\u0105br\u00f3wka"
    ],
    "name:pol_x_preferred":[
        "D\u0105br\u00f3wka"
    ],
    "name:rus_x_preferred":[
        "\u0414\u043e\u043c\u0431\u0440\u0443\u0432\u043a\u0430"
    ],
    "name:ukr_x_preferred":[
        "\u0414\u043e\u043c\u0431\u0440\u0443\u0432\u043a\u0430"
    ],
    "wof:name":"Dabrowka",
    "wof:placetype":"neighbourhood"
},
  "geometry": {"coordinates":[21.93782,51.28458],"type":"Point"}
}