{
  "type": "Feature",
  "properties": {
    "gn:admin1_code":"80.0",
    "gn:admin2_code":"1804.0",
    "gn:admin3_code":"180410.0",
    "gn:asciiname":"Bystrowice",
    "gn:country_code":"PL",
    "gn:dem":235,
    "gn:feature_class":"P",
    "gn:feature_code":"PPL",
    "gn:name":"Bystrowice",
    "gn:population":0,
    "gn:timezone":"Europe/Warsaw",
    "iso:country":"PL",
    "name:ceb_x_preferred":[
        "Bystrowice"
    ],
    "name:pol_x_preferred":[
        "Bystrowice"
    ],
    "name:ukr_x_preferred":[
        "\u0411\u0438\u0441\u0442\u0440\u0435\u0432\u0438\u0447\u0456"
    ],
    "wof:name":"Bystrowice",
    "wof:placetype":"locality"
},
  "geometry": {"coordinates":[22.57296,49.93288],"type":"Point"}
}