{
  "type": "Feature",
  "properties": {
    "gn:admin1_code":"78.0",
    "gn:admin2_code":"1404.0",
    "gn:admin3_code":"140403.0",
    "gn:asciiname":"Luszyn",
    "gn:country_code":"PL",
    "gn:dem":101,
    "gn:feature_class":"P",
    "gn:feature_code":"PPL",
    "gn:name":"Luszyn",
    "gn:population":0,
    "gn:timezone":"Europe/Warsaw",
    "iso:country":"PL",
    "wof:name":"Luszyn",
    "wof:placetype":"locality"
},
  "geometry": {"coordinates":[19.76695,52.27283],"type":"Point"}
}