{
  "type": "Feature",
  "properties": {
    "gn:admin1_code":"74.0",
    "gn:admin2_code":"1006.0",
    "gn:admin3_code":"100607.0",
    "gn:asciiname":"Felicjanow Nowy",
    "gn:cc2":"PL",
    "gn:country_code":"PL",
    "gn:dem":207,
    "gn:feature_class":"P",
    "gn:feature_code":"PPL",
    "gn:name":"Felicjan\u00f3w Nowy",
    "gn:population":0,
    "gn:timezone":"Europe/Warsaw",
    "iso:country":"PL",
    "name:und_x_variant":[
        "Nowy Felicjan\u00f3w",
        "Felicjan\u00f3w Nowy"
    ],
    "wof:name":"Felicjanow Nowy",
    "wof:placetype":"locality"
},
  "geometry": {"coordinates":[19.83333,51.75],"type":"Point"}
}