{
  "type": "Feature",
  "properties": {
    "gn:admin1_code":"80.0",
    "gn:admin2_code":"1805.0",
    "gn:admin3_code":"180504.0",
    "gn:asciiname":"Zolkow",
    "gn:country_code":"PL",
    "gn:dem":245,
    "gn:feature_class":"P",
    "gn:feature_code":"PPL",
    "gn:name":"\u017b\u00f3\u0142k\u00f3w",
    "gn:population":0,
    "gn:timezone":"Europe/Warsaw",
    "iso:country":"PL",
    "name:ceb_x_preferred":[
        "\u017b\u00f3\u0142k\u00f3w"
    ],
    "name:pol_x_preferred":[
        "\u017b\u00f3\u0142k\u00f3w"
    ],
    "name:ukr_x_preferred":[
        "\u0416\u0443\u043b\u043a\u0443\u0432"
    ],
    "wof:name":"Zolkow",
    "wof:placetype":"locality"
},
  "geometry": {"coordinates":[21.47106,49.7126],"type":"Point"}
}