{
  "type": "Feature",
  "properties": {
    "gn:admin1_code":"72.0",
    "gn:admin2_code":"223.0",
    "gn:admin3_code":"22305.0",
    "gn:asciiname":"Cieszyce",
    "gn:country_code":"PL",
    "gn:dem":147,
    "gn:feature_class":"P",
    "gn:feature_code":"PPL",
    "gn:name":"Cieszyce",
    "gn:population":0,
    "gn:timezone":"Europe/Warsaw",
    "iso:country":"PL",
    "name:ceb_x_preferred":[
        "Cieszyce"
    ],
    "name:pol_x_preferred":[
        "Cieszyce"
    ],
    "name:ukr_x_preferred":[
        "\u0426\u0435\u0448\u0438\u0446\u0435"
    ],
    "wof:name":"Cieszyce",
    "wof:placetype":"locality"
},
  "geometry": {"coordinates":[16.8944,50.94123],"type":"Point"}
}