{
  "type": "Feature",
  "properties": {
    "gn:admin1_code":"75.0",
    "gn:asciiname":"Nowe Litewniki",
    "gn:country_code":"PL",
    "gn:dem":183,
    "gn:feature_class":"P",
    "gn:feature_code":"PPL",
    "gn:name":"Nowe Litewniki",
    "gn:population":0,
    "gn:timezone":"Europe/Warsaw",
    "iso:country":"PL",
    "name:ceb_x_preferred":[
        "Nowe Litewniki"
    ],
    "name:fra_x_preferred":[
        "Nowe Litewniki"
    ],
    "name:lit_x_preferred":[
        "Nove Litevnikai"
    ],
    "name:pol_x_preferred":[
        "Nowe Litewniki"
    ],
    "name:ukr_x_preferred":[
        "\u041d\u043e\u0432\u0435 \u041b\u0456\u0442\u0435\u0432\u043d\u0438\u043a\u0438"
    ],
    "wof:name":"Nowe Litewniki",
    "wof:placetype":"locality"
},
  "geometry": {"coordinates":[22.95319,52.2577],"type":"Point"}
}