{
  "type": "Feature",
  "properties": {
    "iso:country":"PL",
    "name:bak_x_preferred":[
        "\u0412\u0430\u0432\u0435\u043b\u044c"
    ],
    "name:bel_x_preferred":[
        "\u0412\u0430\u0432\u0435\u043b\u044c"
    ],
    "name:bel_x_variant":[
        "\u0412\u0430\u0432\u044d\u043b\u044c"
    ],
    "name:bul_x_preferred":[
        "\u0412\u0430\u0432\u0435\u043b"
    ],
    "name:cat_x_preferred":[
        "Wawel"
    ],
    "name:ces_x_preferred":[
        "Wawel"
    ],
    "name:dan_x_preferred":[
        "Wawel"
    ],
    "name:deu_x_preferred":[
        "Wawel"
    ],
    "name:ell_x_preferred":[
        "\u0392\u03ac\u03b2\u03b5\u03bb"
    ],
    "name:eng_x_preferred":[
        "Wawel"
    ],
    "name:epo_x_preferred":[
        "Vavelo"
    ],
    "name:eus_x_preferred":[
        "Wawel"
    ],
    "name:fra_x_preferred":[
        "Wawel"
    ],
    "name:hbs_x_preferred":[
        "Vavel"
    ],
    "name:heb_x_preferred":[
        "\u05d5\u05d0\u05d5\u05d5\u05dc"
    ],
    "name:hrv_x_preferred":[
        "Vavel"
    ],
    "name:hun_x_preferred":[
        "Wawel"
    ],
    "name:hye_x_preferred":[
        "\u054e\u0561\u057e\u0565\u056c"
    ],
    "name:ita_x_preferred":[
        "Wawel"
    ],
    "name:jpn_x_preferred":[
        "\u30f4\u30a1\u30fc\u30f4\u30a7\u30eb\u57ce"
    ],
    "name:lit_x_preferred":[
        "Vavelis"
    ],
    "name:nld_x_preferred":[
        "Wawel"
    ],
    "name:nob_x_preferred":[
        "Wawel"
    ],
    "name:nor_x_preferred":[
        "Wawel"
    ],
    "name:pol_x_preferred":[
        "Wawel"
    ],
    "name:ron_x_preferred":[
        "Wawel"
    ],
    "name:rus_x_preferred":[
        "\u0412\u0430\u0432\u0435\u043b\u044c"
    ],
    "name:slk_x_preferred":[
        "Wawel"
    ],
    "name:spa_x_preferred":[
        "Wawel"
    ],
    "name:srp_x_preferred":[
        "\u0412\u0430\u0432\u0435\u043b"
    ],
    "name:swe_x_preferred":[
        "Wawel"
    ],
    "name:tat_x_preferred":[
        "\u0412\u0430\u0432\u0435\u043b\u044c"
    ],
    "name:ukr_x_preferred":[
        "\u0412\u0430\u0432\u0435\u043b\u044c"
    ],
    "name:zho_x_preferred":[
        "\u74e6\u7ef4\u5c14\u5c71"
    ],
    "qs:gn_adm0_cc":"PL",
    "qs:gn_fcode":"PPLX",
    "qs:gn_local":3094802,
    "qs:gn_nam_loc":"Krak\u00f3w, Krak\u00f3w, Ma\u0142opolskie, PL",
    "qs:gn_namadm1":"77",
    "qs:gn_name":"Wawel",
    "qs:local_max":40205,
    "qs:local_sum":79409,
    "qs:localhoods":6,
    "qs:name":"Wawel",
    "qs:name_adm0":"Polska",
    "qs:name_adm1":"Ma\u0142opolskie",
    "qs:name_adm2":"Krak\u00f3w",
    "qs:name_lau":"Krak\u00f3w",
    "qs:name_local":"Krak\u00f3w",
    "qs:photo_max":3868,
    "qs:photo_sum":23723,
    "qs:placetype":"Suburb",
    "qs:quad_count":136,
    "qs:woe_adm0":23424923,
    "qs:woe_adm1":12577940,
    "qs:woe_adm2":12591253,
    "qs:woe_lau":12618071,
    "qs:woe_local":502075,
    "qs:woe_ver":"7.10.0",
    "wd:wordcount":4667,
    "wof:lang":[
        "pol"
    ],
    "wof:name":"Wawel",
    "wof:placetype":"neighbourhood"
},
  "geometry": {"coordinates":[19.935781,50.054193],"type":"Point"}
}