{
  "type": "Feature",
  "properties": {
    "gn:admin1_code":"84.0",
    "gn:admin2_code":"2609.0",
    "gn:admin3_code":"260903.0",
    "gn:asciiname":"Nawodzice",
    "gn:country_code":"PL",
    "gn:dem":185,
    "gn:feature_class":"P",
    "gn:feature_code":"PPL",
    "gn:name":"Nawodzice",
    "gn:population":0,
    "gn:timezone":"Europe/Warsaw",
    "iso:country":"PL",
    "name:ceb_x_preferred":[
        "Nawodzice"
    ],
    "name:pol_x_preferred":[
        "Nawodzice"
    ],
    "name:ukr_x_preferred":[
        "\u041d\u0430\u0432\u043e\u0434\u0437\u0456\u0446\u0435"
    ],
    "wof:name":"Nawodzice",
    "wof:placetype":"locality"
},
  "geometry": {"coordinates":[21.43049,50.6219],"type":"Point"}
}