{
  "type": "Feature",
  "properties": {
    "gn:admin1_code":"75.0",
    "gn:admin2_code":"611.0",
    "gn:admin3_code":"61104.0",
    "gn:asciiname":"Laski",
    "gn:country_code":"PL",
    "gn:dem":172,
    "gn:feature_class":"P",
    "gn:feature_code":"PPL",
    "gn:name":"Laski",
    "gn:population":0,
    "gn:timezone":"Europe/Warsaw",
    "iso:country":"PL",
    "name:ceb_x_preferred":[
        "Laski"
    ],
    "name:deu_x_preferred":[
        "Laski"
    ],
    "name:fra_x_preferred":[
        "Laski"
    ],
    "name:heb_x_preferred":[
        "\u05dc\u05e1\u05e7\u05d9"
    ],
    "name:ita_x_preferred":[
        "Laski"
    ],
    "name:pol_x_preferred":[
        "Laski"
    ],
    "name:rus_x_preferred":[
        "\u041b\u044f\u0441\u043a\u0438"
    ],
    "name:ukr_x_preferred":[
        "\u041b\u044f\u0441\u043a\u0456"
    ],
    "wof:name":"Laski",
    "wof:placetype":"locality"
},
  "geometry": {"coordinates":[22.08416,51.82709000000001],"type":"Point"}
}