{
  "type": "Feature",
  "properties": {
    "gn:admin1_code":"78.0",
    "gn:admin2_code":"1427.0",
    "gn:admin3_code":"142705.0",
    "gn:asciiname":"Zawisze",
    "gn:country_code":"PL",
    "gn:dem":115,
    "gn:feature_class":"P",
    "gn:feature_code":"PPL",
    "gn:name":"Zawisze",
    "gn:population":0,
    "gn:timezone":"Europe/Warsaw",
    "iso:country":"PL",
    "name:fra_x_preferred":[
        "Zawisze"
    ],
    "name:pol_x_preferred":[
        "Zawisze"
    ],
    "wof:name":"Zawisze",
    "wof:placetype":"locality"
},
  "geometry": {"coordinates":[19.71667,52.81667],"type":"Point"}
}