{
  "type": "Feature",
  "properties": {
    "gn:admin1_code":"85.0",
    "gn:admin2_code":"2804.0",
    "gn:admin3_code":"280406.0",
    "gn:asciiname":"Kurowo Braniewskie",
    "gn:country_code":"PL",
    "gn:dem":45,
    "gn:feature_class":"P",
    "gn:feature_code":"PPL",
    "gn:name":"Kurowo Braniewskie",
    "gn:population":0,
    "gn:timezone":"Europe/Warsaw",
    "iso:country":"PL",
    "name:und_x_variant":[
        "Kurau",
        "Kurowo Braniewskie"
    ],
    "wof:name":"Kurowo Braniewskie",
    "wof:placetype":"locality"
},
  "geometry": {"coordinates":[19.75002000000001,54.22823],"type":"Point"}
}