{
  "type": "Feature",
  "properties": {
    "gn:admin1_code":"85.0",
    "gn:admin2_code":"2804.0",
    "gn:admin3_code":"280406.0",
    "gn:asciiname":"Kurowo Braniewskie",
    "gn:country_code":"PL",
    "gn:dem":45,
    "gn:feature_class":"P",
    "gn:feature_code":"PPL",
    "gn:name":"Kurowo Braniewskie",
    "gn:population":0,
    "gn:timezone":"Europe/Warsaw",
    "iso:country":"PL",
    "name:pol_x_preferred":[
        "Kurowo Braniewskie"
    ],
    "name:ukr_x_preferred":[
        "\u041a\u0443\u0440\u043e\u0432\u043e-\u0411\u0440\u0430\u043d\u0435\u0432\u0441\u044c\u043a\u0435"
    ],
    "name:und_x_variant":[
        "Kurau"
    ],
    "wof:name":"Kurowo Braniewskie",
    "wof:placetype":"locality"
},
  "geometry": {"coordinates":[19.75002000000001,54.22823],"type":"Point"}
}