{
  "type": "Feature",
  "properties": {
    "gn:admin1_code":"73.0",
    "gn:admin2_code":"402.0",
    "gn:admin3_code":"40203.0",
    "gn:asciiname":"Szymkowo",
    "gn:country_code":"PL",
    "gn:dem":139,
    "gn:feature_class":"P",
    "gn:feature_code":"PPL",
    "gn:name":"Szymkowo",
    "gn:population":0,
    "gn:timezone":"Europe/Warsaw",
    "iso:country":"PL",
    "name:pol_x_preferred":[
        "Szymkowo"
    ],
    "name:ukr_x_preferred":[
        "\u0428\u0438\u043c\u043a\u043e\u0432\u043e"
    ],
    "wof:name":"Szymkowo",
    "wof:placetype":"locality"
},
  "geometry": {"coordinates":[19.47389,53.19886],"type":"Point"}
}