{
  "type": "Feature",
  "properties": {
    "gn:admin1_code":"72.0",
    "gn:admin2_code":"218.0",
    "gn:admin3_code":"21803.0",
    "gn:asciiname":"Lenartowice",
    "gn:country_code":"PL",
    "gn:dem":105,
    "gn:feature_class":"P",
    "gn:feature_code":"PPL",
    "gn:name":"Lenartowice",
    "gn:population":0,
    "gn:timezone":"Europe/Warsaw",
    "iso:country":"PL",
    "name:pol_x_preferred":[
        "Lenartowice"
    ],
    "name:ukr_x_preferred":[
        "\u041b\u0435\u043d\u0430\u0440\u0442\u043e\u0432\u0456\u0446\u0435"
    ],
    "wof:name":"Lenartowice",
    "wof:placetype":"locality"
},
  "geometry": {"coordinates":[16.79947,51.24451],"type":"Point"}
}