{
  "type": "Feature",
  "properties": {
    "gn:admin1_code":"76.0",
    "gn:admin2_code":"806.0",
    "gn:admin3_code":"80601.0",
    "gn:asciiname":"Slonow",
    "gn:country_code":"PL",
    "gn:dem":64,
    "gn:feature_class":"P",
    "gn:feature_code":"PPL",
    "gn:name":"S\u0142on\u00f3w",
    "gn:population":0,
    "gn:timezone":"Europe/Warsaw",
    "iso:country":"PL",
    "name:und_x_variant":[
        "Schlanow",
        "S\u0142on\u00f3w"
    ],
    "wof:name":"Slonow",
    "wof:placetype":"locality"
},
  "geometry": {"coordinates":[15.77862,52.93428],"type":"Point"}
}