{
  "type": "Feature",
  "properties": {
    "gn:admin1_code":"82.0",
    "gn:admin2_code":"2208.0",
    "gn:admin3_code":"220803.0",
    "gn:asciiname":"Lebunia",
    "gn:country_code":"PL",
    "gn:dem":132,
    "gn:feature_class":"P",
    "gn:feature_code":"PPL",
    "gn:name":"\u0141ebunia",
    "gn:population":0,
    "gn:timezone":"Europe/Warsaw",
    "iso:country":"PL",
    "name:und_x_variant":[
        "Labuhn",
        "\u0141abunia",
        "\u0141ebunia"
    ],
    "wof:name":"Lebunia",
    "wof:placetype":"locality"
},
  "geometry": {"coordinates":[17.81042,54.45194],"type":"Point"}
}