{
  "type": "Feature",
  "properties": {
    "gn:admin1_code":"82.0",
    "gn:admin2_code":"2208.0",
    "gn:admin3_code":"220803.0",
    "gn:asciiname":"Lebunia",
    "gn:country_code":"PL",
    "gn:dem":132,
    "gn:feature_class":"P",
    "gn:feature_code":"PPL",
    "gn:name":"\u0141ebunia",
    "gn:population":0,
    "gn:timezone":"Europe/Warsaw",
    "iso:country":"PL",
    "name:azb_x_preferred":[
        "\u0648\u0628\u0648\u0646\u0642\u0627"
    ],
    "name:ceb_x_preferred":[
        "\u0141ebunia"
    ],
    "name:csb_x_preferred":[
        "L\u00ebb\u00f9\u0144"
    ],
    "name:deu_x_preferred":[
        "\u0141ebunia"
    ],
    "name:fas_x_preferred":[
        "\u0648\u0628\u0648\u0646\u06af\u0627"
    ],
    "name:nld_x_preferred":[
        "\u0141ebunia"
    ],
    "name:pol_x_preferred":[
        "\u0141ebunia"
    ],
    "name:ukr_x_preferred":[
        "\u041b\u0435\u0431\u0443\u043d\u044f"
    ],
    "name:und_x_variant":[
        "Labuhn",
        "\u0141abunia"
    ],
    "wof:name":"Lebunia",
    "wof:placetype":"locality"
},
  "geometry": {"coordinates":[17.81042,54.45194],"type":"Point"}
}