{
  "type": "Feature",
  "properties": {
    "gn:admin1_code":"82.0",
    "gn:admin2_code":"2201.0",
    "gn:admin3_code":"220106.0",
    "gn:asciiname":"Swierzenko",
    "gn:country_code":"PL",
    "gn:dem":141,
    "gn:feature_class":"P",
    "gn:feature_code":"PPL",
    "gn:name":"\u015awierzenko",
    "gn:population":0,
    "gn:timezone":"Europe/Warsaw",
    "iso:country":"PL",
    "name:und_x_variant":[
        "\u015awierzenko"
    ],
    "wof:name":"Swierzenko",
    "wof:placetype":"locality"
},
  "geometry": {"coordinates":[16.85462,54.08397],"type":"Point"}
}