{
  "type": "Feature",
  "properties": {
    "gn:admin1_code":"82.0",
    "gn:admin2_code":"2201.0",
    "gn:admin3_code":"220106.0",
    "gn:asciiname":"Swierzenko",
    "gn:country_code":"PL",
    "gn:dem":141,
    "gn:feature_class":"P",
    "gn:feature_code":"PPL",
    "gn:name":"\u015awierzenko",
    "gn:population":0,
    "gn:timezone":"Europe/Warsaw",
    "iso:country":"PL",
    "name:azb_x_preferred":[
        "\u0634\u0648\u06cc\u0698\u0646\u06a9\u0648"
    ],
    "name:ceb_x_preferred":[
        "\u015awierzenko"
    ],
    "name:csb_x_preferred":[
        "Swierzenk\u00f2"
    ],
    "name:deu_x_preferred":[
        "\u015awierzenko"
    ],
    "name:fas_x_preferred":[
        "\u0634\u0648\u06cc\u0698\u0646\u06a9\u0648"
    ],
    "name:pol_x_preferred":[
        "\u015awierzenko"
    ],
    "name:ukr_x_preferred":[
        "\u0421\u044c\u0432\u0435\u0436\u0435\u043d\u043a\u043e"
    ],
    "wof:name":"Swierzenko",
    "wof:placetype":"locality"
},
  "geometry": {"coordinates":[16.85462,54.08397],"type":"Point"}
}