{
  "type": "Feature",
  "properties": {
    "gn:admin1_code":"86.0",
    "gn:admin2_code":"3009.0",
    "gn:admin3_code":"300910.0",
    "gn:asciiname":"Borecznia Mala",
    "gn:country_code":"PL",
    "gn:dem":126,
    "gn:feature_class":"P",
    "gn:feature_code":"PPL",
    "gn:name":"Borecznia Ma\u0142a",
    "gn:population":0,
    "gn:timezone":"Europe/Warsaw",
    "iso:country":"PL",
    "wof:name":"Borecznia Mala",
    "wof:placetype":"locality"
},
  "geometry": {"coordinates":[18.61667000000001,52.28333],"type":"Point"}
}