{
  "type": "Feature",
  "properties": {
    "gn:admin1_code":"87.0",
    "gn:admin2_code":"3215.0",
    "gn:admin3_code":"321502.0",
    "gn:asciiname":"Polne",
    "gn:country_code":"PL",
    "gn:dem":150,
    "gn:feature_class":"P",
    "gn:feature_code":"PPL",
    "gn:name":"Polne",
    "gn:population":0,
    "gn:timezone":"Europe/Warsaw",
    "iso:country":"PL",
    "name:pol_x_preferred":[
        "Polne"
    ],
    "name:ukr_x_preferred":[
        "\u041f\u043e\u043b\u044c\u043d\u0435"
    ],
    "name:vie_x_preferred":[
        "Polne"
    ],
    "wof:name":"Polne",
    "wof:placetype":"locality"
},
  "geometry": {"coordinates":[16.31224,53.65212],"type":"Point"}
}