{
  "type": "Feature",
  "properties": {
    "gn:admin1_code":"81.0",
    "gn:admin2_code":"2010.0",
    "gn:admin3_code":"201007.0",
    "gn:asciiname":"Augustynka",
    "gn:country_code":"PL",
    "gn:dem":183,
    "gn:feature_class":"P",
    "gn:feature_code":"PPL",
    "gn:name":"Augustynka",
    "gn:population":0,
    "gn:timezone":"Europe/Warsaw",
    "iso:country":"PL",
    "wof:name":"Augustynka",
    "wof:placetype":"locality"
},
  "geometry": {"coordinates":[23.13935,52.44886],"type":"Point"}
}