{
  "type": "Feature",
  "properties": {
    "gn:admin1_code":"81.0",
    "gn:admin2_code":"2010.0",
    "gn:admin3_code":"201007.0",
    "gn:asciiname":"Augustynka",
    "gn:country_code":"PL",
    "gn:dem":183,
    "gn:feature_class":"P",
    "gn:feature_code":"PPL",
    "gn:name":"Augustynka",
    "gn:population":0,
    "gn:timezone":"Europe/Warsaw",
    "iso:country":"PL",
    "name:azb_x_preferred":[
        "\u0627\u0648\u0642\u0648\u0633\u062a\u0646\u06a9\u0627"
    ],
    "name:fas_x_preferred":[
        "\u0627\u0648\u06af\u0648\u0633\u062a\u0646\u06a9\u0627"
    ],
    "name:fra_x_preferred":[
        "Augustynka"
    ],
    "name:lit_x_preferred":[
        "Augustinka"
    ],
    "name:pol_x_preferred":[
        "Augustynka"
    ],
    "name:ukr_x_preferred":[
        "\u0410\u0443\u0491\u0443\u0441\u0442\u0438\u043d\u043a\u0430"
    ],
    "wof:name":"Augustynka",
    "wof:placetype":"locality"
},
  "geometry": {"coordinates":[23.13935,52.44886],"type":"Point"}
}