{
  "type": "Feature",
  "properties": {
    "gn:admin1_code":"80.0",
    "gn:admin2_code":"1809.0",
    "gn:admin3_code":"180903.0",
    "gn:asciiname":"Brusno",
    "gn:cc2":"PL",
    "gn:country_code":"PL",
    "gn:dem":296,
    "gn:feature_class":"P",
    "gn:feature_code":"PPL",
    "gn:name":"Bru\u015bno",
    "gn:population":0,
    "gn:timezone":"Europe/Warsaw",
    "iso:country":"PL",
    "name:cat_x_preferred":[
        "Brusno"
    ],
    "name:ces_x_preferred":[
        "Brusno"
    ],
    "name:deu_x_preferred":[
        "Brusno"
    ],
    "name:epo_x_preferred":[
        "Brusno"
    ],
    "name:eus_x_preferred":[
        "Brusno"
    ],
    "name:fra_x_preferred":[
        "Brusno"
    ],
    "name:hun_x_preferred":[
        "Boroszn\u00f3"
    ],
    "name:ita_x_preferred":[
        "Brusno"
    ],
    "name:lim_x_preferred":[
        "Brusno"
    ],
    "name:msa_x_preferred":[
        "Brusno"
    ],
    "name:nld_x_preferred":[
        "Brusno"
    ],
    "name:pol_x_preferred":[
        "Brusno"
    ],
    "name:por_x_preferred":[
        "Brusno"
    ],
    "name:ron_x_preferred":[
        "Brusno"
    ],
    "name:rus_x_preferred":[
        "\u0411\u0440\u0443\u0441\u043d\u043e"
    ],
    "name:slk_x_preferred":[
        "Brusno"
    ],
    "name:spa_x_preferred":[
        "Brusno"
    ],
    "name:srp_x_preferred":[
        "\u0411\u0440\u0443\u0441\u043d\u043e"
    ],
    "name:ukr_x_preferred":[
        "\u0411\u0440\u0443\u0441\u043d\u043e"
    ],
    "name:und_x_variant":[
        "Stare Brusno",
        "Bru\u015bno"
    ],
    "name:war_x_preferred":[
        "Brusno"
    ],
    "wof:name":"Brusno",
    "wof:placetype":"locality"
},
  "geometry": {"coordinates":[23.36667000000001,50.23333],"type":"Point"}
}