{
  "type": "Feature",
  "properties": {
    "gn:admin1_code":"80.0",
    "gn:admin2_code":"1809.0",
    "gn:admin3_code":"180903.0",
    "gn:asciiname":"Brusno",
    "gn:cc2":"PL",
    "gn:country_code":"PL",
    "gn:dem":296,
    "gn:feature_class":"P",
    "gn:feature_code":"PPL",
    "gn:name":"Bru\u015bno",
    "gn:population":0,
    "gn:timezone":"Europe/Warsaw",
    "iso:country":"PL",
    "name:und_x_variant":[
        "Stare Brusno",
        "Bru\u015bno"
    ],
    "wof:name":"Brusno",
    "wof:placetype":"locality"
},
  "geometry": {"coordinates":[23.36667000000001,50.23333],"type":"Point"}
}