{
  "type": "Feature",
  "properties": {
    "gn:admin1_code":"78.0",
    "gn:admin2_code":"1413.0",
    "gn:admin3_code":"141310.0",
    "gn:asciiname":"Kowalewo",
    "gn:country_code":"PL",
    "gn:dem":120,
    "gn:feature_class":"P",
    "gn:feature_code":"PPL",
    "gn:name":"Kowalewo",
    "gn:population":0,
    "gn:timezone":"Europe/Warsaw",
    "iso:country":"PL",
    "name:fra_x_preferred":[
        "Kowalewo"
    ],
    "name:pol_x_preferred":[
        "Kowalewo"
    ],
    "name:ukr_x_preferred":[
        "\u041a\u043e\u0432\u0430\u043b\u0435\u0432\u043e"
    ],
    "wof:name":"Kowalewo",
    "wof:placetype":"locality"
},
  "geometry": {"coordinates":[20.27655,53.01174],"type":"Point"}
}