{
  "type": "Feature",
  "properties": {
    "gn:admin1_code":"80.0",
    "gn:admin2_code":"1805.0",
    "gn:admin3_code":"180511.0",
    "gn:asciiname":"Roztoki",
    "gn:country_code":"PL",
    "gn:dem":236,
    "gn:feature_class":"P",
    "gn:feature_code":"PPL",
    "gn:name":"Roztoki",
    "gn:population":0,
    "gn:timezone":"Europe/Warsaw",
    "iso:country":"PL",
    "name:pol_x_preferred":[
        "Roztoki"
    ],
    "name:ukr_x_preferred":[
        "\u0420\u043e\u0437\u0442\u043e\u043a\u0456"
    ],
    "wof:name":"Roztoki",
    "wof:placetype":"locality"
},
  "geometry": {"coordinates":[21.55106,49.746],"type":"Point"}
}