{
  "type": "Feature",
  "properties": {
    "gn:admin1_code":"75.0",
    "gn:admin2_code":"609.0",
    "gn:admin3_code":"60907.0",
    "gn:asciiname":"Plonszowice",
    "gn:country_code":"PL",
    "gn:dem":216,
    "gn:feature_class":"P",
    "gn:feature_code":"PPL",
    "gn:name":"P\u0142onszowice",
    "gn:population":0,
    "gn:timezone":"Europe/Warsaw",
    "iso:country":"PL",
    "name:und_x_variant":[
        "Plouszowice",
        "P\u0142onszowice"
    ],
    "wof:name":"Plonszowice",
    "wof:placetype":"locality"
},
  "geometry": {"coordinates":[22.41714,51.26924],"type":"Point"}
}