{
  "type": "Feature",
  "properties": {
    "gn:admin1_code":"86.0",
    "gn:admin2_code":"3009.0",
    "gn:admin3_code":"300902.0",
    "gn:asciiname":"Lichenek",
    "gn:country_code":"PL",
    "gn:dem":142,
    "gn:feature_class":"P",
    "gn:feature_code":"PPL",
    "gn:name":"Lichenek",
    "gn:population":0,
    "gn:timezone":"Europe/Warsaw",
    "iso:country":"PL",
    "name:pol_x_preferred":[
        "Lichenek"
    ],
    "name:ukr_x_preferred":[
        "\u041b\u0456\u0445\u0435\u043d\u0435\u043a"
    ],
    "name:und_x_variant":[
        "Lichoniek"
    ],
    "wof:name":"Lichenek",
    "wof:placetype":"locality"
},
  "geometry": {"coordinates":[18.63655,52.31800000000001],"type":"Point"}
}