{
  "type": "Feature",
  "properties": {
    "gn:admin1_code":"83.0",
    "gn:admin2_code":"2408.0",
    "gn:admin3_code":"240804.0",
    "gn:asciiname":"Maria",
    "gn:cc2":"PL",
    "gn:country_code":"PL",
    "gn:dem":308,
    "gn:feature_class":"P",
    "gn:feature_code":"PPL",
    "gn:name":"Maria",
    "gn:population":0,
    "gn:timezone":"Europe/Warsaw",
    "iso:country":"PL",
    "name:und_x_variant":[
        "Mariah\u00fctte",
        "Marja",
        "Mariahe",
        "Maria Huta",
        "Maria"
    ],
    "wof:name":"Maria",
    "wof:placetype":"locality"
},
  "geometry": {"coordinates":[18.76667,50.16667],"type":"Point"}
}