{
  "type": "Feature",
  "properties": {
    "gn:admin1_code":"83.0",
    "gn:admin2_code":"2408.0",
    "gn:admin3_code":"240804.0",
    "gn:asciiname":"Maria",
    "gn:cc2":"PL",
    "gn:country_code":"PL",
    "gn:dem":308,
    "gn:feature_class":"P",
    "gn:feature_code":"PPL",
    "gn:name":"Maria",
    "gn:population":0,
    "gn:timezone":"Europe/Warsaw",
    "iso:country":"PL",
    "name:bul_x_preferred":[
        "\u041c\u0430\u0440\u0438\u044f"
    ],
    "name:cat_x_preferred":[
        "Maria"
    ],
    "name:ceb_x_preferred":[
        "Maria"
    ],
    "name:deu_x_preferred":[
        "Maria"
    ],
    "name:est_x_preferred":[
        "Maria"
    ],
    "name:fas_x_preferred":[
        "\u0645\u0627\u0631\u06cc\u0627"
    ],
    "name:fin_x_preferred":[
        "Maria"
    ],
    "name:fra_x_preferred":[
        "Maria"
    ],
    "name:fry_x_preferred":[
        "Marije"
    ],
    "name:heb_x_preferred":[
        "\u05de\u05e8\u05d9\u05d4"
    ],
    "name:ind_x_preferred":[
        "Maria"
    ],
    "name:ita_x_preferred":[
        "Maria"
    ],
    "name:jpn_x_preferred":[
        "\u30de\u30ea\u30a2"
    ],
    "name:kor_x_preferred":[
        "\ub9c8\ub9ac\uc544"
    ],
    "name:lat_x_preferred":[
        "Maria"
    ],
    "name:lin_x_preferred":[
        "Maria"
    ],
    "name:msa_x_preferred":[
        "Maria"
    ],
    "name:nld_x_preferred":[
        "Maria"
    ],
    "name:pol_x_preferred":[
        "Maria"
    ],
    "name:por_x_preferred":[
        "Maria"
    ],
    "name:ron_x_preferred":[
        "Maria"
    ],
    "name:rus_x_preferred":[
        "\u041c\u0430\u0440\u0438\u044f"
    ],
    "name:sco_x_preferred":[
        "Maria"
    ],
    "name:slk_x_preferred":[
        "M\u00e1ria"
    ],
    "name:swe_x_preferred":[
        "Maria"
    ],
    "name:tur_x_preferred":[
        "Maria"
    ],
    "name:ukr_x_preferred":[
        "\u041c\u0430\u0440\u0456\u044f"
    ],
    "name:und_x_variant":[
        "Mariah\u00fctte",
        "Marja",
        "Mariahe",
        "Maria Huta"
    ],
    "name:vls_x_preferred":[
        "Maria"
    ],
    "name:zho_x_preferred":[
        "Maria"
    ],
    "wof:name":"Maria",
    "wof:placetype":"locality"
},
  "geometry": {"coordinates":[18.76667,50.16667],"type":"Point"}
}