{
  "type": "Feature",
  "properties": {
    "gn:admin1_code":"86.0",
    "gn:admin2_code":"3011.0",
    "gn:admin3_code":"301103.0",
    "gn:asciiname":"Sierakowo",
    "gn:country_code":"PL",
    "gn:dem":72,
    "gn:feature_class":"P",
    "gn:feature_code":"PPL",
    "gn:name":"Sierakowo",
    "gn:population":0,
    "gn:timezone":"Europe/Warsaw",
    "iso:country":"PL",
    "name:deu_x_preferred":[
        "Sierakowo"
    ],
    "name:fra_x_preferred":[
        "Sierakowo"
    ],
    "name:pol_x_preferred":[
        "Sierakowo"
    ],
    "name:ukr_x_preferred":[
        "\u0421\u0435\u0440\u0430\u043a\u043e\u0432\u043e"
    ],
    "wof:name":"Sierakowo",
    "wof:placetype":"locality"
},
  "geometry": {"coordinates":[16.61962999999999,52.0941],"type":"Point"}
}