{
  "type": "Feature",
  "properties": {
    "gn:admin1_code":"75.0",
    "gn:admin2_code":"602.0",
    "gn:admin3_code":"60206.0",
    "gn:asciiname":"Bononia",
    "gn:country_code":"PL",
    "gn:dem":250,
    "gn:feature_class":"P",
    "gn:feature_code":"PPL",
    "gn:name":"Bononia",
    "gn:population":0,
    "gn:timezone":"Europe/Warsaw",
    "iso:country":"PL",
    "name:und_x_variant":[
        "Bononja",
        "Bononia"
    ],
    "wof:name":"Bononia",
    "wof:placetype":"locality"
},
  "geometry": {"coordinates":[22.67473,50.71242],"type":"Point"}
}