{
  "type": "Feature",
  "properties": {
    "gn:gn_country":"PL",
    "gn:gn_fcode":"PPL",
    "gn:gn_pop":351,
    "gn:population":351,
    "iso:country":"PL",
    "name:eng_x_preferred":[
        "Trzydnik Du\u017cy-Kolonia"
    ],
    "name:fre_x_preferred":[
        "Trzydnik Du\u017cy-Kolonia"
    ],
    "name:per_x_preferred":[
        "\u0686\u06cc\u062f\u0646\u06cc\u06a9 \u062f\u0648\u0698\u06cc \u06a9\u0644\u0648\u0646\u06cc\u0627"
    ],
    "name:pol_x_preferred":[
        "Trzydnik Du\u017cy-Kolonia"
    ],
    "qs_pg:aaroncc":"PL",
    "qs_pg:gn_country":"PL",
    "qs_pg:gn_fcode":"PPL",
    "qs_pg:gn_pop":351,
    "qs_pg:name":"Trzydnik Du\u017cy-Kolonia",
    "qs_pg:photos_9r":0,
    "qs_pg:photos_sr":0,
    "qs_pg:pop_sr":2,
    "qs_pg:qs_pg_placetype":"locality",
    "wof:name":"Trzydnik Du\u017cy-Kolonia",
    "wof:placetype":"locality",
    "wof:population":351
},
  "geometry": {"coordinates":[22.13556,50.86302],"type":"Point"}
}