{
  "type": "Feature",
  "properties": {
    "gn:admin1_code":"74.0",
    "gn:admin2_code":"1020.0",
    "gn:admin3_code":"102007.0",
    "gn:asciiname":"Golaszyny",
    "gn:country_code":"PL",
    "gn:dem":143,
    "gn:feature_class":"P",
    "gn:feature_code":"PPL",
    "gn:name":"Go\u0142aszyny",
    "gn:population":0,
    "gn:timezone":"Europe/Warsaw",
    "iso:country":"PL",
    "name:pol_x_preferred":[
        "Go\u0142aszyny"
    ],
    "name:ukr_x_preferred":[
        "\u0490\u043e\u043b\u0430\u0448\u0438\u043d\u0438"
    ],
    "wof:name":"Golaszyny",
    "wof:placetype":"locality"
},
  "geometry": {"coordinates":[19.16638,51.92456],"type":"Point"}
}