{
  "type": "Feature",
  "properties": {
    "iso:country":"PL",
    "name:pol_x_preferred":[
        "Kiszkowo"
    ],
    "wof:name":"Kiszkowo",
    "wof:placetype":"locality"
},
  "geometry": {"coordinates":[17.29186516669,52.5880735688173],"type":"Point"}
}