{
  "type": "Feature",
  "properties": {
    "iso:country":"PL",
    "wof:name":"Osiedle Urocze",
    "wof:placetype":"neighbourhood"
},
  "geometry": {"coordinates":[20.03691936050958,50.07808952424181],"type":"Point"}
}