{
  "type": "Feature",
  "properties": {
    "gn:admin1_code":"85.0",
    "gn:admin2_code":"2811.0",
    "gn:admin3_code":"281101.0",
    "gn:asciiname":"Zablocie Kanigowskie",
    "gn:country_code":"PL",
    "gn:dem":192,
    "gn:feature_class":"P",
    "gn:feature_code":"PPL",
    "gn:name":"Zab\u0142ocie Kanigowskie",
    "gn:population":0,
    "gn:timezone":"Europe/Warsaw",
    "iso:country":"PL",
    "name:und_x_variant":[
        "Winrichsrode",
        "Sablotschen",
        "Zab\u0142ocie Kanigowskie"
    ],
    "wof:name":"Zablocie Kanigowskie",
    "wof:placetype":"locality"
},
  "geometry": {"coordinates":[20.48615,53.30278000000001],"type":"Point"}
}