{
  "type": "Feature",
  "properties": {
    "gn:admin1_code":"85.0",
    "gn:admin2_code":"2811.0",
    "gn:admin3_code":"281101.0",
    "gn:asciiname":"Zablocie Kanigowskie",
    "gn:country_code":"PL",
    "gn:dem":192,
    "gn:feature_class":"P",
    "gn:feature_code":"PPL",
    "gn:name":"Zab\u0142ocie Kanigowskie",
    "gn:population":0,
    "gn:timezone":"Europe/Warsaw",
    "iso:country":"PL",
    "name:azb_x_preferred":[
        "\u0632\u0627\u0628\u0648\u0648\u0686\u06cc\u0647 \u06a9\u0627\u0646\u0642\u0642\u0648\u0648\u0633\u06a9\u06cc\u0647"
    ],
    "name:fas_x_preferred":[
        "\u0632\u0627\u0628\u0648\u0648\u0686\u06cc\u0647 \u06a9\u0627\u0646\u06af\u06af\u0648\u0648\u0633\u06a9\u06cc\u0647"
    ],
    "name:fra_x_preferred":[
        "Zab\u0142ocie Kanigowskie"
    ],
    "name:pol_x_preferred":[
        "Zab\u0142ocie Kanigowskie"
    ],
    "name:ukr_x_preferred":[
        "\u0417\u0430\u0431\u043b\u043e\u0446\u0435-\u041a\u0430\u043d\u0456\u0491\u043e\u0432\u0441\u044c\u043a\u0435"
    ],
    "name:und_x_variant":[
        "Winrichsrode",
        "Sablotschen"
    ],
    "name:urd_x_preferred":[
        "\u0636\u0627\u0628\u0648\u0627\u06a9\u06d2 \u06a9\u0646\u06cc\u06af\u0648\u0648\u0633\u06a9\u0626\u06cc"
    ],
    "wof:name":"Zablocie Kanigowskie",
    "wof:placetype":"locality"
},
  "geometry": {"coordinates":[20.48615,53.30278000000001],"type":"Point"}
}