{
  "type": "Feature",
  "properties": {
    "gn:admin1_code":"82.0",
    "gn:admin2_code":"2213.0",
    "gn:admin3_code":"221309.0",
    "gn:asciiname":"Godziszewo",
    "gn:country_code":"PL",
    "gn:dem":77,
    "gn:feature_class":"P",
    "gn:feature_code":"PPL",
    "gn:name":"Godziszewo",
    "gn:population":0,
    "gn:timezone":"Europe/Warsaw",
    "iso:country":"PL",
    "wof:name":"Godziszewo",
    "wof:placetype":"locality"
},
  "geometry": {"coordinates":[18.55571,54.09895],"type":"Point"}
}