{
  "type": "Feature",
  "properties": {
    "gn:admin1_code":"81.0",
    "gn:admin2_code":"2013.0",
    "gn:admin3_code":"201303.0",
    "gn:asciiname":"Siennica-Lipusy",
    "gn:country_code":"PL",
    "gn:dem":138,
    "gn:feature_class":"P",
    "gn:feature_code":"PPL",
    "gn:name":"Siennica-Lipusy",
    "gn:population":0,
    "gn:timezone":"Europe/Warsaw",
    "iso:country":"PL",
    "name:fra_x_preferred":[
        "Siennica-Lipusy"
    ],
    "name:lit_x_preferred":[
        "Senica Lipusai"
    ],
    "name:pol_x_preferred":[
        "Siennica-Lipusy"
    ],
    "name:ukr_x_preferred":[
        "\u0421\u0435\u043d\u043d\u0438\u0446\u044f-\u041b\u0456\u043f\u0443\u0441\u0438"
    ],
    "wof:name":"Siennica-Lipusy",
    "wof:placetype":"locality"
},
  "geometry": {"coordinates":[22.39546,52.80432],"type":"Point"}
}