{
  "type": "Feature",
  "properties": {
    "gn:admin1_code":"81.0",
    "gn:admin2_code":"2013.0",
    "gn:admin3_code":"201303.0",
    "gn:asciiname":"Siennica-Lipusy",
    "gn:country_code":"PL",
    "gn:dem":138,
    "gn:feature_class":"P",
    "gn:feature_code":"PPL",
    "gn:name":"Siennica-Lipusy",
    "gn:population":0,
    "gn:timezone":"Europe/Warsaw",
    "iso:country":"PL",
    "wof:name":"Siennica-Lipusy",
    "wof:placetype":"locality"
},
  "geometry": {"coordinates":[22.39546,52.80432],"type":"Point"}
}