{
  "type": "Feature",
  "properties": {
    "gn:admin1_code":"74.0",
    "gn:admin2_code":"1014.0",
    "gn:admin3_code":"101407.0",
    "gn:asciiname":"Huta Klonowska",
    "gn:country_code":"PL",
    "gn:dem":161,
    "gn:feature_class":"P",
    "gn:feature_code":"PPL",
    "gn:name":"Huta Klonowska",
    "gn:population":0,
    "gn:timezone":"Europe/Warsaw",
    "iso:country":"PL",
    "wof:name":"Huta Klonowska",
    "wof:placetype":"locality"
},
  "geometry": {"coordinates":[18.39587,51.42114],"type":"Point"}
}