{
  "type": "Feature",
  "properties": {
    "gn:admin1_code":"84.0",
    "gn:admin2_code":"2604.0",
    "gn:admin3_code":"260410.0",
    "gn:asciiname":"Cminsk Wyreba",
    "gn:country_code":"PL",
    "gn:dem":284,
    "gn:feature_class":"P",
    "gn:feature_code":"PPL",
    "gn:name":"\u0106mi\u0144sk Wyr\u0119ba",
    "gn:population":0,
    "gn:timezone":"Europe/Warsaw",
    "iso:country":"PL",
    "name:und_x_variant":[
        "Wyr\u0119ba",
        "\u0106mi\u0144sk Wyr\u0119ba"
    ],
    "wof:name":"Cminsk Wyreba",
    "wof:placetype":"locality"
},
  "geometry": {"coordinates":[20.54813,50.98561],"type":"Point"}
}