{
  "type": "Feature",
  "properties": {
    "gn:country":"PL",
    "gn:fcode":"PPL",
    "gn:population":247,
    "iso:country":"PL",
    "name:ast_x_preferred":[
        "Wola S\u0119kowa"
    ],
    "name:ceb_x_preferred":[
        "Wola S\u0119kowa"
    ],
    "name:eng_x_preferred":[
        "Wola S\u0119kowa"
    ],
    "name:fas_x_preferred":[
        "\u0648\u0648\u0644\u0627 \u0633\u0646\u06a9\u0648\u0648\u0627"
    ],
    "name:nld_x_preferred":[
        "Wola S\u0119kowa"
    ],
    "name:pol_x_preferred":[
        "Wola S\u0119kowa"
    ],
    "name:ukr_x_preferred":[
        "\u0412\u043e\u043b\u044f \u0421\u0435\u043d\u044c\u043a\u043e\u0432\u0430"
    ],
    "name:und_x_variant":[
        "S\u0119kowa Wola"
    ],
    "name:vie_x_preferred":[
        "Wola S\u0119kowa"
    ],
    "qs_pg:aaroncc":"PL",
    "qs_pg:gn_country":"PL",
    "qs_pg:gn_fcode":"PPL",
    "qs_pg:gn_pop":247,
    "qs_pg:name":"Wola S\u0119kowa",
    "qs_pg:name_adm0":"Polska",
    "qs_pg:name_adm1":"Podkarpackie",
    "qs_pg:photos_9r":0,
    "qs_pg:photos_sr":0,
    "qs_pg:pop_sr":2,
    "qs_pg:qs_pg_placetype":"locality",
    "qs_pg:qs_pg_placetype_gp":"Town",
    "qs_pg:woe_adm0":23424923,
    "woe:adm0_id":23424923,
    "woe:name_adm0":"Polska",
    "woe:name_adm1":"Podkarpackie",
    "woe:placetype":"Town",
    "wof:name":"Wola S\u0119kowa",
    "wof:placetype":"locality",
    "wof:population":247
},
  "geometry": {"coordinates":[22.00501,49.50844],"type":"Point"}
}