{
  "type": "Feature",
  "properties": {
    "gn:admin1_code":"83.0",
    "gn:admin2_code":"2408.0",
    "gn:admin3_code":"240802.0",
    "gn:asciiname":"Kolonia Wojewodzka",
    "gn:country_code":"PL",
    "gn:dem":312,
    "gn:feature_class":"P",
    "gn:feature_code":"PPL",
    "gn:name":"Kolonia Wojew\u00f3dzka",
    "gn:population":0,
    "gn:timezone":"Europe/Warsaw",
    "iso:country":"PL",
    "wof:name":"Kolonia Wojewodzka",
    "wof:placetype":"locality"
},
  "geometry": {"coordinates":[18.90992,50.16072],"type":"Point"}
}