{
  "type": "Feature",
  "properties": {
    "gn:admin1_code":"85.0",
    "gn:admin2_code":"2812.0",
    "gn:admin3_code":"281205.0",
    "gn:asciiname":"Laki",
    "gn:country_code":"PL",
    "gn:dem":90,
    "gn:feature_class":"P",
    "gn:feature_code":"PPL",
    "gn:name":"\u0141\u0105ki",
    "gn:population":0,
    "gn:timezone":"Europe/Warsaw",
    "iso:country":"PL",
    "name:pol_x_preferred":[
        "\u0141\u0105ki Bratia\u0144skie"
    ],
    "name:und_x_variant":[
        "\u0141\u0105ki"
    ],
    "wof:name":"Laki",
    "wof:placetype":"locality"
},
  "geometry": {"coordinates":[19.598,53.44463],"type":"Point"}
}