{
  "type": "Feature",
  "properties": {
    "gn:admin1_code":"85.0",
    "gn:admin2_code":"2806.0",
    "gn:admin3_code":"280610.0",
    "gn:asciiname":"Gradzkie",
    "gn:country_code":"PL",
    "gn:dem":138,
    "gn:feature_class":"P",
    "gn:feature_code":"PPL",
    "gn:name":"Gr\u0105dzkie",
    "gn:population":0,
    "gn:timezone":"Europe/Warsaw",
    "iso:country":"PL",
    "name:und_x_variant":[
        "Funken",
        "Grondzken",
        "Gr\u0105dzkie"
    ],
    "wof:name":"Gradzkie",
    "wof:placetype":"locality"
},
  "geometry": {"coordinates":[22.10537,54.04051],"type":"Point"}
}