{
  "type": "Feature",
  "properties": {
    "gn:admin1_code":"86.0",
    "gn:admin2_code":"3027.0",
    "gn:admin3_code":"302703.0",
    "gn:asciiname":"Wola Piekarska",
    "gn:country_code":"PL",
    "gn:dem":114,
    "gn:feature_class":"P",
    "gn:feature_code":"PPL",
    "gn:name":"Wola Piekarska",
    "gn:population":0,
    "gn:timezone":"Europe/Warsaw",
    "iso:country":"PL",
    "name:pol_x_preferred":[
        "Wola Piekarska"
    ],
    "name:ukr_x_preferred":[
        "\u0412\u043e\u043b\u044f-\u041f\u0435\u043a\u0430\u0440\u0441\u044c\u043a\u0430"
    ],
    "wof:name":"Wola Piekarska",
    "wof:placetype":"locality"
},
  "geometry": {"coordinates":[18.69375,51.88529000000001],"type":"Point"}
}