{
  "type": "Feature",
  "properties": {
    "gn:admin1_code":"83.0",
    "gn:admin2_code":"2477.0",
    "gn:admin3_code":"247701.0",
    "gn:asciiname":"Jaroszowice",
    "gn:country_code":"PL",
    "gn:dem":247,
    "gn:feature_class":"P",
    "gn:feature_code":"PPL",
    "gn:name":"Jaroszowice",
    "gn:population":0,
    "gn:timezone":"Europe/Warsaw",
    "iso:country":"PL",
    "name:azb_x_preferred":[
        "\u06cc\u0627\u0631\u0648\u0634\u0648\u0648\u06cc\u062a\u0633\u0647"
    ],
    "name:deu_x_preferred":[
        "Jaroszowice"
    ],
    "name:fas_x_preferred":[
        "\u06cc\u0627\u0631\u0648\u0634\u0648\u0648\u06cc\u062a\u0633\u0647"
    ],
    "name:nld_x_preferred":[
        "Jaroszowice"
    ],
    "name:pol_x_preferred":[
        "Jaroszowice"
    ],
    "name:ukr_x_preferred":[
        "\u042f\u0440\u043e\u0448\u043e\u0432\u0456\u0446\u0435"
    ],
    "name:urd_x_preferred":[
        "\u062c\u0631\u0648\u0633\u0632\u0648\u0648\u06a9\u06d2"
    ],
    "wof:name":"Jaroszowice",
    "wof:placetype":"neighbourhood"
},
  "geometry": {"coordinates":[19.06437,50.11393],"type":"Point"}
}