{
  "type": "Feature",
  "properties": {
    "gn:admin1_code":"86.0",
    "gn:admin2_code":"3017.0",
    "gn:admin3_code":"301702.0",
    "gn:asciiname":"Czachory",
    "gn:country_code":"PL",
    "gn:dem":134,
    "gn:feature_class":"P",
    "gn:feature_code":"PPL",
    "gn:name":"Czach\u00f3ry",
    "gn:population":0,
    "gn:timezone":"Europe/Warsaw",
    "iso:country":"PL",
    "name:pol_x_preferred":[
        "Czachory"
    ],
    "name:und_x_variant":[
        "Dw\u00f3r Czach\u00f3ry",
        "Czach\u00f3ry"
    ],
    "wof:name":"Czachory",
    "wof:placetype":"locality"
},
  "geometry": {"coordinates":[17.92336,51.73016],"type":"Point"}
}