{
  "type": "Feature",
  "properties": {
    "gn:admin1_code":"78.0",
    "gn:admin2_code":"1423.0",
    "gn:admin3_code":"142302.0",
    "gn:asciiname":"Zygmuntow",
    "gn:country_code":"PL",
    "gn:dem":205,
    "gn:feature_class":"P",
    "gn:feature_code":"PPL",
    "gn:name":"Zygmunt\u00f3w",
    "gn:population":0,
    "gn:timezone":"Europe/Warsaw",
    "iso:country":"PL",
    "name:ceb_x_preferred":[
        "Zygmunt\u00f3w"
    ],
    "name:fra_x_preferred":[
        "Zygmunt\u00f3w"
    ],
    "name:pol_x_preferred":[
        "Zygmunt\u00f3w"
    ],
    "name:ukr_x_preferred":[
        "\u0417\u0438\u0491\u043c\u0443\u043d\u0442\u0443\u0432"
    ],
    "wof:name":"Zygmuntow",
    "wof:placetype":"locality"
},
  "geometry": {"coordinates":[20.56913,51.39953],"type":"Point"}
}