{
  "type": "Feature",
  "properties": {
    "gn:admin1_code":"78.0",
    "gn:admin2_code":"1412.0",
    "gn:admin3_code":"141214.0",
    "gn:asciiname":"Czarna",
    "gn:country_code":"PL",
    "gn:dem":155,
    "gn:feature_class":"P",
    "gn:feature_code":"PPL",
    "gn:name":"Czarna",
    "gn:population":0,
    "gn:timezone":"Europe/Warsaw",
    "iso:country":"PL",
    "name:ara_x_preferred":[
        "\u0643\u0632\u0631\u0646\u0627"
    ],
    "name:azb_x_preferred":[
        "\u0686\u0627\u0631\u0646\u0627"
    ],
    "name:ceb_x_preferred":[
        "Czarna"
    ],
    "name:fas_x_preferred":[
        "\u0686\u0627\u0631\u0646\u0627"
    ],
    "name:fra_x_preferred":[
        "Czarna"
    ],
    "name:hun_x_preferred":[
        "Czarna"
    ],
    "name:pol_x_preferred":[
        "Czarna"
    ],
    "name:ukr_x_preferred":[
        "\u0427\u0430\u0440\u043d\u0430"
    ],
    "wof:name":"Czarna",
    "wof:placetype":"locality"
},
  "geometry": {"coordinates":[21.59259,52.24417],"type":"Point"}
}