{
  "type": "Feature",
  "properties": {
    "gn:admin1_code":"74.0",
    "gn:admin2_code":"1005.0",
    "gn:admin3_code":"100509.0",
    "gn:asciiname":"Sypien",
    "gn:country_code":"PL",
    "gn:dem":84,
    "gn:feature_class":"P",
    "gn:feature_code":"PPL",
    "gn:name":"Sypie\u0144",
    "gn:population":0,
    "gn:timezone":"Europe/Warsaw",
    "iso:country":"PL",
    "name:fra_x_preferred":[
        "Sypie\u0144"
    ],
    "name:pol_x_preferred":[
        "Sypie\u0144"
    ],
    "name:ukr_x_preferred":[
        "\u0421\u0438\u043f\u0435\u043d\u044c"
    ],
    "wof:name":"Sypien",
    "wof:placetype":"locality"
},
  "geometry": {"coordinates":[20.09262,52.09617],"type":"Point"}
}