{
  "type": "Feature",
  "properties": {
    "gn:admin1_code":"75.0",
    "gn:admin2_code":"601.0",
    "gn:admin3_code":"60119.0",
    "gn:asciiname":"Lachowka Duza",
    "gn:country_code":"PL",
    "gn:dem":141,
    "gn:feature_class":"P",
    "gn:feature_code":"PPL",
    "gn:name":"Lach\u00f3wka Du\u017ca",
    "gn:population":0,
    "gn:timezone":"Europe/Warsaw",
    "iso:country":"PL",
    "name:und_x_variant":[
        "Lach\u00f3wka Wielka",
        "Lach\u00f3wka Du\u017ca"
    ],
    "wof:name":"Lachowka Duza",
    "wof:placetype":"locality"
},
  "geometry": {"coordinates":[23.382,52.03003],"type":"Point"}
}