{
  "type": "Feature",
  "properties": {
    "gn:admin1_code":"75.0",
    "gn:admin2_code":"601.0",
    "gn:admin3_code":"60119.0",
    "gn:asciiname":"Lachowka Duza",
    "gn:country_code":"PL",
    "gn:dem":141,
    "gn:feature_class":"P",
    "gn:feature_code":"PPL",
    "gn:name":"Lach\u00f3wka Du\u017ca",
    "gn:population":0,
    "gn:timezone":"Europe/Warsaw",
    "iso:country":"PL",
    "name:azb_x_preferred":[
        "\u0644\u0627\u062e\u0648\u0648\u06a9\u0627 \u062f\u0648\u0698\u0627"
    ],
    "name:ceb_x_preferred":[
        "Lach\u00f3wka Du\u017ca"
    ],
    "name:fas_x_preferred":[
        "\u0644\u0627\u062e\u0648\u0648\u06a9\u0627 \u062f\u0648\u0698\u0627"
    ],
    "name:fra_x_preferred":[
        "Lach\u00f3wka Du\u017ca"
    ],
    "name:lit_x_preferred":[
        "Lachuvka Du\u017ea"
    ],
    "name:pol_x_preferred":[
        "Lach\u00f3wka Du\u017ca"
    ],
    "name:ukr_x_preferred":[
        "\u041b\u044f\u0445\u0443\u0432\u043a\u0430-\u0414\u0443\u0436\u0430"
    ],
    "name:und_x_variant":[
        "Lach\u00f3wka Wielka"
    ],
    "wof:name":"Lachowka Duza",
    "wof:placetype":"locality"
},
  "geometry": {"coordinates":[23.382,52.03003],"type":"Point"}
}