{
  "type": "Feature",
  "properties": {
    "gn:admin1_code":"78.0",
    "gn:admin2_code":"1418.0",
    "gn:admin3_code":"141805.0",
    "gn:asciiname":"Krupia Wolka",
    "gn:country_code":"PL",
    "gn:dem":120,
    "gn:feature_class":"P",
    "gn:feature_code":"PPL",
    "gn:name":"Krupia W\u00f3lka",
    "gn:population":0,
    "gn:timezone":"Europe/Warsaw",
    "iso:country":"PL",
    "name:azb_x_preferred":[
        "\u06a9\u0631\u0648\u067e\u06cc\u0627 \u0648\u0648\u0644\u06a9\u0627"
    ],
    "name:ceb_x_preferred":[
        "Krupia W\u00f3lka"
    ],
    "name:fas_x_preferred":[
        "\u06a9\u0631\u0648\u067e\u06cc\u0627 \u0648\u0648\u0644\u06a9\u0627"
    ],
    "name:fra_x_preferred":[
        "Krupia W\u00f3lka"
    ],
    "name:nld_x_preferred":[
        "Krupia W\u00f3lka"
    ],
    "name:pol_x_preferred":[
        "Krupia W\u00f3lka"
    ],
    "name:tgl_x_preferred":[
        "Krupia W\u00f3lka"
    ],
    "name:ukr_x_preferred":[
        "\u041a\u0440\u0443\u043f\u044f-\u0412\u0443\u043b\u044c\u043a\u0430"
    ],
    "wof:name":"Krupia Wolka",
    "wof:placetype":"locality"
},
  "geometry": {"coordinates":[21.03753,51.98763],"type":"Point"}
}