{
  "type": "Feature",
  "properties": {
    "gn:admin1_code":"78.0",
    "gn:admin2_code":"1418.0",
    "gn:admin3_code":"141805.0",
    "gn:asciiname":"Krupia Wolka",
    "gn:country_code":"PL",
    "gn:dem":120,
    "gn:feature_class":"P",
    "gn:feature_code":"PPL",
    "gn:name":"Krupia W\u00f3lka",
    "gn:population":0,
    "gn:timezone":"Europe/Warsaw",
    "iso:country":"PL",
    "wof:name":"Krupia Wolka",
    "wof:placetype":"locality"
},
  "geometry": {"coordinates":[21.03753,51.98763],"type":"Point"}
}