{
  "type": "Feature",
  "properties": {
    "gn:country":"PL",
    "gn:fcode":"PPL",
    "gn:population":0,
    "iso:country":"PL",
    "name:ast_x_preferred":[
        "W\u00f3lka"
    ],
    "name:ces_x_preferred":[
        "W\u00f3lka"
    ],
    "name:che_x_preferred":[
        "\u0412\u0443\u043b\u044c\u043a\u0430"
    ],
    "name:eng_x_preferred":[
        "W\u00f3lka"
    ],
    "name:fra_x_preferred":[
        "W\u00f3lka"
    ],
    "name:nan_x_preferred":[
        "W\u00f3lka"
    ],
    "name:pol_x_preferred":[
        "W\u00f3lka"
    ],
    "name:tat_x_preferred":[
        "\u0412\u0443\u043b\u044c\u043a\u0430"
    ],
    "name:ukr_x_preferred":[
        "\u0412\u0443\u043b\u044c\u043a\u0430"
    ],
    "qs_pg:aaroncc":"PL",
    "qs_pg:gn_country":"PL",
    "qs_pg:gn_fcode":"PPL",
    "qs_pg:gn_pop":0,
    "qs_pg:name":"W\u00f3lka",
    "qs_pg:name_adm0":"Polska",
    "qs_pg:name_adm1":"Mazowieckie",
    "qs_pg:photos":10,
    "qs_pg:photos_1k":2,
    "qs_pg:photos_9k":1,
    "qs_pg:photos_9r":1,
    "qs_pg:photos_all":10,
    "qs_pg:photos_sr":1,
    "qs_pg:pop_sr":0,
    "qs_pg:qs_pg_placetype":"locality",
    "qs_pg:qs_pg_placetype_gp":"Town",
    "qs_pg:woe_adm0":23424923,
    "woe:adm0_id":23424923,
    "woe:name_adm0":"Polska",
    "woe:name_adm1":"Mazowieckie",
    "woe:placetype":"Town",
    "wof:name":"W\u00f3lka",
    "wof:placetype":"locality"
},
  "geometry": {"coordinates":[20.71215,52.27929],"type":"Point"}
}