{
  "type": "Feature",
  "properties": {
    "gn:admin1_code":"77.0",
    "gn:admin2_code":"1206.0",
    "gn:admin3_code":"120601.0",
    "gn:asciiname":"Pasieka",
    "gn:country_code":"PL",
    "gn:dem":210,
    "gn:feature_class":"P",
    "gn:feature_code":"PPL",
    "gn:name":"Pasieka",
    "gn:population":0,
    "gn:timezone":"Europe/Warsaw",
    "iso:country":"PL",
    "name:fra_x_preferred":[
        "Pasieka"
    ],
    "name:pol_x_preferred":[
        "Pasieka"
    ],
    "name:ukr_x_preferred":[
        "\u041f\u0430\u0441\u0435\u043a\u0430"
    ],
    "wof:name":"Pasieka",
    "wof:placetype":"locality"
},
  "geometry": {"coordinates":[19.66986,49.98133],"type":"Point"}
}