{
  "type": "Feature",
  "properties": {
    "gn:country":"PL",
    "gn:fcode":"PPL",
    "gn:population":585,
    "iso:country":"PL",
    "name:ast_x_preferred":[
        "So\u015bnica"
    ],
    "name:eng_x_preferred":[
        "So\u015bnica"
    ],
    "name:fra_x_preferred":[
        "So\u015bnica"
    ],
    "name:pol_x_preferred":[
        "So\u015bnica"
    ],
    "name:ukr_x_preferred":[
        "\u0421\u043e\u0441\u044c\u043d\u0438\u0446\u044f"
    ],
    "qs_pg:aaroncc":"PL",
    "qs_pg:gn_country":"PL",
    "qs_pg:gn_fcode":"PPL",
    "qs_pg:gn_pop":585,
    "qs_pg:name":"So\u015bnica",
    "qs_pg:name_adm0":"Polska",
    "qs_pg:name_adm1":"Wielkopolskie",
    "qs_pg:photos_9r":0,
    "qs_pg:photos_sr":0,
    "qs_pg:pop_sr":2,
    "qs_pg:qs_pg_placetype":"locality",
    "qs_pg:qs_pg_placetype_gp":"Town",
    "qs_pg:woe_adm0":23424923,
    "woe:adm0_id":23424923,
    "woe:name_adm0":"Polska",
    "woe:name_adm1":"Wielkopolskie",
    "woe:placetype":"Town",
    "wof:name":"So\u015bnica",
    "wof:placetype":"locality",
    "wof:population":585
},
  "geometry": {"coordinates":[17.68061,51.86123],"type":"Point"}
}