{
  "type": "Feature",
  "properties": {
    "gn:admin1_code":"72.0",
    "gn:admin2_code":"215.0",
    "gn:admin3_code":"21502.0",
    "gn:asciiname":"Piskorzow",
    "gn:country_code":"PL",
    "gn:dem":139,
    "gn:feature_class":"P",
    "gn:feature_code":"PPL",
    "gn:name":"Piskorz\u00f3w",
    "gn:population":0,
    "gn:timezone":"Europe/Warsaw",
    "iso:country":"PL",
    "name:pol_x_preferred":[
        "Piskorz\u00f3w"
    ],
    "name:ukr_x_preferred":[
        "\u041f\u0456\u0441\u043a\u043e\u0436\u0443\u0432"
    ],
    "wof:name":"Piskorzow",
    "wof:placetype":"locality"
},
  "geometry": {"coordinates":[17.14009,50.92773],"type":"Point"}
}