{
  "type": "Feature",
  "properties": {
    "iso:country":"PL",
    "name:eng_x_preferred":[
        "Leniwka"
    ],
    "name:fra_x_preferred":[
        "Leniwka"
    ],
    "name:nno_x_preferred":[
        "Leniwka"
    ],
    "name:nob_x_preferred":[
        "Leniwka"
    ],
    "name:nor_x_preferred":[
        "Leniwka"
    ],
    "name:pol_x_preferred":[
        "Przegalina",
        "Leniwka"
    ],
    "name:pol_x_variant":[
        "Einlage",
        "Einlage bei Schwienenhorst",
        "Przegaliny"
    ],
    "qs:gn_adm0_cc":"PL",
    "qs:gn_fcode":"PPLX",
    "qs:gn_local":3099434,
    "qs:gn_nam_loc":"Gdansk, Gda\u0144sk, Pomorskie, PL",
    "qs:gn_namadm1":"82",
    "qs:gn_name":"Przegalina",
    "qs:local_max":11560,
    "qs:local_sum":12109,
    "qs:localhoods":5,
    "qs:name":"Przegalina",
    "qs:name_adm0":"Polska",
    "qs:name_adm1":"Pomorskie",
    "qs:name_adm2":"Gdansk",
    "qs:name_lau":"Gdansk",
    "qs:name_local":"Gda\u0144sk",
    "qs:photo_max":19,
    "qs:photo_sum":102,
    "qs:placetype":"Suburb",
    "qs:quad_count":39,
    "qs:woe_adm0":23424923,
    "qs:woe_adm1":12577945,
    "qs:woe_adm2":12591368,
    "qs:woe_lau":12618131,
    "qs:woe_local":493417,
    "qs:woe_ver":"7.10.0",
    "wd:wordcount":75,
    "wof:lang":[
        "pol"
    ],
    "wof:name":"Przegalina",
    "wof:placetype":"neighbourhood"
},
  "geometry": {"coordinates":[18.920207,54.312738],"type":"Point"}
}