{
  "type": "Feature",
  "properties": {
    "gn:population":2503,
    "iso:country":"PL",
    "name:azb_x_preferred":[
        "\u0642\u0645\u06cc\u0646\u0627 \u06a9\u0648\u062a\u0648\u0646\u0642"
    ],
    "name:bel_x_preferred":[
        "\u0413\u043c\u0456\u043d\u0430 \u041a\u043e\u0442\u0443\u043d\u044c"
    ],
    "name:ceb_x_preferred":[
        "Kotu\u0144"
    ],
    "name:deu_x_preferred":[
        "Gmina Kotu\u0144"
    ],
    "name:eng_x_preferred":[
        "Kotu\u0144"
    ],
    "name:eng_x_variant":[
        "Gmina Kotu\u0144"
    ],
    "name:eus_x_preferred":[
        "Kotu\u0144 udalerria"
    ],
    "name:fas_x_preferred":[
        "\u06af\u0645\u06cc\u0646\u0627 \u06a9\u0648\u062a\u0648\u0646\u06af"
    ],
    "name:fra_x_preferred":[
        "Kotu\u0144"
    ],
    "name:ita_x_preferred":[
        "Kotu\u0144"
    ],
    "name:lit_x_preferred":[
        "Kotuno vals\u010dius"
    ],
    "name:nan_x_preferred":[
        "Kotu\u0144"
    ],
    "name:nld_x_preferred":[
        "Kotu\u0144"
    ],
    "name:oci_x_preferred":[
        "Kotu\u0144"
    ],
    "name:pol_x_preferred":[
        "Kotu\u0144"
    ],
    "name:por_x_preferred":[
        "Comuna de Kotu\u0144"
    ],
    "name:rus_x_preferred":[
        "\u041a\u043e\u0442\u0443\u043d\u044c"
    ],
    "name:slk_x_preferred":[
        "Gmina Kotu\u0144"
    ],
    "name:ukr_x_preferred":[
        "\u0490\u043c\u0456\u043d\u0430 \u041a\u043e\u0442\u0443\u043d\u044c"
    ],
    "name:war_x_preferred":[
        "Gmina Kotu\u0144"
    ],
    "qs:a0":"Rzeczpospolita Polska",
    "qs:a1":"*Mazowieckie",
    "qs:a1r":"0",
    "qs:a2":"Siedlecki",
    "qs:adm0":"Rzeczpospolita Polska",
    "qs:la":"Kotu\u0144",
    "qs:la_lc":"*PL1426032",
    "qs:level":"locality",
    "qs:loc":"Kotu\u0144",
    "qs:loc_alt":"Kotun",
    "qs:pop":0,
    "qs:type":"rural point-in-poly",
    "wd:wordcount":135,
    "wof:name":"Kotu\u0144",
    "wof:placetype":"locality",
    "wof:population":2503
},
  "geometry": {"coordinates":[21.981598686648,52.1675188320341],"type":"Point"}
}