{
  "type": "Feature",
  "properties": {
    "gn:admin1_code":"83.0",
    "gn:admin2_code":"2401.0",
    "gn:admin3_code":"240105.0",
    "gn:asciiname":"Topor-Dabrowa",
    "gn:country_code":"PL",
    "gn:dem":294,
    "gn:feature_class":"P",
    "gn:feature_code":"PPL",
    "gn:name":"Topor-D\u0105browa",
    "gn:population":0,
    "gn:timezone":"Europe/Warsaw",
    "iso:country":"PL",
    "wof:name":"Topor-Dabrowa",
    "wof:placetype":"locality"
},
  "geometry": {"coordinates":[19.15,50.41667],"type":"Point"}
}