{
  "type": "Feature",
  "properties": {
    "gn:admin1_code":"87.0",
    "gn:admin2_code":"3209.0",
    "gn:admin3_code":"320908.0",
    "gn:asciiname":"Bardzlino",
    "gn:country_code":"PL",
    "gn:dem":46,
    "gn:feature_class":"P",
    "gn:feature_code":"PPL",
    "gn:name":"Bardzlino",
    "gn:population":0,
    "gn:timezone":"Europe/Warsaw",
    "iso:country":"PL",
    "name:ceb_x_preferred":[
        "Bardzlino"
    ],
    "name:pol_x_preferred":[
        "Bardzlino"
    ],
    "name:vie_x_preferred":[
        "Bardzlino"
    ],
    "wof:name":"Bardzlino",
    "wof:placetype":"locality"
},
  "geometry": {"coordinates":[16.12157,54.07586],"type":"Point"}
}