{
  "type": "Feature",
  "properties": {
    "gn:admin1_code":"77.0",
    "gn:admin2_code":"1213.0",
    "gn:admin3_code":"121306.0",
    "gn:asciiname":"Brzezinka",
    "gn:country_code":"PL",
    "gn:dem":232,
    "gn:feature_class":"P",
    "gn:feature_code":"PPL",
    "gn:name":"Brzezinka",
    "gn:population":2100,
    "gn:timezone":"Europe/Warsaw",
    "iso:country":"PL",
    "wof:name":"Brzezinka",
    "wof:placetype":"locality",
    "wof:population":2100
},
  "geometry": {"coordinates":[19.1902,50.04237],"type":"Point"}
}