{
  "type": "Feature",
  "properties": {
    "gn:admin1_code":"84.0",
    "gn:admin2_code":"2603.0",
    "gn:admin3_code":"260302.0",
    "gn:asciiname":"Stradow",
    "gn:country_code":"PL",
    "gn:dem":250,
    "gn:feature_class":"P",
    "gn:feature_code":"PPL",
    "gn:name":"Strad\u00f3w",
    "gn:population":0,
    "gn:timezone":"Europe/Warsaw",
    "iso:country":"PL",
    "name:pol_x_preferred":[
        "Strad\u00f3w"
    ],
    "name:ukr_x_preferred":[
        "\u0421\u0442\u0440\u0430\u0434\u0443\u0432"
    ],
    "wof:name":"Stradow",
    "wof:placetype":"locality"
},
  "geometry": {"coordinates":[20.48105,50.37109],"type":"Point"}
}