{
  "type": "Feature",
  "properties": {
    "gn:admin1_code":"73.0",
    "gn:admin2_code":"410.0",
    "gn:admin3_code":"41001.0",
    "gn:asciiname":"Weronika",
    "gn:country_code":"PL",
    "gn:dem":55,
    "gn:feature_class":"P",
    "gn:feature_code":"PPL",
    "gn:name":"Weronika",
    "gn:population":0,
    "gn:timezone":"Europe/Warsaw",
    "iso:country":"PL",
    "wof:name":"Weronika",
    "wof:placetype":"locality"
},
  "geometry": {"coordinates":[17.45687,53.08106],"type":"Point"}
}