{
  "type": "Feature",
  "properties": {
    "gn:admin1_code":"84.0",
    "gn:admin2_code":"2608.0",
    "gn:admin3_code":"260803.0",
    "gn:asciiname":"Sedowice",
    "gn:country_code":"PL",
    "gn:dem":211,
    "gn:feature_class":"P",
    "gn:feature_code":"PPL",
    "gn:name":"S\u0119dowice",
    "gn:population":0,
    "gn:timezone":"Europe/Warsaw",
    "iso:country":"PL",
    "wof:name":"Sedowice",
    "wof:placetype":"locality"
},
  "geometry": {"coordinates":[20.35389,50.50677],"type":"Point"}
}