{
  "type": "Feature",
  "properties": {
    "gn:admin1_code":"84.0",
    "gn:admin2_code":"2608.0",
    "gn:admin3_code":"260803.0",
    "gn:asciiname":"Sedowice",
    "gn:country_code":"PL",
    "gn:dem":211,
    "gn:feature_class":"P",
    "gn:feature_code":"PPL",
    "gn:name":"S\u0119dowice",
    "gn:population":0,
    "gn:timezone":"Europe/Warsaw",
    "iso:country":"PL",
    "name:pol_x_preferred":[
        "S\u0119dowice"
    ],
    "name:ukr_x_preferred":[
        "\u0421\u0435\u043d\u0434\u043e\u0432\u0456\u0446\u0435"
    ],
    "wof:name":"Sedowice",
    "wof:placetype":"locality"
},
  "geometry": {"coordinates":[20.35389,50.50677],"type":"Point"}
}