{
  "type": "Feature",
  "properties": {
    "gn:admin1_code":"78.0",
    "gn:admin2_code":"1413.0",
    "gn:admin3_code":"141303.0",
    "gn:asciiname":"Keczewo",
    "gn:country_code":"PL",
    "gn:dem":140,
    "gn:feature_class":"P",
    "gn:feature_code":"PPL",
    "gn:name":"K\u0119czewo",
    "gn:population":0,
    "gn:timezone":"Europe/Warsaw",
    "iso:country":"PL",
    "name:azb_x_preferred":[
        "\u06a9\u0646\u0686\u0648\u0648"
    ],
    "name:ceb_x_preferred":[
        "K\u0119czewo"
    ],
    "name:fas_x_preferred":[
        "\u06a9\u0646\u0686\u0648\u0648"
    ],
    "name:fra_x_preferred":[
        "K\u0119czewo"
    ],
    "name:pol_x_preferred":[
        "K\u0119czewo"
    ],
    "name:ukr_x_preferred":[
        "\u041a\u0435\u043d\u0447\u0435\u0432\u043e"
    ],
    "wof:name":"Keczewo",
    "wof:placetype":"locality"
},
  "geometry": {"coordinates":[20.1642,53.12885],"type":"Point"}
}