{
  "type": "Feature",
  "properties": {
    "gn:admin1_code":"75.0",
    "gn:admin2_code":"614.0",
    "gn:admin3_code":"61403.0",
    "gn:asciiname":"Polesie Wojszynskie",
    "gn:cc2":"PL",
    "gn:country_code":"PL",
    "gn:dem":169,
    "gn:feature_class":"P",
    "gn:feature_code":"PPL",
    "gn:name":"Polesie Wojszy\u0144skie",
    "gn:population":0,
    "gn:timezone":"Europe/Warsaw",
    "iso:country":"PL",
    "name:und_x_variant":[
        "Posilenie",
        "Polesie Wojszy\u0144skie"
    ],
    "wof:name":"Polesie Wojszynskie",
    "wof:placetype":"locality"
},
  "geometry": {"coordinates":[21.84597,51.37746],"type":"Point"}
}