{
  "type": "Feature",
  "properties": {
    "gn:admin1_code":"79.0",
    "gn:admin2_code":"1607.0",
    "gn:admin3_code":"160707.0",
    "gn:asciiname":"Goscice",
    "gn:country_code":"PL",
    "gn:dem":262,
    "gn:feature_class":"P",
    "gn:feature_code":"PPL",
    "gn:name":"Go\u015bcice",
    "gn:population":0,
    "gn:timezone":"Europe/Warsaw",
    "iso:country":"PL",
    "name:azb_x_preferred":[
        "\u0642\u0648\u0634\u0686\u06cc\u062a\u0633\u0647"
    ],
    "name:ceb_x_preferred":[
        "Go\u015bcice"
    ],
    "name:deu_x_preferred":[
        "Go\u015bcice"
    ],
    "name:fas_x_preferred":[
        "\u06af\u0648\u0634\u0686\u06cc\u062a\u0633\u0647"
    ],
    "name:pol_x_preferred":[
        "Go\u015bcice"
    ],
    "name:ukr_x_preferred":[
        "\u0490\u043e\u0441\u0446\u0438\u0446\u0435"
    ],
    "wof:name":"Goscice",
    "wof:placetype":"locality"
},
  "geometry": {"coordinates":[16.98709,50.43761],"type":"Point"}
}