{
  "type": "Feature",
  "properties": {
    "gn:admin1_code":"79.0",
    "gn:admin2_code":"1607.0",
    "gn:admin3_code":"160707.0",
    "gn:asciiname":"Goscice",
    "gn:country_code":"PL",
    "gn:dem":262,
    "gn:feature_class":"P",
    "gn:feature_code":"PPL",
    "gn:name":"Go\u015bcice",
    "gn:population":0,
    "gn:timezone":"Europe/Warsaw",
    "iso:country":"PL",
    "wof:name":"Goscice",
    "wof:placetype":"locality"
},
  "geometry": {"coordinates":[16.98709,50.43761],"type":"Point"}
}