{
  "type": "Feature",
  "properties": {
    "gn:admin1_code":"80.0",
    "gn:admin2_code":"1815.0",
    "gn:admin3_code":"181504.0",
    "gn:asciiname":"Ruda",
    "gn:country_code":"PL",
    "gn:dem":208,
    "gn:feature_class":"P",
    "gn:feature_code":"PPL",
    "gn:name":"Ruda",
    "gn:population":0,
    "gn:timezone":"Europe/Warsaw",
    "iso:country":"PL",
    "name:pol_x_preferred":[
        "Ruda"
    ],
    "name:ukr_x_preferred":[
        "\u0420\u0443\u0434\u0430"
    ],
    "wof:name":"Ruda",
    "wof:placetype":"locality"
},
  "geometry": {"coordinates":[21.69391,50.13666],"type":"Point"}
}