{
  "type": "Feature",
  "properties": {
    "gn:country":"PL",
    "gn:fcode":"PPL",
    "gn:population":232,
    "iso:country":"PL",
    "name:ast_x_preferred":[
        "Gr\u0119bosz\u00f3w"
    ],
    "name:ceb_x_preferred":[
        "Gr\u0119bosz\u00f3w"
    ],
    "name:ces_x_preferred":[
        "Gr\u0119bosz\u00f3w"
    ],
    "name:che_x_preferred":[
        "\u0413\u0440\u0435\u043c\u0431\u043e\u0448\u0443\u0432"
    ],
    "name:eng_x_preferred":[
        "Gr\u0119bosz\u00f3w"
    ],
    "name:fra_x_preferred":[
        "Gr\u0119bosz\u00f3w"
    ],
    "name:ido_x_preferred":[
        "Gr\u0119bosz\u00f3w"
    ],
    "name:nan_x_preferred":[
        "Gr\u0119bosz\u00f3w"
    ],
    "name:pol_x_preferred":[
        "Gr\u0119bosz\u00f3w"
    ],
    "name:sqi_x_preferred":[
        "Greboszow"
    ],
    "name:tat_x_preferred":[
        "\u0413\u0440\u0435\u043c\u0431\u043e\u0448\u0443\u0432"
    ],
    "name:ukr_x_preferred":[
        "\u0490\u0440\u0435\u043c\u0431\u043e\u0448\u0443\u0432"
    ],
    "qs_pg:aaroncc":"PL",
    "qs_pg:gn_country":"PL",
    "qs_pg:gn_fcode":"PPL",
    "qs_pg:gn_pop":232,
    "qs_pg:name":"Gr\u0119bosz\u00f3w",
    "qs_pg:name_adm0":"Polska",
    "qs_pg:name_adm1":"\u0141\u00f3dzkie",
    "qs_pg:photos_9r":0,
    "qs_pg:photos_sr":0,
    "qs_pg:pop_sr":2,
    "qs_pg:qs_pg_placetype":"locality",
    "qs_pg:qs_pg_placetype_gp":"Town",
    "qs_pg:woe_adm0":23424923,
    "woe:adm0_id":23424923,
    "woe:name_adm0":"Polska",
    "woe:name_adm1":"\u0141\u00f3dzkie",
    "woe:placetype":"Town",
    "wof:name":"Gr\u0119bosz\u00f3w",
    "wof:placetype":"locality",
    "wof:population":232
},
  "geometry": {"coordinates":[19.40924,51.46502],"type":"Point"}
}