{
  "type": "Feature",
  "properties": {
    "iso:country":"PL",
    "wof:name":"Osiedle Hutnicze",
    "wof:placetype":"neighbourhood"
},
  "geometry": {"coordinates":[20.04570270538303,50.07320540310564],"type":"Point"}
}