{
  "type": "Feature",
  "properties": {
    "gn:admin1_code":"78.0",
    "gn:admin2_code":"1429.0",
    "gn:admin3_code":"142909.0",
    "gn:asciiname":"Grady",
    "gn:country_code":"PL",
    "gn:dem":107,
    "gn:feature_class":"P",
    "gn:feature_code":"PPL",
    "gn:name":"Gr\u0105dy",
    "gn:population":0,
    "gn:timezone":"Europe/Warsaw",
    "iso:country":"PL",
    "wof:name":"Grady",
    "wof:placetype":"locality"
},
  "geometry": {"coordinates":[22.44284,52.57249],"type":"Point"}
}