{
  "type": "Feature",
  "properties": {
    "gn:admin1_code":"78.0",
    "gn:admin2_code":"1429.0",
    "gn:admin3_code":"142909.0",
    "gn:asciiname":"Grady",
    "gn:country_code":"PL",
    "gn:dem":107,
    "gn:feature_class":"P",
    "gn:feature_code":"PPL",
    "gn:name":"Gr\u0105dy",
    "gn:population":0,
    "gn:timezone":"Europe/Warsaw",
    "iso:country":"PL",
    "name:ceb_x_preferred":[
        "Grady"
    ],
    "name:deu_x_preferred":[
        "Grady"
    ],
    "name:fra_x_preferred":[
        "Grady"
    ],
    "name:heb_x_preferred":[
        "\u05d2\u05e8\u05d9\u05d9\u05d3\u05d9"
    ],
    "name:ita_x_preferred":[
        "Grady"
    ],
    "name:nld_x_preferred":[
        "Grady"
    ],
    "name:pol_x_preferred":[
        "Grady"
    ],
    "name:por_x_preferred":[
        "Grady"
    ],
    "name:rus_x_preferred":[
        "\u0413\u0440\u0435\u0439\u0434\u0438"
    ],
    "name:spa_x_preferred":[
        "Grady"
    ],
    "name:srp_x_preferred":[
        "\u0413\u0440\u0435\u0458\u0434\u0438"
    ],
    "name:ukr_x_preferred":[
        "\u0413\u0440\u0435\u0439\u0434\u0456"
    ],
    "name:vol_x_preferred":[
        "Grady"
    ],
    "wof:name":"Grady",
    "wof:placetype":"locality"
},
  "geometry": {"coordinates":[22.44284,52.57249],"type":"Point"}
}