{
  "type": "Feature",
  "properties": {
    "iso:country":"PL",
    "name:eng_x_preferred":[
        "Grabiszyn-Grabiszynek"
    ],
    "name:pol_x_preferred":[
        "Grabiszyn-Grabiszynek"
    ],
    "wof:name":"Grabiszyn-Grabiszynek",
    "wof:placetype":"neighbourhood"
},
  "geometry": {"coordinates":[16.9831672364394,51.08918980768032],"type":"Point"}
}