{
  "type": "Feature",
  "properties": {
    "gn:admin1_code":"83.0",
    "gn:admin2_code":"2407.0",
    "gn:admin3_code":"240706.0",
    "gn:asciiname":"Kolonia Strzebinska",
    "gn:country_code":"PL",
    "gn:dem":290,
    "gn:feature_class":"P",
    "gn:feature_code":"PPL",
    "gn:name":"Kolonia Strzebinska",
    "gn:population":0,
    "gn:timezone":"Europe/Warsaw",
    "iso:country":"PL",
    "wof:name":"Kolonia Strzebinska",
    "wof:placetype":"locality"
},
  "geometry": {"coordinates":[18.90264,50.61295],"type":"Point"}
}