{
  "type": "Feature",
  "properties": {
    "gn:admin1_code":"78.0",
    "gn:admin2_code":"1411.0",
    "gn:admin3_code":"141103.0",
    "gn:asciiname":"Byszewo",
    "gn:country_code":"PL",
    "gn:dem":100,
    "gn:feature_class":"P",
    "gn:feature_code":"PPL",
    "gn:name":"Byszewo",
    "gn:population":0,
    "gn:timezone":"Europe/Warsaw",
    "iso:country":"PL",
    "name:fra_x_preferred":[
        "Byszewo"
    ],
    "name:pol_x_preferred":[
        "Byszewo"
    ],
    "name:ukr_x_preferred":[
        "\u0411\u0438\u0448\u0435\u0432\u043e"
    ],
    "wof:name":"Byszewo",
    "wof:placetype":"locality"
},
  "geometry": {"coordinates":[20.98852,52.83],"type":"Point"}
}