{
  "type": "Feature",
  "properties": {
    "gn:admin1_code":"87.0",
    "gn:admin2_code":"3207.0",
    "gn:admin3_code":"320703.0",
    "gn:asciiname":"Rekowo",
    "gn:country_code":"PL",
    "gn:dem":2,
    "gn:feature_class":"P",
    "gn:feature_code":"PPL",
    "gn:name":"Rekowo",
    "gn:population":0,
    "gn:timezone":"Europe/Warsaw",
    "iso:country":"PL",
    "name:fra_x_preferred":[
        "Rekowo"
    ],
    "name:pol_x_preferred":[
        "Rekowo"
    ],
    "name:ukr_x_preferred":[
        "\u0420\u0435\u043a\u043e\u0432\u043e"
    ],
    "wof:name":"Rekowo",
    "wof:placetype":"locality"
},
  "geometry": {"coordinates":[14.79006,53.88686],"type":"Point"}
}