{
  "type": "Feature",
  "properties": {
    "gn:admin1_code":"86.0",
    "gn:admin2_code":"3063.0",
    "gn:admin3_code":"306301.0",
    "gn:asciiname":"Gronowo",
    "gn:country_code":"PL",
    "gn:dem":102,
    "gn:feature_class":"P",
    "gn:feature_code":"PPL",
    "gn:name":"Gronowo",
    "gn:population":0,
    "gn:timezone":"Europe/Warsaw",
    "iso:country":"PL",
    "name:ceb_x_preferred":[
        "Gronowo"
    ],
    "name:deu_x_preferred":[
        "Gronowo"
    ],
    "name:nld_x_preferred":[
        "Gronowo"
    ],
    "name:pol_x_preferred":[
        "Gronowo"
    ],
    "name:ukr_x_preferred":[
        "\u0490\u0440\u043e\u043d\u043e\u0432\u043e"
    ],
    "wof:name":"Gronowo",
    "wof:placetype":"neighbourhood"
},
  "geometry": {"coordinates":[16.57921,51.86757],"type":"Point"}
}