{
  "type": "Feature",
  "properties": {
    "gn:admin1_code":"73.0",
    "gn:admin2_code":"418.0",
    "gn:admin3_code":"41811.0",
    "gn:asciiname":"Bledowo",
    "gn:country_code":"PL",
    "gn:dem":124,
    "gn:feature_class":"P",
    "gn:feature_code":"PPL",
    "gn:name":"B\u0142\u0119dowo",
    "gn:population":0,
    "gn:timezone":"Europe/Warsaw",
    "iso:country":"PL",
    "wof:name":"Bledowo",
    "wof:placetype":"locality"
},
  "geometry": {"coordinates":[19.11253,52.43999],"type":"Point"}
}