{
  "type": "Feature",
  "properties": {
    "gn:admin1_code":"83.0",
    "gn:admin2_code":"2409.0",
    "gn:admin3_code":"240901.0",
    "gn:asciiname":"Poloniaj",
    "gn:country_code":"PL",
    "gn:dem":304,
    "gn:feature_class":"P",
    "gn:feature_code":"PPL",
    "gn:name":"Po\u0142oniaj",
    "gn:population":0,
    "gn:timezone":"Europe/Warsaw",
    "iso:country":"PL",
    "wof:name":"Poloniaj",
    "wof:placetype":"locality"
},
  "geometry": {"coordinates":[19.31667,50.58333],"type":"Point"}
}