{
  "type": "Feature",
  "properties": {
    "gn:admin1_code":"85.0",
    "gn:admin2_code":"2804.0",
    "gn:admin3_code":"280405.0",
    "gn:asciiname":"Zalesie",
    "gn:country_code":"PL",
    "gn:dem":110,
    "gn:feature_class":"P",
    "gn:feature_code":"PPL",
    "gn:name":"Zalesie",
    "gn:population":0,
    "gn:timezone":"Europe/Warsaw",
    "iso:country":"PL",
    "name:ceb_x_preferred":[
        "Zalesie"
    ],
    "name:deu_x_preferred":[
        "Zalesie"
    ],
    "name:fra_x_preferred":[
        "Zalesie"
    ],
    "name:lit_x_preferred":[
        "Zalesiai"
    ],
    "name:nld_x_preferred":[
        "Zalesie"
    ],
    "name:pol_x_preferred":[
        "Zalesie"
    ],
    "name:rus_x_preferred":[
        "\u0417\u0430\u043b\u0435\u0441\u0435"
    ],
    "name:swe_x_preferred":[
        "Zalesie"
    ],
    "name:ukr_x_preferred":[
        "\u0417\u0430\u043b\u0435\u0441\u0435"
    ],
    "wof:name":"Zalesie",
    "wof:placetype":"locality"
},
  "geometry": {"coordinates":[19.61534,54.14933000000001],"type":"Point"}
}