{
  "type": "Feature",
  "properties": {
    "gn:admin1_code":"75.0",
    "gn:admin2_code":"605.0",
    "gn:admin3_code":"60506.0",
    "gn:asciiname":"Kalenne",
    "gn:country_code":"PL",
    "gn:dem":188,
    "gn:feature_class":"P",
    "gn:feature_code":"PPL",
    "gn:name":"Kalenne",
    "gn:population":0,
    "gn:timezone":"Europe/Warsaw",
    "iso:country":"PL",
    "name:fra_x_preferred":[
        "Kalenne"
    ],
    "name:pol_x_preferred":[
        "Kalenne"
    ],
    "name:ukr_x_preferred":[
        "\u041a\u0430\u043b\u0435\u043d\u043d\u0435"
    ],
    "wof:name":"Kalenne",
    "wof:placetype":"locality"
},
  "geometry": {"coordinates":[22.27086,50.67572],"type":"Point"}
}