{
  "type": "Feature",
  "properties": {
    "gn:admin1_code":"84.0",
    "gn:admin2_code":"2605.0",
    "gn:admin3_code":"260503.0",
    "gn:asciiname":"Grabkow",
    "gn:country_code":"PL",
    "gn:dem":214,
    "gn:feature_class":"P",
    "gn:feature_code":"PPL",
    "gn:name":"Grabk\u00f3w",
    "gn:population":0,
    "gn:timezone":"Europe/Warsaw",
    "iso:country":"PL",
    "name:pol_x_preferred":[
        "Grabk\u00f3w"
    ],
    "name:ukr_x_preferred":[
        "\u0490\u0440\u0430\u0431\u043a\u0443\u0432"
    ],
    "wof:name":"Grabkow",
    "wof:placetype":"locality"
},
  "geometry": {"coordinates":[20.26299,51.22262],"type":"Point"}
}