{
  "type": "Feature",
  "properties": {
    "gn:admin1_code":"82.0",
    "gn:admin2_code":"2212.0",
    "gn:admin3_code":"221210.0",
    "gn:asciiname":"Machowinko",
    "gn:cc2":"PL",
    "gn:country_code":"PL",
    "gn:dem":30,
    "gn:feature_class":"P",
    "gn:feature_code":"PPL",
    "gn:name":"Machowinko",
    "gn:population":0,
    "gn:timezone":"Europe/Warsaw",
    "iso:country":"PL",
    "name:deu_x_historical":[
        "Klein Machmin"
    ],
    "name:deu_x_preferred":[
        "Klein Machmin"
    ],
    "name:und_x_variant":[
        "Machowinka",
        "Machowinko"
    ],
    "wof:name":"Machowinko",
    "wof:placetype":"locality"
},
  "geometry": {"coordinates":[17.00992999999999,54.59942],"type":"Point"}
}