{
  "type": "Feature",
  "properties": {
    "gn:admin1_code":"82.0",
    "gn:admin2_code":"2212.0",
    "gn:admin3_code":"221210.0",
    "gn:asciiname":"Machowinko",
    "gn:cc2":"PL",
    "gn:country_code":"PL",
    "gn:dem":30,
    "gn:feature_class":"P",
    "gn:feature_code":"PPL",
    "gn:name":"Machowinko",
    "gn:population":0,
    "gn:timezone":"Europe/Warsaw",
    "iso:country":"PL",
    "name:azb_x_preferred":[
        "\u0645\u0627\u062e\u0648\u0648\u06cc\u0646\u06a9\u0648"
    ],
    "name:ceb_x_preferred":[
        "Machowinko"
    ],
    "name:csb_x_preferred":[
        "Mach\u00f2wink\u00f2"
    ],
    "name:deu_x_historical":[
        "Klein Machmin"
    ],
    "name:deu_x_preferred":[
        "Klein Machmin"
    ],
    "name:deu_x_variant":[
        "Machowinko"
    ],
    "name:fas_x_preferred":[
        "\u0645\u0627\u062e\u0648\u0648\u06cc\u0646\u06a9\u0648"
    ],
    "name:nld_x_preferred":[
        "Machowinko"
    ],
    "name:pol_x_preferred":[
        "Machowinko"
    ],
    "name:ukr_x_preferred":[
        "\u041c\u0430\u0445\u043e\u0432\u0456\u043d\u043a\u043e"
    ],
    "name:und_x_variant":[
        "Machowinka"
    ],
    "name:vie_x_preferred":[
        "Machowinko"
    ],
    "wof:name":"Machowinko",
    "wof:placetype":"locality"
},
  "geometry": {"coordinates":[17.00992999999999,54.59942],"type":"Point"}
}