{
  "type": "Feature",
  "properties": {
    "gn:admin1_code":"75.0",
    "gn:admin2_code":"604.0",
    "gn:admin3_code":"60404.0",
    "gn:asciiname":"Dziekanow",
    "gn:country_code":"PL",
    "gn:dem":187,
    "gn:feature_class":"P",
    "gn:feature_code":"PPL",
    "gn:name":"Dziekan\u00f3w",
    "gn:population":0,
    "gn:timezone":"Europe/Warsaw",
    "iso:country":"PL",
    "name:und_x_variant":[
        "Dziekan\u00f3w"
    ],
    "wof:name":"Dziekanow",
    "wof:placetype":"locality"
},
  "geometry": {"coordinates":[23.90837,50.8324],"type":"Point"}
}