{
  "type": "Feature",
  "properties": {
    "gn:admin1_code":"85.0",
    "gn:admin2_code":"2815.0",
    "gn:admin3_code":"281509.0",
    "gn:asciiname":"Kajkowo",
    "gn:country_code":"PL",
    "gn:dem":113,
    "gn:feature_class":"P",
    "gn:feature_code":"PPL",
    "gn:name":"Kajkowo",
    "gn:population":0,
    "gn:timezone":"Europe/Warsaw",
    "iso:country":"PL",
    "name:ceb_x_preferred":[
        "Kajkowo"
    ],
    "name:fra_x_preferred":[
        "Kajkowo"
    ],
    "name:pol_x_preferred":[
        "Kajkowo"
    ],
    "name:ukr_x_preferred":[
        "\u041a\u0430\u0439\u043a\u043e\u0432\u043e"
    ],
    "name:und_x_variant":[
        "Buchwalde",
        "Buchwa\u0142d"
    ],
    "wof:name":"Kajkowo",
    "wof:placetype":"locality"
},
  "geometry": {"coordinates":[19.97312,53.68563],"type":"Point"}
}