{
  "type": "Feature",
  "properties": {
    "gn:admin1_code":"78.0",
    "gn:admin2_code":"1414.0",
    "gn:admin3_code":"141402.0",
    "gn:asciiname":"Kiscinne",
    "gn:country_code":"PL",
    "gn:dem":73,
    "gn:feature_class":"P",
    "gn:feature_code":"PPL",
    "gn:name":"Ki\u015bcinne",
    "gn:population":0,
    "gn:timezone":"Europe/Warsaw",
    "iso:country":"PL",
    "name:azb_x_preferred":[
        "\u06a9\u06cc\u0634\u0686\u06cc\u0646\u0646\u0647"
    ],
    "name:fas_x_preferred":[
        "\u06a9\u06cc\u0634\u0686\u06cc\u0646\u0646\u0647"
    ],
    "name:fra_x_preferred":[
        "Ki\u015bcinne"
    ],
    "name:nld_x_preferred":[
        "Ki\u015bcinne"
    ],
    "name:pol_x_preferred":[
        "Ki\u015bcinne"
    ],
    "name:ukr_x_preferred":[
        "\u041a\u0456\u0441\u0446\u0438\u043d\u043d\u0435"
    ],
    "wof:name":"Kiscinne",
    "wof:placetype":"locality"
},
  "geometry": {"coordinates":[20.63696,52.32443],"type":"Point"}
}