{
  "type": "Feature",
  "properties": {
    "gn:admin1_code":"74.0",
    "gn:admin2_code":"1015.0",
    "gn:admin3_code":"101508.0",
    "gn:asciiname":"Debowa Gora",
    "gn:country_code":"PL",
    "gn:dem":137,
    "gn:feature_class":"P",
    "gn:feature_code":"PPL",
    "gn:name":"D\u0119bowa G\u00f3ra",
    "gn:population":0,
    "gn:timezone":"Europe/Warsaw",
    "iso:country":"PL",
    "wof:name":"Debowa Gora",
    "wof:placetype":"locality"
},
  "geometry": {"coordinates":[20.12583,51.91754],"type":"Point"}
}