{
  "type": "Feature",
  "properties": {
    "iso:country":"PL",
    "name:eng_x_preferred":[
        "Powstancow Slaskich"
    ],
    "name:pol_x_preferred":[
        "Powsta\u0144c\u00f3w \u015al\u0105skich"
    ],
    "wof:name":"Powstancow Slaskich",
    "wof:placetype":"neighbourhood"
},
  "geometry": {"coordinates":[17.0199845910677,51.09321143181031],"type":"Point"}
}