{
  "type": "Feature",
  "properties": {
    "gn:admin1_code":"82.0",
    "gn:admin2_code":"2204.0",
    "gn:admin3_code":"220408.0",
    "gn:asciiname":"Golebiewko",
    "gn:country_code":"PL",
    "gn:dem":93,
    "gn:feature_class":"P",
    "gn:feature_code":"PPL",
    "gn:name":"Go\u0142\u0119biewko",
    "gn:population":0,
    "gn:timezone":"Europe/Warsaw",
    "iso:country":"PL",
    "name:ceb_x_preferred":[
        "Go\u0142\u0119biewko"
    ],
    "name:pol_x_preferred":[
        "Go\u0142\u0119biewko"
    ],
    "name:ukr_x_preferred":[
        "\u0490\u043e\u043b\u0435\u043c\u0431\u0435\u0432\u043a\u043e"
    ],
    "wof:name":"Golebiewko",
    "wof:placetype":"locality"
},
  "geometry": {"coordinates":[18.5441,54.12333],"type":"Point"}
}