{
  "type": "Feature",
  "properties": {
    "gn:admin1_code":"78.0",
    "gn:admin2_code":"1426.0",
    "gn:admin3_code":"142610.0",
    "gn:asciiname":"Kownaciska",
    "gn:country_code":"PL",
    "gn:dem":142,
    "gn:feature_class":"P",
    "gn:feature_code":"PPL",
    "gn:name":"Kownaciska",
    "gn:population":0,
    "gn:timezone":"Europe/Warsaw",
    "iso:country":"PL",
    "name:azb_x_preferred":[
        "\u06a9\u0648\u0648\u0646\u0627\u0686\u06cc\u0633\u06a9\u0627"
    ],
    "name:ceb_x_preferred":[
        "Kownaciska"
    ],
    "name:fas_x_preferred":[
        "\u06a9\u0648\u0648\u0646\u0627\u0686\u06cc\u0633\u06a9\u0627"
    ],
    "name:fra_x_preferred":[
        "Kownaciska"
    ],
    "name:lit_x_preferred":[
        "Kovnaciska"
    ],
    "name:pol_x_preferred":[
        "Kownaciska"
    ],
    "name:szl_x_preferred":[
        "Kowna\u0107iska"
    ],
    "name:ukr_x_preferred":[
        "\u041a\u043e\u0432\u043d\u0430\u0446\u0438\u0441\u044c\u043a\u0430"
    ],
    "wof:name":"Kownaciska",
    "wof:placetype":"locality"
},
  "geometry": {"coordinates":[22.33237,52.24557],"type":"Point"}
}