{
  "type": "Feature",
  "properties": {
    "gn:admin1_code":"78.0",
    "gn:admin2_code":"1426.0",
    "gn:admin3_code":"142610.0",
    "gn:asciiname":"Kownaciska",
    "gn:country_code":"PL",
    "gn:dem":142,
    "gn:feature_class":"P",
    "gn:feature_code":"PPL",
    "gn:name":"Kownaciska",
    "gn:population":0,
    "gn:timezone":"Europe/Warsaw",
    "iso:country":"PL",
    "wof:name":"Kownaciska",
    "wof:placetype":"locality"
},
  "geometry": {"coordinates":[22.33237,52.24557],"type":"Point"}
}