{
  "type": "Feature",
  "properties": {
    "gn:admin1_code":"78.0",
    "gn:admin2_code":"1437.0",
    "gn:admin3_code":"143703.0",
    "gn:asciiname":"Zielun",
    "gn:cc2":"PL",
    "gn:country_code":"PL",
    "gn:dem":142,
    "gn:feature_class":"P",
    "gn:feature_code":"PPL",
    "gn:name":"Zielu\u0144",
    "gn:population":0,
    "gn:timezone":"Europe/Warsaw",
    "iso:country":"PL",
    "name:azb_x_preferred":[
        "\u0698\u0644\u0648\u0646\u0642"
    ],
    "name:ceb_x_preferred":[
        "Zielu\u0144"
    ],
    "name:fas_x_preferred":[
        "\u0698\u0644\u0648\u0646\u06af"
    ],
    "name:fra_x_preferred":[
        "Zielu\u0144"
    ],
    "name:nld_x_preferred":[
        "Zielu\u0144"
    ],
    "name:pol_x_preferred":[
        "Zielu\u0144"
    ],
    "name:szl_x_preferred":[
        "\u0179yl\u016f\u0144"
    ],
    "name:ukr_x_preferred":[
        "\u0417\u0435\u043b\u044e\u043d\u044c"
    ],
    "name:und_x_variant":[
        "Zielu\u0144 Osada"
    ],
    "wof:name":"Zielun",
    "wof:placetype":"locality"
},
  "geometry": {"coordinates":[19.85229,53.17477],"type":"Point"}
}