{
  "type": "Feature",
  "properties": {
    "gn:admin1_code":"78.0",
    "gn:admin2_code":"1437.0",
    "gn:admin3_code":"143703.0",
    "gn:asciiname":"Zielun",
    "gn:cc2":"PL",
    "gn:country_code":"PL",
    "gn:dem":142,
    "gn:feature_class":"P",
    "gn:feature_code":"PPL",
    "gn:name":"Zielu\u0144",
    "gn:population":0,
    "gn:timezone":"Europe/Warsaw",
    "iso:country":"PL",
    "name:und_x_variant":[
        "Zielu\u0144 Osada",
        "Zielu\u0144"
    ],
    "wof:name":"Zielun",
    "wof:placetype":"locality"
},
  "geometry": {"coordinates":[19.85229,53.17477],"type":"Point"}
}