{
  "type": "Feature",
  "properties": {
    "gn:admin1_code":"78.0",
    "gn:admin2_code":"1425.0",
    "gn:admin3_code":"142505.0",
    "gn:asciiname":"Gorna Wola",
    "gn:country_code":"PL",
    "gn:dem":147,
    "gn:feature_class":"P",
    "gn:feature_code":"PPL",
    "gn:name":"G\u00f3rna Wola",
    "gn:population":0,
    "gn:timezone":"Europe/Warsaw",
    "iso:country":"PL",
    "name:fra_x_preferred":[
        "G\u00f3rna Wola"
    ],
    "name:pol_x_preferred":[
        "G\u00f3rna Wola"
    ],
    "name:ukr_x_preferred":[
        "\u0490\u0443\u0440\u043d\u0430-\u0412\u043e\u043b\u044f"
    ],
    "wof:name":"Gorna Wola",
    "wof:placetype":"locality"
},
  "geometry": {"coordinates":[21.01443,51.50565],"type":"Point"}
}