{
  "type": "Feature",
  "properties": {
    "gn:gn_country":"PL",
    "gn:gn_fcode":"PPLA3",
    "gn:gn_pop":500,
    "gn:population":500,
    "iso:country":"PL",
    "name:azb_x_preferred":[
        "\u067e\u0627\u06a9\u0648\u0633\u0648\u0627\u0648\u06cc\u062a\u0633\u0647"
    ],
    "name:fas_x_preferred":[
        "\u067e\u0627\u06a9\u0648\u0633\u0648\u0627\u0648\u06cc\u062a\u0633\u0647"
    ],
    "name:nld_x_preferred":[
        "Pakos\u0142awice"
    ],
    "name:pol_x_preferred":[
        "Pakos\u0142awice"
    ],
    "name:ukr_x_preferred":[
        "\u041f\u0430\u043a\u043e\u0441\u043b\u0430\u0432\u0456\u0446\u0435"
    ],
    "qs_pg:aaroncc":"PL",
    "qs_pg:gn_country":"PL",
    "qs_pg:gn_fcode":"PPLA3",
    "qs_pg:gn_pop":500,
    "qs_pg:name":"Pakos\u0142awice",
    "qs_pg:name_adm0":"Polska",
    "qs_pg:name_adm1":"Opolskie",
    "qs_pg:photos_9k":1,
    "qs_pg:photos_9r":3,
    "qs_pg:photos_all":87,
    "qs_pg:photos_sr":0,
    "qs_pg:pop_sr":2,
    "qs_pg:qs_pg_placetype":"localadmin",
    "qs_pg:qs_pg_placetype_gp":"LocalAdmin",
    "qs_pg:woe_adm0":23424923,
    "woe:adm0_id":23424923,
    "woe:name_adm0":"Polska",
    "woe:name_adm1":"Opolskie",
    "woe:placetype":"LocalAdmin",
    "wof:name":"Pakos\u0142awice",
    "wof:placetype":"localadmin",
    "wof:population":500
},
  "geometry": {"coordinates":[17.36578,50.54474],"type":"Point"}
}