{
  "type": "Feature",
  "properties": {
    "iso:country":"PL",
    "name:eng_x_preferred":[
        "Ostrow"
    ],
    "name:pol_x_preferred":[
        "Ostr\u00f3w"
    ],
    "wof:name":"Ostrow",
    "wof:placetype":"neighbourhood"
},
  "geometry": {"coordinates":[18.65651456416289,54.36883996723509],"type":"Point"}
}