{
  "type": "Feature",
  "properties": {
    "iso:country":"PL",
    "name:pol_x_preferred":[
        "Jejkowice"
    ],
    "wof:name":"Jejkowice",
    "wof:placetype":"locality"
},
  "geometry": {"coordinates":[18.4721987177961,50.1077132751998],"type":"Point"}
}