{
  "type": "Feature",
  "properties": {
    "gn:admin1_code":"84.0",
    "gn:admin2_code":"2608.0",
    "gn:admin3_code":"260804.0",
    "gn:asciiname":"Chrapkow",
    "gn:country_code":"PL",
    "gn:dem":248,
    "gn:feature_class":"P",
    "gn:feature_code":"PPL",
    "gn:name":"Chrapk\u00f3w",
    "gn:population":0,
    "gn:timezone":"Europe/Warsaw",
    "iso:country":"PL",
    "wof:name":"Chrapkow",
    "wof:placetype":"locality"
},
  "geometry": {"coordinates":[20.66854,50.53874],"type":"Point"}
}