{
  "type": "Feature",
  "properties": {
    "gn:admin1_code":"77.0",
    "gn:admin2_code":"1219.0",
    "gn:admin3_code":"121905.0",
    "gn:asciiname":"Byszyce",
    "gn:country_code":"PL",
    "gn:dem":374,
    "gn:feature_class":"P",
    "gn:feature_code":"PPL",
    "gn:name":"Byszyce",
    "gn:population":0,
    "gn:timezone":"Europe/Warsaw",
    "iso:country":"PL",
    "name:pol_x_preferred":[
        "Byszyce"
    ],
    "name:ukr_x_preferred":[
        "\u0411\u0438\u0448\u0438\u0446\u0435"
    ],
    "wof:name":"Byszyce",
    "wof:placetype":"locality"
},
  "geometry": {"coordinates":[20.01434,49.92669],"type":"Point"}
}