{
  "type": "Feature",
  "properties": {
    "gn:admin1_code":"81.0",
    "gn:admin2_code":"2013.0",
    "gn:admin3_code":"201303.0",
    "gn:asciiname":"Zareby Gory Lesne",
    "gn:cc2":"PL",
    "gn:country_code":"PL",
    "gn:dem":131,
    "gn:feature_class":"P",
    "gn:feature_code":"PPL",
    "gn:name":"Zar\u0119by G\u00f3ry Le\u015bne",
    "gn:population":0,
    "gn:timezone":"Europe/Warsaw",
    "iso:country":"PL",
    "name:und_x_variant":[
        "G\u00f3ry Le\u015bne",
        "Zar\u0119by-G\u00f3ra Le\u015bne",
        "Zar\u0119by G\u00f3ry Le\u015bne"
    ],
    "wof:name":"Zareby Gory Lesne",
    "wof:placetype":"locality"
},
  "geometry": {"coordinates":[22.29341,52.86405],"type":"Point"}
}