{
  "type": "Feature",
  "properties": {
    "gn:admin1_code":"81.0",
    "gn:admin2_code":"2013.0",
    "gn:admin3_code":"201303.0",
    "gn:asciiname":"Zareby Gory Lesne",
    "gn:cc2":"PL",
    "gn:country_code":"PL",
    "gn:dem":131,
    "gn:feature_class":"P",
    "gn:feature_code":"PPL",
    "gn:name":"Zar\u0119by G\u00f3ry Le\u015bne",
    "gn:population":0,
    "gn:timezone":"Europe/Warsaw",
    "iso:country":"PL",
    "name:fra_x_preferred":[
        "Zar\u0119by-G\u00f3ry Le\u015bne"
    ],
    "name:lit_x_preferred":[
        "Zarembi Guri Le\u0161n\u0117"
    ],
    "name:pol_x_preferred":[
        "Zar\u0119by-G\u00f3ry Le\u015bne"
    ],
    "name:ukr_x_preferred":[
        "\u0417\u0430\u0440\u0435\u043c\u0431\u0438-\u0490\u0443\u0440\u0438-\u041b\u0435\u0441\u044c\u043d\u0435"
    ],
    "name:und_x_variant":[
        "G\u00f3ry Le\u015bne",
        "Zar\u0119by-G\u00f3ra Le\u015bne",
        "Zar\u0119by G\u00f3ry Le\u015bne"
    ],
    "wof:name":"Zareby Gory Lesne",
    "wof:placetype":"locality"
},
  "geometry": {"coordinates":[22.29341,52.86405],"type":"Point"}
}