{
  "type": "Feature",
  "properties": {
    "gn:admin1_code":"75.0",
    "gn:admin2_code":"613.0",
    "gn:admin3_code":"61307.0",
    "gn:asciiname":"Daleczkat",
    "gn:cc2":"PL",
    "gn:country_code":"PL",
    "gn:dem":173,
    "gn:feature_class":"P",
    "gn:feature_code":"PPL",
    "gn:name":"Daleczk\u0105t",
    "gn:population":0,
    "gn:timezone":"Europe/Warsaw",
    "iso:country":"PL",
    "name:und_x_variant":[
        "Daleczkont",
        "Daleczkunt",
        "Daleczk\u0105t"
    ],
    "wof:name":"Daleczkat",
    "wof:placetype":"locality"
},
  "geometry": {"coordinates":[23.06667,51.46667],"type":"Point"}
}