{
  "type": "Feature",
  "properties": {
    "gn:admin1_code":"77.0",
    "gn:admin2_code":"1208.0",
    "gn:admin3_code":"120805.0",
    "gn:asciiname":"Celiny Przeslawskie",
    "gn:country_code":"PL",
    "gn:dem":336,
    "gn:feature_class":"P",
    "gn:feature_code":"PPL",
    "gn:name":"Celiny Przes\u0142awskie",
    "gn:population":0,
    "gn:timezone":"Europe/Warsaw",
    "iso:country":"PL",
    "name:und_x_variant":[
        "Celiny",
        "Celiny Przes\u0142awskie"
    ],
    "wof:name":"Celiny Przeslawskie",
    "wof:placetype":"locality"
},
  "geometry": {"coordinates":[19.98033,50.31667],"type":"Point"}
}