{
  "type": "Feature",
  "properties": {
    "gn:admin1_code":"73.0",
    "gn:admin2_code":"403.0",
    "gn:admin3_code":"40303.0",
    "gn:asciiname":"Linowiec",
    "gn:country_code":"PL",
    "gn:dem":87,
    "gn:feature_class":"P",
    "gn:feature_code":"PPL",
    "gn:name":"Linowiec",
    "gn:population":0,
    "gn:timezone":"Europe/Warsaw",
    "iso:country":"PL",
    "name:pol_x_preferred":[
        "Lin\u00f3wiec"
    ],
    "wof:name":"Linowiec",
    "wof:placetype":"locality"
},
  "geometry": {"coordinates":[18.1091,53.2497],"type":"Point"}
}