{
  "type": "Feature",
  "properties": {
    "gn:admin1_code":"86.0",
    "gn:admin2_code":"3007.0",
    "gn:admin3_code":"300706.0",
    "gn:asciiname":"Pyczek",
    "gn:country_code":"PL",
    "gn:dem":131,
    "gn:feature_class":"P",
    "gn:feature_code":"PPL",
    "gn:name":"Pyczek",
    "gn:population":0,
    "gn:timezone":"Europe/Warsaw",
    "iso:country":"PL",
    "name:pol_x_preferred":[
        "Pyczek"
    ],
    "name:ukr_x_preferred":[
        "\u041f\u0438\u0447\u0435\u043a"
    ],
    "wof:name":"Pyczek",
    "wof:placetype":"locality"
},
  "geometry": {"coordinates":[18.3827,51.87829],"type":"Point"}
}