{
  "type": "Feature",
  "properties": {
    "gn:admin1_code":"85.0",
    "gn:admin2_code":"2814.0",
    "gn:admin3_code":"281407.0",
    "gn:asciiname":"Kajny",
    "gn:country_code":"PL",
    "gn:dem":92,
    "gn:feature_class":"P",
    "gn:feature_code":"PPL",
    "gn:name":"Kajny",
    "gn:population":0,
    "gn:timezone":"Europe/Warsaw",
    "iso:country":"PL",
    "name:pol_x_preferred":[
        "Kajny"
    ],
    "name:ukr_x_preferred":[
        "\u041a\u0430\u0439\u043d\u0438"
    ],
    "name:und_x_variant":[
        "Kainen"
    ],
    "wof:name":"Kajny",
    "wof:placetype":"locality"
},
  "geometry": {"coordinates":[20.37381,53.84961],"type":"Point"}
}