{
  "type": "Feature",
  "properties": {
    "gn:admin1_code":"86.0",
    "gn:admin2_code":"3010.0",
    "gn:admin3_code":"301005.0",
    "gn:asciiname":"Ranna",
    "gn:country_code":"PL",
    "gn:dem":82,
    "gn:feature_class":"P",
    "gn:feature_code":"PPL",
    "gn:name":"Ranna",
    "gn:population":0,
    "gn:timezone":"Europe/Warsaw",
    "iso:country":"PL",
    "name:ceb_x_preferred":[
        "Ranna"
    ],
    "name:deu_x_preferred":[
        "Ranna"
    ],
    "name:pol_x_preferred":[
        "Ranna"
    ],
    "name:swe_x_preferred":[
        "Ranna"
    ],
    "wof:name":"Ranna",
    "wof:placetype":"locality"
},
  "geometry": {"coordinates":[18.40475,52.24972],"type":"Point"}
}