{
  "type": "Feature",
  "properties": {
    "gn:admin1_code":"78.0",
    "gn:admin2_code":"1414.0",
    "gn:admin3_code":"141403.0",
    "gn:asciiname":"Dabrowa",
    "gn:country_code":"PL",
    "gn:dem":69,
    "gn:feature_class":"P",
    "gn:feature_code":"PPL",
    "gn:name":"D\u0105browa",
    "gn:population":0,
    "gn:timezone":"Europe/Warsaw",
    "iso:country":"PL",
    "wof:name":"Dabrowa",
    "wof:placetype":"locality"
},
  "geometry": {"coordinates":[20.58333,52.33333],"type":"Point"}
}