{
  "type": "Feature",
  "properties": {
    "gn:admin1_code":"77.0",
    "gn:admin2_code":"1216.0",
    "gn:admin3_code":"121615.0",
    "gn:asciiname":"Gorny Leg",
    "gn:country_code":"PL",
    "gn:dem":187,
    "gn:feature_class":"P",
    "gn:feature_code":"PPL",
    "gn:name":"G\u00f3rny \u0141\u0119g",
    "gn:population":0,
    "gn:timezone":"Europe/Warsaw",
    "iso:country":"PL",
    "wof:name":"Gorny Leg",
    "wof:placetype":"locality"
},
  "geometry": {"coordinates":[20.92197,50.07401],"type":"Point"}
}