{
  "type": "Feature",
  "properties": {
    "gn:admin1_code":"86.0",
    "gn:admin2_code":"3009.0",
    "gn:admin3_code":"300902.0",
    "gn:asciiname":"Kolonia Lubotyn",
    "gn:country_code":"PL",
    "gn:dem":102,
    "gn:feature_class":"P",
    "gn:feature_code":"PPL",
    "gn:name":"Kolonia Luboty\u0144",
    "gn:population":0,
    "gn:timezone":"Europe/Warsaw",
    "iso:country":"PL",
    "name:und_x_variant":[
        "Kolonia Luboty\u0144",
        "Luboty\u0144"
    ],
    "wof:name":"Kolonia Lubotyn",
    "wof:placetype":"locality"
},
  "geometry": {"coordinates":[18.62659,52.39396],"type":"Point"}
}