{
  "type": "Feature",
  "properties": {
    "gn:admin1_code":"72.0",
    "gn:admin2_code":"209.0",
    "gn:admin3_code":"20902.0",
    "gn:asciiname":"Golocin",
    "gn:country_code":"PL",
    "gn:dem":159,
    "gn:feature_class":"P",
    "gn:feature_code":"PPL",
    "gn:name":"Go\u0142ocin",
    "gn:population":0,
    "gn:timezone":"Europe/Warsaw",
    "iso:country":"PL",
    "name:pol_x_preferred":[
        "Go\u0142ocin"
    ],
    "wof:name":"Golocin",
    "wof:placetype":"locality"
},
  "geometry": {"coordinates":[15.96854,51.23619],"type":"Point"}
}