{
  "type": "Feature",
  "properties": {
    "gn:admin1_code":"85.0",
    "gn:admin2_code":"2816.0",
    "gn:admin3_code":"281603.0",
    "gn:asciiname":"Lysonie",
    "gn:country_code":"PL",
    "gn:dem":122,
    "gn:feature_class":"P",
    "gn:feature_code":"PPL",
    "gn:name":"\u0141ysonie",
    "gn:population":0,
    "gn:timezone":"Europe/Warsaw",
    "iso:country":"PL",
    "name:deu_x_preferred":[
        "\u0141ysonie"
    ],
    "name:fra_x_preferred":[
        "\u0141ysonie"
    ],
    "name:pol_x_preferred":[
        "\u0141ysonie"
    ],
    "name:ukr_x_preferred":[
        "\u041b\u0438\u0441\u043e\u043d\u0435"
    ],
    "name:und_x_variant":[
        "Lissuhnen",
        "Lyssuhnen",
        "\u0141ysonie"
    ],
    "wof:name":"Lysonie",
    "wof:placetype":"locality"
},
  "geometry": {"coordinates":[21.90039,53.73141],"type":"Point"}
}