{
  "type": "Feature",
  "properties": {
    "gn:admin1_code":"72.0",
    "gn:admin2_code":"219.0",
    "gn:admin3_code":"21908.0",
    "gn:asciiname":"Kalno",
    "gn:country_code":"PL",
    "gn:dem":200,
    "gn:feature_class":"P",
    "gn:feature_code":"PPL",
    "gn:name":"Kalno",
    "gn:population":0,
    "gn:timezone":"Europe/Warsaw",
    "iso:country":"PL",
    "name:ceb_x_preferred":[
        "Kalno"
    ],
    "name:pol_x_preferred":[
        "Kalno"
    ],
    "name:ukr_x_preferred":[
        "\u041a\u0430\u043b\u044c\u043d\u043e"
    ],
    "wof:name":"Kalno",
    "wof:placetype":"locality"
},
  "geometry": {"coordinates":[16.52842,50.92803],"type":"Point"}
}