{
  "type": "Feature",
  "properties": {
    "gn:country":"PL",
    "gn:fcode":"PPL",
    "gn:population":0,
    "iso:country":"PL",
    "name:ast_x_preferred":[
        "Tartaczysko"
    ],
    "name:eng_x_preferred":[
        "Tartaczysko"
    ],
    "name:fra_x_preferred":[
        "Tartaczysko"
    ],
    "name:lit_x_preferred":[
        "Tarta\u010diskas"
    ],
    "name:pol_x_preferred":[
        "Tartaczysko"
    ],
    "name:ukr_x_preferred":[
        "\u0422\u0430\u0440\u0442\u0430\u0447\u0438\u0441\u044c\u043a\u043e"
    ],
    "qs_pg:aaroncc":"PL",
    "qs_pg:gn_country":"PL",
    "qs_pg:gn_fcode":"PPL",
    "qs_pg:gn_pop":0,
    "qs_pg:name":"Tartaczysko",
    "qs_pg:name_adm0":"Polska",
    "qs_pg:name_adm1":"Podlaskie",
    "qs_pg:photos":26,
    "qs_pg:photos_1k":5,
    "qs_pg:photos_9k":1,
    "qs_pg:photos_9r":2,
    "qs_pg:photos_all":26,
    "qs_pg:photos_sr":2,
    "qs_pg:pop_sr":0,
    "qs_pg:qs_pg_placetype":"locality",
    "qs_pg:qs_pg_placetype_gp":"Town",
    "qs_pg:woe_adm0":23424923,
    "woe:adm0_id":23424923,
    "woe:name_adm0":"Polska",
    "woe:name_adm1":"Podlaskie",
    "woe:placetype":"Town",
    "wof:name":"Tartaczysko",
    "wof:placetype":"locality"
},
  "geometry": {"coordinates":[23.27798,53.9939],"type":"Point"}
}