{
  "type": "Feature",
  "properties": {
    "gn:admin1_code":"74.0",
    "gn:admin2_code":"1004.0",
    "gn:admin3_code":"100405.0",
    "gn:asciiname":"Wichrow",
    "gn:country_code":"PL",
    "gn:dem":100,
    "gn:feature_class":"P",
    "gn:feature_code":"PPL",
    "gn:name":"Wichr\u00f3w",
    "gn:population":0,
    "gn:timezone":"Europe/Warsaw",
    "iso:country":"PL",
    "name:fra_x_preferred":[
        "Wichr\u00f3w"
    ],
    "name:pol_x_preferred":[
        "Wichr\u00f3w"
    ],
    "name:ukr_x_preferred":[
        "\u0412\u0456\u0445\u0440\u0443\u0432"
    ],
    "wof:name":"Wichrow",
    "wof:placetype":"locality"
},
  "geometry": {"coordinates":[19.12857,52.04373],"type":"Point"}
}