{
  "type": "Feature",
  "properties": {
    "gn:admin1_code":"82.0",
    "gn:admin2_code":"2205.0",
    "gn:admin3_code":"220505.0",
    "gn:asciiname":"Wyczechowo",
    "gn:country_code":"PL",
    "gn:dem":194,
    "gn:feature_class":"P",
    "gn:feature_code":"PPL",
    "gn:name":"Wyczechowo",
    "gn:population":0,
    "gn:timezone":"Europe/Warsaw",
    "iso:country":"PL",
    "name:ceb_x_preferred":[
        "Wyczechowo"
    ],
    "name:csb_x_preferred":[
        "Wiczech\u00f2w\u00f2"
    ],
    "name:pol_x_preferred":[
        "Wyczechowo"
    ],
    "name:ukr_x_preferred":[
        "\u0412\u0438\u0447\u0435\u0445\u043e\u0432\u043e"
    ],
    "wof:name":"Wyczechowo",
    "wof:placetype":"locality"
},
  "geometry": {"coordinates":[18.24655,54.27848],"type":"Point"}
}