{
  "type": "Feature",
  "properties": {
    "gn:admin1_code":"82.0",
    "gn:admin2_code":"2205.0",
    "gn:admin3_code":"220505.0",
    "gn:asciiname":"Wyczechowo",
    "gn:country_code":"PL",
    "gn:dem":194,
    "gn:feature_class":"P",
    "gn:feature_code":"PPL",
    "gn:name":"Wyczechowo",
    "gn:population":0,
    "gn:timezone":"Europe/Warsaw",
    "iso:country":"PL",
    "wof:name":"Wyczechowo",
    "wof:placetype":"locality"
},
  "geometry": {"coordinates":[18.24655,54.27848],"type":"Point"}
}