{
  "type": "Feature",
  "properties": {
    "gn:admin1_code":"75.0",
    "gn:admin2_code":"607.0",
    "gn:admin3_code":"60709.0",
    "gn:asciiname":"Pulankowice",
    "gn:country_code":"PL",
    "gn:dem":224,
    "gn:feature_class":"P",
    "gn:feature_code":"PPL",
    "gn:name":"Pu\u0142ankowice",
    "gn:population":0,
    "gn:timezone":"Europe/Warsaw",
    "iso:country":"PL",
    "name:fra_x_preferred":[
        "Pu\u0142ankowice"
    ],
    "name:pol_x_preferred":[
        "Pu\u0142ankowice"
    ],
    "name:ukr_x_preferred":[
        "\u041f\u0443\u043b\u0430\u043d\u043a\u043e\u0432\u0456\u0446\u0435"
    ],
    "wof:name":"Pulankowice",
    "wof:placetype":"locality"
},
  "geometry": {"coordinates":[22.30972,50.9582],"type":"Point"}
}