{
  "type": "Feature",
  "properties": {
    "gn:admin1_code":"86.0",
    "gn:admin2_code":"3010.0",
    "gn:admin3_code":"301004.0",
    "gn:asciiname":"Alinowo",
    "gn:country_code":"PL",
    "gn:dem":103,
    "gn:feature_class":"P",
    "gn:feature_code":"PPL",
    "gn:name":"Alinowo",
    "gn:population":0,
    "gn:timezone":"Europe/Warsaw",
    "iso:country":"PL",
    "name:azb_x_preferred":[
        "\u0627\u0644\u06cc\u0646\u0627\u0648"
    ],
    "name:fas_x_preferred":[
        "\u0627\u0644\u06cc\u0646\u0627\u0648"
    ],
    "name:fra_x_preferred":[
        "Alinowo"
    ],
    "name:nld_x_preferred":[
        "Alinowo"
    ],
    "name:pol_x_preferred":[
        "Alinowo"
    ],
    "name:srp_x_preferred":[
        "\u0410\u043b\u0438\u043d\u043e\u0432\u043e"
    ],
    "name:ukr_x_preferred":[
        "\u0410\u043b\u0456\u043d\u043e\u0432\u043e"
    ],
    "wof:name":"Alinowo",
    "wof:placetype":"locality"
},
  "geometry": {"coordinates":[18.1421,52.40305],"type":"Point"}
}