{
  "type": "Feature",
  "properties": {
    "gn:admin1_code":"86.0",
    "gn:admin2_code":"3010.0",
    "gn:admin3_code":"301002.0",
    "gn:asciiname":"Biala-Kolonia",
    "gn:country_code":"PL",
    "gn:dem":93,
    "gn:feature_class":"P",
    "gn:feature_code":"PPL",
    "gn:name":"Bia\u0142a-Kolonia",
    "gn:population":0,
    "gn:timezone":"Europe/Warsaw",
    "iso:country":"PL",
    "wof:name":"Biala-Kolonia",
    "wof:placetype":"locality"
},
  "geometry": {"coordinates":[18.00359,52.07386],"type":"Point"}
}