{
  "type": "Feature",
  "properties": {
    "gn:admin1_code":"86.0",
    "gn:admin2_code":"3010.0",
    "gn:admin3_code":"301002.0",
    "gn:asciiname":"Biala-Kolonia",
    "gn:country_code":"PL",
    "gn:dem":93,
    "gn:feature_class":"P",
    "gn:feature_code":"PPL",
    "gn:name":"Bia\u0142a-Kolonia",
    "gn:population":0,
    "gn:timezone":"Europe/Warsaw",
    "iso:country":"PL",
    "name:ceb_x_preferred":[
        "Bia\u0142a-Kolonia"
    ],
    "name:fra_x_preferred":[
        "Bia\u0142a Kolonia"
    ],
    "name:pol_x_preferred":[
        "Bia\u0142a Kolonia"
    ],
    "name:ukr_x_preferred":[
        "\u0411\u0456\u043b\u0430 \u041a\u043e\u043b\u044c\u043e\u043d\u0456\u044f"
    ],
    "wof:name":"Biala-Kolonia",
    "wof:placetype":"locality"
},
  "geometry": {"coordinates":[18.00359,52.07386],"type":"Point"}
}