{
  "type": "Feature",
  "properties": {
    "gn:admin1_code":"73.0",
    "gn:admin2_code":"403.0",
    "gn:admin3_code":"40303.0",
    "gn:asciiname":"Kotomierz",
    "gn:country_code":"PL",
    "gn:dem":90,
    "gn:feature_class":"P",
    "gn:feature_code":"PPL",
    "gn:name":"Kotomierz",
    "gn:population":0,
    "gn:timezone":"Europe/Warsaw",
    "iso:country":"PL",
    "name:ceb_x_preferred":[
        "Kotomierz"
    ],
    "name:eng_x_preferred":[
        "Kotomierz"
    ],
    "name:nld_x_preferred":[
        "Kotomierz"
    ],
    "name:pol_x_preferred":[
        "Kotomierz"
    ],
    "name:rus_x_preferred":[
        "\u041a\u043e\u0442\u043e\u043c\u0435\u0436"
    ],
    "name:ukr_x_preferred":[
        "\u041a\u043e\u0442\u043e\u043c\u0435\u0436"
    ],
    "wof:name":"Kotomierz",
    "wof:placetype":"locality"
},
  "geometry": {"coordinates":[18.12351,53.28477],"type":"Point"}
}