{
  "type": "Feature",
  "properties": {
    "iso:country":"PL",
    "qs_pg:aaroncc":"PL",
    "qs_pg:name":"Stare Dolistowo",
    "qs_pg:name_adm0":"Polska",
    "qs_pg:name_adm1":"Podlaskie",
    "qs_pg:photos":6,
    "qs_pg:photos_1k":1,
    "qs_pg:photos_9k":1,
    "qs_pg:photos_9r":1,
    "qs_pg:photos_all":6,
    "qs_pg:photos_sr":1,
    "qs_pg:pop_sr":0,
    "qs_pg:qs_pg_placetype":"locality",
    "qs_pg:qs_pg_placetype_gp":"Town",
    "qs_pg:woe_adm0":23424923,
    "woe:adm0_id":23424923,
    "woe:name_adm0":"Polska",
    "woe:name_adm1":"Podlaskie",
    "woe:placetype":"Town",
    "wof:name":"Stare Dolistowo",
    "wof:placetype":"locality"
},
  "geometry": {"coordinates":[22.89849,53.55595],"type":"Point"}
}