{
  "type": "Feature",
  "properties": {
    "gn:country":"PL",
    "gn:fcode":"PPL",
    "gn:population":1300,
    "iso:country":"PL",
    "name:ast_x_preferred":[
        "Kamienica"
    ],
    "name:ceb_x_preferred":[
        "Kamienica"
    ],
    "name:deu_x_preferred":[
        "Kamienica"
    ],
    "name:eng_x_preferred":[
        "Kamienica"
    ],
    "name:fra_x_preferred":[
        "Kamienica"
    ],
    "name:nan_x_preferred":[
        "Kamienica"
    ],
    "name:pol_x_preferred":[
        "Kamienica"
    ],
    "name:ukr_x_preferred":[
        "\u041a\u0430\u043c\u0435\u043d\u0438\u0446\u044f"
    ],
    "qs_pg:aaroncc":"PL",
    "qs_pg:gn_country":"PL",
    "qs_pg:gn_fcode":"PPL",
    "qs_pg:gn_pop":1300,
    "qs_pg:name":"Kameni\u010dka",
    "qs_pg:name_adm0":"\u010cesk\u00e1 republika",
    "qs_pg:name_adm1":"Olomouck\u00fd kraj",
    "qs_pg:photos_9k":1,
    "qs_pg:photos_9r":1,
    "qs_pg:photos_all":1,
    "qs_pg:photos_sr":0,
    "qs_pg:pop_sr":3,
    "qs_pg:qs_pg_placetype":"locality",
    "qs_pg:qs_pg_placetype_gp":"Town",
    "qs_pg:woe_adm0":23424810,
    "woe:adm0_id":23424810,
    "woe:name_adm0":"\u010cesk\u00e1 republika",
    "woe:name_adm1":"Olomouck\u00fd kraj",
    "woe:placetype":"Town",
    "wof:name":"Kameni\u010dka",
    "wof:placetype":"locality",
    "wof:population":1300
},
  "geometry": {"coordinates":[16.95396,50.45007],"type":"Point"}
}