{
  "type": "Feature",
  "properties": {
    "gn:admin1_code":"74.0",
    "gn:admin2_code":"1012.0",
    "gn:admin3_code":"101214.0",
    "gn:asciiname":"Silnica Wielka",
    "gn:country_code":"PL",
    "gn:dem":221,
    "gn:feature_class":"P",
    "gn:feature_code":"PPL",
    "gn:name":"Silnica Wielka",
    "gn:population":0,
    "gn:timezone":"Europe/Warsaw",
    "iso:country":"PL",
    "name:und_x_variant":[
        "Silnica",
        "Silnica Wielka"
    ],
    "wof:name":"Silnica Wielka",
    "wof:placetype":"locality"
},
  "geometry": {"coordinates":[19.68838,50.93078],"type":"Point"}
}