{
  "type": "Feature",
  "properties": {
    "gn:admin1_code":"72.0",
    "gn:admin2_code":"208.0",
    "gn:admin3_code":"20811.0",
    "gn:asciiname":"Sakobca",
    "gn:country_code":"PL",
    "gn:dem":511,
    "gn:feature_class":"P",
    "gn:feature_code":"PPL",
    "gn:name":"Sakobca",
    "gn:population":0,
    "gn:timezone":"Europe/Warsaw",
    "iso:country":"PL",
    "wof:name":"Sakobca",
    "wof:placetype":"locality"
},
  "geometry": {"coordinates":[16.46586,50.59242],"type":"Point"}
}