{
  "type": "Feature",
  "properties": {
    "gn:admin1_code":"84.0",
    "gn:admin2_code":"2610.0",
    "gn:admin3_code":"261001.0",
    "gn:asciiname":"Lyzwy",
    "gn:country_code":"PL",
    "gn:dem":236,
    "gn:feature_class":"P",
    "gn:feature_code":"PPL",
    "gn:name":"\u0141y\u017cwy",
    "gn:population":0,
    "gn:timezone":"Europe/Warsaw",
    "iso:country":"PL",
    "name:und_x_variant":[
        "\u0141y\u017cwy Us\u0142ow",
        "\u0141y\u017cwy"
    ],
    "wof:name":"Lyzwy",
    "wof:placetype":"locality"
},
  "geometry": {"coordinates":[20.93029,51.11639],"type":"Point"}
}