{
  "type": "Feature",
  "properties": {
    "gn:admin1_code":"77.0",
    "gn:admin2_code":"1201.0",
    "gn:admin3_code":"120103.0",
    "gn:asciiname":"Wyzyce",
    "gn:country_code":"PL",
    "gn:dem":184,
    "gn:feature_class":"P",
    "gn:feature_code":"PPL",
    "gn:name":"Wy\u017cyce",
    "gn:population":0,
    "gn:timezone":"Europe/Warsaw",
    "iso:country":"PL",
    "name:pol_x_preferred":[
        "Wy\u017cyce"
    ],
    "name:ukr_x_preferred":[
        "\u0412\u0438\u0436\u0438\u0446\u0435"
    ],
    "wof:name":"Wyzyce",
    "wof:placetype":"locality"
},
  "geometry": {"coordinates":[20.48804,50.08512],"type":"Point"}
}