{
  "type": "Feature",
  "properties": {
    "gn:admin1_code":"74.0",
    "gn:admin2_code":"1061.0",
    "gn:admin3_code":"106101.0",
    "gn:asciiname":"Sokolow",
    "gn:country_code":"PL",
    "gn:dem":178,
    "gn:feature_class":"P",
    "gn:feature_code":"PPL",
    "gn:name":"Soko\u0142\u00f3w",
    "gn:population":0,
    "gn:timezone":"Europe/Warsaw",
    "iso:country":"PL",
    "name:deu_x_preferred":[
        "Sokolow"
    ],
    "name:pol_x_preferred":[
        "Soko\u0142\u00f3w"
    ],
    "name:pol_x_variant":[
        "Soko\u0142ow"
    ],
    "wof:name":"Sokolow",
    "wof:placetype":"neighbourhood"
},
  "geometry": {"coordinates":[19.367719,51.828406],"type":"Point"}
}