{
  "type": "Feature",
  "properties": {
    "iso:country":"PL",
    "name:deu_x_preferred":[
        "Sokolow"
    ],
    "name:pol_x_preferred":[
        "Soko\u0142\u00f3w"
    ],
    "name:pol_x_variant":[
        "Soko\u0142ow"
    ],
    "wof:name":"Sokolow",
    "wof:placetype":"neighbourhood"
},
  "geometry": {"coordinates":[19.36771900859302,51.82840588614734],"type":"Point"}
}