{
  "type": "Feature",
  "properties": {
    "gn:admin1_code":"80.0",
    "gn:admin2_code":"1809.0",
    "gn:admin3_code":"180903.0",
    "gn:asciiname":"Podemszczyzna",
    "gn:country_code":"PL",
    "gn:dem":249,
    "gn:feature_class":"P",
    "gn:feature_code":"PPL",
    "gn:name":"Podemszczyzna",
    "gn:population":0,
    "gn:timezone":"Europe/Warsaw",
    "iso:country":"PL",
    "name:pol_x_preferred":[
        "Podemszczyzna"
    ],
    "name:ukr_x_preferred":[
        "\u041f\u043e\u0434\u0435\u043c\u0449\u0438\u043d\u0430"
    ],
    "wof:name":"Podemszczyzna",
    "wof:placetype":"locality"
},
  "geometry": {"coordinates":[23.29444,50.22269],"type":"Point"}
}