{
  "type": "Feature",
  "properties": {
    "gn:admin1_code":"82.0",
    "gn:admin2_code":"2215.0",
    "gn:admin3_code":"221507.0",
    "gn:asciiname":"Kochanowo",
    "gn:country_code":"PL",
    "gn:dem":94,
    "gn:feature_class":"P",
    "gn:feature_code":"PPL",
    "gn:name":"Kochanowo",
    "gn:population":0,
    "gn:timezone":"Europe/Warsaw",
    "iso:country":"PL",
    "name:azb_x_preferred":[
        "\u06a9\u0648\u062e\u0627\u0646\u0648\u0648\u0648"
    ],
    "name:ceb_x_preferred":[
        "Kochanowo"
    ],
    "name:csb_x_preferred":[
        "K\u00f2chanow\u00f2"
    ],
    "name:fas_x_preferred":[
        "\u06a9\u0648\u062e\u0627\u0646\u0648\u0648\u0648"
    ],
    "name:nld_x_preferred":[
        "Kochanowo"
    ],
    "name:pol_x_preferred":[
        "Kochanowo"
    ],
    "name:ukr_x_preferred":[
        "\u041a\u043e\u0445\u0430\u043d\u043e\u0432\u043e"
    ],
    "wof:name":"Kochanowo",
    "wof:placetype":"locality"
},
  "geometry": {"coordinates":[18.10272,54.60588000000001],"type":"Point"}
}