{
  "type": "Feature",
  "properties": {
    "gn:admin1_code":"82.0",
    "gn:admin2_code":"2215.0",
    "gn:admin3_code":"221507.0",
    "gn:asciiname":"Kochanowo",
    "gn:country_code":"PL",
    "gn:dem":94,
    "gn:feature_class":"P",
    "gn:feature_code":"PPL",
    "gn:name":"Kochanowo",
    "gn:population":0,
    "gn:timezone":"Europe/Warsaw",
    "iso:country":"PL",
    "wof:name":"Kochanowo",
    "wof:placetype":"locality"
},
  "geometry": {"coordinates":[18.10272,54.60588000000001],"type":"Point"}
}