{
  "type": "Feature",
  "properties": {
    "gn:admin1_code":"81.0",
    "gn:admin2_code":"2007.0",
    "gn:admin3_code":"200705.0",
    "gn:asciiname":"Niewodowo",
    "gn:country_code":"PL",
    "gn:dem":107,
    "gn:feature_class":"P",
    "gn:feature_code":"PPL",
    "gn:name":"Niewodowo",
    "gn:population":0,
    "gn:timezone":"Europe/Warsaw",
    "iso:country":"PL",
    "wof:name":"Niewodowo",
    "wof:placetype":"locality"
},
  "geometry": {"coordinates":[22.185,53.14317],"type":"Point"}
}