{
  "type": "Feature",
  "properties": {
    "gn:admin1_code":"81.0",
    "gn:admin2_code":"2007.0",
    "gn:admin3_code":"200705.0",
    "gn:asciiname":"Niewodowo",
    "gn:country_code":"PL",
    "gn:dem":107,
    "gn:feature_class":"P",
    "gn:feature_code":"PPL",
    "gn:name":"Niewodowo",
    "gn:population":0,
    "gn:timezone":"Europe/Warsaw",
    "iso:country":"PL",
    "name:lit_x_preferred":[
        "Nevodovas"
    ],
    "name:pol_x_preferred":[
        "Niewodowo"
    ],
    "name:ukr_x_preferred":[
        "\u041d\u0435\u0432\u043e\u0434\u043e\u0432\u043e"
    ],
    "wof:name":"Niewodowo",
    "wof:placetype":"locality"
},
  "geometry": {"coordinates":[22.185,53.14317],"type":"Point"}
}