{
  "type": "Feature",
  "properties": {
    "gn:admin1_code":"82.0",
    "gn:admin2_code":"2206.0",
    "gn:admin3_code":"220608.0",
    "gn:asciiname":"Wygonin",
    "gn:country_code":"PL",
    "gn:dem":128,
    "gn:feature_class":"P",
    "gn:feature_code":"PPL",
    "gn:name":"Wygonin",
    "gn:population":0,
    "gn:timezone":"Europe/Warsaw",
    "iso:country":"PL",
    "name:pol_x_preferred":[
        "Wygonin"
    ],
    "name:ukr_x_preferred":[
        "\u0412\u0438\u0491\u043e\u043d\u0456\u043d"
    ],
    "wof:name":"Wygonin",
    "wof:placetype":"locality"
},
  "geometry": {"coordinates":[18.12895,53.95813],"type":"Point"}
}