{
  "type": "Feature",
  "properties": {
    "gn:admin1_code":"84.0",
    "gn:admin2_code":"2608.0",
    "gn:admin3_code":"260804.0",
    "gn:asciiname":"Zagorzyce",
    "gn:country_code":"PL",
    "gn:dem":202,
    "gn:feature_class":"P",
    "gn:feature_code":"PPL",
    "gn:name":"Zag\u00f3rzyce",
    "gn:population":0,
    "gn:timezone":"Europe/Warsaw",
    "iso:country":"PL",
    "wof:name":"Zagorzyce",
    "wof:placetype":"locality"
},
  "geometry": {"coordinates":[20.48143,50.42722],"type":"Point"}
}