{
  "type": "Feature",
  "properties": {
    "gn:admin1_code":"84.0",
    "gn:admin2_code":"2608.0",
    "gn:admin3_code":"260804.0",
    "gn:asciiname":"Zagorzyce",
    "gn:country_code":"PL",
    "gn:dem":202,
    "gn:feature_class":"P",
    "gn:feature_code":"PPL",
    "gn:name":"Zag\u00f3rzyce",
    "gn:population":0,
    "gn:timezone":"Europe/Warsaw",
    "iso:country":"PL",
    "name:ceb_x_preferred":[
        "Zag\u00f3rzyce"
    ],
    "name:pol_x_preferred":[
        "Zagorzyce"
    ],
    "name:ukr_x_preferred":[
        "\u0417\u0430\u0491\u043e\u0436\u0438\u0446\u0435"
    ],
    "name:urd_x_preferred":[
        "\u0632\u06af\u0648\u0631\u0636\u06cc\u06a9\u06d2"
    ],
    "wof:name":"Zagorzyce",
    "wof:placetype":"locality"
},
  "geometry": {"coordinates":[20.48143,50.42722],"type":"Point"}
}