{
  "type": "Feature",
  "properties": {
    "gn:country":"PL",
    "gn:fcode":"PPL",
    "gn:population":335,
    "iso:country":"PL",
    "name:ast_x_preferred":[
        "Krzesz\u00f3w Dolny"
    ],
    "name:ceb_x_preferred":[
        "Krzesz\u00f3w Dolny"
    ],
    "name:ces_x_preferred":[
        "Krzesz\u00f3w Dolny"
    ],
    "name:che_x_preferred":[
        "\u041a\u0448\u0435\u0448\u0443\u0432-\u0414\u043e\u043b\u044c\u043d\u0438"
    ],
    "name:eng_x_preferred":[
        "Krzesz\u00f3w Dolny"
    ],
    "name:fra_x_preferred":[
        "Krzesz\u00f3w Dolny"
    ],
    "name:nan_x_preferred":[
        "Krzesz\u00f3w Dolny"
    ],
    "name:nld_x_preferred":[
        "Krzesz\u00f3w Dolny"
    ],
    "name:pol_x_preferred":[
        "Krzesz\u00f3w Dolny"
    ],
    "name:tat_x_preferred":[
        "\u041a\u0448\u0435\u0448\u0443\u0432-\u0414\u043e\u043b\u044c\u043d\u0438"
    ],
    "name:ukr_x_preferred":[
        "\u041a\u0448\u0435\u0448\u0443\u0432-\u0414\u043e\u043b\u044c\u043d\u0438"
    ],
    "qs_pg:aaroncc":"PL",
    "qs_pg:gn_country":"PL",
    "qs_pg:gn_fcode":"PPL",
    "qs_pg:gn_pop":335,
    "qs_pg:name":"Krzesz\u00f3w Dolny",
    "qs_pg:name_adm0":"Polska",
    "qs_pg:name_adm1":"Podkarpackie",
    "qs_pg:photos_9r":0,
    "qs_pg:photos_sr":0,
    "qs_pg:pop_sr":2,
    "qs_pg:qs_pg_placetype":"locality",
    "qs_pg:qs_pg_placetype_gp":"Town",
    "qs_pg:woe_adm0":23424923,
    "woe:adm0_id":23424923,
    "woe:name_adm0":"Polska",
    "woe:name_adm1":"Podkarpackie",
    "woe:placetype":"Town",
    "wof:name":"Krzesz\u00f3w Dolny",
    "wof:placetype":"locality",
    "wof:population":335
},
  "geometry": {"coordinates":[22.35898,50.39621],"type":"Point"}
}