{
  "type": "Feature",
  "properties": {
    "gn:admin1_code":"83.0",
    "gn:admin2_code":"2406.0",
    "gn:admin3_code":"240601.0",
    "gn:asciiname":"Smugi",
    "gn:country_code":"PL",
    "gn:dem":234,
    "gn:feature_class":"P",
    "gn:feature_code":"PPL",
    "gn:name":"Smugi",
    "gn:population":0,
    "gn:timezone":"Europe/Warsaw",
    "iso:country":"PL",
    "name:fra_x_preferred":[
        "Smugi"
    ],
    "name:pol_x_preferred":[
        "Smugi"
    ],
    "name:ukr_x_preferred":[
        "\u0421\u043c\u0443\u0491\u0456"
    ],
    "wof:name":"Smugi",
    "wof:placetype":"locality"
},
  "geometry": {"coordinates":[18.97566,50.91179],"type":"Point"}
}