{
  "type": "Feature",
  "properties": {
    "gn:population":1722,
    "iso:country":"PL",
    "name:ast_x_preferred":[
        "Ciasna"
    ],
    "name:azb_x_preferred":[
        "\u0686\u06cc\u0627\u0633\u0646\u0627"
    ],
    "name:ceb_x_preferred":[
        "Ciasna"
    ],
    "name:deu_x_preferred":[
        "Ciasna"
    ],
    "name:eng_x_preferred":[
        "Ciasna"
    ],
    "name:fas_x_preferred":[
        "\u0686\u06cc\u0627\u0633\u0646\u0627"
    ],
    "name:fra_x_preferred":[
        "Ciasna"
    ],
    "name:nld_x_preferred":[
        "Ciasna"
    ],
    "name:pol_x_preferred":[
        "Ciasna"
    ],
    "name:szl_x_preferred":[
        "\u0106asno"
    ],
    "qs:a0":"Rzeczpospolita Polska",
    "qs:a1":"*Slaskie",
    "qs:a1r":"0",
    "qs:a2":"Lubliniecki",
    "qs:adm0":"Rzeczpospolita Polska",
    "qs:la":"Ciasna",
    "qs:la_lc":"*PL2407032",
    "qs:level":"locality",
    "qs:loc":"Ciasna",
    "qs:loc_alt":"Ciasna",
    "qs:pop":0,
    "qs:type":"rural point-in-poly",
    "wd:wordcount":89,
    "wof:name":"Ciasna",
    "wof:placetype":"locality",
    "wof:population":1722
},
  "geometry": {"coordinates":[18.6195253135946,50.780719614856],"type":"Point"}
}