{
  "type": "Feature",
  "properties": {
    "gn:admin1_code":"72.0",
    "gn:admin2_code":"221.0",
    "gn:admin3_code":"22108.0",
    "gn:asciiname":"Sedzimierz",
    "gn:country_code":"PL",
    "gn:dem":426,
    "gn:feature_class":"P",
    "gn:feature_code":"PPL",
    "gn:name":"Sedzimierz",
    "gn:population":0,
    "gn:timezone":"Europe/Warsaw",
    "iso:country":"PL",
    "wof:name":"Sedzimierz",
    "wof:placetype":"locality"
},
  "geometry": {"coordinates":[16.41992999999999,50.71874],"type":"Point"}
}