{
  "type": "Feature",
  "properties": {
    "gn:admin1_code":"78.0",
    "gn:asciiname":"Zaborze",
    "gn:country_code":"PL",
    "gn:dem":176,
    "gn:feature_class":"P",
    "gn:feature_code":"PPL",
    "gn:name":"Zaborze",
    "gn:population":0,
    "gn:timezone":"Europe/Warsaw",
    "iso:country":"PL",
    "name:ceb_x_preferred":[
        "Zaborze"
    ],
    "name:deu_x_preferred":[
        "Zaborze"
    ],
    "name:fra_x_preferred":[
        "Zaborze"
    ],
    "name:pol_x_preferred":[
        "Zaborze"
    ],
    "name:ukr_x_preferred":[
        "\u0417\u0430\u0431\u043e\u0436\u0435"
    ],
    "wof:name":"Zaborze",
    "wof:placetype":"locality"
},
  "geometry": {"coordinates":[20.64507,51.72366],"type":"Point"}
}