{
  "type": "Feature",
  "properties": {
    "gn:admin1_code":"73.0",
    "gn:admin2_code":"407.0",
    "gn:admin3_code":"40709.0",
    "gn:asciiname":"Rucewo",
    "gn:country_code":"PL",
    "gn:dem":78,
    "gn:feature_class":"P",
    "gn:feature_code":"PPL",
    "gn:name":"Rucewo",
    "gn:population":0,
    "gn:timezone":"Europe/Warsaw",
    "iso:country":"PL",
    "name:pol_x_preferred":[
        "Rucewo"
    ],
    "name:ukr_x_preferred":[
        "\u0420\u0443\u0446\u0435\u0432\u043e"
    ],
    "wof:name":"Rucewo",
    "wof:placetype":"locality"
},
  "geometry": {"coordinates":[18.11791,52.90559],"type":"Point"}
}