{
  "type": "Feature",
  "properties": {
    "gn:admin1_code":"82.0",
    "gn:admin2_code":"2212.0",
    "gn:admin3_code":"221202.0",
    "gn:asciiname":"Strzyzyno",
    "gn:cc2":"PL",
    "gn:country_code":"PL",
    "gn:dem":75,
    "gn:feature_class":"P",
    "gn:feature_code":"PPL",
    "gn:name":"Strzy\u017cyno",
    "gn:population":0,
    "gn:timezone":"Europe/Warsaw",
    "iso:country":"PL",
    "name:und_x_variant":[
        "Strzy\u017cyno S\u0142upskie",
        "Strze\u017cewo",
        "Stresow",
        "Strzy\u017cyno"
    ],
    "wof:name":"Strzyzyno",
    "wof:placetype":"locality"
},
  "geometry": {"coordinates":[17.37076,54.49178000000001],"type":"Point"}
}