{
  "type": "Feature",
  "properties": {
    "gn:admin1_code":"82.0",
    "gn:admin2_code":"2212.0",
    "gn:admin3_code":"221202.0",
    "gn:asciiname":"Strzyzyno",
    "gn:cc2":"PL",
    "gn:country_code":"PL",
    "gn:dem":75,
    "gn:feature_class":"P",
    "gn:feature_code":"PPL",
    "gn:name":"Strzy\u017cyno",
    "gn:population":0,
    "gn:timezone":"Europe/Warsaw",
    "iso:country":"PL",
    "name:azb_x_preferred":[
        "\u0633\u062a\u0698\u0698\u0646\u0648"
    ],
    "name:ceb_x_preferred":[
        "Strzy\u017cyno"
    ],
    "name:csb_x_preferred":[
        "Strz\u00eb\u017c\u00ebno"
    ],
    "name:deu_x_preferred":[
        "Strzy\u017cyno"
    ],
    "name:fas_x_preferred":[
        "\u0633\u062a\u0698\u0698\u0646\u0648"
    ],
    "name:pol_x_preferred":[
        "Strzy\u017cyno"
    ],
    "name:ukr_x_preferred":[
        "\u0421\u0442\u0448\u0438\u0436\u0438\u043d\u043e"
    ],
    "name:und_x_variant":[
        "Strzy\u017cyno S\u0142upskie",
        "Strze\u017cewo",
        "Stresow"
    ],
    "wof:name":"Strzyzyno",
    "wof:placetype":"locality"
},
  "geometry": {"coordinates":[17.37076,54.49178000000001],"type":"Point"}
}