{
  "type": "Feature",
  "properties": {
    "gn:admin1_code":"73.0",
    "gn:admin2_code":"419.0",
    "gn:admin3_code":"41904.0",
    "gn:asciiname":"Jezewo",
    "gn:country_code":"PL",
    "gn:dem":87,
    "gn:feature_class":"P",
    "gn:feature_code":"PPL",
    "gn:name":"Je\u017cewo",
    "gn:population":0,
    "gn:timezone":"Europe/Warsaw",
    "iso:country":"PL",
    "name:und_x_variant":[
        "Je\u017cewo"
    ],
    "wof:name":"Jezewo",
    "wof:placetype":"locality"
},
  "geometry": {"coordinates":[17.98325,52.95251],"type":"Point"}
}