{
  "type": "Feature",
  "properties": {
    "gn:admin1_code":"76.0",
    "gn:admin2_code":"806.0",
    "gn:admin3_code":"80602.0",
    "gn:asciiname":"Goscim",
    "gn:country_code":"PL",
    "gn:dem":28,
    "gn:feature_class":"P",
    "gn:feature_code":"PPL",
    "gn:name":"Go\u015bcim",
    "gn:population":0,
    "gn:timezone":"Europe/Warsaw",
    "iso:country":"PL",
    "name:azb_x_preferred":[
        "\u0642\u0648\u0634\u0686\u06cc\u0645"
    ],
    "name:ceb_x_preferred":[
        "Go\u015bcim"
    ],
    "name:fas_x_preferred":[
        "\u06af\u0648\u0634\u0686\u06cc\u0645"
    ],
    "name:fra_x_preferred":[
        "Go\u015bcim"
    ],
    "name:nld_x_preferred":[
        "Go\u015bcim"
    ],
    "name:pol_x_preferred":[
        "Go\u015bcim"
    ],
    "name:ukr_x_preferred":[
        "\u0490\u043e\u0441\u0446\u0438\u043c"
    ],
    "wof:name":"Goscim",
    "wof:placetype":"locality"
},
  "geometry": {"coordinates":[15.70653,52.76753000000001],"type":"Point"}
}