{
  "type": "Feature",
  "properties": {
    "gn:admin1_code":"76.0",
    "gn:admin2_code":"806.0",
    "gn:admin3_code":"80602.0",
    "gn:asciiname":"Goscim",
    "gn:country_code":"PL",
    "gn:dem":28,
    "gn:feature_class":"P",
    "gn:feature_code":"PPL",
    "gn:name":"Go\u015bcim",
    "gn:population":0,
    "gn:timezone":"Europe/Warsaw",
    "iso:country":"PL",
    "name:und_x_variant":[
        "Go\u015bcim"
    ],
    "wof:name":"Goscim",
    "wof:placetype":"locality"
},
  "geometry": {"coordinates":[15.70653,52.76753000000001],"type":"Point"}
}