{
  "type": "Feature",
  "properties": {
    "gn:admin1_code":"82.0",
    "gn:admin2_code":"2201.0",
    "gn:admin3_code":"220110.0",
    "gn:asciiname":"Zagony",
    "gn:country_code":"PL",
    "gn:dem":172,
    "gn:feature_class":"P",
    "gn:feature_code":"PPL",
    "gn:name":"Zagony",
    "gn:population":0,
    "gn:timezone":"Europe/Warsaw",
    "iso:country":"PL",
    "name:ceb_x_preferred":[
        "Zagony"
    ],
    "name:csb_x_preferred":[
        "Z\u00f4g\u00f3n\u00eb"
    ],
    "name:pol_x_preferred":[
        "Zagony"
    ],
    "name:ukr_x_preferred":[
        "\u0417\u0430\u0491\u043e\u043d\u0438"
    ],
    "name:urd_x_preferred":[
        "\u0632\u06af\u0648\u0646\u0646\u06d2"
    ],
    "wof:name":"Zagony",
    "wof:placetype":"locality"
},
  "geometry": {"coordinates":[17.26945,54.11655],"type":"Point"}
}