{
  "type": "Feature",
  "properties": {
    "gn:admin1_code":"87.0",
    "gn:admin2_code":"3213.0",
    "gn:admin3_code":"321305.0",
    "gn:asciiname":"Karsino",
    "gn:country_code":"PL",
    "gn:dem":24,
    "gn:feature_class":"P",
    "gn:feature_code":"PPL",
    "gn:name":"Karsino",
    "gn:population":0,
    "gn:timezone":"Europe/Warsaw",
    "iso:country":"PL",
    "name:azb_x_preferred":[
        "\u06a9\u0627\u0631\u0634\u0646\u0648"
    ],
    "name:ceb_x_preferred":[
        "Karsino"
    ],
    "name:deu_x_preferred":[
        "Karsino"
    ],
    "name:fas_x_preferred":[
        "\u06a9\u0627\u0631\u0634\u0646\u0648"
    ],
    "name:nld_x_preferred":[
        "Karsino"
    ],
    "name:pol_x_preferred":[
        "Karsino"
    ],
    "name:ukr_x_preferred":[
        "\u041a\u0430\u0440\u0441\u0456\u043d\u043e"
    ],
    "name:vie_x_preferred":[
        "Karsino"
    ],
    "wof:name":"Karsino",
    "wof:placetype":"locality"
},
  "geometry": {"coordinates":[16.56225,54.47024],"type":"Point"}
}