{
  "type": "Feature",
  "properties": {
    "gn:admin1_code":"78.0",
    "gn:admin2_code":"1409.0",
    "gn:admin3_code":"140903.0",
    "gn:asciiname":"Dlugowola",
    "gn:country_code":"PL",
    "gn:dem":178,
    "gn:feature_class":"P",
    "gn:feature_code":"PPL",
    "gn:name":"D\u0142ugowola",
    "gn:population":0,
    "gn:timezone":"Europe/Warsaw",
    "iso:country":"PL",
    "name:und_x_variant":[
        "D\u0142ugowola Pierwsza",
        "D\u0142ugowola"
    ],
    "wof:name":"Dlugowola",
    "wof:placetype":"locality"
},
  "geometry": {"coordinates":[21.61115,51.09667],"type":"Point"}
}