{
  "type": "Feature",
  "properties": {
    "iso:country":"PL",
    "name:azb_x_preferred":[
        "\u0642\u0645\u06cc\u0646\u0627 \u062f\u0648\u0628\u0686\u062a\u0633\u0647"
    ],
    "name:bel_x_preferred":[
        "\u0414\u0430\u0431\u0447\u044b\u0446\u044b"
    ],
    "name:ceb_x_preferred":[
        "Dobczyce"
    ],
    "name:deu_x_preferred":[
        "Gmina Dobczyce"
    ],
    "name:eus_x_preferred":[
        "Dobczyce udalerria"
    ],
    "name:fas_x_preferred":[
        "\u06af\u0645\u06cc\u0646\u0627 \u062f\u0648\u0628\u0686\u062a\u0633\u0647"
    ],
    "name:fra_x_preferred":[
        "Dobczyce"
    ],
    "name:ita_x_preferred":[
        "Dobczyce"
    ],
    "name:nld_x_preferred":[
        "Dobczyce"
    ],
    "name:pol_x_preferred":[
        "Dobczyce"
    ],
    "name:rus_x_preferred":[
        "\u0414\u043e\u0431\u0447\u0438\u0446\u0435"
    ],
    "name:slk_x_preferred":[
        "Gmina Dobczyce"
    ],
    "name:szl_x_preferred":[
        "Gmin Dobczycy"
    ],
    "name:ukr_x_preferred":[
        "\u0413\u043c\u0456\u043d\u0430 \u0414\u043e\u0431\u0447\u0438\u0446\u0435"
    ],
    "name:war_x_preferred":[
        "Gmina Dobczyce"
    ],
    "qs_pg:aaroncc":"PL",
    "qs_pg:name":"Gmina Dobczyce",
    "qs_pg:name_adm0":"Polska",
    "qs_pg:name_adm1":"Ma\u0142opolskie",
    "qs_pg:photos":19,
    "qs_pg:photos_1k":4,
    "qs_pg:photos_9k":1,
    "qs_pg:photos_9r":4,
    "qs_pg:photos_all":291,
    "qs_pg:photos_sr":1,
    "qs_pg:pop_sr":0,
    "qs_pg:qs_pg_placetype":"localadmin",
    "qs_pg:qs_pg_placetype_gp":"LocalAdmin",
    "qs_pg:woe_adm0":23424923,
    "woe:adm0_id":23424923,
    "woe:name_adm0":"Polska",
    "woe:name_adm1":"Ma\u0142opolskie",
    "woe:placetype":"LocalAdmin",
    "wof:name":"Gmina Dobczyce",
    "wof:placetype":"localadmin"
},
  "geometry": {"coordinates":[20.117425,49.880145],"type":"Point"}
}