{
  "type": "Feature",
  "properties": {
    "gn:admin1_code":"72.0",
    "gn:admin2_code":"205.0",
    "gn:admin3_code":"20502.0",
    "gn:asciiname":"Jezow",
    "gn:country_code":"PL",
    "gn:dem":446,
    "gn:feature_class":"P",
    "gn:feature_code":"PPL",
    "gn:name":"Je\u017c\u00f3w",
    "gn:population":0,
    "gn:timezone":"Europe/Warsaw",
    "iso:country":"PL",
    "name:pol_x_preferred":[
        "Je\u017c\u00f3w"
    ],
    "wof:name":"Jezow",
    "wof:placetype":"locality"
},
  "geometry": {"coordinates":[16.0498,50.9335],"type":"Point"}
}