{
  "type": "Feature",
  "properties": {
    "gn:admin1_code":"81.0",
    "gn:admin2_code":"2010.0",
    "gn:admin3_code":"201004.0",
    "gn:asciiname":"Zery Pilaki",
    "gn:country_code":"PL",
    "gn:dem":145,
    "gn:feature_class":"P",
    "gn:feature_code":"PPL",
    "gn:name":"\u017bery Pilaki",
    "gn:population":0,
    "gn:timezone":"Europe/Warsaw",
    "iso:country":"PL",
    "name:und_x_variant":[
        "\u017bery Pitaki",
        "\u017bery Pilaki"
    ],
    "wof:name":"Zery Pilaki",
    "wof:placetype":"locality"
},
  "geometry": {"coordinates":[22.6665,52.59406],"type":"Point"}
}