{
  "type": "Feature",
  "properties": {
    "gn:admin1_code":"81.0",
    "gn:admin2_code":"2010.0",
    "gn:admin3_code":"201004.0",
    "gn:asciiname":"Zery Pilaki",
    "gn:country_code":"PL",
    "gn:dem":145,
    "gn:feature_class":"P",
    "gn:feature_code":"PPL",
    "gn:name":"\u017bery Pilaki",
    "gn:population":0,
    "gn:timezone":"Europe/Warsaw",
    "iso:country":"PL",
    "name:fra_x_preferred":[
        "\u017bery-Pilaki"
    ],
    "name:lit_x_preferred":[
        "\u017deri Pilakai"
    ],
    "name:pol_x_preferred":[
        "\u017bery-Pilaki"
    ],
    "name:ukr_x_preferred":[
        "\u0416\u0435\u0440\u0438-\u041f\u0456\u043b\u044f\u043a\u0438"
    ],
    "name:und_x_variant":[
        "\u017bery Pitaki",
        "\u017bery Pilaki"
    ],
    "wof:name":"Zery Pilaki",
    "wof:placetype":"locality"
},
  "geometry": {"coordinates":[22.6665,52.59406],"type":"Point"}
}