{
  "type": "Feature",
  "properties": {
    "gn:admin1_code":"73.0",
    "gn:admin2_code":"414.0",
    "gn:admin3_code":"41405.0",
    "gn:asciiname":"Jedrzejewo",
    "gn:country_code":"PL",
    "gn:dem":107,
    "gn:feature_class":"P",
    "gn:feature_code":"PPL",
    "gn:name":"J\u0119drzejewo",
    "gn:population":0,
    "gn:timezone":"Europe/Warsaw",
    "iso:country":"PL",
    "name:pol_x_preferred":[
        "J\u0119drzejewo"
    ],
    "name:ukr_x_preferred":[
        "\u0404\u043d\u0434\u0436\u0435\u0454\u0432\u043e"
    ],
    "wof:name":"Jedrzejewo",
    "wof:placetype":"locality"
},
  "geometry": {"coordinates":[18.19735,53.52002],"type":"Point"}
}