{
  "type": "Feature",
  "properties": {
    "gn:admin1_code":"85.0",
    "gn:admin2_code":"2817.0",
    "gn:admin3_code":"281706.0",
    "gn:asciiname":"Siodmak",
    "gn:country_code":"PL",
    "gn:dem":139,
    "gn:feature_class":"P",
    "gn:feature_code":"PPL",
    "gn:name":"Si\u00f3dmak",
    "gn:population":0,
    "gn:timezone":"Europe/Warsaw",
    "iso:country":"PL",
    "name:deu_x_preferred":[
        "Siodmak"
    ],
    "name:fra_x_preferred":[
        "Siodmak"
    ],
    "name:rus_x_preferred":[
        "\u0421\u0438\u043e\u0434\u043c\u0430\u043a"
    ],
    "name:und_x_variant":[
        "Wiesendorf",
        "Schodmack",
        "Si\u00f3dmak"
    ],
    "wof:name":"Siodmak",
    "wof:placetype":"locality"
},
  "geometry": {"coordinates":[20.97083,53.52721],"type":"Point"}
}