{
  "type": "Feature",
  "properties": {
    "gn:admin1_code":"84.0",
    "gn:admin2_code":"2602.0",
    "gn:admin3_code":"260205.0",
    "gn:asciiname":"Kanice Stare",
    "gn:country_code":"PL",
    "gn:dem":228,
    "gn:feature_class":"P",
    "gn:feature_code":"PPL",
    "gn:name":"Kanice Stare",
    "gn:population":0,
    "gn:timezone":"Europe/Warsaw",
    "iso:country":"PL",
    "name:pol_x_preferred":[
        "Stare Kanice"
    ],
    "name:ukr_x_preferred":[
        "\u0421\u0442\u0430\u0440\u0435 \u041a\u0430\u043d\u0456\u0446\u0435"
    ],
    "wof:name":"Kanice Stare",
    "wof:placetype":"locality"
},
  "geometry": {"coordinates":[20.21667,50.75],"type":"Point"}
}