{
  "type": "Feature",
  "properties": {
    "gn:admin1_code":"83.0",
    "gn:admin2_code":"2401.0",
    "gn:admin3_code":"240101.0",
    "gn:asciiname":"Lagisza",
    "gn:country_code":"PL",
    "gn:dem":267,
    "gn:feature_class":"P",
    "gn:feature_code":"PPL",
    "gn:name":"\u0141agisza",
    "gn:population":0,
    "gn:timezone":"Europe/Warsaw",
    "iso:country":"PL",
    "wof:name":"Lagisza",
    "wof:placetype":"neighbourhood"
},
  "geometry": {"coordinates":[19.1387,50.34776],"type":"Point"}
}