{
  "type": "Feature",
  "properties": {
    "gn:admin1_code":"84.0",
    "gn:asciiname":"Jazdowice",
    "gn:country_code":"PL",
    "gn:dem":226,
    "gn:feature_class":"P",
    "gn:feature_code":"PPL",
    "gn:name":"Jazdowice",
    "gn:population":0,
    "gn:timezone":"Europe/Warsaw",
    "iso:country":"PL",
    "name:azb_x_preferred":[
        "\u06cc\u0627\u0632\u062f\u0648\u0648\u06cc\u062a\u0633\u0647"
    ],
    "name:ceb_x_preferred":[
        "Jazdowice"
    ],
    "name:fas_x_preferred":[
        "\u06cc\u0627\u0632\u062f\u0648\u0648\u06cc\u062a\u0633\u0647"
    ],
    "name:nld_x_preferred":[
        "Jazdowice"
    ],
    "name:pol_x_preferred":[
        "Jazdowice"
    ],
    "name:rus_x_preferred":[
        "\u042f\u0437\u0434\u043e\u0432\u0438\u0446\u0435"
    ],
    "name:ukr_x_preferred":[
        "\u042f\u0437\u0434\u043e\u0432\u0456\u0446\u0435"
    ],
    "wof:name":"Jazdowice",
    "wof:placetype":"locality"
},
  "geometry": {"coordinates":[20.32677,50.36507],"type":"Point"}
}