{
  "type": "Feature",
  "properties": {
    "gn:admin1_code":"78.0",
    "gn:admin2_code":"1419.0",
    "gn:admin3_code":"141912.0",
    "gn:asciiname":"Miroslaw",
    "gn:country_code":"PL",
    "gn:dem":113,
    "gn:feature_class":"P",
    "gn:feature_code":"PPL",
    "gn:name":"Miros\u0142aw",
    "gn:population":0,
    "gn:timezone":"Europe/Warsaw",
    "iso:country":"PL",
    "name:fra_x_preferred":[
        "Miros\u0142aw"
    ],
    "name:pol_x_preferred":[
        "Miros\u0142aw"
    ],
    "name:ukr_x_preferred":[
        "\u041c\u0456\u0440\u043e\u0441\u043b\u0430\u0432"
    ],
    "wof:name":"Miroslaw",
    "wof:placetype":"locality"
},
  "geometry": {"coordinates":[19.80605,52.53648000000001],"type":"Point"}
}