{
  "type": "Feature",
  "properties": {
    "gn:gn_country":"PL",
    "gn:gn_fcode":"PPLA3",
    "gn:gn_pop":15784,
    "gn:population":15784,
    "iso:country":"PL",
    "name:bul_x_preferred":[
        "\u041c\u0438\u043b\u044f\u043d\u043e\u0432\u0435\u043a"
    ],
    "name:eng_x_preferred":[
        "Milan\u00f3wek"
    ],
    "name:lav_x_preferred":[
        "Milanuveka"
    ],
    "name:rus_x_preferred":[
        "\u041c\u0438\u043b\u044f\u043d\u0443\u0432\u0435\u043a"
    ],
    "name:srp_x_preferred":[
        "\u041c\u0438\u043b\u0430\u043d\u043e\u0432\u0435\u043a"
    ],
    "name:ukr_x_preferred":[
        "\u041c\u0456\u043b\u044f\u043d\u0443\u0432\u0435\u043a"
    ],
    "name:zho_x_preferred":[
        "\u7c73\u62c9\u52aa\u97cb\u514b"
    ],
    "qs_pg:aaroncc":"PL",
    "qs_pg:gn_country":"PL",
    "qs_pg:gn_fcode":"PPLA3",
    "qs_pg:gn_pop":15784,
    "qs_pg:name":"Milan\u00f3wek",
    "qs_pg:name_adm0":"Polska",
    "qs_pg:name_adm1":"Mazowieckie",
    "qs_pg:photos":1,
    "qs_pg:photos_1k":1,
    "qs_pg:photos_9k":1,
    "qs_pg:photos_9r":1,
    "qs_pg:photos_all":21,
    "qs_pg:photos_sr":1,
    "qs_pg:pop_sr":6,
    "qs_pg:qs_pg_placetype":"localadmin",
    "qs_pg:qs_pg_placetype_gp":"LocalAdmin",
    "qs_pg:woe_adm0":23424923,
    "woe:adm0_id":23424923,
    "woe:name_adm0":"Polska",
    "woe:name_adm1":"Mazowieckie",
    "woe:placetype":"LocalAdmin",
    "wof:name":"Milan\u00f3wek",
    "wof:placetype":"localadmin",
    "wof:population":15784
},
  "geometry": {"coordinates":[20.67155,52.11879],"type":"Point"}
}