{
  "type": "Feature",
  "properties": {
    "gn:admin1_code":"86.0",
    "gn:admin2_code":"3004.0",
    "gn:admin3_code":"300404.0",
    "gn:asciiname":"Skoraszewice",
    "gn:country_code":"PL",
    "gn:dem":114,
    "gn:feature_class":"P",
    "gn:feature_code":"PPL",
    "gn:name":"Skoraszewice",
    "gn:population":0,
    "gn:timezone":"Europe/Warsaw",
    "iso:country":"PL",
    "name:azb_x_preferred":[
        "\u0633\u06a9\u0648\u0631\u0627\u0634\u0648\u06cc\u062a\u0633\u0647"
    ],
    "name:fas_x_preferred":[
        "\u0633\u06a9\u0648\u0631\u0627\u0634\u0648\u06cc\u062a\u0633\u0647"
    ],
    "name:fra_x_preferred":[
        "Skoraszewice"
    ],
    "name:nld_x_preferred":[
        "Skoraszewice"
    ],
    "name:pol_x_preferred":[
        "Skoraszewice"
    ],
    "name:ukr_x_preferred":[
        "\u0421\u043a\u043e\u0440\u0430\u0448\u0435\u0432\u0456\u0446\u0435"
    ],
    "wof:name":"Skoraszewice",
    "wof:placetype":"locality"
},
  "geometry": {"coordinates":[17.0642,51.73314],"type":"Point"}
}