{
  "type": "Feature",
  "properties": {
    "gn:admin1_code":"72.0",
    "gn:admin2_code":"223.0",
    "gn:admin3_code":"22303.0",
    "gn:asciiname":"Pozarzyce",
    "gn:country_code":"PL",
    "gn:dem":159,
    "gn:feature_class":"P",
    "gn:feature_code":"PPL",
    "gn:name":"Po\u017carzyce",
    "gn:population":0,
    "gn:timezone":"Europe/Warsaw",
    "iso:country":"PL",
    "name:deu_x_preferred":[
        "Po\u017carzyce"
    ],
    "name:pol_x_preferred":[
        "Po\u017carzyce"
    ],
    "name:ukr_x_preferred":[
        "\u041f\u043e\u0436\u0430\u0436\u0438\u0446\u0435"
    ],
    "name:und_x_variant":[
        "Po\u017carzyce"
    ],
    "wof:name":"Pozarzyce",
    "wof:placetype":"locality"
},
  "geometry": {"coordinates":[16.89354,50.81407],"type":"Point"}
}