{
  "type": "Feature",
  "properties": {
    "gn:country":"PL",
    "gn:fcode":"PPL",
    "gn:population":0,
    "iso:country":"PL",
    "name:ast_x_preferred":[
        "\u0141yna"
    ],
    "name:azb_x_preferred":[
        "\u0648\u0646\u0627"
    ],
    "name:ceb_x_preferred":[
        "\u0141yna"
    ],
    "name:deu_x_preferred":[
        "\u0141yna"
    ],
    "name:eng_x_preferred":[
        "\u0141yna"
    ],
    "name:fas_x_preferred":[
        "\u0648\u0646\u0627"
    ],
    "name:fra_x_preferred":[
        "\u0141yna"
    ],
    "name:nld_x_preferred":[
        "\u0141yna"
    ],
    "name:pol_x_preferred":[
        "\u0141yna"
    ],
    "name:rus_x_preferred":[
        "\u041b\u044b\u043d\u0430"
    ],
    "name:ukr_x_preferred":[
        "\u041b\u0438\u043d\u0430"
    ],
    "name:und_x_variant":[
        "Lahna"
    ],
    "qs_pg:aaroncc":"PL",
    "qs_pg:gn_country":"PL",
    "qs_pg:gn_fcode":"PPL",
    "qs_pg:gn_pop":0,
    "qs_pg:name":"\u0141yna",
    "qs_pg:name_adm0":"Polska",
    "qs_pg:name_adm1":"Warminsko-Mazurskie",
    "qs_pg:photos":15,
    "qs_pg:photos_1k":3,
    "qs_pg:photos_9k":1,
    "qs_pg:photos_9r":1,
    "qs_pg:photos_all":15,
    "qs_pg:photos_sr":1,
    "qs_pg:pop_sr":0,
    "qs_pg:qs_pg_placetype":"locality",
    "qs_pg:qs_pg_placetype_gp":"Town",
    "qs_pg:woe_adm0":23424923,
    "woe:adm0_id":23424923,
    "woe:name_adm0":"Polska",
    "woe:name_adm1":"Warminsko-Mazurskie",
    "woe:placetype":"Town",
    "wof:name":"\u0141yna",
    "wof:placetype":"locality"
},
  "geometry": {"coordinates":[20.40669,53.43878],"type":"Point"}
}