{
  "type": "Feature",
  "properties": {
    "gn:admin1_code":"86.0",
    "gn:admin2_code":"3017.0",
    "gn:admin3_code":"301706.0",
    "gn:asciiname":"Szczurawice",
    "gn:country_code":"PL",
    "gn:dem":151,
    "gn:feature_class":"P",
    "gn:feature_code":"PPL",
    "gn:name":"Szczurawice",
    "gn:population":0,
    "gn:timezone":"Europe/Warsaw",
    "iso:country":"PL",
    "name:pol_x_preferred":[
        "Szczurawice"
    ],
    "name:ukr_x_preferred":[
        "\u0429\u0443\u0440\u0430\u0432\u0456\u0446\u0435"
    ],
    "wof:name":"Szczurawice",
    "wof:placetype":"locality"
},
  "geometry": {"coordinates":[17.78566,51.71969],"type":"Point"}
}