{
  "type": "Feature",
  "properties": {
    "gn:admin1_code":"85.0",
    "gn:admin2_code":"2818.0",
    "gn:admin3_code":"281803.0",
    "gn:asciiname":"Jablonskie",
    "gn:country_code":"PL",
    "gn:dem":210,
    "gn:feature_class":"P",
    "gn:feature_code":"PPL",
    "gn:name":"Jab\u0142o\u0144skie",
    "gn:population":0,
    "gn:timezone":"Europe/Warsaw",
    "iso:country":"PL",
    "name:azb_x_preferred":[
        "\u06cc\u0627\u0628\u0648\u0648\u0646\u0642\u0633\u06a9\u06cc\u0647"
    ],
    "name:deu_x_preferred":[
        "Jab\u0142o\u0144skie"
    ],
    "name:fas_x_preferred":[
        "\u06cc\u0627\u0628\u0648\u0648\u0646\u06af\u0633\u06a9\u06cc\u0647"
    ],
    "name:nld_x_preferred":[
        "Jab\u0142o\u0144skie"
    ],
    "name:pol_x_preferred":[
        "Jab\u0142o\u0144skie"
    ],
    "name:ukr_x_preferred":[
        "\u042f\u0431\u043b\u0443\u043d\u044c\u0441\u043a\u0435"
    ],
    "name:und_x_variant":[
        "Urbansdorf",
        "Jablonsken"
    ],
    "name:urd_x_preferred":[
        "\u062c\u0628\u0648\u0648\u0646\u0633\u06a9\u06d2"
    ],
    "wof:name":"Jablonskie",
    "wof:placetype":"locality"
},
  "geometry": {"coordinates":[22.26574,54.26517],"type":"Point"}
}