{
  "type": "Feature",
  "properties": {
    "gn:admin1_code":"85.0",
    "gn:admin2_code":"2818.0",
    "gn:admin3_code":"281803.0",
    "gn:asciiname":"Jablonskie",
    "gn:country_code":"PL",
    "gn:dem":210,
    "gn:feature_class":"P",
    "gn:feature_code":"PPL",
    "gn:name":"Jab\u0142o\u0144skie",
    "gn:population":0,
    "gn:timezone":"Europe/Warsaw",
    "iso:country":"PL",
    "name:und_x_variant":[
        "Urbansdorf",
        "Jablonsken",
        "Jab\u0142o\u0144skie"
    ],
    "wof:name":"Jablonskie",
    "wof:placetype":"locality"
},
  "geometry": {"coordinates":[22.26574,54.26517],"type":"Point"}
}