{
  "type": "Feature",
  "properties": {
    "gn:admin1_code":"75.0",
    "gn:admin2_code":"608.0",
    "gn:admin3_code":"60805.0",
    "gn:asciiname":"Stanislawow Maly",
    "gn:country_code":"PL",
    "gn:dem":160,
    "gn:feature_class":"P",
    "gn:feature_code":"PPL",
    "gn:name":"Stanis\u0142aw\u00f3w Ma\u0142y",
    "gn:population":0,
    "gn:timezone":"Europe/Warsaw",
    "iso:country":"PL",
    "wof:name":"Stanislawow Maly",
    "wof:placetype":"locality"
},
  "geometry": {"coordinates":[22.38333,51.46667],"type":"Point"}
}