{
  "type": "Feature",
  "properties": {
    "gn:admin1_code":"74.0",
    "gn:admin2_code":"1002.0",
    "gn:admin3_code":"100202.0",
    "gn:asciiname":"Waliszew",
    "gn:country_code":"PL",
    "gn:dem":103,
    "gn:feature_class":"P",
    "gn:feature_code":"PPL",
    "gn:name":"Waliszew",
    "gn:population":0,
    "gn:timezone":"Europe/Warsaw",
    "iso:country":"PL",
    "name:fra_x_preferred":[
        "Waliszew"
    ],
    "name:pol_x_preferred":[
        "Waliszew"
    ],
    "name:ukr_x_preferred":[
        "\u0412\u0430\u043b\u0456\u0448\u0435\u0432"
    ],
    "wof:name":"Waliszew",
    "wof:placetype":"locality"
},
  "geometry": {"coordinates":[19.53987,52.16549000000001],"type":"Point"}
}