{
  "type": "Feature",
  "properties": {
    "gn:admin1_code":"86.0",
    "gn:admin2_code":"3025.0",
    "gn:admin3_code":"302505.0",
    "gn:asciiname":"Piglowice",
    "gn:country_code":"PL",
    "gn:dem":79,
    "gn:feature_class":"P",
    "gn:feature_code":"PPL",
    "gn:name":"Pig\u0142owice",
    "gn:population":0,
    "gn:timezone":"Europe/Warsaw",
    "iso:country":"PL",
    "name:ceb_x_preferred":[
        "Pig\u0142owice"
    ],
    "name:fra_x_preferred":[
        "Pig\u0142owice"
    ],
    "name:pol_x_preferred":[
        "Pig\u0142owice"
    ],
    "name:ukr_x_preferred":[
        "\u041f\u0456\u0491\u043b\u043e\u0432\u0456\u0446\u0435"
    ],
    "wof:name":"Piglowice",
    "wof:placetype":"locality"
},
  "geometry": {"coordinates":[17.25382,52.17914],"type":"Point"}
}