{
  "type": "Feature",
  "properties": {
    "gn:admin1_code":"86.0",
    "gn:admin2_code":"3004.0",
    "gn:admin3_code":"300401.0",
    "gn:asciiname":"Grodnica",
    "gn:country_code":"PL",
    "gn:dem":115,
    "gn:feature_class":"P",
    "gn:feature_code":"PPL",
    "gn:name":"Grodnica",
    "gn:population":0,
    "gn:timezone":"Europe/Warsaw",
    "iso:country":"PL",
    "name:fra_x_preferred":[
        "Grodnica"
    ],
    "name:pol_x_preferred":[
        "Grodnica"
    ],
    "name:ukr_x_preferred":[
        "\u0490\u0440\u043e\u0434\u043d\u0438\u0446\u044f"
    ],
    "wof:name":"Grodnica",
    "wof:placetype":"locality"
},
  "geometry": {"coordinates":[17.13276,51.91032],"type":"Point"}
}