{
  "type": "Feature",
  "properties": {
    "gn:admin1_code":"72.0",
    "gn:admin2_code":"212.0",
    "gn:admin3_code":"21204.0",
    "gn:asciiname":"Kamien",
    "gn:country_code":"PL",
    "gn:dem":372,
    "gn:feature_class":"P",
    "gn:feature_code":"PPL",
    "gn:name":"Kamie\u0144",
    "gn:population":0,
    "gn:timezone":"Europe/Warsaw",
    "iso:country":"PL",
    "name:und_x_variant":[
        "Kamie\u0144"
    ],
    "wof:name":"Kamien",
    "wof:placetype":"locality"
},
  "geometry": {"coordinates":[15.37142,50.9541],"type":"Point"}
}