{
  "type": "Feature",
  "properties": {
    "gn:admin1_code":"80.0",
    "gn:admin2_code":"1813.0",
    "gn:admin3_code":"181303.0",
    "gn:asciiname":"Solca",
    "gn:country_code":"PL",
    "gn:dem":293,
    "gn:feature_class":"P",
    "gn:feature_code":"PPL",
    "gn:name":"Solca",
    "gn:population":0,
    "gn:timezone":"Europe/Warsaw",
    "iso:country":"PL",
    "wof:name":"Solca",
    "wof:placetype":"locality"
},
  "geometry": {"coordinates":[22.73829,49.66143],"type":"Point"}
}