{
  "type": "Feature",
  "properties": {
    "gn:admin1_code":"85.0",
    "gn:admin2_code":"2810.0",
    "gn:admin3_code":"281004.0",
    "gn:asciiname":"Lipowo",
    "gn:country_code":"PL",
    "gn:dem":142,
    "gn:feature_class":"P",
    "gn:feature_code":"PPL",
    "gn:name":"Lipowo",
    "gn:population":0,
    "gn:timezone":"Europe/Warsaw",
    "iso:country":"PL",
    "name:und_x_variant":[
        "Lindendorf",
        "Lipowo"
    ],
    "wof:name":"Lipowo",
    "wof:placetype":"locality"
},
  "geometry": {"coordinates":[21.43101,53.77968000000001],"type":"Point"}
}