{
  "type": "Feature",
  "properties": {
    "gn:admin1_code":"78.0",
    "gn:admin2_code":"1416.0",
    "gn:admin3_code":"141611.0",
    "gn:asciiname":"Zlotoria",
    "gn:country_code":"PL",
    "gn:dem":109,
    "gn:feature_class":"P",
    "gn:feature_code":"PPL",
    "gn:name":"Z\u0142otoria",
    "gn:population":0,
    "gn:timezone":"Europe/Warsaw",
    "iso:country":"PL",
    "name:und_x_variant":[
        "Z\u0142otorja",
        "Z\u0142otoria"
    ],
    "wof:name":"Zlotoria",
    "wof:placetype":"locality"
},
  "geometry": {"coordinates":[22.06228,52.74943],"type":"Point"}
}