{
  "type": "Feature",
  "properties": {
    "gn:country":"PL",
    "gn:fcode":"PPL",
    "gn:population":750,
    "iso:country":"PL",
    "name:pol_x_preferred":[
        "Brzezowa"
    ],
    "name:ukr_x_preferred":[
        "\u0411\u0436\u0435\u0437\u043e\u0432\u0430"
    ],
    "qs_pg:aaroncc":"PL",
    "qs_pg:gn_country":"PL",
    "qs_pg:gn_fcode":"PPL",
    "qs_pg:gn_pop":750,
    "qs_pg:name":"Brzezowa",
    "qs_pg:name_adm0":"Polska",
    "qs_pg:name_adm1":"Ma\u0142opolskie",
    "qs_pg:photos_9k":1,
    "qs_pg:photos_9r":1,
    "qs_pg:photos_all":1,
    "qs_pg:photos_sr":0,
    "qs_pg:pop_sr":2,
    "qs_pg:qs_pg_placetype":"locality",
    "qs_pg:qs_pg_placetype_gp":"Town",
    "qs_pg:woe_adm0":23424923,
    "woe:adm0_id":23424923,
    "woe:name_adm0":"Polska",
    "woe:name_adm1":"Ma\u0142opolskie",
    "woe:placetype":"Town",
    "wof:name":"Brzezowa",
    "wof:placetype":"locality",
    "wof:population":750
},
  "geometry": {"coordinates":[20.05623,49.85697],"type":"Point"}
}