{
  "type": "Feature",
  "properties": {
    "gn:admin1_code":"81.0",
    "gn:admin2_code":"2004.0",
    "gn:admin3_code":"200402.0",
    "gn:asciiname":"Losiewo",
    "gn:country_code":"PL",
    "gn:dem":124,
    "gn:feature_class":"P",
    "gn:feature_code":"PPL",
    "gn:name":"\u0141osiewo",
    "gn:population":0,
    "gn:timezone":"Europe/Warsaw",
    "iso:country":"PL",
    "name:fra_x_preferred":[
        "\u0141osewo"
    ],
    "name:lit_x_preferred":[
        "Losevas"
    ],
    "name:pol_x_preferred":[
        "\u0141osewo"
    ],
    "name:ukr_x_preferred":[
        "\u041b\u043e\u0441\u0435\u0432\u043e"
    ],
    "name:und_x_variant":[
        "\u0141osiewo"
    ],
    "wof:name":"Losiewo",
    "wof:placetype":"locality"
},
  "geometry": {"coordinates":[22.46315,53.56535],"type":"Point"}
}