{
  "type": "Feature",
  "properties": {
    "gn:admin1_code":"82.0",
    "gn:admin2_code":"2212.0",
    "gn:admin3_code":"221207.0",
    "gn:asciiname":"Czerwieniec",
    "gn:country_code":"PL",
    "gn:dem":15,
    "gn:feature_class":"P",
    "gn:feature_code":"PPL",
    "gn:name":"Czerwieniec",
    "gn:population":0,
    "gn:timezone":"Europe/Warsaw",
    "iso:country":"PL",
    "name:azb_x_preferred":[
        "\u0686\u0631\u0648\u06cc\u0646\u0642\u062a\u0633"
    ],
    "name:ceb_x_preferred":[
        "Czerwieniec"
    ],
    "name:csb_x_preferred":[
        "Czerwi\u0144c"
    ],
    "name:deu_x_preferred":[
        "Czerwieniec"
    ],
    "name:fas_x_preferred":[
        "\u0686\u0631\u0648\u06cc\u0646\u06af\u062a\u0633"
    ],
    "name:pol_x_preferred":[
        "Czerwieniec"
    ],
    "name:ukr_x_preferred":[
        "\u0427\u0435\u0440\u0432\u0435\u043d\u0435\u0446\u044c"
    ],
    "wof:name":"Czerwieniec",
    "wof:placetype":"locality"
},
  "geometry": {"coordinates":[17.55642000000001,54.51703000000001],"type":"Point"}
}