{
  "type": "Feature",
  "properties": {
    "gn:admin1_code":"85.0",
    "gn:admin2_code":"2808.0",
    "gn:admin3_code":"280802.0",
    "gn:asciiname":"Debiany",
    "gn:country_code":"PL",
    "gn:dem":71,
    "gn:feature_class":"P",
    "gn:feature_code":"PPL",
    "gn:name":"D\u0119biany",
    "gn:population":0,
    "gn:timezone":"Europe/Warsaw",
    "iso:country":"PL",
    "name:und_x_variant":[
        "Dambehnen",
        "D\u0119biany"
    ],
    "wof:name":"Debiany",
    "wof:placetype":"locality"
},
  "geometry": {"coordinates":[21.39834,54.19246999999999],"type":"Point"}
}