{
  "type": "Feature",
  "properties": {
    "gn:admin1_code":"79.0",
    "gn:admin2_code":"1603.0",
    "gn:admin3_code":"160304.0",
    "gn:asciiname":"Gosciecin",
    "gn:country_code":"PL",
    "gn:dem":208,
    "gn:feature_class":"P",
    "gn:feature_code":"PPL",
    "gn:name":"Go\u015bci\u0119cin",
    "gn:population":0,
    "gn:timezone":"Europe/Warsaw",
    "iso:country":"PL",
    "name:azb_x_preferred":[
        "\u0642\u0648\u0634\u0686\u06cc\u0646\u0686\u06cc\u0646"
    ],
    "name:deu_x_preferred":[
        "Go\u015bci\u0119cin"
    ],
    "name:fas_x_preferred":[
        "\u06af\u0648\u0634\u0686\u06cc\u0646\u0686\u06cc\u0646"
    ],
    "name:fra_x_preferred":[
        "Go\u015bci\u0119cin"
    ],
    "name:pol_x_preferred":[
        "Go\u015bci\u0119cin"
    ],
    "name:ukr_x_preferred":[
        "\u0490\u043e\u0441\u044c\u0446\u0435\u043d\u0446\u0438\u043d"
    ],
    "name:und_x_variant":[
        "Kostenthal"
    ],
    "wof:name":"Gosciecin",
    "wof:placetype":"locality"
},
  "geometry": {"coordinates":[18.00356,50.28455],"type":"Point"}
}