{
  "type": "Feature",
  "properties": {
    "gn:admin1_code":"79.0",
    "gn:admin2_code":"1603.0",
    "gn:admin3_code":"160304.0",
    "gn:asciiname":"Gosciecin",
    "gn:country_code":"PL",
    "gn:dem":208,
    "gn:feature_class":"P",
    "gn:feature_code":"PPL",
    "gn:name":"Go\u015bci\u0119cin",
    "gn:population":0,
    "gn:timezone":"Europe/Warsaw",
    "iso:country":"PL",
    "name:und_x_variant":[
        "Kostenthal",
        "Go\u015bci\u0119cin"
    ],
    "wof:name":"Gosciecin",
    "wof:placetype":"locality"
},
  "geometry": {"coordinates":[18.00356,50.28455],"type":"Point"}
}