{
  "type": "Feature",
  "properties": {
    "gn:admin1_code":"86.0",
    "gn:admin2_code":"3023.0",
    "gn:admin3_code":"302307.0",
    "gn:asciiname":"Janowo",
    "gn:country_code":"PL",
    "gn:dem":104,
    "gn:feature_class":"P",
    "gn:feature_code":"PPL",
    "gn:name":"Janowo",
    "gn:population":0,
    "gn:timezone":"Europe/Warsaw",
    "iso:country":"PL",
    "name:fra_x_preferred":[
        "Janowo"
    ],
    "name:pol_x_preferred":[
        "Janowo"
    ],
    "name:ukr_x_preferred":[
        "\u042f\u043d\u043e\u0432\u043e"
    ],
    "name:urd_x_preferred":[
        "\u062c\u0646\u0648\u0648\u0648"
    ],
    "wof:name":"Janowo",
    "wof:placetype":"locality"
},
  "geometry": {"coordinates":[17.81441000000001,52.3656],"type":"Point"}
}