{
  "type": "Feature",
  "properties": {
    "iso:country":"PL",
    "name:bel_x_preferred":[
        "\u0421\u044c\u0440\u044d\u043c"
    ],
    "name:bul_x_preferred":[
        "\u0428\u0440\u0435\u043c"
    ],
    "name:deu_x_preferred":[
        "\u015arem"
    ],
    "name:epo_x_preferred":[
        "\u015arem"
    ],
    "name:fra_x_preferred":[
        "\u015arem"
    ],
    "name:jav_x_preferred":[
        "\u015arem"
    ],
    "name:jpn_x_preferred":[
        "\u30b7\u30ec\u30fc\u30e0"
    ],
    "name:lav_x_preferred":[
        "Srema"
    ],
    "name:lit_x_preferred":[
        "Sremas"
    ],
    "name:msa_x_preferred":[
        "\u015arem"
    ],
    "name:nld_x_preferred":[
        "\u015arem"
    ],
    "name:nor_x_preferred":[
        "\u015arem"
    ],
    "name:pol_x_preferred":[
        "\u015arem"
    ],
    "name:por_x_preferred":[
        "\u015arem"
    ],
    "name:ron_x_preferred":[
        "\u015arem"
    ],
    "name:rus_x_preferred":[
        "\u0421\u044c\u0440\u0435\u043c"
    ],
    "name:slk_x_preferred":[
        "\u015arem"
    ],
    "name:srp_x_preferred":[
        "\u0421\u0440\u0435\u043c"
    ],
    "name:swe_x_preferred":[
        "\u015arem"
    ],
    "name:szl_x_preferred":[
        "\u015arym"
    ],
    "name:ukr_x_preferred":[
        "\u0421\u044c\u0440\u0435\u043c"
    ],
    "name:vie_x_preferred":[
        "\u015arem"
    ],
    "name:war_x_preferred":[
        "\u015arem"
    ],
    "name:zho_x_preferred":[
        "\u5e0c\u96f7\u59c6"
    ],
    "qs_pg:aaroncc":"PL",
    "qs_pg:name":"\u015arem",
    "qs_pg:name_adm0":"Polska",
    "qs_pg:name_adm1":"Wielkopolskie",
    "qs_pg:photos":1,
    "qs_pg:photos_1k":1,
    "qs_pg:photos_9k":1,
    "qs_pg:photos_9r":1,
    "qs_pg:photos_all":1,
    "qs_pg:photos_sr":1,
    "qs_pg:pop_sr":0,
    "qs_pg:qs_pg_placetype":"localadmin",
    "qs_pg:qs_pg_placetype_gp":"LocalAdmin",
    "qs_pg:woe_adm0":23424923,
    "woe:adm0_id":23424923,
    "woe:name_adm0":"Polska",
    "woe:name_adm1":"Wielkopolskie",
    "woe:placetype":"LocalAdmin",
    "wof:name":"\u015arem",
    "wof:placetype":"localadmin"
},
  "geometry": {"coordinates":[17.013416,52.068833],"type":"Point"}
}