{
  "type": "Feature",
  "properties": {
    "gn:gn_country":"PL",
    "gn:gn_fcode":"PPLA3",
    "gn:gn_pop":14880,
    "gn:population":14880,
    "iso:country":"PL",
    "name:bul_x_preferred":[
        "\u0413\u0440\u043e\u0439\u0435\u0446"
    ],
    "name:bul_x_variant":[
        "\u0413\u0440\u0443\u0439\u0435\u0446"
    ],
    "name:ceb_x_preferred":[
        "Gr\u00f3jec"
    ],
    "name:deu_x_preferred":[
        "Gr\u00f3jec"
    ],
    "name:epo_x_preferred":[
        "Gr\u00f3jec"
    ],
    "name:fra_x_preferred":[
        "Gr\u00f3jec"
    ],
    "name:heb_x_preferred":[
        "\u05d2\u05e8\u05d5\u05d9\u05d9\u05e5"
    ],
    "name:isl_x_preferred":[
        "Gr\u00f3jec"
    ],
    "name:ita_x_preferred":[
        "Gr\u00f3jec"
    ],
    "name:jav_x_preferred":[
        "Gr\u00f3jec"
    ],
    "name:lav_x_preferred":[
        "Grujeca"
    ],
    "name:mkd_x_preferred":[
        "\u0413\u0440\u0443\u0458\u0435\u0446"
    ],
    "name:msa_x_preferred":[
        "Gr\u00f3jec"
    ],
    "name:nld_x_preferred":[
        "Gr\u00f3jec"
    ],
    "name:pol_x_preferred":[
        "Gr\u00f3jec"
    ],
    "name:por_x_preferred":[
        "Gr\u00f3jec"
    ],
    "name:ron_x_preferred":[
        "Gr\u00f3jec"
    ],
    "name:rus_x_preferred":[
        "\u0413\u0440\u0443\u0435\u0446"
    ],
    "name:slk_x_preferred":[
        "Gr\u00f3jec"
    ],
    "name:srp_x_preferred":[
        "\u0413\u0440\u043e\u0458\u0435\u0446"
    ],
    "name:swe_x_preferred":[
        "Gr\u00f3jec"
    ],
    "name:szl_x_preferred":[
        "Gr\u016fjec"
    ],
    "name:ukr_x_preferred":[
        "\u0413\u0440\u0443\u0454\u0446\u044c"
    ],
    "name:vie_x_preferred":[
        "Gr\u00f3jec"
    ],
    "name:war_x_preferred":[
        "Gr\u00f3jec"
    ],
    "name:yid_x_preferred":[
        "\u05d2\u05e8\u05d9\u05e6\u05e2"
    ],
    "name:zho_x_preferred":[
        "\u683c\u9b6f\u8036\u8328"
    ],
    "qs_pg:aaroncc":"PL",
    "qs_pg:gn_country":"PL",
    "qs_pg:gn_fcode":"PPLA3",
    "qs_pg:gn_pop":14880,
    "qs_pg:name":"Gr\u00f3jec",
    "qs_pg:name_adm0":"Polska",
    "qs_pg:name_adm1":"Mazowieckie",
    "qs_pg:photos":114,
    "qs_pg:photos_1k":23,
    "qs_pg:photos_9k":1,
    "qs_pg:photos_9r":3,
    "qs_pg:photos_all":114,
    "qs_pg:photos_sr":3,
    "qs_pg:pop_sr":6,
    "qs_pg:qs_pg_placetype":"localadmin",
    "qs_pg:qs_pg_placetype_gp":"LocalAdmin",
    "qs_pg:woe_adm0":23424923,
    "woe:adm0_id":23424923,
    "woe:name_adm0":"Polska",
    "woe:name_adm1":"Mazowieckie",
    "woe:placetype":"LocalAdmin",
    "wof:name":"Gr\u00f3jec",
    "wof:placetype":"localadmin",
    "wof:population":14880
},
  "geometry": {"coordinates":[20.86757,51.86252],"type":"Point"}
}