{
  "type": "Feature",
  "properties": {
    "gn:admin1_code":"79.0",
    "gn:admin2_code":"1608.0",
    "gn:admin3_code":"160806.0",
    "gn:asciiname":"Stary Bugaj",
    "gn:country_code":"PL",
    "gn:dem":234,
    "gn:feature_class":"P",
    "gn:feature_code":"PPL",
    "gn:name":"Stary Bugaj",
    "gn:population":0,
    "gn:timezone":"Europe/Warsaw",
    "iso:country":"PL",
    "name:ceb_x_preferred":[
        "Stary Bugaj"
    ],
    "name:pol_x_preferred":[
        "Stary Bugaj"
    ],
    "wof:name":"Stary Bugaj",
    "wof:placetype":"locality"
},
  "geometry": {"coordinates":[18.61256,50.99507],"type":"Point"}
}