{
  "type": "Feature",
  "properties": {
    "gn:admin1_code":"86.0",
    "gn:admin2_code":"3023.0",
    "gn:admin3_code":"302307.0",
    "gn:asciiname":"Babin Holendry",
    "gn:country_code":"PL",
    "gn:dem":100,
    "gn:feature_class":"P",
    "gn:feature_code":"PPL",
    "gn:name":"Babin Holendry",
    "gn:population":0,
    "gn:timezone":"Europe/Warsaw",
    "iso:country":"PL",
    "wof:name":"Babin Holendry",
    "wof:placetype":"locality"
},
  "geometry": {"coordinates":[17.86667000000001,52.33333],"type":"Point"}
}