{
  "type": "Feature",
  "properties": {
    "iso:country":"PL",
    "name:ceb_x_preferred":[
        "Prusice"
    ],
    "name:ces_x_preferred":[
        "Prusice"
    ],
    "name:deu_x_preferred":[
        "Prusice"
    ],
    "name:epo_x_preferred":[
        "Prusice"
    ],
    "name:ita_x_preferred":[
        "Prusice"
    ],
    "name:jav_x_preferred":[
        "Prusice"
    ],
    "name:lav_x_preferred":[
        "Prusice"
    ],
    "name:msa_x_preferred":[
        "Prusice"
    ],
    "name:nld_x_preferred":[
        "Prusice"
    ],
    "name:pol_x_preferred":[
        "Prusice"
    ],
    "name:por_x_preferred":[
        "Prusice"
    ],
    "name:ron_x_preferred":[
        "Prusice"
    ],
    "name:rus_x_preferred":[
        "\u041f\u0440\u0443\u0441\u0438\u0446\u0435"
    ],
    "name:srp_x_preferred":[
        "\u041f\u0440\u0443\u0441\u0438\u0446\u0435"
    ],
    "name:swe_x_preferred":[
        "Prusice"
    ],
    "name:ukr_x_preferred":[
        "\u041f\u0440\u0443\u0441\u0456\u0446\u0435"
    ],
    "name:vie_x_preferred":[
        "Prusice"
    ],
    "name:zho_x_preferred":[
        "\u666e\u9b6f\u897f\u91c7"
    ],
    "qs_pg:aaroncc":"PL",
    "qs_pg:name":"Prusice",
    "qs_pg:name_adm0":"Polska",
    "qs_pg:name_adm1":"Dolnosl\u0105skie",
    "qs_pg:photos":3,
    "qs_pg:photos_1k":1,
    "qs_pg:photos_9k":1,
    "qs_pg:photos_9r":1,
    "qs_pg:photos_all":3,
    "qs_pg:photos_sr":1,
    "qs_pg:pop_sr":0,
    "qs_pg:qs_pg_placetype":"localadmin",
    "qs_pg:qs_pg_placetype_gp":"LocalAdmin",
    "qs_pg:woe_adm0":23424923,
    "woe:adm0_id":23424923,
    "woe:name_adm0":"Polska",
    "woe:name_adm1":"Dolnosl\u0105skie",
    "woe:placetype":"LocalAdmin",
    "wof:name":"Prusice",
    "wof:placetype":"localadmin"
},
  "geometry": {"coordinates":[16.955509,51.368257],"type":"Point"}
}