{
  "type": "Feature",
  "properties": {
    "gn:admin1_code":"72.0",
    "gn:admin2_code":"219.0",
    "gn:admin3_code":"21907.0",
    "gn:asciiname":"Bystrzyca Dolna",
    "gn:country_code":"PL",
    "gn:dem":246,
    "gn:feature_class":"P",
    "gn:feature_code":"PPL",
    "gn:name":"Bystrzyca Dolna",
    "gn:population":0,
    "gn:timezone":"Europe/Warsaw",
    "iso:country":"PL",
    "wof:name":"Bystrzyca Dolna",
    "wof:placetype":"locality"
},
  "geometry": {"coordinates":[16.47622999999999,50.81109],"type":"Point"}
}