{
  "type": "Feature",
  "properties": {
    "gn:admin1_code":"72.0",
    "gn:admin2_code":"219.0",
    "gn:admin3_code":"21907.0",
    "gn:asciiname":"Bystrzyca Dolna",
    "gn:country_code":"PL",
    "gn:dem":246,
    "gn:feature_class":"P",
    "gn:feature_code":"PPL",
    "gn:name":"Bystrzyca Dolna",
    "gn:population":0,
    "gn:timezone":"Europe/Warsaw",
    "iso:country":"PL",
    "name:deu_x_preferred":[
        "Bystrzyca Dolna"
    ],
    "name:pol_x_preferred":[
        "Bystrzyca Dolna"
    ],
    "name:ukr_x_preferred":[
        "\u0411\u0438\u0441\u0442\u0448\u0438\u0446\u044f-\u0414\u043e\u043b\u044c\u043d\u0430"
    ],
    "wof:name":"Bystrzyca Dolna",
    "wof:placetype":"locality"
},
  "geometry": {"coordinates":[16.47622999999999,50.81109],"type":"Point"}
}