{
  "type": "Feature",
  "properties": {
    "gn:admin1_code":"74.0",
    "gn:admin2_code":"1003.0",
    "gn:admin3_code":"100302.0",
    "gn:asciiname":"Stryje",
    "gn:country_code":"PL",
    "gn:dem":184,
    "gn:feature_class":"P",
    "gn:feature_code":"PPL",
    "gn:name":"Stryje",
    "gn:population":0,
    "gn:timezone":"Europe/Warsaw",
    "iso:country":"PL",
    "wof:name":"Stryje",
    "wof:placetype":"locality"
},
  "geometry": {"coordinates":[19.08333,51.63333],"type":"Point"}
}