{
  "type": "Feature",
  "properties": {
    "gn:admin1_code":"78.0",
    "gn:admin2_code":"1406.0",
    "gn:admin3_code":"140605.0",
    "gn:asciiname":"Skurow",
    "gn:country_code":"PL",
    "gn:dem":145,
    "gn:feature_class":"P",
    "gn:feature_code":"PPL",
    "gn:name":"Skur\u00f3w",
    "gn:population":0,
    "gn:timezone":"Europe/Warsaw",
    "iso:country":"PL",
    "name:fra_x_preferred":[
        "Skur\u00f3w"
    ],
    "name:pol_x_preferred":[
        "Skur\u00f3w"
    ],
    "name:ukr_x_preferred":[
        "\u0421\u043a\u0443\u0440\u0443\u0432"
    ],
    "name:und_x_variant":[
        "Skur\u00f3w"
    ],
    "wof:name":"Skurow",
    "wof:placetype":"locality"
},
  "geometry": {"coordinates":[20.87413,51.82843],"type":"Point"}
}