{
  "type": "Feature",
  "properties": {
    "gn:country":"PL",
    "gn:fcode":"PPL",
    "gn:population":791,
    "iso:country":"PL",
    "name:fra_x_preferred":[
        "Wielgolas"
    ],
    "name:pol_x_preferred":[
        "Wielgolas"
    ],
    "name:ukr_x_preferred":[
        "\u0412\u0435\u043b\u044c\u0491\u043e\u043b\u044f\u0441"
    ],
    "qs_pg:aaroncc":"PL",
    "qs_pg:gn_country":"PL",
    "qs_pg:gn_fcode":"PPL",
    "qs_pg:gn_pop":791,
    "qs_pg:name":"Wielgolas",
    "qs_pg:name_adm0":"Polska",
    "qs_pg:name_adm1":"Mazowieckie",
    "qs_pg:photos_9k":1,
    "qs_pg:photos_9r":1,
    "qs_pg:photos_all":2,
    "qs_pg:photos_sr":0,
    "qs_pg:pop_sr":2,
    "qs_pg:qs_pg_placetype":"locality",
    "qs_pg:qs_pg_placetype_gp":"Town",
    "qs_pg:woe_adm0":23424923,
    "woe:adm0_id":23424923,
    "woe:name_adm0":"Polska",
    "woe:name_adm1":"Mazowieckie",
    "woe:placetype":"Town",
    "wof:name":"Wielgolas",
    "wof:placetype":"locality",
    "wof:population":791
},
  "geometry": {"coordinates":[21.73242,52.0318],"type":"Point"}
}