{
  "type": "Feature",
  "properties": {
    "gn:admin1_code":"82.0",
    "gn:admin2_code":"2205.0",
    "gn:admin3_code":"220502.0",
    "gn:asciiname":"Nowa Huta",
    "gn:country_code":"PL",
    "gn:dem":147,
    "gn:feature_class":"P",
    "gn:feature_code":"PPL",
    "gn:name":"Nowa Huta",
    "gn:population":0,
    "gn:timezone":"Europe/Warsaw",
    "iso:country":"PL",
    "name:bar_x_preferred":[
        "Nowa Huta"
    ],
    "name:ceb_x_preferred":[
        "Nowa Huta"
    ],
    "name:csb_x_preferred":[
        "Now\u00f4 H\u00ebta"
    ],
    "name:deu_x_preferred":[
        "Nowa Huta"
    ],
    "name:pol_x_preferred":[
        "Nowa Huta"
    ],
    "name:ukr_x_preferred":[
        "\u041d\u043e\u0432\u0430 \u0413\u0443\u0442\u0430"
    ],
    "wof:name":"Nowa Huta",
    "wof:placetype":"locality"
},
  "geometry": {"coordinates":[18.02799,54.41667],"type":"Point"}
}