{
  "type": "Feature",
  "properties": {
    "gn:admin1_code":"73.0",
    "gn:admin2_code":"415.0",
    "gn:admin3_code":"41509.0",
    "gn:asciiname":"Czarnowo",
    "gn:country_code":"PL",
    "gn:dem":35,
    "gn:feature_class":"P",
    "gn:feature_code":"PPL",
    "gn:name":"Czarnowo",
    "gn:population":0,
    "gn:timezone":"Europe/Warsaw",
    "iso:country":"PL",
    "wof:name":"Czarnowo",
    "wof:placetype":"locality"
},
  "geometry": {"coordinates":[18.22544,53.10656],"type":"Point"}
}