{
  "type": "Feature",
  "properties": {
    "gn:admin1_code":"72.0",
    "gn:admin2_code":"264.0",
    "gn:admin3_code":"26401.0",
    "gn:asciiname":"Szczepin",
    "gn:country_code":"PL",
    "gn:dem":119,
    "gn:feature_class":"P",
    "gn:feature_code":"PPL",
    "gn:name":"Szczepin",
    "gn:population":0,
    "gn:timezone":"Europe/Warsaw",
    "iso:country":"PL",
    "name:eng_x_preferred":[
        "Szczepin"
    ],
    "name:pol_x_preferred":[
        "Szczepin"
    ],
    "wof:name":"Szczepin",
    "wof:placetype":"neighbourhood"
},
  "geometry": {"coordinates":[17.009122,51.118123],"type":"Point"}
}