{
  "type": "Feature",
  "properties": {
    "iso:country":"PL",
    "name:eng_x_preferred":[
        "Szczepin"
    ],
    "name:pol_x_preferred":[
        "Szczepin"
    ],
    "wof:name":"Szczepin",
    "wof:placetype":"neighbourhood"
},
  "geometry": {"coordinates":[17.00912232805625,51.1181233492275],"type":"Point"}
}