{
  "type": "Feature",
  "properties": {
    "gn:admin1_code":"80.0",
    "gn:asciiname":"Momoty Dolne",
    "gn:country_code":"PL",
    "gn:dem":186,
    "gn:feature_class":"P",
    "gn:feature_code":"PPL",
    "gn:name":"Momoty Dolne",
    "gn:population":0,
    "gn:timezone":"Europe/Warsaw",
    "iso:country":"PL",
    "name:fra_x_preferred":[
        "Momoty Dolne"
    ],
    "name:pol_x_preferred":[
        "Momoty Dolne"
    ],
    "name:ukr_x_preferred":[
        "\u041c\u043e\u043c\u043e\u0442\u0438-\u0414\u043e\u043b\u044c\u043d\u0435"
    ],
    "wof:name":"Momoty Dolne",
    "wof:placetype":"locality"
},
  "geometry": {"coordinates":[22.38813,50.61061],"type":"Point"}
}