{
  "type": "Feature",
  "properties": {
    "gn:admin1_code":"82.0",
    "gn:admin2_code":"2210.0",
    "gn:admin3_code":"221004.0",
    "gn:asciiname":"Rybinka",
    "gn:country_code":"PL",
    "gn:dem":-3,
    "gn:feature_class":"P",
    "gn:feature_code":"PPL",
    "gn:name":"Rybinka",
    "gn:population":0,
    "gn:timezone":"Europe/Warsaw",
    "iso:country":"PL",
    "wof:name":"Rybinka",
    "wof:placetype":"locality"
},
  "geometry": {"coordinates":[19.1605,54.31191999999999],"type":"Point"}
}