{
  "type": "Feature",
  "properties": {
    "gn:admin1_code":"81.0",
    "gn:admin2_code":"2003.0",
    "gn:admin3_code":"200304.0",
    "gn:asciiname":"Starowies",
    "gn:country_code":"PL",
    "gn:dem":148,
    "gn:feature_class":"P",
    "gn:feature_code":"PPL",
    "gn:name":"Starowie\u015b",
    "gn:population":0,
    "gn:timezone":"Europe/Warsaw",
    "iso:country":"PL",
    "name:azb_x_preferred":[
        "\u0633\u062a\u0627\u0631\u0648\u0648\u06cc\u0634"
    ],
    "name:fas_x_preferred":[
        "\u0633\u062a\u0627\u0631\u0648\u0648\u06cc\u0634"
    ],
    "name:fra_x_preferred":[
        "Starowie\u015b"
    ],
    "name:lit_x_preferred":[
        "Starovie\u0161as"
    ],
    "name:pol_x_preferred":[
        "Starowie\u015b"
    ],
    "name:rue_x_preferred":[
        "\u0421\u0442\u0430\u0440\u0435 \u0421\u0435\u043b\u043e"
    ],
    "name:ukr_x_preferred":[
        "\u0421\u0442\u0430\u0440\u043e\u0432\u0435\u0441\u044c"
    ],
    "name:und_x_variant":[
        "Starowie\u015b"
    ],
    "wof:name":"Starowies",
    "wof:placetype":"locality"
},
  "geometry": {"coordinates":[23.07838,52.69049],"type":"Point"}
}