{
  "type": "Feature",
  "properties": {
    "gn:admin1_code":"81.0",
    "gn:admin2_code":"2003.0",
    "gn:admin3_code":"200304.0",
    "gn:asciiname":"Starowies",
    "gn:country_code":"PL",
    "gn:dem":148,
    "gn:feature_class":"P",
    "gn:feature_code":"PPL",
    "gn:name":"Starowie\u015b",
    "gn:population":0,
    "gn:timezone":"Europe/Warsaw",
    "iso:country":"PL",
    "name:und_x_variant":[
        "Starowie\u015b"
    ],
    "wof:name":"Starowies",
    "wof:placetype":"locality"
},
  "geometry": {"coordinates":[23.07838,52.69049],"type":"Point"}
}