{
  "type": "Feature",
  "properties": {
    "gn:population":1400,
    "iso:country":"PL",
    "name:azb_x_preferred":[
        "\u0642\u0645\u06cc\u0646\u0627 \u0642\u0631\u0648\u062c\u062a\u0633"
    ],
    "name:bel_x_preferred":[
        "\u0413\u043c\u0456\u043d\u0430 \u0413\u0440\u043e\u0434\u0437\u0435\u0446"
    ],
    "name:ceb_x_preferred":[
        "Grodziec"
    ],
    "name:deu_x_preferred":[
        "Gmina Grodziec"
    ],
    "name:eng_x_preferred":[
        "Grodziec"
    ],
    "name:eng_x_variant":[
        "Gmina Grodziec"
    ],
    "name:eus_x_preferred":[
        "Grodziec udalerria"
    ],
    "name:fas_x_preferred":[
        "\u06af\u0645\u06cc\u0646\u0627 \u06af\u0631\u0648\u062c\u062a\u0633"
    ],
    "name:fra_x_preferred":[
        "Grodziec"
    ],
    "name:ita_x_preferred":[
        "Grodziec"
    ],
    "name:nan_x_preferred":[
        "Grodziec"
    ],
    "name:nld_x_preferred":[
        "Grodziec"
    ],
    "name:pol_x_preferred":[
        "Grodziec"
    ],
    "name:por_x_preferred":[
        "Comuna de Grodziec"
    ],
    "name:rus_x_preferred":[
        "\u0413\u0440\u043e\u0434\u0437\u0435\u0446"
    ],
    "name:slk_x_preferred":[
        "Gmina Grodziec"
    ],
    "name:ukr_x_preferred":[
        "\u0490\u043c\u0456\u043d\u0430 \u0490\u0440\u043e\u0434\u0437\u0435\u0446\u044c"
    ],
    "name:war_x_preferred":[
        "Gmina Grodziec"
    ],
    "name:zho_min_nan_x_preferred":[
        "Grodziec"
    ],
    "qs:a0":"Rzeczpospolita Polska",
    "qs:a1":"*Wielkopolskie",
    "qs:a1r":"0",
    "qs:a2":"Koninski",
    "qs:adm0":"Rzeczpospolita Polska",
    "qs:la":"Grodziec",
    "qs:la_lc":"*PL3010022",
    "qs:level":"locality",
    "qs:loc":"Grodziec",
    "qs:loc_alt":"Grodziec",
    "qs:pop":0,
    "qs:type":"rural point-in-poly",
    "wd:wordcount":143,
    "wof:name":"Grodziec",
    "wof:placetype":"locality",
    "wof:population":1400
},
  "geometry": {"coordinates":[18.0338553348432,52.0339968441262],"type":"Point"}
}