{
  "type": "Feature",
  "properties": {
    "gn:admin1_code":"83.0",
    "gn:admin2_code":"2467.0",
    "gn:admin3_code":"246701.0",
    "gn:asciiname":"Moszczenica",
    "gn:country_code":"PL",
    "gn:dem":226,
    "gn:elevation":"235.0",
    "gn:feature_class":"P",
    "gn:feature_code":"PPL",
    "gn:name":"Moszczenica",
    "gn:population":0,
    "gn:timezone":"Europe/Warsaw",
    "iso:country":"PL",
    "name:ceb_x_preferred":[
        "Moszczenica"
    ],
    "name:deu_x_preferred":[
        "Moszczenica"
    ],
    "name:fra_x_preferred":[
        "Moszczenica"
    ],
    "name:ita_x_preferred":[
        "Moszczenica"
    ],
    "name:nld_x_preferred":[
        "Moszczenica"
    ],
    "name:pol_x_preferred":[
        "Moszczenica"
    ],
    "name:rus_x_preferred":[
        "\u041c\u043e\u0449\u0435\u043d\u0438\u0446\u0430"
    ],
    "name:ukr_x_preferred":[
        "\u041c\u043e\u0449\u0435\u043d\u0438\u0446\u044f"
    ],
    "wof:name":"Moszczenica",
    "wof:placetype":"locality"
},
  "geometry": {"coordinates":[18.54683,49.94356],"type":"Point"}
}