{
  "type": "Feature",
  "properties": {
    "gn:admin1_code":"83.0",
    "gn:admin2_code":"2405.0",
    "gn:admin3_code":"240508.0",
    "gn:asciiname":"Wisnicze",
    "gn:country_code":"PL",
    "gn:dem":269,
    "gn:feature_class":"P",
    "gn:feature_code":"PPL",
    "gn:name":"Wi\u015bnicze",
    "gn:population":0,
    "gn:timezone":"Europe/Warsaw",
    "iso:country":"PL",
    "name:ceb_x_preferred":[
        "Wi\u015bnicze"
    ],
    "name:deu_x_preferred":[
        "Wi\u015bnicze"
    ],
    "name:pol_x_preferred":[
        "Wi\u015bnicze"
    ],
    "name:ukr_x_preferred":[
        "\u0412\u0456\u0441\u043d\u0456\u0447\u0435"
    ],
    "wof:name":"Wisnicze",
    "wof:placetype":"locality"
},
  "geometry": {"coordinates":[18.56123,50.49476],"type":"Point"}
}