{
  "type": "Feature",
  "properties": {
    "gn:admin1_code":"87.0",
    "gn:admin2_code":"3205.0",
    "gn:admin3_code":"320502.0",
    "gn:asciiname":"Osciecin",
    "gn:country_code":"PL",
    "gn:dem":38,
    "gn:feature_class":"P",
    "gn:feature_code":"PPL",
    "gn:name":"O\u015bci\u0119cin",
    "gn:population":0,
    "gn:timezone":"Europe/Warsaw",
    "iso:country":"PL",
    "name:pol_x_preferred":[
        "O\u015bci\u0119cin"
    ],
    "name:ukr_x_preferred":[
        "\u041e\u0441\u044c\u0446\u0435\u043d\u0446\u0438\u043d"
    ],
    "name:vie_x_preferred":[
        "O\u015bci\u0119cin"
    ],
    "wof:name":"Osciecin",
    "wof:placetype":"locality"
},
  "geometry": {"coordinates":[15.07473,53.82631],"type":"Point"}
}