{
  "type": "Feature",
  "properties": {
    "gn:admin1_code":"81.0",
    "gn:admin2_code":"2003.0",
    "gn:admin3_code":"200303.0",
    "gn:asciiname":"Stupniki",
    "gn:country_code":"PL",
    "gn:dem":129,
    "gn:feature_class":"P",
    "gn:feature_code":"PPL",
    "gn:name":"Stupniki",
    "gn:population":0,
    "gn:timezone":"Europe/Warsaw",
    "iso:country":"PL",
    "name:azb_x_preferred":[
        "\u0633\u062a\u0648\u067e\u0646\u0642\u06a9\u06cc"
    ],
    "name:fas_x_preferred":[
        "\u0633\u062a\u0648\u067e\u0646\u06af\u06a9\u06cc"
    ],
    "name:fra_x_preferred":[
        "Stupniki"
    ],
    "name:lit_x_preferred":[
        "Stupnikai"
    ],
    "name:pol_x_preferred":[
        "Stupniki"
    ],
    "name:ukr_x_preferred":[
        "\u0421\u0442\u0443\u043f\u043d\u0438\u043a\u0438"
    ],
    "wof:name":"Stupniki",
    "wof:placetype":"locality"
},
  "geometry": {"coordinates":[23.31727,52.88323000000001],"type":"Point"}
}