{
  "type": "Feature",
  "properties": {
    "gn:admin1_code":"81.0",
    "gn:admin2_code":"2003.0",
    "gn:admin3_code":"200303.0",
    "gn:asciiname":"Stupniki",
    "gn:country_code":"PL",
    "gn:dem":129,
    "gn:feature_class":"P",
    "gn:feature_code":"PPL",
    "gn:name":"Stupniki",
    "gn:population":0,
    "gn:timezone":"Europe/Warsaw",
    "iso:country":"PL",
    "wof:name":"Stupniki",
    "wof:placetype":"locality"
},
  "geometry": {"coordinates":[23.31727,52.88323000000001],"type":"Point"}
}