{
  "type": "Feature",
  "properties": {
    "gn:gn_country":"PL",
    "gn:gn_fcode":"PPL",
    "gn:gn_pop":0,
    "iso:country":"PL",
    "name:eng_x_preferred":[
        "Trze\u015bcianka"
    ],
    "name:fre_x_preferred":[
        "Trze\u015bcianka"
    ],
    "name:lit_x_preferred":[
        "T\u017ee\u0161cianka"
    ],
    "name:per_x_preferred":[
        "\u0686\u0634\u06a9\u06cc\u0627\u0646\u06a9\u0627"
    ],
    "name:pol_x_preferred":[
        "Trze\u015bcianka"
    ],
    "qs_pg:aaroncc":"PL",
    "qs_pg:gn_country":"PL",
    "qs_pg:gn_fcode":"PPL",
    "qs_pg:gn_pop":0,
    "qs_pg:name":"Trze\u015bcianka",
    "qs_pg:name_adm0":"Polska",
    "qs_pg:name_adm1":"Podlaskie",
    "qs_pg:photos":21,
    "qs_pg:photos_1k":4,
    "qs_pg:photos_9k":1,
    "qs_pg:photos_9r":1,
    "qs_pg:photos_all":21,
    "qs_pg:photos_sr":1,
    "qs_pg:pop_sr":0,
    "qs_pg:qs_pg_placetype":"locality",
    "qs_pg:qs_pg_placetype_gp":"Town",
    "qs_pg:woe_adm0":23424923,
    "woe:adm0_id":23424923,
    "woe:name_adm0":"Polska",
    "woe:name_adm1":"Podlaskie",
    "woe:placetype":"Town",
    "wof:name":"Trze\u015bcianka",
    "wof:placetype":"locality"
},
  "geometry": {"coordinates":[23.449,52.93896],"type":"Point"}
}