{
  "type": "Feature",
  "properties": {
    "gn:admin1_code":"86.0",
    "gn:admin2_code":"3019.0",
    "gn:admin3_code":"301909.0",
    "gn:asciiname":"Kijaszkowo",
    "gn:country_code":"PL",
    "gn:dem":104,
    "gn:feature_class":"P",
    "gn:feature_code":"PPL",
    "gn:name":"Kijaszkowo",
    "gn:population":0,
    "gn:timezone":"Europe/Warsaw",
    "iso:country":"PL",
    "name:ceb_x_preferred":[
        "Kijaszkowo"
    ],
    "name:fra_x_preferred":[
        "Kijaszkowo"
    ],
    "name:pol_x_preferred":[
        "Kijaszkowo"
    ],
    "name:ukr_x_preferred":[
        "\u041a\u0456\u044f\u0448\u043a\u043e\u0432\u043e"
    ],
    "name:und_x_variant":[
        "Wolfshagen, Kr. Wirsitz"
    ],
    "wof:name":"Kijaszkowo",
    "wof:placetype":"locality"
},
  "geometry": {"coordinates":[17.16982,53.21028],"type":"Point"}
}