{
  "type": "Feature",
  "properties": {
    "gn:admin1_code":"86.0",
    "gn:admin2_code":"3019.0",
    "gn:admin3_code":"301909.0",
    "gn:asciiname":"Kijaszkowo",
    "gn:country_code":"PL",
    "gn:dem":104,
    "gn:feature_class":"P",
    "gn:feature_code":"PPL",
    "gn:name":"Kijaszkowo",
    "gn:population":0,
    "gn:timezone":"Europe/Warsaw",
    "iso:country":"PL",
    "name:und_x_variant":[
        "Wolfshagen, Kr. Wirsitz",
        "Kijaszkowo"
    ],
    "wof:name":"Kijaszkowo",
    "wof:placetype":"locality"
},
  "geometry": {"coordinates":[17.16982,53.21028],"type":"Point"}
}