{
  "type": "Feature",
  "properties": {
    "gn:admin1_code":"78.0",
    "gn:admin2_code":"1402.0",
    "gn:admin3_code":"140206.0",
    "gn:asciiname":"Wojtkowa Wies",
    "gn:country_code":"PL",
    "gn:dem":100,
    "gn:feature_class":"P",
    "gn:feature_code":"PPL",
    "gn:name":"Wojtkowa Wie\u015b",
    "gn:population":0,
    "gn:timezone":"Europe/Warsaw",
    "iso:country":"PL",
    "wof:name":"Wojtkowa Wies",
    "wof:placetype":"locality"
},
  "geometry": {"coordinates":[20.52315,52.76611],"type":"Point"}
}