{
  "type": "Feature",
  "properties": {
    "gn:admin1_code":"78.0",
    "gn:admin2_code":"1438.0",
    "gn:admin3_code":"143805.0",
    "gn:asciiname":"Lubno",
    "gn:country_code":"PL",
    "gn:dem":108,
    "gn:feature_class":"P",
    "gn:feature_code":"PPL",
    "gn:name":"\u0141ubno",
    "gn:population":0,
    "gn:timezone":"Europe/Warsaw",
    "iso:country":"PL",
    "name:fra_x_preferred":[
        "\u0141ubno"
    ],
    "name:pol_x_preferred":[
        "\u0141ubno"
    ],
    "name:ukr_x_preferred":[
        "\u041b\u0443\u0431\u043d\u043e"
    ],
    "wof:name":"Lubno",
    "wof:placetype":"locality"
},
  "geometry": {"coordinates":[20.35904,52.04003],"type":"Point"}
}