{
  "type": "Feature",
  "properties": {
    "gn:admin1_code":"81.0",
    "gn:admin2_code":"2012.0",
    "gn:admin3_code":"201206.0",
    "gn:asciiname":"Trzcianka",
    "gn:country_code":"PL",
    "gn:dem":192,
    "gn:feature_class":"P",
    "gn:feature_code":"PPL",
    "gn:name":"Trzcianka",
    "gn:population":0,
    "gn:timezone":"Europe/Warsaw",
    "iso:country":"PL",
    "name:azb_x_preferred":[
        "\u0627\u0634\u0686\u06cc\u0627\u0646\u06a9\u0627"
    ],
    "name:bul_x_preferred":[
        "\u0422\u0448\u0447\u044f\u043d\u043a\u0430"
    ],
    "name:csb_x_preferred":[
        "Trzc\u00f3nka"
    ],
    "name:deu_x_preferred":[
        "Trzcianka"
    ],
    "name:epo_x_preferred":[
        "Trzcianka"
    ],
    "name:fas_x_preferred":[
        "\u0627\u0634\u0686\u06cc\u0627\u0646\u06a9\u0627"
    ],
    "name:fra_x_preferred":[
        "Trzcianka"
    ],
    "name:jav_x_preferred":[
        "Trzcianka"
    ],
    "name:lav_x_preferred":[
        "T\u0161cjanka"
    ],
    "name:msa_x_preferred":[
        "Trzcianka"
    ],
    "name:nld_x_preferred":[
        "Trzcianka"
    ],
    "name:pol_x_preferred":[
        "Trzcianka"
    ],
    "name:por_x_preferred":[
        "Trzcianka"
    ],
    "name:ron_x_preferred":[
        "Trzcianka"
    ],
    "name:rus_x_preferred":[
        "\u0422\u0448\u0446\u044f\u043d\u043a\u0430"
    ],
    "name:slk_x_preferred":[
        "Trzcianka"
    ],
    "name:srp_x_preferred":[
        "\u0422\u0448\u045b\u0430\u043d\u043a\u0430"
    ],
    "name:swe_x_preferred":[
        "Trzcianka"
    ],
    "name:tgl_x_preferred":[
        "Trzcianka"
    ],
    "name:ukr_x_preferred":[
        "\u0422\u0448\u0446\u044f\u043d\u043a\u0430"
    ],
    "name:urd_x_preferred":[
        "\u0686\u0686\u0627\u0646\u06a9\u0627"
    ],
    "name:vie_x_preferred":[
        "Trzcianka"
    ],
    "name:zho_x_preferred":[
        "\u5947\u5f37\u5361"
    ],
    "wof:name":"Trzcianka",
    "wof:placetype":"locality"
},
  "geometry": {"coordinates":[23.01356,54.31185],"type":"Point"}
}