{
  "type": "Feature",
  "properties": {
    "gn:admin1_code":"74.0",
    "gn:admin2_code":"1006.0",
    "gn:admin3_code":"100610.0",
    "gn:asciiname":"Gadka Nowa",
    "gn:country_code":"PL",
    "gn:dem":183,
    "gn:feature_class":"P",
    "gn:feature_code":"PPL",
    "gn:name":"Gadka Nowa",
    "gn:population":0,
    "gn:timezone":"Europe/Warsaw",
    "iso:country":"PL",
    "name:und_x_variant":[
        "Nowa Gadka"
    ],
    "wof:name":"Gadka Nowa",
    "wof:placetype":"locality"
},
  "geometry": {"coordinates":[19.42735,51.68283],"type":"Point"}
}