{
  "type": "Feature",
  "properties": {
    "iso:country":"PL",
    "name:fra_x_preferred":[
        "Nowe Ostrowy"
    ],
    "name:pol_x_preferred":[
        "Nowe Ostrowy"
    ],
    "name:ukr_x_preferred":[
        "\u041d\u043e\u0432\u0435 \u041e\u0441\u0442\u0440\u043e\u0432\u0438"
    ],
    "wof:coterminous":[
        1125289219
    ],
    "wof:name":"Nowe Ostrowy",
    "wof:placetype":"locality"
},
  "geometry": {"coordinates":[19.1947724865593,52.3133831309381],"type":"Point"}
}