{
  "type": "Feature",
  "properties": {
    "iso:country":"PL",
    "name:pol_x_preferred":[
        "Nowe Ostrowy"
    ],
    "wof:name":"Nowe Ostrowy",
    "wof:placetype":"locality"
},
  "geometry": {"coordinates":[19.1947724865593,52.3133831309381],"type":"Point"}
}