{
  "type": "Feature",
  "properties": {
    "gn:admin1_code":"81.0",
    "gn:admin2_code":"2002.0",
    "gn:admin3_code":"200204.0",
    "gn:asciiname":"Straszewo",
    "gn:country_code":"PL",
    "gn:dem":148,
    "gn:feature_class":"P",
    "gn:feature_code":"PPL",
    "gn:name":"Straszewo",
    "gn:population":0,
    "gn:timezone":"Europe/Warsaw",
    "iso:country":"PL",
    "name:azb_x_preferred":[
        "\u0633\u062a\u0631\u0627\u0634\u0648\u0648"
    ],
    "name:fas_x_preferred":[
        "\u0633\u062a\u0631\u0627\u0634\u0648\u0648"
    ],
    "name:fra_x_preferred":[
        "Straszewo"
    ],
    "name:lit_x_preferred":[
        "Stra\u0161evas"
    ],
    "name:pol_x_preferred":[
        "Straszewo"
    ],
    "name:ukr_x_preferred":[
        "\u0421\u0442\u0440\u0430\u0448\u0435\u0432\u043e"
    ],
    "wof:name":"Straszewo",
    "wof:placetype":"locality"
},
  "geometry": {"coordinates":[23.72951,53.08633],"type":"Point"}
}