{
  "type": "Feature",
  "properties": {
    "gn:admin1_code":"78.0",
    "gn:admin2_code":"1409.0",
    "gn:admin3_code":"140903.0",
    "gn:asciiname":"Walentynow",
    "gn:country_code":"PL",
    "gn:dem":174,
    "gn:feature_class":"P",
    "gn:feature_code":"PPL",
    "gn:name":"Walentyn\u00f3w",
    "gn:population":0,
    "gn:timezone":"Europe/Warsaw",
    "iso:country":"PL",
    "name:fra_x_preferred":[
        "Walentyn\u00f3w"
    ],
    "name:pol_x_preferred":[
        "Walentyn\u00f3w"
    ],
    "name:ukr_x_preferred":[
        "\u0412\u0430\u043b\u0435\u043d\u0442\u0438\u043d\u0443\u0432"
    ],
    "wof:name":"Walentynow",
    "wof:placetype":"locality"
},
  "geometry": {"coordinates":[21.63311,51.10104000000001],"type":"Point"}
}