{
  "type": "Feature",
  "properties": {
    "gn:admin1_code":"85.0",
    "gn:admin2_code":"2801.0",
    "gn:admin3_code":"280103.0",
    "gn:asciiname":"Sokolica",
    "gn:country_code":"PL",
    "gn:dem":49,
    "gn:feature_class":"P",
    "gn:feature_code":"PPL",
    "gn:name":"Sokolica",
    "gn:population":0,
    "gn:timezone":"Europe/Warsaw",
    "iso:country":"PL",
    "name:azb_x_preferred":[
        "\u0633\u0648\u06a9\u0648\u0644\u06cc\u062a\u0633\u0627"
    ],
    "name:deu_x_preferred":[
        "Sokolica"
    ],
    "name:fas_x_preferred":[
        "\u0633\u0648\u06a9\u0648\u0644\u06cc\u062a\u0633\u0627"
    ],
    "name:fra_x_preferred":[
        "Sokolica"
    ],
    "name:pol_x_preferred":[
        "Sokolica"
    ],
    "name:ukr_x_preferred":[
        "\u0421\u043e\u043a\u043e\u043b\u0438\u0446\u044f"
    ],
    "name:und_x_variant":[
        "Falkenau"
    ],
    "wof:name":"Sokolica",
    "wof:placetype":"locality"
},
  "geometry": {"coordinates":[20.96883,54.20238000000001],"type":"Point"}
}