{
  "type": "Feature",
  "properties": {
    "gn:admin1_code":"75.0",
    "gn:admin2_code":"601.0",
    "gn:admin3_code":"60109.0",
    "gn:asciiname":"Kozly",
    "gn:country_code":"PL",
    "gn:dem":145,
    "gn:feature_class":"P",
    "gn:feature_code":"PPL",
    "gn:name":"Koz\u0142y",
    "gn:population":0,
    "gn:timezone":"Europe/Warsaw",
    "iso:country":"PL",
    "name:fra_x_preferred":[
        "Koz\u0142y"
    ],
    "name:lit_x_preferred":[
        "Kozlai"
    ],
    "name:pol_x_preferred":[
        "Koz\u0142y"
    ],
    "name:ukr_x_preferred":[
        "\u041a\u043e\u0437\u043b\u0438"
    ],
    "name:und_x_variant":[
        "Koz\u0142y"
    ],
    "wof:name":"Kozly",
    "wof:placetype":"locality"
},
  "geometry": {"coordinates":[23.06554,51.89616],"type":"Point"}
}