{
  "type": "Feature",
  "properties": {
    "gn:admin1_code":"76.0",
    "gn:admin2_code":"811.0",
    "gn:admin3_code":"81104.0",
    "gn:asciiname":"Wicina",
    "gn:country_code":"PL",
    "gn:dem":80,
    "gn:feature_class":"P",
    "gn:feature_code":"PPL",
    "gn:name":"Wicina",
    "gn:population":0,
    "gn:timezone":"Europe/Warsaw",
    "iso:country":"PL",
    "name:fra_x_preferred":[
        "Wicina"
    ],
    "name:pol_x_preferred":[
        "Wicina"
    ],
    "name:ukr_x_preferred":[
        "\u0412\u0456\u0446\u0438\u043d\u0430"
    ],
    "wof:name":"Wicina",
    "wof:placetype":"locality"
},
  "geometry": {"coordinates":[15.07842,51.76806],"type":"Point"}
}