{
  "type": "Feature",
  "properties": {
    "gn:admin1_code":"78.0",
    "gn:admin2_code":"1419.0",
    "gn:admin3_code":"141910.0",
    "gn:asciiname":"Brochocin",
    "gn:country_code":"PL",
    "gn:dem":110,
    "gn:feature_class":"P",
    "gn:feature_code":"PPL",
    "gn:name":"Brochocin",
    "gn:population":0,
    "gn:timezone":"Europe/Warsaw",
    "iso:country":"PL",
    "name:fra_x_preferred":[
        "Brochocin"
    ],
    "name:pol_x_preferred":[
        "Brochocin"
    ],
    "name:ukr_x_preferred":[
        "\u0411\u0440\u043e\u0445\u043e\u0446\u0438\u043d"
    ],
    "wof:name":"Brochocin",
    "wof:placetype":"locality"
},
  "geometry": {"coordinates":[19.75701,52.57796],"type":"Point"}
}