{
  "type": "Feature",
  "properties": {
    "gn:admin1_code":"82.0",
    "gn:admin2_code":"2207.0",
    "gn:admin3_code":"220706.0",
    "gn:asciiname":"Bronislawowo",
    "gn:country_code":"PL",
    "gn:dem":10,
    "gn:feature_class":"P",
    "gn:feature_code":"PPL",
    "gn:name":"Bronis\u0142awowo",
    "gn:population":0,
    "gn:timezone":"Europe/Warsaw",
    "iso:country":"PL",
    "name:ceb_x_preferred":[
        "Bronis\u0142awowo"
    ],
    "name:nld_x_preferred":[
        "Bronis\u0142awowo"
    ],
    "name:pol_x_preferred":[
        "Bronis\u0142awowo"
    ],
    "name:ukr_x_preferred":[
        "\u0411\u0440\u043e\u043d\u0456\u0441\u043b\u0430\u0432\u043e\u0432\u043e"
    ],
    "name:und_x_variant":[
        "Schinkenberg"
    ],
    "wof:name":"Bronislawowo",
    "wof:placetype":"locality"
},
  "geometry": {"coordinates":[18.82097000000001,53.65046],"type":"Point"}
}