{
  "type": "Feature",
  "properties": {
    "gn:country":"PL",
    "gn:fcode":"PPL",
    "gn:population":750,
    "iso:country":"PL",
    "name:ceb_x_preferred":[
        "Bielawy"
    ],
    "name:deu_x_preferred":[
        "Bielawy"
    ],
    "name:fra_x_preferred":[
        "Bielawy"
    ],
    "name:nld_x_preferred":[
        "Bielawy"
    ],
    "name:pol_x_preferred":[
        "Bielawy"
    ],
    "name:ukr_x_preferred":[
        "\u0411\u0435\u043b\u044f\u0432\u0438"
    ],
    "qs_pg:aaroncc":"PL",
    "qs_pg:gn_country":"PL",
    "qs_pg:gn_fcode":"PPL",
    "qs_pg:gn_pop":750,
    "qs_pg:name":"Bielawy",
    "qs_pg:name_adm0":"Polska",
    "qs_pg:name_adm1":"Lubuskie",
    "qs_pg:photos_9k":1,
    "qs_pg:photos_9r":1,
    "qs_pg:photos_all":2,
    "qs_pg:photos_sr":0,
    "qs_pg:pop_sr":2,
    "qs_pg:qs_pg_placetype":"locality",
    "qs_pg:qs_pg_placetype_gp":"Town",
    "qs_pg:woe_adm0":23424923,
    "woe:adm0_id":23424923,
    "woe:name_adm0":"Polska",
    "woe:name_adm1":"Lubuskie",
    "woe:placetype":"Town",
    "wof:name":"Bielawy",
    "wof:placetype":"locality",
    "wof:population":750
},
  "geometry": {"coordinates":[15.93807,51.76911],"type":"Point"}
}