{
  "type": "Feature",
  "properties": {
    "gn:admin1_code":"75.0",
    "gn:admin2_code":"606.0",
    "gn:admin3_code":"60610.0",
    "gn:asciiname":"Zdzanne",
    "gn:country_code":"PL",
    "gn:dem":205,
    "gn:feature_class":"P",
    "gn:feature_code":"PPL",
    "gn:name":"\u017bd\u017canne",
    "gn:population":0,
    "gn:timezone":"Europe/Warsaw",
    "iso:country":"PL",
    "name:fra_x_preferred":[
        "\u017bd\u017canne"
    ],
    "name:pol_x_preferred":[
        "\u017bd\u017canne"
    ],
    "name:ukr_x_preferred":[
        "\u0416\u0434\u0436\u0430\u043d\u043d\u0435"
    ],
    "wof:name":"Zdzanne",
    "wof:placetype":"locality"
},
  "geometry": {"coordinates":[23.38547,51.02247],"type":"Point"}
}