{
  "type": "Feature",
  "properties": {
    "gn:admin1_code":"78.0",
    "gn:admin2_code":"1416.0",
    "gn:admin3_code":"141606.0",
    "gn:asciiname":"Godlewo Wielkie",
    "gn:country_code":"PL",
    "gn:dem":120,
    "gn:feature_class":"P",
    "gn:feature_code":"PPL",
    "gn:name":"Godlewo Wielkie",
    "gn:population":0,
    "gn:timezone":"Europe/Warsaw",
    "iso:country":"PL",
    "wof:name":"Godlewo Wielkie",
    "wof:placetype":"locality"
},
  "geometry": {"coordinates":[22.31126,52.73754],"type":"Point"}
}