{
  "type": "Feature",
  "properties": {
    "gn:admin1_code":"78.0",
    "gn:admin2_code":"1416.0",
    "gn:admin3_code":"141606.0",
    "gn:asciiname":"Godlewo Wielkie",
    "gn:country_code":"PL",
    "gn:dem":120,
    "gn:feature_class":"P",
    "gn:feature_code":"PPL",
    "gn:name":"Godlewo Wielkie",
    "gn:population":0,
    "gn:timezone":"Europe/Warsaw",
    "iso:country":"PL",
    "name:azb_x_preferred":[
        "\u0642\u0648\u062f\u0644\u0648\u0648 \u0648\u06cc\u0644\u06a9\u06cc\u0647"
    ],
    "name:fas_x_preferred":[
        "\u06af\u0648\u062f\u0644\u0648\u0648 \u0648\u06cc\u0644\u06a9\u06cc\u0647"
    ],
    "name:fra_x_preferred":[
        "Godlewo Wielkie"
    ],
    "name:pol_x_preferred":[
        "Godlewo Wielkie"
    ],
    "name:rus_x_preferred":[
        "\u0413\u043e\u0434\u043b\u0435\u0432\u043e-\u0412\u0435\u043b\u044c\u043a\u0435"
    ],
    "name:ukr_x_preferred":[
        "\u0490\u043e\u0434\u043b\u0435\u0432\u043e-\u0412\u0435\u043b\u0438\u043a\u0435"
    ],
    "wof:name":"Godlewo Wielkie",
    "wof:placetype":"locality"
},
  "geometry": {"coordinates":[22.31126,52.73754],"type":"Point"}
}