{
  "type": "Feature",
  "properties": {
    "gn:admin1_code":"74.0",
    "gn:admin2_code":"1014.0",
    "gn:admin3_code":"101405.0",
    "gn:asciiname":"Strzalki Sekowskie",
    "gn:country_code":"PL",
    "gn:dem":166,
    "gn:feature_class":"P",
    "gn:feature_code":"PPL",
    "gn:name":"Strza\u0142ki S\u0119kowskie",
    "gn:population":0,
    "gn:timezone":"Europe/Warsaw",
    "iso:country":"PL",
    "wof:name":"Strzalki Sekowskie",
    "wof:placetype":"locality"
},
  "geometry": {"coordinates":[18.7646,51.45994],"type":"Point"}
}