{
  "type": "Feature",
  "properties": {
    "gn:admin1_code":"74.0",
    "gn:admin2_code":"1014.0",
    "gn:admin3_code":"101407.0",
    "gn:asciiname":"Grzyb",
    "gn:cc2":"PL",
    "gn:country_code":"PL",
    "gn:dem":150,
    "gn:feature_class":"P",
    "gn:feature_code":"PPL",
    "gn:name":"Grzyb",
    "gn:population":0,
    "gn:timezone":"Europe/Warsaw",
    "iso:country":"PL",
    "name:pol_x_preferred":[
        "Grzyb"
    ],
    "name:ukr_x_preferred":[
        "\u0490\u0436\u0438\u0431"
    ],
    "name:und_x_variant":[
        "Grzyby"
    ],
    "wof:name":"Grzyb",
    "wof:placetype":"locality"
},
  "geometry": {"coordinates":[18.3518,51.44245],"type":"Point"}
}