{
  "type": "Feature",
  "properties": {
    "gn:admin1_code":"85.0",
    "gn:admin2_code":"2814.0",
    "gn:admin3_code":"281409.0",
    "gn:asciiname":"Witramowo",
    "gn:country_code":"PL",
    "gn:dem":185,
    "gn:feature_class":"P",
    "gn:feature_code":"PPL",
    "gn:name":"Witramowo",
    "gn:population":0,
    "gn:timezone":"Europe/Warsaw",
    "iso:country":"PL",
    "name:pol_x_preferred":[
        "Witramowo"
    ],
    "name:ukr_x_preferred":[
        "\u0412\u0456\u0442\u0440\u0430\u043c\u043e\u0432\u043e"
    ],
    "name:und_x_variant":[
        "Wittmansdorf",
        "Wittmannsdorf"
    ],
    "wof:name":"Witramowo",
    "wof:placetype":"locality"
},
  "geometry": {"coordinates":[20.33641,53.47919],"type":"Point"}
}