{
  "type": "Feature",
  "properties": {
    "gn:admin1_code":"78.0",
    "gn:admin2_code":"1427.0",
    "gn:admin3_code":"142702.0",
    "gn:asciiname":"Rycharcice",
    "gn:country_code":"PL",
    "gn:dem":126,
    "gn:feature_class":"P",
    "gn:feature_code":"PPL",
    "gn:name":"Rycharcice",
    "gn:population":0,
    "gn:timezone":"Europe/Warsaw",
    "iso:country":"PL",
    "name:fra_x_preferred":[
        "Rycharcice"
    ],
    "name:pol_x_preferred":[
        "Rycharcice"
    ],
    "name:ukr_x_preferred":[
        "\u0420\u0438\u0445\u0430\u0440\u0446\u0438\u0446\u0435"
    ],
    "wof:name":"Rycharcice",
    "wof:placetype":"locality"
},
  "geometry": {"coordinates":[19.70924,52.70678],"type":"Point"}
}