{
  "type": "Feature",
  "properties": {
    "gn:admin1_code":"78.0",
    "gn:admin2_code":"1436.0",
    "gn:admin3_code":"143603.0",
    "gn:asciiname":"Okreznica",
    "gn:country_code":"PL",
    "gn:dem":143,
    "gn:feature_class":"P",
    "gn:feature_code":"PPL",
    "gn:name":"Okr\u0119\u017cnica",
    "gn:population":0,
    "gn:timezone":"Europe/Warsaw",
    "iso:country":"PL",
    "name:fra_x_preferred":[
        "Okr\u0119\u017cnica"
    ],
    "name:pol_x_preferred":[
        "Okr\u0119\u017cnica"
    ],
    "name:ukr_x_preferred":[
        "\u041e\u043a\u0440\u0435\u043d\u0436\u043d\u0438\u0446\u044f"
    ],
    "wof:name":"Okreznica",
    "wof:placetype":"locality"
},
  "geometry": {"coordinates":[21.7234,51.31699],"type":"Point"}
}