{
  "type": "Feature",
  "properties": {
    "gn:admin1_code":"82.0",
    "gn:admin2_code":"2212.0",
    "gn:admin3_code":"221205.0",
    "gn:asciiname":"Biesowice",
    "gn:cc2":"PL",
    "gn:country_code":"PL",
    "gn:dem":106,
    "gn:feature_class":"P",
    "gn:feature_code":"PPL",
    "gn:name":"Biesowice",
    "gn:population":0,
    "gn:timezone":"Europe/Warsaw",
    "iso:country":"PL",
    "name:azb_x_preferred":[
        "\u0628\u06cc\u0633\u0648\u0648\u06cc\u062a\u0633\u0647"
    ],
    "name:ceb_x_preferred":[
        "Biesowice"
    ],
    "name:csb_x_preferred":[
        "Bi\u00e9sojce"
    ],
    "name:deu_x_preferred":[
        "Biesowice"
    ],
    "name:fas_x_preferred":[
        "\u0628\u06cc\u0633\u0648\u0648\u06cc\u062a\u0633\u0647"
    ],
    "name:nld_x_preferred":[
        "Biesowice"
    ],
    "name:pol_x_preferred":[
        "Biesowice"
    ],
    "name:ukr_x_preferred":[
        "\u0411\u0435\u0441\u043e\u0432\u0456\u0446\u0435"
    ],
    "name:und_x_variant":[
        "Biesowiec",
        "Besswitz"
    ],
    "wof:name":"Biesowice",
    "wof:placetype":"locality"
},
  "geometry": {"coordinates":[16.87586,54.19378],"type":"Point"}
}