{
  "type": "Feature",
  "properties": {
    "gn:admin1_code":"72",
    "gn:admin2_code":"0209",
    "gn:admin3_code":"20903.0",
    "gn:asciiname":"Prostynia",
    "gn:country_code":"PL",
    "gn:dem":130,
    "gn:feature_class":"P",
    "gn:feature_code":"PPL",
    "gn:name":"Prostynia",
    "gn:population":0,
    "gn:timezone":"Europe/Warsaw",
    "iso:country":"PL",
    "name:deu_x_historical":[
        "Scheibsdorf"
    ],
    "name:deu_x_preferred":[
        "Scheibsdorf"
    ],
    "name:pol_x_preferred":[
        "Prostynia"
    ],
    "name:ukr_x_preferred":[
        "\u041f\u0440\u043e\u0441\u0442\u0438\u043d\u044f"
    ],
    "wof:name":"Prostynia",
    "wof:placetype":"locality"
},
  "geometry": {"coordinates":[16.12523,51.16051],"type":"Point"}
}