{
  "type": "Feature",
  "properties": {
    "gn:admin1_code":"85.0",
    "gn:admin2_code":"2807.0",
    "gn:admin3_code":"280705.0",
    "gn:asciiname":"Mortegi",
    "gn:country_code":"PL",
    "gn:dem":127,
    "gn:feature_class":"P",
    "gn:feature_code":"PPL",
    "gn:name":"Mort\u0119gi",
    "gn:population":0,
    "gn:timezone":"Europe/Warsaw",
    "iso:country":"PL",
    "name:ceb_x_preferred":[
        "Mort\u0119gi"
    ],
    "name:pol_x_preferred":[
        "Mort\u0119gi"
    ],
    "name:ukr_x_preferred":[
        "\u041c\u043e\u0440\u0442\u0435\u043d\u0491\u0456"
    ],
    "wof:name":"Mortegi",
    "wof:placetype":"locality"
},
  "geometry": {"coordinates":[19.72511,53.45763],"type":"Point"}
}