{
  "type": "Feature",
  "properties": {
    "gn:admin1_code":"86.0",
    "gn:admin2_code":"3007.0",
    "gn:admin3_code":"300705.0",
    "gn:asciiname":"Agnieszkow",
    "gn:country_code":"PL",
    "gn:dem":145,
    "gn:feature_class":"P",
    "gn:feature_code":"PPL",
    "gn:name":"Agnieszk\u00f3w",
    "gn:population":0,
    "gn:timezone":"Europe/Warsaw",
    "iso:country":"PL",
    "name:azb_x_preferred":[
        "\u0627\u0642\u0646\u06cc\u0632\u06a9\u0648"
    ],
    "name:fas_x_preferred":[
        "\u0627\u06af\u0646\u06cc\u0632\u06a9\u0648"
    ],
    "name:pol_x_preferred":[
        "Agnieszk\u00f3w"
    ],
    "name:und_x_variant":[
        "Agnieszk\u00f3w"
    ],
    "name:urd_x_preferred":[
        "\u0627\u06af\u0646\u06cc\u0632 \u06a9\u0648\u0648"
    ],
    "wof:name":"Agnieszkow",
    "wof:placetype":"locality"
},
  "geometry": {"coordinates":[18.34853,51.7558],"type":"Point"}
}