{
  "type": "Feature",
  "properties": {
    "gn:admin1_code":"85.0",
    "gn:admin2_code":"2803.0",
    "gn:admin3_code":"280306.0",
    "gn:asciiname":"Wery",
    "gn:country_code":"PL",
    "gn:dem":143,
    "gn:feature_class":"P",
    "gn:feature_code":"PPL",
    "gn:name":"Wery",
    "gn:population":0,
    "gn:timezone":"Europe/Warsaw",
    "iso:country":"PL",
    "name:pol_x_preferred":[
        "Wery"
    ],
    "name:ukr_x_preferred":[
        "\u0412\u0435\u0440\u0438"
    ],
    "wof:name":"Wery",
    "wof:placetype":"locality"
},
  "geometry": {"coordinates":[19.88542,53.35327],"type":"Point"}
}