{
  "type": "Feature",
  "properties": {
    "gn:admin1_code":"86.0",
    "gn:admin2_code":"3016.0",
    "gn:admin3_code":"301601.0",
    "gn:asciiname":"Urbanie",
    "gn:country_code":"PL",
    "gn:dem":74,
    "gn:feature_class":"P",
    "gn:feature_code":"PPL",
    "gn:name":"Urbanie",
    "gn:population":0,
    "gn:timezone":"Europe/Warsaw",
    "iso:country":"PL",
    "name:fra_x_preferred":[
        "Urbanie"
    ],
    "name:pol_x_preferred":[
        "Urbanie"
    ],
    "name:ukr_x_preferred":[
        "\u0423\u0440\u0431\u0430\u043d\u0435"
    ],
    "wof:name":"Urbanie",
    "wof:placetype":"locality"
},
  "geometry": {"coordinates":[16.69981,52.62761999999999],"type":"Point"}
}