{
  "type": "Feature",
  "properties": {
    "gn:admin1_code":"78.0",
    "gn:admin2_code":"1410.0",
    "gn:admin3_code":"141003.0",
    "gn:asciiname":"Kolonia Korczowka",
    "gn:cc2":"PL",
    "gn:country_code":"PL",
    "gn:dem":167,
    "gn:feature_class":"P",
    "gn:feature_code":"PPL",
    "gn:name":"Kolonia Korcz\u00f3wka",
    "gn:population":0,
    "gn:timezone":"Europe/Warsaw",
    "iso:country":"PL",
    "name:und_x_variant":[
        "Korcz\u00f3wka Kolonia"
    ],
    "wof:name":"Kolonia Korczowka",
    "wof:placetype":"locality"
},
  "geometry": {"coordinates":[22.7178,52.14147],"type":"Point"}
}