{
  "type": "Feature",
  "properties": {
    "gn:admin1_code":"78.0",
    "gn:admin2_code":"1410.0",
    "gn:admin3_code":"141003.0",
    "gn:asciiname":"Kolonia Korczowka",
    "gn:cc2":"PL",
    "gn:country_code":"PL",
    "gn:dem":167,
    "gn:feature_class":"P",
    "gn:feature_code":"PPL",
    "gn:name":"Kolonia Korcz\u00f3wka",
    "gn:population":0,
    "gn:timezone":"Europe/Warsaw",
    "iso:country":"PL",
    "name:azb_x_preferred":[
        "\u06a9\u0648\u0631\u0686\u0648\u0648\u06a9\u0627-\u06a9\u0648\u0644\u0648\u0646\u0642\u0627"
    ],
    "name:fas_x_preferred":[
        "\u06a9\u0648\u0631\u0686\u0648\u0648\u06a9\u0627-\u06a9\u0648\u0644\u0648\u0646\u06af\u0627"
    ],
    "name:fra_x_preferred":[
        "Korcz\u00f3wka-Kolonia"
    ],
    "name:lit_x_preferred":[
        "Kor\u010duvka Kolonija"
    ],
    "name:pol_x_preferred":[
        "Korcz\u00f3wka-Kolonia"
    ],
    "name:ukr_x_preferred":[
        "\u041a\u043e\u0440\u0447\u0443\u0432\u043a\u0430-\u041a\u043e\u043b\u044c\u043e\u043d\u0456\u044f"
    ],
    "name:und_x_variant":[
        "Korcz\u00f3wka Kolonia"
    ],
    "wof:name":"Kolonia Korczowka",
    "wof:placetype":"locality"
},
  "geometry": {"coordinates":[22.7178,52.14147],"type":"Point"}
}