{
  "type": "Feature",
  "properties": {
    "gn:admin1_code":"86.0",
    "gn:admin2_code":"3008.0",
    "gn:admin3_code":"300801.0",
    "gn:asciiname":"Grebanin",
    "gn:country_code":"PL",
    "gn:dem":181,
    "gn:feature_class":"P",
    "gn:feature_code":"PPL",
    "gn:name":"Gr\u0119banin",
    "gn:population":0,
    "gn:timezone":"Europe/Warsaw",
    "iso:country":"PL",
    "name:und_x_variant":[
        "Gr\u0119banin"
    ],
    "wof:name":"Grebanin",
    "wof:placetype":"locality"
},
  "geometry": {"coordinates":[17.97217999999999,51.245],"type":"Point"}
}