{
  "type": "Feature",
  "properties": {
    "gn:admin1_code":"86.0",
    "gn:admin2_code":"3008.0",
    "gn:admin3_code":"300801.0",
    "gn:asciiname":"Grebanin",
    "gn:country_code":"PL",
    "gn:dem":181,
    "gn:feature_class":"P",
    "gn:feature_code":"PPL",
    "gn:name":"Gr\u0119banin",
    "gn:population":0,
    "gn:timezone":"Europe/Warsaw",
    "iso:country":"PL",
    "name:pol_x_preferred":[
        "Gr\u0119banin"
    ],
    "name:ukr_x_preferred":[
        "\u0490\u0440\u0435\u043c\u0431\u0430\u043d\u0456\u043d"
    ],
    "wof:name":"Grebanin",
    "wof:placetype":"locality"
},
  "geometry": {"coordinates":[17.97217999999999,51.245],"type":"Point"}
}