{
  "type": "Feature",
  "properties": {
    "gn:admin1_code":"77.0",
    "gn:admin2_code":"1205.0",
    "gn:admin3_code":"120505.0",
    "gn:asciiname":"Pagorzyna",
    "gn:cc2":"PL",
    "gn:country_code":"PL",
    "gn:dem":271,
    "gn:feature_class":"P",
    "gn:feature_code":"PPL",
    "gn:name":"Pagorzyna",
    "gn:population":0,
    "gn:timezone":"Europe/Warsaw",
    "iso:country":"PL",
    "name:ceb_x_preferred":[
        "Pagorzyna"
    ],
    "name:pol_x_preferred":[
        "Pagorzyna"
    ],
    "name:ukr_x_preferred":[
        "\u041f\u0430\u0491\u043e\u0436\u0438\u043d\u0430"
    ],
    "name:und_x_variant":[
        "Pog\u00f3rzyna"
    ],
    "wof:name":"Pagorzyna",
    "wof:placetype":"locality"
},
  "geometry": {"coordinates":[21.33717,49.68029],"type":"Point"}
}