{
  "type": "Feature",
  "properties": {
    "gn:admin1_code":"87.0",
    "gn:admin2_code":"3204.0",
    "gn:admin3_code":"320402.0",
    "gn:asciiname":"Niewiadowo",
    "gn:country_code":"PL",
    "gn:dem":30,
    "gn:feature_class":"P",
    "gn:feature_code":"PPL",
    "gn:name":"Niewiadowo",
    "gn:population":0,
    "gn:timezone":"Europe/Warsaw",
    "iso:country":"PL",
    "wof:name":"Niewiadowo",
    "wof:placetype":"locality"
},
  "geometry": {"coordinates":[14.8992,53.65603],"type":"Point"}
}