{
  "type": "Feature",
  "properties": {
    "gn:admin1_code":"85.0",
    "gn:admin2_code":"2805.0",
    "gn:admin3_code":"280502.0",
    "gn:asciiname":"Sajzy",
    "gn:country_code":"PL",
    "gn:dem":126,
    "gn:feature_class":"P",
    "gn:feature_code":"PPL",
    "gn:name":"Sajzy",
    "gn:population":0,
    "gn:timezone":"Europe/Warsaw",
    "iso:country":"PL",
    "name:deu_x_preferred":[
        "Sajzy"
    ],
    "name:fra_x_preferred":[
        "Sajzy"
    ],
    "name:pol_x_preferred":[
        "Sajzy"
    ],
    "name:ukr_x_preferred":[
        "\u0421\u0430\u0439\u0437\u0438"
    ],
    "name:und_x_variant":[
        "Zeysen",
        "Sajzy"
    ],
    "wof:name":"Sajzy",
    "wof:placetype":"locality"
},
  "geometry": {"coordinates":[22.28726,53.9348],"type":"Point"}
}