{
  "type": "Feature",
  "properties": {
    "gn:admin1_code":"87.0",
    "gn:admin2_code":"3201.0",
    "gn:admin3_code":"320104.0",
    "gn:asciiname":"Kowalki",
    "gn:country_code":"PL",
    "gn:dem":111,
    "gn:feature_class":"P",
    "gn:feature_code":"PPL",
    "gn:name":"Kowalki",
    "gn:population":0,
    "gn:timezone":"Europe/Warsaw",
    "iso:country":"PL",
    "name:deu_x_preferred":[
        "Kowalki"
    ],
    "name:pol_x_preferred":[
        "Kowalki"
    ],
    "name:ukr_x_preferred":[
        "\u041a\u043e\u0432\u0430\u043b\u044c\u043a\u0456"
    ],
    "wof:name":"Kowalki",
    "wof:placetype":"locality"
},
  "geometry": {"coordinates":[16.36249,53.92324],"type":"Point"}
}