{
  "type": "Feature",
  "properties": {
    "gn:country":"PL",
    "gn:fcode":"PPL",
    "gn:population":115,
    "iso:country":"PL",
    "name:fra_x_preferred":[
        "P\u0142awno"
    ],
    "name:pol_x_preferred":[
        "P\u0142awno"
    ],
    "name:ukr_x_preferred":[
        "\u041f\u043b\u0430\u0432\u043d\u043e"
    ],
    "qs_pg:aaroncc":"PL",
    "qs_pg:gn_country":"PL",
    "qs_pg:gn_fcode":"PPL",
    "qs_pg:gn_pop":115,
    "qs_pg:name":"P\u0142awno",
    "qs_pg:name_adm0":"Polska",
    "qs_pg:name_adm1":"Zachodniopomorskie",
    "qs_pg:photos_9r":0,
    "qs_pg:photos_sr":0,
    "qs_pg:pop_sr":1,
    "qs_pg:qs_pg_placetype":"locality",
    "qs_pg:qs_pg_placetype_gp":"Town",
    "qs_pg:woe_adm0":23424923,
    "woe:adm0_id":23424923,
    "woe:name_adm0":"Polska",
    "woe:name_adm1":"Zachodniopomorskie",
    "woe:placetype":"Town",
    "wof:name":"P\u0142awno",
    "wof:placetype":"locality",
    "wof:population":115
},
  "geometry": {"coordinates":[16.22492,53.51612],"type":"Point"}
}