{
  "type": "Feature",
  "properties": {
    "gn:admin1_code":"72.0",
    "gn:admin2_code":"202.0",
    "gn:admin3_code":"20206.0",
    "gn:asciiname":"Ratajno",
    "gn:country_code":"PL",
    "gn:dem":202,
    "gn:feature_class":"P",
    "gn:feature_code":"PPL",
    "gn:name":"Ratajno",
    "gn:population":0,
    "gn:timezone":"Europe/Warsaw",
    "iso:country":"PL",
    "name:deu_x_historical":[
        "Panthenau"
    ],
    "name:deu_x_preferred":[
        "Panthenau"
    ],
    "wof:name":"Ratajno",
    "wof:placetype":"locality"
},
  "geometry": {"coordinates":[16.80607,50.77832],"type":"Point"}
}