{
  "type": "Feature",
  "properties": {
    "gn:admin1_code":"85.0",
    "gn:admin2_code":"2811.0",
    "gn:admin3_code":"281103.0",
    "gn:asciiname":"Browina",
    "gn:country_code":"PL",
    "gn:dem":193,
    "gn:feature_class":"P",
    "gn:feature_code":"PPL",
    "gn:name":"Browina",
    "gn:population":0,
    "gn:timezone":"Europe/Warsaw",
    "iso:country":"PL",
    "name:und_x_variant":[
        "Browienen",
        "Froben",
        "Browina"
    ],
    "wof:name":"Browina",
    "wof:placetype":"locality"
},
  "geometry": {"coordinates":[20.20668,53.45561],"type":"Point"}
}