{
  "type": "Feature",
  "properties": {
    "gn:admin1_code":"85.0",
    "gn:admin2_code":"2811.0",
    "gn:admin3_code":"281103.0",
    "gn:asciiname":"Browina",
    "gn:country_code":"PL",
    "gn:dem":193,
    "gn:feature_class":"P",
    "gn:feature_code":"PPL",
    "gn:name":"Browina",
    "gn:population":0,
    "gn:timezone":"Europe/Warsaw",
    "iso:country":"PL",
    "name:azb_x_preferred":[
        "\u0628\u0631\u0648\u0648\u06cc\u0646\u0627"
    ],
    "name:ceb_x_preferred":[
        "Browina"
    ],
    "name:deu_x_preferred":[
        "Browina"
    ],
    "name:fas_x_preferred":[
        "\u0628\u0631\u0648\u0648\u06cc\u0646\u0627"
    ],
    "name:fra_x_preferred":[
        "Browina"
    ],
    "name:pol_x_preferred":[
        "Browina"
    ],
    "name:ukr_x_preferred":[
        "\u0411\u0440\u043e\u0432\u0456\u043d\u0430"
    ],
    "name:und_x_variant":[
        "Browienen",
        "Froben",
        "Browina"
    ],
    "wof:name":"Browina",
    "wof:placetype":"locality"
},
  "geometry": {"coordinates":[20.20668,53.45561],"type":"Point"}
}