{
  "type": "Feature",
  "properties": {
    "gn:admin1_code":"78.0",
    "gn:admin2_code":"1424.0",
    "gn:admin3_code":"142401.0",
    "gn:asciiname":"Przepychy",
    "gn:country_code":"PL",
    "gn:dem":112,
    "gn:feature_class":"P",
    "gn:feature_code":"PPL",
    "gn:name":"Przepychy",
    "gn:population":0,
    "gn:timezone":"Europe/Warsaw",
    "iso:country":"PL",
    "wof:name":"Przepychy",
    "wof:placetype":"locality"
},
  "geometry": {"coordinates":[20.88333,52.75],"type":"Point"}
}