{
  "type": "Feature",
  "properties": {
    "gn:admin1_code":"74.0",
    "gn:admin2_code":"1014.0",
    "gn:admin3_code":"101402.0",
    "gn:asciiname":"Orzezyn",
    "gn:country_code":"PL",
    "gn:dem":151,
    "gn:feature_class":"P",
    "gn:feature_code":"PPL",
    "gn:name":"Orze\u017cyn",
    "gn:population":0,
    "gn:timezone":"Europe/Warsaw",
    "iso:country":"PL",
    "name:und_x_variant":[
        "Orze\u017cyn"
    ],
    "wof:name":"Orzezyn",
    "wof:placetype":"locality"
},
  "geometry": {"coordinates":[18.52435,51.65864000000001],"type":"Point"}
}