{
  "type": "Feature",
  "properties": {
    "gn:admin1_code":"86.0",
    "gn:admin2_code":"3009.0",
    "gn:admin3_code":"300903.0",
    "gn:asciiname":"Bowyczyn Towarzystwo",
    "gn:country_code":"PL",
    "gn:dem":128,
    "gn:feature_class":"P",
    "gn:feature_code":"PPL",
    "gn:name":"Bowyczyn Towarzystwo",
    "gn:population":0,
    "gn:timezone":"Europe/Warsaw",
    "iso:country":"PL",
    "wof:name":"Bowyczyn Towarzystwo",
    "wof:placetype":"locality"
},
  "geometry": {"coordinates":[19.06667,52.21667],"type":"Point"}
}