{
  "type": "Feature",
  "properties": {
    "gn:admin1_code":"78.0",
    "gn:admin2_code":"1413.0",
    "gn:admin3_code":"141302.0",
    "gn:asciiname":"Szumsk",
    "gn:country_code":"PL",
    "gn:dem":153,
    "gn:feature_class":"P",
    "gn:feature_code":"PPL",
    "gn:name":"Szumsk",
    "gn:population":0,
    "gn:timezone":"Europe/Warsaw",
    "iso:country":"PL",
    "name:fra_x_preferred":[
        "Szumsk"
    ],
    "name:pol_x_preferred":[
        "Szumsk"
    ],
    "name:szl_x_preferred":[
        "Szumsk"
    ],
    "name:ukr_x_preferred":[
        "\u0428\u0443\u043c\u0441\u044c\u043a"
    ],
    "wof:name":"Szumsk",
    "wof:placetype":"locality"
},
  "geometry": {"coordinates":[20.66696,53.136],"type":"Point"}
}