{
  "type": "Feature",
  "properties": {
    "gn:admin1_code":"78.0",
    "gn:admin2_code":"1414.0",
    "gn:admin3_code":"141404.0",
    "gn:asciiname":"Debinki",
    "gn:country_code":"PL",
    "gn:dem":102,
    "gn:feature_class":"P",
    "gn:feature_code":"PPL",
    "gn:name":"D\u0119binki",
    "gn:population":0,
    "gn:timezone":"Europe/Warsaw",
    "iso:country":"PL",
    "name:fra_x_preferred":[
        "D\u0119binki"
    ],
    "name:mkd_x_preferred":[
        "\u0414\u0435\u043c\u0431\u0438\u043d\u043a\u0438"
    ],
    "name:pol_x_preferred":[
        "D\u0119binki"
    ],
    "name:ukr_x_preferred":[
        "\u0414\u0435\u043c\u0431\u0456\u043d\u043a\u0456"
    ],
    "wof:name":"Debinki",
    "wof:placetype":"locality"
},
  "geometry": {"coordinates":[20.73438,52.54635],"type":"Point"}
}