{
  "type": "Feature",
  "properties": {
    "gn:admin1_code":"74.0",
    "gn:admin2_code":"1002.0",
    "gn:admin3_code":"100211.0",
    "gn:asciiname":"Pasieka",
    "gn:country_code":"PL",
    "gn:dem":99,
    "gn:feature_class":"P",
    "gn:feature_code":"PPL",
    "gn:name":"Pasieka",
    "gn:population":0,
    "gn:timezone":"Europe/Warsaw",
    "iso:country":"PL",
    "name:fra_x_preferred":[
        "Pasieka"
    ],
    "name:pol_x_preferred":[
        "Pasieka"
    ],
    "name:ukr_x_preferred":[
        "\u041f\u0430\u0441\u0435\u043a\u0430"
    ],
    "name:und_x_variant":[
        "Pasieka Nowa"
    ],
    "wof:name":"Pasieka",
    "wof:placetype":"locality"
},
  "geometry": {"coordinates":[19.58816,52.24618],"type":"Point"}
}