{
  "type": "Feature",
  "properties": {
    "gn:admin1_code":"74.0",
    "gn:admin2_code":"1012.0",
    "gn:admin3_code":"101211.0",
    "gn:asciiname":"Chalupki",
    "gn:country_code":"PL",
    "gn:dem":199,
    "gn:feature_class":"P",
    "gn:feature_code":"PPL",
    "gn:name":"Cha\u0142upki",
    "gn:population":0,
    "gn:timezone":"Europe/Warsaw",
    "iso:country":"PL",
    "name:fra_x_preferred":[
        "Cha\u0142upki"
    ],
    "name:pol_x_preferred":[
        "Cha\u0142upy"
    ],
    "name:ukr_x_preferred":[
        "\u0425\u0430\u043b\u0443\u043f\u0438"
    ],
    "wof:name":"Chalupki",
    "wof:placetype":"locality"
},
  "geometry": {"coordinates":[19.88131,51.0558],"type":"Point"}
}