{
  "type": "Feature",
  "properties": {
    "gn:admin1_code":"82.0",
    "gn:admin2_code":"2214.0",
    "gn:admin3_code":"221402.0",
    "gn:asciiname":"Tymawa",
    "gn:country_code":"PL",
    "gn:dem":74,
    "gn:feature_class":"P",
    "gn:feature_code":"PPL",
    "gn:name":"Tymawa",
    "gn:population":0,
    "gn:timezone":"Europe/Warsaw",
    "iso:country":"PL",
    "name:azb_x_preferred":[
        "\u062a\u06cc\u0645\u0627\u0648\u0627"
    ],
    "name:fas_x_preferred":[
        "\u062a\u06cc\u0645\u0627\u0648\u0627"
    ],
    "name:pol_x_preferred":[
        "Tymawa"
    ],
    "name:ukr_x_preferred":[
        "\u0422\u0438\u043c\u0430\u0432\u0430"
    ],
    "wof:name":"Tymawa",
    "wof:placetype":"locality"
},
  "geometry": {"coordinates":[18.81211,53.79903],"type":"Point"}
}