{
  "type": "Feature",
  "properties": {
    "gn:admin1_code":"84.0",
    "gn:admin2_code":"2610.0",
    "gn:admin3_code":"261001.0",
    "gn:asciiname":"Skarzysko Ksiazece",
    "gn:country_code":"PL",
    "gn:dem":252,
    "gn:feature_class":"P",
    "gn:feature_code":"PPL",
    "gn:name":"Skar\u017cysko Ksi\u0105\u017c\u0119ce",
    "gn:population":0,
    "gn:timezone":"Europe/Warsaw",
    "iso:country":"PL",
    "wof:name":"Skarzysko Ksiazece",
    "wof:placetype":"neighbourhood"
},
  "geometry": {"coordinates":[20.85799,51.1461],"type":"Point"}
}