{
  "type": "Feature",
  "properties": {
    "gn:admin1_code":"84.0",
    "gn:admin2_code":"2661.0",
    "gn:admin3_code":"266101.0",
    "gn:asciiname":"Jagiellonskie",
    "gn:country_code":"PL",
    "gn:dem":269,
    "gn:feature_class":"P",
    "gn:feature_code":"PPL",
    "gn:name":"Jagiello\u0144skie",
    "gn:population":0,
    "gn:timezone":"Europe/Warsaw",
    "iso:country":"PL",
    "wof:name":"Jagiellonskie",
    "wof:placetype":"locality"
},
  "geometry": {"coordinates":[20.61014,50.86966],"type":"Point"}
}