{
  "type": "Feature",
  "properties": {
    "gn:admin1_code":"77.0",
    "gn:admin2_code":"1208.0",
    "gn:admin3_code":"120805.0",
    "gn:asciiname":"Kalina Mala",
    "gn:country_code":"PL",
    "gn:dem":275,
    "gn:feature_class":"P",
    "gn:feature_code":"PPL",
    "gn:name":"Kalina Ma\u0142a",
    "gn:population":0,
    "gn:timezone":"Europe/Warsaw",
    "iso:country":"PL",
    "name:azb_x_preferred":[
        "\u06a9\u0627\u0644\u06cc\u0646\u0627 \u0645\u0627\u0648\u0627"
    ],
    "name:ceb_x_preferred":[
        "Kalina Ma\u0142a"
    ],
    "name:fas_x_preferred":[
        "\u06a9\u0627\u0644\u06cc\u0646\u0627 \u0645\u0627\u0648\u0627"
    ],
    "name:nld_x_preferred":[
        "Kalina Ma\u0142a"
    ],
    "name:pol_x_preferred":[
        "Kalina Ma\u0142a"
    ],
    "name:rus_x_preferred":[
        "\u041a\u0430\u043b\u0438\u043d\u0430-\u041c\u0430\u043b\u0430"
    ],
    "name:szl_x_preferred":[
        "Ma\u0142o Kalina"
    ],
    "name:ukr_x_preferred":[
        "\u041a\u0430\u043b\u0456\u043d\u0430-\u041c\u0430\u043b\u0430"
    ],
    "wof:name":"Kalina Mala",
    "wof:placetype":"locality"
},
  "geometry": {"coordinates":[20.11937,50.36791],"type":"Point"}
}