{
  "type": "Feature",
  "properties": {
    "gn:admin1_code":"84.0",
    "gn:admin2_code":"2601.0",
    "gn:admin3_code":"260106.0",
    "gn:asciiname":"Suchowola",
    "gn:country_code":"PL",
    "gn:dem":257,
    "gn:feature_class":"P",
    "gn:feature_code":"PPL",
    "gn:name":"Suchowola",
    "gn:population":0,
    "gn:timezone":"Europe/Warsaw",
    "iso:country":"PL",
    "wof:name":"Suchowola",
    "wof:placetype":"locality"
},
  "geometry": {"coordinates":[20.92828,50.41391],"type":"Point"}
}