{
  "type": "Feature",
  "properties": {
    "gn:admin1_code":"84.0",
    "gn:admin2_code":"2601.0",
    "gn:admin3_code":"260106.0",
    "gn:asciiname":"Suchowola",
    "gn:country_code":"PL",
    "gn:dem":257,
    "gn:feature_class":"P",
    "gn:feature_code":"PPL",
    "gn:name":"Suchowola",
    "gn:population":0,
    "gn:timezone":"Europe/Warsaw",
    "iso:country":"PL",
    "name:bel_x_preferred":[
        "\u0421\u0443\u0445\u0430\u0432\u043e\u043b\u044f"
    ],
    "name:ceb_x_preferred":[
        "Suchowola"
    ],
    "name:ces_x_preferred":[
        "Suchowola"
    ],
    "name:deu_x_preferred":[
        "Suchowola"
    ],
    "name:dsb_x_preferred":[
        "Suchowola"
    ],
    "name:epo_x_preferred":[
        "Suchowola"
    ],
    "name:est_x_preferred":[
        "Suchowola"
    ],
    "name:fra_x_preferred":[
        "Suchowola"
    ],
    "name:heb_x_preferred":[
        "\u05e1\u05d5\u05d7\u05d5\u05d1\u05d5\u05dc\u05d4"
    ],
    "name:ita_x_preferred":[
        "Suchowola"
    ],
    "name:jav_x_preferred":[
        "Suchowola"
    ],
    "name:lav_x_preferred":[
        "Suhovola"
    ],
    "name:lit_x_preferred":[
        "Suchovola"
    ],
    "name:msa_x_preferred":[
        "Suchowola"
    ],
    "name:nld_x_preferred":[
        "Suchowola"
    ],
    "name:pol_x_preferred":[
        "Suchowola"
    ],
    "name:por_x_preferred":[
        "Suchowola"
    ],
    "name:ron_x_preferred":[
        "Suchowola"
    ],
    "name:rus_x_preferred":[
        "\u0421\u0443\u0445\u043e\u0432\u043e\u043b\u044f"
    ],
    "name:slk_x_preferred":[
        "Suchowola"
    ],
    "name:srp_x_preferred":[
        "\u0421\u0443\u0445\u043e\u0432\u043e\u043b\u0430"
    ],
    "name:swe_x_preferred":[
        "Suchowola"
    ],
    "name:ukr_x_preferred":[
        "\u0421\u0443\u0445\u043e\u0432\u043e\u043b\u044f"
    ],
    "name:vie_x_preferred":[
        "Suchowola"
    ],
    "name:zho_x_preferred":[
        "\u8607\u970d\u6c83\u62c9"
    ],
    "wof:name":"Suchowola",
    "wof:placetype":"locality"
},
  "geometry": {"coordinates":[20.92828,50.41391],"type":"Point"}
}