{
  "type": "Feature",
  "properties": {
    "gn:admin1_code":"78.0",
    "gn:admin2_code":"1412.0",
    "gn:admin3_code":"141209.0",
    "gn:asciiname":"Golebiowka",
    "gn:country_code":"PL",
    "gn:dem":148,
    "gn:feature_class":"P",
    "gn:feature_code":"PPL",
    "gn:name":"Go\u0142\u0119bi\u00f3wka",
    "gn:population":0,
    "gn:timezone":"Europe/Warsaw",
    "iso:country":"PL",
    "name:fra_x_preferred":[
        "Go\u0142\u0119bi\u00f3wka"
    ],
    "name:pol_x_preferred":[
        "Go\u0142\u0119bi\u00f3wka"
    ],
    "name:ukr_x_preferred":[
        "\u0490\u043e\u043b\u0435\u043c\u0431\u044e\u0432\u043a\u0430"
    ],
    "wof:name":"Golebiowka",
    "wof:placetype":"locality"
},
  "geometry": {"coordinates":[21.8821,52.17898],"type":"Point"}
}