{
  "type": "Feature",
  "properties": {
    "gn:admin1_code":"78.0",
    "gn:admin2_code":"1438.0",
    "gn:admin3_code":"143804.0",
    "gn:asciiname":"Budy Jozefowskie",
    "gn:country_code":"PL",
    "gn:dem":128,
    "gn:feature_class":"P",
    "gn:feature_code":"PPL",
    "gn:name":"Budy J\u00f3zefowskie",
    "gn:population":0,
    "gn:timezone":"Europe/Warsaw",
    "iso:country":"PL",
    "name:ceb_x_preferred":[
        "Budy J\u00f3zefowskie"
    ],
    "name:fra_x_preferred":[
        "Budy J\u00f3zefowskie"
    ],
    "name:pol_x_preferred":[
        "Budy J\u00f3zefowskie"
    ],
    "name:ukr_x_preferred":[
        "\u0411\u0443\u0434\u0438-\u042e\u0437\u0435\u0444\u043e\u0432\u0441\u044c\u043a\u0456"
    ],
    "wof:name":"Budy Jozefowskie",
    "wof:placetype":"locality"
},
  "geometry": {"coordinates":[20.5695,52.04531],"type":"Point"}
}