{
  "type": "Feature",
  "properties": {
    "gn:gn_country":"PL",
    "gn:gn_fcode":"PPL",
    "gn:gn_pop":310,
    "gn:population":310,
    "iso:country":"PL",
    "name:dut_x_preferred":[
        "Junoszyno"
    ],
    "name:eng_x_preferred":[
        "Junoszyno"
    ],
    "name:fre_x_preferred":[
        "Junoszyno"
    ],
    "name:nan_x_preferred":[
        "Junoszyno"
    ],
    "name:pol_x_preferred":[
        "Junoszyno"
    ],
    "name:unk_x_variant":[
        "Junckeracker"
    ],
    "qs_pg:aaroncc":"PL",
    "qs_pg:gn_country":"PL",
    "qs_pg:gn_fcode":"PPL",
    "qs_pg:gn_pop":310,
    "qs_pg:name":"Junoszyno",
    "qs_pg:name_adm0":"Polska",
    "qs_pg:name_adm1":"Pomorskie",
    "qs_pg:photos_9k":1,
    "qs_pg:photos_9r":1,
    "qs_pg:photos_all":1,
    "qs_pg:photos_sr":0,
    "qs_pg:pop_sr":2,
    "qs_pg:qs_pg_placetype":"locality",
    "qs_pg:qs_pg_placetype_gp":"Town",
    "qs_pg:woe_adm0":23424923,
    "woe:adm0_id":23424923,
    "woe:name_adm0":"Polska",
    "woe:name_adm1":"Pomorskie",
    "woe:placetype":"Town",
    "wof:name":"Junoszyno",
    "wof:placetype":"locality",
    "wof:population":310
},
  "geometry": {"coordinates":[19.08235,54.33001],"type":"Point"}
}