{
  "type": "Feature",
  "properties": {
    "gn:admin1_code":"80.0",
    "gn:admin2_code":"1804.0",
    "gn:admin3_code":"180408.0",
    "gn:asciiname":"Zalazie",
    "gn:country_code":"PL",
    "gn:dem":218,
    "gn:feature_class":"P",
    "gn:feature_code":"PPL",
    "gn:name":"Za\u0142azie",
    "gn:population":0,
    "gn:timezone":"Europe/Warsaw",
    "iso:country":"PL",
    "wof:name":"Zalazie",
    "wof:placetype":"locality"
},
  "geometry": {"coordinates":[23.0475,49.94201],"type":"Point"}
}