{
  "type": "Feature",
  "properties": {
    "gn:admin1_code":"74.0",
    "gn:admin2_code":"1003.0",
    "gn:admin3_code":"100304.0",
    "gn:asciiname":"Wincentow",
    "gn:country_code":"PL",
    "gn:dem":168,
    "gn:feature_class":"P",
    "gn:feature_code":"PPL",
    "gn:name":"Wincent\u00f3w",
    "gn:population":0,
    "gn:timezone":"Europe/Warsaw",
    "iso:country":"PL",
    "wof:name":"Wincentow",
    "wof:placetype":"locality"
},
  "geometry": {"coordinates":[18.97617,51.37052],"type":"Point"}
}