{
  "type": "Feature",
  "properties": {
    "gn:gn_country":"PL",
    "gn:gn_fcode":"PPL",
    "gn:gn_pop":128,
    "gn:population":128,
    "iso:country":"PL",
    "name:ast_x_preferred":[
        "Bojan\u00f3w"
    ],
    "name:ceb_x_preferred":[
        "Bojan\u00f3w"
    ],
    "name:eng_x_preferred":[
        "Bojan\u00f3w"
    ],
    "name:fra_x_preferred":[
        "Bojan\u00f3w"
    ],
    "name:pol_x_preferred":[
        "Bojan\u00f3w"
    ],
    "name:ukr_x_preferred":[
        "\u0411\u043e\u044f\u043d\u0443\u0432"
    ],
    "qs_pg:aaroncc":"PL",
    "qs_pg:gn_country":"PL",
    "qs_pg:gn_fcode":"PPL",
    "qs_pg:gn_pop":128,
    "qs_pg:name":"Bojan\u00f3w",
    "qs_pg:name_adm0":"Polska",
    "qs_pg:name_adm1":"\u0141\u00f3dzkie",
    "qs_pg:photos_9r":0,
    "qs_pg:photos_sr":0,
    "qs_pg:pop_sr":1,
    "qs_pg:qs_pg_placetype":"locality",
    "qs_pg:qs_pg_placetype_gp":"Town",
    "qs_pg:woe_adm0":23424923,
    "woe:adm0_id":23424923,
    "woe:name_adm0":"Polska",
    "woe:name_adm1":"\u0141\u00f3dzkie",
    "woe:placetype":"Town",
    "wof:name":"Bojan\u00f3w",
    "wof:placetype":"locality",
    "wof:population":128
},
  "geometry": {"coordinates":[18.38802,51.15114],"type":"Point"}
}