{
  "type": "Feature",
  "properties": {
    "gn:admin1_code":"74.0",
    "gn:admin2_code":"1004.0",
    "gn:admin3_code":"100403.0",
    "gn:asciiname":"Kosiorow",
    "gn:country_code":"PL",
    "gn:dem":106,
    "gn:feature_class":"P",
    "gn:feature_code":"PPL",
    "gn:name":"Kosior\u00f3w",
    "gn:population":0,
    "gn:timezone":"Europe/Warsaw",
    "iso:country":"PL",
    "name:fra_x_preferred":[
        "Kosior\u00f3w"
    ],
    "name:pol_x_preferred":[
        "Kosior\u00f3w"
    ],
    "name:ukr_x_preferred":[
        "\u041a\u043e\u0441\u044c\u043e\u0440\u0443\u0432"
    ],
    "name:und_x_variant":[
        "Kosior\u00f3w"
    ],
    "wof:name":"Kosiorow",
    "wof:placetype":"locality"
},
  "geometry": {"coordinates":[19.2851,52.04453],"type":"Point"}
}