{
  "type": "Feature",
  "properties": {
    "gn:admin1_code":"81.0",
    "gn:admin2_code":"2008.0",
    "gn:admin3_code":"200806.0",
    "gn:asciiname":"Zodzie",
    "gn:country_code":"PL",
    "gn:dem":138,
    "gn:feature_class":"P",
    "gn:feature_code":"PPL",
    "gn:name":"Zodzie",
    "gn:population":0,
    "gn:timezone":"Europe/Warsaw",
    "iso:country":"PL",
    "name:fra_x_preferred":[
        "\u017bodzie"
    ],
    "name:ind_x_preferred":[
        "\u017bodzie"
    ],
    "name:lit_x_preferred":[
        "\u017dodziai"
    ],
    "name:pol_x_preferred":[
        "\u017bodzie"
    ],
    "name:ukr_x_preferred":[
        "\u0416\u043e\u0434\u0437\u0435"
    ],
    "wof:name":"Zodzie",
    "wof:placetype":"locality"
},
  "geometry": {"coordinates":[22.73272,53.44009000000001],"type":"Point"}
}