{
  "type": "Feature",
  "properties": {
    "gn:admin1_code":"80.0",
    "gn:admin2_code":"1810.0",
    "gn:admin3_code":"181006.0",
    "gn:asciiname":"Wegliska",
    "gn:country_code":"PL",
    "gn:dem":221,
    "gn:feature_class":"P",
    "gn:feature_code":"PPL",
    "gn:name":"W\u0119gliska",
    "gn:population":0,
    "gn:timezone":"Europe/Warsaw",
    "iso:country":"PL",
    "name:ceb_x_preferred":[
        "W\u0119gliska"
    ],
    "name:pol_x_preferred":[
        "W\u0119gliska"
    ],
    "name:ukr_x_preferred":[
        "\u0412\u0435\u043d\u0491\u043b\u0438\u0441\u044c\u043a\u0430"
    ],
    "wof:name":"Wegliska",
    "wof:placetype":"locality"
},
  "geometry": {"coordinates":[22.20285,50.1648],"type":"Point"}
}