{
  "type": "Feature",
  "properties": {
    "gn:admin1_code":"77.0",
    "gn:admin2_code":"1214.0",
    "gn:admin3_code":"121401.0",
    "gn:asciiname":"Biurkow Wielki",
    "gn:country_code":"PL",
    "gn:dem":252,
    "gn:feature_class":"P",
    "gn:feature_code":"PPL",
    "gn:name":"Biurk\u00f3w Wielki",
    "gn:population":0,
    "gn:timezone":"Europe/Warsaw",
    "iso:country":"PL",
    "name:pol_x_preferred":[
        "Bi\u00f3rk\u00f3w Wielki"
    ],
    "name:rus_x_preferred":[
        "\u0411\u044e\u0440\u043a\u0443\u0432-\u0412\u0435\u043b\u044c\u043a\u0438"
    ],
    "name:ukr_x_preferred":[
        "\u0411\u044e\u0440\u043a\u0443\u0432-\u0412\u0435\u043b\u0438\u043a\u0438\u0439"
    ],
    "name:und_x_variant":[
        "Biurk\u00f3w Wielki"
    ],
    "wof:name":"Biurkow Wielki",
    "wof:placetype":"locality"
},
  "geometry": {"coordinates":[20.17526,50.16977],"type":"Point"}
}