{
  "type": "Feature",
  "properties": {
    "gn:admin1_code":"86.0",
    "gn:admin2_code":"3009.0",
    "gn:admin3_code":"300902.0",
    "gn:asciiname":"Zakrzewo",
    "gn:country_code":"PL",
    "gn:dem":115,
    "gn:feature_class":"P",
    "gn:feature_code":"PPL",
    "gn:name":"Zakrzewo",
    "gn:population":0,
    "gn:timezone":"Europe/Warsaw",
    "iso:country":"PL",
    "name:ceb_x_preferred":[
        "Zakrzewo"
    ],
    "name:pol_x_preferred":[
        "Zakrzewo"
    ],
    "name:ukr_x_preferred":[
        "\u0417\u0430\u043a\u0448\u0435\u0432\u043e"
    ],
    "wof:name":"Zakrzewo",
    "wof:placetype":"locality"
},
  "geometry": {"coordinates":[18.64672,52.37004],"type":"Point"}
}