{
  "type": "Feature",
  "properties": {
    "gn:admin1_code":"82.0",
    "gn:admin2_code":"2204.0",
    "gn:admin3_code":"220407.0",
    "gn:asciiname":"Grabiny-Zameczek",
    "gn:country_code":"PL",
    "gn:dem":6,
    "gn:feature_class":"P",
    "gn:feature_code":"PPL",
    "gn:name":"Grabiny-Zameczek",
    "gn:population":0,
    "gn:timezone":"Europe/Warsaw",
    "iso:country":"PL",
    "name:und_x_variant":[
        "M\u00f6nchengrebin",
        "Grabiny-Zameczek"
    ],
    "wof:name":"Grabiny-Zameczek",
    "wof:placetype":"locality"
},
  "geometry": {"coordinates":[18.74819,54.23743],"type":"Point"}
}