{
  "type": "Feature",
  "properties": {
    "gn:admin1_code":"73.0",
    "gn:admin2_code":"404.0",
    "gn:admin3_code":"40403.0",
    "gn:asciiname":"Kosowizna",
    "gn:country_code":"PL",
    "gn:dem":85,
    "gn:feature_class":"P",
    "gn:feature_code":"PPL",
    "gn:name":"Kosowizna",
    "gn:population":0,
    "gn:timezone":"Europe/Warsaw",
    "iso:country":"PL",
    "name:und_x_variant":[
        "Kossowisna",
        "Kosowizna"
    ],
    "wof:name":"Kosowizna",
    "wof:placetype":"locality"
},
  "geometry": {"coordinates":[18.43845,53.28189],"type":"Point"}
}