{
  "type": "Feature",
  "properties": {
    "gn:population":2604,
    "iso:country":"PL",
    "name:azb_x_preferred":[
        "\u0642\u0645\u06cc\u0646\u0627 \u0648\u0648\u06a9\u0648\u0648\u0627"
    ],
    "name:bel_x_preferred":[
        "\u0413\u043c\u0456\u043d\u0430 \u041b\u0443\u043a\u043e\u0432\u0430"
    ],
    "name:deu_x_preferred":[
        "Gmina \u0141ukowa"
    ],
    "name:eng_x_preferred":[
        "Gmina \u0141ukowa"
    ],
    "name:eus_x_preferred":[
        "\u0141ukowa udalerria"
    ],
    "name:fas_x_preferred":[
        "\u06af\u0645\u06cc\u0646\u0627 \u0648\u0648\u06a9\u0648\u0648\u0627"
    ],
    "name:fra_x_preferred":[
        "\u0141ukowa"
    ],
    "name:ita_x_preferred":[
        "\u0141ukowa"
    ],
    "name:nan_x_preferred":[
        "\u0141ukowa"
    ],
    "name:nld_x_preferred":[
        "\u0141ukowa"
    ],
    "name:pol_x_preferred":[
        "\u0141ukowa"
    ],
    "name:por_x_preferred":[
        "Comuna de \u0141ukowa"
    ],
    "name:rus_x_preferred":[
        "\u041b\u0443\u043a\u043e\u0432\u0430"
    ],
    "name:slk_x_preferred":[
        "Gmina \u0141ukowa"
    ],
    "name:ukr_x_preferred":[
        "\u0490\u043c\u0456\u043d\u0430 \u041b\u0443\u043a\u043e\u0432\u0430"
    ],
    "name:war_x_preferred":[
        "Gmina \u0141ukowa"
    ],
    "qs:a0":"Rzeczpospolita Polska",
    "qs:a1":"*Lubelskie",
    "qs:a1r":"0",
    "qs:a2":"Bilgorajski",
    "qs:adm0":"Rzeczpospolita Polska",
    "qs:la":"\u0141ukowa",
    "qs:la_lc":"*PL0602092",
    "qs:level":"locality",
    "qs:loc":"\u0141ukowa",
    "qs:loc_alt":"Lukowa",
    "qs:pop":0,
    "qs:type":"rural point-in-poly",
    "wd:wordcount":121,
    "wof:coterminous":[
        1125416089
    ],
    "wof:name":"\u0141ukowa",
    "wof:placetype":"locality",
    "wof:population":2604
},
  "geometry": {"coordinates":[22.9526304855179,50.3959174280679],"type":"Point"}
}