{
  "type": "Feature",
  "properties": {
    "gn:admin1_code":"78.0",
    "gn:admin2_code":"1409.0",
    "gn:admin3_code":"140901.0",
    "gn:asciiname":"Chotcza Gorna",
    "gn:country_code":"PL",
    "gn:dem":140,
    "gn:feature_class":"P",
    "gn:feature_code":"PPL",
    "gn:name":"Chotcza G\u00f3rna",
    "gn:population":0,
    "gn:timezone":"Europe/Warsaw",
    "iso:country":"PL",
    "name:fra_x_preferred":[
        "Chotcza G\u00f3rna"
    ],
    "name:pol_x_preferred":[
        "Chotcza G\u00f3rna"
    ],
    "name:ukr_x_preferred":[
        "\u0425\u043e\u0442\u0447\u0430-\u0490\u0443\u0440\u043d\u0430"
    ],
    "wof:name":"Chotcza Gorna",
    "wof:placetype":"locality"
},
  "geometry": {"coordinates":[21.76683,51.23946],"type":"Point"}
}