{
  "type": "Feature",
  "properties": {
    "gn:admin1_code":"78.0",
    "gn:admin2_code":"1409.0",
    "gn:admin3_code":"140901.0",
    "gn:asciiname":"Chotcza Gorna",
    "gn:country_code":"PL",
    "gn:dem":140,
    "gn:feature_class":"P",
    "gn:feature_code":"PPL",
    "gn:name":"Chotcza G\u00f3rna",
    "gn:population":0,
    "gn:timezone":"Europe/Warsaw",
    "iso:country":"PL",
    "wof:name":"Chotcza Gorna",
    "wof:placetype":"locality"
},
  "geometry": {"coordinates":[21.76683,51.23946],"type":"Point"}
}