{
  "type": "Feature",
  "properties": {
    "gn:admin1_code":"75.0",
    "gn:admin2_code":"611.0",
    "gn:admin3_code":"61107.0",
    "gn:asciiname":"Jeleniec",
    "gn:country_code":"PL",
    "gn:dem":161,
    "gn:feature_class":"P",
    "gn:feature_code":"PPL",
    "gn:name":"Jeleniec",
    "gn:population":0,
    "gn:timezone":"Europe/Warsaw",
    "iso:country":"PL",
    "name:ceb_x_preferred":[
        "Jeleniec"
    ],
    "name:fra_x_preferred":[
        "Jeleniec"
    ],
    "name:pol_x_preferred":[
        "Jeleniec"
    ],
    "name:ukr_x_preferred":[
        "\u0404\u043b\u0435\u043d\u0435\u0446\u044c"
    ],
    "wof:name":"Jeleniec",
    "wof:placetype":"locality"
},
  "geometry": {"coordinates":[22.26447000000001,51.86311],"type":"Point"}
}