{
  "type": "Feature",
  "properties": {
    "gn:admin1_code":"75.0",
    "gn:admin2_code":"663.0",
    "gn:admin3_code":"66301.0",
    "gn:asciiname":"Weglin Poludniowy",
    "gn:country_code":"PL",
    "gn:dem":223,
    "gn:feature_class":"P",
    "gn:feature_code":"PPL",
    "gn:name":"W\u0119glin Po\u0142udniowy",
    "gn:population":0,
    "gn:timezone":"Europe/Warsaw",
    "iso:country":"PL",
    "wof:name":"Weglin Poludniowy",
    "wof:placetype":"locality"
},
  "geometry": {"coordinates":[22.47494,51.23488],"type":"Point"}
}