{
  "type": "Feature",
  "properties": {
    "gn:admin1_code":"86.0",
    "gn:admin2_code":"3011.0",
    "gn:admin3_code":"301103.0",
    "gn:asciiname":"Widziszewo",
    "gn:country_code":"PL",
    "gn:dem":81,
    "gn:feature_class":"P",
    "gn:feature_code":"PPL",
    "gn:name":"Widziszewo",
    "gn:population":0,
    "gn:timezone":"Europe/Warsaw",
    "iso:country":"PL",
    "name:ceb_x_preferred":[
        "Widziszewo"
    ],
    "name:fra_x_preferred":[
        "Widziszewo"
    ],
    "name:pol_x_preferred":[
        "Widziszewo"
    ],
    "name:ukr_x_preferred":[
        "\u0412\u0456\u0434\u0437\u0456\u0448\u0435\u0432\u043e"
    ],
    "wof:name":"Widziszewo",
    "wof:placetype":"locality"
},
  "geometry": {"coordinates":[16.6002,52.03925],"type":"Point"}
}