{
  "type": "Feature",
  "properties": {
    "gn:admin1_code":"74.0",
    "gn:admin2_code":"1020.0",
    "gn:admin3_code":"102008.0",
    "gn:asciiname":"Dobra Nowiny",
    "gn:country_code":"PL",
    "gn:dem":219,
    "gn:feature_class":"P",
    "gn:feature_code":"PPL",
    "gn:name":"Dobra Nowiny",
    "gn:population":0,
    "gn:timezone":"Europe/Warsaw",
    "iso:country":"PL",
    "name:pol_x_preferred":[
        "Dobra-Nowiny"
    ],
    "name:ukr_x_preferred":[
        "\u0414\u043e\u0431\u0440\u0430-\u041d\u043e\u0432\u0456\u043d\u0438"
    ],
    "wof:name":"Dobra Nowiny",
    "wof:placetype":"locality"
},
  "geometry": {"coordinates":[19.54524,51.85338],"type":"Point"}
}