{
  "type": "Feature",
  "properties": {
    "gn:admin1_code":"84.0",
    "gn:admin2_code":"2612.0",
    "gn:admin3_code":"261203.0",
    "gn:asciiname":"Sufczyce",
    "gn:country_code":"PL",
    "gn:dem":177,
    "gn:feature_class":"P",
    "gn:feature_code":"PPL",
    "gn:name":"Sufczyce",
    "gn:population":0,
    "gn:timezone":"Europe/Warsaw",
    "iso:country":"PL",
    "name:pol_x_preferred":[
        "Sufczyce"
    ],
    "name:ukr_x_preferred":[
        "\u0421\u0443\u0444\u0447\u0438\u0446\u0435"
    ],
    "wof:name":"Sufczyce",
    "wof:placetype":"locality"
},
  "geometry": {"coordinates":[21.07452,50.46985],"type":"Point"}
}