{
  "type": "Feature",
  "properties": {
    "gn:admin1_code":"78.0",
    "gn:admin2_code":"1435.0",
    "gn:admin3_code":"143504.0",
    "gn:asciiname":"Skorki",
    "gn:country_code":"PL",
    "gn:dem":109,
    "gn:feature_class":"P",
    "gn:feature_code":"PPL",
    "gn:name":"Skorki",
    "gn:population":0,
    "gn:timezone":"Europe/Warsaw",
    "iso:country":"PL",
    "name:fra_x_preferred":[
        "Skorki"
    ],
    "name:pol_x_preferred":[
        "Skorki"
    ],
    "name:ukr_x_preferred":[
        "\u0421\u043a\u043e\u0440\u043a\u0456"
    ],
    "wof:name":"Skorki",
    "wof:placetype":"locality"
},
  "geometry": {"coordinates":[21.29254,52.61081],"type":"Point"}
}