{
  "type": "Feature",
  "properties": {
    "gn:admin1_code":"87.0",
    "gn:admin2_code":"3218.0",
    "gn:admin3_code":"321802.0",
    "gn:asciiname":"Klepnica",
    "gn:country_code":"PL",
    "gn:dem":83,
    "gn:feature_class":"P",
    "gn:feature_code":"PPL",
    "gn:name":"Klepnica",
    "gn:population":0,
    "gn:timezone":"Europe/Warsaw",
    "iso:country":"PL",
    "name:pol_x_preferred":[
        "Kl\u0119pnica"
    ],
    "name:ukr_x_preferred":[
        "\u041a\u043b\u0435\u043c\u043f\u043d\u0438\u0446\u044f"
    ],
    "name:vie_x_preferred":[
        "Kl\u0119pnica"
    ],
    "wof:name":"Klepnica",
    "wof:placetype":"locality"
},
  "geometry": {"coordinates":[15.64078,53.73064],"type":"Point"}
}