{
  "type": "Feature",
  "properties": {
    "gn:admin1_code":"87.0",
    "gn:admin2_code":"3218.0",
    "gn:admin3_code":"321802.0",
    "gn:asciiname":"Klepnica",
    "gn:country_code":"PL",
    "gn:dem":83,
    "gn:feature_class":"P",
    "gn:feature_code":"PPL",
    "gn:name":"Klepnica",
    "gn:population":0,
    "gn:timezone":"Europe/Warsaw",
    "iso:country":"PL",
    "wof:name":"Klepnica",
    "wof:placetype":"locality"
},
  "geometry": {"coordinates":[15.64078,53.73064],"type":"Point"}
}