{
  "type": "Feature",
  "properties": {
    "gn:admin1_code":"74.0",
    "gn:admin2_code":"1020.0",
    "gn:admin3_code":"102008.0",
    "gn:asciiname":"Imielnik Stary",
    "gn:country_code":"PL",
    "gn:dem":187,
    "gn:feature_class":"P",
    "gn:feature_code":"PPL",
    "gn:name":"Imielnik Stary",
    "gn:population":0,
    "gn:timezone":"Europe/Warsaw",
    "iso:country":"PL",
    "name:pol_x_preferred":[
        "Stary Imielnik"
    ],
    "name:ukr_x_preferred":[
        "\u0421\u0442\u0430\u0440\u0438\u0439 \u0406\u043c\u0435\u043b\u044c\u043d\u0438\u043a"
    ],
    "wof:name":"Imielnik Stary",
    "wof:placetype":"locality"
},
  "geometry": {"coordinates":[19.57323,51.8462],"type":"Point"}
}