{
  "type": "Feature",
  "properties": {
    "gn:admin1_code":"74.0",
    "gn:admin2_code":"1013.0",
    "gn:admin3_code":"101303.0",
    "gn:asciiname":"Mala Wies",
    "gn:country_code":"PL",
    "gn:dem":154,
    "gn:feature_class":"P",
    "gn:feature_code":"PPL",
    "gn:name":"Ma\u0142a Wie\u015b",
    "gn:population":0,
    "gn:timezone":"Europe/Warsaw",
    "iso:country":"PL",
    "name:pol_x_preferred":[
        "Ma\u0142a Wie\u015b"
    ],
    "name:ukr_x_preferred":[
        "\u041c\u0430\u043b\u0430 \u0412\u0435\u0441\u044c"
    ],
    "wof:name":"Mala Wies",
    "wof:placetype":"locality"
},
  "geometry": {"coordinates":[20.32488,51.67884],"type":"Point"}
}