{
  "type": "Feature",
  "properties": {
    "gn:admin1_code":"78.0",
    "gn:admin2_code":"1425.0",
    "gn:admin3_code":"142509.0",
    "gn:asciiname":"Sukow",
    "gn:country_code":"PL",
    "gn:dem":155,
    "gn:feature_class":"P",
    "gn:feature_code":"PPL",
    "gn:name":"Suk\u00f3w",
    "gn:population":0,
    "gn:timezone":"Europe/Warsaw",
    "iso:country":"PL",
    "name:fra_x_preferred":[
        "Suk\u00f3w"
    ],
    "name:pol_x_preferred":[
        "Suk\u00f3w"
    ],
    "name:ukr_x_preferred":[
        "\u0421\u0443\u043a\u0443\u0432"
    ],
    "wof:name":"Sukow",
    "wof:placetype":"locality"
},
  "geometry": {"coordinates":[20.92384,51.49373],"type":"Point"}
}