{
  "type": "Feature",
  "properties": {
    "gn:admin1_code":"81.0",
    "gn:admin2_code":"2007.0",
    "gn:admin3_code":"200708.0",
    "gn:asciiname":"Kramkowo",
    "gn:country_code":"PL",
    "gn:dem":111,
    "gn:feature_class":"P",
    "gn:feature_code":"PPL",
    "gn:name":"Kramkowo",
    "gn:population":0,
    "gn:timezone":"Europe/Warsaw",
    "iso:country":"PL",
    "name:lit_x_preferred":[
        "Kramkovas"
    ],
    "name:pol_x_preferred":[
        "Kramkowo"
    ],
    "name:ukr_x_preferred":[
        "\u041a\u0440\u0430\u043c\u043a\u043e\u0432\u043e"
    ],
    "wof:name":"Kramkowo",
    "wof:placetype":"locality"
},
  "geometry": {"coordinates":[22.3407,53.18546],"type":"Point"}
}