{
  "type": "Feature",
  "properties": {
    "gn:admin1_code":"78.0",
    "gn:admin2_code":"1423.0",
    "gn:admin3_code":"142308.0",
    "gn:asciiname":"Zukow",
    "gn:country_code":"PL",
    "gn:dem":179,
    "gn:feature_class":"P",
    "gn:feature_code":"PPL",
    "gn:name":"\u017buk\u00f3w",
    "gn:population":0,
    "gn:timezone":"Europe/Warsaw",
    "iso:country":"PL",
    "name:fra_x_preferred":[
        "\u017buk\u00f3w"
    ],
    "name:pol_x_preferred":[
        "\u017buk\u00f3w"
    ],
    "name:ukr_x_preferred":[
        "\u0416\u0443\u043a\u0443\u0432"
    ],
    "wof:name":"Zukow",
    "wof:placetype":"locality"
},
  "geometry": {"coordinates":[20.74425,51.33935],"type":"Point"}
}