{
  "type": "Feature",
  "properties": {
    "gn:admin1_code":"87.0",
    "gn:admin2_code":"3210.0",
    "gn:admin3_code":"321002.0",
    "gn:asciiname":"Chwarszczany",
    "gn:country_code":"PL",
    "gn:dem":26,
    "gn:feature_class":"P",
    "gn:feature_code":"PPL",
    "gn:name":"Chwarszczany",
    "gn:population":0,
    "gn:timezone":"Europe/Warsaw",
    "iso:country":"PL",
    "name:und_x_variant":[
        "Quartschen",
        "Chwarszczany"
    ],
    "wof:name":"Chwarszczany",
    "wof:placetype":"locality"
},
  "geometry": {"coordinates":[14.63808,52.68741],"type":"Point"}
}