{
  "type": "Feature",
  "properties": {
    "gn:admin1_code":"87.0",
    "gn:admin2_code":"3210.0",
    "gn:admin3_code":"321002.0",
    "gn:asciiname":"Chwarszczany",
    "gn:country_code":"PL",
    "gn:dem":26,
    "gn:feature_class":"P",
    "gn:feature_code":"PPL",
    "gn:name":"Chwarszczany",
    "gn:population":0,
    "gn:timezone":"Europe/Warsaw",
    "iso:country":"PL",
    "name:azb_x_preferred":[
        "\u062e\u0648\u0627\u0631\u0634\u0686\u0627\u0646\u0647"
    ],
    "name:ceb_x_preferred":[
        "Chwarszczany"
    ],
    "name:deu_x_preferred":[
        "Chwarszczany"
    ],
    "name:fas_x_preferred":[
        "\u062e\u0648\u0627\u0631\u0634\u0686\u0627\u0646\u0647"
    ],
    "name:nld_x_preferred":[
        "Chwarszczany"
    ],
    "name:pol_x_preferred":[
        "Chwarszczany"
    ],
    "name:ukr_x_preferred":[
        "\u0425\u0432\u0430\u0440\u0449\u0430\u043d\u0438"
    ],
    "name:und_x_variant":[
        "Quartschen"
    ],
    "name:vie_x_preferred":[
        "Chwarszczany"
    ],
    "wof:name":"Chwarszczany",
    "wof:placetype":"locality"
},
  "geometry": {"coordinates":[14.63808,52.68741],"type":"Point"}
}