{
  "type": "Feature",
  "properties": {
    "gn:admin1_code":"84.0",
    "gn:admin2_code":"2612.0",
    "gn:admin3_code":"261207.0",
    "gn:asciiname":"Laziska",
    "gn:country_code":"PL",
    "gn:dem":217,
    "gn:feature_class":"P",
    "gn:feature_code":"PPL",
    "gn:name":"\u0141aziska",
    "gn:population":0,
    "gn:timezone":"Europe/Warsaw",
    "iso:country":"PL",
    "name:pol_x_preferred":[
        "\u0141aziska"
    ],
    "name:ukr_x_preferred":[
        "\u041b\u0430\u0437\u0438\u0441\u044c\u043a\u0430"
    ],
    "wof:name":"Laziska",
    "wof:placetype":"locality"
},
  "geometry": {"coordinates":[21.26476,50.61429],"type":"Point"}
}