{
  "type": "Feature",
  "properties": {
    "gn:admin1_code":"74.0",
    "gn:asciiname":"Kuklowka Zarzeczna",
    "gn:country_code":"PL",
    "gn:dem":132,
    "gn:feature_class":"P",
    "gn:feature_code":"PPL",
    "gn:name":"Kukl\u00f3wka Zarzeczna",
    "gn:population":0,
    "gn:timezone":"Europe/Warsaw",
    "iso:country":"PL",
    "name:azb_x_preferred":[
        "\u06a9\u0648\u06a9\u0644\u0648\u0648\u06a9\u0627 \u0632\u0627\u0698\u0686\u0646\u0627"
    ],
    "name:fas_x_preferred":[
        "\u06a9\u0648\u06a9\u0644\u0648\u0648\u06a9\u0627 \u0632\u0627\u0698\u0686\u0646\u0627"
    ],
    "name:fra_x_preferred":[
        "Kukl\u00f3wka Zarzeczna"
    ],
    "name:pol_x_preferred":[
        "Kukl\u00f3wka Zarzeczna"
    ],
    "name:ukr_x_preferred":[
        "\u041a\u0443\u043a\u043b\u044e\u0432\u043a\u0430-\u0417\u0430\u0436\u0435\u0447\u043d\u0430"
    ],
    "wof:name":"Kuklowka Zarzeczna",
    "wof:placetype":"locality"
},
  "geometry": {"coordinates":[20.59507,52.04758],"type":"Point"}
}