{
  "type": "Feature",
  "properties": {
    "gn:admin1_code":"74.0",
    "gn:asciiname":"Kuklowka Zarzeczna",
    "gn:country_code":"PL",
    "gn:dem":132,
    "gn:feature_class":"P",
    "gn:feature_code":"PPL",
    "gn:name":"Kukl\u00f3wka Zarzeczna",
    "gn:population":0,
    "gn:timezone":"Europe/Warsaw",
    "iso:country":"PL",
    "wof:name":"Kuklowka Zarzeczna",
    "wof:placetype":"locality"
},
  "geometry": {"coordinates":[20.59507,52.04758],"type":"Point"}
}