{
  "type": "Feature",
  "properties": {
    "iso:country":"PL",
    "name:azb_x_preferred":[
        "\u0642\u0631\u0648\u062f\u06a9 \u0646\u0627\u062f \u062f\u0648\u0646\u0627\u06cc\u062a\u0633\u0645"
    ],
    "name:deu_x_preferred":[
        "Gr\u00f3dek nad Dunajcem"
    ],
    "name:fas_x_preferred":[
        "\u06af\u0631\u0648\u062f\u06a9 \u0646\u0627\u062f \u062f\u0648\u0646\u0627\u06cc\u062a\u0633\u0645"
    ],
    "name:pol_x_preferred":[
        "Gr\u00f3dek nad Dunajcem"
    ],
    "name:ukr_x_preferred":[
        "\u0413\u0440\u0443\u0434\u0435\u043a-\u043d\u0430\u0434-\u0414\u0443\u043d\u0430\u0439\u0446\u0435\u043c"
    ],
    "qs_pg:aaroncc":"PL",
    "qs_pg:name":"Gr\u00f3dek nad Dunajcem",
    "qs_pg:name_adm0":"Polska",
    "qs_pg:name_adm1":"Ma\u0142opolskie",
    "qs_pg:photos":21,
    "qs_pg:photos_1k":4,
    "qs_pg:photos_9k":1,
    "qs_pg:photos_9r":1,
    "qs_pg:photos_all":21,
    "qs_pg:photos_sr":1,
    "qs_pg:pop_sr":0,
    "qs_pg:qs_pg_placetype":"localadmin",
    "qs_pg:qs_pg_placetype_gp":"LocalAdmin",
    "qs_pg:woe_adm0":23424923,
    "woe:adm0_id":23424923,
    "woe:name_adm0":"Polska",
    "woe:name_adm1":"Ma\u0142opolskie",
    "woe:placetype":"LocalAdmin",
    "wof:name":"Gr\u00f3dek nad Dunajcem",
    "wof:placetype":"localadmin"
},
  "geometry": {"coordinates":[20.42624,49.44081],"type":"Point"}
}