{
  "type": "Feature",
  "properties": {
    "gn:admin1_code":"81.0",
    "gn:admin2_code":"2005.0",
    "gn:admin3_code":"200506.0",
    "gn:asciiname":"Kotowka",
    "gn:country_code":"PL",
    "gn:dem":174,
    "gn:feature_class":"P",
    "gn:feature_code":"PPL",
    "gn:name":"Kot\u00f3wka",
    "gn:population":0,
    "gn:timezone":"Europe/Warsaw",
    "iso:country":"PL",
    "name:lit_x_preferred":[
        "Kotuvka"
    ],
    "name:pol_x_preferred":[
        "Kot\u00f3wka"
    ],
    "name:ukr_x_preferred":[
        "\u041a\u043e\u0442\u0443\u0432\u043a\u0430"
    ],
    "name:und_x_variant":[
        "Kot\u00f3wka"
    ],
    "wof:name":"Kotowka",
    "wof:placetype":"locality"
},
  "geometry": {"coordinates":[23.56486,52.80813000000001],"type":"Point"}
}