{
  "type": "Feature",
  "properties": {
    "gn:admin1_code":"78.0",
    "gn:admin2_code":"1410.0",
    "gn:admin3_code":"141004.0",
    "gn:asciiname":"Kolonia Ostromeczyn",
    "gn:country_code":"PL",
    "gn:dem":150,
    "gn:feature_class":"P",
    "gn:feature_code":"PPL",
    "gn:name":"Kolonia Ostrom\u0119czyn",
    "gn:population":0,
    "gn:timezone":"Europe/Warsaw",
    "iso:country":"PL",
    "name:und_x_variant":[
        "Kolonia Ostrom\u0119czyn"
    ],
    "wof:name":"Kolonia Ostromeczyn",
    "wof:placetype":"locality"
},
  "geometry": {"coordinates":[22.82684,52.27619],"type":"Point"}
}