{
  "type": "Feature",
  "properties": {
    "gn:admin1_code":"78.0",
    "gn:admin2_code":"1410.0",
    "gn:admin3_code":"141004.0",
    "gn:asciiname":"Kolonia Ostromeczyn",
    "gn:country_code":"PL",
    "gn:dem":150,
    "gn:feature_class":"P",
    "gn:feature_code":"PPL",
    "gn:name":"Kolonia Ostrom\u0119czyn",
    "gn:population":0,
    "gn:timezone":"Europe/Warsaw",
    "iso:country":"PL",
    "name:fra_x_preferred":[
        "Ostrom\u0119czyn-Kolonia"
    ],
    "name:lit_x_preferred":[
        "Ostromen\u010din Kolonija"
    ],
    "name:pol_x_preferred":[
        "Ostrom\u0119czyn-Kolonia"
    ],
    "name:ukr_x_preferred":[
        "\u041e\u0441\u0442\u0440\u043e\u043c\u0435\u043d\u0447\u0438\u043d-\u041a\u043e\u043b\u044c\u043e\u043d\u0456\u044f"
    ],
    "name:und_x_variant":[
        "Kolonia Ostrom\u0119czyn"
    ],
    "wof:name":"Kolonia Ostromeczyn",
    "wof:placetype":"locality"
},
  "geometry": {"coordinates":[22.82684,52.27619],"type":"Point"}
}