{
  "type": "Feature",
  "properties": {
    "gn:country":"PL",
    "gn:fcode":"PPL",
    "gn:population":640,
    "iso:country":"PL",
    "name:ast_x_preferred":[
        "Trzebiszewo"
    ],
    "name:azb_x_preferred":[
        "\u0686\u0628\u06cc\u0633\u0632\u0626\u0648"
    ],
    "name:ceb_x_preferred":[
        "Trzebiszewo"
    ],
    "name:deu_x_preferred":[
        "Trzebiszewo"
    ],
    "name:eng_x_preferred":[
        "Trzebiszewo"
    ],
    "name:fas_x_preferred":[
        "\u0686\u0628\u06cc\u0633\u0632\u0626\u0648"
    ],
    "name:fra_x_preferred":[
        "Trzebiszewo"
    ],
    "name:nld_x_preferred":[
        "Trzebiszewo"
    ],
    "name:pol_x_preferred":[
        "Trzebiszewo"
    ],
    "name:ukr_x_preferred":[
        "\u0422\u0448\u0435\u0431\u0456\u0448\u0435\u0432\u043e"
    ],
    "qs_pg:aaroncc":"PL",
    "qs_pg:gn_country":"PL",
    "qs_pg:gn_fcode":"PPL",
    "qs_pg:gn_pop":640,
    "qs_pg:name":"Trzebiszewo",
    "qs_pg:name_adm0":"Polska",
    "qs_pg:name_adm1":"Lubuskie",
    "qs_pg:photos_9k":1,
    "qs_pg:photos_9r":1,
    "qs_pg:photos_all":6,
    "qs_pg:photos_sr":0,
    "qs_pg:pop_sr":2,
    "qs_pg:qs_pg_placetype":"locality",
    "qs_pg:qs_pg_placetype_gp":"Town",
    "qs_pg:woe_adm0":23424923,
    "woe:adm0_id":23424923,
    "woe:name_adm0":"Polska",
    "woe:name_adm1":"Lubuskie",
    "woe:placetype":"Town",
    "wof:name":"Trzebiszewo",
    "wof:placetype":"locality",
    "wof:population":640
},
  "geometry": {"coordinates":[15.40026,52.6277],"type":"Point"}
}