{
  "type": "Feature",
  "properties": {
    "gn:admin1_code":"78.0",
    "gn:admin2_code":"1425.0",
    "gn:admin3_code":"142505.0",
    "gn:asciiname":"Wola Grutowska",
    "gn:country_code":"PL",
    "gn:dem":134,
    "gn:feature_class":"P",
    "gn:feature_code":"PPL",
    "gn:name":"Wola Grutowska",
    "gn:population":0,
    "gn:timezone":"Europe/Warsaw",
    "iso:country":"PL",
    "name:und_x_variant":[
        "Wola Gutowska",
        "Wola Grutowska"
    ],
    "wof:name":"Wola Grutowska",
    "wof:placetype":"locality"
},
  "geometry": {"coordinates":[21.09078,51.50793],"type":"Point"}
}