{
  "type": "Feature",
  "properties": {
    "gn:admin1_code":"86.0",
    "gn:admin2_code":"3006.0",
    "gn:admin3_code":"300602.0",
    "gn:asciiname":"Witaszyczki",
    "gn:country_code":"PL",
    "gn:dem":130,
    "gn:feature_class":"P",
    "gn:feature_code":"PPL",
    "gn:name":"Witaszyczki",
    "gn:population":0,
    "gn:timezone":"Europe/Warsaw",
    "iso:country":"PL",
    "wof:name":"Witaszyczki",
    "wof:placetype":"locality"
},
  "geometry": {"coordinates":[17.53333,51.95],"type":"Point"}
}