{
  "type": "Feature",
  "properties": {
    "iso:country":"PL",
    "name:ast_x_preferred":[
        "Wy\u017cne"
    ],
    "name:eng_x_preferred":[
        "Wy\u017cne"
    ],
    "name:fra_x_preferred":[
        "Wy\u017cne"
    ],
    "name:pol_x_preferred":[
        "Wy\u017cne"
    ],
    "name:ukr_x_preferred":[
        "\u0412\u0438\u0436\u043d\u0435"
    ],
    "qs:a0":"Rzeczpospolita Polska",
    "qs:a1":"*Podkarpackie",
    "qs:a1r":"0",
    "qs:a2":"Strzyzowski",
    "qs:adm0":"Rzeczpospolita Polska",
    "qs:la_lc":"*",
    "qs:level":"locality",
    "qs:loc":"Wy\u017cne",
    "qs:loc_alt":"Wyzne",
    "qs:pop":0,
    "qs:type":"buffered point",
    "wd:wordcount":86,
    "wof:name":"Wy\u017cne",
    "wof:placetype":"locality"
},
  "geometry": {"coordinates":[21.877531,49.924022],"type":"Point"}
}