{
  "type": "Feature",
  "properties": {
    "gn:admin1_code":"87.0",
    "gn:admin2_code":"3207.0",
    "gn:admin3_code":"320701.0",
    "gn:asciiname":"Dziwnow Dolny",
    "gn:country_code":"PL",
    "gn:dem":3,
    "gn:feature_class":"P",
    "gn:feature_code":"PPL",
    "gn:name":"Dziwn\u00f3w Dolny",
    "gn:population":0,
    "gn:timezone":"Europe/Warsaw",
    "iso:country":"PL",
    "wof:name":"Dziwnow Dolny",
    "wof:placetype":"locality"
},
  "geometry": {"coordinates":[14.74391,54.02255],"type":"Point"}
}