{
  "type": "Feature",
  "properties": {
    "gn:admin1_code":"84.0",
    "gn:asciiname":"Pieklo",
    "gn:country_code":"PL",
    "gn:dem":275,
    "gn:elevation":"265.0",
    "gn:feature_class":"P",
    "gn:feature_code":"PPL",
    "gn:name":"Piek\u0142o",
    "gn:population":0,
    "gn:timezone":"Europe/Warsaw",
    "iso:country":"PL",
    "wof:name":"Pieklo",
    "wof:placetype":"locality"
},
  "geometry": {"coordinates":[19.9946,50.33924],"type":"Point"}
}