{
  "type": "Feature",
  "properties": {
    "gn:admin1_code":"78.0",
    "gn:admin2_code":"1438.0",
    "gn:admin3_code":"143803.0",
    "gn:asciiname":"Bednary",
    "gn:country_code":"PL",
    "gn:dem":124,
    "gn:feature_class":"P",
    "gn:feature_code":"PPL",
    "gn:name":"Bednary",
    "gn:population":0,
    "gn:timezone":"Europe/Warsaw",
    "iso:country":"PL",
    "name:fra_x_preferred":[
        "Bednary"
    ],
    "name:pol_x_preferred":[
        "Bednary"
    ],
    "name:ukr_x_preferred":[
        "\u0411\u0435\u0434\u043d\u0430\u0440\u0438"
    ],
    "wof:name":"Bednary",
    "wof:placetype":"locality"
},
  "geometry": {"coordinates":[20.3944,52.02234],"type":"Point"}
}