{
  "type": "Feature",
  "properties": {
    "gn:admin1_code":"72.0",
    "gn:admin2_code":"219.0",
    "gn:admin3_code":"21907.0",
    "gn:asciiname":"Wilkow",
    "gn:country_code":"PL",
    "gn:dem":216,
    "gn:feature_class":"P",
    "gn:feature_code":"PPL",
    "gn:name":"Wilk\u00f3w",
    "gn:population":0,
    "gn:timezone":"Europe/Warsaw",
    "iso:country":"PL",
    "name:pol_x_preferred":[
        "Wilk\u00f3w"
    ],
    "name:ukr_x_preferred":[
        "\u0412\u0456\u043b\u044c\u043a\u0443\u0432"
    ],
    "wof:name":"Wilkow",
    "wof:placetype":"locality"
},
  "geometry": {"coordinates":[16.54086,50.86794],"type":"Point"}
}