{
  "type": "Feature",
  "properties": {
    "gn:gn_country":"PL",
    "gn:gn_fcode":"PPL",
    "gn:gn_pop":1005,
    "gn:population":1005,
    "iso:country":"PL",
    "name:ceb_x_preferred":[
        "Zaborze"
    ],
    "name:deu_x_preferred":[
        "Zaborze"
    ],
    "name:fra_x_preferred":[
        "Zaborze"
    ],
    "name:pol_x_preferred":[
        "Zaborze"
    ],
    "name:ukr_x_preferred":[
        "\u0417\u0430\u0431\u043e\u0436\u0435"
    ],
    "qs_pg:aaroncc":"PL",
    "qs_pg:gn_country":"PL",
    "qs_pg:gn_fcode":"PPL",
    "qs_pg:gn_pop":1005,
    "qs_pg:name":"Zaborze",
    "qs_pg:name_adm0":"Polska",
    "qs_pg:name_adm1":"Sl\u0105skie",
    "qs_pg:photos_9r":0,
    "qs_pg:photos_sr":0,
    "qs_pg:pop_sr":3,
    "qs_pg:qs_pg_placetype":"locality",
    "qs_pg:qs_pg_placetype_gp":"Town",
    "qs_pg:woe_adm0":23424923,
    "woe:adm0_id":23424923,
    "woe:name_adm0":"Polska",
    "woe:name_adm1":"Sl\u0105skie",
    "woe:placetype":"Town",
    "wof:name":"Zaborze",
    "wof:placetype":"locality",
    "wof:population":1005
},
  "geometry": {"coordinates":[18.8037,49.87279],"type":"Point"}
}