{
  "type": "Feature",
  "properties": {
    "gn:admin1_code":"77.0",
    "gn:admin2_code":"1206.0",
    "gn:admin3_code":"120604.0",
    "gn:asciiname":"Gotkowice",
    "gn:country_code":"PL",
    "gn:dem":457,
    "gn:feature_class":"P",
    "gn:feature_code":"PPL",
    "gn:name":"Gotkowice",
    "gn:population":0,
    "gn:timezone":"Europe/Warsaw",
    "iso:country":"PL",
    "name:pol_x_preferred":[
        "Gotkowice"
    ],
    "name:rus_x_preferred":[
        "\u0413\u043e\u0442\u043a\u043e\u0432\u0438\u0446\u0435"
    ],
    "name:ukr_x_preferred":[
        "\u0490\u043e\u0442\u043a\u043e\u0432\u0456\u0446\u0435"
    ],
    "wof:name":"Gotkowice",
    "wof:placetype":"locality"
},
  "geometry": {"coordinates":[19.73667,50.22849],"type":"Point"}
}