{
  "type": "Feature",
  "properties": {
    "gn:admin1_code":"76.0",
    "gn:admin2_code":"801.0",
    "gn:admin3_code":"80102.0",
    "gn:asciiname":"Kwiatkowice",
    "gn:country_code":"PL",
    "gn:dem":17,
    "gn:feature_class":"P",
    "gn:feature_code":"PPL",
    "gn:name":"Kwiatkowice",
    "gn:population":0,
    "gn:timezone":"Europe/Warsaw",
    "iso:country":"PL",
    "name:ceb_x_preferred":[
        "Kwiatkowice"
    ],
    "name:deu_x_historical":[
        "Blumenthal"
    ],
    "name:deu_x_preferred":[
        "Blumenthal"
    ],
    "name:fra_x_preferred":[
        "Kwiatkowice"
    ],
    "name:pol_x_preferred":[
        "Kwiatkowice"
    ],
    "name:ukr_x_preferred":[
        "\u041a\u0432\u044f\u0442\u043a\u043e\u0432\u0456\u0446\u0435"
    ],
    "wof:name":"Kwiatkowice",
    "wof:placetype":"locality"
},
  "geometry": {"coordinates":[15.0888,52.66838000000001],"type":"Point"}
}