{
  "type": "Feature",
  "properties": {
    "gn:admin1_code":"74.0",
    "gn:admin2_code":"1018.0",
    "gn:admin3_code":"101806.0",
    "gn:asciiname":"Szustry",
    "gn:country_code":"PL",
    "gn:dem":160,
    "gn:feature_class":"P",
    "gn:feature_code":"PPL",
    "gn:name":"Szustry",
    "gn:population":0,
    "gn:timezone":"Europe/Warsaw",
    "iso:country":"PL",
    "name:pol_x_preferred":[
        "Szustry"
    ],
    "wof:name":"Szustry",
    "wof:placetype":"locality"
},
  "geometry": {"coordinates":[18.37141,51.34289],"type":"Point"}
}