{
  "type": "Feature",
  "properties": {
    "gn:admin1_code":"80.0",
    "gn:admin2_code":"1817.0",
    "gn:admin3_code":"181706.0",
    "gn:asciiname":"Holuczkow",
    "gn:country_code":"PL",
    "gn:dem":306,
    "gn:feature_class":"P",
    "gn:feature_code":"PPL",
    "gn:name":"Ho\u0142uczk\u00f3w",
    "gn:population":0,
    "gn:timezone":"Europe/Warsaw",
    "iso:country":"PL",
    "name:azb_x_preferred":[
        "\u062e\u0648\u0648\u0648\u0686\u06a9\u0648\u0648"
    ],
    "name:ceb_x_preferred":[
        "Ho\u0142uczk\u00f3w"
    ],
    "name:fas_x_preferred":[
        "\u062e\u0648\u0648\u0648\u0686\u06a9\u0648\u0648"
    ],
    "name:nld_x_preferred":[
        "Ho\u0142uczk\u00f3w"
    ],
    "name:pol_x_preferred":[
        "Ho\u0142uczk\u00f3w"
    ],
    "name:rue_x_preferred":[
        "\u0413\u043e\u043b\u0443\u0447\u043a\u0456\u0432"
    ],
    "name:ukr_x_preferred":[
        "\u0413\u043e\u043b\u0443\u0447\u043a\u0456\u0432"
    ],
    "wof:name":"Holuczkow",
    "wof:placetype":"locality"
},
  "geometry": {"coordinates":[22.34001,49.58979],"type":"Point"}
}