{
  "type": "Feature",
  "properties": {
    "gn:admin1_code":"78.0",
    "gn:admin2_code":"1419.0",
    "gn:admin3_code":"141915.0",
    "gn:asciiname":"Rebowo",
    "gn:country_code":"PL",
    "gn:dem":92,
    "gn:feature_class":"P",
    "gn:feature_code":"PPL",
    "gn:name":"R\u0119bowo",
    "gn:population":0,
    "gn:timezone":"Europe/Warsaw",
    "iso:country":"PL",
    "name:ceb_x_preferred":[
        "R\u0119bowo"
    ],
    "name:fra_x_preferred":[
        "R\u0119bowo"
    ],
    "name:pol_x_preferred":[
        "R\u0119bowo"
    ],
    "name:ukr_x_preferred":[
        "\u0420\u0435\u043c\u0431\u043e\u0432\u043e"
    ],
    "name:und_x_variant":[
        "R\u0119bowo"
    ],
    "wof:name":"Rebowo",
    "wof:placetype":"locality"
},
  "geometry": {"coordinates":[20.19286,52.41153],"type":"Point"}
}