{
  "type": "Feature",
  "properties": {
    "gn:admin1_code":"78.0",
    "gn:admin2_code":"1415.0",
    "gn:admin3_code":"141501.0",
    "gn:asciiname":"Witowy Most",
    "gn:country_code":"PL",
    "gn:dem":110,
    "gn:feature_class":"P",
    "gn:feature_code":"PPL",
    "gn:name":"Witowy Most",
    "gn:population":0,
    "gn:timezone":"Europe/Warsaw",
    "iso:country":"PL",
    "name:fra_x_preferred":[
        "Witowy Most"
    ],
    "name:pol_x_preferred":[
        "Witowy Most"
    ],
    "name:ukr_x_preferred":[
        "\u0412\u0456\u0442\u043e\u0432\u0438-\u041c\u043e\u0441\u0442"
    ],
    "wof:name":"Witowy Most",
    "wof:placetype":"locality"
},
  "geometry": {"coordinates":[21.30248,53.12124],"type":"Point"}
}