{
  "type": "Feature",
  "properties": {
    "gn:admin1_code":"74.0",
    "gn:admin2_code":"1012.0",
    "gn:admin3_code":"101202.0",
    "gn:asciiname":"Zaby",
    "gn:country_code":"PL",
    "gn:dem":203,
    "gn:feature_class":"P",
    "gn:feature_code":"PPL",
    "gn:name":"\u017baby",
    "gn:population":0,
    "gn:timezone":"Europe/Warsaw",
    "iso:country":"PL",
    "name:fra_x_preferred":[
        "\u017baby"
    ],
    "name:pol_x_preferred":[
        "\u017baby"
    ],
    "name:ukr_x_preferred":[
        "\u0416\u0430\u0431\u0438"
    ],
    "wof:name":"Zaby",
    "wof:placetype":"locality"
},
  "geometry": {"coordinates":[19.40872,51.17407],"type":"Point"}
}