{
  "type": "Feature",
  "properties": {
    "gn:gn_country":"PL",
    "gn:gn_fcode":"PPLA3",
    "gn:gn_pop":9412,
    "gn:population":9412,
    "iso:country":"PL",
    "name:ceb_x_preferred":[
        "Orneta"
    ],
    "name:deu_x_preferred":[
        "Orneta"
    ],
    "name:dsb_x_preferred":[
        "Orneta"
    ],
    "name:eng_x_preferred":[
        "Orneta"
    ],
    "name:epo_x_preferred":[
        "Orneta"
    ],
    "name:fra_x_preferred":[
        "Orneta"
    ],
    "name:jav_x_preferred":[
        "Orneta"
    ],
    "name:lav_x_preferred":[
        "Orneta"
    ],
    "name:msa_x_preferred":[
        "Orneta"
    ],
    "name:nld_x_preferred":[
        "Orneta"
    ],
    "name:pol_x_preferred":[
        "Orneta"
    ],
    "name:por_x_preferred":[
        "Orneta"
    ],
    "name:ron_x_preferred":[
        "Orneta"
    ],
    "name:rus_x_preferred":[
        "\u041e\u0440\u043d\u0435\u0442\u0430"
    ],
    "name:slk_x_preferred":[
        "Orneta"
    ],
    "name:srp_x_preferred":[
        "\u041e\u0440\u043d\u0435\u0442\u0430"
    ],
    "name:szl_x_preferred":[
        "Uorneta"
    ],
    "name:ukr_x_preferred":[
        "\u041e\u0440\u043d\u0435\u0442\u0430"
    ],
    "name:unk_x_variant":[
        "Wormditt"
    ],
    "name:vie_x_preferred":[
        "Orneta"
    ],
    "name:zho_x_preferred":[
        "\u5965\u5c14\u5185\u5854"
    ],
    "qs_pg:aaroncc":"PL",
    "qs_pg:gn_country":"PL",
    "qs_pg:gn_fcode":"PPLA3",
    "qs_pg:gn_pop":9412,
    "qs_pg:name":"Orneta",
    "qs_pg:name_adm0":"Polska",
    "qs_pg:name_adm1":"Warminsko-Mazurskie",
    "qs_pg:photos":14,
    "qs_pg:photos_1k":3,
    "qs_pg:photos_9k":1,
    "qs_pg:photos_9r":1,
    "qs_pg:photos_all":14,
    "qs_pg:photos_sr":1,
    "qs_pg:pop_sr":5,
    "qs_pg:qs_pg_placetype":"localadmin",
    "qs_pg:qs_pg_placetype_gp":"LocalAdmin",
    "qs_pg:woe_adm0":23424923,
    "woe:adm0_id":23424923,
    "woe:name_adm0":"Polska",
    "woe:name_adm1":"Warminsko-Mazurskie",
    "woe:placetype":"LocalAdmin",
    "wof:name":"Orneta",
    "wof:placetype":"localadmin",
    "wof:population":9412
},
  "geometry": {"coordinates":[20.13328,54.11483],"type":"Point"}
}