{
  "type": "Feature",
  "properties": {
    "gn:admin1_code":"82.0",
    "gn:admin2_code":"2212.0",
    "gn:admin3_code":"221203.0",
    "gn:asciiname":"Motarzyno",
    "gn:country_code":"PL",
    "gn:dem":120,
    "gn:feature_class":"P",
    "gn:feature_code":"PPL",
    "gn:name":"Motarzyno",
    "gn:population":0,
    "gn:timezone":"Europe/Warsaw",
    "iso:country":"PL",
    "wof:name":"Motarzyno",
    "wof:placetype":"locality"
},
  "geometry": {"coordinates":[17.33522,54.32533000000001],"type":"Point"}
}