{
  "type": "Feature",
  "properties": {
    "gn:admin1_code":"82.0",
    "gn:admin2_code":"2212.0",
    "gn:admin3_code":"221203.0",
    "gn:asciiname":"Motarzyno",
    "gn:country_code":"PL",
    "gn:dem":120,
    "gn:feature_class":"P",
    "gn:feature_code":"PPL",
    "gn:name":"Motarzyno",
    "gn:population":0,
    "gn:timezone":"Europe/Warsaw",
    "iso:country":"PL",
    "name:azb_x_preferred":[
        "\u0645\u0648\u062a\u0627\u0698\u0646\u0648"
    ],
    "name:ceb_x_preferred":[
        "Motarzyno"
    ],
    "name:csb_x_preferred":[
        "M\u00f2tarz\u00ebno"
    ],
    "name:deu_x_preferred":[
        "Motarzyno"
    ],
    "name:fas_x_preferred":[
        "\u0645\u0648\u062a\u0627\u0698\u0646\u0648"
    ],
    "name:nld_x_preferred":[
        "Motarzyno"
    ],
    "name:pol_x_preferred":[
        "Motarzyno"
    ],
    "name:ukr_x_preferred":[
        "\u041c\u043e\u0442\u0430\u0436\u0438\u043d\u043e"
    ],
    "wof:name":"Motarzyno",
    "wof:placetype":"locality"
},
  "geometry": {"coordinates":[17.33522,54.32533000000001],"type":"Point"}
}