{
  "type": "Feature",
  "properties": {
    "gn:admin1_code":"77.0",
    "gn:admin2_code":"1203.0",
    "gn:admin3_code":"120305.0",
    "gn:asciiname":"Wodna",
    "gn:country_code":"PL",
    "gn:dem":323,
    "gn:feature_class":"P",
    "gn:feature_code":"PPL",
    "gn:name":"Wodna",
    "gn:population":0,
    "gn:timezone":"Europe/Warsaw",
    "iso:country":"PL",
    "wof:name":"Wodna",
    "wof:placetype":"locality"
},
  "geometry": {"coordinates":[19.43408,50.17221],"type":"Point"}
}