{
  "type": "Feature",
  "properties": {
    "gn:admin1_code":"81.0",
    "gn:admin2_code":"2002.0",
    "gn:admin3_code":"200204.0",
    "gn:asciiname":"Pieszczaniki",
    "gn:country_code":"PL",
    "gn:dem":143,
    "gn:feature_class":"P",
    "gn:feature_code":"PPL",
    "gn:name":"Pieszczaniki",
    "gn:population":0,
    "gn:timezone":"Europe/Warsaw",
    "iso:country":"PL",
    "name:azb_x_preferred":[
        "\u067e\u06cc\u0634\u0686\u0627\u0646\u0642\u06a9\u06cc"
    ],
    "name:fas_x_preferred":[
        "\u067e\u06cc\u0634\u0686\u0627\u0646\u06af\u06a9\u06cc"
    ],
    "name:fra_x_preferred":[
        "Pieszczaniki"
    ],
    "name:lit_x_preferred":[
        "Pie\u0161\u010danikai"
    ],
    "name:pol_x_preferred":[
        "Pieszczaniki"
    ],
    "name:ukr_x_preferred":[
        "\u041f\u0435\u0449\u0430\u043d\u0438\u043a\u0438"
    ],
    "wof:name":"Pieszczaniki",
    "wof:placetype":"locality"
},
  "geometry": {"coordinates":[23.55752,53.13856],"type":"Point"}
}