{
  "type": "Feature",
  "properties": {
    "gn:admin1_code":"73.0",
    "gn:admin2_code":"417.0",
    "gn:admin3_code":"41705.0",
    "gn:asciiname":"Mysliwiec",
    "gn:country_code":"PL",
    "gn:dem":100,
    "gn:feature_class":"P",
    "gn:feature_code":"PPL",
    "gn:name":"My\u015bliwiec",
    "gn:population":0,
    "gn:timezone":"Europe/Warsaw",
    "iso:country":"PL",
    "name:pol_x_preferred":[
        "My\u015bliwiec"
    ],
    "name:ukr_x_preferred":[
        "\u041c\u0438\u0441\u043b\u0456\u0432\u0435\u0446\u044c"
    ],
    "wof:name":"Mysliwiec",
    "wof:placetype":"locality"
},
  "geometry": {"coordinates":[18.99322,53.28596],"type":"Point"}
}