{
  "type": "Feature",
  "properties": {
    "iso:country":"PL",
    "name:ceb_x_preferred":[
        "Buczek"
    ],
    "name:ces_x_preferred":[
        "Buczek"
    ],
    "name:deu_x_preferred":[
        "Buczek"
    ],
    "name:fra_x_preferred":[
        "Buczek"
    ],
    "name:nld_x_preferred":[
        "Buczek"
    ],
    "name:pol_x_preferred":[
        "Buczek"
    ],
    "wof:coterminous":[
        1125303881
    ],
    "wof:name":"Buczek",
    "wof:placetype":"locality"
},
  "geometry": {"coordinates":[19.1743760808977,51.5214082295309],"type":"Point"}
}