{
  "type": "Feature",
  "properties": {
    "iso:country":"PL",
    "name:pol_x_preferred":[
        "Buczek"
    ],
    "wof:name":"Buczek",
    "wof:placetype":"locality"
},
  "geometry": {"coordinates":[19.1743760808977,51.5214082295309],"type":"Point"}
}