{
  "type": "Feature",
  "properties": {
    "gn:country":"PL",
    "gn:fcode":"PPL",
    "gn:population":240,
    "iso:country":"PL",
    "name:ast_x_preferred":[
        "Bobosz\u00f3w"
    ],
    "name:azb_x_preferred":[
        "\u0628\u0648\u0628\u0648\u0634\u0648\u0648"
    ],
    "name:ceb_x_preferred":[
        "Bobosz\u00f3w"
    ],
    "name:ces_x_preferred":[
        "Bobosz\u00f3w"
    ],
    "name:deu_x_preferred":[
        "Bobosz\u00f3w"
    ],
    "name:eng_x_preferred":[
        "Bobosz\u00f3w"
    ],
    "name:fas_x_preferred":[
        "\u0628\u0648\u0628\u0648\u0634\u0648\u0648"
    ],
    "name:fra_x_preferred":[
        "Bobosz\u00f3w"
    ],
    "name:nld_x_preferred":[
        "Bobosz\u00f3w"
    ],
    "name:pol_x_preferred":[
        "Bobosz\u00f3w"
    ],
    "name:ukr_x_preferred":[
        "\u0411\u043e\u0431\u043e\u0448\u0443\u0432"
    ],
    "qs_pg:aaroncc":"PL",
    "qs_pg:gn_country":"PL",
    "qs_pg:gn_fcode":"PPL",
    "qs_pg:gn_pop":240,
    "qs_pg:name":"Bobosz\u00f3w",
    "qs_pg:name_adm0":"Polska",
    "qs_pg:name_adm1":"Dolnosl\u0105skie",
    "qs_pg:photos_9r":0,
    "qs_pg:photos_sr":0,
    "qs_pg:pop_sr":2,
    "qs_pg:qs_pg_placetype":"locality",
    "qs_pg:qs_pg_placetype_gp":"Town",
    "qs_pg:woe_adm0":23424923,
    "woe:adm0_id":23424923,
    "woe:name_adm0":"Polska",
    "woe:name_adm1":"Dolnosl\u0105skie",
    "woe:placetype":"Town",
    "wof:name":"Bobosz\u00f3w",
    "wof:placetype":"locality",
    "wof:population":240
},
  "geometry": {"coordinates":[16.69849,50.10624],"type":"Point"}
}