{
  "type": "Feature",
  "properties": {
    "gn:admin1_code":"75.0",
    "gn:admin2_code":"607.0",
    "gn:admin3_code":"60704.0",
    "gn:asciiname":"Kolanowka",
    "gn:country_code":"PL",
    "gn:dem":153,
    "gn:feature_class":"P",
    "gn:feature_code":"PPL",
    "gn:name":"Kolan\u00f3wka",
    "gn:population":0,
    "gn:timezone":"Europe/Warsaw",
    "iso:country":"PL",
    "wof:name":"Kolanowka",
    "wof:placetype":"locality"
},
  "geometry": {"coordinates":[21.95724,50.83886],"type":"Point"}
}