{
  "type": "Feature",
  "properties": {
    "gn:admin1_code":"84.0",
    "gn:admin2_code":"2609.0",
    "gn:admin3_code":"260906.0",
    "gn:asciiname":"Piekary",
    "gn:country_code":"PL",
    "gn:dem":191,
    "gn:feature_class":"P",
    "gn:feature_code":"PPL",
    "gn:name":"Piekary",
    "gn:population":0,
    "gn:timezone":"Europe/Warsaw",
    "iso:country":"PL",
    "name:ceb_x_preferred":[
        "Piekary"
    ],
    "name:pol_x_preferred":[
        "Piekary"
    ],
    "name:ukr_x_preferred":[
        "\u041f\u0435\u043a\u0430\u0440\u0438"
    ],
    "wof:name":"Piekary",
    "wof:placetype":"locality"
},
  "geometry": {"coordinates":[21.58733,50.68525],"type":"Point"}
}