{
  "type": "Feature",
  "properties": {
    "gn:admin1_code":"86.0",
    "gn:admin2_code":"3023.0",
    "gn:admin3_code":"302303.0",
    "gn:asciiname":"Rekawczyn",
    "gn:country_code":"PL",
    "gn:dem":92,
    "gn:feature_class":"P",
    "gn:feature_code":"PPL",
    "gn:name":"R\u0119kawczyn",
    "gn:population":0,
    "gn:timezone":"Europe/Warsaw",
    "iso:country":"PL",
    "name:fra_x_preferred":[
        "R\u0119kawczyn"
    ],
    "name:pol_x_preferred":[
        "R\u0119kawczyn"
    ],
    "name:ukr_x_preferred":[
        "\u0420\u0435\u043d\u043a\u0430\u0432\u0447\u0438\u043d"
    ],
    "wof:name":"Rekawczyn",
    "wof:placetype":"locality"
},
  "geometry": {"coordinates":[17.94841,52.52132],"type":"Point"}
}