{
  "type": "Feature",
  "properties": {
    "gn:admin1_code":"86.0",
    "gn:admin2_code":"3009.0",
    "gn:admin3_code":"300903.0",
    "gn:asciiname":"Dzierzbice",
    "gn:country_code":"PL",
    "gn:dem":113,
    "gn:feature_class":"P",
    "gn:feature_code":"PPL",
    "gn:name":"Dzierzbice",
    "gn:population":0,
    "gn:timezone":"Europe/Warsaw",
    "iso:country":"PL",
    "name:ceb_x_preferred":[
        "Dzierzbice"
    ],
    "name:pol_x_preferred":[
        "Dzierzbice"
    ],
    "name:ukr_x_preferred":[
        "\u0414\u0437\u0435\u0436\u0431\u0456\u0446\u0435"
    ],
    "wof:name":"Dzierzbice",
    "wof:placetype":"locality"
},
  "geometry": {"coordinates":[18.96298,52.26283],"type":"Point"}
}