{
  "type": "Feature",
  "properties": {
    "gn:admin1_code":"74.0",
    "gn:asciiname":"Stare Budy",
    "gn:country_code":"PL",
    "gn:dem":112,
    "gn:feature_class":"P",
    "gn:feature_code":"PPL",
    "gn:name":"Stare Budy",
    "gn:population":0,
    "gn:timezone":"Europe/Warsaw",
    "iso:country":"PL",
    "name:fra_x_preferred":[
        "Stare Budy"
    ],
    "name:pol_x_preferred":[
        "Stare Budy"
    ],
    "name:ukr_x_preferred":[
        "\u0421\u0442\u0430\u0440\u0435 \u0411\u0443\u0434\u0438"
    ],
    "wof:name":"Stare Budy",
    "wof:placetype":"locality"
},
  "geometry": {"coordinates":[20.5022,52.06246],"type":"Point"}
}