{
  "type": "Feature",
  "properties": {
    "gn:admin1_code":"77.0",
    "gn:admin2_code":"1216.0",
    "gn:admin3_code":"121615.0",
    "gn:asciiname":"Konary",
    "gn:country_code":"PL",
    "gn:dem":179,
    "gn:feature_class":"P",
    "gn:feature_code":"PPL",
    "gn:name":"Konary",
    "gn:population":0,
    "gn:timezone":"Europe/Warsaw",
    "iso:country":"PL",
    "name:ceb_x_preferred":[
        "Konary"
    ],
    "name:fra_x_preferred":[
        "Konary"
    ],
    "name:pol_x_preferred":[
        "Konary"
    ],
    "name:ukr_x_preferred":[
        "\u041a\u043e\u043d\u0430\u0440\u0438"
    ],
    "wof:name":"Konary",
    "wof:placetype":"neighbourhood"
},
  "geometry": {"coordinates":[20.86667000000001,50.13333],"type":"Point"}
}