{
  "type": "Feature",
  "properties": {
    "gn:admin1_code":"84.0",
    "gn:admin2_code":"2613.0",
    "gn:admin3_code":"261305.0",
    "gn:asciiname":"Miedzylesie",
    "gn:country_code":"PL",
    "gn:dem":236,
    "gn:feature_class":"P",
    "gn:feature_code":"PPL",
    "gn:name":"Mi\u0119dzylesie",
    "gn:population":0,
    "gn:timezone":"Europe/Warsaw",
    "iso:country":"PL",
    "wof:name":"Miedzylesie",
    "wof:placetype":"locality"
},
  "geometry": {"coordinates":[19.85804,50.79956],"type":"Point"}
}