{
  "type": "Feature",
  "properties": {
    "gn:admin1_code":"80.0",
    "gn:admin2_code":"1803.0",
    "gn:admin3_code":"180306.0",
    "gn:asciiname":"Dulczowka",
    "gn:country_code":"PL",
    "gn:dem":209,
    "gn:feature_class":"P",
    "gn:feature_code":"PPL",
    "gn:name":"Dulcz\u00f3wka",
    "gn:population":0,
    "gn:timezone":"Europe/Warsaw",
    "iso:country":"PL",
    "wof:name":"Dulczowka",
    "wof:placetype":"locality"
},
  "geometry": {"coordinates":[21.27522,49.97685],"type":"Point"}
}