{
  "type": "Feature",
  "properties": {
    "gn:admin1_code":"80.0",
    "gn:admin2_code":"1803.0",
    "gn:admin3_code":"180303.0",
    "gn:asciiname":"Jawornik Stary",
    "gn:country_code":"PL",
    "gn:dem":217,
    "gn:feature_class":"P",
    "gn:feature_code":"PPL",
    "gn:name":"Jawornik Stary",
    "gn:population":0,
    "gn:timezone":"Europe/Warsaw",
    "iso:country":"PL",
    "name:und_x_variant":[
        "Jawornik",
        "Jawornik Stary"
    ],
    "wof:name":"Jawornik Stary",
    "wof:placetype":"locality"
},
  "geometry": {"coordinates":[21.22473,50.07708],"type":"Point"}
}