{
  "type": "Feature",
  "properties": {
    "gn:admin1_code":"74.0",
    "gn:admin2_code":"1014.0",
    "gn:admin3_code":"101402.0",
    "gn:asciiname":"Zaborow",
    "gn:country_code":"PL",
    "gn:dem":165,
    "gn:feature_class":"P",
    "gn:feature_code":"PPL",
    "gn:name":"Zabor\u00f3w",
    "gn:population":0,
    "gn:timezone":"Europe/Warsaw",
    "iso:country":"PL",
    "wof:name":"Zaborow",
    "wof:placetype":"locality"
},
  "geometry": {"coordinates":[18.44169,51.61612],"type":"Point"}
}