{
  "type": "Feature",
  "properties": {
    "gn:admin1_code":"74.0",
    "gn:admin2_code":"1015.0",
    "gn:admin3_code":"101506.0",
    "gn:asciiname":"Wola Makowska",
    "gn:country_code":"PL",
    "gn:dem":116,
    "gn:feature_class":"P",
    "gn:feature_code":"PPL",
    "gn:name":"Wola Makowska",
    "gn:population":0,
    "gn:timezone":"Europe/Warsaw",
    "iso:country":"PL",
    "name:pol_x_preferred":[
        "Wola Makowska"
    ],
    "name:ukr_x_preferred":[
        "\u0412\u043e\u043b\u044f-\u041c\u0430\u043a\u043e\u0432\u0441\u044c\u043a\u0430"
    ],
    "wof:name":"Wola Makowska",
    "wof:placetype":"locality"
},
  "geometry": {"coordinates":[20.05795,51.98208],"type":"Point"}
}