{
  "type": "Feature",
  "properties": {
    "gn:admin1_code":"78.0",
    "gn:admin2_code":"1415.0",
    "gn:admin3_code":"141503.0",
    "gn:asciiname":"Stylagi",
    "gn:country_code":"PL",
    "gn:dem":107,
    "gn:feature_class":"P",
    "gn:feature_code":"PPL",
    "gn:name":"Styl\u0105gi",
    "gn:population":0,
    "gn:timezone":"Europe/Warsaw",
    "iso:country":"PL",
    "name:fra_x_preferred":[
        "Styl\u0105gi"
    ],
    "name:pol_x_preferred":[
        "Styl\u0105gi"
    ],
    "name:ukr_x_preferred":[
        "\u0421\u0442\u0438\u043b\u044c\u043e\u043d\u0491\u0456"
    ],
    "wof:name":"Stylagi",
    "wof:placetype":"locality"
},
  "geometry": {"coordinates":[21.74967,52.97977],"type":"Point"}
}