{
  "type": "Feature",
  "properties": {
    "gn:admin1_code":"78.0",
    "gn:admin2_code":"1406.0",
    "gn:admin3_code":"140601.0",
    "gn:asciiname":"Mala Wies",
    "gn:country_code":"PL",
    "gn:dem":179,
    "gn:feature_class":"P",
    "gn:feature_code":"PPL",
    "gn:name":"Ma\u0142a Wie\u015b",
    "gn:population":0,
    "gn:timezone":"Europe/Warsaw",
    "iso:country":"PL",
    "name:azb_x_preferred":[
        "\u0645\u0627\u0648\u0627 \u0648\u06cc\u0634"
    ],
    "name:fas_x_preferred":[
        "\u0645\u0627\u0648\u0627 \u0648\u06cc\u0634"
    ],
    "name:fra_x_preferred":[
        "Ma\u0142a Wie\u015b"
    ],
    "name:pol_x_preferred":[
        "Ma\u0142a Wie\u015b"
    ],
    "name:ukr_x_preferred":[
        "\u041c\u0430\u043b\u0430 \u0412\u0435\u0441\u044c"
    ],
    "wof:name":"Mala Wies",
    "wof:placetype":"locality"
},
  "geometry": {"coordinates":[20.77366,51.82782],"type":"Point"}
}