{
  "type": "Feature",
  "properties": {
    "gn:gn_country":"PL",
    "gn:gn_fcode":"PPL",
    "gn:gn_pop":959,
    "gn:population":959,
    "iso:country":"PL",
    "name:eng_x_preferred":[
        "Go\u0142k\u00f3w"
    ],
    "name:fra_x_preferred":[
        "Go\u0142k\u00f3w"
    ],
    "name:nan_x_preferred":[
        "Go\u0142k\u00f3w"
    ],
    "name:pol_x_preferred":[
        "Go\u0142k\u00f3w"
    ],
    "qs_pg:aaroncc":"PL",
    "qs_pg:gn_country":"PL",
    "qs_pg:gn_fcode":"PPL",
    "qs_pg:gn_pop":959,
    "qs_pg:name":"Go\u0142k\u00f3w",
    "qs_pg:name_adm0":"Polska",
    "qs_pg:name_adm1":"Mazowieckie",
    "qs_pg:photos_9k":1,
    "qs_pg:photos_9r":1,
    "qs_pg:photos_all":1,
    "qs_pg:photos_sr":0,
    "qs_pg:pop_sr":2,
    "qs_pg:qs_pg_placetype":"locality",
    "qs_pg:qs_pg_placetype_gp":"Town",
    "qs_pg:woe_adm0":23424923,
    "woe:adm0_id":23424923,
    "woe:name_adm0":"Polska",
    "woe:name_adm1":"Mazowieckie",
    "woe:placetype":"Town",
    "wof:name":"Go\u0142k\u00f3w",
    "wof:placetype":"locality",
    "wof:population":959
},
  "geometry": {"coordinates":[20.97101,52.04172],"type":"Point"}
}