{
  "type": "Feature",
  "properties": {
    "gn:admin1_code":"78.0",
    "gn:admin2_code":"1428.0",
    "gn:admin3_code":"142801.0",
    "gn:asciiname":"Ostrzeszwo",
    "gn:country_code":"PL",
    "gn:dem":74,
    "gn:feature_class":"P",
    "gn:feature_code":"PPL",
    "gn:name":"Ostrzeszwo",
    "gn:population":0,
    "gn:timezone":"Europe/Warsaw",
    "iso:country":"PL",
    "wof:name":"Ostrzeszwo",
    "wof:placetype":"locality"
},
  "geometry": {"coordinates":[20.27197,52.26219],"type":"Point"}
}