{
  "type": "Feature",
  "properties": {
    "gn:admin1_code":"74.0",
    "gn:admin2_code":"1014.0",
    "gn:admin3_code":"101402.0",
    "gn:asciiname":"Zelislaw",
    "gn:country_code":"PL",
    "gn:dem":151,
    "gn:feature_class":"P",
    "gn:feature_code":"PPL",
    "gn:name":"\u017belis\u0142aw",
    "gn:population":0,
    "gn:timezone":"Europe/Warsaw",
    "iso:country":"PL",
    "name:pol_x_preferred":[
        "\u017belis\u0142aw"
    ],
    "name:ukr_x_preferred":[
        "\u0416\u0435\u043b\u0456\u0441\u043b\u0430\u0432"
    ],
    "wof:name":"Zelislaw",
    "wof:placetype":"locality"
},
  "geometry": {"coordinates":[18.44397,51.6307],"type":"Point"}
}