{
  "type": "Feature",
  "properties": {
    "gn:admin1_code":"75.0",
    "gn:admin2_code":"602.0",
    "gn:admin3_code":"60206.0",
    "gn:asciiname":"Hosznia Abramowska",
    "gn:country_code":"PL",
    "gn:dem":301,
    "gn:feature_class":"P",
    "gn:feature_code":"PPL",
    "gn:name":"Hosznia Abramowska",
    "gn:population":0,
    "gn:timezone":"Europe/Warsaw",
    "iso:country":"PL",
    "name:azb_x_preferred":[
        "\u062e\u0648\u0634\u0646\u0642\u0627 \u0627\u0628\u0631\u0627\u0645\u0648\u0648\u0633\u06a9\u0627"
    ],
    "name:fas_x_preferred":[
        "\u062e\u0648\u0634\u0646\u06af\u0627 \u0627\u0628\u0631\u0627\u0645\u0648\u0648\u0633\u06a9\u0627"
    ],
    "name:fra_x_preferred":[
        "Hosznia Abramowska"
    ],
    "name:nld_x_preferred":[
        "Hosznia Abramowska"
    ],
    "name:pol_x_preferred":[
        "Hosznia Abramowska"
    ],
    "name:rus_x_preferred":[
        "\u0425\u043e\u0448\u043d\u044f-\u0410\u0431\u0440\u0430\u043c\u043e\u0432\u0441\u043a\u0430"
    ],
    "name:ukr_x_preferred":[
        "\u0413\u043e\u0448\u043d\u044f-\u0410\u0431\u0440\u0430\u043c\u043e\u0432\u0441\u044c\u043a\u0430"
    ],
    "wof:name":"Hosznia Abramowska",
    "wof:placetype":"locality"
},
  "geometry": {"coordinates":[22.7538,50.72941],"type":"Point"}
}