{
  "type": "Feature",
  "properties": {
    "gn:admin1_code":"75.0",
    "gn:admin2_code":"602.0",
    "gn:admin3_code":"60206.0",
    "gn:asciiname":"Hosznia Abramowska",
    "gn:country_code":"PL",
    "gn:dem":301,
    "gn:feature_class":"P",
    "gn:feature_code":"PPL",
    "gn:name":"Hosznia Abramowska",
    "gn:population":0,
    "gn:timezone":"Europe/Warsaw",
    "iso:country":"PL",
    "wof:name":"Hosznia Abramowska",
    "wof:placetype":"locality"
},
  "geometry": {"coordinates":[22.7538,50.72941],"type":"Point"}
}