{
  "type": "Feature",
  "properties": {
    "gn:admin1_code":"73.0",
    "gn:admin2_code":"402.0",
    "gn:admin3_code":"40202.0",
    "gn:asciiname":"Malki",
    "gn:country_code":"PL",
    "gn:dem":99,
    "gn:feature_class":"P",
    "gn:feature_code":"PPL",
    "gn:name":"Ma\u0142ki",
    "gn:population":0,
    "gn:timezone":"Europe/Warsaw",
    "iso:country":"PL",
    "name:und_x_variant":[
        "Ma\u0142ki"
    ],
    "wof:name":"Malki",
    "wof:placetype":"locality"
},
  "geometry": {"coordinates":[19.25856,53.23861],"type":"Point"}
}