{
  "type": "Feature",
  "properties": {
    "gn:country":"PL",
    "gn:fcode":"PPLA3",
    "gn:population":2043,
    "iso:country":"PL",
    "name:bel_x_preferred":[
        "\u0413\u043e\u0440\u0430\u0434 \u0421\u0435\u043c\u043f\u043e\u043f\u0430\u043b\u044c"
    ],
    "name:bel_x_variant":[
        "\u0421\u044d\u043c\u043f\u043e\u043f\u0430\u043b\u044c"
    ],
    "name:deu_x_preferred":[
        "Schippenbeil"
    ],
    "name:deu_x_variant":[
        "S\u0119popol"
    ],
    "name:dsb_x_preferred":[
        "S\u0119popol"
    ],
    "name:eng_x_preferred":[
        "S\u0119popol"
    ],
    "name:epo_x_preferred":[
        "S\u0119popol"
    ],
    "name:fra_x_preferred":[
        "S\u0119popol"
    ],
    "name:jav_x_preferred":[
        "S\u0119popol"
    ],
    "name:lav_x_preferred":[
        "Sempopole"
    ],
    "name:msa_x_preferred":[
        "S\u0119popol"
    ],
    "name:nld_x_preferred":[
        "S\u0119popol"
    ],
    "name:pol_x_preferred":[
        "S\u0119popol"
    ],
    "name:por_x_preferred":[
        "S\u0119popol"
    ],
    "name:ron_x_preferred":[
        "S\u0119popol"
    ],
    "name:rus_x_preferred":[
        "\u0421\u0435\u043c\u043f\u043e\u043f\u043e\u043b\u044c"
    ],
    "name:slk_x_preferred":[
        "S\u0119popol"
    ],
    "name:srp_x_preferred":[
        "\u0421\u0435\u043d\u043f\u043e\u043f\u043e\u043b"
    ],
    "name:ukr_x_preferred":[
        "\u0421\u0435\u043c\u043f\u043e\u043f\u043e\u043b\u044c"
    ],
    "name:und_x_variant":[
        "Sz\u0119popel"
    ],
    "name:vie_x_preferred":[
        "S\u0119popol"
    ],
    "name:zho_x_preferred":[
        "\u68ee\u6ce2\u6ce2\u723e"
    ],
    "qs_pg:aaroncc":"PL",
    "qs_pg:gn_country":"PL",
    "qs_pg:gn_fcode":"PPLA3",
    "qs_pg:gn_pop":2043,
    "qs_pg:name":"S\u0119popol",
    "qs_pg:name_adm0":"Polska",
    "qs_pg:name_adm1":"Warminsko-Mazurskie",
    "qs_pg:photos":4,
    "qs_pg:photos_1k":1,
    "qs_pg:photos_9k":1,
    "qs_pg:photos_9r":1,
    "qs_pg:photos_all":4,
    "qs_pg:photos_sr":1,
    "qs_pg:pop_sr":4,
    "qs_pg:qs_pg_placetype":"localadmin",
    "qs_pg:qs_pg_placetype_gp":"LocalAdmin",
    "qs_pg:woe_adm0":23424923,
    "woe:adm0_id":23424923,
    "woe:name_adm0":"Polska",
    "woe:name_adm1":"Warminsko-Mazurskie",
    "woe:placetype":"LocalAdmin",
    "wof:name":"S\u0119popol",
    "wof:placetype":"localadmin",
    "wof:population":2043
},
  "geometry": {"coordinates":[21.01453,54.26903],"type":"Point"}
}