{
  "type": "Feature",
  "properties": {
    "gn:admin1_code":"75.0",
    "gn:admin2_code":"606.0",
    "gn:admin3_code":"60601.0",
    "gn:asciiname":"Zadworze",
    "gn:country_code":"PL",
    "gn:dem":179,
    "gn:feature_class":"P",
    "gn:feature_code":"PPL",
    "gn:name":"Zadworze",
    "gn:population":0,
    "gn:timezone":"Europe/Warsaw",
    "iso:country":"PL",
    "name:fra_x_preferred":[
        "Zakr\u0119cie"
    ],
    "name:pol_x_preferred":[
        "Zakr\u0119cie"
    ],
    "name:ukr_x_preferred":[
        "\u0417\u0430\u043a\u0440\u0435\u043d\u0446\u0435"
    ],
    "name:und_x_variant":[
        "Zadworze"
    ],
    "wof:name":"Zadworze",
    "wof:placetype":"locality"
},
  "geometry": {"coordinates":[23.15973,50.99518],"type":"Point"}
}