{
  "type": "Feature",
  "properties": {
    "gn:country":"PL",
    "gn:fcode":"PPL",
    "gn:population":478,
    "iso:country":"PL",
    "name:ast_x_preferred":[
        "Przy\u0142\u0119k"
    ],
    "name:ceb_x_preferred":[
        "Przy\u0142\u0119k"
    ],
    "name:eng_x_preferred":[
        "Przy\u0142\u0119k"
    ],
    "name:fra_x_preferred":[
        "Przy\u0142\u0119k"
    ],
    "name:pol_x_preferred":[
        "Przy\u0142\u0119k"
    ],
    "name:ukr_x_preferred":[
        "\u041f\u0448\u0438\u043b\u0435\u043d\u043a"
    ],
    "qs_pg:aaroncc":"PL",
    "qs_pg:gn_country":"PL",
    "qs_pg:gn_fcode":"PPL",
    "qs_pg:gn_pop":478,
    "qs_pg:name":"Przy\u0142\u0119k",
    "qs_pg:name_adm0":"Polska",
    "qs_pg:name_adm1":"Wielkopolskie",
    "qs_pg:photos_9r":0,
    "qs_pg:photos_sr":0,
    "qs_pg:pop_sr":2,
    "qs_pg:qs_pg_placetype":"locality",
    "qs_pg:qs_pg_placetype_gp":"Town",
    "qs_pg:woe_adm0":23424923,
    "woe:adm0_id":23424923,
    "woe:name_adm0":"Polska",
    "woe:name_adm1":"Wielkopolskie",
    "woe:placetype":"Town",
    "wof:name":"Przy\u0142\u0119k",
    "wof:placetype":"locality",
    "wof:population":478
},
  "geometry": {"coordinates":[16.0875,52.33607],"type":"Point"}
}