{
  "type": "Feature",
  "properties": {
    "gn:country":"PL",
    "gn:fcode":"PPL",
    "gn:population":451,
    "iso:country":"PL",
    "name:ast_x_preferred":[
        "Mycielin"
    ],
    "name:ceb_x_preferred":[
        "Mycielin"
    ],
    "name:ces_x_preferred":[
        "Mycielin"
    ],
    "name:che_x_preferred":[
        "\u041c\u0438\u0446\u0435\u043b\u0438\u043d"
    ],
    "name:deu_x_historical":[
        "Metschlau"
    ],
    "name:deu_x_preferred":[
        "Metschlau"
    ],
    "name:eng_x_preferred":[
        "Mycielin"
    ],
    "name:fra_x_preferred":[
        "Mycielin"
    ],
    "name:nan_x_preferred":[
        "Mycielin"
    ],
    "name:pol_x_preferred":[
        "Mycielin"
    ],
    "name:tat_x_preferred":[
        "\u041c\u0438\u0446\u0435\u043b\u0438\u043d"
    ],
    "name:ukr_x_preferred":[
        "\u041c\u0438\u0446\u0435\u043b\u0456\u043d"
    ],
    "qs_pg:aaroncc":"PL",
    "qs_pg:gn_country":"PL",
    "qs_pg:gn_fcode":"PPL",
    "qs_pg:gn_pop":451,
    "qs_pg:name":"Mycielin",
    "qs_pg:name_adm0":"Polska",
    "qs_pg:name_adm1":"Lubuskie",
    "qs_pg:photos_9k":1,
    "qs_pg:photos_9r":1,
    "qs_pg:photos_all":1,
    "qs_pg:photos_sr":0,
    "qs_pg:pop_sr":2,
    "qs_pg:qs_pg_placetype":"locality",
    "qs_pg:qs_pg_placetype_gp":"Town",
    "qs_pg:woe_adm0":23424923,
    "woe:adm0_id":23424923,
    "woe:name_adm0":"Polska",
    "woe:name_adm1":"Lubuskie",
    "woe:placetype":"Town",
    "wof:name":"Mycielin",
    "wof:placetype":"locality",
    "wof:population":451
},
  "geometry": {"coordinates":[15.6986,51.63096],"type":"Point"}
}