{
  "type": "Feature",
  "properties": {
    "gn:admin1_code":"82.0",
    "gn:admin2_code":"2206.0",
    "gn:admin3_code":"220605.0",
    "gn:asciiname":"Chrosty Wysinskie",
    "gn:country_code":"PL",
    "gn:dem":194,
    "gn:feature_class":"P",
    "gn:feature_code":"PPL",
    "gn:name":"Chr\u00f3sty Wysinskie",
    "gn:population":0,
    "gn:timezone":"Europe/Warsaw",
    "iso:country":"PL",
    "name:nld_x_preferred":[
        "Chr\u00f3sty Wysi\u0144skie"
    ],
    "name:pol_x_preferred":[
        "Chr\u00f3sty Wysi\u0144skie"
    ],
    "name:ukr_x_preferred":[
        "\u0425\u0440\u0443\u0441\u0442\u0438-\u0412\u0438\u0441\u0456\u043d\u0441\u044c\u043a\u0456"
    ],
    "name:und_x_variant":[
        "Chr\u00f3sty Wysinskie"
    ],
    "wof:name":"Chrosty Wysinskie",
    "wof:placetype":"locality"
},
  "geometry": {"coordinates":[18.29133,54.12514],"type":"Point"}
}