{
  "type": "Feature",
  "properties": {
    "gn:admin1_code":"75.0",
    "gn:admin2_code":"607.0",
    "gn:admin3_code":"60703.0",
    "gn:asciiname":"Terpentyna",
    "gn:country_code":"PL",
    "gn:dem":209,
    "gn:feature_class":"P",
    "gn:feature_code":"PPL",
    "gn:name":"Terpentyna",
    "gn:population":0,
    "gn:timezone":"Europe/Warsaw",
    "iso:country":"PL",
    "wof:name":"Terpentyna",
    "wof:placetype":"locality"
},
  "geometry": {"coordinates":[22.08321,50.96794000000001],"type":"Point"}
}