{
  "type": "Feature",
  "properties": {
    "gn:country":"PL",
    "gn:fcode":"PPL",
    "gn:population":0,
    "iso:country":"PL",
    "name:ast_x_preferred":[
        "Stary Giera\u0142t\u00f3w"
    ],
    "name:ceb_x_preferred":[
        "Stary Giera\u0142t\u00f3w"
    ],
    "name:ces_x_preferred":[
        "Stary Giera\u0142t\u00f3w"
    ],
    "name:che_x_preferred":[
        "\u0421\u0442\u0430\u0440\u0438\u0439 \u0413\u0435\u0440\u0430\u043b\u0442\u0443\u0432"
    ],
    "name:deu_x_preferred":[
        "Stary Giera\u0142t\u00f3w"
    ],
    "name:eng_x_preferred":[
        "Stary Giera\u0142t\u00f3w"
    ],
    "name:fra_x_preferred":[
        "Stary Giera\u0142t\u00f3w"
    ],
    "name:nan_x_preferred":[
        "Stary Giera\u0142t\u00f3w"
    ],
    "name:pol_x_preferred":[
        "Stary Giera\u0142t\u00f3w"
    ],
    "name:tat_x_preferred":[
        "\u0421\u0442\u0430\u0440\u0438\u0439 \u0413\u0435\u0440\u0430\u043b\u0442\u0443\u0432"
    ],
    "name:ukr_x_preferred":[
        "\u0421\u0442\u0430\u0440\u0438\u0439 \u0490\u0435\u0440\u0430\u043b\u0442\u0443\u0432"
    ],
    "qs_pg:aaroncc":"PL",
    "qs_pg:gn_country":"PL",
    "qs_pg:gn_fcode":"PPL",
    "qs_pg:gn_pop":0,
    "qs_pg:name":"Stary Giera\u0142t\u00f3w",
    "qs_pg:name_adm0":"Polska",
    "qs_pg:name_adm1":"Dolnosl\u0105skie",
    "qs_pg:photos_9k":1,
    "qs_pg:photos_9r":1,
    "qs_pg:photos_all":9,
    "qs_pg:photos_sr":0,
    "qs_pg:pop_sr":0,
    "qs_pg:qs_pg_placetype":"locality",
    "qs_pg:qs_pg_placetype_gp":"Town",
    "qs_pg:woe_adm0":23424923,
    "woe:adm0_id":23424923,
    "woe:name_adm0":"Polska",
    "woe:name_adm1":"Dolnosl\u0105skie",
    "woe:placetype":"Town",
    "wof:name":"Stary Giera\u0142t\u00f3w",
    "wof:placetype":"locality"
},
  "geometry": {"coordinates":[16.93336,50.30798],"type":"Point"}
}