{
  "type": "Feature",
  "properties": {
    "gn:admin1_code":"81.0",
    "gn:admin2_code":"2006.0",
    "gn:admin3_code":"200603.0",
    "gn:asciiname":"Koziki Olszyny",
    "gn:country_code":"PL",
    "gn:dem":125,
    "gn:feature_class":"P",
    "gn:feature_code":"PPL",
    "gn:name":"Koziki Olszyny",
    "gn:population":0,
    "gn:timezone":"Europe/Warsaw",
    "iso:country":"PL",
    "name:azb_x_preferred":[
        "\u06a9\u0648\u0698\u06a9\u06cc-\u0627\u0648\u0644\u0634\u0646\u0647"
    ],
    "name:fas_x_preferred":[
        "\u06a9\u0648\u0698\u06a9\u06cc-\u0627\u0648\u0644\u0634\u0646\u0647"
    ],
    "name:lit_x_preferred":[
        "Koziki Ol\u0161inai"
    ],
    "name:nld_x_preferred":[
        "Koziki-Olszyny"
    ],
    "name:pol_x_preferred":[
        "Koziki-Olszyny"
    ],
    "name:ukr_x_preferred":[
        "\u041a\u043e\u0437\u0438\u043a\u0438-\u041e\u043b\u044c\u0448\u0438\u043d\u0438"
    ],
    "name:und_x_variant":[
        "Koziki",
        "Koziki Olszyny"
    ],
    "wof:name":"Koziki Olszyny",
    "wof:placetype":"locality"
},
  "geometry": {"coordinates":[22.06345,53.41873],"type":"Point"}
}