{
  "type": "Feature",
  "properties": {
    "gn:admin1_code":"79.0",
    "gn:admin2_code":"1608.0",
    "gn:admin3_code":"160803.0",
    "gn:asciiname":"Kolonia Lomnicka",
    "gn:country_code":"PL",
    "gn:dem":256,
    "gn:feature_class":"P",
    "gn:feature_code":"PPL",
    "gn:name":"Kolonia \u0141omnicka",
    "gn:population":0,
    "gn:timezone":"Europe/Warsaw",
    "iso:country":"PL",
    "name:azb_x_preferred":[
        "\u06a9\u0648\u0644\u0648\u0646\u0642\u0627 \u0648\u0648\u0645\u0646\u0642\u062a\u0633\u06a9\u0627"
    ],
    "name:deu_x_preferred":[
        "Kolonia \u0141omnicka"
    ],
    "name:fas_x_preferred":[
        "\u06a9\u0648\u0644\u0648\u0646\u06af\u0627 \u0648\u0648\u0645\u0646\u06af\u062a\u0633\u06a9\u0627"
    ],
    "name:pol_x_preferred":[
        "Kolonia \u0141omnicka"
    ],
    "name:rus_x_preferred":[
        "\u041a\u043e\u043b\u0451\u043d\u044c\u044f-\u041b\u043e\u043c\u043d\u0438\u0446\u043a\u0430"
    ],
    "name:ukr_x_preferred":[
        "\u041a\u043e\u043b\u044c\u043e\u043d\u0456\u044f-\u041b\u043e\u043c\u043d\u0456\u0446\u044c\u043a\u0430"
    ],
    "wof:name":"Kolonia Lomnicka",
    "wof:placetype":"locality"
},
  "geometry": {"coordinates":[18.48106,50.80941],"type":"Point"}
}