{
  "type": "Feature",
  "properties": {
    "gn:admin1_code":"79.0",
    "gn:admin2_code":"1608.0",
    "gn:admin3_code":"160803.0",
    "gn:asciiname":"Kolonia Lomnicka",
    "gn:country_code":"PL",
    "gn:dem":256,
    "gn:feature_class":"P",
    "gn:feature_code":"PPL",
    "gn:name":"Kolonia \u0141omnicka",
    "gn:population":0,
    "gn:timezone":"Europe/Warsaw",
    "iso:country":"PL",
    "wof:name":"Kolonia Lomnicka",
    "wof:placetype":"locality"
},
  "geometry": {"coordinates":[18.48106,50.80941],"type":"Point"}
}