{
  "type": "Feature",
  "properties": {
    "gn:admin1_code":"84.0",
    "gn:admin2_code":"2601.0",
    "gn:admin3_code":"260107.0",
    "gn:asciiname":"Niecieslawice",
    "gn:country_code":"PL",
    "gn:dem":193,
    "gn:feature_class":"P",
    "gn:feature_code":"PPL",
    "gn:name":"Niecies\u0142awice",
    "gn:population":0,
    "gn:timezone":"Europe/Warsaw",
    "iso:country":"PL",
    "name:pol_x_preferred":[
        "Niecies\u0142awice"
    ],
    "name:ukr_x_preferred":[
        "\u041d\u0435\u0446\u0435\u0441\u043b\u0430\u0432\u0456\u0446\u0435"
    ],
    "name:und_x_variant":[
        "Niecies\u0142awice"
    ],
    "wof:name":"Niecieslawice",
    "wof:placetype":"locality"
},
  "geometry": {"coordinates":[21.01439,50.50162],"type":"Point"}
}