{
  "type": "Feature",
  "properties": {
    "gn:country":"PL",
    "gn:fcode":"PPL",
    "gn:population":390,
    "iso:country":"PL",
    "name:ast_x_preferred":[
        "Lipnica"
    ],
    "name:ceb_x_preferred":[
        "Lipnica"
    ],
    "name:eng_x_preferred":[
        "Lipnica"
    ],
    "name:fra_x_preferred":[
        "Lipnica"
    ],
    "name:pol_x_preferred":[
        "Lipnica"
    ],
    "name:ukr_x_preferred":[
        "\u041b\u0456\u043f\u043d\u0438\u0446\u044f"
    ],
    "qs_pg:aaroncc":"PL",
    "qs_pg:gn_country":"PL",
    "qs_pg:gn_fcode":"PPL",
    "qs_pg:gn_pop":390,
    "qs_pg:name":"Lipnica",
    "qs_pg:name_adm0":"Polska",
    "qs_pg:name_adm1":"Kujawsko-Pomorskie",
    "qs_pg:photos_9k":1,
    "qs_pg:photos_9r":1,
    "qs_pg:photos_all":1,
    "qs_pg:photos_sr":0,
    "qs_pg:pop_sr":2,
    "qs_pg:qs_pg_placetype":"locality",
    "qs_pg:qs_pg_placetype_gp":"Town",
    "qs_pg:woe_adm0":23424923,
    "woe:adm0_id":23424923,
    "woe:name_adm0":"Polska",
    "woe:name_adm1":"Kujawsko-Pomorskie",
    "woe:placetype":"Town",
    "wof:name":"Lipnica",
    "wof:placetype":"locality",
    "wof:population":390
},
  "geometry": {"coordinates":[19.04128,53.18752],"type":"Point"}
}