{
  "type": "Feature",
  "properties": {
    "gn:gn_country":"PL",
    "gn:gn_fcode":"PPLA3",
    "gn:gn_pop":4183,
    "gn:population":4183,
    "iso:country":"PL",
    "name:ceb_x_preferred":[
        "Suszec"
    ],
    "name:deu_x_preferred":[
        "Suszec"
    ],
    "name:fra_x_preferred":[
        "Suszec"
    ],
    "name:nld_x_preferred":[
        "Suszec"
    ],
    "name:pol_x_preferred":[
        "Suszec"
    ],
    "name:ukr_x_preferred":[
        "\u0421\u0443\u0448\u0435\u0446\u044c"
    ],
    "qs_pg:aaroncc":"PL",
    "qs_pg:gn_country":"PL",
    "qs_pg:gn_fcode":"PPLA3",
    "qs_pg:gn_pop":4183,
    "qs_pg:name":"Suszec",
    "qs_pg:name_adm0":"Polska",
    "qs_pg:name_adm1":"Sl\u0105skie",
    "qs_pg:photos":15,
    "qs_pg:photos_1k":3,
    "qs_pg:photos_9k":1,
    "qs_pg:photos_9r":1,
    "qs_pg:photos_all":15,
    "qs_pg:photos_sr":1,
    "qs_pg:pop_sr":4,
    "qs_pg:qs_pg_placetype":"localadmin",
    "qs_pg:qs_pg_placetype_gp":"LocalAdmin",
    "qs_pg:woe_adm0":23424923,
    "woe:adm0_id":23424923,
    "woe:name_adm0":"Polska",
    "woe:name_adm1":"Sl\u0105skie",
    "woe:placetype":"LocalAdmin",
    "wof:name":"Suszec",
    "wof:placetype":"localadmin",
    "wof:population":4183
},
  "geometry": {"coordinates":[18.7916,50.02958],"type":"Point"}
}