{
  "type": "Feature",
  "properties": {
    "gn:admin1_code":"87.0",
    "gn:admin2_code":"3214.0",
    "gn:admin3_code":"321406.0",
    "gn:asciiname":"Niedzwiedz",
    "gn:country_code":"PL",
    "gn:dem":21,
    "gn:feature_class":"P",
    "gn:feature_code":"PPL",
    "gn:name":"Nied\u017awied\u017a",
    "gn:population":0,
    "gn:timezone":"Europe/Warsaw",
    "iso:country":"PL",
    "name:und_x_variant":[
        "Nied\u017awied\u017a"
    ],
    "wof:name":"Niedzwiedz",
    "wof:placetype":"locality"
},
  "geometry": {"coordinates":[14.81837,53.3665],"type":"Point"}
}