{
  "type": "Feature",
  "properties": {
    "gn:admin1_code":"78.0",
    "gn:admin2_code":"1415.0",
    "gn:admin3_code":"141505.0",
    "gn:asciiname":"Todzia",
    "gn:country_code":"PL",
    "gn:dem":110,
    "gn:feature_class":"P",
    "gn:feature_code":"PPL",
    "gn:name":"Todzia",
    "gn:population":0,
    "gn:timezone":"Europe/Warsaw",
    "iso:country":"PL",
    "name:fra_x_preferred":[
        "Todzia"
    ],
    "name:pol_x_preferred":[
        "Todzia"
    ],
    "name:ukr_x_preferred":[
        "\u0422\u043e\u0434\u0437\u044f"
    ],
    "wof:name":"Todzia",
    "wof:placetype":"locality"
},
  "geometry": {"coordinates":[21.43705,53.27419],"type":"Point"}
}