{
  "type": "Feature",
  "properties": {
    "gn:admin1_code":"78.0",
    "gn:admin2_code":"1423.0",
    "gn:admin3_code":"142306.0",
    "gn:asciiname":"Hucisko",
    "gn:country_code":"PL",
    "gn:dem":289,
    "gn:feature_class":"P",
    "gn:feature_code":"PPL",
    "gn:name":"Hucisko",
    "gn:population":0,
    "gn:timezone":"Europe/Warsaw",
    "iso:country":"PL",
    "name:ceb_x_preferred":[
        "Hucisko"
    ],
    "name:deu_x_preferred":[
        "Hucisko"
    ],
    "name:fra_x_preferred":[
        "Hucisko"
    ],
    "name:pol_x_preferred":[
        "Hucisko"
    ],
    "name:ukr_x_preferred":[
        "\u0413\u0443\u0446\u0438\u0441\u044c\u043a\u043e"
    ],
    "wof:name":"Hucisko",
    "wof:placetype":"locality"
},
  "geometry": {"coordinates":[20.60905,51.2503],"type":"Point"}
}