{
  "type": "Feature",
  "properties": {
    "gn:admin1_code":"78.0",
    "gn:admin2_code":"1401.0",
    "gn:admin3_code":"140103.0",
    "gn:asciiname":"Grotki",
    "gn:country_code":"PL",
    "gn:dem":172,
    "gn:feature_class":"P",
    "gn:feature_code":"PPL",
    "gn:name":"Grotki",
    "gn:population":0,
    "gn:timezone":"Europe/Warsaw",
    "iso:country":"PL",
    "wof:name":"Grotki",
    "wof:placetype":"locality"
},
  "geometry": {"coordinates":[20.79785,51.54875],"type":"Point"}
}