{
  "type": "Feature",
  "properties": {
    "gn:admin1_code":"77.0",
    "gn:admin2_code":"1211.0",
    "gn:admin3_code":"121105.0",
    "gn:asciiname":"Suwadow",
    "gn:country_code":"PL",
    "gn:dem":650,
    "gn:feature_class":"P",
    "gn:feature_code":"PPL",
    "gn:name":"Suwad\u00f3w",
    "gn:population":0,
    "gn:timezone":"Europe/Warsaw",
    "iso:country":"PL",
    "wof:name":"Suwadow",
    "wof:placetype":"locality"
},
  "geometry": {"coordinates":[19.71667,49.48333],"type":"Point"}
}