{
  "type": "Feature",
  "properties": {
    "gn:admin1_code":"75.0",
    "gn:admin2_code":"614.0",
    "gn:admin3_code":"61409.0",
    "gn:asciiname":"Anielin",
    "gn:country_code":"PL",
    "gn:dem":160,
    "gn:feature_class":"P",
    "gn:feature_code":"PPL",
    "gn:name":"Anielin",
    "gn:population":0,
    "gn:timezone":"Europe/Warsaw",
    "iso:country":"PL",
    "name:fra_x_preferred":[
        "Anielin"
    ],
    "name:pol_x_preferred":[
        "Anielin"
    ],
    "name:ukr_x_preferred":[
        "\u0410\u043d\u0435\u043b\u0456\u043d"
    ],
    "wof:name":"Anielin",
    "wof:placetype":"locality"
},
  "geometry": {"coordinates":[21.82125,51.41323],"type":"Point"}
}