{
  "type": "Feature",
  "properties": {
    "gn:admin1_code":"77.0",
    "gn:admin2_code":"1201.0",
    "gn:admin3_code":"120102.0",
    "gn:asciiname":"Majkowice",
    "gn:country_code":"PL",
    "gn:dem":187,
    "gn:feature_class":"P",
    "gn:feature_code":"PPL",
    "gn:name":"Majkowice",
    "gn:population":0,
    "gn:timezone":"Europe/Warsaw",
    "iso:country":"PL",
    "name:deu_x_preferred":[
        "Majkowice"
    ],
    "name:pol_x_preferred":[
        "Majkowice"
    ],
    "name:ukr_x_preferred":[
        "\u041c\u0430\u0439\u043a\u043e\u0432\u0456\u0446\u0435"
    ],
    "wof:name":"Majkowice",
    "wof:placetype":"locality"
},
  "geometry": {"coordinates":[20.47646,50.04656],"type":"Point"}
}