{
  "type": "Feature",
  "properties": {
    "gn:admin1_code":"81.0",
    "gn:admin2_code":"2002.0",
    "gn:admin3_code":"200206.0",
    "gn:asciiname":"Lapy Debowizna",
    "gn:country_code":"PL",
    "gn:dem":124,
    "gn:feature_class":"P",
    "gn:feature_code":"PPL",
    "gn:name":"\u0141apy D\u0119bowizna",
    "gn:population":0,
    "gn:timezone":"Europe/Warsaw",
    "iso:country":"PL",
    "name:lit_x_preferred":[
        "Lapi Dembovina"
    ],
    "name:pol_x_preferred":[
        "\u0141apy-D\u0119bowina"
    ],
    "name:ukr_x_preferred":[
        "\u041b\u0430\u043f\u0438-\u0414\u0435\u043c\u0431\u043e\u0432\u0456\u043d\u0430"
    ],
    "name:und_x_variant":[
        "\u0141apy D\u0119bowizna"
    ],
    "wof:name":"Lapy Debowizna",
    "wof:placetype":"locality"
},
  "geometry": {"coordinates":[22.89778,52.97315],"type":"Point"}
}