{
  "type": "Feature",
  "properties": {
    "gn:admin1_code":"86.0",
    "gn:admin2_code":"3010.0",
    "gn:admin3_code":"301006.0",
    "gn:asciiname":"Hiszpania",
    "gn:cc2":"PL",
    "gn:country_code":"PL",
    "gn:dem":161,
    "gn:feature_class":"P",
    "gn:feature_code":"PPL",
    "gn:name":"Hiszpania",
    "gn:population":0,
    "gn:timezone":"Europe/Warsaw",
    "iso:country":"PL",
    "name:und_x_variant":[
        "Hiszpanja",
        "Hiszpania"
    ],
    "wof:name":"Hiszpania",
    "wof:placetype":"locality"
},
  "geometry": {"coordinates":[18.31667,52.13333],"type":"Point"}
}