{
  "type": "Feature",
  "properties": {
    "gn:admin1_code":"86.0",
    "gn:admin2_code":"3013.0",
    "gn:admin3_code":"301302.0",
    "gn:asciiname":"Wilkowo Leszczynskie",
    "gn:country_code":"PL",
    "gn:dem":108,
    "gn:feature_class":"P",
    "gn:feature_code":"PPL",
    "gn:name":"Wilkowo Leszczy\u0144skie",
    "gn:population":0,
    "gn:timezone":"Europe/Warsaw",
    "iso:country":"PL",
    "wof:name":"Wilkowo Leszczynskie",
    "wof:placetype":"neighbourhood"
},
  "geometry": {"coordinates":[16.53333,51.88333],"type":"Point"}
}