{
  "type": "Feature",
  "properties": {
    "gn:admin1_code":"74.0",
    "gn:admin2_code":"1018.0",
    "gn:admin3_code":"101802.0",
    "gn:asciiname":"Chorobel",
    "gn:country_code":"PL",
    "gn:dem":181,
    "gn:feature_class":"P",
    "gn:feature_code":"PPL",
    "gn:name":"Chorobel",
    "gn:population":0,
    "gn:timezone":"Europe/Warsaw",
    "iso:country":"PL",
    "wof:name":"Chorobel",
    "wof:placetype":"locality"
},
  "geometry": {"coordinates":[18.34888,51.24086],"type":"Point"}
}