{
  "type": "Feature",
  "properties": {
    "gn:admin1_code":"74.0",
    "gn:admin2_code":"1010.0",
    "gn:admin3_code":"101001.0",
    "gn:asciiname":"Zalesice",
    "gn:country_code":"PL",
    "gn:dem":189,
    "gn:feature_class":"P",
    "gn:feature_code":"PPL",
    "gn:name":"Zalesice",
    "gn:population":0,
    "gn:timezone":"Europe/Warsaw",
    "iso:country":"PL",
    "name:fra_x_preferred":[
        "Zalesice"
    ],
    "name:pol_x_preferred":[
        "Zalesice"
    ],
    "name:ukr_x_preferred":[
        "\u0417\u0430\u043b\u0435\u0441\u0456\u0446\u0435"
    ],
    "wof:name":"Zalesice",
    "wof:placetype":"locality"
},
  "geometry": {"coordinates":[19.97289,51.32441],"type":"Point"}
}