{
  "type": "Feature",
  "properties": {
    "gn:admin1_code":"82.0",
    "gn:admin2_code":"2202.0",
    "gn:admin3_code":"220202.0",
    "gn:asciiname":"Rolbik",
    "gn:country_code":"PL",
    "gn:dem":122,
    "gn:feature_class":"P",
    "gn:feature_code":"PPL",
    "gn:name":"Rolbik",
    "gn:population":0,
    "gn:timezone":"Europe/Warsaw",
    "iso:country":"PL",
    "name:ceb_x_preferred":[
        "Rolbik"
    ],
    "name:csb_x_preferred":[
        "R\u00f3lbi\u00e9k"
    ],
    "name:pol_x_preferred":[
        "Rolbik"
    ],
    "name:ukr_x_preferred":[
        "\u0420\u043e\u043b\u044c\u0431\u0438\u043a"
    ],
    "wof:name":"Rolbik",
    "wof:placetype":"locality"
},
  "geometry": {"coordinates":[17.57839,53.92831999999999],"type":"Point"}
}