{
  "type": "Feature",
  "properties": {
    "gn:admin1_code":"74.0",
    "gn:admin2_code":"1016.0",
    "gn:admin3_code":"101609.0",
    "gn:asciiname":"Zaborow",
    "gn:country_code":"PL",
    "gn:dem":164,
    "gn:feature_class":"P",
    "gn:feature_code":"PPL",
    "gn:name":"Zabor\u00f3w",
    "gn:population":0,
    "gn:timezone":"Europe/Warsaw",
    "iso:country":"PL",
    "name:und_x_variant":[
        "Zabor\u00f3w Pierwszy",
        "Zabor\u00f3w"
    ],
    "wof:name":"Zaborow",
    "wof:placetype":"locality"
},
  "geometry": {"coordinates":[19.98392,51.56056],"type":"Point"}
}