{
  "type": "Feature",
  "properties": {
    "gn:admin1_code":"74.0",
    "gn:admin2_code":"1016.0",
    "gn:admin3_code":"101609.0",
    "gn:asciiname":"Zaborow",
    "gn:country_code":"PL",
    "gn:dem":164,
    "gn:feature_class":"P",
    "gn:feature_code":"PPL",
    "gn:name":"Zabor\u00f3w",
    "gn:population":0,
    "gn:timezone":"Europe/Warsaw",
    "iso:country":"PL",
    "name:pol_x_preferred":[
        "Zabor\u00f3w Pierwszy"
    ],
    "name:ukr_x_preferred":[
        "\u0417\u0430\u0431\u043e\u0440\u0443\u0432-\u041f\u0435\u0440\u0448\u0438\u0439"
    ],
    "name:und_x_variant":[
        "Zabor\u00f3w"
    ],
    "name:urd_x_preferred":[
        "\u0632\u0628\u0648\u0631\u0648\u0648 \u067e\u06cc\u0631\u0648\u0633\u0632\u06d2"
    ],
    "wof:name":"Zaborow",
    "wof:placetype":"locality"
},
  "geometry": {"coordinates":[19.98392,51.56056],"type":"Point"}
}