{
  "type": "Feature",
  "properties": {
    "gn:admin1_code":"87.0",
    "gn:admin2_code":"3215.0",
    "gn:admin3_code":"321502.0",
    "gn:asciiname":"Chwalimki",
    "gn:country_code":"PL",
    "gn:dem":156,
    "gn:feature_class":"P",
    "gn:feature_code":"PPL",
    "gn:name":"Chwalimki",
    "gn:population":0,
    "gn:timezone":"Europe/Warsaw",
    "iso:country":"PL",
    "name:pol_x_preferred":[
        "Chwalimki"
    ],
    "name:vie_x_preferred":[
        "Chwalimki"
    ],
    "wof:name":"Chwalimki",
    "wof:placetype":"locality"
},
  "geometry": {"coordinates":[16.46037999999999,53.733],"type":"Point"}
}