{
  "type": "Feature",
  "properties": {
    "gn:admin1_code":"74.0",
    "gn:admin2_code":"1006.0",
    "gn:admin3_code":"100607.0",
    "gn:asciiname":"Katarzynow",
    "gn:cc2":"PL",
    "gn:country_code":"PL",
    "gn:dem":206,
    "gn:feature_class":"P",
    "gn:feature_code":"PPL",
    "gn:name":"Katarzyn\u00f3w",
    "gn:population":0,
    "gn:timezone":"Europe/Warsaw",
    "iso:country":"PL",
    "name:fra_x_preferred":[
        "Katarzyn\u00f3w"
    ],
    "name:pol_x_preferred":[
        "Katarzyn\u00f3w"
    ],
    "name:ukr_x_preferred":[
        "\u041a\u0430\u0442\u0430\u0436\u0438\u043d\u0443\u0432"
    ],
    "name:und_x_variant":[
        "Katarzyn\u00f3w Nowy"
    ],
    "wof:name":"Katarzynow",
    "wof:placetype":"locality"
},
  "geometry": {"coordinates":[19.85126,51.74149],"type":"Point"}
}