{
  "type": "Feature",
  "properties": {
    "gn:admin1_code":"74.0",
    "gn:admin2_code":"1006.0",
    "gn:admin3_code":"100607.0",
    "gn:asciiname":"Katarzynow",
    "gn:cc2":"PL",
    "gn:country_code":"PL",
    "gn:dem":206,
    "gn:feature_class":"P",
    "gn:feature_code":"PPL",
    "gn:name":"Katarzyn\u00f3w",
    "gn:population":0,
    "gn:timezone":"Europe/Warsaw",
    "iso:country":"PL",
    "name:und_x_variant":[
        "Katarzyn\u00f3w Nowy",
        "Katarzyn\u00f3w"
    ],
    "wof:name":"Katarzynow",
    "wof:placetype":"locality"
},
  "geometry": {"coordinates":[19.85126,51.74149],"type":"Point"}
}