{
  "type": "Feature",
  "properties": {
    "gn:admin1_code":"85.0",
    "gn:admin2_code":"2805.0",
    "gn:admin3_code":"280505.0",
    "gn:asciiname":"Balamutowo",
    "gn:country_code":"PL",
    "gn:dem":132,
    "gn:feature_class":"P",
    "gn:feature_code":"PPL",
    "gn:name":"Ba\u0142amutowo",
    "gn:population":0,
    "gn:timezone":"Europe/Warsaw",
    "iso:country":"PL",
    "name:deu_x_preferred":[
        "Ba\u0142amutowo"
    ],
    "name:nld_x_preferred":[
        "Ba\u0142amutowo"
    ],
    "name:pol_x_preferred":[
        "Ba\u0142amutowo"
    ],
    "name:ukr_x_preferred":[
        "\u0411\u0430\u043b\u0430\u043c\u0443\u0442\u043e\u0432\u043e"
    ],
    "name:und_x_variant":[
        "Giersfelde",
        "Ballamutowen"
    ],
    "wof:name":"Balamutowo",
    "wof:placetype":"locality"
},
  "geometry": {"coordinates":[22.24623,53.89686999999999],"type":"Point"}
}