{
  "type": "Feature",
  "properties": {
    "gn:admin1_code":"78.0",
    "gn:admin2_code":"1433.0",
    "gn:admin3_code":"143303.0",
    "gn:asciiname":"Szczurow",
    "gn:country_code":"PL",
    "gn:dem":160,
    "gn:feature_class":"P",
    "gn:feature_code":"PPL",
    "gn:name":"Szczur\u00f3w",
    "gn:population":0,
    "gn:timezone":"Europe/Warsaw",
    "iso:country":"PL",
    "name:fra_x_preferred":[
        "Szczur\u00f3w"
    ],
    "name:pol_x_preferred":[
        "Szczur\u00f3w"
    ],
    "name:ukr_x_preferred":[
        "\u0429\u0443\u0440\u0443\u0432"
    ],
    "wof:name":"Szczurow",
    "wof:placetype":"locality"
},
  "geometry": {"coordinates":[21.84035,52.36478],"type":"Point"}
}