{
  "type": "Feature",
  "properties": {
    "gn:gn_country":"PL",
    "gn:gn_fcode":"PPLA3",
    "gn:gn_pop":4522,
    "gn:population":4522,
    "iso:country":"PL",
    "name:deu_x_preferred":[
        "Brze\u015b\u0107 Kujawski"
    ],
    "name:eng_x_preferred":[
        "Brze\u015b\u0107 Kujawski"
    ],
    "name:fra_x_preferred":[
        "Brze\u015b\u0107 Kujawski"
    ],
    "name:heb_x_preferred":[
        "\u05d1\u05d6\u05e9\u05e5 \u05e7\u05d5\u05d9\u05d0\u05d1\u05e1\u05e7\u05d9"
    ],
    "name:jav_x_preferred":[
        "Brze\u015b\u0107 Kujawski"
    ],
    "name:lav_x_preferred":[
        "B\u017eesca Kujavska"
    ],
    "name:lit_x_preferred":[
        "Kujavijos Brestas"
    ],
    "name:nld_x_preferred":[
        "Brze\u015b\u0107 Kujawski"
    ],
    "name:pol_x_preferred":[
        "Brze\u015b\u0107 Kujawski"
    ],
    "name:ron_x_preferred":[
        "Brze\u015b\u0107 Kujawski"
    ],
    "name:rus_x_preferred":[
        "\u0411\u0436\u0435\u0441\u0446\u044c-\u041a\u0443\u044f\u0432\u0441\u043a\u0438\u0439"
    ],
    "name:srp_x_preferred":[
        "\u0411\u0436\u0435\u0448\u045b \u041a\u0443\u0458\u0430\u0432\u0441\u043a\u0438"
    ],
    "name:ukr_x_preferred":[
        "\u0411\u0436\u0435\u0441\u0446\u044c-\u041a\u0443\u044f\u0432\u0441\u044c\u043a\u0438\u0439"
    ],
    "name:urd_x_preferred":[
        "\u0628\u0631\u0632\u06d2\u0633\u0686 \u06a9\u062c\u0648\u0633\u06a9\u06cc"
    ],
    "name:zho_x_preferred":[
        "\u5eab\u4e9e\u7dad\u5730\u5340\u5e03\u71b1\u5e0c\u5947"
    ],
    "qs_pg:aaroncc":"PL",
    "qs_pg:gn_country":"PL",
    "qs_pg:gn_fcode":"PPLA3",
    "qs_pg:gn_pop":4522,
    "qs_pg:name":"Brze\u015b\u0107 Kujawski",
    "qs_pg:name_adm0":"Polska",
    "qs_pg:name_adm1":"Kujawsko-Pomorskie",
    "qs_pg:photos":5,
    "qs_pg:photos_1k":1,
    "qs_pg:photos_9k":1,
    "qs_pg:photos_9r":1,
    "qs_pg:photos_all":5,
    "qs_pg:photos_sr":1,
    "qs_pg:pop_sr":4,
    "qs_pg:qs_pg_placetype":"localadmin",
    "qs_pg:qs_pg_placetype_gp":"LocalAdmin",
    "qs_pg:woe_adm0":23424923,
    "woe:adm0_id":23424923,
    "woe:name_adm0":"Polska",
    "woe:name_adm1":"Kujawsko-Pomorskie",
    "woe:placetype":"LocalAdmin",
    "wof:name":"Brze\u015b\u0107 Kujawski",
    "wof:placetype":"localadmin",
    "wof:population":4522
},
  "geometry": {"coordinates":[18.90173,52.60532],"type":"Point"}
}