{
  "type": "Feature",
  "properties": {
    "gn:admin1_code":"73.0",
    "gn:admin2_code":"419.0",
    "gn:admin3_code":"41902.0",
    "gn:asciiname":"Obudno",
    "gn:country_code":"PL",
    "gn:dem":106,
    "gn:feature_class":"P",
    "gn:feature_code":"PPL",
    "gn:name":"Obudno",
    "gn:population":0,
    "gn:timezone":"Europe/Warsaw",
    "iso:country":"PL",
    "name:pol_x_preferred":[
        "Obudno"
    ],
    "name:ukr_x_preferred":[
        "\u041e\u0431\u0443\u0434\u043d\u043e"
    ],
    "wof:name":"Obudno",
    "wof:placetype":"locality"
},
  "geometry": {"coordinates":[17.88675,52.77061],"type":"Point"}
}