{
  "type": "Feature",
  "properties": {
    "iso:country":"PL",
    "name:azb_x_preferred":[
        "\u0633\u0648\u0645\u0648\u0646\u0642\u0646\u0648"
    ],
    "name:csb_x_preferred":[
        "Som\u00f2nino"
    ],
    "name:fas_x_preferred":[
        "\u0633\u0648\u0645\u0648\u0646\u06af\u0646\u0648"
    ],
    "name:nld_x_preferred":[
        "Somonino"
    ],
    "name:pol_x_preferred":[
        "Somonino"
    ],
    "name:ukr_x_preferred":[
        "\u0421\u043e\u043c\u043e\u043d\u0456\u043d\u043e"
    ],
    "qs_pg:aaroncc":"PL",
    "qs_pg:name":"Somonino",
    "qs_pg:name_adm0":"Polska",
    "qs_pg:name_adm1":"Pomorskie",
    "qs_pg:photos":185,
    "qs_pg:photos_1k":37,
    "qs_pg:photos_9k":1,
    "qs_pg:photos_9r":4,
    "qs_pg:photos_all":196,
    "qs_pg:photos_sr":4,
    "qs_pg:pop_sr":0,
    "qs_pg:qs_pg_placetype":"localadmin",
    "qs_pg:qs_pg_placetype_gp":"LocalAdmin",
    "qs_pg:woe_adm0":23424923,
    "woe:adm0_id":23424923,
    "woe:name_adm0":"Polska",
    "woe:name_adm1":"Pomorskie",
    "woe:placetype":"LocalAdmin",
    "wof:name":"Somonino",
    "wof:placetype":"localadmin"
},
  "geometry": {"coordinates":[18.095358,54.288476],"type":"Point"}
}