{
  "type": "Feature",
  "properties": {
    "gn:admin1_code":"74.0",
    "gn:admin2_code":"1013.0",
    "gn:admin3_code":"101304.0",
    "gn:asciiname":"Zydomice",
    "gn:country_code":"PL",
    "gn:dem":135,
    "gn:feature_class":"P",
    "gn:feature_code":"PPL",
    "gn:name":"\u017bydomice",
    "gn:population":0,
    "gn:timezone":"Europe/Warsaw",
    "iso:country":"PL",
    "name:pol_x_preferred":[
        "\u017bydomice"
    ],
    "name:ukr_x_preferred":[
        "\u0416\u0438\u0434\u043e\u043c\u0456\u0446\u0435"
    ],
    "wof:name":"Zydomice",
    "wof:placetype":"locality"
},
  "geometry": {"coordinates":[20.27165,51.79349000000001],"type":"Point"}
}