{
  "type": "Feature",
  "properties": {
    "iso:country":"PL",
    "name:fas_x_preferred":[
        "\u0641\u0631\u0648\u062f\u06af\u0627\u0647 \u0631\u0627\u062f\u0648\u0645-\u0633\u0627\u062f\u06a9\u0648\u0641"
    ],
    "name:fra_x_preferred":[
        "A\u00e9roport de Radom"
    ],
    "name:ita_x_preferred":[
        "Aeroporto di Radom-Sadk\u00f3w"
    ],
    "name:pol_x_preferred":[
        "Port lotniczy Radom-Sadk\u00f3w"
    ],
    "name:tgk_x_preferred":[
        "\u0424\u0443\u0440\u0443\u0434\u0433\u043e\u04b3\u0438 \u0440\u043e\u0434\u0443\u043c-\u0441\u043e\u0434\u043a\u0443\u0444"
    ],
    "oa:elevation_ft":"610",
    "oa:type":"medium_airport",
    "wd:wordcount":1353,
    "woe:hierarchy":{
        "country_id":23424923,
        "county_id":12591297,
        "localadmin_id":12616706,
        "planet_id":1,
        "state_id":12577941
    },
    "wof:name":"Sadkow Airport",
    "wof:placetype":"campus"
},
  "geometry": {"coordinates":[21.213611111111,51.389166666667],"type":"Point"}
}