{
  "type": "Feature",
  "properties": {
    "iso:country":"PL",
    "name:arz_x_preferred":[
        "\u0645\u0637\u0627\u0631 \u0631\u0627\u062f\u0648\u0645 \u0633\u0627\u062f\u0643\u0648"
    ],
    "name:bel_x_preferred":[
        "\u0410\u044d\u0440\u0430\u043f\u043e\u0440\u0442 \u0412\u0430\u0440\u0448\u0430\u0432\u0430-\u0420\u0430\u0434\u0430\u043c"
    ],
    "name:ceb_x_preferred":[
        "Radom-Sadk\u00f3w Airport"
    ],
    "name:deu_x_preferred":[
        "Flughafen Radom-Sadk\u00f3w"
    ],
    "name:deu_x_variant":[
        "Flughafen Warschau-Radom"
    ],
    "name:ell_x_preferred":[
        "\u0391\u03b5\u03c1\u03bf\u03b4\u03c1\u03cc\u03bc\u03b9\u03bf \u03a1\u03ac\u03bd\u03c4\u03bf\u03bc"
    ],
    "name:eng_x_preferred":[
        "Radom-Sadk\u00f3w Airport"
    ],
    "name:eng_x_variant":[
        "RDO",
        "EPRA",
        "Warsaw Radom Airport"
    ],
    "name:fas_x_preferred":[
        "\u0641\u0631\u0648\u062f\u06af\u0627\u0647 \u0631\u0627\u062f\u0648\u0645-\u0633\u0627\u062f\u06a9\u0648\u0641"
    ],
    "name:fra_x_preferred":[
        "A\u00e9roport de Radom"
    ],
    "name:ita_x_preferred":[
        "Aeroporto di Radom-Sadk\u00f3w"
    ],
    "name:jpn_x_preferred":[
        "\u30e9\u30c9\u30e0\u7a7a\u6e2f"
    ],
    "name:nld_x_preferred":[
        "Radom-Sadk\u00f3w Airport"
    ],
    "name:pol_x_preferred":[
        "Port lotniczy Radom-Sadk\u00f3w"
    ],
    "name:pol_x_variant":[
        "Port lotniczy Warszawa-Radom"
    ],
    "name:ron_x_preferred":[
        "Aeroportul Radom-Sadk\u00f3w"
    ],
    "name:rus_x_preferred":[
        "\u0430\u044d\u0440\u043e\u043f\u043e\u0440\u0442 \u0412\u0430\u0440\u0448\u0430\u0432\u0430-\u0420\u0430\u0434\u043e\u043c"
    ],
    "name:tgk_x_preferred":[
        "\u0424\u0443\u0440\u0443\u0434\u0433\u043e\u04b3\u0438 \u0440\u043e\u0434\u0443\u043c-\u0441\u043e\u0434\u043a\u0443\u0444"
    ],
    "name:ukr_x_preferred":[
        "\u0420\u0430\u0434\u043e\u043c"
    ],
    "name:zho_x_preferred":[
        "\u62c9\u591a\u59c6"
    ],
    "oa:elevation_ft":"610",
    "oa:type":"medium_airport",
    "wd:wordcount":1353,
    "woe:hierarchy":{
        "country_id":23424923,
        "county_id":12591297,
        "localadmin_id":12616706,
        "planet_id":1,
        "state_id":12577941
    },
    "wof:name":"Sadkow Airport",
    "wof:placetype":"campus"
},
  "geometry": {"coordinates":[21.213611,51.389167],"type":"Point"}
}