{
  "type": "Feature",
  "properties": {
    "gn:admin1_code":"87.0",
    "gn:admin2_code":"3201.0",
    "gn:admin3_code":"320104.0",
    "gn:asciiname":"Smecino",
    "gn:country_code":"PL",
    "gn:dem":131,
    "gn:feature_class":"P",
    "gn:feature_code":"PPL",
    "gn:name":"Sm\u0119cino",
    "gn:population":0,
    "gn:timezone":"Europe/Warsaw",
    "iso:country":"PL",
    "name:ceb_x_preferred":[
        "Sm\u0119cino"
    ],
    "name:deu_x_preferred":[
        "Sm\u0119cino"
    ],
    "name:pol_x_preferred":[
        "Sm\u0119cino"
    ],
    "name:swe_x_preferred":[
        "Sm\u0119cino"
    ],
    "name:ukr_x_preferred":[
        "\u0421\u043c\u0435\u043d\u0446\u0438\u043d\u043e"
    ],
    "name:und_x_variant":[
        "Sm\u0119cino"
    ],
    "wof:name":"Smecino",
    "wof:placetype":"locality"
},
  "geometry": {"coordinates":[16.41231,53.94695],"type":"Point"}
}