{
  "type": "Feature",
  "properties": {
    "gn:admin1_code":"74.0",
    "gn:admin2_code":"1021.0",
    "gn:admin3_code":"102103.0",
    "gn:asciiname":"Zabki",
    "gn:country_code":"PL",
    "gn:dem":154,
    "gn:feature_class":"P",
    "gn:feature_code":"PPL",
    "gn:name":"Z\u0105bki",
    "gn:population":0,
    "gn:timezone":"Europe/Warsaw",
    "iso:country":"PL",
    "name:fra_x_preferred":[
        "Z\u0105bki"
    ],
    "name:pol_x_preferred":[
        "Z\u0105bki"
    ],
    "name:ukr_x_preferred":[
        "\u0417\u043e\u043c\u0431\u043a\u0456"
    ],
    "name:und_x_variant":[
        "Z\u0105bki"
    ],
    "name:urd_x_preferred":[
        "\u0632\u0648\u0628\u06a9\u06cc"
    ],
    "wof:name":"Zabki",
    "wof:placetype":"locality"
},
  "geometry": {"coordinates":[19.8017,51.92654],"type":"Point"}
}