{
  "type": "Feature",
  "properties": {
    "gn:admin1_code":"74.0",
    "gn:admin2_code":"1009.0",
    "gn:admin3_code":"100904.0",
    "gn:asciiname":"Makowiska",
    "gn:country_code":"PL",
    "gn:dem":227,
    "gn:feature_class":"P",
    "gn:feature_code":"PPL",
    "gn:name":"Makowiska",
    "gn:population":0,
    "gn:timezone":"Europe/Warsaw",
    "iso:country":"PL",
    "name:fra_x_preferred":[
        "Makowiska"
    ],
    "name:pol_x_preferred":[
        "Makowiska"
    ],
    "name:ukr_x_preferred":[
        "\u041c\u0430\u043a\u043e\u0432\u0438\u0441\u044c\u043a\u0430"
    ],
    "wof:name":"Makowiska",
    "wof:placetype":"locality"
},
  "geometry": {"coordinates":[19.02503,51.11361],"type":"Point"}
}