{
  "type": "Feature",
  "properties": {
    "gn:admin1_code":"86.0",
    "gn:admin2_code":"3027.0",
    "gn:admin3_code":"302705.0",
    "gn:asciiname":"Zdzienice",
    "gn:country_code":"PL",
    "gn:dem":158,
    "gn:feature_class":"P",
    "gn:feature_code":"PPL",
    "gn:name":"Zdzienice",
    "gn:population":0,
    "gn:timezone":"Europe/Warsaw",
    "iso:country":"PL",
    "name:und_x_variant":[
        "Zd\u017cenice",
        "Zdzienice",
        "\u017bd\u017cenice"
    ],
    "wof:name":"Zdzienice",
    "wof:placetype":"locality"
},
  "geometry": {"coordinates":[18.41524,51.97802],"type":"Point"}
}