{
  "type": "Feature",
  "properties": {
    "gn:admin1_code":"78.0",
    "gn:admin2_code":"1413.0",
    "gn:admin3_code":"141310.0",
    "gn:asciiname":"Bogurzynek",
    "gn:country_code":"PL",
    "gn:dem":118,
    "gn:feature_class":"P",
    "gn:feature_code":"PPL",
    "gn:name":"Bogurzynek",
    "gn:population":0,
    "gn:timezone":"Europe/Warsaw",
    "iso:country":"PL",
    "wof:name":"Bogurzynek",
    "wof:placetype":"locality"
},
  "geometry": {"coordinates":[20.26085,53.03688],"type":"Point"}
}