{
  "type": "Feature",
  "properties": {
    "gn:admin1_code":"78.0",
    "gn:admin2_code":"1425.0",
    "gn:admin3_code":"142503.0",
    "gn:asciiname":"Jedlanka Stara",
    "gn:country_code":"PL",
    "gn:dem":173,
    "gn:feature_class":"P",
    "gn:feature_code":"PPL",
    "gn:name":"Jedlanka Stara",
    "gn:population":0,
    "gn:timezone":"Europe/Warsaw",
    "iso:country":"PL",
    "wof:name":"Jedlanka Stara",
    "wof:placetype":"locality"
},
  "geometry": {"coordinates":[21.2821,51.19886],"type":"Point"}
}