{
  "type": "Feature",
  "properties": {
    "gn:admin1_code":"78.0",
    "gn:admin2_code":"1425.0",
    "gn:admin3_code":"142503.0",
    "gn:asciiname":"Jedlanka Stara",
    "gn:country_code":"PL",
    "gn:dem":173,
    "gn:feature_class":"P",
    "gn:feature_code":"PPL",
    "gn:name":"Jedlanka Stara",
    "gn:population":0,
    "gn:timezone":"Europe/Warsaw",
    "iso:country":"PL",
    "name:azb_x_preferred":[
        "\u06cc\u062f\u0644\u0627\u0646\u06a9\u0627 \u0633\u062a\u0627\u0631\u0627"
    ],
    "name:fas_x_preferred":[
        "\u06cc\u062f\u0644\u0627\u0646\u06a9\u0627 \u0633\u062a\u0627\u0631\u0627"
    ],
    "name:fra_x_preferred":[
        "Jedlanka Stara"
    ],
    "name:pol_x_preferred":[
        "Jedlanka Stara"
    ],
    "name:ukr_x_preferred":[
        "\u0404\u0434\u043b\u044f\u043d\u043a\u0430-\u0421\u0442\u0430\u0440\u0430"
    ],
    "wof:name":"Jedlanka Stara",
    "wof:placetype":"locality"
},
  "geometry": {"coordinates":[21.2821,51.19886],"type":"Point"}
}