{
  "type": "Feature",
  "properties": {
    "gn:admin1_code":"85.0",
    "gn:admin2_code":"2814.0",
    "gn:admin3_code":"281402.0",
    "gn:asciiname":"Kamionka",
    "gn:country_code":"PL",
    "gn:dem":145,
    "gn:feature_class":"P",
    "gn:feature_code":"PPL",
    "gn:name":"Kamionka",
    "gn:population":0,
    "gn:timezone":"Europe/Warsaw",
    "iso:country":"PL",
    "name:deu_x_preferred":[
        "Kamionka"
    ],
    "name:pol_x_preferred":[
        "Kamionka"
    ],
    "name:ukr_x_preferred":[
        "\u041a\u0430\u043c\u0439\u043e\u043d\u043a\u0430"
    ],
    "name:und_x_variant":[
        "Steinhof",
        "Kamionka"
    ],
    "name:vie_x_preferred":[
        "Kamionka"
    ],
    "wof:name":"Kamionka",
    "wof:placetype":"locality"
},
  "geometry": {"coordinates":[21.08826,53.80438],"type":"Point"}
}