{
  "type": "Feature",
  "properties": {
    "gn:population":2000,
    "iso:country":"PL",
    "name:azb_x_preferred":[
        "\u0642\u0645\u06cc\u0646\u0627 \u0645\u06cc\u0648\u06a9\u0648\u0648\u06cc\u062a\u0633\u0647"
    ],
    "name:bel_x_preferred":[
        "\u0413\u043c\u0456\u043d\u0430 \u041c\u0456\u043b\u043a\u0430\u0432\u0456\u0446\u044b"
    ],
    "name:ces_x_preferred":[
        "Gmina Mi\u0142kowice"
    ],
    "name:deu_x_historical":[
        "Arnsdorf"
    ],
    "name:deu_x_preferred":[
        "Arnsdorf"
    ],
    "name:deu_x_variant":[
        "Gmina Mi\u0142kowice"
    ],
    "name:eng_x_preferred":[
        "Gmina Mi\u0142kowice"
    ],
    "name:eus_x_preferred":[
        "Mi\u0142kowice udalerria"
    ],
    "name:fas_x_preferred":[
        "\u06af\u0645\u06cc\u0646\u0627 \u0645\u06cc\u0648\u06a9\u0648\u0648\u06cc\u062a\u0633\u0647"
    ],
    "name:fra_x_preferred":[
        "Mi\u0142kowice"
    ],
    "name:ita_x_preferred":[
        "Mi\u0142kowice"
    ],
    "name:nan_x_preferred":[
        "Mi\u0142kowice"
    ],
    "name:nld_x_preferred":[
        "Mi\u0142kowice"
    ],
    "name:pol_x_preferred":[
        "Mi\u0142kowice"
    ],
    "name:por_x_preferred":[
        "Comuna de Mi\u0142kowice"
    ],
    "name:rus_x_preferred":[
        "\u041c\u0438\u043b\u043a\u043e\u0432\u0438\u0446\u0435"
    ],
    "name:slk_x_preferred":[
        "Gmina Mi\u0142kowice"
    ],
    "name:swe_x_preferred":[
        "Mi\u0142kowice kommun"
    ],
    "name:ukr_x_preferred":[
        "\u0490\u043c\u0456\u043d\u0430 \u041c\u0456\u043b\u043a\u043e\u0432\u0456\u0446\u0435"
    ],
    "name:war_x_preferred":[
        "Gmina Mi\u0142kowice"
    ],
    "qs:a0":"Rzeczpospolita Polska",
    "qs:a1":"*Dolnoslaskie",
    "qs:a1r":"0",
    "qs:a2":"Legnicki",
    "qs:adm0":"Rzeczpospolita Polska",
    "qs:la":"Mi\u0142kowice",
    "qs:la_lc":"*PL0209062",
    "qs:level":"locality",
    "qs:loc":"Mi\u0142kowice",
    "qs:loc_alt":"Milkowice",
    "qs:pop":0,
    "qs:type":"rural point-in-poly",
    "wd:wordcount":117,
    "wof:coterminous":[
        1477752455
    ],
    "wof:name":"Mi\u0142kowice",
    "wof:placetype":"locality",
    "wof:population":2000
},
  "geometry": {"coordinates":[16.0974790036953,51.2473048875909],"type":"Point"}
}