{
  "type": "Feature",
  "properties": {
    "gn:admin1_code":"78.0",
    "gn:admin2_code":"1436.0",
    "gn:admin3_code":"143601.0",
    "gn:asciiname":"Osuchow",
    "gn:country_code":"PL",
    "gn:dem":159,
    "gn:feature_class":"P",
    "gn:feature_code":"PPL",
    "gn:name":"Osuch\u00f3w",
    "gn:population":0,
    "gn:timezone":"Europe/Warsaw",
    "iso:country":"PL",
    "name:fra_x_preferred":[
        "Osuch\u00f3w"
    ],
    "name:pol_x_preferred":[
        "Osuch\u00f3w"
    ],
    "name:ukr_x_preferred":[
        "\u041e\u0441\u0443\u0445\u0443\u0432"
    ],
    "wof:name":"Osuchow",
    "wof:placetype":"locality"
},
  "geometry": {"coordinates":[21.42496,51.28477],"type":"Point"}
}