{
  "type": "Feature",
  "properties": {
    "iso:country":"PL",
    "name:deu_x_preferred":[
        "Trzebieszowice"
    ],
    "name:eng_x_preferred":[
        "Trzebieszowice"
    ],
    "name:fas_x_preferred":[
        "\u0686\u0628\u06cc\u0633\u0632\u0648\u0626\u06cc\u06a9"
    ],
    "name:fra_x_preferred":[
        "Trzebieszowice"
    ],
    "name:nld_x_preferred":[
        "Trzebieszowice"
    ],
    "name:pol_x_preferred":[
        "Trzebieszowice"
    ],
    "name:unk_x_variant":[
        "Kunzendorf"
    ],
    "qs:a0":"Rzeczpospolita Polska",
    "qs:a1":"*Dolnoslaskie",
    "qs:a1r":"0",
    "qs:a2":"Klodzki",
    "qs:adm0":"Rzeczpospolita Polska",
    "qs:la_lc":"*",
    "qs:level":"locality",
    "qs:loc":"Trzebieszowice",
    "qs:loc_alt":"Trzebieszowice",
    "qs:pop":0,
    "qs:type":"buffered point",
    "wd:wordcount":86,
    "wof:name":"Trzebieszowice",
    "wof:placetype":"locality"
},
  "geometry": {"coordinates":[16.771995,50.349968],"type":"Point"}
}