{
  "type": "Feature",
  "properties": {
    "gn:admin1_code":"74.0",
    "gn:admin2_code":"1006.0",
    "gn:admin3_code":"100603.0",
    "gn:asciiname":"Kurowice Bankowe",
    "gn:country_code":"PL",
    "gn:dem":192,
    "gn:feature_class":"P",
    "gn:feature_code":"PPL",
    "gn:name":"Kurowice Bankowe",
    "gn:population":0,
    "gn:timezone":"Europe/Warsaw",
    "iso:country":"PL",
    "wof:name":"Kurowice Bankowe",
    "wof:placetype":"locality"
},
  "geometry": {"coordinates":[19.68333,51.65],"type":"Point"}
}