{
  "type": "Feature",
  "properties": {
    "gn:admin1_code":"87.0",
    "gn:admin2_code":"3210.0",
    "gn:admin3_code":"321002.0",
    "gn:asciiname":"Reczyce",
    "gn:country_code":"PL",
    "gn:dem":23,
    "gn:feature_class":"P",
    "gn:feature_code":"PPL",
    "gn:name":"Reczyce",
    "gn:population":0,
    "gn:timezone":"Europe/Warsaw",
    "iso:country":"PL",
    "name:pol_x_preferred":[
        "Reczyce"
    ],
    "name:ukr_x_preferred":[
        "\u0420\u0435\u0447\u0438\u0446\u0435"
    ],
    "name:vie_x_preferred":[
        "Reczyce"
    ],
    "wof:name":"Reczyce",
    "wof:placetype":"locality"
},
  "geometry": {"coordinates":[14.59581,52.67831],"type":"Point"}
}