{
  "type": "Feature",
  "properties": {
    "gn:admin1_code":"73.0",
    "gn:admin2_code":"461.0",
    "gn:admin3_code":"46101.0",
    "gn:asciiname":"Rynkowo",
    "gn:country_code":"PL",
    "gn:dem":73,
    "gn:feature_class":"P",
    "gn:feature_code":"PPL",
    "gn:name":"Rynkowo",
    "gn:population":0,
    "gn:timezone":"Europe/Warsaw",
    "iso:country":"PL",
    "wof:name":"Rynkowo",
    "wof:placetype":"neighbourhood"
},
  "geometry": {"coordinates":[18.00059,53.16781],"type":"Point"}
}