{
  "type": "Feature",
  "properties": {
    "gn:admin1_code":"74.0",
    "gn:admin2_code":"1020.0",
    "gn:admin3_code":"102009.0",
    "gn:asciiname":"Glowa",
    "gn:country_code":"PL",
    "gn:dem":142,
    "gn:feature_class":"P",
    "gn:feature_code":"PPL",
    "gn:name":"G\u0142owa",
    "gn:population":0,
    "gn:timezone":"Europe/Warsaw",
    "iso:country":"PL",
    "name:ceb_x_preferred":[
        "G\u0142owa"
    ],
    "name:pol_x_preferred":[
        "Kolonia G\u0142owa"
    ],
    "name:ukr_x_preferred":[
        "\u041a\u043e\u043b\u044c\u043e\u043d\u0456\u044f-\u0490\u043b\u043e\u0432\u0430"
    ],
    "name:und_x_variant":[
        "G\u0142owo"
    ],
    "wof:name":"Glowa",
    "wof:placetype":"locality"
},
  "geometry": {"coordinates":[19.44527,51.92185],"type":"Point"}
}