{
  "type": "Feature",
  "properties": {
    "gn:gn_country":"PL",
    "gn:gn_fcode":"PPLA3",
    "gn:gn_pop":1723,
    "gn:population":1723,
    "iso:country":"PL",
    "name:azb_x_preferred":[
        "\u062f\u0648\u06cc\u06a9\u0648\u0632\u0647"
    ],
    "name:ceb_x_preferred":[
        "Dwikozy"
    ],
    "name:deu_x_preferred":[
        "Dwikozy"
    ],
    "name:fas_x_preferred":[
        "\u062f\u0648\u06cc\u06a9\u0648\u0632\u0647"
    ],
    "name:fra_x_preferred":[
        "Dwikozy"
    ],
    "name:nld_x_preferred":[
        "Dwikozy"
    ],
    "name:pol_x_preferred":[
        "Dwikozy"
    ],
    "name:ukr_x_preferred":[
        "\u0414\u0432\u0456\u043a\u043e\u0437\u0438"
    ],
    "qs_pg:aaroncc":"PL",
    "qs_pg:gn_country":"PL",
    "qs_pg:gn_fcode":"PPLA3",
    "qs_pg:gn_pop":1723,
    "qs_pg:name":"Dwikozy",
    "qs_pg:name_adm0":"Polska",
    "qs_pg:name_adm1":"Swi\u0119tokrzyskie",
    "qs_pg:photos":5,
    "qs_pg:photos_1k":1,
    "qs_pg:photos_9k":1,
    "qs_pg:photos_9r":1,
    "qs_pg:photos_all":5,
    "qs_pg:photos_sr":1,
    "qs_pg:pop_sr":3,
    "qs_pg:qs_pg_placetype":"localadmin",
    "qs_pg:qs_pg_placetype_gp":"LocalAdmin",
    "qs_pg:woe_adm0":23424923,
    "woe:adm0_id":23424923,
    "woe:name_adm0":"Polska",
    "woe:name_adm1":"Swi\u0119tokrzyskie",
    "woe:placetype":"LocalAdmin",
    "wof:name":"Dwikozy",
    "wof:placetype":"localadmin",
    "wof:population":1723
},
  "geometry": {"coordinates":[21.78864,50.73613],"type":"Point"}
}