{
  "type": "Feature",
  "properties": {
    "gn:admin1_code":"73.0",
    "gn:admin2_code":"407.0",
    "gn:admin3_code":"40708.0",
    "gn:asciiname":"Glinno Wielkie",
    "gn:country_code":"PL",
    "gn:dem":66,
    "gn:feature_class":"P",
    "gn:feature_code":"PPL",
    "gn:name":"Glinno Wielkie",
    "gn:population":0,
    "gn:timezone":"Europe/Warsaw",
    "iso:country":"PL",
    "name:pol_x_preferred":[
        "Glinno Wielkie"
    ],
    "name:ukr_x_preferred":[
        "\u0490\u043b\u0456\u043d\u043d\u043e-\u0412\u0435\u043b\u0438\u043a\u0435"
    ],
    "wof:name":"Glinno Wielkie",
    "wof:placetype":"locality"
},
  "geometry": {"coordinates":[18.34231,52.96814000000001],"type":"Point"}
}