{
  "type": "Feature",
  "properties": {
    "gn:admin1_code":"73.0",
    "gn:admin2_code":"407.0",
    "gn:admin3_code":"40708.0",
    "gn:asciiname":"Glinno Wielkie",
    "gn:country_code":"PL",
    "gn:dem":66,
    "gn:feature_class":"P",
    "gn:feature_code":"PPL",
    "gn:name":"Glinno Wielkie",
    "gn:population":0,
    "gn:timezone":"Europe/Warsaw",
    "iso:country":"PL",
    "wof:name":"Glinno Wielkie",
    "wof:placetype":"locality"
},
  "geometry": {"coordinates":[18.34231,52.96814000000001],"type":"Point"}
}