{
  "type": "Feature",
  "properties": {
    "gn:country":"PL",
    "gn:fcode":"PPLA3",
    "gn:population":0,
    "iso:country":"PL",
    "name:ceb_x_preferred":[
        "Zalesie"
    ],
    "name:deu_x_preferred":[
        "Zalesie"
    ],
    "name:fra_x_preferred":[
        "Zalesie"
    ],
    "name:lit_x_preferred":[
        "Zalesiai"
    ],
    "name:nld_x_preferred":[
        "Zalesie"
    ],
    "name:pol_x_preferred":[
        "Zalesie"
    ],
    "name:rus_x_preferred":[
        "\u0417\u0430\u043b\u0435\u0441\u0435"
    ],
    "name:swe_x_preferred":[
        "Zalesie"
    ],
    "name:ukr_x_preferred":[
        "\u0417\u0430\u043b\u0435\u0441\u0435"
    ],
    "qs_pg:aaroncc":"PL",
    "qs_pg:gn_country":"PL",
    "qs_pg:gn_fcode":"PPLA3",
    "qs_pg:gn_pop":0,
    "qs_pg:name":"Zalesie",
    "qs_pg:name_adm0":"Polska",
    "qs_pg:name_adm1":"Lubelskie",
    "qs_pg:photos":1,
    "qs_pg:photos_1k":1,
    "qs_pg:photos_9k":1,
    "qs_pg:photos_9r":1,
    "qs_pg:photos_all":1,
    "qs_pg:photos_sr":1,
    "qs_pg:pop_sr":0,
    "qs_pg:qs_pg_placetype":"localadmin",
    "qs_pg:qs_pg_placetype_gp":"LocalAdmin",
    "qs_pg:woe_adm0":23424923,
    "woe:adm0_id":23424923,
    "woe:name_adm0":"Polska",
    "woe:name_adm1":"Lubelskie",
    "woe:placetype":"LocalAdmin",
    "wof:name":"Zalesie",
    "wof:placetype":"localadmin"
},
  "geometry": {"coordinates":[23.3636,52.03743],"type":"Point"}
}