{
  "type": "Feature",
  "properties": {
    "gn:admin1_code":"78.0",
    "gn:admin2_code":"1413.0",
    "gn:admin3_code":"141305.0",
    "gn:asciiname":"Jozefowo",
    "gn:country_code":"PL",
    "gn:dem":121,
    "gn:feature_class":"P",
    "gn:feature_code":"PPL",
    "gn:name":"J\u00f3zefowo",
    "gn:population":0,
    "gn:timezone":"Europe/Warsaw",
    "iso:country":"PL",
    "wof:name":"Jozefowo",
    "wof:placetype":"locality"
},
  "geometry": {"coordinates":[20.32283,52.95401999999999],"type":"Point"}
}