{
  "type": "Feature",
  "properties": {
    "gn:admin1_code":"78.0",
    "gn:admin2_code":"1406.0",
    "gn:admin3_code":"140608.0",
    "gn:asciiname":"Zdzary",
    "gn:country_code":"PL",
    "gn:dem":150,
    "gn:feature_class":"P",
    "gn:feature_code":"PPL",
    "gn:name":"\u017bd\u017cary",
    "gn:population":0,
    "gn:timezone":"Europe/Warsaw",
    "iso:country":"PL",
    "name:fra_x_preferred":[
        "\u017bd\u017cary"
    ],
    "name:pol_x_preferred":[
        "\u017bd\u017cary"
    ],
    "name:ukr_x_preferred":[
        "\u0416\u0434\u0436\u0430\u0440\u0438"
    ],
    "wof:name":"Zdzary",
    "wof:placetype":"locality"
},
  "geometry": {"coordinates":[20.46392,51.65797],"type":"Point"}
}