{
  "type": "Feature",
  "properties": {
    "gn:admin1_code":"78.0",
    "gn:admin2_code":"1427.0",
    "gn:admin3_code":"142705.0",
    "gn:asciiname":"Bialyszewo Towarzystwo",
    "gn:country_code":"PL",
    "gn:dem":125,
    "gn:feature_class":"P",
    "gn:feature_code":"PPL",
    "gn:name":"Bia\u0142yszewo Towarzystwo",
    "gn:population":0,
    "gn:timezone":"Europe/Warsaw",
    "iso:country":"PL",
    "name:fra_x_preferred":[
        "Bia\u0142yszewo-Towarzystwo"
    ],
    "name:pol_x_preferred":[
        "Bia\u0142yszewo-Towarzystwo"
    ],
    "name:ukr_x_preferred":[
        "\u0411\u044f\u043b\u0438\u0448\u0435\u0432\u043e-\u0422\u043e\u0432\u0430\u0436\u0438\u0441\u0442\u0432\u043e"
    ],
    "name:und_x_variant":[
        "Bia\u0142yszewo Towarzystwo"
    ],
    "wof:name":"Bialyszewo Towarzystwo",
    "wof:placetype":"locality"
},
  "geometry": {"coordinates":[19.73251,52.77324],"type":"Point"}
}