{
  "type": "Feature",
  "properties": {
    "gn:admin1_code":"72.0",
    "gn:admin2_code":"208.0",
    "gn:admin3_code":"20810.0",
    "gn:asciiname":"Kamienczyk",
    "gn:country_code":"PL",
    "gn:dem":563,
    "gn:feature_class":"P",
    "gn:feature_code":"PPL",
    "gn:name":"Kamie\u0144czyk",
    "gn:population":0,
    "gn:timezone":"Europe/Warsaw",
    "iso:country":"PL",
    "wof:name":"Kamienczyk",
    "wof:placetype":"locality"
},
  "geometry": {"coordinates":[16.64978,50.11827],"type":"Point"}
}