{
  "type": "Feature",
  "properties": {
    "gn:admin1_code":"72.0",
    "gn:admin2_code":"208.0",
    "gn:admin3_code":"20810.0",
    "gn:asciiname":"Kamienczyk",
    "gn:country_code":"PL",
    "gn:dem":563,
    "gn:feature_class":"P",
    "gn:feature_code":"PPL",
    "gn:name":"Kamie\u0144czyk",
    "gn:population":0,
    "gn:timezone":"Europe/Warsaw",
    "iso:country":"PL",
    "name:azb_x_preferred":[
        "\u06a9\u0627\u0645\u06cc\u0646\u0642\u0686\u06a9"
    ],
    "name:ces_x_preferred":[
        "Kamie\u0144czyk"
    ],
    "name:deu_x_preferred":[
        "Kamie\u0144czyk"
    ],
    "name:fas_x_preferred":[
        "\u06a9\u0627\u0645\u06cc\u0646\u06af\u0686\u06a9"
    ],
    "name:pol_x_preferred":[
        "Kamie\u0144czyk"
    ],
    "name:ukr_x_preferred":[
        "\u041a\u0430\u043c\u0435\u043d\u044c\u0447\u0438\u043a"
    ],
    "wof:name":"Kamienczyk",
    "wof:placetype":"locality"
},
  "geometry": {"coordinates":[16.64978,50.11827],"type":"Point"}
}