{
  "type": "Feature",
  "properties": {
    "iso:country":"PL",
    "name:ast_x_preferred":[
        "Budy \u0141a\u0144cuckie"
    ],
    "name:ceb_x_preferred":[
        "Budy \u0141a\u0144cuckie"
    ],
    "name:eng_x_preferred":[
        "Budy \u0141a\u0144cuckie"
    ],
    "name:fra_x_preferred":[
        "Budy \u0141a\u0144cuckie"
    ],
    "name:nan_x_preferred":[
        "Budy \u0141a\u0144cuckie"
    ],
    "name:nld_x_preferred":[
        "Budy \u0141a\u0144cuckie"
    ],
    "name:pol_x_preferred":[
        "Budy \u0141a\u0144cuckie"
    ],
    "name:ukr_x_preferred":[
        "\u0411\u0443\u0434\u0438 \u041b\u0430\u043d\u044c\u0446\u0443\u0442\u0441\u044c\u043a\u0456"
    ],
    "name:zho_min_nan_x_preferred":[
        "Budy \u0141a\u0144cuckie"
    ],
    "qs:a0":"Rzeczpospolita Polska",
    "qs:a1":"*Podkarpackie",
    "qs:a1r":"0",
    "qs:a2":"Lancucki",
    "qs:adm0":"Rzeczpospolita Polska",
    "qs:la_lc":"*",
    "qs:level":"locality",
    "qs:loc":"Budy \u0141a\u0144cuckie",
    "qs:loc_alt":"Budy Lancuckie",
    "qs:pop":0,
    "qs:type":"buffered point",
    "wd:wordcount":85,
    "wof:name":"Budy \u0141a\u0144cuckie",
    "wof:placetype":"locality"
},
  "geometry": {"coordinates":[22.398828,50.117375],"type":"Point"}
}