{
  "type": "Feature",
  "properties": {
    "gn:admin1_code":"73.0",
    "gn:admin2_code":"411.0",
    "gn:admin3_code":"41107.0",
    "gn:asciiname":"Paniewek",
    "gn:country_code":"PL",
    "gn:dem":92,
    "gn:feature_class":"P",
    "gn:feature_code":"PPL",
    "gn:name":"Paniewek",
    "gn:population":0,
    "gn:timezone":"Europe/Warsaw",
    "iso:country":"PL",
    "name:pol_x_preferred":[
        "Paniewek"
    ],
    "name:ukr_x_preferred":[
        "\u041f\u0430\u043d\u0435\u0432\u0435\u043a"
    ],
    "wof:name":"Paniewek",
    "wof:placetype":"locality"
},
  "geometry": {"coordinates":[18.74366,52.53967],"type":"Point"}
}