{
  "type": "Feature",
  "properties": {
    "gn:admin1_code":"84.0",
    "gn:admin2_code":"2610.0",
    "gn:admin3_code":"261004.0",
    "gn:asciiname":"Swierczek",
    "gn:country_code":"PL",
    "gn:dem":237,
    "gn:feature_class":"P",
    "gn:feature_code":"PPL",
    "gn:name":"\u015awierczek",
    "gn:population":0,
    "gn:timezone":"Europe/Warsaw",
    "iso:country":"PL",
    "name:und_x_variant":[
        "\u015awierczek"
    ],
    "wof:name":"Swierczek",
    "wof:placetype":"locality"
},
  "geometry": {"coordinates":[20.91324,51.15953],"type":"Point"}
}