{
  "type": "Feature",
  "properties": {
    "gn:admin1_code":"73.0",
    "gn:admin2_code":"404.0",
    "gn:admin3_code":"40406.0",
    "gn:asciiname":"Obory",
    "gn:country_code":"PL",
    "gn:dem":93,
    "gn:feature_class":"P",
    "gn:feature_code":"PPL",
    "gn:name":"Obory",
    "gn:population":0,
    "gn:timezone":"Europe/Warsaw",
    "iso:country":"PL",
    "name:ceb_x_preferred":[
        "Obory"
    ],
    "name:deu_x_preferred":[
        "Obory"
    ],
    "name:fra_x_preferred":[
        "Obory"
    ],
    "name:pol_x_preferred":[
        "Obory"
    ],
    "name:swe_x_preferred":[
        "Obory"
    ],
    "name:ukr_x_preferred":[
        "\u041e\u0431\u043e\u0440\u0438"
    ],
    "wof:name":"Obory",
    "wof:placetype":"locality"
},
  "geometry": {"coordinates":[18.61991,53.34452],"type":"Point"}
}