{
  "type": "Feature",
  "properties": {
    "gn:admin1_code":"86.0",
    "gn:admin2_code":"3019.0",
    "gn:admin3_code":"301904.0",
    "gn:asciiname":"Liszkowo",
    "gn:country_code":"PL",
    "gn:dem":103,
    "gn:feature_class":"P",
    "gn:feature_code":"PPL",
    "gn:name":"Liszkowo",
    "gn:population":0,
    "gn:timezone":"Europe/Warsaw",
    "iso:country":"PL",
    "name:ceb_x_preferred":[
        "Liszkowo"
    ],
    "name:fra_x_preferred":[
        "Liszkowo"
    ],
    "name:pol_x_preferred":[
        "Liszkowo"
    ],
    "name:ukr_x_preferred":[
        "\u041b\u0456\u0448\u043a\u043e\u0432\u043e"
    ],
    "name:und_x_variant":[
        "Witzleben, Kr. Wirsitz"
    ],
    "wof:name":"Liszkowo",
    "wof:placetype":"locality"
},
  "geometry": {"coordinates":[17.31952,53.22964],"type":"Point"}
}