{
  "type": "Feature",
  "properties": {
    "gn:admin1_code":"86.0",
    "gn:admin2_code":"3019.0",
    "gn:admin3_code":"301906.0",
    "gn:asciiname":"Krepsko",
    "gn:country_code":"PL",
    "gn:dem":73,
    "gn:feature_class":"P",
    "gn:feature_code":"PPL",
    "gn:name":"Kr\u0119psko",
    "gn:population":0,
    "gn:timezone":"Europe/Warsaw",
    "iso:country":"PL",
    "name:ceb_x_preferred":[
        "Kr\u0119psko"
    ],
    "name:deu_x_preferred":[
        "Kr\u0119psko"
    ],
    "name:fra_x_preferred":[
        "Kr\u0119psko"
    ],
    "name:pol_x_preferred":[
        "Kr\u0119psko"
    ],
    "name:ukr_x_preferred":[
        "\u041a\u0440\u0435\u043c\u043f\u0441\u044c\u043a\u043e"
    ],
    "wof:name":"Krepsko",
    "wof:placetype":"locality"
},
  "geometry": {"coordinates":[16.77549,53.26319],"type":"Point"}
}