{
  "type": "Feature",
  "properties": {
    "gn:admin1_code":"81.0",
    "gn:admin2_code":"2008.0",
    "gn:admin3_code":"200802.0",
    "gn:asciiname":"Lekobudy",
    "gn:country_code":"PL",
    "gn:dem":139,
    "gn:feature_class":"P",
    "gn:feature_code":"PPL",
    "gn:name":"\u0141\u0119kobudy",
    "gn:population":0,
    "gn:timezone":"Europe/Warsaw",
    "iso:country":"PL",
    "name:fra_x_preferred":[
        "\u0141\u0119kobudy"
    ],
    "name:lit_x_preferred":[
        "Lenkobudai"
    ],
    "name:pol_x_preferred":[
        "\u0141\u0119kobudy"
    ],
    "name:ukr_x_preferred":[
        "\u041b\u0435\u043d\u043a\u043e\u0431\u0443\u0434\u0438"
    ],
    "wof:name":"Lekobudy",
    "wof:placetype":"locality"
},
  "geometry": {"coordinates":[23.04548,53.34276],"type":"Point"}
}