{
  "type": "Feature",
  "properties": {
    "gn:admin1_code":"80.0",
    "gn:admin2_code":"1804.0",
    "gn:admin3_code":"180410.0",
    "gn:asciiname":"Czudowice",
    "gn:country_code":"PL",
    "gn:dem":234,
    "gn:feature_class":"P",
    "gn:feature_code":"PPL",
    "gn:name":"Czudowice",
    "gn:population":0,
    "gn:timezone":"Europe/Warsaw",
    "iso:country":"PL",
    "name:pol_x_preferred":[
        "Czudowice"
    ],
    "name:ukr_x_preferred":[
        "\u0427\u0443\u0434\u043e\u0432\u0438\u0447\u0456"
    ],
    "wof:name":"Czudowice",
    "wof:placetype":"locality"
},
  "geometry": {"coordinates":[22.52764,49.94106],"type":"Point"}
}