{
  "type": "Feature",
  "properties": {
    "gn:admin1_code":"77.0",
    "gn:admin2_code":"1214.0",
    "gn:admin3_code":"121405.0",
    "gn:asciiname":"Przezwody",
    "gn:country_code":"PL",
    "gn:dem":211,
    "gn:feature_class":"P",
    "gn:feature_code":"PPL",
    "gn:name":"Przezwody",
    "gn:population":0,
    "gn:timezone":"Europe/Warsaw",
    "iso:country":"PL",
    "name:pol_x_preferred":[
        "Przezwody"
    ],
    "name:ukr_x_preferred":[
        "\u041f\u0448\u0435\u0437\u0432\u043e\u0434\u0438"
    ],
    "wof:name":"Przezwody",
    "wof:placetype":"locality"
},
  "geometry": {"coordinates":[20.3561,50.19876],"type":"Point"}
}