{
  "type": "Feature",
  "properties": {
    "gn:admin1_code":"73.0",
    "gn:admin2_code":"461.0",
    "gn:admin3_code":"46101.0",
    "gn:asciiname":"Srodmiescie",
    "gn:country_code":"PL",
    "gn:dem":43,
    "gn:feature_class":"P",
    "gn:feature_code":"PPL",
    "gn:name":"\u015ar\u00f3dmie\u015bcie",
    "gn:population":0,
    "gn:timezone":"Europe/Warsaw",
    "iso:country":"PL",
    "wof:name":"Srodmiescie",
    "wof:placetype":"locality"
},
  "geometry": {"coordinates":[18.00861,53.12716],"type":"Point"}
}