{
  "type": "Feature",
  "properties": {
    "gn:admin1_code":"74.0",
    "gn:admin2_code":"1012.0",
    "gn:admin3_code":"101211.0",
    "gn:asciiname":"Zuzowy",
    "gn:country_code":"PL",
    "gn:dem":210,
    "gn:feature_class":"P",
    "gn:feature_code":"PPL",
    "gn:name":"Zuzowy",
    "gn:population":0,
    "gn:timezone":"Europe/Warsaw",
    "iso:country":"PL",
    "name:ceb_x_preferred":[
        "Zuzowy"
    ],
    "name:fra_x_preferred":[
        "Zuzowy"
    ],
    "name:pol_x_preferred":[
        "Zuzowy"
    ],
    "name:ukr_x_preferred":[
        "\u0417\u0443\u0437\u043e\u0432\u0438"
    ],
    "wof:name":"Zuzowy",
    "wof:placetype":"locality"
},
  "geometry": {"coordinates":[19.96611,51.12486],"type":"Point"}
}