{
  "type": "Feature",
  "properties": {
    "gn:admin1_code":"79.0",
    "gn:admin2_code":"1607.0",
    "gn:admin3_code":"160701.0",
    "gn:asciiname":"Radzow",
    "gn:country_code":"PL",
    "gn:dem":332,
    "gn:feature_class":"P",
    "gn:feature_code":"PPL",
    "gn:name":"Radzow",
    "gn:population":0,
    "gn:timezone":"Europe/Warsaw",
    "iso:country":"PL",
    "wof:name":"Radzow",
    "wof:placetype":"locality"
},
  "geometry": {"coordinates":[17.31667,50.33333],"type":"Point"}
}