{
  "type": "Feature",
  "properties": {
    "iso:country":"PL",
    "name:pol_x_preferred":[
        "Bodzan\u00f3w"
    ],
    "wof:name":"Bodzan\u00f3w",
    "wof:placetype":"locality"
},
  "geometry": {"coordinates":[19.9832739184064,52.490385134823],"type":"Point"}
}