{
  "type": "Feature",
  "properties": {
    "iso:country":"PL",
    "name:ceb_x_preferred":[
        "Bodzan\u00f3w"
    ],
    "name:deu_x_preferred":[
        "Bodzan\u00f3w"
    ],
    "name:fra_x_preferred":[
        "Bodzan\u00f3w"
    ],
    "name:nld_x_preferred":[
        "Bodzan\u00f3w"
    ],
    "name:pol_x_preferred":[
        "Bodzan\u00f3w"
    ],
    "name:ukr_x_preferred":[
        "\u0411\u043e\u0434\u0437\u0430\u043d\u0443\u0432"
    ],
    "wof:coterminous":[
        1125288959
    ],
    "wof:name":"Bodzan\u00f3w",
    "wof:placetype":"locality"
},
  "geometry": {"coordinates":[19.9832739184064,52.490385134823],"type":"Point"}
}