{
  "type": "Feature",
  "properties": {
    "gn:admin1_code":"86.0",
    "gn:admin2_code":"3025.0",
    "gn:admin3_code":"302504.0",
    "gn:asciiname":"Ruszkowo",
    "gn:country_code":"PL",
    "gn:dem":90,
    "gn:feature_class":"P",
    "gn:feature_code":"PPL",
    "gn:name":"Ruszkowo",
    "gn:population":0,
    "gn:timezone":"Europe/Warsaw",
    "iso:country":"PL",
    "name:ceb_x_preferred":[
        "Ruszkowo"
    ],
    "name:fra_x_preferred":[
        "Ruszkowo"
    ],
    "name:pol_x_preferred":[
        "Ruszkowo"
    ],
    "name:ukr_x_preferred":[
        "\u0420\u0443\u0448\u043a\u043e\u0432\u043e"
    ],
    "wof:name":"Ruszkowo",
    "wof:placetype":"locality"
},
  "geometry": {"coordinates":[17.33295,52.23762],"type":"Point"}
}