{
  "type": "Feature",
  "properties": {
    "gn:admin1_code":"87.0",
    "gn:admin2_code":"3216.0",
    "gn:admin3_code":"321606.0",
    "gn:asciiname":"Lekowo",
    "gn:country_code":"PL",
    "gn:dem":121,
    "gn:feature_class":"P",
    "gn:feature_code":"PPL",
    "gn:name":"Lekowo",
    "gn:population":0,
    "gn:timezone":"Europe/Warsaw",
    "iso:country":"PL",
    "name:deu_x_preferred":[
        "Lekowo"
    ],
    "name:pol_x_preferred":[
        "Lekowo"
    ],
    "name:ukr_x_preferred":[
        "\u041b\u0435\u043a\u043e\u0432\u043e"
    ],
    "name:vie_x_preferred":[
        "Lekowo"
    ],
    "wof:name":"Lekowo",
    "wof:placetype":"locality"
},
  "geometry": {"coordinates":[15.67941,53.81921],"type":"Point"}
}