{
  "type": "Feature",
  "properties": {
    "gn:admin1_code":"82.0",
    "gn:admin2_code":"2203.0",
    "gn:admin3_code":"220304.0",
    "gn:asciiname":"Stare Gronowo",
    "gn:country_code":"PL",
    "gn:dem":158,
    "gn:feature_class":"P",
    "gn:feature_code":"PPL",
    "gn:name":"Stare Gronowo",
    "gn:population":0,
    "gn:timezone":"Europe/Warsaw",
    "iso:country":"PL",
    "name:ceb_x_preferred":[
        "Stare Gronowo"
    ],
    "name:pol_x_preferred":[
        "Stare Gronowo"
    ],
    "name:ukr_x_preferred":[
        "\u0421\u0442\u0430\u0440\u0435 \u0490\u0440\u043e\u043d\u043e\u0432\u043e"
    ],
    "wof:name":"Stare Gronowo",
    "wof:placetype":"locality"
},
  "geometry": {"coordinates":[17.38293,53.53989],"type":"Point"}
}