{
  "type": "Feature",
  "properties": {
    "gn:admin1_code":"84.0",
    "gn:admin2_code":"2604.0",
    "gn:admin3_code":"260408.0",
    "gn:asciiname":"Przegrody",
    "gn:country_code":"PL",
    "gn:dem":251,
    "gn:feature_class":"P",
    "gn:feature_code":"PPL",
    "gn:name":"Przegrody",
    "gn:population":0,
    "gn:timezone":"Europe/Warsaw",
    "iso:country":"PL",
    "name:pol_x_preferred":[
        "Przegrody"
    ],
    "name:ukr_x_preferred":[
        "\u041f\u0448\u0435\u0491\u0440\u043e\u0434\u0438"
    ],
    "wof:name":"Przegrody",
    "wof:placetype":"locality"
},
  "geometry": {"coordinates":[20.22934,50.99507],"type":"Point"}
}