{
  "type": "Feature",
  "properties": {
    "gn:admin1_code":"76.0",
    "gn:admin2_code":"805.0",
    "gn:admin3_code":"80505.0",
    "gn:asciiname":"Rybocice",
    "gn:country_code":"PL",
    "gn:dem":28,
    "gn:feature_class":"P",
    "gn:feature_code":"PPL",
    "gn:name":"Rybocice",
    "gn:population":0,
    "gn:timezone":"Europe/Warsaw",
    "iso:country":"PL",
    "name:azb_x_preferred":[
        "\u0631\u0628\u0648\u0686\u06cc\u062a\u0633\u0647"
    ],
    "name:ceb_x_preferred":[
        "Rybocice"
    ],
    "name:deu_x_preferred":[
        "Rybocice"
    ],
    "name:fas_x_preferred":[
        "\u0631\u0628\u0648\u0686\u06cc\u062a\u0633\u0647"
    ],
    "name:fra_x_preferred":[
        "Rybocice"
    ],
    "name:pol_x_preferred":[
        "Rybocice"
    ],
    "name:ukr_x_preferred":[
        "\u0420\u0438\u0431\u043e\u0446\u0438\u0446\u0435"
    ],
    "wof:name":"Rybocice",
    "wof:placetype":"locality"
},
  "geometry": {"coordinates":[14.62403,52.28413],"type":"Point"}
}