{
  "type": "Feature",
  "properties": {
    "gn:admin1_code":"76.0",
    "gn:admin2_code":"805.0",
    "gn:admin3_code":"80505.0",
    "gn:asciiname":"Rybocice",
    "gn:country_code":"PL",
    "gn:dem":28,
    "gn:feature_class":"P",
    "gn:feature_code":"PPL",
    "gn:name":"Rybocice",
    "gn:population":0,
    "gn:timezone":"Europe/Warsaw",
    "iso:country":"PL",
    "wof:name":"Rybocice",
    "wof:placetype":"locality"
},
  "geometry": {"coordinates":[14.62403,52.28413],"type":"Point"}
}