{
  "type": "Feature",
  "properties": {
    "iso:country":"PL",
    "name:ast_x_preferred":[
        "B\u0142a\u017ckowa"
    ],
    "name:ceb_x_preferred":[
        "B\u0142aszkowa"
    ],
    "name:eng_x_preferred":[
        "B\u0142a\u017ckowa"
    ],
    "name:fra_x_preferred":[
        "B\u0142a\u017ckowa"
    ],
    "name:nld_x_preferred":[
        "B\u0142aszkowa"
    ],
    "name:pol_x_preferred":[
        "B\u0142a\u017ckowa"
    ],
    "name:ukr_x_preferred":[
        "\u0411\u043b\u0430\u0436\u043a\u043e\u0432\u0430"
    ],
    "name:unk_x_variant":[
        "B\u0142aszkowa"
    ],
    "qs:a0":"Rzeczpospolita Polska",
    "qs:a1":"*Podkarpackie",
    "qs:a1r":"0",
    "qs:a2":"Jasielski",
    "qs:adm0":"Rzeczpospolita Polska",
    "qs:la_lc":"*",
    "qs:level":"locality",
    "qs:loc":"B\u0142a\u017ckowa",
    "qs:loc_alt":"Blazkowa",
    "qs:pop":0,
    "qs:type":"buffered point",
    "wd:wordcount":104,
    "wof:name":"B\u0142a\u017ckowa",
    "wof:placetype":"locality"
},
  "geometry": {"coordinates":[21.361666,49.850361],"type":"Point"}
}