{
  "type": "Feature",
  "properties": {
    "gn:admin1_code":"83.0",
    "gn:admin2_code":"2417.0",
    "gn:admin3_code":"241711.0",
    "gn:asciiname":"Harensowie",
    "gn:country_code":"PL",
    "gn:dem":662,
    "gn:feature_class":"P",
    "gn:feature_code":"PPL",
    "gn:name":"Harensowie",
    "gn:population":0,
    "gn:timezone":"Europe/Warsaw",
    "iso:country":"PL",
    "wof:name":"Harensowie",
    "wof:placetype":"locality"
},
  "geometry": {"coordinates":[19.01667,49.46667],"type":"Point"}
}