{
  "type": "Feature",
  "properties": {
    "gn:admin1_code":"86.0",
    "gn:admin2_code":"3019.0",
    "gn:admin3_code":"301909.0",
    "gn:asciiname":"Mosciska",
    "gn:country_code":"PL",
    "gn:dem":107,
    "gn:feature_class":"P",
    "gn:feature_code":"PPL",
    "gn:name":"Mo\u015bciska",
    "gn:population":0,
    "gn:timezone":"Europe/Warsaw",
    "iso:country":"PL",
    "name:bul_x_preferred":[
        "\u041c\u043e\u0448\u0447\u0438\u0441\u043a\u0430"
    ],
    "name:ceb_x_preferred":[
        "Mo\u015bciska"
    ],
    "name:fra_x_preferred":[
        "Mo\u015bciska"
    ],
    "name:pol_x_preferred":[
        "Mo\u015bciska"
    ],
    "name:ukr_x_preferred":[
        "\u041c\u043e\u0441\u044c\u0446\u0438\u0441\u044c\u043a\u0430"
    ],
    "name:und_x_variant":[
        "Mosch\u00fctz"
    ],
    "wof:name":"Mosciska",
    "wof:placetype":"locality"
},
  "geometry": {"coordinates":[16.99816,53.17364],"type":"Point"}
}