{
  "type": "Feature",
  "properties": {
    "gn:admin1_code":"78.0",
    "gn:admin2_code":"1402.0",
    "gn:admin3_code":"140207.0",
    "gn:asciiname":"Kolaki Budzyno",
    "gn:country_code":"PL",
    "gn:dem":139,
    "gn:feature_class":"P",
    "gn:feature_code":"PPL",
    "gn:name":"Ko\u0142aki Budzyno",
    "gn:population":0,
    "gn:timezone":"Europe/Warsaw",
    "iso:country":"PL",
    "wof:name":"Kolaki Budzyno",
    "wof:placetype":"locality"
},
  "geometry": {"coordinates":[20.74221,52.95144000000001],"type":"Point"}
}