{
  "type": "Feature",
  "properties": {
    "gn:admin1_code":"72.0",
    "gn:admin2_code":"217.0",
    "gn:admin3_code":"21701.0",
    "gn:asciiname":"Opatowice",
    "gn:country_code":"PL",
    "gn:dem":143,
    "gn:feature_class":"P",
    "gn:feature_code":"PPL",
    "gn:name":"Opatowice",
    "gn:population":0,
    "gn:timezone":"Europe/Warsaw",
    "iso:country":"PL",
    "wof:name":"Opatowice",
    "wof:placetype":"locality"
},
  "geometry": {"coordinates":[17.01308,50.87416],"type":"Point"}
}