{
  "type": "Feature",
  "properties": {
    "gn:gn_country":"PL",
    "gn:gn_fcode":"PPLA3",
    "gn:gn_pop":774,
    "gn:population":774,
    "iso:country":"PL",
    "name:azb_x_preferred":[
        "\u067e\u0698\u0648\u0648"
    ],
    "name:ceb_x_preferred":[
        "Perz\u00f3w"
    ],
    "name:deu_x_preferred":[
        "Perz\u00f3w"
    ],
    "name:fas_x_preferred":[
        "\u067e\u0698\u0648\u0648"
    ],
    "name:nld_x_preferred":[
        "Perz\u00f3w"
    ],
    "name:pol_x_preferred":[
        "Perz\u00f3w"
    ],
    "name:swe_x_preferred":[
        "Perz\u00f3w"
    ],
    "name:ukr_x_preferred":[
        "\u041f\u0435\u0436\u0443\u0432"
    ],
    "qs_pg:aaroncc":"PL",
    "qs_pg:gn_country":"PL",
    "qs_pg:gn_fcode":"PPLA3",
    "qs_pg:gn_pop":774,
    "qs_pg:name":"Perz\u00f3w",
    "qs_pg:name_adm0":"Polska",
    "qs_pg:name_adm1":"Wielkopolskie",
    "qs_pg:photos_9r":0,
    "qs_pg:photos_sr":0,
    "qs_pg:pop_sr":2,
    "qs_pg:qs_pg_placetype":"localadmin",
    "qs_pg:qs_pg_placetype_gp":"LocalAdmin",
    "qs_pg:woe_adm0":23424923,
    "woe:adm0_id":23424923,
    "woe:name_adm0":"Polska",
    "woe:name_adm1":"Wielkopolskie",
    "woe:placetype":"LocalAdmin",
    "wof:name":"Perz\u00f3w",
    "wof:placetype":"localadmin",
    "wof:population":774
},
  "geometry": {"coordinates":[17.8097,51.27625],"type":"Point"}
}