{
  "type": "Feature",
  "properties": {
    "gn:gn_country":"PL",
    "iso:country":"PL",
    "name:azb_x_preferred":[
        "\u062f\u0627\u0631\u0648\u0648\u0648\u0648"
    ],
    "name:bel_x_preferred":[
        "\u0414\u0430\u0440\u043b\u043e\u0432\u0430"
    ],
    "name:ces_x_preferred":[
        "Dar\u0142owo"
    ],
    "name:csb_x_preferred":[
        "D\u00ebr\u0142ow\u00f2"
    ],
    "name:dan_x_preferred":[
        "Dar\u0142owo"
    ],
    "name:deu_x_preferred":[
        "Dar\u0142owo"
    ],
    "name:dsb_x_preferred":[
        "Dar\u0142owo"
    ],
    "name:epo_x_preferred":[
        "Dar\u0142owo"
    ],
    "name:eus_x_preferred":[
        "Dar\u0142owo"
    ],
    "name:fas_x_preferred":[
        "\u062f\u0627\u0631\u0648\u0648\u0648\u0648"
    ],
    "name:fin_x_preferred":[
        "Dar\u0142owo"
    ],
    "name:fra_x_preferred":[
        "Dar\u0142owo"
    ],
    "name:hun_x_preferred":[
        "Dar\u0142owo"
    ],
    "name:ita_x_preferred":[
        "Dar\u0142owo"
    ],
    "name:jav_x_preferred":[
        "Dar\u0142owo"
    ],
    "name:lav_x_preferred":[
        "Darlovo"
    ],
    "name:msa_x_preferred":[
        "Dar\u0142owo"
    ],
    "name:nds_x_preferred":[
        "R\u00fcgenwoold"
    ],
    "name:nld_x_preferred":[
        "Dar\u0142owo"
    ],
    "name:nor_x_preferred":[
        "Dar\u0142owo"
    ],
    "name:pol_x_preferred":[
        "Dar\u0142owo"
    ],
    "name:por_x_preferred":[
        "Dar\u0142owo"
    ],
    "name:ron_x_preferred":[
        "Dar\u0142owo"
    ],
    "name:rus_x_preferred":[
        "\u0414\u0430\u0440\u043b\u043e\u0432\u043e"
    ],
    "name:slk_x_preferred":[
        "Dar\u0142owo"
    ],
    "name:spa_x_preferred":[
        "Dar\u0142owo"
    ],
    "name:srp_x_preferred":[
        "\u0414\u0430\u0440\u043b\u043e\u0432\u043e"
    ],
    "name:swe_x_preferred":[
        "Dar\u0142owo"
    ],
    "name:ukr_x_preferred":[
        "\u0414\u0430\u0440\u043b\u043e\u0432\u043e"
    ],
    "name:vie_x_preferred":[
        "Dar\u0142owo"
    ],
    "name:war_x_preferred":[
        "Dar\u0142owo"
    ],
    "name:zho_x_preferred":[
        "\u9054\u723e\u6c83\u6c83"
    ],
    "qs_pg:aaroncc":"PL",
    "qs_pg:gn_country":"PL",
    "qs_pg:name":"Dar\u0142owo",
    "qs_pg:name_adm0":"Polska",
    "qs_pg:name_adm1":"Zachodniopomorskie",
    "qs_pg:photos":1,
    "qs_pg:photos_1k":1,
    "qs_pg:photos_9k":1,
    "qs_pg:photos_9r":4,
    "qs_pg:photos_all":279,
    "qs_pg:photos_sr":1,
    "qs_pg:pop_sr":0,
    "qs_pg:qs_pg_placetype":"localadmin",
    "qs_pg:qs_pg_placetype_gp":"LocalAdmin",
    "qs_pg:woe_adm0":23424923,
    "woe:adm0_id":23424923,
    "woe:name_adm0":"Polska",
    "woe:name_adm1":"Zachodniopomorskie",
    "woe:placetype":"LocalAdmin",
    "wof:name":"Dar\u0142owo",
    "wof:placetype":"localadmin"
},
  "geometry": {"coordinates":[16.375808,54.442295],"type":"Point"}
}