{
  "type": "Feature",
  "properties": {
    "gn:admin1_code":"76.0",
    "gn:admin2_code":"810.0",
    "gn:admin3_code":"81004.0",
    "gn:asciiname":"Borowe",
    "gn:country_code":"PL",
    "gn:dem":139,
    "gn:feature_class":"P",
    "gn:feature_code":"PPL",
    "gn:name":"Borowe",
    "gn:population":0,
    "gn:timezone":"Europe/Warsaw",
    "iso:country":"PL",
    "name:ceb_x_preferred":[
        "Borowe"
    ],
    "name:fra_x_preferred":[
        "Borowe"
    ],
    "name:nld_x_preferred":[
        "Borowe"
    ],
    "name:pol_x_preferred":[
        "Borowe"
    ],
    "name:ukr_x_preferred":[
        "\u0411\u043e\u0440\u043e\u0432\u0435"
    ],
    "wof:name":"Borowe",
    "wof:placetype":"locality"
},
  "geometry": {"coordinates":[15.12663,51.48384],"type":"Point"}
}