{
  "type": "Feature",
  "properties": {
    "gn:admin1_code":"79.0",
    "gn:admin2_code":"1605.0",
    "gn:admin3_code":"160503.0",
    "gn:asciiname":"Kopalina",
    "gn:country_code":"PL",
    "gn:dem":185,
    "gn:feature_class":"P",
    "gn:feature_code":"PPL",
    "gn:name":"Kopalina",
    "gn:population":0,
    "gn:timezone":"Europe/Warsaw",
    "iso:country":"PL",
    "name:pol_x_preferred":[
        "Kopalina"
    ],
    "name:ukr_x_preferred":[
        "\u041a\u043e\u043f\u0430\u043b\u0456\u043d\u0430"
    ],
    "wof:name":"Kopalina",
    "wof:placetype":"locality"
},
  "geometry": {"coordinates":[17.82562,50.488],"type":"Point"}
}