{
  "type": "Feature",
  "properties": {
    "gn:admin1_code":"72.0",
    "gn:admin2_code":"225.0",
    "gn:admin3_code":"22505.0",
    "gn:asciiname":"Skrzydlice",
    "gn:country_code":"PL",
    "gn:dem":244,
    "gn:feature_class":"P",
    "gn:feature_code":"PPL",
    "gn:name":"Skrzydlice",
    "gn:population":0,
    "gn:timezone":"Europe/Warsaw",
    "iso:country":"PL",
    "name:pol_x_preferred":[
        "Skrzydlice"
    ],
    "name:ukr_x_preferred":[
        "\u0421\u043a\u0448\u0438\u0434\u043b\u0456\u0446\u0435"
    ],
    "wof:name":"Skrzydlice",
    "wof:placetype":"locality"
},
  "geometry": {"coordinates":[15.0638,51.03913],"type":"Point"}
}