{
  "type": "Feature",
  "properties": {
    "gn:admin1_code":"77.0",
    "gn:admin2_code":"1211.0",
    "gn:admin3_code":"121110.0",
    "gn:asciiname":"Klodne",
    "gn:country_code":"PL",
    "gn:dem":469,
    "gn:feature_class":"P",
    "gn:feature_code":"PPL",
    "gn:name":"K\u0142odne",
    "gn:population":0,
    "gn:timezone":"Europe/Warsaw",
    "iso:country":"PL",
    "wof:name":"Klodne",
    "wof:placetype":"locality"
},
  "geometry": {"coordinates":[20.43333,49.46667],"type":"Point"}
}