{
  "type": "Feature",
  "properties": {
    "gn:admin1_code":"85.0",
    "gn:admin2_code":"2816.0",
    "gn:admin3_code":"281601.0",
    "gn:asciiname":"Myszki",
    "gn:country_code":"PL",
    "gn:dem":145,
    "gn:feature_class":"P",
    "gn:feature_code":"PPL",
    "gn:name":"Myszki",
    "gn:population":0,
    "gn:timezone":"Europe/Warsaw",
    "iso:country":"PL",
    "name:ceb_x_preferred":[
        "Myszki"
    ],
    "name:deu_x_preferred":[
        "Myszki"
    ],
    "name:fra_x_preferred":[
        "Myszki"
    ],
    "name:pol_x_preferred":[
        "Myszki"
    ],
    "name:ukr_x_preferred":[
        "\u041c\u0438\u0448\u043a\u0456"
    ],
    "name:und_x_variant":[
        "Mysken",
        "Misken",
        "Mysken Kreis Johannisburg"
    ],
    "wof:name":"Myszki",
    "wof:placetype":"locality"
},
  "geometry": {"coordinates":[22.15619,53.66217],"type":"Point"}
}