{
  "type": "Feature",
  "properties": {
    "gn:admin1_code":"87.0",
    "gn:admin2_code":"3213.0",
    "gn:admin3_code":"321304.0",
    "gn:asciiname":"Borkowo",
    "gn:country_code":"PL",
    "gn:dem":51,
    "gn:feature_class":"P",
    "gn:feature_code":"PPL",
    "gn:name":"Borkowo",
    "gn:population":0,
    "gn:timezone":"Europe/Warsaw",
    "iso:country":"PL",
    "name:ceb_x_preferred":[
        "Borkowo"
    ],
    "name:deu_x_preferred":[
        "Borkowo"
    ],
    "name:pol_x_preferred":[
        "Borkowo"
    ],
    "name:ukr_x_preferred":[
        "\u0411\u043e\u0440\u043a\u043e\u0432\u043e"
    ],
    "name:vie_x_preferred":[
        "Borkowo"
    ],
    "wof:name":"Borkowo",
    "wof:placetype":"locality"
},
  "geometry": {"coordinates":[16.58916,54.23141999999999],"type":"Point"}
}