{
  "type": "Feature",
  "properties": {
    "gn:admin1_code":"84.0",
    "gn:admin2_code":"2601.0",
    "gn:admin3_code":"260104.0",
    "gn:asciiname":"Kolko Zabieckie",
    "gn:country_code":"PL",
    "gn:dem":161,
    "gn:feature_class":"P",
    "gn:feature_code":"PPL",
    "gn:name":"K\u00f3\u0142ko \u017babieckie",
    "gn:population":0,
    "gn:timezone":"Europe/Warsaw",
    "iso:country":"PL",
    "wof:name":"Kolko Zabieckie",
    "wof:placetype":"locality"
},
  "geometry": {"coordinates":[21.09263,50.34464000000001],"type":"Point"}
}