{
  "type": "Feature",
  "properties": {
    "gn:admin1_code":"84.0",
    "gn:admin2_code":"2601.0",
    "gn:admin3_code":"260104.0",
    "gn:asciiname":"Kolko Zabieckie",
    "gn:country_code":"PL",
    "gn:dem":161,
    "gn:feature_class":"P",
    "gn:feature_code":"PPL",
    "gn:name":"K\u00f3\u0142ko \u017babieckie",
    "gn:population":0,
    "gn:timezone":"Europe/Warsaw",
    "iso:country":"PL",
    "name:azb_x_preferred":[
        "\u06a9\u0648\u0648\u06a9\u0648 \u0698\u0627\u0628\u06cc\u062a\u0633\u06a9\u06cc\u0647"
    ],
    "name:ceb_x_preferred":[
        "K\u00f3\u0142ko \u017babieckie"
    ],
    "name:fas_x_preferred":[
        "\u06a9\u0648\u0648\u06a9\u0648 \u0698\u0627\u0628\u06cc\u062a\u0633\u06a9\u06cc\u0647"
    ],
    "name:nld_x_preferred":[
        "K\u00f3\u0142ko \u017babieckie"
    ],
    "name:pol_x_preferred":[
        "K\u00f3\u0142ko \u017babieckie"
    ],
    "name:ukr_x_preferred":[
        "\u041a\u0443\u043b\u043a\u043e-\u0416\u0430\u0431\u0435\u0446\u044c\u043a\u0435"
    ],
    "wof:name":"Kolko Zabieckie",
    "wof:placetype":"locality"
},
  "geometry": {"coordinates":[21.09263,50.34464000000001],"type":"Point"}
}