{
  "type": "Feature",
  "properties": {
    "gn:admin1_code":"72.0",
    "gn:admin2_code":"219.0",
    "gn:admin3_code":"21908.0",
    "gn:asciiname":"Przylegow",
    "gn:country_code":"PL",
    "gn:dem":199,
    "gn:feature_class":"P",
    "gn:feature_code":"PPL",
    "gn:name":"Przy\u0142\u0119g\u00f3w",
    "gn:population":0,
    "gn:timezone":"Europe/Warsaw",
    "iso:country":"PL",
    "name:pol_x_preferred":[
        "Przy\u0142\u0119g\u00f3w"
    ],
    "name:spa_x_preferred":[
        "Przy\u0142\u0119g\u00f3w"
    ],
    "name:ukr_x_preferred":[
        "\u041f\u0448\u0438\u043b\u0435\u043d\u0491\u0443\u0432"
    ],
    "name:und_x_variant":[
        "Przy\u0142\u0119g\u00f3w"
    ],
    "wof:name":"Przylegow",
    "wof:placetype":"locality"
},
  "geometry": {"coordinates":[16.4455,50.95783],"type":"Point"}
}