{
  "type": "Feature",
  "properties": {
    "gn:admin1_code":"78.0",
    "gn:admin2_code":"1426.0",
    "gn:admin3_code":"142608.0",
    "gn:asciiname":"Purzec",
    "gn:cc2":"PL",
    "gn:country_code":"PL",
    "gn:dem":140,
    "gn:feature_class":"P",
    "gn:feature_code":"PPL",
    "gn:name":"Purzec",
    "gn:population":0,
    "gn:timezone":"Europe/Warsaw",
    "iso:country":"PL",
    "name:ceb_x_preferred":[
        "Purzec"
    ],
    "name:fra_x_preferred":[
        "Purzec"
    ],
    "name:nld_x_preferred":[
        "Purzec"
    ],
    "name:pol_x_preferred":[
        "Purzec"
    ],
    "name:szl_x_preferred":[
        "Purzyc"
    ],
    "name:ukr_x_preferred":[
        "\u041f\u0443\u0436\u0435\u0446\u044c"
    ],
    "name:und_x_variant":[
        "Purzyce"
    ],
    "wof:name":"Purzec",
    "wof:placetype":"locality"
},
  "geometry": {"coordinates":[22.28577,52.21507],"type":"Point"}
}