{
  "type": "Feature",
  "properties": {
    "gn:admin1_code":"80.0",
    "gn:admin2_code":"1804.0",
    "gn:admin3_code":"180407.0",
    "gn:asciiname":"Rozborz Dlugi",
    "gn:country_code":"PL",
    "gn:dem":224,
    "gn:feature_class":"P",
    "gn:feature_code":"PPL",
    "gn:name":"Rozb\u00f3rz D\u0142ugi",
    "gn:population":0,
    "gn:timezone":"Europe/Warsaw",
    "iso:country":"PL",
    "wof:name":"Rozborz Dlugi",
    "wof:placetype":"locality"
},
  "geometry": {"coordinates":[22.49931,49.93354],"type":"Point"}
}