{
  "type": "Feature",
  "properties": {
    "gn:admin1_code":"73.0",
    "gn:admin2_code":"407.0",
    "gn:admin3_code":"40706.0",
    "gn:asciiname":"Kolonia Chelmce",
    "gn:cc2":"PL",
    "gn:country_code":"PL",
    "gn:dem":93,
    "gn:feature_class":"P",
    "gn:feature_code":"PPL",
    "gn:name":"Kolonia Che\u0142mce",
    "gn:population":0,
    "gn:timezone":"Europe/Warsaw",
    "iso:country":"PL",
    "name:und_x_variant":[
        "Che\u0142mce Kolonia",
        "Kolonia Che\u0142mce"
    ],
    "wof:name":"Kolonia Chelmce",
    "wof:placetype":"locality"
},
  "geometry": {"coordinates":[18.46667,52.61666999999999],"type":"Point"}
}