{
  "type": "Feature",
  "properties": {
    "gn:admin1_code":"86.0",
    "gn:admin2_code":"3007.0",
    "gn:admin3_code":"300702.0",
    "gn:asciiname":"Wrzaca",
    "gn:country_code":"PL",
    "gn:dem":129,
    "gn:feature_class":"P",
    "gn:feature_code":"PPL",
    "gn:name":"Wrz\u0105ca",
    "gn:population":0,
    "gn:timezone":"Europe/Warsaw",
    "iso:country":"PL",
    "wof:name":"Wrzaca",
    "wof:placetype":"locality"
},
  "geometry": {"coordinates":[18.25504,51.61442],"type":"Point"}
}