{
  "type": "Feature",
  "properties": {
    "gn:admin1_code":"81.0",
    "gn:admin2_code":"2013.0",
    "gn:admin3_code":"201307.0",
    "gn:asciiname":"Koboski",
    "gn:country_code":"PL",
    "gn:dem":135,
    "gn:feature_class":"P",
    "gn:feature_code":"PPL",
    "gn:name":"Koboski",
    "gn:population":0,
    "gn:timezone":"Europe/Warsaw",
    "iso:country":"PL",
    "name:lit_x_preferred":[
        "Koboskai"
    ],
    "name:pol_x_preferred":[
        "Koboski"
    ],
    "name:ukr_x_preferred":[
        "\u041a\u043e\u0431\u043e\u0441\u043a\u0456"
    ],
    "name:und_x_variant":[
        "Piekuty Koboski"
    ],
    "wof:name":"Koboski",
    "wof:placetype":"locality"
},
  "geometry": {"coordinates":[22.72696,52.86077],"type":"Point"}
}