{
  "type": "Feature",
  "properties": {
    "gn:admin1_code":"78.0",
    "gn:admin2_code":"1419.0",
    "gn:admin3_code":"141906.0",
    "gn:asciiname":"Paszniki",
    "gn:country_code":"PL",
    "gn:dem":111,
    "gn:feature_class":"P",
    "gn:feature_code":"PPL",
    "gn:name":"Paszniki",
    "gn:population":0,
    "gn:timezone":"Europe/Warsaw",
    "iso:country":"PL",
    "name:und_x_variant":[
        "Kolonia Kamie\u0144",
        "Paszniki"
    ],
    "wof:name":"Paszniki",
    "wof:placetype":"locality"
},
  "geometry": {"coordinates":[19.72614,52.33883],"type":"Point"}
}