{
  "type": "Feature",
  "properties": {
    "gn:admin1_code":"86.0",
    "gn:admin2_code":"3017.0",
    "gn:admin3_code":"301704.0",
    "gn:asciiname":"Karski",
    "gn:country_code":"PL",
    "gn:dem":130,
    "gn:feature_class":"P",
    "gn:feature_code":"PPL",
    "gn:name":"Karski",
    "gn:population":0,
    "gn:timezone":"Europe/Warsaw",
    "iso:country":"PL",
    "name:pol_x_preferred":[
        "Karski"
    ],
    "name:ukr_x_preferred":[
        "\u041a\u0430\u0440\u0441\u043a\u0456"
    ],
    "name:und_x_variant":[
        "Folwark Karski"
    ],
    "wof:name":"Karski",
    "wof:placetype":"locality"
},
  "geometry": {"coordinates":[17.8561,51.67584],"type":"Point"}
}