{
  "type": "Feature",
  "properties": {
    "gn:country":"PL",
    "gn:fcode":"PPL",
    "gn:population":2914,
    "iso:country":"PL",
    "name:ast_x_preferred":[
        "Ryjewo"
    ],
    "name:azb_x_preferred":[
        "\u0631\u06cc\u0648\u0648"
    ],
    "name:deu_x_preferred":[
        "Ryjewo"
    ],
    "name:eng_x_preferred":[
        "Ryjewo"
    ],
    "name:fas_x_preferred":[
        "\u0631\u06cc\u0648\u0648"
    ],
    "name:fra_x_preferred":[
        "Ryjewo"
    ],
    "name:nld_x_preferred":[
        "Ryjewo"
    ],
    "name:pol_x_preferred":[
        "Ryjewo"
    ],
    "name:ukr_x_preferred":[
        "\u0420\u0438\u0454\u0432\u043e"
    ],
    "name:und_x_variant":[
        "Rehhof"
    ],
    "qs_pg:aaroncc":"PL",
    "qs_pg:gn_country":"PL",
    "qs_pg:gn_fcode":"PPL",
    "qs_pg:gn_pop":2914,
    "qs_pg:name":"Ryjewo",
    "qs_pg:name_adm0":"Polska",
    "qs_pg:name_adm1":"Pomorskie",
    "qs_pg:photos":105,
    "qs_pg:photos_1k":21,
    "qs_pg:photos_9k":1,
    "qs_pg:photos_9r":3,
    "qs_pg:photos_all":105,
    "qs_pg:photos_sr":3,
    "qs_pg:pop_sr":4,
    "qs_pg:qs_pg_placetype":"locality",
    "qs_pg:qs_pg_placetype_gp":"Town",
    "qs_pg:woe_adm0":23424923,
    "woe:adm0_id":23424923,
    "woe:name_adm0":"Polska",
    "woe:name_adm1":"Pomorskie",
    "woe:placetype":"Town",
    "wof:coterminous":[
        1477752523
    ],
    "wof:name":"Ryjewo",
    "wof:placetype":"locality",
    "wof:population":2914
},
  "geometry": {"coordinates":[18.96077,53.84463],"type":"Point"}
}