{
  "type": "Feature",
  "properties": {
    "gn:admin1_code":"86.0",
    "gn:admin2_code":"3010.0",
    "gn:admin3_code":"301011.0",
    "gn:asciiname":"Lisiec Nowy",
    "gn:country_code":"PL",
    "gn:dem":97,
    "gn:feature_class":"P",
    "gn:feature_code":"PPL",
    "gn:name":"Lisiec Nowy",
    "gn:population":0,
    "gn:timezone":"Europe/Warsaw",
    "iso:country":"PL",
    "name:pol_x_preferred":[
        "Lisiec Nowy"
    ],
    "name:ukr_x_preferred":[
        "\u041b\u0456\u0441\u0435\u0446\u044c-\u041d\u043e\u0432\u0438\u0439"
    ],
    "wof:name":"Lisiec Nowy",
    "wof:placetype":"locality"
},
  "geometry": {"coordinates":[18.17953,52.1059],"type":"Point"}
}