{
  "type": "Feature",
  "properties": {
    "gn:admin1_code":"72.0",
    "gn:admin2_code":"212.0",
    "gn:admin3_code":"21202.0",
    "gn:asciiname":"Popielowek",
    "gn:country_code":"PL",
    "gn:dem":419,
    "gn:feature_class":"P",
    "gn:feature_code":"PPL",
    "gn:name":"Popiel\u00f3wek",
    "gn:population":0,
    "gn:timezone":"Europe/Warsaw",
    "iso:country":"PL",
    "name:und_x_variant":[
        "Popiel\u00f3wek"
    ],
    "wof:name":"Popielowek",
    "wof:placetype":"locality"
},
  "geometry": {"coordinates":[15.52687,50.98425],"type":"Point"}
}