{
  "type": "Feature",
  "properties": {
    "gn:admin1_code":"74.0",
    "gn:admin2_code":"1015.0",
    "gn:admin3_code":"101501.0",
    "gn:asciiname":"Wola Szydlowiecka",
    "gn:country_code":"PL",
    "gn:dem":97,
    "gn:feature_class":"P",
    "gn:feature_code":"PPL",
    "gn:name":"Wola Szyd\u0142owiecka",
    "gn:population":0,
    "gn:timezone":"Europe/Warsaw",
    "iso:country":"PL",
    "wof:name":"Wola Szydlowiecka",
    "wof:placetype":"locality"
},
  "geometry": {"coordinates":[20.23956,52.07898],"type":"Point"}
}