{
  "type": "Feature",
  "properties": {
    "gn:admin1_code":"74.0",
    "gn:admin2_code":"1015.0",
    "gn:admin3_code":"101501.0",
    "gn:asciiname":"Wola Szydlowiecka",
    "gn:country_code":"PL",
    "gn:dem":97,
    "gn:feature_class":"P",
    "gn:feature_code":"PPL",
    "gn:name":"Wola Szyd\u0142owiecka",
    "gn:population":0,
    "gn:timezone":"Europe/Warsaw",
    "iso:country":"PL",
    "name:pol_x_preferred":[
        "Wola Szyd\u0142owiecka"
    ],
    "name:ukr_x_preferred":[
        "\u0412\u043e\u043b\u044f-\u0428\u0438\u0434\u043b\u043e\u0432\u0435\u0446\u044c\u043a\u0430"
    ],
    "wof:name":"Wola Szydlowiecka",
    "wof:placetype":"locality"
},
  "geometry": {"coordinates":[20.23956,52.07898],"type":"Point"}
}