{
  "type": "Feature",
  "properties": {
    "gn:admin1_code":"86.0",
    "gn:admin2_code":"3010.0",
    "gn:admin3_code":"301013.0",
    "gn:asciiname":"Galczyce",
    "gn:country_code":"PL",
    "gn:dem":95,
    "gn:feature_class":"P",
    "gn:feature_code":"PPL",
    "gn:name":"Galczyce",
    "gn:population":0,
    "gn:timezone":"Europe/Warsaw",
    "iso:country":"PL",
    "name:pol_x_preferred":[
        "Galczyce"
    ],
    "name:ukr_x_preferred":[
        "\u0490\u0430\u043b\u044c\u0447\u0438\u0446\u0435"
    ],
    "wof:name":"Galczyce",
    "wof:placetype":"locality"
},
  "geometry": {"coordinates":[18.54604,52.47039],"type":"Point"}
}