{
  "type": "Feature",
  "properties": {
    "gn:admin1_code":"86.0",
    "gn:admin2_code":"3019.0",
    "gn:admin3_code":"301905.0",
    "gn:asciiname":"Antoniny",
    "gn:country_code":"PL",
    "gn:dem":46,
    "gn:feature_class":"P",
    "gn:feature_code":"PPL",
    "gn:name":"Antoniny",
    "gn:population":0,
    "gn:timezone":"Europe/Warsaw",
    "iso:country":"PL",
    "name:pol_x_preferred":[
        "Antoniny"
    ],
    "name:rus_x_preferred":[
        "\u0410\u043d\u0442\u043e\u043d\u0438\u043d\u044b"
    ],
    "wof:name":"Antoniny",
    "wof:placetype":"locality"
},
  "geometry": {"coordinates":[17.06667,53.06667],"type":"Point"}
}