{
  "type": "Feature",
  "properties": {
    "gn:admin1_code":"80.0",
    "gn:admin2_code":"1801.0",
    "gn:admin3_code":"180108.0",
    "gn:asciiname":"Krzywe",
    "gn:country_code":"PL",
    "gn:dem":463,
    "gn:feature_class":"P",
    "gn:feature_code":"PPL",
    "gn:name":"Krzywe",
    "gn:population":0,
    "gn:timezone":"Europe/Warsaw",
    "iso:country":"PL",
    "name:deu_x_preferred":[
        "Krzywe"
    ],
    "name:fra_x_preferred":[
        "Krzywe"
    ],
    "name:ind_x_preferred":[
        "Krzywe"
    ],
    "name:pol_x_preferred":[
        "Krzywe"
    ],
    "name:ukr_x_preferred":[
        "\u041a\u0448\u0438\u0432\u0435"
    ],
    "wof:name":"Krzywe",
    "wof:placetype":"locality"
},
  "geometry": {"coordinates":[22.49254,49.61145],"type":"Point"}
}