{
  "type": "Feature",
  "properties": {
    "gn:admin1_code":"80.0",
    "gn:admin2_code":"1801.0",
    "gn:admin3_code":"180108.0",
    "gn:asciiname":"Lobozew",
    "gn:country_code":"PL",
    "gn:dem":439,
    "gn:feature_class":"P",
    "gn:feature_code":"PPL",
    "gn:name":"\u0141obozew",
    "gn:population":0,
    "gn:timezone":"Europe/Warsaw",
    "iso:country":"PL",
    "wof:name":"Lobozew",
    "wof:placetype":"locality"
},
  "geometry": {"coordinates":[22.5079,49.40517],"type":"Point"}
}