{
  "type": "Feature",
  "properties": {
    "gn:gn_country":"PL",
    "gn:gn_fcode":"PPL",
    "gn:gn_pop":471,
    "gn:population":471,
    "iso:country":"PL",
    "name:ast_x_preferred":[
        "Nowy Targ"
    ],
    "name:ceb_x_preferred":[
        "Nowy Targ"
    ],
    "name:deu_x_preferred":[
        "Nowy Targ"
    ],
    "name:eng_x_preferred":[
        "Nowy Targ"
    ],
    "name:fra_x_preferred":[
        "Nowy Targ"
    ],
    "name:pol_x_preferred":[
        "Nowy Targ"
    ],
    "name:ukr_x_preferred":[
        "\u041d\u043e\u0432\u0438\u0439 \u0422\u0430\u0440\u0491"
    ],
    "name:unk_x_variant":[
        "Neumark"
    ],
    "qs_pg:aaroncc":"PL",
    "qs_pg:gn_country":"PL",
    "qs_pg:gn_fcode":"PPL",
    "qs_pg:gn_pop":471,
    "qs_pg:name":"Nowy Targ",
    "qs_pg:name_adm0":"Polska",
    "qs_pg:name_adm1":"Pomorskie",
    "qs_pg:photos_9k":1,
    "qs_pg:photos_9r":1,
    "qs_pg:photos_all":3,
    "qs_pg:photos_sr":0,
    "qs_pg:pop_sr":2,
    "qs_pg:qs_pg_placetype":"locality",
    "qs_pg:qs_pg_placetype_gp":"Town",
    "qs_pg:woe_adm0":23424923,
    "woe:adm0_id":23424923,
    "woe:name_adm0":"Polska",
    "woe:name_adm1":"Pomorskie",
    "woe:placetype":"Town",
    "wof:name":"Nowy Targ",
    "wof:placetype":"locality",
    "wof:population":471
},
  "geometry": {"coordinates":[19.1853,53.89822],"type":"Point"}
}