{
  "type": "Feature",
  "properties": {
    "gn:admin1_code":"74.0",
    "gn:admin2_code":"1014.0",
    "gn:admin3_code":"101403.0",
    "gn:asciiname":"Bugaj",
    "gn:country_code":"PL",
    "gn:dem":192,
    "gn:feature_class":"P",
    "gn:feature_code":"PPL",
    "gn:name":"Bugaj",
    "gn:population":0,
    "gn:timezone":"Europe/Warsaw",
    "iso:country":"PL",
    "wof:name":"Bugaj",
    "wof:placetype":"locality"
},
  "geometry": {"coordinates":[18.48415,51.54678],"type":"Point"}
}