{
  "type": "Feature",
  "properties": {
    "gn:admin1_code":"74.0",
    "gn:admin2_code":"1014.0",
    "gn:admin3_code":"101403.0",
    "gn:asciiname":"Bugaj",
    "gn:country_code":"PL",
    "gn:dem":192,
    "gn:feature_class":"P",
    "gn:feature_code":"PPL",
    "gn:name":"Bugaj",
    "gn:population":0,
    "gn:timezone":"Europe/Warsaw",
    "iso:country":"PL",
    "name:ceb_x_preferred":[
        "Bugaj"
    ],
    "name:deu_x_preferred":[
        "Bugaj"
    ],
    "name:fra_x_preferred":[
        "Bugaj"
    ],
    "name:heb_x_preferred":[
        "\u05d1\u05d5\u05d2\u05d0\u05d9"
    ],
    "name:pol_x_preferred":[
        "Bugaj"
    ],
    "name:ukr_x_preferred":[
        "\u0411\u0443\u0491\u0430\u0439"
    ],
    "wof:name":"Bugaj",
    "wof:placetype":"locality"
},
  "geometry": {"coordinates":[18.48415,51.54678],"type":"Point"}
}