{
  "type": "Feature",
  "properties": {
    "gn:admin1_code":"86.0",
    "gn:admin2_code":"3064.0",
    "gn:admin3_code":"306401.0",
    "gn:asciiname":"Minikowo",
    "gn:country_code":"PL",
    "gn:dem":80,
    "gn:feature_class":"P",
    "gn:feature_code":"PPL",
    "gn:name":"Minikowo",
    "gn:population":0,
    "gn:timezone":"Europe/Warsaw",
    "iso:country":"PL",
    "name:eng_x_preferred":[
        "Minikowo"
    ],
    "name:pol_x_preferred":[
        "Minikowo"
    ],
    "name:ukr_x_preferred":[
        "\u041c\u0456\u043d\u0456\u043a\u043e\u0432\u043e"
    ],
    "wof:name":"Minikowo",
    "wof:placetype":"neighbourhood"
},
  "geometry": {"coordinates":[16.942154,52.356329],"type":"Point"}
}