{
  "type": "Feature",
  "properties": {
    "iso:country":"PL",
    "name:eng_x_preferred":[
        "Minikowo"
    ],
    "name:pol_x_preferred":[
        "Minikowo"
    ],
    "wof:name":"Minikowo",
    "wof:placetype":"neighbourhood"
},
  "geometry": {"coordinates":[16.94215435687638,52.35632909325538],"type":"Point"}
}