{
  "type": "Feature",
  "properties": {
    "gn:admin1_code":"78.0",
    "gn:admin2_code":"1419.0",
    "gn:admin3_code":"141913.0",
    "gn:asciiname":"Stara Biala",
    "gn:cc2":"PL",
    "gn:country_code":"PL",
    "gn:dem":96,
    "gn:feature_class":"P",
    "gn:feature_code":"PPL",
    "gn:name":"Stara Bia\u0142a",
    "gn:population":0,
    "gn:timezone":"Europe/Warsaw",
    "iso:country":"PL",
    "name:deu_x_preferred":[
        "Stara Bia\u0142a"
    ],
    "name:fra_x_preferred":[
        "Stara Bia\u0142a"
    ],
    "name:pol_x_preferred":[
        "Stara Bia\u0142a"
    ],
    "name:ukr_x_preferred":[
        "\u0421\u0442\u0430\u0440\u0430-\u0411\u0456\u043b\u0430"
    ],
    "name:und_x_variant":[
        "Bia\u0142a",
        "Bia\u0142a Stara"
    ],
    "wof:name":"Stara Biala",
    "wof:placetype":"locality"
},
  "geometry": {"coordinates":[19.64458,52.61191],"type":"Point"}
}