{
  "type": "Feature",
  "properties": {
    "gn:admin1_code":"81.0",
    "gn:admin2_code":"2013.0",
    "gn:admin3_code":"201303.0",
    "gn:asciiname":"Dmochy Glinki",
    "gn:country_code":"PL",
    "gn:dem":126,
    "gn:feature_class":"P",
    "gn:feature_code":"PPL",
    "gn:name":"Dmochy Glinki",
    "gn:population":0,
    "gn:timezone":"Europe/Warsaw",
    "iso:country":"PL",
    "name:azb_x_preferred":[
        "\u062f\u0645\u0648\u062e-\u0642\u0644\u06cc\u0646\u06a9\u06cc"
    ],
    "name:fas_x_preferred":[
        "\u062f\u0645\u0648\u062e-\u06af\u0644\u06cc\u0646\u06a9\u06cc"
    ],
    "name:fra_x_preferred":[
        "Dmochy-Glinki"
    ],
    "name:lit_x_preferred":[
        "Dmochi Glinkai"
    ],
    "name:pol_x_preferred":[
        "Dmochy-Glinki"
    ],
    "name:ukr_x_preferred":[
        "\u0414\u043c\u043e\u0445\u0438-\u0490\u043b\u0456\u043d\u043a\u0456"
    ],
    "wof:name":"Dmochy Glinki",
    "wof:placetype":"locality"
},
  "geometry": {"coordinates":[22.34021,52.81817],"type":"Point"}
}