{
  "type": "Feature",
  "properties": {
    "gn:gn_country":"PL",
    "gn:gn_fcode":"PPL",
    "gn:gn_pop":820,
    "gn:population":820,
    "iso:country":"PL",
    "name:ast_x_preferred":[
        "Stanin"
    ],
    "name:azb_x_preferred":[
        "\u0633\u062a\u0627\u0646\u0642\u0646"
    ],
    "name:ceb_x_preferred":[
        "Stanin"
    ],
    "name:deu_x_preferred":[
        "Stanin"
    ],
    "name:eng_x_preferred":[
        "Stanin"
    ],
    "name:fas_x_preferred":[
        "\u0633\u062a\u0627\u0646\u06af\u0646"
    ],
    "name:fra_x_preferred":[
        "Stanin"
    ],
    "name:nld_x_preferred":[
        "Stanin"
    ],
    "name:pol_x_preferred":[
        "Stanin"
    ],
    "name:ukr_x_preferred":[
        "\u0421\u0442\u0430\u043d\u0456\u043d"
    ],
    "qs_pg:aaroncc":"PL",
    "qs_pg:gn_country":"PL",
    "qs_pg:gn_fcode":"PPL",
    "qs_pg:gn_pop":820,
    "qs_pg:name":"Stanin",
    "qs_pg:name_adm0":"Polska",
    "qs_pg:name_adm1":"Lubelskie",
    "qs_pg:photos_9r":0,
    "qs_pg:photos_sr":0,
    "qs_pg:pop_sr":2,
    "qs_pg:qs_pg_placetype":"locality",
    "qs_pg:qs_pg_placetype_gp":"Town",
    "qs_pg:woe_adm0":23424923,
    "woe:adm0_id":23424923,
    "woe:name_adm0":"Polska",
    "woe:name_adm1":"Lubelskie",
    "woe:placetype":"Town",
    "wof:name":"Stanin",
    "wof:placetype":"locality",
    "wof:population":820
},
  "geometry": {"coordinates":[22.20234,51.87013],"type":"Point"}
}