{
  "type": "Feature",
  "properties": {
    "gn:admin1_code":"86.0",
    "gn:admin2_code":"3010.0",
    "gn:admin3_code":"301007.0",
    "gn:asciiname":"Swiecia",
    "gn:country_code":"PL",
    "gn:dem":97,
    "gn:feature_class":"P",
    "gn:feature_code":"PPL",
    "gn:name":"\u015awi\u0119cia",
    "gn:population":0,
    "gn:timezone":"Europe/Warsaw",
    "iso:country":"PL",
    "name:fra_x_preferred":[
        "\u015awi\u0119cia"
    ],
    "name:pol_x_preferred":[
        "\u015awi\u0119cia"
    ],
    "name:ukr_x_preferred":[
        "\u0421\u044c\u0432\u0435\u043d\u0446\u044f"
    ],
    "name:und_x_variant":[
        "\u015awi\u0119cia"
    ],
    "wof:name":"Swiecia",
    "wof:placetype":"locality"
},
  "geometry": {"coordinates":[18.14695,52.13124000000001],"type":"Point"}
}