{
  "type": "Feature",
  "properties": {
    "gn:admin1_code":"81.0",
    "gn:admin2_code":"2008.0",
    "gn:admin3_code":"200803.0",
    "gn:asciiname":"Bagno",
    "gn:country_code":"PL",
    "gn:dem":169,
    "gn:feature_class":"P",
    "gn:feature_code":"PPL",
    "gn:name":"Bagno",
    "gn:population":0,
    "gn:timezone":"Europe/Warsaw",
    "iso:country":"PL",
    "wof:name":"Bagno",
    "wof:placetype":"locality"
},
  "geometry": {"coordinates":[22.92812,53.44185],"type":"Point"}
}