{
  "type": "Feature",
  "properties": {
    "gn:admin1_code":"85.0",
    "gn:admin2_code":"2819.0",
    "gn:admin3_code":"281902.0",
    "gn:asciiname":"Kuty",
    "gn:country_code":"PL",
    "gn:dem":132,
    "gn:feature_class":"P",
    "gn:feature_code":"PPL",
    "gn:name":"Kuty",
    "gn:population":0,
    "gn:timezone":"Europe/Warsaw",
    "iso:country":"PL",
    "name:deu_x_preferred":[
        "Kuty"
    ],
    "name:lit_x_preferred":[
        "Ku\u010diai"
    ],
    "name:pol_x_preferred":[
        "Kuty"
    ],
    "name:ukr_x_preferred":[
        "\u041a\u0443\u0442\u0438"
    ],
    "name:und_x_variant":[
        "Kut",
        "Kutten",
        "Kuty"
    ],
    "wof:name":"Kuty",
    "wof:placetype":"locality"
},
  "geometry": {"coordinates":[21.93837000000001,54.17116],"type":"Point"}
}