{
  "type": "Feature",
  "properties": {
    "gn:admin1_code":"74.0",
    "gn:admin2_code":"1003.0",
    "gn:admin3_code":"100304.0",
    "gn:asciiname":"Katy",
    "gn:country_code":"PL",
    "gn:dem":163,
    "gn:feature_class":"P",
    "gn:feature_code":"PPL",
    "gn:name":"K\u0105ty",
    "gn:population":0,
    "gn:timezone":"Europe/Warsaw",
    "iso:country":"PL",
    "name:fra_x_preferred":[
        "K\u0105ty"
    ],
    "name:pol_x_preferred":[
        "K\u0105ty"
    ],
    "name:ukr_x_preferred":[
        "\u041a\u043e\u043d\u0442\u0438"
    ],
    "wof:name":"Katy",
    "wof:placetype":"locality"
},
  "geometry": {"coordinates":[18.90721,51.41254],"type":"Point"}
}