{
  "type": "Feature",
  "properties": {
    "gn:admin1_code":"73.0",
    "gn:admin2_code":"414.0",
    "gn:admin3_code":"41407.0",
    "gn:asciiname":"Zur",
    "gn:country_code":"PL",
    "gn:dem":65,
    "gn:feature_class":"P",
    "gn:feature_code":"PPL",
    "gn:name":"\u017bur",
    "gn:population":0,
    "gn:timezone":"Europe/Warsaw",
    "iso:country":"PL",
    "name:deu_x_preferred":[
        "Zur"
    ],
    "name:rus_x_preferred":[
        "\u0417\u0443\u0440"
    ],
    "name:ukr_x_preferred":[
        "\u0417\u0443\u0440"
    ],
    "wof:name":"Zur",
    "wof:placetype":"locality"
},
  "geometry": {"coordinates":[18.36365,53.56021],"type":"Point"}
}