{
  "type": "Feature",
  "properties": {
    "gn:admin1_code":"85.0",
    "gn:admin2_code":"2810.0",
    "gn:admin3_code":"281002.0",
    "gn:asciiname":"Olszewo",
    "gn:country_code":"PL",
    "gn:dem":128,
    "gn:feature_class":"P",
    "gn:feature_code":"PPL",
    "gn:name":"Olszewo",
    "gn:population":0,
    "gn:timezone":"Europe/Warsaw",
    "iso:country":"PL",
    "name:deu_x_preferred":[
        "Olszewo"
    ],
    "name:fra_x_preferred":[
        "Olszewo"
    ],
    "name:lit_x_preferred":[
        "Ol\u0161evas"
    ],
    "name:pol_x_preferred":[
        "Olszewo"
    ],
    "name:ukr_x_preferred":[
        "\u041e\u043b\u044c\u0448\u0435\u0432\u043e"
    ],
    "name:und_x_variant":[
        "Erlenau",
        "Olschewen",
        "Olszewo"
    ],
    "wof:name":"Olszewo",
    "wof:placetype":"locality"
},
  "geometry": {"coordinates":[21.67659,53.86046],"type":"Point"}
}