{
  "type": "Feature",
  "properties": {
    "gn:admin1_code":"84.0",
    "gn:admin2_code":"2604.0",
    "gn:admin3_code":"260404.0",
    "gn:asciiname":"Kotlice",
    "gn:country_code":"PL",
    "gn:dem":207,
    "gn:feature_class":"P",
    "gn:feature_code":"PPL",
    "gn:name":"Kotlice",
    "gn:population":0,
    "gn:timezone":"Europe/Warsaw",
    "iso:country":"PL",
    "name:ceb_x_preferred":[
        "Kotlice"
    ],
    "name:pol_x_preferred":[
        "Kotlice"
    ],
    "name:ukr_x_preferred":[
        "\u041a\u043e\u0442\u043b\u0456\u0446\u0435"
    ],
    "wof:name":"Kotlice",
    "wof:placetype":"locality"
},
  "geometry": {"coordinates":[20.78733,50.56623],"type":"Point"}
}