{
  "type": "Feature",
  "properties": {
    "gn:admin1_code":"87.0",
    "gn:admin2_code":"3206.0",
    "gn:admin3_code":"320607.0",
    "gn:asciiname":"Zelislawiec",
    "gn:country_code":"PL",
    "gn:dem":28,
    "gn:feature_class":"P",
    "gn:feature_code":"PPL",
    "gn:name":"\u017belis\u0142awiec",
    "gn:population":0,
    "gn:timezone":"Europe/Warsaw",
    "iso:country":"PL",
    "name:pol_x_preferred":[
        "\u017belis\u0142awiec"
    ],
    "name:ukr_x_preferred":[
        "\u0416\u0435\u043b\u0456\u0441\u043b\u0430\u0432\u0435\u0446\u044c"
    ],
    "name:und_x_variant":[
        "Sinzlow"
    ],
    "name:vie_x_preferred":[
        "\u017belis\u0142awiec"
    ],
    "wof:name":"Zelislawiec",
    "wof:placetype":"locality"
},
  "geometry": {"coordinates":[14.67422,53.27497],"type":"Point"}
}