{
  "type": "Feature",
  "properties": {
    "gn:admin1_code":"85.0",
    "gn:admin2_code":"2801.0",
    "gn:admin3_code":"280106.0",
    "gn:asciiname":"Przewarszyty",
    "gn:country_code":"PL",
    "gn:dem":67,
    "gn:feature_class":"P",
    "gn:feature_code":"PPL",
    "gn:name":"Przewarszyty",
    "gn:population":0,
    "gn:timezone":"Europe/Warsaw",
    "iso:country":"PL",
    "name:fra_x_preferred":[
        "Przewarszyty"
    ],
    "name:pol_x_preferred":[
        "Przewarszyty"
    ],
    "name:und_x_variant":[
        "Prauerschitten",
        "Przewarszyty"
    ],
    "wof:name":"Przewarszyty",
    "wof:placetype":"locality"
},
  "geometry": {"coordinates":[20.8869,54.30573],"type":"Point"}
}