{
  "type": "Feature",
  "properties": {
    "gn:admin1_code":"86.0",
    "gn:admin2_code":"3018.0",
    "gn:admin3_code":"301803.0",
    "gn:asciiname":"Bukownica",
    "gn:country_code":"PL",
    "gn:dem":155,
    "gn:feature_class":"P",
    "gn:feature_code":"PPL",
    "gn:name":"Bukownica",
    "gn:population":0,
    "gn:timezone":"Europe/Warsaw",
    "iso:country":"PL",
    "name:ceb_x_preferred":[
        "Bukownica"
    ],
    "name:pol_x_preferred":[
        "Bukownica"
    ],
    "name:ukr_x_preferred":[
        "\u0411\u0443\u043a\u043e\u0432\u043d\u0438\u0446\u044f"
    ],
    "name:und_x_variant":[
        "Bukownica Kolonja Druga"
    ],
    "wof:name":"Bukownica",
    "wof:placetype":"locality"
},
  "geometry": {"coordinates":[18.0513,51.4692],"type":"Point"}
}