{
  "type": "Feature",
  "properties": {
    "gn:admin1_code":"74.0",
    "gn:admin2_code":"1007.0",
    "gn:admin3_code":"100703.0",
    "gn:asciiname":"Zajaczkow",
    "gn:country_code":"PL",
    "gn:dem":214,
    "gn:feature_class":"P",
    "gn:feature_code":"PPL",
    "gn:name":"Zaj\u0105czk\u00f3w",
    "gn:population":0,
    "gn:timezone":"Europe/Warsaw",
    "iso:country":"PL",
    "name:fra_x_preferred":[
        "Zaj\u0105czk\u00f3w"
    ],
    "name:pol_x_preferred":[
        "Zaj\u0105czk\u00f3w"
    ],
    "name:ukr_x_preferred":[
        "\u0417\u0430\u0439\u043e\u043d\u0447\u043a\u0443\u0432"
    ],
    "wof:name":"Zajaczkow",
    "wof:placetype":"locality"
},
  "geometry": {"coordinates":[20.0466,51.41174],"type":"Point"}
}