{
  "type": "Feature",
  "properties": {
    "gn:admin1_code":"85.0",
    "gn:admin2_code":"2817.0",
    "gn:admin3_code":"281706.0",
    "gn:asciiname":"Prusowy Borek",
    "gn:country_code":"PL",
    "gn:dem":140,
    "gn:feature_class":"P",
    "gn:feature_code":"PPL",
    "gn:name":"Prusowy Borek",
    "gn:population":0,
    "gn:timezone":"Europe/Warsaw",
    "iso:country":"PL",
    "name:fra_x_preferred":[
        "Prusowy Borek"
    ],
    "name:pol_x_preferred":[
        "Prusowy Borek"
    ],
    "name:ukr_x_preferred":[
        "\u041f\u0440\u0443\u0441\u043e\u0432\u0438-\u0411\u043e\u0440\u0435\u043a"
    ],
    "name:und_x_variant":[
        "Prus\u00f3w Borek",
        "Prussowborrek",
        "Preussenwalde"
    ],
    "wof:name":"Prusowy Borek",
    "wof:placetype":"locality"
},
  "geometry": {"coordinates":[21.07013,53.52022],"type":"Point"}
}