{
  "type": "Feature",
  "properties": {
    "gn:admin1_code":"86.0",
    "gn:admin2_code":"3003.0",
    "gn:admin3_code":"300306.0",
    "gn:asciiname":"Goraninek",
    "gn:country_code":"PL",
    "gn:dem":123,
    "gn:feature_class":"P",
    "gn:feature_code":"PPL",
    "gn:name":"Goraninek",
    "gn:population":0,
    "gn:timezone":"Europe/Warsaw",
    "iso:country":"PL",
    "name:pol_x_preferred":[
        "Goraninek"
    ],
    "wof:name":"Goraninek",
    "wof:placetype":"locality"
},
  "geometry": {"coordinates":[17.43333,52.46666999999999],"type":"Point"}
}