{
  "type": "Feature",
  "properties": {
    "gn:admin1_code":"76.0",
    "gn:admin2_code":"811.0",
    "gn:admin3_code":"81106.0",
    "gn:asciiname":"Kalek",
    "gn:country_code":"PL",
    "gn:dem":74,
    "gn:feature_class":"P",
    "gn:feature_code":"PPL",
    "gn:name":"Ka\u0142ek",
    "gn:population":0,
    "gn:timezone":"Europe/Warsaw",
    "iso:country":"PL",
    "name:fra_x_preferred":[
        "Ka\u0142ek"
    ],
    "name:pol_x_preferred":[
        "Ka\u0142ek"
    ],
    "name:szl_x_preferred":[
        "Ka\u0142ek"
    ],
    "name:ukr_x_preferred":[
        "\u041a\u0430\u043b\u0435\u043a"
    ],
    "wof:name":"Kalek",
    "wof:placetype":"locality"
},
  "geometry": {"coordinates":[14.95518,51.87817],"type":"Point"}
}