{
  "type": "Feature",
  "properties": {
    "gn:admin1_code":"86.0",
    "gn:admin2_code":"3013.0",
    "gn:admin3_code":"301304.0",
    "gn:asciiname":"Robczysko",
    "gn:country_code":"PL",
    "gn:dem":96,
    "gn:feature_class":"P",
    "gn:feature_code":"PPL",
    "gn:name":"Robczysko",
    "gn:population":0,
    "gn:timezone":"Europe/Warsaw",
    "iso:country":"PL",
    "name:fra_x_preferred":[
        "Robczysko"
    ],
    "name:pol_x_preferred":[
        "Robczysko"
    ],
    "name:ukr_x_preferred":[
        "\u0420\u043e\u0431\u0447\u0438\u0441\u044c\u043a\u043e"
    ],
    "wof:name":"Robczysko",
    "wof:placetype":"locality"
},
  "geometry": {"coordinates":[16.76149,51.8109],"type":"Point"}
}