{
  "type": "Feature",
  "properties": {
    "gn:admin1_code":"72",
    "gn:admin2_code":"0210",
    "gn:admin3_code":"21004.0",
    "gn:asciiname":"Radostow Sredni",
    "gn:country_code":"PL",
    "gn:dem":249,
    "gn:feature_class":"P",
    "gn:feature_code":"PPL",
    "gn:name":"Radost\u00f3w \u015aredni",
    "gn:population":0,
    "gn:timezone":"Europe/Warsaw",
    "iso:country":"PL",
    "name:deu_x_historical":[
        "Mittel Thiemendorf"
    ],
    "name:deu_x_preferred":[
        "Mittel Thiemendorf"
    ],
    "name:pol_x_preferred":[
        "Radost\u00f3w \u015aredni"
    ],
    "name:ukr_x_preferred":[
        "\u0420\u0430\u0434\u043e\u0441\u0442\u0443\u0432-\u0421\u0435\u0440\u0435\u0434\u043d\u0456\u0439"
    ],
    "wof:name":"Radostow Sredni",
    "wof:placetype":"locality"
},
  "geometry": {"coordinates":[15.36472,51.12025],"type":"Point"}
}