{
  "type": "Feature",
  "properties": {
    "gn:country":"PL",
    "gn:fcode":"PPL",
    "gn:population":323,
    "iso:country":"PL",
    "name:ceb_x_preferred":[
        "Zawada Lanckoro\u0144ska"
    ],
    "name:pol_x_preferred":[
        "Zawada Lanckoro\u0144ska"
    ],
    "name:ukr_x_preferred":[
        "\u0417\u0430\u0432\u0430\u0434\u0430-\u041b\u044f\u043d\u0446\u043a\u043e\u0440\u043e\u043d\u0441\u044c\u043a\u0430"
    ],
    "name:und_x_variant":[
        "Zawada"
    ],
    "qs_pg:aaroncc":"PL",
    "qs_pg:gn_country":"PL",
    "qs_pg:gn_fcode":"PPL",
    "qs_pg:gn_pop":323,
    "qs_pg:name":"Zawada Lanckoro\u0144ska",
    "qs_pg:name_adm0":"Polska",
    "qs_pg:name_adm1":"Ma\u0142opolskie",
    "qs_pg:photos_9r":0,
    "qs_pg:photos_sr":0,
    "qs_pg:pop_sr":2,
    "qs_pg:qs_pg_placetype":"locality",
    "qs_pg:qs_pg_placetype_gp":"Town",
    "qs_pg:woe_adm0":23424923,
    "woe:adm0_id":23424923,
    "woe:name_adm0":"Polska",
    "woe:name_adm1":"Ma\u0142opolskie",
    "woe:placetype":"Town",
    "wof:name":"Zawada Lanckoro\u0144ska",
    "wof:placetype":"locality",
    "wof:population":323
},
  "geometry": {"coordinates":[20.8045,49.87019],"type":"Point"}
}