{
  "type": "Feature",
  "properties": {
    "gn:admin1_code":"77.0",
    "gn:admin2_code":"1211.0",
    "gn:admin3_code":"121112.0",
    "gn:asciiname":"Nowy Swiat",
    "gn:country_code":"PL",
    "gn:dem":576,
    "gn:feature_class":"P",
    "gn:feature_code":"PPL",
    "gn:name":"Nowy \u015awiat",
    "gn:population":0,
    "gn:timezone":"Europe/Warsaw",
    "iso:country":"PL",
    "wof:name":"Nowy Swiat",
    "wof:placetype":"locality"
},
  "geometry": {"coordinates":[19.98333,49.61667],"type":"Point"}
}