{
  "type": "Feature",
  "properties": {
    "gn:admin1_code":"78.0",
    "gn:admin2_code":"1437.0",
    "gn:admin3_code":"143706.0",
    "gn:asciiname":"Poniatowo",
    "gn:country_code":"PL",
    "gn:dem":125,
    "gn:feature_class":"P",
    "gn:feature_code":"PPL",
    "gn:name":"Poniatowo",
    "gn:population":0,
    "gn:timezone":"Europe/Warsaw",
    "iso:country":"PL",
    "wof:name":"Poniatowo",
    "wof:placetype":"locality"
},
  "geometry": {"coordinates":[19.87152,53.04689000000001],"type":"Point"}
}