{
  "type": "Feature",
  "properties": {
    "gn:country":"PL",
    "gn:fcode":"PPL",
    "gn:population":871,
    "iso:country":"PL",
    "name:ast_x_preferred":[
        "Koz\u0142\u00f3w Biskupi"
    ],
    "name:azb_x_preferred":[
        "\u06a9\u0648\u0632\u0648\u0648\u0641 \u0628\u06cc\u0633\u06a9\u0648\u067e\u06cc"
    ],
    "name:ceb_x_preferred":[
        "Koz\u0142\u00f3w Biskupi"
    ],
    "name:ces_x_preferred":[
        "Koz\u0142\u00f3w Biskupi"
    ],
    "name:che_x_preferred":[
        "\u041a\u043e\u0437\u043b\u0443\u0432-\u0411\u0438\u0441\u043a\u0443\u043f\u0438"
    ],
    "name:eng_x_preferred":[
        "Koz\u0142\u00f3w Biskupi"
    ],
    "name:fas_x_preferred":[
        "\u06a9\u0648\u0632\u0648\u0648\u0641 \u0628\u06cc\u0633\u06a9\u0648\u067e\u06cc"
    ],
    "name:fra_x_preferred":[
        "Koz\u0142\u00f3w Biskupi"
    ],
    "name:jpn_x_preferred":[
        "\u30b3\u30ba\u30a6\u30d5\u30fb\u30d3\u30b9\u30af\u30d4"
    ],
    "name:nan_x_preferred":[
        "Koz\u0142\u00f3w Biskupi"
    ],
    "name:nld_x_preferred":[
        "Koz\u0142\u00f3w Biskupi"
    ],
    "name:pol_x_preferred":[
        "Koz\u0142\u00f3w Biskupi"
    ],
    "name:sqi_x_preferred":[
        "Kozlow Biskupi"
    ],
    "name:tat_x_preferred":[
        "\u041a\u043e\u0437\u043b\u0443\u0432-\u0411\u0438\u0441\u043a\u0443\u043f\u0438"
    ],
    "name:ukr_x_preferred":[
        "\u041a\u043e\u0437\u043b\u0443\u0432-\u0411\u0456\u0441\u043a\u0443\u043f\u0456"
    ],
    "name:und_x_variant":[
        "Biskupi Koz\u0142\u00f3w"
    ],
    "qs_pg:aaroncc":"PL",
    "qs_pg:gn_country":"PL",
    "qs_pg:gn_fcode":"PPL",
    "qs_pg:gn_pop":871,
    "qs_pg:name":"Koz\u0142\u00f3w Biskupi",
    "qs_pg:name_adm0":"Polska",
    "qs_pg:name_adm1":"Mazowieckie",
    "qs_pg:photos_9k":1,
    "qs_pg:photos_9r":1,
    "qs_pg:photos_all":12,
    "qs_pg:photos_sr":0,
    "qs_pg:pop_sr":2,
    "qs_pg:qs_pg_placetype":"locality",
    "qs_pg:qs_pg_placetype_gp":"Town",
    "qs_pg:woe_adm0":23424923,
    "woe:adm0_id":23424923,
    "woe:name_adm0":"Polska",
    "woe:name_adm1":"Mazowieckie",
    "woe:placetype":"Town",
    "wof:name":"Koz\u0142\u00f3w Biskupi",
    "wof:placetype":"locality",
    "wof:population":871
},
  "geometry": {"coordinates":[20.1921,52.19161],"type":"Point"}
}