{
  "type": "Feature",
  "properties": {
    "gn:admin1_code":"76",
    "gn:admin2_code":"0808",
    "gn:admin3_code":"80804.0",
    "gn:asciiname":"Wilenko Kolonia",
    "gn:country_code":"PL",
    "gn:dem":70,
    "gn:feature_class":"P",
    "gn:feature_code":"PPLL",
    "gn:name":"Wilenko Kolonia",
    "gn:population":0,
    "gn:timezone":"Europe/Warsaw",
    "iso:country":"PL",
    "wof:name":"Wilenko Kolonia",
    "wof:placetype":"locality"
},
  "geometry": {"coordinates":[15.67062,52.28197],"type":"Point"}
}