{
  "type": "Feature",
  "properties": {
    "gn:gn_country":"PL",
    "gn:gn_fcode":"PPLA3",
    "gn:gn_pop":3100,
    "gn:population":3100,
    "iso:country":"PL",
    "name:ceb_x_preferred":[
        "Domaradz"
    ],
    "name:deu_x_preferred":[
        "Domaradz"
    ],
    "name:nld_x_preferred":[
        "Domaradz"
    ],
    "name:pol_x_preferred":[
        "Domaradz"
    ],
    "name:ukr_x_preferred":[
        "\u0414\u043e\u043c\u0430\u0440\u0430\u0434\u0437"
    ],
    "qs_pg:aaroncc":"PL",
    "qs_pg:gn_country":"PL",
    "qs_pg:gn_fcode":"PPLA3",
    "qs_pg:gn_pop":3100,
    "qs_pg:name":"Domaradz",
    "qs_pg:name_adm0":"Polska",
    "qs_pg:name_adm1":"Podkarpackie",
    "qs_pg:photos_9k":1,
    "qs_pg:photos_9r":1,
    "qs_pg:photos_all":2,
    "qs_pg:photos_sr":0,
    "qs_pg:pop_sr":4,
    "qs_pg:qs_pg_placetype":"localadmin",
    "qs_pg:qs_pg_placetype_gp":"LocalAdmin",
    "qs_pg:woe_adm0":23424923,
    "woe:adm0_id":23424923,
    "woe:name_adm0":"Polska",
    "woe:name_adm1":"Podkarpackie",
    "woe:placetype":"LocalAdmin",
    "wof:name":"Domaradz",
    "wof:placetype":"localadmin",
    "wof:population":3100
},
  "geometry": {"coordinates":[21.94571,49.78675],"type":"Point"}
}