{
  "type": "Feature",
  "properties": {
    "gn:admin1_code":"84.0",
    "gn:admin2_code":"2661.0",
    "gn:admin3_code":"266101.0",
    "gn:asciiname":"Sandomierskie",
    "gn:country_code":"PL",
    "gn:dem":271,
    "gn:feature_class":"P",
    "gn:feature_code":"PPL",
    "gn:name":"Sandomierskie",
    "gn:population":0,
    "gn:timezone":"Europe/Warsaw",
    "iso:country":"PL",
    "wof:name":"Sandomierskie",
    "wof:placetype":"locality"
},
  "geometry": {"coordinates":[20.64797,50.87213],"type":"Point"}
}