{
  "type": "Feature",
  "properties": {
    "gn:admin1_code":"78.0",
    "gn:admin2_code":"1428.0",
    "gn:admin3_code":"142804.0",
    "gn:asciiname":"Januszew",
    "gn:country_code":"PL",
    "gn:dem":63,
    "gn:feature_class":"P",
    "gn:feature_code":"PPL",
    "gn:name":"Januszew",
    "gn:population":0,
    "gn:timezone":"Europe/Warsaw",
    "iso:country":"PL",
    "name:azb_x_preferred":[
        "\u06cc\u0627\u0646\u0648\u0634\u0648"
    ],
    "name:fas_x_preferred":[
        "\u06cc\u0627\u0646\u0648\u0634\u0648"
    ],
    "name:fra_x_preferred":[
        "Januszew"
    ],
    "name:pol_x_preferred":[
        "Januszew"
    ],
    "name:ukr_x_preferred":[
        "\u042f\u043d\u0443\u0448\u0435\u0432"
    ],
    "name:urd_x_preferred":[
        "\u062c\u0627\u0646\u0633\u0632\u06cc\u0648"
    ],
    "wof:name":"Januszew",
    "wof:placetype":"locality"
},
  "geometry": {"coordinates":[20.13463,52.3659],"type":"Point"}
}