{
  "type": "Feature",
  "properties": {
    "gn:admin1_code":"78.0",
    "gn:admin2_code":"1422.0",
    "gn:admin3_code":"142202.0",
    "gn:asciiname":"Paczuszki",
    "gn:country_code":"PL",
    "gn:dem":200,
    "gn:feature_class":"P",
    "gn:feature_code":"PPL",
    "gn:name":"Paczuszki",
    "gn:population":0,
    "gn:timezone":"Europe/Warsaw",
    "iso:country":"PL",
    "wof:name":"Paczuszki",
    "wof:placetype":"locality"
},
  "geometry": {"coordinates":[20.71667,53.23333],"type":"Point"}
}