{
  "type": "Feature",
  "properties": {
    "gn:admin1_code":"73.0",
    "gn:admin2_code":"412.0",
    "gn:admin3_code":"41202.0",
    "gn:asciiname":"Piskorczyn",
    "gn:country_code":"PL",
    "gn:dem":123,
    "gn:feature_class":"P",
    "gn:feature_code":"PPL",
    "gn:name":"Piskorczyn",
    "gn:population":0,
    "gn:timezone":"Europe/Warsaw",
    "iso:country":"PL",
    "name:azb_x_preferred":[
        "\u067e\u06cc\u0633\u06a9\u0648\u0631\u0686\u0646"
    ],
    "name:ceb_x_preferred":[
        "Piskorczyn"
    ],
    "name:fas_x_preferred":[
        "\u067e\u06cc\u0633\u06a9\u0648\u0631\u0686\u0646"
    ],
    "name:fra_x_preferred":[
        "Piskorczyn"
    ],
    "name:nld_x_preferred":[
        "Piskorczyn"
    ],
    "name:pol_x_preferred":[
        "Piskorczyn"
    ],
    "name:ukr_x_preferred":[
        "\u041f\u0456\u0441\u043a\u043e\u0440\u0447\u0438\u043d"
    ],
    "wof:name":"Piskorczyn",
    "wof:placetype":"locality"
},
  "geometry": {"coordinates":[19.25365,53.03939],"type":"Point"}
}