{
  "type": "Feature",
  "properties": {
    "iso:country":"PL",
    "name:bul_x_preferred":[
        "\u0421\u0442\u0430\u0440\u0430\u0445\u043e\u0432\u0438\u0446\u0435"
    ],
    "name:deu_x_preferred":[
        "Starachowice"
    ],
    "name:ell_x_preferred":[
        "\u03a3\u03c4\u03b1\u03c1\u03b1\u03c7\u03bf\u03b2\u03af\u03c4\u03c3\u03b5"
    ],
    "name:epo_x_preferred":[
        "Starachowice"
    ],
    "name:eus_x_preferred":[
        "Starachowice"
    ],
    "name:fas_x_preferred":[
        "\u0633\u062a\u0627\u0631\u0627\u062e\u0648\u0648\u06cc\u062a\u0633\u0647"
    ],
    "name:fra_x_preferred":[
        "Starachowice"
    ],
    "name:hak_x_preferred":[
        "Starachowice"
    ],
    "name:heb_x_preferred":[
        "\u05e1\u05d8\u05e8\u05d7\u05d5\u05d1\u05d9\u05e6\u05d4"
    ],
    "name:hun_x_preferred":[
        "Starachowice"
    ],
    "name:ind_x_preferred":[
        "Starachowice"
    ],
    "name:ita_x_preferred":[
        "Starachowice"
    ],
    "name:jav_x_preferred":[
        "Starachowice"
    ],
    "name:lav_x_preferred":[
        "Starahovice"
    ],
    "name:lit_x_preferred":[
        "Starachovic\u0117s"
    ],
    "name:mkd_x_preferred":[
        "\u0421\u0442\u0430\u0440\u0430\u0445\u043e\u0432\u0438\u0446\u0435"
    ],
    "name:msa_x_preferred":[
        "Starachowice"
    ],
    "name:nld_x_preferred":[
        "Starachowice"
    ],
    "name:pol_x_preferred":[
        "Starachowice"
    ],
    "name:por_x_preferred":[
        "Starachowice"
    ],
    "name:ron_x_preferred":[
        "Starachowice"
    ],
    "name:rus_x_preferred":[
        "\u0421\u0442\u0430\u0440\u0430\u0445\u043e\u0432\u0438\u0446\u0435"
    ],
    "name:slk_x_preferred":[
        "Starachowice"
    ],
    "name:spa_x_preferred":[
        "Starachowice"
    ],
    "name:srp_x_preferred":[
        "\u0421\u0442\u0430\u0440\u0430\u0445\u043e\u0432\u0438\u0446\u0435"
    ],
    "name:szl_x_preferred":[
        "Starachowicy"
    ],
    "name:tat_x_preferred":[
        "\u0421\u0442\u0430\u0440\u0430\u0445\u043e\u0432\u0438\u0446\u0435"
    ],
    "name:ukr_x_preferred":[
        "\u0421\u0442\u0430\u0440\u0430\u0445\u043e\u0432\u0456\u0446\u0435"
    ],
    "name:vie_x_preferred":[
        "Starachowice"
    ],
    "name:war_x_preferred":[
        "Starachowice"
    ],
    "name:zho_x_preferred":[
        "\u65af\u5854\u62c9\u970d\u7dad\u91c7"
    ],
    "qs_pg:aaroncc":"PL",
    "qs_pg:name":"Starachowice",
    "qs_pg:name_adm0":"Polska",
    "qs_pg:name_adm1":"Swi\u0119tokrzyskie",
    "qs_pg:photos":66,
    "qs_pg:photos_1k":13,
    "qs_pg:photos_9k":1,
    "qs_pg:photos_9r":3,
    "qs_pg:photos_all":114,
    "qs_pg:photos_sr":2,
    "qs_pg:pop_sr":0,
    "qs_pg:qs_pg_placetype":"localadmin",
    "qs_pg:qs_pg_placetype_gp":"LocalAdmin",
    "qs_pg:woe_adm0":23424923,
    "woe:adm0_id":23424923,
    "woe:name_adm0":"Polska",
    "woe:name_adm1":"Swi\u0119tokrzyskie",
    "woe:placetype":"LocalAdmin",
    "wof:name":"Starachowice",
    "wof:placetype":"localadmin"
},
  "geometry": {"coordinates":[21.070659,51.040894],"type":"Point"}
}