{
  "type": "Feature",
  "properties": {
    "gn:admin1_code":"77.0",
    "gn:admin2_code":"1206.0",
    "gn:admin3_code":"120603.0",
    "gn:asciiname":"Lesieniec",
    "gn:country_code":"PL",
    "gn:dem":323,
    "gn:feature_class":"P",
    "gn:feature_code":"PPL",
    "gn:name":"Lesieniec",
    "gn:population":0,
    "gn:timezone":"Europe/Warsaw",
    "iso:country":"PL",
    "name:pol_x_preferred":[
        "Lesieniec"
    ],
    "name:rus_x_preferred":[
        "\u041b\u0435\u0441\u0435\u043d\u0435\u0446"
    ],
    "name:ukr_x_preferred":[
        "\u041b\u0435\u0441\u0435\u043d\u0435\u0446\u044c"
    ],
    "wof:name":"Lesieniec",
    "wof:placetype":"locality"
},
  "geometry": {"coordinates":[19.95581,50.24473],"type":"Point"}
}