{
  "type": "Feature",
  "properties": {
    "gn:admin1_code":"86.0",
    "gn:admin2_code":"3009.0",
    "gn:admin3_code":"300910.0",
    "gn:asciiname":"Plebanki",
    "gn:country_code":"PL",
    "gn:dem":117,
    "gn:feature_class":"P",
    "gn:feature_code":"PPL",
    "gn:name":"Plebanki",
    "gn:population":0,
    "gn:timezone":"Europe/Warsaw",
    "iso:country":"PL",
    "wof:name":"Plebanki",
    "wof:placetype":"locality"
},
  "geometry": {"coordinates":[18.5936,52.30549],"type":"Point"}
}