{
  "type": "Feature",
  "properties": {
    "gn:admin1_code":"85.0",
    "gn:admin2_code":"2814.0",
    "gn:admin3_code":"281404.0",
    "gn:asciiname":"Zalbki",
    "gn:country_code":"PL",
    "gn:dem":110,
    "gn:feature_class":"P",
    "gn:feature_code":"PPL",
    "gn:name":"Zalbki",
    "gn:population":0,
    "gn:timezone":"Europe/Warsaw",
    "iso:country":"PL",
    "name:pol_x_preferred":[
        "Zalbki"
    ],
    "name:ukr_x_preferred":[
        "\u0417\u0430\u043b\u044c\u0431\u043a\u0456"
    ],
    "name:und_x_variant":[
        "Salbken",
        "Zalbki"
    ],
    "wof:name":"Zalbki",
    "wof:placetype":"locality"
},
  "geometry": {"coordinates":[20.53908,53.81488],"type":"Point"}
}