{
  "type": "Feature",
  "properties": {
    "gn:admin1_code":"75.0",
    "gn:admin2_code":"607.0",
    "gn:admin3_code":"60706.0",
    "gn:asciiname":"Huta Jozefow",
    "gn:country_code":"PL",
    "gn:dem":269,
    "gn:feature_class":"P",
    "gn:feature_code":"PPL",
    "gn:name":"Huta J\u00f3zef\u00f3w",
    "gn:population":0,
    "gn:timezone":"Europe/Warsaw",
    "iso:country":"PL",
    "name:fra_x_preferred":[
        "Huta J\u00f3zef\u00f3w"
    ],
    "name:pol_x_preferred":[
        "Huta J\u00f3zef\u00f3w"
    ],
    "name:ukr_x_preferred":[
        "\u0413\u0443\u0442\u0430-\u042e\u0437\u0435\u0444\u0443\u0432"
    ],
    "name:und_x_variant":[
        "Huta J\u00f3zef\u00f3w"
    ],
    "wof:name":"Huta Jozefow",
    "wof:placetype":"locality"
},
  "geometry": {"coordinates":[22.28534,50.81419],"type":"Point"}
}