{
  "type": "Feature",
  "properties": {
    "gn:admin1_code":"74.0",
    "gn:admin2_code":"1013.0",
    "gn:admin3_code":"101305.0",
    "gn:asciiname":"Podskarbice Krolewskie",
    "gn:country_code":"PL",
    "gn:dem":151,
    "gn:feature_class":"P",
    "gn:feature_code":"PPL",
    "gn:name":"Podskarbice Kr\u00f3lewskie",
    "gn:population":0,
    "gn:timezone":"Europe/Warsaw",
    "iso:country":"PL",
    "name:pol_x_preferred":[
        "Podskarbice Kr\u00f3lewskie"
    ],
    "name:ukr_x_preferred":[
        "\u041f\u043e\u0434\u0441\u043a\u0430\u0440\u0431\u0456\u0446\u0435-\u041a\u0440\u0443\u043b\u0435\u0432\u0441\u044c\u043a\u0456"
    ],
    "wof:name":"Podskarbice Krolewskie",
    "wof:placetype":"locality"
},
  "geometry": {"coordinates":[20.35498,51.74837],"type":"Point"}
}