{
  "type": "Feature",
  "properties": {
    "gn:admin1_code":"74.0",
    "gn:admin2_code":"1013.0",
    "gn:admin3_code":"101305.0",
    "gn:asciiname":"Podskarbice Krolewskie",
    "gn:country_code":"PL",
    "gn:dem":151,
    "gn:feature_class":"P",
    "gn:feature_code":"PPL",
    "gn:name":"Podskarbice Kr\u00f3lewskie",
    "gn:population":0,
    "gn:timezone":"Europe/Warsaw",
    "iso:country":"PL",
    "name:und_x_variant":[
        "Podskarbice Kr\u00f3lewskie"
    ],
    "wof:name":"Podskarbice Krolewskie",
    "wof:placetype":"locality"
},
  "geometry": {"coordinates":[20.35498,51.74837],"type":"Point"}
}