{
  "type": "Feature",
  "properties": {
    "gn:admin1_code":"78.0",
    "gn:admin2_code":"1426.0",
    "gn:admin3_code":"142609.0",
    "gn:asciiname":"Stara Dabrowka",
    "gn:country_code":"PL",
    "gn:dem":163,
    "gn:feature_class":"P",
    "gn:feature_code":"PPL",
    "gn:name":"Stara D\u0105br\u00f3wka",
    "gn:population":0,
    "gn:timezone":"Europe/Warsaw",
    "iso:country":"PL",
    "name:fra_x_preferred":[
        "Stara D\u0105br\u00f3wka"
    ],
    "name:pol_x_preferred":[
        "Stara D\u0105br\u00f3wka"
    ],
    "name:szl_x_preferred":[
        "Staro D\u016fmbr\u016fwka"
    ],
    "name:ukr_x_preferred":[
        "\u0421\u0442\u0430\u0440\u0430 \u0414\u043e\u043c\u0431\u0440\u0443\u0432\u043a\u0430"
    ],
    "wof:name":"Stara Dabrowka",
    "wof:placetype":"locality"
},
  "geometry": {"coordinates":[22.15118,52.15003],"type":"Point"}
}