{
  "type": "Feature",
  "properties": {
    "gn:admin1_code":"78.0",
    "gn:admin2_code":"1426.0",
    "gn:admin3_code":"142609.0",
    "gn:asciiname":"Stara Dabrowka",
    "gn:country_code":"PL",
    "gn:dem":163,
    "gn:feature_class":"P",
    "gn:feature_code":"PPL",
    "gn:name":"Stara D\u0105br\u00f3wka",
    "gn:population":0,
    "gn:timezone":"Europe/Warsaw",
    "iso:country":"PL",
    "wof:name":"Stara Dabrowka",
    "wof:placetype":"locality"
},
  "geometry": {"coordinates":[22.15118,52.15003],"type":"Point"}
}