{
  "type": "Feature",
  "properties": {
    "gn:admin1_code":"79.0",
    "gn:admin2_code":"1611.0",
    "gn:admin3_code":"161102.0",
    "gn:asciiname":"Gasiorowice",
    "gn:country_code":"PL",
    "gn:dem":205,
    "gn:feature_class":"P",
    "gn:feature_code":"PPL",
    "gn:name":"G\u0105siorowice",
    "gn:population":0,
    "gn:timezone":"Europe/Warsaw",
    "iso:country":"PL",
    "name:deu_x_preferred":[
        "Gonschiorowitz"
    ],
    "name:pol_x_preferred":[
        "G\u0105siorowice"
    ],
    "name:ukr_x_preferred":[
        "\u0490\u043e\u043d\u0441\u044c\u043e\u0440\u043e\u0432\u0456\u0446\u0435"
    ],
    "wof:name":"Gasiorowice",
    "wof:placetype":"locality"
},
  "geometry": {"coordinates":[18.35163,50.5623],"type":"Point"}
}