{
  "type": "Feature",
  "properties": {
    "gn:country":"PL",
    "gn:fcode":"PPL",
    "gn:population":558,
    "iso:country":"PL",
    "name:ast_x_preferred":[
        "Sarbinowo"
    ],
    "name:azb_x_preferred":[
        "\u0633\u0627\u0631\u0628\u06cc\u0646\u0648\u0648\u0648"
    ],
    "name:ceb_x_preferred":[
        "Sarbinowo"
    ],
    "name:deu_x_preferred":[
        "Sarbinowo"
    ],
    "name:eng_x_preferred":[
        "Sarbinowo"
    ],
    "name:fas_x_preferred":[
        "\u0633\u0627\u0631\u0628\u06cc\u0646\u0648\u0648\u0648"
    ],
    "name:fra_x_preferred":[
        "Sarbinowo"
    ],
    "name:nld_x_preferred":[
        "Sarbinowo"
    ],
    "name:pol_x_preferred":[
        "Sarbinowo"
    ],
    "name:srp_x_preferred":[
        "\u0421\u0430\u0440\u0431\u0438\u043d\u043e\u0432\u043e"
    ],
    "name:ukr_x_preferred":[
        "\u0421\u0430\u0440\u0431\u0456\u043d\u043e\u0432\u043e"
    ],
    "qs_pg:aaroncc":"PL",
    "qs_pg:gn_country":"PL",
    "qs_pg:gn_fcode":"PPL",
    "qs_pg:gn_pop":558,
    "qs_pg:name":"Sarbinowo",
    "qs_pg:name_adm0":"Polska",
    "qs_pg:name_adm1":"Zachodniopomorskie",
    "qs_pg:photos":80,
    "qs_pg:photos_1k":16,
    "qs_pg:photos_9k":1,
    "qs_pg:photos_9r":3,
    "qs_pg:photos_all":80,
    "qs_pg:photos_sr":3,
    "qs_pg:pop_sr":2,
    "qs_pg:qs_pg_placetype":"locality",
    "qs_pg:qs_pg_placetype_gp":"Town",
    "qs_pg:woe_adm0":23424923,
    "woe:adm0_id":23424923,
    "woe:name_adm0":"Polska",
    "woe:name_adm1":"Zachodniopomorskie",
    "woe:placetype":"Town",
    "wof:name":"Sarbinowo",
    "wof:placetype":"locality",
    "wof:population":558
},
  "geometry": {"coordinates":[15.95867,54.24878],"type":"Point"}
}