{
  "type": "Feature",
  "properties": {
    "gn:admin1_code":"72.0",
    "gn:admin2_code":"224.0",
    "gn:admin3_code":"22405.0",
    "gn:asciiname":"Grochowiska",
    "gn:country_code":"PL",
    "gn:dem":268,
    "gn:feature_class":"P",
    "gn:feature_code":"PPL",
    "gn:name":"Grochowiska",
    "gn:population":0,
    "gn:timezone":"Europe/Warsaw",
    "iso:country":"PL",
    "name:pol_x_preferred":[
        "Grochowiska"
    ],
    "name:ukr_x_preferred":[
        "\u0490\u0440\u043e\u0445\u043e\u0432\u0438\u0441\u044c\u043a\u0430"
    ],
    "wof:name":"Grochowiska",
    "wof:placetype":"locality"
},
  "geometry": {"coordinates":[16.82917,50.55445],"type":"Point"}
}