{
  "type": "Feature",
  "properties": {
    "gn:admin1_code":"82.0",
    "gn:admin2_code":"2207.0",
    "gn:admin3_code":"220703.0",
    "gn:asciiname":"Nowy Dwor",
    "gn:country_code":"PL",
    "gn:dem":11,
    "gn:feature_class":"P",
    "gn:feature_code":"PPL",
    "gn:name":"Nowy Dw\u00f3r",
    "gn:population":0,
    "gn:timezone":"Europe/Warsaw",
    "iso:country":"PL",
    "name:und_x_variant":[
        "Neuh\u00f6fen",
        "Nowy Dw\u00f3r"
    ],
    "wof:name":"Nowy Dwor",
    "wof:placetype":"locality"
},
  "geometry": {"coordinates":[18.86964,53.71895],"type":"Point"}
}