{
  "type": "Feature",
  "properties": {
    "gn:admin1_code":"75.0",
    "gn:admin2_code":"604.0",
    "gn:admin3_code":"60404.0",
    "gn:asciiname":"Bialoskory",
    "gn:country_code":"PL",
    "gn:dem":206,
    "gn:feature_class":"P",
    "gn:feature_code":"PPL",
    "gn:name":"Bia\u0142osk\u00f3ry",
    "gn:population":0,
    "gn:timezone":"Europe/Warsaw",
    "iso:country":"PL",
    "name:fra_x_preferred":[
        "Bia\u0142osk\u00f3ry"
    ],
    "name:pol_x_preferred":[
        "Bia\u0142osk\u00f3ry"
    ],
    "name:ukr_x_preferred":[
        "\u0411\u044f\u043b\u043e\u0441\u043a\u0443\u0440\u0438"
    ],
    "name:und_x_variant":[
        "Bia\u0142osk\u00f3ry"
    ],
    "wof:name":"Bialoskory",
    "wof:placetype":"locality"
},
  "geometry": {"coordinates":[23.91096,50.91221],"type":"Point"}
}