{
  "type": "Feature",
  "properties": {
    "gn:admin1_code":"84.0",
    "gn:admin2_code":"2601.0",
    "gn:admin3_code":"260106.0",
    "gn:asciiname":"Jastrzebiec",
    "gn:country_code":"PL",
    "gn:dem":186,
    "gn:feature_class":"P",
    "gn:feature_code":"PPL",
    "gn:name":"Jastrz\u0119biec",
    "gn:population":0,
    "gn:timezone":"Europe/Warsaw",
    "iso:country":"PL",
    "wof:name":"Jastrzebiec",
    "wof:placetype":"locality"
},
  "geometry": {"coordinates":[20.94097,50.49039000000001],"type":"Point"}
}