{
  "type": "Feature",
  "properties": {
    "gn:admin1_code":"84.0",
    "gn:admin2_code":"2601.0",
    "gn:admin3_code":"260106.0",
    "gn:asciiname":"Jastrzebiec",
    "gn:country_code":"PL",
    "gn:dem":186,
    "gn:feature_class":"P",
    "gn:feature_code":"PPL",
    "gn:name":"Jastrz\u0119biec",
    "gn:population":0,
    "gn:timezone":"Europe/Warsaw",
    "iso:country":"PL",
    "name:ceb_x_preferred":[
        "Jastrz\u0119biec"
    ],
    "name:pol_x_preferred":[
        "Jastrz\u0119biec"
    ],
    "name:ukr_x_preferred":[
        "\u042f\u0441\u0442\u0448\u0435\u043c\u0431\u0435\u0446\u044c"
    ],
    "name:urd_x_preferred":[
        "\u062c\u0633\u062a\u0631\u0632\u06cc\u0628\u06cc\u06a9"
    ],
    "wof:name":"Jastrzebiec",
    "wof:placetype":"locality"
},
  "geometry": {"coordinates":[20.94097,50.49039000000001],"type":"Point"}
}