{
  "type": "Feature",
  "properties": {
    "gn:admin1_code":"74.0",
    "gn:admin2_code":"1019.0",
    "gn:admin3_code":"101903.0",
    "gn:asciiname":"Stronsko",
    "gn:country_code":"PL",
    "gn:dem":159,
    "gn:feature_class":"P",
    "gn:feature_code":"PPL",
    "gn:name":"Stro\u0144sko",
    "gn:population":0,
    "gn:timezone":"Europe/Warsaw",
    "iso:country":"PL",
    "name:pol_x_preferred":[
        "Stro\u0144sko"
    ],
    "name:ukr_x_preferred":[
        "\u0421\u0442\u0440\u043e\u043d\u0441\u044c\u043a\u043e"
    ],
    "wof:name":"Stronsko",
    "wof:placetype":"locality"
},
  "geometry": {"coordinates":[18.85649,51.54762],"type":"Point"}
}