{
  "type": "Feature",
  "properties": {
    "gn:admin1_code":"82.0",
    "gn:admin2_code":"2214.0",
    "gn:admin3_code":"221405.0",
    "gn:asciiname":"Wielglowy",
    "gn:country_code":"PL",
    "gn:dem":39,
    "gn:feature_class":"P",
    "gn:feature_code":"PPL",
    "gn:name":"Wielg\u0142owy",
    "gn:population":0,
    "gn:timezone":"Europe/Warsaw",
    "iso:country":"PL",
    "name:ceb_x_preferred":[
        "Wielg\u0142owy"
    ],
    "name:pol_x_preferred":[
        "Wielg\u0142owy"
    ],
    "name:ukr_x_preferred":[
        "\u0412\u0435\u043b\u044c\u0491\u043b\u043e\u0432\u0438"
    ],
    "wof:name":"Wielglowy",
    "wof:placetype":"locality"
},
  "geometry": {"coordinates":[18.74755,54.02052],"type":"Point"}
}