{
  "type": "Feature",
  "properties": {
    "gn:admin1_code":"81.0",
    "gn:admin2_code":"2008.0",
    "gn:admin3_code":"200801.0",
    "gn:asciiname":"Guzy",
    "gn:country_code":"PL",
    "gn:dem":129,
    "gn:feature_class":"P",
    "gn:feature_code":"PPL",
    "gn:name":"Guzy",
    "gn:population":0,
    "gn:timezone":"Europe/Warsaw",
    "iso:country":"PL",
    "name:deu_x_preferred":[
        "Guzy"
    ],
    "name:fra_x_preferred":[
        "Guzy"
    ],
    "name:nld_x_preferred":[
        "Guzy"
    ],
    "name:pol_x_preferred":[
        "Guzy"
    ],
    "name:ukr_x_preferred":[
        "\u0490\u0443\u0437\u0438"
    ],
    "wof:name":"Guzy",
    "wof:placetype":"locality"
},
  "geometry": {"coordinates":[22.75,53.48333],"type":"Point"}
}