{
  "type": "Feature",
  "properties": {
    "gn:admin1_code":"86.0",
    "gn:admin2_code":"3007.0",
    "gn:admin3_code":"300707.0",
    "gn:asciiname":"Annowka",
    "gn:country_code":"PL",
    "gn:dem":117,
    "gn:feature_class":"P",
    "gn:feature_code":"PPL",
    "gn:name":"Annowka",
    "gn:population":0,
    "gn:timezone":"Europe/Warsaw",
    "iso:country":"PL",
    "name:pol_x_preferred":[
        "Ann\u00f3wka"
    ],
    "name:ukr_x_preferred":[
        "\u0410\u043d\u043d\u0443\u0432\u043a\u0430"
    ],
    "wof:name":"Annowka",
    "wof:placetype":"locality"
},
  "geometry": {"coordinates":[18.22791,51.99295],"type":"Point"}
}