{
  "type": "Feature",
  "properties": {
    "gn:admin1_code":"74.0",
    "gn:admin2_code":"1016.0",
    "gn:admin3_code":"101607.0",
    "gn:asciiname":"Jankowek",
    "gn:country_code":"PL",
    "gn:dem":204,
    "gn:feature_class":"P",
    "gn:feature_code":"PPL",
    "gn:name":"Jank\u00f3wek",
    "gn:population":0,
    "gn:timezone":"Europe/Warsaw",
    "iso:country":"PL",
    "wof:name":"Jankowek",
    "wof:placetype":"locality"
},
  "geometry": {"coordinates":[19.82445,51.66165],"type":"Point"}
}