{
  "type": "Feature",
  "properties": {
    "gn:admin1_code":"86.0",
    "gn:admin2_code":"3024.0",
    "gn:admin3_code":"302408.0",
    "gn:asciiname":"Chojno",
    "gn:country_code":"PL",
    "gn:dem":45,
    "gn:feature_class":"P",
    "gn:feature_code":"PPL",
    "gn:name":"Chojno",
    "gn:population":0,
    "gn:timezone":"Europe/Warsaw",
    "iso:country":"PL",
    "wof:name":"Chojno",
    "wof:placetype":"locality"
},
  "geometry": {"coordinates":[16.21229,52.69924],"type":"Point"}
}