{
  "type": "Feature",
  "properties": {
    "gn:admin1_code":"86.0",
    "gn:admin2_code":"3024.0",
    "gn:admin3_code":"302408.0",
    "gn:asciiname":"Chojno",
    "gn:country_code":"PL",
    "gn:dem":45,
    "gn:feature_class":"P",
    "gn:feature_code":"PPL",
    "gn:name":"Chojno",
    "gn:population":0,
    "gn:timezone":"Europe/Warsaw",
    "iso:country":"PL",
    "name:azb_x_preferred":[
        "\u062e\u0648\u06cc\u0646\u0648"
    ],
    "name:ceb_x_preferred":[
        "Chojno"
    ],
    "name:fas_x_preferred":[
        "\u062e\u0648\u06cc\u0646\u0648"
    ],
    "name:fra_x_preferred":[
        "Chojno"
    ],
    "name:nld_x_preferred":[
        "Chojno"
    ],
    "name:pol_x_preferred":[
        "Chojno-Wie\u015b"
    ],
    "name:ukr_x_preferred":[
        "\u0425\u043e\u0439\u043d\u043e-\u0412\u0435\u0441\u044c"
    ],
    "wof:name":"Chojno",
    "wof:placetype":"locality"
},
  "geometry": {"coordinates":[16.21229,52.69924],"type":"Point"}
}