{
  "type": "Feature",
  "properties": {
    "gn:admin1_code":"78.0",
    "gn:admin2_code":"1436.0",
    "gn:admin3_code":"143604.0",
    "gn:asciiname":"Rawica Stara",
    "gn:country_code":"PL",
    "gn:dem":169,
    "gn:feature_class":"P",
    "gn:feature_code":"PPL",
    "gn:name":"Rawica Stara",
    "gn:population":0,
    "gn:timezone":"Europe/Warsaw",
    "iso:country":"PL",
    "name:ceb_x_preferred":[
        "Rawica Stara"
    ],
    "name:fra_x_preferred":[
        "Rawica Stara"
    ],
    "name:pol_x_preferred":[
        "Rawica Stara"
    ],
    "name:ukr_x_preferred":[
        "\u0420\u0430\u0432\u0438\u0446\u044f-\u0421\u0442\u0430\u0440\u0430"
    ],
    "wof:name":"Rawica Stara",
    "wof:placetype":"locality"
},
  "geometry": {"coordinates":[21.39021,51.32224],"type":"Point"}
}