{
  "type": "Feature",
  "properties": {
    "gn:admin1_code":"75.0",
    "gn:admin2_code":"613.0",
    "gn:admin3_code":"61301.0",
    "gn:asciiname":"Pachole",
    "gn:country_code":"PL",
    "gn:dem":154,
    "gn:feature_class":"P",
    "gn:feature_code":"PPL",
    "gn:name":"Pachole",
    "gn:population":0,
    "gn:timezone":"Europe/Warsaw",
    "iso:country":"PL",
    "name:fra_x_preferred":[
        "Pachole"
    ],
    "name:lit_x_preferred":[
        "Pachol\u0117"
    ],
    "name:pol_x_preferred":[
        "Pachole"
    ],
    "name:ukr_x_preferred":[
        "\u041f\u0430\u0445\u043e\u043b\u0435"
    ],
    "wof:name":"Pachole",
    "wof:placetype":"locality"
},
  "geometry": {"coordinates":[23.12251,51.63223],"type":"Point"}
}