{
  "type": "Feature",
  "properties": {
    "gn:admin1_code":"87.0",
    "gn:admin2_code":"3203.0",
    "gn:admin3_code":"320304.0",
    "gn:asciiname":"Szczytniki",
    "gn:country_code":"PL",
    "gn:dem":141,
    "gn:feature_class":"P",
    "gn:feature_code":"PPL",
    "gn:name":"Szczytniki",
    "gn:population":0,
    "gn:timezone":"Europe/Warsaw",
    "iso:country":"PL",
    "name:fra_x_preferred":[
        "Szczytniki"
    ],
    "name:pol_x_preferred":[
        "Szczytniki"
    ],
    "name:rus_x_preferred":[
        "\u0429\u0438\u0442\u043d\u0438\u043a\u0438"
    ],
    "name:ukr_x_preferred":[
        "\u0429\u0438\u0442\u043d\u0438\u043a\u0438"
    ],
    "wof:name":"Szczytniki",
    "wof:placetype":"locality"
},
  "geometry": {"coordinates":[15.99338,53.66092],"type":"Point"}
}