{
  "type": "Feature",
  "properties": {
    "gn:gn_country":"PL",
    "gn:gn_fcode":"PPL",
    "gn:gn_pop":265,
    "gn:population":265,
    "iso:country":"PL",
    "name:eng_x_preferred":[
        "\u0141obozew G\u00f3rny"
    ],
    "name:fre_x_preferred":[
        "\u0141obozew G\u00f3rny"
    ],
    "name:hun_x_preferred":[
        "\u0141obozew G\u00f3rny"
    ],
    "name:per_x_preferred":[
        "\u0648\u0648\u0628\u0648\u0632\u0641 \u06af\u0648\u0631\u0646\u0647"
    ],
    "name:pol_x_preferred":[
        "\u0141obozew G\u00f3rny"
    ],
    "name:ukr_x_preferred":[
        "\u041b\u043e\u0431\u0456\u0437\u0432\u0430"
    ],
    "qs_pg:aaroncc":"PL",
    "qs_pg:gn_country":"PL",
    "qs_pg:gn_fcode":"PPL",
    "qs_pg:gn_pop":265,
    "qs_pg:name":"\u0141obozew G\u00f3rny",
    "qs_pg:name_adm0":"Polska",
    "qs_pg:name_adm1":"Podkarpackie",
    "qs_pg:photos_9k":1,
    "qs_pg:photos_9r":1,
    "qs_pg:photos_all":14,
    "qs_pg:photos_sr":0,
    "qs_pg:pop_sr":2,
    "qs_pg:qs_pg_placetype":"locality",
    "qs_pg:qs_pg_placetype_gp":"Town",
    "qs_pg:woe_adm0":23424923,
    "woe:adm0_id":23424923,
    "woe:name_adm0":"Polska",
    "woe:name_adm1":"Podkarpackie",
    "woe:placetype":"Town",
    "wof:name":"\u0141obozew G\u00f3rny",
    "wof:placetype":"locality",
    "wof:population":265
},
  "geometry": {"coordinates":[22.52824,49.39785],"type":"Point"}
}