{
  "type": "Feature",
  "properties": {
    "gn:country":"PL",
    "gn:fcode":"PPL",
    "gn:population":1200,
    "iso:country":"PL",
    "name:ast_x_preferred":[
        "Pawlikowice"
    ],
    "name:ces_x_preferred":[
        "Pawlikowice"
    ],
    "name:che_x_preferred":[
        "\u041f\u0430\u0432\u043b\u0438\u043a\u043e\u0432\u0438\u0446\u0435"
    ],
    "name:deu_x_preferred":[
        "Pawlikowice"
    ],
    "name:eng_x_preferred":[
        "Pawlikowice"
    ],
    "name:fra_x_preferred":[
        "Pawlikowice"
    ],
    "name:nan_x_preferred":[
        "Pawlikowice"
    ],
    "name:pol_x_preferred":[
        "Pawlikowice"
    ],
    "name:tat_x_preferred":[
        "\u041f\u0430\u0432\u043b\u0438\u043a\u043e\u0432\u0438\u0446\u0435"
    ],
    "name:ukr_x_preferred":[
        "\u041f\u0430\u0432\u043b\u0456\u043a\u043e\u0432\u0456\u0446\u0435"
    ],
    "qs_pg:aaroncc":"PL",
    "qs_pg:gn_country":"PL",
    "qs_pg:gn_fcode":"PPL",
    "qs_pg:gn_pop":1200,
    "qs_pg:name":"Pawlikowice",
    "qs_pg:name_adm0":"Polska",
    "qs_pg:name_adm1":"Ma\u0142opolskie",
    "qs_pg:photos_9r":0,
    "qs_pg:photos_sr":0,
    "qs_pg:pop_sr":3,
    "qs_pg:qs_pg_placetype":"locality",
    "qs_pg:qs_pg_placetype_gp":"Town",
    "qs_pg:woe_adm0":23424923,
    "woe:adm0_id":23424923,
    "woe:name_adm0":"Polska",
    "woe:name_adm1":"Ma\u0142opolskie",
    "woe:placetype":"Town",
    "wof:name":"Pawlikowice",
    "wof:placetype":"locality",
    "wof:population":1200
},
  "geometry": {"coordinates":[20.05486,49.9531],"type":"Point"}
}