{
  "type": "Feature",
  "properties": {
    "gn:admin1_code":"75.0",
    "gn:admin2_code":"606.0",
    "gn:admin3_code":"60609.0",
    "gn:asciiname":"Mosciska",
    "gn:country_code":"PL",
    "gn:dem":216,
    "gn:feature_class":"P",
    "gn:feature_code":"PPL",
    "gn:name":"Mo\u015bciska",
    "gn:population":0,
    "gn:timezone":"Europe/Warsaw",
    "iso:country":"PL",
    "wof:name":"Mosciska",
    "wof:placetype":"locality"
},
  "geometry": {"coordinates":[22.94226,50.85642],"type":"Point"}
}