{
  "type": "Feature",
  "properties": {
    "gn:admin1_code":"79.0",
    "gn:admin2_code":"1606.0",
    "gn:admin3_code":"160605.0",
    "gn:asciiname":"Mlokicie",
    "gn:cc2":"PL",
    "gn:country_code":"PL",
    "gn:dem":145,
    "gn:feature_class":"P",
    "gn:feature_code":"PPL",
    "gn:name":"M\u0142okicie",
    "gn:population":0,
    "gn:timezone":"Europe/Warsaw",
    "iso:country":"PL",
    "name:pol_x_preferred":[
        "M\u0142okicie"
    ],
    "name:ukr_x_preferred":[
        "\u041c\u043b\u043e\u043a\u0456\u0446\u0435"
    ],
    "name:und_x_variant":[
        "Weidenbach"
    ],
    "wof:name":"Mlokicie",
    "wof:placetype":"locality"
},
  "geometry": {"coordinates":[17.58585,51.10104000000001],"type":"Point"}
}