{
  "type": "Feature",
  "properties": {
    "gn:admin1_code":"77.0",
    "gn:admin2_code":"1214.0",
    "gn:admin3_code":"121405.0",
    "gn:asciiname":"Stagniowice",
    "gn:country_code":"PL",
    "gn:dem":205,
    "gn:feature_class":"P",
    "gn:feature_code":"PPL",
    "gn:name":"Stagniowice",
    "gn:population":0,
    "gn:timezone":"Europe/Warsaw",
    "iso:country":"PL",
    "name:pol_x_preferred":[
        "Stogniowice"
    ],
    "name:ukr_x_preferred":[
        "\u0421\u0442\u043e\u0491\u043d\u044c\u043e\u0432\u0456\u0446\u0435"
    ],
    "name:und_x_variant":[
        "Stogniowice",
        "Stagniowice"
    ],
    "wof:name":"Stagniowice",
    "wof:placetype":"locality"
},
  "geometry": {"coordinates":[20.34193,50.19317],"type":"Point"}
}