{
  "type": "Feature",
  "properties": {
    "gn:admin1_code":"86.0",
    "gn:admin2_code":"3019.0",
    "gn:admin3_code":"301904.0",
    "gn:asciiname":"Trzebon",
    "gn:country_code":"PL",
    "gn:dem":107,
    "gn:feature_class":"P",
    "gn:feature_code":"PPL",
    "gn:name":"Trzebo\u0144",
    "gn:population":0,
    "gn:timezone":"Europe/Warsaw",
    "iso:country":"PL",
    "name:azb_x_preferred":[
        "\u0686\u0628\u0648\u0646"
    ],
    "name:ceb_x_preferred":[
        "Trzebo\u0144"
    ],
    "name:fas_x_preferred":[
        "\u0686\u0628\u0648\u0646"
    ],
    "name:fra_x_preferred":[
        "Trzebo\u0144"
    ],
    "name:pol_x_preferred":[
        "Trzebo\u0144"
    ],
    "name:ukr_x_preferred":[
        "\u0422\u0448\u0435\u0431\u043e\u043d\u044c"
    ],
    "wof:name":"Trzebon",
    "wof:placetype":"locality"
},
  "geometry": {"coordinates":[17.28679,53.24679],"type":"Point"}
}