{
  "type": "Feature",
  "properties": {
    "gn:admin1_code":"86.0",
    "gn:admin2_code":"3016.0",
    "gn:admin3_code":"301601.0",
    "gn:asciiname":"Bablinek",
    "gn:country_code":"PL",
    "gn:dem":60,
    "gn:feature_class":"P",
    "gn:feature_code":"PPL",
    "gn:name":"B\u0105blinek",
    "gn:population":0,
    "gn:timezone":"Europe/Warsaw",
    "iso:country":"PL",
    "name:ceb_x_preferred":[
        "B\u0105blinek"
    ],
    "name:fra_x_preferred":[
        "B\u0105blinek"
    ],
    "name:pol_x_preferred":[
        "B\u0105blinek"
    ],
    "name:ukr_x_preferred":[
        "\u0411\u043e\u043c\u0431\u043b\u0456\u043d\u0435\u043a"
    ],
    "wof:name":"Bablinek",
    "wof:placetype":"locality"
},
  "geometry": {"coordinates":[16.69572,52.68571],"type":"Point"}
}