{
  "type": "Feature",
  "properties": {
    "gn:admin1_code":"82.0",
    "gn:admin2_code":"2210.0",
    "gn:admin3_code":"221003.0",
    "gn:asciiname":"Gniazdowo",
    "gn:country_code":"PL",
    "gn:dem":1,
    "gn:feature_class":"P",
    "gn:feature_code":"PPL",
    "gn:name":"Gniazdowo",
    "gn:population":0,
    "gn:timezone":"Europe/Warsaw",
    "iso:country":"PL",
    "name:ceb_x_preferred":[
        "Gniazdowo"
    ],
    "name:pol_x_preferred":[
        "Gniazdowo"
    ],
    "name:ukr_x_preferred":[
        "\u0490\u043d\u044f\u0437\u0434\u043e\u0432\u043e"
    ],
    "name:und_x_variant":[
        "Sch\u00f6nhorst"
    ],
    "wof:name":"Gniazdowo",
    "wof:placetype":"locality"
},
  "geometry": {"coordinates":[18.92857,54.19448000000001],"type":"Point"}
}