{
  "type": "Feature",
  "properties": {
    "iso:country":"PL",
    "name:pol_x_preferred":[
        "Jakuszyce"
    ],
    "qs:gn_adm0_cc":"PL",
    "qs:gn_fcode":"PPL",
    "qs:gn_local":3083677,
    "qs:gn_nam_loc":"szklarska poreba",
    "qs:gn_namadm1":"72",
    "qs:gn_name":"Jakuszyce",
    "qs:local_max":620,
    "qs:local_sum":620,
    "qs:localhoods":1,
    "qs:name":"Jakuszyce",
    "qs:name_adm0":"Polska",
    "qs:name_adm1":"Dolnosl\u0105skie",
    "qs:name_adm2":"Jeleniog\u00f3rski",
    "qs:name_lau":"Szklarska Por\u0119ba",
    "qs:name_local":"Szklarska Por\u0119ba",
    "qs:photo_max":114,
    "qs:photo_sum":620,
    "qs:placetype":"Suburb",
    "qs:quad_count":87,
    "qs:woe_adm0":23424923,
    "qs:woe_adm1":12577935,
    "qs:woe_adm2":12591141,
    "qs:woe_lau":12618889,
    "qs:woe_local":521861,
    "qs:woe_ver":"7.10.0",
    "wof:lang":[
        "pol"
    ],
    "wof:name":"Jakuszyce",
    "wof:placetype":"neighbourhood"
},
  "geometry": {"coordinates":[15.394581,50.816894],"type":"Point"}
}