{
  "type": "Feature",
  "properties": {
    "gn:admin1_code":"80.0",
    "gn:admin2_code":"1862.0",
    "gn:admin3_code":"186201.0",
    "gn:asciiname":"Kruhel Maly",
    "gn:country_code":"PL",
    "gn:dem":246,
    "gn:feature_class":"P",
    "gn:feature_code":"PPL",
    "gn:name":"Kruhel Ma\u0142y",
    "gn:population":0,
    "gn:timezone":"Europe/Warsaw",
    "iso:country":"PL",
    "wof:name":"Kruhel Maly",
    "wof:placetype":"locality"
},
  "geometry": {"coordinates":[22.74007000000001,49.77195],"type":"Point"}
}