{
  "type": "Feature",
  "properties": {
    "gn:gn_country":"PL",
    "gn:gn_fcode":"PPL",
    "gn:gn_pop":777,
    "gn:population":777,
    "iso:country":"PL",
    "name:eng_x_preferred":[
        "Wierzchowisko"
    ],
    "name:fra_x_preferred":[
        "Wierzchowisko"
    ],
    "name:pol_x_preferred":[
        "Wierzchowisko"
    ],
    "name:unk_x_variant":[
        "Wierzchowiska"
    ],
    "qs_pg:aaroncc":"PL",
    "qs_pg:gn_country":"PL",
    "qs_pg:gn_fcode":"PPL",
    "qs_pg:gn_pop":777,
    "qs_pg:name":"Wierzchowisko",
    "qs_pg:name_adm0":"Polska",
    "qs_pg:name_adm1":"Ma\u0142opolskie",
    "qs_pg:photos_9r":0,
    "qs_pg:photos_sr":0,
    "qs_pg:pop_sr":2,
    "qs_pg:qs_pg_placetype":"locality",
    "qs_pg:qs_pg_placetype_gp":"Town",
    "qs_pg:woe_adm0":23424923,
    "woe:adm0_id":23424923,
    "woe:name_adm0":"Polska",
    "woe:name_adm1":"Ma\u0142opolskie",
    "woe:placetype":"Town",
    "wof:name":"Wierzchowisko",
    "wof:placetype":"locality",
    "wof:population":777
},
  "geometry": {"coordinates":[19.81522,50.37514],"type":"Point"}
}