{
  "type": "Feature",
  "properties": {
    "gn:admin1_code":"73.0",
    "gn:admin2_code":"406.0",
    "gn:admin3_code":"40604.0",
    "gn:asciiname":"Zielnowo",
    "gn:country_code":"PL",
    "gn:dem":105,
    "gn:feature_class":"P",
    "gn:feature_code":"PPL",
    "gn:name":"Zielnowo",
    "gn:population":0,
    "gn:timezone":"Europe/Warsaw",
    "iso:country":"PL",
    "name:pol_x_preferred":[
        "Zielnowo"
    ],
    "name:ukr_x_preferred":[
        "\u0417\u0435\u043b\u044c\u043d\u043e\u0432\u043e"
    ],
    "wof:name":"Zielnowo",
    "wof:placetype":"locality"
},
  "geometry": {"coordinates":[18.86744,53.37726],"type":"Point"}
}