{
  "type": "Feature",
  "properties": {
    "gn:admin1_code":"73.0",
    "gn:admin2_code":"407.0",
    "gn:admin3_code":"40704.0",
    "gn:asciiname":"Lojewo",
    "gn:country_code":"PL",
    "gn:dem":83,
    "gn:feature_class":"P",
    "gn:feature_code":"PPL",
    "gn:name":"\u0141ojewo",
    "gn:population":0,
    "gn:timezone":"Europe/Warsaw",
    "iso:country":"PL",
    "name:nld_x_preferred":[
        "\u0141ojewo"
    ],
    "name:pol_x_preferred":[
        "\u0141ojewo"
    ],
    "name:ukr_x_preferred":[
        "\u041b\u043e\u0454\u0432\u043e"
    ],
    "wof:name":"Lojewo",
    "wof:placetype":"locality"
},
  "geometry": {"coordinates":[18.30981,52.73628000000001],"type":"Point"}
}