{
  "type": "Feature",
  "properties": {
    "gn:admin1_code":"82.0",
    "gn:admin2_code":"2203.0",
    "gn:admin3_code":"220303.0",
    "gn:asciiname":"Barkowo",
    "gn:cc2":"PL",
    "gn:country_code":"PL",
    "gn:dem":139,
    "gn:feature_class":"P",
    "gn:feature_code":"PPL",
    "gn:name":"Barkowo",
    "gn:population":0,
    "gn:timezone":"Europe/Warsaw",
    "iso:country":"PL",
    "name:ceb_x_preferred":[
        "Barkowo"
    ],
    "name:csb_x_preferred":[
        "Bark\u00f2w\u00f2"
    ],
    "name:pol_x_preferred":[
        "Barkowo"
    ],
    "name:ukr_x_preferred":[
        "\u0411\u0430\u0440\u043a\u043e\u0432\u043e"
    ],
    "name:und_x_variant":[
        "Barkenfelde"
    ],
    "wof:name":"Barkowo",
    "wof:placetype":"locality"
},
  "geometry": {"coordinates":[17.18605,53.61379],"type":"Point"}
}