{
  "type": "Feature",
  "properties": {
    "gn:admin1_code":"83.0",
    "gn:admin2_code":"2417.0",
    "gn:admin3_code":"241704.0",
    "gn:asciiname":"Sumery",
    "gn:country_code":"PL",
    "gn:dem":428,
    "gn:feature_class":"P",
    "gn:feature_code":"PPL",
    "gn:name":"Sumery",
    "gn:population":0,
    "gn:timezone":"Europe/Warsaw",
    "iso:country":"PL",
    "wof:name":"Sumery",
    "wof:placetype":"locality"
},
  "geometry": {"coordinates":[19.31667,49.65],"type":"Point"}
}