{
  "type": "Feature",
  "properties": {
    "gn:admin1_code":"86.0",
    "gn:admin2_code":"3003.0",
    "gn:admin3_code":"300306.0",
    "gn:asciiname":"Moraczewo",
    "gn:country_code":"PL",
    "gn:dem":113,
    "gn:feature_class":"P",
    "gn:feature_code":"PPL",
    "gn:name":"Moraczewo",
    "gn:population":0,
    "gn:timezone":"Europe/Warsaw",
    "iso:country":"PL",
    "name:azb_x_preferred":[
        "\u0645\u0648\u0631\u0627\u0686\u0648\u0648"
    ],
    "name:fas_x_preferred":[
        "\u0645\u0648\u0631\u0627\u0686\u0648\u0648"
    ],
    "name:fra_x_preferred":[
        "Moraczewo"
    ],
    "name:pol_x_preferred":[
        "Moraczewo"
    ],
    "name:ukr_x_preferred":[
        "\u041c\u043e\u0440\u0430\u0447\u0435\u0432\u043e"
    ],
    "wof:name":"Moraczewo",
    "wof:placetype":"locality"
},
  "geometry": {"coordinates":[17.33883,52.50504],"type":"Point"}
}