{
  "type": "Feature",
  "properties": {
    "gn:admin1_code":"86.0",
    "gn:admin2_code":"3021.0",
    "gn:admin3_code":"302111.0",
    "gn:asciiname":"Uchorowo",
    "gn:country_code":"PL",
    "gn:dem":95,
    "gn:feature_class":"P",
    "gn:feature_code":"PPL",
    "gn:name":"Uchorowo",
    "gn:population":0,
    "gn:timezone":"Europe/Warsaw",
    "iso:country":"PL",
    "wof:name":"Uchorowo",
    "wof:placetype":"locality"
},
  "geometry": {"coordinates":[16.94693,52.63723],"type":"Point"}
}