{
  "type": "Feature",
  "properties": {
    "gn:admin1_code":"86.0",
    "gn:admin2_code":"3021.0",
    "gn:admin3_code":"302111.0",
    "gn:asciiname":"Uchorowo",
    "gn:country_code":"PL",
    "gn:dem":95,
    "gn:feature_class":"P",
    "gn:feature_code":"PPL",
    "gn:name":"Uchorowo",
    "gn:population":0,
    "gn:timezone":"Europe/Warsaw",
    "iso:country":"PL",
    "name:azb_x_preferred":[
        "\u06cc\u0648\u0686\u0631\u0648\u0648"
    ],
    "name:ceb_x_preferred":[
        "Uchorowo"
    ],
    "name:fas_x_preferred":[
        "\u06cc\u0648\u0686\u0631\u0648\u0648"
    ],
    "name:fra_x_preferred":[
        "Uchorowo"
    ],
    "name:ita_x_preferred":[
        "Uchorowo"
    ],
    "name:pol_x_preferred":[
        "Uchorowo"
    ],
    "name:ukr_x_preferred":[
        "\u0423\u0445\u043e\u0440\u043e\u0432\u043e"
    ],
    "name:urd_x_preferred":[
        "\u0627\u0686\u0648\u0631\u0648\u0648"
    ],
    "wof:name":"Uchorowo",
    "wof:placetype":"locality"
},
  "geometry": {"coordinates":[16.94693,52.63723],"type":"Point"}
}