{
  "type": "Feature",
  "properties": {
    "gn:admin1_code":"75.0",
    "gn:admin2_code":"663.0",
    "gn:admin3_code":"66301.0",
    "gn:asciiname":"Konstantynow",
    "gn:country_code":"PL",
    "gn:dem":225,
    "gn:feature_class":"P",
    "gn:feature_code":"PPL",
    "gn:name":"Konstantyn\u00f3w",
    "gn:population":0,
    "gn:timezone":"Europe/Warsaw",
    "iso:country":"PL",
    "wof:name":"Konstantynow",
    "wof:placetype":"locality"
},
  "geometry": {"coordinates":[22.50069,51.24404000000001],"type":"Point"}
}