{
  "type": "Feature",
  "properties": {
    "gn:admin1_code":"72.0",
    "gn:admin2_code":"217.0",
    "gn:admin3_code":"21704.0",
    "gn:asciiname":"Piotrowice",
    "gn:country_code":"PL",
    "gn:dem":160,
    "gn:feature_class":"P",
    "gn:feature_code":"PPL",
    "gn:name":"Piotrowice",
    "gn:population":0,
    "gn:timezone":"Europe/Warsaw",
    "iso:country":"PL",
    "name:pol_x_preferred":[
        "Piotrowice"
    ],
    "name:ukr_x_preferred":[
        "\u041f\u0439\u043e\u0442\u0440\u043e\u0432\u0456\u0446\u0435"
    ],
    "wof:name":"Piotrowice",
    "wof:placetype":"locality"
},
  "geometry": {"coordinates":[17.00666,50.79074],"type":"Point"}
}