{
  "type": "Feature",
  "properties": {
    "gn:admin1_code":"83.0",
    "gn:admin2_code":"2416.0",
    "gn:admin3_code":"241610.0",
    "gn:asciiname":"Koryczany",
    "gn:country_code":"PL",
    "gn:dem":319,
    "gn:feature_class":"P",
    "gn:feature_code":"PPL",
    "gn:name":"Koryczany",
    "gn:population":0,
    "gn:timezone":"Europe/Warsaw",
    "iso:country":"PL",
    "name:pol_x_preferred":[
        "Koryczany"
    ],
    "name:ukr_x_preferred":[
        "\u041a\u043e\u0440\u0438\u0447\u0430\u043d\u0438"
    ],
    "wof:name":"Koryczany",
    "wof:placetype":"locality"
},
  "geometry": {"coordinates":[19.93435,50.49017],"type":"Point"}
}