{
  "type": "Feature",
  "properties": {
    "gn:admin1_code":"72.0",
    "gn:admin2_code":"215.0",
    "gn:admin3_code":"21502.0",
    "gn:asciiname":"Kuny",
    "gn:country_code":"PL",
    "gn:dem":147,
    "gn:feature_class":"P",
    "gn:feature_code":"PPL",
    "gn:name":"Kuny",
    "gn:population":0,
    "gn:timezone":"Europe/Warsaw",
    "iso:country":"PL",
    "name:pol_x_preferred":[
        "Kuny"
    ],
    "wof:name":"Kuny",
    "wof:placetype":"locality"
},
  "geometry": {"coordinates":[17.18804,50.90286],"type":"Point"}
}