{
  "type": "Feature",
  "properties": {
    "gn:admin1_code":"86.0",
    "gn:admin2_code":"3021.0",
    "gn:admin3_code":"302116.0",
    "gn:asciiname":"Wierzonka",
    "gn:country_code":"PL",
    "gn:dem":90,
    "gn:feature_class":"P",
    "gn:feature_code":"PPL",
    "gn:name":"Wierzonka",
    "gn:population":0,
    "gn:timezone":"Europe/Warsaw",
    "iso:country":"PL",
    "name:ceb_x_preferred":[
        "Wierzonka"
    ],
    "name:fra_x_preferred":[
        "Wierzonka"
    ],
    "name:pol_x_preferred":[
        "Wierzonka"
    ],
    "name:ukr_x_preferred":[
        "\u0412\u0435\u0436\u043e\u043d\u043a\u0430"
    ],
    "wof:name":"Wierzonka",
    "wof:placetype":"locality"
},
  "geometry": {"coordinates":[17.09679,52.47809],"type":"Point"}
}