{
  "type": "Feature",
  "properties": {
    "gn:admin1_code":"84.0",
    "gn:admin2_code":"2602.0",
    "gn:admin3_code":"260206.0",
    "gn:asciiname":"Gniewiecin",
    "gn:country_code":"PL",
    "gn:dem":277,
    "gn:feature_class":"P",
    "gn:feature_code":"PPL",
    "gn:name":"Gniewi\u0119cin",
    "gn:population":0,
    "gn:timezone":"Europe/Warsaw",
    "iso:country":"PL",
    "name:ceb_x_preferred":[
        "Gniewi\u0119cin"
    ],
    "name:nld_x_preferred":[
        "Gniewi\u0119cin"
    ],
    "name:pol_x_preferred":[
        "Gniewi\u0119cin"
    ],
    "name:ukr_x_preferred":[
        "\u0490\u043d\u0435\u0432\u0435\u043d\u0446\u0438\u043d"
    ],
    "name:und_x_variant":[
        "Gniewi\u0119cin"
    ],
    "wof:name":"Gniewiecin",
    "wof:placetype":"locality"
},
  "geometry": {"coordinates":[20.05835,50.53722],"type":"Point"}
}