{
  "type": "Feature",
  "properties": {
    "gn:admin1_code":"78.0",
    "gn:admin2_code":"1402.0",
    "gn:admin3_code":"140208.0",
    "gn:asciiname":"Zenbok",
    "gn:country_code":"PL",
    "gn:dem":140,
    "gn:feature_class":"P",
    "gn:feature_code":"PPL",
    "gn:name":"\u017be\u0144bok",
    "gn:population":0,
    "gn:timezone":"Europe/Warsaw",
    "iso:country":"PL",
    "name:fra_x_preferred":[
        "Ze\u0144bok"
    ],
    "name:pol_x_preferred":[
        "Ze\u0144bok"
    ],
    "name:ukr_x_preferred":[
        "\u0417\u0435\u043d\u044c\u0431\u043e\u043a"
    ],
    "wof:name":"Zenbok",
    "wof:placetype":"locality"
},
  "geometry": {"coordinates":[20.5846,52.9748],"type":"Point"}
}