{
  "type": "Feature",
  "properties": {
    "gn:admin1_code":"78.0",
    "gn:admin2_code":"1420.0",
    "gn:admin3_code":"142010.0",
    "gn:asciiname":"Koziebrody",
    "gn:country_code":"PL",
    "gn:dem":114,
    "gn:feature_class":"P",
    "gn:feature_code":"PPL",
    "gn:name":"Koziebrody",
    "gn:population":0,
    "gn:timezone":"Europe/Warsaw",
    "iso:country":"PL",
    "name:fra_x_preferred":[
        "Koziebrody"
    ],
    "name:pol_x_preferred":[
        "Koziebrody"
    ],
    "name:ukr_x_preferred":[
        "\u041a\u043e\u0437\u0435\u0431\u0440\u043e\u0434\u0438"
    ],
    "wof:name":"Koziebrody",
    "wof:placetype":"locality"
},
  "geometry": {"coordinates":[19.99231,52.80246999999999],"type":"Point"}
}