{
  "type": "Feature",
  "properties": {
    "gn:admin1_code":"73.0",
    "gn:admin2_code":"410.0",
    "gn:admin3_code":"41004.0",
    "gn:asciiname":"Anieliny",
    "gn:country_code":"PL",
    "gn:dem":58,
    "gn:feature_class":"P",
    "gn:feature_code":"PPL",
    "gn:name":"Anieliny",
    "gn:population":0,
    "gn:timezone":"Europe/Warsaw",
    "iso:country":"PL",
    "name:und_x_variant":[
        "Aniela",
        "Anieliny"
    ],
    "wof:name":"Anieliny",
    "wof:placetype":"locality"
},
  "geometry": {"coordinates":[17.49451,53.12921],"type":"Point"}
}