{
  "type": "Feature",
  "properties": {
    "gn:admin1_code":"73.0",
    "gn:admin2_code":"410.0",
    "gn:admin3_code":"41004.0",
    "gn:asciiname":"Anieliny",
    "gn:country_code":"PL",
    "gn:dem":58,
    "gn:feature_class":"P",
    "gn:feature_code":"PPL",
    "gn:name":"Anieliny",
    "gn:population":0,
    "gn:timezone":"Europe/Warsaw",
    "iso:country":"PL",
    "name:azb_x_preferred":[
        "\u0627\u0646\u0642\u0644\u06cc\u0646\u0647"
    ],
    "name:ceb_x_preferred":[
        "Anieliny"
    ],
    "name:fas_x_preferred":[
        "\u0627\u0646\u06af\u0644\u06cc\u0646\u0647"
    ],
    "name:ita_x_preferred":[
        "Anieliny"
    ],
    "name:nld_x_preferred":[
        "Anieliny"
    ],
    "name:pol_x_preferred":[
        "Anieliny"
    ],
    "name:srp_x_preferred":[
        "\u0410\u045a\u0435\u043b\u0438\u043d\u0438"
    ],
    "name:ukr_x_preferred":[
        "\u0410\u043d\u0435\u043b\u0456\u043d\u0438"
    ],
    "name:und_x_variant":[
        "Aniela"
    ],
    "wof:name":"Anieliny",
    "wof:placetype":"locality"
},
  "geometry": {"coordinates":[17.49451,53.12921],"type":"Point"}
}