{
  "type": "Feature",
  "properties": {
    "gn:admin1_code":"80.0",
    "gn:admin2_code":"1813.0",
    "gn:admin3_code":"181301.0",
    "gn:asciiname":"Chominskie",
    "gn:country_code":"PL",
    "gn:dem":416,
    "gn:feature_class":"P",
    "gn:feature_code":"PPL",
    "gn:name":"Chomi\u0144skie",
    "gn:population":0,
    "gn:timezone":"Europe/Warsaw",
    "iso:country":"PL",
    "wof:name":"Chominskie",
    "wof:placetype":"locality"
},
  "geometry": {"coordinates":[22.51455,49.68298],"type":"Point"}
}