{
  "type": "Feature",
  "properties": {
    "gn:admin1_code":"72.0",
    "gn:admin2_code":"217.0",
    "gn:admin3_code":"21705.0",
    "gn:asciiname":"Zborowice",
    "gn:country_code":"PL",
    "gn:dem":149,
    "gn:feature_class":"P",
    "gn:feature_code":"PPL",
    "gn:name":"Zborowice",
    "gn:population":0,
    "gn:timezone":"Europe/Warsaw",
    "iso:country":"PL",
    "name:pol_x_preferred":[
        "Zborowice"
    ],
    "name:ukr_x_preferred":[
        "\u0417\u0431\u043e\u0440\u043e\u0432\u0456\u0446\u0435"
    ],
    "wof:name":"Zborowice",
    "wof:placetype":"locality"
},
  "geometry": {"coordinates":[17.17524,50.80463],"type":"Point"}
}