{
  "type": "Feature",
  "properties": {
    "gn:admin1_code":"84.0",
    "gn:admin2_code":"2611.0",
    "gn:admin3_code":"261102.0",
    "gn:asciiname":"Polagiew",
    "gn:country_code":"PL",
    "gn:dem":194,
    "gn:feature_class":"P",
    "gn:feature_code":"PPL",
    "gn:name":"Po\u0142\u0105giew",
    "gn:population":0,
    "gn:timezone":"Europe/Warsaw",
    "iso:country":"PL",
    "name:ceb_x_preferred":[
        "Po\u0142\u0105giew"
    ],
    "name:pol_x_preferred":[
        "Po\u0142\u0105giew"
    ],
    "name:ukr_x_preferred":[
        "\u041f\u043e\u043b\u043e\u043d\u0491\u0435\u0432"
    ],
    "wof:name":"Polagiew",
    "wof:placetype":"locality"
},
  "geometry": {"coordinates":[21.23648,51.02191],"type":"Point"}
}