{
  "type": "Feature",
  "properties": {
    "gn:admin1_code":"83.0",
    "gn:admin2_code":"2406.0",
    "gn:admin3_code":"240606.0",
    "gn:asciiname":"Cyganka",
    "gn:country_code":"PL",
    "gn:dem":236,
    "gn:feature_class":"P",
    "gn:feature_code":"PPL",
    "gn:name":"Cyganka",
    "gn:population":0,
    "gn:timezone":"Europe/Warsaw",
    "iso:country":"PL",
    "wof:name":"Cyganka",
    "wof:placetype":"locality"
},
  "geometry": {"coordinates":[18.73632000000001,50.89364000000001],"type":"Point"}
}