{
  "type": "Feature",
  "properties": {
    "gn:admin1_code":"78.0",
    "gn:admin2_code":"1425.0",
    "gn:admin3_code":"142512.0",
    "gn:asciiname":"Jaroslawice",
    "gn:country_code":"PL",
    "gn:dem":163,
    "gn:feature_class":"P",
    "gn:feature_code":"PPL",
    "gn:name":"Jaros\u0142awice",
    "gn:population":0,
    "gn:timezone":"Europe/Warsaw",
    "iso:country":"PL",
    "name:und_x_variant":[
        "Jaros\u0142awice"
    ],
    "wof:name":"Jaroslawice",
    "wof:placetype":"locality"
},
  "geometry": {"coordinates":[20.92635,51.4207],"type":"Point"}
}