{
  "type": "Feature",
  "properties": {
    "gn:admin1_code":"86.0",
    "gn:admin2_code":"3031.0",
    "gn:admin3_code":"303103.0",
    "gn:asciiname":"Paruszka",
    "gn:country_code":"PL",
    "gn:dem":96,
    "gn:feature_class":"P",
    "gn:feature_code":"PPL",
    "gn:name":"Paruszka",
    "gn:population":0,
    "gn:timezone":"Europe/Warsaw",
    "iso:country":"PL",
    "name:ceb_x_preferred":[
        "Paruszka"
    ],
    "name:fra_x_preferred":[
        "Paruszka"
    ],
    "name:pol_x_preferred":[
        "Paruszka"
    ],
    "name:rus_x_preferred":[
        "\u041f\u0430\u0440\u0443\u0448\u043a\u0430"
    ],
    "name:ukr_x_preferred":[
        "\u041f\u0430\u0440\u0443\u0448\u043a\u0430"
    ],
    "wof:name":"Paruszka",
    "wof:placetype":"locality"
},
  "geometry": {"coordinates":[16.90332,53.26881],"type":"Point"}
}