{
  "type": "Feature",
  "properties": {
    "iso:country":"PL",
    "name:ceb_x_preferred":[
        "Olszanka"
    ],
    "name:deu_x_preferred":[
        "Olszanka"
    ],
    "name:fra_x_preferred":[
        "Olszanka"
    ],
    "name:hye_x_preferred":[
        "\u0555\u056c\u056b\u0577\u0561\u0576\u056f\u0561"
    ],
    "name:ita_x_preferred":[
        "Olszanka"
    ],
    "name:kaz_x_preferred":[
        "\u041e\u043b\u044c\u0448\u0430\u043d\u043a\u0430"
    ],
    "name:lit_x_preferred":[
        "Ol\u0161anka"
    ],
    "name:nld_x_preferred":[
        "Olszanka"
    ],
    "name:pol_x_preferred":[
        "Olszanka"
    ],
    "name:rus_x_preferred":[
        "\u041e\u043b\u044c\u0448\u0430\u043d\u043a\u0430"
    ],
    "name:ukr_x_preferred":[
        "\u041e\u043b\u044c\u0448\u0430\u043d\u043a\u0430"
    ],
    "wof:coterminous":[
        1125285249
    ],
    "wof:name":"Olszanka",
    "wof:placetype":"locality"
},
  "geometry": {"coordinates":[17.4734771443257,50.7838054909566],"type":"Point"}
}