{
  "type": "Feature",
  "properties": {
    "iso:country":"PL",
    "name:pol_x_preferred":[
        "Olszanka"
    ],
    "wof:name":"Olszanka",
    "wof:placetype":"locality"
},
  "geometry": {"coordinates":[17.4734771443257,50.7838054909566],"type":"Point"}
}