{
  "type": "Feature",
  "properties": {
    "gn:admin1_code":"86.0",
    "gn:admin2_code":"3011.0",
    "gn:admin3_code":"301103.0",
    "gn:asciiname":"Lagiewniki",
    "gn:country_code":"PL",
    "gn:dem":68,
    "gn:feature_class":"P",
    "gn:feature_code":"PPL",
    "gn:name":"\u0141agiewniki",
    "gn:population":0,
    "gn:timezone":"Europe/Warsaw",
    "iso:country":"PL",
    "wof:name":"Lagiewniki",
    "wof:placetype":"locality"
},
  "geometry": {"coordinates":[16.60473,52.15513],"type":"Point"}
}