{
  "type": "Feature",
  "properties": {
    "gn:admin1_code":"86.0",
    "gn:asciiname":"Zmyslona Ligocka",
    "gn:country_code":"PL",
    "gn:dem":155,
    "gn:feature_class":"P",
    "gn:feature_code":"PPL",
    "gn:name":"Zmy\u015blona Ligocka",
    "gn:population":0,
    "gn:timezone":"Europe/Warsaw",
    "iso:country":"PL",
    "name:pol_x_preferred":[
        "Zmy\u015blona Ligocka"
    ],
    "name:spa_x_preferred":[
        "Zmy\u015blona Ligocka"
    ],
    "name:ukr_x_preferred":[
        "\u0417\u043c\u0438\u0441\u043b\u044c\u043e\u043d\u0430-\u041b\u0456\u0491\u043e\u0446\u044c\u043a\u0430"
    ],
    "name:und_x_variant":[
        "Zmy\u015blona"
    ],
    "wof:name":"Zmyslona Ligocka",
    "wof:placetype":"locality"
},
  "geometry": {"coordinates":[17.75238,51.39886],"type":"Point"}
}