{
  "type": "Feature",
  "properties": {
    "gn:admin1_code":"86.0",
    "gn:asciiname":"Zmyslona Ligocka",
    "gn:country_code":"PL",
    "gn:dem":155,
    "gn:feature_class":"P",
    "gn:feature_code":"PPL",
    "gn:name":"Zmy\u015blona Ligocka",
    "gn:population":0,
    "gn:timezone":"Europe/Warsaw",
    "iso:country":"PL",
    "name:und_x_variant":[
        "Zmy\u015blona",
        "Zmy\u015blona Ligocka"
    ],
    "wof:name":"Zmyslona Ligocka",
    "wof:placetype":"locality"
},
  "geometry": {"coordinates":[17.75238,51.39886],"type":"Point"}
}