{
  "type": "Feature",
  "properties": {
    "gn:admin1_code":"78.0",
    "gn:admin2_code":"1419.0",
    "gn:admin3_code":"141915.0",
    "gn:asciiname":"Chmielewo",
    "gn:country_code":"PL",
    "gn:dem":81,
    "gn:feature_class":"P",
    "gn:feature_code":"PPL",
    "gn:name":"Chmielewo",
    "gn:population":0,
    "gn:timezone":"Europe/Warsaw",
    "iso:country":"PL",
    "name:fra_x_preferred":[
        "Chmielewo"
    ],
    "name:pol_x_preferred":[
        "Chmielewo"
    ],
    "name:ukr_x_preferred":[
        "\u0425\u043c\u0435\u043b\u0435\u0432\u043e"
    ],
    "wof:name":"Chmielewo",
    "wof:placetype":"locality"
},
  "geometry": {"coordinates":[20.23149,52.39896],"type":"Point"}
}