{
  "type": "Feature",
  "properties": {
    "gn:admin1_code":"76.0",
    "gn:admin2_code":"811.0",
    "gn:admin3_code":"81108.0",
    "gn:asciiname":"Jedrzychowiczki",
    "gn:country_code":"PL",
    "gn:dem":142,
    "gn:feature_class":"P",
    "gn:feature_code":"PPL",
    "gn:name":"J\u0119drzychowiczki",
    "gn:population":0,
    "gn:timezone":"Europe/Warsaw",
    "iso:country":"PL",
    "name:und_x_variant":[
        "J\u0119drzychowiczki"
    ],
    "wof:name":"Jedrzychowiczki",
    "wof:placetype":"locality"
},
  "geometry": {"coordinates":[14.86818,51.61976],"type":"Point"}
}