{
  "type": "Feature",
  "properties": {
    "gn:admin1_code":"76.0",
    "gn:admin2_code":"811.0",
    "gn:admin3_code":"81108.0",
    "gn:asciiname":"Jedrzychowiczki",
    "gn:country_code":"PL",
    "gn:dem":142,
    "gn:feature_class":"P",
    "gn:feature_code":"PPL",
    "gn:name":"J\u0119drzychowiczki",
    "gn:population":0,
    "gn:timezone":"Europe/Warsaw",
    "iso:country":"PL",
    "name:fra_x_preferred":[
        "J\u0119drzychowiczki"
    ],
    "name:pol_x_preferred":[
        "J\u0119drzychowiczki"
    ],
    "name:ukr_x_preferred":[
        "\u0404\u043d\u0434\u0436\u0438\u0445\u043e\u0432\u0456\u0447\u043a\u0456"
    ],
    "wof:name":"Jedrzychowiczki",
    "wof:placetype":"locality"
},
  "geometry": {"coordinates":[14.86818,51.61976],"type":"Point"}
}