{
  "type": "Feature",
  "properties": {
    "gn:admin1_code":"85.0",
    "gn:admin2_code":"2802.0",
    "gn:admin3_code":"280205.0",
    "gn:asciiname":"Kajmity",
    "gn:country_code":"PL",
    "gn:dem":106,
    "gn:feature_class":"P",
    "gn:feature_code":"PPL",
    "gn:name":"Kajmity",
    "gn:population":0,
    "gn:timezone":"Europe/Warsaw",
    "iso:country":"PL",
    "name:und_x_variant":[
        "Heistern",
        "Kajmity"
    ],
    "wof:name":"Kajmity",
    "wof:placetype":"locality"
},
  "geometry": {"coordinates":[20.0681,54.22724],"type":"Point"}
}