{
  "type": "Feature",
  "properties": {
    "gn:admin1_code":"84.0",
    "gn:admin2_code":"2613.0",
    "gn:admin3_code":"261306.0",
    "gn:asciiname":"Przygradow",
    "gn:country_code":"PL",
    "gn:dem":259,
    "gn:feature_class":"P",
    "gn:feature_code":"PPL",
    "gn:name":"Przygrad\u00f3w",
    "gn:population":0,
    "gn:timezone":"Europe/Warsaw",
    "iso:country":"PL",
    "name:pol_x_preferred":[
        "Przygrad\u00f3w"
    ],
    "name:ukr_x_preferred":[
        "\u041f\u0448\u0438\u0491\u0440\u0430\u0434\u0443\u0432"
    ],
    "wof:name":"Przygradow",
    "wof:placetype":"locality"
},
  "geometry": {"coordinates":[20.07425,50.79509],"type":"Point"}
}