{
  "type": "Feature",
  "properties": {
    "iso:country":"PL",
    "name:pol_x_preferred":[
        "Borkowice"
    ],
    "wof:name":"Borkowice",
    "wof:placetype":"locality"
},
  "geometry": {"coordinates":[20.6915849782421,51.3035385887024],"type":"Point"}
}