{
  "type": "Feature",
  "properties": {
    "iso:country":"PL",
    "name:ceb_x_preferred":[
        "Borkowice"
    ],
    "name:deu_x_preferred":[
        "Borkowice"
    ],
    "name:fra_x_preferred":[
        "Borkowice"
    ],
    "name:nld_x_preferred":[
        "Borkowice"
    ],
    "name:pol_x_preferred":[
        "Borkowice"
    ],
    "name:ukr_x_preferred":[
        "\u0411\u043e\u0440\u043a\u043e\u0432\u0456\u0446\u0435"
    ],
    "wof:coterminous":[
        1125290141
    ],
    "wof:name":"Borkowice",
    "wof:placetype":"locality"
},
  "geometry": {"coordinates":[20.6915849782421,51.3035385887024],"type":"Point"}
}