{
  "type": "Feature",
  "properties": {
    "gn:admin1_code":"78.0",
    "gn:admin2_code":"1418.0",
    "gn:admin3_code":"141805.0",
    "gn:asciiname":"Aleksandrow",
    "gn:country_code":"PL",
    "gn:dem":121,
    "gn:feature_class":"P",
    "gn:feature_code":"PPL",
    "gn:name":"Aleksandr\u00f3w",
    "gn:population":0,
    "gn:timezone":"Europe/Warsaw",
    "iso:country":"PL",
    "wof:name":"Aleksandrow",
    "wof:placetype":"locality"
},
  "geometry": {"coordinates":[20.95103,51.96885],"type":"Point"}
}