{
  "type": "Feature",
  "properties": {
    "gn:admin1_code":"86.0",
    "gn:admin2_code":"3010.0",
    "gn:admin3_code":"301003.0",
    "gn:asciiname":"Bochlewo",
    "gn:country_code":"PL",
    "gn:dem":100,
    "gn:feature_class":"P",
    "gn:feature_code":"PPL",
    "gn:name":"Bochlewo",
    "gn:population":0,
    "gn:timezone":"Europe/Warsaw",
    "iso:country":"PL",
    "name:pol_x_preferred":[
        "Bochlewo"
    ],
    "name:ukr_x_preferred":[
        "\u0411\u043e\u0445\u043b\u0435\u0432\u043e"
    ],
    "wof:name":"Bochlewo",
    "wof:placetype":"locality"
},
  "geometry": {"coordinates":[18.10143,52.32096],"type":"Point"}
}