{
  "type": "Feature",
  "properties": {
    "gn:admin1_code":"84.0",
    "gn:admin2_code":"2604.0",
    "gn:admin3_code":"260415.0",
    "gn:asciiname":"Drugnia",
    "gn:country_code":"PL",
    "gn:dem":275,
    "gn:feature_class":"P",
    "gn:feature_code":"PPL",
    "gn:name":"Drugnia",
    "gn:population":0,
    "gn:timezone":"Europe/Warsaw",
    "iso:country":"PL",
    "name:ceb_x_preferred":[
        "Drugnia"
    ],
    "name:nld_x_preferred":[
        "Drugnia"
    ],
    "name:pol_x_preferred":[
        "Drugnia"
    ],
    "name:szl_x_preferred":[
        "Drug\u0144a"
    ],
    "name:ukr_x_preferred":[
        "\u0414\u0440\u0443\u0491\u043d\u044f"
    ],
    "wof:name":"Drugnia",
    "wof:placetype":"locality"
},
  "geometry": {"coordinates":[20.8445,50.65632],"type":"Point"}
}