{
  "type": "Feature",
  "properties": {
    "gn:country":"PL",
    "gn:fcode":"PPL",
    "gn:population":463,
    "iso:country":"PL",
    "name:ast_x_preferred":[
        "Romaszki"
    ],
    "name:ceb_x_preferred":[
        "Romaszki"
    ],
    "name:ces_x_preferred":[
        "Romaszki"
    ],
    "name:che_x_preferred":[
        "\u0420\u043e\u043c\u0430\u0448\u043a\u0438"
    ],
    "name:eng_x_preferred":[
        "Romaszki"
    ],
    "name:fra_x_preferred":[
        "Romaszki"
    ],
    "name:lit_x_preferred":[
        "Ramo\u0161kos"
    ],
    "name:nan_x_preferred":[
        "Romaszki"
    ],
    "name:pol_x_preferred":[
        "Romaszki"
    ],
    "name:rus_x_preferred":[
        "\u0420\u043e\u043c\u0430\u0448\u043a\u0438"
    ],
    "name:tat_x_preferred":[
        "\u0420\u043e\u043c\u0430\u0448\u043a\u0438"
    ],
    "name:ukr_x_preferred":[
        "\u0420\u043e\u043c\u0430\u0448\u043a\u0456"
    ],
    "qs_pg:aaroncc":"PL",
    "qs_pg:gn_country":"PL",
    "qs_pg:gn_fcode":"PPL",
    "qs_pg:gn_pop":463,
    "qs_pg:name":"Romaszki",
    "qs_pg:name_adm0":"Polska",
    "qs_pg:name_adm1":"Lubelskie",
    "qs_pg:photos_9r":0,
    "qs_pg:photos_sr":0,
    "qs_pg:pop_sr":2,
    "qs_pg:qs_pg_placetype":"locality",
    "qs_pg:qs_pg_placetype_gp":"Town",
    "qs_pg:woe_adm0":23424923,
    "woe:adm0_id":23424923,
    "woe:name_adm0":"Polska",
    "woe:name_adm1":"Lubelskie",
    "woe:placetype":"Town",
    "wof:name":"Romaszki",
    "wof:placetype":"locality",
    "wof:population":463
},
  "geometry": {"coordinates":[23.05249,51.82146],"type":"Point"}
}