{
  "type": "Feature",
  "properties": {
    "gn:admin1_code":"78.0",
    "gn:admin2_code":"1415.0",
    "gn:admin3_code":"141505.0",
    "gn:asciiname":"Klimki",
    "gn:country_code":"PL",
    "gn:dem":113,
    "gn:feature_class":"P",
    "gn:feature_code":"PPL",
    "gn:name":"Klimki",
    "gn:population":0,
    "gn:timezone":"Europe/Warsaw",
    "iso:country":"PL",
    "name:ceb_x_preferred":[
        "Klimki"
    ],
    "name:fra_x_preferred":[
        "Klimki"
    ],
    "name:pol_x_preferred":[
        "Klimki"
    ],
    "name:ukr_x_preferred":[
        "\u041a\u043b\u0456\u043c\u043a\u0456"
    ],
    "wof:name":"Klimki",
    "wof:placetype":"locality"
},
  "geometry": {"coordinates":[21.47291,53.3124],"type":"Point"}
}