{
  "type": "Feature",
  "properties": {
    "iso:country":"PL",
    "name:eng_x_preferred":[
        "Biskupia Gorka"
    ],
    "name:pol_x_preferred":[
        "Biskupia G\u00f3rka"
    ],
    "wof:name":"Biskupia Gorka",
    "wof:placetype":"neighbourhood"
},
  "geometry": {"coordinates":[18.64082631351791,54.34469836968335],"type":"Point"}
}