{
  "type": "Feature",
  "properties": {
    "gn:admin1_code":"74.0",
    "gn:admin2_code":"1017.0",
    "gn:admin3_code":"101701.0",
    "gn:asciiname":"Bronislawow",
    "gn:country_code":"PL",
    "gn:dem":180,
    "gn:feature_class":"P",
    "gn:feature_code":"PPL",
    "gn:name":"Bronis\u0142aw\u00f3w",
    "gn:population":0,
    "gn:timezone":"Europe/Warsaw",
    "iso:country":"PL",
    "wof:name":"Bronislawow",
    "wof:placetype":"locality"
},
  "geometry": {"coordinates":[18.50274,51.25385],"type":"Point"}
}