{
  "type": "Feature",
  "properties": {
    "gn:admin1_code":"86.0",
    "gn:admin2_code":"3018.0",
    "gn:admin3_code":"301807.0",
    "gn:asciiname":"Okole",
    "gn:country_code":"PL",
    "gn:dem":172,
    "gn:feature_class":"P",
    "gn:feature_code":"PPL",
    "gn:name":"Okole",
    "gn:population":0,
    "gn:timezone":"Europe/Warsaw",
    "iso:country":"PL",
    "name:pol_x_preferred":[
        "Okole"
    ],
    "name:ukr_x_preferred":[
        "\u041e\u043a\u043e\u043b\u0435"
    ],
    "wof:name":"Okole",
    "wof:placetype":"locality"
},
  "geometry": {"coordinates":[17.83612,51.4248],"type":"Point"}
}