{
  "type": "Feature",
  "properties": {
    "gn:country":"PL",
    "gn:fcode":"PPL",
    "gn:population":0,
    "iso:country":"PL",
    "name:ast_x_preferred":[
        "Je\u0142owa"
    ],
    "name:deu_x_preferred":[
        "Jellowa"
    ],
    "name:eng_x_preferred":[
        "Je\u0142owa"
    ],
    "name:fra_x_preferred":[
        "Je\u0142owa"
    ],
    "name:nan_x_preferred":[
        "Je\u0142owa"
    ],
    "name:pol_x_preferred":[
        "Je\u0142owa"
    ],
    "name:ukr_x_preferred":[
        "\u0404\u043b\u043e\u0432\u0430"
    ],
    "name:und_x_variant":[
        "Ilnau"
    ],
    "qs_pg:aaroncc":"PL",
    "qs_pg:gn_country":"PL",
    "qs_pg:gn_fcode":"PPL",
    "qs_pg:gn_pop":0,
    "qs_pg:name":"Je\u0142owa",
    "qs_pg:name_adm0":"Polska",
    "qs_pg:name_adm1":"Opolskie",
    "qs_pg:photos_9k":1,
    "qs_pg:photos_9r":1,
    "qs_pg:photos_all":8,
    "qs_pg:photos_sr":0,
    "qs_pg:pop_sr":0,
    "qs_pg:qs_pg_placetype":"locality",
    "qs_pg:qs_pg_placetype_gp":"Town",
    "qs_pg:woe_adm0":23424923,
    "woe:adm0_id":23424923,
    "woe:name_adm0":"Polska",
    "woe:name_adm1":"Opolskie",
    "woe:placetype":"Town",
    "wof:name":"Je\u0142owa",
    "wof:placetype":"locality"
},
  "geometry": {"coordinates":[18.07331,50.79912],"type":"Point"}
}