{
  "type": "Feature",
  "properties": {
    "gn:admin1_code":"76.0",
    "gn:admin2_code":"862.0",
    "gn:admin3_code":"86201.0",
    "gn:asciiname":"Raculka",
    "gn:country_code":"PL",
    "gn:dem":181,
    "gn:feature_class":"P",
    "gn:feature_code":"PPL",
    "gn:name":"Raculka",
    "gn:population":0,
    "gn:timezone":"Europe/Warsaw",
    "iso:country":"PL",
    "wof:name":"Raculka",
    "wof:placetype":"locality"
},
  "geometry": {"coordinates":[15.54814,51.93037],"type":"Point"}
}