{
  "type": "Feature",
  "properties": {
    "gn:admin1_code":"84.0",
    "gn:admin2_code":"2601.0",
    "gn:admin3_code":"260105.0",
    "gn:asciiname":"Wlosnowice",
    "gn:country_code":"PL",
    "gn:dem":185,
    "gn:feature_class":"P",
    "gn:feature_code":"PPL",
    "gn:name":"W\u0142osnowice",
    "gn:population":0,
    "gn:timezone":"Europe/Warsaw",
    "iso:country":"PL",
    "name:pol_x_preferred":[
        "W\u0142osnowice"
    ],
    "name:ukr_x_preferred":[
        "\u0412\u043b\u043e\u0441\u043d\u043e\u0432\u0456\u0446\u0435"
    ],
    "wof:name":"Wlosnowice",
    "wof:placetype":"locality"
},
  "geometry": {"coordinates":[20.92363,50.37677],"type":"Point"}
}