{
  "type": "Feature",
  "properties": {
    "gn:admin1_code":"84.0",
    "gn:admin2_code":"2601.0",
    "gn:admin3_code":"260105.0",
    "gn:asciiname":"Wlosnowice",
    "gn:country_code":"PL",
    "gn:dem":185,
    "gn:feature_class":"P",
    "gn:feature_code":"PPL",
    "gn:name":"W\u0142osnowice",
    "gn:population":0,
    "gn:timezone":"Europe/Warsaw",
    "iso:country":"PL",
    "name:und_x_variant":[
        "W\u0142osnowice"
    ],
    "wof:name":"Wlosnowice",
    "wof:placetype":"locality"
},
  "geometry": {"coordinates":[20.92363,50.37677],"type":"Point"}
}