{
  "type": "Feature",
  "properties": {
    "gn:admin1_code":"72.0",
    "gn:admin2_code":"222.0",
    "gn:admin3_code":"22201.0",
    "gn:asciiname":"Stary Dwor",
    "gn:country_code":"PL",
    "gn:dem":109,
    "gn:feature_class":"P",
    "gn:feature_code":"PPL",
    "gn:name":"Stary Dw\u00f3r",
    "gn:population":0,
    "gn:timezone":"Europe/Warsaw",
    "iso:country":"PL",
    "name:pol_x_preferred":[
        "Stary Dw\u00f3r"
    ],
    "name:ukr_x_preferred":[
        "\u0421\u0442\u0430\u0440\u0438\u0439 \u0414\u0432\u0443\u0440"
    ],
    "wof:name":"Stary Dwor",
    "wof:placetype":"locality"
},
  "geometry": {"coordinates":[16.79329,51.26675],"type":"Point"}
}