{
  "type": "Feature",
  "properties": {
    "gn:gn_country":"PL",
    "gn:gn_fcode":"PPL",
    "gn:gn_pop":0,
    "iso:country":"PL",
    "name:cze_x_preferred":[
        "M\u0142och\u00f3w"
    ],
    "name:eng_x_preferred":[
        "M\u0142och\u00f3w"
    ],
    "name:fre_x_preferred":[
        "M\u0142och\u00f3w"
    ],
    "name:per_x_preferred":[
        "\u0645\u0648\u0648\u062e\u0648\u0648"
    ],
    "name:pol_x_preferred":[
        "M\u0142och\u00f3w"
    ],
    "qs_pg:aaroncc":"PL",
    "qs_pg:gn_country":"PL",
    "qs_pg:gn_fcode":"PPL",
    "qs_pg:gn_pop":0,
    "qs_pg:name":"M\u0142och\u00f3w",
    "qs_pg:name_adm0":"Polska",
    "qs_pg:name_adm1":"Mazowieckie",
    "qs_pg:photos":10,
    "qs_pg:photos_1k":2,
    "qs_pg:photos_9k":1,
    "qs_pg:photos_9r":1,
    "qs_pg:photos_all":10,
    "qs_pg:photos_sr":1,
    "qs_pg:pop_sr":0,
    "qs_pg:qs_pg_placetype":"locality",
    "qs_pg:qs_pg_placetype_gp":"Town",
    "qs_pg:woe_adm0":23424923,
    "woe:adm0_id":23424923,
    "woe:name_adm0":"Polska",
    "woe:name_adm1":"Mazowieckie",
    "woe:placetype":"Town",
    "wof:name":"M\u0142och\u00f3w",
    "wof:placetype":"locality"
},
  "geometry": {"coordinates":[20.78081,52.04785],"type":"Point"}
}