{
  "type": "Feature",
  "properties": {
    "gn:population":3135,
    "iso:country":"PL",
    "name:azb_x_preferred":[
        "\u0642\u0645\u06cc\u0646\u0627 \u0627\u0644\u06a9\u0633\u0627\u0646\u062f\u0631\u0648\u0648"
    ],
    "name:bel_x_preferred":[
        "\u0413\u043c\u0456\u043d\u0430 \u0410\u043b\u044f\u043a\u0441\u0430\u043d\u0434\u0440\u0430\u045e"
    ],
    "name:deu_x_preferred":[
        "Gmina Aleksandr\u00f3w"
    ],
    "name:eng_x_preferred":[
        "Gmina Aleksandr\u00f3w"
    ],
    "name:eus_x_preferred":[
        "Aleksandr\u00f3w udalerria"
    ],
    "name:fas_x_preferred":[
        "\u06af\u0645\u06cc\u0646\u0627 \u0627\u0644\u06a9\u0633\u0627\u0646\u062f\u0631\u0648\u0648"
    ],
    "name:fra_x_preferred":[
        "Aleksandr\u00f3w"
    ],
    "name:ita_x_preferred":[
        "Aleksandr\u00f3w"
    ],
    "name:nld_x_preferred":[
        "Aleksandr\u00f3w"
    ],
    "name:pol_x_preferred":[
        "Aleksandr\u00f3w"
    ],
    "name:rus_x_preferred":[
        "\u0410\u043b\u0435\u043a\u0441\u0430\u043d\u0434\u0440\u0443\u0432"
    ],
    "name:slk_x_preferred":[
        "Gmina Aleksandr\u00f3w"
    ],
    "name:ukr_x_preferred":[
        "\u0413\u043c\u0456\u043d\u0430 \u0410\u043b\u0435\u043a\u0441\u0430\u043d\u0434\u0440\u0443\u0432"
    ],
    "name:ukr_x_variant":[
        "\u0490\u043c\u0456\u043d\u0430 \u0410\u043b\u0435\u043a\u0441\u0430\u043d\u0434\u0440\u0443\u0432"
    ],
    "name:war_x_preferred":[
        "Gmina Aleksandr\u00f3w"
    ],
    "qs:a0":"Rzeczpospolita Polska",
    "qs:a1":"*Lubelskie",
    "qs:a1r":"0",
    "qs:a2":"Bilgorajski",
    "qs:adm0":"Rzeczpospolita Polska",
    "qs:la":"Aleksandr\u00f3w",
    "qs:la_lc":"*PL0602022",
    "qs:level":"locality",
    "qs:loc":"Aleksandr\u00f3w",
    "qs:loc_alt":"Aleksandrow",
    "qs:pop":0,
    "qs:type":"rural point-in-poly",
    "wd:wordcount":204,
    "wof:name":"Aleksandr\u00f3w",
    "wof:placetype":"locality",
    "wof:population":3135
},
  "geometry": {"coordinates":[22.8897764012233,50.4677530373468],"type":"Point"}
}