{
  "type": "Feature",
  "properties": {
    "gn:country":"PL",
    "gn:fcode":"PPLA3",
    "gn:population":1112,
    "iso:country":"PL",
    "name:azb_x_preferred":[
        "\u0686\u0627\u0631\u0646\u0627 \u062f\u0627\u0646\u0628\u0631\u0648\u0648\u06a9\u0627"
    ],
    "name:csb_x_preferred":[
        "Cz\u00f4rn\u00f4 D\u0105br\u00f3wka"
    ],
    "name:deu_x_preferred":[
        "Czarna D\u0105br\u00f3wka"
    ],
    "name:fas_x_preferred":[
        "\u0686\u0627\u0631\u0646\u0627 \u062f\u0627\u0646\u0628\u0631\u0648\u0648\u06a9\u0627"
    ],
    "name:nld_x_preferred":[
        "Czarna D\u0105br\u00f3wka"
    ],
    "name:pol_x_preferred":[
        "Czarna D\u0105br\u00f3wka"
    ],
    "name:ukr_x_preferred":[
        "\u0427\u0430\u0440\u043d\u0430-\u0414\u043e\u043c\u0431\u0440\u0443\u0432\u043a\u0430"
    ],
    "qs_pg:aaroncc":"PL",
    "qs_pg:gn_country":"PL",
    "qs_pg:gn_fcode":"PPLA3",
    "qs_pg:gn_pop":1112,
    "qs_pg:name":"Czarna D\u0105br\u00f3wka",
    "qs_pg:name_adm0":"Polska",
    "qs_pg:name_adm1":"Pomorskie",
    "qs_pg:photos":8,
    "qs_pg:photos_1k":2,
    "qs_pg:photos_9k":1,
    "qs_pg:photos_9r":1,
    "qs_pg:photos_all":8,
    "qs_pg:photos_sr":1,
    "qs_pg:pop_sr":3,
    "qs_pg:qs_pg_placetype":"localadmin",
    "qs_pg:qs_pg_placetype_gp":"LocalAdmin",
    "qs_pg:woe_adm0":23424923,
    "woe:adm0_id":23424923,
    "woe:name_adm0":"Polska",
    "woe:name_adm1":"Pomorskie",
    "woe:placetype":"LocalAdmin",
    "wof:name":"Czarna D\u0105br\u00f3wka",
    "wof:placetype":"localadmin",
    "wof:population":1112
},
  "geometry": {"coordinates":[17.56456,54.35631],"type":"Point"}
}