{
  "type": "Feature",
  "properties": {
    "gn:admin1_code":"81.0",
    "gn:admin2_code":"2012.0",
    "gn:admin3_code":"201202.0",
    "gn:asciiname":"Supienie",
    "gn:cc2":"PL",
    "gn:country_code":"PL",
    "gn:dem":198,
    "gn:feature_class":"P",
    "gn:feature_code":"PPL",
    "gn:name":"Supienie",
    "gn:population":0,
    "gn:timezone":"Europe/Warsaw",
    "iso:country":"PL",
    "name:und_x_variant":[
        "Supienia",
        "Supienie"
    ],
    "wof:name":"Supienie",
    "wof:placetype":"locality"
},
  "geometry": {"coordinates":[22.54789,54.21647],"type":"Point"}
}