{
  "type": "Feature",
  "properties": {
    "gn:admin1_code":"81.0",
    "gn:admin2_code":"2012.0",
    "gn:admin3_code":"201202.0",
    "gn:asciiname":"Supienie",
    "gn:cc2":"PL",
    "gn:country_code":"PL",
    "gn:dem":198,
    "gn:feature_class":"P",
    "gn:feature_code":"PPL",
    "gn:name":"Supienie",
    "gn:population":0,
    "gn:timezone":"Europe/Warsaw",
    "iso:country":"PL",
    "name:azb_x_preferred":[
        "\u0633\u0648\u067e\u06cc\u0646\u0642\u0647"
    ],
    "name:deu_x_preferred":[
        "Supienie"
    ],
    "name:fas_x_preferred":[
        "\u0633\u0648\u067e\u06cc\u0646\u06af\u0647"
    ],
    "name:fra_x_preferred":[
        "Supienie"
    ],
    "name:lit_x_preferred":[
        "Supieniai"
    ],
    "name:nld_x_preferred":[
        "Supienie"
    ],
    "name:pol_x_preferred":[
        "Supienie"
    ],
    "name:ukr_x_preferred":[
        "\u0421\u0443\u043f\u0435\u043d\u0435"
    ],
    "name:und_x_variant":[
        "Supienia",
        "Supienie"
    ],
    "wof:name":"Supienie",
    "wof:placetype":"locality"
},
  "geometry": {"coordinates":[22.54789,54.21647],"type":"Point"}
}