{
  "type": "Feature",
  "properties": {
    "gn:admin1_code":"82.0",
    "gn:admin2_code":"2208.0",
    "gn:admin3_code":"220804.0",
    "gn:asciiname":"Janowiczki",
    "gn:country_code":"PL",
    "gn:dem":48,
    "gn:feature_class":"P",
    "gn:feature_code":"PPL",
    "gn:name":"Janowiczki",
    "gn:population":0,
    "gn:timezone":"Europe/Warsaw",
    "iso:country":"PL",
    "wof:name":"Janowiczki",
    "wof:placetype":"locality"
},
  "geometry": {"coordinates":[17.63906,54.59056999999999],"type":"Point"}
}