{
  "type": "Feature",
  "properties": {
    "gn:admin1_code":"72.0",
    "gn:admin2_code":"220.0",
    "gn:admin3_code":"22002.0",
    "gn:asciiname":"Pawlow Trzebnicki",
    "gn:country_code":"PL",
    "gn:dem":119,
    "gn:feature_class":"P",
    "gn:feature_code":"PPL",
    "gn:name":"Pawl\u00f3w Trzebnicki",
    "gn:population":0,
    "gn:timezone":"Europe/Warsaw",
    "iso:country":"PL",
    "name:pol_x_preferred":[
        "Paw\u0142\u00f3w Trzebnicki"
    ],
    "name:ukr_x_preferred":[
        "\u041f\u0430\u0432\u043b\u0443\u0432-\u0422\u0448\u0435\u0431\u043d\u0456\u0446\u044c\u043a\u0438\u0439"
    ],
    "name:und_x_variant":[
        "Pawl\u00f3w Trzebnicki"
    ],
    "wof:name":"Pawlow Trzebnicki",
    "wof:placetype":"locality"
},
  "geometry": {"coordinates":[17.02869,51.35905],"type":"Point"}
}