{
  "type": "Feature",
  "properties": {
    "gn:admin1_code":"76.0",
    "gn:admin2_code":"808.0",
    "gn:admin3_code":"80804.0",
    "gn:asciiname":"Smardzewo",
    "gn:cc2":"PL",
    "gn:country_code":"PL",
    "gn:dem":81,
    "gn:feature_class":"P",
    "gn:feature_code":"PPL",
    "gn:name":"Smardzewo",
    "gn:population":0,
    "gn:timezone":"Europe/Warsaw",
    "iso:country":"PL",
    "name:ceb_x_preferred":[
        "Smardzewo"
    ],
    "name:deu_x_historical":[
        "Schmarse"
    ],
    "name:deu_x_preferred":[
        "Schmarse"
    ],
    "name:fra_x_preferred":[
        "Smardzewo"
    ],
    "name:pol_x_preferred":[
        "Smardzewo"
    ],
    "name:ukr_x_preferred":[
        "\u0421\u043c\u0430\u0440\u0434\u0437\u0435\u0432\u043e"
    ],
    "wof:name":"Smardzewo",
    "wof:placetype":"locality"
},
  "geometry": {"coordinates":[15.69852,52.1983],"type":"Point"}
}