{
  "type": "Feature",
  "properties": {
    "gn:admin1_code":"82.0",
    "gn:admin2_code":"2201.0",
    "gn:admin3_code":"220105.0",
    "gn:asciiname":"Rucowe Lasy",
    "gn:country_code":"PL",
    "gn:dem":151,
    "gn:feature_class":"P",
    "gn:feature_code":"PPL",
    "gn:name":"Rucowe Lasy",
    "gn:population":0,
    "gn:timezone":"Europe/Warsaw",
    "iso:country":"PL",
    "name:ceb_x_preferred":[
        "Rucowe Lasy"
    ],
    "name:pol_x_preferred":[
        "Rucowe Lasy"
    ],
    "wof:name":"Rucowe Lasy",
    "wof:placetype":"locality"
},
  "geometry": {"coordinates":[17.3723,53.95417],"type":"Point"}
}