{
  "type": "Feature",
  "properties": {
    "gn:admin1_code":"77.0",
    "gn:admin2_code":"1210.0",
    "gn:admin3_code":"121014.0",
    "gn:asciiname":"Podrzecze",
    "gn:country_code":"PL",
    "gn:dem":294,
    "gn:feature_class":"P",
    "gn:feature_code":"PPL",
    "gn:name":"Podrzecze",
    "gn:population":0,
    "gn:timezone":"Europe/Warsaw",
    "iso:country":"PL",
    "name:deu_x_preferred":[
        "Podrzecze"
    ],
    "name:pol_x_preferred":[
        "Podrzecze"
    ],
    "name:ukr_x_preferred":[
        "\u041f\u043e\u0434\u0436\u0435\u0447\u0435"
    ],
    "wof:name":"Podrzecze",
    "wof:placetype":"locality"
},
  "geometry": {"coordinates":[20.63904,49.5994],"type":"Point"}
}