{
  "type": "Feature",
  "properties": {
    "gn:admin1_code":"82.0",
    "gn:admin2_code":"2202.0",
    "gn:admin3_code":"220202.0",
    "gn:asciiname":"Antoniewo",
    "gn:country_code":"PL",
    "gn:dem":154,
    "gn:feature_class":"P",
    "gn:feature_code":"PPL",
    "gn:name":"Antoniewo",
    "gn:population":0,
    "gn:timezone":"Europe/Warsaw",
    "iso:country":"PL",
    "wof:name":"Antoniewo",
    "wof:placetype":"locality"
},
  "geometry": {"coordinates":[17.61978,53.89304],"type":"Point"}
}