{
  "type": "Feature",
  "properties": {
    "gn:admin1_code":"72.0",
    "gn:admin2_code":"221.0",
    "gn:admin3_code":"22101.0",
    "gn:asciiname":"Chelmiec",
    "gn:country_code":"PL",
    "gn:dem":555,
    "gn:feature_class":"P",
    "gn:feature_code":"PPL",
    "gn:name":"Che\u0142miec",
    "gn:population":0,
    "gn:timezone":"Europe/Warsaw",
    "iso:country":"PL",
    "wof:name":"Chelmiec",
    "wof:placetype":"locality"
},
  "geometry": {"coordinates":[16.18801,50.77989],"type":"Point"}
}