{
  "type": "Feature",
  "properties": {
    "gn:admin1_code":"75.0",
    "gn:admin2_code":"611.0",
    "gn:admin3_code":"61108.0",
    "gn:asciiname":"Januszowka",
    "gn:country_code":"PL",
    "gn:dem":175,
    "gn:feature_class":"P",
    "gn:feature_code":"PPL",
    "gn:name":"Janusz\u00f3wka",
    "gn:population":0,
    "gn:timezone":"Europe/Warsaw",
    "iso:country":"PL",
    "name:fra_x_preferred":[
        "Janusz\u00f3wka"
    ],
    "name:pol_x_preferred":[
        "Janusz\u00f3wka"
    ],
    "name:ukr_x_preferred":[
        "\u042f\u043d\u0443\u0448\u0443\u0432\u043a\u0430"
    ],
    "name:und_x_variant":[
        "Janusz\u00f3wka"
    ],
    "name:urd_x_preferred":[
        "\u062c\u0627\u0646\u0633\u0632\u0648\u0648\u06a9\u0627"
    ],
    "wof:name":"Januszowka",
    "wof:placetype":"locality"
},
  "geometry": {"coordinates":[21.9662,51.90537],"type":"Point"}
}