{
  "type": "Feature",
  "properties": {
    "gn:admin1_code":"81.0",
    "gn:admin2_code":"2011.0",
    "gn:admin3_code":"201106.0",
    "gn:asciiname":"Nowosiolki",
    "gn:country_code":"PL",
    "gn:dem":130,
    "gn:feature_class":"P",
    "gn:feature_code":"PPL",
    "gn:name":"Nowosi\u00f3\u0142ki",
    "gn:population":0,
    "gn:timezone":"Europe/Warsaw",
    "iso:country":"PL",
    "wof:name":"Nowosiolki",
    "wof:placetype":"locality"
},
  "geometry": {"coordinates":[23.46848,53.69799],"type":"Point"}
}