{
  "type": "Feature",
  "properties": {
    "gn:admin1_code":"74.0",
    "gn:admin2_code":"1020.0",
    "gn:admin3_code":"102007.0",
    "gn:asciiname":"Chociszew",
    "gn:country_code":"PL",
    "gn:dem":139,
    "gn:feature_class":"P",
    "gn:feature_code":"PPL",
    "gn:name":"Chociszew",
    "gn:population":0,
    "gn:timezone":"Europe/Warsaw",
    "iso:country":"PL",
    "name:pol_x_preferred":[
        "Chociszew"
    ],
    "name:ukr_x_preferred":[
        "\u0425\u043e\u0446\u0438\u0448\u0435\u0432"
    ],
    "wof:name":"Chociszew",
    "wof:placetype":"locality"
},
  "geometry": {"coordinates":[19.24346,51.92589],"type":"Point"}
}