{
  "type": "Feature",
  "properties": {
    "gn:admin1_code":"78.0",
    "gn:admin2_code":"1406.0",
    "gn:admin3_code":"140602.0",
    "gn:asciiname":"Dabrowka Stara",
    "gn:country_code":"PL",
    "gn:dem":172,
    "gn:feature_class":"P",
    "gn:feature_code":"PPL",
    "gn:name":"D\u0105br\u00f3wka Stara",
    "gn:population":0,
    "gn:timezone":"Europe/Warsaw",
    "iso:country":"PL",
    "name:fra_x_preferred":[
        "D\u0105br\u00f3wka Stara"
    ],
    "name:pol_x_preferred":[
        "D\u0105br\u00f3wka Stara"
    ],
    "name:ukr_x_preferred":[
        "\u0414\u043e\u043c\u0431\u0440\u0443\u0432\u043a\u0430-\u0421\u0442\u0430\u0440\u0430"
    ],
    "wof:name":"Dabrowka Stara",
    "wof:placetype":"locality"
},
  "geometry": {"coordinates":[20.72749,51.77601],"type":"Point"}
}