{
  "type": "Feature",
  "properties": {
    "gn:population":2059,
    "iso:country":"PL",
    "name:eng_x_preferred":[
        "Trzebunia"
    ],
    "name:fas_x_preferred":[
        "\u0686\u0628\u0648\u0646\u06cc\u0627"
    ],
    "name:fra_x_preferred":[
        "Trzebunia"
    ],
    "name:pol_x_preferred":[
        "Trzebunia"
    ],
    "name:unk_x_variant":[
        "Trzebunie"
    ],
    "qs:a0":"Rzeczpospolita Polska",
    "qs:a1":"*Malopolskie",
    "qs:a1r":"0",
    "qs:a2":"Myslenicki",
    "qs:adm0":"Rzeczpospolita Polska",
    "qs:la_lc":"*",
    "qs:level":"locality",
    "qs:loc":"Trzebunia",
    "qs:loc_alt":"Trzebunia",
    "qs:pop":0,
    "qs:type":"buffered point",
    "wd:wordcount":85,
    "wof:name":"Trzebunia",
    "wof:placetype":"locality",
    "wof:population":2059
},
  "geometry": {"coordinates":[19.842612,49.788666],"type":"Point"}
}