{
  "type": "Feature",
  "properties": {
    "gn:population":2620,
    "iso:country":"PL",
    "name:azb_x_preferred":[
        "\u0642\u0645\u06cc\u0646\u0627 \u062f\u0648\u0648\u0642\u0648\u0648\u0646\u06a9\u0627"
    ],
    "name:bel_x_preferred":[
        "\u0413\u043c\u0456\u043d\u0430 \u0414\u043b\u0443\u0433\u0430\u043b\u044d\u043d\u043a\u0430"
    ],
    "name:ceb_x_preferred":[
        "D\u0142ugo\u0142\u0119ka"
    ],
    "name:dan_x_preferred":[
        "D\u0142ugo\u0142\u0119ka kommune"
    ],
    "name:deu_x_preferred":[
        "Gmina D\u0142ugo\u0142\u0119ka"
    ],
    "name:eng_x_preferred":[
        "Gmina D\u0142ugo\u0142\u0119ka"
    ],
    "name:eus_x_preferred":[
        "D\u0142ugo\u0142\u0119ka udalerria"
    ],
    "name:fas_x_preferred":[
        "\u06af\u0645\u06cc\u0646\u0627 \u062f\u0648\u0648\u06af\u0648\u0648\u0646\u06a9\u0627"
    ],
    "name:fra_x_preferred":[
        "D\u0142ugo\u0142\u0119ka"
    ],
    "name:ita_x_preferred":[
        "D\u0142ugo\u0142\u0119ka"
    ],
    "name:nan_x_preferred":[
        "D\u0142ugo\u0142\u0119ka"
    ],
    "name:nld_x_preferred":[
        "D\u0142ugo\u0142\u0119ka"
    ],
    "name:pol_x_preferred":[
        "D\u0142ugo\u0142\u0119ka"
    ],
    "name:por_x_preferred":[
        "Comuna de D\u0142ugo\u0142\u0119ka"
    ],
    "name:rus_x_preferred":[
        "\u0414\u043b\u0443\u0433\u043e\u043b\u0435\u043d\u043a\u0430"
    ],
    "name:slk_x_preferred":[
        "Gmina D\u0142ugo\u0142\u0119ka"
    ],
    "name:swe_x_preferred":[
        "D\u0142ugo\u0142\u0119ka kommun"
    ],
    "name:ukr_x_preferred":[
        "\u0490\u043c\u0456\u043d\u0430 \u0414\u043b\u0443\u0491\u043e\u043b\u0435\u043d\u043a\u0430"
    ],
    "name:war_x_preferred":[
        "Gmina D\u0142ugo\u0142\u0119ka"
    ],
    "qs:a0":"Rzeczpospolita Polska",
    "qs:a1":"*Dolnoslaskie",
    "qs:a1r":"0",
    "qs:a2":"Wroclawski",
    "qs:adm0":"Rzeczpospolita Polska",
    "qs:la":"D\u0142ugo\u0142\u0119ka",
    "qs:la_lc":"*PL0223022",
    "qs:level":"locality",
    "qs:loc":"D\u0142ugo\u0142\u0119ka",
    "qs:loc_alt":"Dlugoleka",
    "qs:pop":0,
    "qs:type":"rural point-in-poly",
    "wd:wordcount":139,
    "wof:coterminous":[
        1477751691
    ],
    "wof:name":"D\u0142ugo\u0142\u0119ka",
    "wof:placetype":"locality",
    "wof:population":2620
},
  "geometry": {"coordinates":[17.2217087077968,51.1809445350708],"type":"Point"}
}