{
  "type": "Feature",
  "properties": {
    "gn:admin1_code":"81.0",
    "gn:admin2_code":"2010.0",
    "gn:admin3_code":"201009.0",
    "gn:asciiname":"Baciki Srednie",
    "gn:country_code":"PL",
    "gn:dem":150,
    "gn:feature_class":"P",
    "gn:feature_code":"PPL",
    "gn:name":"Baciki \u015arednie",
    "gn:population":0,
    "gn:timezone":"Europe/Warsaw",
    "iso:country":"PL",
    "name:lit_x_preferred":[
        "Baciki \u0160redniai"
    ],
    "name:pol_x_preferred":[
        "Baciki \u015arednie"
    ],
    "name:ukr_x_preferred":[
        "\u0411\u0430\u0446\u0438\u043a\u0438-\u0421\u0435\u0440\u0435\u0434\u043d\u0456"
    ],
    "wof:name":"Baciki Srednie",
    "wof:placetype":"locality"
},
  "geometry": {"coordinates":[22.9095,52.45166],"type":"Point"}
}