{
  "type": "Feature",
  "properties": {
    "gn:admin1_code":"86.0",
    "gn:admin2_code":"3013.0",
    "gn:admin3_code":"301307.0",
    "gn:asciiname":"Dominice",
    "gn:country_code":"PL",
    "gn:dem":62,
    "gn:feature_class":"P",
    "gn:feature_code":"PPL",
    "gn:name":"Dominice",
    "gn:population":0,
    "gn:timezone":"Europe/Warsaw",
    "iso:country":"PL",
    "name:azb_x_preferred":[
        "\u062f\u0648\u0645\u06cc\u0646\u0642\u062a\u0633\u0647"
    ],
    "name:fas_x_preferred":[
        "\u062f\u0648\u0645\u06cc\u0646\u06af\u062a\u0633\u0647"
    ],
    "name:fra_x_preferred":[
        "Dominice"
    ],
    "name:pol_x_preferred":[
        "Dominice"
    ],
    "name:ukr_x_preferred":[
        "\u0414\u043e\u043c\u0456\u043d\u0456\u0446\u0435"
    ],
    "wof:name":"Dominice",
    "wof:placetype":"locality"
},
  "geometry": {"coordinates":[16.29962,51.9408],"type":"Point"}
}