{
  "type": "Feature",
  "properties": {
    "gn:admin1_code":"86.0",
    "gn:admin2_code":"3013.0",
    "gn:admin3_code":"301307.0",
    "gn:asciiname":"Dominice",
    "gn:country_code":"PL",
    "gn:dem":62,
    "gn:feature_class":"P",
    "gn:feature_code":"PPL",
    "gn:name":"Dominice",
    "gn:population":0,
    "gn:timezone":"Europe/Warsaw",
    "iso:country":"PL",
    "wof:name":"Dominice",
    "wof:placetype":"locality"
},
  "geometry": {"coordinates":[16.29962,51.9408],"type":"Point"}
}