{
  "type": "Feature",
  "properties": {
    "gn:admin1_code":"72.0",
    "gn:admin2_code":"209.0",
    "gn:admin3_code":"20906.0",
    "gn:asciiname":"Siedliska",
    "gn:country_code":"PL",
    "gn:dem":128,
    "gn:feature_class":"P",
    "gn:feature_code":"PPL",
    "gn:name":"Siedliska",
    "gn:population":0,
    "gn:timezone":"Europe/Warsaw",
    "iso:country":"PL",
    "name:deu_x_historical":[
        "Siegendorf"
    ],
    "name:deu_x_preferred":[
        "Siegendorf"
    ],
    "wof:name":"Siedliska",
    "wof:placetype":"locality"
},
  "geometry": {"coordinates":[16.03902,51.25536],"type":"Point"}
}