{
  "type": "Feature",
  "properties": {
    "gn:admin1_code":"75.0",
    "gn:admin2_code":"620.0",
    "gn:admin3_code":"62004.0",
    "gn:asciiname":"Kaczorki",
    "gn:country_code":"PL",
    "gn:dem":250,
    "gn:feature_class":"P",
    "gn:feature_code":"PPL",
    "gn:name":"Kacz\u00f3rki",
    "gn:population":0,
    "gn:timezone":"Europe/Warsaw",
    "iso:country":"PL",
    "name:fra_x_preferred":[
        "Kacz\u00f3rki"
    ],
    "name:pol_x_preferred":[
        "Kacz\u00f3rki"
    ],
    "name:ukr_x_preferred":[
        "\u041a\u0430\u0447\u0443\u0440\u043a\u0456"
    ],
    "wof:name":"Kaczorki",
    "wof:placetype":"locality"
},
  "geometry": {"coordinates":[23.13958,50.56198],"type":"Point"}
}