{
  "type": "Feature",
  "properties": {
    "gn:country":"PL",
    "gn:fcode":"PPL",
    "gn:population":480,
    "iso:country":"PL",
    "name:ast_x_preferred":[
        "Sulej\u00f3w"
    ],
    "name:ceb_x_preferred":[
        "Sulej\u00f3w"
    ],
    "name:eng_x_preferred":[
        "Sulej\u00f3w"
    ],
    "name:fra_x_preferred":[
        "Sulej\u00f3w"
    ],
    "name:pol_x_preferred":[
        "Sulej\u00f3w"
    ],
    "name:ukr_x_preferred":[
        "\u0421\u0443\u043b\u0435\u044e\u0432"
    ],
    "qs_pg:aaroncc":"PL",
    "qs_pg:gn_country":"PL",
    "qs_pg:gn_fcode":"PPL",
    "qs_pg:gn_pop":480,
    "qs_pg:name":"Sulej\u00f3w",
    "qs_pg:name_adm0":"Polska",
    "qs_pg:name_adm1":"Mazowieckie",
    "qs_pg:photos_9r":0,
    "qs_pg:photos_sr":0,
    "qs_pg:pop_sr":2,
    "qs_pg:qs_pg_placetype":"locality",
    "qs_pg:qs_pg_placetype_gp":"Town",
    "qs_pg:woe_adm0":23424923,
    "woe:adm0_id":23424923,
    "woe:name_adm0":"Polska",
    "woe:name_adm1":"Mazowieckie",
    "woe:placetype":"Town",
    "wof:name":"Sulej\u00f3w",
    "wof:placetype":"locality",
    "wof:population":480
},
  "geometry": {"coordinates":[21.56067,52.44058],"type":"Point"}
}