{
  "type": "Feature",
  "properties": {
    "gn:admin1_code":"84.0",
    "gn:admin2_code":"2608.0",
    "gn:admin3_code":"260803.0",
    "gn:asciiname":"Przeclawka",
    "gn:country_code":"PL",
    "gn:dem":333,
    "gn:feature_class":"P",
    "gn:feature_code":"PPL",
    "gn:name":"Przec\u0142awka",
    "gn:population":0,
    "gn:timezone":"Europe/Warsaw",
    "iso:country":"PL",
    "name:pol_x_preferred":[
        "Przec\u0142awka"
    ],
    "name:ukr_x_preferred":[
        "\u041f\u0448\u0435\u0446\u043b\u0430\u0432\u043a\u0430"
    ],
    "wof:name":"Przeclawka",
    "wof:placetype":"locality"
},
  "geometry": {"coordinates":[20.38337000000001,50.43266],"type":"Point"}
}