{
  "type": "Feature",
  "properties": {
    "gn:admin1_code":"83.0",
    "gn:admin2_code":"2416.0",
    "gn:admin3_code":"241610.0",
    "gn:asciiname":"Zamiechowka",
    "gn:country_code":"PL",
    "gn:dem":310,
    "gn:feature_class":"P",
    "gn:feature_code":"PPL",
    "gn:name":"Zamiech\u00f3wka",
    "gn:population":0,
    "gn:timezone":"Europe/Warsaw",
    "iso:country":"PL",
    "name:pol_x_preferred":[
        "Zamiech\u00f3wka"
    ],
    "name:und_x_variant":[
        "Zamiech\u00f3wki Chlina",
        "Zamiech\u00f3wka"
    ],
    "wof:name":"Zamiechowka",
    "wof:placetype":"locality"
},
  "geometry": {"coordinates":[19.83949,50.46079],"type":"Point"}
}