{
  "type": "Feature",
  "properties": {
    "gn:admin1_code":"78.0",
    "gn:admin2_code":"1428.0",
    "gn:admin3_code":"142806.0",
    "gn:asciiname":"Zlota Emiljanow",
    "gn:country_code":"PL",
    "gn:dem":90,
    "gn:feature_class":"P",
    "gn:feature_code":"PPL",
    "gn:name":"Z\u0142ota Emiljan\u00f3w",
    "gn:population":0,
    "gn:timezone":"Europe/Warsaw",
    "iso:country":"PL",
    "wof:name":"Zlota Emiljanow",
    "wof:placetype":"locality"
},
  "geometry": {"coordinates":[20.07804,52.187],"type":"Point"}
}