{
  "type": "Feature",
  "properties": {
    "gn:admin1_code":"74.0",
    "gn:admin2_code":"1001.0",
    "gn:admin3_code":"100103.0",
    "gn:asciiname":"Kobylki",
    "gn:country_code":"PL",
    "gn:dem":203,
    "gn:feature_class":"P",
    "gn:feature_code":"PPL",
    "gn:name":"Koby\u0142ki",
    "gn:population":0,
    "gn:timezone":"Europe/Warsaw",
    "iso:country":"PL",
    "name:fra_x_preferred":[
        "Koby\u0142ki"
    ],
    "name:pol_x_preferred":[
        "Koby\u0142ki"
    ],
    "name:ukr_x_preferred":[
        "\u041a\u043e\u0431\u0438\u043b\u043a\u0456"
    ],
    "wof:name":"Kobylki",
    "wof:placetype":"locality"
},
  "geometry": {"coordinates":[19.40794,51.45472],"type":"Point"}
}