{
  "type": "Feature",
  "properties": {
    "gn:admin1_code":"79.0",
    "gn:admin2_code":"1606.0",
    "gn:admin3_code":"160602.0",
    "gn:asciiname":"Minkowskie",
    "gn:country_code":"PL",
    "gn:dem":145,
    "gn:feature_class":"P",
    "gn:feature_code":"PPL",
    "gn:name":"Minkowskie",
    "gn:population":0,
    "gn:timezone":"Europe/Warsaw",
    "iso:country":"PL",
    "name:ceb_x_preferred":[
        "Minkowskie"
    ],
    "name:pol_x_preferred":[
        "Minkowskie"
    ],
    "name:ukr_x_preferred":[
        "\u041c\u0456\u043d\u043a\u043e\u0432\u0441\u044c\u043a\u0435"
    ],
    "wof:name":"Minkowskie",
    "wof:placetype":"locality"
},
  "geometry": {"coordinates":[17.61928,50.99744000000001],"type":"Point"}
}