{
  "type": "Feature",
  "properties": {
    "gn:admin1_code":"74.0",
    "gn:admin2_code":"1003.0",
    "gn:admin3_code":"100302.0",
    "gn:asciiname":"Orchow",
    "gn:country_code":"PL",
    "gn:dem":165,
    "gn:feature_class":"P",
    "gn:feature_code":"PPL",
    "gn:name":"Orch\u00f3w",
    "gn:population":0,
    "gn:timezone":"Europe/Warsaw",
    "iso:country":"PL",
    "name:fra_x_preferred":[
        "Orch\u00f3w"
    ],
    "name:pol_x_preferred":[
        "Orch\u00f3w"
    ],
    "name:ukr_x_preferred":[
        "\u041e\u0440\u0445\u0443\u0432"
    ],
    "wof:name":"Orchow",
    "wof:placetype":"locality"
},
  "geometry": {"coordinates":[19.09533,51.60181],"type":"Point"}
}