{
  "type": "Feature",
  "properties": {
    "gn:gn_country":"PL",
    "gn:gn_fcode":"PPL",
    "gn:gn_pop":0,
    "iso:country":"PL",
    "name:ceb_x_preferred":[
        "Kotowice"
    ],
    "name:deu_x_preferred":[
        "Kotowice"
    ],
    "name:fra_x_preferred":[
        "Kotowice"
    ],
    "name:pol_x_preferred":[
        "Kotowice"
    ],
    "name:ukr_x_preferred":[
        "\u041a\u043e\u0442\u043e\u0432\u0456\u0446\u0435"
    ],
    "qs_pg:aaroncc":"PL",
    "qs_pg:gn_country":"PL",
    "qs_pg:gn_fcode":"PPL",
    "qs_pg:gn_pop":0,
    "qs_pg:name":"Kotowice",
    "qs_pg:name_adm0":"Polska",
    "qs_pg:name_adm1":"Dolnosl\u0105skie",
    "qs_pg:photos":9,
    "qs_pg:photos_1k":2,
    "qs_pg:photos_9k":1,
    "qs_pg:photos_9r":1,
    "qs_pg:photos_all":9,
    "qs_pg:photos_sr":1,
    "qs_pg:pop_sr":0,
    "qs_pg:qs_pg_placetype":"locality",
    "qs_pg:qs_pg_placetype_gp":"Town",
    "qs_pg:woe_adm0":23424923,
    "woe:adm0_id":23424923,
    "woe:name_adm0":"Polska",
    "woe:name_adm1":"Dolnosl\u0105skie",
    "woe:placetype":"Town",
    "wof:name":"Kotowice",
    "wof:placetype":"locality"
},
  "geometry": {"coordinates":[16.92367,51.2242],"type":"Point"}
}