{
  "type": "Feature",
  "properties": {
    "gn:admin1_code":"85.0",
    "gn:admin2_code":"2807.0",
    "gn:admin3_code":"280704.0",
    "gn:asciiname":"Galinowo",
    "gn:country_code":"PL",
    "gn:dem":89,
    "gn:feature_class":"P",
    "gn:feature_code":"PPL",
    "gn:name":"Galinowo",
    "gn:population":0,
    "gn:timezone":"Europe/Warsaw",
    "iso:country":"PL",
    "name:nld_x_preferred":[
        "Galinowo"
    ],
    "name:pol_x_preferred":[
        "Galinowo"
    ],
    "name:ukr_x_preferred":[
        "\u0490\u0430\u043b\u0456\u043d\u043e\u0432\u043e"
    ],
    "wof:name":"Galinowo",
    "wof:placetype":"locality"
},
  "geometry": {"coordinates":[19.19466,53.63304],"type":"Point"}
}