{
  "type": "Feature",
  "properties": {
    "gn:admin1_code":"80.0",
    "gn:admin2_code":"1805.0",
    "gn:admin3_code":"180505.0",
    "gn:asciiname":"Lublica",
    "gn:country_code":"PL",
    "gn:dem":297,
    "gn:feature_class":"P",
    "gn:feature_code":"PPL",
    "gn:name":"Lublica",
    "gn:population":0,
    "gn:timezone":"Europe/Warsaw",
    "iso:country":"PL",
    "name:ceb_x_preferred":[
        "Lublica"
    ],
    "name:nld_x_preferred":[
        "Lublica"
    ],
    "name:pol_x_preferred":[
        "Lublica"
    ],
    "name:ukr_x_preferred":[
        "\u041b\u044e\u0431\u043b\u0438\u0446\u044f"
    ],
    "wof:name":"Lublica",
    "wof:placetype":"locality"
},
  "geometry": {"coordinates":[21.5142,49.80276],"type":"Point"}
}