{
  "type": "Feature",
  "properties": {
    "gn:admin1_code":"79.0",
    "gn:admin2_code":"1607.0",
    "gn:admin3_code":"160702.0",
    "gn:asciiname":"Szklary",
    "gn:cc2":"PL",
    "gn:country_code":"PL",
    "gn:dem":217,
    "gn:feature_class":"P",
    "gn:feature_code":"PPL",
    "gn:name":"Szklary",
    "gn:population":0,
    "gn:timezone":"Europe/Warsaw",
    "iso:country":"PL",
    "name:azb_x_preferred":[
        "\u0634\u06a9\u0644\u0627\u0631\u0647"
    ],
    "name:fas_x_preferred":[
        "\u0634\u06a9\u0644\u0627\u0631\u0647"
    ],
    "name:pol_x_preferred":[
        "Szklary"
    ],
    "name:ukr_x_preferred":[
        "\u0428\u043a\u043b\u044f\u0440\u0438"
    ],
    "name:und_x_variant":[
        "Gl\u00e4sendorf",
        "Sklara"
    ],
    "wof:name":"Szklary",
    "wof:placetype":"locality"
},
  "geometry": {"coordinates":[17.17901,50.59888],"type":"Point"}
}