{
  "type": "Feature",
  "properties": {
    "gn:admin1_code":"79.0",
    "gn:admin2_code":"1607.0",
    "gn:admin3_code":"160702.0",
    "gn:asciiname":"Szklary",
    "gn:cc2":"PL",
    "gn:country_code":"PL",
    "gn:dem":217,
    "gn:feature_class":"P",
    "gn:feature_code":"PPL",
    "gn:name":"Szklary",
    "gn:population":0,
    "gn:timezone":"Europe/Warsaw",
    "iso:country":"PL",
    "name:und_x_variant":[
        "Gl\u00e4sendorf",
        "Sklara",
        "Szklary"
    ],
    "wof:name":"Szklary",
    "wof:placetype":"locality"
},
  "geometry": {"coordinates":[17.17901,50.59888],"type":"Point"}
}