{
  "type": "Feature",
  "properties": {
    "gn:admin1_code":"86.0",
    "gn:admin2_code":"3024.0",
    "gn:admin3_code":"302405.0",
    "gn:asciiname":"Dobrojewo",
    "gn:country_code":"PL",
    "gn:dem":83,
    "gn:feature_class":"P",
    "gn:feature_code":"PPL",
    "gn:name":"Dobrojewo",
    "gn:population":0,
    "gn:timezone":"Europe/Warsaw",
    "iso:country":"PL",
    "name:fra_x_preferred":[
        "Dobrojewo"
    ],
    "name:pol_x_preferred":[
        "Dobrojewo"
    ],
    "name:ukr_x_preferred":[
        "\u0414\u043e\u0431\u0440\u043e\u0454\u0432\u043e"
    ],
    "wof:name":"Dobrojewo",
    "wof:placetype":"locality"
},
  "geometry": {"coordinates":[16.41638,52.64514000000001],"type":"Point"}
}