{
  "type": "Feature",
  "properties": {
    "gn:country":"PL",
    "gn:fcode":"PPL",
    "gn:population":750,
    "iso:country":"PL",
    "name:ara_x_preferred":[
        "\u0628\u0631\u0648\u062f\u064a"
    ],
    "name:azb_x_preferred":[
        "\u0628\u0631\u0648\u062f\u06cc"
    ],
    "name:bel_x_preferred":[
        "\u0411\u0440\u043e\u0434\u044b"
    ],
    "name:bre_x_preferred":[
        "Brody"
    ],
    "name:bul_x_preferred":[
        "\u0411\u0440\u043e\u0434\u0438"
    ],
    "name:cat_x_preferred":[
        "Brodi"
    ],
    "name:ceb_x_preferred":[
        "Brody"
    ],
    "name:ces_x_preferred":[
        "Brody"
    ],
    "name:crh_x_preferred":[
        "Brod\u0131"
    ],
    "name:deu_x_preferred":[
        "Brody"
    ],
    "name:epo_x_preferred":[
        "Brodi"
    ],
    "name:est_x_preferred":[
        "Brod\u00f5"
    ],
    "name:eus_x_preferred":[
        "Brody"
    ],
    "name:fas_x_preferred":[
        "\u0628\u0631\u0648\u062f\u06cc"
    ],
    "name:fra_x_preferred":[
        "Brody"
    ],
    "name:heb_x_preferred":[
        "\u05d1\u05e8\u05d5\u05d3\u05d9"
    ],
    "name:hsb_x_preferred":[
        "Brody"
    ],
    "name:hye_x_preferred":[
        "\u0532\u0580\u0578\u0564\u056b"
    ],
    "name:ita_x_preferred":[
        "Brody"
    ],
    "name:jpn_x_preferred":[
        "\u30d6\u30ed\u30c7\u30a3"
    ],
    "name:kat_x_preferred":[
        "\u10d1\u10e0\u10dd\u10d3\u10d8"
    ],
    "name:kor_x_preferred":[
        "\ube0c\ub85c\ub514"
    ],
    "name:lav_x_preferred":[
        "Brodi"
    ],
    "name:lit_x_preferred":[
        "Brodai"
    ],
    "name:nld_x_preferred":[
        "Brody"
    ],
    "name:nno_x_preferred":[
        "Brody"
    ],
    "name:pol_x_preferred":[
        "Brody"
    ],
    "name:ron_x_preferred":[
        "Brod\u00ee"
    ],
    "name:rus_x_preferred":[
        "\u0411\u0440\u043e\u0434\u044b"
    ],
    "name:spa_x_preferred":[
        "Brody"
    ],
    "name:srp_x_preferred":[
        "\u0411\u0440\u043e\u0434\u0438"
    ],
    "name:swe_x_preferred":[
        "Brody"
    ],
    "name:szl_x_preferred":[
        "Brody"
    ],
    "name:ukr_x_preferred":[
        "\u0411\u0440\u043e\u0434\u0438"
    ],
    "name:und_x_variant":[
        "Gross Blumberg"
    ],
    "name:vie_x_preferred":[
        "Brody"
    ],
    "name:zho_x_preferred":[
        "\u5e03\u7f85\u5fb7"
    ],
    "qs_pg:aaroncc":"PL",
    "qs_pg:gn_country":"PL",
    "qs_pg:gn_fcode":"PPL",
    "qs_pg:gn_pop":750,
    "qs_pg:name":"Brody",
    "qs_pg:name_adm0":"Polska",
    "qs_pg:name_adm1":"Lubuskie",
    "qs_pg:photos_9k":1,
    "qs_pg:photos_9r":1,
    "qs_pg:photos_all":1,
    "qs_pg:photos_sr":0,
    "qs_pg:pop_sr":2,
    "qs_pg:qs_pg_placetype":"locality",
    "qs_pg:qs_pg_placetype_gp":"Town",
    "qs_pg:woe_adm0":23424923,
    "woe:adm0_id":23424923,
    "woe:name_adm0":"Polska",
    "woe:name_adm1":"Lubuskie",
    "woe:placetype":"Town",
    "wof:name":"Brody",
    "wof:placetype":"locality",
    "wof:population":750
},
  "geometry": {"coordinates":[15.43433,52.06115],"type":"Point"}
}