{
  "type": "Feature",
  "properties": {
    "gn:gn_country":"PL",
    "gn:gn_fcode":"PPL",
    "gn:gn_pop":750,
    "gn:population":750,
    "iso:country":"PL",
    "name:unk_x_variant":[
        "Gross Blumberg"
    ],
    "qs_pg:aaroncc":"PL",
    "qs_pg:gn_country":"PL",
    "qs_pg:gn_fcode":"PPL",
    "qs_pg:gn_pop":750,
    "qs_pg:name":"Brody",
    "qs_pg:name_adm0":"Polska",
    "qs_pg:name_adm1":"Lubuskie",
    "qs_pg:photos_9k":1,
    "qs_pg:photos_9r":1,
    "qs_pg:photos_all":1,
    "qs_pg:photos_sr":0,
    "qs_pg:pop_sr":2,
    "qs_pg:qs_pg_placetype":"locality",
    "qs_pg:qs_pg_placetype_gp":"Town",
    "qs_pg:woe_adm0":23424923,
    "woe:adm0_id":23424923,
    "woe:name_adm0":"Polska",
    "woe:name_adm1":"Lubuskie",
    "woe:placetype":"Town",
    "wof:name":"Brody",
    "wof:placetype":"locality",
    "wof:population":750
},
  "geometry": {"coordinates":[15.43433,52.06115],"type":"Point"}
}