{
  "type": "Feature",
  "properties": {
    "gn:admin1_code":"77.0",
    "gn:admin2_code":"1214.0",
    "gn:admin3_code":"121402.0",
    "gn:asciiname":"Wroczkow",
    "gn:country_code":"PL",
    "gn:dem":177,
    "gn:feature_class":"P",
    "gn:feature_code":"PPL",
    "gn:name":"Wroczk\u00f3w",
    "gn:population":0,
    "gn:timezone":"Europe/Warsaw",
    "iso:country":"PL",
    "wof:name":"Wroczkow",
    "wof:placetype":"locality"
},
  "geometry": {"coordinates":[20.55,50.16667],"type":"Point"}
}