{
  "type": "Feature",
  "properties": {
    "gn:admin1_code":"73.0",
    "gn:admin2_code":"401.0",
    "gn:admin3_code":"40104.0",
    "gn:asciiname":"Kolonia Przybranowo",
    "gn:country_code":"PL",
    "gn:dem":78,
    "gn:feature_class":"P",
    "gn:feature_code":"PPL",
    "gn:name":"Kolonia Przybranowo",
    "gn:population":0,
    "gn:timezone":"Europe/Warsaw",
    "iso:country":"PL",
    "name:und_x_variant":[
        "Przybranowo Kolonia",
        "Kolonia Przybranowo"
    ],
    "wof:name":"Kolonia Przybranowo",
    "wof:placetype":"locality"
},
  "geometry": {"coordinates":[18.64453,52.82898],"type":"Point"}
}