{
  "type": "Feature",
  "properties": {
    "gn:admin1_code":"82.0",
    "gn:admin2_code":"2205.0",
    "gn:admin3_code":"220507.0",
    "gn:asciiname":"Kistowko",
    "gn:country_code":"PL",
    "gn:dem":209,
    "gn:feature_class":"P",
    "gn:feature_code":"PPL",
    "gn:name":"Kistowko",
    "gn:population":0,
    "gn:timezone":"Europe/Warsaw",
    "iso:country":"PL",
    "name:ceb_x_preferred":[
        "Kistowko"
    ],
    "name:pol_x_preferred":[
        "Kist\u00f3wko"
    ],
    "name:und_x_variant":[
        "Kistowo",
        "Kistowko"
    ],
    "wof:name":"Kistowko",
    "wof:placetype":"locality"
},
  "geometry": {"coordinates":[17.73091,54.27921],"type":"Point"}
}