{
  "type": "Feature",
  "properties": {
    "gn:admin1_code":"78.0",
    "gn:admin2_code":"1415.0",
    "gn:admin3_code":"141509.0",
    "gn:asciiname":"Dobroleka",
    "gn:country_code":"PL",
    "gn:dem":94,
    "gn:feature_class":"P",
    "gn:feature_code":"PPL",
    "gn:name":"Dobro\u0142\u0119ka",
    "gn:population":0,
    "gn:timezone":"Europe/Warsaw",
    "iso:country":"PL",
    "name:fra_x_preferred":[
        "Dobro\u0142\u0119ka"
    ],
    "name:pol_x_preferred":[
        "Dobro\u0142\u0119ka"
    ],
    "name:ukr_x_preferred":[
        "\u0414\u043e\u0431\u0440\u043e\u043b\u0435\u043d\u043a\u0430"
    ],
    "wof:name":"Dobroleka",
    "wof:placetype":"locality"
},
  "geometry": {"coordinates":[21.49115,53.01633],"type":"Point"}
}