{
  "type": "Feature",
  "properties": {
    "gn:country":"PL",
    "gn:fcode":"PPL",
    "gn:population":854,
    "iso:country":"PL",
    "name:ast_x_preferred":[
        "Kije"
    ],
    "name:ceb_x_preferred":[
        "Kije"
    ],
    "name:eng_x_preferred":[
        "Kije"
    ],
    "name:fra_x_preferred":[
        "Kije"
    ],
    "name:jpn_x_preferred":[
        "\u30ad\u30a4\u30a7"
    ],
    "name:pol_x_preferred":[
        "Kije"
    ],
    "name:ukr_x_preferred":[
        "\u041a\u0456\u0454"
    ],
    "qs_pg:aaroncc":"PL",
    "qs_pg:gn_country":"PL",
    "qs_pg:gn_fcode":"PPL",
    "qs_pg:gn_pop":854,
    "qs_pg:name":"Kije",
    "qs_pg:name_adm0":"Polska",
    "qs_pg:name_adm1":"Lubuskie",
    "qs_pg:photos_9r":0,
    "qs_pg:photos_sr":0,
    "qs_pg:pop_sr":2,
    "qs_pg:qs_pg_placetype":"locality",
    "qs_pg:qs_pg_placetype_gp":"Town",
    "qs_pg:woe_adm0":23424923,
    "woe:adm0_id":23424923,
    "woe:name_adm0":"Polska",
    "woe:name_adm1":"Lubuskie",
    "woe:placetype":"Town",
    "wof:name":"Kije",
    "wof:placetype":"locality",
    "wof:population":854
},
  "geometry": {"coordinates":[15.54085,52.0986],"type":"Point"}
}