{
  "type": "Feature",
  "properties": {
    "gn:admin1_code":"85.0",
    "gn:admin2_code":"2802.0",
    "gn:admin3_code":"280202.0",
    "gn:asciiname":"Cieletnik",
    "gn:country_code":"PL",
    "gn:dem":28,
    "gn:feature_class":"P",
    "gn:feature_code":"PPL",
    "gn:name":"Ciel\u0119tnik",
    "gn:population":0,
    "gn:timezone":"Europe/Warsaw",
    "iso:country":"PL",
    "name:azb_x_preferred":[
        "\u0686\u06cc\u0644\u0646\u062a\u0646\u0642\u06a9"
    ],
    "name:fas_x_preferred":[
        "\u0686\u06cc\u0644\u0646\u062a\u0646\u06af\u06a9"
    ],
    "name:fra_x_preferred":[
        "Ciel\u0119tnik"
    ],
    "name:nld_x_preferred":[
        "Ciel\u0119tnik"
    ],
    "name:pol_x_preferred":[
        "Ciel\u0119tnik"
    ],
    "name:vie_x_preferred":[
        "Ciel\u0119tnik"
    ],
    "wof:name":"Cieletnik",
    "wof:placetype":"locality"
},
  "geometry": {"coordinates":[19.75479,54.37306],"type":"Point"}
}