{
  "type": "Feature",
  "properties": {
    "gn:admin1_code":"78.0",
    "gn:admin2_code":"1426.0",
    "gn:admin3_code":"142606.0",
    "gn:asciiname":"Lozy",
    "gn:country_code":"PL",
    "gn:dem":169,
    "gn:feature_class":"P",
    "gn:feature_code":"PPL",
    "gn:name":"\u0141ozy",
    "gn:population":0,
    "gn:timezone":"Europe/Warsaw",
    "iso:country":"PL",
    "name:fra_x_preferred":[
        "\u0141ozy"
    ],
    "name:lit_x_preferred":[
        "Lozai"
    ],
    "name:pol_x_preferred":[
        "\u0141ozy"
    ],
    "name:szl_x_preferred":[
        "\u0141ozy"
    ],
    "name:ukr_x_preferred":[
        "\u041b\u043e\u0437\u0438"
    ],
    "wof:name":"Lozy",
    "wof:placetype":"locality"
},
  "geometry": {"coordinates":[22.49116,52.30444],"type":"Point"}
}