{
  "type": "Feature",
  "properties": {
    "gn:admin1_code":"78.0",
    "gn:admin2_code":"1426.0",
    "gn:admin3_code":"142607.0",
    "gn:asciiname":"Lysow",
    "gn:country_code":"PL",
    "gn:dem":148,
    "gn:feature_class":"P",
    "gn:feature_code":"PPL",
    "gn:name":"\u0141ys\u00f3w",
    "gn:population":0,
    "gn:timezone":"Europe/Warsaw",
    "iso:country":"PL",
    "name:ceb_x_preferred":[
        "\u0141ys\u00f3w"
    ],
    "name:fra_x_preferred":[
        "\u0141ys\u00f3w"
    ],
    "name:lit_x_preferred":[
        "Lisuvas"
    ],
    "name:pol_x_preferred":[
        "\u0141ys\u00f3w"
    ],
    "name:szl_x_preferred":[
        "\u0141ys\u016fw"
    ],
    "name:ukr_x_preferred":[
        "\u041b\u0438\u0441\u0443\u0432"
    ],
    "wof:name":"Lysow",
    "wof:placetype":"locality"
},
  "geometry": {"coordinates":[22.69157,52.29294],"type":"Point"}
}