{
  "type": "Feature",
  "properties": {
    "gn:admin1_code":"81.0",
    "gn:admin2_code":"2003.0",
    "gn:admin3_code":"200303.0",
    "gn:asciiname":"Pilipki",
    "gn:country_code":"PL",
    "gn:dem":137,
    "gn:feature_class":"P",
    "gn:feature_code":"PPL",
    "gn:name":"Pilipki",
    "gn:population":0,
    "gn:timezone":"Europe/Warsaw",
    "iso:country":"PL",
    "name:azb_x_preferred":[
        "\u067e\u06cc\u0644\u06cc\u067e\u06a9\u06cc"
    ],
    "name:fas_x_preferred":[
        "\u067e\u06cc\u0644\u06cc\u067e\u06a9\u06cc"
    ],
    "name:fra_x_preferred":[
        "Pilipki"
    ],
    "name:lit_x_preferred":[
        "Pilipkai"
    ],
    "name:pol_x_preferred":[
        "Pilipki"
    ],
    "name:ukr_x_preferred":[
        "\u041f\u0456\u043b\u0456\u043f\u043a\u0456"
    ],
    "wof:name":"Pilipki",
    "wof:placetype":"locality"
},
  "geometry": {"coordinates":[23.33424,52.83394000000001],"type":"Point"}
}