{
  "type": "Feature",
  "properties": {
    "gn:admin1_code":"72.0",
    "gn:admin2_code":"225.0",
    "gn:admin3_code":"22507.0",
    "gn:asciiname":"Kozmin",
    "gn:country_code":"PL",
    "gn:dem":222,
    "gn:feature_class":"P",
    "gn:feature_code":"PPL",
    "gn:name":"Ko\u017amin",
    "gn:population":0,
    "gn:timezone":"Europe/Warsaw",
    "iso:country":"PL",
    "name:deu_x_historical":[
        "Kosma"
    ],
    "name:deu_x_preferred":[
        "Kosma"
    ],
    "name:und_x_variant":[
        "Ko\u017cmin"
    ],
    "wof:name":"Kozmin",
    "wof:placetype":"locality"
},
  "geometry": {"coordinates":[15.022,51.09431],"type":"Point"}
}