{
  "type": "Feature",
  "properties": {
    "gn:admin1_code":"87.0",
    "gn:admin2_code":"3205.0",
    "gn:admin3_code":"320508.0",
    "gn:asciiname":"Sadlenko",
    "gn:cc2":"PL",
    "gn:country_code":"PL",
    "gn:dem":14,
    "gn:feature_class":"P",
    "gn:feature_code":"PPL",
    "gn:name":"Sadlenko",
    "gn:population":0,
    "gn:timezone":"Europe/Warsaw",
    "iso:country":"PL",
    "name:pol_x_preferred":[
        "Sadlenko"
    ],
    "name:und_x_variant":[
        "Zedlinerberg",
        "Sadlenko"
    ],
    "name:urd_x_preferred":[
        "\u0633\u062f\u0644\u06cc\u0646\u06a9\u0648"
    ],
    "name:vie_x_preferred":[
        "Sadlenko"
    ],
    "wof:name":"Sadlenko",
    "wof:placetype":"locality"
},
  "geometry": {"coordinates":[15.19701,54.05123],"type":"Point"}
}