{
  "type": "Feature",
  "properties": {
    "gn:admin1_code":"78.0",
    "gn:admin2_code":"1420.0",
    "gn:admin3_code":"142008.0",
    "gn:asciiname":"Jurzyn",
    "gn:country_code":"PL",
    "gn:dem":109,
    "gn:feature_class":"P",
    "gn:feature_code":"PPL",
    "gn:name":"Jurzyn",
    "gn:population":0,
    "gn:timezone":"Europe/Warsaw",
    "iso:country":"PL",
    "name:fra_x_preferred":[
        "Jurzyn"
    ],
    "name:pol_x_preferred":[
        "Jurzyn"
    ],
    "name:ukr_x_preferred":[
        "\u042e\u0436\u0438\u043d"
    ],
    "wof:name":"Jurzyn",
    "wof:placetype":"locality"
},
  "geometry": {"coordinates":[20.67978,52.70851999999999],"type":"Point"}
}