{
  "type": "Feature",
  "properties": {
    "gn:admin1_code":"83.0",
    "gn:admin2_code":"2469.0",
    "gn:admin3_code":"246901.0",
    "gn:asciiname":"Zespol dzielnic srodmiejskich",
    "gn:country_code":"PL",
    "gn:dem":272,
    "gn:feature_class":"P",
    "gn:feature_code":"PPL",
    "gn:name":"Zesp\u00f3\u0142 dzielnic \u015br\u00f3dmiejskich",
    "gn:population":0,
    "gn:timezone":"Europe/Warsaw",
    "iso:country":"PL",
    "wof:name":"Zespol dzielnic srodmiejskich",
    "wof:placetype":"locality"
},
  "geometry": {"coordinates":[19.02437,50.26549],"type":"Point"}
}