{
  "type": "Feature",
  "properties": {
    "gn:admin1_code":"77.0",
    "gn:admin2_code":"1205.0",
    "gn:admin3_code":"120509.0",
    "gn:asciiname":"Malastow",
    "gn:country_code":"PL",
    "gn:dem":406,
    "gn:feature_class":"P",
    "gn:feature_code":"PPL",
    "gn:name":"Ma\u0142ast\u00f3w",
    "gn:population":0,
    "gn:timezone":"Europe/Warsaw",
    "iso:country":"PL",
    "name:azb_x_preferred":[
        "\u0645\u0627\u0648\u0627\u0633\u062a\u0648\u0648"
    ],
    "name:fas_x_preferred":[
        "\u0645\u0627\u0648\u0627\u0633\u062a\u0648\u0648"
    ],
    "name:pol_x_preferred":[
        "Ma\u0142ast\u00f3w"
    ],
    "name:rue_x_preferred":[
        "\u041c\u0430\u043b\u0430\u0441\u0442\u0456\u0432"
    ],
    "name:rus_x_preferred":[
        "\u041c\u0430\u043b\u0430\u0441\u0442\u0443\u0432"
    ],
    "name:ukr_x_preferred":[
        "\u041c\u0430\u043b\u0430\u0441\u0442\u0456\u0432"
    ],
    "wof:name":"Malastow",
    "wof:placetype":"locality"
},
  "geometry": {"coordinates":[21.24464,49.56764],"type":"Point"}
}