{
  "type": "Feature",
  "properties": {
    "gn:admin1_code":"78.0",
    "gn:admin2_code":"1463.0",
    "gn:admin3_code":"146301.0",
    "gn:asciiname":"Konczyce",
    "gn:country_code":"PL",
    "gn:dem":191,
    "gn:feature_class":"P",
    "gn:feature_code":"PPL",
    "gn:name":"Ko\u0144czyce",
    "gn:population":0,
    "gn:timezone":"Europe/Warsaw",
    "iso:country":"PL",
    "wof:name":"Konczyce",
    "wof:placetype":"neighbourhood"
},
  "geometry": {"coordinates":[21.06744,51.37125],"type":"Point"}
}