{
  "type": "Feature",
  "properties": {
    "gn:admin1_code":"75.0",
    "gn:admin2_code":"620.0",
    "gn:admin3_code":"62009.0",
    "gn:asciiname":"Wolka Horyszowska",
    "gn:country_code":"PL",
    "gn:dem":215,
    "gn:feature_class":"P",
    "gn:feature_code":"PPL",
    "gn:name":"W\u00f3lka Horyszowska",
    "gn:population":0,
    "gn:timezone":"Europe/Warsaw",
    "iso:country":"PL",
    "name:fra_x_preferred":[
        "W\u00f3lka Horyszowska"
    ],
    "name:pol_x_preferred":[
        "W\u00f3lka Horyszowska"
    ],
    "name:ukr_x_preferred":[
        "\u0412\u0443\u043b\u044c\u043a\u0430-\u0413\u043e\u0440\u0438\u0448\u043e\u0432\u0441\u044c\u043a\u0430"
    ],
    "wof:name":"Wolka Horyszowska",
    "wof:placetype":"locality"
},
  "geometry": {"coordinates":[23.40707,50.73809],"type":"Point"}
}