{
  "type": "Feature",
  "properties": {
    "gn:admin1_code":"75.0",
    "gn:admin2_code":"620.0",
    "gn:admin3_code":"62009.0",
    "gn:asciiname":"Wolka Horyszowska",
    "gn:country_code":"PL",
    "gn:dem":215,
    "gn:feature_class":"P",
    "gn:feature_code":"PPL",
    "gn:name":"W\u00f3lka Horyszowska",
    "gn:population":0,
    "gn:timezone":"Europe/Warsaw",
    "iso:country":"PL",
    "name:und_x_variant":[
        "W\u00f3lka Horyszowska"
    ],
    "wof:name":"Wolka Horyszowska",
    "wof:placetype":"locality"
},
  "geometry": {"coordinates":[23.40707,50.73809],"type":"Point"}
}