{
  "type": "Feature",
  "properties": {
    "gn:admin1_code":"86.0",
    "gn:admin2_code":"3007.0",
    "gn:admin3_code":"300705.0",
    "gn:asciiname":"Tymianek",
    "gn:country_code":"PL",
    "gn:dem":128,
    "gn:feature_class":"P",
    "gn:feature_code":"PPL",
    "gn:name":"Tymianek",
    "gn:population":0,
    "gn:timezone":"Europe/Warsaw",
    "iso:country":"PL",
    "name:azb_x_preferred":[
        "\u062a\u06cc\u0645\u06cc\u0627\u0646\u06a9"
    ],
    "name:ceb_x_preferred":[
        "Tymianek"
    ],
    "name:fas_x_preferred":[
        "\u062a\u06cc\u0645\u06cc\u0627\u0646\u06a9"
    ],
    "name:pol_x_preferred":[
        "Tymianek"
    ],
    "name:ukr_x_preferred":[
        "\u0422\u0438\u043c\u044f\u043d\u0435\u043a"
    ],
    "wof:name":"Tymianek",
    "wof:placetype":"locality"
},
  "geometry": {"coordinates":[18.34635,51.80686],"type":"Point"}
}