{
  "type": "Feature",
  "properties": {
    "gn:admin1_code":"72.0",
    "gn:admin2_code":"221.0",
    "gn:admin3_code":"22106.0",
    "gn:asciiname":"Kowalowa",
    "gn:country_code":"PL",
    "gn:dem":531,
    "gn:feature_class":"P",
    "gn:feature_code":"PPL",
    "gn:name":"Kowalowa",
    "gn:population":0,
    "gn:timezone":"Europe/Warsaw",
    "iso:country":"PL",
    "name:deu_x_preferred":[
        "Kowalowa"
    ],
    "name:pol_x_preferred":[
        "Kowalowa"
    ],
    "name:ukr_x_preferred":[
        "\u041a\u043e\u0432\u0430\u043b\u044c\u043e\u0432\u0430"
    ],
    "wof:name":"Kowalowa",
    "wof:placetype":"locality"
},
  "geometry": {"coordinates":[16.20569,50.68471],"type":"Point"}
}