{
  "type": "Feature",
  "properties": {
    "gn:admin1_code":"84.0",
    "gn:admin2_code":"2611.0",
    "gn:admin3_code":"261104.0",
    "gn:asciiname":"Wydryszow",
    "gn:country_code":"PL",
    "gn:dem":256,
    "gn:feature_class":"P",
    "gn:feature_code":"PPL",
    "gn:name":"Wydrysz\u00f3w",
    "gn:population":0,
    "gn:timezone":"Europe/Warsaw",
    "iso:country":"PL",
    "wof:name":"Wydryszow",
    "wof:placetype":"locality"
},
  "geometry": {"coordinates":[21.09829,50.9621],"type":"Point"}
}