{
  "type": "Feature",
  "properties": {
    "gn:admin1_code":"80.0",
    "gn:admin2_code":"1805.0",
    "gn:admin3_code":"180506.0",
    "gn:asciiname":"Grab",
    "gn:country_code":"PL",
    "gn:dem":485,
    "gn:feature_class":"P",
    "gn:feature_code":"PPL",
    "gn:name":"Grab",
    "gn:population":0,
    "gn:timezone":"Europe/Warsaw",
    "iso:country":"PL",
    "name:azb_x_preferred":[
        "\u0642\u0631\u0627\u0628"
    ],
    "name:fas_x_preferred":[
        "\u06af\u0631\u0627\u0628"
    ],
    "name:pol_x_preferred":[
        "Grab"
    ],
    "name:rue_x_preferred":[
        "\u0413\u0440\u0430\u0431"
    ],
    "name:rus_x_preferred":[
        "\u0413\u0440\u0430\u0431"
    ],
    "name:ukr_x_preferred":[
        "\u0413\u0440\u0430\u0431"
    ],
    "wof:name":"Grab",
    "wof:placetype":"locality"
},
  "geometry": {"coordinates":[21.43965,49.44078],"type":"Point"}
}