{
  "type": "Feature",
  "properties": {
    "gn:admin1_code":"78.0",
    "gn:admin2_code":"1407.0",
    "gn:admin3_code":"140705.0",
    "gn:asciiname":"Piotrkowice",
    "gn:country_code":"PL",
    "gn:dem":103,
    "gn:feature_class":"P",
    "gn:feature_code":"PPL",
    "gn:name":"Piotrkowice",
    "gn:population":0,
    "gn:timezone":"Europe/Warsaw",
    "iso:country":"PL",
    "name:fra_x_preferred":[
        "Piotrkowice"
    ],
    "name:pol_x_preferred":[
        "Piotrkowice"
    ],
    "name:ukr_x_preferred":[
        "\u041f\u0439\u043e\u0442\u0440\u043a\u043e\u0432\u0456\u0446\u0435"
    ],
    "wof:name":"Piotrkowice",
    "wof:placetype":"locality"
},
  "geometry": {"coordinates":[21.54282000000001,51.63399999999999],"type":"Point"}
}