{
  "type": "Feature",
  "properties": {
    "gn:admin1_code":"81.0",
    "gn:admin2_code":"2014.0",
    "gn:admin3_code":"201403.0",
    "gn:asciiname":"Ozary",
    "gn:country_code":"PL",
    "gn:dem":110,
    "gn:feature_class":"P",
    "gn:feature_code":"PPL",
    "gn:name":"O\u017cary",
    "gn:population":0,
    "gn:timezone":"Europe/Warsaw",
    "iso:country":"PL",
    "name:lit_x_preferred":[
        "O\u017eari Vielkiai"
    ],
    "name:pol_x_preferred":[
        "O\u017cary Wielkie"
    ],
    "name:ukr_x_preferred":[
        "\u041e\u0436\u0430\u0440\u0438-\u0412\u0435\u043b\u0438\u043a\u0456"
    ],
    "name:und_x_variant":[
        "O\u017cary"
    ],
    "wof:name":"Ozary",
    "wof:placetype":"locality"
},
  "geometry": {"coordinates":[22.49352,53.12217],"type":"Point"}
}