{
  "type": "Feature",
  "properties": {
    "gn:admin1_code":"82.0",
    "gn:admin2_code":"2212.0",
    "gn:admin3_code":"221207.0",
    "gn:asciiname":"Rzechcino",
    "gn:country_code":"PL",
    "gn:dem":60,
    "gn:feature_class":"P",
    "gn:feature_code":"PPL",
    "gn:name":"Rzechcino",
    "gn:population":0,
    "gn:timezone":"Europe/Warsaw",
    "iso:country":"PL",
    "name:ceb_x_preferred":[
        "Rzechcino"
    ],
    "name:csb_x_preferred":[
        "Rzechc\u00ebno"
    ],
    "name:deu_x_preferred":[
        "Rzechcino"
    ],
    "name:pol_x_preferred":[
        "Rzechcino"
    ],
    "name:ukr_x_preferred":[
        "\u0416\u0435\u0445\u0446\u0438\u043d\u043e"
    ],
    "wof:name":"Rzechcino",
    "wof:placetype":"locality"
},
  "geometry": {"coordinates":[17.45773,54.53115],"type":"Point"}
}