{
  "type": "Feature",
  "properties": {
    "gn:admin1_code":"72.0",
    "gn:admin2_code":"205.0",
    "gn:admin3_code":"20503.0",
    "gn:asciiname":"Kondratow",
    "gn:country_code":"PL",
    "gn:dem":322,
    "gn:feature_class":"P",
    "gn:feature_code":"PPL",
    "gn:name":"Kondrat\u00f3w",
    "gn:population":0,
    "gn:timezone":"Europe/Warsaw",
    "iso:country":"PL",
    "name:deu_x_preferred":[
        "Kondrat\u00f3w"
    ],
    "name:pol_x_preferred":[
        "Kondrat\u00f3w"
    ],
    "name:ukr_x_preferred":[
        "\u041a\u043e\u043d\u0434\u0440\u0430\u0442\u0443\u0432"
    ],
    "wof:name":"Kondratow",
    "wof:placetype":"locality"
},
  "geometry": {"coordinates":[15.97275,51.04744],"type":"Point"}
}