{
  "type": "Feature",
  "properties": {
    "iso:country":"PL",
    "name:pol_x_preferred":[
        "Ko\u0142aczkowo"
    ],
    "wof:coterminous":[
        1125324237
    ],
    "wof:name":"Ko\u0142aczkowo",
    "wof:placetype":"locality"
},
  "geometry": {"coordinates":[17.6373248755756,52.2190905559761],"type":"Point"}
}