{
  "type": "Feature",
  "properties": {
    "iso:country":"PL",
    "name:ceb_x_preferred":[
        "Ko\u0142aczkowo"
    ],
    "name:deu_x_preferred":[
        "Ko\u0142aczkowo"
    ],
    "name:fra_x_preferred":[
        "Ko\u0142aczkowo"
    ],
    "name:nld_x_preferred":[
        "Ko\u0142aczkowo"
    ],
    "name:pol_x_preferred":[
        "Ko\u0142aczkowo"
    ],
    "name:ukr_x_preferred":[
        "\u041a\u043e\u043b\u0430\u0447\u043a\u043e\u0432\u043e"
    ],
    "wof:coterminous":[
        1125324237
    ],
    "wof:name":"Ko\u0142aczkowo",
    "wof:placetype":"locality"
},
  "geometry": {"coordinates":[17.6373248755756,52.2190905559761],"type":"Point"}
}