{
  "type": "Feature",
  "properties": {
    "gn:admin1_code":"78.0",
    "gn:admin2_code":"1415.0",
    "gn:admin3_code":"141503.0",
    "gn:asciiname":"Wisniewo Wielkie",
    "gn:country_code":"PL",
    "gn:dem":110,
    "gn:feature_class":"P",
    "gn:feature_code":"PPL",
    "gn:name":"Wi\u015bniewo Wielkie",
    "gn:population":0,
    "gn:timezone":"Europe/Warsaw",
    "iso:country":"PL",
    "name:und_x_variant":[
        "Wi\u015bniewo",
        "Wi\u015bniewo Wielkie"
    ],
    "wof:name":"Wisniewo Wielkie",
    "wof:placetype":"locality"
},
  "geometry": {"coordinates":[21.84632,52.95898],"type":"Point"}
}