{
  "type": "Feature",
  "properties": {
    "gn:admin1_code":"78.0",
    "gn:admin2_code":"1420.0",
    "gn:admin3_code":"142007.0",
    "gn:asciiname":"Sosenkowo",
    "gn:country_code":"PL",
    "gn:dem":127,
    "gn:feature_class":"P",
    "gn:feature_code":"PPL",
    "gn:name":"Sosenkowo",
    "gn:population":0,
    "gn:timezone":"Europe/Warsaw",
    "iso:country":"PL",
    "name:fra_x_preferred":[
        "Sosenkowo"
    ],
    "name:pol_x_preferred":[
        "Sosenkowo"
    ],
    "name:ukr_x_preferred":[
        "\u0421\u043e\u0441\u0435\u043d\u043a\u043e\u0432\u043e"
    ],
    "wof:name":"Sosenkowo",
    "wof:placetype":"locality"
},
  "geometry": {"coordinates":[20.23521,52.53203000000001],"type":"Point"}
}