{
  "type": "Feature",
  "properties": {
    "gn:admin1_code":"77.0",
    "gn:admin2_code":"1207.0",
    "gn:admin3_code":"120705.0",
    "gn:asciiname":"Kicznia",
    "gn:country_code":"PL",
    "gn:dem":491,
    "gn:feature_class":"P",
    "gn:feature_code":"PPL",
    "gn:name":"Kicznia",
    "gn:population":0,
    "gn:timezone":"Europe/Warsaw",
    "iso:country":"PL",
    "name:pol_x_preferred":[
        "Kicznia"
    ],
    "name:ukr_x_preferred":[
        "\u041a\u0456\u0447\u043d\u044f"
    ],
    "wof:name":"Kicznia",
    "wof:placetype":"locality"
},
  "geometry": {"coordinates":[20.35,49.58333],"type":"Point"}
}