{
  "type": "Feature",
  "properties": {
    "iso:country":"PL",
    "name:dut_x_preferred":[
        "Rozkopaczew"
    ],
    "name:eng_x_preferred":[
        "Rozkopaczew"
    ],
    "name:fra_x_preferred":[
        "Rozkopaczew"
    ],
    "name:fre_x_preferred":[
        "Rozkopaczew"
    ],
    "name:nld_x_preferred":[
        "Rozkopaczew"
    ],
    "name:pol_x_preferred":[
        "Rozkopaczew"
    ],
    "qs:a0":"Rzeczpospolita Polska",
    "qs:a1":"*Lubelskie",
    "qs:a1r":"0",
    "qs:a2":"Lubartowski",
    "qs:adm0":"Rzeczpospolita Polska",
    "qs:la_lc":"*",
    "qs:level":"locality",
    "qs:loc":"Rozkopaczew",
    "qs:loc_alt":"Rozkopaczew",
    "qs:pop":0,
    "qs:type":"buffered point",
    "wd:wordcount":92,
    "wof:name":"Rozkopaczew",
    "wof:placetype":"locality"
},
  "geometry": {"coordinates":[22.832543,51.424446],"type":"Point"}
}