{
  "type": "Feature",
  "properties": {
    "iso:country":"PL",
    "name:ast_x_preferred":[
        "Rozkopaczew"
    ],
    "name:eng_x_preferred":[
        "Rozkopaczew"
    ],
    "name:fra_x_preferred":[
        "Rozkopaczew"
    ],
    "name:nld_x_preferred":[
        "Rozkopaczew"
    ],
    "name:pol_x_preferred":[
        "Rozkopaczew"
    ],
    "name:ukr_x_preferred":[
        "\u0420\u043e\u0437\u043a\u043e\u043f\u0430\u0447\u0435\u0432"
    ],
    "qs:a0":"Rzeczpospolita Polska",
    "qs:a1":"*Lubelskie",
    "qs:a1r":"0",
    "qs:a2":"Lubartowski",
    "qs:adm0":"Rzeczpospolita Polska",
    "qs:la_lc":"*",
    "qs:level":"locality",
    "qs:loc":"Rozkopaczew",
    "qs:loc_alt":"Rozkopaczew",
    "qs:pop":0,
    "qs:type":"buffered point",
    "wd:wordcount":92,
    "wof:name":"Rozkopaczew",
    "wof:placetype":"locality"
},
  "geometry": {"coordinates":[22.832543,51.424446],"type":"Point"}
}