{
  "type": "Feature",
  "properties": {
    "gn:country":"PL",
    "gn:fcode":"PPL",
    "gn:population":141,
    "iso:country":"PL",
    "name:ceb_x_preferred":[
        "Korczew"
    ],
    "name:deu_x_preferred":[
        "Korczew"
    ],
    "name:fra_x_preferred":[
        "Korczew"
    ],
    "name:nld_x_preferred":[
        "Korczew"
    ],
    "name:pol_x_preferred":[
        "Korczew"
    ],
    "name:szl_x_preferred":[
        "Korczew"
    ],
    "name:ukr_x_preferred":[
        "\u041a\u043e\u0440\u0447\u0435\u0432"
    ],
    "qs_pg:aaroncc":"PL",
    "qs_pg:gn_country":"PL",
    "qs_pg:gn_fcode":"PPL",
    "qs_pg:gn_pop":141,
    "qs_pg:name":"Korczew",
    "qs_pg:name_adm0":"Polska",
    "qs_pg:name_adm1":"\u0141\u00f3dzkie",
    "qs_pg:photos_9r":0,
    "qs_pg:photos_sr":0,
    "qs_pg:pop_sr":1,
    "qs_pg:qs_pg_placetype":"locality",
    "qs_pg:qs_pg_placetype_gp":"Town",
    "qs_pg:woe_adm0":23424923,
    "woe:adm0_id":23424923,
    "woe:name_adm0":"Polska",
    "woe:name_adm1":"\u0141\u00f3dzkie",
    "woe:placetype":"Town",
    "wof:name":"Korczew",
    "wof:placetype":"locality",
    "wof:population":141
},
  "geometry": {"coordinates":[19.45121,51.35661],"type":"Point"}
}