{
  "type": "Feature",
  "properties": {
    "gn:admin1_code":"78.0",
    "gn:admin2_code":"1409.0",
    "gn:admin3_code":"140905.0",
    "gn:asciiname":"Krzyzanowka",
    "gn:country_code":"PL",
    "gn:dem":199,
    "gn:feature_class":"P",
    "gn:feature_code":"PPL",
    "gn:name":"Krzy\u017can\u00f3wka",
    "gn:population":0,
    "gn:timezone":"Europe/Warsaw",
    "iso:country":"PL",
    "name:und_x_variant":[
        "Krzy\u017can\u00f3wka"
    ],
    "wof:name":"Krzyzanowka",
    "wof:placetype":"locality"
},
  "geometry": {"coordinates":[21.41534,51.08571],"type":"Point"}
}