{
  "type": "Feature",
  "properties": {
    "gn:admin1_code":"85.0",
    "gn:admin2_code":"2811.0",
    "gn:admin3_code":"281101.0",
    "gn:asciiname":"Wilunie",
    "gn:cc2":"PL",
    "gn:country_code":"PL",
    "gn:dem":181,
    "gn:feature_class":"P",
    "gn:feature_code":"PPL",
    "gn:name":"Wi\u0142unie",
    "gn:population":0,
    "gn:timezone":"Europe/Warsaw",
    "iso:country":"PL",
    "name:deu_x_preferred":[
        "Wi\u0142unie"
    ],
    "name:fra_x_preferred":[
        "Wi\u0142unie"
    ],
    "name:pol_x_preferred":[
        "Wi\u0142unie"
    ],
    "name:ukr_x_preferred":[
        "\u0412\u0456\u043b\u0443\u043d\u0435"
    ],
    "name:und_x_variant":[
        "Willuhnen",
        "Wi\u0142unie"
    ],
    "wof:name":"Wilunie",
    "wof:placetype":"locality"
},
  "geometry": {"coordinates":[20.45551,53.28564],"type":"Point"}
}