{
  "type": "Feature",
  "properties": {
    "gn:admin1_code":"79.0",
    "gn:admin2_code":"1601.0",
    "gn:admin3_code":"160105.0",
    "gn:asciiname":"Stawy",
    "gn:country_code":"PL",
    "gn:dem":135,
    "gn:feature_class":"P",
    "gn:feature_code":"PPL",
    "gn:name":"Stawy",
    "gn:population":0,
    "gn:timezone":"Europe/Warsaw",
    "iso:country":"PL",
    "name:pol_x_preferred":[
        "Stawy"
    ],
    "wof:name":"Stawy",
    "wof:placetype":"locality"
},
  "geometry": {"coordinates":[17.59358,50.87965],"type":"Point"}
}