{
  "type": "Feature",
  "properties": {
    "gn:admin1_code":"72.0",
    "gn:admin2_code":"224.0",
    "gn:admin3_code":"22404.0",
    "gn:asciiname":"Michalkow",
    "gn:country_code":"PL",
    "gn:dem":657,
    "gn:feature_class":"P",
    "gn:feature_code":"PPL",
    "gn:name":"Micha\u0142k\u00f3w",
    "gn:population":0,
    "gn:timezone":"Europe/Warsaw",
    "iso:country":"PL",
    "wof:name":"Michalkow",
    "wof:placetype":"locality"
},
  "geometry": {"coordinates":[16.64394,50.57564],"type":"Point"}
}