{
  "type": "Feature",
  "properties": {
    "gn:admin1_code":"87.0",
    "gn:admin2_code":"3205.0",
    "gn:admin3_code":"320503.0",
    "gn:asciiname":"Trzeszyn",
    "gn:country_code":"PL",
    "gn:dem":20,
    "gn:feature_class":"P",
    "gn:feature_code":"PPL",
    "gn:name":"Trzeszyn",
    "gn:population":0,
    "gn:timezone":"Europe/Warsaw",
    "iso:country":"PL",
    "name:azb_x_preferred":[
        "\u0686\u0633\u0632\u06cc\u0646"
    ],
    "name:fas_x_preferred":[
        "\u0686\u0633\u0632\u06cc\u0646"
    ],
    "name:pol_x_preferred":[
        "Trzeszyn"
    ],
    "name:ukr_x_preferred":[
        "\u0422\u0448\u0435\u0448\u0438\u043d"
    ],
    "name:vie_x_preferred":[
        "Trzeszyn"
    ],
    "wof:name":"Trzeszyn",
    "wof:placetype":"locality"
},
  "geometry": {"coordinates":[15.15015,53.99869],"type":"Point"}
}