{
  "type": "Feature",
  "properties": {
    "gn:admin1_code":"83.0",
    "gn:admin2_code":"2473.0",
    "gn:admin3_code":"247301.0",
    "gn:asciiname":"Huta Gotartowska",
    "gn:country_code":"PL",
    "gn:dem":236,
    "gn:feature_class":"P",
    "gn:feature_code":"PPL",
    "gn:name":"Huta Gotartowska",
    "gn:population":0,
    "gn:timezone":"Europe/Warsaw",
    "iso:country":"PL",
    "wof:name":"Huta Gotartowska",
    "wof:placetype":"locality"
},
  "geometry": {"coordinates":[18.60212000000001,50.08584000000001],"type":"Point"}
}