{
  "type": "Feature",
  "properties": {
    "iso:country":"PL",
    "name:azb_x_preferred":[
        "\u0633\u062a\u0631\u062f\u0646\u0642"
    ],
    "name:ceb_x_preferred":[
        "Sterdy\u0144"
    ],
    "name:deu_x_preferred":[
        "Sterdy\u0144"
    ],
    "name:fas_x_preferred":[
        "\u0633\u062a\u0631\u062f\u0646\u06af"
    ],
    "name:fra_x_preferred":[
        "Sterdy\u0144"
    ],
    "name:heb_x_preferred":[
        "\u05e1\u05d8\u05e8\u05d3\u05d9\u05df"
    ],
    "name:lit_x_preferred":[
        "Sterdinas"
    ],
    "name:nld_x_preferred":[
        "Sterdy\u0144"
    ],
    "name:pol_x_preferred":[
        "Sterdy\u0144"
    ],
    "name:szl_x_preferred":[
        "Sterdy\u0144"
    ],
    "name:ukr_x_preferred":[
        "\u0421\u0442\u0435\u0440\u0434\u0438\u043d\u044c"
    ],
    "wof:coterminous":[
        1125401105
    ],
    "wof:name":"Sterdy\u0144",
    "wof:placetype":"locality"
},
  "geometry": {"coordinates":[22.3599644598462,52.5759357084334],"type":"Point"}
}