{
  "type": "Feature",
  "properties": {
    "iso:country":"PL",
    "name:pol_x_preferred":[
        "Sterdy\u0144"
    ],
    "wof:coterminous":[
        1125401105
    ],
    "wof:name":"Sterdy\u0144",
    "wof:placetype":"locality"
},
  "geometry": {"coordinates":[22.3599644598462,52.5759357084334],"type":"Point"}
}