{
  "type": "Feature",
  "properties": {
    "gn:admin1_code":"85.0",
    "gn:admin2_code":"2811.0",
    "gn:admin3_code":"281101.0",
    "gn:asciiname":"Kownatki-Falecino",
    "gn:country_code":"PL",
    "gn:dem":136,
    "gn:feature_class":"P",
    "gn:feature_code":"PPL",
    "gn:name":"Kownatki-Fal\u0119cino",
    "gn:population":0,
    "gn:timezone":"Europe/Warsaw",
    "iso:country":"PL",
    "name:azb_x_preferred":[
        "\u06a9\u0648\u0648\u0646\u0627\u062a\u06a9\u06cc-\u0641\u0627\u0644\u0646\u0686\u06cc\u0646\u0648"
    ],
    "name:deu_x_preferred":[
        "Kownatki-Fal\u0119cino"
    ],
    "name:fas_x_preferred":[
        "\u06a9\u0648\u0648\u0646\u0627\u062a\u06a9\u06cc-\u0641\u0627\u0644\u0646\u0686\u06cc\u0646\u0648"
    ],
    "name:fra_x_preferred":[
        "Kownatki-Fal\u0119cino"
    ],
    "name:pol_x_preferred":[
        "Kownatki-Fal\u0119cino"
    ],
    "name:ukr_x_preferred":[
        "\u041a\u043e\u0432\u043d\u0430\u0442\u043a\u0456-\u0424\u0430\u043b\u0435\u043d\u0446\u0438\u043d\u043e"
    ],
    "wof:name":"Kownatki-Falecino",
    "wof:placetype":"locality"
},
  "geometry": {"coordinates":[20.58889,53.23974000000001],"type":"Point"}
}