{
  "type": "Feature",
  "properties": {
    "gn:admin1_code":"85.0",
    "gn:admin2_code":"2811.0",
    "gn:admin3_code":"281101.0",
    "gn:asciiname":"Kownatki-Falecino",
    "gn:country_code":"PL",
    "gn:dem":136,
    "gn:feature_class":"P",
    "gn:feature_code":"PPL",
    "gn:name":"Kownatki-Fal\u0119cino",
    "gn:population":0,
    "gn:timezone":"Europe/Warsaw",
    "iso:country":"PL",
    "wof:name":"Kownatki-Falecino",
    "wof:placetype":"locality"
},
  "geometry": {"coordinates":[20.58889,53.23974000000001],"type":"Point"}
}