{
  "type": "Feature",
  "properties": {
    "gn:admin1_code":"75.0",
    "gn:admin2_code":"602.0",
    "gn:admin3_code":"60203.0",
    "gn:asciiname":"Hedwizyn",
    "gn:country_code":"PL",
    "gn:dem":244,
    "gn:feature_class":"P",
    "gn:feature_code":"PPL",
    "gn:name":"Hedwi\u017cyn",
    "gn:population":0,
    "gn:timezone":"Europe/Warsaw",
    "iso:country":"PL",
    "name:azb_x_preferred":[
        "\u062e\u062f\u0648\u06cc\u0698\u0646"
    ],
    "name:ceb_x_preferred":[
        "Hedwi\u017cyn"
    ],
    "name:fas_x_preferred":[
        "\u062e\u062f\u0648\u06cc\u0698\u0646"
    ],
    "name:fra_x_preferred":[
        "Hedwi\u017cyn"
    ],
    "name:ita_x_preferred":[
        "Hedwi\u017cyn"
    ],
    "name:pol_x_preferred":[
        "Hedwi\u017cyn"
    ],
    "name:rus_x_preferred":[
        "\u0425\u0435\u0434\u0432\u0438\u0436\u0438\u043d"
    ],
    "name:ukr_x_preferred":[
        "\u0413\u0435\u0434\u0432\u0456\u0436\u0438\u043d"
    ],
    "name:und_x_variant":[
        "Hedwi\u017cyn"
    ],
    "wof:name":"Hedwizyn",
    "wof:placetype":"locality"
},
  "geometry": {"coordinates":[22.81089,50.58442],"type":"Point"}
}