{
  "type": "Feature",
  "properties": {
    "gn:admin1_code":"75.0",
    "gn:admin2_code":"602.0",
    "gn:admin3_code":"60203.0",
    "gn:asciiname":"Hedwizyn",
    "gn:country_code":"PL",
    "gn:dem":244,
    "gn:feature_class":"P",
    "gn:feature_code":"PPL",
    "gn:name":"Hedwi\u017cyn",
    "gn:population":0,
    "gn:timezone":"Europe/Warsaw",
    "iso:country":"PL",
    "name:und_x_variant":[
        "Hedwi\u017cyn"
    ],
    "wof:name":"Hedwizyn",
    "wof:placetype":"locality"
},
  "geometry": {"coordinates":[22.81089,50.58442],"type":"Point"}
}