{
  "type": "Feature",
  "properties": {
    "gn:admin1_code":"78.0",
    "gn:admin2_code":"1417.0",
    "gn:admin3_code":"141707.0",
    "gn:asciiname":"Wysoczyn",
    "gn:country_code":"PL",
    "gn:dem":92,
    "gn:feature_class":"P",
    "gn:feature_code":"PPL",
    "gn:name":"Wysoczyn",
    "gn:population":0,
    "gn:timezone":"Europe/Warsaw",
    "iso:country":"PL",
    "name:ceb_x_preferred":[
        "Wysoczyn"
    ],
    "name:fra_x_preferred":[
        "Wysoczyn"
    ],
    "name:pol_x_preferred":[
        "Wysoczyn"
    ],
    "name:ukr_x_preferred":[
        "\u0412\u0438\u0441\u043e\u0447\u0438\u043d"
    ],
    "wof:name":"Wysoczyn",
    "wof:placetype":"locality"
},
  "geometry": {"coordinates":[21.26415,51.91301],"type":"Point"}
}