{
  "type": "Feature",
  "properties": {
    "gn:admin1_code":"73.0",
    "gn:admin2_code":"408.0",
    "gn:admin3_code":"40803.0",
    "gn:asciiname":"Janiszewo",
    "gn:country_code":"PL",
    "gn:dem":122,
    "gn:feature_class":"P",
    "gn:feature_code":"PPL",
    "gn:name":"Janiszewo",
    "gn:population":0,
    "gn:timezone":"Europe/Warsaw",
    "iso:country":"PL",
    "name:deu_x_preferred":[
        "Janiszewo"
    ],
    "name:fra_x_preferred":[
        "Janiszewo"
    ],
    "name:pol_x_preferred":[
        "Janiszewo"
    ],
    "name:ukr_x_preferred":[
        "\u042f\u043d\u0456\u0448\u0435\u0432\u043e"
    ],
    "wof:name":"Janiszewo",
    "wof:placetype":"locality"
},
  "geometry": {"coordinates":[19.25193,52.93441],"type":"Point"}
}