{
  "type": "Feature",
  "properties": {
    "gn:admin1_code":"80.0",
    "gn:admin2_code":"1807.0",
    "gn:admin3_code":"180701.0",
    "gn:asciiname":"Bobrka",
    "gn:country_code":"PL",
    "gn:dem":291,
    "gn:feature_class":"P",
    "gn:feature_code":"PPL",
    "gn:name":"B\u00f3brka",
    "gn:population":0,
    "gn:timezone":"Europe/Warsaw",
    "iso:country":"PL",
    "name:ceb_x_preferred":[
        "B\u00f3brka"
    ],
    "name:nld_x_preferred":[
        "B\u00f3brka"
    ],
    "name:pol_x_preferred":[
        "B\u00f3brka"
    ],
    "name:ukr_x_preferred":[
        "\u0411\u0443\u0431\u0440\u043a\u0430"
    ],
    "wof:name":"Bobrka",
    "wof:placetype":"locality"
},
  "geometry": {"coordinates":[21.69943,49.63276],"type":"Point"}
}