{
  "type": "Feature",
  "properties": {
    "gn:admin1_code":"78.0",
    "gn:admin2_code":"1429.0",
    "gn:admin3_code":"142906.0",
    "gn:asciiname":"Remiszew",
    "gn:country_code":"PL",
    "gn:dem":182,
    "gn:feature_class":"P",
    "gn:feature_code":"PPL",
    "gn:name":"Remiszew",
    "gn:population":0,
    "gn:timezone":"Europe/Warsaw",
    "iso:country":"PL",
    "name:fra_x_preferred":[
        "Remiszew"
    ],
    "name:pol_x_preferred":[
        "Remiszew"
    ],
    "name:ukr_x_preferred":[
        "\u0420\u0435\u043c\u0456\u0448\u0435\u0432"
    ],
    "wof:name":"Remiszew",
    "wof:placetype":"locality"
},
  "geometry": {"coordinates":[22.33621,52.38508],"type":"Point"}
}