{
  "type": "Feature",
  "properties": {
    "gn:admin1_code":"77.0",
    "gn:admin2_code":"1207.0",
    "gn:admin3_code":"120703.0",
    "gn:asciiname":"Stroza",
    "gn:country_code":"PL",
    "gn:dem":430,
    "gn:feature_class":"P",
    "gn:feature_code":"PPL",
    "gn:name":"Str\u00f3\u017ca",
    "gn:population":0,
    "gn:timezone":"Europe/Warsaw",
    "iso:country":"PL",
    "name:ceb_x_preferred":[
        "Str\u00f3\u017ca"
    ],
    "name:pol_x_preferred":[
        "Str\u00f3\u017ca"
    ],
    "name:ukr_x_preferred":[
        "\u0421\u0442\u0440\u0443\u0436\u0430"
    ],
    "wof:name":"Stroza",
    "wof:placetype":"locality"
},
  "geometry": {"coordinates":[20.21553,49.74889],"type":"Point"}
}