{
  "type": "Feature",
  "properties": {
    "gn:admin1_code":"82.0",
    "gn:admin2_code":"2209.0",
    "gn:admin3_code":"220906.0",
    "gn:asciiname":"Pogorzala-Wies",
    "gn:country_code":"PL",
    "gn:dem":6,
    "gn:feature_class":"P",
    "gn:feature_code":"PPL",
    "gn:name":"Pogorza\u0142a-Wie\u015b",
    "gn:population":0,
    "gn:timezone":"Europe/Warsaw",
    "iso:country":"PL",
    "name:deu_x_preferred":[
        "Pogorza\u0142a Wie\u015b"
    ],
    "name:nld_x_preferred":[
        "Pogorza\u0142a Wie\u015b"
    ],
    "name:pol_x_preferred":[
        "Pogorza\u0142a Wie\u015b"
    ],
    "name:ukr_x_preferred":[
        "\u041f\u043e\u0491\u043e\u0436\u0430\u043b\u0430-\u0412\u0435\u0441\u044c"
    ],
    "name:und_x_variant":[
        "Wernersdorf",
        "Pogorza\u0142a-Wie\u015b"
    ],
    "wof:name":"Pogorzala-Wies",
    "wof:placetype":"locality"
},
  "geometry": {"coordinates":[18.92561,53.97208000000001],"type":"Point"}
}