{
  "type": "Feature",
  "properties": {
    "gn:admin1_code":"81.0",
    "gn:admin2_code":"2010.0",
    "gn:admin3_code":"201007.0",
    "gn:asciiname":"Klukowicze",
    "gn:country_code":"PL",
    "gn:dem":162,
    "gn:feature_class":"P",
    "gn:feature_code":"PPL",
    "gn:name":"Klukowicze",
    "gn:population":0,
    "gn:timezone":"Europe/Warsaw",
    "iso:country":"PL",
    "name:azb_x_preferred":[
        "\u06a9\u0644\u0648\u06a9\u0648\u0648\u06cc\u0686\u0647"
    ],
    "name:ceb_x_preferred":[
        "Klukowicze"
    ],
    "name:eng_x_preferred":[
        "Klukowicze"
    ],
    "name:fas_x_preferred":[
        "\u06a9\u0644\u0648\u06a9\u0648\u0648\u06cc\u0686\u0647"
    ],
    "name:fra_x_preferred":[
        "Klukowicze"
    ],
    "name:lit_x_preferred":[
        "Klukovi\u010d\u0117"
    ],
    "name:nld_x_preferred":[
        "Klukowicze"
    ],
    "name:pol_x_preferred":[
        "Klukowicze"
    ],
    "name:rus_x_preferred":[
        "\u041a\u043b\u044e\u043a\u043e\u0432\u0438\u0447\u0435"
    ],
    "name:ukr_x_preferred":[
        "\u041a\u043b\u044e\u043a\u043e\u0432\u0456\u0447\u0435"
    ],
    "wof:name":"Klukowicze",
    "wof:placetype":"locality"
},
  "geometry": {"coordinates":[23.27314,52.40600000000001],"type":"Point"}
}