{
  "type": "Feature",
  "properties": {
    "gn:admin1_code":"86.0",
    "gn:admin2_code":"3019.0",
    "gn:admin3_code":"301908.0",
    "gn:asciiname":"Wyciag",
    "gn:country_code":"PL",
    "gn:dem":48,
    "gn:feature_class":"P",
    "gn:feature_code":"PPL",
    "gn:name":"Wyci\u0105g",
    "gn:population":0,
    "gn:timezone":"Europe/Warsaw",
    "iso:country":"PL",
    "name:und_x_variant":[
        "Wyci\u0105g"
    ],
    "wof:name":"Wyciag",
    "wof:placetype":"locality"
},
  "geometry": {"coordinates":[17.33335,53.08993],"type":"Point"}
}