{
  "type": "Feature",
  "properties": {
    "gn:admin1_code":"86.0",
    "gn:admin2_code":"3020.0",
    "gn:admin3_code":"302004.0",
    "gn:asciiname":"Wronow",
    "gn:country_code":"PL",
    "gn:dem":91,
    "gn:feature_class":"P",
    "gn:feature_code":"PPL",
    "gn:name":"Wron\u00f3w",
    "gn:population":0,
    "gn:timezone":"Europe/Warsaw",
    "iso:country":"PL",
    "wof:name":"Wronow",
    "wof:placetype":"locality"
},
  "geometry": {"coordinates":[17.81429,52.04558],"type":"Point"}
}