{
  "type": "Feature",
  "properties": {
    "iso:country":"PL",
    "name:eng_x_preferred":[
        "Wielkie"
    ],
    "name:pol_x_preferred":[
        "Wielkie"
    ],
    "wof:name":"Wielkie",
    "wof:placetype":"neighbourhood"
},
  "geometry": {"coordinates":[16.7638839272133,52.46533493927798],"type":"Point"}
}