{
  "type": "Feature",
  "properties": {
    "gn:admin1_code":"79.0",
    "gn:admin2_code":"1607.0",
    "gn:admin3_code":"160701.0",
    "gn:asciiname":"Swietow Polski",
    "gn:country_code":"PL",
    "gn:dem":240,
    "gn:feature_class":"P",
    "gn:feature_code":"PPL",
    "gn:name":"Swi\u0119t\u00f3w Polski",
    "gn:population":0,
    "gn:timezone":"Europe/Warsaw",
    "iso:country":"PL",
    "name:pol_x_preferred":[
        "Polski \u015awi\u0119t\u00f3w"
    ],
    "name:ukr_x_preferred":[
        "\u041f\u043e\u043b\u044c\u0441\u044c\u043a\u0438\u0439-\u0421\u044c\u0432\u0435\u043d\u0442\u0443\u0432"
    ],
    "wof:name":"Swietow Polski",
    "wof:placetype":"locality"
},
  "geometry": {"coordinates":[17.34947,50.39013],"type":"Point"}
}