{
  "type": "Feature",
  "properties": {
    "gn:admin1_code":"79.0",
    "gn:admin2_code":"1607.0",
    "gn:admin3_code":"160701.0",
    "gn:asciiname":"Swietow Polski",
    "gn:country_code":"PL",
    "gn:dem":240,
    "gn:feature_class":"P",
    "gn:feature_code":"PPL",
    "gn:name":"Swi\u0119t\u00f3w Polski",
    "gn:population":0,
    "gn:timezone":"Europe/Warsaw",
    "iso:country":"PL",
    "name:und_x_variant":[
        "Polski \u015awi\u0119t\u00f3w"
    ],
    "wof:name":"Swietow Polski",
    "wof:placetype":"locality"
},
  "geometry": {"coordinates":[17.34947,50.39013],"type":"Point"}
}