{
  "type": "Feature",
  "properties": {
    "gn:admin1_code":"82.0",
    "gn:admin2_code":"2213.0",
    "gn:admin3_code":"221306.0",
    "gn:asciiname":"Wilcze Blota",
    "gn:country_code":"PL",
    "gn:dem":106,
    "gn:feature_class":"P",
    "gn:feature_code":"PPL",
    "gn:name":"Wilcze B\u0142ota",
    "gn:population":0,
    "gn:timezone":"Europe/Warsaw",
    "iso:country":"PL",
    "name:ceb_x_preferred":[
        "Wilcze B\u0142ota"
    ],
    "name:pol_x_preferred":[
        "Wilcze B\u0142ota"
    ],
    "name:ukr_x_preferred":[
        "\u0412\u0456\u043b\u044c\u0447\u0435-\u0411\u043b\u043e\u0442\u0430"
    ],
    "wof:name":"Wilcze Blota",
    "wof:placetype":"locality"
},
  "geometry": {"coordinates":[18.39538,53.82435],"type":"Point"}
}