{
  "type": "Feature",
  "properties": {
    "gn:admin1_code":"84.0",
    "gn:admin2_code":"2605.0",
    "gn:admin3_code":"260503.0",
    "gn:asciiname":"Pieklo",
    "gn:country_code":"PL",
    "gn:dem":260,
    "gn:feature_class":"P",
    "gn:feature_code":"PPL",
    "gn:name":"Piek\u0142o",
    "gn:population":0,
    "gn:timezone":"Europe/Warsaw",
    "iso:country":"PL",
    "name:pol_x_preferred":[
        "Piek\u0142o"
    ],
    "name:ukr_x_preferred":[
        "\u041f\u0435\u043a\u043b\u043e"
    ],
    "wof:name":"Pieklo",
    "wof:placetype":"locality"
},
  "geometry": {"coordinates":[20.4115,51.1277],"type":"Point"}
}