{
  "type": "Feature",
  "properties": {
    "iso:country":"PL",
    "name:eng_x_preferred":[
        "Stare Szkoty"
    ],
    "name:pol_x_preferred":[
        "Stare Szkoty"
    ],
    "wof:name":"Stare Szkoty",
    "wof:placetype":"neighbourhood"
},
  "geometry": {"coordinates":[18.63521461853824,54.33569173519212],"type":"Point"}
}