{
  "type": "Feature",
  "properties": {
    "gn:admin1_code":"87.0",
    "gn:admin2_code":"3217.0",
    "gn:admin3_code":"321705.0",
    "gn:asciiname":"Golce",
    "gn:country_code":"PL",
    "gn:dem":108,
    "gn:feature_class":"P",
    "gn:feature_code":"PPL",
    "gn:name":"Golce",
    "gn:population":0,
    "gn:timezone":"Europe/Warsaw",
    "iso:country":"PL",
    "wof:name":"Golce",
    "wof:placetype":"locality"
},
  "geometry": {"coordinates":[16.4292,53.37114],"type":"Point"}
}