{
  "type": "Feature",
  "properties": {
    "gn:admin1_code":"80.0",
    "gn:admin2_code":"1815.0",
    "gn:admin3_code":"181503.0",
    "gn:asciiname":"Sepnica",
    "gn:country_code":"PL",
    "gn:dem":208,
    "gn:feature_class":"P",
    "gn:feature_code":"PPL",
    "gn:name":"Sepnica",
    "gn:population":0,
    "gn:timezone":"Europe/Warsaw",
    "iso:country":"PL",
    "wof:name":"Sepnica",
    "wof:placetype":"locality"
},
  "geometry": {"coordinates":[21.51419,50.06296],"type":"Point"}
}