{
  "type": "Feature",
  "properties": {
    "gn:admin1_code":"81.0",
    "gn:admin2_code":"2006.0",
    "gn:admin3_code":"200603.0",
    "gn:asciiname":"Okurowo",
    "gn:country_code":"PL",
    "gn:dem":134,
    "gn:feature_class":"P",
    "gn:feature_code":"PPL",
    "gn:name":"Okurowo",
    "gn:population":0,
    "gn:timezone":"Europe/Warsaw",
    "iso:country":"PL",
    "name:ceb_x_preferred":[
        "Okurowo"
    ],
    "name:lit_x_preferred":[
        "Okurovas"
    ],
    "name:pol_x_preferred":[
        "Okurowo"
    ],
    "name:ukr_x_preferred":[
        "\u041e\u043a\u0443\u0440\u043e\u0432\u043e"
    ],
    "wof:name":"Okurowo",
    "wof:placetype":"locality"
},
  "geometry": {"coordinates":[21.96473,53.49269],"type":"Point"}
}