{
  "type": "Feature",
  "properties": {
    "gn:admin1_code":"78.0",
    "gn:admin2_code":"1438.0",
    "gn:admin3_code":"143802.0",
    "gn:asciiname":"Lindow",
    "gn:country_code":"PL",
    "gn:dem":196,
    "gn:feature_class":"P",
    "gn:feature_code":"PPL",
    "gn:name":"Lind\u00f3w",
    "gn:population":0,
    "gn:timezone":"Europe/Warsaw",
    "iso:country":"PL",
    "name:ceb_x_preferred":[
        "Lind\u00f3w"
    ],
    "name:fra_x_preferred":[
        "Lind\u00f3w"
    ],
    "name:pol_x_preferred":[
        "Lind\u00f3w"
    ],
    "name:ukr_x_preferred":[
        "\u041b\u0456\u043d\u0434\u0443\u0432"
    ],
    "wof:name":"Lindow",
    "wof:placetype":"locality"
},
  "geometry": {"coordinates":[20.50856,51.90584000000001],"type":"Point"}
}