{
  "type": "Feature",
  "properties": {
    "gn:admin1_code":"73.0",
    "gn:admin2_code":"461.0",
    "gn:admin3_code":"46101.0",
    "gn:asciiname":"Osowa Gora",
    "gn:country_code":"PL",
    "gn:dem":59,
    "gn:feature_class":"P",
    "gn:feature_code":"PPL",
    "gn:name":"Osowa G\u00f3ra",
    "gn:population":0,
    "gn:timezone":"Europe/Warsaw",
    "iso:country":"PL",
    "name:und_x_variant":[
        "Osowa G\u00f3ra"
    ],
    "wof:name":"Osowa Gora",
    "wof:placetype":"locality"
},
  "geometry": {"coordinates":[17.91219,53.15533000000001],"type":"Point"}
}