{
  "type": "Feature",
  "properties": {
    "gn:admin1_code":"84.0",
    "gn:admin2_code":"2613.0",
    "gn:admin3_code":"261301.0",
    "gn:asciiname":"Jakubowice",
    "gn:country_code":"PL",
    "gn:dem":224,
    "gn:feature_class":"P",
    "gn:feature_code":"PPL",
    "gn:name":"Jakubowice",
    "gn:population":0,
    "gn:timezone":"Europe/Warsaw",
    "iso:country":"PL",
    "name:deu_x_preferred":[
        "Jakubowice"
    ],
    "name:fra_x_preferred":[
        "Jakubowice"
    ],
    "name:pol_x_preferred":[
        "Jakubowice"
    ],
    "name:ukr_x_preferred":[
        "\u042f\u043a\u0443\u0431\u043e\u0432\u0456\u0446\u0435"
    ],
    "name:und_x_variant":[
        "Siatki",
        "Jak\u00f3bowice"
    ],
    "wof:name":"Jakubowice",
    "wof:placetype":"locality"
},
  "geometry": {"coordinates":[19.9328,50.94665],"type":"Point"}
}