{
  "type": "Feature",
  "properties": {
    "gn:admin1_code":"73.0",
    "gn:admin2_code":"410.0",
    "gn:admin3_code":"41003.0",
    "gn:asciiname":"Kazmierowo",
    "gn:country_code":"PL",
    "gn:dem":68,
    "gn:feature_class":"P",
    "gn:feature_code":"PPL",
    "gn:name":"Ka\u017amierowo",
    "gn:population":0,
    "gn:timezone":"Europe/Warsaw",
    "iso:country":"PL",
    "name:pol_x_preferred":[
        "Ka\u017amierowo"
    ],
    "name:und_x_variant":[
        "Ka\u017amierowo"
    ],
    "wof:name":"Kazmierowo",
    "wof:placetype":"locality"
},
  "geometry": {"coordinates":[17.7557,53.12515],"type":"Point"}
}