{
  "type": "Feature",
  "properties": {
    "gn:country":"PL",
    "gn:fcode":"PPL",
    "gn:population":66,
    "iso:country":"PL",
    "name:fra_x_preferred":[
        "Wymys\u0142\u00f3w"
    ],
    "name:pol_x_preferred":[
        "Wymys\u0142\u00f3w"
    ],
    "name:rus_x_preferred":[
        "\u0412\u044b\u043c\u044b\u0441\u043b\u0443\u0432"
    ],
    "name:ukr_x_preferred":[
        "\u0412\u0438\u043c\u0438\u0441\u043b\u0443\u0432"
    ],
    "qs_pg:aaroncc":"PL",
    "qs_pg:gn_country":"PL",
    "qs_pg:gn_fcode":"PPL",
    "qs_pg:gn_pop":66,
    "qs_pg:name":"Wymys\u0142\u00f3w",
    "qs_pg:name_adm0":"Polska",
    "qs_pg:name_adm1":"Swi\u0119tokrzyskie",
    "qs_pg:photos_9r":0,
    "qs_pg:photos_sr":0,
    "qs_pg:pop_sr":1,
    "qs_pg:qs_pg_placetype":"locality",
    "qs_pg:qs_pg_placetype_gp":"Town",
    "qs_pg:woe_adm0":23424923,
    "woe:adm0_id":23424923,
    "woe:name_adm0":"Polska",
    "woe:name_adm1":"Swi\u0119tokrzyskie",
    "woe:placetype":"Town",
    "wof:name":"Wymys\u0142\u00f3w",
    "wof:placetype":"locality",
    "wof:population":66
},
  "geometry": {"coordinates":[20.55207,50.25939],"type":"Point"}
}