{
  "type": "Feature",
  "properties": {
    "gn:gn_country":"PL",
    "gn:gn_fcode":"PPL",
    "gn:gn_pop":183,
    "gn:population":183,
    "iso:country":"PL",
    "name:eng_x_preferred":[
        "Szymanowo"
    ],
    "name:fas_x_preferred":[
        "\u0634\u0645\u0627\u0646\u0648\u0648\u0648"
    ],
    "name:fra_x_preferred":[
        "Szymanowo"
    ],
    "name:lit_x_preferred":[
        "\u0160imanovas"
    ],
    "name:pol_x_preferred":[
        "Szymanowo"
    ],
    "qs_pg:aaroncc":"PL",
    "qs_pg:gn_country":"PL",
    "qs_pg:gn_fcode":"PPL",
    "qs_pg:gn_pop":183,
    "qs_pg:name":"Szymanowo",
    "qs_pg:name_adm0":"Polska",
    "qs_pg:name_adm1":"Lubelskie",
    "qs_pg:photos_9r":0,
    "qs_pg:photos_sr":0,
    "qs_pg:pop_sr":1,
    "qs_pg:qs_pg_placetype":"locality",
    "qs_pg:qs_pg_placetype_gp":"Town",
    "qs_pg:woe_adm0":23424923,
    "woe:adm0_id":23424923,
    "woe:name_adm0":"Polska",
    "woe:name_adm1":"Lubelskie",
    "woe:placetype":"Town",
    "wof:name":"Szymanowo",
    "wof:placetype":"locality",
    "wof:population":183
},
  "geometry": {"coordinates":[23.19361,51.89389],"type":"Point"}
}