{
  "type": "Feature",
  "properties": {
    "gn:admin1_code":"85.0",
    "gn:admin2_code":"2802.0",
    "gn:admin3_code":"280202.0",
    "gn:asciiname":"Ujscie",
    "gn:country_code":"PL",
    "gn:dem":0,
    "gn:feature_class":"P",
    "gn:feature_code":"PPL",
    "gn:name":"Uj\u015bcie",
    "gn:population":0,
    "gn:timezone":"Europe/Warsaw",
    "iso:country":"PL",
    "name:azb_x_preferred":[
        "\u0627\u0648\u06cc\u0634\u0686\u06cc\u0647"
    ],
    "name:deu_x_preferred":[
        "Uj\u015bcie"
    ],
    "name:fas_x_preferred":[
        "\u0627\u0648\u06cc\u0634\u0686\u06cc\u0647"
    ],
    "name:fra_x_preferred":[
        "Uj\u015bcie"
    ],
    "name:pol_x_preferred":[
        "Uj\u015bcie"
    ],
    "wof:name":"Ujscie",
    "wof:placetype":"locality"
},
  "geometry": {"coordinates":[19.74861,54.42661999999999],"type":"Point"}
}