{
  "type": "Feature",
  "properties": {
    "gn:gn_country":"PL",
    "gn:gn_fcode":"PPL",
    "gn:gn_pop":0,
    "iso:country":"PL",
    "name:deu_x_preferred":[
        "Go\u0142\u0105b"
    ],
    "name:fra_x_preferred":[
        "Go\u0142\u0105b"
    ],
    "name:nld_x_preferred":[
        "Go\u0142\u0105b"
    ],
    "name:pol_x_preferred":[
        "Go\u0142\u0105b"
    ],
    "name:ukr_x_preferred":[
        "\u0490\u043e\u043b\u043e\u043c\u0431"
    ],
    "qs_pg:aaroncc":"PL",
    "qs_pg:gn_country":"PL",
    "qs_pg:gn_fcode":"PPL",
    "qs_pg:gn_pop":0,
    "qs_pg:name":"Go\u0142\u0105b",
    "qs_pg:name_adm0":"Polska",
    "qs_pg:name_adm1":"Lubelskie",
    "qs_pg:photos_9k":1,
    "qs_pg:photos_9r":1,
    "qs_pg:photos_all":17,
    "qs_pg:photos_sr":0,
    "qs_pg:pop_sr":0,
    "qs_pg:qs_pg_placetype":"locality",
    "qs_pg:qs_pg_placetype_gp":"Town",
    "qs_pg:woe_adm0":23424923,
    "woe:adm0_id":23424923,
    "woe:name_adm0":"Polska",
    "woe:name_adm1":"Lubelskie",
    "woe:placetype":"Town",
    "wof:name":"Go\u0142\u0105b",
    "wof:placetype":"locality"
},
  "geometry": {"coordinates":[21.87532,51.48748],"type":"Point"}
}