{
  "type": "Feature",
  "properties": {
    "gn:admin1_code":"75.0",
    "gn:admin2_code":"619.0",
    "gn:admin3_code":"61904.0",
    "gn:asciiname":"Nowy Brus",
    "gn:country_code":"PL",
    "gn:dem":176,
    "gn:feature_class":"P",
    "gn:feature_code":"PPL",
    "gn:name":"Nowy Brus",
    "gn:population":0,
    "gn:timezone":"Europe/Warsaw",
    "iso:country":"PL",
    "name:azb_x_preferred":[
        "\u0646\u0648\u0648 \u0628\u0631\u0648\u0633"
    ],
    "name:fas_x_preferred":[
        "\u0646\u0648\u0648 \u0628\u0631\u0648\u0633"
    ],
    "name:fra_x_preferred":[
        "Nowy Brus"
    ],
    "name:lit_x_preferred":[
        "Novi Brusas"
    ],
    "name:pol_x_preferred":[
        "Nowy Brus"
    ],
    "name:ukr_x_preferred":[
        "\u041d\u043e\u0432\u0438\u0439 \u0411\u0440\u0443\u0441"
    ],
    "wof:name":"Nowy Brus",
    "wof:placetype":"locality"
},
  "geometry": {"coordinates":[23.31024,51.48416],"type":"Point"}
}