{
  "type": "Feature",
  "properties": {
    "gn:admin1_code":"74.0",
    "gn:admin2_code":"1006.0",
    "gn:admin3_code":"100607.0",
    "gn:asciiname":"Przanowice",
    "gn:country_code":"PL",
    "gn:dem":210,
    "gn:feature_class":"P",
    "gn:feature_code":"PPL",
    "gn:name":"Przanowice",
    "gn:population":0,
    "gn:timezone":"Europe/Warsaw",
    "iso:country":"PL",
    "name:fra_x_preferred":[
        "Przanowice"
    ],
    "name:pol_x_preferred":[
        "Przanowice"
    ],
    "name:ukr_x_preferred":[
        "\u041f\u0448\u0430\u043d\u043e\u0432\u0456\u0446\u0435"
    ],
    "wof:name":"Przanowice",
    "wof:placetype":"locality"
},
  "geometry": {"coordinates":[19.77779,51.74244],"type":"Point"}
}