{
  "type": "Feature",
  "properties": {
    "gn:admin1_code":"76.0",
    "gn:admin2_code":"811.0",
    "gn:admin3_code":"81106.0",
    "gn:asciiname":"Chocimek",
    "gn:country_code":"PL",
    "gn:dem":78,
    "gn:feature_class":"P",
    "gn:feature_code":"PPL",
    "gn:name":"Chocimek",
    "gn:population":0,
    "gn:timezone":"Europe/Warsaw",
    "iso:country":"PL",
    "name:azb_x_preferred":[
        "\u062e\u0648\u0686\u06cc\u0645\u06a9"
    ],
    "name:fas_x_preferred":[
        "\u062e\u0648\u0686\u06cc\u0645\u06a9"
    ],
    "name:fra_x_preferred":[
        "Chocimek"
    ],
    "name:nld_x_preferred":[
        "Chocimek"
    ],
    "name:pol_x_preferred":[
        "Chocimek"
    ],
    "name:ukr_x_preferred":[
        "\u0425\u043e\u0446\u0438\u043c\u0435\u043a"
    ],
    "wof:name":"Chocimek",
    "wof:placetype":"locality"
},
  "geometry": {"coordinates":[15.06054,51.84002],"type":"Point"}
}