{
  "type": "Feature",
  "properties": {
    "gn:gn_country":"PL",
    "gn:gn_fcode":"PPL",
    "gn:gn_pop":797,
    "gn:population":797,
    "iso:country":"PL",
    "name:eng_x_preferred":[
        "Golina Wielka"
    ],
    "name:fas_x_preferred":[
        "\u06af\u0648\u0644\u06cc\u0646\u0627 \u0648\u06cc\u0644\u06a9\u0627"
    ],
    "name:fra_x_preferred":[
        "Golina Wielka"
    ],
    "name:nan_x_preferred":[
        "Golina Wielka"
    ],
    "name:pol_x_preferred":[
        "Golina Wielka"
    ],
    "qs_pg:aaroncc":"PL",
    "qs_pg:gn_country":"PL",
    "qs_pg:gn_fcode":"PPL",
    "qs_pg:gn_pop":797,
    "qs_pg:name":"Golina Wielka",
    "qs_pg:name_adm0":"Polska",
    "qs_pg:name_adm1":"Wielkopolskie",
    "qs_pg:photos_9r":0,
    "qs_pg:photos_sr":0,
    "qs_pg:pop_sr":2,
    "qs_pg:qs_pg_placetype":"locality",
    "qs_pg:qs_pg_placetype_gp":"Town",
    "qs_pg:woe_adm0":23424923,
    "woe:adm0_id":23424923,
    "woe:name_adm0":"Polska",
    "woe:name_adm1":"Wielkopolskie",
    "woe:placetype":"Town",
    "wof:name":"Golina Wielka",
    "wof:placetype":"locality",
    "wof:population":797
},
  "geometry": {"coordinates":[16.78402,51.70015],"type":"Point"}
}