{
  "type": "Feature",
  "properties": {
    "gn:admin1_code":"73.0",
    "gn:admin2_code":"408.0",
    "gn:admin3_code":"40803.0",
    "gn:asciiname":"Ksawery",
    "gn:country_code":"PL",
    "gn:dem":119,
    "gn:feature_class":"P",
    "gn:feature_code":"PPL",
    "gn:name":"Ksawery",
    "gn:population":0,
    "gn:timezone":"Europe/Warsaw",
    "iso:country":"PL",
    "name:pol_x_preferred":[
        "Ksawery"
    ],
    "name:ukr_x_preferred":[
        "\u041a\u0441\u0430\u0432\u0435\u0440\u0438"
    ],
    "name:und_x_variant":[
        "Kolonia Ksawery"
    ],
    "wof:name":"Ksawery",
    "wof:placetype":"locality"
},
  "geometry": {"coordinates":[19.22451,52.9284],"type":"Point"}
}