{
  "type": "Feature",
  "properties": {
    "gn:gn_country":"PL",
    "gn:gn_fcode":"PPL",
    "gn:gn_pop":200,
    "gn:population":200,
    "iso:country":"PL",
    "name:eng_x_preferred":[
        "Czermin"
    ],
    "name:fra_x_preferred":[
        "Czermin"
    ],
    "name:nan_x_preferred":[
        "Czermin"
    ],
    "name:pol_x_preferred":[
        "Czermin"
    ],
    "qs_pg:aaroncc":"PL",
    "qs_pg:gn_country":"PL",
    "qs_pg:gn_fcode":"PPL",
    "qs_pg:gn_pop":200,
    "qs_pg:name":"Czermin",
    "qs_pg:name_adm0":"Polska",
    "qs_pg:name_adm1":"Wielkopolskie",
    "qs_pg:photos_9k":1,
    "qs_pg:photos_9r":1,
    "qs_pg:photos_all":1,
    "qs_pg:photos_sr":0,
    "qs_pg:pop_sr":1,
    "qs_pg:qs_pg_placetype":"locality",
    "qs_pg:qs_pg_placetype_gp":"Town",
    "qs_pg:woe_adm0":23424923,
    "woe:adm0_id":23424923,
    "woe:name_adm0":"Polska",
    "woe:name_adm1":"Wielkopolskie",
    "woe:placetype":"Town",
    "wof:name":"Czermin",
    "wof:placetype":"locality",
    "wof:population":200
},
  "geometry": {"coordinates":[17.85768,51.33276],"type":"Point"}
}