{
  "type": "Feature",
  "properties": {
    "gn:country":"PL",
    "gn:fcode":"PPL",
    "gn:population":200,
    "iso:country":"PL",
    "name:ast_x_preferred":[
        "Czermin"
    ],
    "name:ceb_x_preferred":[
        "Czermin"
    ],
    "name:ces_x_preferred":[
        "Czermin"
    ],
    "name:che_x_preferred":[
        "\u0427\u0435\u0440\u043c\u0438\u043d"
    ],
    "name:deu_x_preferred":[
        "Czermin"
    ],
    "name:eng_x_preferred":[
        "Czermin"
    ],
    "name:fra_x_preferred":[
        "Czermin"
    ],
    "name:nan_x_preferred":[
        "Czermin"
    ],
    "name:pol_x_preferred":[
        "Czermin"
    ],
    "name:tat_x_preferred":[
        "\u0427\u0435\u0440\u043c\u0438\u043d"
    ],
    "name:ukr_x_preferred":[
        "\u0427\u0435\u0440\u043c\u0456\u043d"
    ],
    "qs_pg:aaroncc":"PL",
    "qs_pg:gn_country":"PL",
    "qs_pg:gn_fcode":"PPL",
    "qs_pg:gn_pop":200,
    "qs_pg:name":"Czermin",
    "qs_pg:name_adm0":"Polska",
    "qs_pg:name_adm1":"Wielkopolskie",
    "qs_pg:photos_9k":1,
    "qs_pg:photos_9r":1,
    "qs_pg:photos_all":1,
    "qs_pg:photos_sr":0,
    "qs_pg:pop_sr":1,
    "qs_pg:qs_pg_placetype":"locality",
    "qs_pg:qs_pg_placetype_gp":"Town",
    "qs_pg:woe_adm0":23424923,
    "woe:adm0_id":23424923,
    "woe:name_adm0":"Polska",
    "woe:name_adm1":"Wielkopolskie",
    "woe:placetype":"Town",
    "wof:name":"Czermin",
    "wof:placetype":"locality",
    "wof:population":200
},
  "geometry": {"coordinates":[17.85768,51.33276],"type":"Point"}
}