{
  "type": "Feature",
  "properties": {
    "gn:population":1900,
    "iso:country":"PL",
    "name:azb_x_preferred":[
        "\u0642\u0645\u06cc\u0646\u0627 \u0631\u0648\u06a9\u06cc\u062a\u0646\u0642\u062a\u0633\u0627"
    ],
    "name:bel_x_preferred":[
        "\u0413\u043c\u0456\u043d\u0430 \u0420\u0430\u043a\u044f\u0442\u043d\u0456\u0446\u0430"
    ],
    "name:ceb_x_preferred":[
        "Rokietnica"
    ],
    "name:deu_x_preferred":[
        "Gmina Rokietnica"
    ],
    "name:eng_x_preferred":[
        "Gmina Rokietnica"
    ],
    "name:eus_x_preferred":[
        "Rokietnica udalerria"
    ],
    "name:fas_x_preferred":[
        "\u06af\u0645\u06cc\u0646\u0627 \u0631\u0648\u06a9\u06cc\u062a\u0646\u06af\u062a\u0633\u0627"
    ],
    "name:fra_x_preferred":[
        "Rokietnica"
    ],
    "name:ita_x_preferred":[
        "Rokietnica"
    ],
    "name:nan_x_preferred":[
        "Rokietnica"
    ],
    "name:nld_x_preferred":[
        "Rokietnica"
    ],
    "name:pol_x_preferred":[
        "Rokietnica"
    ],
    "name:por_x_preferred":[
        "Comuna de Rokietnica"
    ],
    "name:rus_x_preferred":[
        "\u0420\u043e\u043a\u0435\u0442\u043d\u0438\u0446\u0430"
    ],
    "name:slk_x_preferred":[
        "Gmina Rokietnica"
    ],
    "name:ukr_x_preferred":[
        "\u0490\u043c\u0456\u043d\u0430 \u0420\u043e\u043a\u0435\u0442\u043d\u0438\u0446\u044f"
    ],
    "name:war_x_preferred":[
        "Gmina Rokietnica"
    ],
    "qs:a0":"Rzeczpospolita Polska",
    "qs:a1":"*Wielkopolskie",
    "qs:a1r":"0",
    "qs:a2":"Poznanski",
    "qs:adm0":"Rzeczpospolita Polska",
    "qs:la":"Rokietnica",
    "qs:la_lc":"*PL3021132",
    "qs:level":"locality",
    "qs:loc":"Rokietnica",
    "qs:loc_alt":"Rokietnica",
    "qs:pop":0,
    "qs:type":"rural point-in-poly",
    "wd:wordcount":144,
    "wof:coterminous":[
        1125278781
    ],
    "wof:name":"Rokietnica",
    "wof:placetype":"locality",
    "wof:population":1900
},
  "geometry": {"coordinates":[16.754266,52.512796],"type":"Point"}
}