{
  "type": "Feature",
  "properties": {
    "gn:admin1_code":"85.0",
    "gn:admin2_code":"2817.0",
    "gn:admin3_code":"281703.0",
    "gn:asciiname":"Baldzki Piec",
    "gn:cc2":"PL",
    "gn:country_code":"PL",
    "gn:dem":148,
    "gn:feature_class":"P",
    "gn:feature_code":"PPL",
    "gn:name":"Ba\u0142dzki Piec",
    "gn:population":0,
    "gn:timezone":"Europe/Warsaw",
    "iso:country":"PL",
    "name:nld_x_preferred":[
        "Ba\u0142dzki Piec"
    ],
    "name:pol_x_preferred":[
        "Ba\u0142dzki Piec"
    ],
    "name:ukr_x_preferred":[
        "\u0411\u0430\u043b\u0434\u0437\u044c\u043a\u0438\u0439-\u041f\u0435\u0446\u044c"
    ],
    "name:und_x_variant":[
        "Baldenofen"
    ],
    "wof:name":"Baldzki Piec",
    "wof:placetype":"locality"
},
  "geometry": {"coordinates":[20.65,53.61666999999999],"type":"Point"}
}