{
  "type": "Feature",
  "properties": {
    "gn:admin1_code":"85.0",
    "gn:admin2_code":"2817.0",
    "gn:admin3_code":"281703.0",
    "gn:asciiname":"Baldzki Piec",
    "gn:cc2":"PL",
    "gn:country_code":"PL",
    "gn:dem":148,
    "gn:feature_class":"P",
    "gn:feature_code":"PPL",
    "gn:name":"Ba\u0142dzki Piec",
    "gn:population":0,
    "gn:timezone":"Europe/Warsaw",
    "iso:country":"PL",
    "name:und_x_variant":[
        "Baldenofen",
        "Ba\u0142dzki Piec"
    ],
    "wof:name":"Baldzki Piec",
    "wof:placetype":"locality"
},
  "geometry": {"coordinates":[20.65,53.61666999999999],"type":"Point"}
}