{
  "type": "Feature",
  "properties": {
    "gn:admin1_code":"82.0",
    "gn:admin2_code":"2211.0",
    "gn:admin3_code":"221107.0",
    "gn:asciiname":"Slawutowko",
    "gn:country_code":"PL",
    "gn:dem":25,
    "gn:feature_class":"P",
    "gn:feature_code":"PPL",
    "gn:name":"S\u0142awut\u00f3wko",
    "gn:population":0,
    "gn:timezone":"Europe/Warsaw",
    "iso:country":"PL",
    "name:und_x_variant":[
        "S\u0142awut\u00f3wko"
    ],
    "wof:name":"Slawutowko",
    "wof:placetype":"locality"
},
  "geometry": {"coordinates":[18.37109,54.6623],"type":"Point"}
}