{
  "type": "Feature",
  "properties": {
    "gn:admin1_code":"75.0",
    "gn:admin2_code":"606.0",
    "gn:admin3_code":"60607.0",
    "gn:asciiname":"Zulin",
    "gn:country_code":"PL",
    "gn:dem":186,
    "gn:feature_class":"P",
    "gn:feature_code":"PPL",
    "gn:name":"\u017bulin",
    "gn:population":0,
    "gn:timezone":"Europe/Warsaw",
    "iso:country":"PL",
    "name:fra_x_preferred":[
        "\u017bulin"
    ],
    "name:pol_x_preferred":[
        "\u017bulin"
    ],
    "name:ukr_x_preferred":[
        "\u0416\u0443\u043b\u0456\u043d"
    ],
    "wof:name":"Zulin",
    "wof:placetype":"locality"
},
  "geometry": {"coordinates":[23.19068,51.07457],"type":"Point"}
}