{
  "type": "Feature",
  "properties": {
    "gn:country":"PL",
    "gn:fcode":"PPL",
    "gn:population":60,
    "iso:country":"PL",
    "name:ast_x_preferred":[
        "Kazimierz"
    ],
    "name:eng_x_preferred":[
        "Kazimierz"
    ],
    "name:fra_x_preferred":[
        "Kazimierz"
    ],
    "name:pol_x_preferred":[
        "Kazimierz"
    ],
    "name:ukr_x_preferred":[
        "\u041a\u0430\u0437\u0456\u043c\u0435\u0436"
    ],
    "name:vie_x_preferred":[
        "Kazimierz"
    ],
    "qs_pg:aaroncc":"PL",
    "qs_pg:gn_country":"PL",
    "qs_pg:gn_fcode":"PPL",
    "qs_pg:gn_pop":60,
    "qs_pg:name":"Kazimierz",
    "qs_pg:name_adm0":"Polska",
    "qs_pg:name_adm1":"Zachodniopomorskie",
    "qs_pg:photos_9r":0,
    "qs_pg:photos_sr":0,
    "qs_pg:pop_sr":1,
    "qs_pg:qs_pg_placetype":"locality",
    "qs_pg:qs_pg_placetype_gp":"Town",
    "qs_pg:woe_adm0":23424923,
    "woe:adm0_id":23424923,
    "woe:name_adm0":"Polska",
    "woe:name_adm1":"Zachodniopomorskie",
    "woe:placetype":"Town",
    "wof:name":"Kazimierz",
    "wof:placetype":"locality",
    "wof:population":60
},
  "geometry": {"coordinates":[16.75372,53.86346],"type":"Point"}
}