{
  "type": "Feature",
  "properties": {
    "gn:admin1_code":"72.0",
    "gn:admin2_code":"209.0",
    "gn:admin3_code":"20903.0",
    "gn:asciiname":"Janowice Duze",
    "gn:country_code":"PL",
    "gn:dem":181,
    "gn:feature_class":"P",
    "gn:feature_code":"PPL",
    "gn:name":"Janowice Du\u017ce",
    "gn:population":0,
    "gn:timezone":"Europe/Warsaw",
    "iso:country":"PL",
    "name:deu_x_historical":[
        "Gro\u00df J\u00e4nowitz"
    ],
    "name:deu_x_preferred":[
        "Gro\u00df J\u00e4nowitz"
    ],
    "wof:name":"Janowice Duze",
    "wof:placetype":"locality"
},
  "geometry": {"coordinates":[16.10083,51.14084],"type":"Point"}
}