{
  "type": "Feature",
  "properties": {
    "gn:admin1_code":"72.0",
    "gn:admin2_code":"209.0",
    "gn:admin3_code":"20903.0",
    "gn:asciiname":"Janowice Duze",
    "gn:country_code":"PL",
    "gn:dem":181,
    "gn:feature_class":"P",
    "gn:feature_code":"PPL",
    "gn:name":"Janowice Du\u017ce",
    "gn:population":0,
    "gn:timezone":"Europe/Warsaw",
    "iso:country":"PL",
    "name:deu_x_historical":[
        "Gro\u00df J\u00e4nowitz"
    ],
    "name:deu_x_preferred":[
        "Gro\u00df J\u00e4nowitz"
    ],
    "name:pol_x_preferred":[
        "Janowice Du\u017ce"
    ],
    "name:ukr_x_preferred":[
        "\u042f\u043d\u043e\u0432\u0456\u0446\u0435-\u0414\u0443\u0436\u0435"
    ],
    "name:urd_x_preferred":[
        "\u062c\u0646\u0648\u0648\u06a9\u06d2 \u062f\u0648\u0632\u0627"
    ],
    "wof:name":"Janowice Duze",
    "wof:placetype":"locality"
},
  "geometry": {"coordinates":[16.10083,51.14084],"type":"Point"}
}