{
  "type": "Feature",
  "properties": {
    "gn:admin1_code":"78.0",
    "gn:admin2_code":"1416.0",
    "gn:admin3_code":"141602.0",
    "gn:asciiname":"Pienki Sobotki",
    "gn:country_code":"PL",
    "gn:dem":121,
    "gn:feature_class":"P",
    "gn:feature_code":"PPL",
    "gn:name":"Pie\u0144ki Sob\u00f3tki",
    "gn:population":0,
    "gn:timezone":"Europe/Warsaw",
    "iso:country":"PL",
    "name:fra_x_preferred":[
        "Pie\u0144ki-Sob\u00f3tki"
    ],
    "name:pol_x_preferred":[
        "Pie\u0144ki-Sob\u00f3tki"
    ],
    "name:ukr_x_preferred":[
        "\u041f\u0435\u043d\u044c\u043a\u0456-\u0421\u043e\u0431\u0443\u0442\u043a\u0456"
    ],
    "name:und_x_variant":[
        "Pie\u0144ki Sob\u00f3tki"
    ],
    "wof:name":"Pienki Sobotki",
    "wof:placetype":"locality"
},
  "geometry": {"coordinates":[22.21749,52.81198000000001],"type":"Point"}
}