{
  "type": "Feature",
  "properties": {
    "gn:admin1_code":"76.0",
    "gn:admin2_code":"808.0",
    "gn:admin3_code":"80801.0",
    "gn:asciiname":"Zagorze",
    "gn:country_code":"PL",
    "gn:dem":112,
    "gn:feature_class":"P",
    "gn:feature_code":"PPL",
    "gn:name":"Zag\u00f3rze",
    "gn:population":0,
    "gn:timezone":"Europe/Warsaw",
    "iso:country":"PL",
    "name:deu_x_historical":[
        "Kl. Heinersdorf"
    ],
    "name:deu_x_preferred":[
        "Kl. Heinersdorf"
    ],
    "wof:name":"Zagorze",
    "wof:placetype":"locality"
},
  "geometry": {"coordinates":[15.33777,52.26396],"type":"Point"}
}