{
  "type": "Feature",
  "properties": {
    "gn:admin1_code":"85.0",
    "gn:admin2_code":"2805.0",
    "gn:admin3_code":"280502.0",
    "gn:asciiname":"Chrzanowo",
    "gn:country_code":"PL",
    "gn:dem":128,
    "gn:feature_class":"P",
    "gn:feature_code":"PPL",
    "gn:name":"Chrzanowo",
    "gn:population":0,
    "gn:timezone":"Europe/Warsaw",
    "iso:country":"PL",
    "name:und_x_variant":[
        "Kalkofen",
        "Chrzanowen",
        "Chrzanowo"
    ],
    "wof:name":"Chrzanowo",
    "wof:placetype":"locality"
},
  "geometry": {"coordinates":[22.27952,53.83996],"type":"Point"}
}