{
  "type": "Feature",
  "properties": {
    "gn:admin1_code":"85.0",
    "gn:admin2_code":"2804.0",
    "gn:admin3_code":"280404.0",
    "gn:asciiname":"Balewo",
    "gn:cc2":"PL",
    "gn:country_code":"PL",
    "gn:dem":-2,
    "gn:feature_class":"P",
    "gn:feature_code":"PPL",
    "gn:name":"Balewo",
    "gn:population":0,
    "gn:timezone":"Europe/Warsaw",
    "iso:country":"PL",
    "name:pol_x_preferred":[
        "Balewo"
    ],
    "name:ukr_x_preferred":[
        "\u0411\u0430\u043b\u0435\u0432\u043e"
    ],
    "name:und_x_variant":[
        "Malborskie",
        "Baalau"
    ],
    "wof:name":"Balewo",
    "wof:placetype":"locality"
},
  "geometry": {"coordinates":[19.40289,54.05999],"type":"Point"}
}