{
  "type": "Feature",
  "properties": {
    "gn:admin1_code":"84.0",
    "gn:admin2_code":"2602.0",
    "gn:admin3_code":"260202.0",
    "gn:asciiname":"Ludwinow",
    "gn:country_code":"PL",
    "gn:dem":265,
    "gn:feature_class":"P",
    "gn:feature_code":"PPL",
    "gn:name":"Ludwin\u00f3w",
    "gn:population":0,
    "gn:timezone":"Europe/Warsaw",
    "iso:country":"PL",
    "name:und_x_variant":[
        "Kolonia Ludwin\u00f3w",
        "Ludwin\u00f3w"
    ],
    "wof:name":"Ludwinow",
    "wof:placetype":"locality"
},
  "geometry": {"coordinates":[20.31415,50.61063],"type":"Point"}
}