{
  "type": "Feature",
  "properties": {
    "gn:admin1_code":"85.0",
    "gn:admin2_code":"2814.0",
    "gn:admin3_code":"281402.0",
    "gn:asciiname":"Botowo",
    "gn:country_code":"PL",
    "gn:dem":181,
    "gn:feature_class":"P",
    "gn:feature_code":"PPL",
    "gn:name":"Botowo",
    "gn:population":0,
    "gn:timezone":"Europe/Warsaw",
    "iso:country":"PL",
    "name:pol_x_preferred":[
        "Botowo"
    ],
    "name:ukr_x_preferred":[
        "\u0411\u043e\u0442\u043e\u0432\u043e"
    ],
    "name:und_x_variant":[
        "Bottau",
        "Bottowen"
    ],
    "name:vie_x_preferred":[
        "Botowo"
    ],
    "wof:name":"Botowo",
    "wof:placetype":"locality"
},
  "geometry": {"coordinates":[20.94851,53.79676],"type":"Point"}
}