{
  "type": "Feature",
  "properties": {
    "gn:admin1_code":"83.0",
    "gn:asciiname":"Misiury",
    "gn:country_code":"PL",
    "gn:dem":323,
    "gn:feature_class":"P",
    "gn:feature_code":"PPL",
    "gn:name":"Misiury",
    "gn:population":0,
    "gn:timezone":"Europe/Warsaw",
    "iso:country":"PL",
    "wof:name":"Misiury",
    "wof:placetype":"locality"
},
  "geometry": {"coordinates":[19.42333,50.2046],"type":"Point"}
}