{
  "type": "Feature",
  "properties": {
    "gn:admin1_code":"81.0",
    "gn:admin2_code":"2011.0",
    "gn:admin3_code":"201109.0",
    "gn:asciiname":"Podhorodnianka",
    "gn:country_code":"PL",
    "gn:dem":122,
    "gn:feature_class":"P",
    "gn:feature_code":"PPL",
    "gn:name":"Podhorodnianka",
    "gn:population":0,
    "gn:timezone":"Europe/Warsaw",
    "iso:country":"PL",
    "name:lit_x_preferred":[
        "Podhorodnianka"
    ],
    "name:pol_x_preferred":[
        "Podhorodnianka"
    ],
    "name:ukr_x_preferred":[
        "\u041f\u043e\u0434\u0433\u043e\u0440\u043e\u0434\u043d\u044f\u043d\u043a\u0430"
    ],
    "wof:name":"Podhorodnianka",
    "wof:placetype":"locality"
},
  "geometry": {"coordinates":[23.10358,53.65759],"type":"Point"}
}