{
  "type": "Feature",
  "properties": {
    "gn:admin1_code":"72.0",
    "gn:admin2_code":"208.0",
    "gn:admin3_code":"20810.0",
    "gn:asciiname":"Nagodzice",
    "gn:country_code":"PL",
    "gn:dem":428,
    "gn:feature_class":"P",
    "gn:feature_code":"PPL",
    "gn:name":"Nagodzice",
    "gn:population":0,
    "gn:timezone":"Europe/Warsaw",
    "iso:country":"PL",
    "name:deu_x_preferred":[
        "Nagodzice"
    ],
    "name:pol_x_preferred":[
        "Nagodzice"
    ],
    "name:ukr_x_preferred":[
        "\u041d\u0430\u0491\u043e\u0434\u0437\u0456\u0446\u0435"
    ],
    "wof:name":"Nagodzice",
    "wof:placetype":"locality"
},
  "geometry": {"coordinates":[16.66111,50.167],"type":"Point"}
}