{
  "type": "Feature",
  "properties": {
    "gn:admin1_code":"86.0",
    "gn:admin2_code":"3004.0",
    "gn:admin3_code":"300401.0",
    "gn:asciiname":"Leonow",
    "gn:country_code":"PL",
    "gn:dem":122,
    "gn:feature_class":"P",
    "gn:feature_code":"PPL",
    "gn:name":"Leon\u00f3w",
    "gn:population":0,
    "gn:timezone":"Europe/Warsaw",
    "iso:country":"PL",
    "name:ceb_x_preferred":[
        "Leon\u00f3w"
    ],
    "name:fra_x_preferred":[
        "Leon\u00f3w"
    ],
    "name:pol_x_preferred":[
        "Leon\u00f3w"
    ],
    "name:ukr_x_preferred":[
        "\u041b\u0435\u043e\u043d\u0443\u0432"
    ],
    "name:und_x_variant":[
        "Leon\u00f3w"
    ],
    "wof:name":"Leonow",
    "wof:placetype":"locality"
},
  "geometry": {"coordinates":[17.27745,51.89446],"type":"Point"}
}