{
  "type": "Feature",
  "properties": {
    "gn:admin1_code":"75.0",
    "gn:admin2_code":"615.0",
    "gn:admin3_code":"61504.0",
    "gn:asciiname":"Zosinowo",
    "gn:country_code":"PL",
    "gn:dem":151,
    "gn:feature_class":"P",
    "gn:feature_code":"PPL",
    "gn:name":"Zosinowo",
    "gn:population":0,
    "gn:timezone":"Europe/Warsaw",
    "iso:country":"PL",
    "name:fra_x_preferred":[
        "Zosinowo"
    ],
    "name:pol_x_preferred":[
        "Zosinowo"
    ],
    "name:ukr_x_preferred":[
        "\u0417\u043e\u0441\u0456\u043d\u043e\u0432\u043e"
    ],
    "wof:name":"Zosinowo",
    "wof:placetype":"locality"
},
  "geometry": {"coordinates":[22.65369,51.86833],"type":"Point"}
}