{
  "type": "Feature",
  "properties": {
    "gn:admin1_code":"78.0",
    "gn:admin2_code":"1425.0",
    "gn:admin3_code":"142511.0",
    "gn:asciiname":"Podgorki",
    "gn:country_code":"PL",
    "gn:dem":180,
    "gn:feature_class":"P",
    "gn:feature_code":"PPL",
    "gn:name":"Podg\u00f3rki",
    "gn:population":0,
    "gn:timezone":"Europe/Warsaw",
    "iso:country":"PL",
    "name:fra_x_preferred":[
        "Podg\u00f3rki"
    ],
    "name:pol_x_preferred":[
        "Podg\u00f3rki"
    ],
    "name:ukr_x_preferred":[
        "\u041f\u043e\u0434\u0491\u0443\u0440\u043a\u0456"
    ],
    "wof:name":"Podgorki",
    "wof:placetype":"locality"
},
  "geometry": {"coordinates":[21.17772,51.25429000000001],"type":"Point"}
}