{
  "type": "Feature",
  "properties": {
    "gn:admin1_code":"75.0",
    "gn:admin2_code":"608.0",
    "gn:admin3_code":"60808.0",
    "gn:asciiname":"Kolonia Rudno",
    "gn:cc2":"PL",
    "gn:country_code":"PL",
    "gn:dem":141,
    "gn:feature_class":"P",
    "gn:feature_code":"PPL",
    "gn:name":"Kolonia Rudno",
    "gn:population":0,
    "gn:timezone":"Europe/Warsaw",
    "iso:country":"PL",
    "name:und_x_variant":[
        "Do Rudna",
        "Kolonia Rudno"
    ],
    "wof:name":"Kolonia Rudno",
    "wof:placetype":"locality"
},
  "geometry": {"coordinates":[22.38333,51.51667],"type":"Point"}
}