{
  "type": "Feature",
  "properties": {
    "gn:admin1_code":"72.0",
    "gn:admin2_code":"217.0",
    "gn:admin3_code":"21705.0",
    "gn:asciiname":"Miechowice",
    "gn:country_code":"PL",
    "gn:dem":153,
    "gn:feature_class":"P",
    "gn:feature_code":"PPL",
    "gn:name":"Miechowice",
    "gn:population":0,
    "gn:timezone":"Europe/Warsaw",
    "iso:country":"PL",
    "name:fra_x_preferred":[
        "Miechowice"
    ],
    "name:pol_x_preferred":[
        "Miechowice"
    ],
    "name:ukr_x_preferred":[
        "\u041c\u0435\u0445\u043e\u0432\u0456\u0446\u0435"
    ],
    "wof:name":"Miechowice",
    "wof:placetype":"locality"
},
  "geometry": {"coordinates":[17.24804,50.81285],"type":"Point"}
}