{
  "type": "Feature",
  "properties": {
    "gn:admin1_code":"72.0",
    "gn:admin2_code":"261.0",
    "gn:admin3_code":"26101.0",
    "gn:asciiname":"Maciejowa",
    "gn:cc2":"PL",
    "gn:country_code":"PL",
    "gn:dem":335,
    "gn:feature_class":"P",
    "gn:feature_code":"PPL",
    "gn:name":"Maciejowa",
    "gn:population":0,
    "gn:timezone":"Europe/Warsaw",
    "iso:country":"PL",
    "name:und_x_variant":[
        "Maciejowo",
        "Maciejowa"
    ],
    "wof:name":"Maciejowa",
    "wof:placetype":"neighbourhood"
},
  "geometry": {"coordinates":[15.75917,50.91083],"type":"Point"}
}