{
  "type": "Feature",
  "properties": {
    "gn:admin1_code":"84.0",
    "gn:admin2_code":"2607.0",
    "gn:admin3_code":"260702.0",
    "gn:asciiname":"Wolka Petkowska",
    "gn:country_code":"PL",
    "gn:dem":146,
    "gn:feature_class":"P",
    "gn:feature_code":"PPL",
    "gn:name":"W\u00f3lka P\u0119tkowska",
    "gn:population":0,
    "gn:timezone":"Europe/Warsaw",
    "iso:country":"PL",
    "name:ceb_x_preferred":[
        "W\u00f3lka P\u0119tkowska"
    ],
    "name:pol_x_preferred":[
        "W\u00f3lka P\u0119tkowska"
    ],
    "name:ukr_x_preferred":[
        "\u0412\u0443\u043b\u044c\u043a\u0430-\u041f\u0435\u043d\u0442\u043a\u043e\u0432\u0441\u044c\u043a\u0430"
    ],
    "wof:name":"Wolka Petkowska",
    "wof:placetype":"locality"
},
  "geometry": {"coordinates":[21.61887,51.00163],"type":"Point"}
}