{
  "type": "Feature",
  "properties": {
    "gn:admin1_code":"87.0",
    "gn:admin2_code":"3206.0",
    "gn:admin3_code":"320601.0",
    "gn:asciiname":"Piaseczno",
    "gn:country_code":"PL",
    "gn:dem":97,
    "gn:feature_class":"P",
    "gn:feature_code":"PPL",
    "gn:name":"Piaseczno",
    "gn:population":0,
    "gn:timezone":"Europe/Warsaw",
    "iso:country":"PL",
    "name:ceb_x_preferred":[
        "Piaseczno"
    ],
    "name:deu_x_preferred":[
        "Piaseczno"
    ],
    "name:pol_x_preferred":[
        "Piaseczno"
    ],
    "name:ukr_x_preferred":[
        "\u041f\u044f\u0441\u0435\u0447\u043d\u043e"
    ],
    "name:vie_x_preferred":[
        "Piaseczno"
    ],
    "wof:name":"Piaseczno",
    "wof:placetype":"locality"
},
  "geometry": {"coordinates":[14.70181,53.06039000000001],"type":"Point"}
}