{
  "type": "Feature",
  "properties": {
    "gn:admin1_code":"77.0",
    "gn:admin2_code":"1204.0",
    "gn:admin3_code":"120406.0",
    "gn:asciiname":"Podkosciele",
    "gn:country_code":"PL",
    "gn:dem":215,
    "gn:feature_class":"P",
    "gn:feature_code":"PPL",
    "gn:name":"Podko\u015bciele",
    "gn:population":0,
    "gn:timezone":"Europe/Warsaw",
    "iso:country":"PL",
    "wof:name":"Podkosciele",
    "wof:placetype":"locality"
},
  "geometry": {"coordinates":[21.10359,50.1497],"type":"Point"}
}