{
  "type": "Feature",
  "properties": {
    "gn:admin1_code":"72.0",
    "gn:admin2_code":"209.0",
    "gn:admin3_code":"20907.0",
    "gn:asciiname":"Golanka Dolna",
    "gn:country_code":"PL",
    "gn:dem":126,
    "gn:feature_class":"P",
    "gn:feature_code":"PPL",
    "gn:name":"Golanka Dolna",
    "gn:population":0,
    "gn:timezone":"Europe/Warsaw",
    "iso:country":"PL",
    "name:deu_x_historical":[
        "Nieder-Heidau"
    ],
    "name:deu_x_preferred":[
        "Nieder-Heidau"
    ],
    "wof:name":"Golanka Dolna",
    "wof:placetype":"locality"
},
  "geometry": {"coordinates":[16.32146,51.256],"type":"Point"}
}