{
  "type": "Feature",
  "properties": {
    "iso:country":"PL",
    "name:azb_x_preferred":[
        "\u0633\u062a\u0698\u0642\u0648\u0648\u0648"
    ],
    "name:ceb_x_preferred":[
        "Strzegowo"
    ],
    "name:deu_x_preferred":[
        "Strzegowo"
    ],
    "name:fas_x_preferred":[
        "\u0633\u062a\u0698\u06af\u0648\u0648\u0648"
    ],
    "name:fra_x_preferred":[
        "Strzegowo"
    ],
    "name:heb_x_preferred":[
        "\u05e9\u05e6'\u05d2\u05d5\u05d1\u05d5"
    ],
    "name:nld_x_preferred":[
        "Strzegowo"
    ],
    "name:pol_x_preferred":[
        "Strzegowo"
    ],
    "name:por_x_preferred":[
        "Strzegowo"
    ],
    "name:ukr_x_preferred":[
        "\u0421\u0442\u0448\u0435\u0491\u043e\u0432\u043e"
    ],
    "wof:coterminous":[
        1125381181
    ],
    "wof:name":"Strzegowo",
    "wof:placetype":"locality"
},
  "geometry": {"coordinates":[20.3100163551357,52.9161212594806],"type":"Point"}
}