{
  "type": "Feature",
  "properties": {
    "iso:country":"PL",
    "name:pol_x_preferred":[
        "Strzegowo"
    ],
    "wof:name":"Strzegowo",
    "wof:placetype":"locality"
},
  "geometry": {"coordinates":[20.3100163551357,52.9161212594806],"type":"Point"}
}