{
  "type": "Feature",
  "properties": {
    "gn:country":"PL",
    "gn:fcode":"PPL",
    "gn:population":590,
    "iso:country":"PL",
    "name:ast_x_preferred":[
        "Czersk"
    ],
    "name:azb_x_preferred":[
        "\u0686\u0631\u0633\u06a9"
    ],
    "name:ceb_x_preferred":[
        "Czersk"
    ],
    "name:deu_x_preferred":[
        "Czersk"
    ],
    "name:eng_x_preferred":[
        "Czersk"
    ],
    "name:fas_x_preferred":[
        "\u0686\u0631\u0633\u06a9"
    ],
    "name:fra_x_preferred":[
        "Czersk"
    ],
    "name:nld_x_preferred":[
        "Czersk"
    ],
    "name:pol_x_preferred":[
        "Czersk"
    ],
    "name:rus_x_preferred":[
        "\u0427\u0435\u0440\u0441\u043a"
    ],
    "name:ukr_x_preferred":[
        "\u0427\u0435\u0440\u0441\u044c\u043a"
    ],
    "qs_pg:aaroncc":"PL",
    "qs_pg:gn_country":"PL",
    "qs_pg:gn_fcode":"PPL",
    "qs_pg:gn_pop":590,
    "qs_pg:name":"Czersk",
    "qs_pg:name_adm0":"Polska",
    "qs_pg:name_adm1":"Mazowieckie",
    "qs_pg:photos":186,
    "qs_pg:photos_1k":38,
    "qs_pg:photos_9k":1,
    "qs_pg:photos_9r":4,
    "qs_pg:photos_all":186,
    "qs_pg:photos_sr":4,
    "qs_pg:pop_sr":2,
    "qs_pg:qs_pg_placetype":"locality",
    "qs_pg:qs_pg_placetype_gp":"Town",
    "qs_pg:woe_adm0":23424923,
    "woe:adm0_id":23424923,
    "woe:name_adm0":"Polska",
    "woe:name_adm1":"Mazowieckie",
    "woe:placetype":"Town",
    "wof:name":"Czersk",
    "wof:placetype":"locality",
    "wof:population":590
},
  "geometry": {"coordinates":[21.23108,51.95876],"type":"Point"}
}