{
  "type": "Feature",
  "properties": {
    "gn:admin1_code":"79.0",
    "gn:admin2_code":"1607.0",
    "gn:admin3_code":"160706.0",
    "gn:asciiname":"Siodlary",
    "gn:country_code":"PL",
    "gn:dem":291,
    "gn:feature_class":"P",
    "gn:feature_code":"PPL",
    "gn:name":"Siod\u0142ary",
    "gn:population":0,
    "gn:timezone":"Europe/Warsaw",
    "iso:country":"PL",
    "name:und_x_variant":[
        "Siod\u0142ary"
    ],
    "wof:name":"Siodlary",
    "wof:placetype":"locality"
},
  "geometry": {"coordinates":[17.15,50.51667],"type":"Point"}
}