{
  "type": "Feature",
  "properties": {
    "gn:admin1_code":"81.0",
    "gn:admin2_code":"2012.0",
    "gn:admin3_code":"201208.0",
    "gn:asciiname":"Sadzawki",
    "gn:country_code":"PL",
    "gn:dem":201,
    "gn:feature_class":"P",
    "gn:feature_code":"PPL",
    "gn:name":"Sadzawki",
    "gn:population":0,
    "gn:timezone":"Europe/Warsaw",
    "iso:country":"PL",
    "name:lit_x_preferred":[
        "So\u017eelkos"
    ],
    "name:pol_x_preferred":[
        "Sadzawki"
    ],
    "name:ukr_x_preferred":[
        "\u0421\u0430\u0434\u0437\u0430\u0432\u043a\u0456"
    ],
    "name:urd_x_preferred":[
        "\u0633\u062f\u0632\u0648\u06a9\u06cc"
    ],
    "wof:name":"Sadzawki",
    "wof:placetype":"locality"
},
  "geometry": {"coordinates":[23.11094,54.29198],"type":"Point"}
}