{
  "type": "Feature",
  "properties": {
    "gn:admin1_code":"72.0",
    "gn:admin2_code":"217.0",
    "gn:admin3_code":"21704.0",
    "gn:asciiname":"Strzegow",
    "gn:country_code":"PL",
    "gn:dem":169,
    "gn:feature_class":"P",
    "gn:feature_code":"PPL",
    "gn:name":"Strzeg\u00f3w",
    "gn:population":0,
    "gn:timezone":"Europe/Warsaw",
    "iso:country":"PL",
    "name:pol_x_preferred":[
        "Strzeg\u00f3w"
    ],
    "name:ukr_x_preferred":[
        "\u0421\u0442\u0448\u0435\u0491\u0443\u0432"
    ],
    "wof:name":"Strzegow",
    "wof:placetype":"locality"
},
  "geometry": {"coordinates":[17.03928,50.75231],"type":"Point"}
}