{
  "type": "Feature",
  "properties": {
    "gn:admin1_code":"74.0",
    "gn:admin2_code":"1020.0",
    "gn:admin3_code":"102006.0",
    "gn:asciiname":"Sokolniki",
    "gn:cc2":"PL",
    "gn:country_code":"PL",
    "gn:dem":142,
    "gn:feature_class":"P",
    "gn:feature_code":"PPL",
    "gn:name":"Sokolniki",
    "gn:population":321,
    "gn:timezone":"Europe/Warsaw",
    "iso:country":"PL",
    "name:ceb_x_preferred":[
        "Sokolniki"
    ],
    "name:pol_x_preferred":[
        "Sokolniki"
    ],
    "name:ukr_x_preferred":[
        "\u0421\u043e\u043a\u043e\u043b\u044c\u043d\u0438\u043a\u0438"
    ],
    "name:und_x_variant":[
        "Sokolniki-Las"
    ],
    "wof:name":"Sokolniki",
    "wof:placetype":"locality",
    "wof:population":321
},
  "geometry": {"coordinates":[19.36529,51.9669],"type":"Point"}
}