{
  "type": "Feature",
  "properties": {
    "gn:admin1_code":"75.0",
    "gn:admin2_code":"609.0",
    "gn:admin3_code":"60906.0",
    "gn:asciiname":"Wierciszow",
    "gn:country_code":"PL",
    "gn:dem":226,
    "gn:feature_class":"P",
    "gn:feature_code":"PPL",
    "gn:name":"Wiercisz\u00f3w",
    "gn:population":0,
    "gn:timezone":"Europe/Warsaw",
    "iso:country":"PL",
    "name:ceb_x_preferred":[
        "Wiercisz\u00f3w"
    ],
    "name:fra_x_preferred":[
        "Wiercisz\u00f3w"
    ],
    "name:pol_x_preferred":[
        "Wiercisz\u00f3w"
    ],
    "name:ukr_x_preferred":[
        "\u0412\u0435\u0440\u0446\u0438\u0448\u0443\u0432"
    ],
    "wof:name":"Wierciszow",
    "wof:placetype":"locality"
},
  "geometry": {"coordinates":[22.57157,51.06481],"type":"Point"}
}