{
  "type": "Feature",
  "properties": {
    "gn:admin1_code":"78.0",
    "gn:admin2_code":"1427.0",
    "gn:admin3_code":"142705.0",
    "gn:asciiname":"Goleszyn",
    "gn:country_code":"PL",
    "gn:dem":120,
    "gn:feature_class":"P",
    "gn:feature_code":"PPL",
    "gn:name":"Goleszyn",
    "gn:population":0,
    "gn:timezone":"Europe/Warsaw",
    "iso:country":"PL",
    "name:ceb_x_preferred":[
        "Goleszyn"
    ],
    "name:eng_x_preferred":[
        "Goleszyn"
    ],
    "name:fra_x_preferred":[
        "Goleszyn"
    ],
    "name:pol_x_preferred":[
        "Goleszyn"
    ],
    "name:rus_x_preferred":[
        "\u0413\u043e\u043b\u0435\u0448\u0438\u043d"
    ],
    "name:ukr_x_preferred":[
        "\u0490\u043e\u043b\u0435\u0448\u0438\u043d"
    ],
    "wof:name":"Goleszyn",
    "wof:placetype":"locality"
},
  "geometry": {"coordinates":[19.72142,52.78374],"type":"Point"}
}