{
  "type": "Feature",
  "properties": {
    "gn:country":"PL",
    "gn:fcode":"PPL",
    "gn:population":130,
    "iso:country":"PL",
    "name:ceb_x_preferred":[
        "Stanis\u0142aw\u00f3w"
    ],
    "name:deu_x_preferred":[
        "Stanis\u0142aw\u00f3w"
    ],
    "name:fra_x_preferred":[
        "Stanis\u0142aw\u00f3w"
    ],
    "name:nld_x_preferred":[
        "Stanis\u0142aw\u00f3w"
    ],
    "name:pol_x_preferred":[
        "Stanis\u0142aw\u00f3w"
    ],
    "name:por_x_preferred":[
        "Stanis\u0142aw\u00f3w"
    ],
    "name:sco_x_preferred":[
        "Stanis\u0142aw\u00f3w"
    ],
    "name:ukr_x_preferred":[
        "\u0421\u0442\u0430\u043d\u0456\u0441\u043b\u0430\u0432\u0443\u0432"
    ],
    "qs_pg:aaroncc":"PL",
    "qs_pg:gn_country":"PL",
    "qs_pg:gn_fcode":"PPL",
    "qs_pg:gn_pop":130,
    "qs_pg:name":"Stanis\u0142aw\u00f3w",
    "qs_pg:name_adm0":"Polska",
    "qs_pg:name_adm1":"Wielkopolskie",
    "qs_pg:photos_9r":0,
    "qs_pg:photos_sr":0,
    "qs_pg:pop_sr":1,
    "qs_pg:qs_pg_placetype":"locality",
    "qs_pg:qs_pg_placetype_gp":"Town",
    "qs_pg:woe_adm0":23424923,
    "woe:adm0_id":23424923,
    "woe:name_adm0":"Polska",
    "woe:name_adm1":"Wielkopolskie",
    "woe:placetype":"Town",
    "wof:name":"Stanis\u0142aw\u00f3w",
    "wof:placetype":"locality",
    "wof:population":130
},
  "geometry": {"coordinates":[17.98428,52.11578],"type":"Point"}
}