{
  "type": "Feature",
  "properties": {
    "gn:admin1_code":"86.0",
    "gn:admin2_code":"3018.0",
    "gn:admin3_code":"301804.0",
    "gn:asciiname":"Kobyla Gora",
    "gn:country_code":"PL",
    "gn:dem":201,
    "gn:feature_class":"P",
    "gn:feature_code":"PPLA3",
    "gn:name":"Kobyla G\u00f3ra",
    "gn:population":2000,
    "gn:timezone":"Europe/Warsaw",
    "iso:country":"PL",
    "wof:name":"Kobyla Gora",
    "wof:placetype":"locality",
    "wof:population":2000
},
  "geometry": {"coordinates":[17.83811,51.37923],"type":"Point"}
}