{
  "type": "Feature",
  "properties": {
    "gn:admin1_code":"86.0",
    "gn:admin2_code":"3018.0",
    "gn:admin3_code":"301804.0",
    "gn:asciiname":"Kobyla Gora",
    "gn:country_code":"PL",
    "gn:dem":201,
    "gn:feature_class":"P",
    "gn:feature_code":"PPLA3",
    "gn:name":"Kobyla G\u00f3ra",
    "gn:population":2000,
    "gn:timezone":"Europe/Warsaw",
    "iso:country":"PL",
    "name:azb_x_preferred":[
        "\u0642\u0645\u06cc\u0646\u0627 \u06a9\u0648\u0628\u0644\u0627 \u0642\u0648\u0631\u0627"
    ],
    "name:bel_x_preferred":[
        "\u041a\u0430\u0431\u044b\u043b\u044f \u0413\u0443\u0440\u0430"
    ],
    "name:ceb_x_preferred":[
        "Kobyla G\u00f3ra"
    ],
    "name:eus_x_preferred":[
        "Kobyla G\u00f3ra udalerria"
    ],
    "name:fas_x_preferred":[
        "\u06af\u0645\u06cc\u0646\u0627 \u06a9\u0648\u0628\u0644\u0627 \u06af\u0648\u0631\u0627"
    ],
    "name:fra_x_preferred":[
        "Kobyla G\u00f3ra"
    ],
    "name:ita_x_preferred":[
        "Kobyla G\u00f3ra"
    ],
    "name:nld_x_preferred":[
        "Kobyla G\u00f3ra"
    ],
    "name:pol_x_preferred":[
        "Kobyla G\u00f3ra"
    ],
    "name:rus_x_preferred":[
        "\u041a\u043e\u0431\u044b\u043b\u044f-\u0413\u0443\u0440\u0430"
    ],
    "name:slk_x_preferred":[
        "Gmina Kobyla G\u00f3ra"
    ],
    "name:ukr_x_preferred":[
        "\u0413\u043c\u0456\u043d\u0430 \u041a\u043e\u0431\u0438\u043b\u044f \u0490\u0443\u0440\u0430"
    ],
    "name:war_x_preferred":[
        "Gmina Kobyla G\u00f3ra"
    ],
    "wof:name":"Kobyla Gora",
    "wof:placetype":"locality",
    "wof:population":2000
},
  "geometry": {"coordinates":[17.83811,51.37923],"type":"Point"}
}