{
  "type": "Feature",
  "properties": {
    "gn:admin1_code":"82.0",
    "gn:admin2_code":"2206.0",
    "gn:admin3_code":"220602.0",
    "gn:asciiname":"Turzonka",
    "gn:country_code":"PL",
    "gn:dem":167,
    "gn:feature_class":"P",
    "gn:feature_code":"PPL",
    "gn:name":"Turzonka",
    "gn:population":0,
    "gn:timezone":"Europe/Warsaw",
    "iso:country":"PL",
    "name:azb_x_preferred":[
        "\u062a\u0648\u0631\u0632\u0646\u06a9\u0627"
    ],
    "name:fas_x_preferred":[
        "\u062a\u0648\u0631\u0632\u0646\u06a9\u0627"
    ],
    "name:pol_x_preferred":[
        "Turzonka"
    ],
    "name:urd_x_preferred":[
        "\u062a\u0631\u0632\u0646\u06a9\u0627"
    ],
    "wof:name":"Turzonka",
    "wof:placetype":"locality"
},
  "geometry": {"coordinates":[17.73943,54.03896],"type":"Point"}
}