{
  "type": "Feature",
  "properties": {
    "gn:admin1_code":"81.0",
    "gn:admin2_code":"2010.0",
    "gn:admin3_code":"201002.0",
    "gn:asciiname":"Putkowice Nagorne",
    "gn:country_code":"PL",
    "gn:dem":125,
    "gn:feature_class":"P",
    "gn:feature_code":"PPL",
    "gn:name":"Putkowice Nag\u00f3rne",
    "gn:population":0,
    "gn:timezone":"Europe/Warsaw",
    "iso:country":"PL",
    "name:fra_x_preferred":[
        "Putkowice Nag\u00f3rne"
    ],
    "name:lit_x_preferred":[
        "Putkovice Nagurn\u0117"
    ],
    "name:pol_x_preferred":[
        "Putkowice Nag\u00f3rne"
    ],
    "name:ukr_x_preferred":[
        "\u041f\u0443\u0442\u043a\u043e\u0432\u0456\u0446\u0435-\u041d\u0430\u0491\u0443\u0440\u043d\u0435"
    ],
    "wof:name":"Putkowice Nagorne",
    "wof:placetype":"locality"
},
  "geometry": {"coordinates":[22.59476,52.46961],"type":"Point"}
}