{
  "type": "Feature",
  "properties": {
    "gn:admin1_code":"81.0",
    "gn:admin2_code":"2010.0",
    "gn:admin3_code":"201002.0",
    "gn:asciiname":"Putkowice Nagorne",
    "gn:country_code":"PL",
    "gn:dem":125,
    "gn:feature_class":"P",
    "gn:feature_code":"PPL",
    "gn:name":"Putkowice Nag\u00f3rne",
    "gn:population":0,
    "gn:timezone":"Europe/Warsaw",
    "iso:country":"PL",
    "wof:name":"Putkowice Nagorne",
    "wof:placetype":"locality"
},
  "geometry": {"coordinates":[22.59476,52.46961],"type":"Point"}
}