{
  "type": "Feature",
  "properties": {
    "gn:admin1_code":"79.0",
    "gn:admin2_code":"1601.0",
    "gn:admin3_code":"160106.0",
    "gn:asciiname":"Siemkow",
    "gn:country_code":"PL",
    "gn:dem":153,
    "gn:feature_class":"P",
    "gn:feature_code":"PPL",
    "gn:name":"Siemk\u00f3w",
    "gn:population":0,
    "gn:timezone":"Europe/Warsaw",
    "iso:country":"PL",
    "wof:name":"Siemkow",
    "wof:placetype":"locality"
},
  "geometry": {"coordinates":[17.45,50.81667],"type":"Point"}
}