{
  "type": "Feature",
  "properties": {
    "gn:admin1_code":"74.0",
    "gn:admin2_code":"1007.0",
    "gn:admin3_code":"100708.0",
    "gn:asciiname":"Skorkowice",
    "gn:country_code":"PL",
    "gn:dem":200,
    "gn:feature_class":"P",
    "gn:feature_code":"PPL",
    "gn:name":"Sk\u00f3rkowice",
    "gn:population":0,
    "gn:timezone":"Europe/Warsaw",
    "iso:country":"PL",
    "name:fra_x_preferred":[
        "Sk\u00f3rkowice"
    ],
    "name:pol_x_preferred":[
        "Sk\u00f3rkowice"
    ],
    "name:ukr_x_preferred":[
        "\u0421\u043a\u0443\u0440\u043a\u043e\u0432\u0456\u0446\u0435"
    ],
    "wof:name":"Skorkowice",
    "wof:placetype":"locality"
},
  "geometry": {"coordinates":[20.0437,51.2307],"type":"Point"}
}