{
  "type": "Feature",
  "properties": {
    "gn:admin1_code":"80.0",
    "gn:admin2_code":"1805.0",
    "gn:admin3_code":"180503.0",
    "gn:asciiname":"Pagorek Radosc",
    "gn:country_code":"PL",
    "gn:dem":263,
    "gn:feature_class":"P",
    "gn:feature_code":"PPL",
    "gn:name":"Pag\u00f3rek Rado\u015b\u0107",
    "gn:population":0,
    "gn:timezone":"Europe/Warsaw",
    "iso:country":"PL",
    "wof:name":"Pagorek Radosc",
    "wof:placetype":"locality"
},
  "geometry": {"coordinates":[21.37562,49.67763],"type":"Point"}
}