{
  "type": "Feature",
  "properties": {
    "iso:country":"PL",
    "name:ast_x_preferred":[
        "Konina"
    ],
    "name:ceb_x_preferred":[
        "Konina"
    ],
    "name:eng_x_preferred":[
        "Konina"
    ],
    "name:fra_x_preferred":[
        "Konina"
    ],
    "name:nld_x_preferred":[
        "Konina"
    ],
    "name:pol_x_preferred":[
        "Konina"
    ],
    "name:ukr_x_preferred":[
        "\u041a\u043e\u043d\u0456\u043d\u0430"
    ],
    "qs:a0":"Rzeczpospolita Polska",
    "qs:a1":"*Malopolskie",
    "qs:a1r":"0",
    "qs:a2":"Limanowski",
    "qs:adm0":"Rzeczpospolita Polska",
    "qs:la_lc":"*",
    "qs:level":"locality",
    "qs:loc":"Konina",
    "qs:loc_alt":"Konina",
    "qs:pop":0,
    "qs:type":"buffered point",
    "wd:wordcount":92,
    "wof:name":"Konina",
    "wof:placetype":"locality"
},
  "geometry": {"coordinates":[20.127251,49.609806],"type":"Point"}
}