{
  "type": "Feature",
  "properties": {
    "gn:admin1_code":"84.0",
    "gn:admin2_code":"2607.0",
    "gn:admin3_code":"260705.0",
    "gn:asciiname":"Prawecin",
    "gn:country_code":"PL",
    "gn:dem":237,
    "gn:feature_class":"P",
    "gn:feature_code":"PPL",
    "gn:name":"Praw\u0119cin",
    "gn:population":0,
    "gn:timezone":"Europe/Warsaw",
    "iso:country":"PL",
    "name:ceb_x_preferred":[
        "Praw\u0119cin"
    ],
    "name:pol_x_preferred":[
        "Praw\u0119cin"
    ],
    "name:ukr_x_preferred":[
        "\u041f\u0440\u0430\u0432\u0435\u043d\u0446\u0438\u043d"
    ],
    "wof:name":"Prawecin",
    "wof:placetype":"locality"
},
  "geometry": {"coordinates":[21.23648,50.95219],"type":"Point"}
}