{
  "type": "Feature",
  "properties": {
    "iso:country":"PL",
    "name:ceb_x_preferred":[
        "Czarna Bia\u0142ostocka"
    ],
    "name:deu_x_preferred":[
        "Czarna Bia\u0142ostocka"
    ],
    "name:dsb_x_preferred":[
        "Czarna Bia\u0142ostocka"
    ],
    "name:epo_x_preferred":[
        "Czarna Bia\u0142ostocka"
    ],
    "name:fra_x_preferred":[
        "Czarna Bia\u0142ostocka"
    ],
    "name:jav_x_preferred":[
        "Czarna Bia\u0142ostocka"
    ],
    "name:lav_x_preferred":[
        "\u010carna Bjalostocka"
    ],
    "name:lit_x_preferred":[
        "\u010carna Bialostocka"
    ],
    "name:msa_x_preferred":[
        "Czarna Bia\u0142ostocka"
    ],
    "name:nld_x_preferred":[
        "Czarna Bia\u0142ostocka"
    ],
    "name:pol_x_preferred":[
        "Czarna Bia\u0142ostocka"
    ],
    "name:por_x_preferred":[
        "Czarna Bia\u0142ostocka"
    ],
    "name:ron_x_preferred":[
        "Czarna Bia\u0142ostocka"
    ],
    "name:rus_x_preferred":[
        "\u0427\u0430\u0440\u043d\u0430-\u0411\u044f\u043b\u043e\u0441\u0442\u043e\u0446\u043a\u0430"
    ],
    "name:slk_x_preferred":[
        "Czarna Bia\u0142ostocka"
    ],
    "name:srp_x_preferred":[
        "\u0427\u0430\u0440\u043d\u0430 \u0411\u0458\u0430\u043b\u043e\u0441\u0442\u043e\u0446\u043a\u0430"
    ],
    "name:szl_x_preferred":[
        "Czorno Bjo\u0142ostocko"
    ],
    "name:ukr_x_preferred":[
        "\u0427\u0430\u0440\u043d\u0430-\u0411\u0456\u043b\u043e\u0441\u0442\u043e\u0446\u044c\u043a\u0430"
    ],
    "name:vie_x_preferred":[
        "Czarna Bia\u0142ostocka"
    ],
    "name:zho_x_preferred":[
        "\u9ed1\u6bd4\u4e9e\u6c83\u65af\u6258\u8328\u5361"
    ],
    "qs_pg:aaroncc":"PL",
    "qs_pg:name":"Czarna Bia\u0142ostocka",
    "qs_pg:name_adm0":"Polska",
    "qs_pg:name_adm1":"Podlaskie",
    "qs_pg:photos":1,
    "qs_pg:photos_1k":1,
    "qs_pg:photos_9k":1,
    "qs_pg:photos_9r":1,
    "qs_pg:photos_all":1,
    "qs_pg:photos_sr":1,
    "qs_pg:pop_sr":0,
    "qs_pg:qs_pg_placetype":"localadmin",
    "qs_pg:qs_pg_placetype_gp":"LocalAdmin",
    "qs_pg:woe_adm0":23424923,
    "woe:adm0_id":23424923,
    "woe:name_adm0":"Polska",
    "woe:name_adm1":"Podlaskie",
    "woe:placetype":"LocalAdmin",
    "wof:name":"Czarna Bia\u0142ostocka",
    "wof:placetype":"localadmin"
},
  "geometry": {"coordinates":[23.28146,53.30509],"type":"Point"}
}