{
  "type": "Feature",
  "properties": {
    "gn:admin1_code":"72.0",
    "gn:admin2_code":"212.0",
    "gn:admin3_code":"21201.0",
    "gn:asciiname":"Wolbromow",
    "gn:country_code":"PL",
    "gn:dem":289,
    "gn:feature_class":"P",
    "gn:feature_code":"PPL",
    "gn:name":"Wolbrom\u00f3w",
    "gn:population":0,
    "gn:timezone":"Europe/Warsaw",
    "iso:country":"PL",
    "name:nld_x_preferred":[
        "Wolbrom\u00f3w"
    ],
    "name:pol_x_preferred":[
        "Wolbrom\u00f3w"
    ],
    "name:ukr_x_preferred":[
        "\u0412\u043e\u043b\u044c\u0431\u0440\u043e\u043c\u0443\u0432"
    ],
    "wof:name":"Wolbromow",
    "wof:placetype":"locality"
},
  "geometry": {"coordinates":[15.43553,51.10981],"type":"Point"}
}