{
  "type": "Feature",
  "properties": {
    "gn:country":"PL",
    "gn:fcode":"PPL",
    "gn:population":966,
    "iso:country":"PL",
    "name:fra_x_preferred":[
        "\u0141\u0119ki"
    ],
    "name:pol_x_preferred":[
        "\u0141\u0119ki"
    ],
    "name:ukr_x_preferred":[
        "\u041b\u0435\u043d\u043a\u0456"
    ],
    "qs_pg:aaroncc":"PL",
    "qs_pg:gn_country":"PL",
    "qs_pg:gn_fcode":"PPL",
    "qs_pg:gn_pop":966,
    "qs_pg:name":"\u0141\u0119ki",
    "qs_pg:name_adm0":"Polska",
    "qs_pg:name_adm1":"Ma\u0142opolskie",
    "qs_pg:photos_9r":0,
    "qs_pg:photos_sr":0,
    "qs_pg:pop_sr":2,
    "qs_pg:qs_pg_placetype":"locality",
    "qs_pg:qs_pg_placetype_gp":"Town",
    "qs_pg:woe_adm0":23424923,
    "woe:adm0_id":23424923,
    "woe:name_adm0":"Polska",
    "woe:name_adm1":"Ma\u0142opolskie",
    "woe:placetype":"Town",
    "wof:name":"\u0141\u0119ki",
    "wof:placetype":"locality",
    "wof:population":966
},
  "geometry": {"coordinates":[20.01657,49.83538],"type":"Point"}
}