{
  "type": "Feature",
  "properties": {
    "gn:admin1_code":"81.0",
    "gn:admin2_code":"2008.0",
    "gn:admin3_code":"200806.0",
    "gn:asciiname":"Konopczyn",
    "gn:country_code":"PL",
    "gn:dem":141,
    "gn:feature_class":"P",
    "gn:feature_code":"PPL",
    "gn:name":"Konopczyn",
    "gn:population":0,
    "gn:timezone":"Europe/Warsaw",
    "iso:country":"PL",
    "name:azb_x_preferred":[
        "\u06a9\u0648\u0646\u0648\u067e\u0686\u0646"
    ],
    "name:fas_x_preferred":[
        "\u06a9\u0648\u0646\u0648\u067e\u0686\u0646"
    ],
    "name:fra_x_preferred":[
        "Konopczyn"
    ],
    "name:lit_x_preferred":[
        "Konop\u010dinas"
    ],
    "name:pol_x_preferred":[
        "Konopczyn"
    ],
    "name:ukr_x_preferred":[
        "\u041a\u043e\u043d\u043e\u043f\u0447\u0438\u043d"
    ],
    "wof:name":"Konopczyn",
    "wof:placetype":"locality"
},
  "geometry": {"coordinates":[22.8336,53.36846],"type":"Point"}
}