{
  "type": "Feature",
  "properties": {
    "gn:admin1_code":"78.0",
    "gn:admin2_code":"1403.0",
    "gn:admin3_code":"140305.0",
    "gn:asciiname":"Unin",
    "gn:country_code":"PL",
    "gn:dem":151,
    "gn:feature_class":"P",
    "gn:feature_code":"PPL",
    "gn:name":"Unin",
    "gn:population":0,
    "gn:timezone":"Europe/Warsaw",
    "iso:country":"PL",
    "wof:name":"Unin",
    "wof:placetype":"locality"
},
  "geometry": {"coordinates":[21.69675,51.90792],"type":"Point"}
}