{
  "type": "Feature",
  "properties": {
    "gn:admin1_code":"78.0",
    "gn:admin2_code":"1406.0",
    "gn:admin3_code":"140607.0",
    "gn:asciiname":"Kaplin",
    "gn:country_code":"PL",
    "gn:dem":136,
    "gn:feature_class":"P",
    "gn:feature_code":"PPL",
    "gn:name":"Kaplin",
    "gn:population":0,
    "gn:timezone":"Europe/Warsaw",
    "iso:country":"PL",
    "name:ceb_x_preferred":[
        "Kaplin"
    ],
    "name:fra_x_preferred":[
        "Kaplin"
    ],
    "name:pol_x_preferred":[
        "Kaplin"
    ],
    "name:ukr_x_preferred":[
        "\u041a\u0430\u043f\u043b\u0456\u043d"
    ],
    "wof:name":"Kaplin",
    "wof:placetype":"locality"
},
  "geometry": {"coordinates":[20.74194,51.69133],"type":"Point"}
}