{
  "type": "Feature",
  "properties": {
    "gn:gn_country":"PL",
    "gn:gn_fcode":"PPLA3",
    "gn:gn_pop":0,
    "iso:country":"PL",
    "name:bul_x_preferred":[
        "\u041b\u0430\u0437\u0438"
    ],
    "name:deu_x_preferred":[
        "\u0141azy"
    ],
    "name:epo_x_preferred":[
        "\u0141azy"
    ],
    "name:fra_x_preferred":[
        "\u0141azy"
    ],
    "name:heb_x_preferred":[
        "\u05dc\u05d0\u05d6\u05d9"
    ],
    "name:jav_x_preferred":[
        "\u0141azy"
    ],
    "name:jpn_x_preferred":[
        "\u30ef\u30b8"
    ],
    "name:lav_x_preferred":[
        "Lazi"
    ],
    "name:msa_x_preferred":[
        "\u0141azy"
    ],
    "name:nld_x_preferred":[
        "\u0141azy"
    ],
    "name:pol_x_preferred":[
        "\u0141azy"
    ],
    "name:por_x_preferred":[
        "\u0141azy"
    ],
    "name:ron_x_preferred":[
        "\u0141azy"
    ],
    "name:rus_x_preferred":[
        "\u041b\u0430\u0437\u044b"
    ],
    "name:slk_x_preferred":[
        "\u0141azy"
    ],
    "name:srp_x_preferred":[
        "\u041b\u0430\u0437\u0438"
    ],
    "name:tha_x_preferred":[
        "\u0e27\u0e32\u0e0b\u0e37\u0e2d"
    ],
    "name:ukr_x_preferred":[
        "\u041b\u0430\u0437\u0438"
    ],
    "name:vie_x_preferred":[
        "\u0141azy"
    ],
    "name:zho_x_preferred":[
        "\u74e6\u6fdf"
    ],
    "qs_pg:aaroncc":"PL",
    "qs_pg:gn_country":"PL",
    "qs_pg:gn_fcode":"PPLA3",
    "qs_pg:gn_pop":0,
    "qs_pg:name":"\u0141azy",
    "qs_pg:name_adm0":"Polska",
    "qs_pg:name_adm1":"Sl\u0105skie",
    "qs_pg:photos":184,
    "qs_pg:photos_1k":37,
    "qs_pg:photos_9k":1,
    "qs_pg:photos_9r":4,
    "qs_pg:photos_all":184,
    "qs_pg:photos_sr":4,
    "qs_pg:pop_sr":0,
    "qs_pg:qs_pg_placetype":"localadmin",
    "qs_pg:qs_pg_placetype_gp":"LocalAdmin",
    "qs_pg:woe_adm0":23424923,
    "woe:adm0_id":23424923,
    "woe:name_adm0":"Polska",
    "woe:name_adm1":"Sl\u0105skie",
    "woe:placetype":"LocalAdmin",
    "wof:name":"\u0141azy",
    "wof:placetype":"localadmin"
},
  "geometry": {"coordinates":[19.41667,50.35],"type":"Point"}
}