{
  "type": "Feature",
  "properties": {
    "gn:admin1_code":"86.0",
    "gn:admin2_code":"3009.0",
    "gn:admin3_code":"300908.0",
    "gn:asciiname":"Leka",
    "gn:country_code":"PL",
    "gn:dem":93,
    "gn:feature_class":"P",
    "gn:feature_code":"PPL",
    "gn:name":"\u0141\u0119ka",
    "gn:population":0,
    "gn:timezone":"Europe/Warsaw",
    "iso:country":"PL",
    "name:und_x_variant":[
        "\u0141\u0119ka"
    ],
    "wof:name":"Leka",
    "wof:placetype":"locality"
},
  "geometry": {"coordinates":[18.63133,52.12547],"type":"Point"}
}