{
  "type": "Feature",
  "properties": {
    "gn:admin1_code":"78.0",
    "gn:admin2_code":"1412.0",
    "gn:admin3_code":"141209.0",
    "gn:asciiname":"Garczyn Duzy",
    "gn:country_code":"PL",
    "gn:dem":214,
    "gn:feature_class":"P",
    "gn:feature_code":"PPL",
    "gn:name":"Garczyn Du\u017cy",
    "gn:population":0,
    "gn:timezone":"Europe/Warsaw",
    "iso:country":"PL",
    "name:azb_x_preferred":[
        "\u0642\u0627\u0631\u0686\u0646 \u062f\u0648\u0698\u0647"
    ],
    "name:fas_x_preferred":[
        "\u06af\u0627\u0631\u0686\u0646 \u062f\u0648\u0698\u0647"
    ],
    "name:fra_x_preferred":[
        "Garczyn Du\u017cy"
    ],
    "name:nld_x_preferred":[
        "Garczyn Du\u017cy"
    ],
    "name:pol_x_preferred":[
        "Garczyn Du\u017cy"
    ],
    "name:spa_x_preferred":[
        "Garczyn Du\u017cy"
    ],
    "name:ukr_x_preferred":[
        "\u0490\u0430\u0440\u0447\u0438\u043d-\u0414\u0443\u0436\u0438"
    ],
    "name:und_x_variant":[
        "Garczyn"
    ],
    "wof:name":"Garczyn Duzy",
    "wof:placetype":"locality"
},
  "geometry": {"coordinates":[21.77879,52.27164000000001],"type":"Point"}
}