{
  "type": "Feature",
  "properties": {
    "gn:admin1_code":"78.0",
    "gn:admin2_code":"1412.0",
    "gn:admin3_code":"141209.0",
    "gn:asciiname":"Garczyn Duzy",
    "gn:country_code":"PL",
    "gn:dem":214,
    "gn:feature_class":"P",
    "gn:feature_code":"PPL",
    "gn:name":"Garczyn Du\u017cy",
    "gn:population":0,
    "gn:timezone":"Europe/Warsaw",
    "iso:country":"PL",
    "name:und_x_variant":[
        "Garczyn",
        "Garczyn Du\u017cy"
    ],
    "wof:name":"Garczyn Duzy",
    "wof:placetype":"locality"
},
  "geometry": {"coordinates":[21.77879,52.27164000000001],"type":"Point"}
}