{
  "type": "Feature",
  "properties": {
    "gn:admin1_code":"78.0",
    "gn:admin2_code":"1416.0",
    "gn:admin3_code":"141603.0",
    "gn:asciiname":"Tymianki Adamy",
    "gn:country_code":"PL",
    "gn:dem":118,
    "gn:feature_class":"P",
    "gn:feature_code":"PPL",
    "gn:name":"Tymianki Adamy",
    "gn:population":0,
    "gn:timezone":"Europe/Warsaw",
    "iso:country":"PL",
    "wof:name":"Tymianki Adamy",
    "wof:placetype":"locality"
},
  "geometry": {"coordinates":[22.43837000000001,52.6768],"type":"Point"}
}