{
  "type": "Feature",
  "properties": {
    "gn:admin1_code":"77.0",
    "gn:admin2_code":"1208.0",
    "gn:admin3_code":"120804.0",
    "gn:asciiname":"Czestoszowice",
    "gn:country_code":"PL",
    "gn:dem":247,
    "gn:feature_class":"P",
    "gn:feature_code":"PPL",
    "gn:name":"Cz\u0119stoszowice",
    "gn:population":0,
    "gn:timezone":"Europe/Warsaw",
    "iso:country":"PL",
    "name:azb_x_preferred":[
        "\u0686\u0646\u0633\u062a\u0648\u0634\u0648\u0648\u06cc\u062a\u0633\u0647"
    ],
    "name:ceb_x_preferred":[
        "Cz\u0119stoszowice"
    ],
    "name:fas_x_preferred":[
        "\u0686\u0646\u0633\u062a\u0648\u0634\u0648\u0648\u06cc\u062a\u0633\u0647"
    ],
    "name:ita_x_preferred":[
        "Cz\u0119stoszowice"
    ],
    "name:nld_x_preferred":[
        "Cz\u0119stoszowice"
    ],
    "name:pol_x_preferred":[
        "Cz\u0119stoszowice"
    ],
    "name:rus_x_preferred":[
        "\u0427\u0435\u043d\u0441\u0442\u043e\u0448\u043e\u0432\u0438\u0446\u0435"
    ],
    "name:ukr_x_preferred":[
        "\u0427\u0435\u043d\u0441\u0442\u043e\u0448\u043e\u0432\u0456\u0446\u0435"
    ],
    "wof:name":"Czestoszowice",
    "wof:placetype":"locality"
},
  "geometry": {"coordinates":[20.15179,50.42919000000001],"type":"Point"}
}