{
  "type": "Feature",
  "properties": {
    "gn:admin1_code":"77.0",
    "gn:admin2_code":"1208.0",
    "gn:admin3_code":"120804.0",
    "gn:asciiname":"Czestoszowice",
    "gn:country_code":"PL",
    "gn:dem":247,
    "gn:feature_class":"P",
    "gn:feature_code":"PPL",
    "gn:name":"Cz\u0119stoszowice",
    "gn:population":0,
    "gn:timezone":"Europe/Warsaw",
    "iso:country":"PL",
    "name:und_x_variant":[
        "Cz\u0119stoszowice"
    ],
    "wof:name":"Czestoszowice",
    "wof:placetype":"locality"
},
  "geometry": {"coordinates":[20.15179,50.42919000000001],"type":"Point"}
}