{
  "type": "Feature",
  "properties": {
    "iso:country":"PL",
    "name:ceb_x_preferred":[
        "Kluki"
    ],
    "name:deu_x_preferred":[
        "Kluki"
    ],
    "name:fra_x_preferred":[
        "Kluki"
    ],
    "name:nld_x_preferred":[
        "Kluki"
    ],
    "name:pol_x_preferred":[
        "Kluki"
    ],
    "name:ukr_x_preferred":[
        "\u041a\u043b\u044e\u043a\u0456"
    ],
    "wof:coterminous":[
        1125317341
    ],
    "wof:name":"Kluki",
    "wof:placetype":"locality"
},
  "geometry": {"coordinates":[19.2352258306511,51.3415148046822],"type":"Point"}
}