{
  "type": "Feature",
  "properties": {
    "iso:country":"PL",
    "name:pol_x_preferred":[
        "Kluki"
    ],
    "wof:name":"Kluki",
    "wof:placetype":"locality"
},
  "geometry": {"coordinates":[19.2352258306511,51.3415148046822],"type":"Point"}
}