{
  "type": "Feature",
  "properties": {
    "gn:admin1_code":"83.0",
    "gn:admin2_code":"2417.0",
    "gn:admin3_code":"241704.0",
    "gn:asciiname":"Przyborow",
    "gn:country_code":"PL",
    "gn:dem":520,
    "gn:feature_class":"P",
    "gn:feature_code":"PPL",
    "gn:name":"Przybor\u00f3w",
    "gn:population":1793,
    "gn:timezone":"Europe/Warsaw",
    "iso:country":"PL",
    "name:deu_x_preferred":[
        "Przybor\u00f3w"
    ],
    "name:nld_x_preferred":[
        "Przybor\u00f3w"
    ],
    "name:pol_x_preferred":[
        "Przybor\u00f3w"
    ],
    "name:ukr_x_preferred":[
        "\u041f\u0448\u0438\u0431\u043e\u0440\u0443\u0432"
    ],
    "wof:name":"Przyborow",
    "wof:placetype":"locality",
    "wof:population":1793
},
  "geometry": {"coordinates":[19.38701,49.6215],"type":"Point"}
}