{
  "type": "Feature",
  "properties": {
    "gn:admin1_code":"77.0",
    "gn:admin2_code":"1208.0",
    "gn:admin3_code":"120804.0",
    "gn:asciiname":"Boczkowice",
    "gn:country_code":"PL",
    "gn:dem":257,
    "gn:feature_class":"P",
    "gn:feature_code":"PPL",
    "gn:name":"Boczkowice",
    "gn:population":0,
    "gn:timezone":"Europe/Warsaw",
    "iso:country":"PL",
    "wof:name":"Boczkowice",
    "wof:placetype":"locality"
},
  "geometry": {"coordinates":[20.20657000000001,50.42743],"type":"Point"}
}