{
  "type": "Feature",
  "properties": {
    "gn:admin1_code":"77.0",
    "gn:admin2_code":"1208.0",
    "gn:admin3_code":"120804.0",
    "gn:asciiname":"Boczkowice",
    "gn:country_code":"PL",
    "gn:dem":257,
    "gn:feature_class":"P",
    "gn:feature_code":"PPL",
    "gn:name":"Boczkowice",
    "gn:population":0,
    "gn:timezone":"Europe/Warsaw",
    "iso:country":"PL",
    "name:ceb_x_preferred":[
        "Boczkowice"
    ],
    "name:ita_x_preferred":[
        "Boczkowice"
    ],
    "name:pol_x_preferred":[
        "Boczkowice"
    ],
    "name:rus_x_preferred":[
        "\u0411\u043e\u0447\u043a\u043e\u0432\u0438\u0446\u0435"
    ],
    "name:ukr_x_preferred":[
        "\u0411\u043e\u0447\u043a\u043e\u0432\u0456\u0446\u0435"
    ],
    "wof:name":"Boczkowice",
    "wof:placetype":"locality"
},
  "geometry": {"coordinates":[20.20657000000001,50.42743],"type":"Point"}
}