{
  "type": "Feature",
  "properties": {
    "gn:country":"PL",
    "gn:fcode":"PPL",
    "gn:population":285,
    "iso:country":"PL",
    "name:ceb_x_preferred":[
        "Czernich\u00f3w"
    ],
    "name:deu_x_preferred":[
        "Czernich\u00f3w"
    ],
    "name:fra_x_preferred":[
        "Czernich\u00f3w"
    ],
    "name:ita_x_preferred":[
        "Czernich\u00f3w"
    ],
    "name:nld_x_preferred":[
        "Czernich\u00f3w"
    ],
    "name:pol_x_preferred":[
        "Czernich\u00f3w"
    ],
    "name:rus_x_preferred":[
        "\u0427\u0435\u0440\u043d\u0438\u0445\u0443\u0432"
    ],
    "name:ukr_x_preferred":[
        "\u0427\u0435\u0440\u043d\u0456\u0445\u0443\u0432"
    ],
    "qs_pg:aaroncc":"PL",
    "qs_pg:gn_country":"PL",
    "qs_pg:gn_fcode":"PPL",
    "qs_pg:gn_pop":285,
    "qs_pg:name":"Czernich\u00f3w",
    "qs_pg:name_adm0":"Polska",
    "qs_pg:name_adm1":"Ma\u0142opolskie",
    "qs_pg:photos_9r":0,
    "qs_pg:photos_sr":0,
    "qs_pg:pop_sr":2,
    "qs_pg:qs_pg_placetype":"locality",
    "qs_pg:qs_pg_placetype_gp":"Town",
    "qs_pg:woe_adm0":23424923,
    "woe:adm0_id":23424923,
    "woe:name_adm0":"Polska",
    "woe:name_adm1":"Ma\u0142opolskie",
    "woe:placetype":"Town",
    "wof:name":"Czernich\u00f3w",
    "wof:placetype":"locality",
    "wof:population":285
},
  "geometry": {"coordinates":[20.22403,50.11871],"type":"Point"}
}