{
  "type": "Feature",
  "properties": {
    "gn:admin1_code":"75.0",
    "gn:admin2_code":"603.0",
    "gn:admin3_code":"60307.0",
    "gn:asciiname":"Rakolupy",
    "gn:country_code":"PL",
    "gn:dem":205,
    "gn:feature_class":"P",
    "gn:feature_code":"PPL",
    "gn:name":"Rako\u0142upy",
    "gn:population":0,
    "gn:timezone":"Europe/Warsaw",
    "iso:country":"PL",
    "name:fra_x_preferred":[
        "Rako\u0142upy"
    ],
    "name:pol_x_preferred":[
        "Rako\u0142upy"
    ],
    "name:ukr_x_preferred":[
        "\u0420\u0430\u043a\u043e\u043b\u0443\u043f\u0438"
    ],
    "wof:name":"Rakolupy",
    "wof:placetype":"locality"
},
  "geometry": {"coordinates":[23.44654,50.97291],"type":"Point"}
}