{
  "type": "Feature",
  "properties": {
    "gn:admin1_code":"81.0",
    "gn:admin2_code":"2013.0",
    "gn:admin3_code":"201305.0",
    "gn:asciiname":"Garbowo Stare",
    "gn:country_code":"PL",
    "gn:dem":121,
    "gn:feature_class":"P",
    "gn:feature_code":"PPL",
    "gn:name":"Garbowo Stare",
    "gn:population":0,
    "gn:timezone":"Europe/Warsaw",
    "iso:country":"PL",
    "wof:name":"Garbowo Stare",
    "wof:placetype":"locality"
},
  "geometry": {"coordinates":[22.64127,53.06866],"type":"Point"}
}