{
  "type": "Feature",
  "properties": {
    "gn:admin1_code":"84.0",
    "gn:admin2_code":"2612.0",
    "gn:admin3_code":"261201.0",
    "gn:asciiname":"Szczeglice",
    "gn:country_code":"PL",
    "gn:dem":286,
    "gn:feature_class":"P",
    "gn:feature_code":"PPL",
    "gn:name":"Szczeglice",
    "gn:population":0,
    "gn:timezone":"Europe/Warsaw",
    "iso:country":"PL",
    "name:pol_x_preferred":[
        "Szczeglice"
    ],
    "name:ukr_x_preferred":[
        "\u0429\u0435\u0491\u043b\u0456\u0446\u0435"
    ],
    "wof:name":"Szczeglice",
    "wof:placetype":"locality"
},
  "geometry": {"coordinates":[21.31588,50.67568],"type":"Point"}
}