{
  "type": "Feature",
  "properties": {
    "gn:admin1_code":"86.0",
    "gn:admin2_code":"3007.0",
    "gn:admin3_code":"300710.0",
    "gn:asciiname":"Borek Ksiezy",
    "gn:country_code":"PL",
    "gn:dem":126,
    "gn:feature_class":"P",
    "gn:feature_code":"PPL",
    "gn:name":"Borek Ksi\u0119\u017cy",
    "gn:population":0,
    "gn:timezone":"Europe/Warsaw",
    "iso:country":"PL",
    "wof:name":"Borek Ksiezy",
    "wof:placetype":"locality"
},
  "geometry": {"coordinates":[18.29199,51.67233],"type":"Point"}
}