{
  "type": "Feature",
  "properties": {
    "gn:admin1_code":"86.0",
    "gn:admin2_code":"3019.0",
    "gn:admin3_code":"301906.0",
    "gn:asciiname":"Nowa Lubianka",
    "gn:country_code":"PL",
    "gn:dem":124,
    "gn:feature_class":"P",
    "gn:feature_code":"PPL",
    "gn:name":"Nowa \u0141ubianka",
    "gn:population":0,
    "gn:timezone":"Europe/Warsaw",
    "iso:country":"PL",
    "wof:name":"Nowa Lubianka",
    "wof:placetype":"locality"
},
  "geometry": {"coordinates":[16.64214,53.24026],"type":"Point"}
}