{
  "type": "Feature",
  "properties": {
    "gn:admin1_code":"74.0",
    "gn:admin2_code":"1012.0",
    "gn:admin3_code":"101212.0",
    "gn:asciiname":"Dziepulc",
    "gn:country_code":"PL",
    "gn:dem":258,
    "gn:feature_class":"P",
    "gn:feature_code":"PPL",
    "gn:name":"Dziepu\u0142\u0107",
    "gn:population":0,
    "gn:timezone":"Europe/Warsaw",
    "iso:country":"PL",
    "name:fra_x_preferred":[
        "Dziep\u00f3\u0142\u0107"
    ],
    "name:pol_x_preferred":[
        "Dziep\u00f3\u0142\u0107"
    ],
    "name:ukr_x_preferred":[
        "\u0414\u0437\u0435\u043f\u0443\u043b\u0446\u044c"
    ],
    "name:und_x_variant":[
        "Dziepu\u0142\u0107"
    ],
    "wof:name":"Dziepulc",
    "wof:placetype":"neighbourhood"
},
  "geometry": {"coordinates":[19.52867,51.05786],"type":"Point"}
}