{
  "type": "Feature",
  "properties": {
    "gn:admin1_code":"72.0",
    "gn:admin2_code":"216.0",
    "gn:admin3_code":"21604.0",
    "gn:asciiname":"Guzice",
    "gn:country_code":"PL",
    "gn:dem":126,
    "gn:feature_class":"P",
    "gn:feature_code":"PPL",
    "gn:name":"Guzice",
    "gn:population":0,
    "gn:timezone":"Europe/Warsaw",
    "iso:country":"PL",
    "name:pol_x_preferred":[
        "Guzice"
    ],
    "name:ukr_x_preferred":[
        "\u0490\u0443\u0437\u0456\u0446\u0435"
    ],
    "wof:name":"Guzice",
    "wof:placetype":"locality"
},
  "geometry": {"coordinates":[16.10321,51.53205],"type":"Point"}
}