{
  "type": "Feature",
  "properties": {
    "gn:admin1_code":"87.0",
    "gn:admin2_code":"3209.0",
    "gn:admin3_code":"320907.0",
    "gn:asciiname":"Sucha Koszalinska",
    "gn:country_code":"PL",
    "gn:dem":19,
    "gn:feature_class":"P",
    "gn:feature_code":"PPL",
    "gn:name":"Sucha Koszali\u0144ska",
    "gn:population":0,
    "gn:timezone":"Europe/Warsaw",
    "iso:country":"PL",
    "name:deu_x_preferred":[
        "Sucha Koszali\u0144ska"
    ],
    "name:pol_x_preferred":[
        "Sucha Koszali\u0144ska"
    ],
    "name:ukr_x_preferred":[
        "\u0421\u0443\u0445\u0430-\u041a\u043e\u0448\u0430\u043b\u0456\u043d\u0441\u044c\u043a\u0430"
    ],
    "name:vie_x_preferred":[
        "Sucha Koszali\u0144ska"
    ],
    "wof:name":"Sucha Koszalinska",
    "wof:placetype":"locality"
},
  "geometry": {"coordinates":[16.26711,54.25999],"type":"Point"}
}