{
  "type": "Feature",
  "properties": {
    "gn:admin1_code":"78.0",
    "gn:admin2_code":"1419.0",
    "gn:admin3_code":"141913.0",
    "gn:asciiname":"Bronowo Kmiecie",
    "gn:country_code":"PL",
    "gn:dem":115,
    "gn:feature_class":"P",
    "gn:feature_code":"PPL",
    "gn:name":"Bronowo Kmiecie",
    "gn:population":0,
    "gn:timezone":"Europe/Warsaw",
    "iso:country":"PL",
    "name:und_x_variant":[
        "Bronowo",
        "Bronowo Kmiecie"
    ],
    "wof:name":"Bronowo Kmiecie",
    "wof:placetype":"locality"
},
  "geometry": {"coordinates":[19.70891,52.61903],"type":"Point"}
}