{
  "type": "Feature",
  "properties": {
    "gn:admin1_code":"74.0",
    "gn:admin2_code":"1009.0",
    "gn:admin3_code":"100907.0",
    "gn:asciiname":"Wola Jajkowska",
    "gn:country_code":"PL",
    "gn:dem":222,
    "gn:feature_class":"P",
    "gn:feature_code":"PPL",
    "gn:name":"Wola Jajkowska",
    "gn:population":0,
    "gn:timezone":"Europe/Warsaw",
    "iso:country":"PL",
    "wof:name":"Wola Jajkowska",
    "wof:placetype":"locality"
},
  "geometry": {"coordinates":[19.09676,51.10746],"type":"Point"}
}