{
  "type": "Feature",
  "properties": {
    "gn:admin1_code":"85.0",
    "gn:admin2_code":"2806.0",
    "gn:admin3_code":"280610.0",
    "gn:asciiname":"Siemionki",
    "gn:country_code":"PL",
    "gn:dem":154,
    "gn:feature_class":"P",
    "gn:feature_code":"PPL",
    "gn:name":"Siemionki",
    "gn:population":0,
    "gn:timezone":"Europe/Warsaw",
    "iso:country":"PL",
    "name:deu_x_preferred":[
        "Siemionki"
    ],
    "name:fra_x_preferred":[
        "Siemionki"
    ],
    "name:pol_x_preferred":[
        "Siemionki"
    ],
    "name:ukr_x_preferred":[
        "\u0421\u0435\u043c\u0439\u043e\u043d\u043a\u0456"
    ],
    "name:und_x_variant":[
        "Bergwalde",
        "Siemonki",
        "Schemionken"
    ],
    "wof:name":"Siemionki",
    "wof:placetype":"locality"
},
  "geometry": {"coordinates":[22.01277,53.95189],"type":"Point"}
}