{
  "type": "Feature",
  "properties": {
    "gn:admin1_code":"73.0",
    "gn:admin2_code":"463.0",
    "gn:admin3_code":"46301.0",
    "gn:asciiname":"Chelminskie Przedmiescie",
    "gn:country_code":"PL",
    "gn:dem":59,
    "gn:feature_class":"P",
    "gn:feature_code":"PPL",
    "gn:name":"Che\u0142mi\u0144skie Przedmie\u015bcie",
    "gn:population":0,
    "gn:timezone":"Europe/Warsaw",
    "iso:country":"PL",
    "wof:name":"Chelminskie Przedmiescie",
    "wof:placetype":"locality"
},
  "geometry": {"coordinates":[18.59264,53.02161],"type":"Point"}
}