{
  "type": "Feature",
  "properties": {
    "gn:country":"PL",
    "gn:fcode":"PPL",
    "gn:population":117,
    "iso:country":"PL",
    "name:ast_x_preferred":[
        "Ob\u00f3rki"
    ],
    "name:ceb_x_preferred":[
        "Ob\u00f3rki"
    ],
    "name:eng_x_preferred":[
        "Ob\u00f3rki"
    ],
    "name:fra_x_preferred":[
        "Ob\u00f3rki"
    ],
    "name:pol_x_preferred":[
        "Ob\u00f3rki"
    ],
    "name:ukr_x_preferred":[
        "\u041e\u0431\u0443\u0440\u043a\u0456"
    ],
    "qs_pg:aaroncc":"PL",
    "qs_pg:gn_country":"PL",
    "qs_pg:gn_fcode":"PPL",
    "qs_pg:gn_pop":117,
    "qs_pg:name":"Ob\u00f3rki",
    "qs_pg:name_adm0":"Polska",
    "qs_pg:name_adm1":"Mazowieckie",
    "qs_pg:photos_9k":1,
    "qs_pg:photos_9r":1,
    "qs_pg:photos_all":21,
    "qs_pg:photos_sr":0,
    "qs_pg:pop_sr":1,
    "qs_pg:qs_pg_placetype":"locality",
    "qs_pg:qs_pg_placetype_gp":"Town",
    "qs_pg:woe_adm0":23424923,
    "woe:adm0_id":23424923,
    "woe:name_adm0":"Polska",
    "woe:name_adm1":"Mazowieckie",
    "woe:placetype":"Town",
    "wof:name":"Ob\u00f3rki",
    "wof:placetype":"locality",
    "wof:population":117
},
  "geometry": {"coordinates":[21.16559,52.12132],"type":"Point"}
}