{
  "type": "Feature",
  "properties": {
    "gn:admin1_code":"74.0",
    "gn:admin2_code":"1001.0",
    "gn:admin3_code":"100108.0",
    "gn:asciiname":"Pszczolki",
    "gn:country_code":"PL",
    "gn:dem":173,
    "gn:feature_class":"P",
    "gn:feature_code":"PPL",
    "gn:name":"Pszcz\u00f3\u0142ki",
    "gn:population":0,
    "gn:timezone":"Europe/Warsaw",
    "iso:country":"PL",
    "name:fra_x_preferred":[
        "Pszcz\u00f3\u0142ki"
    ],
    "name:pol_x_preferred":[
        "Pszcz\u00f3\u0142ki"
    ],
    "name:ukr_x_preferred":[
        "\u041f\u0449\u0443\u043b\u043a\u0456"
    ],
    "wof:name":"Pszczolki",
    "wof:placetype":"locality"
},
  "geometry": {"coordinates":[19.10677,51.42362],"type":"Point"}
}