{
  "type": "Feature",
  "properties": {
    "gn:admin1_code":"81.0",
    "gn:admin2_code":"2013.0",
    "gn:admin3_code":"201302.0",
    "gn:asciiname":"Czaje Wolka",
    "gn:country_code":"PL",
    "gn:dem":146,
    "gn:feature_class":"P",
    "gn:feature_code":"PPL",
    "gn:name":"Czaje W\u00f3lka",
    "gn:population":0,
    "gn:timezone":"Europe/Warsaw",
    "iso:country":"PL",
    "name:azb_x_preferred":[
        "\u0686\u0627\u06cc-\u0648\u0648\u0644\u06a9\u0627"
    ],
    "name:fas_x_preferred":[
        "\u0686\u0627\u06cc-\u0648\u0648\u0644\u06a9\u0627"
    ],
    "name:fra_x_preferred":[
        "Czaje-W\u00f3lka"
    ],
    "name:lit_x_preferred":[
        "\u010caje Vulka"
    ],
    "name:pol_x_preferred":[
        "Czaje-W\u00f3lka"
    ],
    "name:ukr_x_preferred":[
        "\u0427\u0430\u0454-\u0412\u0443\u043b\u044c\u043a\u0430"
    ],
    "name:und_x_variant":[
        "Czaje W\u00f3lka"
    ],
    "wof:name":"Czaje Wolka",
    "wof:placetype":"locality"
},
  "geometry": {"coordinates":[22.71032,52.67409],"type":"Point"}
}