{
  "type": "Feature",
  "properties": {
    "gn:admin1_code":"78.0",
    "gn:admin2_code":"1412.0",
    "gn:admin3_code":"141206.0",
    "gn:asciiname":"Rakowiec",
    "gn:cc2":"PL",
    "gn:country_code":"PL",
    "gn:dem":149,
    "gn:feature_class":"P",
    "gn:feature_code":"PPL",
    "gn:name":"Rakowiec",
    "gn:population":0,
    "gn:timezone":"Europe/Warsaw",
    "iso:country":"PL",
    "name:fra_x_preferred":[
        "Rak\u00f3wiec"
    ],
    "name:pol_x_preferred":[
        "Rak\u00f3wiec"
    ],
    "name:ukr_x_preferred":[
        "\u0420\u0430\u043a\u0443\u0432\u0435\u0446\u044c"
    ],
    "name:und_x_variant":[
        "Rakowiec Stary"
    ],
    "wof:name":"Rakowiec",
    "wof:placetype":"locality"
},
  "geometry": {"coordinates":[21.62551,52.29677],"type":"Point"}
}