{
  "type": "Feature",
  "properties": {
    "gn:admin1_code":"76.0",
    "gn:admin2_code":"809.0",
    "gn:admin3_code":"80905.0",
    "gn:asciiname":"Przybymierz",
    "gn:country_code":"PL",
    "gn:dem":106,
    "gn:feature_class":"P",
    "gn:feature_code":"PPL",
    "gn:name":"Przybymierz",
    "gn:population":0,
    "gn:timezone":"Europe/Warsaw",
    "iso:country":"PL",
    "name:ceb_x_preferred":[
        "Przybymierz"
    ],
    "name:fra_x_preferred":[
        "Przybymierz"
    ],
    "name:pol_x_preferred":[
        "Przybymierz"
    ],
    "name:ukr_x_preferred":[
        "\u041f\u0448\u0438\u0431\u0438\u043c\u0435\u0436"
    ],
    "wof:name":"Przybymierz",
    "wof:placetype":"locality"
},
  "geometry": {"coordinates":[15.35601,51.75371],"type":"Point"}
}