{
  "type": "Feature",
  "properties": {
    "gn:admin1_code":"87.0",
    "gn:admin2_code":"3217.0",
    "gn:admin3_code":"321704.0",
    "gn:asciiname":"Jamienko",
    "gn:country_code":"PL",
    "gn:dem":129,
    "gn:feature_class":"P",
    "gn:feature_code":"PPL",
    "gn:name":"Jamienko",
    "gn:population":0,
    "gn:timezone":"Europe/Warsaw",
    "iso:country":"PL",
    "name:azb_x_preferred":[
        "\u06cc\u0627\u0645\u06cc\u0646\u06a9\u0648"
    ],
    "name:ceb_x_preferred":[
        "Jamienko"
    ],
    "name:fas_x_preferred":[
        "\u06cc\u0627\u0645\u06cc\u0646\u06a9\u0648"
    ],
    "name:fra_x_preferred":[
        "Jamienko"
    ],
    "name:pol_x_preferred":[
        "Jamienko"
    ],
    "name:ukr_x_preferred":[
        "\u042f\u043c\u0435\u043d\u043a\u043e"
    ],
    "name:urd_x_preferred":[
        "\u062c\u0645\u06cc\u0646\u06a9\u0648"
    ],
    "name:vie_x_preferred":[
        "Jamienko"
    ],
    "wof:name":"Jamienko",
    "wof:placetype":"locality"
},
  "geometry": {"coordinates":[16.2041,53.28442],"type":"Point"}
}