{
  "type": "Feature",
  "properties": {
    "gn:admin1_code":"78.0",
    "gn:admin2_code":"1420.0",
    "gn:admin3_code":"142010.0",
    "gn:asciiname":"Kraszewo Gaczulty",
    "gn:country_code":"PL",
    "gn:dem":108,
    "gn:feature_class":"P",
    "gn:feature_code":"PPL",
    "gn:name":"Kraszewo Gaczu\u0142ty",
    "gn:population":0,
    "gn:timezone":"Europe/Warsaw",
    "iso:country":"PL",
    "wof:name":"Kraszewo Gaczulty",
    "wof:placetype":"locality"
},
  "geometry": {"coordinates":[20.06157,52.79207],"type":"Point"}
}