{
  "type": "Feature",
  "properties": {
    "gn:admin1_code":"86.0",
    "gn:admin2_code":"3009.0",
    "gn:admin3_code":"300902.0",
    "gn:asciiname":"Debno Krolewskie",
    "gn:country_code":"PL",
    "gn:dem":120,
    "gn:feature_class":"P",
    "gn:feature_code":"PPL",
    "gn:name":"D\u0119bno Kr\u00f3lewskie",
    "gn:population":0,
    "gn:timezone":"Europe/Warsaw",
    "iso:country":"PL",
    "name:und_x_variant":[
        "D\u0119bno Kr\u00f3lewskie"
    ],
    "wof:name":"Debno Krolewskie",
    "wof:placetype":"locality"
},
  "geometry": {"coordinates":[18.67372,52.30408],"type":"Point"}
}