{
  "type": "Feature",
  "properties": {
    "gn:admin1_code":"76",
    "gn:admin2_code":"0808",
    "gn:admin3_code":"80805.0",
    "gn:asciiname":"Wityn",
    "gn:country_code":"PL",
    "gn:dem":85,
    "gn:feature_class":"P",
    "gn:feature_code":"PPL",
    "gn:name":"Wity\u0144",
    "gn:population":0,
    "gn:timezone":"Europe/Warsaw",
    "iso:country":"PL",
    "name:deu_x_historical":[
        "Witten"
    ],
    "name:deu_x_preferred":[
        "Witten"
    ],
    "name:fra_x_preferred":[
        "Wity\u0144"
    ],
    "name:pol_x_preferred":[
        "Wity\u0144"
    ],
    "wof:name":"Wityn",
    "wof:placetype":"locality"
},
  "geometry": {"coordinates":[15.6084,52.2706],"type":"Point"}
}