{
  "type": "Feature",
  "properties": {
    "gn:admin1_code":"84.0",
    "gn:admin2_code":"2606.0",
    "gn:admin3_code":"260602.0",
    "gn:asciiname":"Wygielzow",
    "gn:country_code":"PL",
    "gn:dem":312,
    "gn:feature_class":"P",
    "gn:feature_code":"PPL",
    "gn:name":"Wygie\u0142z\u00f3w",
    "gn:population":0,
    "gn:timezone":"Europe/Warsaw",
    "iso:country":"PL",
    "name:ceb_x_preferred":[
        "Wygie\u0142z\u00f3w"
    ],
    "name:pol_x_preferred":[
        "Wygie\u0142z\u00f3w"
    ],
    "name:ukr_x_preferred":[
        "\u0412\u0438\u0491\u0435\u043b\u0437\u0443\u0432"
    ],
    "wof:name":"Wygielzow",
    "wof:placetype":"locality"
},
  "geometry": {"coordinates":[21.24344,50.69831],"type":"Point"}
}