{
  "type": "Feature",
  "properties": {
    "gn:admin1_code":"78.0",
    "gn:admin2_code":"1413.0",
    "gn:admin3_code":"141309.0",
    "gn:asciiname":"Kulany",
    "gn:country_code":"PL",
    "gn:dem":161,
    "gn:feature_class":"P",
    "gn:feature_code":"PPL",
    "gn:name":"Kulany",
    "gn:population":0,
    "gn:timezone":"Europe/Warsaw",
    "iso:country":"PL",
    "name:ceb_x_preferred":[
        "Kulany"
    ],
    "name:fra_x_preferred":[
        "Kulany"
    ],
    "name:pol_x_preferred":[
        "Kulany"
    ],
    "name:ukr_x_preferred":[
        "\u041a\u0443\u043b\u044f\u043d\u0438"
    ],
    "wof:name":"Kulany",
    "wof:placetype":"locality"
},
  "geometry": {"coordinates":[20.45963,53.20747],"type":"Point"}
}