{
  "type": "Feature",
  "properties": {
    "gn:admin1_code":"76.0",
    "gn:admin2_code":"802.0",
    "gn:admin3_code":"80205.0",
    "gn:asciiname":"Zytowan",
    "gn:country_code":"PL",
    "gn:dem":42,
    "gn:feature_class":"P",
    "gn:feature_code":"PPL",
    "gn:name":"\u017bytowa\u0144",
    "gn:population":0,
    "gn:timezone":"Europe/Warsaw",
    "iso:country":"PL",
    "name:ceb_x_preferred":[
        "\u017bytowa\u0144"
    ],
    "name:deu_x_preferred":[
        "\u017bytowa\u0144"
    ],
    "name:fra_x_preferred":[
        "\u017bytowa\u0144"
    ],
    "name:pol_x_preferred":[
        "\u017bytowa\u0144"
    ],
    "name:ukr_x_preferred":[
        "\u0416\u0438\u0442\u043e\u0432\u0430\u043d\u044c"
    ],
    "wof:name":"Zytowan",
    "wof:placetype":"locality"
},
  "geometry": {"coordinates":[14.75005,52.01762],"type":"Point"}
}