{
  "type": "Feature",
  "properties": {
    "gn:admin1_code":"73.0",
    "gn:admin2_code":"419.0",
    "gn:admin3_code":"41901.0",
    "gn:asciiname":"Szeroki Kamien",
    "gn:country_code":"PL",
    "gn:dem":105,
    "gn:feature_class":"P",
    "gn:feature_code":"PPL",
    "gn:name":"Szeroki Kamie\u0144",
    "gn:population":0,
    "gn:timezone":"Europe/Warsaw",
    "iso:country":"PL",
    "name:und_x_variant":[
        "Szeroki Kamie\u0144"
    ],
    "wof:name":"Szeroki Kamien",
    "wof:placetype":"locality"
},
  "geometry": {"coordinates":[17.99696,52.79939],"type":"Point"}
}