{
  "type": "Feature",
  "properties": {
    "gn:admin1_code":"73.0",
    "gn:admin2_code":"419.0",
    "gn:admin3_code":"41901.0",
    "gn:asciiname":"Szeroki Kamien",
    "gn:country_code":"PL",
    "gn:dem":105,
    "gn:feature_class":"P",
    "gn:feature_code":"PPL",
    "gn:name":"Szeroki Kamie\u0144",
    "gn:population":0,
    "gn:timezone":"Europe/Warsaw",
    "iso:country":"PL",
    "name:pol_x_preferred":[
        "Szeroki Kamie\u0144"
    ],
    "name:ukr_x_preferred":[
        "\u0428\u0435\u0440\u043e\u043a\u0456-\u041a\u0430\u043c\u0435\u043d\u044c"
    ],
    "wof:name":"Szeroki Kamien",
    "wof:placetype":"locality"
},
  "geometry": {"coordinates":[17.99696,52.79939],"type":"Point"}
}