{
  "type": "Feature",
  "properties": {
    "gn:country":"PL",
    "gn:fcode":"PPL",
    "gn:population":0,
    "iso:country":"PL",
    "name:ast_x_preferred":[
        "Borowe"
    ],
    "name:deu_x_preferred":[
        "Borowe"
    ],
    "name:eng_x_preferred":[
        "Borowe"
    ],
    "name:fra_x_preferred":[
        "Borowe"
    ],
    "name:pol_x_preferred":[
        "Borowe"
    ],
    "name:ukr_x_preferred":[
        "\u0411\u043e\u0440\u043e\u0432\u0435"
    ],
    "name:und_x_variant":[
        "Prausken"
    ],
    "qs_pg:aaroncc":"PL",
    "qs_pg:gn_country":"PL",
    "qs_pg:gn_fcode":"PPL",
    "qs_pg:gn_pop":0,
    "qs_pg:name":"Bor\u00f3w",
    "qs_pg:name_adm0":"Polska",
    "qs_pg:name_adm1":"Mazowieckie",
    "qs_pg:photos_9r":0,
    "qs_pg:photos_sr":0,
    "qs_pg:pop_sr":0,
    "qs_pg:qs_pg_placetype":"locality",
    "qs_pg:qs_pg_placetype_gp":"Town",
    "qs_pg:woe_adm0":23424923,
    "woe:adm0_id":23424923,
    "woe:name_adm0":"Polska",
    "woe:name_adm1":"Mazowieckie",
    "woe:placetype":"Town",
    "wof:name":"Bor\u00f3w",
    "wof:placetype":"locality"
},
  "geometry": {"coordinates":[21.22218,53.77544],"type":"Point"}
}