{
  "type": "Feature",
  "properties": {
    "gn:admin1_code":"78.0",
    "gn:admin2_code":"1422.0",
    "gn:admin3_code":"142202.0",
    "gn:asciiname":"Kwiatkowo",
    "gn:country_code":"PL",
    "gn:dem":136,
    "gn:feature_class":"P",
    "gn:feature_code":"PPL",
    "gn:name":"Kwiatkowo",
    "gn:population":0,
    "gn:timezone":"Europe/Warsaw",
    "iso:country":"PL",
    "name:fra_x_preferred":[
        "Kwiatkowo"
    ],
    "name:pol_x_preferred":[
        "Kwiatkowo"
    ],
    "name:ukr_x_preferred":[
        "\u041a\u0432\u044f\u0442\u043a\u043e\u0432\u043e"
    ],
    "wof:name":"Kwiatkowo",
    "wof:placetype":"locality"
},
  "geometry": {"coordinates":[20.83333,53.23333],"type":"Point"}
}