{
  "type": "Feature",
  "properties": {
    "gn:gn_country":"PL",
    "gn:gn_fcode":"PPLA3",
    "gn:gn_pop":6821,
    "gn:population":6821,
    "iso:country":"PL",
    "name:ceb_x_preferred":[
        "Witnica"
    ],
    "name:csb_x_preferred":[
        "Wicno"
    ],
    "name:deu_x_preferred":[
        "Witnica"
    ],
    "name:epo_x_preferred":[
        "Witnica"
    ],
    "name:fra_x_preferred":[
        "Witnica"
    ],
    "name:jav_x_preferred":[
        "Witnica"
    ],
    "name:lav_x_preferred":[
        "Vit\u0146ica"
    ],
    "name:msa_x_preferred":[
        "Witnica"
    ],
    "name:nld_x_preferred":[
        "Witnica"
    ],
    "name:pol_x_preferred":[
        "Witnica"
    ],
    "name:por_x_preferred":[
        "Witnica"
    ],
    "name:ron_x_preferred":[
        "Witnica"
    ],
    "name:rus_x_preferred":[
        "\u0412\u0438\u0442\u043d\u0438\u0446\u0430"
    ],
    "name:slk_x_preferred":[
        "Witnica"
    ],
    "name:srp_x_preferred":[
        "\u0412\u0438\u0442\u045a\u0438\u0446\u0430"
    ],
    "name:swe_x_preferred":[
        "Witnica"
    ],
    "name:szl_x_preferred":[
        "Wit\u0144ica"
    ],
    "name:ukr_x_preferred":[
        "\u0412\u0456\u0442\u043d\u0438\u0446\u044f"
    ],
    "name:unk_x_variant":[
        "Vietz"
    ],
    "name:vie_x_preferred":[
        "Witnica"
    ],
    "name:zho_x_preferred":[
        "\u7dad\u7279\u5c3c\u5bdf"
    ],
    "qs_pg:aaroncc":"PL",
    "qs_pg:gn_country":"PL",
    "qs_pg:gn_fcode":"PPLA3",
    "qs_pg:gn_pop":6821,
    "qs_pg:name":"Witnica",
    "qs_pg:name_adm0":"Polska",
    "qs_pg:name_adm1":"Lubuskie",
    "qs_pg:photos":15,
    "qs_pg:photos_1k":3,
    "qs_pg:photos_9k":1,
    "qs_pg:photos_9r":1,
    "qs_pg:photos_all":15,
    "qs_pg:photos_sr":1,
    "qs_pg:pop_sr":5,
    "qs_pg:qs_pg_placetype":"localadmin",
    "qs_pg:qs_pg_placetype_gp":"LocalAdmin",
    "qs_pg:woe_adm0":23424923,
    "woe:adm0_id":23424923,
    "woe:name_adm0":"Polska",
    "woe:name_adm1":"Lubuskie",
    "woe:placetype":"LocalAdmin",
    "wof:name":"Witnica",
    "wof:placetype":"localadmin",
    "wof:population":6821
},
  "geometry": {"coordinates":[14.89765,52.67318],"type":"Point"}
}