{
  "type": "Feature",
  "properties": {
    "gn:admin1_code":"86.0",
    "gn:admin2_code":"3021.0",
    "gn:admin3_code":"302101.0",
    "gn:asciiname":"Bocianowo",
    "gn:country_code":"PL",
    "gn:dem":66,
    "gn:feature_class":"P",
    "gn:feature_code":"PPL",
    "gn:name":"Bocianowo",
    "gn:population":0,
    "gn:timezone":"Europe/Warsaw",
    "iso:country":"PL",
    "name:pol_x_preferred":[
        "Bocianowo"
    ],
    "wof:name":"Bocianowo",
    "wof:placetype":"neighbourhood"
},
  "geometry": {"coordinates":[16.88332999999999,52.35],"type":"Point"}
}