{
  "type": "Feature",
  "properties": {
    "gn:admin1_code":"82.0",
    "gn:admin2_code":"2206.0",
    "gn:admin3_code":"220607.0",
    "gn:asciiname":"Grabowko",
    "gn:country_code":"PL",
    "gn:dem":197,
    "gn:feature_class":"P",
    "gn:feature_code":"PPL",
    "gn:name":"Grab\u00f3wko",
    "gn:population":0,
    "gn:timezone":"Europe/Warsaw",
    "iso:country":"PL",
    "name:eng_x_preferred":[
        "Grab\u00f3wko"
    ],
    "name:rus_x_preferred":[
        "\u0413\u0440\u0430\u0431\u043e\u0432\u043e"
    ],
    "name:und_x_variant":[
        "Grab\u00f3wko"
    ],
    "wof:name":"Grabowko",
    "wof:placetype":"locality"
},
  "geometry": {"coordinates":[18.16714,54.14629],"type":"Point"}
}