{
  "type": "Feature",
  "properties": {
    "gn:admin1_code":"85.0",
    "gn:admin2_code":"2817.0",
    "gn:admin3_code":"281708.0",
    "gn:asciiname":"Zieleniec",
    "gn:cc2":"PL",
    "gn:country_code":"PL",
    "gn:dem":132,
    "gn:feature_class":"P",
    "gn:feature_code":"PPL",
    "gn:name":"Zieleniec",
    "gn:population":0,
    "gn:timezone":"Europe/Warsaw",
    "iso:country":"PL",
    "name:pol_x_preferred":[
        "Zieleniec"
    ],
    "name:szl_x_preferred":[
        "\u0179ely\u0144ec"
    ],
    "name:ukr_x_preferred":[
        "\u0417\u0435\u043b\u0435\u043d\u0435\u0446\u044c"
    ],
    "name:und_x_variant":[
        "Gross Radzienen",
        "Radzienen",
        "H\u00fcgelwalde",
        "Zieleniec"
    ],
    "wof:name":"Zieleniec",
    "wof:placetype":"locality"
},
  "geometry": {"coordinates":[21.11795,53.42406],"type":"Point"}
}