{
  "type": "Feature",
  "properties": {
    "gn:admin1_code":"86.0",
    "gn:admin2_code":"3010.0",
    "gn:admin3_code":"301009.0",
    "gn:asciiname":"Gawrony",
    "gn:country_code":"PL",
    "gn:dem":93,
    "gn:feature_class":"P",
    "gn:feature_code":"PPL",
    "gn:name":"Gawrony",
    "gn:population":0,
    "gn:timezone":"Europe/Warsaw",
    "iso:country":"PL",
    "name:pol_x_preferred":[
        "Gawrony"
    ],
    "name:ukr_x_preferred":[
        "\u0490\u0430\u0432\u0440\u043e\u043d\u0438"
    ],
    "wof:name":"Gawrony",
    "wof:placetype":"locality"
},
  "geometry": {"coordinates":[18.35078,52.42809000000001],"type":"Point"}
}