{
  "type": "Feature",
  "properties": {
    "iso:country":"PL",
    "name:pol_x_preferred":[
        "Kobia\u0142ka"
    ],
    "wof:name":"Kobialka",
    "wof:placetype":"neighbourhood"
},
  "geometry": {"coordinates":[21.0383517655856,52.35733417678014],"type":"Point"}
}