{
  "type": "Feature",
  "properties": {
    "gn:admin1_code":"83.0",
    "gn:admin2_code":"2407.0",
    "gn:admin3_code":"240707.0",
    "gn:asciiname":"Kosmidry",
    "gn:country_code":"PL",
    "gn:dem":228,
    "gn:feature_class":"P",
    "gn:feature_code":"PPL",
    "gn:name":"Ko\u015bmidry",
    "gn:population":0,
    "gn:timezone":"Europe/Warsaw",
    "iso:country":"PL",
    "name:pol_x_preferred":[
        "Ko\u015bmidry"
    ],
    "name:ukr_x_preferred":[
        "\u041a\u043e\u0441\u044c\u043c\u0456\u0434\u0440\u0438"
    ],
    "wof:name":"Kosmidry",
    "wof:placetype":"locality"
},
  "geometry": {"coordinates":[18.57101,50.66437],"type":"Point"}
}