{
  "type": "Feature",
  "properties": {
    "gn:admin1_code":"81.0",
    "gn:admin2_code":"2007.0",
    "gn:admin3_code":"200705.0",
    "gn:asciiname":"Jeziorko",
    "gn:country_code":"PL",
    "gn:dem":146,
    "gn:feature_class":"P",
    "gn:feature_code":"PPL",
    "gn:name":"Jeziorko",
    "gn:population":0,
    "gn:timezone":"Europe/Warsaw",
    "iso:country":"PL",
    "name:lit_x_preferred":[
        "Jeziorkas"
    ],
    "name:pol_x_preferred":[
        "Jeziorko"
    ],
    "name:ukr_x_preferred":[
        "\u0404\u0437\u044c\u043e\u0440\u043a\u043e"
    ],
    "wof:name":"Jeziorko",
    "wof:placetype":"locality"
},
  "geometry": {"coordinates":[22.1596,53.21796],"type":"Point"}
}