{
  "type": "Feature",
  "properties": {
    "gn:admin1_code":"78.0",
    "gn:admin2_code":"1428.0",
    "gn:admin3_code":"142802.0",
    "gn:asciiname":"Konary",
    "gn:country_code":"PL",
    "gn:dem":70,
    "gn:feature_class":"P",
    "gn:feature_code":"PPL",
    "gn:name":"Konary",
    "gn:population":0,
    "gn:timezone":"Europe/Warsaw",
    "iso:country":"PL",
    "name:pol_x_preferred":[
        "Konary"
    ],
    "name:ukr_x_preferred":[
        "\u041a\u043e\u043d\u0430\u0440\u0438"
    ],
    "wof:name":"Konary",
    "wof:placetype":"locality"
},
  "geometry": {"coordinates":[20.28143,52.29461],"type":"Point"}
}