{
  "type": "Feature",
  "properties": {
    "gn:admin1_code":"75.0",
    "gn:admin2_code":"611.0",
    "gn:admin3_code":"61103.0",
    "gn:asciiname":"Turzystwo A",
    "gn:country_code":"PL",
    "gn:dem":164,
    "gn:feature_class":"P",
    "gn:feature_code":"PPL",
    "gn:name":"Turzystwo A",
    "gn:population":0,
    "gn:timezone":"Europe/Warsaw",
    "iso:country":"PL",
    "wof:name":"Turzystwo A",
    "wof:placetype":"locality"
},
  "geometry": {"coordinates":[22.18307,51.70528],"type":"Point"}
}