{
  "type": "Feature",
  "properties": {
    "gn:admin1_code":"81.0",
    "gn:admin2_code":"2011.0",
    "gn:admin3_code":"201102.0",
    "gn:asciiname":"Nowa Wola",
    "gn:country_code":"PL",
    "gn:dem":182,
    "gn:feature_class":"P",
    "gn:feature_code":"PPL",
    "gn:name":"Nowa Wola",
    "gn:population":0,
    "gn:timezone":"Europe/Warsaw",
    "iso:country":"PL",
    "name:fra_x_preferred":[
        "Nowowola"
    ],
    "name:lit_x_preferred":[
        "Novovola"
    ],
    "name:pol_x_preferred":[
        "Nowowola"
    ],
    "name:ukr_x_preferred":[
        "\u041d\u043e\u0432\u043e\u0432\u043e\u043b\u044f"
    ],
    "name:und_x_variant":[
        "Nowa Wola"
    ],
    "wof:name":"Nowa Wola",
    "wof:placetype":"locality"
},
  "geometry": {"coordinates":[23.39799,53.47824],"type":"Point"}
}