{
  "type": "Feature",
  "properties": {
    "gn:gn_country":"PL",
    "gn:gn_fcode":"PPLA3",
    "gn:gn_pop":920,
    "gn:population":920,
    "iso:country":"PL",
    "name:eng_x_preferred":[
        "Gmina Chrzypsko Wielkie"
    ],
    "name:pol_x_preferred":[
        "Chrzypsko Wielkie"
    ],
    "name:por_x_preferred":[
        "Comuna de Chrzypsko Wielkie"
    ],
    "name:rus_x_preferred":[
        "\u0425\u0448\u0438\u043f\u0441\u043a\u043e-\u0412\u0435\u043b\u044c\u043a\u0435"
    ],
    "name:slk_x_preferred":[
        "Gmina Chrzypsko Wielkie"
    ],
    "name:ukr_x_preferred":[
        "\u0490\u043c\u0456\u043d\u0430 \u0425\u0436\u0438\u043f\u0441\u044c\u043a\u043e-\u0412\u0435\u043b\u044c\u043a\u0435"
    ],
    "name:war_x_preferred":[
        "Gmina Chrzypsko Wielkie"
    ],
    "qs_pg:aaroncc":"PL",
    "qs_pg:gn_country":"PL",
    "qs_pg:gn_fcode":"PPLA3",
    "qs_pg:gn_pop":920,
    "qs_pg:name":"Chrzypsko Wielkie",
    "qs_pg:name_adm0":"Polska",
    "qs_pg:name_adm1":"Wielkopolskie",
    "qs_pg:photos":1,
    "qs_pg:photos_1k":1,
    "qs_pg:photos_9k":1,
    "qs_pg:photos_9r":1,
    "qs_pg:photos_all":1,
    "qs_pg:photos_sr":1,
    "qs_pg:pop_sr":2,
    "qs_pg:qs_pg_placetype":"localadmin",
    "qs_pg:qs_pg_placetype_gp":"LocalAdmin",
    "qs_pg:woe_adm0":23424923,
    "woe:adm0_id":23424923,
    "woe:name_adm0":"Polska",
    "woe:name_adm1":"Wielkopolskie",
    "woe:placetype":"LocalAdmin",
    "wof:name":"Chrzypsko Wielkie",
    "wof:placetype":"localadmin",
    "wof:population":920
},
  "geometry": {"coordinates":[16.22852,52.62817],"type":"Point"}
}