{
  "type": "Feature",
  "properties": {
    "gn:admin1_code":"75.0",
    "gn:admin2_code":"601.0",
    "gn:admin3_code":"60106.0",
    "gn:asciiname":"Woloszki",
    "gn:country_code":"PL",
    "gn:dem":153,
    "gn:feature_class":"P",
    "gn:feature_code":"PPL",
    "gn:name":"Wo\u0142oszki",
    "gn:population":0,
    "gn:timezone":"Europe/Warsaw",
    "iso:country":"PL",
    "wof:name":"Woloszki",
    "wof:placetype":"locality"
},
  "geometry": {"coordinates":[23.51667,51.96667],"type":"Point"}
}