{
  "type": "Feature",
  "properties": {
    "gn:population":2936,
    "iso:country":"PL",
    "name:ast_x_preferred":[
        "Zielonki"
    ],
    "name:azb_x_preferred":[
        "\u0698\u0644\u0648\u0646\u06a9\u06cc"
    ],
    "name:ceb_x_preferred":[
        "Zielonki"
    ],
    "name:deu_x_preferred":[
        "Zielonki"
    ],
    "name:eng_x_preferred":[
        "Zielonki"
    ],
    "name:fas_x_preferred":[
        "\u0698\u0644\u0648\u0646\u06a9\u06cc"
    ],
    "name:fra_x_preferred":[
        "Zielonki"
    ],
    "name:nld_x_preferred":[
        "Zielonki"
    ],
    "name:pol_x_preferred":[
        "Zielonki"
    ],
    "name:rus_x_preferred":[
        "\u0417\u0435\u043b\u0451\u043d\u043a\u0438"
    ],
    "name:swe_x_preferred":[
        "Zielonki"
    ],
    "name:ukr_x_preferred":[
        "\u0417\u0435\u043b\u044c\u043e\u043d\u043a\u0456"
    ],
    "qs:a0":"Rzeczpospolita Polska",
    "qs:a1":"*Malopolskie",
    "qs:a1r":"0",
    "qs:a2":"Krakowski",
    "qs:adm0":"Rzeczpospolita Polska",
    "qs:la":"Zielonki",
    "qs:la_lc":"*PL1206172",
    "qs:level":"locality",
    "qs:loc":"Zielonki",
    "qs:loc_alt":"Zielonki",
    "qs:pop":0,
    "qs:type":"rural point-in-poly",
    "wd:wordcount":83,
    "wof:coterminous":[
        1125366317
    ],
    "wof:name":"Zielonki",
    "wof:placetype":"locality",
    "wof:population":2936
},
  "geometry": {"coordinates":[19.9367829074757,50.1376396254784],"type":"Point"}
}