{
  "type": "Feature",
  "properties": {
    "gn:admin1_code":"73.0",
    "gn:admin2_code":"404.0",
    "gn:admin3_code":"40403.0",
    "gn:asciiname":"Kielp",
    "gn:country_code":"PL",
    "gn:dem":85,
    "gn:feature_class":"P",
    "gn:feature_code":"PPL",
    "gn:name":"Kie\u0142p",
    "gn:population":0,
    "gn:timezone":"Europe/Warsaw",
    "iso:country":"PL",
    "name:pol_x_preferred":[
        "Kie\u0142p"
    ],
    "name:ukr_x_preferred":[
        "\u041a\u0435\u043b\u043f"
    ],
    "wof:name":"Kielp",
    "wof:placetype":"locality"
},
  "geometry": {"coordinates":[18.3963,53.29034],"type":"Point"}
}