{
  "type": "Feature",
  "properties": {
    "gn:admin1_code":"81.0",
    "gn:admin2_code":"2005.0",
    "gn:admin3_code":"200509.0",
    "gn:asciiname":"Podlewkowie",
    "gn:country_code":"PL",
    "gn:dem":141,
    "gn:feature_class":"P",
    "gn:feature_code":"PPL",
    "gn:name":"Podlewkowie",
    "gn:population":0,
    "gn:timezone":"Europe/Warsaw",
    "iso:country":"PL",
    "name:fas_x_preferred":[
        "\u067e\u0648\u062f\u0644\u0647\u200c\u0648\u06a9\u0648\u0648\u06cc"
    ],
    "name:lit_x_preferred":[
        "Podlevkoviai"
    ],
    "name:pol_x_preferred":[
        "Podlewkowie"
    ],
    "name:ukr_x_preferred":[
        "\u041f\u043e\u0434\u043b\u0435\u0432\u043a\u043e\u0432\u0435"
    ],
    "wof:name":"Podlewkowie",
    "wof:placetype":"locality"
},
  "geometry": {"coordinates":[23.70732000000001,52.87300000000001],"type":"Point"}
}