{
  "type": "Feature",
  "properties": {
    "gn:admin1_code":"77.0",
    "gn:admin2_code":"1216.0",
    "gn:admin3_code":"121605.0",
    "gn:asciiname":"Glow",
    "gn:country_code":"PL",
    "gn:dem":183,
    "gn:feature_class":"P",
    "gn:feature_code":"PPL",
    "gn:name":"G\u0142\u00f3w",
    "gn:population":0,
    "gn:timezone":"Europe/Warsaw",
    "iso:country":"PL",
    "name:pol_x_preferred":[
        "Gl\u00f3w"
    ],
    "name:ukr_x_preferred":[
        "\u0490\u043b\u044e\u0432"
    ],
    "wof:name":"Glow",
    "wof:placetype":"locality"
},
  "geometry": {"coordinates":[20.87523,50.10197],"type":"Point"}
}