{
  "type": "Feature",
  "properties": {
    "gn:admin1_code":"82.0",
    "gn:admin2_code":"2213.0",
    "gn:admin3_code":"221311.0",
    "gn:asciiname":"Lesna Jania",
    "gn:country_code":"PL",
    "gn:dem":81,
    "gn:feature_class":"P",
    "gn:feature_code":"PPL",
    "gn:name":"Le\u015bna Jania",
    "gn:population":0,
    "gn:timezone":"Europe/Warsaw",
    "iso:country":"PL",
    "name:und_x_variant":[
        "Le\u015bna Jania"
    ],
    "wof:name":"Lesna Jania",
    "wof:placetype":"locality"
},
  "geometry": {"coordinates":[18.60452,53.72221999999999],"type":"Point"}
}