{
  "type": "Feature",
  "properties": {
    "gn:admin1_code":"82.0",
    "gn:admin2_code":"2213.0",
    "gn:admin3_code":"221311.0",
    "gn:asciiname":"Lesna Jania",
    "gn:country_code":"PL",
    "gn:dem":81,
    "gn:feature_class":"P",
    "gn:feature_code":"PPL",
    "gn:name":"Le\u015bna Jania",
    "gn:population":0,
    "gn:timezone":"Europe/Warsaw",
    "iso:country":"PL",
    "name:azb_x_preferred":[
        "\u0644\u0634\u0646\u0627 \u06cc\u0627\u0646\u0642\u0627"
    ],
    "name:ceb_x_preferred":[
        "Le\u015bna Jania"
    ],
    "name:fas_x_preferred":[
        "\u0644\u0634\u0646\u0627 \u06cc\u0627\u0646\u06af\u0627"
    ],
    "name:nld_x_preferred":[
        "Le\u015bna Jania"
    ],
    "name:pol_x_preferred":[
        "Le\u015bna Jania"
    ],
    "name:ukr_x_preferred":[
        "\u041b\u0435\u0441\u044c\u043d\u0430-\u042f\u043d\u044f"
    ],
    "wof:name":"Lesna Jania",
    "wof:placetype":"locality"
},
  "geometry": {"coordinates":[18.60452,53.72221999999999],"type":"Point"}
}