{
  "type": "Feature",
  "properties": {
    "gn:admin1_code":"77.0",
    "gn:admin2_code":"1202.0",
    "gn:admin3_code":"120205.0",
    "gn:asciiname":"Zawada Uszewska",
    "gn:country_code":"PL",
    "gn:dem":251,
    "gn:feature_class":"P",
    "gn:feature_code":"PPL",
    "gn:name":"Zawada Uszewska",
    "gn:population":0,
    "gn:timezone":"Europe/Warsaw",
    "iso:country":"PL",
    "name:pol_x_preferred":[
        "Zawada Uszewska"
    ],
    "name:ukr_x_preferred":[
        "\u0417\u0430\u0432\u0430\u0434\u0430-\u0423\u0448\u0435\u0432\u0441\u044c\u043a\u0430"
    ],
    "wof:name":"Zawada Uszewska",
    "wof:placetype":"locality"
},
  "geometry": {"coordinates":[20.61316,49.90313],"type":"Point"}
}