{
  "type": "Feature",
  "properties": {
    "gn:admin1_code":"85.0",
    "gn:admin2_code":"2804.0",
    "gn:admin3_code":"280408.0",
    "gn:asciiname":"Jankowo",
    "gn:country_code":"PL",
    "gn:dem":26,
    "gn:feature_class":"P",
    "gn:feature_code":"PPL",
    "gn:name":"Jankowo",
    "gn:population":0,
    "gn:timezone":"Europe/Warsaw",
    "iso:country":"PL",
    "name:ceb_x_preferred":[
        "Jankowo"
    ],
    "name:pol_x_preferred":[
        "Jankowo"
    ],
    "name:urd_x_preferred":[
        "\u062c\u0627\u0646\u06a9\u0648\u0648"
    ],
    "wof:name":"Jankowo",
    "wof:placetype":"locality"
},
  "geometry": {"coordinates":[19.4022,53.96265],"type":"Point"}
}