{
  "type": "Feature",
  "properties": {
    "gn:admin1_code":"72.0",
    "gn:admin2_code":"208.0",
    "gn:admin3_code":"20807.0",
    "gn:asciiname":"Wojborz",
    "gn:country_code":"PL",
    "gn:dem":360,
    "gn:feature_class":"P",
    "gn:feature_code":"PPL",
    "gn:name":"Wojborz",
    "gn:population":0,
    "gn:timezone":"Europe/Warsaw",
    "iso:country":"PL",
    "name:deu_x_preferred":[
        "Wojb\u00f3rz"
    ],
    "name:pol_x_preferred":[
        "Wojb\u00f3rz"
    ],
    "name:ukr_x_preferred":[
        "\u0412\u043e\u0439\u0431\u0443\u0436"
    ],
    "wof:name":"Wojborz",
    "wof:placetype":"locality"
},
  "geometry": {"coordinates":[16.65184,50.50753],"type":"Point"}
}