{
  "type": "Feature",
  "properties": {
    "gn:admin1_code":"76.0",
    "gn:admin2_code":"806.0",
    "gn:admin3_code":"80603.0",
    "gn:asciiname":"Kawki",
    "gn:country_code":"PL",
    "gn:dem":99,
    "gn:feature_class":"P",
    "gn:feature_code":"PPL",
    "gn:name":"Kawki",
    "gn:population":0,
    "gn:timezone":"Europe/Warsaw",
    "iso:country":"PL",
    "name:fra_x_preferred":[
        "Kawki"
    ],
    "name:pol_x_preferred":[
        "Kawki"
    ],
    "name:ukr_x_preferred":[
        "\u041a\u0430\u0432\u043a\u0456"
    ],
    "wof:name":"Kawki",
    "wof:placetype":"locality"
},
  "geometry": {"coordinates":[15.67901,52.87193000000001],"type":"Point"}
}