{
  "type": "Feature",
  "properties": {
    "gn:admin1_code":"86.0",
    "gn:admin2_code":"3024.0",
    "gn:admin3_code":"302403.0",
    "gn:asciiname":"Wierzchaczewo",
    "gn:country_code":"PL",
    "gn:dem":96,
    "gn:feature_class":"P",
    "gn:feature_code":"PPL",
    "gn:name":"Wierzchaczewo",
    "gn:population":0,
    "gn:timezone":"Europe/Warsaw",
    "iso:country":"PL",
    "wof:name":"Wierzchaczewo",
    "wof:placetype":"locality"
},
  "geometry": {"coordinates":[16.46914,52.53643],"type":"Point"}
}