{
  "type": "Feature",
  "properties": {
    "gn:admin1_code":"76.0",
    "gn:admin2_code":"861.0",
    "gn:admin3_code":"86101.0",
    "gn:asciiname":"Piaski",
    "gn:country_code":"PL",
    "gn:dem":43,
    "gn:feature_class":"P",
    "gn:feature_code":"PPL",
    "gn:name":"Piaski",
    "gn:population":0,
    "gn:timezone":"Europe/Warsaw",
    "iso:country":"PL",
    "wof:name":"Piaski",
    "wof:placetype":"locality"
},
  "geometry": {"coordinates":[15.23023,52.75003],"type":"Point"}
}