{
  "type": "Feature",
  "properties": {
    "gn:admin1_code":"74.0",
    "gn:admin2_code":"1009.0",
    "gn:admin3_code":"100908.0",
    "gn:asciiname":"Wola Wydrzyna",
    "gn:country_code":"PL",
    "gn:dem":196,
    "gn:feature_class":"P",
    "gn:feature_code":"PPL",
    "gn:name":"Wola Wydrzyna",
    "gn:population":0,
    "gn:timezone":"Europe/Warsaw",
    "iso:country":"PL",
    "name:fra_x_preferred":[
        "Wola Wydrzyna"
    ],
    "name:pol_x_preferred":[
        "Wola Wydrzyna"
    ],
    "name:ukr_x_preferred":[
        "\u0412\u043e\u043b\u044f-\u0412\u0438\u0434\u0436\u0438\u043d\u0430"
    ],
    "wof:name":"Wola Wydrzyna",
    "wof:placetype":"locality"
},
  "geometry": {"coordinates":[19.14694,51.2012],"type":"Point"}
}