{
  "type": "Feature",
  "properties": {
    "gn:admin1_code":"78.0",
    "gn:admin2_code":"1427.0",
    "gn:admin3_code":"142707.0",
    "gn:asciiname":"Kolonia Skoczkowo",
    "gn:country_code":"PL",
    "gn:dem":118,
    "gn:feature_class":"P",
    "gn:feature_code":"PPL",
    "gn:name":"Kolonia Skoczkowo",
    "gn:population":0,
    "gn:timezone":"Europe/Warsaw",
    "iso:country":"PL",
    "name:und_x_variant":[
        "Skoczkowo Kolonia",
        "Kolonia Skoczkowo"
    ],
    "wof:name":"Kolonia Skoczkowo",
    "wof:placetype":"locality"
},
  "geometry": {"coordinates":[19.81284,52.84705],"type":"Point"}
}