{
  "type": "Feature",
  "properties": {
    "gn:admin1_code":"84.0",
    "gn:admin2_code":"2602.0",
    "gn:admin3_code":"260203.0",
    "gn:asciiname":"Bocheniec",
    "gn:country_code":"PL",
    "gn:dem":223,
    "gn:feature_class":"P",
    "gn:feature_code":"PPL",
    "gn:name":"Bocheniec",
    "gn:population":0,
    "gn:timezone":"Europe/Warsaw",
    "iso:country":"PL",
    "name:pol_x_preferred":[
        "Bocheniec"
    ],
    "name:ukr_x_preferred":[
        "\u0411\u043e\u0445\u0435\u043d\u0435\u0446\u044c"
    ],
    "wof:name":"Bocheniec",
    "wof:placetype":"locality"
},
  "geometry": {"coordinates":[20.31186,50.79754000000001],"type":"Point"}
}