{
  "type": "Feature",
  "properties": {
    "gn:admin1_code":"81.0",
    "gn:admin2_code":"2061.0",
    "gn:admin3_code":"206101.0",
    "gn:asciiname":"Kolonia Bacieczki",
    "gn:country_code":"PL",
    "gn:dem":130,
    "gn:feature_class":"P",
    "gn:feature_code":"PPL",
    "gn:name":"Kolonia Bacieczki",
    "gn:population":0,
    "gn:timezone":"Europe/Warsaw",
    "iso:country":"PL",
    "wof:name":"Kolonia Bacieczki",
    "wof:placetype":"neighbourhood"
},
  "geometry": {"coordinates":[23.11677,53.16908000000001],"type":"Point"}
}