{
  "type": "Feature",
  "properties": {
    "gn:admin1_code":"79.0",
    "gn:admin2_code":"1610.0",
    "gn:admin3_code":"161001.0",
    "gn:asciiname":"Laskowiec",
    "gn:country_code":"PL",
    "gn:dem":254,
    "gn:feature_class":"P",
    "gn:feature_code":"PPL",
    "gn:name":"L\u00e1skowiec",
    "gn:population":0,
    "gn:timezone":"Europe/Warsaw",
    "iso:country":"PL",
    "name:azb_x_preferred":[
        "\u0644\u0627\u0633\u06a9\u0648\u0648\u06cc\u062a\u0633"
    ],
    "name:deu_x_preferred":[
        "Laskowiec"
    ],
    "name:fas_x_preferred":[
        "\u0644\u0627\u0633\u06a9\u0648\u0648\u06cc\u062a\u0633"
    ],
    "name:pol_x_preferred":[
        "Laskowiec"
    ],
    "name:ukr_x_preferred":[
        "\u041b\u044f\u0441\u043a\u043e\u0432\u0435\u0446\u044c"
    ],
    "name:und_x_variant":[
        "L\u00e1skowiec"
    ],
    "wof:name":"Laskowiec",
    "wof:placetype":"locality"
},
  "geometry": {"coordinates":[17.57735,50.38293],"type":"Point"}
}