{
  "type": "Feature",
  "properties": {
    "gn:admin1_code":"79.0",
    "gn:admin2_code":"1610.0",
    "gn:admin3_code":"161001.0",
    "gn:asciiname":"Laskowiec",
    "gn:country_code":"PL",
    "gn:dem":254,
    "gn:feature_class":"P",
    "gn:feature_code":"PPL",
    "gn:name":"L\u00e1skowiec",
    "gn:population":0,
    "gn:timezone":"Europe/Warsaw",
    "iso:country":"PL",
    "name:und_x_variant":[
        "L\u00e1skowiec"
    ],
    "wof:name":"Laskowiec",
    "wof:placetype":"locality"
},
  "geometry": {"coordinates":[17.57735,50.38293],"type":"Point"}
}