{
  "type": "Feature",
  "properties": {
    "gn:gn_country":"PL",
    "gn:gn_fcode":"PPL",
    "gn:gn_pop":310,
    "gn:population":310,
    "iso:country":"PL",
    "name:ast_x_preferred":[
        "P\u0119kowice"
    ],
    "name:azb_x_preferred":[
        "\u067e\u0646\u06a9\u0648\u0648\u06cc\u062a\u0633\u0647"
    ],
    "name:ceb_x_preferred":[
        "P\u0119kowice"
    ],
    "name:eng_x_preferred":[
        "P\u0119kowice"
    ],
    "name:fas_x_preferred":[
        "\u067e\u0646\u06a9\u0648\u0648\u06cc\u062a\u0633\u0647"
    ],
    "name:fra_x_preferred":[
        "P\u0119kowice"
    ],
    "name:pol_x_preferred":[
        "P\u0119kowice"
    ],
    "name:rus_x_preferred":[
        "\u041f\u0435\u043d\u043a\u043e\u0432\u0438\u0446\u0435"
    ],
    "name:ukr_x_preferred":[
        "\u041f\u0435\u043d\u043a\u043e\u0432\u0456\u0446\u0435"
    ],
    "qs_pg:aaroncc":"PL",
    "qs_pg:gn_country":"PL",
    "qs_pg:gn_fcode":"PPL",
    "qs_pg:gn_pop":310,
    "qs_pg:name":"P\u0119kowice",
    "qs_pg:name_adm0":"Polska",
    "qs_pg:name_adm1":"Ma\u0142opolskie",
    "qs_pg:photos_9k":1,
    "qs_pg:photos_9r":1,
    "qs_pg:photos_all":3,
    "qs_pg:photos_sr":0,
    "qs_pg:pop_sr":2,
    "qs_pg:qs_pg_placetype":"locality",
    "qs_pg:qs_pg_placetype_gp":"Town",
    "qs_pg:woe_adm0":23424923,
    "woe:adm0_id":23424923,
    "woe:name_adm0":"Polska",
    "woe:name_adm1":"Ma\u0142opolskie",
    "woe:placetype":"Town",
    "wof:name":"P\u0119kowice",
    "wof:placetype":"locality",
    "wof:population":310
},
  "geometry": {"coordinates":[19.90294,50.12718],"type":"Point"}
}