{
  "type": "Feature",
  "properties": {
    "gn:admin1_code":"75.0",
    "gn:admin2_code":"602.0",
    "gn:admin3_code":"60209.0",
    "gn:asciiname":"Maziarze",
    "gn:country_code":"PL",
    "gn:dem":212,
    "gn:feature_class":"P",
    "gn:feature_code":"PPL",
    "gn:name":"Maziarze",
    "gn:population":0,
    "gn:timezone":"Europe/Warsaw",
    "iso:country":"PL",
    "name:fra_x_preferred":[
        "Maziarze"
    ],
    "name:pol_x_preferred":[
        "Maziarze"
    ],
    "name:ukr_x_preferred":[
        "\u041c\u0430\u0437\u044f\u0436\u0435"
    ],
    "wof:name":"Maziarze",
    "wof:placetype":"locality"
},
  "geometry": {"coordinates":[23.03333,50.41667],"type":"Point"}
}