{
  "type": "Feature",
  "properties": {
    "gn:admin1_code":"77.0",
    "gn:admin2_code":"1207.0",
    "gn:admin3_code":"120704.0",
    "gn:asciiname":"Wilkowisko",
    "gn:country_code":"PL",
    "gn:dem":428,
    "gn:feature_class":"P",
    "gn:feature_code":"PPL",
    "gn:name":"Wilkowisko",
    "gn:population":0,
    "gn:timezone":"Europe/Warsaw",
    "iso:country":"PL",
    "name:pol_x_preferred":[
        "Wilkowisko"
    ],
    "name:ukr_x_preferred":[
        "\u0412\u0456\u043b\u044c\u043a\u043e\u0432\u0438\u0441\u044c\u043a\u043e"
    ],
    "wof:name":"Wilkowisko",
    "wof:placetype":"locality"
},
  "geometry": {"coordinates":[20.25501,49.75632],"type":"Point"}
}