{
  "type": "Feature",
  "properties": {
    "gn:admin1_code":"86.0",
    "gn:admin2_code":"3009.0",
    "gn:admin3_code":"300909.0",
    "gn:asciiname":"Umien",
    "gn:country_code":"PL",
    "gn:dem":111,
    "gn:feature_class":"P",
    "gn:feature_code":"PPL",
    "gn:name":"Umie\u0144",
    "gn:population":0,
    "gn:timezone":"Europe/Warsaw",
    "iso:country":"PL",
    "name:ceb_x_preferred":[
        "Umie\u0144"
    ],
    "name:pol_x_preferred":[
        "Umie\u0144"
    ],
    "name:ukr_x_preferred":[
        "\u0423\u043c\u0435\u043d\u044c"
    ],
    "name:und_x_variant":[
        "Umie\u0144"
    ],
    "wof:name":"Umien",
    "wof:placetype":"locality"
},
  "geometry": {"coordinates":[18.83114,52.16385],"type":"Point"}
}