{
  "type": "Feature",
  "properties": {
    "gn:country":"PL",
    "gn:fcode":"PPL",
    "gn:population":145,
    "iso:country":"PL",
    "name:ast_x_preferred":[
        "Zabrodzie"
    ],
    "name:ceb_x_preferred":[
        "Zabrodzie"
    ],
    "name:ces_x_preferred":[
        "Zabrodzie"
    ],
    "name:che_x_preferred":[
        "\u0417\u0430\u0431\u0440\u043e\u0434\u0437\u0435"
    ],
    "name:eng_x_preferred":[
        "Zabrodzie"
    ],
    "name:fra_x_preferred":[
        "Zabrodzie"
    ],
    "name:lit_x_preferred":[
        "Zabrodziai"
    ],
    "name:nan_x_preferred":[
        "Zabrodzie"
    ],
    "name:pol_x_preferred":[
        "Zabrodzie"
    ],
    "name:tat_x_preferred":[
        "\u0417\u0430\u0431\u0440\u043e\u0434\u0437\u0435"
    ],
    "name:ukr_x_preferred":[
        "\u0417\u0430\u0431\u0440\u043e\u0434\u0437\u0435"
    ],
    "name:urd_x_preferred":[
        "\u0632\u0628\u0631\u0648\u062f\u0632\u0626\u06d2\u060c \u067e\u0648\u062f\u0644\u0633\u06a9\u0626\u06cc \u0648\u0648\u06cc\u0648\u0648\u062f\u0634\u067e"
    ],
    "name:urd_x_variant":[
        "\u0632\u0628\u0631\u0648\u062f\u0632\u0626\u06d2"
    ],
    "qs_pg:aaroncc":"PL",
    "qs_pg:gn_country":"PL",
    "qs_pg:gn_fcode":"PPL",
    "qs_pg:gn_pop":145,
    "qs_pg:name":"Zabrodzie",
    "qs_pg:name_adm0":"Polska",
    "qs_pg:name_adm1":"Podlaskie",
    "qs_pg:photos_9r":0,
    "qs_pg:photos_sr":0,
    "qs_pg:pop_sr":1,
    "qs_pg:qs_pg_placetype":"locality",
    "qs_pg:qs_pg_placetype_gp":"Town",
    "qs_pg:woe_adm0":23424923,
    "woe:adm0_id":23424923,
    "woe:name_adm0":"Polska",
    "woe:name_adm1":"Podlaskie",
    "woe:placetype":"Town",
    "wof:name":"Zabrodzie",
    "wof:placetype":"locality",
    "wof:population":145
},
  "geometry": {"coordinates":[23.13103,53.46705],"type":"Point"}
}