{
  "type": "Feature",
  "properties": {
    "gn:admin1_code":"75.0",
    "gn:admin2_code":"610.0",
    "gn:admin3_code":"61001.0",
    "gn:asciiname":"Zagorze",
    "gn:cc2":"PL",
    "gn:country_code":"PL",
    "gn:dem":173,
    "gn:feature_class":"P",
    "gn:feature_code":"PPL",
    "gn:name":"Zag\u00f3rze",
    "gn:population":0,
    "gn:timezone":"Europe/Warsaw",
    "iso:country":"PL",
    "name:fra_x_preferred":[
        "Zag\u00f3rze"
    ],
    "name:pol_x_preferred":[
        "Zag\u00f3rze"
    ],
    "name:ukr_x_preferred":[
        "\u0417\u0430\u0491\u0443\u0436\u0435"
    ],
    "name:und_x_variant":[
        "Kolonia Zag\u00f3rze",
        "Zag\u00f3rze"
    ],
    "name:urd_x_preferred":[
        "\u0632\u06af\u0648\u0631\u0636\u06cc"
    ],
    "wof:name":"Zagorze",
    "wof:placetype":"locality"
},
  "geometry": {"coordinates":[23.20158,51.34273],"type":"Point"}
}