{
  "type": "Feature",
  "properties": {
    "gn:admin1_code":"86.0",
    "gn:admin2_code":"3009.0",
    "gn:admin3_code":"300903.0",
    "gn:asciiname":"Dlugie",
    "gn:country_code":"PL",
    "gn:dem":117,
    "gn:feature_class":"P",
    "gn:feature_code":"PPL",
    "gn:name":"D\u0142ugie",
    "gn:population":0,
    "gn:timezone":"Europe/Warsaw",
    "iso:country":"PL",
    "name:pol_x_preferred":[
        "D\u0142ugie"
    ],
    "name:ukr_x_preferred":[
        "\u0414\u043b\u0443\u0491\u0435"
    ],
    "name:und_x_variant":[
        "D\u0142ugie"
    ],
    "wof:name":"Dlugie",
    "wof:placetype":"locality"
},
  "geometry": {"coordinates":[18.95464,52.29189],"type":"Point"}
}