{
  "type": "Feature",
  "properties": {
    "gn:country":"PL",
    "gn:fcode":"PPL",
    "gn:population":0,
    "iso:country":"PL",
    "name:ast_x_preferred":[
        "R\u0119boszewo"
    ],
    "name:ceb_x_preferred":[
        "R\u0119boszewo"
    ],
    "name:ces_x_preferred":[
        "R\u0119boszewo"
    ],
    "name:che_x_preferred":[
        "\u0420\u0435\u043c\u0431\u043e\u0448\u0435\u0432\u043e"
    ],
    "name:csb_x_preferred":[
        "R\u00e3b\u00f2szew\u00f2"
    ],
    "name:deu_x_preferred":[
        "R\u0119boszewo"
    ],
    "name:eng_x_preferred":[
        "R\u0119boszewo"
    ],
    "name:fra_x_preferred":[
        "R\u0119boszewo"
    ],
    "name:nan_x_preferred":[
        "R\u0119boszewo"
    ],
    "name:pol_x_preferred":[
        "R\u0119boszewo"
    ],
    "name:tat_x_preferred":[
        "\u0420\u0435\u043c\u0431\u043e\u0448\u0435\u0432\u043e"
    ],
    "name:ukr_x_preferred":[
        "\u0420\u0435\u043c\u0431\u043e\u0448\u0435\u0432\u043e"
    ],
    "qs_pg:aaroncc":"PL",
    "qs_pg:gn_country":"PL",
    "qs_pg:gn_fcode":"PPL",
    "qs_pg:gn_pop":0,
    "qs_pg:name":"R\u0119boszewo",
    "qs_pg:name_adm0":"Polska",
    "qs_pg:name_adm1":"Pomorskie",
    "qs_pg:photos":10,
    "qs_pg:photos_1k":2,
    "qs_pg:photos_9k":1,
    "qs_pg:photos_9r":1,
    "qs_pg:photos_all":10,
    "qs_pg:photos_sr":1,
    "qs_pg:pop_sr":0,
    "qs_pg:qs_pg_placetype":"locality",
    "qs_pg:qs_pg_placetype_gp":"Town",
    "qs_pg:woe_adm0":23424923,
    "woe:adm0_id":23424923,
    "woe:name_adm0":"Polska",
    "woe:name_adm1":"Pomorskie",
    "woe:placetype":"Town",
    "wof:name":"R\u0119boszewo",
    "wof:placetype":"locality"
},
  "geometry": {"coordinates":[18.12258,54.29019],"type":"Point"}
}