{
  "type": "Feature",
  "properties": {
    "gn:admin1_code":"75.0",
    "gn:admin2_code":"619.0",
    "gn:admin3_code":"61902.0",
    "gn:asciiname":"Dolhobrody",
    "gn:country_code":"PL",
    "gn:dem":151,
    "gn:feature_class":"P",
    "gn:feature_code":"PPL",
    "gn:name":"Do\u0142hobrody",
    "gn:population":0,
    "gn:timezone":"Europe/Warsaw",
    "iso:country":"PL",
    "name:azb_x_preferred":[
        "\u062f\u0648\u0648\u062e\u0648\u0628\u0631\u0648\u062f\u0647"
    ],
    "name:ceb_x_preferred":[
        "Do\u0142hobrody"
    ],
    "name:fas_x_preferred":[
        "\u062f\u0648\u0648\u062e\u0648\u0628\u0631\u0648\u062f\u0647"
    ],
    "name:fra_x_preferred":[
        "Do\u0142hobrody"
    ],
    "name:lit_x_preferred":[
        "Dolhobrodai"
    ],
    "name:nld_x_preferred":[
        "Do\u0142hobrody"
    ],
    "name:pol_x_preferred":[
        "Do\u0142hobrody"
    ],
    "name:ukr_x_preferred":[
        "\u0414\u043e\u043b\u0433\u043e\u0431\u0440\u043e\u0434\u0438"
    ],
    "wof:name":"Dolhobrody",
    "wof:placetype":"locality"
},
  "geometry": {"coordinates":[23.51337,51.6852],"type":"Point"}
}