{
  "type": "Feature",
  "properties": {
    "gn:admin1_code":"75.0",
    "gn:admin2_code":"619.0",
    "gn:admin3_code":"61902.0",
    "gn:asciiname":"Dolhobrody",
    "gn:country_code":"PL",
    "gn:dem":151,
    "gn:feature_class":"P",
    "gn:feature_code":"PPL",
    "gn:name":"Do\u0142hobrody",
    "gn:population":0,
    "gn:timezone":"Europe/Warsaw",
    "iso:country":"PL",
    "name:und_x_variant":[
        "Do\u0142hobrody"
    ],
    "wof:name":"Dolhobrody",
    "wof:placetype":"locality"
},
  "geometry": {"coordinates":[23.51337,51.6852],"type":"Point"}
}