{
  "type": "Feature",
  "properties": {
    "gn:admin1_code":"85.0",
    "gn:admin2_code":"2813.0",
    "gn:admin3_code":"281303.0",
    "gn:asciiname":"Golubki",
    "gn:country_code":"PL",
    "gn:dem":186,
    "gn:feature_class":"P",
    "gn:feature_code":"PPL",
    "gn:name":"Golubki",
    "gn:population":0,
    "gn:timezone":"Europe/Warsaw",
    "iso:country":"PL",
    "name:azb_x_preferred":[
        "\u0642\u0648\u0644\u0648\u0628\u06a9\u06cc"
    ],
    "name:deu_x_preferred":[
        "Golubki"
    ],
    "name:fas_x_preferred":[
        "\u06af\u0648\u0644\u0648\u0628\u06a9\u06cc"
    ],
    "name:nld_x_preferred":[
        "Golubki"
    ],
    "name:pol_x_preferred":[
        "Golubki"
    ],
    "name:ukr_x_preferred":[
        "\u0490\u043e\u043b\u044e\u0431\u043a\u0456"
    ],
    "name:und_x_variant":[
        "Gollubien",
        "Golubie",
        "Gollubien Kreis Treuburg",
        "Kalkhof"
    ],
    "wof:name":"Golubki",
    "wof:placetype":"locality"
},
  "geometry": {"coordinates":[22.45255,54.0969],"type":"Point"}
}