{
  "type": "Feature",
  "properties": {
    "iso:country":"PL",
    "name:pol_x_preferred":[
        "Br\u00f3dno Podgrodzie"
    ],
    "wof:name":"Brodno Podgrodzie",
    "wof:placetype":"neighbourhood"
},
  "geometry": {"coordinates":[21.0515696982616,52.29799007578573],"type":"Point"}
}