{
  "type": "Feature",
  "properties": {
    "gn:admin1_code":"85.0",
    "gn:admin2_code":"2815.0",
    "gn:admin3_code":"281509.0",
    "gn:asciiname":"Ostrowin",
    "gn:country_code":"PL",
    "gn:dem":145,
    "gn:feature_class":"P",
    "gn:feature_code":"PPL",
    "gn:name":"Ostrowin",
    "gn:population":0,
    "gn:timezone":"Europe/Warsaw",
    "iso:country":"PL",
    "name:fra_x_preferred":[
        "Ostrowin"
    ],
    "name:pol_x_preferred":[
        "Ostrowin"
    ],
    "name:ukr_x_preferred":[
        "\u041e\u0441\u0442\u0440\u043e\u0432\u0456\u043d"
    ],
    "name:und_x_variant":[
        "Osterwein"
    ],
    "wof:name":"Ostrowin",
    "wof:placetype":"locality"
},
  "geometry": {"coordinates":[20.09981,53.64983],"type":"Point"}
}