{
  "type": "Feature",
  "properties": {
    "gn:admin1_code":"86.0",
    "gn:admin2_code":"3019.0",
    "gn:admin3_code":"301903.0",
    "gn:asciiname":"Rownopole",
    "gn:country_code":"PL",
    "gn:dem":92,
    "gn:feature_class":"P",
    "gn:feature_code":"PPL",
    "gn:name":"R\u00f3wnopole",
    "gn:population":0,
    "gn:timezone":"Europe/Warsaw",
    "iso:country":"PL",
    "name:und_x_variant":[
        "R\u00f3wnopole"
    ],
    "wof:name":"Rownopole",
    "wof:placetype":"locality"
},
  "geometry": {"coordinates":[16.91667,53.11666999999999],"type":"Point"}
}