{
  "type": "Feature",
  "properties": {
    "gn:admin1_code":"73.0",
    "gn:admin2_code":"408.0",
    "gn:admin3_code":"40805.0",
    "gn:asciiname":"Zajeziorze",
    "gn:country_code":"PL",
    "gn:dem":103,
    "gn:feature_class":"P",
    "gn:feature_code":"PPL",
    "gn:name":"Zajeziorze",
    "gn:population":0,
    "gn:timezone":"Europe/Warsaw",
    "iso:country":"PL",
    "name:und_x_variant":[
        "Zajezierze",
        "Zajeziorze"
    ],
    "wof:name":"Zajeziorze",
    "wof:placetype":"locality"
},
  "geometry": {"coordinates":[19.13954,52.95454],"type":"Point"}
}