{
  "type": "Feature",
  "properties": {
    "gn:admin1_code":"76.0",
    "gn:admin2_code":"811.0",
    "gn:admin3_code":"81110.0",
    "gn:asciiname":"Marszow",
    "gn:country_code":"PL",
    "gn:dem":136,
    "gn:feature_class":"P",
    "gn:feature_code":"PPL",
    "gn:name":"Marsz\u00f3w",
    "gn:population":0,
    "gn:timezone":"Europe/Warsaw",
    "iso:country":"PL",
    "name:fra_x_preferred":[
        "Marsz\u00f3w"
    ],
    "name:pol_x_preferred":[
        "Marsz\u00f3w"
    ],
    "name:ukr_x_preferred":[
        "\u041c\u0430\u0440\u0448\u0443\u0432"
    ],
    "wof:name":"Marszow",
    "wof:placetype":"locality"
},
  "geometry": {"coordinates":[15.21606,51.63427],"type":"Point"}
}