{
  "type": "Feature",
  "properties": {
    "gn:admin1_code":"86.0",
    "gn:admin2_code":"3029.0",
    "gn:admin3_code":"302901.0",
    "gn:asciiname":"Saczkowo",
    "gn:country_code":"PL",
    "gn:dem":67,
    "gn:feature_class":"P",
    "gn:feature_code":"PPL",
    "gn:name":"S\u0105czkowo",
    "gn:population":0,
    "gn:timezone":"Europe/Warsaw",
    "iso:country":"PL",
    "name:fra_x_preferred":[
        "S\u0105czkowo"
    ],
    "name:pol_x_preferred":[
        "S\u0105czkowo"
    ],
    "name:ukr_x_preferred":[
        "\u0421\u043e\u043d\u0447\u043a\u043e\u0432\u043e"
    ],
    "name:urd_x_preferred":[
        "\u0633\u06a9\u0632\u06a9\u0648\u0648\u0648"
    ],
    "wof:name":"Saczkowo",
    "wof:placetype":"locality"
},
  "geometry": {"coordinates":[16.35839,52.0062],"type":"Point"}
}