{
  "type": "Feature",
  "properties": {
    "gn:admin1_code":"86.0",
    "gn:admin2_code":"3029.0",
    "gn:admin3_code":"302901.0",
    "gn:asciiname":"Saczkowo",
    "gn:country_code":"PL",
    "gn:dem":67,
    "gn:feature_class":"P",
    "gn:feature_code":"PPL",
    "gn:name":"S\u0105czkowo",
    "gn:population":0,
    "gn:timezone":"Europe/Warsaw",
    "iso:country":"PL",
    "name:und_x_variant":[
        "S\u0105czkowo"
    ],
    "wof:name":"Saczkowo",
    "wof:placetype":"locality"
},
  "geometry": {"coordinates":[16.35839,52.0062],"type":"Point"}
}