{
  "type": "Feature",
  "properties": {
    "gn:country":"PL",
    "gn:fcode":"PPL",
    "gn:population":0,
    "iso:country":"PL",
    "name:ast_x_preferred":[
        "Bydlino"
    ],
    "name:azb_x_preferred":[
        "\u0628\u062f\u0644\u06cc\u0646\u0648"
    ],
    "name:ceb_x_preferred":[
        "Bydlino"
    ],
    "name:ces_x_preferred":[
        "Bydlino"
    ],
    "name:che_x_preferred":[
        "\u0411\u0438\u0434\u043b\u0438\u043d\u043e"
    ],
    "name:csb_x_preferred":[
        "B\u00ebdl\u00ebno"
    ],
    "name:dan_x_preferred":[
        "Bydlino"
    ],
    "name:deu_x_preferred":[
        "Bydlino"
    ],
    "name:eng_x_preferred":[
        "Bydlino"
    ],
    "name:fas_x_preferred":[
        "\u0628\u062f\u0644\u06cc\u0646\u0648"
    ],
    "name:fra_x_preferred":[
        "Bydlino"
    ],
    "name:nan_x_preferred":[
        "Bydlino"
    ],
    "name:nld_x_preferred":[
        "Bydlino"
    ],
    "name:pol_x_preferred":[
        "Bydlino"
    ],
    "name:tat_x_preferred":[
        "\u0411\u0438\u0434\u043b\u0438\u043d\u043e"
    ],
    "name:ukr_x_preferred":[
        "\u0411\u0438\u0434\u043b\u0456\u043d\u043e"
    ],
    "name:urd_x_preferred":[
        "\u0628\u0627\u0626\u062f\u0644\u06cc\u0646\u0648"
    ],
    "qs_pg:aaroncc":"PL",
    "qs_pg:gn_country":"PL",
    "qs_pg:gn_fcode":"PPL",
    "qs_pg:gn_pop":0,
    "qs_pg:name":"Bydlino",
    "qs_pg:name_adm0":"Polska",
    "qs_pg:name_adm1":"Pomorskie",
    "qs_pg:photos_9k":1,
    "qs_pg:photos_9r":1,
    "qs_pg:photos_all":3,
    "qs_pg:photos_sr":0,
    "qs_pg:pop_sr":0,
    "qs_pg:qs_pg_placetype":"locality",
    "qs_pg:qs_pg_placetype_gp":"Town",
    "qs_pg:woe_adm0":23424923,
    "woe:adm0_id":23424923,
    "woe:name_adm0":"Polska",
    "woe:name_adm1":"Pomorskie",
    "woe:placetype":"Town",
    "wof:name":"Bydlino",
    "wof:placetype":"locality"
},
  "geometry": {"coordinates":[16.97353,54.5396],"type":"Point"}
}