{
  "type": "Feature",
  "properties": {
    "gn:admin1_code":"84.0",
    "gn:admin2_code":"2602.0",
    "gn:admin3_code":"260206.0",
    "gn:asciiname":"Grodek",
    "gn:country_code":"PL",
    "gn:dem":252,
    "gn:feature_class":"P",
    "gn:feature_code":"PPL",
    "gn:name":"Gr\u00f3dek",
    "gn:population":0,
    "gn:timezone":"Europe/Warsaw",
    "iso:country":"PL",
    "name:deu_x_preferred":[
        "Grodek"
    ],
    "wof:name":"Grodek",
    "wof:placetype":"locality"
},
  "geometry": {"coordinates":[20.04638,50.56613],"type":"Point"}
}