{
  "type": "Feature",
  "properties": {
    "gn:admin1_code":"85.0",
    "gn:admin2_code":"2813.0",
    "gn:admin3_code":"281305.0",
    "gn:asciiname":"Pietrasze",
    "gn:country_code":"PL",
    "gn:dem":152,
    "gn:feature_class":"P",
    "gn:feature_code":"PPL",
    "gn:name":"Pietrasze",
    "gn:population":0,
    "gn:timezone":"Europe/Warsaw",
    "iso:country":"PL",
    "name:deu_x_preferred":[
        "Pietrasze"
    ],
    "name:nld_x_preferred":[
        "Pietrasze"
    ],
    "name:pol_x_preferred":[
        "Pietrasze"
    ],
    "name:ukr_x_preferred":[
        "\u041f\u0435\u0442\u0440\u0430\u0448\u0435"
    ],
    "name:und_x_variant":[
        "Petersgrund",
        "Pietraschen",
        "Pietrasze"
    ],
    "wof:name":"Pietrasze",
    "wof:placetype":"locality"
},
  "geometry": {"coordinates":[22.18116,54.01682],"type":"Point"}
}