{
  "type": "Feature",
  "properties": {
    "gn:admin1_code":"80.0",
    "gn:admin2_code":"1815.0",
    "gn:admin3_code":"181501.0",
    "gn:asciiname":"Brzeznik",
    "gn:country_code":"PL",
    "gn:dem":282,
    "gn:feature_class":"P",
    "gn:feature_code":"PPL",
    "gn:name":"Brze\u017anik",
    "gn:population":0,
    "gn:timezone":"Europe/Warsaw",
    "iso:country":"PL",
    "wof:name":"Brzeznik",
    "wof:placetype":"locality"
},
  "geometry": {"coordinates":[21.71791,50.00839000000001],"type":"Point"}
}