{
  "type": "Feature",
  "properties": {
    "gn:admin1_code":"76.0",
    "gn:admin2_code":"809.0",
    "gn:admin3_code":"80901.0",
    "gn:asciiname":"Podmokle Wielkie",
    "gn:country_code":"PL",
    "gn:dem":59,
    "gn:feature_class":"P",
    "gn:feature_code":"PPL",
    "gn:name":"Podmok\u0142e Wielkie",
    "gn:population":0,
    "gn:timezone":"Europe/Warsaw",
    "iso:country":"PL",
    "name:deu_x_preferred":[
        "Gro\u00df Posemuckel"
    ],
    "wof:name":"Podmokle Wielkie",
    "wof:placetype":"locality"
},
  "geometry": {"coordinates":[15.81971,52.19319],"type":"Point"}
}