{
  "type": "Feature",
  "properties": {
    "gn:admin1_code":"76.0",
    "gn:admin2_code":"809.0",
    "gn:admin3_code":"80901.0",
    "gn:asciiname":"Podmokle Wielkie",
    "gn:country_code":"PL",
    "gn:dem":59,
    "gn:feature_class":"P",
    "gn:feature_code":"PPL",
    "gn:name":"Podmok\u0142e Wielkie",
    "gn:population":0,
    "gn:timezone":"Europe/Warsaw",
    "iso:country":"PL",
    "name:deu_x_preferred":[
        "Gro\u00df Posemuckel"
    ],
    "name:deu_x_variant":[
        "Podmokle Wielkie"
    ],
    "name:fas_x_preferred":[
        "\u067e\u0648\u062f\u0645\u0648\u06a9\u0644\u0647 \u0648\u06cc\u0644\u06a9\u06cc\u0647"
    ],
    "name:fra_x_preferred":[
        "Podmokle Wielkie"
    ],
    "name:pol_x_preferred":[
        "Podmokle Wielkie"
    ],
    "name:ukr_x_preferred":[
        "\u041f\u043e\u0434\u043c\u043e\u043a\u043b\u0435-\u0412\u0435\u043b\u0438\u043a\u0435"
    ],
    "wof:name":"Podmokle Wielkie",
    "wof:placetype":"locality"
},
  "geometry": {"coordinates":[15.81971,52.19319],"type":"Point"}
}