{
  "type": "Feature",
  "properties": {
    "gn:admin1_code":"84.0",
    "gn:admin2_code":"2608.0",
    "gn:admin3_code":"260804.0",
    "gn:asciiname":"Kozubow",
    "gn:country_code":"PL",
    "gn:dem":207,
    "gn:feature_class":"P",
    "gn:feature_code":"PPL",
    "gn:name":"Kozub\u00f3w",
    "gn:population":0,
    "gn:timezone":"Europe/Warsaw",
    "iso:country":"PL",
    "name:pol_x_preferred":[
        "Kozub\u00f3w"
    ],
    "name:ukr_x_preferred":[
        "\u041a\u043e\u0437\u0443\u0431\u0443\u0432"
    ],
    "wof:name":"Kozubow",
    "wof:placetype":"locality"
},
  "geometry": {"coordinates":[20.4847,50.43324000000001],"type":"Point"}
}