{
  "type": "Feature",
  "properties": {
    "gn:admin1_code":"78.0",
    "gn:admin2_code":"1418.0",
    "gn:admin3_code":"141805.0",
    "gn:asciiname":"Chosna",
    "gn:country_code":"PL",
    "gn:dem":126,
    "gn:feature_class":"P",
    "gn:feature_code":"PPL",
    "gn:name":"Cho\u015bna",
    "gn:population":0,
    "gn:timezone":"Europe/Warsaw",
    "iso:country":"PL",
    "name:azb_x_preferred":[
        "\u062e\u0648\u0633\u0646\u0627"
    ],
    "name:ceb_x_preferred":[
        "Cho\u015bna"
    ],
    "name:fas_x_preferred":[
        "\u062e\u0648\u0633\u0646\u0627"
    ],
    "name:fra_x_preferred":[
        "Chosna"
    ],
    "name:pol_x_preferred":[
        "Chosna"
    ],
    "name:tgl_x_preferred":[
        "Chosna"
    ],
    "name:ukr_x_preferred":[
        "\u0425\u043e\u0441\u043d\u0430"
    ],
    "wof:name":"Chosna",
    "wof:placetype":"locality"
},
  "geometry": {"coordinates":[21.03942,51.93622],"type":"Point"}
}