{
  "type": "Feature",
  "properties": {
    "gn:admin1_code":"78.0",
    "gn:admin2_code":"1436.0",
    "gn:admin3_code":"143602.0",
    "gn:asciiname":"Wolka Policka",
    "gn:country_code":"PL",
    "gn:dem":151,
    "gn:feature_class":"P",
    "gn:feature_code":"PPL",
    "gn:name":"W\u00f3lka Policka",
    "gn:population":0,
    "gn:timezone":"Europe/Warsaw",
    "iso:country":"PL",
    "name:fra_x_preferred":[
        "W\u00f3lka Policka"
    ],
    "name:pol_x_preferred":[
        "W\u00f3lka Policka"
    ],
    "name:ukr_x_preferred":[
        "\u0412\u0443\u043b\u044c\u043a\u0430-\u041f\u043e\u043b\u0456\u0446\u044c\u043a\u0430"
    ],
    "wof:name":"Wolka Policka",
    "wof:placetype":"locality"
},
  "geometry": {"coordinates":[21.64924,51.45849000000001],"type":"Point"}
}