{
  "type": "Feature",
  "properties": {
    "gn:admin1_code":"78.0",
    "gn:admin2_code":"1438.0",
    "gn:admin3_code":"143805.0",
    "gn:asciiname":"Podbuszyce",
    "gn:country_code":"PL",
    "gn:dem":93,
    "gn:feature_class":"P",
    "gn:feature_code":"PPL",
    "gn:name":"Podbuszyce",
    "gn:population":0,
    "gn:timezone":"Europe/Warsaw",
    "iso:country":"PL",
    "wof:name":"Podbuszyce",
    "wof:placetype":"locality"
},
  "geometry": {"coordinates":[20.41243,52.12263],"type":"Point"}
}