{
  "type": "Feature",
  "properties": {
    "gn:admin1_code":"75.0",
    "gn:admin2_code":"607.0",
    "gn:admin3_code":"60707.0",
    "gn:asciiname":"Wolka Olbiecka",
    "gn:country_code":"PL",
    "gn:dem":217,
    "gn:feature_class":"P",
    "gn:feature_code":"PPL",
    "gn:name":"W\u00f3lka Olbi\u0119cka",
    "gn:population":0,
    "gn:timezone":"Europe/Warsaw",
    "iso:country":"PL",
    "name:fra_x_preferred":[
        "W\u00f3lka Olbi\u0119cka"
    ],
    "name:pol_x_preferred":[
        "W\u00f3lka Olbi\u0119cka"
    ],
    "name:ukr_x_preferred":[
        "\u0412\u0443\u043b\u044c\u043a\u0430-\u041e\u043b\u044c\u0431\u0435\u043d\u0446\u044c\u043a\u0430"
    ],
    "name:und_x_variant":[
        "W\u00f3lka Olbicka"
    ],
    "wof:name":"Wolka Olbiecka",
    "wof:placetype":"locality"
},
  "geometry": {"coordinates":[22.13771,50.90886],"type":"Point"}
}