{
  "type": "Feature",
  "properties": {
    "gn:admin1_code":"76.0",
    "gn:admin2_code":"801.0",
    "gn:admin3_code":"80102.0",
    "gn:asciiname":"Podjenin",
    "gn:country_code":"PL",
    "gn:dem":18,
    "gn:feature_class":"P",
    "gn:feature_code":"PPL",
    "gn:name":"Podjenin",
    "gn:population":0,
    "gn:timezone":"Europe/Warsaw",
    "iso:country":"PL",
    "name:ceb_x_preferred":[
        "Podjenin"
    ],
    "name:deu_x_historical":[
        "Unter Gennin"
    ],
    "name:deu_x_preferred":[
        "Unter Gennin"
    ],
    "name:fra_x_preferred":[
        "Podjenin"
    ],
    "name:pol_x_preferred":[
        "Podjenin"
    ],
    "name:ukr_x_preferred":[
        "\u041f\u043e\u0434\u0454\u043d\u0456\u043d"
    ],
    "wof:name":"Podjenin",
    "wof:placetype":"locality"
},
  "geometry": {"coordinates":[15.05442,52.65669000000001],"type":"Point"}
}