{
  "type": "Feature",
  "properties": {
    "gn:country":"PL",
    "gn:fcode":"PPL",
    "gn:population":330,
    "iso:country":"PL",
    "name:ast_x_preferred":[
        "Sul\u0119cin Szlachecki"
    ],
    "name:ceb_x_preferred":[
        "Sul\u0119cin Szlachecki"
    ],
    "name:eng_x_preferred":[
        "Sul\u0119cin"
    ],
    "name:eng_x_variant":[
        "Sul\u0119cin Szlachecki"
    ],
    "name:fra_x_preferred":[
        "Sul\u0119cin Szlachecki"
    ],
    "name:pol_x_preferred":[
        "Sul\u0119cin Szlachecki"
    ],
    "name:rus_x_preferred":[
        "\u0421\u0443\u043b\u0435\u043d\u0446\u0438\u043d"
    ],
    "name:ukr_x_preferred":[
        "\u0421\u0443\u043b\u0435\u043d\u0446\u0438\u043d-\u0428\u043b\u044f\u0445\u0435\u0446\u044c\u043a\u0438\u0439"
    ],
    "qs_pg:aaroncc":"PL",
    "qs_pg:gn_country":"PL",
    "qs_pg:gn_fcode":"PPL",
    "qs_pg:gn_pop":330,
    "qs_pg:name":"Sul\u0119cin Szlachecki",
    "qs_pg:photos_9r":0,
    "qs_pg:photos_sr":0,
    "qs_pg:pop_sr":2,
    "qs_pg:qs_pg_placetype":"locality",
    "wof:name":"Sul\u0119cin Szlachecki",
    "wof:placetype":"locality",
    "wof:population":330
},
  "geometry": {"coordinates":[21.88185,52.88379],"type":"Point"}
}