{
  "type": "Feature",
  "properties": {
    "gn:admin1_code":"86.0",
    "gn:admin2_code":"3007.0",
    "gn:admin3_code":"300702.0",
    "gn:asciiname":"Rozenno",
    "gn:country_code":"PL",
    "gn:dem":162,
    "gn:feature_class":"P",
    "gn:feature_code":"PPL",
    "gn:name":"Ro\u017cenno",
    "gn:population":0,
    "gn:timezone":"Europe/Warsaw",
    "iso:country":"PL",
    "name:pol_x_preferred":[
        "Ro\u017cenno"
    ],
    "name:ukr_x_preferred":[
        "\u0420\u043e\u0436\u0435\u043d\u043d\u043e"
    ],
    "wof:name":"Rozenno",
    "wof:placetype":"locality"
},
  "geometry": {"coordinates":[18.36039,51.58464],"type":"Point"}
}