{
  "type": "Feature",
  "properties": {
    "gn:gn_country":"PL",
    "gn:gn_fcode":"PPL",
    "gn:gn_pop":669,
    "gn:population":669,
    "iso:country":"PL",
    "name:eng_x_preferred":[
        "Bukowiec Opoczy\u0144ski"
    ],
    "name:fra_x_preferred":[
        "Bukowiec Opoczy\u0144ski"
    ],
    "name:nan_x_preferred":[
        "Bukowiec Opoczy\u0144ski"
    ],
    "name:pol_x_preferred":[
        "Bukowiec Opoczy\u0144ski"
    ],
    "qs_pg:aaroncc":"PL",
    "qs_pg:gn_country":"PL",
    "qs_pg:gn_fcode":"PPL",
    "qs_pg:gn_pop":669,
    "qs_pg:name":"Bukowiec Opoczy\u0144ski",
    "qs_pg:name_adm0":"Polska",
    "qs_pg:name_adm1":"\u0141\u00f3dzkie",
    "qs_pg:photos_9r":0,
    "qs_pg:photos_sr":0,
    "qs_pg:pop_sr":2,
    "qs_pg:qs_pg_placetype":"locality",
    "qs_pg:qs_pg_placetype_gp":"Town",
    "qs_pg:woe_adm0":23424923,
    "woe:adm0_id":23424923,
    "woe:name_adm0":"Polska",
    "woe:name_adm1":"\u0141\u00f3dzkie",
    "woe:placetype":"Town",
    "wof:name":"Bukowiec Opoczy\u0144ski",
    "wof:placetype":"locality",
    "wof:population":669
},
  "geometry": {"coordinates":[20.26583,51.41682],"type":"Point"}
}