{
  "type": "Feature",
  "properties": {
    "gn:admin1_code":"81.0",
    "gn:admin2_code":"2062.0",
    "gn:admin3_code":"206201.0",
    "gn:asciiname":"Zawady",
    "gn:country_code":"PL",
    "gn:dem":137,
    "gn:feature_class":"P",
    "gn:feature_code":"PPL",
    "gn:name":"Zawady",
    "gn:population":0,
    "gn:timezone":"Europe/Warsaw",
    "iso:country":"PL",
    "wof:name":"Zawady",
    "wof:placetype":"locality"
},
  "geometry": {"coordinates":[22.08333,53.16667],"type":"Point"}
}