{
  "type": "Feature",
  "properties": {
    "gn:country":"PL",
    "gn:fcode":"PPLA3",
    "gn:population":2200,
    "iso:country":"PL",
    "name:azb_x_preferred":[
        "\u0632\u0627\u0646\u0642\u0645\u0634\u0644"
    ],
    "name:deu_x_preferred":[
        "Zaniemy\u015bl"
    ],
    "name:fas_x_preferred":[
        "\u0632\u0627\u0646\u06af\u0645\u0634\u0644"
    ],
    "name:fra_x_preferred":[
        "Zaniemy\u015bl"
    ],
    "name:nld_x_preferred":[
        "Zaniemy\u015bl"
    ],
    "name:pol_x_preferred":[
        "Zaniemy\u015bl"
    ],
    "name:ukr_x_preferred":[
        "\u0417\u0430\u043d\u0435\u043c\u0438\u0441\u043b\u044c"
    ],
    "qs_pg:aaroncc":"PL",
    "qs_pg:gn_country":"PL",
    "qs_pg:gn_fcode":"PPLA3",
    "qs_pg:gn_pop":2200,
    "qs_pg:name":"Zaniemy\u015bl",
    "qs_pg:name_adm0":"Polska",
    "qs_pg:name_adm1":"Wielkopolskie",
    "qs_pg:photos":5,
    "qs_pg:photos_1k":1,
    "qs_pg:photos_9k":1,
    "qs_pg:photos_9r":1,
    "qs_pg:photos_all":5,
    "qs_pg:photos_sr":1,
    "qs_pg:pop_sr":4,
    "qs_pg:qs_pg_placetype":"localadmin",
    "qs_pg:qs_pg_placetype_gp":"LocalAdmin",
    "qs_pg:woe_adm0":23424923,
    "woe:adm0_id":23424923,
    "woe:name_adm0":"Polska",
    "woe:name_adm1":"Wielkopolskie",
    "woe:placetype":"LocalAdmin",
    "wof:name":"Zaniemy\u015bl",
    "wof:placetype":"localadmin",
    "wof:population":2200
},
  "geometry": {"coordinates":[17.16228,52.15561],"type":"Point"}
}