{
  "type": "Feature",
  "properties": {
    "gn:country":"PL",
    "gn:fcode":"PPLA3",
    "gn:population":8452,
    "iso:country":"PL",
    "name:ceb_x_preferred":[
        "Jastrowie"
    ],
    "name:csb_x_preferred":[
        "Jastrowi\u00e9"
    ],
    "name:deu_x_preferred":[
        "Jastrow"
    ],
    "name:deu_x_variant":[
        "Jastrowie"
    ],
    "name:epo_x_preferred":[
        "Jastrowie"
    ],
    "name:fra_x_preferred":[
        "Jastrowie"
    ],
    "name:jav_x_preferred":[
        "Jastrowie"
    ],
    "name:lav_x_preferred":[
        "Jastrove"
    ],
    "name:lit_x_preferred":[
        "Jastrov\u0117"
    ],
    "name:msa_x_preferred":[
        "Jastrowie"
    ],
    "name:nld_x_preferred":[
        "Jastrowie"
    ],
    "name:pol_x_preferred":[
        "Jastrowie"
    ],
    "name:por_x_preferred":[
        "Jastrowie"
    ],
    "name:ron_x_preferred":[
        "Jastrowie"
    ],
    "name:rus_x_preferred":[
        "\u042f\u0441\u0442\u0440\u043e\u0432\u0435"
    ],
    "name:slk_x_preferred":[
        "Jastrowie"
    ],
    "name:srp_x_preferred":[
        "\u0408\u0430\u0441\u0442\u0440\u043e\u0432\u0458\u0435"
    ],
    "name:swe_x_preferred":[
        "Jastrowie"
    ],
    "name:ukr_x_preferred":[
        "\u042f\u0441\u0442\u0440\u043e\u0432\u0435"
    ],
    "name:urd_x_preferred":[
        "\u062c\u0633\u062a\u0631\u0648\u0648\u0626\u06d2"
    ],
    "name:vie_x_preferred":[
        "Jastrowie"
    ],
    "name:zho_x_preferred":[
        "\u4e9e\u65af\u7279\u7f85\u7dad"
    ],
    "qs_pg:aaroncc":"PL",
    "qs_pg:gn_country":"PL",
    "qs_pg:gn_fcode":"PPLA3",
    "qs_pg:gn_pop":8452,
    "qs_pg:name":"Jastrowie",
    "qs_pg:name_adm0":"Polska",
    "qs_pg:name_adm1":"Wielkopolskie",
    "qs_pg:photos_9r":0,
    "qs_pg:photos_sr":0,
    "qs_pg:pop_sr":5,
    "qs_pg:qs_pg_placetype":"localadmin",
    "qs_pg:qs_pg_placetype_gp":"LocalAdmin",
    "qs_pg:woe_adm0":23424923,
    "woe:adm0_id":23424923,
    "woe:name_adm0":"Polska",
    "woe:name_adm1":"Wielkopolskie",
    "woe:placetype":"LocalAdmin",
    "wof:name":"Jastrowie",
    "wof:placetype":"localadmin",
    "wof:population":8452
},
  "geometry": {"coordinates":[16.81756,53.42048],"type":"Point"}
}