{
  "type": "Feature",
  "properties": {
    "gn:admin1_code":"82.0",
    "gn:admin2_code":"2214.0",
    "gn:admin3_code":"221406.0",
    "gn:asciiname":"Turze",
    "gn:country_code":"PL",
    "gn:dem":69,
    "gn:feature_class":"P",
    "gn:feature_code":"PPL",
    "gn:name":"Turze",
    "gn:population":0,
    "gn:timezone":"Europe/Warsaw",
    "iso:country":"PL",
    "wof:name":"Turze",
    "wof:placetype":"locality"
},
  "geometry": {"coordinates":[18.62896,54.09571999999999],"type":"Point"}
}