{
  "type": "Feature",
  "properties": {
    "gn:population":1429,
    "iso:country":"PL",
    "name:azb_x_preferred":[
        "\u0642\u0645\u06cc\u0646\u0627 \u067e\u0648\u0644\u0633\u06a9\u0627 \u062a\u0633\u0631\u06a9\u06cc\u0648"
    ],
    "name:bel_x_preferred":[
        "\u0413\u043c\u0456\u043d\u0430 \u041f\u043e\u043b\u044c\u0441\u043a\u0430 \u0426\u044d\u0440\u044d\u043a\u0435\u045e"
    ],
    "name:ceb_x_preferred":[
        "Polska Cerekiew"
    ],
    "name:deu_x_preferred":[
        "Gemeinde Gro\u00df Neukirch"
    ],
    "name:eng_x_preferred":[
        "Gmina Polska Cerekiew"
    ],
    "name:eus_x_preferred":[
        "Polska Cerekiew udalerria"
    ],
    "name:fas_x_preferred":[
        "\u06af\u0645\u06cc\u0646\u0627 \u067e\u0648\u0644\u0633\u06a9\u0627 \u062a\u0633\u0631\u06a9\u06cc\u0648"
    ],
    "name:fra_x_preferred":[
        "Polska Cerekiew"
    ],
    "name:ita_x_preferred":[
        "Polska Cerekiew"
    ],
    "name:nan_x_preferred":[
        "Polska Cerekiew"
    ],
    "name:nld_x_preferred":[
        "Polska Cerekiew"
    ],
    "name:pol_x_preferred":[
        "Polska Cerekiew"
    ],
    "name:por_x_preferred":[
        "Comuna de Polska Cerekiew"
    ],
    "name:rus_x_preferred":[
        "\u041f\u043e\u043b\u044c\u0441\u043a\u0430-\u0426\u0435\u0440\u0435\u043a\u0435\u0432"
    ],
    "name:slk_x_preferred":[
        "Gmina Polska Cerekiew"
    ],
    "name:ukr_x_preferred":[
        "\u0490\u043c\u0456\u043d\u0430 \u041f\u043e\u043b\u044c\u0441\u044c\u043a\u0430 \u0426\u0435\u0440\u0435\u043a\u0435\u0432"
    ],
    "name:und_x_variant":[
        "Cerkiew Polska"
    ],
    "name:war_x_preferred":[
        "Gmina Polska Cerekiew"
    ],
    "name:zho_min_nan_x_preferred":[
        "Polska Cerekiew"
    ],
    "qs:a0":"Rzeczpospolita Polska",
    "qs:a1":"*Opolskie",
    "qs:a1r":"0",
    "qs:a2":"Kedzierzynsko-kozielski",
    "qs:adm0":"Rzeczpospolita Polska",
    "qs:la":"Polska Cerekiew",
    "qs:la_lc":"*PL1603052",
    "qs:level":"locality",
    "qs:loc":"Polska Cerekiew",
    "qs:loc_alt":"Polska Cerekiew",
    "qs:pop":0,
    "qs:type":"rural point-in-poly",
    "wd:wordcount":179,
    "wof:name":"Polska Cerekiew",
    "wof:placetype":"locality",
    "wof:population":1429
},
  "geometry": {"coordinates":[18.1276747149538,50.2182821102437],"type":"Point"}
}