{
  "type": "Feature",
  "properties": {
    "gn:admin1_code":"81.0",
    "gn:admin2_code":"2012.0",
    "gn:admin3_code":"201204.0",
    "gn:asciiname":"Zarzecze",
    "gn:country_code":"PL",
    "gn:dem":257,
    "gn:feature_class":"P",
    "gn:feature_code":"PPL",
    "gn:name":"Zarzecze",
    "gn:population":0,
    "gn:timezone":"Europe/Warsaw",
    "iso:country":"PL",
    "wof:name":"Zarzecze",
    "wof:placetype":"locality"
},
  "geometry": {"coordinates":[22.74874,54.27064],"type":"Point"}
}