{
  "type": "Feature",
  "properties": {
    "gn:admin1_code":"84.0",
    "gn:admin2_code":"2603.0",
    "gn:admin3_code":"260303.0",
    "gn:asciiname":"Gorzkow",
    "gn:country_code":"PL",
    "gn:dem":263,
    "gn:feature_class":"P",
    "gn:feature_code":"PPL",
    "gn:name":"Gorzk\u00f3w",
    "gn:population":0,
    "gn:timezone":"Europe/Warsaw",
    "iso:country":"PL",
    "name:pol_x_preferred":[
        "Gorzk\u00f3w"
    ],
    "name:ukr_x_preferred":[
        "\u0490\u043e\u0436\u043a\u0443\u0432"
    ],
    "wof:name":"Gorzkow",
    "wof:placetype":"locality"
},
  "geometry": {"coordinates":[20.50701,50.22217],"type":"Point"}
}