{
  "type": "Feature",
  "properties": {
    "gn:admin1_code":"72.0",
    "gn:admin2_code":"226.0",
    "gn:admin3_code":"22606.0",
    "gn:asciiname":"Czartkowice",
    "gn:country_code":"PL",
    "gn:dem":181,
    "gn:feature_class":"P",
    "gn:feature_code":"PPL",
    "gn:name":"Czartkowice",
    "gn:population":0,
    "gn:timezone":"Europe/Warsaw",
    "iso:country":"PL",
    "wof:name":"Czartkowice",
    "wof:placetype":"locality"
},
  "geometry": {"coordinates":[15.96794,51.16597],"type":"Point"}
}