{
  "type": "Feature",
  "properties": {
    "gn:admin1_code":"75.0",
    "gn:admin2_code":"601.0",
    "gn:admin3_code":"60114.0",
    "gn:asciiname":"Zankow",
    "gn:country_code":"PL",
    "gn:dem":155,
    "gn:feature_class":"P",
    "gn:feature_code":"PPL",
    "gn:name":"Za\u0144k\u00f3w",
    "gn:population":0,
    "gn:timezone":"Europe/Warsaw",
    "iso:country":"PL",
    "name:fra_x_preferred":[
        "Za\u0144k\u00f3w"
    ],
    "name:lit_x_preferred":[
        "Zankuvas"
    ],
    "name:pol_x_preferred":[
        "Za\u0144k\u00f3w"
    ],
    "name:ukr_x_preferred":[
        "\u0417\u0430\u043d\u044c\u043a\u0443\u0432"
    ],
    "wof:name":"Zankow",
    "wof:placetype":"locality"
},
  "geometry": {"coordinates":[23.52178,51.80944],"type":"Point"}
}