{
  "type": "Feature",
  "properties": {
    "gn:admin1_code":"86.0",
    "gn:admin2_code":"3012.0",
    "gn:admin3_code":"301204.0",
    "gn:asciiname":"Rozopole",
    "gn:country_code":"PL",
    "gn:dem":152,
    "gn:feature_class":"P",
    "gn:feature_code":"PPL",
    "gn:name":"R\u00f3\u017copole",
    "gn:population":0,
    "gn:timezone":"Europe/Warsaw",
    "iso:country":"PL",
    "name:fra_x_preferred":[
        "R\u00f3\u017copole"
    ],
    "name:pol_x_preferred":[
        "R\u00f3\u017copole"
    ],
    "name:ukr_x_preferred":[
        "\u0420\u0443\u0436\u043e\u043f\u043e\u043b\u0435"
    ],
    "wof:name":"Rozopole",
    "wof:placetype":"locality"
},
  "geometry": {"coordinates":[17.52016,51.72549],"type":"Point"}
}