{
  "type": "Feature",
  "properties": {
    "gn:admin1_code":"87.0",
    "gn:admin2_code":"3205.0",
    "gn:admin3_code":"320504.0",
    "gn:asciiname":"Sowno",
    "gn:country_code":"PL",
    "gn:dem":39,
    "gn:feature_class":"P",
    "gn:feature_code":"PPL",
    "gn:name":"Sowno",
    "gn:population":0,
    "gn:timezone":"Europe/Warsaw",
    "iso:country":"PL",
    "name:pol_x_preferred":[
        "Sowno"
    ],
    "name:ukr_x_preferred":[
        "\u0421\u043e\u0432\u043d\u043e"
    ],
    "name:vie_x_preferred":[
        "Sowno"
    ],
    "wof:name":"Sowno",
    "wof:placetype":"locality"
},
  "geometry": {"coordinates":[15.20662,53.80591999999999],"type":"Point"}
}