{
  "type": "Feature",
  "properties": {
    "gn:admin1_code":"75.0",
    "gn:admin2_code":"616.0",
    "gn:admin3_code":"61601.0",
    "gn:asciiname":"Masow",
    "gn:country_code":"PL",
    "gn:dem":115,
    "gn:feature_class":"P",
    "gn:feature_code":"PPL",
    "gn:name":"Mas\u00f3w",
    "gn:population":0,
    "gn:timezone":"Europe/Warsaw",
    "iso:country":"PL",
    "wof:name":"Masow",
    "wof:placetype":"locality"
},
  "geometry": {"coordinates":[21.88347000000001,51.54019],"type":"Point"}
}