{
  "type": "Feature",
  "properties": {
    "gn:admin1_code":"78.0",
    "gn:admin2_code":"1429.0",
    "gn:admin3_code":"142909.0",
    "gn:asciiname":"Dziecioly",
    "gn:country_code":"PL",
    "gn:dem":113,
    "gn:feature_class":"P",
    "gn:feature_code":"PPL",
    "gn:name":"Dzi\u0119cio\u0142y",
    "gn:population":0,
    "gn:timezone":"Europe/Warsaw",
    "iso:country":"PL",
    "wof:name":"Dziecioly",
    "wof:placetype":"locality"
},
  "geometry": {"coordinates":[22.29325,52.59614000000001],"type":"Point"}
}