{
  "type": "Feature",
  "properties": {
    "gn:country":"PL",
    "gn:fcode":"PPL",
    "gn:population":309,
    "iso:country":"PL",
    "name:ast_x_preferred":[
        "Strumiany"
    ],
    "name:eng_x_preferred":[
        "Strumiany"
    ],
    "name:fra_x_preferred":[
        "Strumiany"
    ],
    "name:pol_x_preferred":[
        "Strumiany"
    ],
    "name:ukr_x_preferred":[
        "\u0421\u0442\u0440\u0443\u043c\u044f\u043d\u0438"
    ],
    "qs_pg:aaroncc":"PL",
    "qs_pg:gn_country":"PL",
    "qs_pg:gn_fcode":"PPL",
    "qs_pg:gn_pop":309,
    "qs_pg:name":"Strumiany",
    "qs_pg:name_adm0":"Polska",
    "qs_pg:name_adm1":"Ma\u0142opolskie",
    "qs_pg:photos_9k":1,
    "qs_pg:photos_9r":1,
    "qs_pg:photos_all":2,
    "qs_pg:photos_sr":0,
    "qs_pg:pop_sr":2,
    "qs_pg:qs_pg_placetype":"locality",
    "qs_pg:qs_pg_placetype_gp":"Town",
    "qs_pg:woe_adm0":23424923,
    "woe:adm0_id":23424923,
    "woe:name_adm0":"Polska",
    "woe:name_adm1":"Ma\u0142opolskie",
    "woe:placetype":"Town",
    "wof:name":"Strumiany",
    "wof:placetype":"neighbourhood",
    "wof:population":309
},
  "geometry": {"coordinates":[20.09356,50.01386],"type":"Point"}
}