{
  "type": "Feature",
  "properties": {
    "gn:admin1_code":"83.0",
    "gn:admin2_code":"2414.0",
    "gn:admin3_code":"241404.0",
    "gn:asciiname":"Bojszowy Dolne",
    "gn:country_code":"PL",
    "gn:dem":233,
    "gn:feature_class":"P",
    "gn:feature_code":"PPL",
    "gn:name":"Bojszowy Dolne",
    "gn:population":0,
    "gn:timezone":"Europe/Warsaw",
    "iso:country":"PL",
    "wof:name":"Bojszowy Dolne",
    "wof:placetype":"neighbourhood"
},
  "geometry": {"coordinates":[19.10938,50.05525],"type":"Point"}
}