{
  "type": "Feature",
  "properties": {
    "gn:admin1_code":"78.0",
    "gn:admin2_code":"1406.0",
    "gn:admin3_code":"140601.0",
    "gn:asciiname":"Belsk Maly",
    "gn:country_code":"PL",
    "gn:dem":180,
    "gn:feature_class":"P",
    "gn:feature_code":"PPL",
    "gn:name":"Belsk Ma\u0142y",
    "gn:population":0,
    "gn:timezone":"Europe/Warsaw",
    "iso:country":"PL",
    "name:fra_x_preferred":[
        "Belsk Ma\u0142y"
    ],
    "name:pol_x_preferred":[
        "Belsk Ma\u0142y"
    ],
    "name:ukr_x_preferred":[
        "\u0411\u0435\u043b\u044c\u0441\u044c\u043a-\u041c\u0430\u043b\u0438\u0439"
    ],
    "name:und_x_variant":[
        "Belsk Ma\u0142y"
    ],
    "wof:name":"Belsk Maly",
    "wof:placetype":"locality"
},
  "geometry": {"coordinates":[20.81658,51.83927],"type":"Point"}
}