{
  "type": "Feature",
  "properties": {
    "gn:admin1_code":"80.0",
    "gn:admin2_code":"1814.0",
    "gn:admin3_code":"181405.0",
    "gn:asciiname":"Chodakowka",
    "gn:country_code":"PL",
    "gn:dem":275,
    "gn:feature_class":"P",
    "gn:feature_code":"PPL",
    "gn:name":"Chodak\u00f3wka",
    "gn:population":0,
    "gn:timezone":"Europe/Warsaw",
    "iso:country":"PL",
    "name:ceb_x_preferred":[
        "Chodak\u00f3wka"
    ],
    "name:nld_x_preferred":[
        "Chodak\u00f3wka"
    ],
    "name:pol_x_preferred":[
        "Chodak\u00f3wka"
    ],
    "name:ukr_x_preferred":[
        "\u0425\u043e\u0434\u0430\u043a\u0443\u0432\u043a\u0430"
    ],
    "wof:name":"Chodakowka",
    "wof:placetype":"locality"
},
  "geometry": {"coordinates":[22.32708,49.98089],"type":"Point"}
}