{
  "type": "Feature",
  "properties": {
    "gn:admin1_code":"80.0",
    "gn:admin2_code":"1814.0",
    "gn:admin3_code":"181405.0",
    "gn:asciiname":"Chodakowka",
    "gn:country_code":"PL",
    "gn:dem":275,
    "gn:feature_class":"P",
    "gn:feature_code":"PPL",
    "gn:name":"Chodak\u00f3wka",
    "gn:population":0,
    "gn:timezone":"Europe/Warsaw",
    "iso:country":"PL",
    "name:und_x_variant":[
        "Chodak\u00f3wka"
    ],
    "wof:name":"Chodakowka",
    "wof:placetype":"locality"
},
  "geometry": {"coordinates":[22.32708,49.98089],"type":"Point"}
}