{
  "type": "Feature",
  "properties": {
    "gn:admin1_code":"77.0",
    "gn:admin2_code":"1214.0",
    "gn:admin3_code":"121405.0",
    "gn:asciiname":"Kadzice",
    "gn:country_code":"PL",
    "gn:dem":236,
    "gn:feature_class":"P",
    "gn:feature_code":"PPL",
    "gn:name":"Kadzice",
    "gn:population":0,
    "gn:timezone":"Europe/Warsaw",
    "iso:country":"PL",
    "name:pol_x_preferred":[
        "Kadzice"
    ],
    "name:ukr_x_preferred":[
        "\u041a\u0430\u0434\u0437\u0456\u0446\u0435"
    ],
    "wof:name":"Kadzice",
    "wof:placetype":"locality"
},
  "geometry": {"coordinates":[20.36007,50.24556],"type":"Point"}
}