{
  "type": "Feature",
  "properties": {
    "iso:country":"PL",
    "name:pol_x_preferred":[
        "Nowe W\u0142ochy"
    ],
    "wof:name":"Nowe Wlochy",
    "wof:placetype":"neighbourhood"
},
  "geometry": {"coordinates":[20.90411250126545,52.20842137163412],"type":"Point"}
}