{
  "type": "Feature",
  "properties": {
    "gn:admin1_code":"87.0",
    "gn:admin2_code":"3209.0",
    "gn:admin3_code":"320906.0",
    "gn:asciiname":"Dadzewo",
    "gn:country_code":"PL",
    "gn:dem":136,
    "gn:feature_class":"P",
    "gn:feature_code":"PPL",
    "gn:name":"Dadzewo",
    "gn:population":0,
    "gn:timezone":"Europe/Warsaw",
    "iso:country":"PL",
    "name:azb_x_preferred":[
        "\u062f\u0627\u0632\u0648\u0648"
    ],
    "name:ceb_x_preferred":[
        "Dadzewo"
    ],
    "name:deu_x_preferred":[
        "Dadzewo"
    ],
    "name:fas_x_preferred":[
        "\u062f\u0627\u0632\u0648\u0648"
    ],
    "name:pol_x_preferred":[
        "Dadzewo"
    ],
    "name:ukr_x_preferred":[
        "\u0414\u0430\u0434\u0437\u0435\u0432\u043e"
    ],
    "name:vie_x_preferred":[
        "Dadzewo"
    ],
    "wof:name":"Dadzewo",
    "wof:placetype":"locality"
},
  "geometry": {"coordinates":[16.58585,54.12821],"type":"Point"}
}