{
  "type": "Feature",
  "properties": {
    "gn:admin1_code":"87.0",
    "gn:admin2_code":"3209.0",
    "gn:admin3_code":"320906.0",
    "gn:asciiname":"Dadzewo",
    "gn:country_code":"PL",
    "gn:dem":136,
    "gn:feature_class":"P",
    "gn:feature_code":"PPL",
    "gn:name":"Dadzewo",
    "gn:population":0,
    "gn:timezone":"Europe/Warsaw",
    "iso:country":"PL",
    "wof:name":"Dadzewo",
    "wof:placetype":"locality"
},
  "geometry": {"coordinates":[16.58585,54.12821],"type":"Point"}
}