{
  "type": "Feature",
  "properties": {
    "gn:admin1_code":"72.0",
    "gn:admin2_code":"224.0",
    "gn:admin3_code":"22403.0",
    "gn:asciiname":"Deborog",
    "gn:cc2":"PL",
    "gn:country_code":"PL",
    "gn:dem":253,
    "gn:feature_class":"P",
    "gn:feature_code":"PPL",
    "gn:name":"D\u0119bor\u00f3g",
    "gn:population":0,
    "gn:timezone":"Europe/Warsaw",
    "iso:country":"PL",
    "name:und_x_variant":[
        "Eichvorwerk",
        "D\u0119bor\u00f3g"
    ],
    "wof:name":"Deborog",
    "wof:placetype":"locality"
},
  "geometry": {"coordinates":[16.86667000000001,50.53333],"type":"Point"}
}