{
  "type": "Feature",
  "properties": {
    "gn:admin1_code":"80.0",
    "gn:admin2_code":"1807.0",
    "gn:admin3_code":"180701.0",
    "gn:asciiname":"Szczepancowa",
    "gn:country_code":"PL",
    "gn:dem":280,
    "gn:feature_class":"P",
    "gn:feature_code":"PPL",
    "gn:name":"Szczepa\u0144cowa",
    "gn:population":0,
    "gn:timezone":"Europe/Warsaw",
    "iso:country":"PL",
    "name:ceb_x_preferred":[
        "Szczepa\u0144cowa"
    ],
    "name:nld_x_preferred":[
        "Szczepa\u0144cowa"
    ],
    "name:pol_x_preferred":[
        "Szczepa\u0144cowa"
    ],
    "name:ukr_x_preferred":[
        "\u0429\u0435\u043f\u0430\u043d\u044c\u0446\u043e\u0432\u0430"
    ],
    "wof:name":"Szczepancowa",
    "wof:placetype":"locality"
},
  "geometry": {"coordinates":[21.71619,49.66474],"type":"Point"}
}