{
  "type": "Feature",
  "properties": {
    "gn:admin1_code":"86.0",
    "gn:admin2_code":"3007.0",
    "gn:admin3_code":"300705.0",
    "gn:asciiname":"Chodybki",
    "gn:country_code":"PL",
    "gn:dem":138,
    "gn:feature_class":"P",
    "gn:feature_code":"PPL",
    "gn:name":"Chodybki",
    "gn:population":0,
    "gn:timezone":"Europe/Warsaw",
    "iso:country":"PL",
    "name:pol_x_preferred":[
        "Chodybki"
    ],
    "name:ukr_x_preferred":[
        "\u0425\u043e\u0434\u0438\u0431\u043a\u0456"
    ],
    "wof:name":"Chodybki",
    "wof:placetype":"locality"
},
  "geometry": {"coordinates":[18.38202,51.80103],"type":"Point"}
}