{
  "type": "Feature",
  "properties": {
    "gn:admin1_code":"72.0",
    "gn:admin2_code":"218.0",
    "gn:admin3_code":"21802.0",
    "gn:asciiname":"Rachow",
    "gn:country_code":"PL",
    "gn:dem":136,
    "gn:feature_class":"P",
    "gn:feature_code":"PPL",
    "gn:name":"Rach\u00f3w",
    "gn:population":0,
    "gn:timezone":"Europe/Warsaw",
    "iso:country":"PL",
    "name:pol_x_preferred":[
        "Rach\u00f3w"
    ],
    "name:ukr_x_preferred":[
        "\u0420\u0430\u0445\u0443\u0432"
    ],
    "wof:name":"Rachow",
    "wof:placetype":"locality"
},
  "geometry": {"coordinates":[16.50807,51.20011],"type":"Point"}
}