{
  "type": "Feature",
  "properties": {
    "gn:admin1_code":"79.0",
    "gn:admin2_code":"1606.0",
    "gn:admin3_code":"160603.0",
    "gn:asciiname":"Krogulna",
    "gn:country_code":"PL",
    "gn:dem":152,
    "gn:feature_class":"P",
    "gn:feature_code":"PPL",
    "gn:name":"Krogulna",
    "gn:population":0,
    "gn:timezone":"Europe/Warsaw",
    "iso:country":"PL",
    "name:azb_x_preferred":[
        "\u06a9\u0631\u0648\u0642\u0648\u0644\u0646\u0627"
    ],
    "name:deu_x_preferred":[
        "Krogulna"
    ],
    "name:fas_x_preferred":[
        "\u06a9\u0631\u0648\u06af\u0648\u0644\u0646\u0627"
    ],
    "name:pol_x_preferred":[
        "Krogulna"
    ],
    "name:szl_x_preferred":[
        "Krogulno"
    ],
    "name:ukr_x_preferred":[
        "\u041a\u0440\u043e\u0491\u0443\u043b\u044c\u043d\u0430"
    ],
    "wof:name":"Krogulna",
    "wof:placetype":"locality"
},
  "geometry": {"coordinates":[17.7949,50.92718],"type":"Point"}
}