{
  "type": "Feature",
  "properties": {
    "gn:admin1_code":"79.0",
    "gn:admin2_code":"1606.0",
    "gn:admin3_code":"160603.0",
    "gn:asciiname":"Krogulna",
    "gn:country_code":"PL",
    "gn:dem":152,
    "gn:feature_class":"P",
    "gn:feature_code":"PPL",
    "gn:name":"Krogulna",
    "gn:population":0,
    "gn:timezone":"Europe/Warsaw",
    "iso:country":"PL",
    "wof:name":"Krogulna",
    "wof:placetype":"locality"
},
  "geometry": {"coordinates":[17.7949,50.92718],"type":"Point"}
}