{
  "type": "Feature",
  "properties": {
    "gn:admin1_code":"75.0",
    "gn:admin2_code":"615.0",
    "gn:admin3_code":"61506.0",
    "gn:asciiname":"Jaski",
    "gn:country_code":"PL",
    "gn:dem":154,
    "gn:feature_class":"P",
    "gn:feature_code":"PPL",
    "gn:name":"Ja\u015bki",
    "gn:population":0,
    "gn:timezone":"Europe/Warsaw",
    "iso:country":"PL",
    "name:und_x_variant":[
        "Ja\u015bki"
    ],
    "wof:name":"Jaski",
    "wof:placetype":"locality"
},
  "geometry": {"coordinates":[22.5991,51.85775],"type":"Point"}
}