{
  "type": "Feature",
  "properties": {
    "gn:admin1_code":"74.0",
    "gn:admin2_code":"1002.0",
    "gn:admin3_code":"100202.0",
    "gn:asciiname":"Stradzew Gorki",
    "gn:country_code":"PL",
    "gn:dem":100,
    "gn:feature_class":"P",
    "gn:feature_code":"PPL",
    "gn:name":"Stradzew G\u00f3rki",
    "gn:population":0,
    "gn:timezone":"Europe/Warsaw",
    "iso:country":"PL",
    "name:und_x_variant":[
        "G\u00f3rki Stradzewskie",
        "Stradzew G\u00f3rki"
    ],
    "wof:name":"Stradzew Gorki",
    "wof:placetype":"locality"
},
  "geometry": {"coordinates":[19.58288,52.16475],"type":"Point"}
}