{
  "type": "Feature",
  "properties": {
    "gn:admin1_code":"87.0",
    "gn:admin2_code":"3209.0",
    "gn:admin3_code":"320905.0",
    "gn:asciiname":"Mielno",
    "gn:cc2":"PL",
    "gn:country_code":"PL",
    "gn:dem":4,
    "gn:feature_class":"P",
    "gn:feature_code":"PPL",
    "gn:name":"Mielno",
    "gn:population":2184,
    "gn:timezone":"Europe/Warsaw",
    "iso:country":"PL",
    "name:deu_x_preferred":[
        "Mielno"
    ],
    "name:epo_x_preferred":[
        "Mielno"
    ],
    "name:fra_x_preferred":[
        "Mielno"
    ],
    "name:ita_x_preferred":[
        "Mielno"
    ],
    "name:nld_x_preferred":[
        "Mielno"
    ],
    "name:pol_x_preferred":[
        "Mielno"
    ],
    "name:rus_x_preferred":[
        "\u041c\u0435\u043b\u044c\u043d\u043e"
    ],
    "name:ukr_x_preferred":[
        "\u041c\u0435\u043b\u044c\u043d\u043e"
    ],
    "name:und_x_variant":[
        "Grossm\u00f6llen",
        "Mielno Koszali\u0144skie",
        "Grossm\u00f6llen \u00fcber K\u00f6slin"
    ],
    "name:vie_x_preferred":[
        "Mielno"
    ],
    "wof:name":"Mielno",
    "wof:placetype":"locality",
    "wof:population":2184
},
  "geometry": {"coordinates":[16.0621,54.26086],"type":"Point"}
}