{
  "type": "Feature",
  "properties": {
    "gn:admin1_code":"82.0",
    "gn:admin2_code":"2216.0",
    "gn:admin3_code":"221601.0",
    "gn:asciiname":"Jasna",
    "gn:cc2":"PL",
    "gn:country_code":"PL",
    "gn:dem":6,
    "gn:feature_class":"P",
    "gn:feature_code":"PPL",
    "gn:name":"Jasna",
    "gn:population":0,
    "gn:timezone":"Europe/Warsaw",
    "iso:country":"PL",
    "name:azb_x_preferred":[
        "\u06cc\u0627\u0633\u0646\u0627"
    ],
    "name:ceb_x_preferred":[
        "Jasna"
    ],
    "name:fas_x_preferred":[
        "\u06cc\u0627\u0633\u0646\u0627"
    ],
    "name:nld_x_preferred":[
        "Jasna"
    ],
    "name:pol_x_preferred":[
        "Jasna"
    ],
    "name:ukr_x_preferred":[
        "\u042f\u0441\u043d\u0430"
    ],
    "name:und_x_variant":[
        "Lichtfelde"
    ],
    "name:urd_x_preferred":[
        "\u062c\u0633\u0646\u0627"
    ],
    "wof:name":"Jasna",
    "wof:placetype":"locality"
},
  "geometry": {"coordinates":[19.30521,54.00767],"type":"Point"}
}