{
  "type": "Feature",
  "properties": {
    "gn:admin1_code":"82.0",
    "gn:admin2_code":"2216.0",
    "gn:admin3_code":"221601.0",
    "gn:asciiname":"Jasna",
    "gn:cc2":"PL",
    "gn:country_code":"PL",
    "gn:dem":6,
    "gn:feature_class":"P",
    "gn:feature_code":"PPL",
    "gn:name":"Jasna",
    "gn:population":0,
    "gn:timezone":"Europe/Warsaw",
    "iso:country":"PL",
    "name:und_x_variant":[
        "Lichtfelde",
        "Jasna"
    ],
    "wof:name":"Jasna",
    "wof:placetype":"locality"
},
  "geometry": {"coordinates":[19.30521,54.00767],"type":"Point"}
}