{
  "type": "Feature",
  "properties": {
    "iso:country":"PL",
    "name:azb_x_preferred":[
        "\u0645\u0627\u062e\u0648\u0648"
    ],
    "name:ceb_x_preferred":[
        "Machov"
    ],
    "name:ces_x_preferred":[
        "Machov"
    ],
    "name:deu_x_preferred":[
        "Machov"
    ],
    "name:eus_x_preferred":[
        "Machov"
    ],
    "name:fas_x_preferred":[
        "\u0645\u0627\u062e\u0648\u0648"
    ],
    "name:fra_x_preferred":[
        "Machov"
    ],
    "name:hun_x_preferred":[
        "Machov"
    ],
    "name:ita_x_preferred":[
        "Machov"
    ],
    "name:msa_x_preferred":[
        "Machov"
    ],
    "name:nld_x_preferred":[
        "Machov"
    ],
    "name:pol_x_preferred":[
        "Machov"
    ],
    "name:por_x_preferred":[
        "Machov"
    ],
    "name:slk_x_preferred":[
        "Machov"
    ],
    "name:spa_x_preferred":[
        "Machov"
    ],
    "name:srp_x_preferred":[
        "\u041c\u0430\u0445\u043e\u0432"
    ],
    "name:swe_x_preferred":[
        "Machov"
    ],
    "name:vie_x_preferred":[
        "Machov"
    ],
    "qs_pg:aaroncc":"PL",
    "qs_pg:name":"Machov",
    "qs_pg:name_adm0":"\u010cesk\u00e1 republika",
    "qs_pg:name_adm1":"Kr\u00e1lov\u00e9hradeck\u00fd kraj",
    "qs_pg:photos":40,
    "qs_pg:photos_1k":8,
    "qs_pg:photos_9k":2,
    "qs_pg:photos_9r":5,
    "qs_pg:photos_all":501,
    "qs_pg:photos_sr":2,
    "qs_pg:pop_sr":0,
    "qs_pg:qs_pg_placetype":"localadmin",
    "qs_pg:qs_pg_placetype_gp":"LocalAdmin",
    "qs_pg:woe_adm0":23424810,
    "woe:adm0_id":23424810,
    "woe:name_adm0":"\u010cesk\u00e1 republika",
    "woe:name_adm1":"Kr\u00e1lov\u00e9hradeck\u00fd kraj",
    "woe:placetype":"LocalAdmin",
    "wof:name":"Machov",
    "wof:placetype":"localadmin"
},
  "geometry": {"coordinates":[16.3382145,50.482797],"type":"Point"}
}