{
  "type": "Feature",
  "properties": {
    "gn:admin1_code":"74.0",
    "gn:admin2_code":"1017.0",
    "gn:admin3_code":"101703.0",
    "gn:asciiname":"Rychlocice",
    "gn:country_code":"PL",
    "gn:dem":150,
    "gn:feature_class":"P",
    "gn:feature_code":"PPL",
    "gn:name":"Rych\u0142ocice",
    "gn:population":0,
    "gn:timezone":"Europe/Warsaw",
    "iso:country":"PL",
    "name:und_x_variant":[
        "Rych\u0142ocice"
    ],
    "wof:name":"Rychlocice",
    "wof:placetype":"locality"
},
  "geometry": {"coordinates":[18.81781,51.38964],"type":"Point"}
}