{
  "type": "Feature",
  "properties": {
    "gn:admin1_code":"82.0",
    "gn:admin2_code":"2207.0",
    "gn:admin3_code":"220705.0",
    "gn:asciiname":"Szwedy",
    "gn:country_code":"PL",
    "gn:dem":10,
    "gn:feature_class":"P",
    "gn:feature_code":"PPL",
    "gn:name":"Szwedy",
    "gn:population":0,
    "gn:timezone":"Europe/Warsaw",
    "iso:country":"PL",
    "name:pol_x_preferred":[
        "Szwedy"
    ],
    "name:ukr_x_preferred":[
        "\u0428\u0432\u0435\u0434\u0438"
    ],
    "name:und_x_variant":[
        "Schweingrude",
        "Tragheimerweide"
    ],
    "wof:name":"Szwedy",
    "wof:placetype":"locality"
},
  "geometry": {"coordinates":[18.93333,53.88333000000001],"type":"Point"}
}