{
  "type": "Feature",
  "properties": {
    "gn:admin1_code":"75.0",
    "gn:admin2_code":"620.0",
    "gn:admin3_code":"62001.0",
    "gn:asciiname":"Trzepieciny",
    "gn:country_code":"PL",
    "gn:dem":258,
    "gn:feature_class":"P",
    "gn:feature_code":"PPL",
    "gn:name":"Trzepieciny",
    "gn:population":0,
    "gn:timezone":"Europe/Warsaw",
    "iso:country":"PL",
    "name:azb_x_preferred":[
        "\u0686\u067e\u06cc\u06a9\u06cc\u0646\u06cc"
    ],
    "name:fas_x_preferred":[
        "\u0686\u067e\u06cc\u06a9\u06cc\u0646\u06cc"
    ],
    "name:fra_x_preferred":[
        "Trzepieciny"
    ],
    "name:pol_x_preferred":[
        "Trzepieciny"
    ],
    "name:ukr_x_preferred":[
        "\u0422\u0448\u0435\u043f\u0435\u0446\u0438\u043d\u0438"
    ],
    "wof:name":"Trzepieciny",
    "wof:placetype":"locality"
},
  "geometry": {"coordinates":[23.12498,50.57325],"type":"Point"}
}