{
  "type": "Feature",
  "properties": {
    "gn:admin1_code":"84.0",
    "gn:admin2_code":"2609.0",
    "gn:admin3_code":"260905.0",
    "gn:asciiname":"Zawidza",
    "gn:country_code":"PL",
    "gn:dem":157,
    "gn:feature_class":"P",
    "gn:feature_code":"PPL",
    "gn:name":"Zawidza",
    "gn:population":0,
    "gn:timezone":"Europe/Warsaw",
    "iso:country":"PL",
    "name:pol_x_preferred":[
        "Zawidza"
    ],
    "name:ukr_x_preferred":[
        "\u0417\u0430\u0432\u0456\u0434\u0437\u0430"
    ],
    "wof:name":"Zawidza",
    "wof:placetype":"locality"
},
  "geometry": {"coordinates":[21.49836,50.53754],"type":"Point"}
}