{
  "type": "Feature",
  "properties": {
    "gn:admin1_code":"78.0",
    "gn:admin2_code":"1403.0",
    "gn:admin3_code":"140304.0",
    "gn:asciiname":"Lucin",
    "gn:country_code":"PL",
    "gn:dem":133,
    "gn:feature_class":"P",
    "gn:feature_code":"PPL",
    "gn:name":"Lucin",
    "gn:population":0,
    "gn:timezone":"Europe/Warsaw",
    "iso:country":"PL",
    "name:fra_x_preferred":[
        "Lucin"
    ],
    "name:pol_x_preferred":[
        "Lucin"
    ],
    "name:ukr_x_preferred":[
        "\u041b\u044e\u0446\u0438\u043d"
    ],
    "wof:name":"Lucin",
    "wof:placetype":"locality"
},
  "geometry": {"coordinates":[21.61311,51.88083],"type":"Point"}
}