{
  "type": "Feature",
  "properties": {
    "gn:admin1_code":"86.0",
    "gn:admin2_code":"3025.0",
    "gn:admin3_code":"302504.0",
    "gn:asciiname":"Chwalkowo",
    "gn:country_code":"PL",
    "gn:dem":83,
    "gn:feature_class":"P",
    "gn:feature_code":"PPL",
    "gn:name":"Chwa\u0142kowo",
    "gn:population":0,
    "gn:timezone":"Europe/Warsaw",
    "iso:country":"PL",
    "wof:name":"Chwalkowo",
    "wof:placetype":"locality"
},
  "geometry": {"coordinates":[17.26415,52.19315],"type":"Point"}
}