{
  "type": "Feature",
  "properties": {
    "gn:admin1_code":"84.0",
    "gn:admin2_code":"2608.0",
    "gn:admin3_code":"260804.0",
    "gn:asciiname":"Wola Zagojska Dolna",
    "gn:country_code":"PL",
    "gn:dem":185,
    "gn:feature_class":"P",
    "gn:feature_code":"PPL",
    "gn:name":"Wola Zagojska Dolna",
    "gn:population":0,
    "gn:timezone":"Europe/Warsaw",
    "iso:country":"PL",
    "name:pol_x_preferred":[
        "Wola Zagojska Dolna"
    ],
    "name:ukr_x_preferred":[
        "\u0412\u043e\u043b\u044f-\u0417\u0430\u0491\u043e\u0439\u0441\u044c\u043a\u0430-\u0414\u043e\u043b\u044c\u043d\u0430"
    ],
    "wof:name":"Wola Zagojska Dolna",
    "wof:placetype":"locality"
},
  "geometry": {"coordinates":[20.6052,50.43947],"type":"Point"}
}