{
  "type": "Feature",
  "properties": {
    "gn:admin1_code":"72.0",
    "gn:admin2_code":"219.0",
    "gn:admin3_code":"21903.0",
    "gn:asciiname":"Bronowek",
    "gn:country_code":"PL",
    "gn:dem":358,
    "gn:feature_class":"P",
    "gn:feature_code":"PPL",
    "gn:name":"Bronowek",
    "gn:population":0,
    "gn:timezone":"Europe/Warsaw",
    "iso:country":"PL",
    "wof:name":"Bronowek",
    "wof:placetype":"locality"
},
  "geometry": {"coordinates":[16.2189,50.90877],"type":"Point"}
}