{
  "type": "Feature",
  "properties": {
    "gn:admin1_code":"80.0",
    "gn:admin2_code":"1810.0",
    "gn:admin3_code":"181006.0",
    "gn:asciiname":"Basakowka",
    "gn:country_code":"PL",
    "gn:dem":198,
    "gn:feature_class":"P",
    "gn:feature_code":"PPL",
    "gn:name":"Basak\u00f3wka",
    "gn:population":0,
    "gn:timezone":"Europe/Warsaw",
    "iso:country":"PL",
    "wof:name":"Basakowka",
    "wof:placetype":"locality"
},
  "geometry": {"coordinates":[22.246,50.13895],"type":"Point"}
}