{
  "type": "Feature",
  "properties": {
    "gn:admin1_code":"86.0",
    "gn:admin2_code":"3011.0",
    "gn:admin3_code":"301105.0",
    "gn:asciiname":"Przysieka Polska",
    "gn:country_code":"PL",
    "gn:dem":72,
    "gn:feature_class":"P",
    "gn:feature_code":"PPL",
    "gn:name":"Przysieka Polska",
    "gn:population":0,
    "gn:timezone":"Europe/Warsaw",
    "iso:country":"PL",
    "name:fra_x_preferred":[
        "Przysieka Polska"
    ],
    "name:pol_x_preferred":[
        "Przysieka Polska"
    ],
    "name:ukr_x_preferred":[
        "\u041f\u0448\u0438\u0441\u0435\u043a\u0430-\u041f\u043e\u043b\u044c\u0441\u044c\u043a\u0430"
    ],
    "wof:name":"Przysieka Polska",
    "wof:placetype":"locality"
},
  "geometry": {"coordinates":[16.59734,52.03248],"type":"Point"}
}