{
  "type": "Feature",
  "properties": {
    "gn:admin1_code":"72.0",
    "gn:admin2_code":"217.0",
    "gn:admin3_code":"21703.0",
    "gn:asciiname":"Krolewiec",
    "gn:country_code":"PL",
    "gn:dem":179,
    "gn:feature_class":"P",
    "gn:feature_code":"PPL",
    "gn:name":"Kr\u00f3lewiec",
    "gn:population":0,
    "gn:timezone":"Europe/Warsaw",
    "iso:country":"PL",
    "wof:name":"Krolewiec",
    "wof:placetype":"locality"
},
  "geometry": {"coordinates":[17.21797999999999,50.70092],"type":"Point"}
}