{
  "type": "Feature",
  "properties": {
    "gn:admin1_code":"81.0",
    "gn:admin2_code":"2011.0",
    "gn:admin3_code":"201102.0",
    "gn:asciiname":"Kladziewo",
    "gn:country_code":"PL",
    "gn:dem":170,
    "gn:feature_class":"P",
    "gn:feature_code":"PPL",
    "gn:name":"K\u0142adziewo",
    "gn:population":0,
    "gn:timezone":"Europe/Warsaw",
    "iso:country":"PL",
    "name:und_x_variant":[
        "K\u0142adziewo"
    ],
    "wof:name":"Kladziewo",
    "wof:placetype":"locality"
},
  "geometry": {"coordinates":[23.36127,53.45411],"type":"Point"}
}