{
  "type": "Feature",
  "properties": {
    "gn:admin1_code":"80.0",
    "gn:admin2_code":"1805.0",
    "gn:admin3_code":"180503.0",
    "gn:asciiname":"Majscowa",
    "gn:country_code":"PL",
    "gn:dem":273,
    "gn:feature_class":"P",
    "gn:feature_code":"PPL",
    "gn:name":"Majscowa",
    "gn:population":0,
    "gn:timezone":"Europe/Warsaw",
    "iso:country":"PL",
    "name:pol_x_preferred":[
        "Majscowa"
    ],
    "name:ukr_x_preferred":[
        "\u041c\u0430\u0439\u0441\u0446\u043e\u0432\u0430"
    ],
    "wof:name":"Majscowa",
    "wof:placetype":"locality"
},
  "geometry": {"coordinates":[21.47982,49.69473],"type":"Point"}
}