{
  "type": "Feature",
  "properties": {
    "gn:admin1_code":"86.0",
    "gn:admin2_code":"3009.0",
    "gn:admin3_code":"300902.0",
    "gn:asciiname":"Polonisz",
    "gn:country_code":"PL",
    "gn:dem":105,
    "gn:feature_class":"P",
    "gn:feature_code":"PPL",
    "gn:name":"Polonisz",
    "gn:population":0,
    "gn:timezone":"Europe/Warsaw",
    "iso:country":"PL",
    "name:pol_x_preferred":[
        "Polonisz"
    ],
    "name:ukr_x_preferred":[
        "\u041f\u043e\u043b\u044c\u043e\u043d\u0456\u0448"
    ],
    "wof:name":"Polonisz",
    "wof:placetype":"locality"
},
  "geometry": {"coordinates":[18.68946,52.35626],"type":"Point"}
}