{
  "type": "Feature",
  "properties": {
    "gn:admin1_code":"81.0",
    "gn:admin2_code":"2004.0",
    "gn:admin3_code":"200403.0",
    "gn:asciiname":"Glinki",
    "gn:country_code":"PL",
    "gn:dem":131,
    "gn:feature_class":"P",
    "gn:feature_code":"PPL",
    "gn:name":"Glinki",
    "gn:population":0,
    "gn:timezone":"Europe/Warsaw",
    "iso:country":"PL",
    "name:deu_x_preferred":[
        "Glinki"
    ],
    "name:fra_x_preferred":[
        "Glinki"
    ],
    "name:lit_x_preferred":[
        "Glinkai"
    ],
    "name:pol_x_preferred":[
        "Glinki"
    ],
    "name:ukr_x_preferred":[
        "\u0490\u043b\u0456\u043d\u043a\u0456"
    ],
    "wof:name":"Glinki",
    "wof:placetype":"locality"
},
  "geometry": {"coordinates":[22.30622,53.41591],"type":"Point"}
}