{
  "type": "Feature",
  "properties": {
    "gn:admin1_code":"77.0",
    "gn:admin2_code":"1207.0",
    "gn:admin3_code":"120703.0",
    "gn:asciiname":"Przenosza",
    "gn:country_code":"PL",
    "gn:dem":415,
    "gn:feature_class":"P",
    "gn:feature_code":"PPL",
    "gn:name":"Przenosza",
    "gn:population":0,
    "gn:timezone":"Europe/Warsaw",
    "iso:country":"PL",
    "name:pol_x_preferred":[
        "Przenosza"
    ],
    "name:ukr_x_preferred":[
        "\u041f\u0448\u0435\u043d\u043e\u0448\u0430"
    ],
    "wof:name":"Przenosza",
    "wof:placetype":"locality"
},
  "geometry": {"coordinates":[20.15236,49.75188],"type":"Point"}
}