{
  "type": "Feature",
  "properties": {
    "gn:admin1_code":"76.0",
    "gn:admin2_code":"812.0",
    "gn:admin3_code":"81202.0",
    "gn:asciiname":"Kowalewo",
    "gn:country_code":"PL",
    "gn:dem":97,
    "gn:feature_class":"P",
    "gn:feature_code":"PPL",
    "gn:name":"Kowalewo",
    "gn:population":0,
    "gn:timezone":"Europe/Warsaw",
    "iso:country":"PL",
    "name:deu_x_historical":[
        "Kabel"
    ],
    "name:deu_x_preferred":[
        "Kabel"
    ],
    "wof:name":"Kowalewo",
    "wof:placetype":"locality"
},
  "geometry": {"coordinates":[16.31435,51.73149],"type":"Point"}
}