{
  "type": "Feature",
  "properties": {
    "gn:admin1_code":"78.0",
    "gn:admin2_code":"1430.0",
    "gn:admin3_code":"143005.0",
    "gn:asciiname":"Swiniow",
    "gn:country_code":"PL",
    "gn:dem":173,
    "gn:feature_class":"P",
    "gn:feature_code":"PPL",
    "gn:name":"\u015awini\u00f3w",
    "gn:population":0,
    "gn:timezone":"Europe/Warsaw",
    "iso:country":"PL",
    "name:und_x_variant":[
        "\u015awini\u00f3w"
    ],
    "wof:name":"Swiniow",
    "wof:placetype":"locality"
},
  "geometry": {"coordinates":[20.89839,51.30029],"type":"Point"}
}