{
  "type": "Feature",
  "properties": {
    "gn:admin1_code":"73.0",
    "gn:admin2_code":"411.0",
    "gn:admin3_code":"41104.0",
    "gn:asciiname":"Latkowo",
    "gn:country_code":"PL",
    "gn:dem":89,
    "gn:feature_class":"P",
    "gn:feature_code":"PPL",
    "gn:name":"Latkowo",
    "gn:population":0,
    "gn:timezone":"Europe/Warsaw",
    "iso:country":"PL",
    "name:pol_x_preferred":[
        "Latkowo"
    ],
    "name:ukr_x_preferred":[
        "\u041b\u044f\u0442\u043a\u043e\u0432\u043e"
    ],
    "wof:name":"Latkowo",
    "wof:placetype":"locality"
},
  "geometry": {"coordinates":[18.65611,52.63563000000001],"type":"Point"}
}