{
  "type": "Feature",
  "properties": {
    "gn:country":"PL",
    "gn:fcode":"PPL",
    "gn:population":540,
    "iso:country":"PL",
    "name:bul_x_preferred":[
        "\u041f\u0441\u0430\u0440\u0438"
    ],
    "name:ceb_x_preferred":[
        "Psary"
    ],
    "name:deu_x_preferred":[
        "Psary"
    ],
    "name:fra_x_preferred":[
        "Psary"
    ],
    "name:ita_x_preferred":[
        "Psary"
    ],
    "name:nld_x_preferred":[
        "Psary"
    ],
    "name:pol_x_preferred":[
        "Psary"
    ],
    "name:swe_x_preferred":[
        "Psary"
    ],
    "name:ukr_x_preferred":[
        "\u041f\u0441\u0430\u0440\u0438"
    ],
    "qs_pg:aaroncc":"PL",
    "qs_pg:gn_country":"PL",
    "qs_pg:gn_fcode":"PPL",
    "qs_pg:gn_pop":540,
    "qs_pg:name":"Psary",
    "qs_pg:name_adm0":"Polska",
    "qs_pg:name_adm1":"Swi\u0119tokrzyskie",
    "qs_pg:photos_9r":0,
    "qs_pg:photos_sr":0,
    "qs_pg:pop_sr":2,
    "qs_pg:qs_pg_placetype":"locality",
    "qs_pg:qs_pg_placetype_gp":"Town",
    "qs_pg:woe_adm0":23424923,
    "woe:adm0_id":23424923,
    "woe:name_adm0":"Polska",
    "woe:name_adm1":"Swi\u0119tokrzyskie",
    "woe:placetype":"Town",
    "wof:name":"Psary",
    "wof:placetype":"locality",
    "wof:population":540
},
  "geometry": {"coordinates":[19.82401,50.73032],"type":"Point"}
}