{
  "type": "Feature",
  "properties": {
    "gn:admin1_code":"83.0",
    "gn:admin2_code":"2416.0",
    "gn:admin3_code":"241601.0",
    "gn:asciiname":"Krzemenda",
    "gn:country_code":"PL",
    "gn:dem":301,
    "gn:feature_class":"P",
    "gn:feature_code":"PPL",
    "gn:name":"Krzemenda",
    "gn:population":0,
    "gn:timezone":"Europe/Warsaw",
    "iso:country":"PL",
    "wof:name":"Krzemenda",
    "wof:placetype":"locality"
},
  "geometry": {"coordinates":[19.30288,50.48959],"type":"Point"}
}