{
  "type": "Feature",
  "properties": {
    "gn:admin1_code":"75.0",
    "gn:admin2_code":"606.0",
    "gn:admin3_code":"60611.0",
    "gn:asciiname":"Majdan Wierzchowinski",
    "gn:country_code":"PL",
    "gn:dem":268,
    "gn:feature_class":"P",
    "gn:feature_code":"PPL",
    "gn:name":"Majdan Wierzchowi\u0144ski",
    "gn:population":0,
    "gn:timezone":"Europe/Warsaw",
    "iso:country":"PL",
    "name:fra_x_preferred":[
        "Majdan Wierzchowi\u0144ski"
    ],
    "name:pol_x_preferred":[
        "Majdan Wierzchowi\u0144ski"
    ],
    "name:ukr_x_preferred":[
        "\u041c\u0430\u0439\u0434\u0430\u043d-\u0412\u0435\u0436\u0445\u043e\u0432\u0456\u043d\u0441\u044c\u043a\u0438\u0439"
    ],
    "name:und_x_variant":[
        "Majdan",
        "Majdan Wierzchowski"
    ],
    "wof:name":"Majdan Wierzchowinski",
    "wof:placetype":"locality"
},
  "geometry": {"coordinates":[22.85621,50.86765],"type":"Point"}
}