{
  "type": "Feature",
  "properties": {
    "gn:population":1293,
    "iso:country":"PL",
    "name:deu_x_preferred":[
        "Lubie\u0144 Kujawski"
    ],
    "name:dsb_x_preferred":[
        "Lubie\u0144 Kujawski"
    ],
    "name:epo_x_preferred":[
        "Lubie\u0144 Kujawski"
    ],
    "name:fra_x_preferred":[
        "Lubie\u0144 Kujawski"
    ],
    "name:jav_x_preferred":[
        "Lubie\u0144 Kujawski"
    ],
    "name:lav_x_preferred":[
        "Lube\u0146a Kujavska"
    ],
    "name:msa_x_preferred":[
        "Lubie\u0144 Kujawski"
    ],
    "name:nld_x_preferred":[
        "Lubie\u0144 Kujawski"
    ],
    "name:pol_x_preferred":[
        "Lubie\u0144 Kujawski"
    ],
    "name:por_x_preferred":[
        "Lubie\u0144 Kujawski"
    ],
    "name:unk_x_variant":[
        "Lubie\u0144"
    ],
    "qs:a0":"Rzeczpospolita Polska",
    "qs:a1":"*Kujawsko-pomorskie",
    "qs:a1r":"0",
    "qs:a2":"Wloclawski",
    "qs:adm0":"Rzeczpospolita Polska",
    "qs:la_lc":"*",
    "qs:level":"locality",
    "qs:loc":"Lubie\u0144 Kujawski",
    "qs:loc_alt":"Lubien Kujawski",
    "qs:pop":0,
    "qs:type":"buffered point",
    "wd:wordcount":53,
    "wof:name":"Lubie\u0144 Kujawski",
    "wof:placetype":"locality",
    "wof:population":1293
},
  "geometry": {"coordinates":[19.177084,52.410057],"type":"Point"}
}