{
  "type": "Feature",
  "properties": {
    "gn:population":1293,
    "iso:country":"PL",
    "name:ast_x_preferred":[
        "Lubie\u0144 Kujawski"
    ],
    "name:azb_x_preferred":[
        "\u0644\u0648\u0628\u06cc\u0646 \u06a9\u0648\u06cc\u0627\u0641\u0633\u06a9\u06cc"
    ],
    "name:ceb_x_preferred":[
        "Lubie\u0144 Kujawski"
    ],
    "name:deu_x_preferred":[
        "Lubie\u0144 Kujawski"
    ],
    "name:dsb_x_preferred":[
        "Lubie\u0144 Kujawski"
    ],
    "name:ell_x_preferred":[
        "\u039b\u03bf\u03cd\u03bc\u03c0\u03b9\u03b5\u03bd \u039a\u03bf\u03c5\u03b3\u03b9\u03ac\u03c6\u03c3\u03ba\u03b9"
    ],
    "name:eng_x_preferred":[
        "Lubie\u0144 Kujawski"
    ],
    "name:epo_x_preferred":[
        "Lubie\u0144 Kujawski"
    ],
    "name:est_x_preferred":[
        "Lubie\u0144 Kujawski"
    ],
    "name:fas_x_preferred":[
        "\u0644\u0648\u0628\u06cc\u0646 \u06a9\u0648\u06cc\u0627\u0641\u0633\u06a9\u06cc"
    ],
    "name:fra_x_preferred":[
        "Lubie\u0144 Kujawski"
    ],
    "name:jav_x_preferred":[
        "Lubie\u0144 Kujawski"
    ],
    "name:lav_x_preferred":[
        "Lube\u0146a Kujavska"
    ],
    "name:msa_x_preferred":[
        "Lubie\u0144 Kujawski"
    ],
    "name:nld_x_preferred":[
        "Lubie\u0144 Kujawski"
    ],
    "name:pol_x_preferred":[
        "Lubie\u0144 Kujawski"
    ],
    "name:por_x_preferred":[
        "Lubie\u0144 Kujawski"
    ],
    "name:ron_x_preferred":[
        "Lubie\u0144 Kujawski"
    ],
    "name:rus_x_preferred":[
        "\u041b\u044e\u0431\u0435\u043d\u044c-\u041a\u0443\u044f\u0432\u0441\u043a\u0438\u0439"
    ],
    "name:slk_x_preferred":[
        "Lubie\u0144 Kujawski"
    ],
    "name:srp_x_preferred":[
        "\u041b\u0443\u0431\u0458\u0435\u045a \u041a\u0443\u0458\u0430\u0432\u0441\u043a\u0438"
    ],
    "name:szl_x_preferred":[
        "Kujawski Lubjy\u0144"
    ],
    "name:tat_x_preferred":[
        "\u041b\u04af\u0431\u0435\u043d-\u041a\u0443\u044f\u0432\u0441\u043a\u0438"
    ],
    "name:ukr_x_preferred":[
        "\u041b\u044e\u0431\u0435\u043d\u044c-\u041a\u0443\u044f\u0432\u0441\u044c\u043a\u0438\u0439"
    ],
    "name:unk_x_variant":[
        "Lubie\u0144"
    ],
    "name:vie_x_preferred":[
        "Lubie\u0144 Kujawski"
    ],
    "qs:a0":"Rzeczpospolita Polska",
    "qs:a1":"*Kujawsko-pomorskie",
    "qs:a1r":"0",
    "qs:a2":"Wloclawski",
    "qs:adm0":"Rzeczpospolita Polska",
    "qs:la_lc":"*",
    "qs:level":"locality",
    "qs:loc":"Lubie\u0144 Kujawski",
    "qs:loc_alt":"Lubien Kujawski",
    "qs:pop":0,
    "qs:type":"buffered point",
    "wd:wordcount":53,
    "wof:name":"Lubie\u0144 Kujawski",
    "wof:placetype":"locality",
    "wof:population":1293
},
  "geometry": {"coordinates":[19.177084,52.410057],"type":"Point"}
}