{
  "type": "Feature",
  "properties": {
    "gn:admin1_code":"86.0",
    "gn:admin2_code":"3014.0",
    "gn:admin3_code":"301403.0",
    "gn:asciiname":"Krzyzkowko",
    "gn:country_code":"PL",
    "gn:dem":76,
    "gn:feature_class":"P",
    "gn:feature_code":"PPL",
    "gn:name":"Krzy\u017ck\u00f3wko",
    "gn:population":0,
    "gn:timezone":"Europe/Warsaw",
    "iso:country":"PL",
    "name:fra_x_preferred":[
        "Krzy\u017ck\u00f3wko"
    ],
    "name:pol_x_preferred":[
        "Krzy\u017ck\u00f3wko"
    ],
    "name:ukr_x_preferred":[
        "\u041a\u0448\u0438\u0436\u043a\u0443\u0432\u043a\u043e"
    ],
    "name:und_x_variant":[
        "Krzyszk\u00f3wko"
    ],
    "wof:name":"Krzyzkowko",
    "wof:placetype":"locality"
},
  "geometry": {"coordinates":[16.00605,52.49399],"type":"Point"}
}