{
  "type": "Feature",
  "properties": {
    "gn:population":1100,
    "iso:country":"PL",
    "name:azb_x_preferred":[
        "\u0642\u0645\u06cc\u0646\u0627 \u067e\u0627\u0631\u0633\u0648\u0648"
    ],
    "name:bel_x_preferred":[
        "\u0413\u043c\u0456\u043d\u0430 \u041f\u0430\u0440\u044b\u0441\u0430\u045e"
    ],
    "name:ceb_x_preferred":[
        "Parys\u00f3w"
    ],
    "name:deu_x_preferred":[
        "Gmina Parys\u00f3w"
    ],
    "name:eng_x_preferred":[
        "Gmina Parys\u00f3w"
    ],
    "name:eus_x_preferred":[
        "Parys\u00f3w udalerria"
    ],
    "name:fas_x_preferred":[
        "\u06af\u0645\u06cc\u0646\u0627 \u067e\u0627\u0631\u0633\u0648\u0648"
    ],
    "name:fra_x_preferred":[
        "Parys\u00f3w"
    ],
    "name:ita_x_preferred":[
        "Parys\u00f3w"
    ],
    "name:nan_x_preferred":[
        "Parys\u00f3w"
    ],
    "name:nld_x_preferred":[
        "Parys\u00f3w"
    ],
    "name:pol_x_preferred":[
        "Parys\u00f3w"
    ],
    "name:rus_x_preferred":[
        "\u041f\u0430\u0440\u044b\u0441\u0443\u0432"
    ],
    "name:slk_x_preferred":[
        "Gmina Parys\u00f3w"
    ],
    "name:ukr_x_preferred":[
        "\u0490\u043c\u0456\u043d\u0430 \u041f\u0430\u0440\u0438\u0441\u0443\u0432"
    ],
    "name:war_x_preferred":[
        "Gmina Parys\u00f3w"
    ],
    "name:zho_min_nan_x_preferred":[
        "Parys\u00f3w"
    ],
    "qs:a0":"Rzeczpospolita Polska",
    "qs:a1":"*Mazowieckie",
    "qs:a1r":"0",
    "qs:a2":"Garwolinski",
    "qs:adm0":"Rzeczpospolita Polska",
    "qs:la":"Parys\u00f3w",
    "qs:la_lc":"*PL1403092",
    "qs:level":"locality",
    "qs:loc":"Parys\u00f3w",
    "qs:loc_alt":"Parysow",
    "qs:pop":0,
    "qs:type":"rural point-in-poly",
    "wd:wordcount":108,
    "wof:name":"Parys\u00f3w",
    "wof:placetype":"locality",
    "wof:population":1100
},
  "geometry": {"coordinates":[21.6732774785112,51.9837285033219],"type":"Point"}
}