{
  "type": "Feature",
  "properties": {
    "gn:admin1_code":"83.0",
    "gn:admin2_code":"2409.0",
    "gn:admin3_code":"240903.0",
    "gn:asciiname":"Tomiszowice",
    "gn:country_code":"PL",
    "gn:dem":322,
    "gn:feature_class":"P",
    "gn:feature_code":"PPL",
    "gn:name":"Tomiszowice",
    "gn:population":0,
    "gn:timezone":"Europe/Warsaw",
    "iso:country":"PL",
    "name:pol_x_preferred":[
        "Tomiszowice"
    ],
    "wof:name":"Tomiszowice",
    "wof:placetype":"locality"
},
  "geometry": {"coordinates":[19.53721,50.64347],"type":"Point"}
}