{
  "type": "Feature",
  "properties": {
    "gn:gn_country":"PL",
    "gn:gn_fcode":"PPL",
    "gn:gn_pop":1622,
    "gn:population":1622,
    "iso:country":"PL",
    "name:deu_x_preferred":[
        "Tyniec Ma\u0142y"
    ],
    "name:eng_x_preferred":[
        "Tyniec Ma\u0142y"
    ],
    "name:fas_x_preferred":[
        "\u062a\u0646\u06cc\u062a\u0633 \u0645\u0648\u06cc"
    ],
    "name:fra_x_preferred":[
        "Tyniec Ma\u0142y"
    ],
    "name:pol_x_preferred":[
        "Tyniec Ma\u0142y"
    ],
    "qs_pg:aaroncc":"PL",
    "qs_pg:gn_country":"PL",
    "qs_pg:gn_fcode":"PPL",
    "qs_pg:gn_pop":1622,
    "qs_pg:name":"Tyniec Ma\u0142y",
    "qs_pg:name_adm0":"Polska",
    "qs_pg:name_adm1":"Dolnosl\u0105skie",
    "qs_pg:photos_9k":1,
    "qs_pg:photos_9r":1,
    "qs_pg:photos_all":1,
    "qs_pg:photos_sr":0,
    "qs_pg:pop_sr":3,
    "qs_pg:qs_pg_placetype":"locality",
    "qs_pg:qs_pg_placetype_gp":"Town",
    "qs_pg:woe_adm0":23424923,
    "woe:adm0_id":23424923,
    "woe:name_adm0":"Polska",
    "woe:name_adm1":"Dolnosl\u0105skie",
    "woe:placetype":"Town",
    "wof:name":"Tyniec Ma\u0142y",
    "wof:placetype":"locality",
    "wof:population":1622
},
  "geometry": {"coordinates":[16.91998,51.01948],"type":"Point"}
}