{
  "type": "Feature",
  "properties": {
    "gn:admin1_code":"83.0",
    "gn:admin2_code":"2417.0",
    "gn:admin3_code":"241703.0",
    "gn:asciiname":"Gilowice",
    "gn:country_code":"PL",
    "gn:dem":387,
    "gn:feature_class":"P",
    "gn:feature_code":"PPL",
    "gn:name":"Gilowice",
    "gn:population":4259,
    "gn:timezone":"Europe/Warsaw",
    "iso:country":"PL",
    "name:deu_x_preferred":[
        "Gilowice"
    ],
    "name:fas_x_preferred":[
        "\u06af\u06cc\u0644\u0648\u0648\u06cc\u062a\u0633\u0647"
    ],
    "name:nld_x_preferred":[
        "Gilowice"
    ],
    "name:pol_x_preferred":[
        "Gilowice"
    ],
    "name:ukr_x_preferred":[
        "\u0490\u0456\u043b\u044c\u043e\u0432\u0456\u0446\u0435"
    ],
    "wof:name":"Gilowice",
    "wof:placetype":"locality",
    "wof:population":4259
},
  "geometry": {"coordinates":[19.31045,49.71277],"type":"Point"}
}