{
  "type": "Feature",
  "properties": {
    "gn:admin1_code":"83.0",
    "gn:admin2_code":"2417.0",
    "gn:admin3_code":"241703.0",
    "gn:asciiname":"Gilowice",
    "gn:country_code":"PL",
    "gn:dem":387,
    "gn:feature_class":"P",
    "gn:feature_code":"PPL",
    "gn:name":"Gilowice",
    "gn:population":4259,
    "gn:timezone":"Europe/Warsaw",
    "iso:country":"PL",
    "wof:name":"Gilowice",
    "wof:placetype":"locality",
    "wof:population":4259
},
  "geometry": {"coordinates":[19.31045,49.71277],"type":"Point"}
}