{
  "type": "Feature",
  "properties": {
    "gn:admin1_code":"84.0",
    "gn:admin2_code":"2605.0",
    "gn:admin3_code":"260508.0",
    "gn:asciiname":"Wlochow",
    "gn:country_code":"PL",
    "gn:dem":344,
    "gn:feature_class":"P",
    "gn:feature_code":"PPL",
    "gn:name":"W\u0142och\u00f3w",
    "gn:population":0,
    "gn:timezone":"Europe/Warsaw",
    "iso:country":"PL",
    "name:und_x_variant":[
        "W\u0142och\u00f3w"
    ],
    "wof:name":"Wlochow",
    "wof:placetype":"locality"
},
  "geometry": {"coordinates":[20.60848,51.09905],"type":"Point"}
}