{
  "type": "Feature",
  "properties": {
    "gn:admin1_code":"72.0",
    "gn:admin2_code":"211.0",
    "gn:admin3_code":"21102.0",
    "gn:asciiname":"Miloradzice",
    "gn:country_code":"PL",
    "gn:dem":127,
    "gn:feature_class":"P",
    "gn:feature_code":"PPL",
    "gn:name":"Mi\u0142oradzice",
    "gn:population":0,
    "gn:timezone":"Europe/Warsaw",
    "iso:country":"PL",
    "name:ceb_x_preferred":[
        "Mi\u0142oradzice"
    ],
    "name:deu_x_preferred":[
        "Mi\u0142oradzice"
    ],
    "name:pol_x_preferred":[
        "Mi\u0142oradzice"
    ],
    "name:ukr_x_preferred":[
        "\u041c\u0456\u043b\u043e\u0440\u0430\u0434\u0437\u0456\u0446\u0435"
    ],
    "wof:name":"Miloradzice",
    "wof:placetype":"locality"
},
  "geometry": {"coordinates":[16.26921,51.32246],"type":"Point"}
}