{
  "type": "Feature",
  "properties": {
    "gn:admin1_code":"74.0",
    "gn:admin2_code":"1004.0",
    "gn:admin3_code":"100407.0",
    "gn:asciiname":"Bielawy",
    "gn:country_code":"PL",
    "gn:dem":95,
    "gn:feature_class":"P",
    "gn:feature_code":"PPL",
    "gn:name":"Bielawy",
    "gn:population":0,
    "gn:timezone":"Europe/Warsaw",
    "iso:country":"PL",
    "name:ceb_x_preferred":[
        "Bielawy"
    ],
    "name:deu_x_preferred":[
        "Bielawy"
    ],
    "name:fra_x_preferred":[
        "Bielawy"
    ],
    "name:nld_x_preferred":[
        "Bielawy"
    ],
    "name:pol_x_preferred":[
        "Bielawy"
    ],
    "name:ukr_x_preferred":[
        "\u0411\u0435\u043b\u044f\u0432\u0438"
    ],
    "wof:name":"Bielawy",
    "wof:placetype":"locality"
},
  "geometry": {"coordinates":[18.98441,52.05566],"type":"Point"}
}