{
  "type": "Feature",
  "properties": {
    "gn:admin1_code":"75.0",
    "gn:admin2_code":"609.0",
    "gn:admin3_code":"60911.0",
    "gn:asciiname":"Majdan Krasieninski",
    "gn:country_code":"PL",
    "gn:dem":198,
    "gn:feature_class":"P",
    "gn:feature_code":"PPL",
    "gn:name":"Majdan Krasieni\u0144ski",
    "gn:population":0,
    "gn:timezone":"Europe/Warsaw",
    "iso:country":"PL",
    "name:fra_x_preferred":[
        "Majdan Krasieni\u0144ski"
    ],
    "name:pol_x_preferred":[
        "Majdan Krasieni\u0144ski"
    ],
    "name:ukr_x_preferred":[
        "\u041c\u0430\u0439\u0434\u0430\u043d-\u041a\u0440\u0430\u0441\u0435\u043d\u0456\u043d\u0441\u044c\u043a\u0438\u0439"
    ],
    "wof:name":"Majdan Krasieninski",
    "wof:placetype":"locality"
},
  "geometry": {"coordinates":[22.45211,51.34509],"type":"Point"}
}