{
  "type": "Feature",
  "properties": {
    "gn:admin1_code":"72.0",
    "gn:admin2_code":"223.0",
    "gn:admin3_code":"22309.0",
    "gn:asciiname":"Okrzeszyce",
    "gn:country_code":"PL",
    "gn:dem":134,
    "gn:feature_class":"P",
    "gn:feature_code":"PPL",
    "gn:name":"Okrzeszyce",
    "gn:population":0,
    "gn:timezone":"Europe/Warsaw",
    "iso:country":"PL",
    "name:pol_x_preferred":[
        "Okrzeszyce"
    ],
    "name:ukr_x_preferred":[
        "\u041e\u043a\u0448\u0435\u0448\u0438\u0446\u0435"
    ],
    "wof:name":"Okrzeszyce",
    "wof:placetype":"locality"
},
  "geometry": {"coordinates":[17.12245,50.97664],"type":"Point"}
}