{
  "type": "Feature",
  "properties": {
    "gn:admin1_code":"78.0",
    "gn:admin2_code":"1409.0",
    "gn:admin3_code":"140902.0",
    "gn:asciiname":"Rochalina",
    "gn:country_code":"PL",
    "gn:dem":173,
    "gn:feature_class":"P",
    "gn:feature_code":"PPL",
    "gn:name":"Rochalina",
    "gn:population":0,
    "gn:timezone":"Europe/Warsaw",
    "iso:country":"PL",
    "wof:name":"Rochalina",
    "wof:placetype":"locality"
},
  "geometry": {"coordinates":[21.42324,51.22277],"type":"Point"}
}