{
  "type": "Feature",
  "properties": {
    "iso:country":"PL",
    "wof:name":"Jeziorki",
    "wof:placetype":"neighbourhood"
},
  "geometry": {"coordinates":[20.99703857341203,52.12359036149779],"type":"Point"}
}