{
  "type": "Feature",
  "properties": {
    "iso:country":"PL",
    "name:ceb_x_preferred":[
        "Jeziorki"
    ],
    "name:deu_x_preferred":[
        "Jeziorki"
    ],
    "name:fra_x_preferred":[
        "Jeziorki"
    ],
    "name:lit_x_preferred":[
        "Jeziorkai"
    ],
    "name:pol_x_preferred":[
        "Jeziorki"
    ],
    "name:ukr_x_preferred":[
        "\u0404\u0437\u044c\u043e\u0440\u043a\u0456"
    ],
    "wof:name":"Jeziorki",
    "wof:placetype":"neighbourhood"
},
  "geometry": {"coordinates":[20.99703857341203,52.12359036149779],"type":"Point"}
}