{
  "type": "Feature",
  "properties": {
    "iso:country":"PL",
    "name:eng_x_preferred":[
        "Fabianowo"
    ],
    "name:pol_x_preferred":[
        "Fabianowo"
    ],
    "wof:name":"Fabianowo",
    "wof:placetype":"neighbourhood"
},
  "geometry": {"coordinates":[16.84390677936666,52.36834934597127],"type":"Point"}
}