{
  "type": "Feature",
  "properties": {
    "gn:admin1_code":"72.0",
    "gn:admin2_code":"223.0",
    "gn:admin3_code":"22307.0",
    "gn:asciiname":"Rogow Sobocki",
    "gn:country_code":"PL",
    "gn:dem":152,
    "gn:feature_class":"P",
    "gn:feature_code":"PPL",
    "gn:name":"Rog\u00f3w Sobocki",
    "gn:population":0,
    "gn:timezone":"Europe/Warsaw",
    "iso:country":"PL",
    "name:deu_x_historical":[
        "Rogau"
    ],
    "name:deu_x_preferred":[
        "Rogau"
    ],
    "name:deu_x_variant":[
        "Rog\u00f3w Sob\u00f3cki"
    ],
    "name:nld_x_preferred":[
        "Rog\u00f3w Sob\u00f3cki"
    ],
    "name:pol_x_preferred":[
        "Rog\u00f3w Sob\u00f3cki"
    ],
    "name:ukr_x_preferred":[
        "\u0420\u043e\u0491\u0443\u0432-\u0421\u043e\u0431\u0443\u0446\u044c\u043a\u0438\u0439"
    ],
    "wof:name":"Rogow Sobocki",
    "wof:placetype":"locality"
},
  "geometry": {"coordinates":[16.75664,50.92159],"type":"Point"}
}