{
  "type": "Feature",
  "properties": {
    "gn:admin1_code":"78.0",
    "gn:admin2_code":"1402.0",
    "gn:admin3_code":"140209.0",
    "gn:asciiname":"Gutkowo",
    "gn:country_code":"PL",
    "gn:dem":103,
    "gn:feature_class":"P",
    "gn:feature_code":"PPL",
    "gn:name":"Gutkowo",
    "gn:population":0,
    "gn:timezone":"Europe/Warsaw",
    "iso:country":"PL",
    "name:ceb_x_preferred":[
        "Gutkowo"
    ],
    "name:fra_x_preferred":[
        "Gutk\u00f3w"
    ],
    "name:pol_x_preferred":[
        "Gutk\u00f3w"
    ],
    "name:ukr_x_preferred":[
        "\u0490\u0443\u0442\u043a\u0443\u0432"
    ],
    "wof:name":"Gutkowo",
    "wof:placetype":"locality"
},
  "geometry": {"coordinates":[20.64144,52.736],"type":"Point"}
}