{
  "type": "Feature",
  "properties": {
    "gn:admin1_code":"80.0",
    "gn:admin2_code":"1805.0",
    "gn:admin3_code":"180509.0",
    "gn:asciiname":"Pusta Wola",
    "gn:country_code":"PL",
    "gn:dem":244,
    "gn:feature_class":"P",
    "gn:feature_code":"PPL",
    "gn:name":"Pusta Wola",
    "gn:population":0,
    "gn:timezone":"Europe/Warsaw",
    "iso:country":"PL",
    "name:pol_x_preferred":[
        "Pusta Wola"
    ],
    "name:ukr_x_preferred":[
        "\u041f\u0443\u0441\u0442\u0430-\u0412\u043e\u043b\u044f"
    ],
    "wof:name":"Pusta Wola",
    "wof:placetype":"locality"
},
  "geometry": {"coordinates":[21.34678,49.73435],"type":"Point"}
}