{
  "type": "Feature",
  "properties": {
    "gn:admin1_code":"84.0",
    "gn:admin2_code":"2611.0",
    "gn:admin3_code":"261104.0",
    "gn:asciiname":"Krajkow",
    "gn:country_code":"PL",
    "gn:dem":289,
    "gn:feature_class":"P",
    "gn:feature_code":"PPL",
    "gn:name":"Krajk\u00f3w",
    "gn:population":0,
    "gn:timezone":"Europe/Warsaw",
    "iso:country":"PL",
    "name:ceb_x_preferred":[
        "Krajk\u00f3w"
    ],
    "name:fra_x_preferred":[
        "Krajk\u00f3w"
    ],
    "name:pol_x_preferred":[
        "Krajk\u00f3w"
    ],
    "name:ukr_x_preferred":[
        "\u041a\u0440\u0430\u0439\u043a\u0443\u0432"
    ],
    "wof:name":"Krajkow",
    "wof:placetype":"locality"
},
  "geometry": {"coordinates":[21.03124,50.91828],"type":"Point"}
}