{
  "type": "Feature",
  "properties": {
    "gn:gn_country":"PL",
    "gn:gn_fcode":"PPL",
    "gn:gn_pop":441,
    "gn:population":441,
    "iso:country":"PL",
    "name:ast_x_preferred":[
        "Nowe Koz\u0142owice"
    ],
    "name:ceb_x_preferred":[
        "Nowe Koz\u0142owice"
    ],
    "name:eng_x_preferred":[
        "Nowe Koz\u0142owice"
    ],
    "name:fra_x_preferred":[
        "Nowe Koz\u0142owice"
    ],
    "name:pol_x_preferred":[
        "Nowe Koz\u0142owice"
    ],
    "name:ukr_x_preferred":[
        "\u041d\u043e\u0432\u0435 \u041a\u043e\u0437\u043b\u043e\u0432\u0456\u0446\u0435"
    ],
    "qs_pg:aaroncc":"PL",
    "qs_pg:gn_country":"PL",
    "qs_pg:gn_fcode":"PPL",
    "qs_pg:gn_pop":441,
    "qs_pg:name":"Nowe Koz\u0142owice",
    "qs_pg:name_adm0":"Polska",
    "qs_pg:name_adm1":"Mazowieckie",
    "qs_pg:photos_9r":0,
    "qs_pg:photos_sr":0,
    "qs_pg:pop_sr":2,
    "qs_pg:qs_pg_placetype":"locality",
    "qs_pg:qs_pg_placetype_gp":"Town",
    "qs_pg:woe_adm0":23424923,
    "woe:adm0_id":23424923,
    "woe:name_adm0":"Polska",
    "woe:name_adm1":"Mazowieckie",
    "woe:placetype":"Town",
    "wof:name":"Nowe Koz\u0142owice",
    "wof:placetype":"locality",
    "wof:population":441
},
  "geometry": {"coordinates":[20.42968,52.08478],"type":"Point"}
}