{
  "type": "Feature",
  "properties": {
    "iso:country":"PL",
    "name:deu_x_preferred":[
        "Nowe Sady"
    ],
    "name:pol_x_preferred":[
        "Nowe Sady"
    ],
    "name:ukr_x_preferred":[
        "\u041d\u043e\u0432\u0435 \u0421\u0430\u0434\u0438"
    ],
    "wof:name":"Nowe Sady",
    "wof:placetype":"neighbourhood"
},
  "geometry": {"coordinates":[19.42938462180495,51.74069838732382],"type":"Point"}
}