{
  "type": "Feature",
  "properties": {
    "gn:admin1_code":"86.0",
    "gn:admin2_code":"3011.0",
    "gn:admin3_code":"301104.0",
    "gn:asciiname":"Rogaczewo Male",
    "gn:country_code":"PL",
    "gn:dem":78,
    "gn:feature_class":"P",
    "gn:feature_code":"PPL",
    "gn:name":"Rogaczewo Ma\u0142e",
    "gn:population":0,
    "gn:timezone":"Europe/Warsaw",
    "iso:country":"PL",
    "name:und_x_variant":[
        "Rogaczewo Ma\u0142e"
    ],
    "wof:name":"Rogaczewo Male",
    "wof:placetype":"locality"
},
  "geometry": {"coordinates":[16.80972,52.03925],"type":"Point"}
}