{
  "type": "Feature",
  "properties": {
    "gn:admin1_code":"76.0",
    "gn:admin2_code":"803.0",
    "gn:admin3_code":"80302.0",
    "gn:asciiname":"Bobowicko",
    "gn:country_code":"PL",
    "gn:dem":55,
    "gn:feature_class":"P",
    "gn:feature_code":"PPL",
    "gn:name":"Bobowicko",
    "gn:population":0,
    "gn:timezone":"Europe/Warsaw",
    "iso:country":"PL",
    "name:ceb_x_preferred":[
        "Bobowicko"
    ],
    "name:fra_x_preferred":[
        "Bobowicko"
    ],
    "name:nld_x_preferred":[
        "Bobowicko"
    ],
    "name:pol_x_preferred":[
        "Bobowicko"
    ],
    "name:ukr_x_preferred":[
        "\u0411\u043e\u0431\u043e\u0432\u0456\u0446\u044c\u043a\u043e"
    ],
    "wof:name":"Bobowicko",
    "wof:placetype":"locality"
},
  "geometry": {"coordinates":[15.64499,52.44094000000001],"type":"Point"}
}