{
  "type": "Feature",
  "properties": {
    "gn:admin1_code":"75.0",
    "gn:admin2_code":"603.0",
    "gn:admin3_code":"60309.0",
    "gn:asciiname":"Jazikowska Stobodka",
    "gn:country_code":"PL",
    "gn:dem":173,
    "gn:feature_class":"P",
    "gn:feature_code":"PPL",
    "gn:name":"Jazikowska Stob\u00f3dka",
    "gn:population":0,
    "gn:timezone":"Europe/Warsaw",
    "iso:country":"PL",
    "wof:name":"Jazikowska Stobodka",
    "wof:placetype":"locality"
},
  "geometry": {"coordinates":[23.63333,51.23333],"type":"Point"}
}