{
  "type": "Feature",
  "properties": {
    "gn:admin1_code":"81.0",
    "gn:admin2_code":"2003.0",
    "gn:admin3_code":"200305.0",
    "gn:asciiname":"Domanowo Nowe",
    "gn:country_code":"PL",
    "gn:dem":127,
    "gn:feature_class":"P",
    "gn:feature_code":"PPL",
    "gn:name":"Domanowo Nowe",
    "gn:population":0,
    "gn:timezone":"Europe/Warsaw",
    "iso:country":"PL",
    "wof:name":"Domanowo Nowe",
    "wof:placetype":"locality"
},
  "geometry": {"coordinates":[22.76667,52.78333000000001],"type":"Point"}
}