{
  "type": "Feature",
  "properties": {
    "gn:admin1_code":"84.0",
    "gn:admin2_code":"2604.0",
    "gn:admin3_code":"260408.0",
    "gn:asciiname":"Eustachow",
    "gn:country_code":"PL",
    "gn:dem":268,
    "gn:feature_class":"P",
    "gn:feature_code":"PPL",
    "gn:name":"Eustach\u00f3w",
    "gn:population":0,
    "gn:timezone":"Europe/Warsaw",
    "iso:country":"PL",
    "name:und_x_variant":[
        "Eustach\u00f3w"
    ],
    "wof:name":"Eustachow",
    "wof:placetype":"locality"
},
  "geometry": {"coordinates":[20.27148,50.93016],"type":"Point"}
}