{
  "type": "Feature",
  "properties": {
    "gn:admin1_code":"84.0",
    "gn:admin2_code":"2604.0",
    "gn:admin3_code":"260408.0",
    "gn:asciiname":"Eustachow",
    "gn:country_code":"PL",
    "gn:dem":268,
    "gn:feature_class":"P",
    "gn:feature_code":"PPL",
    "gn:name":"Eustach\u00f3w",
    "gn:population":0,
    "gn:timezone":"Europe/Warsaw",
    "iso:country":"PL",
    "name:ceb_x_preferred":[
        "Eustach\u00f3w"
    ],
    "name:nld_x_preferred":[
        "Eustach\u00f3w"
    ],
    "name:pol_x_preferred":[
        "Eustach\u00f3w"
    ],
    "name:ukr_x_preferred":[
        "\u0415\u0443\u0441\u0442\u0430\u0445\u0443\u0432"
    ],
    "wof:name":"Eustachow",
    "wof:placetype":"locality"
},
  "geometry": {"coordinates":[20.27148,50.93016],"type":"Point"}
}