{
  "type": "Feature",
  "properties": {
    "gn:admin1_code":"75.0",
    "gn:admin2_code":"616.0",
    "gn:admin3_code":"61602.0",
    "gn:asciiname":"Stare Zadybie",
    "gn:country_code":"PL",
    "gn:dem":166,
    "gn:feature_class":"P",
    "gn:feature_code":"PPL",
    "gn:name":"Stare Zadybie",
    "gn:population":0,
    "gn:timezone":"Europe/Warsaw",
    "iso:country":"PL",
    "name:fra_x_preferred":[
        "Stare Zadybie"
    ],
    "name:pol_x_preferred":[
        "Stare Zadybie"
    ],
    "name:ukr_x_preferred":[
        "\u0421\u0442\u0430\u0440\u0435 \u0417\u0430\u0434\u0438\u0431\u0435"
    ],
    "name:und_x_variant":[
        "Zadybie Stare"
    ],
    "wof:name":"Stare Zadybie",
    "wof:placetype":"locality"
},
  "geometry": {"coordinates":[21.92923,51.75339],"type":"Point"}
}