{
  "type": "Feature",
  "properties": {
    "gn:admin1_code":"86.0",
    "gn:admin2_code":"3007.0",
    "gn:admin3_code":"300711.0",
    "gn:asciiname":"Russow",
    "gn:country_code":"PL",
    "gn:dem":126,
    "gn:feature_class":"P",
    "gn:feature_code":"PPL",
    "gn:name":"Russ\u00f3w",
    "gn:population":0,
    "gn:timezone":"Europe/Warsaw",
    "iso:country":"PL",
    "name:nld_x_preferred":[
        "Russ\u00f3w"
    ],
    "name:pol_x_preferred":[
        "Russ\u00f3w"
    ],
    "name:ukr_x_preferred":[
        "\u0420\u0443\u0441\u0441\u0443\u0432"
    ],
    "wof:name":"Russow",
    "wof:placetype":"locality"
},
  "geometry": {"coordinates":[18.0879,51.8427],"type":"Point"}
}