{
  "type": "Feature",
  "properties": {
    "gn:admin1_code":"86.0",
    "gn:admin2_code":"3005.0",
    "gn:admin3_code":"300502.0",
    "gn:asciiname":"Grablewo",
    "gn:country_code":"PL",
    "gn:dem":80,
    "gn:feature_class":"P",
    "gn:feature_code":"PPL",
    "gn:name":"Grablewo",
    "gn:population":0,
    "gn:timezone":"Europe/Warsaw",
    "iso:country":"PL",
    "name:fra_x_preferred":[
        "Gr\u0105blewo"
    ],
    "name:pol_x_preferred":[
        "Gr\u0105blewo"
    ],
    "name:ukr_x_preferred":[
        "\u0490\u0440\u043e\u043c\u0431\u043b\u0435\u0432\u043e"
    ],
    "wof:name":"Grablewo",
    "wof:placetype":"locality"
},
  "geometry": {"coordinates":[16.38877,52.24009],"type":"Point"}
}