{
  "type": "Feature",
  "properties": {
    "gn:admin1_code":"78.0",
    "gn:admin2_code":"1426.0",
    "gn:admin3_code":"142606.0",
    "gn:asciiname":"Rzeszotkow",
    "gn:country_code":"PL",
    "gn:dem":150,
    "gn:feature_class":"P",
    "gn:feature_code":"PPL",
    "gn:name":"Rzeszotk\u00f3w",
    "gn:population":0,
    "gn:timezone":"Europe/Warsaw",
    "iso:country":"PL",
    "name:azb_x_preferred":[
        "\u0698\u0634\u0648\u062a\u06a9\u0648\u0648"
    ],
    "name:fas_x_preferred":[
        "\u0698\u0634\u0648\u062a\u06a9\u0648\u0648"
    ],
    "name:fra_x_preferred":[
        "Rzeszotk\u00f3w"
    ],
    "name:lit_x_preferred":[
        "\u017de\u0161otkuvas"
    ],
    "name:pol_x_preferred":[
        "Rzeszotk\u00f3w"
    ],
    "name:szl_x_preferred":[
        "Rzeszotk\u016fw"
    ],
    "name:ukr_x_preferred":[
        "\u0416\u0435\u0448\u043e\u0442\u043a\u0443\u0432"
    ],
    "wof:name":"Rzeszotkow",
    "wof:placetype":"locality"
},
  "geometry": {"coordinates":[22.36979,52.2837],"type":"Point"}
}