{
  "type": "Feature",
  "properties": {
    "gn:admin1_code":"84.0",
    "gn:admin2_code":"2602.0",
    "gn:admin3_code":"260203.0",
    "gn:asciiname":"Zakrucze",
    "gn:country_code":"PL",
    "gn:dem":229,
    "gn:feature_class":"P",
    "gn:feature_code":"PPL",
    "gn:name":"Zakrucze",
    "gn:population":0,
    "gn:timezone":"Europe/Warsaw",
    "iso:country":"PL",
    "name:ceb_x_preferred":[
        "Zakrucze"
    ],
    "name:pol_x_preferred":[
        "Zakrucze"
    ],
    "name:ukr_x_preferred":[
        "\u0417\u0430\u043a\u0440\u0443\u0447\u0435"
    ],
    "wof:name":"Zakrucze",
    "wof:placetype":"locality"
},
  "geometry": {"coordinates":[20.28956,50.82852000000001],"type":"Point"}
}