{
  "type": "Feature",
  "properties": {
    "gn:gn_country":"PL",
    "gn:gn_fcode":"PPL",
    "gn:gn_pop":160,
    "gn:population":160,
    "iso:country":"PL",
    "name:ast_x_preferred":[
        "Juchnowiec Ko\u015bcielny"
    ],
    "name:azb_x_preferred":[
        "\u06cc\u0648\u062e\u0646\u0648\u0648\u06cc\u062a\u0633 \u06a9\u0648\u0634\u0686\u06cc\u0644\u0646\u0647"
    ],
    "name:ceb_x_preferred":[
        "Juchnowiec Ko\u015bcielny"
    ],
    "name:deu_x_preferred":[
        "Juchnowiec Ko\u015bcielny"
    ],
    "name:eng_x_preferred":[
        "Juchnowiec Ko\u015bcielny"
    ],
    "name:fas_x_preferred":[
        "\u06cc\u0648\u062e\u0646\u0648\u0648\u06cc\u062a\u0633 \u06a9\u0648\u0634\u0686\u06cc\u0644\u0646\u0647"
    ],
    "name:fra_x_preferred":[
        "Juchnowiec Ko\u015bcielny"
    ],
    "name:lit_x_preferred":[
        "Juchnovec Ko\u0161celnai"
    ],
    "name:nan_x_preferred":[
        "Juchnowiec Ko\u015bcielny"
    ],
    "name:nld_x_preferred":[
        "Juchnowiec Ko\u015bcielny"
    ],
    "name:pol_x_preferred":[
        "Juchnowiec Ko\u015bcielny"
    ],
    "name:rus_x_preferred":[
        "\u042e\u0445\u043d\u043e\u0432\u0435\u0446-\u041a\u043e\u0441\u044c\u0446\u0435\u043b\u044c\u043d\u044b"
    ],
    "name:ukr_x_preferred":[
        "\u042e\u0445\u043d\u043e\u0432\u0435\u0446\u044c-\u041a\u043e\u0441\u044c\u0446\u0435\u043b\u044c\u043d\u0438"
    ],
    "qs_pg:aaroncc":"PL",
    "qs_pg:gn_country":"PL",
    "qs_pg:gn_fcode":"PPL",
    "qs_pg:gn_pop":160,
    "qs_pg:name":"Juchnowiec Ko\u015bcielny",
    "qs_pg:name_adm0":"Polska",
    "qs_pg:name_adm1":"Podlaskie",
    "qs_pg:photos_9k":1,
    "qs_pg:photos_9r":1,
    "qs_pg:photos_all":1,
    "qs_pg:photos_sr":0,
    "qs_pg:pop_sr":1,
    "qs_pg:qs_pg_placetype":"locality",
    "qs_pg:qs_pg_placetype_gp":"Town",
    "qs_pg:woe_adm0":23424923,
    "woe:adm0_id":23424923,
    "woe:name_adm0":"Polska",
    "woe:name_adm1":"Podlaskie",
    "woe:placetype":"Town",
    "wof:name":"Juchnowiec Ko\u015bcielny",
    "wof:placetype":"locality",
    "wof:population":160
},
  "geometry": {"coordinates":[23.13334,53.00719],"type":"Point"}
}