{
  "type": "Feature",
  "properties": {
    "gn:admin1_code":"85.0",
    "gn:admin2_code":"2801.0",
    "gn:admin3_code":"280106.0",
    "gn:asciiname":"Dluga",
    "gn:country_code":"PL",
    "gn:dem":47,
    "gn:feature_class":"P",
    "gn:feature_code":"PPL",
    "gn:name":"D\u0142uga",
    "gn:population":0,
    "gn:timezone":"Europe/Warsaw",
    "iso:country":"PL",
    "name:deu_x_preferred":[
        "D\u0142uga"
    ],
    "name:fra_x_preferred":[
        "D\u0142uga"
    ],
    "name:pol_x_preferred":[
        "D\u0142uga"
    ],
    "name:ukr_x_preferred":[
        "\u0414\u043b\u0443\u0491\u0430"
    ],
    "name:und_x_variant":[
        "Langendorf"
    ],
    "wof:name":"Dluga",
    "wof:placetype":"locality"
},
  "geometry": {"coordinates":[21.00969,54.28151],"type":"Point"}
}