{
  "type": "Feature",
  "properties": {
    "gn:admin1_code":"86.0",
    "gn:admin2_code":"3007.0",
    "gn:admin3_code":"300706.0",
    "gn:asciiname":"Liskow Dabrowica",
    "gn:country_code":"PL",
    "gn:dem":132,
    "gn:feature_class":"P",
    "gn:feature_code":"PPL",
    "gn:name":"Lisk\u00f3w D\u0105browica",
    "gn:population":0,
    "gn:timezone":"Europe/Warsaw",
    "iso:country":"PL",
    "wof:name":"Liskow Dabrowica",
    "wof:placetype":"locality"
},
  "geometry": {"coordinates":[18.38333,51.83333],"type":"Point"}
}