{
  "type": "Feature",
  "properties": {
    "gn:admin1_code":"82.0",
    "gn:admin2_code":"2210.0",
    "gn:admin3_code":"221005.0",
    "gn:asciiname":"Sztutowska Kepa",
    "gn:country_code":"PL",
    "gn:dem":-1,
    "gn:feature_class":"P",
    "gn:feature_code":"PPL",
    "gn:name":"Sztutowska K\u0119pa",
    "gn:population":0,
    "gn:timezone":"Europe/Warsaw",
    "iso:country":"PL",
    "wof:name":"Sztutowska Kepa",
    "wof:placetype":"locality"
},
  "geometry": {"coordinates":[19.18882,54.31592],"type":"Point"}
}