{
  "type": "Feature",
  "properties": {
    "iso:country":"PL",
    "name:deu_x_preferred":[
        "Certificate Signing Request"
    ],
    "name:eng_x_preferred":[
        "certificate signing request"
    ],
    "name:fas_x_preferred":[
        "\u062f\u0631\u062e\u0648\u0627\u0633\u062a \u0627\u0645\u0636\u0627\u06cc \u06af\u0648\u0627\u0647\u06cc\u200c\u0646\u0627\u0645\u0647"
    ],
    "name:fra_x_preferred":[
        "Demande de signature de certificat"
    ],
    "name:jpn_x_preferred":[
        "\u8a3c\u660e\u66f8\u7f72\u540d\u8981\u6c42"
    ],
    "name:pol_x_colloquial":[
        "Gadow Maly",
        "GdAw May",
        "Wrocaw-Gdaw May",
        "Wroclaw-Gadow Maly"
    ],
    "name:pol_x_preferred":[
        "Gd\u00e3w May"
    ],
    "name:pol_x_variant":[
        "Gandau",
        "Klein Gandau",
        "Wrocaw-Gd\u00e3w May"
    ],
    "name:vie_x_preferred":[
        "Certificate signing request"
    ],
    "name:zho_x_preferred":[
        "\u6191\u8b49\u7c3d\u7f72\u8acb\u6c42"
    ],
    "qs:gn_adm0_cc":"PL",
    "qs:gn_local":3081368,
    "qs:gn_namadm1":"72",
    "qs:local_max":3187,
    "qs:local_sum":10994,
    "qs:localhoods":7,
    "qs:name":"Gd\u00e3w May",
    "qs:name_adm0":"Polska",
    "qs:name_adm1":"Dolnosl\u0105skie",
    "qs:name_adm2":"Wroclaw",
    "qs:name_lau":"Wroclaw",
    "qs:name_local":"Wroclaw",
    "qs:photo_max":198,
    "qs:photo_sum":1835,
    "qs:placetype":"Suburb",
    "qs:quad_count":118,
    "qs:woe_adm0":23424923,
    "qs:woe_adm1":12577935,
    "qs:woe_adm2":12591160,
    "qs:woe_lau":12618090,
    "qs:woe_local":12618090,
    "qs:woe_ver":"7.10.0",
    "wd:wordcount":979,
    "wof:lang":[
        "pol"
    ],
    "wof:name":"Gd\u00e3w May",
    "wof:placetype":"neighbourhood"
},
  "geometry": {"coordinates":[16.969812,51.1063],"type":"Point"}
}