{
  "type": "Feature",
  "properties": {
    "gn:population":1304,
    "iso:country":"PL",
    "name:ast_x_preferred":[
        "Psary"
    ],
    "name:ceb_x_preferred":[
        "Psary"
    ],
    "name:deu_x_preferred":[
        "Psary"
    ],
    "name:eng_x_preferred":[
        "Psary"
    ],
    "name:fra_x_preferred":[
        "Psary"
    ],
    "name:pol_x_preferred":[
        "Psary"
    ],
    "name:ukr_x_preferred":[
        "\u041f\u0441\u0430\u0440\u0438"
    ],
    "qs:a0":"Rzeczpospolita Polska",
    "qs:a1":"*Slaskie",
    "qs:a1r":"0",
    "qs:a2":"Lubliniecki",
    "qs:adm0":"Rzeczpospolita Polska",
    "qs:la":"Wo\u017aniki",
    "qs:la_lc":"*PL2407083",
    "qs:level":"locality",
    "qs:loc":"Psary",
    "qs:loc_alt":"Psary",
    "qs:pop":0,
    "qs:type":"rural point-multi-in-poly-resolved",
    "wd:wordcount":93,
    "wof:coterminous":[
        1477751371
    ],
    "wof:name":"Psary",
    "wof:placetype":"locality",
    "wof:population":1304
},
  "geometry": {"coordinates":[19.1240416234682,50.3932607346636],"type":"Point"}
}