{
  "type": "Feature",
  "properties": {
    "gn:admin1_code":"78.0",
    "gn:admin2_code":"1425.0",
    "gn:admin3_code":"142502.0",
    "gn:asciiname":"Podmostki",
    "gn:country_code":"PL",
    "gn:dem":175,
    "gn:feature_class":"P",
    "gn:feature_code":"PPL",
    "gn:name":"Podmostki",
    "gn:population":0,
    "gn:timezone":"Europe/Warsaw",
    "iso:country":"PL",
    "wof:name":"Podmostki",
    "wof:placetype":"locality"
},
  "geometry": {"coordinates":[21.43048,51.3581],"type":"Point"}
}