{
  "type": "Feature",
  "properties": {
    "gn:admin1_code":"80.0",
    "gn:admin2_code":"1804.0",
    "gn:admin3_code":"180411.0",
    "gn:asciiname":"Lichacze",
    "gn:country_code":"PL",
    "gn:dem":204,
    "gn:feature_class":"P",
    "gn:feature_code":"PPL",
    "gn:name":"Lichacze",
    "gn:population":0,
    "gn:timezone":"Europe/Warsaw",
    "iso:country":"PL",
    "wof:name":"Lichacze",
    "wof:placetype":"locality"
},
  "geometry": {"coordinates":[22.86667000000001,50.15],"type":"Point"}
}