{
  "type": "Feature",
  "properties": {
    "gn:admin1_code":"86.0",
    "gn:admin2_code":"3029.0",
    "gn:admin3_code":"302901.0",
    "gn:asciiname":"Perkowo",
    "gn:country_code":"PL",
    "gn:dem":61,
    "gn:feature_class":"P",
    "gn:feature_code":"PPL",
    "gn:name":"Perkowo",
    "gn:population":0,
    "gn:timezone":"Europe/Warsaw",
    "iso:country":"PL",
    "name:ceb_x_preferred":[
        "Perkowo"
    ],
    "name:fra_x_preferred":[
        "Perkowo"
    ],
    "name:nld_x_preferred":[
        "Perkowo"
    ],
    "name:pol_x_preferred":[
        "Perkowo"
    ],
    "name:ukr_x_preferred":[
        "\u041f\u0435\u0440\u043a\u043e\u0432\u043e"
    ],
    "wof:name":"Perkowo",
    "wof:placetype":"locality"
},
  "geometry": {"coordinates":[16.25867,52.00477],"type":"Point"}
}