{
  "type": "Feature",
  "properties": {
    "gn:admin1_code":"72.0",
    "gn:admin2_code":"223.0",
    "gn:admin3_code":"22306.0",
    "gn:asciiname":"Maniow Maly",
    "gn:country_code":"PL",
    "gn:dem":171,
    "gn:feature_class":"P",
    "gn:feature_code":"PPL",
    "gn:name":"Mani\u00f3w Ma\u0142y",
    "gn:population":0,
    "gn:timezone":"Europe/Warsaw",
    "iso:country":"PL",
    "name:pol_x_preferred":[
        "Mani\u00f3w Ma\u0142y"
    ],
    "name:ukr_x_preferred":[
        "\u041c\u0430\u043d\u044e\u0432-\u041c\u0430\u043b\u0438"
    ],
    "wof:name":"Maniow Maly",
    "wof:placetype":"locality"
},
  "geometry": {"coordinates":[16.65175,50.94848],"type":"Point"}
}