{
  "type": "Feature",
  "properties": {
    "gn:admin1_code":"78.0",
    "gn:admin2_code":"1417.0",
    "gn:admin3_code":"141707.0",
    "gn:asciiname":"Katy",
    "gn:country_code":"PL",
    "gn:dem":94,
    "gn:feature_class":"P",
    "gn:feature_code":"PPL",
    "gn:name":"K\u0105ty",
    "gn:population":0,
    "gn:timezone":"Europe/Warsaw",
    "iso:country":"PL",
    "wof:name":"Katy",
    "wof:placetype":"locality"
},
  "geometry": {"coordinates":[21.32134,51.91162],"type":"Point"}
}