{
  "type": "Feature",
  "properties": {
    "gn:gn_country":"PL",
    "gn:gn_fcode":"PPL",
    "gn:gn_pop":0,
    "iso:country":"PL",
    "name:ast_x_preferred":[
        "Pustk\u00f3w \u017burawski"
    ],
    "name:ceb_x_preferred":[
        "Pustk\u00f3w \u017burawski"
    ],
    "name:deu_x_preferred":[
        "Pustk\u00f3w \u017burawski"
    ],
    "name:eng_x_preferred":[
        "Pustk\u00f3w \u017burawski"
    ],
    "name:fra_x_preferred":[
        "Pustk\u00f3w \u017burawski"
    ],
    "name:pol_x_preferred":[
        "Pustk\u00f3w \u017burawski"
    ],
    "name:ukr_x_preferred":[
        "\u041f\u0443\u0441\u0442\u043a\u0443\u0432-\u0416\u0443\u0440\u0430\u0432\u0441\u044c\u043a\u0438\u0439"
    ],
    "qs_pg:aaroncc":"PL",
    "qs_pg:gn_country":"PL",
    "qs_pg:gn_fcode":"PPL",
    "qs_pg:gn_pop":0,
    "qs_pg:name":"Pustk\u00f3w \u017burawski",
    "qs_pg:name_adm0":"Polska",
    "qs_pg:name_adm1":"Dolnosl\u0105skie",
    "qs_pg:photos_9k":1,
    "qs_pg:photos_9r":1,
    "qs_pg:photos_all":1,
    "qs_pg:photos_sr":0,
    "qs_pg:pop_sr":0,
    "qs_pg:qs_pg_placetype":"locality",
    "qs_pg:qs_pg_placetype_gp":"Town",
    "qs_pg:woe_adm0":23424923,
    "woe:adm0_id":23424923,
    "woe:name_adm0":"Polska",
    "woe:name_adm1":"Dolnosl\u0105skie",
    "woe:placetype":"Town",
    "wof:name":"Pustk\u00f3w \u017burawski",
    "wof:placetype":"locality"
},
  "geometry": {"coordinates":[16.86487,50.96199],"type":"Point"}
}