{
  "type": "Feature",
  "properties": {
    "gn:admin1_code":"73.0",
    "gn:admin2_code":"417.0",
    "gn:admin3_code":"41702.0",
    "gn:asciiname":"Lobdowo",
    "gn:country_code":"PL",
    "gn:dem":95,
    "gn:feature_class":"P",
    "gn:feature_code":"PPL",
    "gn:name":"\u0141obdowo",
    "gn:population":0,
    "gn:timezone":"Europe/Warsaw",
    "iso:country":"PL",
    "name:ceb_x_preferred":[
        "\u0141obdowo"
    ],
    "name:nld_x_preferred":[
        "\u0141obdowo"
    ],
    "name:pol_x_preferred":[
        "\u0141obdowo"
    ],
    "name:ukr_x_preferred":[
        "\u041b\u043e\u0431\u0434\u043e\u0432\u043e"
    ],
    "wof:name":"Lobdowo",
    "wof:placetype":"locality"
},
  "geometry": {"coordinates":[19.11614,53.21787],"type":"Point"}
}