{
  "type": "Feature",
  "properties": {
    "gn:gn_country":"PL",
    "gn:gn_fcode":"PPL",
    "gn:gn_pop":557,
    "gn:population":557,
    "iso:country":"PL",
    "name:eng_x_preferred":[
        "G\u00f3ra W\u0142odowska"
    ],
    "name:fra_x_preferred":[
        "G\u00f3ra W\u0142odowska"
    ],
    "name:nan_x_preferred":[
        "G\u00f3ra W\u0142odowska"
    ],
    "name:pol_x_preferred":[
        "G\u00f3ra W\u0142odowska"
    ],
    "name:unk_x_variant":[
        "G\u00f3ra W\u0142odawska"
    ],
    "qs_pg:aaroncc":"PL",
    "qs_pg:gn_country":"PL",
    "qs_pg:gn_fcode":"PPL",
    "qs_pg:gn_pop":557,
    "qs_pg:name":"G\u00f3ra W\u0142odowska",
    "qs_pg:name_adm0":"Polska",
    "qs_pg:name_adm1":"Sl\u0105skie",
    "qs_pg:photos_9r":0,
    "qs_pg:photos_sr":0,
    "qs_pg:pop_sr":2,
    "qs_pg:qs_pg_placetype":"locality",
    "qs_pg:qs_pg_placetype_gp":"Town",
    "qs_pg:woe_adm0":23424923,
    "woe:adm0_id":23424923,
    "woe:name_adm0":"Polska",
    "woe:name_adm1":"Sl\u0105skie",
    "woe:placetype":"Town",
    "wof:name":"G\u00f3ra W\u0142odowska",
    "wof:placetype":"locality",
    "wof:population":557
},
  "geometry": {"coordinates":[19.44803,50.57675],"type":"Point"}
}