{
  "type": "Feature",
  "properties": {
    "gn:admin1_code":"85.0",
    "gn:admin2_code":"2804.0",
    "gn:admin3_code":"280404.0",
    "gn:asciiname":"Kepniewo",
    "gn:cc2":"PL",
    "gn:country_code":"PL",
    "gn:dem":-1,
    "gn:feature_class":"P",
    "gn:feature_code":"PPL",
    "gn:name":"K\u0119pniewo",
    "gn:population":0,
    "gn:timezone":"Europe/Warsaw",
    "iso:country":"PL",
    "name:ceb_x_preferred":[
        "K\u0119pniewo"
    ],
    "name:pol_x_preferred":[
        "K\u0119pniewo"
    ],
    "name:ukr_x_preferred":[
        "\u041a\u0435\u043c\u043f\u043d\u0435\u0432\u043e"
    ],
    "name:und_x_variant":[
        "Kampenau"
    ],
    "wof:name":"Kepniewo",
    "wof:placetype":"locality"
},
  "geometry": {"coordinates":[19.35774,54.01836],"type":"Point"}
}