{
  "type": "Feature",
  "properties": {
    "gn:admin1_code":"80.0",
    "gn:admin2_code":"1805.0",
    "gn:admin3_code":"180508.0",
    "gn:asciiname":"Klopotnica",
    "gn:country_code":"PL",
    "gn:dem":318,
    "gn:feature_class":"P",
    "gn:feature_code":"PPL",
    "gn:name":"K\u0142opotnica",
    "gn:population":0,
    "gn:timezone":"Europe/Warsaw",
    "iso:country":"PL",
    "name:pol_x_preferred":[
        "K\u0142opotnica"
    ],
    "name:ukr_x_preferred":[
        "\u041a\u043b\u043e\u043f\u043e\u0442\u043d\u0438\u0446\u044f"
    ],
    "name:und_x_variant":[
        "K\u0142opotnica"
    ],
    "wof:name":"Klopotnica",
    "wof:placetype":"locality"
},
  "geometry": {"coordinates":[21.42076,49.61883],"type":"Point"}
}