{
  "type": "Feature",
  "properties": {
    "gn:admin1_code":"82.0",
    "gn:admin2_code":"2205.0",
    "gn:admin3_code":"220506.0",
    "gn:asciiname":"Gapowo",
    "gn:country_code":"PL",
    "gn:dem":193,
    "gn:feature_class":"P",
    "gn:feature_code":"PPL",
    "gn:name":"Gapowo",
    "gn:population":0,
    "gn:timezone":"Europe/Warsaw",
    "iso:country":"PL",
    "name:ceb_x_preferred":[
        "Gapowo"
    ],
    "name:csb_x_preferred":[
        "Gap\u00f2w\u00f2"
    ],
    "name:nld_x_preferred":[
        "Gapowo"
    ],
    "name:pol_x_preferred":[
        "Gapowo"
    ],
    "name:ukr_x_preferred":[
        "\u0490\u0430\u043f\u043e\u0432\u043e"
    ],
    "wof:name":"Gapowo",
    "wof:placetype":"locality"
},
  "geometry": {"coordinates":[17.90472999999999,54.21176],"type":"Point"}
}