{
  "type": "Feature",
  "properties": {
    "gn:admin1_code":"82.0",
    "gn:admin2_code":"2261.0",
    "gn:admin3_code":"226101.0",
    "gn:asciiname":"Bretowo",
    "gn:country_code":"PL",
    "gn:dem":53,
    "gn:feature_class":"P",
    "gn:feature_code":"PPL",
    "gn:name":"Br\u0119towo",
    "gn:population":0,
    "gn:timezone":"Europe/Warsaw",
    "iso:country":"PL",
    "name:csb_x_preferred":[
        "Br\u00e3tow\u00f2"
    ],
    "name:deu_x_preferred":[
        "Brentau"
    ],
    "name:deu_x_variant":[
        "Br\u0119towo"
    ],
    "name:ita_x_preferred":[
        "Br\u0119towo"
    ],
    "name:pol_x_preferred":[
        "Br\u0119towo"
    ],
    "wof:name":"Bretowo",
    "wof:placetype":"neighbourhood"
},
  "geometry": {"coordinates":[18.57105,54.37009000000001],"type":"Point"}
}