{
  "type": "Feature",
  "properties": {
    "gn:admin1_code":"79.0",
    "gn:admin2_code":"1608.0",
    "gn:admin3_code":"160804.0",
    "gn:asciiname":"Soltysy",
    "gn:country_code":"PL",
    "gn:dem":215,
    "gn:feature_class":"P",
    "gn:feature_code":"PPL",
    "gn:name":"So\u0142tysy",
    "gn:population":0,
    "gn:timezone":"Europe/Warsaw",
    "iso:country":"PL",
    "name:pol_x_preferred":[
        "So\u0142tysy"
    ],
    "name:rus_x_preferred":[
        "\u0421\u043e\u043b\u0442\u044b\u0441\u044b"
    ],
    "name:ukr_x_preferred":[
        "\u0421\u043e\u043b\u0442\u0438\u0441\u0438"
    ],
    "wof:name":"Soltysy",
    "wof:placetype":"locality"
},
  "geometry": {"coordinates":[18.53127000000001,51.11387],"type":"Point"}
}