{
  "type": "Feature",
  "properties": {
    "gn:gn_country":"PL",
    "gn:gn_fcode":"PPL",
    "gn:gn_pop":363,
    "gn:population":363,
    "iso:country":"PL",
    "name:eng_x_preferred":[
        "Kierpie\u0144"
    ],
    "name:fre_x_preferred":[
        "Kierpie\u0144"
    ],
    "name:ger_x_preferred":[
        "Kerpen"
    ],
    "name:nan_x_preferred":[
        "Kierpie\u0144"
    ],
    "name:per_x_preferred":[
        "\u06a9\u06cc\u0631\u067e\u06cc\u0646\u06af"
    ],
    "name:pol_x_preferred":[
        "Kierpie\u0144"
    ],
    "qs_pg:aaroncc":"PL",
    "qs_pg:gn_country":"PL",
    "qs_pg:gn_fcode":"PPL",
    "qs_pg:gn_pop":363,
    "qs_pg:name":"Kierpie\u0144",
    "qs_pg:name_adm0":"Polska",
    "qs_pg:name_adm1":"Opolskie",
    "qs_pg:photos_9r":0,
    "qs_pg:photos_sr":0,
    "qs_pg:pop_sr":2,
    "qs_pg:qs_pg_placetype":"locality",
    "qs_pg:qs_pg_placetype_gp":"Town",
    "qs_pg:woe_adm0":23424923,
    "woe:adm0_id":23424923,
    "woe:name_adm0":"Polska",
    "woe:name_adm1":"Opolskie",
    "woe:placetype":"Town",
    "wof:name":"Kierpie\u0144",
    "wof:placetype":"locality",
    "wof:population":363
},
  "geometry": {"coordinates":[17.85673,50.39178],"type":"Point"}
}