{
  "type": "Feature",
  "properties": {
    "gn:admin1_code":"78.0",
    "gn:admin2_code":"1408.0",
    "gn:admin3_code":"140803.0",
    "gn:asciiname":"Wola Aleksandra",
    "gn:cc2":"PL",
    "gn:country_code":"PL",
    "gn:dem":77,
    "gn:feature_class":"P",
    "gn:feature_code":"PPL",
    "gn:name":"Wola Aleksandra",
    "gn:population":0,
    "gn:timezone":"Europe/Warsaw",
    "iso:country":"PL",
    "name:und_x_variant":[
        "Wola Aleleksandra"
    ],
    "wof:name":"Wola Aleksandra",
    "wof:placetype":"locality"
},
  "geometry": {"coordinates":[20.98818,52.40357],"type":"Point"}
}