{
  "type": "Feature",
  "properties": {
    "gn:admin1_code":"75.0",
    "gn:admin2_code":"613.0",
    "gn:admin3_code":"61307.0",
    "gn:asciiname":"Bohutyn",
    "gn:cc2":"PL",
    "gn:country_code":"PL",
    "gn:dem":160,
    "gn:feature_class":"P",
    "gn:feature_code":"PPL",
    "gn:name":"Bohutyn",
    "gn:population":0,
    "gn:timezone":"Europe/Warsaw",
    "iso:country":"PL",
    "name:fra_x_preferred":[
        "Bohutyn"
    ],
    "name:pol_x_preferred":[
        "Bohutyn"
    ],
    "name:ukr_x_preferred":[
        "\u0411\u043e\u0433\u0443\u0442\u0438\u043d"
    ],
    "name:und_x_variant":[
        "Bohaty\u0144"
    ],
    "wof:name":"Bohutyn",
    "wof:placetype":"locality"
},
  "geometry": {"coordinates":[23.07163,51.54964],"type":"Point"}
}