{
  "type": "Feature",
  "properties": {
    "gn:admin1_code":"78.0",
    "gn:admin2_code":"1420.0",
    "gn:admin3_code":"142010.0",
    "gn:asciiname":"Kraszewo Slawecin",
    "gn:country_code":"PL",
    "gn:dem":108,
    "gn:feature_class":"P",
    "gn:feature_code":"PPL",
    "gn:name":"Kraszewo S\u0142aw\u0119cin",
    "gn:population":0,
    "gn:timezone":"Europe/Warsaw",
    "iso:country":"PL",
    "wof:name":"Kraszewo Slawecin",
    "wof:placetype":"locality"
},
  "geometry": {"coordinates":[20.07025,52.78375],"type":"Point"}
}