{
  "type": "Feature",
  "properties": {
    "gn:admin1_code":"87.0",
    "gn:admin2_code":"3201.0",
    "gn:admin3_code":"320104.0",
    "gn:asciiname":"Dobrowo",
    "gn:country_code":"PL",
    "gn:dem":42,
    "gn:feature_class":"P",
    "gn:feature_code":"PPL",
    "gn:name":"Dobrowo",
    "gn:population":0,
    "gn:timezone":"Europe/Warsaw",
    "iso:country":"PL",
    "name:azb_x_preferred":[
        "\u062f\u0648\u0628\u0631\u0648\u0648\u0648"
    ],
    "name:ceb_x_preferred":[
        "Dobrowo"
    ],
    "name:deu_x_preferred":[
        "Dobrowo"
    ],
    "name:fas_x_preferred":[
        "\u062f\u0648\u0628\u0631\u0648\u0648\u0648"
    ],
    "name:nld_x_preferred":[
        "Dobrowo"
    ],
    "name:pol_x_preferred":[
        "Dobrowo"
    ],
    "name:ukr_x_preferred":[
        "\u0414\u043e\u0431\u0440\u043e\u0432\u043e"
    ],
    "name:und_x_variant":[
        "Dubberow",
        "Dubrowo"
    ],
    "name:vie_x_preferred":[
        "Dobrowo"
    ],
    "wof:name":"Dobrowo",
    "wof:placetype":"locality"
},
  "geometry": {"coordinates":[16.11862,53.98919],"type":"Point"}
}