{
  "type": "Feature",
  "properties": {
    "gn:admin1_code":"87.0",
    "gn:admin2_code":"3201.0",
    "gn:admin3_code":"320104.0",
    "gn:asciiname":"Dobrowo",
    "gn:country_code":"PL",
    "gn:dem":42,
    "gn:feature_class":"P",
    "gn:feature_code":"PPL",
    "gn:name":"Dobrowo",
    "gn:population":0,
    "gn:timezone":"Europe/Warsaw",
    "iso:country":"PL",
    "name:und_x_variant":[
        "Dubberow",
        "Dubrowo",
        "Dobrowo"
    ],
    "wof:name":"Dobrowo",
    "wof:placetype":"locality"
},
  "geometry": {"coordinates":[16.11862,53.98919],"type":"Point"}
}