{
  "type": "Feature",
  "properties": {
    "gn:admin1_code":"82.0",
    "gn:admin2_code":"2213.0",
    "gn:admin3_code":"221312.0",
    "gn:asciiname":"Koteze",
    "gn:country_code":"PL",
    "gn:dem":103,
    "gn:feature_class":"P",
    "gn:feature_code":"PPL",
    "gn:name":"Kote\u017ce",
    "gn:population":0,
    "gn:timezone":"Europe/Warsaw",
    "iso:country":"PL",
    "name:und_x_variant":[
        "Kote\u017ce"
    ],
    "wof:name":"Koteze",
    "wof:placetype":"locality"
},
  "geometry": {"coordinates":[18.49102,53.9245],"type":"Point"}
}