{
  "type": "Feature",
  "properties": {
    "gn:admin1_code":"81.0",
    "gn:admin2_code":"2003.0",
    "gn:admin3_code":"200304.0",
    "gn:asciiname":"Wojtki",
    "gn:country_code":"PL",
    "gn:dem":135,
    "gn:feature_class":"P",
    "gn:feature_code":"PPL",
    "gn:name":"Wojtki",
    "gn:population":0,
    "gn:timezone":"Europe/Warsaw",
    "iso:country":"PL",
    "name:ceb_x_preferred":[
        "Wojtki"
    ],
    "name:fra_x_preferred":[
        "Wojtki"
    ],
    "name:lit_x_preferred":[
        "Vojtkai"
    ],
    "name:pol_x_preferred":[
        "Wojtki"
    ],
    "name:ukr_x_preferred":[
        "\u0412\u043e\u0439\u0442\u043a\u0456"
    ],
    "wof:name":"Wojtki",
    "wof:placetype":"locality"
},
  "geometry": {"coordinates":[22.93843,52.65647],"type":"Point"}
}