{
  "type": "Feature",
  "properties": {
    "iso:country":"PL",
    "name:pol_x_preferred":[
        "D\u0105bie"
    ],
    "wof:name":"D\u0105bie",
    "wof:placetype":"locality"
},
  "geometry": {"coordinates":[15.192245471549,51.9959110701663],"type":"Point"}
}