{
  "type": "Feature",
  "properties": {
    "iso:country":"PL",
    "name:ceb_x_preferred":[
        "D\u0105bie"
    ],
    "name:deu_x_preferred":[
        "D\u0105bie"
    ],
    "name:epo_x_preferred":[
        "D\u0105bie"
    ],
    "name:fra_x_preferred":[
        "D\u0105bie"
    ],
    "name:ita_x_preferred":[
        "D\u0105bie"
    ],
    "name:nld_x_preferred":[
        "D\u0105bie"
    ],
    "name:pol_x_preferred":[
        "D\u0105bie"
    ],
    "name:rus_x_preferred":[
        "\u0414\u043e\u043c\u0431\u0435"
    ],
    "name:srp_x_preferred":[
        "\u0414\u043e\u043c\u0431\u0458\u0435"
    ],
    "name:swe_x_preferred":[
        "D\u0105bie"
    ],
    "name:ukr_x_preferred":[
        "\u0414\u043e\u043c\u0431'\u0454"
    ],
    "wof:coterminous":[
        1125396417
    ],
    "wof:name":"D\u0105bie",
    "wof:placetype":"locality"
},
  "geometry": {"coordinates":[15.192245471549,51.9959110701663],"type":"Point"}
}