{
  "type": "Feature",
  "properties": {
    "gn:admin1_code":"81.0",
    "gn:admin2_code":"2011.0",
    "gn:admin3_code":"201107.0",
    "gn:asciiname":"Zalesie",
    "gn:country_code":"PL",
    "gn:dem":164,
    "gn:feature_class":"P",
    "gn:feature_code":"PPL",
    "gn:name":"Zalesie",
    "gn:population":0,
    "gn:timezone":"Europe/Warsaw",
    "iso:country":"PL",
    "name:ceb_x_preferred":[
        "Zalesie"
    ],
    "name:lit_x_preferred":[
        "Zalesiai"
    ],
    "name:pol_x_preferred":[
        "Zalesie"
    ],
    "name:ukr_x_preferred":[
        "\u0417\u0430\u043b\u0435\u0441\u0435"
    ],
    "wof:name":"Zalesie",
    "wof:placetype":"locality"
},
  "geometry": {"coordinates":[23.54696,53.55336],"type":"Point"}
}