{
  "type": "Feature",
  "properties": {
    "gn:admin1_code":"87.0",
    "gn:admin2_code":"3214.0",
    "gn:admin3_code":"321404.0",
    "gn:asciiname":"Morzyca",
    "gn:country_code":"PL",
    "gn:dem":34,
    "gn:feature_class":"P",
    "gn:feature_code":"PPL",
    "gn:name":"Morzyca",
    "gn:population":0,
    "gn:timezone":"Europe/Warsaw",
    "iso:country":"PL",
    "name:vie_x_preferred":[
        "Morzyca"
    ],
    "wof:name":"Morzyca",
    "wof:placetype":"locality"
},
  "geometry": {"coordinates":[15.14623,53.21038000000001],"type":"Point"}
}