{
  "type": "Feature",
  "properties": {
    "gn:admin1_code":"78.0",
    "gn:admin2_code":"1403.0",
    "gn:admin3_code":"140306.0",
    "gn:asciiname":"Budy Krepskie",
    "gn:country_code":"PL",
    "gn:dem":132,
    "gn:feature_class":"P",
    "gn:feature_code":"PPL",
    "gn:name":"Budy Kr\u0119pskie",
    "gn:population":0,
    "gn:timezone":"Europe/Warsaw",
    "iso:country":"PL",
    "name:und_x_variant":[
        "Budy Kr\u0119pskie"
    ],
    "wof:name":"Budy Krepskie",
    "wof:placetype":"locality"
},
  "geometry": {"coordinates":[21.55706,51.75435],"type":"Point"}
}