{
  "type": "Feature",
  "properties": {
    "gn:admin1_code":"78.0",
    "gn:admin2_code":"1403.0",
    "gn:admin3_code":"140306.0",
    "gn:asciiname":"Budy Krepskie",
    "gn:country_code":"PL",
    "gn:dem":132,
    "gn:feature_class":"P",
    "gn:feature_code":"PPL",
    "gn:name":"Budy Kr\u0119pskie",
    "gn:population":0,
    "gn:timezone":"Europe/Warsaw",
    "iso:country":"PL",
    "name:azb_x_preferred":[
        "\u0628\u0648\u062f \u06a9\u0631\u0646\u067e\u0633\u06a9\u06cc\u0647"
    ],
    "name:ell_x_preferred":[
        "\u039c\u03c0\u03bf\u03cd\u03bd\u03c4\u03b9 \u039a\u03c1\u03ad\u03c0\u03c3\u03ba\u03b9\u03b5"
    ],
    "name:fas_x_preferred":[
        "\u0628\u0648\u062f \u06a9\u0631\u0646\u067e\u0633\u06a9\u06cc\u0647"
    ],
    "name:fra_x_preferred":[
        "Budy Kr\u0119pskie"
    ],
    "name:pol_x_preferred":[
        "Budy Kr\u0119pskie"
    ],
    "name:spa_x_preferred":[
        "Budy Kr\u0119pskie"
    ],
    "name:ukr_x_preferred":[
        "\u0411\u0443\u0434\u0438-\u041a\u0440\u0435\u043c\u043f\u0441\u044c\u043a\u0456"
    ],
    "name:und_x_variant":[
        "Budy Kr\u0119pskie"
    ],
    "wof:name":"Budy Krepskie",
    "wof:placetype":"locality"
},
  "geometry": {"coordinates":[21.55706,51.75435],"type":"Point"}
}