{
  "type": "Feature",
  "properties": {
    "gn:admin1_code":"84.0",
    "gn:admin2_code":"2602.0",
    "gn:admin3_code":"260202.0",
    "gn:asciiname":"Pierscien",
    "gn:country_code":"PL",
    "gn:dem":258,
    "gn:feature_class":"P",
    "gn:feature_code":"PPL",
    "gn:name":"Pier\u015bcien",
    "gn:population":0,
    "gn:timezone":"Europe/Warsaw",
    "iso:country":"PL",
    "wof:name":"Pierscien",
    "wof:placetype":"locality"
},
  "geometry": {"coordinates":[20.20493,50.61506],"type":"Point"}
}