{
  "type": "Feature",
  "properties": {
    "gn:admin1_code":"81.0",
    "gn:admin2_code":"2002.0",
    "gn:admin3_code":"200203.0",
    "gn:asciiname":"Kozince",
    "gn:country_code":"PL",
    "gn:dem":136,
    "gn:feature_class":"P",
    "gn:feature_code":"PPL",
    "gn:name":"Kozi\u0144ce",
    "gn:population":0,
    "gn:timezone":"Europe/Warsaw",
    "iso:country":"PL",
    "name:und_x_variant":[
        "Kozi\u0144ce"
    ],
    "wof:name":"Kozince",
    "wof:placetype":"locality"
},
  "geometry": {"coordinates":[22.9843,53.24463000000001],"type":"Point"}
}