{
  "type": "Feature",
  "properties": {
    "gn:admin1_code":"81.0",
    "gn:admin2_code":"2002.0",
    "gn:admin3_code":"200203.0",
    "gn:asciiname":"Kozince",
    "gn:country_code":"PL",
    "gn:dem":136,
    "gn:feature_class":"P",
    "gn:feature_code":"PPL",
    "gn:name":"Kozi\u0144ce",
    "gn:population":0,
    "gn:timezone":"Europe/Warsaw",
    "iso:country":"PL",
    "name:fas_x_preferred":[
        "\u06a9\u0648\u0698\u0646\u06af\u062a\u0633\u0647"
    ],
    "name:fra_x_preferred":[
        "Kozi\u0144ce"
    ],
    "name:lit_x_preferred":[
        "Kozinc\u0117"
    ],
    "name:pol_x_preferred":[
        "Kozi\u0144ce"
    ],
    "name:ukr_x_preferred":[
        "\u041a\u043e\u0437\u0456\u043d\u044c\u0446\u0435"
    ],
    "name:und_x_variant":[
        "Kozi\u0144ce"
    ],
    "wof:name":"Kozince",
    "wof:placetype":"locality"
},
  "geometry": {"coordinates":[22.9843,53.24463000000001],"type":"Point"}
}