{
  "type": "Feature",
  "properties": {
    "gn:admin1_code":"80.0",
    "gn:admin2_code":"1803.0",
    "gn:admin3_code":"180302.0",
    "gn:asciiname":"Baczalka",
    "gn:country_code":"PL",
    "gn:dem":305,
    "gn:feature_class":"P",
    "gn:feature_code":"PPL",
    "gn:name":"B\u0105cza\u0142ka",
    "gn:population":0,
    "gn:timezone":"Europe/Warsaw",
    "iso:country":"PL",
    "name:ceb_x_preferred":[
        "B\u0105cza\u0142ka"
    ],
    "name:nld_x_preferred":[
        "B\u0105cza\u0142ka"
    ],
    "name:pol_x_preferred":[
        "B\u0105cza\u0142ka"
    ],
    "name:ukr_x_preferred":[
        "\u0411\u043e\u043d\u0447\u0430\u043b\u043a\u0430"
    ],
    "wof:name":"Baczalka",
    "wof:placetype":"locality"
},
  "geometry": {"coordinates":[21.47913,49.91056],"type":"Point"}
}