{
  "type": "Feature",
  "properties": {
    "gn:admin1_code":"80.0",
    "gn:admin2_code":"1813.0",
    "gn:admin3_code":"181303.0",
    "gn:asciiname":"Koniuszki",
    "gn:country_code":"PL",
    "gn:dem":225,
    "gn:feature_class":"P",
    "gn:feature_code":"PPL",
    "gn:name":"Koniuszki",
    "gn:population":0,
    "gn:timezone":"Europe/Warsaw",
    "iso:country":"PL",
    "wof:name":"Koniuszki",
    "wof:placetype":"locality"
},
  "geometry": {"coordinates":[22.7824,49.71115],"type":"Point"}
}