{
  "type": "Feature",
  "properties": {
    "gn:admin1_code":"78.0",
    "gn:admin2_code":"1427.0",
    "gn:admin3_code":"142705.0",
    "gn:asciiname":"Susk",
    "gn:country_code":"PL",
    "gn:dem":118,
    "gn:feature_class":"P",
    "gn:feature_code":"PPL",
    "gn:name":"Susk",
    "gn:population":0,
    "gn:timezone":"Europe/Warsaw",
    "iso:country":"PL",
    "name:ceb_x_preferred":[
        "Susk"
    ],
    "name:fra_x_preferred":[
        "Susk"
    ],
    "name:pol_x_preferred":[
        "Susk"
    ],
    "name:ukr_x_preferred":[
        "\u0421\u0443\u0441\u044c\u043a"
    ],
    "wof:name":"Susk",
    "wof:placetype":"locality"
},
  "geometry": {"coordinates":[19.68445,52.80363000000001],"type":"Point"}
}