{
  "type": "Feature",
  "properties": {
    "gn:admin1_code":"81.0",
    "gn:admin2_code":"2008.0",
    "gn:admin3_code":"200807.0",
    "gn:asciiname":"Wilamowka",
    "gn:country_code":"PL",
    "gn:dem":108,
    "gn:feature_class":"P",
    "gn:feature_code":"PPL",
    "gn:name":"Wilam\u00f3wka",
    "gn:population":0,
    "gn:timezone":"Europe/Warsaw",
    "iso:country":"PL",
    "name:fra_x_preferred":[
        "Wilam\u00f3wka"
    ],
    "name:lit_x_preferred":[
        "Vilamuvka"
    ],
    "name:pol_x_preferred":[
        "Wilam\u00f3wka"
    ],
    "name:ukr_x_preferred":[
        "\u0412\u0456\u043b\u044f\u043c\u0443\u0432\u043a\u0430"
    ],
    "wof:name":"Wilamowka",
    "wof:placetype":"locality"
},
  "geometry": {"coordinates":[22.61645,53.40983000000001],"type":"Point"}
}