{
  "type": "Feature",
  "properties": {
    "gn:admin1_code":"78.0",
    "gn:admin2_code":"1414.0",
    "gn:admin3_code":"141404.0",
    "gn:asciiname":"Andzin",
    "gn:country_code":"PL",
    "gn:dem":91,
    "gn:feature_class":"P",
    "gn:feature_code":"PPL",
    "gn:name":"Andzin",
    "gn:population":0,
    "gn:timezone":"Europe/Warsaw",
    "iso:country":"PL",
    "name:fra_x_preferred":[
        "Andzin"
    ],
    "name:mkd_x_preferred":[
        "\u0410\u043d\u0453\u0438\u043d"
    ],
    "name:pol_x_preferred":[
        "Andzin"
    ],
    "name:srp_x_preferred":[
        "\u0410\u043d\u0452\u0438\u043d"
    ],
    "name:ukr_x_preferred":[
        "\u0410\u043d\u0434\u0437\u0456\u043d"
    ],
    "wof:name":"Andzin",
    "wof:placetype":"locality"
},
  "geometry": {"coordinates":[20.68306,52.58561],"type":"Point"}
}