{
  "type": "Feature",
  "properties": {
    "gn:admin1_code":"75.0",
    "gn:admin2_code":"605.0",
    "gn:admin3_code":"60507.0",
    "gn:asciiname":"Stawki",
    "gn:country_code":"PL",
    "gn:dem":200,
    "gn:feature_class":"P",
    "gn:feature_code":"PPL",
    "gn:name":"Stawki",
    "gn:population":0,
    "gn:timezone":"Europe/Warsaw",
    "iso:country":"PL",
    "name:fra_x_preferred":[
        "Stawki"
    ],
    "name:pol_x_preferred":[
        "Stawki"
    ],
    "name:ukr_x_preferred":[
        "\u0421\u0442\u0430\u0432\u043a\u0456"
    ],
    "wof:name":"Stawki",
    "wof:placetype":"locality"
},
  "geometry": {"coordinates":[22.17633,50.77354],"type":"Point"}
}