{
  "type": "Feature",
  "properties": {
    "gn:admin1_code":"78.0",
    "gn:admin2_code":"1413.0",
    "gn:admin3_code":"141306.0",
    "gn:asciiname":"Jeze",
    "gn:country_code":"PL",
    "gn:dem":128,
    "gn:feature_class":"P",
    "gn:feature_code":"PPL",
    "gn:name":"Je\u017ce",
    "gn:population":0,
    "gn:timezone":"Europe/Warsaw",
    "iso:country":"PL",
    "name:fra_x_preferred":[
        "Je\u017ce"
    ],
    "name:pol_x_preferred":[
        "Je\u017ce"
    ],
    "name:ukr_x_preferred":[
        "\u0404\u0436\u0435"
    ],
    "wof:name":"Jeze",
    "wof:placetype":"locality"
},
  "geometry": {"coordinates":[20.47482,53.03001],"type":"Point"}
}