{
  "type": "Feature",
  "properties": {
    "gn:admin1_code":"75.0",
    "gn:admin2_code":"603.0",
    "gn:admin3_code":"60313.0",
    "gn:asciiname":"Witoldow",
    "gn:country_code":"PL",
    "gn:dem":248,
    "gn:feature_class":"P",
    "gn:feature_code":"PPL",
    "gn:name":"Witold\u00f3w",
    "gn:population":0,
    "gn:timezone":"Europe/Warsaw",
    "iso:country":"PL",
    "wof:name":"Witoldow",
    "wof:placetype":"locality"
},
  "geometry": {"coordinates":[23.5025,50.92211],"type":"Point"}
}