{
  "type": "Feature",
  "properties": {
    "gn:admin1_code":"84.0",
    "gn:admin2_code":"2605.0",
    "gn:admin3_code":"260501.0",
    "gn:asciiname":"Rudka",
    "gn:country_code":"PL",
    "gn:dem":226,
    "gn:feature_class":"P",
    "gn:feature_code":"PPL",
    "gn:name":"Rudka",
    "gn:population":0,
    "gn:timezone":"Europe/Warsaw",
    "iso:country":"PL",
    "name:pol_x_preferred":[
        "Rudka"
    ],
    "name:ukr_x_preferred":[
        "\u0420\u0443\u0434\u043a\u0430"
    ],
    "wof:name":"Rudka",
    "wof:placetype":"locality"
},
  "geometry": {"coordinates":[20.08087,51.12113],"type":"Point"}
}