{
  "type": "Feature",
  "properties": {
    "gn:admin1_code":"73.0",
    "gn:admin2_code":"418.0",
    "gn:admin3_code":"41810.0",
    "gn:asciiname":"Tadzin",
    "gn:country_code":"PL",
    "gn:dem":93,
    "gn:feature_class":"P",
    "gn:feature_code":"PPL",
    "gn:name":"Tadzin",
    "gn:population":0,
    "gn:timezone":"Europe/Warsaw",
    "iso:country":"PL",
    "name:pol_x_preferred":[
        "Tadzin"
    ],
    "name:ukr_x_preferred":[
        "\u0422\u0430\u0434\u0437\u0456\u043d"
    ],
    "wof:name":"Tadzin",
    "wof:placetype":"locality"
},
  "geometry": {"coordinates":[18.84397,52.74506],"type":"Point"}
}