{
  "type": "Feature",
  "properties": {
    "gn:country":"PL",
    "gn:fcode":"PPL",
    "gn:population":100,
    "iso:country":"PL",
    "name:deu_x_preferred":[
        "Piaski"
    ],
    "name:dsb_x_preferred":[
        "Piaski"
    ],
    "name:epo_x_preferred":[
        "Piaski"
    ],
    "name:fra_x_preferred":[
        "Piaski"
    ],
    "name:heb_x_preferred":[
        "\u05e4\u05d9\u05d0\u05e1\u05e7\u05d9"
    ],
    "name:lav_x_preferred":[
        "Pjaski"
    ],
    "name:msa_x_preferred":[
        "Piaski"
    ],
    "name:nld_x_preferred":[
        "Piaski"
    ],
    "name:pol_x_preferred":[
        "Piaski"
    ],
    "name:por_x_preferred":[
        "Piaski"
    ],
    "name:ron_x_preferred":[
        "Piaski"
    ],
    "name:rus_x_preferred":[
        "\u041f\u044f\u0441\u043a\u0438"
    ],
    "name:slk_x_preferred":[
        "Piaski"
    ],
    "name:srp_x_preferred":[
        "\u041f\u0458\u0430\u0441\u043a\u0438"
    ],
    "name:ukr_x_preferred":[
        "\u041f\u044f\u0441\u043a\u0456"
    ],
    "name:und_x_variant":[
        "Piasken"
    ],
    "name:vie_x_preferred":[
        "Piaski"
    ],
    "name:zho_x_preferred":[
        "\u76ae\u4e9e\u65af\u57fa"
    ],
    "qs_pg:aaroncc":"PL",
    "qs_pg:gn_country":"PL",
    "qs_pg:gn_fcode":"PPL",
    "qs_pg:gn_pop":100,
    "qs_pg:name":"Piaski",
    "qs_pg:name_adm0":"Polska",
    "qs_pg:name_adm1":"Mazowieckie",
    "qs_pg:photos_9r":0,
    "qs_pg:photos_sr":0,
    "qs_pg:pop_sr":1,
    "qs_pg:qs_pg_placetype":"locality",
    "qs_pg:qs_pg_placetype_gp":"Town",
    "qs_pg:woe_adm0":23424923,
    "woe:adm0_id":23424923,
    "woe:name_adm0":"Polska",
    "woe:name_adm1":"Mazowieckie",
    "woe:placetype":"Town",
    "wof:name":"Piaski",
    "wof:placetype":"locality",
    "wof:population":100
},
  "geometry": {"coordinates":[21.58137,53.68633],"type":"Point"}
}