{
  "type": "Feature",
  "properties": {
    "gn:gn_country":"PL",
    "gn:gn_fcode":"PPL",
    "gn:gn_pop":100,
    "gn:population":100,
    "iso:country":"PL",
    "name:rus_x_preferred":[
        "\u041f\u044f\u0441\u043a\u0438"
    ],
    "name:unk_x_variant":[
        "Piasken"
    ],
    "qs_pg:aaroncc":"PL",
    "qs_pg:gn_country":"PL",
    "qs_pg:gn_fcode":"PPL",
    "qs_pg:gn_pop":100,
    "qs_pg:name":"Piaski",
    "qs_pg:name_adm0":"Polska",
    "qs_pg:name_adm1":"Mazowieckie",
    "qs_pg:photos_9r":0,
    "qs_pg:photos_sr":0,
    "qs_pg:pop_sr":1,
    "qs_pg:qs_pg_placetype":"locality",
    "qs_pg:qs_pg_placetype_gp":"Town",
    "qs_pg:woe_adm0":23424923,
    "woe:adm0_id":23424923,
    "woe:name_adm0":"Polska",
    "woe:name_adm1":"Mazowieckie",
    "woe:placetype":"Town",
    "wof:name":"Piaski",
    "wof:placetype":"locality",
    "wof:population":100
},
  "geometry": {"coordinates":[21.58137,53.68633],"type":"Point"}
}