{
  "type": "Feature",
  "properties": {
    "gn:admin1_code":"76.0",
    "gn:admin2_code":"810.0",
    "gn:admin3_code":"81006.0",
    "gn:asciiname":"Nowa Jablona",
    "gn:country_code":"PL",
    "gn:dem":143,
    "gn:feature_class":"P",
    "gn:feature_code":"PPL",
    "gn:name":"Nowa Jab\u0142ona",
    "gn:population":0,
    "gn:timezone":"Europe/Warsaw",
    "iso:country":"PL",
    "name:deu_x_historical":[
        "Neu Gabel"
    ],
    "name:deu_x_preferred":[
        "Neu Gabel"
    ],
    "name:fra_x_preferred":[
        "Nowa Jab\u0142ona"
    ],
    "name:pol_x_preferred":[
        "Nowa Jab\u0142ona"
    ],
    "name:ukr_x_preferred":[
        "\u041d\u043e\u0432\u0430 \u042f\u0431\u043b\u043e\u043d\u0430"
    ],
    "wof:name":"Nowa Jablona",
    "wof:placetype":"locality"
},
  "geometry": {"coordinates":[15.80988,51.62996],"type":"Point"}
}