{
  "type": "Feature",
  "properties": {
    "gn:admin1_code":"74.0",
    "gn:admin2_code":"1004.0",
    "gn:admin3_code":"100405.0",
    "gn:asciiname":"Dabie",
    "gn:country_code":"PL",
    "gn:dem":116,
    "gn:feature_class":"P",
    "gn:feature_code":"PPL",
    "gn:name":"D\u0105bie",
    "gn:population":0,
    "gn:timezone":"Europe/Warsaw",
    "iso:country":"PL",
    "wof:name":"Dabie",
    "wof:placetype":"locality"
},
  "geometry": {"coordinates":[19.16522,52.10053],"type":"Point"}
}