{
  "type": "Feature",
  "properties": {
    "gn:admin1_code":"75.0",
    "gn:admin2_code":"604.0",
    "gn:admin3_code":"60405.0",
    "gn:asciiname":"Malkow",
    "gn:country_code":"PL",
    "gn:dem":212,
    "gn:feature_class":"P",
    "gn:feature_code":"PPL",
    "gn:name":"Ma\u0142k\u00f3w",
    "gn:population":0,
    "gn:timezone":"Europe/Warsaw",
    "iso:country":"PL",
    "name:deu_x_preferred":[
        "Malkow"
    ],
    "wof:name":"Malkow",
    "wof:placetype":"locality"
},
  "geometry": {"coordinates":[24.01331,50.64905],"type":"Point"}
}