{
  "type": "Feature",
  "properties": {
    "gn:admin1_code":"78.0",
    "gn:admin2_code":"1436.0",
    "gn:admin3_code":"143603.0",
    "gn:asciiname":"Helenow",
    "gn:country_code":"PL",
    "gn:dem":160,
    "gn:feature_class":"P",
    "gn:feature_code":"PPL",
    "gn:name":"Helen\u00f3w",
    "gn:population":0,
    "gn:timezone":"Europe/Warsaw",
    "iso:country":"PL",
    "wof:name":"Helenow",
    "wof:placetype":"locality"
},
  "geometry": {"coordinates":[21.82151,51.36585],"type":"Point"}
}