{
  "type": "Feature",
  "properties": {
    "gn:admin1_code":"82.0",
    "gn:admin2_code":"2206.0",
    "gn:admin3_code":"220605.0",
    "gn:asciiname":"Wysin",
    "gn:country_code":"PL",
    "gn:dem":152,
    "gn:feature_class":"P",
    "gn:feature_code":"PPL",
    "gn:name":"Wysin",
    "gn:population":0,
    "gn:timezone":"Europe/Warsaw",
    "iso:country":"PL",
    "name:ceb_x_preferred":[
        "Wysin"
    ],
    "name:csb_x_preferred":[
        "W\u00ebs\u00ebno"
    ],
    "name:eng_x_preferred":[
        "Wysin"
    ],
    "name:pol_x_preferred":[
        "Wysin"
    ],
    "name:rus_x_preferred":[
        "\u0412\u044b\u0441\u0438\u043d"
    ],
    "name:ukr_x_preferred":[
        "\u0412\u0438\u0441\u0456\u043d"
    ],
    "wof:name":"Wysin",
    "wof:placetype":"locality"
},
  "geometry": {"coordinates":[18.28543,54.0999],"type":"Point"}
}