{
  "type": "Feature",
  "properties": {
    "iso:country":"PL",
    "name:eng_x_preferred":[
        "Osiedle Studenckie"
    ],
    "name:pol_x_preferred":[
        "Osiedle Studenckie"
    ],
    "wof:name":"Osiedle Studenckie",
    "wof:placetype":"neighbourhood"
},
  "geometry": {"coordinates":[16.91563266079267,52.42920403775607],"type":"Point"}
}