{
  "type": "Feature",
  "properties": {
    "gn:admin1_code":"73.0",
    "gn:admin2_code":"406.0",
    "gn:admin3_code":"40601.0",
    "gn:asciiname":"Szynych",
    "gn:country_code":"PL",
    "gn:dem":20,
    "gn:feature_class":"P",
    "gn:feature_code":"PPL",
    "gn:name":"Szynych",
    "gn:population":0,
    "gn:timezone":"Europe/Warsaw",
    "iso:country":"PL",
    "name:ceb_x_preferred":[
        "Szynych"
    ],
    "name:pol_x_preferred":[
        "Szynych"
    ],
    "name:ukr_x_preferred":[
        "\u0428\u0438\u043d\u0438\u0445"
    ],
    "wof:name":"Szynych",
    "wof:placetype":"locality"
},
  "geometry": {"coordinates":[18.66488,53.42373000000001],"type":"Point"}
}