{
  "type": "Feature",
  "properties": {
    "gn:admin1_code":"78.0",
    "gn:admin2_code":"1426.0",
    "gn:admin3_code":"142613.0",
    "gn:asciiname":"Lipiny",
    "gn:country_code":"PL",
    "gn:dem":170,
    "gn:feature_class":"P",
    "gn:feature_code":"PPL",
    "gn:name":"Lipiny",
    "gn:population":0,
    "gn:timezone":"Europe/Warsaw",
    "iso:country":"PL",
    "name:ces_x_preferred":[
        "Lipiny"
    ],
    "name:deu_x_preferred":[
        "Lipiny"
    ],
    "name:fra_x_preferred":[
        "Lipiny"
    ],
    "name:lit_x_preferred":[
        "Lipinai"
    ],
    "name:pol_x_preferred":[
        "Lipiny"
    ],
    "name:spa_x_preferred":[
        "Lipiny"
    ],
    "name:ukr_x_preferred":[
        "\u041b\u0456\u043f\u0456\u043d\u0438"
    ],
    "wof:name":"Lipiny",
    "wof:placetype":"locality"
},
  "geometry": {"coordinates":[22.3825,52.13085],"type":"Point"}
}