{
  "type": "Feature",
  "properties": {
    "gn:admin1_code":"82.0",
    "gn:admin2_code":"2205.0",
    "gn:admin3_code":"220504.0",
    "gn:asciiname":"Mojusz",
    "gn:country_code":"PL",
    "gn:dem":256,
    "gn:feature_class":"P",
    "gn:feature_code":"PPL",
    "gn:name":"Mojusz",
    "gn:population":0,
    "gn:timezone":"Europe/Warsaw",
    "iso:country":"PL",
    "name:ceb_x_preferred":[
        "Mojusz"
    ],
    "name:csb_x_preferred":[
        "M\u00f2jsz"
    ],
    "name:nld_x_preferred":[
        "Mojusz"
    ],
    "name:pol_x_preferred":[
        "Mojusz"
    ],
    "name:ukr_x_preferred":[
        "\u041c\u043e\u044e\u0448"
    ],
    "wof:name":"Mojusz",
    "wof:placetype":"locality"
},
  "geometry": {"coordinates":[17.96702999999999,54.346],"type":"Point"}
}