{
  "type": "Feature",
  "properties": {
    "gn:admin1_code":"78.0",
    "gn:admin2_code":"1419.0",
    "gn:admin3_code":"141905.0",
    "gn:asciiname":"Cieszewo",
    "gn:country_code":"PL",
    "gn:dem":134,
    "gn:feature_class":"P",
    "gn:feature_code":"PPL",
    "gn:name":"Cieszewo",
    "gn:population":0,
    "gn:timezone":"Europe/Warsaw",
    "iso:country":"PL",
    "name:fra_x_preferred":[
        "Cieszewo"
    ],
    "name:pol_x_preferred":[
        "Cieszewo"
    ],
    "name:ukr_x_preferred":[
        "\u0426\u0435\u0448\u0435\u0432\u043e"
    ],
    "wof:name":"Cieszewo",
    "wof:placetype":"locality"
},
  "geometry": {"coordinates":[19.96708,52.68476999999999],"type":"Point"}
}