{
  "type": "Feature",
  "properties": {
    "gn:admin1_code":"84.0",
    "gn:admin2_code":"2606.0",
    "gn:admin3_code":"260601.0",
    "gn:asciiname":"Nieskurzow Podlesie",
    "gn:country_code":"PL",
    "gn:dem":343,
    "gn:feature_class":"P",
    "gn:feature_code":"PPL",
    "gn:name":"Nieskurz\u00f3w Podlesie",
    "gn:population":0,
    "gn:timezone":"Europe/Warsaw",
    "iso:country":"PL",
    "wof:name":"Nieskurzow Podlesie",
    "wof:placetype":"locality"
},
  "geometry": {"coordinates":[21.21124,50.81077],"type":"Point"}
}