{
  "type": "Feature",
  "properties": {
    "gn:admin1_code":"78.0",
    "gn:admin2_code":"1402.0",
    "gn:admin3_code":"140205.0",
    "gn:asciiname":"Kolonia Sokolowo",
    "gn:country_code":"PL",
    "gn:dem":136,
    "gn:feature_class":"P",
    "gn:feature_code":"PPL",
    "gn:name":"Kolonia Soko\u0142owo",
    "gn:population":0,
    "gn:timezone":"Europe/Warsaw",
    "iso:country":"PL",
    "wof:name":"Kolonia Sokolowo",
    "wof:placetype":"locality"
},
  "geometry": {"coordinates":[20.61667000000001,53.05],"type":"Point"}
}