{
  "type": "Feature",
  "properties": {
    "gn:admin1_code":"77.0",
    "gn:admin2_code":"1211.0",
    "gn:admin3_code":"121105.0",
    "gn:asciiname":"Zaleslo",
    "gn:country_code":"PL",
    "gn:dem":677,
    "gn:feature_class":"P",
    "gn:feature_code":"PPL",
    "gn:name":"Zaleslo",
    "gn:population":0,
    "gn:timezone":"Europe/Warsaw",
    "iso:country":"PL",
    "wof:name":"Zaleslo",
    "wof:placetype":"locality"
},
  "geometry": {"coordinates":[19.76667,49.43333],"type":"Point"}
}