{
  "type": "Feature",
  "properties": {
    "gn:admin1_code":"81.0",
    "gn:admin2_code":"2006.0",
    "gn:admin3_code":"200604.0",
    "gn:asciiname":"Budy Kozlowka",
    "gn:country_code":"PL",
    "gn:dem":133,
    "gn:feature_class":"P",
    "gn:feature_code":"PPL",
    "gn:name":"Budy Koz\u0142\u00f3wka",
    "gn:population":0,
    "gn:timezone":"Europe/Warsaw",
    "iso:country":"PL",
    "name:lit_x_preferred":[
        "Bud\u0173 Kozluvka"
    ],
    "name:pol_x_preferred":[
        "Budy-Koz\u0142\u00f3wka"
    ],
    "name:ukr_x_preferred":[
        "\u0411\u0443\u0434\u0438-\u041a\u043e\u0437\u043b\u0443\u0432\u043a\u0430"
    ],
    "name:und_x_variant":[
        "Budy Koz\u0142\u00f3wka"
    ],
    "wof:name":"Budy Kozlowka",
    "wof:placetype":"locality"
},
  "geometry": {"coordinates":[21.99164,53.30653],"type":"Point"}
}