{
  "type": "Feature",
  "properties": {
    "gn:admin1_code":"81.0",
    "gn:admin2_code":"2006.0",
    "gn:admin3_code":"200606.0",
    "gn:asciiname":"Samule",
    "gn:country_code":"PL",
    "gn:dem":107,
    "gn:feature_class":"P",
    "gn:feature_code":"PPL",
    "gn:name":"Samule",
    "gn:population":0,
    "gn:timezone":"Europe/Warsaw",
    "iso:country":"PL",
    "name:lit_x_preferred":[
        "Samul\u0117"
    ],
    "name:pol_x_preferred":[
        "Samule"
    ],
    "name:ukr_x_preferred":[
        "\u0421\u0430\u043c\u0443\u043b\u0435"
    ],
    "wof:name":"Samule",
    "wof:placetype":"locality"
},
  "geometry": {"coordinates":[21.79331,53.3834],"type":"Point"}
}