{
  "type": "Feature",
  "properties": {
    "gn:gn_country":"PL",
    "gn:gn_fcode":"PPL",
    "gn:gn_pop":460,
    "gn:population":460,
    "iso:country":"PL",
    "name:ast_x_preferred":[
        "S\u0119dziejowice"
    ],
    "name:ceb_x_preferred":[
        "S\u0119dziejowice"
    ],
    "name:eng_x_preferred":[
        "S\u0119dziejowice"
    ],
    "name:fra_x_preferred":[
        "S\u0119dziejowice"
    ],
    "name:pol_x_preferred":[
        "S\u0119dziejowice"
    ],
    "name:rus_x_preferred":[
        "\u0421\u0435\u043d\u0434\u00ad\u0437\u0435\u0451\u00ad\u0432\u0438\u00ad\u0446\u044b"
    ],
    "name:ukr_x_preferred":[
        "\u0421\u0435\u043d\u0434\u0437\u0435\u0439\u043e\u0432\u0456\u0446\u0435"
    ],
    "qs_pg:aaroncc":"PL",
    "qs_pg:gn_country":"PL",
    "qs_pg:gn_fcode":"PPL",
    "qs_pg:gn_pop":460,
    "qs_pg:name":"S\u0119dziejowice",
    "qs_pg:name_adm0":"Polska",
    "qs_pg:name_adm1":"Swi\u0119tokrzyskie",
    "qs_pg:photos_9r":0,
    "qs_pg:photos_sr":0,
    "qs_pg:pop_sr":2,
    "qs_pg:qs_pg_placetype":"locality",
    "qs_pg:qs_pg_placetype_gp":"Town",
    "qs_pg:woe_adm0":23424923,
    "woe:adm0_id":23424923,
    "woe:name_adm0":"Polska",
    "woe:name_adm1":"Swi\u0119tokrzyskie",
    "woe:placetype":"Town",
    "wof:name":"S\u0119dziejowice",
    "wof:placetype":"locality",
    "wof:population":460
},
  "geometry": {"coordinates":[20.66065,50.578],"type":"Point"}
}