{
  "type": "Feature",
  "properties": {
    "gn:admin1_code":"73.0",
    "gn:admin2_code":"418.0",
    "gn:admin3_code":"41807.0",
    "gn:asciiname":"Lisek",
    "gn:country_code":"PL",
    "gn:dem":85,
    "gn:feature_class":"P",
    "gn:feature_code":"PPL",
    "gn:name":"Lisek",
    "gn:population":0,
    "gn:timezone":"Europe/Warsaw",
    "iso:country":"PL",
    "name:ceb_x_preferred":[
        "Lisek"
    ],
    "name:pol_x_preferred":[
        "Lisek"
    ],
    "name:ukr_x_preferred":[
        "\u041b\u0456\u0441\u0435\u043a"
    ],
    "wof:name":"Lisek",
    "wof:placetype":"locality"
},
  "geometry": {"coordinates":[19.07607,52.77205],"type":"Point"}
}