{
  "type": "Feature",
  "properties": {
    "gn:admin1_code":"86.0",
    "gn:admin2_code":"3003.0",
    "gn:admin3_code":"300304.0",
    "gn:asciiname":"Karczewo",
    "gn:country_code":"PL",
    "gn:dem":99,
    "gn:feature_class":"P",
    "gn:feature_code":"PPL",
    "gn:name":"Karczewo",
    "gn:population":0,
    "gn:timezone":"Europe/Warsaw",
    "iso:country":"PL",
    "wof:name":"Karczewo",
    "wof:placetype":"locality"
},
  "geometry": {"coordinates":[17.21583,52.57869],"type":"Point"}
}