{
  "type": "Feature",
  "properties": {
    "gn:admin1_code":"85.0",
    "gn:admin2_code":"2814.0",
    "gn:admin3_code":"281407.0",
    "gn:asciiname":"Giedajty",
    "gn:country_code":"PL",
    "gn:dem":123,
    "gn:feature_class":"P",
    "gn:feature_code":"PPL",
    "gn:name":"Giedajty",
    "gn:population":0,
    "gn:timezone":"Europe/Warsaw",
    "iso:country":"PL",
    "name:pol_x_preferred":[
        "Giedajty"
    ],
    "name:ukr_x_preferred":[
        "\u0490\u0435\u0434\u0430\u0439\u0442\u0438"
    ],
    "name:und_x_variant":[
        "Gedaithen",
        "Gedaiten",
        "Giedajty"
    ],
    "wof:name":"Giedajty",
    "wof:placetype":"locality"
},
  "geometry": {"coordinates":[20.29496,53.7979],"type":"Point"}
}