{
  "type": "Feature",
  "properties": {
    "gn:admin1_code":"73.0",
    "gn:admin2_code":"405.0",
    "gn:admin3_code":"40503.0",
    "gn:asciiname":"Pusta Dabrowka",
    "gn:country_code":"PL",
    "gn:dem":92,
    "gn:feature_class":"P",
    "gn:feature_code":"PPL",
    "gn:name":"Pusta D\u0105br\u00f3wka",
    "gn:population":0,
    "gn:timezone":"Europe/Warsaw",
    "iso:country":"PL",
    "name:und_x_variant":[
        "Pusta D\u0105br\u00f3wka"
    ],
    "wof:name":"Pusta Dabrowka",
    "wof:placetype":"locality"
},
  "geometry": {"coordinates":[19.23248,53.20074],"type":"Point"}
}