{
  "type": "Feature",
  "properties": {
    "iso:country":"PL",
    "name:ast_x_preferred":[
        "Trz\u0119s\u00f3wka"
    ],
    "name:azb_x_preferred":[
        "\u0686\u0633\u0648\u06a9\u0627"
    ],
    "name:ceb_x_preferred":[
        "Trz\u0119s\u00f3wka"
    ],
    "name:eng_x_preferred":[
        "Trz\u0119s\u00f3wka"
    ],
    "name:fas_x_preferred":[
        "\u0686\u0633\u0648\u06a9\u0627"
    ],
    "name:fra_x_preferred":[
        "Trz\u0119s\u00f3wka"
    ],
    "name:pol_x_preferred":[
        "Trz\u0119s\u00f3wka"
    ],
    "name:ukr_x_preferred":[
        "\u0422\u0448\u0435\u043d\u0441\u0443\u0432\u043a\u0430"
    ],
    "qs:a0":"Rzeczpospolita Polska",
    "qs:a1":"*Podkarpackie",
    "qs:a1r":"0",
    "qs:a2":"Kolbuszowski",
    "qs:adm0":"Rzeczpospolita Polska",
    "qs:la_lc":"*",
    "qs:level":"locality",
    "qs:loc":"Trz\u0119s\u00f3wka",
    "qs:loc_alt":"Trzesowka",
    "qs:pop":0,
    "qs:type":"buffered point",
    "wd:wordcount":93,
    "wof:name":"Trz\u0119s\u00f3wka",
    "wof:placetype":"locality"
},
  "geometry": {"coordinates":[21.681869,50.294819],"type":"Point"}
}