{
  "type": "Feature",
  "properties": {
    "gn:admin1_code":"81.0",
    "gn:admin2_code":"2013.0",
    "gn:admin3_code":"201310.0",
    "gn:asciiname":"Dabrowa Dzieciel",
    "gn:country_code":"PL",
    "gn:dem":133,
    "gn:feature_class":"P",
    "gn:feature_code":"PPL",
    "gn:name":"D\u0105browa Dzieciel",
    "gn:population":0,
    "gn:timezone":"Europe/Warsaw",
    "iso:country":"PL",
    "name:und_x_variant":[
        "D\u0105browa Dzieciel"
    ],
    "wof:name":"Dabrowa Dzieciel",
    "wof:placetype":"locality"
},
  "geometry": {"coordinates":[22.43925,52.89063],"type":"Point"}
}