{
  "type": "Feature",
  "properties": {
    "gn:admin1_code":"74.0",
    "gn:admin2_code":"1003.0",
    "gn:admin3_code":"100301.0",
    "gn:asciiname":"Gucin",
    "gn:country_code":"PL",
    "gn:dem":189,
    "gn:feature_class":"P",
    "gn:feature_code":"PPL",
    "gn:name":"Gucin",
    "gn:population":0,
    "gn:timezone":"Europe/Warsaw",
    "iso:country":"PL",
    "name:fra_x_preferred":[
        "Gucin"
    ],
    "name:pol_x_preferred":[
        "Gucin"
    ],
    "name:ukr_x_preferred":[
        "\u0490\u0443\u0446\u0438\u043d"
    ],
    "wof:name":"Gucin",
    "wof:placetype":"locality"
},
  "geometry": {"coordinates":[19.2365,51.54852],"type":"Point"}
}