{
  "type": "Feature",
  "properties": {
    "gn:admin1_code":"74.0",
    "gn:admin2_code":"1020.0",
    "gn:admin3_code":"102007.0",
    "gn:asciiname":"Kolonia Wielka Wies Nowa",
    "gn:cc2":"PL",
    "gn:country_code":"PL",
    "gn:dem":135,
    "gn:feature_class":"P",
    "gn:feature_code":"PPL",
    "gn:name":"Kolonia Wielka Wie\u015b Nowa",
    "gn:population":0,
    "gn:timezone":"Europe/Warsaw",
    "iso:country":"PL",
    "name:und_x_variant":[
        "Kolonia Wielka Wie\u015b",
        "Kolonia Wielka Wie\u015b Nowa"
    ],
    "wof:name":"Kolonia Wielka Wies Nowa",
    "wof:placetype":"locality"
},
  "geometry": {"coordinates":[19.21667,51.96667],"type":"Point"}
}