{
  "type": "Feature",
  "properties": {
    "iso:country":"PL",
    "name:ast_x_preferred":[
        "Wrocanka"
    ],
    "name:ceb_x_preferred":[
        "Wrocanka"
    ],
    "name:eng_x_preferred":[
        "Wrocanka"
    ],
    "name:fra_x_preferred":[
        "Wrocanka"
    ],
    "name:nld_x_preferred":[
        "Wrocanka"
    ],
    "name:pol_x_preferred":[
        "Wrocanka"
    ],
    "name:ukr_x_preferred":[
        "\u0412\u0440\u043e\u0446\u0430\u043d\u043a\u0430"
    ],
    "name:und_x_variant":[
        "Wrocanko"
    ],
    "qs:a0":"Rzeczpospolita Polska",
    "qs:a1":"*Podkarpackie",
    "qs:a1r":"0",
    "qs:a2":"Krosnienski",
    "qs:adm0":"Rzeczpospolita Polska",
    "qs:la_lc":"*",
    "qs:level":"locality",
    "qs:loc":"Wrocanka",
    "qs:loc_alt":"Wrocanka",
    "qs:pop":0,
    "qs:type":"buffered point",
    "wd:wordcount":92,
    "wof:name":"Wrocanka",
    "wof:placetype":"locality"
},
  "geometry": {"coordinates":[21.72727,49.636284],"type":"Point"}
}