{
  "type": "Feature",
  "properties": {
    "gn:admin1_code":"78.0",
    "gn:admin2_code":"1419.0",
    "gn:admin3_code":"141908.0",
    "gn:asciiname":"Orszymowo",
    "gn:country_code":"PL",
    "gn:dem":110,
    "gn:feature_class":"P",
    "gn:feature_code":"PPL",
    "gn:name":"Orszymowo",
    "gn:population":0,
    "gn:timezone":"Europe/Warsaw",
    "iso:country":"PL",
    "name:und_x_variant":[
        "Olszynowo",
        "Orszymowo"
    ],
    "wof:name":"Orszymowo",
    "wof:placetype":"locality"
},
  "geometry": {"coordinates":[20.15793,52.45226],"type":"Point"}
}