{
  "type": "Feature",
  "properties": {
    "gn:admin1_code":"82.0",
    "gn:admin2_code":"2201.0",
    "gn:admin3_code":"220105.0",
    "gn:asciiname":"Brzezno Szlacheckie",
    "gn:country_code":"PL",
    "gn:dem":196,
    "gn:feature_class":"P",
    "gn:feature_code":"PPL",
    "gn:name":"Brze\u017ano Szlacheckie",
    "gn:population":0,
    "gn:timezone":"Europe/Warsaw",
    "iso:country":"PL",
    "name:azb_x_preferred":[
        "\u0628\u0698\u0698\u0646\u0648 \u0634\u0644\u0627\u062e\u062a\u0633\u06a9\u06cc\u0647"
    ],
    "name:ceb_x_preferred":[
        "Brze\u017ano Szlacheckie"
    ],
    "name:csb_x_preferred":[
        "Brz\u00e9zno Szlacheccz\u00e9"
    ],
    "name:deu_x_preferred":[
        "Brze\u017ano Szlacheckie"
    ],
    "name:fas_x_preferred":[
        "\u0628\u0698\u0698\u0646\u0648 \u0634\u0644\u0627\u062e\u062a\u0633\u06a9\u06cc\u0647"
    ],
    "name:nld_x_preferred":[
        "Brze\u017ano Szlacheckie"
    ],
    "name:pol_x_preferred":[
        "Brze\u017ano Szlacheckie"
    ],
    "name:ukr_x_preferred":[
        "\u0411\u0436\u0435\u0437\u044c\u043d\u043e-\u0428\u043b\u044f\u0445\u0435\u0446\u044c\u043a\u0435"
    ],
    "name:und_x_variant":[
        "Brze\u017ano"
    ],
    "name:urd_x_preferred":[
        "\u0628\u0631\u0632\u06d2\u0632\u0646\u0648 \u0633\u0632\u0644\u0686\u06a9\u06a9\u0626\u06cc"
    ],
    "wof:name":"Brzezno Szlacheckie",
    "wof:placetype":"locality"
},
  "geometry": {"coordinates":[17.24465,54.01833000000001],"type":"Point"}
}