{
  "type": "Feature",
  "properties": {
    "gn:admin1_code":"82.0",
    "gn:admin2_code":"2201.0",
    "gn:admin3_code":"220105.0",
    "gn:asciiname":"Brzezno Szlacheckie",
    "gn:country_code":"PL",
    "gn:dem":196,
    "gn:feature_class":"P",
    "gn:feature_code":"PPL",
    "gn:name":"Brze\u017ano Szlacheckie",
    "gn:population":0,
    "gn:timezone":"Europe/Warsaw",
    "iso:country":"PL",
    "name:und_x_variant":[
        "Brze\u017ano",
        "Brze\u017ano Szlacheckie"
    ],
    "wof:name":"Brzezno Szlacheckie",
    "wof:placetype":"locality"
},
  "geometry": {"coordinates":[17.24465,54.01833000000001],"type":"Point"}
}