{
  "type": "Feature",
  "properties": {
    "gn:admin1_code":"87.0",
    "gn:admin2_code":"3215.0",
    "gn:admin3_code":"321504.0",
    "gn:asciiname":"Nobliny",
    "gn:country_code":"PL",
    "gn:dem":141,
    "gn:feature_class":"P",
    "gn:feature_code":"PPL",
    "gn:name":"Nobliny",
    "gn:population":0,
    "gn:timezone":"Europe/Warsaw",
    "iso:country":"PL",
    "wof:name":"Nobliny",
    "wof:placetype":"locality"
},
  "geometry": {"coordinates":[16.39194,53.56213],"type":"Point"}
}