{
  "type": "Feature",
  "properties": {
    "gn:admin1_code":"83.0",
    "gn:admin2_code":"2406.0",
    "gn:admin3_code":"240604.0",
    "gn:asciiname":"Nowy Folwark",
    "gn:country_code":"PL",
    "gn:dem":206,
    "gn:feature_class":"P",
    "gn:feature_code":"PPL",
    "gn:name":"Nowy Folwark",
    "gn:population":0,
    "gn:timezone":"Europe/Warsaw",
    "iso:country":"PL",
    "name:pol_x_preferred":[
        "Nowy Folwark"
    ],
    "wof:name":"Nowy Folwark",
    "wof:placetype":"locality"
},
  "geometry": {"coordinates":[19.09338,51.02002],"type":"Point"}
}