{
  "type": "Feature",
  "properties": {
    "gn:admin1_code":"86.0",
    "gn:admin2_code":"3025.0",
    "gn:admin3_code":"302501.0",
    "gn:asciiname":"Bukowy Las",
    "gn:country_code":"PL",
    "gn:dem":96,
    "gn:feature_class":"P",
    "gn:feature_code":"PPL",
    "gn:name":"Bukowy Las",
    "gn:population":0,
    "gn:timezone":"Europe/Warsaw",
    "iso:country":"PL",
    "name:fra_x_preferred":[
        "Bukowy Las"
    ],
    "name:pol_x_preferred":[
        "Bukowy Las"
    ],
    "name:ukr_x_preferred":[
        "\u0411\u0443\u043a\u043e\u0432\u0438-\u041b\u044f\u0441"
    ],
    "wof:name":"Bukowy Las",
    "wof:placetype":"locality"
},
  "geometry": {"coordinates":[17.48029,52.26676],"type":"Point"}
}