{
  "type": "Feature",
  "properties": {
    "gn:admin1_code":"74.0",
    "gn:admin2_code":"1013.0",
    "gn:admin3_code":"101303.0",
    "gn:asciiname":"Kolonia Niemglowy",
    "gn:country_code":"PL",
    "gn:dem":158,
    "gn:feature_class":"P",
    "gn:feature_code":"PPL",
    "gn:name":"Kolonia Niemg\u0142owy",
    "gn:population":0,
    "gn:timezone":"Europe/Warsaw",
    "iso:country":"PL",
    "wof:name":"Kolonia Niemglowy",
    "wof:placetype":"locality"
},
  "geometry": {"coordinates":[20.4054,51.70094],"type":"Point"}
}