{
  "type": "Feature",
  "properties": {
    "gn:admin1_code":"79.0",
    "gn:admin2_code":"1605.0",
    "gn:admin3_code":"160504.0",
    "gn:asciiname":"Brozec",
    "gn:country_code":"PL",
    "gn:dem":180,
    "gn:feature_class":"P",
    "gn:feature_code":"PPL",
    "gn:name":"Bro\u017cec",
    "gn:population":0,
    "gn:timezone":"Europe/Warsaw",
    "iso:country":"PL",
    "name:azb_x_preferred":[
        "\u0628\u0631\u0648\u0698\u062a\u0633"
    ],
    "name:deu_x_preferred":[
        "Brosch\u00fctz"
    ],
    "name:fas_x_preferred":[
        "\u0628\u0631\u0648\u0698\u062a\u0633"
    ],
    "name:pol_x_preferred":[
        "Bro\u017cec"
    ],
    "name:ukr_x_preferred":[
        "\u0411\u0440\u043e\u0436\u0435\u0446\u044c"
    ],
    "name:und_x_variant":[
        "Schobersfelde",
        "Brosec"
    ],
    "wof:name":"Brozec",
    "wof:placetype":"locality"
},
  "geometry": {"coordinates":[17.9816,50.41575],"type":"Point"}
}