{
  "type": "Feature",
  "properties": {
    "gn:admin1_code":"78.0",
    "gn:admin2_code":"1402.0",
    "gn:admin3_code":"140206.0",
    "gn:asciiname":"Skarzynek",
    "gn:country_code":"PL",
    "gn:dem":116,
    "gn:feature_class":"P",
    "gn:feature_code":"PPL",
    "gn:name":"Skarzynek",
    "gn:population":0,
    "gn:timezone":"Europe/Warsaw",
    "iso:country":"PL",
    "name:fra_x_preferred":[
        "Skar\u017cynek"
    ],
    "name:pol_x_preferred":[
        "Skar\u017cynek"
    ],
    "name:spa_x_preferred":[
        "Skar\u017cynek"
    ],
    "name:ukr_x_preferred":[
        "\u0421\u043a\u0430\u0440\u0436\u0438\u043d\u0435\u043a"
    ],
    "wof:name":"Skarzynek",
    "wof:placetype":"locality"
},
  "geometry": {"coordinates":[20.58923,52.80206],"type":"Point"}
}