{
  "type": "Feature",
  "properties": {
    "gn:admin1_code":"87.0",
    "gn:admin2_code":"3204.0",
    "gn:admin3_code":"320405.0",
    "gn:asciiname":"Redlo",
    "gn:country_code":"PL",
    "gn:dem":69,
    "gn:feature_class":"P",
    "gn:feature_code":"PPL",
    "gn:name":"Red\u0142o",
    "gn:population":0,
    "gn:timezone":"Europe/Warsaw",
    "iso:country":"PL",
    "wof:name":"Redlo",
    "wof:placetype":"locality"
},
  "geometry": {"coordinates":[15.0811,53.58235],"type":"Point"}
}