{
  "type": "Feature",
  "properties": {
    "gn:admin1_code":"83.0",
    "gn:admin2_code":"2409.0",
    "gn:admin3_code":"240902.0",
    "gn:asciiname":"Wylagi",
    "gn:country_code":"PL",
    "gn:dem":338,
    "gn:feature_class":"P",
    "gn:feature_code":"PPL",
    "gn:name":"Wyl\u0105gi",
    "gn:population":0,
    "gn:timezone":"Europe/Warsaw",
    "iso:country":"PL",
    "wof:name":"Wylagi",
    "wof:placetype":"neighbourhood"
},
  "geometry": {"coordinates":[19.11667000000001,50.61667],"type":"Point"}
}