{
  "type": "Feature",
  "properties": {
    "gn:admin1_code":"78.0",
    "gn:admin2_code":"1407.0",
    "gn:admin3_code":"140703.0",
    "gn:asciiname":"Wysokie Kolo",
    "gn:country_code":"PL",
    "gn:dem":121,
    "gn:feature_class":"P",
    "gn:feature_code":"PPL",
    "gn:name":"Wysokie Ko\u0142o",
    "gn:population":0,
    "gn:timezone":"Europe/Warsaw",
    "iso:country":"PL",
    "name:fra_x_preferred":[
        "Wysokie Ko\u0142o"
    ],
    "name:pol_x_preferred":[
        "Wysokie Ko\u0142o"
    ],
    "name:ukr_x_preferred":[
        "\u0412\u0438\u0441\u043e\u043a\u0435 \u041a\u043e\u043b\u043e"
    ],
    "wof:name":"Wysokie Kolo",
    "wof:placetype":"locality"
},
  "geometry": {"coordinates":[21.83086,51.46182],"type":"Point"}
}