{
  "type": "Feature",
  "properties": {
    "gn:admin1_code":"82.0",
    "gn:admin2_code":"2206.0",
    "gn:admin3_code":"220607.0",
    "gn:asciiname":"Nowy Barkoczyn",
    "gn:country_code":"PL",
    "gn:dem":167,
    "gn:feature_class":"P",
    "gn:feature_code":"PPL",
    "gn:name":"Nowy Barkoczyn",
    "gn:population":0,
    "gn:timezone":"Europe/Warsaw",
    "iso:country":"PL",
    "name:und_x_variant":[
        "Barkocinek",
        "Nowy Barkoczyn"
    ],
    "wof:name":"Nowy Barkoczyn",
    "wof:placetype":"locality"
},
  "geometry": {"coordinates":[18.13276,54.10152],"type":"Point"}
}