{
  "type": "Feature",
  "properties": {
    "gn:admin1_code":"82.0",
    "gn:admin2_code":"2206.0",
    "gn:admin3_code":"220607.0",
    "gn:asciiname":"Nowy Barkoczyn",
    "gn:country_code":"PL",
    "gn:dem":167,
    "gn:feature_class":"P",
    "gn:feature_code":"PPL",
    "gn:name":"Nowy Barkoczyn",
    "gn:population":0,
    "gn:timezone":"Europe/Warsaw",
    "iso:country":"PL",
    "name:ceb_x_preferred":[
        "Nowy Barkoczyn"
    ],
    "name:csb_x_preferred":[
        "Nowi Bark\u00f2czin"
    ],
    "name:pol_x_preferred":[
        "Nowy Barkoczyn"
    ],
    "name:ukr_x_preferred":[
        "\u041d\u043e\u0432\u0438\u0439 \u0411\u0430\u0440\u043a\u043e\u0447\u0438\u043d"
    ],
    "name:und_x_variant":[
        "Barkocinek",
        "Nowy Barkoczyn"
    ],
    "wof:name":"Nowy Barkoczyn",
    "wof:placetype":"locality"
},
  "geometry": {"coordinates":[18.13276,54.10152],"type":"Point"}
}