{
  "type": "Feature",
  "properties": {
    "gn:admin1_code":"74.0",
    "gn:admin2_code":"1020.0",
    "gn:admin3_code":"102005.0",
    "gn:asciiname":"Rudnik",
    "gn:country_code":"PL",
    "gn:dem":150,
    "gn:feature_class":"P",
    "gn:feature_code":"PPL",
    "gn:name":"Rudnik",
    "gn:population":0,
    "gn:timezone":"Europe/Warsaw",
    "iso:country":"PL",
    "name:bel_x_preferred":[
        "\u0420\u0443\u0434\u043d\u0456\u043a"
    ],
    "name:bos_x_preferred":[
        "Rudnik"
    ],
    "name:bul_x_preferred":[
        "\u0420\u0443\u0434\u043d\u0438\u043a"
    ],
    "name:ceb_x_preferred":[
        "Rudnik"
    ],
    "name:deu_x_preferred":[
        "Rudnik"
    ],
    "name:fra_x_preferred":[
        "Rudnik"
    ],
    "name:hrv_x_preferred":[
        "Rudnik"
    ],
    "name:ita_x_preferred":[
        "Rudnik"
    ],
    "name:nld_x_preferred":[
        "Rudnik"
    ],
    "name:pol_x_preferred":[
        "Rudnik"
    ],
    "name:ron_x_preferred":[
        "Rudnik"
    ],
    "name:rus_x_preferred":[
        "\u0420\u0443\u0434\u043d\u0438\u043a"
    ],
    "name:slv_x_preferred":[
        "Rudnik"
    ],
    "name:srp_x_preferred":[
        "\u0420\u0443\u0434\u043d\u0438\u043a"
    ],
    "name:swe_x_preferred":[
        "Rudnik"
    ],
    "name:ukr_x_preferred":[
        "\u0420\u0443\u0434\u043d\u0438\u043a"
    ],
    "wof:name":"Rudnik",
    "wof:placetype":"locality"
},
  "geometry": {"coordinates":[19.83333,51.96667],"type":"Point"}
}