{
  "type": "Feature",
  "properties": {
    "iso:country":"PL",
    "name:pol_x_preferred":[
        "P\u00f3\u0142wsie Zwierzynieckie"
    ],
    "wof:name":"Polwsie Zwierzynieckie",
    "wof:placetype":"neighbourhood"
},
  "geometry": {"coordinates":[19.919462237314,50.05610737631888],"type":"Point"}
}