{
  "type": "Feature",
  "properties": {
    "gn:admin1_code":"74.0",
    "gn:admin2_code":"1010.0",
    "gn:admin3_code":"101009.0",
    "gn:asciiname":"Podklasztorze",
    "gn:country_code":"PL",
    "gn:dem":174,
    "gn:feature_class":"P",
    "gn:feature_code":"PPL",
    "gn:name":"Podklasztorze",
    "gn:population":0,
    "gn:timezone":"Europe/Warsaw",
    "iso:country":"PL",
    "wof:name":"Podklasztorze",
    "wof:placetype":"locality"
},
  "geometry": {"coordinates":[19.88122000000001,51.36854],"type":"Point"}
}