{
  "type": "Feature",
  "properties": {
    "gn:country":"PL",
    "gn:fcode":"PPL",
    "gn:population":126,
    "iso:country":"PL",
    "name:ast_x_preferred":[
        "Kobylanka"
    ],
    "name:ceb_x_preferred":[
        "Kobylanka"
    ],
    "name:eng_x_preferred":[
        "Kobylanka"
    ],
    "name:fra_x_preferred":[
        "Kobylanka"
    ],
    "name:pol_x_preferred":[
        "Kobylanka"
    ],
    "name:ukr_x_preferred":[
        "\u041a\u043e\u0431\u0438\u043b\u044f\u043d\u043a\u0430"
    ],
    "qs_pg:aaroncc":"PL",
    "qs_pg:gn_country":"PL",
    "qs_pg:gn_fcode":"PPL",
    "qs_pg:gn_pop":126,
    "qs_pg:name":"Kobylanka",
    "qs_pg:name_adm0":"Polska",
    "qs_pg:name_adm1":"Mazowieckie",
    "qs_pg:photos_9r":0,
    "qs_pg:photos_sr":0,
    "qs_pg:pop_sr":1,
    "qs_pg:qs_pg_placetype":"locality",
    "qs_pg:qs_pg_placetype_gp":"Town",
    "qs_pg:woe_adm0":23424923,
    "woe:adm0_id":23424923,
    "woe:name_adm0":"Polska",
    "woe:name_adm1":"Mazowieckie",
    "woe:placetype":"Town",
    "wof:name":"Kobylanka",
    "wof:placetype":"locality",
    "wof:population":126
},
  "geometry": {"coordinates":[21.69662,52.34769],"type":"Point"}
}