{
  "type": "Feature",
  "properties": {
    "gn:admin1_code":"84.0",
    "gn:admin2_code":"2613.0",
    "gn:admin3_code":"261306.0",
    "gn:asciiname":"Kotowe",
    "gn:country_code":"PL",
    "gn:dem":229,
    "gn:feature_class":"P",
    "gn:feature_code":"PPL",
    "gn:name":"Kotowe",
    "gn:population":0,
    "gn:timezone":"Europe/Warsaw",
    "iso:country":"PL",
    "wof:name":"Kotowe",
    "wof:placetype":"locality"
},
  "geometry": {"coordinates":[20.00421,50.89218],"type":"Point"}
}