{
  "type": "Feature",
  "properties": {
    "gn:admin1_code":"78.0",
    "gn:admin2_code":"1424.0",
    "gn:admin3_code":"142407.0",
    "gn:asciiname":"Ciski",
    "gn:country_code":"PL",
    "gn:dem":103,
    "gn:feature_class":"P",
    "gn:feature_code":"PPL",
    "gn:name":"Ciski",
    "gn:population":0,
    "gn:timezone":"Europe/Warsaw",
    "iso:country":"PL",
    "name:azb_x_preferred":[
        "\u0686\u06cc\u0633\u06a9\u06cc"
    ],
    "name:fas_x_preferred":[
        "\u0686\u06cc\u0633\u06a9\u06cc"
    ],
    "name:fra_x_preferred":[
        "Ciski"
    ],
    "name:pol_x_preferred":[
        "Ciski"
    ],
    "name:ukr_x_preferred":[
        "\u0426\u0438\u0441\u043a\u0456"
    ],
    "wof:name":"Ciski",
    "wof:placetype":"locality"
},
  "geometry": {"coordinates":[21.25709,52.60273000000001],"type":"Point"}
}