{
  "type": "Feature",
  "properties": {
    "gn:admin1_code":"74.0",
    "gn:admin2_code":"1010.0",
    "gn:admin3_code":"101005.0",
    "gn:asciiname":"Kolonia Ignacow Szlachecki",
    "gn:country_code":"PL",
    "gn:dem":211,
    "gn:feature_class":"P",
    "gn:feature_code":"PPL",
    "gn:name":"Kolonia Ignac\u00f3w Szlachecki",
    "gn:population":0,
    "gn:timezone":"Europe/Warsaw",
    "iso:country":"PL",
    "wof:name":"Kolonia Ignacow Szlachecki",
    "wof:placetype":"locality"
},
  "geometry": {"coordinates":[19.81488,51.21112],"type":"Point"}
}