{
  "type": "Feature",
  "properties": {
    "gn:admin1_code":"78.0",
    "gn:admin2_code":"1415.0",
    "gn:admin3_code":"141511.0",
    "gn:asciiname":"Zamosc",
    "gn:country_code":"PL",
    "gn:dem":103,
    "gn:feature_class":"P",
    "gn:feature_code":"PPL",
    "gn:name":"Zamo\u015b\u0107",
    "gn:population":0,
    "gn:timezone":"Europe/Warsaw",
    "iso:country":"PL",
    "wof:name":"Zamosc",
    "wof:placetype":"locality"
},
  "geometry": {"coordinates":[21.68306,53.03647],"type":"Point"}
}