{
  "type": "Feature",
  "properties": {
    "gn:admin1_code":"83.0",
    "gn:admin2_code":"2405.0",
    "gn:admin3_code":"240502.0",
    "gn:asciiname":"Paczynka",
    "gn:country_code":"PL",
    "gn:dem":224,
    "gn:feature_class":"P",
    "gn:feature_code":"PPL",
    "gn:name":"Paczynka",
    "gn:population":0,
    "gn:timezone":"Europe/Warsaw",
    "iso:country":"PL",
    "name:ceb_x_preferred":[
        "Paczynka"
    ],
    "name:deu_x_preferred":[
        "Paczynka"
    ],
    "name:pol_x_preferred":[
        "Paczynka"
    ],
    "name:ukr_x_preferred":[
        "\u041f\u0430\u0447\u0438\u043d\u043a\u0430"
    ],
    "name:und_x_variant":[
        "Klein Patschin",
        "Ellerbr\u00fcck"
    ],
    "wof:name":"Paczynka",
    "wof:placetype":"locality"
},
  "geometry": {"coordinates":[18.61454,50.38851],"type":"Point"}
}