{
  "type": "Feature",
  "properties": {
    "gn:admin1_code":"83.0",
    "gn:admin2_code":"2405.0",
    "gn:admin3_code":"240502.0",
    "gn:asciiname":"Paczynka",
    "gn:country_code":"PL",
    "gn:dem":224,
    "gn:feature_class":"P",
    "gn:feature_code":"PPL",
    "gn:name":"Paczynka",
    "gn:population":0,
    "gn:timezone":"Europe/Warsaw",
    "iso:country":"PL",
    "name:und_x_variant":[
        "Klein Patschin",
        "Ellerbr\u00fcck",
        "Paczynka"
    ],
    "wof:name":"Paczynka",
    "wof:placetype":"locality"
},
  "geometry": {"coordinates":[18.61454,50.38851],"type":"Point"}
}