{
  "type": "Feature",
  "properties": {
    "gn:admin1_code":"83.0",
    "gn:admin2_code":"2404.0",
    "gn:admin3_code":"240416.0",
    "gn:asciiname":"Wlasna",
    "gn:country_code":"PL",
    "gn:dem":276,
    "gn:feature_class":"P",
    "gn:feature_code":"PPL",
    "gn:name":"W\u0142asna",
    "gn:population":0,
    "gn:timezone":"Europe/Warsaw",
    "iso:country":"PL",
    "name:ceb_x_preferred":[
        "W\u0142asna"
    ],
    "name:pol_x_preferred":[
        "W\u0142asna"
    ],
    "name:ukr_x_preferred":[
        "\u0412\u043b\u0430\u0441\u043d\u0430"
    ],
    "name:und_x_variant":[
        "W\u0142asne"
    ],
    "wof:name":"Wlasna",
    "wof:placetype":"locality"
},
  "geometry": {"coordinates":[19.0859,50.67015],"type":"Point"}
}