{
  "type": "Feature",
  "properties": {
    "gn:admin1_code":"87.0",
    "gn:admin2_code":"3205.0",
    "gn:admin3_code":"320502.0",
    "gn:asciiname":"Lubieszewo",
    "gn:country_code":"PL",
    "gn:dem":29,
    "gn:feature_class":"P",
    "gn:feature_code":"PPL",
    "gn:name":"Lubieszewo",
    "gn:population":0,
    "gn:timezone":"Europe/Warsaw",
    "iso:country":"PL",
    "name:pol_x_preferred":[
        "Lubieszewo"
    ],
    "name:ukr_x_preferred":[
        "\u041b\u044e\u0431\u0435\u0448\u0435\u0432\u043e"
    ],
    "wof:name":"Lubieszewo",
    "wof:placetype":"locality"
},
  "geometry": {"coordinates":[15.25545,53.92002],"type":"Point"}
}