{
  "type": "Feature",
  "properties": {
    "gn:admin1_code":"80.0",
    "gn:admin2_code":"1813.0",
    "gn:admin3_code":"181304.0",
    "gn:asciiname":"Olszany",
    "gn:country_code":"PL",
    "gn:dem":221,
    "gn:feature_class":"P",
    "gn:feature_code":"PPL",
    "gn:name":"Olszany",
    "gn:population":0,
    "gn:timezone":"Europe/Warsaw",
    "iso:country":"PL",
    "name:ceb_x_preferred":[
        "Olszany"
    ],
    "name:pol_x_preferred":[
        "Olszany"
    ],
    "name:ukr_x_preferred":[
        "\u0412\u0456\u043b\u044c\u0448\u0430\u043d\u0438"
    ],
    "wof:name":"Olszany",
    "wof:placetype":"locality"
},
  "geometry": {"coordinates":[22.64153,49.7401],"type":"Point"}
}