{
  "type": "Feature",
  "properties": {
    "gn:admin1_code":"86.0",
    "gn:admin2_code":"3009.0",
    "gn:admin3_code":"300904.0",
    "gn:asciiname":"Chelmno",
    "gn:country_code":"PL",
    "gn:dem":108,
    "gn:feature_class":"P",
    "gn:feature_code":"PPL",
    "gn:name":"Che\u0142mno",
    "gn:population":0,
    "gn:timezone":"Europe/Warsaw",
    "iso:country":"PL",
    "name:und_x_variant":[
        "Che\u0142mno"
    ],
    "wof:name":"Chelmno",
    "wof:placetype":"locality"
},
  "geometry": {"coordinates":[18.75076,52.11285],"type":"Point"}
}