{
  "type": "Feature",
  "properties": {
    "gn:admin1_code":"86.0",
    "gn:admin2_code":"3009.0",
    "gn:admin3_code":"300904.0",
    "gn:asciiname":"Chelmno",
    "gn:country_code":"PL",
    "gn:dem":108,
    "gn:feature_class":"P",
    "gn:feature_code":"PPL",
    "gn:name":"Che\u0142mno",
    "gn:population":0,
    "gn:timezone":"Europe/Warsaw",
    "iso:country":"PL",
    "name:dan_x_preferred":[
        "Che\u0142mno udryddelseslejr"
    ],
    "name:deu_x_preferred":[
        "Vernichtungslager Kulmhof"
    ],
    "name:epo_x_preferred":[
        "Ekstermejo Che\u0142mno"
    ],
    "name:fin_x_preferred":[
        "Che\u0142mnon tuhoamisleiri"
    ],
    "name:fry_x_preferred":[
        "Chelmno"
    ],
    "name:heb_x_preferred":[
        "\u05d7\u05dc\u05de\u05e0\u05d5"
    ],
    "name:hye_x_preferred":[
        "\u053d\u0565\u056c\u0574\u0576\u0578"
    ],
    "name:jpn_x_preferred":[
        "\u30d8\u30a6\u30e0\u30ce\u5f37\u5236\u53ce\u5bb9\u6240"
    ],
    "name:ltz_x_preferred":[
        "Vernichtungslager Chelmno"
    ],
    "name:nld_x_preferred":[
        "Che\u0142mno"
    ],
    "name:nor_x_preferred":[
        "Kulmhof"
    ],
    "name:rus_x_preferred":[
        "\u0425\u0435\u043b\u043c\u043d\u043e"
    ],
    "name:srp_x_preferred":[
        "\u041b\u043e\u0433\u043e\u0440 \u0425\u0435\u043b\u043c\u043d\u043e"
    ],
    "name:swe_x_preferred":[
        "F\u00f6rintelsel\u00e4gret Che\u0142mno"
    ],
    "name:und_x_variant":[
        "Che\u0142mno"
    ],
    "name:zho_x_preferred":[
        "\u6d77\u4e4c\u59c6\u8bfa\u706d\u7edd\u8425"
    ],
    "wof:name":"Chelmno",
    "wof:placetype":"locality"
},
  "geometry": {"coordinates":[18.75076,52.11285],"type":"Point"}
}