{
  "type": "Feature",
  "properties": {
    "gn:country":"PL",
    "gn:fcode":"PPL",
    "gn:population":0,
    "iso:country":"PL",
    "name:ast_x_preferred":[
        "Strzek\u0119cino"
    ],
    "name:azb_x_preferred":[
        "\u0633\u062a\u0698\u06a9\u0646\u0686\u06cc\u0646\u0648"
    ],
    "name:ceb_x_preferred":[
        "Strzek\u0119cino"
    ],
    "name:deu_x_preferred":[
        "Strzek\u0119cino"
    ],
    "name:eng_x_preferred":[
        "Strzek\u0119cino"
    ],
    "name:fas_x_preferred":[
        "\u0633\u062a\u0698\u06a9\u0646\u0686\u06cc\u0646\u0648"
    ],
    "name:fra_x_preferred":[
        "Strzek\u0119cino"
    ],
    "name:pol_x_preferred":[
        "Strzek\u0119cino"
    ],
    "name:ukr_x_preferred":[
        "\u0421\u0442\u0448\u0435\u043a\u0435\u043d\u0447\u0456\u043d\u043e"
    ],
    "name:ukr_x_variant":[
        "\u0421\u0442\u0448\u0435\u043a\u0435\u043d\u0446\u0456\u043d\u043e"
    ],
    "name:vie_x_preferred":[
        "Strzek\u0119cino"
    ],
    "qs_pg:aaroncc":"PL",
    "qs_pg:gn_country":"PL",
    "qs_pg:gn_fcode":"PPL",
    "qs_pg:gn_pop":0,
    "qs_pg:name":"Strzek\u0119cino",
    "qs_pg:name_adm0":"Polska",
    "qs_pg:name_adm1":"Zachodniopomorskie",
    "qs_pg:photos_9r":0,
    "qs_pg:photos_sr":0,
    "qs_pg:pop_sr":0,
    "qs_pg:qs_pg_placetype":"locality",
    "qs_pg:qs_pg_placetype_gp":"Town",
    "qs_pg:woe_adm0":23424923,
    "woe:adm0_id":23424923,
    "woe:name_adm0":"Polska",
    "woe:name_adm1":"Zachodniopomorskie",
    "woe:placetype":"Town",
    "wof:name":"Strzek\u0119cino",
    "wof:placetype":"locality"
},
  "geometry": {"coordinates":[16.15593,54.10067],"type":"Point"}
}