{
  "type": "Feature",
  "properties": {
    "gn:admin1_code":"85.0",
    "gn:admin2_code":"2815.0",
    "gn:admin3_code":"281505.0",
    "gn:asciiname":"Szymonowo",
    "gn:country_code":"PL",
    "gn:dem":114,
    "gn:feature_class":"P",
    "gn:feature_code":"PPL",
    "gn:name":"Szymonowo",
    "gn:population":0,
    "gn:timezone":"Europe/Warsaw",
    "iso:country":"PL",
    "name:azb_x_preferred":[
        "\u0634\u0645\u0648\u0646\u0648\u0648\u0648"
    ],
    "name:deu_x_preferred":[
        "Szymonowo"
    ],
    "name:fas_x_preferred":[
        "\u0634\u0645\u0648\u0646\u0648\u0648\u0648"
    ],
    "name:fra_x_preferred":[
        "Szymonowo"
    ],
    "name:pol_x_preferred":[
        "Szymonowo"
    ],
    "name:ukr_x_preferred":[
        "\u0428\u0438\u043c\u043e\u043d\u043e\u0432\u043e"
    ],
    "name:und_x_variant":[
        "Simnau",
        "Gross Simnau"
    ],
    "wof:name":"Szymonowo",
    "wof:placetype":"locality"
},
  "geometry": {"coordinates":[19.78383,53.86146],"type":"Point"}
}