{
  "type": "Feature",
  "properties": {
    "gn:admin1_code":"86.0",
    "gn:admin2_code":"3018.0",
    "gn:admin3_code":"301802.0",
    "gn:asciiname":"Stary Pan",
    "gn:country_code":"PL",
    "gn:dem":146,
    "gn:feature_class":"P",
    "gn:feature_code":"PPL",
    "gn:name":"Stary Pan",
    "gn:population":0,
    "gn:timezone":"Europe/Warsaw",
    "iso:country":"PL",
    "wof:name":"Stary Pan",
    "wof:placetype":"locality"
},
  "geometry": {"coordinates":[18.15637000000001,51.39897],"type":"Point"}
}