{
  "type": "Feature",
  "properties": {
    "gn:admin1_code":"80.0",
    "gn:admin2_code":"1816.0",
    "gn:admin3_code":"181606.0",
    "gn:asciiname":"Wola Cicha",
    "gn:country_code":"PL",
    "gn:dem":210,
    "gn:feature_class":"P",
    "gn:feature_code":"PPL",
    "gn:name":"Wola Cicha",
    "gn:population":0,
    "gn:timezone":"Europe/Warsaw",
    "iso:country":"PL",
    "wof:name":"Wola Cicha",
    "wof:placetype":"locality"
},
  "geometry": {"coordinates":[21.95677,50.12848],"type":"Point"}
}