{
  "type": "Feature",
  "properties": {
    "gn:admin1_code":"85.0",
    "gn:admin2_code":"2816.0",
    "gn:admin3_code":"281601.0",
    "gn:asciiname":"Lipowskie",
    "gn:country_code":"PL",
    "gn:dem":123,
    "gn:feature_class":"P",
    "gn:feature_code":"PPL",
    "gn:name":"Lipowskie",
    "gn:population":0,
    "gn:timezone":"Europe/Warsaw",
    "iso:country":"PL",
    "name:und_x_variant":[
        "Dupken",
        "Lindensee",
        "Lipowsken",
        "Lipowskie"
    ],
    "wof:name":"Lipowskie",
    "wof:placetype":"locality"
},
  "geometry": {"coordinates":[22.16667,53.73333],"type":"Point"}
}