{
  "type": "Feature",
  "properties": {
    "gn:gn_country":"PL",
    "gn:gn_fcode":"PPLA3",
    "gn:gn_pop":402,
    "gn:population":402,
    "iso:country":"PL",
    "name:ceb_x_preferred":[
        "Za\u0142uski"
    ],
    "name:deu_x_preferred":[
        "Za\u0142uski"
    ],
    "name:fra_x_preferred":[
        "Za\u0142uski"
    ],
    "name:ita_x_preferred":[
        "Za\u0142uski"
    ],
    "name:nld_x_preferred":[
        "Za\u0142uski"
    ],
    "name:pol_x_preferred":[
        "Za\u0142uski"
    ],
    "name:rus_x_preferred":[
        "\u0417\u0430\u043b\u0443\u0441\u043a\u0438\u0439"
    ],
    "name:ukr_x_preferred":[
        "\u0417\u0430\u043b\u0443\u0441\u043a\u0456"
    ],
    "qs_pg:aaroncc":"PL",
    "qs_pg:gn_country":"PL",
    "qs_pg:gn_fcode":"PPLA3",
    "qs_pg:gn_pop":402,
    "qs_pg:name":"Za\u0142uski",
    "qs_pg:name_adm0":"Polska",
    "qs_pg:name_adm1":"Mazowieckie",
    "qs_pg:photos":2,
    "qs_pg:photos_1k":1,
    "qs_pg:photos_9k":1,
    "qs_pg:photos_9r":1,
    "qs_pg:photos_all":2,
    "qs_pg:photos_sr":1,
    "qs_pg:pop_sr":2,
    "qs_pg:qs_pg_placetype":"localadmin",
    "qs_pg:qs_pg_placetype_gp":"LocalAdmin",
    "qs_pg:woe_adm0":23424923,
    "woe:adm0_id":23424923,
    "woe:name_adm0":"Polska",
    "woe:name_adm1":"Mazowieckie",
    "woe:placetype":"LocalAdmin",
    "wof:name":"Za\u0142uski",
    "wof:placetype":"localadmin",
    "wof:population":402
},
  "geometry": {"coordinates":[20.52864,52.51152],"type":"Point"}
}