{
  "type": "Feature",
  "properties": {
    "gn:population":1800,
    "iso:country":"PL",
    "name:ast_x_preferred":[
        "Baboszewo"
    ],
    "name:azb_x_preferred":[
        "\u0628\u0627\u0628\u0648\u0634\u0648\u0648"
    ],
    "name:ceb_x_preferred":[
        "Baboszewo"
    ],
    "name:deu_x_preferred":[
        "Baboszewo"
    ],
    "name:eng_x_preferred":[
        "Baboszewo"
    ],
    "name:fas_x_preferred":[
        "\u0628\u0627\u0628\u0648\u0634\u0648\u0648"
    ],
    "name:fra_x_preferred":[
        "Baboszewo"
    ],
    "name:nld_x_preferred":[
        "Baboszewo"
    ],
    "name:pol_x_preferred":[
        "Baboszewo"
    ],
    "name:rus_x_preferred":[
        "\u0411\u0430\u0431\u043e\u0448\u0435\u0432\u043e"
    ],
    "name:ukr_x_preferred":[
        "\u0411\u0430\u0431\u043e\u0448\u0435\u0432\u043e"
    ],
    "qs:a0":"Rzeczpospolita Polska",
    "qs:a1":"*Mazowieckie",
    "qs:a1r":"0",
    "qs:a2":"Plonski",
    "qs:adm0":"Rzeczpospolita Polska",
    "qs:la":"Baboszewo",
    "qs:la_lc":"*PL1420032",
    "qs:level":"locality",
    "qs:loc":"Baboszewo",
    "qs:loc_alt":"Baboszewo",
    "qs:pop":0,
    "qs:type":"rural point-in-poly",
    "wd:wordcount":87,
    "wof:name":"Baboszewo",
    "wof:placetype":"locality",
    "wof:population":1800
},
  "geometry": {"coordinates":[20.2743678703673,52.7084614699494],"type":"Point"}
}