{
  "type": "Feature",
  "properties": {
    "gn:admin1_code":"74.0",
    "gn:admin2_code":"1016.0",
    "gn:admin3_code":"101601.0",
    "gn:asciiname":"Niwka",
    "gn:country_code":"PL",
    "gn:dem":150,
    "gn:feature_class":"P",
    "gn:feature_code":"PPL",
    "gn:name":"Niwka",
    "gn:population":0,
    "gn:timezone":"Europe/Warsaw",
    "iso:country":"PL",
    "name:pol_x_preferred":[
        "Niwka"
    ],
    "name:ukr_x_preferred":[
        "\u041d\u0456\u0432\u043a\u0430"
    ],
    "wof:name":"Niwka",
    "wof:placetype":"neighbourhood"
},
  "geometry": {"coordinates":[20.05,51.53333],"type":"Point"}
}