{
  "type": "Feature",
  "properties": {
    "gn:admin1_code":"80.0",
    "gn:admin2_code":"1807.0",
    "gn:admin3_code":"180701.0",
    "gn:asciiname":"Sulistrowa",
    "gn:country_code":"PL",
    "gn:dem":309,
    "gn:feature_class":"P",
    "gn:feature_code":"PPL",
    "gn:name":"Sulistrowa",
    "gn:population":0,
    "gn:timezone":"Europe/Warsaw",
    "iso:country":"PL",
    "name:pol_x_preferred":[
        "Sulistrowa"
    ],
    "name:ukr_x_preferred":[
        "\u0421\u0443\u043b\u0456\u0441\u0442\u0440\u043e\u0432\u0430"
    ],
    "name:und_x_variant":[
        "Sulishowa"
    ],
    "wof:name":"Sulistrowa",
    "wof:placetype":"locality"
},
  "geometry": {"coordinates":[21.62942,49.6061],"type":"Point"}
}