{
  "type": "Feature",
  "properties": {
    "gn:admin1_code":"72.0",
    "gn:admin2_code":"224.0",
    "gn:admin3_code":"22404.0",
    "gn:asciiname":"Zdanow",
    "gn:country_code":"PL",
    "gn:dem":427,
    "gn:feature_class":"P",
    "gn:feature_code":"PPL",
    "gn:name":"Zdan\u00f3w",
    "gn:population":0,
    "gn:timezone":"Europe/Warsaw",
    "iso:country":"PL",
    "wof:name":"Zdanow",
    "wof:placetype":"locality"
},
  "geometry": {"coordinates":[16.65459,50.55991],"type":"Point"}
}