{
  "type": "Feature",
  "properties": {
    "gn:admin1_code":"78.0",
    "gn:admin2_code":"1403.0",
    "gn:admin3_code":"140308.0",
    "gn:asciiname":"Zwola Poduchowna",
    "gn:country_code":"PL",
    "gn:dem":172,
    "gn:feature_class":"P",
    "gn:feature_code":"PPL",
    "gn:name":"Zwola Poduchowna",
    "gn:population":0,
    "gn:timezone":"Europe/Warsaw",
    "iso:country":"PL",
    "name:ceb_x_preferred":[
        "Zwola Poduchowna"
    ],
    "name:fra_x_preferred":[
        "Zwola Poduchowna"
    ],
    "name:pol_x_preferred":[
        "Zwola Poduchowna"
    ],
    "name:spa_x_preferred":[
        "Zwola Poduchowna"
    ],
    "name:ukr_x_preferred":[
        "\u0417\u0432\u043e\u043b\u044f-\u041f\u043e\u0434\u0443\u0445\u043e\u0432\u043d\u0430"
    ],
    "wof:name":"Zwola Poduchowna",
    "wof:placetype":"locality"
},
  "geometry": {"coordinates":[21.87756,51.86981],"type":"Point"}
}