{
  "type": "Feature",
  "properties": {
    "gn:admin1_code":"81.0",
    "gn:admin2_code":"2008.0",
    "gn:admin3_code":"200802.0",
    "gn:asciiname":"Kujbiedy",
    "gn:country_code":"PL",
    "gn:dem":134,
    "gn:feature_class":"P",
    "gn:feature_code":"PPL",
    "gn:name":"Kujbiedy",
    "gn:population":0,
    "gn:timezone":"Europe/Warsaw",
    "iso:country":"PL",
    "name:azb_x_preferred":[
        "\u06a9\u0648\u06cc\u0628\u06cc\u062f\u0647"
    ],
    "name:fas_x_preferred":[
        "\u06a9\u0648\u06cc\u0628\u06cc\u062f\u0647"
    ],
    "name:fra_x_preferred":[
        "Kujbiedy"
    ],
    "name:lit_x_preferred":[
        "Kuibedai"
    ],
    "name:pol_x_preferred":[
        "Kujbiedy"
    ],
    "name:ukr_x_preferred":[
        "\u041a\u0443\u0439\u0431\u0435\u0434\u0438"
    ],
    "wof:name":"Kujbiedy",
    "wof:placetype":"locality"
},
  "geometry": {"coordinates":[23.051,53.37007],"type":"Point"}
}