{
  "type": "Feature",
  "properties": {
    "gn:admin1_code":"81.0",
    "gn:admin2_code":"2008.0",
    "gn:admin3_code":"200802.0",
    "gn:asciiname":"Kujbiedy",
    "gn:country_code":"PL",
    "gn:dem":134,
    "gn:feature_class":"P",
    "gn:feature_code":"PPL",
    "gn:name":"Kujbiedy",
    "gn:population":0,
    "gn:timezone":"Europe/Warsaw",
    "iso:country":"PL",
    "wof:name":"Kujbiedy",
    "wof:placetype":"locality"
},
  "geometry": {"coordinates":[23.051,53.37007],"type":"Point"}
}