{
  "type": "Feature",
  "properties": {
    "gn:admin1_code":"81.0",
    "gn:admin2_code":"2013.0",
    "gn:admin3_code":"201302.0",
    "gn:asciiname":"Malec",
    "gn:country_code":"PL",
    "gn:dem":137,
    "gn:feature_class":"P",
    "gn:feature_code":"PPL",
    "gn:name":"Malec",
    "gn:population":0,
    "gn:timezone":"Europe/Warsaw",
    "iso:country":"PL",
    "name:ceb_x_preferred":[
        "Malec"
    ],
    "name:fra_x_preferred":[
        "Malec"
    ],
    "name:lit_x_preferred":[
        "Malecas"
    ],
    "name:pol_x_preferred":[
        "Malec"
    ],
    "name:ukr_x_preferred":[
        "\u041c\u0430\u043b\u0435\u0446\u044c"
    ],
    "wof:name":"Malec",
    "wof:placetype":"locality"
},
  "geometry": {"coordinates":[22.56666,52.63705],"type":"Point"}
}