{
  "type": "Feature",
  "properties": {
    "gn:admin1_code":"86.0",
    "gn:admin2_code":"3016.0",
    "gn:admin3_code":"301601.0",
    "gn:asciiname":"Rudki",
    "gn:country_code":"PL",
    "gn:dem":52,
    "gn:feature_class":"P",
    "gn:feature_code":"PPL",
    "gn:name":"Rudki",
    "gn:population":0,
    "gn:timezone":"Europe/Warsaw",
    "iso:country":"PL",
    "name:fra_x_preferred":[
        "Rudki"
    ],
    "name:heb_x_preferred":[
        "\u05e8\u05d5\u05d3\u05e7\u05d9"
    ],
    "name:pol_x_preferred":[
        "Rudki"
    ],
    "name:ukr_x_preferred":[
        "\u0420\u0443\u0434\u043a\u0456"
    ],
    "wof:name":"Rudki",
    "wof:placetype":"locality"
},
  "geometry": {"coordinates":[16.81667,52.66667],"type":"Point"}
}