{
  "type": "Feature",
  "properties": {
    "gn:admin1_code":"86.0",
    "gn:admin2_code":"3016.0",
    "gn:admin3_code":"301601.0",
    "gn:asciiname":"Rudki",
    "gn:country_code":"PL",
    "gn:dem":52,
    "gn:feature_class":"P",
    "gn:feature_code":"PPL",
    "gn:name":"Rudki",
    "gn:population":0,
    "gn:timezone":"Europe/Warsaw",
    "iso:country":"PL",
    "wof:name":"Rudki",
    "wof:placetype":"locality"
},
  "geometry": {"coordinates":[16.81667,52.66667],"type":"Point"}
}