{
  "type": "Feature",
  "properties": {
    "gn:admin1_code":"81.0",
    "gn:admin2_code":"2002.0",
    "gn:admin3_code":"200212.0",
    "gn:asciiname":"Lesniki",
    "gn:country_code":"PL",
    "gn:dem":132,
    "gn:feature_class":"P",
    "gn:feature_code":"PPL",
    "gn:name":"Le\u015bniki",
    "gn:population":0,
    "gn:timezone":"Europe/Warsaw",
    "iso:country":"PL",
    "name:ceb_x_preferred":[
        "Le\u015bniki"
    ],
    "name:lit_x_preferred":[
        "Le\u0161nikai"
    ],
    "name:pol_x_preferred":[
        "Le\u015bniki"
    ],
    "name:ukr_x_preferred":[
        "\u041b\u0435\u0441\u044c\u043d\u0438\u043a\u0438"
    ],
    "wof:name":"Lesniki",
    "wof:placetype":"locality"
},
  "geometry": {"coordinates":[22.80565,53.16239],"type":"Point"}
}