{
  "type": "Feature",
  "properties": {
    "gn:admin1_code":"82.0",
    "gn:admin2_code":"2208.0",
    "gn:admin3_code":"220803.0",
    "gn:asciiname":"Osowo Leborskie",
    "gn:country_code":"PL",
    "gn:dem":98,
    "gn:feature_class":"P",
    "gn:feature_code":"PPL",
    "gn:name":"Osowo L\u0119borskie",
    "gn:population":0,
    "gn:timezone":"Europe/Warsaw",
    "iso:country":"PL",
    "name:ceb_x_preferred":[
        "Osowo L\u0119borskie"
    ],
    "name:csb_x_preferred":[
        "\u00d2sow\u00f2 L\u00e3b\u00f2rscz\u00e9"
    ],
    "name:deu_x_preferred":[
        "Osowo L\u0119borskie"
    ],
    "name:pol_x_preferred":[
        "Osowo L\u0119borskie"
    ],
    "wof:name":"Osowo Leborskie",
    "wof:placetype":"locality"
},
  "geometry": {"coordinates":[17.78491,54.46691],"type":"Point"}
}