{
  "type": "Feature",
  "properties": {
    "gn:admin1_code":"87.0",
    "gn:admin2_code":"3201.0",
    "gn:admin3_code":"320102.0",
    "gn:asciiname":"Zelimucha",
    "gn:country_code":"PL",
    "gn:dem":18,
    "gn:feature_class":"P",
    "gn:feature_code":"PPL",
    "gn:name":"\u017belimucha",
    "gn:population":0,
    "gn:timezone":"Europe/Warsaw",
    "iso:country":"PL",
    "name:deu_x_preferred":[
        "\u017belimucha"
    ],
    "name:pol_x_preferred":[
        "\u017belimucha"
    ],
    "name:ukr_x_preferred":[
        "\u0416\u0435\u043b\u0456\u043c\u0443\u0445\u0430"
    ],
    "name:und_x_variant":[
        "Buchhorst",
        "\u017belimucha"
    ],
    "name:vie_x_preferred":[
        "\u017belimucha"
    ],
    "wof:name":"Zelimucha",
    "wof:placetype":"locality"
},
  "geometry": {"coordinates":[15.97487,54.06423],"type":"Point"}
}