{
  "type": "Feature",
  "properties": {
    "gn:admin1_code":"84.0",
    "gn:admin2_code":"2604.0",
    "gn:admin3_code":"260419.0",
    "gn:asciiname":"Koloman",
    "gn:country_code":"PL",
    "gn:dem":305,
    "gn:feature_class":"P",
    "gn:feature_code":"PPL",
    "gn:name":"Ko\u0142oma\u0144",
    "gn:population":0,
    "gn:timezone":"Europe/Warsaw",
    "iso:country":"PL",
    "name:ceb_x_preferred":[
        "Ko\u0142oma\u0144"
    ],
    "name:nld_x_preferred":[
        "Ko\u0142oma\u0144"
    ],
    "name:pol_x_preferred":[
        "Ko\u0142oma\u0144"
    ],
    "name:ukr_x_preferred":[
        "\u041a\u043e\u043b\u043e\u043c\u0430\u043d\u044c"
    ],
    "wof:name":"Koloman",
    "wof:placetype":"locality"
},
  "geometry": {"coordinates":[20.6039,51.00448],"type":"Point"}
}