{
  "type": "Feature",
  "properties": {
    "gn:admin1_code":"84.0",
    "gn:admin2_code":"2604.0",
    "gn:admin3_code":"260419.0",
    "gn:asciiname":"Koloman",
    "gn:country_code":"PL",
    "gn:dem":305,
    "gn:feature_class":"P",
    "gn:feature_code":"PPL",
    "gn:name":"Ko\u0142oma\u0144",
    "gn:population":0,
    "gn:timezone":"Europe/Warsaw",
    "iso:country":"PL",
    "name:und_x_variant":[
        "Ko\u0142oma\u0144"
    ],
    "wof:name":"Koloman",
    "wof:placetype":"locality"
},
  "geometry": {"coordinates":[20.6039,51.00448],"type":"Point"}
}