{
  "type": "Feature",
  "properties": {
    "gn:admin1_code":"72.0",
    "gn:admin2_code":"219.0",
    "gn:admin3_code":"21905.0",
    "gn:asciiname":"Gola Swidnicka",
    "gn:country_code":"PL",
    "gn:dem":187,
    "gn:feature_class":"P",
    "gn:feature_code":"PPL",
    "gn:name":"Gola Swidnicka",
    "gn:population":0,
    "gn:timezone":"Europe/Warsaw",
    "iso:country":"PL",
    "name:pol_x_preferred":[
        "Gola \u015awidnicka"
    ],
    "name:ukr_x_preferred":[
        "\u0490\u043e\u043b\u044f-\u0421\u044c\u0432\u0456\u0434\u043d\u0456\u0446\u044c\u043a\u0430"
    ],
    "wof:name":"Gola Swidnicka",
    "wof:placetype":"locality"
},
  "geometry": {"coordinates":[16.61038,50.91862],"type":"Point"}
}