{
  "type": "Feature",
  "properties": {
    "gn:admin1_code":"79.0",
    "gn:admin2_code":"1602.0",
    "gn:admin3_code":"160203.0",
    "gn:asciiname":"Grobniki",
    "gn:country_code":"PL",
    "gn:dem":251,
    "gn:feature_class":"P",
    "gn:feature_code":"PPL",
    "gn:name":"Grobniki",
    "gn:population":0,
    "gn:timezone":"Europe/Warsaw",
    "iso:country":"PL",
    "name:pol_x_preferred":[
        "Grobniki"
    ],
    "name:ukr_x_preferred":[
        "\u0490\u0440\u043e\u0431\u043d\u0438\u043a\u0438"
    ],
    "wof:name":"Grobniki",
    "wof:placetype":"locality"
},
  "geometry": {"coordinates":[17.87098,50.19734],"type":"Point"}
}