{
  "type": "Feature",
  "properties": {
    "gn:admin1_code":"87.0",
    "gn:admin2_code":"3201.0",
    "gn:admin3_code":"320104.0",
    "gn:asciiname":"Bukowo",
    "gn:country_code":"PL",
    "gn:dem":83,
    "gn:feature_class":"P",
    "gn:feature_code":"PPL",
    "gn:name":"Bukowo",
    "gn:population":0,
    "gn:timezone":"Europe/Warsaw",
    "iso:country":"PL",
    "name:deu_x_preferred":[
        "Bukowo"
    ],
    "name:pol_x_preferred":[
        "Bukowo"
    ],
    "name:vie_x_preferred":[
        "Bukowo"
    ],
    "wof:name":"Bukowo",
    "wof:placetype":"locality"
},
  "geometry": {"coordinates":[16.24221,53.97528000000001],"type":"Point"}
}