{
  "type": "Feature",
  "properties": {
    "gn:admin1_code":"79.0",
    "gn:admin2_code":"1607.0",
    "gn:admin3_code":"160705.0",
    "gn:asciiname":"Lipowa",
    "gn:country_code":"PL",
    "gn:dem":256,
    "gn:feature_class":"P",
    "gn:feature_code":"PPL",
    "gn:name":"Lipowa",
    "gn:population":0,
    "gn:timezone":"Europe/Warsaw",
    "iso:country":"PL",
    "name:deu_x_preferred":[
        "Lipowa"
    ],
    "name:pol_x_preferred":[
        "Lipowa"
    ],
    "name:ukr_x_preferred":[
        "\u041b\u0456\u043f\u043e\u0432\u0430"
    ],
    "wof:name":"Lipowa",
    "wof:placetype":"locality"
},
  "geometry": {"coordinates":[17.4692,50.40061],"type":"Point"}
}