{
  "type": "Feature",
  "properties": {
    "gn:admin1_code":"73.0",
    "gn:admin2_code":"414.0",
    "gn:admin3_code":"41406.0",
    "gn:asciiname":"Rychlawa",
    "gn:cc2":"PL",
    "gn:country_code":"PL",
    "gn:dem":78,
    "gn:feature_class":"P",
    "gn:feature_code":"PPL",
    "gn:name":"Rych\u0142awa",
    "gn:population":0,
    "gn:timezone":"Europe/Warsaw",
    "iso:country":"PL",
    "name:und_x_variant":[
        "Rych\u0142owa",
        "Rych\u0142awa"
    ],
    "wof:name":"Rychlawa",
    "wof:placetype":"locality"
},
  "geometry": {"coordinates":[18.67212,53.6842],"type":"Point"}
}