{
  "type": "Feature",
  "properties": {
    "gn:admin1_code":"76.0",
    "gn:admin2_code":"806.0",
    "gn:admin3_code":"80605.0",
    "gn:asciiname":"Przysieka",
    "gn:country_code":"PL",
    "gn:dem":22,
    "gn:feature_class":"P",
    "gn:feature_code":"PPL",
    "gn:name":"Przysieka",
    "gn:population":0,
    "gn:timezone":"Europe/Warsaw",
    "iso:country":"PL",
    "name:ceb_x_preferred":[
        "Przysieka"
    ],
    "name:fra_x_preferred":[
        "Przysieka"
    ],
    "name:pol_x_preferred":[
        "Przysieka"
    ],
    "name:ukr_x_preferred":[
        "\u041f\u0448\u0438\u0441\u0435\u043a\u0430"
    ],
    "wof:name":"Przysieka",
    "wof:placetype":"locality"
},
  "geometry": {"coordinates":[15.54381,52.80371],"type":"Point"}
}