{
  "type": "Feature",
  "properties": {
    "iso:country":"PL",
    "name:pol_x_preferred":[
        "Ojrze\u0144"
    ],
    "wof:coterminous":[
        1125375695
    ],
    "wof:name":"Ojrze\u0144",
    "wof:placetype":"locality"
},
  "geometry": {"coordinates":[20.5285979820738,52.7661432859047],"type":"Point"}
}