{
  "type": "Feature",
  "properties": {
    "gn:admin1_code":"81.0",
    "gn:admin2_code":"2009.0",
    "gn:admin3_code":"200905.0",
    "gn:asciiname":"Buble",
    "gn:country_code":"PL",
    "gn:dem":144,
    "gn:feature_class":"P",
    "gn:feature_code":"PPL",
    "gn:name":"Buble",
    "gn:population":0,
    "gn:timezone":"Europe/Warsaw",
    "iso:country":"PL",
    "name:lit_x_preferred":[
        "Bubeliai"
    ],
    "name:pol_x_preferred":[
        "Bubele"
    ],
    "name:ukr_x_preferred":[
        "\u0411\u0443\u0431\u0435\u043b\u0435"
    ],
    "name:und_x_variant":[
        "Bubele",
        "Buble"
    ],
    "wof:name":"Buble",
    "wof:placetype":"locality"
},
  "geometry": {"coordinates":[23.36522,54.17056],"type":"Point"}
}