{
  "type": "Feature",
  "properties": {
    "gn:admin1_code":"78.0",
    "gn:admin2_code":"1413.0",
    "gn:admin3_code":"141301.0",
    "gn:asciiname":"Krajewo",
    "gn:country_code":"PL",
    "gn:dem":161,
    "gn:feature_class":"P",
    "gn:feature_code":"PPL",
    "gn:name":"Krajewo",
    "gn:population":0,
    "gn:timezone":"Europe/Warsaw",
    "iso:country":"PL",
    "name:pol_x_preferred":[
        "Krajewo"
    ],
    "wof:name":"Krajewo",
    "wof:placetype":"locality"
},
  "geometry": {"coordinates":[20.38445,53.15552],"type":"Point"}
}