{
  "type": "Feature",
  "properties": {
    "gn:admin1_code":"73.0",
    "gn:admin2_code":"401.0",
    "gn:admin3_code":"40109.0",
    "gn:asciiname":"Kolonia Bodzanowo",
    "gn:country_code":"PL",
    "gn:dem":88,
    "gn:feature_class":"P",
    "gn:feature_code":"PPL",
    "gn:name":"Kolonia Bodzanowo",
    "gn:population":0,
    "gn:timezone":"Europe/Warsaw",
    "iso:country":"PL",
    "wof:name":"Kolonia Bodzanowo",
    "wof:placetype":"locality"
},
  "geometry": {"coordinates":[18.65,52.71666999999999],"type":"Point"}
}