{
  "type": "Feature",
  "properties": {
    "gn:admin1_code":"73.0",
    "gn:asciiname":"Siemianowo",
    "gn:country_code":"PL",
    "gn:dem":114,
    "gn:feature_class":"P",
    "gn:feature_code":"PPL",
    "gn:name":"Siemianowo",
    "gn:population":0,
    "gn:timezone":"Europe/Warsaw",
    "iso:country":"PL",
    "name:fra_x_preferred":[
        "Siemianowo"
    ],
    "name:pol_x_preferred":[
        "Siemianowo"
    ],
    "name:ukr_x_preferred":[
        "\u0421\u0435\u043c\u044f\u043d\u043e\u0432\u043e"
    ],
    "wof:name":"Siemianowo",
    "wof:placetype":"locality"
},
  "geometry": {"coordinates":[17.39359,52.53753],"type":"Point"}
}