{
  "type": "Feature",
  "properties": {
    "gn:admin1_code":"75.0",
    "gn:admin2_code":"612.0",
    "gn:admin3_code":"61207.0",
    "gn:asciiname":"Zagloba",
    "gn:country_code":"PL",
    "gn:dem":126,
    "gn:feature_class":"P",
    "gn:feature_code":"PPL",
    "gn:name":"Zag\u0142oba",
    "gn:population":0,
    "gn:timezone":"Europe/Warsaw",
    "iso:country":"PL",
    "name:und_x_variant":[
        "Zag\u0142oba"
    ],
    "wof:name":"Zagloba",
    "wof:placetype":"locality"
},
  "geometry": {"coordinates":[21.86039,51.2259],"type":"Point"}
}