{
  "type": "Feature",
  "properties": {
    "gn:admin1_code":"75.0",
    "gn:admin2_code":"612.0",
    "gn:admin3_code":"61207.0",
    "gn:asciiname":"Zagloba",
    "gn:country_code":"PL",
    "gn:dem":126,
    "gn:feature_class":"P",
    "gn:feature_code":"PPL",
    "gn:name":"Zag\u0142oba",
    "gn:population":0,
    "gn:timezone":"Europe/Warsaw",
    "iso:country":"PL",
    "name:azb_x_preferred":[
        "\u0632\u0627\u0642\u0648\u0648\u0628\u0627"
    ],
    "name:fas_x_preferred":[
        "\u0632\u0627\u06af\u0648\u0648\u0628\u0627"
    ],
    "name:fra_x_preferred":[
        "Zag\u0142oba"
    ],
    "name:pol_x_preferred":[
        "Zag\u0142oba"
    ],
    "name:ukr_x_preferred":[
        "\u0417\u0430\u0491\u043b\u043e\u0431\u0430"
    ],
    "name:urd_x_preferred":[
        "\u0632\u06af\u0648\u0648\u0628\u0627"
    ],
    "wof:name":"Zagloba",
    "wof:placetype":"locality"
},
  "geometry": {"coordinates":[21.86039,51.2259],"type":"Point"}
}