{
  "type": "Feature",
  "properties": {
    "gn:admin1_code":"87.0",
    "gn:admin2_code":"3202.0",
    "gn:admin3_code":"320206.0",
    "gn:asciiname":"Slutowo",
    "gn:country_code":"PL",
    "gn:dem":104,
    "gn:feature_class":"P",
    "gn:feature_code":"PPL",
    "gn:name":"S\u0142utowo",
    "gn:population":0,
    "gn:timezone":"Europe/Warsaw",
    "iso:country":"PL",
    "name:pol_x_preferred":[
        "S\u0142utowo"
    ],
    "name:und_x_variant":[
        "S\u0142utowo"
    ],
    "name:vie_x_preferred":[
        "S\u0142utowo"
    ],
    "wof:name":"Slutowo",
    "wof:placetype":"locality"
},
  "geometry": {"coordinates":[15.60023,53.28386999999999],"type":"Point"}
}