{
  "type": "Feature",
  "properties": {
    "gn:admin1_code":"78.0",
    "gn:admin2_code":"1420.0",
    "gn:admin3_code":"142007.0",
    "gn:asciiname":"Januszewo",
    "gn:country_code":"PL",
    "gn:dem":127,
    "gn:feature_class":"P",
    "gn:feature_code":"PPL",
    "gn:name":"Januszewo",
    "gn:population":0,
    "gn:timezone":"Europe/Warsaw",
    "iso:country":"PL",
    "name:azb_x_preferred":[
        "\u06cc\u0627\u0646\u0648\u0634\u0648\u0648"
    ],
    "name:fas_x_preferred":[
        "\u06cc\u0627\u0646\u0648\u0634\u0648\u0648"
    ],
    "name:fra_x_preferred":[
        "Januszewo"
    ],
    "name:pol_x_preferred":[
        "Januszewo"
    ],
    "name:ukr_x_preferred":[
        "\u042f\u043d\u0443\u0448\u0435\u0432\u043e"
    ],
    "name:urd_x_preferred":[
        "\u062c\u0627\u0646\u0633\u0632\u0648\u0648"
    ],
    "wof:name":"Januszewo",
    "wof:placetype":"locality"
},
  "geometry": {"coordinates":[20.41775,52.48496],"type":"Point"}
}