{
  "type": "Feature",
  "properties": {
    "gn:admin1_code":"78.0",
    "gn:admin2_code":"1408.0",
    "gn:admin3_code":"140804.0",
    "gn:asciiname":"Karolino",
    "gn:country_code":"PL",
    "gn:dem":101,
    "gn:feature_class":"P",
    "gn:feature_code":"PPL",
    "gn:name":"Karolino",
    "gn:population":0,
    "gn:timezone":"Europe/Warsaw",
    "iso:country":"PL",
    "name:fra_x_preferred":[
        "Karolino"
    ],
    "name:pol_x_preferred":[
        "Karolino"
    ],
    "name:ukr_x_preferred":[
        "\u041a\u0430\u0440\u043e\u043b\u0456\u043d\u043e"
    ],
    "wof:name":"Karolino",
    "wof:placetype":"locality"
},
  "geometry": {"coordinates":[21.02248,52.51227],"type":"Point"}
}