{
  "type": "Feature",
  "properties": {
    "gn:country":"PL",
    "gn:fcode":"PPL",
    "gn:population":0,
    "iso:country":"PL",
    "name:ast_x_preferred":[
        "Czerna"
    ],
    "name:ceb_x_preferred":[
        "Czerna"
    ],
    "name:ces_x_preferred":[
        "Czerna"
    ],
    "name:che_x_preferred":[
        "\u0427\u0435\u0440\u043d\u0430"
    ],
    "name:deu_x_preferred":[
        "Czerna"
    ],
    "name:diq_x_preferred":[
        "Czerna"
    ],
    "name:eng_x_preferred":[
        "Czerna"
    ],
    "name:fra_x_preferred":[
        "Czerna"
    ],
    "name:nan_x_preferred":[
        "Czerna"
    ],
    "name:pol_x_preferred":[
        "Czerna"
    ],
    "name:spa_x_preferred":[
        "Czerna"
    ],
    "name:tat_x_preferred":[
        "\u0427\u0435\u0440\u043d\u0430"
    ],
    "name:ukr_x_preferred":[
        "\u0427\u0435\u0440\u043d\u0430"
    ],
    "qs_pg:aaroncc":"PL",
    "qs_pg:gn_country":"PL",
    "qs_pg:gn_fcode":"PPL",
    "qs_pg:gn_pop":0,
    "qs_pg:name":"Czerna",
    "qs_pg:name_adm0":"Polska",
    "qs_pg:name_adm1":"Ma\u0142opolskie",
    "qs_pg:photos":6,
    "qs_pg:photos_1k":1,
    "qs_pg:photos_9k":1,
    "qs_pg:photos_9r":1,
    "qs_pg:photos_all":6,
    "qs_pg:photos_sr":1,
    "qs_pg:pop_sr":0,
    "qs_pg:qs_pg_placetype":"locality",
    "qs_pg:qs_pg_placetype_gp":"Town",
    "qs_pg:woe_adm0":23424923,
    "woe:adm0_id":23424923,
    "woe:name_adm0":"Polska",
    "woe:name_adm1":"Ma\u0142opolskie",
    "woe:placetype":"Town",
    "wof:name":"Czerna",
    "wof:placetype":"locality"
},
  "geometry": {"coordinates":[19.61732,50.17355],"type":"Point"}
}