{
  "type": "Feature",
  "properties": {
    "gn:admin1_code":"84.0",
    "gn:admin2_code":"2608.0",
    "gn:admin3_code":"260804.0",
    "gn:asciiname":"Zakrzow",
    "gn:country_code":"PL",
    "gn:dem":183,
    "gn:feature_class":"P",
    "gn:feature_code":"PPL",
    "gn:name":"Zakrz\u00f3w",
    "gn:population":0,
    "gn:timezone":"Europe/Warsaw",
    "iso:country":"PL",
    "name:pol_x_preferred":[
        "Zakrz\u00f3w"
    ],
    "name:ukr_x_preferred":[
        "\u0417\u0430\u043a\u0448\u0443\u0432"
    ],
    "wof:name":"Zakrzow",
    "wof:placetype":"locality"
},
  "geometry": {"coordinates":[20.53173,50.48349],"type":"Point"}
}