{
  "type": "Feature",
  "properties": {
    "gn:admin1_code":"86.0",
    "gn:admin2_code":"3027.0",
    "gn:admin3_code":"302703.0",
    "gn:asciiname":"Strachanow",
    "gn:country_code":"PL",
    "gn:dem":133,
    "gn:feature_class":"P",
    "gn:feature_code":"PPL",
    "gn:name":"Strachan\u00f3w",
    "gn:population":0,
    "gn:timezone":"Europe/Warsaw",
    "iso:country":"PL",
    "name:pol_x_preferred":[
        "Strachan\u00f3w"
    ],
    "name:ukr_x_preferred":[
        "\u0421\u0442\u0440\u0430\u0445\u0430\u043d\u0443\u0432"
    ],
    "name:und_x_variant":[
        "Strachan\u00f3w"
    ],
    "wof:name":"Strachanow",
    "wof:placetype":"locality"
},
  "geometry": {"coordinates":[18.65,51.85],"type":"Point"}
}