{
  "type": "Feature",
  "properties": {
    "gn:admin1_code":"78.0",
    "gn:admin2_code":"1435.0",
    "gn:admin3_code":"143504.0",
    "gn:asciiname":"Huta Podgorna",
    "gn:country_code":"PL",
    "gn:dem":91,
    "gn:feature_class":"P",
    "gn:feature_code":"PPL",
    "gn:name":"Huta Podg\u00f3rna",
    "gn:population":0,
    "gn:timezone":"Europe/Warsaw",
    "iso:country":"PL",
    "name:fra_x_preferred":[
        "Huta Podg\u00f3rna"
    ],
    "name:pol_x_preferred":[
        "Huta Podg\u00f3rna"
    ],
    "name:ukr_x_preferred":[
        "\u0413\u0443\u0442\u0430-\u041f\u043e\u0434\u0491\u0443\u0440\u043d\u0430"
    ],
    "wof:name":"Huta Podgorna",
    "wof:placetype":"locality"
},
  "geometry": {"coordinates":[21.16982,52.55289000000001],"type":"Point"}
}