{
  "type": "Feature",
  "properties": {
    "gn:gn_country":"PL",
    "gn:gn_fcode":"PPLX",
    "gn:gn_pop":0,
    "iso:country":"PL",
    "name:fra_x_preferred":[
        "Biskupie"
    ],
    "name:pol_x_preferred":[
        "Biskupie"
    ],
    "name:ukr_x_preferred":[
        "\u0411\u0456\u0441\u043a\u0443\u043f\u0435"
    ],
    "qs_pg:aaroncc":"PL",
    "qs_pg:gn_country":"PL",
    "qs_pg:gn_fcode":"PPLX",
    "qs_pg:gn_pop":0,
    "qs_pg:name":"Biskupie",
    "qs_pg:name_adm0":"Polska",
    "qs_pg:name_adm1":"Lubelskie",
    "qs_pg:photos":430,
    "qs_pg:photos_1k":87,
    "qs_pg:photos_9k":2,
    "qs_pg:photos_9r":5,
    "qs_pg:photos_all":430,
    "qs_pg:photos_sr":6,
    "qs_pg:pop_sr":0,
    "qs_pg:qs_pg_placetype":"neighbourhood",
    "qs_pg:qs_pg_placetype_gp":"Suburb",
    "qs_pg:woe_adm0":23424923,
    "woe:adm0_id":23424923,
    "woe:name_adm0":"Polska",
    "woe:name_adm1":"Lubelskie",
    "woe:placetype":"Suburb",
    "wof:name":"Biskupie",
    "wof:placetype":"neighbourhood"
},
  "geometry": {"coordinates":[22.66036,51.24738],"type":"Point"}
}