{
  "type": "Feature",
  "properties": {
    "gn:gn_country":"PL",
    "gn:gn_fcode":"PPL",
    "gn:gn_pop":332,
    "gn:population":332,
    "iso:country":"PL",
    "name:eng_x_preferred":[
        "Kostkowice"
    ],
    "name:fra_x_preferred":[
        "Kostkowice"
    ],
    "name:pol_x_preferred":[
        "Kostkowice"
    ],
    "qs_pg:aaroncc":"PL",
    "qs_pg:gn_country":"PL",
    "qs_pg:gn_fcode":"PPL",
    "qs_pg:gn_pop":332,
    "qs_pg:name":"Kostkowice",
    "qs_pg:name_adm0":"Polska",
    "qs_pg:name_adm1":"Sl\u0105skie",
    "qs_pg:photos_9r":0,
    "qs_pg:photos_sr":0,
    "qs_pg:pop_sr":2,
    "qs_pg:qs_pg_placetype":"locality",
    "qs_pg:qs_pg_placetype_gp":"Town",
    "qs_pg:woe_adm0":23424923,
    "woe:adm0_id":23424923,
    "woe:name_adm0":"Polska",
    "woe:name_adm1":"Sl\u0105skie",
    "woe:placetype":"Town",
    "wof:name":"Kostkowice",
    "wof:placetype":"locality",
    "wof:population":332
},
  "geometry": {"coordinates":[19.57523,50.58498],"type":"Point"}
}