{
  "type": "Feature",
  "properties": {
    "gn:admin1_code":"86.0",
    "gn:admin2_code":"3016.0",
    "gn:admin3_code":"301601.0",
    "gn:asciiname":"Kiszewo",
    "gn:country_code":"PL",
    "gn:dem":53,
    "gn:feature_class":"P",
    "gn:feature_code":"PPL",
    "gn:name":"Kiszewo",
    "gn:population":0,
    "gn:timezone":"Europe/Warsaw",
    "iso:country":"PL",
    "name:azb_x_preferred":[
        "\u06a9\u06cc\u0634\u0648\u0648"
    ],
    "name:ceb_x_preferred":[
        "Kiszewo"
    ],
    "name:fas_x_preferred":[
        "\u06a9\u06cc\u0634\u0648\u0648"
    ],
    "name:fra_x_preferred":[
        "Kiszewo"
    ],
    "name:pol_x_preferred":[
        "Kiszewo"
    ],
    "name:ukr_x_preferred":[
        "\u041a\u0456\u0448\u0435\u0432\u043e"
    ],
    "wof:name":"Kiszewo",
    "wof:placetype":"locality"
},
  "geometry": {"coordinates":[16.67381,52.67943],"type":"Point"}
}