{
  "type": "Feature",
  "properties": {
    "gn:admin1_code":"84.0",
    "gn:admin2_code":"2602.0",
    "gn:admin3_code":"260207.0",
    "gn:asciiname":"Wywla",
    "gn:country_code":"PL",
    "gn:dem":271,
    "gn:feature_class":"P",
    "gn:feature_code":"PPL",
    "gn:name":"Wyw\u0142a",
    "gn:population":0,
    "gn:timezone":"Europe/Warsaw",
    "iso:country":"PL",
    "name:ceb_x_preferred":[
        "Wyw\u0142a"
    ],
    "name:pol_x_preferred":[
        "Wyw\u0142a"
    ],
    "name:ukr_x_preferred":[
        "\u0412\u0438\u0432\u043b\u0430"
    ],
    "wof:name":"Wywla",
    "wof:placetype":"locality"
},
  "geometry": {"coordinates":[19.91879,50.61429],"type":"Point"}
}