{
  "type": "Feature",
  "properties": {
    "gn:admin1_code":"84.0",
    "gn:admin2_code":"2602.0",
    "gn:admin3_code":"260207.0",
    "gn:asciiname":"Wywla",
    "gn:country_code":"PL",
    "gn:dem":271,
    "gn:feature_class":"P",
    "gn:feature_code":"PPL",
    "gn:name":"Wyw\u0142a",
    "gn:population":0,
    "gn:timezone":"Europe/Warsaw",
    "iso:country":"PL",
    "name:und_x_variant":[
        "Wyw\u0142a"
    ],
    "wof:name":"Wywla",
    "wof:placetype":"locality"
},
  "geometry": {"coordinates":[19.91879,50.61429],"type":"Point"}
}