{
  "type": "Feature",
  "properties": {
    "gn:admin1_code":"85.0",
    "gn:admin2_code":"2812.0",
    "gn:admin3_code":"281204.0",
    "gn:asciiname":"Kaciki",
    "gn:country_code":"PL",
    "gn:dem":112,
    "gn:feature_class":"P",
    "gn:feature_code":"PPL",
    "gn:name":"K\u0105ciki",
    "gn:population":0,
    "gn:timezone":"Europe/Warsaw",
    "iso:country":"PL",
    "name:pol_x_preferred":[
        "K\u0105ciki"
    ],
    "name:ukr_x_preferred":[
        "\u041a\u043e\u043d\u0446\u0438\u043a\u0438"
    ],
    "wof:name":"Kaciki",
    "wof:placetype":"locality"
},
  "geometry": {"coordinates":[19.49558,53.38097],"type":"Point"}
}