{
  "type": "Feature",
  "properties": {
    "gn:admin1_code":"83.0",
    "gn:admin2_code":"2406.0",
    "gn:admin3_code":"240604.0",
    "gn:asciiname":"Mazowki",
    "gn:country_code":"PL",
    "gn:dem":216,
    "gn:feature_class":"P",
    "gn:feature_code":"PPL",
    "gn:name":"Maz\u00f3wki",
    "gn:population":0,
    "gn:timezone":"Europe/Warsaw",
    "iso:country":"PL",
    "name:pol_x_preferred":[
        "Maz\u00f3wki"
    ],
    "name:ukr_x_preferred":[
        "\u041c\u0430\u0437\u0443\u0432\u043a\u0456"
    ],
    "wof:name":"Mazowki",
    "wof:placetype":"locality"
},
  "geometry": {"coordinates":[19.05343,50.99684],"type":"Point"}
}