{
  "type": "Feature",
  "properties": {
    "gn:admin1_code":"81.0",
    "gn:admin2_code":"2014.0",
    "gn:admin3_code":"201403.0",
    "gn:asciiname":"Zambrzyce Stare",
    "gn:country_code":"PL",
    "gn:dem":118,
    "gn:feature_class":"P",
    "gn:feature_code":"PPL",
    "gn:name":"Zambrzyce Stare",
    "gn:population":0,
    "gn:timezone":"Europe/Warsaw",
    "iso:country":"PL",
    "name:lit_x_preferred":[
        "Stare Zamb\u017eic\u0117"
    ],
    "name:pol_x_preferred":[
        "Stare Zambrzyce"
    ],
    "name:ukr_x_preferred":[
        "\u0421\u0442\u0430\u0440\u0435 \u0417\u0430\u043c\u0431\u0436\u0438\u0446\u0435"
    ],
    "wof:name":"Zambrzyce Stare",
    "wof:placetype":"locality"
},
  "geometry": {"coordinates":[22.52783,53.10121],"type":"Point"}
}