{
  "type": "Feature",
  "properties": {
    "gn:country":"PL",
    "gn:fcode":"PPL",
    "gn:population":1064,
    "iso:country":"PL",
    "name:ceb_x_preferred":[
        "Osiek"
    ],
    "name:deu_x_preferred":[
        "Osiek"
    ],
    "name:fra_x_preferred":[
        "Osiek"
    ],
    "name:heb_x_preferred":[
        "\u05d0\u05d5\u05e9\u05d9\u05d9\u05e7"
    ],
    "name:ita_x_preferred":[
        "Osiek"
    ],
    "name:jav_x_preferred":[
        "Osiek"
    ],
    "name:nld_x_preferred":[
        "Osiek"
    ],
    "name:pol_x_preferred":[
        "Osiek"
    ],
    "name:und_x_variant":[
        "Osiek-nad-Wis\u0142a"
    ],
    "name:vie_x_preferred":[
        "Osiek"
    ],
    "qs_pg:aaroncc":"PL",
    "qs_pg:gn_country":"PL",
    "qs_pg:gn_fcode":"PPL",
    "qs_pg:gn_pop":1064,
    "qs_pg:name":"Osiek",
    "qs_pg:name_adm0":"Polska",
    "qs_pg:name_adm1":"Kujawsko-Pomorskie",
    "qs_pg:photos_9r":0,
    "qs_pg:photos_sr":0,
    "qs_pg:pop_sr":3,
    "qs_pg:qs_pg_placetype":"locality",
    "qs_pg:qs_pg_placetype_gp":"Town",
    "qs_pg:woe_adm0":23424923,
    "woe:adm0_id":23424923,
    "woe:name_adm0":"Polska",
    "woe:name_adm1":"Kujawsko-Pomorskie",
    "woe:placetype":"Town",
    "wof:name":"Osiek",
    "wof:placetype":"locality",
    "wof:population":1064
},
  "geometry": {"coordinates":[18.80765,52.92629],"type":"Point"}
}