{
  "type": "Feature",
  "properties": {
    "gn:admin1_code":"85.0",
    "gn:admin2_code":"2804.0",
    "gn:admin3_code":"280401.0",
    "gn:asciiname":"Olszanki",
    "gn:cc2":"PL",
    "gn:country_code":"PL",
    "gn:dem":-2,
    "gn:feature_class":"P",
    "gn:feature_code":"PPL",
    "gn:name":"Olszanki",
    "gn:population":0,
    "gn:timezone":"Europe/Warsaw",
    "iso:country":"PL",
    "name:und_x_variant":[
        "Ellerwald",
        "Olszanki"
    ],
    "wof:name":"Olszanki",
    "wof:placetype":"locality"
},
  "geometry": {"coordinates":[19.33333,54.16667],"type":"Point"}
}