{
  "type": "Feature",
  "properties": {
    "gn:admin1_code":"80.0",
    "gn:admin2_code":"1803.0",
    "gn:admin3_code":"180303.0",
    "gn:asciiname":"Chotowa",
    "gn:country_code":"PL",
    "gn:dem":194,
    "gn:feature_class":"P",
    "gn:feature_code":"PPL",
    "gn:name":"Chotowa",
    "gn:population":0,
    "gn:timezone":"Europe/Warsaw",
    "iso:country":"PL",
    "name:ceb_x_preferred":[
        "Chotowa"
    ],
    "name:ita_x_preferred":[
        "Chotowa"
    ],
    "name:pol_x_preferred":[
        "Chotowa"
    ],
    "name:spa_x_preferred":[
        "Chotowa"
    ],
    "name:ukr_x_preferred":[
        "\u0425\u043e\u0442\u043e\u0432\u0430"
    ],
    "wof:name":"Chotowa",
    "wof:placetype":"locality"
},
  "geometry": {"coordinates":[21.30744,50.02533],"type":"Point"}
}