{
  "type": "Feature",
  "properties": {
    "gn:admin1_code":"72.0",
    "gn:admin2_code":"203.0",
    "gn:admin3_code":"20306.0",
    "gn:asciiname":"Czerna",
    "gn:country_code":"PL",
    "gn:dem":68,
    "gn:feature_class":"P",
    "gn:feature_code":"PPL",
    "gn:name":"Czerna",
    "gn:population":0,
    "gn:timezone":"Europe/Warsaw",
    "iso:country":"PL",
    "name:ceb_x_preferred":[
        "Czerna"
    ],
    "name:deu_x_historical":[
        "Klein Tschirne"
    ],
    "name:deu_x_preferred":[
        "Klein Tschirne"
    ],
    "name:pol_x_preferred":[
        "Czerna"
    ],
    "name:spa_x_preferred":[
        "Czerna"
    ],
    "name:ukr_x_preferred":[
        "\u0427\u0435\u0440\u043d\u0430"
    ],
    "wof:name":"Czerna",
    "wof:placetype":"locality"
},
  "geometry": {"coordinates":[15.90786,51.71129000000001],"type":"Point"}
}