{
  "type": "Feature",
  "properties": {
    "gn:population":3438,
    "iso:country":"PL",
    "name:ast_x_preferred":[
        "Rajcza"
    ],
    "name:azb_x_preferred":[
        "\u0631\u0627\u06cc\u0686\u0627"
    ],
    "name:deu_x_preferred":[
        "Rajcza"
    ],
    "name:eng_x_preferred":[
        "Rajcza"
    ],
    "name:fas_x_preferred":[
        "\u0631\u0627\u06cc\u0686\u0627"
    ],
    "name:fra_x_preferred":[
        "Rajcza"
    ],
    "name:nld_x_preferred":[
        "Rajcza"
    ],
    "name:pol_x_preferred":[
        "Rajcza"
    ],
    "name:szl_x_preferred":[
        "Rajcza"
    ],
    "name:ukr_x_preferred":[
        "\u0420\u0430\u0439\u0447\u0430"
    ],
    "qs:a0":"Rzeczpospolita Polska",
    "qs:a1":"*Slaskie",
    "qs:a1r":"0",
    "qs:a2":"Zywiecki",
    "qs:adm0":"Rzeczpospolita Polska",
    "qs:la":"Rajcza",
    "qs:la_lc":"*PL2417112",
    "qs:level":"locality",
    "qs:loc":"Rajcza",
    "qs:loc_alt":"Rajcza",
    "qs:pop":0,
    "qs:type":"rural point-in-poly",
    "wd:wordcount":443,
    "wof:name":"Rajcza",
    "wof:placetype":"locality",
    "wof:population":3438
},
  "geometry": {"coordinates":[19.0233888372434,49.4694886945651],"type":"Point"}
}