{
  "type": "Feature",
  "properties": {
    "gn:gn_country":"PL",
    "gn:gn_fcode":"PPL",
    "gn:gn_pop":1256,
    "gn:population":1256,
    "iso:country":"PL",
    "name:ceb_x_preferred":[
        "\u017babia Wola"
    ],
    "name:eng_x_preferred":[
        "Gmina \u017babia Wola"
    ],
    "name:fra_x_preferred":[
        "\u017babia Wola"
    ],
    "name:nld_x_preferred":[
        "\u017babia Wola"
    ],
    "name:pol_x_preferred":[
        "\u017babia Wola"
    ],
    "name:por_x_preferred":[
        "Comuna de \u017babia Wola"
    ],
    "name:rus_x_preferred":[
        "\u0416\u0430\u0431\u044f-\u0412\u043e\u043b\u044f"
    ],
    "name:slk_x_preferred":[
        "Gmina \u017babia Wola"
    ],
    "name:ukr_x_preferred":[
        "\u0490\u043c\u0456\u043d\u0430 \u0416\u0430\u0431\u044f \u0412\u043e\u043b\u044f"
    ],
    "name:ukr_x_variant":[
        "\u0416\u0430\u0431\u044f-\u0412\u043e\u043b\u044f"
    ],
    "name:war_x_preferred":[
        "Gmina \u017babia Wola"
    ],
    "qs_pg:aaroncc":"PL",
    "qs_pg:gn_country":"PL",
    "qs_pg:gn_fcode":"PPL",
    "qs_pg:gn_pop":1256,
    "qs_pg:name":"\u017babia Wola",
    "qs_pg:name_adm0":"Polska",
    "qs_pg:name_adm1":"Mazowieckie",
    "qs_pg:photos_9k":1,
    "qs_pg:photos_9r":1,
    "qs_pg:photos_all":8,
    "qs_pg:photos_sr":0,
    "qs_pg:pop_sr":3,
    "qs_pg:qs_pg_placetype":"locality",
    "qs_pg:qs_pg_placetype_gp":"Town",
    "qs_pg:woe_adm0":23424923,
    "woe:adm0_id":23424923,
    "woe:name_adm0":"Polska",
    "woe:name_adm1":"Mazowieckie",
    "woe:placetype":"Town",
    "wof:name":"\u017babia Wola",
    "wof:placetype":"locality",
    "wof:population":1256
},
  "geometry": {"coordinates":[20.69112,52.03169],"type":"Point"}
}