{
  "type": "Feature",
  "properties": {
    "gn:admin1_code":"74.0",
    "gn:admin2_code":"1005.0",
    "gn:admin3_code":"100502.0",
    "gn:asciiname":"Bielawska Wies",
    "gn:country_code":"PL",
    "gn:dem":97,
    "gn:feature_class":"P",
    "gn:feature_code":"PPL",
    "gn:name":"Bielawska Wie\u015b",
    "gn:population":0,
    "gn:timezone":"Europe/Warsaw",
    "iso:country":"PL",
    "name:fra_x_preferred":[
        "Bielawska Wie\u015b"
    ],
    "name:pol_x_preferred":[
        "Bielawska Wie\u015b"
    ],
    "name:ukr_x_preferred":[
        "\u0411\u0435\u043b\u044f\u0432\u0441\u044c\u043a\u0430-\u0412\u0435\u0441\u044c"
    ],
    "name:und_x_variant":[
        "Bielawska Wie\u015b"
    ],
    "wof:name":"Bielawska Wies",
    "wof:placetype":"locality"
},
  "geometry": {"coordinates":[19.65274,52.08689],"type":"Point"}
}