{
  "type": "Feature",
  "properties": {
    "gn:admin1_code":"82.0",
    "gn:admin2_code":"2215.0",
    "gn:admin3_code":"221509.0",
    "gn:asciiname":"Kowalewo",
    "gn:country_code":"PL",
    "gn:dem":199,
    "gn:feature_class":"P",
    "gn:feature_code":"PPL",
    "gn:name":"Kowalewo",
    "gn:population":0,
    "gn:timezone":"Europe/Warsaw",
    "iso:country":"PL",
    "name:ceb_x_preferred":[
        "Kowalewo"
    ],
    "name:csb_x_preferred":[
        "K\u00f2w\u00f4lew\u00f2"
    ],
    "name:pol_x_preferred":[
        "Kowalewo"
    ],
    "name:ukr_x_preferred":[
        "\u041a\u043e\u0432\u0430\u043b\u0435\u0432\u043e"
    ],
    "wof:name":"Kowalewo",
    "wof:placetype":"locality"
},
  "geometry": {"coordinates":[18.25801,54.4361],"type":"Point"}
}