{
  "type": "Feature",
  "properties": {
    "gn:country":"PL",
    "gn:fcode":"PPL",
    "gn:population":272,
    "iso:country":"PL",
    "name:ceb_x_preferred":[
        "L\u0105dek"
    ],
    "name:fra_x_preferred":[
        "L\u0105dek"
    ],
    "name:nld_x_preferred":[
        "L\u0105dek"
    ],
    "name:pol_x_preferred":[
        "L\u0105dek"
    ],
    "name:ukr_x_preferred":[
        "\u041b\u044c\u043e\u043d\u0434\u0435\u043a"
    ],
    "qs_pg:aaroncc":"PL",
    "qs_pg:gn_country":"PL",
    "qs_pg:gn_fcode":"PPL",
    "qs_pg:gn_pop":272,
    "qs_pg:name":"L\u0105dek",
    "qs_pg:name_adm0":"Polska",
    "qs_pg:name_adm1":"Wielkopolskie",
    "qs_pg:photos_9k":1,
    "qs_pg:photos_9r":1,
    "qs_pg:photos_all":4,
    "qs_pg:photos_sr":0,
    "qs_pg:pop_sr":2,
    "qs_pg:qs_pg_placetype":"locality",
    "qs_pg:qs_pg_placetype_gp":"Town",
    "qs_pg:woe_adm0":23424923,
    "woe:adm0_id":23424923,
    "woe:name_adm0":"Polska",
    "woe:name_adm1":"Wielkopolskie",
    "woe:placetype":"Town",
    "wof:name":"L\u0105dek",
    "wof:placetype":"locality",
    "wof:population":272
},
  "geometry": {"coordinates":[18.00642,52.03106],"type":"Point"}
}