{
  "type": "Feature",
  "properties": {
    "gn:admin1_code":"75.0",
    "gn:admin2_code":"601.0",
    "gn:admin3_code":"60108.0",
    "gn:asciiname":"Bordzilowka Nowa",
    "gn:country_code":"PL",
    "gn:dem":149,
    "gn:feature_class":"P",
    "gn:feature_code":"PPL",
    "gn:name":"Bordzi\u0142\u00f3wka Nowa",
    "gn:population":0,
    "gn:timezone":"Europe/Warsaw",
    "iso:country":"PL",
    "name:fra_x_preferred":[
        "Nowa Bordzi\u0142\u00f3wka"
    ],
    "name:lit_x_preferred":[
        "Nova Bordziluvka"
    ],
    "name:pol_x_preferred":[
        "Nowa Bordzi\u0142\u00f3wka"
    ],
    "name:ukr_x_preferred":[
        "\u041d\u043e\u0432\u0430 \u0411\u043e\u0440\u0434\u0437\u0456\u043b\u0443\u0432\u043a\u0430"
    ],
    "name:und_x_variant":[
        "Bordzi\u0142\u00f3wka Nowa"
    ],
    "wof:name":"Bordzilowka Nowa",
    "wof:placetype":"locality"
},
  "geometry": {"coordinates":[23.02002,52.12439000000001],"type":"Point"}
}