{
  "type": "Feature",
  "properties": {
    "gn:admin1_code":"74.0",
    "gn:admin2_code":"1005.0",
    "gn:admin3_code":"100502.0",
    "gn:asciiname":"Trzaskowce",
    "gn:country_code":"PL",
    "gn:dem":108,
    "gn:feature_class":"P",
    "gn:feature_code":"PPL",
    "gn:name":"Trzaskowce",
    "gn:population":0,
    "gn:timezone":"Europe/Warsaw",
    "iso:country":"PL",
    "name:und_x_variant":[
        "Trzaskowice",
        "Trzaskowce"
    ],
    "wof:name":"Trzaskowce",
    "wof:placetype":"locality"
},
  "geometry": {"coordinates":[19.57614,52.07074],"type":"Point"}
}