{
  "type": "Feature",
  "properties": {
    "gn:admin1_code":"82.0",
    "gn:admin2_code":"2215.0",
    "gn:admin3_code":"221508.0",
    "gn:asciiname":"Dziecielec",
    "gn:country_code":"PL",
    "gn:dem":143,
    "gn:feature_class":"P",
    "gn:feature_code":"PPL",
    "gn:name":"Dzi\u0119cielec",
    "gn:population":0,
    "gn:timezone":"Europe/Warsaw",
    "iso:country":"PL",
    "name:azb_x_preferred":[
        "\u062c\u0646\u0686\u06cc\u0644\u062a\u0633"
    ],
    "name:ceb_x_preferred":[
        "Dzi\u0119cielec"
    ],
    "name:csb_x_preferred":[
        "Dz\u00ebc\u00e9lcz"
    ],
    "name:deu_x_preferred":[
        "Dzi\u0119cielec"
    ],
    "name:fas_x_preferred":[
        "\u062c\u0646\u0686\u06cc\u0644\u062a\u0633"
    ],
    "name:nld_x_preferred":[
        "Dzi\u0119cielec"
    ],
    "name:pol_x_preferred":[
        "Dzi\u0119cielec"
    ],
    "name:ukr_x_preferred":[
        "\u0414\u0437\u0435\u043d\u0446\u0435\u043b\u0435\u0446\u044c"
    ],
    "wof:name":"Dziecielec",
    "wof:placetype":"locality"
},
  "geometry": {"coordinates":[17.91248,54.49915],"type":"Point"}
}