{
  "type": "Feature",
  "properties": {
    "gn:admin1_code":"82.0",
    "gn:admin2_code":"2215.0",
    "gn:admin3_code":"221508.0",
    "gn:asciiname":"Dziecielec",
    "gn:country_code":"PL",
    "gn:dem":143,
    "gn:feature_class":"P",
    "gn:feature_code":"PPL",
    "gn:name":"Dzi\u0119cielec",
    "gn:population":0,
    "gn:timezone":"Europe/Warsaw",
    "iso:country":"PL",
    "name:und_x_variant":[
        "Dzi\u0119cielec"
    ],
    "wof:name":"Dziecielec",
    "wof:placetype":"locality"
},
  "geometry": {"coordinates":[17.91248,54.49915],"type":"Point"}
}