{
  "type": "Feature",
  "properties": {
    "gn:admin1_code":"74.0",
    "gn:admin2_code":"1008.0",
    "gn:admin3_code":"100803.0",
    "gn:asciiname":"Huta Dlutowska",
    "gn:country_code":"PL",
    "gn:dem":200,
    "gn:feature_class":"P",
    "gn:feature_code":"PPL",
    "gn:name":"Huta D\u0142utowska",
    "gn:population":0,
    "gn:timezone":"Europe/Warsaw",
    "iso:country":"PL",
    "name:und_x_variant":[
        "Huta D\u0142utowska"
    ],
    "wof:name":"Huta Dlutowska",
    "wof:placetype":"locality"
},
  "geometry": {"coordinates":[19.38418,51.59382],"type":"Point"}
}