{
  "type": "Feature",
  "properties": {
    "gn:admin1_code":"74.0",
    "gn:admin2_code":"1008.0",
    "gn:admin3_code":"100803.0",
    "gn:asciiname":"Huta Dlutowska",
    "gn:country_code":"PL",
    "gn:dem":200,
    "gn:feature_class":"P",
    "gn:feature_code":"PPL",
    "gn:name":"Huta D\u0142utowska",
    "gn:population":0,
    "gn:timezone":"Europe/Warsaw",
    "iso:country":"PL",
    "name:azb_x_preferred":[
        "\u062e\u0648\u062a\u0627 \u062f\u0648\u0648\u062a\u0648\u0648\u0633\u06a9\u0627"
    ],
    "name:ceb_x_preferred":[
        "Huta D\u0142utowska"
    ],
    "name:fas_x_preferred":[
        "\u062e\u0648\u062a\u0627 \u062f\u0648\u0648\u062a\u0648\u0648\u0633\u06a9\u0627"
    ],
    "name:fra_x_preferred":[
        "Huta D\u0142utowska"
    ],
    "name:nld_x_preferred":[
        "Huta D\u0142utowska"
    ],
    "name:pol_x_preferred":[
        "Huta D\u0142utowska"
    ],
    "name:szl_x_preferred":[
        "D\u0142utowsko Huta"
    ],
    "name:ukr_x_preferred":[
        "\u0413\u0443\u0442\u0430-\u0414\u043b\u0443\u0442\u043e\u0432\u0441\u044c\u043a\u0430"
    ],
    "wof:name":"Huta Dlutowska",
    "wof:placetype":"locality"
},
  "geometry": {"coordinates":[19.38418,51.59382],"type":"Point"}
}