{
  "type": "Feature",
  "properties": {
    "gn:admin1_code":"73.0",
    "gn:admin2_code":"406.0",
    "gn:admin3_code":"40605.0",
    "gn:asciiname":"Rogozno-Zamek",
    "gn:country_code":"PL",
    "gn:dem":80,
    "gn:feature_class":"P",
    "gn:feature_code":"PPL",
    "gn:name":"Rogo\u017ano-Zamek",
    "gn:population":0,
    "gn:timezone":"Europe/Warsaw",
    "iso:country":"PL",
    "name:pol_x_preferred":[
        "Rog\u00f3\u017ano-Zamek"
    ],
    "name:ukr_x_preferred":[
        "\u0420\u043e\u0491\u0443\u0437\u044c\u043d\u043e-\u0417\u0430\u043c\u0435\u043a"
    ],
    "name:und_x_variant":[
        "Rogo\u017ano-Zamek"
    ],
    "wof:name":"Rogozno-Zamek",
    "wof:placetype":"locality"
},
  "geometry": {"coordinates":[18.95887,53.52146],"type":"Point"}
}