{
  "type": "Feature",
  "properties": {
    "gn:admin1_code":"81.0",
    "gn:admin2_code":"2013.0",
    "gn:admin3_code":"201304.0",
    "gn:asciiname":"Kostry Stare",
    "gn:country_code":"PL",
    "gn:dem":132,
    "gn:feature_class":"P",
    "gn:feature_code":"PPL",
    "gn:name":"Kostry Stare",
    "gn:population":0,
    "gn:timezone":"Europe/Warsaw",
    "iso:country":"PL",
    "name:lit_x_preferred":[
        "Stare Kostrai"
    ],
    "name:pol_x_preferred":[
        "Stare Kostry"
    ],
    "name:ukr_x_preferred":[
        "\u0421\u0442\u0430\u0440\u0435 \u041a\u043e\u0441\u0442\u0440\u0438"
    ],
    "wof:name":"Kostry Stare",
    "wof:placetype":"locality"
},
  "geometry": {"coordinates":[22.57797,52.75876],"type":"Point"}
}