{
  "type": "Feature",
  "properties": {
    "gn:admin1_code":"73.0",
    "gn:admin2_code":"412.0",
    "gn:admin3_code":"41203.0",
    "gn:asciiname":"Brzeszczki Duze",
    "gn:country_code":"PL",
    "gn:dem":130,
    "gn:feature_class":"P",
    "gn:feature_code":"PPL",
    "gn:name":"Brzeszczki Du\u017ce",
    "gn:population":0,
    "gn:timezone":"Europe/Warsaw",
    "iso:country":"PL",
    "name:pol_x_preferred":[
        "Brzeszczki Du\u017ce"
    ],
    "name:ukr_x_preferred":[
        "\u0411\u0436\u0435\u0449\u043a\u0456-\u0414\u0443\u0436\u0435"
    ],
    "name:und_x_variant":[
        "Brzeszczki Du\u017ce"
    ],
    "wof:name":"Brzeszczki Duze",
    "wof:placetype":"locality"
},
  "geometry": {"coordinates":[19.40312,52.96012],"type":"Point"}
}