{
  "type": "Feature",
  "properties": {
    "gn:admin1_code":"87.0",
    "gn:admin2_code":"3202.0",
    "gn:admin3_code":"320203.0",
    "gn:asciiname":"Swieciechow",
    "gn:country_code":"PL",
    "gn:dem":103,
    "gn:feature_class":"P",
    "gn:feature_code":"PPL",
    "gn:name":"Swi\u0119ciech\u00f3w",
    "gn:population":0,
    "gn:timezone":"Europe/Warsaw",
    "iso:country":"PL",
    "name:deu_x_preferred":[
        "\u015awi\u0119ciech\u00f3w"
    ],
    "name:pol_x_preferred":[
        "\u015awi\u0119ciech\u00f3w"
    ],
    "name:ukr_x_preferred":[
        "\u0421\u044c\u0432\u0435\u043d\u0446\u0435\u0445\u0443\u0432"
    ],
    "name:und_x_variant":[
        "Swi\u0119ciech\u00f3w"
    ],
    "name:vie_x_preferred":[
        "\u015awi\u0119ciech\u00f3w"
    ],
    "wof:name":"Swieciechow",
    "wof:placetype":"locality"
},
  "geometry": {"coordinates":[15.71324,53.25393],"type":"Point"}
}