{
  "type": "Feature",
  "properties": {
    "gn:admin1_code":"74.0",
    "gn:admin2_code":"1017.0",
    "gn:admin3_code":"101701.0",
    "gn:asciiname":"Wygoda",
    "gn:country_code":"PL",
    "gn:dem":181,
    "gn:feature_class":"P",
    "gn:feature_code":"PPL",
    "gn:name":"Wygoda",
    "gn:population":0,
    "gn:timezone":"Europe/Warsaw",
    "iso:country":"PL",
    "name:bel_x_preferred":[
        "\u0412\u044b\u0433\u043e\u0434\u0430"
    ],
    "name:deu_x_preferred":[
        "Wygoda"
    ],
    "name:fra_x_preferred":[
        "Wygoda"
    ],
    "name:hye_x_preferred":[
        "\u054e\u056b\u0563\u0578\u0564\u0561"
    ],
    "name:lit_x_preferred":[
        "Vigoda"
    ],
    "name:pol_x_preferred":[
        "Wygoda"
    ],
    "name:rus_x_preferred":[
        "\u0412\u044b\u0433\u043e\u0434\u0430"
    ],
    "name:ukr_x_preferred":[
        "\u0412\u0438\u0491\u043e\u0434\u0430"
    ],
    "wof:name":"Wygoda",
    "wof:placetype":"locality"
},
  "geometry": {"coordinates":[18.46714,51.279],"type":"Point"}
}