{
  "type": "Feature",
  "properties": {
    "gn:admin1_code":"85.0",
    "gn:admin2_code":"2807.0",
    "gn:admin3_code":"280706.0",
    "gn:asciiname":"Olbrachtowo",
    "gn:country_code":"PL",
    "gn:dem":99,
    "gn:feature_class":"P",
    "gn:feature_code":"PPL",
    "gn:name":"Olbrachtowo",
    "gn:population":0,
    "gn:timezone":"Europe/Warsaw",
    "iso:country":"PL",
    "name:pol_x_preferred":[
        "Olbrachtowo"
    ],
    "name:ukr_x_preferred":[
        "\u041e\u043b\u044c\u0431\u0440\u0430\u0445\u0442\u043e\u0432\u043e"
    ],
    "wof:name":"Olbrachtowo",
    "wof:placetype":"locality"
},
  "geometry": {"coordinates":[19.41658,53.74466],"type":"Point"}
}