{
  "type": "Feature",
  "properties": {
    "gn:admin1_code":"87.0",
    "gn:admin2_code":"3217.0",
    "gn:admin3_code":"321705.0",
    "gn:asciiname":"Dzikowo",
    "gn:country_code":"PL",
    "gn:dem":126,
    "gn:feature_class":"P",
    "gn:feature_code":"PPL",
    "gn:name":"Dzikowo",
    "gn:population":0,
    "gn:timezone":"Europe/Warsaw",
    "iso:country":"PL",
    "name:deu_x_preferred":[
        "Dzikowo"
    ],
    "name:fra_x_preferred":[
        "Dzikowo"
    ],
    "name:pol_x_preferred":[
        "Dzikowo"
    ],
    "name:ukr_x_preferred":[
        "\u0414\u0437\u0456\u043a\u043e\u0432\u043e"
    ],
    "wof:name":"Dzikowo",
    "wof:placetype":"locality"
},
  "geometry": {"coordinates":[16.38093,53.19008],"type":"Point"}
}