{
  "type": "Feature",
  "properties": {
    "gn:population":4689,
    "iso:country":"PL",
    "name:azb_x_preferred":[
        "\u0642\u0645\u06cc\u0646\u0627 \u0632\u0627\u0628\u06cc\u0698\u0648\u0648"
    ],
    "name:bel_x_preferred":[
        "\u0413\u043c\u0456\u043d\u0430 \u0417\u0430\u0431\u0435\u0436\u0430\u045e"
    ],
    "name:deu_x_preferred":[
        "Gmina Zabierz\u00f3w"
    ],
    "name:eng_x_preferred":[
        "Gmina Zabierz\u00f3w"
    ],
    "name:eus_x_preferred":[
        "Zabierz\u00f3w udalerria"
    ],
    "name:fas_x_preferred":[
        "\u06af\u0645\u06cc\u0646\u0627 \u0632\u0627\u0628\u06cc\u0698\u0648\u0648"
    ],
    "name:fra_x_preferred":[
        "Zabierz\u00f3w"
    ],
    "name:ita_x_preferred":[
        "Zabierz\u00f3w"
    ],
    "name:nan_x_preferred":[
        "Zabierz\u00f3w"
    ],
    "name:nld_x_preferred":[
        "Zabierz\u00f3w"
    ],
    "name:pol_x_preferred":[
        "Zabierz\u00f3w"
    ],
    "name:por_x_preferred":[
        "Comuna de Zabierz\u00f3w"
    ],
    "name:rus_x_preferred":[
        "\u0417\u0430\u0431\u0435\u0436\u0443\u0432"
    ],
    "name:slk_x_preferred":[
        "Gmina Zabierz\u00f3w"
    ],
    "name:swe_x_preferred":[
        "Zabierz\u00f3ws kommun"
    ],
    "name:ukr_x_preferred":[
        "\u0490\u043c\u0456\u043d\u0430 \u0417\u0430\u0431\u0435\u0436\u0443\u0432"
    ],
    "name:war_x_preferred":[
        "Gmina Zabierz\u00f3w"
    ],
    "qs:a0":"Rzeczpospolita Polska",
    "qs:a1":"*Malopolskie",
    "qs:a1r":"0",
    "qs:a2":"Krakowski",
    "qs:adm0":"Rzeczpospolita Polska",
    "qs:la":"Zabierz\u00f3w",
    "qs:la_lc":"*PL1206162",
    "qs:level":"locality",
    "qs:loc":"Zabierz\u00f3w",
    "qs:loc_alt":"Zabierzow",
    "qs:pop":0,
    "qs:type":"rural point-multi-in-poly-resolved",
    "wd:wordcount":179,
    "wof:coterminous":[
        1125358505
    ],
    "wof:name":"Zabierz\u00f3w",
    "wof:placetype":"locality",
    "wof:population":4689
},
  "geometry": {"coordinates":[19.781140819234,50.1207247956573],"type":"Point"}
}