{
  "type": "Feature",
  "properties": {
    "gn:admin1_code":"77.0",
    "gn:admin2_code":"1214.0",
    "gn:admin3_code":"121403.0",
    "gn:asciiname":"Mniszow",
    "gn:country_code":"PL",
    "gn:dem":226,
    "gn:feature_class":"P",
    "gn:feature_code":"PPL",
    "gn:name":"Mnisz\u00f3w",
    "gn:population":0,
    "gn:timezone":"Europe/Warsaw",
    "iso:country":"PL",
    "name:pol_x_preferred":[
        "Mnisz\u00f3w"
    ],
    "name:ukr_x_preferred":[
        "\u041c\u043d\u0456\u0448\u0443\u0432"
    ],
    "wof:name":"Mniszow",
    "wof:placetype":"locality"
},
  "geometry": {"coordinates":[20.37185,50.15621],"type":"Point"}
}