{
  "type": "Feature",
  "properties": {
    "gn:admin1_code":"78.0",
    "gn:admin2_code":"1427.0",
    "gn:admin3_code":"142702.0",
    "gn:asciiname":"Bonislaw",
    "gn:country_code":"PL",
    "gn:dem":133,
    "gn:feature_class":"P",
    "gn:feature_code":"PPL",
    "gn:name":"Bonis\u0142aw",
    "gn:population":0,
    "gn:timezone":"Europe/Warsaw",
    "iso:country":"PL",
    "wof:name":"Bonislaw",
    "wof:placetype":"locality"
},
  "geometry": {"coordinates":[19.75171,52.71666999999999],"type":"Point"}
}