{
  "type": "Feature",
  "properties": {
    "gn:admin1_code":"78.0",
    "gn:admin2_code":"1424.0",
    "gn:admin3_code":"142401.0",
    "gn:asciiname":"Ostaszewo Panki",
    "gn:country_code":"PL",
    "gn:dem":116,
    "gn:feature_class":"P",
    "gn:feature_code":"PPL",
    "gn:name":"Ostaszewo Pa\u0144ki",
    "gn:population":0,
    "gn:timezone":"Europe/Warsaw",
    "iso:country":"PL",
    "name:fra_x_preferred":[
        "Ostaszewo-Pa\u0144ki"
    ],
    "name:pol_x_preferred":[
        "Ostaszewo-Pa\u0144ki"
    ],
    "name:ukr_x_preferred":[
        "\u041e\u0441\u0442\u0430\u0448\u0435\u0432\u043e-\u041f\u0430\u043d\u044c\u043a\u0456"
    ],
    "name:und_x_variant":[
        "Ostaszewo Pa\u0144ki"
    ],
    "wof:name":"Ostaszewo Panki",
    "wof:placetype":"locality"
},
  "geometry": {"coordinates":[20.82139,52.7407],"type":"Point"}
}