{
  "type": "Feature",
  "properties": {
    "gn:admin1_code":"77.0",
    "gn:admin2_code":"1204.0",
    "gn:admin3_code":"120405.0",
    "gn:asciiname":"Bucze",
    "gn:country_code":"PL",
    "gn:dem":196,
    "gn:feature_class":"P",
    "gn:feature_code":"PPL",
    "gn:name":"Bucze",
    "gn:population":0,
    "gn:timezone":"Europe/Warsaw",
    "iso:country":"PL",
    "wof:name":"Bucze",
    "wof:placetype":"locality"
},
  "geometry": {"coordinates":[20.92559,50.16898],"type":"Point"}
}