{
  "type": "Feature",
  "properties": {
    "gn:admin1_code":"84.0",
    "gn:admin2_code":"2607.0",
    "gn:admin3_code":"260704.0",
    "gn:asciiname":"Jastkow",
    "gn:country_code":"PL",
    "gn:dem":182,
    "gn:feature_class":"P",
    "gn:feature_code":"PPL",
    "gn:name":"Jastk\u00f3w",
    "gn:population":0,
    "gn:timezone":"Europe/Warsaw",
    "iso:country":"PL",
    "name:ceb_x_preferred":[
        "Jastk\u00f3w"
    ],
    "name:pol_x_preferred":[
        "Jastk\u00f3w"
    ],
    "name:ukr_x_preferred":[
        "\u042f\u0441\u0442\u043a\u0443\u0432"
    ],
    "name:und_x_variant":[
        "Jastk\u00f3w"
    ],
    "name:urd_x_preferred":[
        "\u062c\u0633\u0679\u06a9\u0648\u0648"
    ],
    "wof:name":"Jastkow",
    "wof:placetype":"locality"
},
  "geometry": {"coordinates":[21.53333,50.8738],"type":"Point"}
}