{
  "type": "Feature",
  "properties": {
    "gn:admin1_code":"78.0",
    "gn:admin2_code":"1408.0",
    "gn:admin3_code":"140804.0",
    "gn:asciiname":"Borowa Gora",
    "gn:country_code":"PL",
    "gn:dem":101,
    "gn:feature_class":"P",
    "gn:feature_code":"PPL",
    "gn:name":"Borowa G\u00f3ra",
    "gn:population":0,
    "gn:timezone":"Europe/Warsaw",
    "iso:country":"PL",
    "wof:name":"Borowa Gora",
    "wof:placetype":"locality"
},
  "geometry": {"coordinates":[21.0295,52.4812],"type":"Point"}
}