{
  "type": "Feature",
  "properties": {
    "gn:admin1_code":"86.0",
    "gn:admin2_code":"3018.0",
    "gn:admin3_code":"301801.0",
    "gn:asciiname":"Salamony Grabowskie",
    "gn:cc2":"PL",
    "gn:country_code":"PL",
    "gn:dem":155,
    "gn:feature_class":"P",
    "gn:feature_code":"PPL",
    "gn:name":"Salamony Grabowskie",
    "gn:population":0,
    "gn:timezone":"Europe/Warsaw",
    "iso:country":"PL",
    "name:pol_x_preferred":[
        "Salamony"
    ],
    "name:ukr_x_preferred":[
        "\u0421\u0430\u043b\u044f\u043c\u043e\u043d\u0438"
    ],
    "name:und_x_variant":[
        "Salamony Grabowskie"
    ],
    "wof:name":"Salamony Grabowskie",
    "wof:placetype":"locality"
},
  "geometry": {"coordinates":[18.36262,51.5174],"type":"Point"}
}