{
  "type": "Feature",
  "properties": {
    "gn:admin1_code":"86.0",
    "gn:admin2_code":"3019.0",
    "gn:admin3_code":"301904.0",
    "gn:asciiname":"Koscierzynek",
    "gn:country_code":"PL",
    "gn:dem":105,
    "gn:feature_class":"P",
    "gn:feature_code":"PPL",
    "gn:name":"Ko\u015bcierzynek",
    "gn:population":0,
    "gn:timezone":"Europe/Warsaw",
    "iso:country":"PL",
    "wof:name":"Koscierzynek",
    "wof:placetype":"locality"
},
  "geometry": {"coordinates":[17.26667,53.25],"type":"Point"}
}