{
  "type": "Feature",
  "properties": {
    "gn:admin1_code":"81.0",
    "gn:admin2_code":"2062.0",
    "gn:admin3_code":"206201.0",
    "gn:asciiname":"Lomzyca",
    "gn:country_code":"PL",
    "gn:dem":109,
    "gn:feature_class":"P",
    "gn:feature_code":"PPL",
    "gn:name":"\u0141om\u017cyca",
    "gn:population":0,
    "gn:timezone":"Europe/Warsaw",
    "iso:country":"PL",
    "name:eng_x_preferred":[
        "\u0141om\u017cyca"
    ],
    "name:rus_x_preferred":[
        "\u041b\u043e\u043c\u0436\u0430"
    ],
    "wof:name":"Lomzyca",
    "wof:placetype":"locality"
},
  "geometry": {"coordinates":[22.03982,53.17381999999999],"type":"Point"}
}