{
  "type": "Feature",
  "properties": {
    "gn:admin1_code":"73.0",
    "gn:admin2_code":"407.0",
    "gn:admin3_code":"40706.0",
    "gn:asciiname":"Glebokie",
    "gn:country_code":"PL",
    "gn:dem":88,
    "gn:feature_class":"P",
    "gn:feature_code":"PPL",
    "gn:name":"G\u0142\u0119bokie",
    "gn:population":0,
    "gn:timezone":"Europe/Warsaw",
    "iso:country":"PL",
    "name:pol_x_preferred":[
        "G\u0142\u0119bokie"
    ],
    "wof:name":"Glebokie",
    "wof:placetype":"locality"
},
  "geometry": {"coordinates":[18.43967,52.64435],"type":"Point"}
}