{
  "type": "Feature",
  "properties": {
    "gn:admin1_code":"75.0",
    "gn:admin2_code":"611.0",
    "gn:admin3_code":"61105.0",
    "gn:asciiname":"Ryzki",
    "gn:country_code":"PL",
    "gn:dem":159,
    "gn:feature_class":"P",
    "gn:feature_code":"PPL",
    "gn:name":"Ry\u017cki",
    "gn:population":0,
    "gn:timezone":"Europe/Warsaw",
    "iso:country":"PL",
    "name:fra_x_preferred":[
        "Ry\u017cki"
    ],
    "name:pol_x_preferred":[
        "Ry\u017cki"
    ],
    "name:ukr_x_preferred":[
        "\u0420\u0438\u0436\u043a\u0456"
    ],
    "wof:name":"Ryzki",
    "wof:placetype":"locality"
},
  "geometry": {"coordinates":[22.31956,51.90044],"type":"Point"}
}