{
  "type": "Feature",
  "properties": {
    "gn:admin1_code":"75.0",
    "gn:admin2_code":"611.0",
    "gn:admin3_code":"61105.0",
    "gn:asciiname":"Ryzki",
    "gn:country_code":"PL",
    "gn:dem":159,
    "gn:feature_class":"P",
    "gn:feature_code":"PPL",
    "gn:name":"Ry\u017cki",
    "gn:population":0,
    "gn:timezone":"Europe/Warsaw",
    "iso:country":"PL",
    "name:und_x_variant":[
        "Ry\u017cki"
    ],
    "wof:name":"Ryzki",
    "wof:placetype":"locality"
},
  "geometry": {"coordinates":[22.31956,51.90044],"type":"Point"}
}