{
  "type": "Feature",
  "properties": {
    "gn:admin1_code":"86.0",
    "gn:admin2_code":"3021.0",
    "gn:admin3_code":"302104.0",
    "gn:asciiname":"Czerwonczyn",
    "gn:country_code":"PL",
    "gn:dem":66,
    "gn:feature_class":"P",
    "gn:feature_code":"PPL",
    "gn:name":"Czerwonczyn",
    "gn:population":0,
    "gn:timezone":"Europe/Warsaw",
    "iso:country":"PL",
    "wof:name":"Czerwonczyn",
    "wof:placetype":"locality"
},
  "geometry": {"coordinates":[16.9802,52.47991],"type":"Point"}
}