{
  "type": "Feature",
  "properties": {
    "gn:admin1_code":"77.0",
    "gn:admin2_code":"1212.0",
    "gn:admin3_code":"121205.0",
    "gn:asciiname":"Podlesie",
    "gn:country_code":"PL",
    "gn:dem":377,
    "gn:feature_class":"P",
    "gn:feature_code":"PPL",
    "gn:name":"Podlesie",
    "gn:population":0,
    "gn:timezone":"Europe/Warsaw",
    "iso:country":"PL",
    "name:ceb_x_preferred":[
        "Podlesie"
    ],
    "name:pol_x_preferred":[
        "Podlesie"
    ],
    "name:ukr_x_preferred":[
        "\u041f\u043e\u0434\u043b\u0435\u0441\u0435"
    ],
    "name:und_x_variant":[
        "Todlesie"
    ],
    "wof:name":"Podlesie",
    "wof:placetype":"locality"
},
  "geometry": {"coordinates":[19.63659,50.31917],"type":"Point"}
}