{
  "type": "Feature",
  "properties": {
    "gn:admin1_code":"87.0",
    "gn:admin2_code":"3207.0",
    "gn:admin3_code":"320703.0",
    "gn:asciiname":"Trzebieszewo",
    "gn:country_code":"PL",
    "gn:dem":5,
    "gn:feature_class":"P",
    "gn:feature_code":"PPL",
    "gn:name":"Trzebieszewo",
    "gn:population":0,
    "gn:timezone":"Europe/Warsaw",
    "iso:country":"PL",
    "name:azb_x_preferred":[
        "\u0686\u0628\u06cc\u0633\u0632\u0648\u0627"
    ],
    "name:deu_x_preferred":[
        "Trzebieszewo"
    ],
    "name:fas_x_preferred":[
        "\u0686\u0628\u06cc\u0633\u0632\u0648\u0627"
    ],
    "name:pol_x_preferred":[
        "Trzebieszewo"
    ],
    "name:ukr_x_preferred":[
        "\u0422\u0448\u0435\u0431\u0435\u0448\u0435\u0432\u043e"
    ],
    "name:vie_x_preferred":[
        "Trzebieszewo"
    ],
    "wof:name":"Trzebieszewo",
    "wof:placetype":"locality"
},
  "geometry": {"coordinates":[14.84905,53.97416],"type":"Point"}
}