{
  "type": "Feature",
  "properties": {
    "iso:country":"PL",
    "name:azb_x_preferred":[
        "\u0642\u0645\u06cc\u0646\u0627 \u062e\u0648\u06cc\u0646\u0627"
    ],
    "name:bel_x_preferred":[
        "\u0425\u043e\u0439\u043d\u0430"
    ],
    "name:deu_x_preferred":[
        "Gmina Chojna"
    ],
    "name:eus_x_preferred":[
        "Chojna udalerria"
    ],
    "name:fas_x_preferred":[
        "\u06af\u0645\u06cc\u0646\u0627 \u062e\u0648\u06cc\u0646\u0627"
    ],
    "name:fra_x_preferred":[
        "Chojna"
    ],
    "name:nld_x_preferred":[
        "Chojna"
    ],
    "name:pol_x_preferred":[
        "Chojna"
    ],
    "name:rus_x_preferred":[
        "\u0425\u043e\u0439\u043d\u0430"
    ],
    "name:slk_x_preferred":[
        "Gmina Chojna"
    ],
    "name:ukr_x_preferred":[
        "\u0413\u043c\u0456\u043d\u0430 \u0425\u043e\u0439\u043d\u0430"
    ],
    "name:war_x_preferred":[
        "Gmina Chojna"
    ],
    "qs_pg:aaroncc":"PL",
    "qs_pg:name":"Gmina Chojna",
    "qs_pg:name_adm0":"Polska",
    "qs_pg:name_adm1":"Zachodniopomorskie",
    "qs_pg:photos":94,
    "qs_pg:photos_1k":19,
    "qs_pg:photos_9k":1,
    "qs_pg:photos_9r":3,
    "qs_pg:photos_all":100,
    "qs_pg:photos_sr":3,
    "qs_pg:pop_sr":0,
    "qs_pg:qs_pg_placetype":"localadmin",
    "qs_pg:qs_pg_placetype_gp":"LocalAdmin",
    "qs_pg:woe_adm0":23424923,
    "woe:adm0_id":23424923,
    "woe:name_adm0":"Polska",
    "woe:name_adm1":"Zachodniopomorskie",
    "woe:placetype":"LocalAdmin",
    "wof:name":"Gmina Chojna",
    "wof:placetype":"localadmin"
},
  "geometry": {"coordinates":[14.325078,53.034271],"type":"Point"}
}