{
  "type": "Feature",
  "properties": {
    "gn:admin1_code":"87.0",
    "gn:admin2_code":"3215.0",
    "gn:admin3_code":"321505.0",
    "gn:asciiname":"Mieszalki",
    "gn:country_code":"PL",
    "gn:dem":98,
    "gn:feature_class":"P",
    "gn:feature_code":"PPL",
    "gn:name":"Miesza\u0142ki",
    "gn:population":0,
    "gn:timezone":"Europe/Warsaw",
    "iso:country":"PL",
    "name:und_x_variant":[
        "Miesza\u0142ki"
    ],
    "wof:name":"Mieszalki",
    "wof:placetype":"locality"
},
  "geometry": {"coordinates":[16.42005,53.88673000000001],"type":"Point"}
}