{
  "type": "Feature",
  "properties": {
    "gn:admin1_code":"86.0",
    "gn:admin2_code":"3030.0",
    "gn:admin3_code":"303003.0",
    "gn:asciiname":"Targowagorka",
    "gn:country_code":"PL",
    "gn:dem":108,
    "gn:feature_class":"P",
    "gn:feature_code":"PPL",
    "gn:name":"Targowag\u00f3rka",
    "gn:population":0,
    "gn:timezone":"Europe/Warsaw",
    "iso:country":"PL",
    "name:azb_x_preferred":[
        "\u062a\u0627\u0631\u0642\u0648\u0648\u0627 \u0642\u0648\u0631\u06a9\u0627"
    ],
    "name:fas_x_preferred":[
        "\u062a\u0627\u0631\u06af\u0648\u0648\u0627 \u06af\u0648\u0631\u06a9\u0627"
    ],
    "name:fra_x_preferred":[
        "Targowa G\u00f3rka"
    ],
    "name:pol_x_preferred":[
        "Targowa G\u00f3rka"
    ],
    "name:szl_x_preferred":[
        "Targowo G\u016frka"
    ],
    "name:ukr_x_preferred":[
        "\u0422\u0430\u0440\u0491\u043e\u0432\u0430-\u0490\u0443\u0440\u043a\u0430"
    ],
    "name:und_x_variant":[
        "Targowag\u00f3rka"
    ],
    "wof:name":"Targowagorka",
    "wof:placetype":"locality"
},
  "geometry": {"coordinates":[17.44475,52.30476],"type":"Point"}
}