{
  "type": "Feature",
  "properties": {
    "gn:admin1_code":"74.0",
    "gn:admin2_code":"1012.0",
    "gn:admin3_code":"101207.0",
    "gn:asciiname":"Antoniow",
    "gn:country_code":"PL",
    "gn:dem":229,
    "gn:feature_class":"P",
    "gn:feature_code":"PPL",
    "gn:name":"Antoni\u00f3w",
    "gn:population":0,
    "gn:timezone":"Europe/Warsaw",
    "iso:country":"PL",
    "name:fra_x_preferred":[
        "Antoni\u00f3w"
    ],
    "name:pol_x_preferred":[
        "Antoni\u00f3w"
    ],
    "name:ukr_x_preferred":[
        "\u0410\u043d\u0442\u043e\u043d\u044e\u0432"
    ],
    "wof:name":"Antoniow",
    "wof:placetype":"locality"
},
  "geometry": {"coordinates":[19.57978,51.13046],"type":"Point"}
}