{
  "type": "Feature",
  "properties": {
    "gn:admin1_code":"83.0",
    "gn:admin2_code":"2413.0",
    "gn:admin3_code":"241304.0",
    "gn:asciiname":"Opatowice",
    "gn:country_code":"PL",
    "gn:dem":277,
    "gn:feature_class":"P",
    "gn:feature_code":"PPL",
    "gn:name":"Opatowice",
    "gn:population":0,
    "gn:timezone":"Europe/Warsaw",
    "iso:country":"PL",
    "name:pol_x_preferred":[
        "Opatowice"
    ],
    "name:ukr_x_preferred":[
        "\u041e\u043f\u0430\u0442\u043e\u0432\u0456\u0446\u0435"
    ],
    "wof:name":"Opatowice",
    "wof:placetype":"locality"
},
  "geometry": {"coordinates":[18.8158,50.4586],"type":"Point"}
}