{
  "type": "Feature",
  "properties": {
    "gn:admin1_code":"85.0",
    "gn:admin2_code":"2806.0",
    "gn:admin3_code":"280608.0",
    "gn:asciiname":"Nowa Rudowka",
    "gn:country_code":"PL",
    "gn:dem":138,
    "gn:feature_class":"P",
    "gn:feature_code":"PPL",
    "gn:name":"Nowa Rud\u00f3wka",
    "gn:population":0,
    "gn:timezone":"Europe/Warsaw",
    "iso:country":"PL",
    "name:und_x_variant":[
        "Neu Rudowken",
        "Neuhammerbruch",
        "Nowa Rud\u00f3wka"
    ],
    "wof:name":"Nowa Rudowka",
    "wof:placetype":"locality"
},
  "geometry": {"coordinates":[21.66667,53.93333000000001],"type":"Point"}
}