{
  "type": "Feature",
  "properties": {
    "gn:admin1_code":"87.0",
    "gn:admin2_code":"3215.0",
    "gn:admin3_code":"321504.0",
    "gn:asciiname":"Jelen",
    "gn:country_code":"PL",
    "gn:dem":145,
    "gn:feature_class":"P",
    "gn:feature_code":"PPL",
    "gn:name":"Jele\u0144",
    "gn:population":0,
    "gn:timezone":"Europe/Warsaw",
    "iso:country":"PL",
    "name:pol_x_preferred":[
        "Jele\u0144"
    ],
    "name:ukr_x_preferred":[
        "\u0404\u043b\u0435\u043d\u044c"
    ],
    "name:und_x_variant":[
        "Jele\u0144"
    ],
    "name:vie_x_preferred":[
        "Jele\u0144"
    ],
    "wof:name":"Jelen",
    "wof:placetype":"locality"
},
  "geometry": {"coordinates":[16.60282999999999,53.6249],"type":"Point"}
}