{
  "type": "Feature",
  "properties": {
    "gn:admin1_code":"85.0",
    "gn:admin2_code":"2804.0",
    "gn:admin3_code":"280403.0",
    "gn:asciiname":"Czarna Grobla",
    "gn:cc2":"PL",
    "gn:country_code":"PL",
    "gn:dem":-4,
    "gn:feature_class":"P",
    "gn:feature_code":"PPL",
    "gn:name":"Czarna Grobla",
    "gn:population":0,
    "gn:timezone":"Europe/Warsaw",
    "iso:country":"PL",
    "name:und_x_variant":[
        "Schwarzdamm",
        "Czarna Grobla"
    ],
    "wof:name":"Czarna Grobla",
    "wof:placetype":"locality"
},
  "geometry": {"coordinates":[19.25114,54.11014],"type":"Point"}
}