{
  "type": "Feature",
  "properties": {
    "gn:admin1_code":"81.0",
    "gn:admin2_code":"2012.0",
    "gn:admin3_code":"201208.0",
    "gn:asciiname":"Romaniuki",
    "gn:country_code":"PL",
    "gn:dem":206,
    "gn:feature_class":"P",
    "gn:feature_code":"PPL",
    "gn:name":"Romaniuki",
    "gn:population":0,
    "gn:timezone":"Europe/Warsaw",
    "iso:country":"PL",
    "wof:name":"Romaniuki",
    "wof:placetype":"locality"
},
  "geometry": {"coordinates":[23.13083,54.27065],"type":"Point"}
}