{
  "type": "Feature",
  "properties": {
    "gn:admin1_code":"81.0",
    "gn:admin2_code":"2012.0",
    "gn:admin3_code":"201208.0",
    "gn:asciiname":"Romaniuki",
    "gn:country_code":"PL",
    "gn:dem":206,
    "gn:feature_class":"P",
    "gn:feature_code":"PPL",
    "gn:name":"Romaniuki",
    "gn:population":0,
    "gn:timezone":"Europe/Warsaw",
    "iso:country":"PL",
    "name:lit_x_preferred":[
        "Ramonai"
    ],
    "name:pol_x_preferred":[
        "Romaniuki"
    ],
    "name:ukr_x_preferred":[
        "\u0420\u043e\u043c\u0430\u043d\u044e\u043a\u0438"
    ],
    "wof:name":"Romaniuki",
    "wof:placetype":"locality"
},
  "geometry": {"coordinates":[23.13083,54.27065],"type":"Point"}
}