{
  "type": "Feature",
  "properties": {
    "iso:country":"PL",
    "name:pol_x_preferred":[
        "Trzciana"
    ],
    "wof:name":"Trzciana",
    "wof:placetype":"locality"
},
  "geometry": {"coordinates":[20.3738854316437,49.8446812702296],"type":"Point"}
}