{
  "type": "Feature",
  "properties": {
    "iso:country":"PL",
    "name:ceb_x_preferred":[
        "Trzciana"
    ],
    "name:deu_x_preferred":[
        "Trzciana"
    ],
    "name:nld_x_preferred":[
        "Trzciana"
    ],
    "name:pol_x_preferred":[
        "Trzciana"
    ],
    "name:rus_x_preferred":[
        "\u0422\u0448\u0446\u044f\u043d\u0430"
    ],
    "name:ukr_x_preferred":[
        "\u0422\u0448\u0446\u044f\u043d\u0430"
    ],
    "name:urd_x_preferred":[
        "\u0686\u0686\u0627\u0646\u0627"
    ],
    "wof:coterminous":[
        1477751235
    ],
    "wof:name":"Trzciana",
    "wof:placetype":"locality"
},
  "geometry": {"coordinates":[20.3738854316437,49.8446812702296],"type":"Point"}
}