{
  "type": "Feature",
  "properties": {
    "gn:admin1_code":"81.0",
    "gn:admin2_code":"2011.0",
    "gn:admin3_code":"201104.0",
    "gn:asciiname":"Ostrow Poludniowy",
    "gn:country_code":"PL",
    "gn:dem":182,
    "gn:feature_class":"P",
    "gn:feature_code":"PPL",
    "gn:name":"Ostr\u00f3w Po\u0142udniowy",
    "gn:population":0,
    "gn:timezone":"Europe/Warsaw",
    "iso:country":"PL",
    "name:fra_x_preferred":[
        "Ostr\u00f3w Po\u0142udniowy"
    ],
    "name:lit_x_preferred":[
        "Ostruvo Poludniovai"
    ],
    "name:pol_x_preferred":[
        "Ostr\u00f3w Po\u0142udniowy"
    ],
    "name:ukr_x_preferred":[
        "\u041e\u0441\u0442\u0440\u0443\u0432-\u041f\u043e\u043b\u0443\u0434\u043d\u044c\u043e\u0432\u0438"
    ],
    "wof:name":"Ostrow Poludniowy",
    "wof:placetype":"locality"
},
  "geometry": {"coordinates":[23.68453,53.2509],"type":"Point"}
}