{
  "type": "Feature",
  "properties": {
    "gn:admin1_code":"73.0",
    "gn:admin2_code":"418.0",
    "gn:admin3_code":"41812.0",
    "gn:asciiname":"Redecz Kalny",
    "gn:country_code":"PL",
    "gn:dem":91,
    "gn:feature_class":"P",
    "gn:feature_code":"PPL",
    "gn:name":"Redecz Kalny",
    "gn:population":0,
    "gn:timezone":"Europe/Warsaw",
    "iso:country":"PL",
    "name:ita_x_preferred":[
        "Redecz Kalny"
    ],
    "name:pol_x_preferred":[
        "Redecz Kalny"
    ],
    "name:ukr_x_preferred":[
        "\u0420\u0435\u0434\u0435\u0447-\u041a\u0430\u043b\u044c\u043d\u0438"
    ],
    "wof:name":"Redecz Kalny",
    "wof:placetype":"locality"
},
  "geometry": {"coordinates":[18.82482000000001,52.56145],"type":"Point"}
}