{
  "type": "Feature",
  "properties": {
    "gn:admin1_code":"75.0",
    "gn:admin2_code":"603.0",
    "gn:admin3_code":"60310.0",
    "gn:asciiname":"Wolka Petrylowska",
    "gn:country_code":"PL",
    "gn:dem":183,
    "gn:feature_class":"P",
    "gn:feature_code":"PPL",
    "gn:name":"W\u00f3lka Petry\u0142owska",
    "gn:population":0,
    "gn:timezone":"Europe/Warsaw",
    "iso:country":"PL",
    "name:fra_x_preferred":[
        "W\u00f3lka Petry\u0142owska"
    ],
    "name:pol_x_preferred":[
        "W\u00f3lka Petry\u0142owska"
    ],
    "name:ukr_x_preferred":[
        "\u0412\u0443\u043b\u044c\u043a\u0430-\u041f\u0435\u0442\u0440\u0438\u043b\u043e\u0432\u0441\u044c\u043a\u0430"
    ],
    "wof:name":"Wolka Petrylowska",
    "wof:placetype":"locality"
},
  "geometry": {"coordinates":[23.43862,51.3488],"type":"Point"}
}