{
  "type": "Feature",
  "properties": {
    "gn:admin1_code":"74.0",
    "gn:admin2_code":"1012.0",
    "gn:admin3_code":"101203.0",
    "gn:asciiname":"Wlynice",
    "gn:country_code":"PL",
    "gn:dem":221,
    "gn:feature_class":"P",
    "gn:feature_code":"PPL",
    "gn:name":"W\u0142ynice",
    "gn:population":0,
    "gn:timezone":"Europe/Warsaw",
    "iso:country":"PL",
    "name:fra_x_preferred":[
        "W\u0142ynice"
    ],
    "name:pol_x_preferred":[
        "W\u0142ynice"
    ],
    "name:ukr_x_preferred":[
        "\u0412\u043b\u0438\u043d\u0456\u0446\u0435"
    ],
    "name:und_x_variant":[
        "W\u0142ynice"
    ],
    "wof:name":"Wlynice",
    "wof:placetype":"locality"
},
  "geometry": {"coordinates":[19.52532,50.98659],"type":"Point"}
}