{
  "type": "Feature",
  "properties": {
    "gn:admin1_code":"84.0",
    "gn:admin2_code":"2612.0",
    "gn:admin3_code":"261208.0",
    "gn:asciiname":"Grabki Duze",
    "gn:country_code":"PL",
    "gn:dem":233,
    "gn:feature_class":"P",
    "gn:feature_code":"PPL",
    "gn:name":"Grabki Du\u017ce",
    "gn:population":0,
    "gn:timezone":"Europe/Warsaw",
    "iso:country":"PL",
    "name:und_x_variant":[
        "Grabki",
        "Grabki Du\u017ce"
    ],
    "wof:name":"Grabki Duze",
    "wof:placetype":"locality"
},
  "geometry": {"coordinates":[20.95466,50.58676],"type":"Point"}
}