{
  "type": "Feature",
  "properties": {
    "gn:admin1_code":"84.0",
    "gn:admin2_code":"2612.0",
    "gn:admin3_code":"261208.0",
    "gn:asciiname":"Grabki Duze",
    "gn:country_code":"PL",
    "gn:dem":233,
    "gn:feature_class":"P",
    "gn:feature_code":"PPL",
    "gn:name":"Grabki Du\u017ce",
    "gn:population":0,
    "gn:timezone":"Europe/Warsaw",
    "iso:country":"PL",
    "name:nld_x_preferred":[
        "Grabki Du\u017ce"
    ],
    "name:pol_x_preferred":[
        "Grabki Du\u017ce"
    ],
    "name:ukr_x_preferred":[
        "\u0490\u0440\u0430\u0431\u043a\u0456-\u0414\u0443\u0436\u0435"
    ],
    "name:und_x_variant":[
        "Grabki"
    ],
    "name:vie_x_preferred":[
        "Grabki Du\u017ce"
    ],
    "wof:name":"Grabki Duze",
    "wof:placetype":"locality"
},
  "geometry": {"coordinates":[20.95466,50.58676],"type":"Point"}
}