{
  "type": "Feature",
  "properties": {
    "gn:admin1_code":"73.0",
    "gn:admin2_code":"416.0",
    "gn:admin3_code":"41606.0",
    "gn:asciiname":"Bladowo",
    "gn:country_code":"PL",
    "gn:dem":136,
    "gn:feature_class":"P",
    "gn:feature_code":"PPL",
    "gn:name":"Bladowo",
    "gn:population":0,
    "gn:timezone":"Europe/Warsaw",
    "iso:country":"PL",
    "name:ceb_x_preferred":[
        "Bladowo"
    ],
    "name:nld_x_preferred":[
        "Bladowo"
    ],
    "name:pol_x_preferred":[
        "Bladowo"
    ],
    "name:ukr_x_preferred":[
        "\u0411\u043b\u044f\u0434\u043e\u0432\u043e"
    ],
    "wof:name":"Bladowo",
    "wof:placetype":"locality"
},
  "geometry": {"coordinates":[17.81656,53.5965],"type":"Point"}
}