{
  "type": "Feature",
  "properties": {
    "gn:country":"PL",
    "gn:fcode":"PPL",
    "gn:population":1690,
    "iso:country":"PL",
    "name:azb_x_preferred":[
        "\u0628\u0648\u0642\u0648\u062a-\u067e\u06cc\u0627\u0646\u06a9\u06cc"
    ],
    "name:ceb_x_preferred":[
        "Boguty-Pianki"
    ],
    "name:deu_x_preferred":[
        "Boguty-Pianki"
    ],
    "name:eng_x_preferred":[
        "Boguty-Pianki"
    ],
    "name:fas_x_preferred":[
        "\u0628\u0648\u06af\u0648\u062a-\u067e\u06cc\u0627\u0646\u06a9\u06cc"
    ],
    "name:fra_x_preferred":[
        "Boguty-Pianki"
    ],
    "name:nld_x_preferred":[
        "Boguty-Pianki"
    ],
    "name:pol_x_preferred":[
        "Boguty-Pianki"
    ],
    "name:rus_x_preferred":[
        "\u0411\u043e\u0433\u0443\u0442\u044b-\u041f\u044f\u043d\u043a\u0438"
    ],
    "name:ukr_x_preferred":[
        "\u0411\u043e\u0491\u0443\u0442\u0438-\u041f\u044f\u043d\u043a\u0456"
    ],
    "name:und_x_variant":[
        "Boguty"
    ],
    "qs_pg:aaroncc":"PL",
    "qs_pg:gn_country":"PL",
    "qs_pg:gn_fcode":"PPL",
    "qs_pg:gn_pop":1690,
    "qs_pg:name":"Boguty-Pianki",
    "qs_pg:name_adm0":"Polska",
    "qs_pg:name_adm1":"Mazowieckie",
    "qs_pg:photos_9r":0,
    "qs_pg:photos_sr":0,
    "qs_pg:pop_sr":3,
    "qs_pg:qs_pg_placetype":"locality",
    "qs_pg:qs_pg_placetype_gp":"Town",
    "qs_pg:woe_adm0":23424923,
    "woe:adm0_id":23424923,
    "woe:name_adm0":"Polska",
    "woe:name_adm1":"Mazowieckie",
    "woe:placetype":"Town",
    "wof:name":"Boguty-Pianki",
    "wof:placetype":"locality",
    "wof:population":1690
},
  "geometry": {"coordinates":[22.41546,52.7168],"type":"Point"}
}