{
  "type": "Feature",
  "properties": {
    "gn:admin1_code":"82.0",
    "gn:admin2_code":"2261.0",
    "gn:admin3_code":"226101.0",
    "gn:asciiname":"Gorki Zachodnie",
    "gn:country_code":"PL",
    "gn:dem":1,
    "gn:feature_class":"P",
    "gn:feature_code":"PPL",
    "gn:name":"G\u00f3rki Zachodnie",
    "gn:population":0,
    "gn:timezone":"Europe/Warsaw",
    "iso:country":"PL",
    "name:und_x_variant":[
        "Westlich Neuf\u00e4hr",
        "G\u00f3rki Zachodnie"
    ],
    "wof:name":"Gorki Zachodnie",
    "wof:placetype":"locality"
},
  "geometry": {"coordinates":[18.77733,54.36857],"type":"Point"}
}