{
  "type": "Feature",
  "properties": {
    "gn:admin1_code":"86.0",
    "gn:admin2_code":"3022.0",
    "gn:admin3_code":"302203.0",
    "gn:asciiname":"Sobialkowo",
    "gn:country_code":"PL",
    "gn:dem":105,
    "gn:feature_class":"P",
    "gn:feature_code":"PPL",
    "gn:name":"Sobia\u0142kowo",
    "gn:population":0,
    "gn:timezone":"Europe/Warsaw",
    "iso:country":"PL",
    "name:ceb_x_preferred":[
        "Sobia\u0142kowo"
    ],
    "name:fra_x_preferred":[
        "Sobia\u0142kowo"
    ],
    "name:pol_x_preferred":[
        "Sobia\u0142kowo"
    ],
    "name:ukr_x_preferred":[
        "\u0421\u043e\u0431\u044f\u043b\u043a\u043e\u0432\u043e"
    ],
    "name:und_x_variant":[
        "Sabia\u0142kowo",
        "Sobia\u0142kowo"
    ],
    "wof:name":"Sobialkowo",
    "wof:placetype":"locality"
},
  "geometry": {"coordinates":[16.99274,51.66843],"type":"Point"}
}