{
  "type": "Feature",
  "properties": {
    "gn:admin1_code":"74.0",
    "gn:admin2_code":"1010.0",
    "gn:admin3_code":"101004.0",
    "gn:asciiname":"Lubanow",
    "gn:country_code":"PL",
    "gn:dem":224,
    "gn:feature_class":"P",
    "gn:feature_code":"PPL",
    "gn:name":"Luban\u00f3w",
    "gn:population":0,
    "gn:timezone":"Europe/Warsaw",
    "iso:country":"PL",
    "name:fra_x_preferred":[
        "Luban\u00f3w"
    ],
    "name:pol_x_preferred":[
        "Luban\u00f3w"
    ],
    "name:ukr_x_preferred":[
        "\u041b\u044e\u0431\u0430\u043d\u0443\u0432"
    ],
    "wof:name":"Lubanow",
    "wof:placetype":"locality"
},
  "geometry": {"coordinates":[19.56291,51.48208],"type":"Point"}
}