{
  "type": "Feature",
  "properties": {
    "gn:admin1_code":"80.0",
    "gn:admin2_code":"1820.0",
    "gn:admin3_code":"182001.0",
    "gn:asciiname":"Knapy",
    "gn:country_code":"PL",
    "gn:dem":152,
    "gn:feature_class":"P",
    "gn:feature_code":"PPL",
    "gn:name":"Knapy",
    "gn:population":0,
    "gn:timezone":"Europe/Warsaw",
    "iso:country":"PL",
    "name:ceb_x_preferred":[
        "Knapy"
    ],
    "name:pol_x_preferred":[
        "Knapy"
    ],
    "name:ukr_x_preferred":[
        "\u041a\u043d\u0430\u043f\u0438"
    ],
    "wof:name":"Knapy",
    "wof:placetype":"locality"
},
  "geometry": {"coordinates":[21.5817,50.44142],"type":"Point"}
}