{
  "type": "Feature",
  "properties": {
    "gn:country":"PL",
    "gn:fcode":"PPLA3",
    "gn:population":0,
    "iso:country":"PL",
    "name:ceb_x_preferred":[
        "Pop\u00f3w"
    ],
    "name:deu_x_preferred":[
        "Pop\u00f3w"
    ],
    "name:fra_x_preferred":[
        "Pop\u00f3w"
    ],
    "name:nld_x_preferred":[
        "Pop\u00f3w"
    ],
    "name:pol_x_preferred":[
        "Pop\u00f3w"
    ],
    "name:ukr_x_preferred":[
        "\u041f\u043e\u043f\u0443\u0432"
    ],
    "qs_pg:aaroncc":"PL",
    "qs_pg:gn_country":"PL",
    "qs_pg:gn_fcode":"PPLA3",
    "qs_pg:gn_pop":0,
    "qs_pg:name":"Pop\u00f3w",
    "qs_pg:name_adm0":"Polska",
    "qs_pg:name_adm1":"Sl\u0105skie",
    "qs_pg:photos":4,
    "qs_pg:photos_1k":1,
    "qs_pg:photos_9k":1,
    "qs_pg:photos_9r":1,
    "qs_pg:photos_all":9,
    "qs_pg:photos_sr":1,
    "qs_pg:pop_sr":0,
    "qs_pg:qs_pg_placetype":"localadmin",
    "qs_pg:qs_pg_placetype_gp":"LocalAdmin",
    "qs_pg:woe_adm0":23424923,
    "woe:adm0_id":23424923,
    "woe:name_adm0":"Polska",
    "woe:name_adm1":"Sl\u0105skie",
    "woe:placetype":"LocalAdmin",
    "wof:name":"Pop\u00f3w",
    "wof:placetype":"localadmin"
},
  "geometry": {"coordinates":[18.93116,51.04029],"type":"Point"}
}