{
  "type": "Feature",
  "properties": {
    "gn:gn_country":"PL",
    "gn:gn_fcode":"PPLA3",
    "gn:gn_pop":6771,
    "gn:population":6771,
    "iso:country":"PL",
    "name:ceb_x_preferred":[
        "S\u0119dzisz\u00f3w"
    ],
    "name:deu_x_preferred":[
        "S\u0119dzisz\u00f3w"
    ],
    "name:epo_x_preferred":[
        "S\u0119dzisz\u00f3w"
    ],
    "name:est_x_preferred":[
        "S\u0119dzisz\u00f3w"
    ],
    "name:fra_x_preferred":[
        "S\u0119dzisz\u00f3w"
    ],
    "name:hak_x_preferred":[
        "S\u0119dzisz\u00f3w"
    ],
    "name:heb_x_preferred":[
        "\u05e1\u05e0\u05d3\u05d6\u05d9\u05e9\u05d5\u05d1"
    ],
    "name:heb_x_variant":[
        "\u05e1\u05e0\u05d3\u05d6'\u05d9\u05e9\u05d5\u05d1"
    ],
    "name:jav_x_preferred":[
        "S\u0119dzisz\u00f3w"
    ],
    "name:lav_x_preferred":[
        "Se\u0146dzi\u0161ova"
    ],
    "name:msa_x_preferred":[
        "S\u0119dzisz\u00f3w"
    ],
    "name:nld_x_preferred":[
        "S\u0119dzisz\u00f3w"
    ],
    "name:pol_x_preferred":[
        "S\u0119dzisz\u00f3w"
    ],
    "name:por_x_preferred":[
        "S\u0119dzisz\u00f3w"
    ],
    "name:ron_x_preferred":[
        "S\u0119dzisz\u00f3w"
    ],
    "name:rus_x_preferred":[
        "\u0421\u0435\u043d\u0434\u0437\u0438\u0448\u0443\u0432"
    ],
    "name:slk_x_preferred":[
        "S\u0119dzisz\u00f3w"
    ],
    "name:srp_x_preferred":[
        "\u0421\u0435\u043d\u0452\u0438\u0448\u043e\u0432"
    ],
    "name:szl_x_preferred":[
        "Synd\u017aisz\u016fw"
    ],
    "name:ukr_x_preferred":[
        "\u0421\u0435\u043d\u0434\u0437\u0456\u0448\u0443\u0432"
    ],
    "name:vie_x_preferred":[
        "S\u0119dzisz\u00f3w"
    ],
    "name:zho_x_preferred":[
        "\u68ee\u6fdf\u8212\u592b"
    ],
    "qs_pg:aaroncc":"PL",
    "qs_pg:gn_country":"PL",
    "qs_pg:gn_fcode":"PPLA3",
    "qs_pg:gn_pop":6771,
    "qs_pg:name":"S\u0119dzisz\u00f3w",
    "qs_pg:name_adm0":"Polska",
    "qs_pg:name_adm1":"Swi\u0119tokrzyskie",
    "qs_pg:photos":1,
    "qs_pg:photos_1k":1,
    "qs_pg:photos_9k":1,
    "qs_pg:photos_9r":1,
    "qs_pg:photos_all":1,
    "qs_pg:photos_sr":1,
    "qs_pg:pop_sr":5,
    "qs_pg:qs_pg_placetype":"localadmin",
    "qs_pg:qs_pg_placetype_gp":"LocalAdmin",
    "qs_pg:woe_adm0":23424923,
    "woe:adm0_id":23424923,
    "woe:name_adm0":"Polska",
    "woe:name_adm1":"Swi\u0119tokrzyskie",
    "woe:placetype":"LocalAdmin",
    "wof:name":"S\u0119dzisz\u00f3w",
    "wof:placetype":"localadmin",
    "wof:population":6771
},
  "geometry": {"coordinates":[20.05563,50.5659],"type":"Point"}
}