{
  "type": "Feature",
  "properties": {
    "gn:admin1_code":"74.0",
    "gn:admin2_code":"1007.0",
    "gn:admin3_code":"100703.0",
    "gn:asciiname":"Obdzierz",
    "gn:country_code":"PL",
    "gn:dem":179,
    "gn:feature_class":"P",
    "gn:feature_code":"PPL",
    "gn:name":"Obdzierz",
    "gn:population":0,
    "gn:timezone":"Europe/Warsaw",
    "iso:country":"PL",
    "wof:name":"Obdzierz",
    "wof:placetype":"locality"
},
  "geometry": {"coordinates":[19.86667000000001,51.38333],"type":"Point"}
}