{
  "type": "Feature",
  "properties": {
    "gn:admin1_code":"78.0",
    "gn:admin2_code":"1428.0",
    "gn:admin3_code":"142806.0",
    "gn:asciiname":"Antosin",
    "gn:country_code":"PL",
    "gn:dem":94,
    "gn:feature_class":"P",
    "gn:feature_code":"PPL",
    "gn:name":"Antosin",
    "gn:population":0,
    "gn:timezone":"Europe/Warsaw",
    "iso:country":"PL",
    "name:fra_x_preferred":[
        "Antosin"
    ],
    "name:pol_x_preferred":[
        "Antosin"
    ],
    "name:ukr_x_preferred":[
        "\u0410\u043d\u0442\u043e\u0441\u0456\u043d"
    ],
    "wof:name":"Antosin",
    "wof:placetype":"locality"
},
  "geometry": {"coordinates":[20.08347,52.27399000000001],"type":"Point"}
}