{
  "type": "Feature",
  "properties": {
    "gn:admin1_code":"73.0",
    "gn:admin2_code":"416.0",
    "gn:admin3_code":"41604.0",
    "gn:asciiname":"Plazowo",
    "gn:country_code":"PL",
    "gn:dem":97,
    "gn:feature_class":"P",
    "gn:feature_code":"PPL",
    "gn:name":"P\u0142azowo",
    "gn:population":0,
    "gn:timezone":"Europe/Warsaw",
    "iso:country":"PL",
    "name:ceb_x_preferred":[
        "P\u0142azowo"
    ],
    "name:pol_x_preferred":[
        "P\u0142azowo"
    ],
    "name:ukr_x_preferred":[
        "\u041f\u043b\u0430\u0437\u043e\u0432\u043e"
    ],
    "name:und_x_variant":[
        "P\u0142azowo"
    ],
    "wof:name":"Plazowo",
    "wof:placetype":"locality"
},
  "geometry": {"coordinates":[17.9447,53.53185],"type":"Point"}
}