{
  "type": "Feature",
  "properties": {
    "gn:country":"PL",
    "gn:fcode":"PPL",
    "gn:population":300,
    "iso:country":"PL",
    "name:ast_x_preferred":[
        "Mchawa"
    ],
    "name:ceb_x_preferred":[
        "Mchawa"
    ],
    "name:eng_x_preferred":[
        "Mchawa"
    ],
    "name:fra_x_preferred":[
        "Mchawa"
    ],
    "name:hun_x_preferred":[
        "Mchawa"
    ],
    "name:pol_x_preferred":[
        "Mchawa"
    ],
    "name:rue_x_preferred":[
        "\u041c\u0445\u0430\u0432\u0430"
    ],
    "name:ukr_x_preferred":[
        "\u041c\u0445\u0430\u0432\u0430"
    ],
    "qs_pg:aaroncc":"PL",
    "qs_pg:gn_country":"PL",
    "qs_pg:gn_fcode":"PPL",
    "qs_pg:gn_pop":300,
    "qs_pg:name":"Mchawa",
    "qs_pg:name_adm0":"Polska",
    "qs_pg:name_adm1":"Podkarpackie",
    "qs_pg:photos_9r":0,
    "qs_pg:photos_sr":0,
    "qs_pg:pop_sr":2,
    "qs_pg:qs_pg_placetype":"locality",
    "qs_pg:qs_pg_placetype_gp":"Town",
    "qs_pg:woe_adm0":23424923,
    "woe:adm0_id":23424923,
    "woe:name_adm0":"Polska",
    "woe:name_adm1":"Podkarpackie",
    "woe:placetype":"Town",
    "wof:name":"Mchawa",
    "wof:placetype":"locality",
    "wof:population":300
},
  "geometry": {"coordinates":[22.2813,49.35845],"type":"Point"}
}