{
  "type": "Feature",
  "properties": {
    "gn:admin1_code":"78.0",
    "gn:admin2_code":"1428.0",
    "gn:admin3_code":"142808.0",
    "gn:asciiname":"Granice",
    "gn:country_code":"PL",
    "gn:dem":87,
    "gn:feature_class":"P",
    "gn:feature_code":"PPL",
    "gn:name":"Granice",
    "gn:population":0,
    "gn:timezone":"Europe/Warsaw",
    "iso:country":"PL",
    "name:fra_x_preferred":[
        "Granice"
    ],
    "name:pol_x_preferred":[
        "Granice"
    ],
    "name:szl_x_preferred":[
        "Gra\u0144ice"
    ],
    "name:ukr_x_preferred":[
        "\u0490\u0440\u0430\u043d\u0456\u0446\u0435"
    ],
    "wof:name":"Granice",
    "wof:placetype":"locality"
},
  "geometry": {"coordinates":[20.43509,52.2074],"type":"Point"}
}