{
  "type": "Feature",
  "properties": {
    "gn:admin1_code":"81.0",
    "gn:admin2_code":"2013.0",
    "gn:admin3_code":"201308.0",
    "gn:asciiname":"Dragi",
    "gn:country_code":"PL",
    "gn:dem":143,
    "gn:feature_class":"P",
    "gn:feature_code":"PPL",
    "gn:name":"Dr\u0105gi",
    "gn:population":0,
    "gn:timezone":"Europe/Warsaw",
    "iso:country":"PL",
    "name:lit_x_preferred":[
        "Drongai"
    ],
    "name:pol_x_preferred":[
        "Dr\u0105gi"
    ],
    "name:ukr_x_preferred":[
        "\u0414\u0440\u043e\u043d\u0491\u0456"
    ],
    "wof:name":"Dragi",
    "wof:placetype":"locality"
},
  "geometry": {"coordinates":[22.72283,52.95201],"type":"Point"}
}