{
  "type": "Feature",
  "properties": {
    "gn:admin1_code":"74.0",
    "gn:admin2_code":"1021.0",
    "gn:admin3_code":"102104.0",
    "gn:asciiname":"Jasienin Maly",
    "gn:country_code":"PL",
    "gn:dem":182,
    "gn:feature_class":"P",
    "gn:feature_code":"PPL",
    "gn:name":"Jasienin Ma\u0142y",
    "gn:population":0,
    "gn:timezone":"Europe/Warsaw",
    "iso:country":"PL",
    "name:azb_x_preferred":[
        "\u06cc\u0627\u0634\u0646\u0642\u0646 \u0645\u0627\u0648\u0647"
    ],
    "name:fas_x_preferred":[
        "\u06cc\u0627\u0634\u0646\u06af\u0646 \u0645\u0627\u0648\u0647"
    ],
    "name:fra_x_preferred":[
        "Jasienin Ma\u0142y"
    ],
    "name:pol_x_preferred":[
        "Jasienin Ma\u0142y"
    ],
    "name:ukr_x_preferred":[
        "\u042f\u0441\u0435\u043d\u0456\u043d-\u041c\u0430\u043b\u0438\u0439"
    ],
    "name:und_x_variant":[
        "Jasienin Ma\u0142y"
    ],
    "name:urd_x_preferred":[
        "\u062c\u0633\u06cc\u0646\u06cc\u06ba \u0645\u0648\u06cc"
    ],
    "wof:name":"Jasienin Maly",
    "wof:placetype":"locality"
},
  "geometry": {"coordinates":[19.94274,51.81605],"type":"Point"}
}