{
  "type": "Feature",
  "properties": {
    "gn:admin1_code":"87.0",
    "gn:admin2_code":"3216.0",
    "gn:admin3_code":"321606.0",
    "gn:asciiname":"Osowo",
    "gn:country_code":"PL",
    "gn:dem":111,
    "gn:feature_class":"P",
    "gn:feature_code":"PPL",
    "gn:name":"Osowo",
    "gn:population":0,
    "gn:timezone":"Europe/Warsaw",
    "iso:country":"PL",
    "name:deu_x_preferred":[
        "Osowo"
    ],
    "name:pol_x_preferred":[
        "Osowo"
    ],
    "name:ukr_x_preferred":[
        "\u041e\u0441\u043e\u0432\u043e"
    ],
    "wof:name":"Osowo",
    "wof:placetype":"locality"
},
  "geometry": {"coordinates":[15.63779,53.7642],"type":"Point"}
}