{
  "type": "Feature",
  "properties": {
    "gn:admin1_code":"86.0",
    "gn:admin2_code":"3029.0",
    "gn:admin3_code":"302902.0",
    "gn:asciiname":"Stara Tuchorza",
    "gn:country_code":"PL",
    "gn:dem":59,
    "gn:feature_class":"P",
    "gn:feature_code":"PPL",
    "gn:name":"Stara Tuchorza",
    "gn:population":0,
    "gn:timezone":"Europe/Warsaw",
    "iso:country":"PL",
    "name:ceb_x_preferred":[
        "Stara Tuchorza"
    ],
    "name:fra_x_preferred":[
        "Stara Tuchorza"
    ],
    "name:pol_x_preferred":[
        "Stara Tuchorza"
    ],
    "name:ukr_x_preferred":[
        "\u0421\u0442\u0430\u0440\u0430 \u0422\u0443\u0445\u043e\u0436\u0430"
    ],
    "wof:name":"Stara Tuchorza",
    "wof:placetype":"locality"
},
  "geometry": {"coordinates":[16.04759,52.17067],"type":"Point"}
}