{
  "type": "Feature",
  "properties": {
    "gn:admin1_code":"81.0",
    "gn:admin2_code":"2011.0",
    "gn:admin3_code":"201109.0",
    "gn:asciiname":"Kolonia Bachmacka",
    "gn:country_code":"PL",
    "gn:dem":190,
    "gn:feature_class":"P",
    "gn:feature_code":"PPL",
    "gn:name":"Kolonia Bachmacka",
    "gn:population":0,
    "gn:timezone":"Europe/Warsaw",
    "iso:country":"PL",
    "wof:name":"Kolonia Bachmacka",
    "wof:placetype":"locality"
},
  "geometry": {"coordinates":[23.25592,53.58554],"type":"Point"}
}