{
  "type": "Feature",
  "properties": {
    "gn:admin1_code":"86.0",
    "gn:admin2_code":"3020.0",
    "gn:admin3_code":"302001.0",
    "gn:asciiname":"Jozefow",
    "gn:country_code":"PL",
    "gn:dem":98,
    "gn:feature_class":"P",
    "gn:feature_code":"PPL",
    "gn:name":"J\u00f3zef\u00f3w",
    "gn:population":0,
    "gn:timezone":"Europe/Warsaw",
    "iso:country":"PL",
    "name:pol_x_preferred":[
        "J\u00f3zef\u00f3w"
    ],
    "name:ukr_x_preferred":[
        "\u042e\u0437\u0435\u0444\u0443\u0432"
    ],
    "wof:name":"Jozefow",
    "wof:placetype":"locality"
},
  "geometry": {"coordinates":[17.90909,51.99545],"type":"Point"}
}