{
  "type": "Feature",
  "properties": {
    "gn:admin1_code":"86.0",
    "gn:admin2_code":"3021.0",
    "gn:admin3_code":"302107.0",
    "gn:asciiname":"Walerianowo",
    "gn:country_code":"PL",
    "gn:dem":96,
    "gn:feature_class":"P",
    "gn:feature_code":"PPL",
    "gn:name":"Walerianowo",
    "gn:population":0,
    "gn:timezone":"Europe/Warsaw",
    "iso:country":"PL",
    "wof:name":"Walerianowo",
    "wof:placetype":"locality"
},
  "geometry": {"coordinates":[16.77239,52.31762],"type":"Point"}
}