{
  "type": "Feature",
  "properties": {
    "gn:admin1_code":"86.0",
    "gn:admin2_code":"3021.0",
    "gn:admin3_code":"302107.0",
    "gn:asciiname":"Walerianowo",
    "gn:country_code":"PL",
    "gn:dem":96,
    "gn:feature_class":"P",
    "gn:feature_code":"PPL",
    "gn:name":"Walerianowo",
    "gn:population":0,
    "gn:timezone":"Europe/Warsaw",
    "iso:country":"PL",
    "name:ceb_x_preferred":[
        "Walerianowo"
    ],
    "name:fra_x_preferred":[
        "Walerianowo"
    ],
    "name:pol_x_preferred":[
        "Walerianowo"
    ],
    "name:ukr_x_preferred":[
        "\u0412\u0430\u043b\u0435\u0440\u044f\u043d\u043e\u0432\u043e"
    ],
    "wof:name":"Walerianowo",
    "wof:placetype":"locality"
},
  "geometry": {"coordinates":[16.77239,52.31762],"type":"Point"}
}