{
  "type": "Feature",
  "properties": {
    "gn:admin1_code":"85.0",
    "gn:admin2_code":"2814.0",
    "gn:admin3_code":"281403.0",
    "gn:asciiname":"Podlesna",
    "gn:country_code":"PL",
    "gn:dem":146,
    "gn:feature_class":"P",
    "gn:feature_code":"PPL",
    "gn:name":"Podle\u015bna",
    "gn:population":0,
    "gn:timezone":"Europe/Warsaw",
    "iso:country":"PL",
    "name:eng_x_preferred":[
        "Podle\u015bna"
    ],
    "name:pol_x_preferred":[
        "Podle\u015bna"
    ],
    "name:rus_x_preferred":[
        "\u041f\u043e\u0434\u043b\u0435\u0441\u044c\u043d\u0430"
    ],
    "name:ukr_x_preferred":[
        "\u041f\u043e\u0434\u043b\u0435\u0441\u044c\u043d\u0430"
    ],
    "name:und_x_variant":[
        "Klingerswalde",
        "Podle\u015bna"
    ],
    "wof:name":"Podlesna",
    "wof:placetype":"locality"
},
  "geometry": {"coordinates":[20.49635,53.94989],"type":"Point"}
}