{
  "type": "Feature",
  "properties": {
    "gn:admin1_code":"77.0",
    "gn:admin2_code":"1215.0",
    "gn:admin3_code":"121507.0",
    "gn:asciiname":"Krzeszow Dolny",
    "gn:country_code":"PL",
    "gn:dem":449,
    "gn:feature_class":"P",
    "gn:feature_code":"PPL",
    "gn:name":"Krzesz\u00f3w Dolny",
    "gn:population":0,
    "gn:timezone":"Europe/Warsaw",
    "iso:country":"PL",
    "wof:name":"Krzeszow Dolny",
    "wof:placetype":"locality"
},
  "geometry": {"coordinates":[19.4664,49.74611],"type":"Point"}
}