{
  "type": "Feature",
  "properties": {
    "gn:admin1_code":"85.0",
    "gn:admin2_code":"2810.0",
    "gn:admin3_code":"281003.0",
    "gn:asciiname":"Zawada",
    "gn:country_code":"PL",
    "gn:dem":142,
    "gn:feature_class":"P",
    "gn:feature_code":"PPL",
    "gn:name":"Zawada",
    "gn:population":0,
    "gn:timezone":"Europe/Warsaw",
    "iso:country":"PL",
    "name:ceb_x_preferred":[
        "Zawada"
    ],
    "name:ces_x_preferred":[
        "Z\u00e1vada"
    ],
    "name:deu_x_preferred":[
        "Zawada"
    ],
    "name:fra_x_preferred":[
        "Zawada"
    ],
    "name:pol_x_preferred":[
        "Zawada"
    ],
    "name:slk_x_preferred":[
        "Z\u00e1vada"
    ],
    "name:und_x_variant":[
        "Sawaden Kreis Sensburg",
        "Swadden",
        "Balz Ostpreussen",
        "Zawady",
        "Balz"
    ],
    "wof:name":"Zawada",
    "wof:placetype":"locality"
},
  "geometry": {"coordinates":[21.3843,53.84726],"type":"Point"}
}