{
  "type": "Feature",
  "properties": {
    "gn:admin1_code":"85.0",
    "gn:admin2_code":"2810.0",
    "gn:admin3_code":"281003.0",
    "gn:asciiname":"Zawada",
    "gn:country_code":"PL",
    "gn:dem":142,
    "gn:feature_class":"P",
    "gn:feature_code":"PPL",
    "gn:name":"Zawada",
    "gn:population":0,
    "gn:timezone":"Europe/Warsaw",
    "iso:country":"PL",
    "name:und_x_variant":[
        "Sawaden Kreis Sensburg",
        "Swadden",
        "Balz Ostpreussen",
        "Zawady",
        "Balz",
        "Zawada"
    ],
    "wof:name":"Zawada",
    "wof:placetype":"locality"
},
  "geometry": {"coordinates":[21.3843,53.84726],"type":"Point"}
}