{
  "type": "Feature",
  "properties": {
    "gn:admin1_code":"78.0",
    "gn:admin2_code":"1429.0",
    "gn:admin3_code":"142904.0",
    "gn:asciiname":"Luzki",
    "gn:country_code":"PL",
    "gn:dem":137,
    "gn:feature_class":"P",
    "gn:feature_code":"PPL",
    "gn:name":"\u0141u\u017cki",
    "gn:population":0,
    "gn:timezone":"Europe/Warsaw",
    "iso:country":"PL",
    "name:azb_x_preferred":[
        "\u0648\u0648\u0632\u06a9\u06cc"
    ],
    "name:fas_x_preferred":[
        "\u0648\u0648\u0632\u06a9\u06cc"
    ],
    "name:fra_x_preferred":[
        "\u0141uzki"
    ],
    "name:lit_x_preferred":[
        "Luzkai"
    ],
    "name:pol_x_preferred":[
        "\u0141uzki"
    ],
    "name:ukr_x_preferred":[
        "\u041b\u0443\u0437\u043a\u0438"
    ],
    "wof:name":"Luzki",
    "wof:placetype":"locality"
},
  "geometry": {"coordinates":[22.44541,52.44398],"type":"Point"}
}