{
  "type": "Feature",
  "properties": {
    "gn:gn_country":"PL",
    "gn:gn_fcode":"PPL",
    "gn:gn_pop":0,
    "iso:country":"PL",
    "name:ast_x_preferred":[
        "Suchowola"
    ],
    "name:ceb_x_preferred":[
        "Suchowola"
    ],
    "name:eng_x_preferred":[
        "Suchowola"
    ],
    "name:fra_x_preferred":[
        "Suchowola"
    ],
    "name:pol_x_preferred":[
        "Suchowola"
    ],
    "name:rus_x_preferred":[
        "\u0421\u0443\u0445\u043e\u0432\u043e\u043b\u044f"
    ],
    "name:ukr_x_preferred":[
        "\u0421\u0443\u0445\u043e\u0432\u043e\u043b\u044f"
    ],
    "qs_pg:aaroncc":"PL",
    "qs_pg:gn_country":"PL",
    "qs_pg:gn_fcode":"PPL",
    "qs_pg:gn_pop":0,
    "qs_pg:name":"Suchowola",
    "qs_pg:name_adm0":"Polska",
    "qs_pg:name_adm1":"Lubelskie",
    "qs_pg:photos":4,
    "qs_pg:photos_1k":1,
    "qs_pg:photos_9k":1,
    "qs_pg:photos_9r":1,
    "qs_pg:photos_all":4,
    "qs_pg:photos_sr":1,
    "qs_pg:pop_sr":0,
    "qs_pg:qs_pg_placetype":"locality",
    "qs_pg:qs_pg_placetype_gp":"Town",
    "qs_pg:woe_adm0":23424923,
    "woe:adm0_id":23424923,
    "woe:name_adm0":"Polska",
    "woe:name_adm1":"Lubelskie",
    "woe:placetype":"Town",
    "wof:name":"Suchowola",
    "wof:placetype":"locality"
},
  "geometry": {"coordinates":[23.25363,50.58967],"type":"Point"}
}