{
  "type": "Feature",
  "properties": {
    "gn:admin1_code":"72.0",
    "gn:admin2_code":"207.0",
    "gn:admin3_code":"20704.0",
    "gn:asciiname":"Slowikow",
    "gn:country_code":"PL",
    "gn:dem":635,
    "gn:feature_class":"P",
    "gn:feature_code":"PPL",
    "gn:name":"S\u0142owikow",
    "gn:population":0,
    "gn:timezone":"Europe/Warsaw",
    "iso:country":"PL",
    "wof:name":"Slowikow",
    "wof:placetype":"locality"
},
  "geometry": {"coordinates":[16.02451,50.89934],"type":"Point"}
}