{
  "type": "Feature",
  "properties": {
    "gn:admin1_code":"73.0",
    "gn:admin2_code":"407.0",
    "gn:admin3_code":"40709.0",
    "gn:asciiname":"Tarkowo",
    "gn:country_code":"PL",
    "gn:dem":81,
    "gn:feature_class":"P",
    "gn:feature_code":"PPL",
    "gn:name":"Tarkowo",
    "gn:population":0,
    "gn:timezone":"Europe/Warsaw",
    "iso:country":"PL",
    "wof:name":"Tarkowo",
    "wof:placetype":"locality"
},
  "geometry": {"coordinates":[18.11667000000001,52.93333000000001],"type":"Point"}
}