{
  "type": "Feature",
  "properties": {
    "gn:admin1_code":"86.0",
    "gn:admin2_code":"3019.0",
    "gn:admin3_code":"301905.0",
    "gn:asciiname":"Okaliniec",
    "gn:country_code":"PL",
    "gn:dem":96,
    "gn:feature_class":"P",
    "gn:feature_code":"PPL",
    "gn:name":"Okaliniec",
    "gn:population":0,
    "gn:timezone":"Europe/Warsaw",
    "iso:country":"PL",
    "name:fra_x_preferred":[
        "Okaliniec"
    ],
    "name:pol_x_preferred":[
        "Okaliniec"
    ],
    "name:ukr_x_preferred":[
        "\u041e\u043a\u0430\u043b\u0456\u043d\u0435\u0446\u044c"
    ],
    "wof:name":"Okaliniec",
    "wof:placetype":"locality"
},
  "geometry": {"coordinates":[17.06743,53.1375],"type":"Point"}
}