{
  "type": "Feature",
  "properties": {
    "iso:country":"PL",
    "name:eng_x_preferred":[
        "Sw. Lazarz"
    ],
    "name:pol_x_preferred":[
        "\u015aw. \u0141azarz"
    ],
    "wof:name":"Sw. Lazarz",
    "wof:placetype":"neighbourhood"
},
  "geometry": {"coordinates":[16.89727782694631,52.3947369939828],"type":"Point"}
}