{
  "type": "Feature",
  "properties": {
    "gn:country":"PL",
    "gn:fcode":"PPL",
    "gn:population":0,
    "iso:country":"PL",
    "name:csb_x_preferred":[
        "K\u00f2k\u00f2szczi"
    ],
    "name:deu_x_preferred":[
        "Kokoszki"
    ],
    "name:ita_x_preferred":[
        "Kokoszki"
    ],
    "name:pol_x_preferred":[
        "Kokoszki"
    ],
    "name:vie_x_preferred":[
        "Kokoszki"
    ],
    "qs_pg:aaroncc":"PL",
    "qs_pg:gn_country":"PL",
    "qs_pg:gn_fcode":"PPL",
    "qs_pg:gn_pop":0,
    "qs_pg:name":"Kokoszki",
    "qs_pg:name_adm0":"Polska",
    "qs_pg:name_adm1":"Pomorskie",
    "qs_pg:photos":48,
    "qs_pg:photos_1k":10,
    "qs_pg:photos_9k":1,
    "qs_pg:photos_9r":2,
    "qs_pg:photos_all":48,
    "qs_pg:photos_sr":2,
    "qs_pg:pop_sr":0,
    "qs_pg:qs_pg_placetype":"locality",
    "qs_pg:qs_pg_placetype_gp":"Town",
    "qs_pg:woe_adm0":23424923,
    "woe:adm0_id":23424923,
    "woe:name_adm0":"Polska",
    "woe:name_adm1":"Pomorskie",
    "woe:placetype":"Town",
    "wof:name":"Kokoszki",
    "wof:placetype":"locality"
},
  "geometry": {"coordinates":[18.49102,54.35563],"type":"Point"}
}