{
  "type": "Feature",
  "properties": {
    "gn:admin1_code":"72.0",
    "gn:admin2_code":"223.0",
    "gn:admin3_code":"22306.0",
    "gn:asciiname":"Ujow",
    "gn:country_code":"PL",
    "gn:dem":168,
    "gn:feature_class":"P",
    "gn:feature_code":"PPL",
    "gn:name":"Uj\u00f3w",
    "gn:population":0,
    "gn:timezone":"Europe/Warsaw",
    "iso:country":"PL",
    "name:und_x_variant":[
        "Uj\u00f3w"
    ],
    "wof:name":"Ujow",
    "wof:placetype":"locality"
},
  "geometry": {"coordinates":[16.62266,50.99982],"type":"Point"}
}