{
  "type": "Feature",
  "properties": {
    "gn:gn_country":"PL",
    "gn:gn_fcode":"PPL",
    "gn:gn_pop":713,
    "gn:population":713,
    "iso:country":"PL",
    "name:dan_x_preferred":[
        "Szczodre"
    ],
    "name:dut_x_preferred":[
        "Sibyllenort"
    ],
    "name:eng_x_preferred":[
        "Szczodre"
    ],
    "name:fre_x_preferred":[
        "Szczodre"
    ],
    "name:ger_x_preferred":[
        "Szczodre"
    ],
    "name:heb_x_preferred":[
        "\u05e9\u05d8\u05e9\u05d5\u05d3\u05e8\u05d4"
    ],
    "name:jpn_x_preferred":[
        "\u30b8\u30d3\u30ec\u30ce\u30eb\u30c8"
    ],
    "name:per_x_preferred":[
        "\u0634\u0686\u0648\u062f\u0631\u0647"
    ],
    "name:pol_x_preferred":[
        "Szczodre"
    ],
    "name:rus_x_preferred":[
        "\u0429\u043e\u0434\u0440\u0435"
    ],
    "name:swe_x_preferred":[
        "Szczodre"
    ],
    "name:unk_x_variant":[
        "Sibyllenort"
    ],
    "qs_pg:aaroncc":"PL",
    "qs_pg:gn_country":"PL",
    "qs_pg:gn_fcode":"PPL",
    "qs_pg:gn_pop":713,
    "qs_pg:name":"Szczodre",
    "qs_pg:name_adm0":"Polska",
    "qs_pg:name_adm1":"Dolnosl\u0105skie",
    "qs_pg:photos_9k":1,
    "qs_pg:photos_9r":1,
    "qs_pg:photos_all":12,
    "qs_pg:photos_sr":0,
    "qs_pg:pop_sr":2,
    "qs_pg:qs_pg_placetype":"locality",
    "qs_pg:qs_pg_placetype_gp":"Town",
    "qs_pg:woe_adm0":23424923,
    "woe:adm0_id":23424923,
    "woe:name_adm0":"Polska",
    "woe:name_adm1":"Dolnosl\u0105skie",
    "woe:placetype":"Town",
    "wof:name":"Szczodre",
    "wof:placetype":"locality",
    "wof:population":713
},
  "geometry": {"coordinates":[17.18262,51.19484],"type":"Point"}
}