{
  "type": "Feature",
  "properties": {
    "gn:admin1_code":"86.0",
    "gn:admin2_code":"3020.0",
    "gn:admin3_code":"302006.0",
    "gn:asciiname":"Prokopow",
    "gn:country_code":"PL",
    "gn:dem":109,
    "gn:feature_class":"P",
    "gn:feature_code":"PPL",
    "gn:name":"Prokop\u00f3w",
    "gn:population":0,
    "gn:timezone":"Europe/Warsaw",
    "iso:country":"PL",
    "name:und_x_variant":[
        "Prokop\u00f3w"
    ],
    "wof:name":"Prokopow",
    "wof:placetype":"locality"
},
  "geometry": {"coordinates":[17.80246,51.9151],"type":"Point"}
}