{
  "type": "Feature",
  "properties": {
    "gn:admin1_code":"86.0",
    "gn:admin2_code":"3020.0",
    "gn:admin3_code":"302006.0",
    "gn:asciiname":"Prokopow",
    "gn:country_code":"PL",
    "gn:dem":109,
    "gn:feature_class":"P",
    "gn:feature_code":"PPL",
    "gn:name":"Prokop\u00f3w",
    "gn:population":0,
    "gn:timezone":"Europe/Warsaw",
    "iso:country":"PL",
    "name:pol_x_preferred":[
        "Prokop\u00f3w"
    ],
    "name:ukr_x_preferred":[
        "\u041f\u0440\u043e\u043a\u043e\u043f\u0443\u0432"
    ],
    "wof:name":"Prokopow",
    "wof:placetype":"locality"
},
  "geometry": {"coordinates":[17.80246,51.9151],"type":"Point"}
}