{
  "type": "Feature",
  "properties": {
    "gn:admin1_code":"72.0",
    "gn:admin2_code":"208.0",
    "gn:admin3_code":"20813.0",
    "gn:asciiname":"Bielice",
    "gn:country_code":"PL",
    "gn:dem":694,
    "gn:feature_class":"P",
    "gn:feature_code":"PPL",
    "gn:name":"Bielice",
    "gn:population":0,
    "gn:timezone":"Europe/Warsaw",
    "iso:country":"PL",
    "name:azb_x_preferred":[
        "\u0628\u06cc\u0644\u06cc\u062a\u0633\u0647"
    ],
    "name:deu_x_preferred":[
        "Bielice"
    ],
    "name:fas_x_preferred":[
        "\u0628\u06cc\u0644\u06cc\u062a\u0633\u0647"
    ],
    "name:nld_x_preferred":[
        "Bielice"
    ],
    "name:pol_x_preferred":[
        "Bielice"
    ],
    "name:ukr_x_preferred":[
        "\u0411\u0435\u043b\u0456\u0446\u0435"
    ],
    "wof:name":"Bielice",
    "wof:placetype":"locality"
},
  "geometry": {"coordinates":[17.00615,50.27497],"type":"Point"}
}