{
  "type": "Feature",
  "properties": {
    "gn:admin1_code":"72.0",
    "gn:admin2_code":"208.0",
    "gn:admin3_code":"20813.0",
    "gn:asciiname":"Bielice",
    "gn:country_code":"PL",
    "gn:dem":694,
    "gn:feature_class":"P",
    "gn:feature_code":"PPL",
    "gn:name":"Bielice",
    "gn:population":0,
    "gn:timezone":"Europe/Warsaw",
    "iso:country":"PL",
    "wof:name":"Bielice",
    "wof:placetype":"locality"
},
  "geometry": {"coordinates":[17.00615,50.27497],"type":"Point"}
}