{
  "type": "Feature",
  "properties": {
    "gn:admin1_code":"81.0",
    "gn:admin2_code":"2002.0",
    "gn:admin3_code":"200207.0",
    "gn:asciiname":"Bindziuha",
    "gn:country_code":"PL",
    "gn:dem":138,
    "gn:feature_class":"P",
    "gn:feature_code":"PPL",
    "gn:name":"Bindziuha",
    "gn:population":0,
    "gn:timezone":"Europe/Warsaw",
    "iso:country":"PL",
    "wof:name":"Bindziuha",
    "wof:placetype":"locality"
},
  "geometry": {"coordinates":[23.64397,52.93313000000001],"type":"Point"}
}