{
  "type": "Feature",
  "properties": {
    "gn:admin1_code":"72.0",
    "gn:admin2_code":"219.0",
    "gn:admin3_code":"21905.0",
    "gn:asciiname":"Klecin",
    "gn:country_code":"PL",
    "gn:dem":196,
    "gn:feature_class":"P",
    "gn:feature_code":"PPL",
    "gn:name":"Klecin",
    "gn:population":0,
    "gn:timezone":"Europe/Warsaw",
    "iso:country":"PL",
    "name:ceb_x_preferred":[
        "Klecin"
    ],
    "name:nld_x_preferred":[
        "Klecin"
    ],
    "name:pol_x_preferred":[
        "Klecin"
    ],
    "name:ukr_x_preferred":[
        "\u041a\u043b\u0435\u0446\u0438\u043d"
    ],
    "wof:name":"Klecin",
    "wof:placetype":"locality"
},
  "geometry": {"coordinates":[16.57253,50.90065],"type":"Point"}
}