{
  "type": "Feature",
  "properties": {
    "gn:admin1_code":"85.0",
    "gn:admin2_code":"2811.0",
    "gn:admin3_code":"281103.0",
    "gn:asciiname":"Lemiesze",
    "gn:cc2":"PL",
    "gn:country_code":"PL",
    "gn:dem":198,
    "gn:feature_class":"P",
    "gn:feature_code":"PPL",
    "gn:name":"Lemiesze",
    "gn:population":0,
    "gn:timezone":"Europe/Warsaw",
    "iso:country":"PL",
    "name:und_x_variant":[
        "Lehmany",
        "Lehmanns",
        "Lemiesze"
    ],
    "wof:name":"Lemiesze",
    "wof:placetype":"locality"
},
  "geometry": {"coordinates":[20.28333,53.45],"type":"Point"}
}