{
  "type": "Feature",
  "properties": {
    "gn:admin1_code":"85.0",
    "gn:admin2_code":"2804.0",
    "gn:admin3_code":"280402.0",
    "gn:asciiname":"Gradki",
    "gn:country_code":"PL",
    "gn:dem":112,
    "gn:feature_class":"P",
    "gn:feature_code":"PPL",
    "gn:name":"Gr\u0105dki",
    "gn:population":0,
    "gn:timezone":"Europe/Warsaw",
    "iso:country":"PL",
    "name:und_x_variant":[
        "Gross Thierbach",
        "Gr\u0105dki"
    ],
    "wof:name":"Gradki",
    "wof:placetype":"locality"
},
  "geometry": {"coordinates":[19.84932,54.03697],"type":"Point"}
}