{
  "type": "Feature",
  "properties": {
    "gn:admin1_code":"86.0",
    "gn:admin2_code":"3008.0",
    "gn:admin3_code":"300803.0",
    "gn:asciiname":"Kliny",
    "gn:country_code":"PL",
    "gn:dem":181,
    "gn:feature_class":"P",
    "gn:feature_code":"PPL",
    "gn:name":"Kliny",
    "gn:population":0,
    "gn:timezone":"Europe/Warsaw",
    "iso:country":"PL",
    "name:pol_x_preferred":[
        "Kliny"
    ],
    "name:ukr_x_preferred":[
        "\u041a\u043b\u0456\u043d\u0438"
    ],
    "wof:name":"Kliny",
    "wof:placetype":"locality"
},
  "geometry": {"coordinates":[17.98565,51.32192],"type":"Point"}
}