{
  "type": "Feature",
  "properties": {
    "gn:admin1_code":"86.0",
    "gn:admin2_code":"3028.0",
    "gn:admin3_code":"302805.0",
    "gn:asciiname":"Losiniec",
    "gn:country_code":"PL",
    "gn:dem":90,
    "gn:feature_class":"P",
    "gn:feature_code":"PPL",
    "gn:name":"\u0141osiniec",
    "gn:population":0,
    "gn:timezone":"Europe/Warsaw",
    "iso:country":"PL",
    "wof:name":"Losiniec",
    "wof:placetype":"locality"
},
  "geometry": {"coordinates":[17.20356,52.72455],"type":"Point"}
}