{
  "type": "Feature",
  "properties": {
    "gn:admin1_code":"78.0",
    "gn:admin2_code":"1433.0",
    "gn:admin3_code":"143305.0",
    "gn:asciiname":"Zambrzeniec Nowy",
    "gn:country_code":"PL",
    "gn:dem":114,
    "gn:feature_class":"P",
    "gn:feature_code":"PPL",
    "gn:name":"Zambrzeniec Nowy",
    "gn:population":0,
    "gn:timezone":"Europe/Warsaw",
    "iso:country":"PL",
    "name:fra_x_preferred":[
        "Zambrzyniec"
    ],
    "name:ita_x_preferred":[
        "Zambrzyniec"
    ],
    "name:pol_x_preferred":[
        "Zambrzyniec"
    ],
    "name:ukr_x_preferred":[
        "\u0417\u0430\u043c\u0431\u0436\u0438\u043d\u0435\u0446\u044c"
    ],
    "name:und_x_variant":[
        "Zambrzyniec Nowy",
        "Zambrzeniec Nowy"
    ],
    "wof:name":"Zambrzeniec Nowy",
    "wof:placetype":"locality"
},
  "geometry": {"coordinates":[21.81505,52.51281],"type":"Point"}
}