{
  "type": "Feature",
  "properties": {
    "gn:admin1_code":"87.0",
    "gn:admin2_code":"3203.0",
    "gn:admin3_code":"320306.0",
    "gn:asciiname":"Warcislaw",
    "gn:cc2":"PL",
    "gn:country_code":"PL",
    "gn:dem":137,
    "gn:feature_class":"P",
    "gn:feature_code":"PPL",
    "gn:name":"Warcis\u0142aw",
    "gn:population":0,
    "gn:timezone":"Europe/Warsaw",
    "iso:country":"PL",
    "name:und_x_variant":[
        "Marienhof",
        "Warcis\u0142aw"
    ],
    "wof:name":"Warcislaw",
    "wof:placetype":"locality"
},
  "geometry": {"coordinates":[15.98333,53.45],"type":"Point"}
}