{
  "type": "Feature",
  "properties": {
    "gn:admin1_code":"75.0",
    "gn:admin2_code":"609.0",
    "gn:admin3_code":"60910.0",
    "gn:asciiname":"Radawczyk",
    "gn:country_code":"PL",
    "gn:dem":196,
    "gn:feature_class":"P",
    "gn:feature_code":"PPL",
    "gn:name":"Radawczyk",
    "gn:population":0,
    "gn:timezone":"Europe/Warsaw",
    "iso:country":"PL",
    "name:fra_x_preferred":[
        "Radawczyk"
    ],
    "name:pol_x_preferred":[
        "Radawczyk"
    ],
    "name:ukr_x_preferred":[
        "\u0420\u0430\u0434\u0430\u0432\u0447\u0438\u043a"
    ],
    "wof:name":"Radawczyk",
    "wof:placetype":"locality"
},
  "geometry": {"coordinates":[22.38333,51.16667],"type":"Point"}
}