{
  "type": "Feature",
  "properties": {
    "iso:country":"PL",
    "name:pol_x_preferred":[
        "Goszczan\u00f3w"
    ],
    "wof:coterminous":[
        1125289235
    ],
    "wof:name":"Goszczan\u00f3w",
    "wof:placetype":"locality"
},
  "geometry": {"coordinates":[18.5151160157997,51.7919868136621],"type":"Point"}
}