{
  "type": "Feature",
  "properties": {
    "iso:country":"PL",
    "name:azb_x_preferred":[
        "\u0642\u0648\u0634\u0686\u0627\u0646\u0648\u0648"
    ],
    "name:deu_x_preferred":[
        "Goszczan\u00f3w"
    ],
    "name:fas_x_preferred":[
        "\u06af\u0648\u0634\u0686\u0627\u0646\u0648\u0648"
    ],
    "name:nld_x_preferred":[
        "Goszczan\u00f3w"
    ],
    "name:pol_x_preferred":[
        "Goszczan\u00f3w"
    ],
    "name:ukr_x_preferred":[
        "\u0490\u043e\u0449\u0430\u043d\u0443\u0432"
    ],
    "wof:coterminous":[
        1125289235
    ],
    "wof:name":"Goszczan\u00f3w",
    "wof:placetype":"locality"
},
  "geometry": {"coordinates":[18.5151160157997,51.7919868136621],"type":"Point"}
}