{
  "type": "Feature",
  "properties": {
    "gn:admin1_code":"82.0",
    "gn:admin2_code":"2210.0",
    "gn:admin3_code":"221004.0",
    "gn:asciiname":"Zulawki",
    "gn:country_code":"PL",
    "gn:dem":1,
    "gn:feature_class":"P",
    "gn:feature_code":"PPL",
    "gn:name":"\u017bu\u0142awki",
    "gn:population":0,
    "gn:timezone":"Europe/Warsaw",
    "iso:country":"PL",
    "name:ceb_x_preferred":[
        "\u017bu\u0142awki"
    ],
    "name:deu_x_preferred":[
        "\u017bu\u0142awki"
    ],
    "name:pol_x_preferred":[
        "\u017bu\u0142awki"
    ],
    "name:ukr_x_preferred":[
        "\u0416\u0443\u043b\u0430\u0432\u043a\u0456"
    ],
    "name:und_x_variant":[
        "F\u00fcrstenwerder",
        "\u017bu\u0142awki"
    ],
    "wof:name":"Zulawki",
    "wof:placetype":"locality"
},
  "geometry": {"coordinates":[18.96824,54.28226],"type":"Point"}
}