{
  "type": "Feature",
  "properties": {
    "gn:admin1_code":"75.0",
    "gn:admin2_code":"619.0",
    "gn:admin3_code":"61903.0",
    "gn:asciiname":"Stary Majdan",
    "gn:country_code":"PL",
    "gn:dem":177,
    "gn:feature_class":"P",
    "gn:feature_code":"PPL",
    "gn:name":"Stary Majdan",
    "gn:population":0,
    "gn:timezone":"Europe/Warsaw",
    "iso:country":"PL",
    "name:fra_x_preferred":[
        "Stary Majdan"
    ],
    "name:pol_x_preferred":[
        "Stary Majdan"
    ],
    "wof:name":"Stary Majdan",
    "wof:placetype":"locality"
},
  "geometry": {"coordinates":[23.38668,51.35937],"type":"Point"}
}