{
  "type": "Feature",
  "properties": {
    "gn:admin1_code":"75.0",
    "gn:admin2_code":"610.0",
    "gn:admin3_code":"61005.0",
    "gn:asciiname":"Bogdanka",
    "gn:country_code":"PL",
    "gn:dem":169,
    "gn:feature_class":"P",
    "gn:feature_code":"PPL",
    "gn:name":"Bogdanka",
    "gn:population":0,
    "gn:timezone":"Europe/Warsaw",
    "iso:country":"PL",
    "name:fra_x_preferred":[
        "Bogdanka"
    ],
    "name:pol_x_preferred":[
        "Bogdanka"
    ],
    "name:ukr_x_preferred":[
        "\u0411\u043e\u0491\u0434\u0430\u043d\u043a\u0430"
    ],
    "name:und_x_variant":[
        "Kolonia Bogdanka",
        "Bogdanka"
    ],
    "wof:name":"Bogdanka",
    "wof:placetype":"locality"
},
  "geometry": {"coordinates":[23.0195,51.32603],"type":"Point"}
}