{
  "type": "Feature",
  "properties": {
    "gn:admin1_code":"74.0",
    "gn:admin2_code":"1002.0",
    "gn:admin3_code":"100201.0",
    "gn:asciiname":"Stara Wies",
    "gn:country_code":"PL",
    "gn:dem":104,
    "gn:feature_class":"P",
    "gn:feature_code":"PPL",
    "gn:name":"Stara Wies",
    "gn:population":0,
    "gn:timezone":"Europe/Warsaw",
    "iso:country":"PL",
    "wof:name":"Stara Wies",
    "wof:placetype":"neighbourhood"
},
  "geometry": {"coordinates":[19.4342,52.22777],"type":"Point"}
}