{
  "type": "Feature",
  "properties": {
    "gn:admin1_code":"82.0",
    "gn:admin2_code":"2212.0",
    "gn:admin3_code":"221202.0",
    "gn:asciiname":"Karzniczka",
    "gn:country_code":"PL",
    "gn:dem":61,
    "gn:feature_class":"P",
    "gn:feature_code":"PPL",
    "gn:name":"Karzniczka",
    "gn:population":0,
    "gn:timezone":"Europe/Warsaw",
    "iso:country":"PL",
    "wof:name":"Karzniczka",
    "wof:placetype":"locality"
},
  "geometry": {"coordinates":[17.23549,54.48889000000001],"type":"Point"}
}