{
  "type": "Feature",
  "properties": {
    "gn:admin1_code":"82.0",
    "gn:admin2_code":"2212.0",
    "gn:admin3_code":"221202.0",
    "gn:asciiname":"Karzniczka",
    "gn:country_code":"PL",
    "gn:dem":61,
    "gn:feature_class":"P",
    "gn:feature_code":"PPL",
    "gn:name":"Karzniczka",
    "gn:population":0,
    "gn:timezone":"Europe/Warsaw",
    "iso:country":"PL",
    "name:azb_x_preferred":[
        "\u06a9\u0627\u0631\u0698\u0646\u0642\u0686\u06a9\u0627"
    ],
    "name:ceb_x_preferred":[
        "Karzniczka"
    ],
    "name:csb_x_preferred":[
        "Niemieck\u00f4 Karznica"
    ],
    "name:deu_x_preferred":[
        "Kar\u017cniczka"
    ],
    "name:fas_x_preferred":[
        "\u06a9\u0627\u0631\u0698\u0646\u06af\u0686\u06a9\u0627"
    ],
    "name:nld_x_preferred":[
        "Kar\u017cniczka"
    ],
    "name:pol_x_preferred":[
        "Karzniczka"
    ],
    "wof:name":"Karzniczka",
    "wof:placetype":"locality"
},
  "geometry": {"coordinates":[17.23549,54.48889000000001],"type":"Point"}
}