{
  "type": "Feature",
  "properties": {
    "iso:country":"PL",
    "name:ast_x_preferred":[
        "Matys\u00f3wka"
    ],
    "name:ceb_x_preferred":[
        "Matys\u00f3wka"
    ],
    "name:eng_x_preferred":[
        "Matys\u00f3wka"
    ],
    "name:fra_x_preferred":[
        "Matys\u00f3wka"
    ],
    "name:pol_x_preferred":[
        "Matys\u00f3wka"
    ],
    "name:ukr_x_preferred":[
        "\u041c\u0430\u0442\u0438\u0441\u0456\u0432\u043a\u0430"
    ],
    "qs:a0":"Rzeczpospolita Polska",
    "qs:a1":"*Podkarpackie",
    "qs:a1r":"0",
    "qs:a2":"Rzeszowski",
    "qs:adm0":"Rzeczpospolita Polska",
    "qs:la_lc":"*",
    "qs:level":"locality",
    "qs:loc":"Matys\u00f3wka",
    "qs:loc_alt":"Matysowka",
    "qs:pop":0,
    "qs:type":"buffered point",
    "wd:wordcount":67,
    "wof:name":"Matys\u00f3wka",
    "wof:placetype":"locality"
},
  "geometry": {"coordinates":[22.05702,49.996849],"type":"Point"}
}