{
  "type": "Feature",
  "properties": {
    "gn:admin1_code":"86.0",
    "gn:admin2_code":"3010.0",
    "gn:admin3_code":"301013.0",
    "gn:asciiname":"Morzyczyn",
    "gn:country_code":"PL",
    "gn:dem":89,
    "gn:feature_class":"P",
    "gn:feature_code":"PPL",
    "gn:name":"Morzyczyn",
    "gn:population":0,
    "gn:timezone":"Europe/Warsaw",
    "iso:country":"PL",
    "wof:name":"Morzyczyn",
    "wof:placetype":"locality"
},
  "geometry": {"coordinates":[18.40348,52.42426],"type":"Point"}
}