{
  "type": "Feature",
  "properties": {
    "gn:admin1_code":"87.0",
    "gn:admin2_code":"3201.0",
    "gn:admin3_code":"320104.0",
    "gn:asciiname":"Warnino",
    "gn:country_code":"PL",
    "gn:dem":103,
    "gn:feature_class":"P",
    "gn:feature_code":"PPL",
    "gn:name":"Warnino",
    "gn:population":0,
    "gn:timezone":"Europe/Warsaw",
    "iso:country":"PL",
    "name:deu_x_preferred":[
        "Warnino"
    ],
    "name:pol_x_preferred":[
        "Warnino"
    ],
    "name:szl_x_preferred":[
        "War\u0144ino"
    ],
    "name:ukr_x_preferred":[
        "\u0412\u0430\u0440\u043d\u0456\u043d\u043e"
    ],
    "wof:name":"Warnino",
    "wof:placetype":"locality"
},
  "geometry": {"coordinates":[16.34858,53.94891],"type":"Point"}
}