{
  "type": "Feature",
  "properties": {
    "gn:admin1_code":"82.0",
    "gn:admin2_code":"2202.0",
    "gn:admin3_code":"220203.0",
    "gn:asciiname":"Ciechocin",
    "gn:country_code":"PL",
    "gn:dem":124,
    "gn:feature_class":"P",
    "gn:feature_code":"PPL",
    "gn:name":"Ciechocin",
    "gn:population":0,
    "gn:timezone":"Europe/Warsaw",
    "iso:country":"PL",
    "name:azb_x_preferred":[
        "\u0686\u06cc\u062e\u0648\u0686\u06cc\u0646"
    ],
    "name:ceb_x_preferred":[
        "Ciechocin"
    ],
    "name:deu_x_preferred":[
        "Ciechocin"
    ],
    "name:fas_x_preferred":[
        "\u0686\u06cc\u062e\u0648\u0686\u06cc\u0646"
    ],
    "name:nld_x_preferred":[
        "Ciechocin"
    ],
    "name:pol_x_preferred":[
        "Ciechocin"
    ],
    "name:ukr_x_preferred":[
        "\u0426\u0435\u0445\u043e\u0446\u0438\u043d"
    ],
    "wof:name":"Ciechocin",
    "wof:placetype":"locality"
},
  "geometry": {"coordinates":[17.69859,53.61223],"type":"Point"}
}