{
  "type": "Feature",
  "properties": {
    "gn:admin1_code":"86.0",
    "gn:admin2_code":"3064.0",
    "gn:admin3_code":"306401.0",
    "gn:asciiname":"Garaszewo",
    "gn:country_code":"PL",
    "gn:dem":79,
    "gn:feature_class":"P",
    "gn:feature_code":"PPL",
    "gn:name":"Garaszewo",
    "gn:population":0,
    "gn:timezone":"Europe/Warsaw",
    "iso:country":"PL",
    "wof:name":"Garaszewo",
    "wof:placetype":"neighbourhood"
},
  "geometry": {"coordinates":[16.96381,52.35162],"type":"Point"}
}