{
  "type": "Feature",
  "properties": {
    "gn:admin1_code":"72.0",
    "gn:admin2_code":"202.0",
    "gn:admin3_code":"20207.0",
    "gn:asciiname":"Ruszkowice",
    "gn:country_code":"PL",
    "gn:dem":301,
    "gn:feature_class":"P",
    "gn:feature_code":"PPL",
    "gn:name":"Ruszkowice",
    "gn:population":0,
    "gn:timezone":"Europe/Warsaw",
    "iso:country":"PL",
    "name:pol_x_preferred":[
        "Ruszkowice"
    ],
    "name:spa_x_preferred":[
        "Ruszkowice"
    ],
    "name:ukr_x_preferred":[
        "\u0420\u0443\u0448\u043a\u043e\u0432\u0456\u0446\u0435"
    ],
    "wof:name":"Ruszkowice",
    "wof:placetype":"locality"
},
  "geometry": {"coordinates":[16.86877,50.69114],"type":"Point"}
}