{
  "type": "Feature",
  "properties": {
    "gn:admin1_code":"85.0",
    "gn:admin2_code":"2809.0",
    "gn:admin3_code":"280903.0",
    "gn:asciiname":"Bobrownik",
    "gn:country_code":"PL",
    "gn:dem":72,
    "gn:feature_class":"P",
    "gn:feature_code":"PPL",
    "gn:name":"Bobrownik",
    "gn:population":0,
    "gn:timezone":"Europe/Warsaw",
    "iso:country":"PL",
    "name:fra_x_preferred":[
        "Bobrownik"
    ],
    "name:pol_x_preferred":[
        "Bobrownik"
    ],
    "name:ukr_x_preferred":[
        "\u0411\u043e\u0431\u0440\u043e\u0432\u043d\u0438\u043a"
    ],
    "name:und_x_variant":[
        "Babrownik",
        "Bewernick"
    ],
    "wof:name":"Bobrownik",
    "wof:placetype":"locality"
},
  "geometry": {"coordinates":[20.48743,54.11638000000001],"type":"Point"}
}