{
  "type": "Feature",
  "properties": {
    "gn:admin1_code":"80.0",
    "gn:admin2_code":"1809.0",
    "gn:admin3_code":"180902.0",
    "gn:asciiname":"Lubliniec Nowy",
    "gn:country_code":"PL",
    "gn:dem":208,
    "gn:feature_class":"P",
    "gn:feature_code":"PPL",
    "gn:name":"Lubliniec Nowy",
    "gn:population":0,
    "gn:timezone":"Europe/Warsaw",
    "iso:country":"PL",
    "name:pol_x_preferred":[
        "Nowy Lubliniec"
    ],
    "name:ukr_x_preferred":[
        "\u041d\u043e\u0432\u0438\u0439 \u041b\u044e\u0431\u043b\u0438\u043d\u0435\u0446\u044c"
    ],
    "name:und_x_variant":[
        "Nowy Lubliniec",
        "Lubliniec Nowy"
    ],
    "wof:name":"Lubliniec Nowy",
    "wof:placetype":"locality"
},
  "geometry": {"coordinates":[23.09483,50.29467],"type":"Point"}
}