{
  "type": "Feature",
  "properties": {
    "gn:admin1_code":"78.0",
    "gn:admin2_code":"1429.0",
    "gn:admin3_code":"142906.0",
    "gn:asciiname":"Skrzeszew",
    "gn:country_code":"PL",
    "gn:dem":133,
    "gn:feature_class":"P",
    "gn:feature_code":"PPL",
    "gn:name":"Skrzeszew",
    "gn:population":0,
    "gn:timezone":"Europe/Warsaw",
    "iso:country":"PL",
    "wof:name":"Skrzeszew",
    "wof:placetype":"locality"
},
  "geometry": {"coordinates":[22.50854,52.40158],"type":"Point"}
}