{
  "type": "Feature",
  "properties": {
    "gn:admin1_code":"83.0",
    "gn:admin2_code":"2468.0",
    "gn:admin3_code":"246801.0",
    "gn:asciiname":"Dlugoszyn",
    "gn:country_code":"PL",
    "gn:dem":267,
    "gn:feature_class":"P",
    "gn:feature_code":"PPL",
    "gn:name":"D\u0142ugoszyn",
    "gn:population":0,
    "gn:timezone":"Europe/Warsaw",
    "iso:country":"PL",
    "wof:name":"Dlugoszyn",
    "wof:placetype":"locality"
},
  "geometry": {"coordinates":[19.25423,50.24841],"type":"Point"}
}