{
  "type": "Feature",
  "properties": {
    "gn:admin1_code":"82.0",
    "gn:admin2_code":"2212.0",
    "gn:admin3_code":"221207.0",
    "gn:asciiname":"Warcimino",
    "gn:country_code":"PL",
    "gn:dem":100,
    "gn:feature_class":"P",
    "gn:feature_code":"PPL",
    "gn:name":"Warcimino",
    "gn:population":0,
    "gn:timezone":"Europe/Warsaw",
    "iso:country":"PL",
    "name:ceb_x_preferred":[
        "Warcimino"
    ],
    "name:csb_x_preferred":[
        "Warc\u00ebmino"
    ],
    "name:deu_x_preferred":[
        "Warcimino"
    ],
    "name:pol_x_preferred":[
        "Warcimino"
    ],
    "name:ukr_x_preferred":[
        "\u0412\u0430\u0440\u0446\u0438\u043c\u0456\u043d\u043e"
    ],
    "wof:name":"Warcimino",
    "wof:placetype":"locality"
},
  "geometry": {"coordinates":[17.55133,54.44794],"type":"Point"}
}