{
  "type": "Feature",
  "properties": {
    "gn:admin1_code":"73.0",
    "gn:admin2_code":"401.0",
    "gn:admin3_code":"40108.0",
    "gn:asciiname":"Lewin",
    "gn:country_code":"PL",
    "gn:dem":85,
    "gn:feature_class":"P",
    "gn:feature_code":"PPL",
    "gn:name":"Lewin",
    "gn:population":0,
    "gn:timezone":"Europe/Warsaw",
    "iso:country":"PL",
    "name:pol_x_preferred":[
        "Lewin"
    ],
    "name:ukr_x_preferred":[
        "\u041b\u0435\u0432\u0456\u043d"
    ],
    "wof:name":"Lewin",
    "wof:placetype":"locality"
},
  "geometry": {"coordinates":[18.79907,52.78976],"type":"Point"}
}