{
  "type": "Feature",
  "properties": {
    "gn:admin1_code":"78.0",
    "gn:admin2_code":"1406.0",
    "gn:admin3_code":"140603.0",
    "gn:asciiname":"Budziszynek",
    "gn:country_code":"PL",
    "gn:dem":132,
    "gn:feature_class":"P",
    "gn:feature_code":"PPL",
    "gn:name":"Budziszynek",
    "gn:population":0,
    "gn:timezone":"Europe/Warsaw",
    "iso:country":"PL",
    "name:azb_x_preferred":[
        "\u0628\u0648\u062c\u0634\u0646\u06a9"
    ],
    "name:ceb_x_preferred":[
        "Budziszynek"
    ],
    "name:fas_x_preferred":[
        "\u0628\u0648\u062c\u0634\u0646\u06a9"
    ],
    "name:fra_x_preferred":[
        "Budziszynek"
    ],
    "name:nld_x_preferred":[
        "Budziszynek"
    ],
    "name:pol_x_preferred":[
        "Budziszynek"
    ],
    "name:ukr_x_preferred":[
        "\u0411\u0443\u0434\u0437\u0456\u0448\u0438\u043d\u0435\u043a"
    ],
    "wof:name":"Budziszynek",
    "wof:placetype":"locality"
},
  "geometry": {"coordinates":[21.05993,51.86213],"type":"Point"}
}