{
  "type": "Feature",
  "properties": {
    "gn:admin1_code":"75.0",
    "gn:admin2_code":"616.0",
    "gn:admin3_code":"61602.0",
    "gn:asciiname":"Padarz",
    "gn:country_code":"PL",
    "gn:dem":175,
    "gn:feature_class":"P",
    "gn:feature_code":"PPL",
    "gn:name":"Padarz",
    "gn:population":0,
    "gn:timezone":"Europe/Warsaw",
    "iso:country":"PL",
    "name:fra_x_preferred":[
        "Padarz"
    ],
    "name:pol_x_preferred":[
        "Padarz"
    ],
    "name:ukr_x_preferred":[
        "\u041f\u0430\u0434\u0430\u0436"
    ],
    "wof:name":"Padarz",
    "wof:placetype":"locality"
},
  "geometry": {"coordinates":[22.02305,51.71287],"type":"Point"}
}