{
  "type": "Feature",
  "properties": {
    "gn:admin1_code":"86.0",
    "gn:admin2_code":"3021.0",
    "gn:admin3_code":"302104.0",
    "gn:asciiname":"Debogora",
    "gn:country_code":"PL",
    "gn:dem":99,
    "gn:feature_class":"P",
    "gn:feature_code":"PPL",
    "gn:name":"D\u0119bog\u00f3ra",
    "gn:population":0,
    "gn:timezone":"Europe/Warsaw",
    "iso:country":"PL",
    "name:ceb_x_preferred":[
        "D\u0119bog\u00f3ra"
    ],
    "name:fra_x_preferred":[
        "D\u0119bog\u00f3ra"
    ],
    "name:pol_x_preferred":[
        "D\u0119bog\u00f3ra"
    ],
    "name:ukr_x_preferred":[
        "\u0414\u0435\u043c\u0431\u043e\u0491\u0443\u0440\u0430"
    ],
    "wof:name":"Debogora",
    "wof:placetype":"locality"
},
  "geometry": {"coordinates":[17.09258,52.49705],"type":"Point"}
}