{
  "type": "Feature",
  "properties": {
    "gn:country":"PL",
    "gn:fcode":"PPL",
    "gn:population":382,
    "iso:country":"PL",
    "name:ast_x_preferred":[
        "Juszczyn"
    ],
    "name:eng_x_preferred":[
        "Juszczyn"
    ],
    "name:fra_x_preferred":[
        "Juszczyn"
    ],
    "name:pol_x_preferred":[
        "Juszczyn"
    ],
    "name:ukr_x_preferred":[
        "\u042e\u0449\u0438\u043d"
    ],
    "qs_pg:aaroncc":"PL",
    "qs_pg:gn_country":"PL",
    "qs_pg:gn_fcode":"PPL",
    "qs_pg:gn_pop":382,
    "qs_pg:name":"Juszczyn",
    "qs_pg:name_adm0":"Polska",
    "qs_pg:name_adm1":"Dolnosl\u0105skie",
    "qs_pg:photos_9r":0,
    "qs_pg:photos_sr":0,
    "qs_pg:pop_sr":2,
    "qs_pg:qs_pg_placetype":"locality",
    "qs_pg:qs_pg_placetype_gp":"Town",
    "qs_pg:woe_adm0":23424923,
    "woe:adm0_id":23424923,
    "woe:name_adm0":"Polska",
    "woe:name_adm1":"Dolnosl\u0105skie",
    "woe:placetype":"Town",
    "wof:name":"Juszczyn",
    "wof:placetype":"locality",
    "wof:population":382
},
  "geometry": {"coordinates":[16.67879,51.15507],"type":"Point"}
}