{
  "type": "Feature",
  "properties": {
    "gn:admin1_code":"82.0",
    "gn:admin2_code":"2201.0",
    "gn:admin3_code":"220103.0",
    "gn:asciiname":"Kozin",
    "gn:country_code":"PL",
    "gn:dem":110,
    "gn:feature_class":"P",
    "gn:feature_code":"PPL",
    "gn:name":"Kozin",
    "gn:population":0,
    "gn:timezone":"Europe/Warsaw",
    "iso:country":"PL",
    "name:csb_x_preferred":[
        "K\u00f2z\u00ebno"
    ],
    "name:pol_x_preferred":[
        "Kozin"
    ],
    "wof:name":"Kozin",
    "wof:placetype":"locality"
},
  "geometry": {"coordinates":[17.62702999999999,54.37857],"type":"Point"}
}