{
  "type": "Feature",
  "properties": {
    "gn:admin1_code":"73.0",
    "gn:admin2_code":"401.0",
    "gn:admin3_code":"40109.0",
    "gn:asciiname":"Kuczkowo",
    "gn:country_code":"PL",
    "gn:dem":91,
    "gn:feature_class":"P",
    "gn:feature_code":"PPL",
    "gn:name":"Kuczkowo",
    "gn:population":0,
    "gn:timezone":"Europe/Warsaw",
    "iso:country":"PL",
    "wof:name":"Kuczkowo",
    "wof:placetype":"locality"
},
  "geometry": {"coordinates":[18.61093,52.74015],"type":"Point"}
}