{
  "type": "Feature",
  "properties": {
    "gn:country":"PL",
    "gn:fcode":"PPLA3",
    "gn:population":700,
    "iso:country":"PL",
    "name:azb_x_preferred":[
        "\u062a\u0648\u0631\u0634\u0646 \u06a9\u0634\u06a9\u06cc\u0644\u0646\u0627"
    ],
    "name:fas_x_preferred":[
        "\u062a\u0648\u0631\u0634\u0646 \u06a9\u0634\u06a9\u06cc\u0644\u0646\u0627"
    ],
    "name:fra_x_preferred":[
        "Turo\u015b\u0144 Ko\u015bcielna"
    ],
    "name:lit_x_preferred":[
        "Turo\u0161n Ko\u0161celna"
    ],
    "name:nld_x_preferred":[
        "Turo\u015b\u0144 Ko\u015bcielna"
    ],
    "name:pol_x_preferred":[
        "Turo\u015b\u0144 Ko\u015bcielna"
    ],
    "name:rus_x_preferred":[
        "\u0422\u0443\u0440\u043e\u0441\u043d\u044c-\u041a\u043e\u0441\u044c\u0446\u0435\u043b\u044c\u043d\u0430"
    ],
    "name:ukr_x_preferred":[
        "\u0422\u0443\u0440\u043e\u0441\u043d\u044c-\u041a\u043e\u0441\u044c\u0446\u0435\u043b\u044c\u043d\u0430"
    ],
    "name:urd_x_preferred":[
        "\u062a\u0648\u0631\u0648\u0634\u0646 \u06a9\u0648\u0634\u0633\u06cc\u0644\u0646\u0627"
    ],
    "qs_pg:aaroncc":"PL",
    "qs_pg:gn_country":"PL",
    "qs_pg:gn_fcode":"PPLA3",
    "qs_pg:gn_pop":700,
    "qs_pg:name":"Turo\u015b\u0144 Ko\u015bcielna",
    "qs_pg:name_adm0":"Polska",
    "qs_pg:name_adm1":"Podlaskie",
    "qs_pg:photos":1,
    "qs_pg:photos_1k":1,
    "qs_pg:photos_9k":1,
    "qs_pg:photos_9r":1,
    "qs_pg:photos_all":1,
    "qs_pg:photos_sr":1,
    "qs_pg:pop_sr":2,
    "qs_pg:qs_pg_placetype":"localadmin",
    "qs_pg:qs_pg_placetype_gp":"LocalAdmin",
    "qs_pg:woe_adm0":23424923,
    "woe:adm0_id":23424923,
    "woe:name_adm0":"Polska",
    "woe:name_adm1":"Podlaskie",
    "woe:placetype":"LocalAdmin",
    "wof:name":"Turo\u015b\u0144 Ko\u015bcielna",
    "wof:placetype":"localadmin",
    "wof:population":700
},
  "geometry": {"coordinates":[23.05532,53.01463],"type":"Point"}
}