{
  "type": "Feature",
  "properties": {
    "iso:country":"PL",
    "name:eng_x_preferred":[
        "Wojnow"
    ],
    "name:pol_x_preferred":[
        "Wojn\u00f3w"
    ],
    "wof:name":"Wojnow",
    "wof:placetype":"neighbourhood"
},
  "geometry": {"coordinates":[17.16073665177401,51.09859698772877],"type":"Point"}
}