{
  "type": "Feature",
  "properties": {
    "gn:admin1_code":"85.0",
    "gn:admin2_code":"2813.0",
    "gn:admin3_code":"281306.0",
    "gn:asciiname":"Urbanki",
    "gn:cc2":"PL",
    "gn:country_code":"PL",
    "gn:dem":167,
    "gn:feature_class":"P",
    "gn:feature_code":"PPL",
    "gn:name":"Urbanki",
    "gn:population":0,
    "gn:timezone":"Europe/Warsaw",
    "iso:country":"PL",
    "name:deu_x_preferred":[
        "Urbanki"
    ],
    "name:pol_x_preferred":[
        "Urbanki"
    ],
    "name:ukr_x_preferred":[
        "\u0423\u0440\u0431\u0430\u043d\u043a\u0456"
    ],
    "name:und_x_variant":[
        "Urbanken",
        "Urbanki"
    ],
    "wof:name":"Urbanki",
    "wof:placetype":"locality"
},
  "geometry": {"coordinates":[22.6351,54.04054],"type":"Point"}
}