{
  "type": "Feature",
  "properties": {
    "gn:admin1_code":"84.0",
    "gn:admin2_code":"2605.0",
    "gn:admin3_code":"260506.0",
    "gn:asciiname":"Rytlow",
    "gn:country_code":"PL",
    "gn:dem":262,
    "gn:feature_class":"P",
    "gn:feature_code":"PPL",
    "gn:name":"Rytl\u00f3w",
    "gn:population":0,
    "gn:timezone":"Europe/Warsaw",
    "iso:country":"PL",
    "name:pol_x_preferred":[
        "Rytl\u00f3w"
    ],
    "name:ukr_x_preferred":[
        "\u0420\u0438\u0442\u043b\u044e\u0432"
    ],
    "wof:name":"Rytlow",
    "wof:placetype":"locality"
},
  "geometry": {"coordinates":[20.10687,51.01262],"type":"Point"}
}