{
  "type": "Feature",
  "properties": {
    "gn:admin1_code":"75.0",
    "gn:admin2_code":"608.0",
    "gn:admin3_code":"60802.0",
    "gn:asciiname":"Michalowka",
    "gn:country_code":"PL",
    "gn:dem":158,
    "gn:feature_class":"P",
    "gn:feature_code":"PPL",
    "gn:name":"Micha\u0142\u00f3wka",
    "gn:population":0,
    "gn:timezone":"Europe/Warsaw",
    "iso:country":"PL",
    "name:azb_x_preferred":[
        "\u0645\u06cc\u062e\u0627\u0648\u0648\u0648\u06a9\u0627"
    ],
    "name:ceb_x_preferred":[
        "Micha\u0142\u00f3wka"
    ],
    "name:fas_x_preferred":[
        "\u0645\u06cc\u062e\u0627\u0648\u0648\u0648\u06a9\u0627"
    ],
    "name:fra_x_preferred":[
        "Micha\u0142\u00f3wka"
    ],
    "name:pol_x_preferred":[
        "Micha\u0142\u00f3wka"
    ],
    "name:ukr_x_preferred":[
        "\u041c\u0456\u0445\u0430\u043b\u0443\u0432\u043a\u0430"
    ],
    "wof:name":"Michalowka",
    "wof:placetype":"locality"
},
  "geometry": {"coordinates":[22.374,51.45508],"type":"Point"}
}