{
  "type": "Feature",
  "properties": {
    "gn:admin1_code":"87.0",
    "gn:admin2_code":"3201.0",
    "gn:admin3_code":"320102.0",
    "gn:asciiname":"Laski",
    "gn:country_code":"PL",
    "gn:dem":59,
    "gn:feature_class":"P",
    "gn:feature_code":"PPL",
    "gn:name":"Laski",
    "gn:population":0,
    "gn:timezone":"Europe/Warsaw",
    "iso:country":"PL",
    "name:ceb_x_preferred":[
        "Laski"
    ],
    "name:deu_x_preferred":[
        "Laski"
    ],
    "name:pol_x_preferred":[
        "Laski"
    ],
    "name:ukr_x_preferred":[
        "\u041b\u044f\u0441\u043a\u0456"
    ],
    "wof:name":"Laski",
    "wof:placetype":"locality"
},
  "geometry": {"coordinates":[15.92084,53.94633],"type":"Point"}
}