{
  "type": "Feature",
  "properties": {
    "gn:admin1_code":"77.0",
    "gn:admin2_code":"1209.0",
    "gn:admin3_code":"120902.0",
    "gn:asciiname":"Smigawa",
    "gn:country_code":"PL",
    "gn:dem":457,
    "gn:feature_class":"P",
    "gn:feature_code":"PPL",
    "gn:name":"Smigawa",
    "gn:population":0,
    "gn:timezone":"Europe/Warsaw",
    "iso:country":"PL",
    "wof:name":"Smigawa",
    "wof:placetype":"locality"
},
  "geometry": {"coordinates":[19.93333,49.68333],"type":"Point"}
}