{
  "type": "Feature",
  "properties": {
    "gn:admin1_code":"85.0",
    "gn:admin2_code":"2810.0",
    "gn:admin3_code":"281004.0",
    "gn:asciiname":"Nawiady",
    "gn:country_code":"PL",
    "gn:dem":154,
    "gn:feature_class":"P",
    "gn:feature_code":"PPL",
    "gn:name":"Nawiady",
    "gn:population":0,
    "gn:timezone":"Europe/Warsaw",
    "iso:country":"PL",
    "name:und_x_variant":[
        "Aweyden",
        "Niewiady",
        "Nawiady"
    ],
    "wof:name":"Nawiady",
    "wof:placetype":"locality"
},
  "geometry": {"coordinates":[21.32597,53.71384000000001],"type":"Point"}
}