{
  "type": "Feature",
  "properties": {
    "gn:admin1_code":"78.0",
    "gn:admin2_code":"1436.0",
    "gn:admin3_code":"143601.0",
    "gn:asciiname":"Debnica",
    "gn:country_code":"PL",
    "gn:dem":162,
    "gn:feature_class":"P",
    "gn:feature_code":"PPL",
    "gn:name":"D\u0119bnica",
    "gn:population":0,
    "gn:timezone":"Europe/Warsaw",
    "iso:country":"PL",
    "name:fra_x_preferred":[
        "D\u0119bnica"
    ],
    "name:pol_x_preferred":[
        "D\u0119bnica"
    ],
    "name:ukr_x_preferred":[
        "\u0414\u0435\u043c\u0431\u043d\u0438\u0446\u044f"
    ],
    "wof:name":"Debnica",
    "wof:placetype":"locality"
},
  "geometry": {"coordinates":[21.47238,51.29172],"type":"Point"}
}