{
  "type": "Feature",
  "properties": {
    "gn:admin1_code":"81.0",
    "gn:admin2_code":"2011.0",
    "gn:admin3_code":"201102.0",
    "gn:asciiname":"Sitkowo",
    "gn:country_code":"PL",
    "gn:dem":174,
    "gn:feature_class":"P",
    "gn:feature_code":"PPL",
    "gn:name":"Sitkowo",
    "gn:population":0,
    "gn:timezone":"Europe/Warsaw",
    "iso:country":"PL",
    "name:fra_x_preferred":[
        "Sitkowo"
    ],
    "name:lit_x_preferred":[
        "Sitkovas"
    ],
    "name:pol_x_preferred":[
        "Sitkowo"
    ],
    "name:ukr_x_preferred":[
        "\u0421\u0456\u0442\u043a\u043e\u0432\u043e"
    ],
    "wof:name":"Sitkowo",
    "wof:placetype":"locality"
},
  "geometry": {"coordinates":[23.19652,53.39665],"type":"Point"}
}