{
  "type": "Feature",
  "properties": {
    "gn:admin1_code":"83.0",
    "gn:admin2_code":"2464.0",
    "gn:admin3_code":"246401.0",
    "gn:asciiname":"Wyczerpy",
    "gn:country_code":"PL",
    "gn:dem":243,
    "gn:feature_class":"P",
    "gn:feature_code":"PPL",
    "gn:name":"Wyczerpy",
    "gn:population":0,
    "gn:timezone":"Europe/Warsaw",
    "iso:country":"PL",
    "wof:name":"Wyczerpy",
    "wof:placetype":"locality"
},
  "geometry": {"coordinates":[19.16226,50.83787],"type":"Point"}
}