{
  "type": "Feature",
  "properties": {
    "gn:admin1_code":"75.0",
    "gn:admin2_code":"601.0",
    "gn:admin3_code":"60109.0",
    "gn:asciiname":"Jusaki",
    "gn:country_code":"PL",
    "gn:dem":148,
    "gn:feature_class":"P",
    "gn:feature_code":"PPL",
    "gn:name":"Jusaki",
    "gn:population":0,
    "gn:timezone":"Europe/Warsaw",
    "iso:country":"PL",
    "name:und_x_variant":[
        "Kolonia Jusaki",
        "Jusaki"
    ],
    "wof:name":"Jusaki",
    "wof:placetype":"locality"
},
  "geometry": {"coordinates":[23.17374,51.88649],"type":"Point"}
}