{
  "type": "Feature",
  "properties": {
    "gn:admin1_code":"84.0",
    "gn:admin2_code":"2602.0",
    "gn:admin3_code":"260206.0",
    "gn:asciiname":"Bolescice",
    "gn:country_code":"PL",
    "gn:dem":242,
    "gn:feature_class":"P",
    "gn:feature_code":"PPL",
    "gn:name":"Bole\u015bcice",
    "gn:population":0,
    "gn:timezone":"Europe/Warsaw",
    "iso:country":"PL",
    "wof:name":"Bolescice",
    "wof:placetype":"locality"
},
  "geometry": {"coordinates":[20.11923,50.58329000000001],"type":"Point"}
}