{
  "type": "Feature",
  "properties": {
    "gn:admin1_code":"78.0",
    "gn:admin2_code":"1434.0",
    "gn:admin3_code":"143410.0",
    "gn:asciiname":"Ruda Czernik",
    "gn:country_code":"PL",
    "gn:dem":126,
    "gn:feature_class":"P",
    "gn:feature_code":"PPL",
    "gn:name":"Ruda Czernik",
    "gn:population":0,
    "gn:timezone":"Europe/Warsaw",
    "iso:country":"PL",
    "wof:name":"Ruda Czernik",
    "wof:placetype":"locality"
},
  "geometry": {"coordinates":[21.65783,52.39257],"type":"Point"}
}