{
  "type": "Feature",
  "properties": {
    "iso:country":"PL",
    "name:eng_x_preferred":[
        "Grabno"
    ],
    "name:fre_x_preferred":[
        "Grabno"
    ],
    "name:pol_x_preferred":[
        "Grabno"
    ],
    "qs:a0":"Rzeczpospolita Polska",
    "qs:a1":"*Malopolskie",
    "qs:a1r":"0",
    "qs:a2":"Tarnowski",
    "qs:adm0":"Rzeczpospolita Polska",
    "qs:la_lc":"*",
    "qs:level":"locality",
    "qs:loc":"Grabno",
    "qs:loc_alt":"Grabno",
    "qs:pop":0,
    "qs:type":"buffered point",
    "wd:wordcount":101,
    "wof:name":"Grabno",
    "wof:placetype":"locality"
},
  "geometry": {"coordinates":[20.781189,49.929989],"type":"Point"}
}