{
  "type": "Feature",
  "properties": {
    "gn:admin1_code":"87.0",
    "gn:admin2_code":"3215.0",
    "gn:admin3_code":"321504.0",
    "gn:asciiname":"Smiadowo",
    "gn:country_code":"PL",
    "gn:dem":152,
    "gn:feature_class":"P",
    "gn:feature_code":"PPL",
    "gn:name":"\u015amiadowo",
    "gn:population":0,
    "gn:timezone":"Europe/Warsaw",
    "iso:country":"PL",
    "name:pol_x_preferred":[
        "\u015amiadowo"
    ],
    "name:vie_x_preferred":[
        "\u015amiadowo"
    ],
    "wof:name":"Smiadowo",
    "wof:placetype":"locality"
},
  "geometry": {"coordinates":[16.55345,53.61289],"type":"Point"}
}