{
  "type": "Feature",
  "properties": {
    "gn:admin1_code":"86.0",
    "gn:admin2_code":"3011.0",
    "gn:admin3_code":"301105.0",
    "gn:asciiname":"Woniesc",
    "gn:country_code":"PL",
    "gn:dem":78,
    "gn:feature_class":"P",
    "gn:feature_code":"PPL",
    "gn:name":"Wonie\u015b\u0107",
    "gn:population":0,
    "gn:timezone":"Europe/Warsaw",
    "iso:country":"PL",
    "name:fra_x_preferred":[
        "Wonie\u015b\u0107"
    ],
    "name:pol_x_preferred":[
        "Wonie\u015b\u0107"
    ],
    "name:ukr_x_preferred":[
        "\u0412\u043e\u043d\u0435\u0441\u0446\u044c"
    ],
    "name:und_x_variant":[
        "Wonie\u015b\u0107"
    ],
    "wof:name":"Woniesc",
    "wof:placetype":"locality"
},
  "geometry": {"coordinates":[16.68686,52.00353],"type":"Point"}
}