{
  "type": "Feature",
  "properties": {
    "gn:admin1_code":"81.0",
    "gn:admin2_code":"2006.0",
    "gn:admin3_code":"200605.0",
    "gn:asciiname":"Dzierzbia",
    "gn:country_code":"PL",
    "gn:dem":128,
    "gn:feature_class":"P",
    "gn:feature_code":"PPL",
    "gn:name":"Dzierzbia",
    "gn:population":0,
    "gn:timezone":"Europe/Warsaw",
    "iso:country":"PL",
    "name:azb_x_preferred":[
        "\u062c\u0698\u0628\u06cc\u0627"
    ],
    "name:fas_x_preferred":[
        "\u062c\u0698\u0628\u06cc\u0627"
    ],
    "name:lit_x_preferred":[
        "Dze\u017ebia"
    ],
    "name:pol_x_preferred":[
        "Dzierzbia"
    ],
    "name:rus_x_preferred":[
        "\u0414\u0437\u0435\u0436\u0431\u044f"
    ],
    "name:ukr_x_preferred":[
        "\u0414\u0437\u0435\u0436\u0431\u044f"
    ],
    "wof:name":"Dzierzbia",
    "wof:placetype":"locality"
},
  "geometry": {"coordinates":[22.08888,53.37985],"type":"Point"}
}