{
  "type": "Feature",
  "properties": {
    "gn:admin1_code":"74.0",
    "gn:admin2_code":"1005.0",
    "gn:admin3_code":"100502.0",
    "gn:asciiname":"Waliszew Dworski",
    "gn:country_code":"PL",
    "gn:dem":106,
    "gn:feature_class":"P",
    "gn:feature_code":"PPL",
    "gn:name":"Waliszew Dworski",
    "gn:population":0,
    "gn:timezone":"Europe/Warsaw",
    "iso:country":"PL",
    "name:fra_x_preferred":[
        "Waliszew Dworski"
    ],
    "name:pol_x_preferred":[
        "Waliszew Dworski"
    ],
    "name:ukr_x_preferred":[
        "\u0412\u0430\u043b\u0456\u0448\u0435\u0432-\u0414\u0432\u043e\u0440\u0441\u044c\u043a\u0438\u0439"
    ],
    "name:und_x_variant":[
        "Waliszew",
        "Waliszew Dworski"
    ],
    "wof:name":"Waliszew Dworski",
    "wof:placetype":"locality"
},
  "geometry": {"coordinates":[19.6243,52.03867],"type":"Point"}
}