{
  "type": "Feature",
  "properties": {
    "gn:admin1_code":"85.0",
    "gn:admin2_code":"2803.0",
    "gn:admin3_code":"280306.0",
    "gn:asciiname":"Hartowiec",
    "gn:country_code":"PL",
    "gn:dem":164,
    "gn:feature_class":"P",
    "gn:feature_code":"PPL",
    "gn:name":"Hartowiec",
    "gn:population":0,
    "gn:timezone":"Europe/Warsaw",
    "iso:country":"PL",
    "name:pol_x_preferred":[
        "Hartowiec"
    ],
    "name:ukr_x_preferred":[
        "\u0413\u0430\u0440\u0442\u043e\u0432\u0435\u0446\u044c"
    ],
    "wof:name":"Hartowiec",
    "wof:placetype":"locality"
},
  "geometry": {"coordinates":[19.84123,53.39744],"type":"Point"}
}