{
  "type": "Feature",
  "properties": {
    "gn:admin1_code":"85.0",
    "gn:admin2_code":"2803.0",
    "gn:admin3_code":"280304.0",
    "gn:asciiname":"Nowy Zielun",
    "gn:country_code":"PL",
    "gn:dem":153,
    "gn:feature_class":"P",
    "gn:feature_code":"PPL",
    "gn:name":"Nowy Zielu\u0144",
    "gn:population":0,
    "gn:timezone":"Europe/Warsaw",
    "iso:country":"PL",
    "name:ceb_x_preferred":[
        "Nowy Zielu\u0144"
    ],
    "name:pol_x_preferred":[
        "Nowy Zielu\u0144"
    ],
    "name:ukr_x_preferred":[
        "\u041d\u043e\u0432\u0438\u0439 \u0417\u0435\u043b\u044e\u043d\u044c"
    ],
    "wof:name":"Nowy Zielun",
    "wof:placetype":"locality"
},
  "geometry": {"coordinates":[19.84418,53.20161],"type":"Point"}
}