{
  "type": "Feature",
  "properties": {
    "gn:admin1_code":"78.0",
    "gn:admin2_code":"1412.0",
    "gn:admin3_code":"141205.0",
    "gn:asciiname":"Ostrow Kania",
    "gn:country_code":"PL",
    "gn:dem":127,
    "gn:feature_class":"P",
    "gn:feature_code":"PPL",
    "gn:name":"Ostr\u00f3w Kania",
    "gn:population":0,
    "gn:timezone":"Europe/Warsaw",
    "iso:country":"PL",
    "wof:name":"Ostrow Kania",
    "wof:placetype":"locality"
},
  "geometry": {"coordinates":[21.43201,52.20929],"type":"Point"}
}