{
  "type": "Feature",
  "properties": {
    "iso:country":"PL",
    "wof:name":"Lublinek",
    "wof:placetype":"neighbourhood"
},
  "geometry": {"coordinates":[19.40443648913506,51.73442646109675],"type":"Point"}
}