{
  "type": "Feature",
  "properties": {
    "gn:admin1_code":"78.0",
    "gn:admin2_code":"1436.0",
    "gn:admin3_code":"143602.0",
    "gn:asciiname":"Frankow",
    "gn:country_code":"PL",
    "gn:dem":170,
    "gn:feature_class":"P",
    "gn:feature_code":"PPL",
    "gn:name":"Frank\u00f3w",
    "gn:population":0,
    "gn:timezone":"Europe/Warsaw",
    "iso:country":"PL",
    "name:azb_x_preferred":[
        "\u0641\u0631\u0627\u0646\u06a9\u0648\u0648"
    ],
    "name:ceb_x_preferred":[
        "Frank\u00f3w"
    ],
    "name:fas_x_preferred":[
        "\u0641\u0631\u0627\u0646\u06a9\u0648\u0648"
    ],
    "name:fra_x_preferred":[
        "Frank\u00f3w"
    ],
    "name:pol_x_preferred":[
        "Frank\u00f3w"
    ],
    "name:ukr_x_preferred":[
        "\u0424\u0440\u0430\u043d\u043a\u0443\u0432"
    ],
    "name:und_x_variant":[
        "Frank\u00f3w"
    ],
    "wof:name":"Frankow",
    "wof:placetype":"locality"
},
  "geometry": {"coordinates":[21.59534,51.43228],"type":"Point"}
}