{
  "type": "Feature",
  "properties": {
    "gn:admin1_code":"78.0",
    "gn:admin2_code":"1432.0",
    "gn:admin3_code":"143201.0",
    "gn:asciiname":"Cholewy",
    "gn:country_code":"PL",
    "gn:dem":86,
    "gn:feature_class":"P",
    "gn:feature_code":"PPL",
    "gn:name":"Cholewy",
    "gn:population":0,
    "gn:timezone":"Europe/Warsaw",
    "iso:country":"PL",
    "name:fra_x_preferred":[
        "Cholewy"
    ],
    "name:pol_x_preferred":[
        "Cholewy"
    ],
    "name:ukr_x_preferred":[
        "\u0425\u043e\u043b\u0435\u0432\u0438"
    ],
    "wof:name":"Cholewy",
    "wof:placetype":"locality"
},
  "geometry": {"coordinates":[20.49053,52.2207],"type":"Point"}
}