{
  "type": "Feature",
  "properties": {
    "gn:admin1_code":"87.0",
    "gn:admin2_code":"3215.0",
    "gn:admin3_code":"321505.0",
    "gn:asciiname":"Radomysl",
    "gn:country_code":"PL",
    "gn:dem":132,
    "gn:feature_class":"P",
    "gn:feature_code":"PPL",
    "gn:name":"Radomy\u015bl",
    "gn:population":0,
    "gn:timezone":"Europe/Warsaw",
    "iso:country":"PL",
    "wof:name":"Radomysl",
    "wof:placetype":"locality"
},
  "geometry": {"coordinates":[16.52856,53.75946999999999],"type":"Point"}
}