{
  "type": "Feature",
  "properties": {
    "gn:admin1_code":"73.0",
    "gn:admin2_code":"410.0",
    "gn:admin3_code":"41005.0",
    "gn:asciiname":"Slupy",
    "gn:country_code":"PL",
    "gn:dem":79,
    "gn:feature_class":"P",
    "gn:feature_code":"PPL",
    "gn:name":"S\u0142upy",
    "gn:population":0,
    "gn:timezone":"Europe/Warsaw",
    "iso:country":"PL",
    "wof:name":"Slupy",
    "wof:placetype":"locality"
},
  "geometry": {"coordinates":[17.66667,52.96666999999999],"type":"Point"}
}