{
  "type": "Feature",
  "properties": {
    "gn:admin1_code":"75.0",
    "gn:admin2_code":"604.0",
    "gn:admin3_code":"60406.0",
    "gn:asciiname":"Zadubce",
    "gn:country_code":"PL",
    "gn:dem":208,
    "gn:feature_class":"P",
    "gn:feature_code":"PPL",
    "gn:name":"Zadubce",
    "gn:population":0,
    "gn:timezone":"Europe/Warsaw",
    "iso:country":"PL",
    "name:fra_x_preferred":[
        "Zad\u0119bce"
    ],
    "name:pol_x_preferred":[
        "Zad\u0119bce"
    ],
    "name:ukr_x_preferred":[
        "\u0417\u0430\u0434\u0435\u043c\u0431\u0446\u0435"
    ],
    "name:und_x_variant":[
        "Zad\u0119bce",
        "Zadubce"
    ],
    "name:urd_x_preferred":[
        "\u0632\u062f\u06cc\u0628\u06a9\u06d2"
    ],
    "wof:name":"Zadubce",
    "wof:placetype":"locality"
},
  "geometry": {"coordinates":[23.76622,50.85527],"type":"Point"}
}