{
  "type": "Feature",
  "properties": {
    "gn:country":"PL",
    "gn:fcode":"PPL",
    "gn:population":500,
    "iso:country":"PL",
    "name:ceb_x_preferred":[
        "Krzy\u017cowa"
    ],
    "name:deu_x_preferred":[
        "Krzy\u017cowa"
    ],
    "name:pol_x_preferred":[
        "Krzy\u017cowa"
    ],
    "name:spa_x_preferred":[
        "Krzy\u017cowa"
    ],
    "name:ukr_x_preferred":[
        "\u041a\u0448\u0438\u0436\u043e\u0432\u0430"
    ],
    "qs_pg:aaroncc":"PL",
    "qs_pg:gn_country":"PL",
    "qs_pg:gn_fcode":"PPL",
    "qs_pg:gn_pop":500,
    "qs_pg:name":"Krzy\u017cowa",
    "qs_pg:name_adm0":"Polska",
    "qs_pg:name_adm1":"Dolnosl\u0105skie",
    "qs_pg:photos_9k":1,
    "qs_pg:photos_9r":1,
    "qs_pg:photos_all":19,
    "qs_pg:photos_sr":0,
    "qs_pg:pop_sr":2,
    "qs_pg:qs_pg_placetype":"locality",
    "qs_pg:qs_pg_placetype_gp":"Town",
    "qs_pg:woe_adm0":23424923,
    "woe:adm0_id":23424923,
    "woe:name_adm0":"Polska",
    "woe:name_adm1":"Dolnosl\u0105skie",
    "woe:placetype":"Town",
    "wof:name":"Krzy\u017cowa",
    "wof:placetype":"locality",
    "wof:population":500
},
  "geometry": {"coordinates":[15.67929,51.32852],"type":"Point"}
}