{
  "type": "Feature",
  "properties": {
    "gn:admin1_code":"78.0",
    "gn:admin2_code":"1404.0",
    "gn:admin3_code":"140405.0",
    "gn:asciiname":"Teodorow",
    "gn:country_code":"PL",
    "gn:dem":94,
    "gn:feature_class":"P",
    "gn:feature_code":"PPL",
    "gn:name":"Teodor\u00f3w",
    "gn:population":0,
    "gn:timezone":"Europe/Warsaw",
    "iso:country":"PL",
    "name:fra_x_preferred":[
        "Teodor\u00f3w"
    ],
    "name:pol_x_preferred":[
        "Teodor\u00f3w"
    ],
    "name:ukr_x_preferred":[
        "\u0422\u0435\u043e\u0434\u043e\u0440\u0443\u0432"
    ],
    "wof:name":"Teodorow",
    "wof:placetype":"locality"
},
  "geometry": {"coordinates":[19.59507,52.31461],"type":"Point"}
}