{
  "type": "Feature",
  "properties": {
    "gn:country":"PL",
    "gn:fcode":"PPLA3",
    "gn:population":7500,
    "iso:country":"PL",
    "name:azb_x_preferred":[
        "\u0645\u0634\u0627\u0646\u0627 \u062f\u0648\u0644\u0646\u0627"
    ],
    "name:bul_x_preferred":[
        "\u041c\u0448\u0430\u043d\u0430 \u0414\u043e\u043b\u043d\u0430"
    ],
    "name:deu_x_preferred":[
        "Mszana Dolna"
    ],
    "name:epo_x_preferred":[
        "Mszana Dolna"
    ],
    "name:eus_x_preferred":[
        "Mszana Dolna"
    ],
    "name:fas_x_preferred":[
        "\u0645\u0634\u0627\u0646\u0627 \u062f\u0648\u0644\u0646\u0627"
    ],
    "name:fra_x_preferred":[
        "Mszana Dolna"
    ],
    "name:heb_x_preferred":[
        "\u05de\u05e9\u05d0\u05e0\u05d4 \u05d3\u05d5\u05dc\u05e0\u05d4"
    ],
    "name:ita_x_preferred":[
        "Mszana Dolna"
    ],
    "name:jav_x_preferred":[
        "Mszana Dolna"
    ],
    "name:lav_x_preferred":[
        "M\u0161ana Dolna"
    ],
    "name:msa_x_preferred":[
        "Mszana Dolna"
    ],
    "name:nld_x_preferred":[
        "Mszana Dolna"
    ],
    "name:pol_x_preferred":[
        "Mszana Dolna"
    ],
    "name:por_x_preferred":[
        "Mszana Dolna"
    ],
    "name:ron_x_preferred":[
        "Mszana Dolna"
    ],
    "name:rus_x_preferred":[
        "\u041c\u0448\u0430\u043d\u0430-\u0414\u043e\u043b\u044c\u043d\u0430"
    ],
    "name:slk_x_preferred":[
        "Mszana Dolna"
    ],
    "name:srp_x_preferred":[
        "\u041c\u0448\u0430\u043d\u0430 \u0414\u043e\u043b\u043d\u0430"
    ],
    "name:ukr_x_preferred":[
        "\u041c\u0448\u0430\u043d\u0430-\u0414\u043e\u043b\u044c\u043d\u0430"
    ],
    "name:vie_x_preferred":[
        "Mszana Dolna"
    ],
    "name:war_x_preferred":[
        "Mszana Dolna"
    ],
    "name:zho_x_preferred":[
        "\u4e0b\u59c6\u6c99\u7d0d"
    ],
    "qs_pg:aaroncc":"PL",
    "qs_pg:gn_country":"PL",
    "qs_pg:gn_fcode":"PPLA3",
    "qs_pg:gn_pop":7500,
    "qs_pg:name":"Mszana Dolna",
    "qs_pg:name_adm0":"Polska",
    "qs_pg:name_adm1":"Ma\u0142opolskie",
    "qs_pg:photos":21,
    "qs_pg:photos_1k":4,
    "qs_pg:photos_9k":1,
    "qs_pg:photos_9r":1,
    "qs_pg:photos_all":21,
    "qs_pg:photos_sr":1,
    "qs_pg:pop_sr":5,
    "qs_pg:qs_pg_placetype":"localadmin",
    "qs_pg:qs_pg_placetype_gp":"LocalAdmin",
    "qs_pg:woe_adm0":23424923,
    "woe:adm0_id":23424923,
    "woe:name_adm0":"Polska",
    "woe:name_adm1":"Ma\u0142opolskie",
    "woe:placetype":"LocalAdmin",
    "wof:name":"Mszana Dolna",
    "wof:placetype":"localadmin",
    "wof:population":7500
},
  "geometry": {"coordinates":[20.07992,49.67432],"type":"Point"}
}