{
  "type": "Feature",
  "properties": {
    "gn:admin1_code":"74.0",
    "gn:admin2_code":"1020.0",
    "gn:admin3_code":"102009.0",
    "gn:asciiname":"Biesiekierz Nawojowy",
    "gn:country_code":"PL",
    "gn:dem":129,
    "gn:feature_class":"P",
    "gn:feature_code":"PPL",
    "gn:name":"Biesiekierz Nawojowy",
    "gn:population":0,
    "gn:timezone":"Europe/Warsaw",
    "iso:country":"PL",
    "name:pol_x_preferred":[
        "Besiekierz Nawojowy"
    ],
    "name:ukr_x_preferred":[
        "\u0411\u0435\u0441\u0435\u043a\u0435\u0436-\u041d\u0430\u0432\u043e\u0439\u043e\u0432\u0438"
    ],
    "name:und_x_variant":[
        "Biesiekierz Nawojowy"
    ],
    "wof:name":"Biesiekierz Nawojowy",
    "wof:placetype":"locality"
},
  "geometry": {"coordinates":[19.50216,51.96045],"type":"Point"}
}