{
  "type": "Feature",
  "properties": {
    "gn:admin1_code":"83.0",
    "gn:admin2_code":"2406.0",
    "gn:admin3_code":"240603.0",
    "gn:asciiname":"Karcze",
    "gn:country_code":"PL",
    "gn:dem":245,
    "gn:feature_class":"P",
    "gn:feature_code":"PPL",
    "gn:name":"Karcze",
    "gn:population":0,
    "gn:timezone":"Europe/Warsaw",
    "iso:country":"PL",
    "name:fra_x_preferred":[
        "Karcze"
    ],
    "name:pol_x_preferred":[
        "Karcze"
    ],
    "wof:name":"Karcze",
    "wof:placetype":"locality"
},
  "geometry": {"coordinates":[18.71435,51.02941],"type":"Point"}
}