{
  "type": "Feature",
  "properties": {
    "gn:admin1_code":"75.0",
    "gn:admin2_code":"663.0",
    "gn:admin3_code":"66301.0",
    "gn:asciiname":"Hajdow-Zadebie",
    "gn:country_code":"PL",
    "gn:dem":184,
    "gn:feature_class":"P",
    "gn:feature_code":"PPL",
    "gn:name":"Hajd\u00f3w-Zad\u0119bie",
    "gn:population":0,
    "gn:timezone":"Europe/Warsaw",
    "iso:country":"PL",
    "wof:name":"Hajdow-Zadebie",
    "wof:placetype":"locality"
},
  "geometry": {"coordinates":[22.63853,51.24853],"type":"Point"}
}