{
  "type": "Feature",
  "properties": {
    "gn:admin1_code":"81.0",
    "gn:admin2_code":"2011.0",
    "gn:admin3_code":"201101.0",
    "gn:asciiname":"Wiazowka",
    "gn:country_code":"PL",
    "gn:dem":172,
    "gn:feature_class":"P",
    "gn:feature_code":"PPL",
    "gn:name":"Wi\u0105z\u00f3wka",
    "gn:population":0,
    "gn:timezone":"Europe/Warsaw",
    "iso:country":"PL",
    "name:fra_x_preferred":[
        "Wi\u0105z\u00f3wka"
    ],
    "name:lit_x_preferred":[
        "Vionzuvka"
    ],
    "name:pol_x_preferred":[
        "Wi\u0105z\u00f3wka"
    ],
    "name:ukr_x_preferred":[
        "\u0412\u0439\u043e\u043d\u0437\u0443\u0432\u043a\u0430"
    ],
    "name:und_x_variant":[
        "Wi\u0105z\u00f3wka"
    ],
    "wof:name":"Wiazowka",
    "wof:placetype":"locality"
},
  "geometry": {"coordinates":[23.28261,53.62755],"type":"Point"}
}