{
  "type": "Feature",
  "properties": {
    "gn:admin1_code":"78.0",
    "gn:admin2_code":"1419.0",
    "gn:admin3_code":"141911.0",
    "gn:asciiname":"Zyck Niemiecki",
    "gn:country_code":"PL",
    "gn:dem":60,
    "gn:feature_class":"P",
    "gn:feature_code":"PPL",
    "gn:name":"Zyck Niemiecki",
    "gn:population":0,
    "gn:timezone":"Europe/Warsaw",
    "iso:country":"PL",
    "wof:name":"Zyck Niemiecki",
    "wof:placetype":"locality"
},
  "geometry": {"coordinates":[19.92215,52.41031],"type":"Point"}
}