{
  "type": "Feature",
  "properties": {
    "gn:admin1_code":"86.0",
    "gn:admin2_code":"3017.0",
    "gn:admin3_code":"301704.0",
    "gn:asciiname":"Gutow",
    "gn:country_code":"PL",
    "gn:dem":139,
    "gn:feature_class":"P",
    "gn:feature_code":"PPL",
    "gn:name":"Gut\u00f3w",
    "gn:population":0,
    "gn:timezone":"Europe/Warsaw",
    "iso:country":"PL",
    "name:azb_x_preferred":[
        "\u0642\u0648\u062a\u0648\u0648"
    ],
    "name:ceb_x_preferred":[
        "Gut\u00f3w"
    ],
    "name:fas_x_preferred":[
        "\u06af\u0648\u062a\u0648\u0648"
    ],
    "name:nld_x_preferred":[
        "Gut\u00f3w"
    ],
    "name:pol_x_preferred":[
        "Gut\u00f3w"
    ],
    "name:ukr_x_preferred":[
        "\u0490\u0443\u0442\u0443\u0432"
    ],
    "wof:name":"Gutow",
    "wof:placetype":"locality"
},
  "geometry": {"coordinates":[17.86796,51.76129],"type":"Point"}
}