{
  "type": "Feature",
  "properties": {
    "gn:gn_country":"PL",
    "gn:gn_fcode":"PPL",
    "gn:gn_pop":504,
    "gn:population":504,
    "iso:country":"PL",
    "name:dut_x_preferred":[
        "Wisznia Ma\u0142a"
    ],
    "name:eng_x_preferred":[
        "Wisznia Ma\u0142a"
    ],
    "name:fre_x_preferred":[
        "Wisznia Ma\u0142a"
    ],
    "name:ger_x_preferred":[
        "Wisznia Ma\u0142a"
    ],
    "name:per_x_preferred":[
        "\u0648\u06cc\u0634\u0646\u06af\u0627 \u0645\u0627\u0648\u0627"
    ],
    "name:pol_x_preferred":[
        "Wisznia Ma\u0142a"
    ],
    "name:rus_x_preferred":[
        "\u0412\u0438\u0448\u043d\u044f-\u041c\u0430\u043b\u0430"
    ],
    "name:swe_x_preferred":[
        "Wisznia Ma\u0142a"
    ],
    "qs_pg:aaroncc":"PL",
    "qs_pg:gn_country":"PL",
    "qs_pg:gn_fcode":"PPL",
    "qs_pg:gn_pop":504,
    "qs_pg:name":"Wisznia Ma\u0142a",
    "qs_pg:name_adm0":"Polska",
    "qs_pg:name_adm1":"Dolnosl\u0105skie",
    "qs_pg:photos_9k":1,
    "qs_pg:photos_9r":1,
    "qs_pg:photos_all":1,
    "qs_pg:photos_sr":0,
    "qs_pg:pop_sr":2,
    "qs_pg:qs_pg_placetype":"locality",
    "qs_pg:qs_pg_placetype_gp":"Town",
    "qs_pg:woe_adm0":23424923,
    "woe:adm0_id":23424923,
    "woe:name_adm0":"Polska",
    "woe:name_adm1":"Dolnosl\u0105skie",
    "woe:placetype":"Town",
    "wof:name":"Wisznia Ma\u0142a",
    "wof:placetype":"locality",
    "wof:population":504
},
  "geometry": {"coordinates":[17.04477,51.24752],"type":"Point"}
}