{
  "type": "Feature",
  "properties": {
    "gn:admin1_code":"76.0",
    "gn:admin2_code":"807.0",
    "gn:admin3_code":"80705.0",
    "gn:asciiname":"Tarnawa",
    "gn:cc2":"PL",
    "gn:country_code":"PL",
    "gn:dem":66,
    "gn:feature_class":"P",
    "gn:feature_code":"PPL",
    "gn:name":"Tarnawa",
    "gn:population":0,
    "gn:timezone":"Europe/Warsaw",
    "iso:country":"PL",
    "name:deu_x_preferred":[
        "Tornow"
    ],
    "name:pol_x_preferred":[
        "Tarnawa Rzepi\u0144ska"
    ],
    "wof:name":"Tarnawa",
    "wof:placetype":"locality"
},
  "geometry": {"coordinates":[14.91308,52.34509],"type":"Point"}
}