{
  "type": "Feature",
  "properties": {
    "gn:admin1_code":"76.0",
    "gn:admin2_code":"807.0",
    "gn:admin3_code":"80705.0",
    "gn:asciiname":"Tarnawa",
    "gn:cc2":"PL",
    "gn:country_code":"PL",
    "gn:dem":66,
    "gn:feature_class":"P",
    "gn:feature_code":"PPL",
    "gn:name":"Tarnawa",
    "gn:population":0,
    "gn:timezone":"Europe/Warsaw",
    "iso:country":"PL",
    "name:deu_x_preferred":[
        "Tornow"
    ],
    "name:fra_x_preferred":[
        "Tarnawa Rzepi\u0144ska"
    ],
    "name:pol_x_preferred":[
        "Tarnawa Rzepi\u0144ska"
    ],
    "name:ukr_x_preferred":[
        "\u0422\u0430\u0440\u043d\u0430\u0432\u0430-\u0416\u0435\u043f\u0456\u043d\u0441\u044c\u043a\u0430"
    ],
    "wof:name":"Tarnawa",
    "wof:placetype":"locality"
},
  "geometry": {"coordinates":[14.91308,52.34509],"type":"Point"}
}