{
  "type": "Feature",
  "properties": {
    "gn:admin1_code":"77.0",
    "gn:admin2_code":"1211.0",
    "gn:admin3_code":"121105.0",
    "gn:asciiname":"Otrebowa",
    "gn:country_code":"PL",
    "gn:dem":616,
    "gn:feature_class":"P",
    "gn:feature_code":"PPL",
    "gn:name":"Otr\u0119bowa",
    "gn:population":0,
    "gn:timezone":"Europe/Warsaw",
    "iso:country":"PL",
    "wof:name":"Otrebowa",
    "wof:placetype":"locality"
},
  "geometry": {"coordinates":[19.6867,49.47288],"type":"Point"}
}