{
  "type": "Feature",
  "properties": {
    "gn:admin1_code":"72.0",
    "gn:admin2_code":"264.0",
    "gn:admin3_code":"26401.0",
    "gn:asciiname":"Bienkowice",
    "gn:country_code":"PL",
    "gn:dem":119,
    "gn:feature_class":"P",
    "gn:feature_code":"PPL",
    "gn:name":"Bie\u0144kowice",
    "gn:population":0,
    "gn:timezone":"Europe/Warsaw",
    "iso:country":"PL",
    "name:eng_x_preferred":[
        "Bienkowice"
    ],
    "name:pol_x_preferred":[
        "Bie\u0144kowice"
    ],
    "wof:name":"Bienkowice",
    "wof:placetype":"neighbourhood"
},
  "geometry": {"coordinates":[17.096821,51.051254],"type":"Point"}
}