{
  "type": "Feature",
  "properties": {
    "iso:country":"PL",
    "name:eng_x_preferred":[
        "Bienkowice"
    ],
    "name:pol_x_preferred":[
        "Bie\u0144kowice"
    ],
    "wof:name":"Bienkowice",
    "wof:placetype":"neighbourhood"
},
  "geometry": {"coordinates":[17.0968208094224,51.05125444203081],"type":"Point"}
}