{
  "type": "Feature",
  "properties": {
    "gn:admin1_code":"75.0",
    "gn:admin2_code":"609.0",
    "gn:admin3_code":"60908.0",
    "gn:asciiname":"Radawczyk Boboszow",
    "gn:country_code":"PL",
    "gn:dem":205,
    "gn:feature_class":"P",
    "gn:feature_code":"PPL",
    "gn:name":"Radawczyk Bobosz\u00f3w",
    "gn:population":0,
    "gn:timezone":"Europe/Warsaw",
    "iso:country":"PL",
    "name:und_x_variant":[
        "Kolonia Radawczyk",
        "Radawczyk Bobosz\u00f3w"
    ],
    "wof:name":"Radawczyk Boboszow",
    "wof:placetype":"locality"
},
  "geometry": {"coordinates":[22.4101,51.18447000000001],"type":"Point"}
}