{
  "type": "Feature",
  "properties": {
    "gn:admin1_code":"83.0",
    "gn:admin2_code":"2473.0",
    "gn:admin3_code":"247301.0",
    "gn:asciiname":"Ochojec",
    "gn:country_code":"PL",
    "gn:dem":256,
    "gn:feature_class":"P",
    "gn:feature_code":"PPL",
    "gn:name":"Ochojec",
    "gn:population":0,
    "gn:timezone":"Europe/Warsaw",
    "iso:country":"PL",
    "wof:name":"Ochojec",
    "wof:placetype":"neighbourhood"
},
  "geometry": {"coordinates":[18.54299,50.16891],"type":"Point"}
}