{
  "type": "Feature",
  "properties": {
    "gn:admin1_code":"81.0",
    "gn:admin2_code":"2012.0",
    "gn:admin3_code":"201204.0",
    "gn:asciiname":"Pawlowka",
    "gn:cc2":"PL",
    "gn:country_code":"PL",
    "gn:dem":225,
    "gn:feature_class":"P",
    "gn:feature_code":"PPL",
    "gn:name":"Paw\u0142\u00f3wka",
    "gn:population":0,
    "gn:timezone":"Europe/Warsaw",
    "iso:country":"PL",
    "name:und_x_variant":[
        "Nowy Paw\u0142\u00f3wka"
    ],
    "wof:name":"Pawlowka",
    "wof:placetype":"locality"
},
  "geometry": {"coordinates":[22.77328,54.21376],"type":"Point"}
}