{
  "type": "Feature",
  "properties": {
    "gn:admin1_code":"75.0",
    "gn:admin2_code":"606.0",
    "gn:admin3_code":"60610.0",
    "gn:asciiname":"Maciejow",
    "gn:country_code":"PL",
    "gn:dem":223,
    "gn:feature_class":"P",
    "gn:feature_code":"PPL",
    "gn:name":"Maciej\u00f3w",
    "gn:population":0,
    "gn:timezone":"Europe/Warsaw",
    "iso:country":"PL",
    "name:fra_x_preferred":[
        "Maciej\u00f3w"
    ],
    "name:pol_x_preferred":[
        "Maciej\u00f3w"
    ],
    "name:ukr_x_preferred":[
        "\u041c\u0430\u0446\u0435\u044e\u0432"
    ],
    "wof:name":"Maciejow",
    "wof:placetype":"locality"
},
  "geometry": {"coordinates":[23.38131,50.98659],"type":"Point"}
}