{
  "type": "Feature",
  "properties": {
    "gn:admin1_code":"73.0",
    "gn:admin2_code":"414.0",
    "gn:admin3_code":"41408.0",
    "gn:asciiname":"Bagniewo",
    "gn:country_code":"PL",
    "gn:dem":94,
    "gn:feature_class":"P",
    "gn:feature_code":"PPL",
    "gn:name":"Bagniewo",
    "gn:population":0,
    "gn:timezone":"Europe/Warsaw",
    "iso:country":"PL",
    "wof:name":"Bagniewo",
    "wof:placetype":"locality"
},
  "geometry": {"coordinates":[18.23621,53.35653000000001],"type":"Point"}
}