{
  "type": "Feature",
  "properties": {
    "gn:admin1_code":"74.0",
    "gn:admin2_code":"1010.0",
    "gn:admin3_code":"101011.0",
    "gn:asciiname":"Swolszowice Duze",
    "gn:country_code":"PL",
    "gn:dem":182,
    "gn:feature_class":"P",
    "gn:feature_code":"PPL",
    "gn:name":"Swolszowice Du\u017ce",
    "gn:population":0,
    "gn:timezone":"Europe/Warsaw",
    "iso:country":"PL",
    "name:fra_x_preferred":[
        "Swolszewice Du\u017ce"
    ],
    "name:pol_x_preferred":[
        "Swolszewice Du\u017ce"
    ],
    "name:ukr_x_preferred":[
        "\u0421\u0432\u043e\u043b\u044c\u0448\u0435\u0432\u0456\u0446\u0435-\u0414\u0443\u0436\u0435"
    ],
    "name:und_x_variant":[
        "Swolszowice Du\u017ce"
    ],
    "wof:name":"Swolszowice Duze",
    "wof:placetype":"locality"
},
  "geometry": {"coordinates":[19.94742,51.46585],"type":"Point"}
}