{
  "type": "Feature",
  "properties": {
    "gn:admin1_code":"80.0",
    "gn:admin2_code":"1811.0",
    "gn:admin3_code":"181103.0",
    "gn:asciiname":"Zawada",
    "gn:country_code":"PL",
    "gn:dem":161,
    "gn:feature_class":"P",
    "gn:feature_code":"PPL",
    "gn:name":"Zawada",
    "gn:population":0,
    "gn:timezone":"Europe/Warsaw",
    "iso:country":"PL",
    "name:ceb_x_preferred":[
        "Zawada"
    ],
    "name:ces_x_preferred":[
        "Z\u00e1vada"
    ],
    "name:deu_x_preferred":[
        "Zawada"
    ],
    "name:fra_x_preferred":[
        "Zawada"
    ],
    "name:pol_x_preferred":[
        "Zawada"
    ],
    "name:slk_x_preferred":[
        "Z\u00e1vada"
    ],
    "wof:name":"Zawada",
    "wof:placetype":"neighbourhood"
},
  "geometry": {"coordinates":[21.32696,50.32581],"type":"Point"}
}