{
  "type": "Feature",
  "properties": {
    "gn:admin1_code":"78.0",
    "gn:admin2_code":"1434.0",
    "gn:admin3_code":"143408.0",
    "gn:asciiname":"Reczaje",
    "gn:country_code":"PL",
    "gn:dem":104,
    "gn:feature_class":"P",
    "gn:feature_code":"PPL",
    "gn:name":"R\u0119czaje",
    "gn:population":0,
    "gn:timezone":"Europe/Warsaw",
    "iso:country":"PL",
    "name:fra_x_preferred":[
        "Nowe R\u0119czaje"
    ],
    "name:pol_x_preferred":[
        "Nowe R\u0119czaje"
    ],
    "name:ukr_x_preferred":[
        "\u041d\u043e\u0432\u0435 \u0420\u0435\u043d\u0447\u0430\u0454"
    ],
    "name:und_x_variant":[
        "R\u0119czaje Nowe",
        "R\u0119czaje"
    ],
    "wof:name":"Reczaje",
    "wof:placetype":"locality"
},
  "geometry": {"coordinates":[21.356,52.33785],"type":"Point"}
}