{
  "type": "Feature",
  "properties": {
    "gn:admin1_code":"84.0",
    "gn:admin2_code":"2601.0",
    "gn:admin3_code":"260105.0",
    "gn:asciiname":"Janow",
    "gn:country_code":"PL",
    "gn:dem":180,
    "gn:feature_class":"P",
    "gn:feature_code":"PPL",
    "gn:name":"Jan\u00f3w",
    "gn:population":0,
    "gn:timezone":"Europe/Warsaw",
    "iso:country":"PL",
    "wof:name":"Janow",
    "wof:placetype":"locality"
},
  "geometry": {"coordinates":[20.8982,50.36543],"type":"Point"}
}