{
  "type": "Feature",
  "properties": {
    "gn:admin1_code":"85.0",
    "gn:admin2_code":"2814.0",
    "gn:admin3_code":"281403.0",
    "gn:asciiname":"Bzowiec",
    "gn:country_code":"PL",
    "gn:dem":112,
    "gn:feature_class":"P",
    "gn:feature_code":"PPL",
    "gn:name":"Bzowiec",
    "gn:population":0,
    "gn:timezone":"Europe/Warsaw",
    "iso:country":"PL",
    "name:und_x_variant":[
        "Beiswalde",
        "Bzowiec"
    ],
    "wof:name":"Bzowiec",
    "wof:placetype":"locality"
},
  "geometry": {"coordinates":[20.31121,54.01809],"type":"Point"}
}