{
  "type": "Feature",
  "properties": {
    "gn:admin1_code":"75.0",
    "gn:admin2_code":"607.0",
    "gn:admin3_code":"60702.0",
    "gn:asciiname":"Borow",
    "gn:country_code":"PL",
    "gn:dem":139,
    "gn:feature_class":"P",
    "gn:feature_code":"PPL",
    "gn:name":"Bor\u00f3w",
    "gn:population":0,
    "gn:timezone":"Europe/Warsaw",
    "iso:country":"PL",
    "name:ceb_x_preferred":[
        "Bor\u00f3w"
    ],
    "name:fra_x_preferred":[
        "Bor\u00f3w"
    ],
    "name:pol_x_preferred":[
        "Bor\u00f3w"
    ],
    "name:ukr_x_preferred":[
        "\u0411\u043e\u0440\u0443\u0432"
    ],
    "wof:name":"Borow",
    "wof:placetype":"locality"
},
  "geometry": {"coordinates":[21.91017,50.7966],"type":"Point"}
}