{
  "type": "Feature",
  "properties": {
    "gn:admin1_code":"78.0",
    "gn:admin2_code":"1415.0",
    "gn:admin3_code":"141504.0",
    "gn:asciiname":"Nogawki",
    "gn:country_code":"PL",
    "gn:dem":104,
    "gn:feature_class":"P",
    "gn:feature_code":"PPL",
    "gn:name":"Nogawki",
    "gn:population":0,
    "gn:timezone":"Europe/Warsaw",
    "iso:country":"PL",
    "name:fra_x_preferred":[
        "Nogawki"
    ],
    "name:pol_x_preferred":[
        "Nogawki"
    ],
    "name:ukr_x_preferred":[
        "\u041d\u043e\u0491\u0430\u0432\u043a\u0456"
    ],
    "wof:name":"Nogawki",
    "wof:placetype":"locality"
},
  "geometry": {"coordinates":[21.60841,52.94824000000001],"type":"Point"}
}