{
  "type": "Feature",
  "properties": {
    "iso:country":"PL",
    "name:eng_x_preferred":[
        "Zabianka-Wejhera-Jelitkowo-Tysiaclecia"
    ],
    "name:pol_x_preferred":[
        "\u017babianka-Wejhera-Jelitkowo-Tysi\u0105clecia"
    ],
    "wof:name":"Zabianka-Wejhera-Jelitkowo-Tysiaclecia",
    "wof:placetype":"neighbourhood"
},
  "geometry": {"coordinates":[18.58551824395617,54.42204091899967],"type":"Point"}
}