{
  "type": "Feature",
  "properties": {
    "gn:admin1_code":"73.0",
    "gn:admin2_code":"413.0",
    "gn:admin3_code":"41303.0",
    "gn:asciiname":"Szynwald",
    "gn:country_code":"PL",
    "gn:dem":117,
    "gn:feature_class":"P",
    "gn:feature_code":"PPL",
    "gn:name":"Szynwa\u0142d",
    "gn:population":0,
    "gn:timezone":"Europe/Warsaw",
    "iso:country":"PL",
    "name:pol_x_preferred":[
        "Szynwa\u0142d"
    ],
    "name:ukr_x_preferred":[
        "\u0428\u0438\u043d\u0432\u0430\u043b\u0434"
    ],
    "wof:name":"Szynwald",
    "wof:placetype":"locality"
},
  "geometry": {"coordinates":[17.61495,53.40343000000001],"type":"Point"}
}