{
  "type": "Feature",
  "properties": {
    "gn:admin1_code":"87.0",
    "gn:admin2_code":"3213.0",
    "gn:admin3_code":"321305.0",
    "gn:asciiname":"Lacko",
    "gn:country_code":"PL",
    "gn:dem":6,
    "gn:feature_class":"P",
    "gn:feature_code":"PPL",
    "gn:name":"\u0141acko",
    "gn:population":0,
    "gn:timezone":"Europe/Warsaw",
    "iso:country":"PL",
    "name:deu_x_preferred":[
        "\u0141\u0105cko"
    ],
    "name:pol_x_preferred":[
        "\u0141\u0105cko"
    ],
    "name:ukr_x_preferred":[
        "\u041b\u043e\u043d\u0446\u044c\u043a\u043e"
    ],
    "name:und_x_variant":[
        "\u0141acko"
    ],
    "name:vie_x_preferred":[
        "\u0141\u0105cko"
    ],
    "wof:name":"Lacko",
    "wof:placetype":"locality"
},
  "geometry": {"coordinates":[16.61091,54.51993],"type":"Point"}
}