{
  "type": "Feature",
  "properties": {
    "gn:admin1_code":"86.0",
    "gn:admin2_code":"3006.0",
    "gn:admin3_code":"300601.0",
    "gn:asciiname":"Lowecice",
    "gn:country_code":"PL",
    "gn:dem":113,
    "gn:feature_class":"P",
    "gn:feature_code":"PPL",
    "gn:name":"\u0141ow\u0119cice",
    "gn:population":0,
    "gn:timezone":"Europe/Warsaw",
    "iso:country":"PL",
    "name:fra_x_preferred":[
        "\u0141ow\u0119cice"
    ],
    "name:pol_x_preferred":[
        "\u0141ow\u0119cice"
    ],
    "name:ukr_x_preferred":[
        "\u041b\u043e\u0432\u0435\u043d\u0446\u0438\u0446\u0435"
    ],
    "name:und_x_variant":[
        "\u0141ow\u0119cice"
    ],
    "wof:name":"Lowecice",
    "wof:placetype":"locality"
},
  "geometry": {"coordinates":[17.30305,51.94306],"type":"Point"}
}