{
  "type": "Feature",
  "properties": {
    "gn:admin1_code":"76.0",
    "gn:admin2_code":"808.0",
    "gn:admin3_code":"80802.0",
    "gn:asciiname":"Kosobudz",
    "gn:country_code":"PL",
    "gn:dem":91,
    "gn:feature_class":"P",
    "gn:feature_code":"PPL",
    "gn:name":"Kosobudz",
    "gn:population":0,
    "gn:timezone":"Europe/Warsaw",
    "iso:country":"PL",
    "name:ceb_x_preferred":[
        "Kosobudz"
    ],
    "name:fra_x_preferred":[
        "Kosobudz"
    ],
    "name:pol_x_preferred":[
        "Kosobudz"
    ],
    "name:ukr_x_preferred":[
        "\u041a\u043e\u0441\u043e\u0431\u0443\u0434\u0437"
    ],
    "wof:name":"Kosobudz",
    "wof:placetype":"locality"
},
  "geometry": {"coordinates":[15.24492,52.23364],"type":"Point"}
}