{
  "type": "Feature",
  "properties": {
    "gn:admin1_code":"75.0",
    "gn:admin2_code":"611.0",
    "gn:admin3_code":"61107.0",
    "gn:asciiname":"Kierzkow",
    "gn:country_code":"PL",
    "gn:dem":161,
    "gn:feature_class":"P",
    "gn:feature_code":"PPL",
    "gn:name":"Kierzk\u00f3w",
    "gn:population":0,
    "gn:timezone":"Europe/Warsaw",
    "iso:country":"PL",
    "name:fra_x_preferred":[
        "Kierzk\u00f3w"
    ],
    "name:pol_x_preferred":[
        "Kierzk\u00f3w"
    ],
    "name:ukr_x_preferred":[
        "\u041a\u0435\u0436\u043a\u0443\u0432"
    ],
    "wof:name":"Kierzkow",
    "wof:placetype":"locality"
},
  "geometry": {"coordinates":[22.28028,51.88325],"type":"Point"}
}