{
  "type": "Feature",
  "properties": {
    "gn:admin1_code":"77.0",
    "gn:admin2_code":"1218.0",
    "gn:admin3_code":"121801.0",
    "gn:asciiname":"Targanica",
    "gn:country_code":"PL",
    "gn:dem":391,
    "gn:feature_class":"P",
    "gn:feature_code":"PPL",
    "gn:name":"Targanica",
    "gn:population":0,
    "gn:timezone":"Europe/Warsaw",
    "iso:country":"PL",
    "wof:name":"Targanica",
    "wof:placetype":"locality"
},
  "geometry": {"coordinates":[19.33333,49.81667],"type":"Point"}
}