{
  "type": "Feature",
  "properties": {
    "gn:gn_country":"PL",
    "gn:gn_fcode":"PPL",
    "gn:gn_pop":0,
    "iso:country":"PL",
    "name:ceb_x_preferred":[
        "Pola\u0144czyk"
    ],
    "name:deu_x_preferred":[
        "Pola\u0144czyk"
    ],
    "name:hun_x_preferred":[
        "Pola\u0144czyk"
    ],
    "name:nld_x_preferred":[
        "Pola\u0144czyk"
    ],
    "name:pol_x_preferred":[
        "Pola\u0144czyk"
    ],
    "name:ukr_x_preferred":[
        "\u041f\u043e\u043b\u044f\u043d\u0447\u0438\u043a"
    ],
    "name:unk_x_variant":[
        "Polany"
    ],
    "qs_pg:aaroncc":"PL",
    "qs_pg:gn_country":"PL",
    "qs_pg:gn_fcode":"PPL",
    "qs_pg:gn_pop":0,
    "qs_pg:name":"Pola\u0144czyk",
    "qs_pg:name_adm0":"Polska",
    "qs_pg:name_adm1":"Podkarpackie",
    "qs_pg:photos":16,
    "qs_pg:photos_1k":3,
    "qs_pg:photos_9k":1,
    "qs_pg:photos_9r":1,
    "qs_pg:photos_all":16,
    "qs_pg:photos_sr":1,
    "qs_pg:pop_sr":0,
    "qs_pg:qs_pg_placetype":"locality",
    "qs_pg:qs_pg_placetype_gp":"Town",
    "qs_pg:woe_adm0":23424923,
    "woe:adm0_id":23424923,
    "woe:name_adm0":"Polska",
    "woe:name_adm1":"Podkarpackie",
    "woe:placetype":"Town",
    "wof:name":"Pola\u0144czyk",
    "wof:placetype":"locality"
},
  "geometry": {"coordinates":[21.56838,49.49304],"type":"Point"}
}