{
  "type": "Feature",
  "properties": {
    "gn:admin1_code":"80.0",
    "gn:admin2_code":"1807.0",
    "gn:admin3_code":"180709.0",
    "gn:asciiname":"Podlesie",
    "gn:country_code":"PL",
    "gn:dem":317,
    "gn:feature_class":"P",
    "gn:feature_code":"PPL",
    "gn:name":"Podlesie",
    "gn:population":0,
    "gn:timezone":"Europe/Warsaw",
    "iso:country":"PL",
    "name:ceb_x_preferred":[
        "Podlesie"
    ],
    "name:deu_x_preferred":[
        "Podlesie"
    ],
    "name:fra_x_preferred":[
        "Podlesie"
    ],
    "name:nld_x_preferred":[
        "Podlesie"
    ],
    "name:pol_x_preferred":[
        "Podlesie"
    ],
    "name:ukr_x_preferred":[
        "\u041f\u043e\u0434\u043b\u0435\u0441\u0435"
    ],
    "wof:name":"Podlesie",
    "wof:placetype":"locality"
},
  "geometry": {"coordinates":[21.68333,49.81667],"type":"Point"}
}