{
  "type": "Feature",
  "properties": {
    "gn:admin1_code":"85.0",
    "gn:admin2_code":"2802.0",
    "gn:admin3_code":"280205.0",
    "gn:asciiname":"Gajle",
    "gn:country_code":"PL",
    "gn:dem":102,
    "gn:feature_class":"P",
    "gn:feature_code":"PPL",
    "gn:name":"Gajle",
    "gn:population":0,
    "gn:timezone":"Europe/Warsaw",
    "iso:country":"PL",
    "name:fra_x_preferred":[
        "Gajle"
    ],
    "name:pol_x_preferred":[
        "Gajle"
    ],
    "name:und_x_variant":[
        "Gayl"
    ],
    "wof:name":"Gajle",
    "wof:placetype":"locality"
},
  "geometry": {"coordinates":[20.0202,54.30781],"type":"Point"}
}