{
  "type": "Feature",
  "properties": {
    "gn:admin1_code":"84.0",
    "gn:asciiname":"Kolonia Szczerbacka",
    "gn:country_code":"PL",
    "gn:dem":301,
    "gn:feature_class":"P",
    "gn:feature_code":"PPL",
    "gn:name":"Kolonia Szczerbacka",
    "gn:population":0,
    "gn:timezone":"Europe/Warsaw",
    "iso:country":"PL",
    "wof:name":"Kolonia Szczerbacka",
    "wof:placetype":"locality"
},
  "geometry": {"coordinates":[20.56913,51.24448],"type":"Point"}
}