{
  "type": "Feature",
  "properties": {
    "gn:admin1_code":"84.0",
    "gn:asciiname":"Kolonia Szczerbacka",
    "gn:country_code":"PL",
    "gn:dem":301,
    "gn:feature_class":"P",
    "gn:feature_code":"PPL",
    "gn:name":"Kolonia Szczerbacka",
    "gn:population":0,
    "gn:timezone":"Europe/Warsaw",
    "iso:country":"PL",
    "name:fra_x_preferred":[
        "Kolonia Szczerbacka"
    ],
    "name:pol_x_preferred":[
        "Kolonia Szczerbacka"
    ],
    "name:szl_x_preferred":[
        "Szczerbacko Kol\u016f\u0144ijo"
    ],
    "name:ukr_x_preferred":[
        "\u041a\u043e\u043b\u044c\u043e\u043d\u0456\u044f-\u0429\u0435\u0440\u0431\u0430\u0446\u044c\u043a\u0430"
    ],
    "wof:name":"Kolonia Szczerbacka",
    "wof:placetype":"locality"
},
  "geometry": {"coordinates":[20.56913,51.24448],"type":"Point"}
}