{
  "type": "Feature",
  "properties": {
    "gn:admin1_code":"78.0",
    "gn:admin2_code":"1402.0",
    "gn:admin3_code":"140207.0",
    "gn:asciiname":"Sosnowo",
    "gn:country_code":"PL",
    "gn:dem":132,
    "gn:feature_class":"P",
    "gn:feature_code":"PPL",
    "gn:name":"Sosnowo",
    "gn:population":0,
    "gn:timezone":"Europe/Warsaw",
    "iso:country":"PL",
    "name:fra_x_preferred":[
        "Sosnowo"
    ],
    "name:pol_x_preferred":[
        "Sosnowo"
    ],
    "name:ukr_x_preferred":[
        "\u0421\u043e\u0441\u043d\u043e\u0432\u043e"
    ],
    "wof:name":"Sosnowo",
    "wof:placetype":"locality"
},
  "geometry": {"coordinates":[20.77158,52.93522],"type":"Point"}
}