{
  "type": "Feature",
  "properties": {
    "gn:admin1_code":"72.0",
    "gn:admin2_code":"219.0",
    "gn:admin3_code":"21904.0",
    "gn:asciiname":"Tomkawa",
    "gn:country_code":"PL",
    "gn:dem":233,
    "gn:feature_class":"P",
    "gn:feature_code":"PPL",
    "gn:name":"Tomkawa",
    "gn:population":0,
    "gn:timezone":"Europe/Warsaw",
    "iso:country":"PL",
    "wof:name":"Tomkawa",
    "wof:placetype":"locality"
},
  "geometry": {"coordinates":[16.45956,50.87859],"type":"Point"}
}