{
  "type": "Feature",
  "properties": {
    "gn:admin1_code":"74.0",
    "gn:admin2_code":"1005.0",
    "gn:admin3_code":"100510.0",
    "gn:asciiname":"Bakow Dolny",
    "gn:cc2":"PL",
    "gn:country_code":"PL",
    "gn:dem":97,
    "gn:feature_class":"P",
    "gn:feature_code":"PPL",
    "gn:name":"B\u0105k\u00f3w Dolny",
    "gn:population":0,
    "gn:timezone":"Europe/Warsaw",
    "iso:country":"PL",
    "name:fra_x_preferred":[
        "B\u0105k\u00f3w Dolny"
    ],
    "name:pol_x_preferred":[
        "B\u0105k\u00f3w Dolny"
    ],
    "name:ukr_x_preferred":[
        "\u0411\u043e\u043d\u043a\u0443\u0432-\u0414\u043e\u043b\u044c\u043d\u0438"
    ],
    "name:und_x_variant":[
        "B\u0105k\u00f3w"
    ],
    "wof:name":"Bakow Dolny",
    "wof:placetype":"locality"
},
  "geometry": {"coordinates":[19.71737000000001,52.15414000000001],"type":"Point"}
}