{
  "type": "Feature",
  "properties": {
    "gn:admin1_code":"74.0",
    "gn:admin2_code":"1011.0",
    "gn:admin3_code":"101101.0",
    "gn:asciiname":"Domaniewek",
    "gn:country_code":"PL",
    "gn:dem":127,
    "gn:feature_class":"P",
    "gn:feature_code":"PPL",
    "gn:name":"Domaniewek",
    "gn:population":0,
    "gn:timezone":"Europe/Warsaw",
    "iso:country":"PL",
    "wof:name":"Domaniewek",
    "wof:placetype":"locality"
},
  "geometry": {"coordinates":[19.08206,51.93978],"type":"Point"}
}