{
  "type": "Feature",
  "properties": {
    "gn:admin1_code":"78.0",
    "gn:admin2_code":"1401.0",
    "gn:admin3_code":"140106.0",
    "gn:asciiname":"Romanow",
    "gn:country_code":"PL",
    "gn:dem":176,
    "gn:feature_class":"P",
    "gn:feature_code":"PPL",
    "gn:name":"Roman\u00f3w",
    "gn:population":0,
    "gn:timezone":"Europe/Warsaw",
    "iso:country":"PL",
    "name:fra_x_preferred":[
        "Roman\u00f3w"
    ],
    "name:pol_x_preferred":[
        "Roman\u00f3w"
    ],
    "name:ukr_x_preferred":[
        "\u0420\u043e\u043c\u0430\u043d\u0443\u0432"
    ],
    "name:und_x_variant":[
        "Roman\u00f3w"
    ],
    "wof:name":"Romanow",
    "wof:placetype":"locality"
},
  "geometry": {"coordinates":[20.80842,51.58342],"type":"Point"}
}