{
  "type": "Feature",
  "properties": {
    "gn:admin1_code":"76",
    "gn:admin2_code":"0808",
    "gn:admin3_code":"80803.0",
    "gn:asciiname":"Przetocznicki Mlyn",
    "gn:country_code":"PL",
    "gn:dem":64,
    "gn:feature_class":"P",
    "gn:feature_code":"PPL",
    "gn:name":"Przetocznicki M\u0142yn",
    "gn:population":0,
    "gn:timezone":"Europe/Warsaw",
    "iso:country":"PL",
    "name:fra_x_preferred":[
        "Przetocznicki M\u0142yn"
    ],
    "name:pol_x_preferred":[
        "Przetocznicki M\u0142yn"
    ],
    "wof:name":"Przetocznicki Mlyn",
    "wof:placetype":"locality"
},
  "geometry": {"coordinates":[15.42063,52.12369],"type":"Point"}
}