{
  "type": "Feature",
  "properties": {
    "gn:admin1_code":"74.0",
    "gn:admin2_code":"1002.0",
    "gn:admin3_code":"100205.0",
    "gn:asciiname":"Wyreby Siemienickie",
    "gn:country_code":"PL",
    "gn:dem":105,
    "gn:feature_class":"P",
    "gn:feature_code":"PPL",
    "gn:name":"Wyr\u0119by Siemienickie",
    "gn:population":0,
    "gn:timezone":"Europe/Warsaw",
    "iso:country":"PL",
    "name:und_x_variant":[
        "Wyr\u0119by",
        "Wyr\u0119by Siemienickie"
    ],
    "wof:name":"Wyreby Siemienickie",
    "wof:placetype":"locality"
},
  "geometry": {"coordinates":[19.40144,52.15],"type":"Point"}
}