{
  "type": "Feature",
  "properties": {
    "gn:admin1_code":"73.0",
    "gn:admin2_code":"405.0",
    "gn:admin3_code":"40503.0",
    "gn:asciiname":"Pocwiardowo",
    "gn:country_code":"PL",
    "gn:dem":94,
    "gn:feature_class":"P",
    "gn:feature_code":"PPL",
    "gn:name":"Po\u0107wiardowo",
    "gn:population":0,
    "gn:timezone":"Europe/Warsaw",
    "iso:country":"PL",
    "wof:name":"Pocwiardowo",
    "wof:placetype":"locality"
},
  "geometry": {"coordinates":[19.01995,53.14678000000001],"type":"Point"}
}