{
  "type": "Feature",
  "properties": {
    "iso:country":"PL",
    "name:azb_x_preferred":[
        "\u0642\u0645\u06cc\u0646\u0627 \u0632\u0642\u06cc\u0698"
    ],
    "name:bel_x_preferred":[
        "\u0417\u0433\u0435\u0436"
    ],
    "name:deu_x_preferred":[
        "Zgierz"
    ],
    "name:eus_x_preferred":[
        "Zgierz landa-udalerria"
    ],
    "name:fas_x_preferred":[
        "\u06af\u0645\u06cc\u0646\u0627 \u0632\u06af\u06cc\u0698"
    ],
    "name:fra_x_preferred":[
        "Zgierz"
    ],
    "name:ita_x_preferred":[
        "Zgierz"
    ],
    "name:nld_x_preferred":[
        "Zgierz"
    ],
    "name:pol_x_preferred":[
        "Zgierz"
    ],
    "name:rus_x_preferred":[
        "\u0417\u0433\u0435\u0436"
    ],
    "name:slk_x_preferred":[
        "Gmina Zgierz"
    ],
    "name:tha_x_preferred":[
        "\u0e40\u0e17\u0e28\u0e1a\u0e32\u0e25\u0e0b\u0e01\u0e35\u0e41\u0e22\u0e0a"
    ],
    "name:ukr_x_preferred":[
        "\u0413\u043c\u0456\u043d\u0430 \u0417\u0491\u0435\u0436"
    ],
    "name:war_x_preferred":[
        "Gmina Zgierz"
    ],
    "qs_pg:aaroncc":"PL",
    "qs_pg:name":"Gmina Zgierz",
    "qs_pg:name_adm0":"Polska",
    "qs_pg:name_adm1":"\u0141\u00f3dzkie",
    "qs_pg:photos":2,
    "qs_pg:photos_1k":1,
    "qs_pg:photos_9k":1,
    "qs_pg:photos_9r":4,
    "qs_pg:photos_all":164,
    "qs_pg:photos_sr":1,
    "qs_pg:pop_sr":0,
    "qs_pg:qs_pg_placetype":"localadmin",
    "qs_pg:qs_pg_placetype_gp":"LocalAdmin",
    "qs_pg:woe_adm0":23424923,
    "woe:adm0_id":23424923,
    "woe:name_adm0":"Polska",
    "woe:name_adm1":"\u0141\u00f3dzkie",
    "woe:placetype":"LocalAdmin",
    "wof:name":"Gmina Zgierz",
    "wof:placetype":"localadmin"
},
  "geometry": {"coordinates":[19.433205,51.872122],"type":"Point"}
}