{
  "type": "Feature",
  "properties": {
    "gn:admin1_code":"75.0",
    "gn:admin2_code":"601.0",
    "gn:admin3_code":"60116.0",
    "gn:asciiname":"Zuki",
    "gn:country_code":"PL",
    "gn:dem":133,
    "gn:feature_class":"P",
    "gn:feature_code":"PPL",
    "gn:name":"\u017buki",
    "gn:population":0,
    "gn:timezone":"Europe/Warsaw",
    "iso:country":"PL",
    "name:ceb_x_preferred":[
        "Zuki"
    ],
    "name:fra_x_preferred":[
        "\u017buki"
    ],
    "name:lit_x_preferred":[
        "\u017dukai"
    ],
    "name:pol_x_preferred":[
        "\u017buki"
    ],
    "name:ukr_x_preferred":[
        "\u0416\u0443\u043a\u0456"
    ],
    "wof:name":"Zuki",
    "wof:placetype":"locality"
},
  "geometry": {"coordinates":[23.6582,52.02345],"type":"Point"}
}