{
  "type": "Feature",
  "properties": {
    "gn:admin1_code":"82.0",
    "gn:admin2_code":"2201.0",
    "gn:admin3_code":"220104.0",
    "gn:asciiname":"Radusz",
    "gn:country_code":"PL",
    "gn:dem":119,
    "gn:feature_class":"P",
    "gn:feature_code":"PPL",
    "gn:name":"Radusz",
    "gn:population":0,
    "gn:timezone":"Europe/Warsaw",
    "iso:country":"PL",
    "name:ceb_x_preferred":[
        "Radusz"
    ],
    "name:csb_x_preferred":[
        "Redusz"
    ],
    "name:pol_x_preferred":[
        "Radusz"
    ],
    "name:ukr_x_preferred":[
        "\u0420\u0430\u0434\u0443\u0448"
    ],
    "wof:name":"Radusz",
    "wof:placetype":"locality"
},
  "geometry": {"coordinates":[17.22321,54.24952],"type":"Point"}
}