{
  "type": "Feature",
  "properties": {
    "gn:admin1_code":"78.0",
    "gn:admin2_code":"1408.0",
    "gn:admin3_code":"140804.0",
    "gn:asciiname":"Zegrze",
    "gn:country_code":"PL",
    "gn:dem":96,
    "gn:feature_class":"P",
    "gn:feature_code":"PPL",
    "gn:name":"Zegrze",
    "gn:population":0,
    "gn:timezone":"Europe/Warsaw",
    "iso:country":"PL",
    "name:azb_x_preferred":[
        "\u0632\u0642\u0698\u0647"
    ],
    "name:ceb_x_preferred":[
        "Zegrze"
    ],
    "name:deu_x_preferred":[
        "Zegrze"
    ],
    "name:epo_x_preferred":[
        "Zegrze"
    ],
    "name:fas_x_preferred":[
        "\u0632\u06af\u0698\u0647"
    ],
    "name:fra_x_preferred":[
        "Zegrze"
    ],
    "name:ita_x_preferred":[
        "Zegrze"
    ],
    "name:nld_x_preferred":[
        "Zegrze"
    ],
    "name:pol_x_preferred":[
        "Zegrze"
    ],
    "name:ukr_x_preferred":[
        "\u0417\u0435\u0491\u0436\u0435"
    ],
    "wof:name":"Zegrze",
    "wof:placetype":"locality"
},
  "geometry": {"coordinates":[21.03624,52.46291],"type":"Point"}
}