{
  "type": "Feature",
  "properties": {
    "gn:admin1_code":"86.0",
    "gn:admin2_code":"3002.0",
    "gn:admin3_code":"300208.0",
    "gn:asciiname":"Wielen Polnocny",
    "gn:country_code":"PL",
    "gn:dem":42,
    "gn:feature_class":"P",
    "gn:feature_code":"PPL",
    "gn:name":"Wiele\u0144 P\u00f3\u0142nocny",
    "gn:population":0,
    "gn:timezone":"Europe/Warsaw",
    "iso:country":"PL",
    "wof:name":"Wielen Polnocny",
    "wof:placetype":"neighbourhood"
},
  "geometry": {"coordinates":[16.18303,52.91565],"type":"Point"}
}