{
  "type": "Feature",
  "properties": {
    "gn:admin1_code":"80.0",
    "gn:admin2_code":"1808.0",
    "gn:admin3_code":"180802.0",
    "gn:asciiname":"Moczary",
    "gn:country_code":"PL",
    "gn:dem":213,
    "gn:feature_class":"P",
    "gn:feature_code":"PPL",
    "gn:name":"Moczary",
    "gn:population":0,
    "gn:timezone":"Europe/Warsaw",
    "iso:country":"PL",
    "wof:name":"Moczary",
    "wof:placetype":"locality"
},
  "geometry": {"coordinates":[22.38305,50.18276],"type":"Point"}
}