{
  "type": "Feature",
  "properties": {
    "gn:admin1_code":"84.0",
    "gn:admin2_code":"2603.0",
    "gn:admin3_code":"260301.0",
    "gn:asciiname":"Usciszowice",
    "gn:country_code":"PL",
    "gn:dem":224,
    "gn:feature_class":"P",
    "gn:feature_code":"PPL",
    "gn:name":"U\u015bciszowice",
    "gn:population":0,
    "gn:timezone":"Europe/Warsaw",
    "iso:country":"PL",
    "name:pol_x_preferred":[
        "U\u015bciszowice"
    ],
    "name:ukr_x_preferred":[
        "\u0423\u0441\u0446\u0438\u0448\u043e\u0432\u0456\u0446\u0435"
    ],
    "wof:name":"Usciszowice",
    "wof:placetype":"locality"
},
  "geometry": {"coordinates":[20.65086,50.23194],"type":"Point"}
}