{
  "type": "Feature",
  "properties": {
    "gn:admin1_code":"75.0",
    "gn:admin2_code":"605.0",
    "gn:admin3_code":"60507.0",
    "gn:asciiname":"Stojeszyn Zarajec",
    "gn:country_code":"PL",
    "gn:dem":251,
    "gn:feature_class":"P",
    "gn:feature_code":"PPL",
    "gn:name":"Stojeszyn Zarajec",
    "gn:population":0,
    "gn:timezone":"Europe/Warsaw",
    "iso:country":"PL",
    "wof:name":"Stojeszyn Zarajec",
    "wof:placetype":"locality"
},
  "geometry": {"coordinates":[22.28162,50.79142],"type":"Point"}
}