{
  "type": "Feature",
  "properties": {
    "iso:country":"PL",
    "name:bul_x_preferred":[
        "\u041a\u0440\u043e\u0441\u043d\u043e \u041e\u0434\u0436\u0430\u043d\u0441\u043a\u0435"
    ],
    "name:ceb_x_preferred":[
        "Krosno Odrza\u0144skie"
    ],
    "name:dan_x_preferred":[
        "Krosno Odrza\u0144skie"
    ],
    "name:deu_x_preferred":[
        "Krosno Odrza\u0144skie"
    ],
    "name:dsb_x_preferred":[
        "Krosno"
    ],
    "name:epo_x_preferred":[
        "Krosno Odrza\u0144skie"
    ],
    "name:fra_x_preferred":[
        "Krosno Odrza\u0144skie"
    ],
    "name:ind_x_preferred":[
        "Krosno Odrza\u0144skie"
    ],
    "name:jav_x_preferred":[
        "Krosno Odrza\u0144skie"
    ],
    "name:kor_x_preferred":[
        "\ud06c\ub85c\uc2a4\ub178\uc624\uc794\uc2a4\ud0a4\uc5d0"
    ],
    "name:lav_x_preferred":[
        "Krosno Od\u017ea\u0146ske"
    ],
    "name:msa_x_preferred":[
        "Krosno Odrza\u0144skie"
    ],
    "name:nld_x_preferred":[
        "Krosno Odrza\u0144skie"
    ],
    "name:pol_x_preferred":[
        "Krosno Odrza\u0144skie"
    ],
    "name:por_x_preferred":[
        "Krosno Odrza\u0144skie"
    ],
    "name:ron_x_preferred":[
        "Krosno Odrza\u0144skie"
    ],
    "name:rus_x_preferred":[
        "\u041a\u0440\u043e\u0441\u043d\u043e-\u041e\u0434\u0436\u0430\u043d\u044c\u0441\u043a\u0435"
    ],
    "name:slk_x_preferred":[
        "Krosno Odrza\u0144skie"
    ],
    "name:spa_x_preferred":[
        "Krosno Odrza\u0144skie"
    ],
    "name:srp_x_preferred":[
        "\u041a\u0440\u043e\u0441\u043d\u043e \u041e\u0434\u0436\u0430\u045a\u0441\u043a\u0458\u0435"
    ],
    "name:swe_x_preferred":[
        "Krosno Odrza\u0144skie"
    ],
    "name:szl_x_preferred":[
        "Uodrza\u0144ske Krosno"
    ],
    "name:ukr_x_preferred":[
        "\u041a\u0440\u043e\u0441\u043d\u043e-\u041e\u0434\u0436\u0430\u043d\u0441\u044c\u043a\u0435"
    ],
    "name:vie_x_preferred":[
        "Krosno Odrza\u0144skie"
    ],
    "name:war_x_preferred":[
        "Krosno Odrza\u0144skie"
    ],
    "name:zho_x_preferred":[
        "\u5967\u5f97\u6cb3\u7554\u514b\u7f85\u65af\u8afe"
    ],
    "qs_pg:aaroncc":"PL",
    "qs_pg:name":"Krosno Odrza\u0144skie",
    "qs_pg:name_adm0":"Polska",
    "qs_pg:name_adm1":"Lubuskie",
    "qs_pg:photos":1,
    "qs_pg:photos_1k":1,
    "qs_pg:photos_9k":1,
    "qs_pg:photos_9r":2,
    "qs_pg:photos_all":55,
    "qs_pg:photos_sr":1,
    "qs_pg:pop_sr":0,
    "qs_pg:qs_pg_placetype":"localadmin",
    "qs_pg:qs_pg_placetype_gp":"LocalAdmin",
    "qs_pg:woe_adm0":23424923,
    "woe:adm0_id":23424923,
    "woe:name_adm0":"Polska",
    "woe:name_adm1":"Lubuskie",
    "woe:placetype":"LocalAdmin",
    "wof:name":"Krosno Odrza\u0144skie",
    "wof:placetype":"localadmin"
},
  "geometry": {"coordinates":[15.098272,52.048373],"type":"Point"}
}