{
  "type": "Feature",
  "properties": {
    "gn:admin1_code":"78.0",
    "gn:admin2_code":"1415.0",
    "gn:admin3_code":"141501.0",
    "gn:asciiname":"Gaczyska",
    "gn:country_code":"PL",
    "gn:dem":116,
    "gn:feature_class":"P",
    "gn:feature_code":"PPL",
    "gn:name":"Gaczyska",
    "gn:population":0,
    "gn:timezone":"Europe/Warsaw",
    "iso:country":"PL",
    "name:ceb_x_preferred":[
        "Gaczyska"
    ],
    "name:fra_x_preferred":[
        "Gaczyska"
    ],
    "name:pol_x_preferred":[
        "Gaczyska"
    ],
    "name:ukr_x_preferred":[
        "\u0490\u0430\u0447\u0438\u0441\u044c\u043a\u0430"
    ],
    "wof:name":"Gaczyska",
    "wof:placetype":"locality"
},
  "geometry": {"coordinates":[21.2281,53.14143000000001],"type":"Point"}
}