{
  "type": "Feature",
  "properties": {
    "gn:admin1_code":"80.0",
    "gn:admin2_code":"1806.0",
    "gn:admin3_code":"180606.0",
    "gn:asciiname":"Koloniska",
    "gn:country_code":"PL",
    "gn:dem":173,
    "gn:feature_class":"P",
    "gn:feature_code":"PPL",
    "gn:name":"Koloniska",
    "gn:population":0,
    "gn:timezone":"Europe/Warsaw",
    "iso:country":"PL",
    "wof:name":"Koloniska",
    "wof:placetype":"locality"
},
  "geometry": {"coordinates":[21.92582,50.40316],"type":"Point"}
}