{
  "type": "Feature",
  "properties": {
    "gn:admin1_code":"80.0",
    "gn:admin2_code":"1815.0",
    "gn:admin3_code":"181504.0",
    "gn:asciiname":"Szkodna",
    "gn:country_code":"PL",
    "gn:dem":335,
    "gn:feature_class":"P",
    "gn:feature_code":"PPL",
    "gn:name":"Szkodna",
    "gn:population":0,
    "gn:timezone":"Europe/Warsaw",
    "iso:country":"PL",
    "name:pol_x_preferred":[
        "Szkodna"
    ],
    "name:ukr_x_preferred":[
        "\u0428\u043a\u043e\u0434\u043d\u0430"
    ],
    "wof:name":"Szkodna",
    "wof:placetype":"locality"
},
  "geometry": {"coordinates":[21.64135,49.97816],"type":"Point"}
}