{
  "type": "Feature",
  "properties": {
    "gn:admin1_code":"86.0",
    "gn:admin2_code":"3064.0",
    "gn:admin3_code":"306401.0",
    "gn:asciiname":"Wola",
    "gn:country_code":"PL",
    "gn:dem":91,
    "gn:feature_class":"P",
    "gn:feature_code":"PPL",
    "gn:name":"Wola",
    "gn:population":0,
    "gn:timezone":"Europe/Warsaw",
    "iso:country":"PL",
    "name:ceb_x_preferred":[
        "Wola"
    ],
    "name:ces_x_preferred":[
        "Wola"
    ],
    "name:deu_x_preferred":[
        "Wola"
    ],
    "name:est_x_preferred":[
        "Wola"
    ],
    "name:fra_x_preferred":[
        "Wola"
    ],
    "name:ita_x_preferred":[
        "Wola"
    ],
    "name:nld_x_preferred":[
        "Wola"
    ],
    "name:pol_x_preferred":[
        "Wola"
    ],
    "name:por_x_preferred":[
        "Wola"
    ],
    "name:rus_x_preferred":[
        "\u0412\u043e\u043b\u044f"
    ],
    "name:slk_x_preferred":[
        "Wola"
    ],
    "name:spa_x_preferred":[
        "Wola"
    ],
    "name:swe_x_preferred":[
        "Wola"
    ],
    "name:ukr_x_preferred":[
        "\u0412\u043e\u043b\u044f"
    ],
    "name:vie_x_preferred":[
        "Wola"
    ],
    "name:zho_x_preferred":[
        "\u6c83\u62c9\u5340"
    ],
    "wof:name":"Wola",
    "wof:placetype":"locality"
},
  "geometry": {"coordinates":[16.86256,52.42396],"type":"Point"}
}