{
  "type": "Feature",
  "properties": {
    "gn:admin1_code":"74.0",
    "gn:admin2_code":"1001.0",
    "gn:admin3_code":"100108.0",
    "gn:asciiname":"Kurow",
    "gn:country_code":"PL",
    "gn:dem":183,
    "gn:feature_class":"P",
    "gn:feature_code":"PPL",
    "gn:name":"Kur\u00f3w",
    "gn:population":0,
    "gn:timezone":"Europe/Warsaw",
    "iso:country":"PL",
    "wof:name":"Kurow",
    "wof:placetype":"locality"
},
  "geometry": {"coordinates":[19.1492,51.45],"type":"Point"}
}