{
  "type": "Feature",
  "properties": {
    "gn:admin1_code":"78.0",
    "gn:admin2_code":"1401.0",
    "gn:admin3_code":"140105.0",
    "gn:asciiname":"Male Boze",
    "gn:country_code":"PL",
    "gn:dem":118,
    "gn:feature_class":"P",
    "gn:feature_code":"PPL",
    "gn:name":"Ma\u0142e Bo\u017ce",
    "gn:population":0,
    "gn:timezone":"Europe/Warsaw",
    "iso:country":"PL",
    "name:fra_x_preferred":[
        "Ma\u0142e Bo\u017ce"
    ],
    "name:pol_x_preferred":[
        "Ma\u0142e Bo\u017ce"
    ],
    "name:ukr_x_preferred":[
        "\u041c\u0430\u043b\u0435 \u0411\u043e\u0436\u0435"
    ],
    "wof:name":"Male Boze",
    "wof:placetype":"locality"
},
  "geometry": {"coordinates":[21.1298,51.68128],"type":"Point"}
}