{
  "type": "Feature",
  "properties": {
    "gn:admin1_code":"85.0",
    "gn:admin2_code":"2816.0",
    "gn:admin3_code":"281601.0",
    "gn:asciiname":"Skarzyn",
    "gn:country_code":"PL",
    "gn:dem":145,
    "gn:feature_class":"P",
    "gn:feature_code":"PPL",
    "gn:name":"Skar\u017cyn",
    "gn:population":0,
    "gn:timezone":"Europe/Warsaw",
    "iso:country":"PL",
    "name:und_x_variant":[
        "Richtenberg",
        "Skarzinnen",
        "Skarszyny",
        "Skarzyn"
    ],
    "wof:name":"Skarzyn",
    "wof:placetype":"locality"
},
  "geometry": {"coordinates":[22.22345,53.61237],"type":"Point"}
}