{
  "type": "Feature",
  "properties": {
    "gn:admin1_code":"86.0",
    "gn:admin2_code":"3002.0",
    "gn:admin3_code":"300202.0",
    "gn:asciiname":"Pianowka",
    "gn:country_code":"PL",
    "gn:dem":42,
    "gn:feature_class":"P",
    "gn:feature_code":"PPL",
    "gn:name":"Pia\u0144owka",
    "gn:population":0,
    "gn:timezone":"Europe/Warsaw",
    "iso:country":"PL",
    "name:und_x_variant":[
        "Pia\u0144owka"
    ],
    "wof:name":"Pianowka",
    "wof:placetype":"locality"
},
  "geometry": {"coordinates":[16.50187,52.88392],"type":"Point"}
}