{
  "type": "Feature",
  "properties": {
    "gn:admin1_code":"87.0",
    "gn:admin2_code":"3205.0",
    "gn:admin3_code":"320501.0",
    "gn:asciiname":"Bielikowo",
    "gn:country_code":"PL",
    "gn:dem":15,
    "gn:feature_class":"P",
    "gn:feature_code":"PPL",
    "gn:name":"Bielikowo",
    "gn:population":0,
    "gn:timezone":"Europe/Warsaw",
    "iso:country":"PL",
    "name:ceb_x_preferred":[
        "Bielikowo"
    ],
    "name:nld_x_preferred":[
        "Bielikowo"
    ],
    "name:pol_x_preferred":[
        "Bielikowo"
    ],
    "name:ukr_x_preferred":[
        "\u0411\u0435\u043b\u0456\u043a\u043e\u0432\u043e"
    ],
    "name:vie_x_preferred":[
        "Bielikowo"
    ],
    "wof:name":"Bielikowo",
    "wof:placetype":"locality"
},
  "geometry": {"coordinates":[15.3069,53.98797],"type":"Point"}
}