{
  "type": "Feature",
  "properties": {
    "gn:admin1_code":"78.0",
    "gn:admin2_code":"1402.0",
    "gn:admin3_code":"140207.0",
    "gn:asciiname":"Wolka Laniecka",
    "gn:country_code":"PL",
    "gn:dem":120,
    "gn:feature_class":"P",
    "gn:feature_code":"PPL",
    "gn:name":"W\u00f3lka \u0141ani\u0119cka",
    "gn:population":0,
    "gn:timezone":"Europe/Warsaw",
    "iso:country":"PL",
    "name:fra_x_preferred":[
        "W\u00f3lka \u0141ani\u0119cka"
    ],
    "name:pol_x_preferred":[
        "W\u00f3lka \u0141ani\u0119cka"
    ],
    "name:spa_x_preferred":[
        "W\u00f3lka \u0141ani\u0119cka"
    ],
    "name:ukr_x_preferred":[
        "\u0412\u0443\u043b\u044c\u043a\u0430-\u041b\u0430\u043d\u0435\u043d\u0446\u044c\u043a\u0430"
    ],
    "name:und_x_variant":[
        "W\u00f3lka \u0141ami\u0119cka",
        "W\u00f3lka \u0141ani\u0119cka"
    ],
    "wof:name":"Wolka Laniecka",
    "wof:placetype":"locality"
},
  "geometry": {"coordinates":[20.79427,52.90473000000001],"type":"Point"}
}