{
  "type": "Feature",
  "properties": {
    "gn:admin1_code":"75.0",
    "gn:admin2_code":"606.0",
    "gn:admin3_code":"60602.0",
    "gn:asciiname":"Dziecinin",
    "gn:country_code":"PL",
    "gn:dem":211,
    "gn:feature_class":"P",
    "gn:feature_code":"PPL",
    "gn:name":"Dziecinin",
    "gn:population":0,
    "gn:timezone":"Europe/Warsaw",
    "iso:country":"PL",
    "name:azb_x_preferred":[
        "\u062c\u0686\u06cc\u0646\u0642\u0646"
    ],
    "name:fas_x_preferred":[
        "\u062c\u0686\u06cc\u0646\u06af\u0646"
    ],
    "name:fra_x_preferred":[
        "Dziecinin"
    ],
    "name:pol_x_preferred":[
        "Dziecinin"
    ],
    "name:ukr_x_preferred":[
        "\u0414\u0437\u0435\u0446\u0438\u043d\u0456\u043d"
    ],
    "name:und_x_variant":[
        "Kolonia Dziecinin",
        "Dziecinin"
    ],
    "wof:name":"Dziecinin",
    "wof:placetype":"locality"
},
  "geometry": {"coordinates":[23.00664,51.07364000000001],"type":"Point"}
}