{
  "type": "Feature",
  "properties": {
    "gn:admin1_code":"80.0",
    "gn:admin2_code":"1803.0",
    "gn:admin3_code":"180302.0",
    "gn:asciiname":"Nawsie Brzosteckie",
    "gn:country_code":"PL",
    "gn:dem":232,
    "gn:feature_class":"P",
    "gn:feature_code":"PPL",
    "gn:name":"Nawsie Brzosteckie",
    "gn:population":0,
    "gn:timezone":"Europe/Warsaw",
    "iso:country":"PL",
    "name:ceb_x_preferred":[
        "Nawsie Brzosteckie"
    ],
    "name:nld_x_preferred":[
        "Nawsie Brzosteckie"
    ],
    "name:pol_x_preferred":[
        "Nawsie Brzosteckie"
    ],
    "name:ukr_x_preferred":[
        "\u041d\u0430\u0432\u0441\u0435-\u0411\u0436\u043e\u0441\u0442\u0435\u0446\u044c\u043a\u0456"
    ],
    "wof:name":"Nawsie Brzosteckie",
    "wof:placetype":"locality"
},
  "geometry": {"coordinates":[21.43673,49.88302],"type":"Point"}
}