{
  "type": "Feature",
  "properties": {
    "gn:admin1_code":"86.0",
    "gn:admin2_code":"3011.0",
    "gn:admin3_code":"301103.0",
    "gn:asciiname":"Oborzyska Nowe",
    "gn:country_code":"PL",
    "gn:dem":78,
    "gn:feature_class":"P",
    "gn:feature_code":"PPL",
    "gn:name":"Oborzyska Nowe",
    "gn:population":0,
    "gn:timezone":"Europe/Warsaw",
    "iso:country":"PL",
    "name:fra_x_preferred":[
        "Nowe Oborzyska"
    ],
    "name:pol_x_preferred":[
        "Nowe Oborzyska"
    ],
    "name:ukr_x_preferred":[
        "\u041d\u043e\u0432\u0435 \u041e\u0431\u043e\u0436\u0438\u0441\u044c\u043a\u0430"
    ],
    "name:und_x_variant":[
        "Nowe Oborzyska"
    ],
    "wof:name":"Oborzyska Nowe",
    "wof:placetype":"locality"
},
  "geometry": {"coordinates":[16.69838,52.10001],"type":"Point"}
}