{
  "type": "Feature",
  "properties": {
    "gn:country":"PL",
    "gn:fcode":"PPL",
    "gn:population":0,
    "iso:country":"PL",
    "name:ceb_x_preferred":[
        "Wojnowice"
    ],
    "name:deu_x_preferred":[
        "Wojnowice"
    ],
    "name:fra_x_preferred":[
        "Wojnowice"
    ],
    "name:nld_x_preferred":[
        "Wojnowice"
    ],
    "name:pol_x_preferred":[
        "Wojnowice"
    ],
    "name:ukr_x_preferred":[
        "\u0412\u043e\u0439\u043d\u043e\u0432\u0456\u0446\u0435"
    ],
    "qs_pg:aaroncc":"PL",
    "qs_pg:gn_country":"PL",
    "qs_pg:gn_fcode":"PPL",
    "qs_pg:gn_pop":0,
    "qs_pg:name":"Wojnowice",
    "qs_pg:name_adm0":"Polska",
    "qs_pg:name_adm1":"Sl\u0105skie",
    "qs_pg:photos_9r":0,
    "qs_pg:photos_sr":0,
    "qs_pg:pop_sr":0,
    "qs_pg:qs_pg_placetype":"locality",
    "qs_pg:qs_pg_placetype_gp":"Town",
    "qs_pg:woe_adm0":23424923,
    "woe:adm0_id":23424923,
    "woe:name_adm0":"Polska",
    "woe:name_adm1":"Sl\u0105skie",
    "woe:placetype":"Town",
    "wof:name":"Wojnowice",
    "wof:placetype":"locality"
},
  "geometry": {"coordinates":[17.88265,50.11485],"type":"Point"}
}