{
  "type": "Feature",
  "properties": {
    "gn:admin1_code":"85.0",
    "gn:admin2_code":"2818.0",
    "gn:admin3_code":"281801.0",
    "gn:asciiname":"Ziemiany",
    "gn:country_code":"PL",
    "gn:dem":144,
    "gn:feature_class":"P",
    "gn:feature_code":"PPL",
    "gn:name":"Ziemiany",
    "gn:population":0,
    "gn:timezone":"Europe/Warsaw",
    "iso:country":"PL",
    "name:und_x_variant":[
        "Ziemianen",
        "Ziemiany"
    ],
    "wof:name":"Ziemiany",
    "wof:placetype":"locality"
},
  "geometry": {"coordinates":[22.08876,54.2611],"type":"Point"}
}