{
  "type": "Feature",
  "properties": {
    "gn:admin1_code":"85.0",
    "gn:admin2_code":"2818.0",
    "gn:admin3_code":"281801.0",
    "gn:asciiname":"Ziemiany",
    "gn:country_code":"PL",
    "gn:dem":144,
    "gn:feature_class":"P",
    "gn:feature_code":"PPL",
    "gn:name":"Ziemiany",
    "gn:population":0,
    "gn:timezone":"Europe/Warsaw",
    "iso:country":"PL",
    "name:azb_x_preferred":[
        "\u0698\u0645\u06cc\u0627\u0646\u0647"
    ],
    "name:deu_x_preferred":[
        "Ziemiany"
    ],
    "name:fas_x_preferred":[
        "\u0698\u0645\u06cc\u0627\u0646\u0647"
    ],
    "name:nld_x_preferred":[
        "Ziemiany"
    ],
    "name:pol_x_preferred":[
        "Ziemiany"
    ],
    "name:ukr_x_preferred":[
        "\u0417\u0435\u043c\u044f\u043d\u0438"
    ],
    "name:und_x_variant":[
        "Ziemianen"
    ],
    "wof:name":"Ziemiany",
    "wof:placetype":"locality"
},
  "geometry": {"coordinates":[22.08876,54.2611],"type":"Point"}
}