{
  "type": "Feature",
  "properties": {
    "gn:admin1_code":"77.0",
    "gn:admin2_code":"1201.0",
    "gn:admin3_code":"120104.0",
    "gn:asciiname":"Kucek",
    "gn:country_code":"PL",
    "gn:dem":446,
    "gn:feature_class":"P",
    "gn:feature_code":"PPL",
    "gn:name":"Kucek",
    "gn:population":0,
    "gn:timezone":"Europe/Warsaw",
    "iso:country":"PL",
    "wof:name":"Kucek",
    "wof:placetype":"locality"
},
  "geometry": {"coordinates":[20.51667,49.81667],"type":"Point"}
}