{
  "type": "Feature",
  "properties": {
    "gn:population":2077,
    "iso:country":"PL",
    "name:ast_x_preferred":[
        "Straszydle"
    ],
    "name:ceb_x_preferred":[
        "Straszydle"
    ],
    "name:eng_x_preferred":[
        "Straszydle"
    ],
    "name:fra_x_preferred":[
        "Straszydle"
    ],
    "name:pol_x_preferred":[
        "Straszydle"
    ],
    "name:szl_x_preferred":[
        "Straszydle"
    ],
    "name:ukr_x_preferred":[
        "\u0421\u0442\u0440\u0430\u0448\u0438\u0434\u043b\u0454"
    ],
    "qs:a0":"Rzeczpospolita Polska",
    "qs:a1":"*Podkarpackie",
    "qs:a1r":"0",
    "qs:a2":"Rzeszowski",
    "qs:adm0":"Rzeczpospolita Polska",
    "qs:la_lc":"*",
    "qs:level":"locality",
    "qs:loc":"Straszydle",
    "qs:loc_alt":"Straszydle",
    "qs:pop":0,
    "qs:type":"buffered point",
    "wd:wordcount":90,
    "wof:name":"Straszydle",
    "wof:placetype":"locality",
    "wof:population":2077
},
  "geometry": {"coordinates":[21.981037,49.89978],"type":"Point"}
}