{
  "type": "Feature",
  "properties": {
    "gn:country":"PL",
    "gn:fcode":"PPL",
    "gn:population":0,
    "iso:country":"PL",
    "name:ast_x_preferred":[
        "Wenecja"
    ],
    "name:ceb_x_preferred":[
        "Wenecja"
    ],
    "name:deu_x_preferred":[
        "Wenecja"
    ],
    "name:eng_x_preferred":[
        "Wenecja"
    ],
    "name:fra_x_preferred":[
        "Wenecja"
    ],
    "name:jpn_x_preferred":[
        "\u30f4\u30a7\u30cd\u30c4\u30e4"
    ],
    "name:pol_x_preferred":[
        "Wenecja"
    ],
    "name:rus_x_preferred":[
        "\u0412\u0435\u043d\u0435\u0446\u044c\u044f"
    ],
    "name:ukr_x_preferred":[
        "\u0412\u0435\u043d\u0435\u0446\u044f"
    ],
    "qs_pg:aaroncc":"PL",
    "qs_pg:gn_country":"PL",
    "qs_pg:gn_fcode":"PPL",
    "qs_pg:gn_pop":0,
    "qs_pg:name":"Wenecja",
    "qs_pg:name_adm0":"Polska",
    "qs_pg:name_adm1":"Kujawsko-Pomorskie",
    "qs_pg:photos":35,
    "qs_pg:photos_1k":7,
    "qs_pg:photos_9k":1,
    "qs_pg:photos_9r":2,
    "qs_pg:photos_all":35,
    "qs_pg:photos_sr":2,
    "qs_pg:pop_sr":0,
    "qs_pg:qs_pg_placetype":"locality",
    "qs_pg:qs_pg_placetype_gp":"Town",
    "qs_pg:woe_adm0":23424923,
    "woe:adm0_id":23424923,
    "woe:name_adm0":"Polska",
    "woe:name_adm1":"Kujawsko-Pomorskie",
    "woe:placetype":"Town",
    "wof:name":"Wenecja",
    "wof:placetype":"locality"
},
  "geometry": {"coordinates":[17.76534,52.8059],"type":"Point"}
}