{
  "type": "Feature",
  "properties": {
    "gn:admin1_code":"74.0",
    "gn:admin2_code":"1011.0",
    "gn:admin3_code":"101103.0",
    "gn:asciiname":"Mrowiczna",
    "gn:country_code":"PL",
    "gn:dem":132,
    "gn:feature_class":"P",
    "gn:feature_code":"PPL",
    "gn:name":"Mrowiczna",
    "gn:population":0,
    "gn:timezone":"Europe/Warsaw",
    "iso:country":"PL",
    "wof:name":"Mrowiczna",
    "wof:placetype":"locality"
},
  "geometry": {"coordinates":[19.0184,51.91712],"type":"Point"}
}