{
  "type": "Feature",
  "properties": {
    "gn:admin1_code":"75.0",
    "gn:admin2_code":"602.0",
    "gn:admin3_code":"60203.0",
    "gn:asciiname":"Korczow",
    "gn:country_code":"PL",
    "gn:dem":203,
    "gn:feature_class":"P",
    "gn:feature_code":"PPL",
    "gn:name":"Korcz\u00f3w",
    "gn:population":0,
    "gn:timezone":"Europe/Warsaw",
    "iso:country":"PL",
    "name:azb_x_preferred":[
        "\u06a9\u0648\u0631\u0686\u0648\u0648"
    ],
    "name:ceb_x_preferred":[
        "Korcz\u00f3w"
    ],
    "name:fas_x_preferred":[
        "\u06a9\u0648\u0631\u0686\u0648\u0648"
    ],
    "name:fra_x_preferred":[
        "Korcz\u00f3w"
    ],
    "name:nld_x_preferred":[
        "Korcz\u00f3w"
    ],
    "name:pol_x_preferred":[
        "Korcz\u00f3w"
    ],
    "name:rus_x_preferred":[
        "\u041a\u043e\u0440\u0447\u0443\u0432"
    ],
    "name:szl_x_preferred":[
        "Korcz\u016fw"
    ],
    "name:ukr_x_preferred":[
        "\u041a\u043e\u0440\u0447\u0443\u0432"
    ],
    "name:und_x_variant":[
        "Korcz\u00f3w"
    ],
    "wof:name":"Korczow",
    "wof:placetype":"locality"
},
  "geometry": {"coordinates":[22.72538,50.4988],"type":"Point"}
}