{
  "type": "Feature",
  "properties": {
    "gn:admin1_code":"77.0",
    "gn:admin2_code":"1207.0",
    "gn:admin3_code":"120709.0",
    "gn:asciiname":"Kasinka",
    "gn:country_code":"PL",
    "gn:dem":418,
    "gn:feature_class":"P",
    "gn:feature_code":"PPL",
    "gn:name":"Kasinka",
    "gn:population":0,
    "gn:timezone":"Europe/Warsaw",
    "iso:country":"PL",
    "wof:name":"Kasinka",
    "wof:placetype":"locality"
},
  "geometry": {"coordinates":[20.05,49.71667],"type":"Point"}
}