{
  "type": "Feature",
  "properties": {
    "gn:admin1_code":"73.0",
    "gn:admin2_code":"411.0",
    "gn:admin3_code":"41106.0",
    "gn:asciiname":"Plowki",
    "gn:country_code":"PL",
    "gn:dem":89,
    "gn:feature_class":"P",
    "gn:feature_code":"PPL",
    "gn:name":"P\u0142owki",
    "gn:population":0,
    "gn:timezone":"Europe/Warsaw",
    "iso:country":"PL",
    "name:und_x_variant":[
        "P\u0142owki"
    ],
    "wof:name":"Plowki",
    "wof:placetype":"locality"
},
  "geometry": {"coordinates":[18.47206,52.64639],"type":"Point"}
}