{
  "type": "Feature",
  "properties": {
    "gn:admin1_code":"85.0",
    "gn:admin2_code":"2817.0",
    "gn:admin3_code":"281703.0",
    "gn:asciiname":"Nowy Dwor",
    "gn:country_code":"PL",
    "gn:dem":134,
    "gn:feature_class":"P",
    "gn:feature_code":"PPL",
    "gn:name":"Nowy Dw\u00f3r",
    "gn:population":0,
    "gn:timezone":"Europe/Warsaw",
    "iso:country":"PL",
    "name:und_x_variant":[
        "Neuhof",
        "Nowy Dw\u00f3r"
    ],
    "wof:name":"Nowy Dwor",
    "wof:placetype":"locality"
},
  "geometry": {"coordinates":[20.83378,53.56084],"type":"Point"}
}