{
  "type": "Feature",
  "properties": {
    "gn:admin1_code":"83.0",
    "gn:admin2_code":"2403.0",
    "gn:admin3_code":"240304.0",
    "gn:asciiname":"Kotelniczysko",
    "gn:country_code":"PL",
    "gn:dem":359,
    "gn:feature_class":"P",
    "gn:feature_code":"PPL",
    "gn:name":"Kotelniczysko",
    "gn:population":0,
    "gn:timezone":"Europe/Warsaw",
    "iso:country":"PL",
    "wof:name":"Kotelniczysko",
    "wof:placetype":"locality"
},
  "geometry": {"coordinates":[18.85456,49.77942],"type":"Point"}
}