{
  "type": "Feature",
  "properties": {
    "gn:admin1_code":"83.0",
    "gn:admin2_code":"2406.0",
    "gn:admin3_code":"240609.0",
    "gn:asciiname":"Zamlynie",
    "gn:country_code":"PL",
    "gn:dem":246,
    "gn:feature_class":"P",
    "gn:feature_code":"PPL",
    "gn:name":"Zam\u0142ynie",
    "gn:population":0,
    "gn:timezone":"Europe/Warsaw",
    "iso:country":"PL",
    "name:ceb_x_preferred":[
        "Zam\u0142ynie"
    ],
    "name:pol_x_preferred":[
        "Zam\u0142ynie"
    ],
    "name:por_x_preferred":[
        "Zam\u0142ynie"
    ],
    "name:ukr_x_preferred":[
        "\u0417\u0430\u043c\u043b\u0438\u043d\u0435"
    ],
    "wof:name":"Zamlynie",
    "wof:placetype":"locality"
},
  "geometry": {"coordinates":[18.80529,50.86132],"type":"Point"}
}