{
  "type": "Feature",
  "properties": {
    "gn:admin1_code":"74.0",
    "gn:admin2_code":"1017.0",
    "gn:admin3_code":"101707.0",
    "gn:asciiname":"Patnow",
    "gn:country_code":"PL",
    "gn:dem":211,
    "gn:feature_class":"P",
    "gn:feature_code":"PPL",
    "gn:name":"P\u0105tn\u00f3w",
    "gn:population":1400,
    "gn:timezone":"Europe/Warsaw",
    "iso:country":"PL",
    "name:azb_x_preferred":[
        "\u067e\u0627\u0646\u062a\u0646\u0648\u0648"
    ],
    "name:deu_x_preferred":[
        "P\u0105tn\u00f3w"
    ],
    "name:fas_x_preferred":[
        "\u067e\u0627\u0646\u062a\u0646\u0648\u0648"
    ],
    "name:nld_x_preferred":[
        "P\u0105tn\u00f3w"
    ],
    "name:pol_x_preferred":[
        "P\u0105tn\u00f3w"
    ],
    "name:ukr_x_preferred":[
        "\u041f\u043e\u043d\u0442\u043d\u0443\u0432"
    ],
    "wof:name":"Patnow",
    "wof:placetype":"locality",
    "wof:population":1400
},
  "geometry": {"coordinates":[18.61659,51.14403],"type":"Point"}
}