{
  "type": "Feature",
  "properties": {
    "gn:gn_country":"PL",
    "gn:gn_fcode":"PPL",
    "gn:gn_pop":3154,
    "gn:population":3154,
    "iso:country":"PL",
    "name:dut_x_preferred":[
        "Mi\u0119dzybrodzie Bialskie"
    ],
    "name:eng_x_preferred":[
        "Mi\u0119dzybrodzie Bialskie"
    ],
    "name:fre_x_preferred":[
        "Mi\u0119dzybrodzie Bialskie"
    ],
    "name:ger_x_preferred":[
        "Mi\u0119dzybrodzie Bialskie"
    ],
    "name:per_x_preferred":[
        "\u0645\u06cc\u0646\u0632\u0628\u0631\u0648\u062c\u0647 \u0628\u06cc\u0627\u0644\u0633\u06a9\u06cc\u0647"
    ],
    "name:pol_x_preferred":[
        "Mi\u0119dzybrodzie Bialskie"
    ],
    "name:unk_x_variant":[
        "Mi\u0119dzybrodzie"
    ],
    "qs_pg:aaroncc":"PL",
    "qs_pg:gn_country":"PL",
    "qs_pg:gn_fcode":"PPL",
    "qs_pg:gn_pop":3154,
    "qs_pg:name":"Mi\u0119dzybrodzie Bialskie",
    "qs_pg:name_adm0":"Polska",
    "qs_pg:name_adm1":"Sl\u0105skie",
    "qs_pg:photos_9k":1,
    "qs_pg:photos_9r":1,
    "qs_pg:photos_all":4,
    "qs_pg:photos_sr":0,
    "qs_pg:pop_sr":4,
    "qs_pg:qs_pg_placetype":"locality",
    "qs_pg:qs_pg_placetype_gp":"Town",
    "qs_pg:woe_adm0":23424923,
    "woe:adm0_id":23424923,
    "woe:name_adm0":"Polska",
    "woe:name_adm1":"Sl\u0105skie",
    "woe:placetype":"Town",
    "wof:name":"Mi\u0119dzybrodzie Bialskie",
    "wof:placetype":"locality",
    "wof:population":3154
},
  "geometry": {"coordinates":[19.19741,49.78747],"type":"Point"}
}