{
  "type": "Feature",
  "properties": {
    "gn:admin1_code":"75.0",
    "gn:admin2_code":"618.0",
    "gn:admin3_code":"61803.0",
    "gn:asciiname":"Sowiniec",
    "gn:country_code":"PL",
    "gn:dem":233,
    "gn:feature_class":"P",
    "gn:feature_code":"PPL",
    "gn:name":"Sowiniec",
    "gn:population":0,
    "gn:timezone":"Europe/Warsaw",
    "iso:country":"PL",
    "name:fra_x_preferred":[
        "Sowiniec"
    ],
    "name:pol_x_preferred":[
        "Sowiniec"
    ],
    "name:ukr_x_preferred":[
        "\u0421\u043e\u0432\u0456\u043d\u0435\u0446\u044c"
    ],
    "name:und_x_variant":[
        "Kolonia Sowiniec"
    ],
    "wof:name":"Sowiniec",
    "wof:placetype":"locality"
},
  "geometry": {"coordinates":[23.59562,50.4653],"type":"Point"}
}