{
  "type": "Feature",
  "properties": {
    "gn:admin1_code":"83.0",
    "gn:admin2_code":"2404.0",
    "gn:admin3_code":"240411.0",
    "gn:asciiname":"Grabowka",
    "gn:country_code":"PL",
    "gn:dem":222,
    "gn:feature_class":"P",
    "gn:feature_code":"PPL",
    "gn:name":"Grab\u00f3wka",
    "gn:population":0,
    "gn:timezone":"Europe/Warsaw",
    "iso:country":"PL",
    "name:ceb_x_preferred":[
        "Grab\u00f3wka"
    ],
    "name:pol_x_preferred":[
        "Grab\u00f3wka"
    ],
    "name:ukr_x_preferred":[
        "\u0490\u0440\u0430\u0431\u0443\u0432\u043a\u0430"
    ],
    "wof:name":"Grabowka",
    "wof:placetype":"locality"
},
  "geometry": {"coordinates":[19.21715,50.95767],"type":"Point"}
}