{
  "type": "Feature",
  "properties": {
    "gn:admin1_code":"81.0",
    "gn:admin2_code":"2012.0",
    "gn:admin3_code":"201209.0",
    "gn:asciiname":"Lugiele",
    "gn:country_code":"PL",
    "gn:dem":232,
    "gn:feature_class":"P",
    "gn:feature_code":"PPL",
    "gn:name":"\u0141ugiele",
    "gn:population":0,
    "gn:timezone":"Europe/Warsaw",
    "iso:country":"PL",
    "wof:name":"Lugiele",
    "wof:placetype":"locality"
},
  "geometry": {"coordinates":[22.8677,54.29709],"type":"Point"}
}