{
  "type": "Feature",
  "properties": {
    "gn:admin1_code":"78.0",
    "gn:admin2_code":"1430.0",
    "gn:admin3_code":"143001.0",
    "gn:asciiname":"Broniow",
    "gn:country_code":"PL",
    "gn:dem":199,
    "gn:feature_class":"P",
    "gn:feature_code":"PPL",
    "gn:name":"Broni\u00f3w",
    "gn:population":0,
    "gn:timezone":"Europe/Warsaw",
    "iso:country":"PL",
    "name:und_x_variant":[
        "Broni\u00f3w"
    ],
    "wof:name":"Broniow",
    "wof:placetype":"locality"
},
  "geometry": {"coordinates":[20.79581,51.276],"type":"Point"}
}