{
  "type": "Feature",
  "properties": {
    "gn:admin1_code":"78.0",
    "gn:admin2_code":"1430.0",
    "gn:admin3_code":"143001.0",
    "gn:asciiname":"Broniow",
    "gn:country_code":"PL",
    "gn:dem":199,
    "gn:feature_class":"P",
    "gn:feature_code":"PPL",
    "gn:name":"Broni\u00f3w",
    "gn:population":0,
    "gn:timezone":"Europe/Warsaw",
    "iso:country":"PL",
    "name:azb_x_preferred":[
        "\u0628\u0631\u0648\u0646\u0642\u0648\u0648"
    ],
    "name:ceb_x_preferred":[
        "Broni\u00f3w"
    ],
    "name:fas_x_preferred":[
        "\u0628\u0631\u0648\u0646\u06af\u0648\u0648"
    ],
    "name:fra_x_preferred":[
        "Broni\u00f3w"
    ],
    "name:pol_x_preferred":[
        "Broni\u00f3w"
    ],
    "name:ukr_x_preferred":[
        "\u0411\u0440\u043e\u043d\u044e\u0432"
    ],
    "wof:name":"Broniow",
    "wof:placetype":"locality"
},
  "geometry": {"coordinates":[20.79581,51.276],"type":"Point"}
}