{
  "type": "Feature",
  "properties": {
    "gn:admin1_code":"78.0",
    "gn:admin2_code":"1407.0",
    "gn:admin3_code":"140705.0",
    "gn:asciiname":"Stara Wies",
    "gn:country_code":"PL",
    "gn:dem":118,
    "gn:feature_class":"P",
    "gn:feature_code":"PPL",
    "gn:name":"Stara Wie\u015b",
    "gn:population":0,
    "gn:timezone":"Europe/Warsaw",
    "iso:country":"PL",
    "wof:name":"Stara Wies",
    "wof:placetype":"neighbourhood"
},
  "geometry": {"coordinates":[21.55975,51.57211],"type":"Point"}
}