{
  "type": "Feature",
  "properties": {
    "gn:admin1_code":"86.0",
    "gn:admin2_code":"3015.0",
    "gn:admin3_code":"301505.0",
    "gn:asciiname":"Niegolewo",
    "gn:country_code":"PL",
    "gn:dem":82,
    "gn:feature_class":"P",
    "gn:feature_code":"PPL",
    "gn:name":"Niegolewo",
    "gn:population":0,
    "gn:timezone":"Europe/Warsaw",
    "iso:country":"PL",
    "name:ceb_x_preferred":[
        "Niegolewo"
    ],
    "name:fra_x_preferred":[
        "Niegolewo"
    ],
    "name:pol_x_preferred":[
        "Niegolewo"
    ],
    "name:ukr_x_preferred":[
        "\u041d\u0435\u0491\u043e\u043b\u0435\u0432\u043e"
    ],
    "wof:name":"Niegolewo",
    "wof:placetype":"locality"
},
  "geometry": {"coordinates":[16.43349,52.36963],"type":"Point"}
}