{
  "type": "Feature",
  "properties": {
    "gn:admin1_code":"78.0",
    "gn:admin2_code":"1422.0",
    "gn:admin3_code":"142203.0",
    "gn:asciiname":"Olszewiec",
    "gn:country_code":"PL",
    "gn:dem":135,
    "gn:feature_class":"P",
    "gn:feature_code":"PPL",
    "gn:name":"Olszewiec",
    "gn:population":0,
    "gn:timezone":"Europe/Warsaw",
    "iso:country":"PL",
    "name:fra_x_preferred":[
        "Olszewiec"
    ],
    "name:pol_x_preferred":[
        "Olszewiec"
    ],
    "name:ukr_x_preferred":[
        "\u041e\u043b\u044c\u0448\u0435\u0432\u0435\u0446\u044c"
    ],
    "wof:name":"Olszewiec",
    "wof:placetype":"locality"
},
  "geometry": {"coordinates":[20.7967,53.04932],"type":"Point"}
}