{
  "type": "Feature",
  "properties": {
    "gn:admin1_code":"86.0",
    "gn:admin2_code":"3010.0",
    "gn:admin3_code":"301012.0",
    "gn:asciiname":"Kijowiec",
    "gn:country_code":"PL",
    "gn:dem":101,
    "gn:feature_class":"P",
    "gn:feature_code":"PPL",
    "gn:name":"Kijowiec",
    "gn:population":0,
    "gn:timezone":"Europe/Warsaw",
    "iso:country":"PL",
    "name:fra_x_preferred":[
        "Kijowiec"
    ],
    "name:pol_x_preferred":[
        "Kijowiec"
    ],
    "name:ukr_x_preferred":[
        "\u041a\u0456\u0439\u043e\u0432\u0435\u0446\u044c"
    ],
    "wof:name":"Kijowiec",
    "wof:placetype":"locality"
},
  "geometry": {"coordinates":[18.31611,52.4311],"type":"Point"}
}