{
  "type": "Feature",
  "properties": {
    "gn:admin1_code":"76.0",
    "gn:admin2_code":"811.0",
    "gn:admin3_code":"81108.0",
    "gn:asciiname":"Nowe Czaple",
    "gn:country_code":"PL",
    "gn:dem":166,
    "gn:feature_class":"P",
    "gn:feature_code":"PPL",
    "gn:name":"Nowe Czaple",
    "gn:population":0,
    "gn:timezone":"Europe/Warsaw",
    "iso:country":"PL",
    "name:deu_x_historical":[
        "Birkenstedt",
        "Neu Tsch\u00f6peln"
    ],
    "name:deu_x_preferred":[
        "Birkenstedt"
    ],
    "name:deu_x_variant":[
        "Neu Tsch\u00f6peln",
        "Nowe Czaple"
    ],
    "name:fra_x_preferred":[
        "Nowe Czaple"
    ],
    "name:pol_x_preferred":[
        "Nowe Czaple"
    ],
    "name:ukr_x_preferred":[
        "\u041d\u043e\u0432\u0435 \u0427\u0430\u043f\u043b\u0435"
    ],
    "wof:name":"Nowe Czaple",
    "wof:placetype":"locality"
},
  "geometry": {"coordinates":[14.77959,51.5522],"type":"Point"}
}