{
  "type": "Feature",
  "properties": {
    "gn:admin1_code":"74.0",
    "gn:admin2_code":"1004.0",
    "gn:admin3_code":"100407.0",
    "gn:asciiname":"Chorzepin",
    "gn:country_code":"PL",
    "gn:dem":98,
    "gn:feature_class":"P",
    "gn:feature_code":"PPL",
    "gn:name":"Chorzepin",
    "gn:population":0,
    "gn:timezone":"Europe/Warsaw",
    "iso:country":"PL",
    "name:azb_x_preferred":[
        "\u062e\u0648\u0698\u067e\u06cc\u0646"
    ],
    "name:fas_x_preferred":[
        "\u062e\u0648\u0698\u067e\u06cc\u0646"
    ],
    "name:fra_x_preferred":[
        "Chorzepin"
    ],
    "name:pol_x_preferred":[
        "Chorzepin"
    ],
    "name:szl_x_preferred":[
        "Chorzepin"
    ],
    "name:ukr_x_preferred":[
        "\u0425\u043e\u0436\u0435\u043f\u0456\u043d"
    ],
    "wof:name":"Chorzepin",
    "wof:placetype":"locality"
},
  "geometry": {"coordinates":[18.87486,52.07191],"type":"Point"}
}