{
  "type": "Feature",
  "properties": {
    "gn:admin1_code":"74.0",
    "gn:admin2_code":"1004.0",
    "gn:admin3_code":"100407.0",
    "gn:asciiname":"Chorzepin",
    "gn:country_code":"PL",
    "gn:dem":98,
    "gn:feature_class":"P",
    "gn:feature_code":"PPL",
    "gn:name":"Chorzepin",
    "gn:population":0,
    "gn:timezone":"Europe/Warsaw",
    "iso:country":"PL",
    "wof:name":"Chorzepin",
    "wof:placetype":"locality"
},
  "geometry": {"coordinates":[18.87486,52.07191],"type":"Point"}
}