{
  "type": "Feature",
  "properties": {
    "gn:gn_country":"PL",
    "gn:gn_fcode":"PPL",
    "gn:gn_pop":1278,
    "gn:population":1278,
    "iso:country":"PL",
    "name:dut_x_preferred":[
        "G\u0142uszyca G\u00f3rna"
    ],
    "name:eng_x_preferred":[
        "G\u0142uszyca G\u00f3rna"
    ],
    "name:fre_x_preferred":[
        "G\u0142uszyca G\u00f3rna"
    ],
    "name:ger_x_preferred":[
        "G\u0142uszyca G\u00f3rna"
    ],
    "name:nan_x_preferred":[
        "G\u0142uszyca G\u00f3rna"
    ],
    "name:pol_x_preferred":[
        "G\u0142uszyca G\u00f3rna"
    ],
    "name:unk_x_variant":[
        "Ober W\u00fcstegiersdorf"
    ],
    "qs_pg:aaroncc":"PL",
    "qs_pg:gn_country":"PL",
    "qs_pg:gn_fcode":"PPL",
    "qs_pg:gn_pop":1278,
    "qs_pg:name":"Gluszyca Gorna",
    "qs_pg:name_adm0":"Polska",
    "qs_pg:name_adm1":"Dolnosl\u0105skie",
    "qs_pg:photos_9r":0,
    "qs_pg:photos_sr":0,
    "qs_pg:pop_sr":3,
    "qs_pg:qs_pg_placetype":"locality",
    "qs_pg:qs_pg_placetype_gp":"Town",
    "qs_pg:woe_adm0":23424923,
    "woe:adm0_id":23424923,
    "woe:name_adm0":"Polska",
    "woe:name_adm1":"Dolnosl\u0105skie",
    "woe:placetype":"Town",
    "wof:name":"Gluszyca Gorna",
    "wof:placetype":"locality",
    "wof:population":1278
},
  "geometry": {"coordinates":[16.37585,50.66606],"type":"Point"}
}