{
  "type": "Feature",
  "properties": {
    "gn:admin1_code":"73.0",
    "gn:admin2_code":"415.0",
    "gn:admin3_code":"41509.0",
    "gn:asciiname":"Skludzewo",
    "gn:country_code":"PL",
    "gn:dem":74,
    "gn:feature_class":"P",
    "gn:feature_code":"PPL",
    "gn:name":"Sk\u0142udzewo",
    "gn:population":0,
    "gn:timezone":"Europe/Warsaw",
    "iso:country":"PL",
    "name:ceb_x_preferred":[
        "Sk\u0142udzewo"
    ],
    "name:nld_x_preferred":[
        "Sk\u0142udzewo"
    ],
    "name:pol_x_preferred":[
        "Sk\u0142udzewo"
    ],
    "name:ukr_x_preferred":[
        "\u0421\u043a\u043b\u0443\u0434\u0437\u0435\u0432\u043e"
    ],
    "name:und_x_variant":[
        "Sk\u0142udzewo"
    ],
    "wof:name":"Skludzewo",
    "wof:placetype":"locality"
},
  "geometry": {"coordinates":[18.33252,53.12826],"type":"Point"}
}