{
  "type": "Feature",
  "properties": {
    "gn:admin1_code":"85.0",
    "gn:admin2_code":"2804.0",
    "gn:admin3_code":"280407.0",
    "gn:asciiname":"Rogajny",
    "gn:country_code":"PL",
    "gn:dem":68,
    "gn:feature_class":"P",
    "gn:feature_code":"PPL",
    "gn:name":"Rogajny",
    "gn:population":0,
    "gn:timezone":"Europe/Warsaw",
    "iso:country":"PL",
    "name:und_x_variant":[
        "Rogehnen",
        "Rogajny"
    ],
    "wof:name":"Rogajny",
    "wof:placetype":"locality"
},
  "geometry": {"coordinates":[19.72981,54.04705],"type":"Point"}
}