{
  "type": "Feature",
  "properties": {
    "gn:admin1_code":"75.0",
    "gn:admin2_code":"609.0",
    "gn:admin3_code":"60901.0",
    "gn:asciiname":"Podole",
    "gn:country_code":"PL",
    "gn:dem":217,
    "gn:feature_class":"P",
    "gn:feature_code":"PPL",
    "gn:name":"Podole",
    "gn:population":0,
    "gn:timezone":"Europe/Warsaw",
    "iso:country":"PL",
    "name:fra_x_preferred":[
        "Podole"
    ],
    "name:pol_x_preferred":[
        "Podole"
    ],
    "name:ukr_x_preferred":[
        "\u041f\u043e\u0434\u043e\u043b\u0435"
    ],
    "wof:name":"Podole",
    "wof:placetype":"locality"
},
  "geometry": {"coordinates":[22.27495,51.20065],"type":"Point"}
}