{
  "type": "Feature",
  "properties": {
    "gn:gn_country":"PL",
    "gn:gn_fcode":"PPL",
    "gn:gn_pop":523,
    "gn:population":523,
    "iso:country":"PL",
    "name:eng_x_preferred":[
        "Trzcinna"
    ],
    "name:fre_x_preferred":[
        "Trzcinna"
    ],
    "name:per_x_preferred":[
        "\u0627\u0634\u0686\u06cc\u0646\u0627"
    ],
    "name:pol_x_preferred":[
        "Trzcinna"
    ],
    "name:unk_x_variant":[
        "Trzcinno"
    ],
    "name:urd_x_preferred":[
        "\u0627\u0634\u0686\u06cc\u0646\u0627"
    ],
    "qs_pg:aaroncc":"PL",
    "qs_pg:gn_country":"PL",
    "qs_pg:gn_fcode":"PPL",
    "qs_pg:gn_pop":523,
    "qs_pg:name":"Trzcinna",
    "qs_pg:name_adm0":"Polska",
    "qs_pg:name_adm1":"Zachodniopomorskie",
    "qs_pg:photos_9r":0,
    "qs_pg:photos_sr":0,
    "qs_pg:pop_sr":2,
    "qs_pg:qs_pg_placetype":"locality",
    "qs_pg:qs_pg_placetype_gp":"Town",
    "qs_pg:woe_adm0":23424923,
    "woe:adm0_id":23424923,
    "woe:name_adm0":"Polska",
    "woe:name_adm1":"Zachodniopomorskie",
    "woe:placetype":"Town",
    "wof:name":"Trzcinna",
    "wof:placetype":"locality",
    "wof:population":523
},
  "geometry": {"coordinates":[15.01076,52.88239],"type":"Point"}
}