{
  "type": "Feature",
  "properties": {
    "gn:country":"PL",
    "gn:fcode":"PPL",
    "gn:population":523,
    "iso:country":"PL",
    "name:ast_x_preferred":[
        "Trzcinna"
    ],
    "name:azb_x_preferred":[
        "\u0627\u0634\u0686\u06cc\u0646\u0627"
    ],
    "name:ceb_x_preferred":[
        "Trzcinna"
    ],
    "name:eng_x_preferred":[
        "Trzcinna"
    ],
    "name:fas_x_preferred":[
        "\u0627\u0634\u0686\u06cc\u0646\u0627"
    ],
    "name:fra_x_preferred":[
        "Trzcinna"
    ],
    "name:pol_x_preferred":[
        "Trzcinna"
    ],
    "name:ukr_x_preferred":[
        "\u0422\u0448\u0446\u0438\u043d\u043d\u0430"
    ],
    "name:und_x_variant":[
        "Trzcinno"
    ],
    "name:urd_x_preferred":[
        "\u0627\u0634\u0686\u06cc\u0646\u0627"
    ],
    "name:vie_x_preferred":[
        "Trzcinna"
    ],
    "qs_pg:aaroncc":"PL",
    "qs_pg:gn_country":"PL",
    "qs_pg:gn_fcode":"PPL",
    "qs_pg:gn_pop":523,
    "qs_pg:name":"Trzcinna",
    "qs_pg:name_adm0":"Polska",
    "qs_pg:name_adm1":"Zachodniopomorskie",
    "qs_pg:photos_9r":0,
    "qs_pg:photos_sr":0,
    "qs_pg:pop_sr":2,
    "qs_pg:qs_pg_placetype":"locality",
    "qs_pg:qs_pg_placetype_gp":"Town",
    "qs_pg:woe_adm0":23424923,
    "woe:adm0_id":23424923,
    "woe:name_adm0":"Polska",
    "woe:name_adm1":"Zachodniopomorskie",
    "woe:placetype":"Town",
    "wof:name":"Trzcinna",
    "wof:placetype":"locality",
    "wof:population":523
},
  "geometry": {"coordinates":[15.01076,52.88239],"type":"Point"}
}