{
  "type": "Feature",
  "properties": {
    "gn:admin1_code":"74.0",
    "gn:admin2_code":"1014.0",
    "gn:admin3_code":"101405.0",
    "gn:asciiname":"Samborz",
    "gn:country_code":"PL",
    "gn:dem":164,
    "gn:feature_class":"P",
    "gn:feature_code":"PPL",
    "gn:name":"Samb\u00f3rz",
    "gn:population":0,
    "gn:timezone":"Europe/Warsaw",
    "iso:country":"PL",
    "name:pol_x_preferred":[
        "Samb\u00f3rz"
    ],
    "name:ukr_x_preferred":[
        "\u0421\u0430\u043c\u0431\u0443\u0436"
    ],
    "wof:name":"Samborz",
    "wof:placetype":"locality"
},
  "geometry": {"coordinates":[18.81258,51.46796],"type":"Point"}
}