{
  "type": "Feature",
  "properties": {
    "gn:admin1_code":"86.0",
    "gn:admin2_code":"3022.0",
    "gn:admin3_code":"302205.0",
    "gn:asciiname":"Laszczyn",
    "gn:country_code":"PL",
    "gn:dem":99,
    "gn:feature_class":"P",
    "gn:feature_code":"PPL",
    "gn:name":"\u0141aszczyn",
    "gn:population":0,
    "gn:timezone":"Europe/Warsaw",
    "iso:country":"PL",
    "name:fra_x_preferred":[
        "\u0141aszczyn"
    ],
    "name:pol_x_preferred":[
        "\u0141aszczyn"
    ],
    "name:ukr_x_preferred":[
        "\u041b\u0430\u0449\u0438\u043d"
    ],
    "wof:name":"Laszczyn",
    "wof:placetype":"locality"
},
  "geometry": {"coordinates":[16.86453,51.63869],"type":"Point"}
}