{
  "type": "Feature",
  "properties": {
    "gn:admin1_code":"77",
    "gn:admin2_code":"1216",
    "gn:admin3_code":"121614.0",
    "gn:asciiname":"Jamna",
    "gn:country_code":"PL",
    "gn:dem":459,
    "gn:feature_class":"P",
    "gn:feature_code":"PPL",
    "gn:name":"Jamna",
    "gn:population":0,
    "gn:timezone":"Europe/Warsaw",
    "iso:country":"PL",
    "name:ceb_x_preferred":[
        "Jamna"
    ],
    "name:pol_x_preferred":[
        "Jamna"
    ],
    "name:swe_x_preferred":[
        "Jamna"
    ],
    "wof:name":"Jamna",
    "wof:placetype":"locality"
},
  "geometry": {"coordinates":[20.83591,49.7745],"type":"Point"}
}