{
  "type": "Feature",
  "properties": {
    "gn:admin1_code":"72.0",
    "gn:admin2_code":"208.0",
    "gn:admin3_code":"20804.0",
    "gn:asciiname":"Drogoslaw",
    "gn:country_code":"PL",
    "gn:dem":402,
    "gn:feature_class":"P",
    "gn:feature_code":"PPL",
    "gn:name":"Drogos\u0142aw",
    "gn:population":0,
    "gn:timezone":"Europe/Warsaw",
    "iso:country":"PL",
    "name:und_x_variant":[
        "Kunzendorf",
        "Drotoslaw",
        "Kurzendorf",
        "Drogos\u0142aw"
    ],
    "wof:name":"Drogoslaw",
    "wof:placetype":"locality"
},
  "geometry": {"coordinates":[16.50839,50.6002],"type":"Point"}
}