{
  "type": "Feature",
  "properties": {
    "gn:admin1_code":"86.0",
    "gn:admin2_code":"3007.0",
    "gn:admin3_code":"300707.0",
    "gn:asciiname":"Grabek",
    "gn:country_code":"PL",
    "gn:dem":121,
    "gn:feature_class":"P",
    "gn:feature_code":"PPL",
    "gn:name":"Grabek",
    "gn:population":0,
    "gn:timezone":"Europe/Warsaw",
    "iso:country":"PL",
    "wof:name":"Grabek",
    "wof:placetype":"locality"
},
  "geometry": {"coordinates":[18.26029,51.95552],"type":"Point"}
}