{
  "type": "Feature",
  "properties": {
    "gn:admin1_code":"84.0",
    "gn:admin2_code":"2604.0",
    "gn:admin3_code":"260416.0",
    "gn:asciiname":"Pulaczow",
    "gn:country_code":"PL",
    "gn:dem":239,
    "gn:feature_class":"P",
    "gn:feature_code":"PPL",
    "gn:name":"Pu\u0142acz\u00f3w",
    "gn:population":0,
    "gn:timezone":"Europe/Warsaw",
    "iso:country":"PL",
    "name:und_x_variant":[
        "Pu\u0142acz\u00f3w"
    ],
    "wof:name":"Pulaczow",
    "wof:placetype":"locality"
},
  "geometry": {"coordinates":[21.13438,50.68182],"type":"Point"}
}