{
  "type": "Feature",
  "properties": {
    "iso:country":"PL",
    "name:pol_x_colloquial":[
        "Sabieszow"
    ],
    "name:pol_x_preferred":[
        "Sabiesz\u00f3w"
    ],
    "qs:gn_adm0_cc":"PL",
    "qs:gn_local":3101367,
    "qs:gn_nam_loc":"pielice",
    "qs:gn_namadm1":"72",
    "qs:local_max":86,
    "qs:local_sum":118,
    "qs:localhoods":2,
    "qs:name":"Sabiesz\u00f3w",
    "qs:name_adm0":"Polska",
    "qs:name_adm1":"Dolnosl\u0105skie",
    "qs:name_adm2":"Jelenia Gora",
    "qs:name_lau":"Jelenia G\u00f3ra",
    "qs:name_local":"Cieplice lskie Zdr\u00f3j",
    "qs:photo_max":33,
    "qs:photo_sum":86,
    "qs:placetype":"Suburb",
    "qs:quad_count":20,
    "qs:woe_adm0":23424923,
    "qs:woe_adm1":12577935,
    "qs:woe_adm2":12591140,
    "qs:woe_lau":12618518,
    "qs:woe_local":489943,
    "qs:woe_ver":"7.10.0",
    "wof:lang":[
        "pol"
    ],
    "wof:name":"Sabiesz\u00f3w",
    "wof:placetype":"neighbourhood"
},
  "geometry": {"coordinates":[15.666871,50.863607],"type":"Point"}
}