{
  "type": "Feature",
  "properties": {
    "gn:admin1_code":"73.0",
    "gn:admin2_code":"418.0",
    "gn:admin3_code":"41805.0",
    "gn:asciiname":"Pusti Wilkowickie",
    "gn:country_code":"PL",
    "gn:dem":93,
    "gn:feature_class":"P",
    "gn:feature_code":"PPL",
    "gn:name":"Pusti Wilkowickie",
    "gn:population":0,
    "gn:timezone":"Europe/Warsaw",
    "iso:country":"PL",
    "wof:name":"Pusti Wilkowickie",
    "wof:placetype":"locality"
},
  "geometry": {"coordinates":[19.05,52.51667],"type":"Point"}
}