{
  "type": "Feature",
  "properties": {
    "gn:country":"PL",
    "gn:fcode":"PPL",
    "gn:population":0,
    "iso:country":"PL",
    "name:ast_x_preferred":[
        "Szczebra"
    ],
    "name:azb_x_preferred":[
        "\u0634\u0686\u0628\u0631\u0627"
    ],
    "name:ceb_x_preferred":[
        "Szczebra"
    ],
    "name:deu_x_preferred":[
        "Szczebra"
    ],
    "name:eng_x_preferred":[
        "Szczebra"
    ],
    "name:fas_x_preferred":[
        "\u0634\u0686\u0628\u0631\u0627"
    ],
    "name:fra_x_preferred":[
        "Szczebra"
    ],
    "name:lit_x_preferred":[
        "\u0160\u010debra"
    ],
    "name:pol_x_preferred":[
        "Szczebra"
    ],
    "name:rus_x_preferred":[
        "\u0429\u0435\u0431\u0440\u0430"
    ],
    "name:ukr_x_preferred":[
        "\u0429\u0435\u0431\u0440\u0430"
    ],
    "qs_pg:aaroncc":"PL",
    "qs_pg:gn_country":"PL",
    "qs_pg:gn_fcode":"PPL",
    "qs_pg:gn_pop":0,
    "qs_pg:name":"Szczebra",
    "qs_pg:name_adm0":"Polska",
    "qs_pg:name_adm1":"Podlaskie",
    "qs_pg:photos":4,
    "qs_pg:photos_1k":1,
    "qs_pg:photos_9k":1,
    "qs_pg:photos_9r":1,
    "qs_pg:photos_all":4,
    "qs_pg:photos_sr":1,
    "qs_pg:pop_sr":0,
    "qs_pg:qs_pg_placetype":"locality",
    "qs_pg:qs_pg_placetype_gp":"Town",
    "qs_pg:woe_adm0":23424923,
    "woe:adm0_id":23424923,
    "woe:name_adm0":"Polska",
    "woe:name_adm1":"Podlaskie",
    "woe:placetype":"Town",
    "wof:name":"Szczebra",
    "wof:placetype":"locality"
},
  "geometry": {"coordinates":[22.97269,53.90811],"type":"Point"}
}