{
  "type": "Feature",
  "properties": {
    "gn:country":"PL",
    "gn:fcode":"PPL",
    "gn:population":0,
    "iso:country":"PL",
    "name:ast_x_preferred":[
        "D\u0142uga Go\u015blina"
    ],
    "name:azb_x_preferred":[
        "\u062f\u0648\u0648\u0642\u0627 \u0642\u0648\u0634\u0644\u06cc\u0646\u0627"
    ],
    "name:ceb_x_preferred":[
        "D\u0142uga Go\u015blina"
    ],
    "name:deu_x_preferred":[
        "D\u0142uga Go\u015blina"
    ],
    "name:eng_x_preferred":[
        "D\u0142uga Go\u015blina"
    ],
    "name:fas_x_preferred":[
        "\u062f\u0648\u0648\u06af\u0627 \u06af\u0648\u0634\u0644\u06cc\u0646\u0627"
    ],
    "name:fra_x_preferred":[
        "D\u0142uga Go\u015blina"
    ],
    "name:nan_x_preferred":[
        "D\u0142uga Go\u015blina"
    ],
    "name:nld_x_preferred":[
        "D\u0142uga Go\u015blina"
    ],
    "name:pol_x_preferred":[
        "D\u0142uga Go\u015blina"
    ],
    "name:ukr_x_preferred":[
        "\u0414\u043b\u0443\u0491\u0430-\u0490\u043e\u0441\u043b\u0456\u043d\u0430"
    ],
    "qs_pg:aaroncc":"PL",
    "qs_pg:gn_country":"PL",
    "qs_pg:gn_fcode":"PPL",
    "qs_pg:gn_pop":0,
    "qs_pg:name":"D\u0142uga Go\u015blina",
    "qs_pg:name_adm0":"Polska",
    "qs_pg:name_adm1":"Wielkopolskie",
    "qs_pg:photos":31,
    "qs_pg:photos_1k":6,
    "qs_pg:photos_9k":1,
    "qs_pg:photos_9r":2,
    "qs_pg:photos_all":31,
    "qs_pg:photos_sr":2,
    "qs_pg:pop_sr":0,
    "qs_pg:qs_pg_placetype":"locality",
    "qs_pg:qs_pg_placetype_gp":"Town",
    "qs_pg:woe_adm0":23424923,
    "woe:adm0_id":23424923,
    "woe:name_adm0":"Polska",
    "woe:name_adm1":"Wielkopolskie",
    "woe:placetype":"Town",
    "wof:name":"D\u0142uga Go\u015blina",
    "wof:placetype":"locality"
},
  "geometry": {"coordinates":[17.03381,52.63237],"type":"Point"}
}