{
  "type": "Feature",
  "properties": {
    "gn:admin1_code":"87.0",
    "gn:admin2_code":"3214.0",
    "gn:admin3_code":"321410.0",
    "gn:asciiname":"Warchlinko",
    "gn:country_code":"PL",
    "gn:dem":46,
    "gn:feature_class":"P",
    "gn:feature_code":"PPL",
    "gn:name":"Warchlinko",
    "gn:population":0,
    "gn:timezone":"Europe/Warsaw",
    "iso:country":"PL",
    "wof:name":"Warchlinko",
    "wof:placetype":"locality"
},
  "geometry": {"coordinates":[14.98723,53.43636],"type":"Point"}
}