{
  "type": "Feature",
  "properties": {
    "gn:admin1_code":"76.0",
    "gn:admin2_code":"810.0",
    "gn:admin3_code":"81007.0",
    "gn:asciiname":"Buczek",
    "gn:country_code":"PL",
    "gn:dem":145,
    "gn:feature_class":"P",
    "gn:feature_code":"PPL",
    "gn:name":"Buczek",
    "gn:population":0,
    "gn:timezone":"Europe/Warsaw",
    "iso:country":"PL",
    "name:fra_x_preferred":[
        "Buczek"
    ],
    "name:pol_x_preferred":[
        "Buczek"
    ],
    "name:ukr_x_preferred":[
        "\u0411\u0443\u0447\u0435\u043a"
    ],
    "wof:name":"Buczek",
    "wof:placetype":"locality"
},
  "geometry": {"coordinates":[15.58916,51.46055],"type":"Point"}
}