{
  "type": "Feature",
  "properties": {
    "gn:admin1_code":"80.0",
    "gn:admin2_code":"1815.0",
    "gn:admin3_code":"181505.0",
    "gn:asciiname":"Bukowina",
    "gn:country_code":"PL",
    "gn:dem":352,
    "gn:feature_class":"P",
    "gn:feature_code":"PPL",
    "gn:name":"Bukowina",
    "gn:population":0,
    "gn:timezone":"Europe/Warsaw",
    "iso:country":"PL",
    "name:ceb_x_preferred":[
        "Bukowina"
    ],
    "name:deu_x_preferred":[
        "Bukowina"
    ],
    "name:fra_x_preferred":[
        "Bukowina"
    ],
    "name:nds_x_preferred":[
        "Bukowina"
    ],
    "name:pol_x_preferred":[
        "Bukowina"
    ],
    "name:ukr_x_preferred":[
        "\u0411\u0443\u043a\u043e\u0432\u0456\u043d\u0430"
    ],
    "wof:name":"Bukowina",
    "wof:placetype":"locality"
},
  "geometry": {"coordinates":[21.53951,49.94943],"type":"Point"}
}