{
  "type": "Feature",
  "properties": {
    "gn:admin1_code":"85.0",
    "gn:admin2_code":"2814.0",
    "gn:admin3_code":"281401.0",
    "gn:asciiname":"Prole",
    "gn:country_code":"PL",
    "gn:dem":147,
    "gn:feature_class":"P",
    "gn:feature_code":"PPL",
    "gn:name":"Pr\u00f3le",
    "gn:population":0,
    "gn:timezone":"Europe/Warsaw",
    "iso:country":"PL",
    "name:pol_x_preferred":[
        "Pr\u00f3le"
    ],
    "name:ukr_x_preferred":[
        "\u041f\u0440\u0443\u043b\u0435"
    ],
    "name:und_x_variant":[
        "Prohlen"
    ],
    "name:vie_x_preferred":[
        "Pr\u00f3le"
    ],
    "wof:name":"Prole",
    "wof:placetype":"locality"
},
  "geometry": {"coordinates":[20.76301,53.90612],"type":"Point"}
}