{
  "type": "Feature",
  "properties": {
    "gn:admin1_code":"74.0",
    "gn:admin2_code":"1010.0",
    "gn:admin3_code":"101010.0",
    "gn:asciiname":"Krezna",
    "gn:country_code":"PL",
    "gn:dem":204,
    "gn:feature_class":"P",
    "gn:feature_code":"PPL",
    "gn:name":"Kr\u0119\u017cna",
    "gn:population":0,
    "gn:timezone":"Europe/Warsaw",
    "iso:country":"PL",
    "name:fra_x_preferred":[
        "Kr\u0119\u017cna"
    ],
    "name:pol_x_preferred":[
        "Kr\u0119\u017cna"
    ],
    "name:ukr_x_preferred":[
        "\u041a\u0440\u0435\u043d\u0436\u043d\u0430"
    ],
    "wof:name":"Krezna",
    "wof:placetype":"locality"
},
  "geometry": {"coordinates":[19.58052,51.35869],"type":"Point"}
}