{
  "type": "Feature",
  "properties": {
    "iso:country":"PL",
    "wof:name":"Osiedle Wandy",
    "wof:placetype":"neighbourhood"
},
  "geometry": {"coordinates":[20.04956508830784,50.07032243647205],"type":"Point"}
}