{
  "type": "Feature",
  "properties": {
    "gn:admin1_code":"86.0",
    "gn:admin2_code":"3001.0",
    "gn:admin3_code":"300105.0",
    "gn:asciiname":"Smolary",
    "gn:country_code":"PL",
    "gn:dem":73,
    "gn:feature_class":"P",
    "gn:feature_code":"PPL",
    "gn:name":"Smolary",
    "gn:population":0,
    "gn:timezone":"Europe/Warsaw",
    "iso:country":"PL",
    "name:fra_x_preferred":[
        "Smolary"
    ],
    "name:pol_x_preferred":[
        "Smolary"
    ],
    "wof:name":"Smolary",
    "wof:placetype":"locality"
},
  "geometry": {"coordinates":[17.13332999999999,53.03333000000001],"type":"Point"}
}