{
  "type": "Feature",
  "properties": {
    "gn:admin1_code":"75.0",
    "gn:admin2_code":"603.0",
    "gn:admin3_code":"60305.0",
    "gn:asciiname":"Uchanka",
    "gn:country_code":"PL",
    "gn:dem":175,
    "gn:feature_class":"P",
    "gn:feature_code":"PPL",
    "gn:name":"Ucha\u0144ka",
    "gn:population":0,
    "gn:timezone":"Europe/Warsaw",
    "iso:country":"PL",
    "name:azb_x_preferred":[
        "\u06cc\u0648\u0686\u0646\u06a9\u0627"
    ],
    "name:fas_x_preferred":[
        "\u06cc\u0648\u0686\u0646\u06a9\u0627"
    ],
    "name:fra_x_preferred":[
        "Ucha\u0144ka"
    ],
    "name:pol_x_preferred":[
        "Ucha\u0144ka"
    ],
    "name:ukr_x_preferred":[
        "\u0423\u0445\u0430\u043d\u044c\u043a\u0430"
    ],
    "name:urd_x_preferred":[
        "\u0627\u0686\u0646\u06a9\u0627"
    ],
    "wof:name":"Uchanka",
    "wof:placetype":"locality"
},
  "geometry": {"coordinates":[23.86515,51.0861],"type":"Point"}
}