{
  "type": "Feature",
  "properties": {
    "gn:admin1_code":"75.0",
    "gn:admin2_code":"602.0",
    "gn:admin3_code":"60203.0",
    "gn:asciiname":"Nadrzecze",
    "gn:country_code":"PL",
    "gn:dem":213,
    "gn:feature_class":"P",
    "gn:feature_code":"PPL",
    "gn:name":"Nadrzecze",
    "gn:population":0,
    "gn:timezone":"Europe/Warsaw",
    "iso:country":"PL",
    "name:ceb_x_preferred":[
        "Nadrzecze"
    ],
    "name:fra_x_preferred":[
        "Nadrzecze"
    ],
    "name:pol_x_preferred":[
        "Nadrzecze"
    ],
    "name:ukr_x_preferred":[
        "\u041d\u0430\u0434\u0436\u0435\u0447\u0435"
    ],
    "name:und_x_variant":[
        "S\u0119d\u0142aki"
    ],
    "wof:name":"Nadrzecze",
    "wof:placetype":"locality"
},
  "geometry": {"coordinates":[22.68943,50.60218],"type":"Point"}
}