{
  "type": "Feature",
  "properties": {
    "gn:admin1_code":"75.0",
    "gn:admin2_code":"602.0",
    "gn:admin3_code":"60203.0",
    "gn:asciiname":"Nadrzecze",
    "gn:country_code":"PL",
    "gn:dem":213,
    "gn:feature_class":"P",
    "gn:feature_code":"PPL",
    "gn:name":"Nadrzecze",
    "gn:population":0,
    "gn:timezone":"Europe/Warsaw",
    "iso:country":"PL",
    "name:und_x_variant":[
        "S\u0119d\u0142aki",
        "Nadrzecze"
    ],
    "wof:name":"Nadrzecze",
    "wof:placetype":"locality"
},
  "geometry": {"coordinates":[22.68943,50.60218],"type":"Point"}
}