{
  "type": "Feature",
  "properties": {
    "gn:admin1_code":"82.0",
    "gn:admin2_code":"2204.0",
    "gn:admin3_code":"220402.0",
    "gn:asciiname":"Dlugie Pole",
    "gn:country_code":"PL",
    "gn:dem":2,
    "gn:feature_class":"P",
    "gn:feature_code":"PPL",
    "gn:name":"D\u0142ugie Pole",
    "gn:population":0,
    "gn:timezone":"Europe/Warsaw",
    "iso:country":"PL",
    "name:und_x_variant":[
        "Langfelde",
        "D\u0142ugie Pole"
    ],
    "wof:name":"Dlugie Pole",
    "wof:placetype":"locality"
},
  "geometry": {"coordinates":[18.86629,54.21782],"type":"Point"}
}