{
  "type": "Feature",
  "properties": {
    "gn:population":1172,
    "iso:country":"PL",
    "name:ast_x_preferred":[
        "U\u015bcie Gorlickie"
    ],
    "name:azb_x_preferred":[
        "\u0627\u0648\u0634\u0686\u06cc\u0647 \u0642\u0648\u0631\u0644\u06cc\u062a\u0633\u06a9\u06cc\u0647"
    ],
    "name:deu_x_preferred":[
        "U\u015bcie Gorlickie"
    ],
    "name:eng_x_preferred":[
        "U\u015bcie Gorlickie"
    ],
    "name:fas_x_preferred":[
        "\u0627\u0648\u0634\u0686\u06cc\u0647 \u06af\u0648\u0631\u0644\u06cc\u062a\u0633\u06a9\u06cc\u0647"
    ],
    "name:fra_x_preferred":[
        "U\u015bcie Gorlickie"
    ],
    "name:nld_x_preferred":[
        "U\u015bcie Gorlickie"
    ],
    "name:pol_x_preferred":[
        "U\u015bcie Gorlickie"
    ],
    "name:rue_x_preferred":[
        "\u0423\u0441\u0442\u0454"
    ],
    "name:rus_x_preferred":[
        "\u0423\u0441\u0446\u0435-\u0413\u043e\u0440\u043b\u0438\u0446\u043a\u0435"
    ],
    "name:swe_x_preferred":[
        "U\u015bcie Gorlickie"
    ],
    "name:ukr_x_preferred":[
        "\u0423\u0441\u0442\u044f-\u0420\u0443\u0441\u044c\u043a\u0435"
    ],
    "qs:a0":"Rzeczpospolita Polska",
    "qs:a1":"*Malopolskie",
    "qs:a1r":"0",
    "qs:a2":"Gorlicki",
    "qs:adm0":"Rzeczpospolita Polska",
    "qs:la":"U\u015bcie Gorlickie",
    "qs:la_lc":"*PL1205102",
    "qs:level":"locality",
    "qs:loc":"U\u015bcie Gorlickie",
    "qs:loc_alt":"Uscie Gorlickie",
    "qs:pop":0,
    "qs:type":"rural point-in-poly",
    "wd:wordcount":105,
    "wof:name":"U\u015bcie Gorlickie",
    "wof:placetype":"locality",
    "wof:population":1172
},
  "geometry": {"coordinates":[21.1727298862266,49.4909597443239],"type":"Point"}
}