{
  "type": "Feature",
  "properties": {
    "gn:admin1_code":"85.0",
    "gn:admin2_code":"2804.0",
    "gn:admin3_code":"280407.0",
    "gn:asciiname":"Kielminek",
    "gn:country_code":"PL",
    "gn:dem":130,
    "gn:feature_class":"P",
    "gn:feature_code":"PPL",
    "gn:name":"Kielminek",
    "gn:population":0,
    "gn:timezone":"Europe/Warsaw",
    "iso:country":"PL",
    "name:pol_x_preferred":[
        "Kielminek"
    ],
    "name:und_x_variant":[
        "K\u00f6llming"
    ],
    "wof:name":"Kielminek",
    "wof:placetype":"locality"
},
  "geometry": {"coordinates":[19.70811,54.01009000000001],"type":"Point"}
}