{
  "type": "Feature",
  "properties": {
    "gn:admin1_code":"87.0",
    "gn:admin2_code":"3202.0",
    "gn:admin3_code":"320202.0",
    "gn:asciiname":"Zamecin",
    "gn:country_code":"PL",
    "gn:dem":63,
    "gn:feature_class":"P",
    "gn:feature_code":"PPL",
    "gn:name":"Zam\u0119cin",
    "gn:population":0,
    "gn:timezone":"Europe/Warsaw",
    "iso:country":"PL",
    "name:deu_x_preferred":[
        "Zam\u0119cin"
    ],
    "name:ita_x_preferred":[
        "Zam\u0119cin"
    ],
    "name:pol_x_preferred":[
        "Zam\u0119cin"
    ],
    "name:ukr_x_preferred":[
        "\u0417\u0430\u043c\u0435\u043d\u0446\u0438\u043d"
    ],
    "name:vie_x_preferred":[
        "Zam\u0119cin"
    ],
    "wof:name":"Zamecin",
    "wof:placetype":"locality"
},
  "geometry": {"coordinates":[15.37688,53.13065],"type":"Point"}
}