{
  "type": "Feature",
  "properties": {
    "gn:gn_country":"PL",
    "gn:gn_fcode":"PPLA2",
    "gn:gn_pop":55371,
    "gn:population":55371,
    "iso:country":"PL",
    "name:bel_x_preferred":[
        "\u041f\u0440\u0443\u0448\u043a\u0430\u045e"
    ],
    "name:bul_x_preferred":[
        "\u041f\u0440\u0443\u0448\u043a\u043e\u0432"
    ],
    "name:ces_x_preferred":[
        "Pruszk\u00f3w"
    ],
    "name:deu_x_preferred":[
        "Pruszk\u00f3w"
    ],
    "name:eng_x_preferred":[
        "Pruszk\u00f3w"
    ],
    "name:epo_x_preferred":[
        "Pruszk\u00f3w"
    ],
    "name:est_x_preferred":[
        "Pruszk\u00f3w"
    ],
    "name:eus_x_preferred":[
        "Pruszk\u00f3w"
    ],
    "name:fas_x_preferred":[
        "\u067e\u0631\u0648\u0634\u06a9\u0648\u0641"
    ],
    "name:fra_x_preferred":[
        "Pruszk\u00f3w"
    ],
    "name:heb_x_preferred":[
        "\u05e4\u05e8\u05d5\u05e9\u05e7\u05d5\u05d1"
    ],
    "name:hun_x_preferred":[
        "Pruszk\u00f3w"
    ],
    "name:isl_x_preferred":[
        "Pruszk\u00f3w"
    ],
    "name:ita_x_preferred":[
        "Pruszk\u00f3w"
    ],
    "name:jav_x_preferred":[
        "Pruszk\u00f3w"
    ],
    "name:jpn_x_preferred":[
        "\u30d7\u30eb\u30b7\u30e5\u30af\u30d5"
    ],
    "name:kor_x_preferred":[
        "\ud504\ub8e8\uc288\ucfe0\ud504"
    ],
    "name:lav_x_preferred":[
        "Pru\u0161kova"
    ],
    "name:lit_x_preferred":[
        "Pru\u0161kuvas"
    ],
    "name:mkd_x_preferred":[
        "\u041f\u0440\u0443\u0448\u043a\u043e\u0432"
    ],
    "name:msa_x_preferred":[
        "Pruszk\u00f3w"
    ],
    "name:nld_x_preferred":[
        "Pruszk\u00f3w"
    ],
    "name:pol_x_preferred":[
        "Pruszk\u00f3w"
    ],
    "name:por_x_preferred":[
        "Pruszk\u00f3w"
    ],
    "name:ron_x_preferred":[
        "Pruszk\u00f3w"
    ],
    "name:rus_x_preferred":[
        "\u041f\u0440\u0443\u0448\u043a\u0443\u0432"
    ],
    "name:rus_x_variant":[
        "\u041f\u0440\u0443\u0448\u043a\u043e\u0432"
    ],
    "name:slk_x_preferred":[
        "Pruszk\u00f3w"
    ],
    "name:spa_x_preferred":[
        "Pruszk\u00f3w"
    ],
    "name:srp_x_preferred":[
        "\u041f\u0440\u0443\u0448\u043a\u043e\u0432"
    ],
    "name:swe_x_preferred":[
        "Pruszk\u00f3w"
    ],
    "name:szl_x_preferred":[
        "Pruszk\u016fw"
    ],
    "name:tat_x_preferred":[
        "\u041f\u0440\u0443\u0448\u043a\u0443\u0432"
    ],
    "name:ukr_x_preferred":[
        "\u041f\u0440\u0443\u0448\u043a\u0443\u0432"
    ],
    "name:unk_x_variant":[
        "Prushkov"
    ],
    "name:vie_x_preferred":[
        "Pruszk\u00f3w"
    ],
    "name:war_x_preferred":[
        "Pruszk\u00f3w"
    ],
    "name:zho_x_preferred":[
        "\u666e\u9b6f\u65af\u79d1\u592b"
    ],
    "qs_pg:aaroncc":"PL",
    "qs_pg:gn_country":"PL",
    "qs_pg:gn_fcode":"PPLA2",
    "qs_pg:gn_pop":55371,
    "qs_pg:name":"Pruszk\u00f3w",
    "qs_pg:photos_9r":0,
    "qs_pg:photos_sr":0,
    "qs_pg:pop_sr":8,
    "qs_pg:qs_pg_placetype":"locality",
    "wof:name":"Pruszk\u00f3w",
    "wof:placetype":"locality",
    "wof:population":55371
},
  "geometry": {"coordinates":[20.81214,52.17072],"type":"Point"}
}