{
  "type": "Feature",
  "properties": {
    "gn:gn_country":"PL",
    "gn:gn_fcode":"PPLA2",
    "gn:gn_pop":55371,
    "gn:population":55371,
    "iso:country":"PL",
    "name:bul_x_preferred":[
        "\u041f\u0440\u0443\u0448\u043a\u043e\u0432"
    ],
    "name:deu_x_preferred":[
        "Pruszk\u00f3w"
    ],
    "name:eng_x_preferred":[
        "Pruszk\u00f3w"
    ],
    "name:jpn_x_preferred":[
        "\u30d7\u30eb\u30b7\u30e5\u30af\u30d5"
    ],
    "name:lav_x_preferred":[
        "Pru\u0161kova"
    ],
    "name:lit_x_preferred":[
        "Pru\u0161kuvas"
    ],
    "name:nld_x_preferred":[
        "Pruszk\u00f3w"
    ],
    "name:pol_x_preferred":[
        "Pruszk\u00f3w"
    ],
    "name:ron_x_preferred":[
        "Pruszk\u00f3w"
    ],
    "name:rus_x_preferred":[
        "\u041f\u0440\u0443\u0448\u043a\u0443\u0432"
    ],
    "name:srp_x_preferred":[
        "\u041f\u0440\u0443\u0448\u043a\u043e\u0432"
    ],
    "name:tat_x_preferred":[
        "\u041f\u0440\u0443\u0448\u043a\u0443\u0432"
    ],
    "name:ukr_x_preferred":[
        "\u041f\u0440\u0443\u0448\u043a\u0443\u0432"
    ],
    "name:unk_x_variant":[
        "Prushkov"
    ],
    "name:zho_x_preferred":[
        "\u666e\u9b6f\u65af\u79d1\u592b"
    ],
    "qs_pg:aaroncc":"PL",
    "qs_pg:gn_country":"PL",
    "qs_pg:gn_fcode":"PPLA2",
    "qs_pg:gn_pop":55371,
    "qs_pg:name":"Pruszk\u00f3w",
    "qs_pg:photos_9r":0,
    "qs_pg:photos_sr":0,
    "qs_pg:pop_sr":8,
    "qs_pg:qs_pg_placetype":"locality",
    "wof:name":"Pruszk\u00f3w",
    "wof:placetype":"locality",
    "wof:population":55371
},
  "geometry": {"coordinates":[20.81214,52.17072],"type":"Point"}
}