{
  "type": "Feature",
  "properties": {
    "gn:admin1_code":"87.0",
    "gn:admin2_code":"3201.0",
    "gn:admin3_code":"320102.0",
    "gn:asciiname":"Klepino Bialogardskie",
    "gn:country_code":"PL",
    "gn:dem":45,
    "gn:feature_class":"P",
    "gn:feature_code":"PPL",
    "gn:name":"Kl\u0119pino Bia\u0142ogardskie",
    "gn:population":0,
    "gn:timezone":"Europe/Warsaw",
    "iso:country":"PL",
    "wof:name":"Klepino Bialogardskie",
    "wof:placetype":"locality"
},
  "geometry": {"coordinates":[16.05966,53.99901],"type":"Point"}
}