{
  "type": "Feature",
  "properties": {
    "gn:admin1_code":"78.0",
    "gn:admin2_code":"1427.0",
    "gn:admin3_code":"142703.0",
    "gn:asciiname":"Ligowo",
    "gn:country_code":"PL",
    "gn:dem":109,
    "gn:feature_class":"P",
    "gn:feature_code":"PPL",
    "gn:name":"Ligowo",
    "gn:population":0,
    "gn:timezone":"Europe/Warsaw",
    "iso:country":"PL",
    "name:azb_x_preferred":[
        "\u0644\u06cc\u0642\u0648\u0648\u0648"
    ],
    "name:ceb_x_preferred":[
        "Ligowo"
    ],
    "name:fas_x_preferred":[
        "\u0644\u06cc\u06af\u0648\u0648\u0648"
    ],
    "name:fra_x_preferred":[
        "Ligowo"
    ],
    "name:pol_x_preferred":[
        "Ligowo"
    ],
    "name:rus_x_preferred":[
        "\u041b\u0438\u0433\u043e\u0432\u043e"
    ],
    "name:ukr_x_preferred":[
        "\u041b\u0456\u0491\u043e\u0432\u043e"
    ],
    "wof:name":"Ligowo",
    "wof:placetype":"locality"
},
  "geometry": {"coordinates":[19.48065,52.82455],"type":"Point"}
}