{
  "type": "Feature",
  "properties": {
    "gn:admin1_code":"86.0",
    "gn:admin2_code":"3028.0",
    "gn:admin3_code":"302807.0",
    "gn:asciiname":"Wiatrowo",
    "gn:country_code":"PL",
    "gn:dem":79,
    "gn:feature_class":"P",
    "gn:feature_code":"PPL",
    "gn:name":"Wiatrowo",
    "gn:population":0,
    "gn:timezone":"Europe/Warsaw",
    "iso:country":"PL",
    "name:ceb_x_preferred":[
        "Wiatrowo"
    ],
    "name:fra_x_preferred":[
        "Wiatrowo"
    ],
    "name:pol_x_preferred":[
        "Wiatrowo"
    ],
    "name:ukr_x_preferred":[
        "\u0412\u044f\u0442\u0440\u043e\u0432\u043e"
    ],
    "wof:name":"Wiatrowo",
    "wof:placetype":"locality"
},
  "geometry": {"coordinates":[17.13179,52.75785],"type":"Point"}
}