{
  "type": "Feature",
  "properties": {
    "gn:admin1_code":"78.0",
    "gn:admin2_code":"1413.0",
    "gn:admin3_code":"141308.0",
    "gn:asciiname":"Pawlowo",
    "gn:country_code":"PL",
    "gn:dem":149,
    "gn:feature_class":"P",
    "gn:feature_code":"PPL",
    "gn:name":"Paw\u0142owo",
    "gn:population":0,
    "gn:timezone":"Europe/Warsaw",
    "iso:country":"PL",
    "name:fra_x_preferred":[
        "Paw\u0142owo"
    ],
    "name:pol_x_preferred":[
        "Paw\u0142owo"
    ],
    "name:ukr_x_preferred":[
        "\u041f\u0430\u0432\u043b\u043e\u0432\u043e"
    ],
    "wof:name":"Pawlowo",
    "wof:placetype":"locality"
},
  "geometry": {"coordinates":[20.48563,53.09009],"type":"Point"}
}