{
  "type": "Feature",
  "properties": {
    "gn:admin1_code":"74.0",
    "gn:admin2_code":"1012.0",
    "gn:admin3_code":"101205.0",
    "gn:asciiname":"Podjezioro",
    "gn:country_code":"PL",
    "gn:dem":212,
    "gn:feature_class":"P",
    "gn:feature_code":"PPL",
    "gn:name":"Podjezioro",
    "gn:population":0,
    "gn:timezone":"Europe/Warsaw",
    "iso:country":"PL",
    "name:fra_x_preferred":[
        "Podjezioro"
    ],
    "name:pol_x_preferred":[
        "Podjezioro"
    ],
    "name:ukr_x_preferred":[
        "\u041f\u043e\u0434\u0454\u0437\u044c\u043e\u0440\u043e"
    ],
    "wof:name":"Podjezioro",
    "wof:placetype":"locality"
},
  "geometry": {"coordinates":[19.47311,51.24956],"type":"Point"}
}