{
  "type": "Feature",
  "properties": {
    "gn:admin1_code":"85.0",
    "gn:admin2_code":"2804.0",
    "gn:admin3_code":"280407.0",
    "gn:asciiname":"Rogowo",
    "gn:country_code":"PL",
    "gn:dem":108,
    "gn:feature_class":"P",
    "gn:feature_code":"PPL",
    "gn:name":"Rogowo",
    "gn:population":0,
    "gn:timezone":"Europe/Warsaw",
    "iso:country":"PL",
    "name:pol_x_preferred":[
        "Rogowo"
    ],
    "name:ukr_x_preferred":[
        "\u0420\u043e\u0491\u043e\u0432\u043e"
    ],
    "name:und_x_variant":[
        "Rogau"
    ],
    "wof:name":"Rogowo",
    "wof:placetype":"locality"
},
  "geometry": {"coordinates":[19.57743,54.13687],"type":"Point"}
}