{
  "type": "Feature",
  "properties": {
    "gn:admin1_code":"78.0",
    "gn:admin2_code":"1463.0",
    "gn:admin3_code":"146301.0",
    "gn:asciiname":"Halinow",
    "gn:country_code":"PL",
    "gn:dem":156,
    "gn:feature_class":"P",
    "gn:feature_code":"PPL",
    "gn:name":"Halin\u00f3w",
    "gn:population":0,
    "gn:timezone":"Europe/Warsaw",
    "iso:country":"PL",
    "wof:name":"Halinow",
    "wof:placetype":"neighbourhood"
},
  "geometry": {"coordinates":[21.10491,51.39253],"type":"Point"}
}