{
  "type": "Feature",
  "properties": {
    "gn:admin1_code":"72.0",
    "gn:admin2_code":"223.0",
    "gn:admin3_code":"22303.0",
    "gn:asciiname":"Piotrowek",
    "gn:country_code":"PL",
    "gn:dem":178,
    "gn:feature_class":"P",
    "gn:feature_code":"PPL",
    "gn:name":"Piotr\u00f3wek",
    "gn:population":0,
    "gn:timezone":"Europe/Warsaw",
    "iso:country":"PL",
    "name:pol_x_preferred":[
        "Piotr\u00f3wek"
    ],
    "name:ukr_x_preferred":[
        "\u041f\u0439\u043e\u0442\u0440\u0443\u0432\u0435\u043a"
    ],
    "wof:name":"Piotrowek",
    "wof:placetype":"locality"
},
  "geometry": {"coordinates":[16.81865,50.83613],"type":"Point"}
}