{
  "type": "Feature",
  "properties": {
    "gn:admin1_code":"87.0",
    "gn:admin2_code":"3207.0",
    "gn:admin3_code":"320705.0",
    "gn:asciiname":"Krzepocin",
    "gn:country_code":"PL",
    "gn:dem":16,
    "gn:feature_class":"P",
    "gn:feature_code":"PPL",
    "gn:name":"Krzepocin",
    "gn:population":0,
    "gn:timezone":"Europe/Warsaw",
    "iso:country":"PL",
    "name:pol_x_preferred":[
        "Krzepocin"
    ],
    "name:ukr_x_preferred":[
        "\u041a\u0448\u0435\u043f\u043e\u0446\u0438\u043d"
    ],
    "name:vie_x_preferred":[
        "Krzepocin"
    ],
    "wof:name":"Krzepocin",
    "wof:placetype":"locality"
},
  "geometry": {"coordinates":[14.9778,53.9102],"type":"Point"}
}