{
  "type": "Feature",
  "properties": {
    "iso:country":"PL",
    "name:ceb_x_preferred":[
        "Czarna"
    ],
    "name:deu_x_preferred":[
        "Czarna"
    ],
    "name:fra_x_preferred":[
        "Czarna"
    ],
    "name:hun_x_preferred":[
        "Czarna"
    ],
    "name:ita_x_preferred":[
        "Czarna"
    ],
    "name:nld_x_preferred":[
        "Czarna"
    ],
    "name:pol_x_preferred":[
        "Czarna"
    ],
    "name:rus_x_preferred":[
        "\u0427\u0430\u0440\u043d\u0430"
    ],
    "name:ukr_x_preferred":[
        "\u0427\u0430\u0440\u043d\u0430"
    ],
    "wof:coterminous":[
        1125272681
    ],
    "wof:name":"Czarna",
    "wof:placetype":"locality"
},
  "geometry": {"coordinates":[22.5853040731102,49.3144263534433],"type":"Point"}
}