{
  "type": "Feature",
  "properties": {
    "iso:country":"PL",
    "name:pol_x_preferred":[
        "Czarna"
    ],
    "wof:coterminous":[
        1125272681
    ],
    "wof:name":"Czarna",
    "wof:placetype":"locality"
},
  "geometry": {"coordinates":[22.5853040731102,49.3144263534433],"type":"Point"}
}