{
  "type": "Feature",
  "properties": {
    "gn:admin1_code":"78.0",
    "gn:admin2_code":"1418.0",
    "gn:admin3_code":"141805.0",
    "gn:asciiname":"Lawki",
    "gn:country_code":"PL",
    "gn:dem":112,
    "gn:feature_class":"P",
    "gn:feature_code":"PPL",
    "gn:name":"\u0141awki",
    "gn:population":0,
    "gn:timezone":"Europe/Warsaw",
    "iso:country":"PL",
    "name:fra_x_preferred":[
        "\u0141awki"
    ],
    "name:pol_x_preferred":[
        "\u0141awki"
    ],
    "name:tgl_x_preferred":[
        "\u0141awki"
    ],
    "name:ukr_x_preferred":[
        "\u041b\u0430\u0432\u043a\u0456"
    ],
    "wof:name":"Lawki",
    "wof:placetype":"locality"
},
  "geometry": {"coordinates":[21.07727,51.94797],"type":"Point"}
}