{
  "type": "Feature",
  "properties": {
    "gn:population":3390,
    "iso:country":"PL",
    "name:deu_x_preferred":[
        "Spytkowice"
    ],
    "name:nld_x_preferred":[
        "Spytkowice"
    ],
    "name:pol_x_preferred":[
        "Spytkowice"
    ],
    "qs:a0":"Rzeczpospolita Polska",
    "qs:a1":"*Malopolskie",
    "qs:a1r":"0",
    "qs:a2":"Nowotarski",
    "qs:adm0":"Rzeczpospolita Polska",
    "qs:la_lc":"*",
    "qs:level":"locality",
    "qs:loc":"Spytkowice",
    "qs:loc_alt":"Spytkowice",
    "qs:pop":0,
    "qs:type":"buffered point",
    "wd:wordcount":103,
    "wof:name":"Spytkowice",
    "wof:placetype":"locality",
    "wof:population":3390
},
  "geometry": {"coordinates":[19.833918,49.577057],"type":"Point"}
}