{
  "type": "Feature",
  "properties": {
    "gn:population":3390,
    "iso:country":"PL",
    "name:ast_x_preferred":[
        "Spytkowice"
    ],
    "name:azb_x_preferred":[
        "\u0633\u067e\u062a\u06a9\u0648\u0648\u06cc\u062a\u0633\u0647"
    ],
    "name:deu_x_preferred":[
        "Spytkowice"
    ],
    "name:eng_x_preferred":[
        "Spytkowice"
    ],
    "name:fas_x_preferred":[
        "\u0633\u067e\u062a\u06a9\u0648\u0648\u06cc\u062a\u0633\u0647"
    ],
    "name:fra_x_preferred":[
        "Spytkowice"
    ],
    "name:nld_x_preferred":[
        "Spytkowice"
    ],
    "name:pol_x_preferred":[
        "Spytkowice"
    ],
    "name:ukr_x_preferred":[
        "\u0421\u043f\u0438\u0442\u043a\u043e\u0432\u0456\u0446\u0435"
    ],
    "name:zho_x_preferred":[
        "\u53f2\u6bd4\u9ad8\u7dad\u8332"
    ],
    "qs:a0":"Rzeczpospolita Polska",
    "qs:a1":"*Malopolskie",
    "qs:a1r":"0",
    "qs:a2":"Nowotarski",
    "qs:adm0":"Rzeczpospolita Polska",
    "qs:la_lc":"*",
    "qs:level":"locality",
    "qs:loc":"Spytkowice",
    "qs:loc_alt":"Spytkowice",
    "qs:pop":0,
    "qs:type":"buffered point",
    "wd:wordcount":103,
    "wof:name":"Spytkowice",
    "wof:placetype":"locality",
    "wof:population":3390
},
  "geometry": {"coordinates":[19.833918,49.577057],"type":"Point"}
}