{
  "type": "Feature",
  "properties": {
    "gn:admin1_code":"79.0",
    "gn:admin2_code":"1607.0",
    "gn:admin3_code":"160705.0",
    "gn:asciiname":"Przelek",
    "gn:country_code":"PL",
    "gn:dem":218,
    "gn:feature_class":"P",
    "gn:feature_code":"PPL",
    "gn:name":"Prze\u0142\u0119k",
    "gn:population":0,
    "gn:timezone":"Europe/Warsaw",
    "iso:country":"PL",
    "name:pol_x_preferred":[
        "Prze\u0142\u0119k"
    ],
    "name:ukr_x_preferred":[
        "\u041f\u0448\u0435\u043b\u0435\u043d\u043a"
    ],
    "wof:name":"Przelek",
    "wof:placetype":"locality"
},
  "geometry": {"coordinates":[17.33299,50.41114],"type":"Point"}
}