{
  "type": "Feature",
  "properties": {
    "iso:country":"PL",
    "wof:name":"Stary Widzew",
    "wof:placetype":"neighbourhood"
},
  "geometry": {"coordinates":[19.50109619810893,51.76166049902423],"type":"Point"}
}