{
  "type": "Feature",
  "properties": {
    "gn:gn_country":"PL",
    "gn:gn_fcode":"PPLA3",
    "gn:gn_pop":8991,
    "gn:population":8991,
    "iso:country":"PL",
    "name:lav_x_preferred":[
        "Opale\u0146ica"
    ],
    "name:rus_x_preferred":[
        "\u041e\u043f\u0430\u043b\u0435\u043d\u0438\u0446\u0430"
    ],
    "name:srp_x_preferred":[
        "\u041e\u043f\u0430\u043b\u0435\u045a\u0438\u0446\u0430"
    ],
    "name:ukr_x_preferred":[
        "\u041e\u043f\u0430\u043b\u0435\u043d\u0438\u0446\u044f"
    ],
    "name:zho_x_preferred":[
        "\u5967\u5e15\u840a\u5c3c\u5bdf"
    ],
    "qs_pg:aaroncc":"PL",
    "qs_pg:gn_country":"PL",
    "qs_pg:gn_fcode":"PPLA3",
    "qs_pg:gn_pop":8991,
    "qs_pg:name":"Opalenica",
    "qs_pg:name_adm0":"Polska",
    "qs_pg:name_adm1":"Wielkopolskie",
    "qs_pg:photos_9r":0,
    "qs_pg:photos_sr":0,
    "qs_pg:pop_sr":5,
    "qs_pg:qs_pg_placetype":"localadmin",
    "qs_pg:qs_pg_placetype_gp":"LocalAdmin",
    "qs_pg:woe_adm0":23424923,
    "woe:adm0_id":23424923,
    "woe:name_adm0":"Polska",
    "woe:name_adm1":"Wielkopolskie",
    "woe:placetype":"LocalAdmin",
    "wof:name":"Opalenica",
    "wof:placetype":"localadmin",
    "wof:population":8991
},
  "geometry": {"coordinates":[16.41278,52.30887],"type":"Point"}
}