{
  "type": "Feature",
  "properties": {
    "gn:population":2421,
    "iso:country":"PL",
    "name:ast_x_preferred":[
        "Herby"
    ],
    "name:azb_x_preferred":[
        "\u062e\u0631\u0628\u0647"
    ],
    "name:ceb_x_preferred":[
        "Herby"
    ],
    "name:eng_x_preferred":[
        "Herby"
    ],
    "name:fas_x_preferred":[
        "\u062e\u0631\u0628\u0647"
    ],
    "name:fra_x_preferred":[
        "Herby"
    ],
    "name:nan_x_preferred":[
        "Herby"
    ],
    "name:nld_x_preferred":[
        "Herby"
    ],
    "name:pol_x_preferred":[
        "Herby"
    ],
    "name:ukr_x_preferred":[
        "\u0413\u0435\u0440\u0431\u0438"
    ],
    "name:zho_min_nan_x_preferred":[
        "Herby"
    ],
    "qs:a0":"Rzeczpospolita Polska",
    "qs:a1":"*Slaskie",
    "qs:a1r":"0",
    "qs:a2":"Lubliniecki",
    "qs:adm0":"Rzeczpospolita Polska",
    "qs:la":"Herby",
    "qs:la_lc":"*PL2407042",
    "qs:level":"locality",
    "qs:loc":"Herby",
    "qs:loc_alt":"Herby",
    "qs:pop":0,
    "qs:type":"rural point-in-poly",
    "wd:wordcount":119,
    "wof:name":"Herby",
    "wof:placetype":"locality",
    "wof:population":2421
},
  "geometry": {"coordinates":[18.8297152661238,50.7364213638343],"type":"Point"}
}