{
  "type": "Feature",
  "properties": {
    "gn:admin1_code":"82.0",
    "gn:admin2_code":"2202.0",
    "gn:admin3_code":"220202.0",
    "gn:asciiname":"Kaszuba",
    "gn:country_code":"PL",
    "gn:dem":135,
    "gn:feature_class":"P",
    "gn:feature_code":"PPL",
    "gn:name":"Kaszuba",
    "gn:population":0,
    "gn:timezone":"Europe/Warsaw",
    "iso:country":"PL",
    "wof:name":"Kaszuba",
    "wof:placetype":"locality"
},
  "geometry": {"coordinates":[17.64845,53.94491],"type":"Point"}
}