{
  "type": "Feature",
  "properties": {
    "gn:country":"PL",
    "gn:fcode":"PPL",
    "gn:population":334,
    "iso:country":"PL",
    "name:ast_x_preferred":[
        "Lubieszyn"
    ],
    "name:ceb_x_preferred":[
        "Lubieszyn"
    ],
    "name:ces_x_preferred":[
        "Lubieszyn"
    ],
    "name:che_x_preferred":[
        "\u041b\u044e\u0431\u0435\u0448\u0438\u043d"
    ],
    "name:eng_x_preferred":[
        "Lubieszyn"
    ],
    "name:fra_x_preferred":[
        "Lubieszyn"
    ],
    "name:nan_x_preferred":[
        "Lubieszyn"
    ],
    "name:pol_x_preferred":[
        "Lubieszyn"
    ],
    "name:tat_x_preferred":[
        "\u041b\u044e\u0431\u0435\u0448\u0438\u043d"
    ],
    "name:ukr_x_preferred":[
        "\u041b\u044e\u0431\u0435\u0448\u0438\u043d"
    ],
    "qs_pg:aaroncc":"PL",
    "qs_pg:gn_country":"PL",
    "qs_pg:gn_fcode":"PPL",
    "qs_pg:gn_pop":334,
    "qs_pg:name":"Lubierzyn",
    "qs_pg:name_adm0":"Polska",
    "qs_pg:name_adm1":"Kujawsko-Pomorskie",
    "qs_pg:photos_9r":0,
    "qs_pg:photos_sr":0,
    "qs_pg:pop_sr":2,
    "qs_pg:qs_pg_placetype":"locality",
    "qs_pg:qs_pg_placetype_gp":"Town",
    "qs_pg:woe_adm0":23424923,
    "woe:adm0_id":23424923,
    "woe:name_adm0":"Polska",
    "woe:name_adm1":"Kujawsko-Pomorskie",
    "woe:placetype":"Town",
    "wof:name":"Lubierzyn",
    "wof:placetype":"locality",
    "wof:population":334
},
  "geometry": {"coordinates":[18.2373,54.10732],"type":"Point"}
}