{
  "type": "Feature",
  "properties": {
    "gn:admin1_code":"85.0",
    "gn:admin2_code":"2806.0",
    "gn:admin3_code":"280608.0",
    "gn:asciiname":"Grzybowo",
    "gn:country_code":"PL",
    "gn:dem":127,
    "gn:feature_class":"P",
    "gn:feature_code":"PPL",
    "gn:name":"Grzybowo",
    "gn:population":0,
    "gn:timezone":"Europe/Warsaw",
    "iso:country":"PL",
    "name:und_x_variant":[
        "Birkensee",
        "Grzybowen",
        "Grzybowo"
    ],
    "wof:name":"Grzybowo",
    "wof:placetype":"locality"
},
  "geometry": {"coordinates":[21.59223,54.03199],"type":"Point"}
}