{
  "type": "Feature",
  "properties": {
    "gn:admin1_code":"80.0",
    "gn:admin2_code":"1804.0",
    "gn:admin3_code":"180406.0",
    "gn:asciiname":"Cieszacin Maly",
    "gn:country_code":"PL",
    "gn:dem":214,
    "gn:feature_class":"P",
    "gn:feature_code":"PPL",
    "gn:name":"Cieszacin Ma\u0142y",
    "gn:population":0,
    "gn:timezone":"Europe/Warsaw",
    "iso:country":"PL",
    "wof:name":"Cieszacin Maly",
    "wof:placetype":"locality"
},
  "geometry": {"coordinates":[22.57484,49.99737],"type":"Point"}
}