{
  "type": "Feature",
  "properties": {
    "gn:admin1_code":"74.0",
    "gn:admin2_code":"1002.0",
    "gn:admin3_code":"100211.0",
    "gn:asciiname":"Biala",
    "gn:country_code":"PL",
    "gn:dem":98,
    "gn:feature_class":"P",
    "gn:feature_code":"PPL",
    "gn:name":"Bia\u0142a",
    "gn:population":0,
    "gn:timezone":"Europe/Warsaw",
    "iso:country":"PL",
    "name:fra_x_preferred":[
        "Bia\u0142a"
    ],
    "name:pol_x_preferred":[
        "Bia\u0142a"
    ],
    "name:ukr_x_preferred":[
        "\u0411\u0456\u043b\u0430"
    ],
    "wof:name":"Biala",
    "wof:placetype":"locality"
},
  "geometry": {"coordinates":[19.69952,52.22012],"type":"Point"}
}