{
  "type": "Feature",
  "properties": {
    "gn:admin1_code":"81.0",
    "gn:admin2_code":"2001.0",
    "gn:admin3_code":"200105.0",
    "gn:asciiname":"Szczepki",
    "gn:country_code":"PL",
    "gn:dem":130,
    "gn:feature_class":"P",
    "gn:feature_code":"PPL",
    "gn:name":"Szczepki",
    "gn:population":0,
    "gn:timezone":"Europe/Warsaw",
    "iso:country":"PL",
    "name:lit_x_preferred":[
        "\u0160\u010depkai"
    ],
    "name:pol_x_preferred":[
        "Szczepki"
    ],
    "name:ukr_x_preferred":[
        "\u0429\u0435\u043f\u043a\u0456"
    ],
    "wof:name":"Szczepki",
    "wof:placetype":"locality"
},
  "geometry": {"coordinates":[22.9662,53.95653000000001],"type":"Point"}
}