{
  "type": "Feature",
  "properties": {
    "gn:admin1_code":"83.0",
    "gn:admin2_code":"2404.0",
    "gn:admin3_code":"240410.0",
    "gn:asciiname":"Kuchary",
    "gn:country_code":"PL",
    "gn:dem":244,
    "gn:feature_class":"P",
    "gn:feature_code":"PPL",
    "gn:name":"Kuchary",
    "gn:population":0,
    "gn:timezone":"Europe/Warsaw",
    "iso:country":"PL",
    "name:ceb_x_preferred":[
        "Kuchary"
    ],
    "name:pol_x_preferred":[
        "Kuchary"
    ],
    "name:ukr_x_preferred":[
        "\u041a\u0443\u0445\u0430\u0440\u0438"
    ],
    "wof:name":"Kuchary",
    "wof:placetype":"locality"
},
  "geometry": {"coordinates":[19.30641,50.85749000000001],"type":"Point"}
}