{
  "type": "Feature",
  "properties": {
    "gn:admin1_code":"85.0",
    "gn:admin2_code":"2817.0",
    "gn:admin3_code":"281702.0",
    "gn:asciiname":"Zimna Woda",
    "gn:country_code":"PL",
    "gn:dem":150,
    "gn:feature_class":"P",
    "gn:feature_code":"PPL",
    "gn:name":"Zimna Woda",
    "gn:population":0,
    "gn:timezone":"Europe/Warsaw",
    "iso:country":"PL",
    "name:fra_x_preferred":[
        "Zimna Woda"
    ],
    "name:pol_x_preferred":[
        "Zimna Woda"
    ],
    "name:ukr_x_preferred":[
        "\u0417\u0456\u043c\u043d\u0430-\u0412\u043e\u0434\u0430"
    ],
    "name:und_x_variant":[
        "Hirschthal",
        "Zimnawodda"
    ],
    "wof:name":"Zimna Woda",
    "wof:placetype":"locality"
},
  "geometry": {"coordinates":[21.16307,53.67104000000001],"type":"Point"}
}