{
  "type": "Feature",
  "properties": {
    "gn:admin1_code":"77.0",
    "gn:admin2_code":"1205.0",
    "gn:admin3_code":"120509.0",
    "gn:asciiname":"Lipna",
    "gn:country_code":"PL",
    "gn:dem":545,
    "gn:feature_class":"P",
    "gn:feature_code":"PPL",
    "gn:name":"Lipna",
    "gn:population":0,
    "gn:timezone":"Europe/Warsaw",
    "iso:country":"PL",
    "name:pol_x_preferred":[
        "Lipna"
    ],
    "name:rus_x_preferred":[
        "\u041b\u0438\u043f\u043d\u0430"
    ],
    "name:ukr_x_preferred":[
        "\u041b\u0438\u043f\u043d\u0430"
    ],
    "wof:name":"Lipna",
    "wof:placetype":"locality"
},
  "geometry": {"coordinates":[21.35,49.46667],"type":"Point"}
}