{
  "type": "Feature",
  "properties": {
    "gn:admin1_code":"86.0",
    "gn:admin2_code":"3009.0",
    "gn:admin3_code":"300902.0",
    "gn:asciiname":"Kiejsze",
    "gn:country_code":"PL",
    "gn:dem":109,
    "gn:feature_class":"P",
    "gn:feature_code":"PPL",
    "gn:name":"Kiejsze",
    "gn:population":0,
    "gn:timezone":"Europe/Warsaw",
    "iso:country":"PL",
    "name:pol_x_preferred":[
        "Kiejsze"
    ],
    "name:ukr_x_preferred":[
        "\u041a\u0435\u0439\u0448\u0435"
    ],
    "wof:name":"Kiejsze",
    "wof:placetype":"locality"
},
  "geometry": {"coordinates":[18.70499,52.30494],"type":"Point"}
}