{
  "type": "Feature",
  "properties": {
    "gn:admin1_code":"86.0",
    "gn:admin2_code":"3016.0",
    "gn:admin3_code":"301601.0",
    "gn:asciiname":"Lukowo",
    "gn:country_code":"PL",
    "gn:dem":78,
    "gn:feature_class":"P",
    "gn:feature_code":"PPL",
    "gn:name":"\u0141ukowo",
    "gn:population":0,
    "gn:timezone":"Europe/Warsaw",
    "iso:country":"PL",
    "wof:name":"Lukowo",
    "wof:placetype":"locality"
},
  "geometry": {"coordinates":[16.8786,52.63879],"type":"Point"}
}