{
  "type": "Feature",
  "properties": {
    "gn:admin1_code":"85.0",
    "gn:admin2_code":"2818.0",
    "gn:admin3_code":"281803.0",
    "gn:asciiname":"Kumiecie",
    "gn:country_code":"PL",
    "gn:dem":163,
    "gn:feature_class":"P",
    "gn:feature_code":"PPL",
    "gn:name":"Kumiecie",
    "gn:population":0,
    "gn:timezone":"Europe/Warsaw",
    "iso:country":"PL",
    "name:und_x_variant":[
        "Hermeshof",
        "Gross Kummetschen",
        "Hermenshof",
        "Kumiecie"
    ],
    "wof:name":"Kumiecie",
    "wof:placetype":"neighbourhood"
},
  "geometry": {"coordinates":[22.31279,54.32318000000001],"type":"Point"}
}