{
  "type": "Feature",
  "properties": {
    "gn:admin1_code":"72.0",
    "gn:admin2_code":"204.0",
    "gn:admin3_code":"20403.0",
    "gn:asciiname":"Klimontow",
    "gn:country_code":"PL",
    "gn:dem":83,
    "gn:feature_class":"P",
    "gn:feature_code":"PPL",
    "gn:name":"Klimont\u00f3w",
    "gn:population":0,
    "gn:timezone":"Europe/Warsaw",
    "iso:country":"PL",
    "wof:name":"Klimontow",
    "wof:placetype":"locality"
},
  "geometry": {"coordinates":[16.33472,51.69694000000001],"type":"Point"}
}