{
  "type": "Feature",
  "properties": {
    "gn:admin1_code":"75.0",
    "gn:admin2_code":"619.0",
    "gn:admin3_code":"61905.0",
    "gn:asciiname":"Zawadowka",
    "gn:country_code":"PL",
    "gn:dem":173,
    "gn:feature_class":"P",
    "gn:feature_code":"PPL",
    "gn:name":"Zawad\u00f3wka",
    "gn:population":0,
    "gn:timezone":"Europe/Warsaw",
    "iso:country":"PL",
    "name:fra_x_preferred":[
        "Zawad\u00f3wka"
    ],
    "name:pol_x_preferred":[
        "Zawad\u00f3wka"
    ],
    "name:ukr_x_preferred":[
        "\u0417\u0430\u0432\u0430\u0434\u0443\u0432\u043a\u0430"
    ],
    "wof:name":"Zawadowka",
    "wof:placetype":"locality"
},
  "geometry": {"coordinates":[23.11566,51.42346],"type":"Point"}
}