{
  "type": "Feature",
  "properties": {
    "gn:admin1_code":"72.0",
    "gn:admin2_code":"207.0",
    "gn:admin3_code":"20702.0",
    "gn:asciiname":"Raszow",
    "gn:country_code":"PL",
    "gn:dem":533,
    "gn:feature_class":"P",
    "gn:feature_code":"PPL",
    "gn:name":"Rasz\u00f3w",
    "gn:population":0,
    "gn:timezone":"Europe/Warsaw",
    "iso:country":"PL",
    "name:azb_x_preferred":[
        "\u0631\u0627\u0634\u0648\u0648"
    ],
    "name:deu_x_historical":[
        "Reu\u00dfendorf"
    ],
    "name:deu_x_preferred":[
        "Reu\u00dfendorf"
    ],
    "name:deu_x_variant":[
        "Rasz\u00f3w"
    ],
    "name:fas_x_preferred":[
        "\u0631\u0627\u0634\u0648\u0648"
    ],
    "name:nld_x_preferred":[
        "Rasz\u00f3w"
    ],
    "name:pol_x_preferred":[
        "Rasz\u00f3w"
    ],
    "name:ukr_x_preferred":[
        "\u0420\u0430\u0448\u0443\u0432"
    ],
    "wof:name":"Raszow",
    "wof:placetype":"locality"
},
  "geometry": {"coordinates":[15.98305,50.80301],"type":"Point"}
}