{
  "type": "Feature",
  "properties": {
    "iso:country":"PL",
    "name:azb_x_preferred":[
        "\u0642\u0645\u06cc\u0646\u0627 \u0627\u06cc\u0648\u0627\u0648\u0627"
    ],
    "name:bel_x_preferred":[
        "\u0406\u043b\u0430\u0432\u0430"
    ],
    "name:deu_x_preferred":[
        "I\u0142awa"
    ],
    "name:eus_x_preferred":[
        "I\u0142awa landa-udalerria"
    ],
    "name:fas_x_preferred":[
        "\u06af\u0645\u06cc\u0646\u0627 \u0627\u06cc\u0648\u0627\u0648\u0627"
    ],
    "name:fra_x_preferred":[
        "I\u0142awa"
    ],
    "name:ita_x_preferred":[
        "I\u0142awa"
    ],
    "name:nld_x_preferred":[
        "I\u0142awa"
    ],
    "name:pol_x_preferred":[
        "I\u0142awa"
    ],
    "name:rus_x_preferred":[
        "\u0418\u043b\u0430\u0432\u0430"
    ],
    "name:slk_x_preferred":[
        "Gmina I\u0142awa"
    ],
    "name:ukr_x_preferred":[
        "\u0413\u043c\u0456\u043d\u0430 \u0406\u043b\u0430\u0432\u0430"
    ],
    "name:war_x_preferred":[
        "Gmina I\u0142awa"
    ],
    "qs_pg:aaroncc":"PL",
    "qs_pg:name":"Gmina I\u0142awa",
    "qs_pg:name_adm0":"Polska",
    "qs_pg:name_adm1":"Warminsko-Mazurskie",
    "qs_pg:photos":1,
    "qs_pg:photos_1k":1,
    "qs_pg:photos_9k":3,
    "qs_pg:photos_9r":5,
    "qs_pg:photos_all":717,
    "qs_pg:photos_sr":1,
    "qs_pg:pop_sr":0,
    "qs_pg:qs_pg_placetype":"localadmin",
    "qs_pg:qs_pg_placetype_gp":"LocalAdmin",
    "qs_pg:woe_adm0":23424923,
    "woe:adm0_id":23424923,
    "woe:name_adm0":"Polska",
    "woe:name_adm1":"Warminsko-Mazurskie",
    "woe:placetype":"LocalAdmin",
    "wof:name":"Gmina I\u0142awa",
    "wof:placetype":"localadmin"
},
  "geometry": {"coordinates":[19.588896,53.729267],"type":"Point"}
}