{
  "type": "Feature",
  "properties": {
    "gn:admin1_code":"78.0",
    "gn:admin2_code":"1420.0",
    "gn:admin3_code":"142004.0",
    "gn:asciiname":"Wolka Przybojewska",
    "gn:country_code":"PL",
    "gn:dem":93,
    "gn:feature_class":"P",
    "gn:feature_code":"PPL",
    "gn:name":"W\u00f3lka Przybojewska",
    "gn:population":0,
    "gn:timezone":"Europe/Warsaw",
    "iso:country":"PL",
    "name:und_x_variant":[
        "W\u00f3lka Przybojewska"
    ],
    "wof:name":"Wolka Przybojewska",
    "wof:placetype":"locality"
},
  "geometry": {"coordinates":[20.46978,52.4288],"type":"Point"}
}