{
  "type": "Feature",
  "properties": {
    "gn:admin1_code":"78.0",
    "gn:admin2_code":"1420.0",
    "gn:admin3_code":"142004.0",
    "gn:asciiname":"Wolka Przybojewska",
    "gn:country_code":"PL",
    "gn:dem":93,
    "gn:feature_class":"P",
    "gn:feature_code":"PPL",
    "gn:name":"W\u00f3lka Przybojewska",
    "gn:population":0,
    "gn:timezone":"Europe/Warsaw",
    "iso:country":"PL",
    "name:fra_x_preferred":[
        "W\u00f3lka Przyb\u00f3jewska"
    ],
    "name:pol_x_preferred":[
        "W\u00f3lka Przyb\u00f3jewska"
    ],
    "name:ukr_x_preferred":[
        "\u0412\u0443\u043b\u044c\u043a\u0430-\u041f\u0448\u0438\u0431\u0443\u0454\u0432\u0441\u044c\u043a\u0430"
    ],
    "name:und_x_variant":[
        "W\u00f3lka Przybojewska"
    ],
    "wof:name":"Wolka Przybojewska",
    "wof:placetype":"locality"
},
  "geometry": {"coordinates":[20.46978,52.4288],"type":"Point"}
}