{
  "type": "Feature",
  "properties": {
    "gn:population":2268,
    "iso:country":"PL",
    "name:azb_x_preferred":[
        "\u0642\u0645\u06cc\u0646\u0627 \u06a9\u0627\u0644\u06cc\u0633\u06a9\u0627"
    ],
    "name:bel_x_preferred":[
        "\u0413\u043c\u0456\u043d\u0430 \u041a\u0430\u043b\u0456\u0441\u043a\u0430"
    ],
    "name:ceb_x_preferred":[
        "Kaliska"
    ],
    "name:deu_x_preferred":[
        "Gmina Kaliska"
    ],
    "name:eng_x_preferred":[
        "Kaliska"
    ],
    "name:eng_x_variant":[
        "Gmina Kaliska"
    ],
    "name:eus_x_preferred":[
        "Kaliska udalerria"
    ],
    "name:fas_x_preferred":[
        "\u06af\u0645\u06cc\u0646\u0627 \u06a9\u0627\u0644\u06cc\u0633\u06a9\u0627"
    ],
    "name:fra_x_preferred":[
        "Kaliska"
    ],
    "name:ita_x_preferred":[
        "Kaliska"
    ],
    "name:nan_x_preferred":[
        "Kaliska"
    ],
    "name:nld_x_preferred":[
        "Kaliska"
    ],
    "name:pol_x_preferred":[
        "Kaliska"
    ],
    "name:por_x_preferred":[
        "Comuna de Kaliska"
    ],
    "name:rus_x_preferred":[
        "\u041a\u0430\u043b\u0438\u0441\u043a\u0430"
    ],
    "name:slk_x_preferred":[
        "Gmina Kaliska"
    ],
    "name:ukr_x_preferred":[
        "\u0490\u043c\u0456\u043d\u0430 \u041a\u0430\u043b\u0456\u0441\u044c\u043a\u0430"
    ],
    "name:war_x_preferred":[
        "Gmina Kaliska"
    ],
    "name:zho_min_nan_x_preferred":[
        "Kaliska"
    ],
    "qs:a0":"Rzeczpospolita Polska",
    "qs:a1":"*Pomorskie",
    "qs:a1r":"0",
    "qs:a2":"Starogardzki",
    "qs:adm0":"Rzeczpospolita Polska",
    "qs:la":"Kaliska",
    "qs:la_lc":"*PL2213052",
    "qs:level":"locality",
    "qs:loc":"Kaliska",
    "qs:loc_alt":"Kaliska",
    "qs:pop":0,
    "qs:type":"rural point-in-poly",
    "wd:wordcount":126,
    "wof:name":"Kaliska",
    "wof:placetype":"locality",
    "wof:population":2268
},
  "geometry": {"coordinates":[18.1779268012521,53.909140528434],"type":"Point"}
}