{
  "type": "Feature",
  "properties": {
    "gn:admin1_code":"74.0",
    "gn:admin2_code":"1007.0",
    "gn:admin3_code":"100708.0",
    "gn:asciiname":"Bronow",
    "gn:country_code":"PL",
    "gn:dem":224,
    "gn:feature_class":"P",
    "gn:feature_code":"PPL",
    "gn:name":"Bron\u00f3w",
    "gn:population":0,
    "gn:timezone":"Europe/Warsaw",
    "iso:country":"PL",
    "name:fra_x_preferred":[
        "Bron\u00f3w"
    ],
    "name:pol_x_preferred":[
        "Bron\u00f3w"
    ],
    "name:ukr_x_preferred":[
        "\u0411\u0440\u043e\u043d\u0443\u0432"
    ],
    "wof:name":"Bronow",
    "wof:placetype":"locality"
},
  "geometry": {"coordinates":[20.19851,51.24017],"type":"Point"}
}