{
  "type": "Feature",
  "properties": {
    "gn:admin1_code":"78.0",
    "gn:admin2_code":"1423.0",
    "gn:admin3_code":"142303.0",
    "gn:asciiname":"Dobra Wola",
    "gn:country_code":"PL",
    "gn:dem":165,
    "gn:feature_class":"P",
    "gn:feature_code":"PPL",
    "gn:name":"Dobra Wola",
    "gn:population":0,
    "gn:timezone":"Europe/Warsaw",
    "iso:country":"PL",
    "name:ceb_x_preferred":[
        "Dobra Wola"
    ],
    "name:deu_x_preferred":[
        "Dobra Wola"
    ],
    "name:fra_x_preferred":[
        "Dobra Wola"
    ],
    "name:pol_x_preferred":[
        "Dobra Wola"
    ],
    "name:ukr_x_preferred":[
        "\u0414\u043e\u0431\u0440\u0430-\u0412\u043e\u043b\u044f"
    ],
    "wof:name":"Dobra Wola",
    "wof:placetype":"locality"
},
  "geometry": {"coordinates":[20.67405,51.48965],"type":"Point"}
}