{
  "type": "Feature",
  "properties": {
    "gn:gn_country":"PL",
    "gn:gn_fcode":"PPLA3",
    "gn:gn_pop":270,
    "gn:population":270,
    "iso:country":"PL",
    "name:azb_x_preferred":[
        "\u062e\u0648\u062a\u0686\u0627"
    ],
    "name:ceb_x_preferred":[
        "Chotcza"
    ],
    "name:deu_x_preferred":[
        "Chotcza-J\u00f3zef\u00f3w"
    ],
    "name:fas_x_preferred":[
        "\u062e\u0648\u062a\u0686\u0627"
    ],
    "name:fra_x_preferred":[
        "Chotcza"
    ],
    "name:nld_x_preferred":[
        "Chotcza"
    ],
    "name:pol_x_preferred":[
        "Chotcza-J\u00f3zef\u00f3w"
    ],
    "name:ukr_x_preferred":[
        "\u0425\u043e\u0442\u0447\u0430-\u042e\u0437\u0435\u0444\u0443\u0432"
    ],
    "qs_pg:aaroncc":"PL",
    "qs_pg:gn_country":"PL",
    "qs_pg:gn_fcode":"PPLA3",
    "qs_pg:gn_pop":270,
    "qs_pg:name":"Chotcza",
    "qs_pg:name_adm0":"Polska",
    "qs_pg:name_adm1":"Mazowieckie",
    "qs_pg:photos_9r":0,
    "qs_pg:photos_sr":0,
    "qs_pg:pop_sr":2,
    "qs_pg:qs_pg_placetype":"localadmin",
    "qs_pg:qs_pg_placetype_gp":"LocalAdmin",
    "qs_pg:woe_adm0":23424923,
    "woe:adm0_id":23424923,
    "woe:name_adm0":"Polska",
    "woe:name_adm1":"Mazowieckie",
    "woe:placetype":"LocalAdmin",
    "wof:name":"Chotcza",
    "wof:placetype":"localadmin",
    "wof:population":270
},
  "geometry": {"coordinates":[21.77662,51.24043],"type":"Point"}
}