{
  "type": "Feature",
  "properties": {
    "gn:country":"PL",
    "gn:fcode":"PPL",
    "gn:population":117,
    "iso:country":"PL",
    "name:ast_x_preferred":[
        "Stare Bulkowo"
    ],
    "name:cat_x_preferred":[
        "Stare Bulkowo"
    ],
    "name:ceb_x_preferred":[
        "Stare Bulkowo"
    ],
    "name:ces_x_preferred":[
        "Stare Bulkowo"
    ],
    "name:che_x_preferred":[
        "\u0421\u0442\u0430\u0440\u0435 \u0411\u0443\u043b\u044c\u043a\u043e\u0432\u043e"
    ],
    "name:eng_x_preferred":[
        "Stare Bulkowo"
    ],
    "name:fra_x_preferred":[
        "Stare Bulkowo"
    ],
    "name:nan_x_preferred":[
        "Stare Bulkowo"
    ],
    "name:nld_x_preferred":[
        "Stare Bulkowo"
    ],
    "name:oci_x_preferred":[
        "Stare Bulkowo"
    ],
    "name:pol_x_preferred":[
        "Stare Bulkowo"
    ],
    "name:tat_x_preferred":[
        "\u0421\u0442\u0430\u0440\u0435 \u0411\u0443\u043b\u044c\u043a\u043e\u0432\u043e"
    ],
    "name:ukr_x_preferred":[
        "\u0421\u0442\u0430\u0440\u0435 \u0411\u0443\u043b\u044c\u043a\u043e\u0432\u043e"
    ],
    "qs_pg:aaroncc":"PL",
    "qs_pg:gn_country":"PL",
    "qs_pg:gn_fcode":"PPL",
    "qs_pg:gn_pop":117,
    "qs_pg:name":"Stare Bulkowo",
    "qs_pg:name_adm0":"Polska",
    "qs_pg:name_adm1":"Mazowieckie",
    "qs_pg:photos_9r":0,
    "qs_pg:photos_sr":0,
    "qs_pg:pop_sr":1,
    "qs_pg:qs_pg_placetype":"locality",
    "qs_pg:qs_pg_placetype_gp":"Town",
    "qs_pg:woe_adm0":23424923,
    "woe:adm0_id":23424923,
    "woe:name_adm0":"Polska",
    "woe:name_adm1":"Mazowieckie",
    "woe:placetype":"Town",
    "wof:name":"Stare Bulkowo",
    "wof:placetype":"locality",
    "wof:population":117
},
  "geometry": {"coordinates":[20.97316,52.68554],"type":"Point"}
}