{
  "type": "Feature",
  "properties": {
    "gn:admin1_code":"87.0",
    "gn:admin2_code":"3208.0",
    "gn:admin3_code":"320804.0",
    "gn:asciiname":"Przecmino",
    "gn:country_code":"PL",
    "gn:dem":21,
    "gn:feature_class":"P",
    "gn:feature_code":"PPL",
    "gn:name":"Prze\u0107mino",
    "gn:population":0,
    "gn:timezone":"Europe/Warsaw",
    "iso:country":"PL",
    "name:ceb_x_preferred":[
        "Prze\u0107mino"
    ],
    "name:deu_x_preferred":[
        "Prze\u0107mino"
    ],
    "name:pol_x_preferred":[
        "Prze\u0107mino"
    ],
    "name:ukr_x_preferred":[
        "\u041f\u0448\u0435\u0446\u044c\u043c\u0456\u043d\u043e"
    ],
    "name:vie_x_preferred":[
        "Prze\u0107mino"
    ],
    "wof:name":"Przecmino",
    "wof:placetype":"locality"
},
  "geometry": {"coordinates":[15.52402,54.11894],"type":"Point"}
}