{
  "type": "Feature",
  "properties": {
    "gn:admin1_code":"87.0",
    "gn:admin2_code":"3208.0",
    "gn:admin3_code":"320804.0",
    "gn:asciiname":"Przecmino",
    "gn:country_code":"PL",
    "gn:dem":21,
    "gn:feature_class":"P",
    "gn:feature_code":"PPL",
    "gn:name":"Prze\u0107mino",
    "gn:population":0,
    "gn:timezone":"Europe/Warsaw",
    "iso:country":"PL",
    "wof:name":"Przecmino",
    "wof:placetype":"locality"
},
  "geometry": {"coordinates":[15.52402,54.11894],"type":"Point"}
}