{
  "type": "Feature",
  "properties": {
    "iso:country":"PL",
    "name:bel_x_preferred":[
        "\u0411\u0456\u043b\u0433\u043e\u0440\u0430\u0439"
    ],
    "name:bul_x_preferred":[
        "\u0411\u0438\u043b\u0433\u043e\u0440\u0430\u0439"
    ],
    "name:ces_x_preferred":[
        "Bi\u0142goraj"
    ],
    "name:deu_x_preferred":[
        "Bi\u0142goraj"
    ],
    "name:dsb_x_preferred":[
        "Bi\u0142goraj"
    ],
    "name:epo_x_preferred":[
        "Bi\u0142goraj"
    ],
    "name:est_x_preferred":[
        "Bi\u0142goraj"
    ],
    "name:eus_x_preferred":[
        "Bi\u0142goraj"
    ],
    "name:fas_x_preferred":[
        "\u0628\u06cc\u0648\u06af\u0648\u0631\u0627\u06cc"
    ],
    "name:fra_x_preferred":[
        "Bi\u0142goraj"
    ],
    "name:hak_x_preferred":[
        "Bi\u0142goraj"
    ],
    "name:heb_x_preferred":[
        "\u05d1\u05d9\u05dc\u05d2\u05d5\u05e8\u05d9\u05d9"
    ],
    "name:hun_x_preferred":[
        "Bi\u0142goraj"
    ],
    "name:ita_x_preferred":[
        "Bi\u0142goraj"
    ],
    "name:jav_x_preferred":[
        "Bi\u0142goraj"
    ],
    "name:lat_x_preferred":[
        "Bilgoraia"
    ],
    "name:lav_x_preferred":[
        "Bilgoraja"
    ],
    "name:lit_x_preferred":[
        "Bilgorajus"
    ],
    "name:msa_x_preferred":[
        "Bi\u0142goraj"
    ],
    "name:nld_x_preferred":[
        "Bi\u0142goraj"
    ],
    "name:nor_x_preferred":[
        "Bi\u0142goraj"
    ],
    "name:pol_x_preferred":[
        "Bi\u0142goraj"
    ],
    "name:por_x_preferred":[
        "Bi\u0142goraj"
    ],
    "name:ron_x_preferred":[
        "Bi\u0142goraj"
    ],
    "name:rus_x_preferred":[
        "\u0411\u0438\u043b\u0433\u043e\u0440\u0430\u0439"
    ],
    "name:slk_x_preferred":[
        "Bi\u0142goraj"
    ],
    "name:spa_x_preferred":[
        "Bi\u0142goraj"
    ],
    "name:srp_x_preferred":[
        "\u0411\u0438\u043b\u0433\u043e\u0440\u0430\u0458"
    ],
    "name:swe_x_preferred":[
        "Bi\u0142goraj"
    ],
    "name:szl_x_preferred":[
        "Bi\u0142goraj"
    ],
    "name:tur_x_preferred":[
        "Bi\u0142goraj"
    ],
    "name:ukr_x_preferred":[
        "\u0411\u0456\u043b\u0491\u043e\u0440\u0430\u0439"
    ],
    "name:vie_x_preferred":[
        "Bi\u0142goraj"
    ],
    "name:war_x_preferred":[
        "Bi\u0142goraj"
    ],
    "name:zho_x_preferred":[
        "\u6bd4\u70cf\u6208\u62c9\u4f0a"
    ],
    "qs_pg:aaroncc":"PL",
    "qs_pg:name":"Bi\u0142goraj",
    "qs_pg:name_adm0":"Polska",
    "qs_pg:name_adm1":"Lubelskie",
    "qs_pg:photos":147,
    "qs_pg:photos_1k":30,
    "qs_pg:photos_9k":1,
    "qs_pg:photos_9r":3,
    "qs_pg:photos_all":147,
    "qs_pg:photos_sr":3,
    "qs_pg:pop_sr":0,
    "qs_pg:qs_pg_placetype":"localadmin",
    "qs_pg:qs_pg_placetype_gp":"LocalAdmin",
    "qs_pg:woe_adm0":23424923,
    "woe:adm0_id":23424923,
    "woe:name_adm0":"Polska",
    "woe:name_adm1":"Lubelskie",
    "woe:placetype":"LocalAdmin",
    "wof:name":"Bi\u0142goraj",
    "wof:placetype":"localadmin"
},
  "geometry": {"coordinates":[22.79663,50.53438],"type":"Point"}
}