{
  "type": "Feature",
  "properties": {
    "iso:country":"PL",
    "name:eng_x_preferred":[
        "Smegorzyno"
    ],
    "name:pol_x_preferred":[
        "Sm\u0119gorzyno"
    ],
    "wof:name":"Smegorzyno",
    "wof:placetype":"neighbourhood"
},
  "geometry": {"coordinates":[18.47674209669593,54.34679984640572],"type":"Point"}
}