{
  "type": "Feature",
  "properties": {
    "gn:admin1_code":"79.0",
    "gn:admin2_code":"1601.0",
    "gn:admin3_code":"160105.0",
    "gn:asciiname":"Raciszow",
    "gn:country_code":"PL",
    "gn:dem":145,
    "gn:feature_class":"P",
    "gn:feature_code":"PPL",
    "gn:name":"Raciszow",
    "gn:population":0,
    "gn:timezone":"Europe/Warsaw",
    "iso:country":"PL",
    "name:pol_x_preferred":[
        "Racisz\u00f3w"
    ],
    "name:ukr_x_preferred":[
        "\u0420\u0430\u0446\u0438\u0448\u0443\u0432"
    ],
    "wof:name":"Raciszow",
    "wof:placetype":"locality"
},
  "geometry": {"coordinates":[17.64277000000001,50.97798],"type":"Point"}
}