{
  "type": "Feature",
  "properties": {
    "gn:admin1_code":"75.0",
    "gn:admin2_code":"611.0",
    "gn:admin3_code":"61110.0",
    "gn:asciiname":"Burzec",
    "gn:country_code":"PL",
    "gn:dem":155,
    "gn:feature_class":"P",
    "gn:feature_code":"PPL",
    "gn:name":"Burzec",
    "gn:population":0,
    "gn:timezone":"Europe/Warsaw",
    "iso:country":"PL",
    "name:azb_x_preferred":[
        "\u0628\u0648\u0698\u062a\u0633"
    ],
    "name:ceb_x_preferred":[
        "Burzec"
    ],
    "name:fas_x_preferred":[
        "\u0628\u0648\u0698\u062a\u0633"
    ],
    "name:fra_x_preferred":[
        "Burzec"
    ],
    "name:nld_x_preferred":[
        "Burzec"
    ],
    "name:pol_x_preferred":[
        "Burzec"
    ],
    "name:ukr_x_preferred":[
        "\u0411\u0443\u0436\u0435\u0446\u044c"
    ],
    "wof:name":"Burzec",
    "wof:placetype":"locality"
},
  "geometry": {"coordinates":[22.2607,51.7877],"type":"Point"}
}