{
  "type": "Feature",
  "properties": {
    "iso:country":"PL",
    "name:pol_x_preferred":[
        "Bia\u0142o\u0142\u0119ka"
    ],
    "wof:name":"Bialoleka",
    "wof:placetype":"neighbourhood"
},
  "geometry": {"coordinates":[21.02320264144712,52.33378267912833],"type":"Point"}
}