{
  "type": "Feature",
  "properties": {
    "gn:admin1_code":"72.0",
    "gn:admin2_code":"209.0",
    "gn:admin3_code":"20905.0",
    "gn:asciiname":"Taczalin",
    "gn:country_code":"PL",
    "gn:dem":153,
    "gn:feature_class":"P",
    "gn:feature_code":"PPL",
    "gn:name":"Taczalin",
    "gn:population":0,
    "gn:timezone":"Europe/Warsaw",
    "iso:country":"PL",
    "name:deu_x_historical":[
        "Tentschel"
    ],
    "name:deu_x_preferred":[
        "Tentschel"
    ],
    "name:pol_x_preferred":[
        "Taczalin"
    ],
    "name:ukr_x_preferred":[
        "\u0422\u0430\u0447\u0430\u043b\u0456\u043d"
    ],
    "wof:name":"Taczalin",
    "wof:placetype":"locality"
},
  "geometry": {"coordinates":[16.30577000000001,51.15459],"type":"Point"}
}