{
  "type": "Feature",
  "properties": {
    "gn:admin1_code":"84.0",
    "gn:admin2_code":"2605.0",
    "gn:admin3_code":"260503.0",
    "gn:asciiname":"Wasosz",
    "gn:country_code":"PL",
    "gn:dem":276,
    "gn:feature_class":"P",
    "gn:feature_code":"PPL",
    "gn:name":"W\u0105sosz",
    "gn:population":0,
    "gn:timezone":"Europe/Warsaw",
    "iso:country":"PL",
    "wof:name":"Wasosz",
    "wof:placetype":"locality"
},
  "geometry": {"coordinates":[20.46444,51.13685],"type":"Point"}
}