{
  "type": "Feature",
  "properties": {
    "gn:admin1_code":"76.0",
    "gn:admin2_code":"802.0",
    "gn:admin3_code":"80205.0",
    "gn:asciiname":"Kozow",
    "gn:country_code":"PL",
    "gn:dem":59,
    "gn:feature_class":"P",
    "gn:feature_code":"PPL",
    "gn:name":"Koz\u00f3w",
    "gn:population":0,
    "gn:timezone":"Europe/Warsaw",
    "iso:country":"PL",
    "name:fra_x_preferred":[
        "Koz\u00f3w"
    ],
    "name:pol_x_preferred":[
        "Koz\u00f3w"
    ],
    "name:ron_x_preferred":[
        "Koz\u00f3w"
    ],
    "name:ukr_x_preferred":[
        "\u041a\u043e\u0437\u0443\u0432"
    ],
    "wof:name":"Kozow",
    "wof:placetype":"locality"
},
  "geometry": {"coordinates":[14.74118,51.85943],"type":"Point"}
}