{
  "type": "Feature",
  "properties": {
    "gn:admin1_code":"86.0",
    "gn:admin2_code":"3021.0",
    "gn:admin3_code":"302117.0",
    "gn:asciiname":"Krzyzowniki",
    "gn:country_code":"PL",
    "gn:dem":92,
    "gn:feature_class":"P",
    "gn:feature_code":"PPL",
    "gn:name":"Krzy\u017cowniki",
    "gn:population":0,
    "gn:timezone":"Europe/Warsaw",
    "iso:country":"PL",
    "wof:name":"Krzyzowniki",
    "wof:placetype":"neighbourhood"
},
  "geometry": {"coordinates":[16.79536,52.43833000000001],"type":"Point"}
}