{
  "type": "Feature",
  "properties": {
    "gn:admin1_code":"78.0",
    "gn:admin2_code":"1422.0",
    "gn:admin3_code":"142207.0",
    "gn:asciiname":"Cierpigorz",
    "gn:country_code":"PL",
    "gn:dem":115,
    "gn:feature_class":"P",
    "gn:feature_code":"PPL",
    "gn:name":"Cierpig\u00f3rz",
    "gn:population":0,
    "gn:timezone":"Europe/Warsaw",
    "iso:country":"PL",
    "wof:name":"Cierpigorz",
    "wof:placetype":"locality"
},
  "geometry": {"coordinates":[20.87993,52.98296],"type":"Point"}
}