{
  "type": "Feature",
  "properties": {
    "gn:admin1_code":"74.0",
    "gn:admin2_code":"1015.0",
    "gn:admin3_code":"101506.0",
    "gn:asciiname":"Sielce Prawe",
    "gn:country_code":"PL",
    "gn:dem":113,
    "gn:feature_class":"P",
    "gn:feature_code":"PPL",
    "gn:name":"Sielce Prawe",
    "gn:population":0,
    "gn:timezone":"Europe/Warsaw",
    "iso:country":"PL",
    "name:ceb_x_preferred":[
        "Sielce Prawe"
    ],
    "name:pol_x_preferred":[
        "Sielce Prawe"
    ],
    "name:ukr_x_preferred":[
        "\u0421\u0435\u043b\u044c\u0446\u0435-\u041f\u0440\u0430\u0432\u0435"
    ],
    "wof:name":"Sielce Prawe",
    "wof:placetype":"locality"
},
  "geometry": {"coordinates":[20.05125,51.98937],"type":"Point"}
}