{
  "type": "Feature",
  "properties": {
    "gn:admin1_code":"72.0",
    "gn:admin2_code":"224.0",
    "gn:admin3_code":"22403.0",
    "gn:asciiname":"Rogow",
    "gn:country_code":"PL",
    "gn:dem":249,
    "gn:feature_class":"P",
    "gn:feature_code":"PPL",
    "gn:name":"Rogow",
    "gn:population":0,
    "gn:timezone":"Europe/Warsaw",
    "iso:country":"PL",
    "wof:name":"Rogow",
    "wof:placetype":"locality"
},
  "geometry": {"coordinates":[16.87122,50.5012],"type":"Point"}
}