{
  "type": "Feature",
  "properties": {
    "gn:admin1_code":"78.0",
    "gn:admin2_code":"1411.0",
    "gn:admin3_code":"141104.0",
    "gn:asciiname":"Niesulowo",
    "gn:country_code":"PL",
    "gn:dem":107,
    "gn:feature_class":"P",
    "gn:feature_code":"PPL",
    "gn:name":"Niesu\u0142owo",
    "gn:population":0,
    "gn:timezone":"Europe/Warsaw",
    "iso:country":"PL",
    "wof:name":"Niesulowo",
    "wof:placetype":"locality"
},
  "geometry": {"coordinates":[21.27074,53.06311],"type":"Point"}
}