{
  "type": "Feature",
  "properties": {
    "gn:admin1_code":"72.0",
    "gn:admin2_code":"205.0",
    "gn:admin3_code":"20505.0",
    "gn:asciiname":"Sokola",
    "gn:country_code":"PL",
    "gn:dem":238,
    "gn:feature_class":"P",
    "gn:feature_code":"PPL",
    "gn:name":"Sokola",
    "gn:population":0,
    "gn:timezone":"Europe/Warsaw",
    "iso:country":"PL",
    "name:pol_x_preferred":[
        "Sokola"
    ],
    "name:ukr_x_preferred":[
        "\u0421\u043e\u043a\u043e\u043b\u044f"
    ],
    "wof:name":"Sokola",
    "wof:placetype":"locality"
},
  "geometry": {"coordinates":[16.1602,50.97583],"type":"Point"}
}