{
  "type": "Feature",
  "properties": {
    "gn:admin1_code":"83.0",
    "gn:admin2_code":"2404.0",
    "gn:admin3_code":"240408.0",
    "gn:asciiname":"Lgota",
    "gn:country_code":"PL",
    "gn:dem":219,
    "gn:feature_class":"P",
    "gn:feature_code":"PPL",
    "gn:name":"Lgota",
    "gn:population":0,
    "gn:timezone":"Europe/Warsaw",
    "iso:country":"PL",
    "name:pol_x_preferred":[
        "Lgota Ma\u0142a"
    ],
    "name:ukr_x_preferred":[
        "\u041b\u044c\u0491\u043e\u0442\u0430-\u041c\u0430\u043b\u0430"
    ],
    "name:und_x_variant":[
        "Lgota"
    ],
    "wof:name":"Lgota",
    "wof:placetype":"locality"
},
  "geometry": {"coordinates":[19.33758,50.98415],"type":"Point"}
}