{
  "type": "Feature",
  "properties": {
    "gn:admin1_code":"82.0",
    "gn:admin2_code":"2201.0",
    "gn:admin3_code":"220105.0",
    "gn:asciiname":"Brzozowo",
    "gn:country_code":"PL",
    "gn:dem":184,
    "gn:feature_class":"P",
    "gn:feature_code":"PPL",
    "gn:name":"Brzozowo",
    "gn:population":0,
    "gn:timezone":"Europe/Warsaw",
    "iso:country":"PL",
    "name:ceb_x_preferred":[
        "Brzozowo"
    ],
    "name:csb_x_preferred":[
        "Brzozow\u00f2"
    ],
    "name:pol_x_preferred":[
        "Brzozowo"
    ],
    "name:ukr_x_preferred":[
        "\u0411\u0436\u043e\u0437\u043e\u0432\u043e"
    ],
    "wof:name":"Brzozowo",
    "wof:placetype":"locality"
},
  "geometry": {"coordinates":[17.1951,53.99429],"type":"Point"}
}