{
  "type": "Feature",
  "properties": {
    "gn:admin1_code":"83.0",
    "gn:admin2_code":"2404.0",
    "gn:admin3_code":"240409.0",
    "gn:asciiname":"Konstantynow",
    "gn:country_code":"PL",
    "gn:dem":253,
    "gn:feature_class":"P",
    "gn:feature_code":"PPL",
    "gn:name":"Konstantyn\u00f3w",
    "gn:population":0,
    "gn:timezone":"Europe/Warsaw",
    "iso:country":"PL",
    "wof:name":"Konstantynow",
    "wof:placetype":"locality"
},
  "geometry": {"coordinates":[19.55687,50.74482],"type":"Point"}
}