{
  "type": "Feature",
  "properties": {
    "gn:admin1_code":"78.0",
    "gn:admin2_code":"1428.0",
    "gn:admin3_code":"142803.0",
    "gn:asciiname":"Budy Ilowskie",
    "gn:country_code":"PL",
    "gn:dem":70,
    "gn:feature_class":"P",
    "gn:feature_code":"PPL",
    "gn:name":"Budy I\u0142owskie",
    "gn:population":0,
    "gn:timezone":"Europe/Warsaw",
    "iso:country":"PL",
    "name:azb_x_preferred":[
        "\u0628\u0648\u062f \u0627\u06cc\u0648\u0648\u0648\u0633\u06a9\u06cc\u0647"
    ],
    "name:fas_x_preferred":[
        "\u0628\u0648\u062f \u0627\u06cc\u0648\u0648\u0648\u0633\u06a9\u06cc\u0647"
    ],
    "name:fra_x_preferred":[
        "Budy I\u0142owskie"
    ],
    "name:pol_x_preferred":[
        "Budy I\u0142owskie"
    ],
    "name:ukr_x_preferred":[
        "\u0411\u0443\u0434\u0438-\u0406\u043b\u043e\u0432\u0441\u044c\u043a\u0456"
    ],
    "wof:name":"Budy Ilowskie",
    "wof:placetype":"locality"
},
  "geometry": {"coordinates":[20.11256,52.32874],"type":"Point"}
}