{
  "type": "Feature",
  "properties": {
    "gn:admin1_code":"78.0",
    "gn:admin2_code":"1428.0",
    "gn:admin3_code":"142803.0",
    "gn:asciiname":"Budy Ilowskie",
    "gn:country_code":"PL",
    "gn:dem":70,
    "gn:feature_class":"P",
    "gn:feature_code":"PPL",
    "gn:name":"Budy I\u0142owskie",
    "gn:population":0,
    "gn:timezone":"Europe/Warsaw",
    "iso:country":"PL",
    "name:und_x_variant":[
        "Budy I\u0142owskie"
    ],
    "wof:name":"Budy Ilowskie",
    "wof:placetype":"locality"
},
  "geometry": {"coordinates":[20.11256,52.32874],"type":"Point"}
}