{
  "type": "Feature",
  "properties": {
    "gn:admin1_code":"78.0",
    "gn:admin2_code":"1435.0",
    "gn:admin3_code":"143502.0",
    "gn:asciiname":"Plewki",
    "gn:country_code":"PL",
    "gn:dem":110,
    "gn:feature_class":"P",
    "gn:feature_code":"PPL",
    "gn:name":"Plewki",
    "gn:population":0,
    "gn:timezone":"Europe/Warsaw",
    "iso:country":"PL",
    "name:deu_x_preferred":[
        "Plewki"
    ],
    "name:fra_x_preferred":[
        "Plewki"
    ],
    "name:pol_x_preferred":[
        "Plewki"
    ],
    "name:ukr_x_preferred":[
        "\u041f\u043b\u0435\u0432\u043a\u0456"
    ],
    "wof:name":"Plewki",
    "wof:placetype":"locality"
},
  "geometry": {"coordinates":[21.64398,52.81562],"type":"Point"}
}