{
  "type": "Feature",
  "properties": {
    "gn:country":"PL",
    "gn:fcode":"PPLA3",
    "gn:population":627,
    "iso:country":"PL",
    "name:ast_x_preferred":[
        "Rzg\u00f3w Pierwszy"
    ],
    "name:ceb_x_preferred":[
        "Rzg\u00f3w Pierwszy"
    ],
    "name:deu_x_preferred":[
        "Rzg\u00f3w"
    ],
    "name:eng_x_preferred":[
        "Rzg\u00f3w Pierwszy"
    ],
    "name:fra_x_preferred":[
        "Rzg\u00f3w Pierwszy"
    ],
    "name:pol_x_preferred":[
        "Rzg\u00f3w Pierwszy"
    ],
    "name:ukr_x_preferred":[
        "\u0416\u0491\u0443\u0432"
    ],
    "qs_pg:aaroncc":"PL",
    "qs_pg:gn_country":"PL",
    "qs_pg:gn_fcode":"PPLA3",
    "qs_pg:gn_pop":627,
    "qs_pg:name":"Rzg\u00f3w Pierwszy",
    "qs_pg:photos_9r":0,
    "qs_pg:photos_sr":0,
    "qs_pg:pop_sr":2,
    "qs_pg:qs_pg_placetype":"locality",
    "wof:name":"Rzg\u00f3w Pierwszy",
    "wof:placetype":"locality",
    "wof:population":627
},
  "geometry": {"coordinates":[18.04976,52.15134],"type":"Point"}
}