{
  "type": "Feature",
  "properties": {
    "gn:admin1_code":"81.0",
    "gn:admin2_code":"2012.0",
    "gn:admin3_code":"201202.0",
    "gn:asciiname":"Rospuda",
    "gn:country_code":"PL",
    "gn:dem":191,
    "gn:feature_class":"P",
    "gn:feature_code":"PPL",
    "gn:name":"Rospuda",
    "gn:population":0,
    "gn:timezone":"Europe/Warsaw",
    "iso:country":"PL",
    "name:ceb_x_preferred":[
        "Rospuda"
    ],
    "name:ces_x_preferred":[
        "Rospuda"
    ],
    "name:deu_x_preferred":[
        "Rospuda"
    ],
    "name:epo_x_preferred":[
        "Rospuda"
    ],
    "name:fas_x_preferred":[
        "\u0631\u0633\u067e\u0648\u062f\u0627"
    ],
    "name:ita_x_preferred":[
        "Rospuda"
    ],
    "name:lit_x_preferred":[
        "Rospuda"
    ],
    "name:nld_x_preferred":[
        "Rospuda"
    ],
    "name:nno_x_preferred":[
        "Rospuda"
    ],
    "name:pol_x_preferred":[
        "Rospuda"
    ],
    "name:rus_x_preferred":[
        "\u0420\u043e\u0441\u043f\u0443\u0434\u0430"
    ],
    "name:tgk_x_preferred":[
        "\u0420\u0441\u043f\u0443\u0434\u043e"
    ],
    "name:tur_x_preferred":[
        "Rospuda Nehri"
    ],
    "wof:name":"Rospuda",
    "wof:placetype":"locality"
},
  "geometry": {"coordinates":[22.61747,54.20615],"type":"Point"}
}