{
  "type": "Feature",
  "properties": {
    "gn:country":"PL",
    "gn:fcode":"PPL",
    "gn:population":532,
    "iso:country":"PL",
    "name:ceb_x_preferred":[
        "Wielgie"
    ],
    "name:fra_x_preferred":[
        "Wielgie"
    ],
    "name:nld_x_preferred":[
        "Wielgie"
    ],
    "name:pol_x_preferred":[
        "Wielgie"
    ],
    "name:ukr_x_preferred":[
        "\u0412\u0435\u043b\u044c\u0491\u0435"
    ],
    "qs_pg:aaroncc":"PL",
    "qs_pg:gn_country":"PL",
    "qs_pg:gn_fcode":"PPL",
    "qs_pg:gn_pop":532,
    "qs_pg:name":"Wielgie",
    "qs_pg:name_adm0":"Polska",
    "qs_pg:name_adm1":"Kujawsko-Pomorskie",
    "qs_pg:photos_9r":0,
    "qs_pg:photos_sr":0,
    "qs_pg:pop_sr":2,
    "qs_pg:qs_pg_placetype":"locality",
    "qs_pg:qs_pg_placetype_gp":"Town",
    "qs_pg:woe_adm0":23424923,
    "woe:adm0_id":23424923,
    "woe:name_adm0":"Polska",
    "woe:name_adm1":"Kujawsko-Pomorskie",
    "woe:placetype":"Town",
    "wof:name":"Wielgie",
    "wof:placetype":"locality",
    "wof:population":532
},
  "geometry": {"coordinates":[19.10102,53.00239],"type":"Point"}
}