{
  "type": "Feature",
  "properties": {
    "gn:admin1_code":"74.0",
    "gn:admin2_code":"1012.0",
    "gn:admin3_code":"101214.0",
    "gn:asciiname":"Rogaczowek",
    "gn:country_code":"PL",
    "gn:dem":225,
    "gn:feature_class":"P",
    "gn:feature_code":"PPL",
    "gn:name":"Rogacz\u00f3wek",
    "gn:population":0,
    "gn:timezone":"Europe/Warsaw",
    "iso:country":"PL",
    "name:pol_x_preferred":[
        "Rogacz\u00f3wek"
    ],
    "name:ukr_x_preferred":[
        "\u0420\u043e\u0491\u0430\u0447\u0443\u0432\u0435\u043a"
    ],
    "wof:name":"Rogaczowek",
    "wof:placetype":"locality"
},
  "geometry": {"coordinates":[19.65617,50.92185],"type":"Point"}
}