{
  "type": "Feature",
  "properties": {
    "gn:admin1_code":"78.0",
    "gn:admin2_code":"1426.0",
    "gn:admin3_code":"142604.0",
    "gn:asciiname":"Niwiski",
    "gn:country_code":"PL",
    "gn:dem":143,
    "gn:feature_class":"P",
    "gn:feature_code":"PPL",
    "gn:name":"Niwiski",
    "gn:population":0,
    "gn:timezone":"Europe/Warsaw",
    "iso:country":"PL",
    "name:azb_x_preferred":[
        "\u0646\u0642\u0648\u06cc\u0633\u06a9\u06cc"
    ],
    "name:ceb_x_preferred":[
        "Niwiski"
    ],
    "name:fas_x_preferred":[
        "\u0646\u06af\u0648\u06cc\u0633\u06a9\u06cc"
    ],
    "name:fra_x_preferred":[
        "Niwiski"
    ],
    "name:lit_x_preferred":[
        "Niviskai"
    ],
    "name:pol_x_preferred":[
        "Niwiski"
    ],
    "name:szl_x_preferred":[
        "Niwiski"
    ],
    "name:ukr_x_preferred":[
        "\u041d\u0456\u0432\u0456\u0441\u043a\u0456"
    ],
    "wof:name":"Niwiski",
    "wof:placetype":"locality"
},
  "geometry": {"coordinates":[22.17015,52.21997],"type":"Point"}
}