{
  "type": "Feature",
  "properties": {
    "gn:admin1_code":"78.0",
    "gn:admin2_code":"1415.0",
    "gn:admin3_code":"141503.0",
    "gn:asciiname":"Tomasze",
    "gn:country_code":"PL",
    "gn:dem":102,
    "gn:feature_class":"P",
    "gn:feature_code":"PPL",
    "gn:name":"Tomasze",
    "gn:population":0,
    "gn:timezone":"Europe/Warsaw",
    "iso:country":"PL",
    "name:fra_x_preferred":[
        "Tomasze"
    ],
    "name:pol_x_preferred":[
        "Tomasze"
    ],
    "name:ukr_x_preferred":[
        "\u0422\u043e\u043c\u0430\u0448\u0435"
    ],
    "wof:name":"Tomasze",
    "wof:placetype":"locality"
},
  "geometry": {"coordinates":[21.65065,52.96954],"type":"Point"}
}