{
  "type": "Feature",
  "properties": {
    "gn:admin1_code":"85.0",
    "gn:admin2_code":"2807.0",
    "gn:admin3_code":"280707.0",
    "gn:asciiname":"Bukowiec",
    "gn:country_code":"PL",
    "gn:dem":101,
    "gn:feature_class":"P",
    "gn:feature_code":"PPL",
    "gn:name":"Bukowiec",
    "gn:population":0,
    "gn:timezone":"Europe/Warsaw",
    "iso:country":"PL",
    "name:ceb_x_preferred":[
        "Bukowiec"
    ],
    "name:deu_x_preferred":[
        "Bukowiec"
    ],
    "name:fra_x_preferred":[
        "Bukowiec"
    ],
    "name:nld_x_preferred":[
        "Bukowiec"
    ],
    "name:pol_x_preferred":[
        "Bukowiec"
    ],
    "name:und_x_variant":[
        "Bukowitz"
    ],
    "wof:name":"Bukowiec",
    "wof:placetype":"locality"
},
  "geometry": {"coordinates":[19.58069,53.7614],"type":"Point"}
}