{
  "type": "Feature",
  "properties": {
    "gn:admin1_code":"78.0",
    "gn:admin2_code":"1423.0",
    "gn:admin3_code":"142302.0",
    "gn:asciiname":"Stoczki",
    "gn:country_code":"PL",
    "gn:dem":239,
    "gn:feature_class":"P",
    "gn:feature_code":"PPL",
    "gn:name":"Stoczki",
    "gn:population":0,
    "gn:timezone":"Europe/Warsaw",
    "iso:country":"PL",
    "name:fra_x_preferred":[
        "Stoczki"
    ],
    "name:pol_x_preferred":[
        "Stoczki"
    ],
    "name:ukr_x_preferred":[
        "\u0421\u0442\u043e\u0447\u043a\u0456"
    ],
    "wof:name":"Stoczki",
    "wof:placetype":"locality"
},
  "geometry": {"coordinates":[20.53791,51.3916],"type":"Point"}
}