{
  "type": "Feature",
  "properties": {
    "gn:admin1_code":"77.0",
    "gn:admin2_code":"1208.0",
    "gn:admin3_code":"120803.0",
    "gn:asciiname":"Bogdanow",
    "gn:country_code":"PL",
    "gn:dem":307,
    "gn:feature_class":"P",
    "gn:feature_code":"PPL",
    "gn:name":"Bogdan\u00f3w",
    "gn:population":0,
    "gn:timezone":"Europe/Warsaw",
    "iso:country":"PL",
    "name:ceb_x_preferred":[
        "Bogdan\u00f3w"
    ],
    "name:pol_x_preferred":[
        "Bogdan\u00f3w"
    ],
    "name:rus_x_preferred":[
        "\u0411\u043e\u0433\u0434\u0430\u043d\u0443\u0432"
    ],
    "name:ukr_x_preferred":[
        "\u0411\u043e\u0491\u0434\u0430\u043d\u0443\u0432"
    ],
    "wof:name":"Bogdanow",
    "wof:placetype":"locality"
},
  "geometry": {"coordinates":[20.04232,50.46373],"type":"Point"}
}