{
  "type": "Feature",
  "properties": {
    "gn:admin1_code":"80.0",
    "gn:admin2_code":"1818.0",
    "gn:admin3_code":"181804.0",
    "gn:asciiname":"Witkowice",
    "gn:country_code":"PL",
    "gn:dem":137,
    "gn:feature_class":"P",
    "gn:feature_code":"PPL",
    "gn:name":"Witkowice",
    "gn:population":0,
    "gn:timezone":"Europe/Warsaw",
    "iso:country":"PL",
    "name:pol_x_preferred":[
        "Witkowice"
    ],
    "name:ukr_x_preferred":[
        "\u0412\u0456\u0442\u043a\u043e\u0432\u0456\u0446\u0435"
    ],
    "wof:name":"Witkowice",
    "wof:placetype":"locality"
},
  "geometry": {"coordinates":[21.87189,50.75905],"type":"Point"}
}