{
  "type": "Feature",
  "properties": {
    "gn:admin1_code":"76.0",
    "gn:admin2_code":"802.0",
    "gn:admin3_code":"80202.0",
    "gn:asciiname":"Czeklin",
    "gn:country_code":"PL",
    "gn:dem":68,
    "gn:feature_class":"P",
    "gn:feature_code":"PPL",
    "gn:name":"Czeklin",
    "gn:population":0,
    "gn:timezone":"Europe/Warsaw",
    "iso:country":"PL",
    "wof:name":"Czeklin",
    "wof:placetype":"locality"
},
  "geometry": {"coordinates":[14.95777,51.95894000000001],"type":"Point"}
}