{
  "type": "Feature",
  "properties": {
    "gn:admin1_code":"78.0",
    "gn:admin2_code":"1406.0",
    "gn:admin3_code":"140607.0",
    "gn:asciiname":"Wezawiec",
    "gn:country_code":"PL",
    "gn:dem":163,
    "gn:feature_class":"P",
    "gn:feature_code":"PPL",
    "gn:name":"W\u0119\u017cawiec",
    "gn:population":0,
    "gn:timezone":"Europe/Warsaw",
    "iso:country":"PL",
    "wof:name":"Wezawiec",
    "wof:placetype":"locality"
},
  "geometry": {"coordinates":[20.66075,51.68011],"type":"Point"}
}