{
  "type": "Feature",
  "properties": {
    "gn:admin1_code":"73.0",
    "gn:admin2_code":"415.0",
    "gn:admin3_code":"41504.0",
    "gn:asciiname":"Mierzynek",
    "gn:country_code":"PL",
    "gn:dem":75,
    "gn:feature_class":"P",
    "gn:feature_code":"PPL",
    "gn:name":"Mierzynek",
    "gn:population":0,
    "gn:timezone":"Europe/Warsaw",
    "iso:country":"PL",
    "name:pol_x_preferred":[
        "Mierzynek"
    ],
    "name:rus_x_preferred":[
        "\u041c\u0435\u0436\u0438\u043d\u0435\u043a"
    ],
    "name:ukr_x_preferred":[
        "\u041c\u0435\u0436\u0438\u043d\u0435\u043a"
    ],
    "wof:name":"Mierzynek",
    "wof:placetype":"locality"
},
  "geometry": {"coordinates":[18.80516,53.03884],"type":"Point"}
}