{
  "type": "Feature",
  "properties": {
    "gn:admin1_code":"84.0",
    "gn:admin2_code":"2601.0",
    "gn:admin3_code":"260103.0",
    "gn:asciiname":"Grotniki Duze",
    "gn:cc2":"PL",
    "gn:country_code":"PL",
    "gn:dem":169,
    "gn:feature_class":"P",
    "gn:feature_code":"PPL",
    "gn:name":"Grotniki Du\u017ce",
    "gn:population":0,
    "gn:timezone":"Europe/Warsaw",
    "iso:country":"PL",
    "name:nld_x_preferred":[
        "Grotniki Du\u017ce"
    ],
    "name:pol_x_preferred":[
        "Grotniki Du\u017ce"
    ],
    "name:ukr_x_preferred":[
        "\u0490\u0440\u043e\u0442\u043d\u0438\u043a\u0438-\u0414\u0443\u0436\u0435"
    ],
    "name:und_x_variant":[
        "Grotniki Wielkie"
    ],
    "wof:name":"Grotniki Duze",
    "wof:placetype":"locality"
},
  "geometry": {"coordinates":[20.82184,50.30294],"type":"Point"}
}