{
  "type": "Feature",
  "properties": {
    "gn:admin1_code":"74.0",
    "gn:admin2_code":"1013.0",
    "gn:admin3_code":"101304.0",
    "gn:asciiname":"Przewodowice",
    "gn:country_code":"PL",
    "gn:dem":137,
    "gn:feature_class":"P",
    "gn:feature_code":"PPL",
    "gn:name":"Przewodowice",
    "gn:population":0,
    "gn:timezone":"Europe/Warsaw",
    "iso:country":"PL",
    "wof:name":"Przewodowice",
    "wof:placetype":"locality"
},
  "geometry": {"coordinates":[20.32112,51.82921],"type":"Point"}
}