{
  "type": "Feature",
  "properties": {
    "gn:admin1_code":"74.0",
    "gn:admin2_code":"1013.0",
    "gn:admin3_code":"101304.0",
    "gn:asciiname":"Przewodowice",
    "gn:country_code":"PL",
    "gn:dem":137,
    "gn:feature_class":"P",
    "gn:feature_code":"PPL",
    "gn:name":"Przewodowice",
    "gn:population":0,
    "gn:timezone":"Europe/Warsaw",
    "iso:country":"PL",
    "name:azb_x_preferred":[
        "\u067e\u0698\u0648\u0648\u062f\u0648\u0648\u06cc\u062a\u0633\u0647"
    ],
    "name:ceb_x_preferred":[
        "Przewodowice"
    ],
    "name:deu_x_preferred":[
        "Przewodowice"
    ],
    "name:fas_x_preferred":[
        "\u067e\u0698\u0648\u0648\u062f\u0648\u0648\u06cc\u062a\u0633\u0647"
    ],
    "name:pol_x_preferred":[
        "Przewodowice"
    ],
    "name:srp_x_preferred":[
        "\u041f\u0448\u0435\u0432\u043e\u0434\u043e\u0432\u0438\u0446\u0435"
    ],
    "name:ukr_x_preferred":[
        "\u041f\u0448\u0435\u0432\u043e\u0434\u043e\u0432\u0456\u0446\u0435"
    ],
    "wof:name":"Przewodowice",
    "wof:placetype":"locality"
},
  "geometry": {"coordinates":[20.32112,51.82921],"type":"Point"}
}