{
  "type": "Feature",
  "properties": {
    "gn:admin1_code":"77.0",
    "gn:admin2_code":"1208.0",
    "gn:admin3_code":"120805.0",
    "gn:asciiname":"Pstroszyce",
    "gn:country_code":"PL",
    "gn:dem":331,
    "gn:feature_class":"P",
    "gn:feature_code":"PPL",
    "gn:name":"Pstroszyce",
    "gn:population":0,
    "gn:timezone":"Europe/Warsaw",
    "iso:country":"PL",
    "wof:name":"Pstroszyce",
    "wof:placetype":"locality"
},
  "geometry": {"coordinates":[20.00662,50.39214000000001],"type":"Point"}
}