{
  "type": "Feature",
  "properties": {
    "gn:admin1_code":"78.0",
    "gn:admin2_code":"1404.0",
    "gn:admin3_code":"140403.0",
    "gn:asciiname":"Radycza",
    "gn:country_code":"PL",
    "gn:dem":107,
    "gn:feature_class":"P",
    "gn:feature_code":"PPL",
    "gn:name":"Radycza",
    "gn:population":0,
    "gn:timezone":"Europe/Warsaw",
    "iso:country":"PL",
    "name:ceb_x_preferred":[
        "Radycza"
    ],
    "name:fra_x_preferred":[
        "Radycza"
    ],
    "name:pol_x_preferred":[
        "Radycza"
    ],
    "name:ukr_x_preferred":[
        "\u0420\u0430\u0434\u0438\u0447\u0430"
    ],
    "wof:name":"Radycza",
    "wof:placetype":"locality"
},
  "geometry": {"coordinates":[19.73762,52.32943],"type":"Point"}
}