{
  "type": "Feature",
  "properties": {
    "gn:admin1_code":"84.0",
    "gn:admin2_code":"2601.0",
    "gn:admin3_code":"260102.0",
    "gn:asciiname":"Rzeszutki",
    "gn:cc2":"PL",
    "gn:country_code":"PL",
    "gn:dem":207,
    "gn:feature_class":"P",
    "gn:feature_code":"PPL",
    "gn:name":"Rzeszutki",
    "gn:population":0,
    "gn:timezone":"Europe/Warsaw",
    "iso:country":"PL",
    "name:pol_x_preferred":[
        "Rzeszutki"
    ],
    "name:ukr_x_preferred":[
        "\u0416\u0435\u0448\u0443\u0442\u043a\u0456"
    ],
    "name:und_x_variant":[
        "Rzeszotki"
    ],
    "wof:name":"Rzeszutki",
    "wof:placetype":"locality"
},
  "geometry": {"coordinates":[20.81755,50.59512],"type":"Point"}
}