{
  "type": "Feature",
  "properties": {
    "gn:gn_country":"PL",
    "gn:gn_fcode":"PPL",
    "gn:gn_pop":0,
    "iso:country":"PL",
    "name:eng_x_preferred":[
        "Wola Rasztowska"
    ],
    "name:fre_x_preferred":[
        "Wola Rasztowska"
    ],
    "name:per_x_preferred":[
        "\u0648\u0648\u0644\u0627 \u0631\u0627\u0634\u062a\u0648\u0648\u0633\u06a9\u0627"
    ],
    "name:pol_x_preferred":[
        "Wola Rasztowska"
    ],
    "qs_pg:aaroncc":"PL",
    "qs_pg:gn_country":"PL",
    "qs_pg:gn_fcode":"PPL",
    "qs_pg:gn_pop":0,
    "qs_pg:name":"Wola Rasztowska",
    "qs_pg:name_adm0":"Polska",
    "qs_pg:name_adm1":"Mazowieckie",
    "qs_pg:photos_9k":1,
    "qs_pg:photos_9r":1,
    "qs_pg:photos_all":13,
    "qs_pg:photos_sr":0,
    "qs_pg:pop_sr":0,
    "qs_pg:qs_pg_placetype":"locality",
    "qs_pg:qs_pg_placetype_gp":"Town",
    "qs_pg:woe_adm0":23424923,
    "woe:adm0_id":23424923,
    "woe:name_adm0":"Polska",
    "woe:name_adm1":"Mazowieckie",
    "woe:placetype":"Town",
    "wof:name":"Wola Rasztowska",
    "wof:placetype":"locality"
},
  "geometry": {"coordinates":[21.28945,52.44116],"type":"Point"}
}