{
  "type": "Feature",
  "properties": {
    "gn:country":"PL",
    "gn:fcode":"PPL",
    "gn:population":0,
    "iso:country":"PL",
    "name:ast_x_preferred":[
        "Wola Rasztowska"
    ],
    "name:azb_x_preferred":[
        "\u0648\u0648\u0644\u0627 \u0631\u0627\u0634\u062a\u0648\u0648\u0633\u06a9\u0627"
    ],
    "name:ces_x_preferred":[
        "Wola Rasztowska"
    ],
    "name:che_x_preferred":[
        "\u0412\u043e\u043b\u044f-\u0420\u0430\u0448\u0442\u043e\u0432\u0441\u043a\u0430"
    ],
    "name:eng_x_preferred":[
        "Wola Rasztowska"
    ],
    "name:fas_x_preferred":[
        "\u0648\u0648\u0644\u0627 \u0631\u0627\u0634\u062a\u0648\u0648\u0633\u06a9\u0627"
    ],
    "name:fra_x_preferred":[
        "Wola Rasztowska"
    ],
    "name:nan_x_preferred":[
        "Wola Rasztowska"
    ],
    "name:pol_x_preferred":[
        "Wola Rasztowska"
    ],
    "name:tat_x_preferred":[
        "\u0412\u043e\u043b\u044f-\u0420\u0430\u0448\u0442\u043e\u0432\u0441\u043a\u0430"
    ],
    "name:ukr_x_preferred":[
        "\u0412\u043e\u043b\u044f-\u0420\u0430\u0448\u0442\u043e\u0432\u0441\u044c\u043a\u0430"
    ],
    "qs_pg:aaroncc":"PL",
    "qs_pg:gn_country":"PL",
    "qs_pg:gn_fcode":"PPL",
    "qs_pg:gn_pop":0,
    "qs_pg:name":"Wola Rasztowska",
    "qs_pg:name_adm0":"Polska",
    "qs_pg:name_adm1":"Mazowieckie",
    "qs_pg:photos_9k":1,
    "qs_pg:photos_9r":1,
    "qs_pg:photos_all":13,
    "qs_pg:photos_sr":0,
    "qs_pg:pop_sr":0,
    "qs_pg:qs_pg_placetype":"locality",
    "qs_pg:qs_pg_placetype_gp":"Town",
    "qs_pg:woe_adm0":23424923,
    "woe:adm0_id":23424923,
    "woe:name_adm0":"Polska",
    "woe:name_adm1":"Mazowieckie",
    "woe:placetype":"Town",
    "wof:name":"Wola Rasztowska",
    "wof:placetype":"locality"
},
  "geometry": {"coordinates":[21.28945,52.44116],"type":"Point"}
}