{
  "type": "Feature",
  "properties": {
    "gn:admin1_code":"73.0",
    "gn:admin2_code":"403.0",
    "gn:admin3_code":"40307.0",
    "gn:asciiname":"Trzemietowo",
    "gn:country_code":"PL",
    "gn:dem":115,
    "gn:feature_class":"P",
    "gn:feature_code":"PPL",
    "gn:name":"Trzemi\u0119towo",
    "gn:population":0,
    "gn:timezone":"Europe/Warsaw",
    "iso:country":"PL",
    "name:azb_x_preferred":[
        "\u0686\u0645\u06cc\u062a\u0648\u0648"
    ],
    "name:fas_x_preferred":[
        "\u0686\u0645\u06cc\u062a\u0648\u0648"
    ],
    "name:pol_x_preferred":[
        "Trzemi\u0119towo"
    ],
    "name:ukr_x_preferred":[
        "\u0422\u0448\u0435\u043c\u0435\u043d\u0442\u043e\u0432\u043e"
    ],
    "wof:name":"Trzemietowo",
    "wof:placetype":"locality"
},
  "geometry": {"coordinates":[17.76762,53.23857],"type":"Point"}
}