{
  "type": "Feature",
  "properties": {
    "gn:admin1_code":"73.0",
    "gn:admin2_code":"403.0",
    "gn:admin3_code":"40307.0",
    "gn:asciiname":"Trzemietowo",
    "gn:country_code":"PL",
    "gn:dem":115,
    "gn:feature_class":"P",
    "gn:feature_code":"PPL",
    "gn:name":"Trzemi\u0119towo",
    "gn:population":0,
    "gn:timezone":"Europe/Warsaw",
    "iso:country":"PL",
    "name:und_x_variant":[
        "Trzemi\u0119towo"
    ],
    "wof:name":"Trzemietowo",
    "wof:placetype":"locality"
},
  "geometry": {"coordinates":[17.76762,53.23857],"type":"Point"}
}