{
  "type": "Feature",
  "properties": {
    "gn:admin1_code":"81.0",
    "gn:admin2_code":"2003.0",
    "gn:admin3_code":"200301.0",
    "gn:asciiname":"Studziwody",
    "gn:country_code":"PL",
    "gn:dem":139,
    "gn:feature_class":"P",
    "gn:feature_code":"PPL",
    "gn:name":"Studziwody",
    "gn:population":0,
    "gn:timezone":"Europe/Warsaw",
    "iso:country":"PL",
    "wof:name":"Studziwody",
    "wof:placetype":"neighbourhood"
},
  "geometry": {"coordinates":[23.19057,52.74652],"type":"Point"}
}