{
  "type": "Feature",
  "properties": {
    "gn:admin1_code":"86.0",
    "gn:admin2_code":"3007.0",
    "gn:admin3_code":"300711.0",
    "gn:asciiname":"Goliszew",
    "gn:country_code":"PL",
    "gn:dem":122,
    "gn:feature_class":"P",
    "gn:feature_code":"PPL",
    "gn:name":"Goliszew",
    "gn:population":0,
    "gn:timezone":"Europe/Warsaw",
    "iso:country":"PL",
    "name:pol_x_preferred":[
        "Goliszew"
    ],
    "name:ukr_x_preferred":[
        "\u0490\u043e\u043b\u0456\u0448\u0435\u0432"
    ],
    "wof:name":"Goliszew",
    "wof:placetype":"locality"
},
  "geometry": {"coordinates":[18.17871,51.87308],"type":"Point"}
}