{
  "type": "Feature",
  "properties": {
    "gn:admin1_code":"83.0",
    "gn:admin2_code":"2406.0",
    "gn:admin3_code":"240607.0",
    "gn:asciiname":"Debie",
    "gn:country_code":"PL",
    "gn:dem":216,
    "gn:feature_class":"P",
    "gn:feature_code":"PPL",
    "gn:name":"D\u0119bie",
    "gn:population":0,
    "gn:timezone":"Europe/Warsaw",
    "iso:country":"PL",
    "name:ceb_x_preferred":[
        "D\u0119bie"
    ],
    "name:pol_x_preferred":[
        "D\u0119bie"
    ],
    "name:ukr_x_preferred":[
        "\u0414\u0435\u043c\u0431\u0435"
    ],
    "wof:name":"Debie",
    "wof:placetype":"locality"
},
  "geometry": {"coordinates":[18.92378,51.05078],"type":"Point"}
}