{
  "type": "Feature",
  "properties": {
    "gn:admin1_code":"78.0",
    "gn:admin2_code":"1403.0",
    "gn:admin3_code":"140307.0",
    "gn:asciiname":"Podoblin",
    "gn:cc2":"PL",
    "gn:country_code":"PL",
    "gn:dem":105,
    "gn:feature_class":"P",
    "gn:feature_code":"PPL",
    "gn:name":"Podoblin",
    "gn:population":0,
    "gn:timezone":"Europe/Warsaw",
    "iso:country":"PL",
    "name:fra_x_preferred":[
        "Podoblin"
    ],
    "name:pol_x_preferred":[
        "Podoblin"
    ],
    "name:spa_x_preferred":[
        "Podoblin"
    ],
    "name:ukr_x_preferred":[
        "\u041f\u043e\u0434\u043e\u0431\u043b\u0456\u043d"
    ],
    "name:und_x_variant":[
        "Budki"
    ],
    "wof:name":"Podoblin",
    "wof:placetype":"locality"
},
  "geometry": {"coordinates":[21.52702,51.70703],"type":"Point"}
}