{
  "type": "Feature",
  "properties": {
    "gn:admin1_code":"80.0",
    "gn:admin2_code":"1813.0",
    "gn:admin3_code":"181304.0",
    "gn:asciiname":"Na Gorach",
    "gn:country_code":"PL",
    "gn:dem":300,
    "gn:feature_class":"P",
    "gn:feature_code":"PPL",
    "gn:name":"Na G\u00f3rach",
    "gn:population":0,
    "gn:timezone":"Europe/Warsaw",
    "iso:country":"PL",
    "wof:name":"Na Gorach",
    "wof:placetype":"locality"
},
  "geometry": {"coordinates":[22.66667,49.75],"type":"Point"}
}