{
  "type": "Feature",
  "properties": {
    "gn:admin1_code":"86.0",
    "gn:admin2_code":"3008.0",
    "gn:admin3_code":"300803.0",
    "gn:asciiname":"Szklarka",
    "gn:country_code":"PL",
    "gn:dem":173,
    "gn:feature_class":"P",
    "gn:feature_code":"PPL",
    "gn:name":"Szklarka",
    "gn:population":0,
    "gn:timezone":"Europe/Warsaw",
    "iso:country":"PL",
    "name:pol_x_preferred":[
        "Szklarka Miel\u0119cka"
    ],
    "name:ukr_x_preferred":[
        "\u0428\u043a\u043b\u044f\u0440\u043a\u0430-\u041c\u0435\u043b\u0435\u043d\u0446\u044c\u043a\u0430"
    ],
    "name:und_x_variant":[
        "Szklarka"
    ],
    "wof:name":"Szklarka",
    "wof:placetype":"locality"
},
  "geometry": {"coordinates":[17.9305,51.30607],"type":"Point"}
}