{
  "type": "Feature",
  "properties": {
    "gn:admin1_code":"78.0",
    "gn:admin2_code":"1419.0",
    "gn:admin3_code":"141910.0",
    "gn:asciiname":"Sniegocin",
    "gn:country_code":"PL",
    "gn:dem":144,
    "gn:feature_class":"P",
    "gn:feature_code":"PPL",
    "gn:name":"\u015aniegocin",
    "gn:population":0,
    "gn:timezone":"Europe/Warsaw",
    "iso:country":"PL",
    "name:fra_x_preferred":[
        "\u015aniegocin"
    ],
    "name:pol_x_preferred":[
        "\u015aniegocin"
    ],
    "name:ukr_x_preferred":[
        "\u0421\u044c\u043d\u0435\u0491\u043e\u0446\u0438\u043d"
    ],
    "wof:name":"Sniegocin",
    "wof:placetype":"locality"
},
  "geometry": {"coordinates":[19.88672,52.62334],"type":"Point"}
}