{
  "type": "Feature",
  "properties": {
    "gn:admin1_code":"74.0",
    "gn:admin2_code":"1001.0",
    "gn:admin3_code":"100108.0",
    "gn:asciiname":"Zelowek",
    "gn:country_code":"PL",
    "gn:dem":193,
    "gn:feature_class":"P",
    "gn:feature_code":"PPL",
    "gn:name":"Zel\u00f3wek",
    "gn:population":0,
    "gn:timezone":"Europe/Warsaw",
    "iso:country":"PL",
    "name:und_x_variant":[
        "Zel\u00f3wek"
    ],
    "wof:name":"Zelowek",
    "wof:placetype":"locality"
},
  "geometry": {"coordinates":[19.23907,51.48522],"type":"Point"}
}