{
  "type": "Feature",
  "properties": {
    "iso:country":"PL",
    "name:azb_x_preferred":[
        "\u0686\u0627\u0633\u062a\u0627\u0631\u0647"
    ],
    "name:ceb_x_preferred":[
        "Czastary"
    ],
    "name:deu_x_preferred":[
        "Czastary"
    ],
    "name:fas_x_preferred":[
        "\u0686\u0627\u0633\u062a\u0627\u0631\u0647"
    ],
    "name:nld_x_preferred":[
        "Czastary"
    ],
    "name:pol_x_preferred":[
        "Czastary"
    ],
    "name:ukr_x_preferred":[
        "\u0427\u0430\u0441\u0442\u0430\u0440\u0438"
    ],
    "wof:coterminous":[
        1125366303
    ],
    "wof:name":"Czastary",
    "wof:placetype":"locality"
},
  "geometry": {"coordinates":[18.3162060187601,51.2526533546173],"type":"Point"}
}