{
  "type": "Feature",
  "properties": {
    "iso:country":"PL",
    "name:pol_x_preferred":[
        "Czastary"
    ],
    "wof:name":"Czastary",
    "wof:placetype":"locality"
},
  "geometry": {"coordinates":[18.3162060187601,51.2526533546173],"type":"Point"}
}