{
  "type": "Feature",
  "properties": {
    "gn:admin1_code":"87.0",
    "gn:admin2_code":"3207.0",
    "gn:admin3_code":"320706.0",
    "gn:asciiname":"Ostromice",
    "gn:country_code":"PL",
    "gn:dem":13,
    "gn:feature_class":"P",
    "gn:feature_code":"PPL",
    "gn:name":"Ostromice",
    "gn:population":0,
    "gn:timezone":"Europe/Warsaw",
    "iso:country":"PL",
    "name:azb_x_preferred":[
        "\u0627\u0648\u0633\u062a\u0631\u0648\u0645\u06cc\u062a\u0633\u0647"
    ],
    "name:ceb_x_preferred":[
        "Ostromice"
    ],
    "name:deu_x_preferred":[
        "Ostromice"
    ],
    "name:fas_x_preferred":[
        "\u0627\u0648\u0633\u062a\u0631\u0648\u0645\u06cc\u062a\u0633\u0647"
    ],
    "name:nld_x_preferred":[
        "Ostromice"
    ],
    "name:pol_x_preferred":[
        "Ostromice"
    ],
    "name:ukr_x_preferred":[
        "\u041e\u0441\u0442\u0440\u043e\u043c\u0456\u0446\u0435"
    ],
    "name:vie_x_preferred":[
        "Ostromice"
    ],
    "wof:name":"Ostromice",
    "wof:placetype":"locality"
},
  "geometry": {"coordinates":[14.76133,53.81886],"type":"Point"}
}