{
  "type": "Feature",
  "properties": {
    "gn:admin1_code":"87.0",
    "gn:admin2_code":"3207.0",
    "gn:admin3_code":"320706.0",
    "gn:asciiname":"Ostromice",
    "gn:country_code":"PL",
    "gn:dem":13,
    "gn:feature_class":"P",
    "gn:feature_code":"PPL",
    "gn:name":"Ostromice",
    "gn:population":0,
    "gn:timezone":"Europe/Warsaw",
    "iso:country":"PL",
    "wof:name":"Ostromice",
    "wof:placetype":"locality"
},
  "geometry": {"coordinates":[14.76133,53.81886],"type":"Point"}
}