{
  "type": "Feature",
  "properties": {
    "gn:admin1_code":"78.0",
    "gn:admin2_code":"1403.0",
    "gn:admin3_code":"140314.0",
    "gn:asciiname":"Huta Zelechowska",
    "gn:country_code":"PL",
    "gn:dem":172,
    "gn:feature_class":"P",
    "gn:feature_code":"PPL",
    "gn:name":"Huta \u017belechowska",
    "gn:population":0,
    "gn:timezone":"Europe/Warsaw",
    "iso:country":"PL",
    "name:fra_x_preferred":[
        "Br\u00f3d"
    ],
    "name:pol_x_preferred":[
        "Br\u00f3d"
    ],
    "wof:name":"Huta Zelechowska",
    "wof:placetype":"locality"
},
  "geometry": {"coordinates":[21.92974,51.82485],"type":"Point"}
}