{
  "type": "Feature",
  "properties": {
    "gn:admin1_code":"77.0",
    "gn:admin2_code":"1212.0",
    "gn:admin3_code":"121205.0",
    "gn:asciiname":"Zawada",
    "gn:country_code":"PL",
    "gn:dem":405,
    "gn:feature_class":"P",
    "gn:feature_code":"PPL",
    "gn:name":"Zawada",
    "gn:population":0,
    "gn:timezone":"Europe/Warsaw",
    "iso:country":"PL",
    "wof:name":"Zawada",
    "wof:placetype":"locality"
},
  "geometry": {"coordinates":[19.64015,50.22666],"type":"Point"}
}