{
  "type": "Feature",
  "properties": {
    "gn:admin1_code":"81.0",
    "gn:admin2_code":"2006.0",
    "gn:admin3_code":"200606.0",
    "gn:asciiname":"Pupki",
    "gn:country_code":"PL",
    "gn:dem":107,
    "gn:feature_class":"P",
    "gn:feature_code":"PPL",
    "gn:name":"Pupki",
    "gn:population":0,
    "gn:timezone":"Europe/Warsaw",
    "iso:country":"PL",
    "name:ceb_x_preferred":[
        "Pupki"
    ],
    "name:lit_x_preferred":[
        "Pupkai"
    ],
    "name:pol_x_preferred":[
        "Pupki"
    ],
    "name:ukr_x_preferred":[
        "\u041f\u0443\u043f\u043a\u0456"
    ],
    "wof:name":"Pupki",
    "wof:placetype":"locality"
},
  "geometry": {"coordinates":[21.80464,53.36399],"type":"Point"}
}