{
  "type": "Feature",
  "properties": {
    "gn:admin1_code":"84.0",
    "gn:admin2_code":"2610.0",
    "gn:admin3_code":"261004.0",
    "gn:asciiname":"Michalow Maly",
    "gn:country_code":"PL",
    "gn:dem":232,
    "gn:feature_class":"P",
    "gn:feature_code":"PPL",
    "gn:name":"Micha\u0142\u00f3w Ma\u0142y",
    "gn:population":0,
    "gn:timezone":"Europe/Warsaw",
    "iso:country":"PL",
    "name:und_x_variant":[
        "Micha\u0142\u00f3w",
        "Micha\u0142\u00f3w Ma\u0142y"
    ],
    "wof:name":"Michalow Maly",
    "wof:placetype":"locality"
},
  "geometry": {"coordinates":[20.93649,51.1002],"type":"Point"}
}