{
  "type": "Feature",
  "properties": {
    "gn:admin1_code":"84.0",
    "gn:admin2_code":"2608.0",
    "gn:admin3_code":"260802.0",
    "gn:asciiname":"Stawiany",
    "gn:country_code":"PL",
    "gn:dem":227,
    "gn:feature_class":"P",
    "gn:feature_code":"PPL",
    "gn:name":"Stawiany",
    "gn:population":0,
    "gn:timezone":"Europe/Warsaw",
    "iso:country":"PL",
    "name:pol_x_preferred":[
        "Stawiany"
    ],
    "name:ukr_x_preferred":[
        "\u0421\u0442\u0430\u0432\u044f\u043d\u0438"
    ],
    "wof:name":"Stawiany",
    "wof:placetype":"locality"
},
  "geometry": {"coordinates":[20.60331,50.59043],"type":"Point"}
}