{
  "type": "Feature",
  "properties": {
    "gn:admin1_code":"77.0",
    "gn:admin2_code":"1208.0",
    "gn:admin3_code":"120804.0",
    "gn:asciiname":"Mianocice",
    "gn:country_code":"PL",
    "gn:dem":264,
    "gn:feature_class":"P",
    "gn:feature_code":"PPL",
    "gn:name":"Mianocice",
    "gn:population":0,
    "gn:timezone":"Europe/Warsaw",
    "iso:country":"PL",
    "name:azb_x_preferred":[
        "\u0645\u06cc\u0627\u0646\u0648\u0686\u06cc\u062a\u0633\u0647"
    ],
    "name:ceb_x_preferred":[
        "Mianocice"
    ],
    "name:fas_x_preferred":[
        "\u0645\u06cc\u0627\u0646\u0648\u0686\u06cc\u062a\u0633\u0647"
    ],
    "name:ita_x_preferred":[
        "Mianocice"
    ],
    "name:nld_x_preferred":[
        "Mianocice"
    ],
    "name:pol_x_preferred":[
        "Mianocice"
    ],
    "name:rus_x_preferred":[
        "\u041c\u044f\u043d\u043e\u0446\u0438\u0446\u0435"
    ],
    "name:ukr_x_preferred":[
        "\u041c\u044f\u043d\u043e\u0446\u0438\u0446\u0435"
    ],
    "wof:name":"Mianocice",
    "wof:placetype":"locality"
},
  "geometry": {"coordinates":[20.10824,50.43739],"type":"Point"}
}