{
  "type": "Feature",
  "properties": {
    "gn:admin1_code":"78.0",
    "gn:admin2_code":"1425.0",
    "gn:admin3_code":"142510.0",
    "gn:asciiname":"Wolka Twarogowa",
    "gn:country_code":"PL",
    "gn:dem":165,
    "gn:feature_class":"P",
    "gn:feature_code":"PPL",
    "gn:name":"W\u00f3lka Twarogowa",
    "gn:population":0,
    "gn:timezone":"Europe/Warsaw",
    "iso:country":"PL",
    "name:fra_x_preferred":[
        "W\u00f3lka Twarogowa"
    ],
    "name:pol_x_preferred":[
        "W\u00f3lka Twarogowa"
    ],
    "name:ukr_x_preferred":[
        "\u0412\u0443\u043b\u044c\u043a\u0430-\u0422\u0432\u0430\u0440\u043e\u0491\u043e\u0432\u0430"
    ],
    "wof:name":"Wolka Twarogowa",
    "wof:placetype":"locality"
},
  "geometry": {"coordinates":[21.31325,51.27905],"type":"Point"}
}