{
  "type": "Feature",
  "properties": {
    "gn:admin1_code":"73.0",
    "gn:admin2_code":"418.0",
    "gn:admin3_code":"41811.0",
    "gn:asciiname":"Kolonia Rzezewo",
    "gn:country_code":"PL",
    "gn:dem":129,
    "gn:feature_class":"P",
    "gn:feature_code":"PPL",
    "gn:name":"Kolonia Rze\u017cewo",
    "gn:population":0,
    "gn:timezone":"Europe/Warsaw",
    "iso:country":"PL",
    "wof:name":"Kolonia Rzezewo",
    "wof:placetype":"locality"
},
  "geometry": {"coordinates":[19.11667000000001,52.41667],"type":"Point"}
}