{
  "type": "Feature",
  "properties": {
    "gn:admin1_code":"86.0",
    "gn:admin2_code":"3010.0",
    "gn:admin3_code":"301010.0",
    "gn:asciiname":"Szczerkowo",
    "gn:country_code":"PL",
    "gn:dem":95,
    "gn:feature_class":"P",
    "gn:feature_code":"PPL",
    "gn:name":"Szczerkowo",
    "gn:population":0,
    "gn:timezone":"Europe/Warsaw",
    "iso:country":"PL",
    "name:pol_x_preferred":[
        "Szczerkowo"
    ],
    "name:ukr_x_preferred":[
        "\u0429\u0435\u0440\u043a\u043e\u0432\u043e"
    ],
    "wof:name":"Szczerkowo",
    "wof:placetype":"locality"
},
  "geometry": {"coordinates":[18.52435,52.38529000000001],"type":"Point"}
}