{
  "type": "Feature",
  "properties": {
    "gn:admin1_code":"74.0",
    "gn:admin2_code":"1014.0",
    "gn:admin3_code":"101404.0",
    "gn:asciiname":"Zapole",
    "gn:country_code":"PL",
    "gn:dem":168,
    "gn:feature_class":"P",
    "gn:feature_code":"PPL",
    "gn:name":"Zapole",
    "gn:population":0,
    "gn:timezone":"Europe/Warsaw",
    "iso:country":"PL",
    "name:pol_x_preferred":[
        "Zapole"
    ],
    "name:ukr_x_preferred":[
        "\u0417\u0430\u043f\u043e\u043b\u0435"
    ],
    "wof:name":"Zapole",
    "wof:placetype":"locality"
},
  "geometry": {"coordinates":[18.6553,51.49100000000001],"type":"Point"}
}