{
  "type": "Feature",
  "properties": {
    "gn:admin1_code":"84.0",
    "gn:admin2_code":"2605.0",
    "gn:admin3_code":"260508.0",
    "gn:asciiname":"Blaszkow",
    "gn:country_code":"PL",
    "gn:dem":268,
    "gn:feature_class":"P",
    "gn:feature_code":"PPL",
    "gn:name":"B\u0142aszk\u00f3w",
    "gn:population":0,
    "gn:timezone":"Europe/Warsaw",
    "iso:country":"PL",
    "name:azb_x_preferred":[
        "\u0628\u0648\u0627\u0634\u06a9\u0648\u0648"
    ],
    "name:ceb_x_preferred":[
        "B\u0142aszk\u00f3w"
    ],
    "name:fas_x_preferred":[
        "\u0628\u0648\u0627\u0634\u06a9\u0648\u0648"
    ],
    "name:nld_x_preferred":[
        "B\u0142aszk\u00f3w"
    ],
    "name:pol_x_preferred":[
        "B\u0142aszk\u00f3w"
    ],
    "name:ukr_x_preferred":[
        "\u0411\u043b\u0430\u0448\u043a\u0443\u0432"
    ],
    "name:und_x_variant":[
        "B\u0142aszk\u00f3w"
    ],
    "wof:name":"Blaszkow",
    "wof:placetype":"locality"
},
  "geometry": {"coordinates":[20.60963,51.14124],"type":"Point"}
}