{
  "type": "Feature",
  "properties": {
    "gn:country":"PL",
    "gn:fcode":"PPL",
    "gn:population":312,
    "iso:country":"PL",
    "name:ast_x_preferred":[
        "Czerwonka"
    ],
    "name:ceb_x_preferred":[
        "Czerwonka"
    ],
    "name:eng_x_preferred":[
        "Czerwonka"
    ],
    "name:fra_x_preferred":[
        "Czerwonka"
    ],
    "name:lit_x_preferred":[
        "\u010cervonka"
    ],
    "name:pol_x_preferred":[
        "Czerwonka"
    ],
    "name:rus_x_preferred":[
        "\u0427\u0435\u0440\u0432\u043e\u043d\u043a\u0430"
    ],
    "name:ukr_x_preferred":[
        "\u0427\u0435\u0440\u0432\u043e\u043d\u043a\u0430"
    ],
    "qs_pg:aaroncc":"PL",
    "qs_pg:gn_country":"PL",
    "qs_pg:gn_fcode":"PPL",
    "qs_pg:gn_pop":312,
    "qs_pg:name":"Czerwonka",
    "qs_pg:name_adm0":"Polska",
    "qs_pg:name_adm1":"Podlaskie",
    "qs_pg:photos_9r":0,
    "qs_pg:photos_sr":0,
    "qs_pg:pop_sr":2,
    "qs_pg:qs_pg_placetype":"locality",
    "qs_pg:qs_pg_placetype_gp":"Town",
    "qs_pg:woe_adm0":23424923,
    "woe:adm0_id":23424923,
    "woe:name_adm0":"Polska",
    "woe:name_adm1":"Podlaskie",
    "woe:placetype":"Town",
    "wof:name":"Czerwonka",
    "wof:placetype":"locality",
    "wof:population":312
},
  "geometry": {"coordinates":[23.21239,53.5763],"type":"Point"}
}