{
  "type": "Feature",
  "properties": {
    "gn:admin1_code":"75.0",
    "gn:admin2_code":"609.0",
    "gn:admin3_code":"60904.0",
    "gn:asciiname":"Borkow",
    "gn:country_code":"PL",
    "gn:dem":182,
    "gn:feature_class":"P",
    "gn:feature_code":"PPL",
    "gn:name":"Bork\u00f3w",
    "gn:population":0,
    "gn:timezone":"Europe/Warsaw",
    "iso:country":"PL",
    "name:fra_x_preferred":[
        "Bork\u00f3w"
    ],
    "name:pol_x_preferred":[
        "Bork\u00f3w"
    ],
    "name:ukr_x_preferred":[
        "\u0411\u043e\u0440\u043a\u0443\u0432"
    ],
    "wof:name":"Borkow",
    "wof:placetype":"locality"
},
  "geometry": {"coordinates":[22.38602,51.38271],"type":"Point"}
}