{
  "type": "Feature",
  "properties": {
    "gn:admin1_code":"78.0",
    "gn:admin2_code":"1416.0",
    "gn:admin3_code":"141609.0",
    "gn:asciiname":"Uscianek Debianka",
    "gn:country_code":"PL",
    "gn:dem":118,
    "gn:feature_class":"P",
    "gn:feature_code":"PPL",
    "gn:name":"U\u015bcianek D\u0119bianka",
    "gn:population":0,
    "gn:timezone":"Europe/Warsaw",
    "iso:country":"PL",
    "wof:name":"Uscianek Debianka",
    "wof:placetype":"locality"
},
  "geometry": {"coordinates":[22.28577,52.74715],"type":"Point"}
}