{
  "type": "Feature",
  "properties": {
    "gn:admin1_code":"85.0",
    "gn:admin2_code":"2818.0",
    "gn:admin3_code":"281801.0",
    "gn:asciiname":"Zielony Lasek",
    "gn:country_code":"PL",
    "gn:dem":158,
    "gn:feature_class":"P",
    "gn:feature_code":"PPL",
    "gn:name":"Zielony Lasek",
    "gn:population":0,
    "gn:timezone":"Europe/Warsaw",
    "iso:country":"PL",
    "name:deu_x_preferred":[
        "Zielony Lasek"
    ],
    "name:fra_x_preferred":[
        "Zielony Lasek"
    ],
    "name:pol_x_preferred":[
        "Zielony Lasek"
    ],
    "name:und_x_variant":[
        "Gr\u00fcnwalde"
    ],
    "wof:name":"Zielony Lasek",
    "wof:placetype":"locality"
},
  "geometry": {"coordinates":[22.00099,54.20235],"type":"Point"}
}