{
  "type": "Feature",
  "properties": {
    "gn:admin1_code":"78.0",
    "gn:admin2_code":"1422.0",
    "gn:admin3_code":"142207.0",
    "gn:asciiname":"Gostkowo",
    "gn:country_code":"PL",
    "gn:dem":121,
    "gn:feature_class":"P",
    "gn:feature_code":"PPL",
    "gn:name":"Gostkowo",
    "gn:population":0,
    "gn:timezone":"Europe/Warsaw",
    "iso:country":"PL",
    "name:fra_x_preferred":[
        "Gostkowo"
    ],
    "name:pol_x_preferred":[
        "Gostkowo"
    ],
    "name:ukr_x_preferred":[
        "\u0490\u043e\u0441\u0442\u043a\u043e\u0432\u043e"
    ],
    "wof:name":"Gostkowo",
    "wof:placetype":"locality"
},
  "geometry": {"coordinates":[20.91356,52.95815],"type":"Point"}
}