{
  "type": "Feature",
  "properties": {
    "gn:admin1_code":"82.0",
    "gn:admin2_code":"2203.0",
    "gn:admin3_code":"220307.0",
    "gn:asciiname":"Gockowo",
    "gn:country_code":"PL",
    "gn:dem":152,
    "gn:feature_class":"P",
    "gn:feature_code":"PPL",
    "gn:name":"Gockowo",
    "gn:population":0,
    "gn:timezone":"Europe/Warsaw",
    "iso:country":"PL",
    "name:ceb_x_preferred":[
        "Gockowo"
    ],
    "name:pol_x_preferred":[
        "Gockowo"
    ],
    "wof:name":"Gockowo",
    "wof:placetype":"locality"
},
  "geometry": {"coordinates":[17.06424,53.72227],"type":"Point"}
}