{
  "type": "Feature",
  "properties": {
    "gn:admin1_code":"73.0",
    "gn:admin2_code":"403.0",
    "gn:admin3_code":"40303.0",
    "gn:asciiname":"Wudzyn",
    "gn:country_code":"PL",
    "gn:dem":94,
    "gn:feature_class":"P",
    "gn:feature_code":"PPL",
    "gn:name":"Wudzyn",
    "gn:population":0,
    "gn:timezone":"Europe/Warsaw",
    "iso:country":"PL",
    "name:pol_x_preferred":[
        "Wudzyn"
    ],
    "name:ukr_x_preferred":[
        "\u0412\u0443\u0434\u0437\u0438\u043d"
    ],
    "wof:name":"Wudzyn",
    "wof:placetype":"locality"
},
  "geometry": {"coordinates":[18.07969,53.32259000000001],"type":"Point"}
}