{
  "type": "Feature",
  "properties": {
    "iso:country":"PL",
    "name:pol_x_preferred":[
        "Lipnica Wielka"
    ],
    "wof:coterminous":[
        1125280979
    ],
    "wof:name":"Lipnica Wielka",
    "wof:placetype":"locality"
},
  "geometry": {"coordinates":[19.5794586349586,49.5072586521305],"type":"Point"}
}