{
  "type": "Feature",
  "properties": {
    "gn:admin1_code":"76.0",
    "gn:admin2_code":"811.0",
    "gn:admin3_code":"81110.0",
    "gn:asciiname":"Surowa",
    "gn:country_code":"PL",
    "gn:dem":156,
    "gn:feature_class":"P",
    "gn:feature_code":"PPL",
    "gn:name":"Surowa",
    "gn:population":0,
    "gn:timezone":"Europe/Warsaw",
    "iso:country":"PL",
    "name:fra_x_preferred":[
        "Surowa"
    ],
    "name:pol_x_preferred":[
        "Surowa"
    ],
    "name:ukr_x_preferred":[
        "\u0421\u0443\u0440\u043e\u0432\u0430"
    ],
    "wof:name":"Surowa",
    "wof:placetype":"locality"
},
  "geometry": {"coordinates":[15.13426,51.69299],"type":"Point"}
}