{
  "type": "Feature",
  "properties": {
    "gn:country":"PL",
    "gn:fcode":"PPL",
    "gn:population":270,
    "iso:country":"PL",
    "name:ast_x_preferred":[
        "Wawrze\u0144czyce"
    ],
    "name:ceb_x_preferred":[
        "Wawrze\u0144czyce"
    ],
    "name:eng_x_preferred":[
        "Wawrze\u0144czyce"
    ],
    "name:fra_x_preferred":[
        "Wawrze\u0144czyce"
    ],
    "name:pol_x_preferred":[
        "Wawrze\u0144czyce"
    ],
    "name:ukr_x_preferred":[
        "\u0412\u0430\u0432\u0436\u0435\u043d\u044c\u0447\u0438\u0446\u0435"
    ],
    "qs_pg:aaroncc":"PL",
    "qs_pg:gn_country":"PL",
    "qs_pg:gn_fcode":"PPL",
    "qs_pg:gn_pop":270,
    "qs_pg:name":"Wawrze\u0144czyce",
    "qs_pg:name_adm0":"Polska",
    "qs_pg:name_adm1":"Swi\u0119tokrzyskie",
    "qs_pg:photos_9r":0,
    "qs_pg:photos_sr":0,
    "qs_pg:pop_sr":2,
    "qs_pg:qs_pg_placetype":"locality",
    "qs_pg:qs_pg_placetype_gp":"Town",
    "qs_pg:woe_adm0":23424923,
    "woe:adm0_id":23424923,
    "woe:name_adm0":"Polska",
    "woe:name_adm1":"Swi\u0119tokrzyskie",
    "woe:placetype":"Town",
    "wof:name":"Wawrze\u0144czyce",
    "wof:placetype":"neighbourhood",
    "wof:population":270
},
  "geometry": {"coordinates":[21.10528,50.93028],"type":"Point"}
}