{
  "type": "Feature",
  "properties": {
    "gn:admin1_code":"72.0",
    "gn:admin2_code":"218.0",
    "gn:admin3_code":"21805.0",
    "gn:asciiname":"Lasek",
    "gn:country_code":"PL",
    "gn:dem":178,
    "gn:feature_class":"P",
    "gn:feature_code":"PPL",
    "gn:name":"Lasek",
    "gn:population":0,
    "gn:timezone":"Europe/Warsaw",
    "iso:country":"PL",
    "name:pol_x_preferred":[
        "Lasek"
    ],
    "name:ukr_x_preferred":[
        "\u041b\u044f\u0441\u0435\u043a"
    ],
    "wof:name":"Lasek",
    "wof:placetype":"locality"
},
  "geometry": {"coordinates":[16.4661,51.01527],"type":"Point"}
}