{
  "type": "Feature",
  "properties": {
    "gn:admin1_code":"76.0",
    "gn:admin2_code":"809.0",
    "gn:admin3_code":"80909.0",
    "gn:asciiname":"Tarnawa",
    "gn:country_code":"PL",
    "gn:dem":61,
    "gn:feature_class":"P",
    "gn:feature_code":"PPL",
    "gn:name":"Tarnawa",
    "gn:population":0,
    "gn:timezone":"Europe/Warsaw",
    "iso:country":"PL",
    "name:fra_x_preferred":[
        "Tarnawa"
    ],
    "name:pol_x_preferred":[
        "Tarnawa"
    ],
    "name:ukr_x_preferred":[
        "\u0422\u0430\u0440\u043d\u0430\u0432\u0430"
    ],
    "wof:name":"Tarnawa",
    "wof:placetype":"locality"
},
  "geometry": {"coordinates":[15.71933,51.96449000000001],"type":"Point"}
}