{
  "type": "Feature",
  "properties": {
    "gn:admin1_code":"74.0",
    "gn:admin2_code":"1015.0",
    "gn:admin3_code":"101509.0",
    "gn:asciiname":"Bonarow",
    "gn:country_code":"PL",
    "gn:dem":208,
    "gn:feature_class":"P",
    "gn:feature_code":"PPL",
    "gn:name":"Bonar\u00f3w",
    "gn:population":0,
    "gn:timezone":"Europe/Warsaw",
    "iso:country":"PL",
    "name:pol_x_preferred":[
        "Bonar\u00f3w"
    ],
    "name:ukr_x_preferred":[
        "\u0411\u043e\u043d\u0430\u0440\u0443\u0432"
    ],
    "wof:name":"Bonarow",
    "wof:placetype":"locality"
},
  "geometry": {"coordinates":[19.91008,51.86055],"type":"Point"}
}