{
  "type": "Feature",
  "properties": {
    "gn:gn_country":"PL",
    "gn:gn_fcode":"PPLA3",
    "gn:gn_pop":442,
    "gn:population":442,
    "iso:country":"PL",
    "name:unk_x_variant":[
        "Dzierz\u0105\u017ana"
    ],
    "qs_pg:aaroncc":"PL",
    "qs_pg:gn_country":"PL",
    "qs_pg:gn_fcode":"PPLA3",
    "qs_pg:gn_pop":442,
    "qs_pg:name":"Dzierz\u0105\u017cnia",
    "qs_pg:name_adm0":"Polska",
    "qs_pg:name_adm1":"Mazowieckie",
    "qs_pg:photos_9k":1,
    "qs_pg:photos_9r":1,
    "qs_pg:photos_all":9,
    "qs_pg:photos_sr":0,
    "qs_pg:pop_sr":2,
    "qs_pg:qs_pg_placetype":"localadmin",
    "qs_pg:qs_pg_placetype_gp":"LocalAdmin",
    "qs_pg:woe_adm0":23424923,
    "woe:adm0_id":23424923,
    "woe:name_adm0":"Polska",
    "woe:name_adm1":"Mazowieckie",
    "woe:placetype":"LocalAdmin",
    "wof:name":"Dzierz\u0105\u017cnia",
    "wof:placetype":"localadmin",
    "wof:population":442
},
  "geometry": {"coordinates":[20.23364,52.62811],"type":"Point"}
}