{
  "type": "Feature",
  "properties": {
    "gn:country":"PL",
    "gn:fcode":"PPLA3",
    "gn:population":442,
    "iso:country":"PL",
    "name:azb_x_preferred":[
        "\u062c\u0698\u0627\u0646\u0698\u0646\u0642\u0627"
    ],
    "name:ceb_x_preferred":[
        "Dzierz\u0105\u017cnia"
    ],
    "name:deu_x_preferred":[
        "Dzierz\u0105\u017cnia"
    ],
    "name:fas_x_preferred":[
        "\u062c\u0698\u0627\u0646\u0698\u0646\u06af\u0627"
    ],
    "name:fra_x_preferred":[
        "Dzierz\u0105\u017cnia"
    ],
    "name:nld_x_preferred":[
        "Dzierz\u0105\u017cnia"
    ],
    "name:pol_x_preferred":[
        "Dzierz\u0105\u017cnia"
    ],
    "name:ukr_x_preferred":[
        "\u0414\u0437\u0435\u0436\u043e\u043d\u0436\u043d\u044f"
    ],
    "name:und_x_variant":[
        "Dzierz\u0105\u017ana"
    ],
    "qs_pg:aaroncc":"PL",
    "qs_pg:gn_country":"PL",
    "qs_pg:gn_fcode":"PPLA3",
    "qs_pg:gn_pop":442,
    "qs_pg:name":"Dzierz\u0105\u017cnia",
    "qs_pg:name_adm0":"Polska",
    "qs_pg:name_adm1":"Mazowieckie",
    "qs_pg:photos_9k":1,
    "qs_pg:photos_9r":1,
    "qs_pg:photos_all":9,
    "qs_pg:photos_sr":0,
    "qs_pg:pop_sr":2,
    "qs_pg:qs_pg_placetype":"localadmin",
    "qs_pg:qs_pg_placetype_gp":"LocalAdmin",
    "qs_pg:woe_adm0":23424923,
    "woe:adm0_id":23424923,
    "woe:name_adm0":"Polska",
    "woe:name_adm1":"Mazowieckie",
    "woe:placetype":"LocalAdmin",
    "wof:name":"Dzierz\u0105\u017cnia",
    "wof:placetype":"localadmin",
    "wof:population":442
},
  "geometry": {"coordinates":[20.23364,52.62811],"type":"Point"}
}