{
  "type": "Feature",
  "properties": {
    "gn:admin1_code":"85.0",
    "gn:admin2_code":"2812.0",
    "gn:admin3_code":"281204.0",
    "gn:asciiname":"Wawrowice",
    "gn:country_code":"PL",
    "gn:dem":115,
    "gn:feature_class":"P",
    "gn:feature_code":"PPL",
    "gn:name":"Wawrowice",
    "gn:population":0,
    "gn:timezone":"Europe/Warsaw",
    "iso:country":"PL",
    "name:pol_x_preferred":[
        "Wawrowice"
    ],
    "name:ukr_x_preferred":[
        "\u0412\u0430\u0432\u0440\u043e\u0432\u0456\u0446\u0435"
    ],
    "wof:name":"Wawrowice",
    "wof:placetype":"locality"
},
  "geometry": {"coordinates":[19.46379,53.44244000000001],"type":"Point"}
}