{
  "type": "Feature",
  "properties": {
    "gn:admin1_code":"81.0",
    "gn:admin2_code":"2011.0",
    "gn:admin3_code":"201108.0",
    "gn:asciiname":"Geniusze",
    "gn:country_code":"PL",
    "gn:dem":154,
    "gn:feature_class":"P",
    "gn:feature_code":"PPL",
    "gn:name":"Geniusze",
    "gn:population":0,
    "gn:timezone":"Europe/Warsaw",
    "iso:country":"PL",
    "name:lit_x_preferred":[
        "Geniu\u0161\u0117"
    ],
    "name:pol_x_preferred":[
        "Geniusze"
    ],
    "name:ukr_x_preferred":[
        "\u0490\u0435\u043d\u044e\u0448\u0435"
    ],
    "name:und_x_variant":[
        "Cieniusze",
        "Gilniusze"
    ],
    "wof:name":"Geniusze",
    "wof:placetype":"locality"
},
  "geometry": {"coordinates":[23.42355,53.37328],"type":"Point"}
}