{
  "type": "Feature",
  "properties": {
    "gn:admin1_code":"85.0",
    "gn:admin2_code":"2804.0",
    "gn:admin3_code":"280405.0",
    "gn:asciiname":"Majewo",
    "gn:country_code":"PL",
    "gn:dem":156,
    "gn:feature_class":"P",
    "gn:feature_code":"PPL",
    "gn:name":"Majewo",
    "gn:population":0,
    "gn:timezone":"Europe/Warsaw",
    "iso:country":"PL",
    "name:azb_x_preferred":[
        "\u0645\u0627\u06cc\u0648\u0648"
    ],
    "name:ceb_x_preferred":[
        "Majewo"
    ],
    "name:deu_x_preferred":[
        "Majewo"
    ],
    "name:fas_x_preferred":[
        "\u0645\u0627\u06cc\u0648\u0648"
    ],
    "name:nld_x_preferred":[
        "Majewo"
    ],
    "name:pol_x_preferred":[
        "Majewo"
    ],
    "name:ukr_x_preferred":[
        "\u041c\u0430\u0454\u0432\u043e"
    ],
    "name:und_x_variant":[
        "Maibaum"
    ],
    "wof:name":"Majewo",
    "wof:placetype":"locality"
},
  "geometry": {"coordinates":[19.58152,54.22087],"type":"Point"}
}