{
  "type": "Feature",
  "properties": {
    "gn:country":"PL",
    "gn:fcode":"PPLA3",
    "gn:population":543,
    "iso:country":"PL",
    "name:azb_x_preferred":[
        "\u067e\u0648\u0648\u0698\u0646\u0642\u062a\u0633\u0627"
    ],
    "name:ceb_x_preferred":[
        "P\u0142u\u017cnica"
    ],
    "name:fas_x_preferred":[
        "\u067e\u0648\u0648\u0698\u0646\u06af\u062a\u0633\u0627"
    ],
    "name:nld_x_preferred":[
        "P\u0142u\u017cnica"
    ],
    "name:pol_x_preferred":[
        "P\u0142u\u017cnica"
    ],
    "name:ukr_x_preferred":[
        "\u041f\u043b\u0443\u0436\u043d\u0438\u0446\u044f"
    ],
    "qs_pg:aaroncc":"PL",
    "qs_pg:gn_country":"PL",
    "qs_pg:gn_fcode":"PPLA3",
    "qs_pg:gn_pop":543,
    "qs_pg:name":"P\u0142u\u017cnica",
    "qs_pg:name_adm0":"Polska",
    "qs_pg:name_adm1":"Kujawsko-Pomorskie",
    "qs_pg:photos_9r":0,
    "qs_pg:photos_sr":0,
    "qs_pg:pop_sr":2,
    "qs_pg:qs_pg_placetype":"localadmin",
    "qs_pg:qs_pg_placetype_gp":"LocalAdmin",
    "qs_pg:woe_adm0":23424923,
    "woe:adm0_id":23424923,
    "woe:name_adm0":"Polska",
    "woe:name_adm1":"Kujawsko-Pomorskie",
    "woe:placetype":"LocalAdmin",
    "wof:name":"P\u0142u\u017cnica",
    "wof:placetype":"localadmin",
    "wof:population":543
},
  "geometry": {"coordinates":[18.77692,53.29672],"type":"Point"}
}