{
  "type": "Feature",
  "properties": {
    "gn:admin1_code":"78.0",
    "gn:admin2_code":"1414.0",
    "gn:admin3_code":"141402.0",
    "gn:asciiname":"Dabrowka",
    "gn:cc2":"PL",
    "gn:country_code":"PL",
    "gn:dem":87,
    "gn:feature_class":"P",
    "gn:feature_code":"PPL",
    "gn:name":"D\u0105br\u00f3wka",
    "gn:population":0,
    "gn:timezone":"Europe/Warsaw",
    "iso:country":"PL",
    "name:fra_x_preferred":[
        "D\u0105br\u00f3wka"
    ],
    "name:pol_x_preferred":[
        "D\u0105br\u00f3wka"
    ],
    "name:ukr_x_preferred":[
        "\u0414\u043e\u043c\u0431\u0440\u0443\u0432\u043a\u0430"
    ],
    "name:und_x_variant":[
        "D\u0105br\u00f3wka Stara"
    ],
    "wof:name":"Dabrowka",
    "wof:placetype":"locality"
},
  "geometry": {"coordinates":[20.60555,52.35138],"type":"Point"}
}