{
  "type": "Feature",
  "properties": {
    "gn:admin1_code":"86.0",
    "gn:admin2_code":"3028.0",
    "gn:admin3_code":"302803.0",
    "gn:asciiname":"Rybowo",
    "gn:country_code":"PL",
    "gn:dem":100,
    "gn:feature_class":"P",
    "gn:feature_code":"PPL",
    "gn:name":"Rybowo",
    "gn:population":0,
    "gn:timezone":"Europe/Warsaw",
    "iso:country":"PL",
    "name:fra_x_preferred":[
        "Rybowo"
    ],
    "name:pol_x_preferred":[
        "Rybowo"
    ],
    "name:ukr_x_preferred":[
        "\u0420\u0438\u0431\u043e\u0432\u043e"
    ],
    "wof:name":"Rybowo",
    "wof:placetype":"locality"
},
  "geometry": {"coordinates":[17.22481,52.93659],"type":"Point"}
}