{
  "type": "Feature",
  "properties": {
    "gn:admin1_code":"83.0",
    "gn:admin2_code":"2401.0",
    "gn:admin3_code":"240107.0",
    "gn:asciiname":"Slowik",
    "gn:country_code":"PL",
    "gn:dem":315,
    "gn:feature_class":"P",
    "gn:feature_code":"PPL",
    "gn:name":"S\u0142owik",
    "gn:population":0,
    "gn:timezone":"Europe/Warsaw",
    "iso:country":"PL",
    "wof:name":"Slowik",
    "wof:placetype":"locality"
},
  "geometry": {"coordinates":[19.252,50.52004],"type":"Point"}
}