{
  "type": "Feature",
  "properties": {
    "gn:admin1_code":"86.0",
    "gn:admin2_code":"3027.0",
    "gn:admin3_code":"302703.0",
    "gn:asciiname":"Dabrowica",
    "gn:country_code":"PL",
    "gn:dem":122,
    "gn:feature_class":"P",
    "gn:feature_code":"PPL",
    "gn:name":"D\u0105browica",
    "gn:population":0,
    "gn:timezone":"Europe/Warsaw",
    "iso:country":"PL",
    "name:pol_x_preferred":[
        "D\u0105browica"
    ],
    "name:ukr_x_preferred":[
        "\u0414\u043e\u043c\u0431\u0440\u043e\u0432\u0438\u0446\u044f"
    ],
    "wof:name":"Dabrowica",
    "wof:placetype":"locality"
},
  "geometry": {"coordinates":[18.6838,51.94056],"type":"Point"}
}