{
  "type": "Feature",
  "properties": {
    "gn:admin1_code":"82.0",
    "gn:admin2_code":"2204.0",
    "gn:admin3_code":"220402.0",
    "gn:asciiname":"Cedry Male",
    "gn:country_code":"PL",
    "gn:dem":0,
    "gn:feature_class":"P",
    "gn:feature_code":"PPL",
    "gn:name":"Cedry Ma\u0142e",
    "gn:population":0,
    "gn:timezone":"Europe/Warsaw",
    "iso:country":"PL",
    "name:und_x_variant":[
        "Klein Z\u00fcnder",
        "Cedry Ma\u0142e"
    ],
    "wof:name":"Cedry Male",
    "wof:placetype":"locality"
},
  "geometry": {"coordinates":[18.86124,54.27304],"type":"Point"}
}