{
  "type": "Feature",
  "properties": {
    "gn:admin1_code":"82.0",
    "gn:admin2_code":"2204.0",
    "gn:admin3_code":"220402.0",
    "gn:asciiname":"Cedry Male",
    "gn:country_code":"PL",
    "gn:dem":0,
    "gn:feature_class":"P",
    "gn:feature_code":"PPL",
    "gn:name":"Cedry Ma\u0142e",
    "gn:population":0,
    "gn:timezone":"Europe/Warsaw",
    "iso:country":"PL",
    "name:ceb_x_preferred":[
        "Cedry Ma\u0142e"
    ],
    "name:nld_x_preferred":[
        "Cedry Ma\u0142e"
    ],
    "name:pol_x_preferred":[
        "Cedry Ma\u0142e"
    ],
    "name:ukr_x_preferred":[
        "\u0426\u0435\u0434\u0440\u0438-\u041c\u0430\u043b\u0435"
    ],
    "name:und_x_variant":[
        "Klein Z\u00fcnder"
    ],
    "wof:name":"Cedry Male",
    "wof:placetype":"locality"
},
  "geometry": {"coordinates":[18.86124,54.27304],"type":"Point"}
}