{
  "type": "Feature",
  "properties": {
    "gn:admin1_code":"80.0",
    "gn:admin2_code":"1811.0",
    "gn:admin3_code":"181103.0",
    "gn:asciiname":"Wagrada",
    "gn:country_code":"PL",
    "gn:dem":158,
    "gn:feature_class":"P",
    "gn:feature_code":"PPL",
    "gn:name":"W\u0105grada",
    "gn:population":0,
    "gn:timezone":"Europe/Warsaw",
    "iso:country":"PL",
    "wof:name":"Wagrada",
    "wof:placetype":"locality"
},
  "geometry": {"coordinates":[21.23142,50.3459],"type":"Point"}
}