{
  "type": "Feature",
  "properties": {
    "gn:admin1_code":"77.0",
    "gn:admin2_code":"1212.0",
    "gn:admin3_code":"121206.0",
    "gn:asciiname":"Tarnawa",
    "gn:country_code":"PL",
    "gn:dem":395,
    "gn:feature_class":"P",
    "gn:feature_code":"PPL",
    "gn:name":"Tarnawa",
    "gn:population":0,
    "gn:timezone":"Europe/Warsaw",
    "iso:country":"PL",
    "name:fra_x_preferred":[
        "Tarnawa"
    ],
    "name:pol_x_preferred":[
        "Tarnawa"
    ],
    "name:rus_x_preferred":[
        "\u0422\u0430\u0440\u043d\u0430\u0432\u0430"
    ],
    "name:ukr_x_preferred":[
        "\u0422\u0430\u0440\u043d\u0430\u0432\u0430"
    ],
    "wof:name":"Tarnawa",
    "wof:placetype":"locality"
},
  "geometry": {"coordinates":[19.84211,50.27519],"type":"Point"}
}