{
  "type": "Feature",
  "properties": {
    "iso:country":"PL",
    "name:ast_x_preferred":[
        "Silno"
    ],
    "name:ceb_x_preferred":[
        "Silno"
    ],
    "name:eng_x_preferred":[
        "Silno"
    ],
    "name:fra_x_preferred":[
        "Silno"
    ],
    "name:pol_x_preferred":[
        "Silno"
    ],
    "name:ukr_x_preferred":[
        "\u0421\u0456\u043b\u044c\u043d\u043e"
    ],
    "qs:a0":"Rzeczpospolita Polska",
    "qs:a1":"*Pomorskie",
    "qs:a1r":"0",
    "qs:a2":"Chojnicki",
    "qs:adm0":"Rzeczpospolita Polska",
    "qs:la_lc":"*",
    "qs:level":"locality",
    "qs:loc":"Silno",
    "qs:loc_alt":"Silno",
    "qs:pop":0,
    "qs:type":"buffered point",
    "wd:wordcount":106,
    "wof:name":"Silno",
    "wof:placetype":"locality"
},
  "geometry": {"coordinates":[17.705416,53.64803],"type":"Point"}
}