{
  "type": "Feature",
  "properties": {
    "gn:admin1_code":"86.0",
    "gn:admin2_code":"3022.0",
    "gn:admin3_code":"302204.0",
    "gn:asciiname":"Kubeczki",
    "gn:country_code":"PL",
    "gn:dem":95,
    "gn:feature_class":"P",
    "gn:feature_code":"PPL",
    "gn:name":"Kubeczki",
    "gn:population":0,
    "gn:timezone":"Europe/Warsaw",
    "iso:country":"PL",
    "wof:name":"Kubeczki",
    "wof:placetype":"locality"
},
  "geometry": {"coordinates":[16.99618,51.57785],"type":"Point"}
}