{
  "type": "Feature",
  "properties": {
    "gn:admin1_code":"86.0",
    "gn:admin2_code":"3022.0",
    "gn:admin3_code":"302204.0",
    "gn:asciiname":"Kubeczki",
    "gn:country_code":"PL",
    "gn:dem":95,
    "gn:feature_class":"P",
    "gn:feature_code":"PPL",
    "gn:name":"Kubeczki",
    "gn:population":0,
    "gn:timezone":"Europe/Warsaw",
    "iso:country":"PL",
    "name:azb_x_preferred":[
        "\u06a9\u0648\u0628\u0686\u06a9\u06cc"
    ],
    "name:fas_x_preferred":[
        "\u06a9\u0648\u0628\u0686\u06a9\u06cc"
    ],
    "name:fra_x_preferred":[
        "Kubeczki"
    ],
    "name:pol_x_preferred":[
        "Kubeczki"
    ],
    "name:ukr_x_preferred":[
        "\u041a\u0443\u0431\u0435\u0447\u043a\u0456"
    ],
    "wof:name":"Kubeczki",
    "wof:placetype":"locality"
},
  "geometry": {"coordinates":[16.99618,51.57785],"type":"Point"}
}