{
  "type": "Feature",
  "properties": {
    "gn:admin1_code":"87.0",
    "gn:admin2_code":"3209.0",
    "gn:admin3_code":"320907.0",
    "gn:asciiname":"Karnieszewice",
    "gn:country_code":"PL",
    "gn:dem":40,
    "gn:feature_class":"P",
    "gn:feature_code":"PPL",
    "gn:name":"Karnieszewice",
    "gn:population":0,
    "gn:timezone":"Europe/Warsaw",
    "iso:country":"PL",
    "name:azb_x_preferred":[
        "\u06a9\u0627\u0631\u0646\u0642\u0634\u0648\u06cc\u062a\u0633\u0647"
    ],
    "name:ceb_x_preferred":[
        "Karnieszewice"
    ],
    "name:deu_x_preferred":[
        "Karnieszewice"
    ],
    "name:fas_x_preferred":[
        "\u06a9\u0627\u0631\u0646\u06af\u0634\u0648\u06cc\u062a\u0633\u0647"
    ],
    "name:nld_x_preferred":[
        "Karnieszewice"
    ],
    "name:pol_x_preferred":[
        "Karnieszewice"
    ],
    "name:ukr_x_preferred":[
        "\u041a\u0430\u0440\u043d\u0435\u0448\u0435\u0432\u0456\u0446\u0435"
    ],
    "name:und_x_variant":[
        "Karnkewitz"
    ],
    "name:vie_x_preferred":[
        "Karnieszewice"
    ],
    "wof:name":"Karnieszewice",
    "wof:placetype":"locality"
},
  "geometry": {"coordinates":[16.34937,54.25782],"type":"Point"}
}