{
  "type": "Feature",
  "properties": {
    "gn:admin1_code":"87.0",
    "gn:admin2_code":"3209.0",
    "gn:admin3_code":"320907.0",
    "gn:asciiname":"Karnieszewice",
    "gn:country_code":"PL",
    "gn:dem":40,
    "gn:feature_class":"P",
    "gn:feature_code":"PPL",
    "gn:name":"Karnieszewice",
    "gn:population":0,
    "gn:timezone":"Europe/Warsaw",
    "iso:country":"PL",
    "name:und_x_variant":[
        "Karnkewitz",
        "Karnieszewice"
    ],
    "wof:name":"Karnieszewice",
    "wof:placetype":"locality"
},
  "geometry": {"coordinates":[16.34937,54.25782],"type":"Point"}
}