{
  "type": "Feature",
  "properties": {
    "gn:admin1_code":"81.0",
    "gn:admin2_code":"2003.0",
    "gn:admin3_code":"200305.0",
    "gn:asciiname":"Kalnica",
    "gn:country_code":"PL",
    "gn:dem":133,
    "gn:feature_class":"P",
    "gn:feature_code":"PPL",
    "gn:name":"Kalnica",
    "gn:population":0,
    "gn:timezone":"Europe/Warsaw",
    "iso:country":"PL",
    "name:fra_x_preferred":[
        "Kalnica"
    ],
    "name:lit_x_preferred":[
        "Kalnica"
    ],
    "name:pol_x_preferred":[
        "Kalnica"
    ],
    "name:ukr_x_preferred":[
        "\u041a\u0430\u043b\u044c\u043d\u0438\u0446\u044f"
    ],
    "wof:name":"Kalnica",
    "wof:placetype":"locality"
},
  "geometry": {"coordinates":[22.91825,52.74276],"type":"Point"}
}