{
  "type": "Feature",
  "properties": {
    "gn:admin1_code":"78.0",
    "gn:admin2_code":"1433.0",
    "gn:admin3_code":"143309.0",
    "gn:asciiname":"Cierpieta",
    "gn:country_code":"PL",
    "gn:dem":171,
    "gn:feature_class":"P",
    "gn:feature_code":"PPL",
    "gn:name":"Cierpi\u0119ta",
    "gn:population":0,
    "gn:timezone":"Europe/Warsaw",
    "iso:country":"PL",
    "wof:name":"Cierpieta",
    "wof:placetype":"locality"
},
  "geometry": {"coordinates":[21.8458,52.27639],"type":"Point"}
}