{
  "type": "Feature",
  "properties": {
    "gn:admin1_code":"84.0",
    "gn:admin2_code":"2603.0",
    "gn:admin3_code":"260305.0",
    "gn:asciiname":"Boszczynek",
    "gn:country_code":"PL",
    "gn:dem":208,
    "gn:feature_class":"P",
    "gn:feature_code":"PPL",
    "gn:name":"Boszczynek",
    "gn:population":0,
    "gn:timezone":"Europe/Warsaw",
    "iso:country":"PL",
    "name:pol_x_preferred":[
        "Boszczynek"
    ],
    "name:ukr_x_preferred":[
        "\u0411\u043e\u0449\u0438\u043d\u0435\u043a"
    ],
    "wof:name":"Boszczynek",
    "wof:placetype":"locality"
},
  "geometry": {"coordinates":[20.41595,50.28199],"type":"Point"}
}