{
  "type": "Feature",
  "properties": {
    "gn:admin1_code":"87.0",
    "gn:admin2_code":"3216.0",
    "gn:admin3_code":"321604.0",
    "gn:asciiname":"Rzecino",
    "gn:country_code":"PL",
    "gn:dem":99,
    "gn:feature_class":"P",
    "gn:feature_code":"PPL",
    "gn:name":"Rzecino",
    "gn:population":0,
    "gn:timezone":"Europe/Warsaw",
    "iso:country":"PL",
    "name:ceb_x_preferred":[
        "Rzecino"
    ],
    "name:deu_x_preferred":[
        "Rzecino"
    ],
    "name:pol_x_preferred":[
        "Rzecino"
    ],
    "name:ukr_x_preferred":[
        "\u0416\u0435\u0446\u0438\u043d\u043e"
    ],
    "name:vie_x_preferred":[
        "Rzecino"
    ],
    "wof:name":"Rzecino",
    "wof:placetype":"locality"
},
  "geometry": {"coordinates":[15.99963,53.8427],"type":"Point"}
}