{
  "type": "Feature",
  "properties": {
    "gn:gn_country":"PL",
    "gn:gn_fcode":"PPLA3",
    "gn:gn_pop":2700,
    "gn:population":2700,
    "iso:country":"PL",
    "qs_pg:aaroncc":"PL",
    "qs_pg:gn_country":"PL",
    "qs_pg:gn_fcode":"PPLA3",
    "qs_pg:gn_pop":2700,
    "qs_pg:name":"Kamie\u0144",
    "qs_pg:name_adm0":"Polska",
    "qs_pg:name_adm1":"Podkarpackie",
    "qs_pg:photos":2,
    "qs_pg:photos_1k":1,
    "qs_pg:photos_9k":1,
    "qs_pg:photos_9r":1,
    "qs_pg:photos_all":2,
    "qs_pg:photos_sr":1,
    "qs_pg:pop_sr":4,
    "qs_pg:qs_pg_placetype":"localadmin",
    "qs_pg:qs_pg_placetype_gp":"LocalAdmin",
    "qs_pg:woe_adm0":23424923,
    "woe:adm0_id":23424923,
    "woe:name_adm0":"Polska",
    "woe:name_adm1":"Podkarpackie",
    "woe:placetype":"LocalAdmin",
    "wof:name":"Kamie\u0144",
    "wof:placetype":"localadmin",
    "wof:population":2700
},
  "geometry": {"coordinates":[22.13539,50.34064],"type":"Point"}
}