{
  "type": "Feature",
  "properties": {
    "gn:admin1_code":"75.0",
    "gn:admin2_code":"608.0",
    "gn:admin3_code":"60807.0",
    "gn:asciiname":"Lisow",
    "gn:country_code":"PL",
    "gn:dem":156,
    "gn:feature_class":"P",
    "gn:feature_code":"PPL",
    "gn:name":"Lis\u00f3w",
    "gn:population":0,
    "gn:timezone":"Europe/Warsaw",
    "iso:country":"PL",
    "name:und_x_variant":[
        "Lis\u00f3w"
    ],
    "wof:name":"Lisow",
    "wof:placetype":"locality"
},
  "geometry": {"coordinates":[22.60552,51.48798],"type":"Point"}
}