{
  "type": "Feature",
  "properties": {
    "gn:admin1_code":"80.0",
    "gn:admin2_code":"1812.0",
    "gn:admin3_code":"181202.0",
    "gn:asciiname":"Majdan Jarocinski",
    "gn:country_code":"PL",
    "gn:dem":183,
    "gn:feature_class":"P",
    "gn:feature_code":"PPL",
    "gn:name":"Majdan Jaroci\u0144ski",
    "gn:population":0,
    "gn:timezone":"Europe/Warsaw",
    "iso:country":"PL",
    "wof:name":"Majdan Jarocinski",
    "wof:placetype":"locality"
},
  "geometry": {"coordinates":[22.30022,50.5842],"type":"Point"}
}