{
  "type": "Feature",
  "properties": {
    "gn:admin1_code":"74.0",
    "gn:admin2_code":"1013.0",
    "gn:admin3_code":"101303.0",
    "gn:asciiname":"Niemglowy",
    "gn:country_code":"PL",
    "gn:dem":152,
    "gn:feature_class":"P",
    "gn:feature_code":"PPL",
    "gn:name":"Niemg\u0142owy",
    "gn:population":0,
    "gn:timezone":"Europe/Warsaw",
    "iso:country":"PL",
    "name:pol_x_preferred":[
        "Niemg\u0142owy"
    ],
    "name:ukr_x_preferred":[
        "\u041d\u0435\u043c\u0491\u043b\u043e\u0432\u0438"
    ],
    "wof:name":"Niemglowy",
    "wof:placetype":"locality"
},
  "geometry": {"coordinates":[20.38221,51.70235],"type":"Point"}
}