{
  "type": "Feature",
  "properties": {
    "gn:admin1_code":"85.0",
    "gn:admin2_code":"2802.0",
    "gn:admin3_code":"280202.0",
    "gn:asciiname":"Chlopki",
    "gn:cc2":"PL",
    "gn:country_code":"PL",
    "gn:dem":42,
    "gn:feature_class":"P",
    "gn:feature_code":"PPL",
    "gn:name":"Ch\u0142opki",
    "gn:population":0,
    "gn:timezone":"Europe/Warsaw",
    "iso:country":"PL",
    "name:und_x_variant":[
        "Klopchen",
        "Ch\u0142opki"
    ],
    "wof:name":"Chlopki",
    "wof:placetype":"locality"
},
  "geometry": {"coordinates":[19.88333,54.33333],"type":"Point"}
}