{
  "type": "Feature",
  "properties": {
    "gn:admin1_code":"75.0",
    "gn:admin2_code":"617.0",
    "gn:admin3_code":"61703.0",
    "gn:asciiname":"Gardzienice",
    "gn:country_code":"PL",
    "gn:dem":194,
    "gn:feature_class":"P",
    "gn:feature_code":"PPL",
    "gn:name":"Gardzienice",
    "gn:population":0,
    "gn:timezone":"Europe/Warsaw",
    "iso:country":"PL",
    "name:und_x_variant":[
        "Gardzienice Drugie",
        "Gardzienice"
    ],
    "wof:name":"Gardzienice",
    "wof:placetype":"locality"
},
  "geometry": {"coordinates":[22.85785,51.10796],"type":"Point"}
}