{
  "type": "Feature",
  "properties": {
    "gn:admin1_code":"75.0",
    "gn:admin2_code":"617.0",
    "gn:admin3_code":"61703.0",
    "gn:asciiname":"Gardzienice",
    "gn:country_code":"PL",
    "gn:dem":194,
    "gn:feature_class":"P",
    "gn:feature_code":"PPL",
    "gn:name":"Gardzienice",
    "gn:population":0,
    "gn:timezone":"Europe/Warsaw",
    "iso:country":"PL",
    "name:fra_x_preferred":[
        "Gardzienice Drugie"
    ],
    "name:pol_x_preferred":[
        "Gardzienice Drugie"
    ],
    "name:ukr_x_preferred":[
        "\u0490\u0430\u0440\u0434\u0437\u0435\u043d\u0456\u0446\u0435-\u0414\u0440\u0443\u0433\u0456"
    ],
    "name:und_x_variant":[
        "Gardzienice"
    ],
    "wof:name":"Gardzienice",
    "wof:placetype":"locality"
},
  "geometry": {"coordinates":[22.85785,51.10796],"type":"Point"}
}