{
  "type": "Feature",
  "properties": {
    "gn:admin1_code":"85.0",
    "gn:admin2_code":"2817.0",
    "gn:admin3_code":"281708.0",
    "gn:asciiname":"Wesolowko",
    "gn:country_code":"PL",
    "gn:dem":128,
    "gn:feature_class":"P",
    "gn:feature_code":"PPL",
    "gn:name":"Weso\u0142\u00f3wko",
    "gn:population":0,
    "gn:timezone":"Europe/Warsaw",
    "iso:country":"PL",
    "name:pol_x_preferred":[
        "Weso\u0142\u00f3wko"
    ],
    "name:ukr_x_preferred":[
        "\u0412\u0435\u0441\u043e\u043b\u0443\u0432\u043a\u043e"
    ],
    "name:und_x_variant":[
        "Fr\u00f6hlichswalde"
    ],
    "wof:name":"Wesolowko",
    "wof:placetype":"locality"
},
  "geometry": {"coordinates":[20.85899,53.43247],"type":"Point"}
}