{
  "type": "Feature",
  "properties": {
    "gn:admin1_code":"75.0",
    "gn:admin2_code":"618.0",
    "gn:admin3_code":"61811.0",
    "gn:asciiname":"Klekacze",
    "gn:country_code":"PL",
    "gn:dem":239,
    "gn:feature_class":"P",
    "gn:feature_code":"PPL",
    "gn:name":"Klekacze",
    "gn:population":0,
    "gn:timezone":"Europe/Warsaw",
    "iso:country":"PL",
    "name:fra_x_preferred":[
        "Klekacz"
    ],
    "name:pol_x_preferred":[
        "Klekacz"
    ],
    "name:ukr_x_preferred":[
        "\u041a\u043b\u0435\u043a\u0430\u0447"
    ],
    "name:und_x_variant":[
        "Kolonia Klekacz",
        "Klekacze"
    ],
    "wof:name":"Klekacze",
    "wof:placetype":"locality"
},
  "geometry": {"coordinates":[23.54713,50.46889],"type":"Point"}
}