{
  "type": "Feature",
  "properties": {
    "gn:admin1_code":"78.0",
    "gn:admin2_code":"1426.0",
    "gn:admin3_code":"142605.0",
    "gn:asciiname":"Krzymosze",
    "gn:country_code":"PL",
    "gn:dem":157,
    "gn:feature_class":"P",
    "gn:feature_code":"PPL",
    "gn:name":"Krzymosze",
    "gn:population":0,
    "gn:timezone":"Europe/Warsaw",
    "iso:country":"PL",
    "name:azb_x_preferred":[
        "\u06a9\u0698\u0645\u0648\u0634\u0647"
    ],
    "name:ceb_x_preferred":[
        "Krzymosze"
    ],
    "name:fas_x_preferred":[
        "\u06a9\u0698\u0645\u0648\u0634\u0647"
    ],
    "name:fra_x_preferred":[
        "Krzymosze"
    ],
    "name:lit_x_preferred":[
        "K\u017eimo\u0161\u0117"
    ],
    "name:pol_x_preferred":[
        "Krzymosze"
    ],
    "name:ukr_x_preferred":[
        "\u041a\u0448\u0438\u043c\u043e\u0448\u0435"
    ],
    "wof:name":"Krzymosze",
    "wof:placetype":"locality"
},
  "geometry": {"coordinates":[22.46241,52.1613],"type":"Point"}
}