{
  "type": "Feature",
  "properties": {
    "gn:gn_country":"PL",
    "gn:gn_fcode":"PPL",
    "gn:gn_pop":803,
    "gn:population":803,
    "iso:country":"PL",
    "name:deu_x_preferred":[
        "Podsarnie"
    ],
    "name:eng_x_preferred":[
        "Podsarnie"
    ],
    "name:epo_x_preferred":[
        "Podsarnie"
    ],
    "name:fas_x_preferred":[
        "\u067e\u0648\u062f\u0633\u0627\u0631\u0646\u06af\u0647"
    ],
    "name:fra_x_preferred":[
        "Podsarnie"
    ],
    "name:hun_x_preferred":[
        "Sz\u00e1rnya"
    ],
    "name:nld_x_preferred":[
        "Podsarnie"
    ],
    "name:pol_x_preferred":[
        "Podsarnie"
    ],
    "name:slk_x_preferred":[
        "S\u0155nie"
    ],
    "name:unk_x_variant":[
        "Podsarnia"
    ],
    "qs_pg:aaroncc":"PL",
    "qs_pg:gn_country":"PL",
    "qs_pg:gn_fcode":"PPL",
    "qs_pg:gn_pop":803,
    "qs_pg:name":"Podsarnie",
    "qs_pg:name_adm0":"Polska",
    "qs_pg:name_adm1":"Ma\u0142opolskie",
    "qs_pg:photos_9r":0,
    "qs_pg:photos_sr":0,
    "qs_pg:pop_sr":2,
    "qs_pg:qs_pg_placetype":"locality",
    "qs_pg:qs_pg_placetype_gp":"Town",
    "qs_pg:woe_adm0":23424923,
    "woe:adm0_id":23424923,
    "woe:name_adm0":"Polska",
    "woe:name_adm1":"Ma\u0142opolskie",
    "woe:placetype":"Town",
    "wof:name":"Podsarnie",
    "wof:placetype":"locality",
    "wof:population":803
},
  "geometry": {"coordinates":[19.79024,49.5525],"type":"Point"}
}