{
  "type": "Feature",
  "properties": {
    "gn:admin1_code":"85.0",
    "gn:admin2_code":"2814.0",
    "gn:admin3_code":"281406.0",
    "gn:asciiname":"Kramarzewo",
    "gn:country_code":"PL",
    "gn:dem":160,
    "gn:feature_class":"P",
    "gn:feature_code":"PPL",
    "gn:name":"Kramarzewo",
    "gn:population":0,
    "gn:timezone":"Europe/Warsaw",
    "iso:country":"PL",
    "name:und_x_variant":[
        "Kr\u00e4mmersdorf",
        "Kr\u00e4mersdorf",
        "Kramarzewo"
    ],
    "wof:name":"Kramarzewo",
    "wof:placetype":"locality"
},
  "geometry": {"coordinates":[20.79003,54.01407],"type":"Point"}
}