{
  "type": "Feature",
  "properties": {
    "gn:admin1_code":"75.0",
    "gn:admin2_code":"609.0",
    "gn:admin3_code":"60901.0",
    "gn:asciiname":"Wierzchowiska Gorne",
    "gn:country_code":"PL",
    "gn:dem":231,
    "gn:feature_class":"P",
    "gn:feature_code":"PPL",
    "gn:name":"Wierzchowiska G\u00f3rne",
    "gn:population":0,
    "gn:timezone":"Europe/Warsaw",
    "iso:country":"PL",
    "name:fra_x_preferred":[
        "Wierzchowiska G\u00f3rne"
    ],
    "name:pol_x_preferred":[
        "Wierzchowiska G\u00f3rne"
    ],
    "name:ukr_x_preferred":[
        "\u0412\u0435\u0436\u0445\u043e\u0432\u0438\u0441\u044c\u043a\u0430-\u0490\u0443\u0440\u043d\u0435"
    ],
    "wof:name":"Wierzchowiska Gorne",
    "wof:placetype":"locality"
},
  "geometry": {"coordinates":[22.29003,51.12629],"type":"Point"}
}