{
  "type": "Feature",
  "properties": {
    "gn:admin1_code":"85.0",
    "gn:admin2_code":"2817.0",
    "gn:admin3_code":"281704.0",
    "gn:asciiname":"Grom",
    "gn:cc2":"PL",
    "gn:country_code":"PL",
    "gn:dem":152,
    "gn:feature_class":"P",
    "gn:feature_code":"PPL",
    "gn:name":"Grom",
    "gn:population":0,
    "gn:timezone":"Europe/Warsaw",
    "iso:country":"PL",
    "name:eng_x_preferred":[
        "Grom"
    ],
    "name:pol_x_preferred":[
        "Grom"
    ],
    "name:rus_x_preferred":[
        "\u0413\u0440\u043e\u043c"
    ],
    "name:ukr_x_preferred":[
        "\u0490\u0440\u043e\u043c"
    ],
    "name:und_x_variant":[
        "Grammen"
    ],
    "wof:name":"Grom",
    "wof:placetype":"locality"
},
  "geometry": {"coordinates":[20.85,53.61666999999999],"type":"Point"}
}