{
  "type": "Feature",
  "properties": {
    "gn:gn_country":"PL",
    "gn:gn_fcode":"PPLA3",
    "gn:gn_pop":4769,
    "gn:population":4769,
    "iso:country":"PL",
    "name:azb_x_preferred":[
        "\u0686\u0627\u0631\u0646 \u0628\u0648\u0631"
    ],
    "name:ceb_x_preferred":[
        "Czarny B\u00f3r"
    ],
    "name:deu_x_historical":[
        "Schwarzwaldau"
    ],
    "name:deu_x_preferred":[
        "Schwarzwaldau"
    ],
    "name:deu_x_variant":[
        "Czarny B\u00f3r"
    ],
    "name:fas_x_preferred":[
        "\u0686\u0627\u0631\u0646 \u0628\u0648\u0631"
    ],
    "name:nld_x_preferred":[
        "Czarny B\u00f3r"
    ],
    "name:pol_x_preferred":[
        "Czarny B\u00f3r"
    ],
    "name:ukr_x_preferred":[
        "\u0427\u0430\u0440\u043d\u0438-\u0411\u0443\u0440"
    ],
    "qs_pg:aaroncc":"PL",
    "qs_pg:gn_country":"PL",
    "qs_pg:gn_fcode":"PPLA3",
    "qs_pg:gn_pop":4769,
    "qs_pg:name":"Czarny B\u00f3r",
    "qs_pg:name_adm0":"Polska",
    "qs_pg:name_adm1":"Dolnosl\u0105skie",
    "qs_pg:photos":10,
    "qs_pg:photos_1k":2,
    "qs_pg:photos_9k":1,
    "qs_pg:photos_9r":1,
    "qs_pg:photos_all":10,
    "qs_pg:photos_sr":1,
    "qs_pg:pop_sr":4,
    "qs_pg:qs_pg_placetype":"localadmin",
    "qs_pg:qs_pg_placetype_gp":"LocalAdmin",
    "qs_pg:woe_adm0":23424923,
    "woe:adm0_id":23424923,
    "woe:name_adm0":"Polska",
    "woe:name_adm1":"Dolnosl\u0105skie",
    "woe:placetype":"LocalAdmin",
    "wof:name":"Czarny B\u00f3r",
    "wof:placetype":"localadmin",
    "wof:population":4769
},
  "geometry": {"coordinates":[16.1305,50.77083],"type":"Point"}
}