{
  "type": "Feature",
  "properties": {
    "gn:admin1_code":"86.0",
    "gn:admin2_code":"3017.0",
    "gn:admin3_code":"301704.0",
    "gn:asciiname":"Greblow",
    "gn:country_code":"PL",
    "gn:dem":138,
    "gn:feature_class":"P",
    "gn:feature_code":"PPL",
    "gn:name":"Gr\u0119bl\u00f3w",
    "gn:population":0,
    "gn:timezone":"Europe/Warsaw",
    "iso:country":"PL",
    "wof:name":"Greblow",
    "wof:placetype":"locality"
},
  "geometry": {"coordinates":[17.80662000000001,51.69136],"type":"Point"}
}