{
  "type": "Feature",
  "properties": {
    "gn:admin1_code":"74.0",
    "gn:admin2_code":"1004.0",
    "gn:admin3_code":"100402.0",
    "gn:asciiname":"Upale",
    "gn:country_code":"PL",
    "gn:dem":115,
    "gn:feature_class":"P",
    "gn:feature_code":"PPL",
    "gn:name":"Upale",
    "gn:population":0,
    "gn:timezone":"Europe/Warsaw",
    "iso:country":"PL",
    "name:fra_x_preferred":[
        "Upale"
    ],
    "name:pol_x_preferred":[
        "Upale"
    ],
    "name:ukr_x_preferred":[
        "\u0423\u043f\u0430\u043b\u0435"
    ],
    "wof:name":"Upale",
    "wof:placetype":"locality"
},
  "geometry": {"coordinates":[19.19871,52.10633],"type":"Point"}
}