{
  "type": "Feature",
  "properties": {
    "gn:admin1_code":"78.0",
    "gn:admin2_code":"1465.0",
    "gn:admin3_code":"146501.0",
    "gn:admin4_code":"146503_8",
    "gn:asciiname":"Dabrowka Grzybowska",
    "gn:country_code":"PL",
    "gn:dem":80,
    "gn:feature_class":"P",
    "gn:feature_code":"PPL",
    "gn:name":"D\u0105br\u00f3wka Grzybowska",
    "gn:population":0,
    "gn:timezone":"Europe/Warsaw",
    "iso:country":"PL",
    "wof:name":"Dabrowka Grzybowska",
    "wof:placetype":"neighbourhood"
},
  "geometry": {"coordinates":[20.95,52.35],"type":"Point"}
}