{
  "type": "Feature",
  "properties": {
    "gn:admin1_code":"85.0",
    "gn:admin2_code":"2812.0",
    "gn:admin3_code":"281205.0",
    "gn:asciiname":"Nowy Dwor",
    "gn:country_code":"PL",
    "gn:dem":109,
    "gn:feature_class":"P",
    "gn:feature_code":"PPL",
    "gn:name":"Nowy Dw\u00f3r",
    "gn:population":0,
    "gn:timezone":"Europe/Warsaw",
    "iso:country":"PL",
    "wof:name":"Nowy Dwor",
    "wof:placetype":"locality"
},
  "geometry": {"coordinates":[19.55611,53.47233000000001],"type":"Point"}
}