{
  "type": "Feature",
  "properties": {
    "gn:admin1_code":"81.0",
    "gn:admin2_code":"2011.0",
    "gn:admin3_code":"201102.0",
    "gn:asciiname":"Jasionowa Dolina",
    "gn:country_code":"PL",
    "gn:dem":147,
    "gn:feature_class":"P",
    "gn:feature_code":"PPL",
    "gn:name":"Jasionowa Dolina",
    "gn:population":0,
    "gn:timezone":"Europe/Warsaw",
    "iso:country":"PL",
    "name:azb_x_preferred":[
        "\u06cc\u0627\u0634\u0648\u0646\u0648\u0648\u0627 \u062f\u0648\u0644\u06cc\u0646\u0627"
    ],
    "name:fas_x_preferred":[
        "\u06cc\u0627\u0634\u0648\u0646\u0648\u0648\u0627 \u062f\u0648\u0644\u06cc\u0646\u0627"
    ],
    "name:fra_x_preferred":[
        "Jasionowa Dolina"
    ],
    "name:lit_x_preferred":[
        "Jasionova Dolina"
    ],
    "name:pol_x_preferred":[
        "Jasionowa Dolina"
    ],
    "name:ukr_x_preferred":[
        "\u042f\u0441\u044c\u043e\u043d\u043e\u0432\u0430-\u0414\u043e\u043b\u0456\u043d\u0430"
    ],
    "name:urd_x_preferred":[
        "\u062c\u0633\u0648\u0646\u0648\u0648\u0627 \u0688\u0648\u0644\u0646\u0627"
    ],
    "wof:name":"Jasionowa Dolina",
    "wof:placetype":"locality"
},
  "geometry": {"coordinates":[23.19263,53.47235],"type":"Point"}
}