{
  "type": "Feature",
  "properties": {
    "iso:country":"PL",
    "name:eng_x_preferred":[
        "Osiedle Powstancow Slaskich"
    ],
    "name:pol_x_preferred":[
        "Osiedle Powsta\u0144c\u00f3w \u015al\u0105skich"
    ],
    "wof:name":"Osiedle Powstancow Slaskich",
    "wof:placetype":"neighbourhood"
},
  "geometry": {"coordinates":[16.88974039007446,52.3582162097701],"type":"Point"}
}