{
  "type": "Feature",
  "properties": {
    "gn:admin1_code":"74.0",
    "gn:admin2_code":"1010.0",
    "gn:admin3_code":"101009.0",
    "gn:asciiname":"Biala",
    "gn:country_code":"PL",
    "gn:dem":197,
    "gn:feature_class":"P",
    "gn:feature_code":"PPL",
    "gn:name":"Bia\u0142a",
    "gn:population":0,
    "gn:timezone":"Europe/Warsaw",
    "iso:country":"PL",
    "wof:name":"Biala",
    "wof:placetype":"locality"
},
  "geometry": {"coordinates":[19.87113,51.29988],"type":"Point"}
}