{
  "type": "Feature",
  "properties": {
    "gn:admin1_code":"72.0",
    "gn:admin2_code":"221.0",
    "gn:admin3_code":"22106.0",
    "gn:asciiname":"Kaminoka",
    "gn:country_code":"PL",
    "gn:dem":634,
    "gn:feature_class":"P",
    "gn:feature_code":"PPL",
    "gn:name":"Kaminoka",
    "gn:population":0,
    "gn:timezone":"Europe/Warsaw",
    "iso:country":"PL",
    "wof:name":"Kaminoka",
    "wof:placetype":"locality"
},
  "geometry": {"coordinates":[16.28347,50.71446],"type":"Point"}
}