{
  "type": "Feature",
  "properties": {
    "gn:admin1_code":"78.0",
    "gn:admin2_code":"1417.0",
    "gn:admin3_code":"141708.0",
    "gn:asciiname":"Peclin",
    "gn:country_code":"PL",
    "gn:dem":114,
    "gn:feature_class":"P",
    "gn:feature_code":"PPL",
    "gn:name":"P\u0119clin",
    "gn:population":0,
    "gn:timezone":"Europe/Warsaw",
    "iso:country":"PL",
    "name:fra_x_preferred":[
        "P\u0119clin"
    ],
    "name:pol_x_preferred":[
        "P\u0119clin"
    ],
    "name:szl_x_preferred":[
        "Pynclin"
    ],
    "name:ukr_x_preferred":[
        "\u041f\u0435\u043d\u0446\u043b\u0456\u043d"
    ],
    "wof:name":"Peclin",
    "wof:placetype":"locality"
},
  "geometry": {"coordinates":[21.3533,52.16351],"type":"Point"}
}