{
  "type": "Feature",
  "properties": {
    "gn:admin1_code":"83.0",
    "gn:admin2_code":"2415.0",
    "gn:admin3_code":"241505.0",
    "gn:asciiname":"Podbucze",
    "gn:country_code":"PL",
    "gn:dem":217,
    "gn:feature_class":"P",
    "gn:feature_code":"PPL",
    "gn:name":"Podbucze",
    "gn:population":0,
    "gn:timezone":"Europe/Warsaw",
    "iso:country":"PL",
    "name:ceb_x_preferred":[
        "Podbucze"
    ],
    "name:pol_x_preferred":[
        "Podbucze"
    ],
    "name:ukr_x_preferred":[
        "\u041f\u043e\u0434\u0431\u0443\u0447\u0435"
    ],
    "wof:name":"Podbucze",
    "wof:placetype":"locality"
},
  "geometry": {"coordinates":[18.46499,49.95109],"type":"Point"}
}