{
  "type": "Feature",
  "properties": {
    "gn:admin1_code":"86.0",
    "gn:admin2_code":"3001.0",
    "gn:admin3_code":"300102.0",
    "gn:asciiname":"Ostrowki",
    "gn:country_code":"PL",
    "gn:dem":92,
    "gn:feature_class":"P",
    "gn:feature_code":"PPL",
    "gn:name":"Ostr\u00f3wki",
    "gn:population":0,
    "gn:timezone":"Europe/Warsaw",
    "iso:country":"PL",
    "name:fra_x_preferred":[
        "Ostr\u00f3wki"
    ],
    "name:pol_x_preferred":[
        "Ostr\u00f3wki"
    ],
    "name:ukr_x_preferred":[
        "\u041e\u0441\u0442\u0440\u0443\u0432\u043a\u0456"
    ],
    "wof:name":"Ostrowki",
    "wof:placetype":"locality"
},
  "geometry": {"coordinates":[16.9241,52.9178],"type":"Point"}
}