{
  "type": "Feature",
  "properties": {
    "gn:admin1_code":"83.0",
    "gn:admin2_code":"2409.0",
    "gn:admin3_code":"240905.0",
    "gn:asciiname":"Zaborze",
    "gn:country_code":"PL",
    "gn:dem":336,
    "gn:feature_class":"P",
    "gn:feature_code":"PPL",
    "gn:name":"Zaborze",
    "gn:population":154,
    "gn:timezone":"Europe/Warsaw",
    "iso:country":"PL",
    "name:ceb_x_preferred":[
        "Zaborze"
    ],
    "name:pol_x_preferred":[
        "Zaborze"
    ],
    "name:ukr_x_preferred":[
        "\u0417\u0430\u0431\u043e\u0436\u0435"
    ],
    "name:urd_x_preferred":[
        "\u0632\u0628\u0648\u0631\u0632\u06d2"
    ],
    "wof:name":"Zaborze",
    "wof:placetype":"locality",
    "wof:population":154
},
  "geometry": {"coordinates":[19.32032,50.67683],"type":"Point"}
}