{
  "type": "Feature",
  "properties": {
    "gn:admin1_code":"86.0",
    "gn:admin2_code":"3010.0",
    "gn:admin3_code":"301009.0",
    "gn:asciiname":"Pilich",
    "gn:country_code":"PL",
    "gn:dem":96,
    "gn:feature_class":"P",
    "gn:feature_code":"PPL",
    "gn:name":"Pilich",
    "gn:population":0,
    "gn:timezone":"Europe/Warsaw",
    "iso:country":"PL",
    "name:pol_x_preferred":[
        "Pilich"
    ],
    "name:ukr_x_preferred":[
        "\u041f\u0456\u043b\u0456\u0445"
    ],
    "wof:name":"Pilich",
    "wof:placetype":"locality"
},
  "geometry": {"coordinates":[18.29824,52.49799],"type":"Point"}
}