{
  "type": "Feature",
  "properties": {
    "gn:admin1_code":"75.0",
    "gn:admin2_code":"612.0",
    "gn:admin3_code":"61205.0",
    "gn:asciiname":"Ludwikow",
    "gn:country_code":"PL",
    "gn:dem":216,
    "gn:feature_class":"P",
    "gn:feature_code":"PPL",
    "gn:name":"Ludwik\u00f3w",
    "gn:population":0,
    "gn:timezone":"Europe/Warsaw",
    "iso:country":"PL",
    "name:und_x_variant":[
        "Ludwik\u00f3w"
    ],
    "wof:name":"Ludwikow",
    "wof:placetype":"locality"
},
  "geometry": {"coordinates":[22.03552,51.07943],"type":"Point"}
}