{
  "type": "Feature",
  "properties": {
    "gn:admin1_code":"78.0",
    "gn:admin2_code":"1463.0",
    "gn:admin3_code":"146301.0",
    "gn:asciiname":"Stare Miasto",
    "gn:country_code":"PL",
    "gn:dem":156,
    "gn:feature_class":"P",
    "gn:feature_code":"PPL",
    "gn:name":"Stare Miasto",
    "gn:population":0,
    "gn:timezone":"Europe/Warsaw",
    "iso:country":"PL",
    "name:ceb_x_preferred":[
        "Stare Miasto"
    ],
    "name:deu_x_preferred":[
        "Stare Miasto"
    ],
    "name:fra_x_preferred":[
        "Stare Miasto"
    ],
    "name:ita_x_preferred":[
        "Stare Miasto"
    ],
    "name:kor_x_preferred":[
        "\uc2a4\ud0c0\ub808\ubbf8\uc544\uc2a4\ud1a0"
    ],
    "name:nld_x_preferred":[
        "Stare Miasto"
    ],
    "name:nor_x_preferred":[
        "Stare Miasto"
    ],
    "name:pol_x_preferred":[
        "Stare Miasto"
    ],
    "name:slk_x_preferred":[
        "Stare Miasto"
    ],
    "name:swe_x_preferred":[
        "Stare Miasto"
    ],
    "name:ukr_x_preferred":[
        "\u0421\u0442\u0430\u0440\u0435 \u041c\u044f\u0441\u0442\u043e"
    ],
    "wof:name":"Stare Miasto",
    "wof:placetype":"locality"
},
  "geometry": {"coordinates":[21.13624,51.40126],"type":"Point"}
}