{
  "type": "Feature",
  "properties": {
    "gn:gn_country":"PL",
    "gn:gn_fcode":"PPL",
    "gn:gn_pop":0,
    "iso:country":"PL",
    "name:ast_x_preferred":[
        "Stobno"
    ],
    "name:azb_x_preferred":[
        "\u0633\u062a\u0648\u0628\u0646\u0648"
    ],
    "name:ceb_x_preferred":[
        "Stobno"
    ],
    "name:deu_x_preferred":[
        "Stobno"
    ],
    "name:eng_x_preferred":[
        "Stobno"
    ],
    "name:fas_x_preferred":[
        "\u0633\u062a\u0648\u0628\u0646\u0648"
    ],
    "name:fra_x_preferred":[
        "Stobno"
    ],
    "name:nld_x_preferred":[
        "Stobno"
    ],
    "name:pol_x_preferred":[
        "Stobno"
    ],
    "name:ukr_x_preferred":[
        "\u0421\u0442\u043e\u0431\u043d\u043e"
    ],
    "name:unk_x_variant":[
        "St\u00f6ven"
    ],
    "name:vie_x_preferred":[
        "Stobno"
    ],
    "qs_pg:aaroncc":"PL",
    "qs_pg:gn_country":"PL",
    "qs_pg:gn_fcode":"PPL",
    "qs_pg:gn_pop":0,
    "qs_pg:name":"Stobno",
    "qs_pg:name_adm0":"Polska",
    "qs_pg:name_adm1":"Zachodniopomorskie",
    "qs_pg:photos":9,
    "qs_pg:photos_1k":2,
    "qs_pg:photos_9k":1,
    "qs_pg:photos_9r":1,
    "qs_pg:photos_all":9,
    "qs_pg:photos_sr":1,
    "qs_pg:pop_sr":0,
    "qs_pg:qs_pg_placetype":"locality",
    "qs_pg:qs_pg_placetype_gp":"Town",
    "qs_pg:woe_adm0":23424923,
    "woe:adm0_id":23424923,
    "woe:name_adm0":"Polska",
    "woe:name_adm1":"Zachodniopomorskie",
    "woe:placetype":"Town",
    "wof:name":"Stobno",
    "wof:placetype":"locality"
},
  "geometry": {"coordinates":[14.42994,53.41337],"type":"Point"}
}