{
  "type": "Feature",
  "properties": {
    "gn:admin1_code":"78.0",
    "gn:admin2_code":"1409.0",
    "gn:admin3_code":"140903.0",
    "gn:asciiname":"Gruszczyn",
    "gn:country_code":"PL",
    "gn:dem":173,
    "gn:feature_class":"P",
    "gn:feature_code":"PPL",
    "gn:name":"Gruszczyn",
    "gn:population":0,
    "gn:timezone":"Europe/Warsaw",
    "iso:country":"PL",
    "name:fra_x_preferred":[
        "Gruszczyn"
    ],
    "name:pol_x_preferred":[
        "Gruszczyn"
    ],
    "name:ukr_x_preferred":[
        "\u0490\u0440\u0443\u0449\u0438\u043d"
    ],
    "wof:name":"Gruszczyn",
    "wof:placetype":"locality"
},
  "geometry": {"coordinates":[21.62418,51.13095],"type":"Point"}
}