{
  "type": "Feature",
  "properties": {
    "gn:admin1_code":"83.0",
    "gn:admin2_code":"2477.0",
    "gn:admin3_code":"247701.0",
    "gn:asciiname":"Makotowiec",
    "gn:country_code":"PL",
    "gn:dem":268,
    "gn:feature_class":"P",
    "gn:feature_code":"PPL",
    "gn:name":"Makotowiec",
    "gn:population":0,
    "gn:timezone":"Europe/Warsaw",
    "iso:country":"PL",
    "wof:name":"Makotowiec",
    "wof:placetype":"neighbourhood"
},
  "geometry": {"coordinates":[18.96825,50.14589],"type":"Point"}
}