{
  "type": "Feature",
  "properties": {
    "gn:admin1_code":"85.0",
    "gn:admin2_code":"2808.0",
    "gn:admin3_code":"280802.0",
    "gn:asciiname":"Borszyny",
    "gn:cc2":"PL",
    "gn:country_code":"PL",
    "gn:dem":69,
    "gn:feature_class":"P",
    "gn:feature_code":"PPL",
    "gn:name":"Borszyny",
    "gn:population":0,
    "gn:timezone":"Europe/Warsaw",
    "iso:country":"PL",
    "name:und_x_variant":[
        "Borschenen",
        "Borszyny"
    ],
    "wof:name":"Borszyny",
    "wof:placetype":"locality"
},
  "geometry": {"coordinates":[21.31667,54.16667],"type":"Point"}
}