{
  "type": "Feature",
  "properties": {
    "gn:admin1_code":"82.0",
    "gn:admin2_code":"2207.0",
    "gn:admin3_code":"220704.0",
    "gn:asciiname":"Gonty",
    "gn:country_code":"PL",
    "gn:dem":94,
    "gn:feature_class":"P",
    "gn:feature_code":"PPL",
    "gn:name":"Gonty",
    "gn:population":0,
    "gn:timezone":"Europe/Warsaw",
    "iso:country":"PL",
    "name:und_x_variant":[
        "Gunthen",
        "Gonty"
    ],
    "wof:name":"Gonty",
    "wof:placetype":"locality"
},
  "geometry": {"coordinates":[19.17771,53.78425],"type":"Point"}
}