{
  "type": "Feature",
  "properties": {
    "gn:admin1_code":"73.0",
    "gn:admin2_code":"408.0",
    "gn:admin3_code":"40804.0",
    "gn:asciiname":"Szpiegowo",
    "gn:country_code":"PL",
    "gn:dem":101,
    "gn:feature_class":"P",
    "gn:feature_code":"PPL",
    "gn:name":"Szpiegowo",
    "gn:population":0,
    "gn:timezone":"Europe/Warsaw",
    "iso:country":"PL",
    "name:pol_x_preferred":[
        "Szpiegowo"
    ],
    "name:ukr_x_preferred":[
        "\u0428\u043f\u0435\u0491\u043e\u0432\u043e"
    ],
    "wof:name":"Szpiegowo",
    "wof:placetype":"locality"
},
  "geometry": {"coordinates":[19.23446,52.69188000000001],"type":"Point"}
}