{
  "type": "Feature",
  "properties": {
    "gn:admin1_code":"86.0",
    "gn:admin2_code":"3015.0",
    "gn:admin3_code":"301503.0",
    "gn:asciiname":"Szklarka Trzcielska",
    "gn:country_code":"PL",
    "gn:dem":66,
    "gn:feature_class":"P",
    "gn:feature_code":"PPL",
    "gn:name":"Szklarka Trzcielska",
    "gn:population":0,
    "gn:timezone":"Europe/Warsaw",
    "iso:country":"PL",
    "name:fra_x_preferred":[
        "Szklarka Trzcielska"
    ],
    "name:pol_x_preferred":[
        "Szklarka Trzcielska"
    ],
    "name:ukr_x_preferred":[
        "\u0428\u043a\u043b\u044f\u0440\u043a\u0430-\u0422\u0448\u0446\u0435\u043b\u044c\u0441\u044c\u043a\u0430"
    ],
    "wof:name":"Szklarka Trzcielska",
    "wof:placetype":"locality"
},
  "geometry": {"coordinates":[15.9287,52.3924],"type":"Point"}
}