{
  "type": "Feature",
  "properties": {
    "gn:admin1_code":"86.0",
    "gn:admin2_code":"3003.0",
    "gn:admin3_code":"300301.0",
    "gn:asciiname":"Skiereszewko",
    "gn:country_code":"PL",
    "gn:dem":117,
    "gn:feature_class":"P",
    "gn:feature_code":"PPL",
    "gn:name":"Skiereszewko",
    "gn:population":0,
    "gn:timezone":"Europe/Warsaw",
    "iso:country":"PL",
    "name:und_x_variant":[
        "Skiereszewo",
        "Skiereszewko"
    ],
    "wof:name":"Skiereszewko",
    "wof:placetype":"neighbourhood"
},
  "geometry": {"coordinates":[17.5519,52.53029],"type":"Point"}
}