{
  "type": "Feature",
  "properties": {
    "gn:admin1_code":"80.0",
    "gn:admin2_code":"1820.0",
    "gn:admin3_code":"182001.0",
    "gn:asciiname":"Koniecpol",
    "gn:country_code":"PL",
    "gn:dem":157,
    "gn:feature_class":"P",
    "gn:feature_code":"PPL",
    "gn:name":"Koniecpol",
    "gn:population":0,
    "gn:timezone":"Europe/Warsaw",
    "iso:country":"PL",
    "wof:name":"Koniecpol",
    "wof:placetype":"locality"
},
  "geometry": {"coordinates":[21.6438,50.45381],"type":"Point"}
}