{
  "type": "Feature",
  "properties": {
    "gn:admin1_code":"80.0",
    "gn:admin2_code":"1820.0",
    "gn:admin3_code":"182001.0",
    "gn:asciiname":"Koniecpol",
    "gn:country_code":"PL",
    "gn:dem":157,
    "gn:feature_class":"P",
    "gn:feature_code":"PPL",
    "gn:name":"Koniecpol",
    "gn:population":0,
    "gn:timezone":"Europe/Warsaw",
    "iso:country":"PL",
    "name:bul_x_preferred":[
        "\u041a\u043e\u043d\u0435\u0446\u043f\u043e\u043b"
    ],
    "name:deu_x_preferred":[
        "Koniecpol"
    ],
    "name:epo_x_preferred":[
        "Koniecpol"
    ],
    "name:fra_x_preferred":[
        "Koniecpol"
    ],
    "name:heb_x_preferred":[
        "\u05e7\u05d5\u05e0\u05d9\u05d9\u05e6\u05e4\u05d5\u05dc"
    ],
    "name:jav_x_preferred":[
        "Koniecpol"
    ],
    "name:lav_x_preferred":[
        "Ko\u0146ecpole"
    ],
    "name:msa_x_preferred":[
        "Koniecpol"
    ],
    "name:nld_x_preferred":[
        "Koniecpol"
    ],
    "name:pol_x_preferred":[
        "Koniecpol"
    ],
    "name:por_x_preferred":[
        "Koniecpol"
    ],
    "name:ron_x_preferred":[
        "Koniecpol"
    ],
    "name:rus_x_preferred":[
        "\u041a\u043e\u043d\u0435\u0446\u043f\u043e\u043b\u044c"
    ],
    "name:slk_x_preferred":[
        "Koniecpol"
    ],
    "name:srp_x_preferred":[
        "\u041a\u043e\u045a\u0435\u0446\u043f\u043e\u043b"
    ],
    "name:ukr_x_preferred":[
        "\u041a\u043e\u043d\u0435\u0446\u043f\u043e\u043b\u044c"
    ],
    "name:vie_x_preferred":[
        "Koniecpol"
    ],
    "name:zho_x_preferred":[
        "\u79d1\u6d85\u8328\u6ce2\u5c14"
    ],
    "wof:name":"Koniecpol",
    "wof:placetype":"locality"
},
  "geometry": {"coordinates":[21.6438,50.45381],"type":"Point"}
}