{
  "type": "Feature",
  "properties": {
    "gn:admin1_code":"79.0",
    "gn:admin2_code":"1611.0",
    "gn:admin3_code":"161104.0",
    "gn:asciiname":"Lichynia",
    "gn:cc2":"PL",
    "gn:country_code":"PL",
    "gn:dem":237,
    "gn:feature_class":"P",
    "gn:feature_code":"PPL",
    "gn:name":"Lichynia",
    "gn:population":0,
    "gn:timezone":"Europe/Warsaw",
    "iso:country":"PL",
    "name:und_x_variant":[
        "Lichtenforst",
        "Lichinia",
        "Lichynia"
    ],
    "wof:name":"Lichynia",
    "wof:placetype":"locality"
},
  "geometry": {"coordinates":[18.23318,50.42383],"type":"Point"}
}