{
  "type": "Feature",
  "properties": {
    "gn:admin1_code":"79.0",
    "gn:admin2_code":"1611.0",
    "gn:admin3_code":"161104.0",
    "gn:asciiname":"Lichynia",
    "gn:cc2":"PL",
    "gn:country_code":"PL",
    "gn:dem":237,
    "gn:feature_class":"P",
    "gn:feature_code":"PPL",
    "gn:name":"Lichynia",
    "gn:population":0,
    "gn:timezone":"Europe/Warsaw",
    "iso:country":"PL",
    "name:azb_x_preferred":[
        "\u0644\u06cc\u062e\u0646\u0642\u0627"
    ],
    "name:bul_x_preferred":[
        "\u041b\u0438\u0445\u0438\u043d\u044f"
    ],
    "name:deu_x_preferred":[
        "Lichinia"
    ],
    "name:fas_x_preferred":[
        "\u0644\u06cc\u062e\u0646\u06af\u0627"
    ],
    "name:nld_x_preferred":[
        "Lichynia"
    ],
    "name:pol_x_preferred":[
        "Lichynia"
    ],
    "name:szl_x_preferred":[
        "Lichy\u0144a"
    ],
    "name:ukr_x_preferred":[
        "\u041b\u0456\u0445\u0438\u043d\u044f"
    ],
    "name:und_x_variant":[
        "Lichtenforst"
    ],
    "wof:name":"Lichynia",
    "wof:placetype":"locality"
},
  "geometry": {"coordinates":[18.23318,50.42383],"type":"Point"}
}