{
  "type": "Feature",
  "properties": {
    "gn:admin1_code":"86.0",
    "gn:admin2_code":"3010.0",
    "gn:admin3_code":"301005.0",
    "gn:asciiname":"Konstantynow",
    "gn:country_code":"PL",
    "gn:dem":89,
    "gn:feature_class":"P",
    "gn:feature_code":"PPL",
    "gn:name":"Konstantyn\u00f3w",
    "gn:population":0,
    "gn:timezone":"Europe/Warsaw",
    "iso:country":"PL",
    "name:ita_x_preferred":[
        "Konstantyn\u00f3w"
    ],
    "name:pol_x_preferred":[
        "Konstantyn\u00f3w"
    ],
    "name:ukr_x_preferred":[
        "\u041a\u043e\u043d\u0441\u0442\u0430\u043d\u0442\u0438\u043d\u0443\u0432"
    ],
    "wof:name":"Konstantynow",
    "wof:placetype":"locality"
},
  "geometry": {"coordinates":[18.49986,52.24099],"type":"Point"}
}