{
  "type": "Feature",
  "properties": {
    "gn:admin1_code":"73.0",
    "gn:admin2_code":"409.0",
    "gn:admin3_code":"40903.0",
    "gn:asciiname":"Kunowo",
    "gn:country_code":"PL",
    "gn:dem":86,
    "gn:feature_class":"P",
    "gn:feature_code":"PPL",
    "gn:name":"Kunowo",
    "gn:population":0,
    "gn:timezone":"Europe/Warsaw",
    "iso:country":"PL",
    "name:pol_x_preferred":[
        "Kunowo"
    ],
    "name:ukr_x_preferred":[
        "\u041a\u0443\u043d\u043e\u0432\u043e"
    ],
    "wof:name":"Kunowo",
    "wof:placetype":"locality"
},
  "geometry": {"coordinates":[18.06297,52.63636999999999],"type":"Point"}
}