{
  "type": "Feature",
  "properties": {
    "gn:admin1_code":"85.0",
    "gn:admin2_code":"2814.0",
    "gn:admin3_code":"281408.0",
    "gn:asciiname":"Wojtowo",
    "gn:country_code":"PL",
    "gn:dem":170,
    "gn:feature_class":"P",
    "gn:feature_code":"PPL",
    "gn:name":"W\u00f3jtowo",
    "gn:population":0,
    "gn:timezone":"Europe/Warsaw",
    "iso:country":"PL",
    "name:und_x_variant":[
        "Voigtsdorf",
        "W\u00f3jtowo"
    ],
    "wof:name":"Wojtowo",
    "wof:placetype":"locality"
},
  "geometry": {"coordinates":[20.94723,54.00681],"type":"Point"}
}