{
  "type": "Feature",
  "properties": {
    "gn:admin1_code":"84.0",
    "gn:admin2_code":"2604.0",
    "gn:admin3_code":"260402.0",
    "gn:asciiname":"Kamieniec",
    "gn:country_code":"PL",
    "gn:dem":296,
    "gn:feature_class":"P",
    "gn:feature_code":"PPL",
    "gn:name":"Kamieniec",
    "gn:population":0,
    "gn:timezone":"Europe/Warsaw",
    "iso:country":"PL",
    "name:ceb_x_preferred":[
        "Kamieniec"
    ],
    "name:deu_x_preferred":[
        "Kamieniec"
    ],
    "name:fra_x_preferred":[
        "Kamieniec"
    ],
    "name:nld_x_preferred":[
        "Kamieniec"
    ],
    "name:pol_x_preferred":[
        "Kamieniec"
    ],
    "wof:name":"Kamieniec",
    "wof:placetype":"locality"
},
  "geometry": {"coordinates":[20.89781,50.96152],"type":"Point"}
}