{
  "type": "Feature",
  "properties": {
    "gn:admin1_code":"73.0",
    "gn:admin2_code":"402.0",
    "gn:admin3_code":"40202.0",
    "gn:asciiname":"Kawki",
    "gn:country_code":"PL",
    "gn:dem":109,
    "gn:feature_class":"P",
    "gn:feature_code":"PPL",
    "gn:name":"Kawki",
    "gn:population":0,
    "gn:timezone":"Europe/Warsaw",
    "iso:country":"PL",
    "name:pol_x_preferred":[
        "Kawki"
    ],
    "name:ukr_x_preferred":[
        "\u041a\u0430\u0432\u043a\u0456"
    ],
    "wof:name":"Kawki",
    "wof:placetype":"locality"
},
  "geometry": {"coordinates":[19.19292,53.24858],"type":"Point"}
}