{
  "type": "Feature",
  "properties": {
    "gn:admin1_code":"81.0",
    "gn:admin2_code":"2007.0",
    "gn:admin3_code":"200702.0",
    "gn:asciiname":"Koty",
    "gn:country_code":"PL",
    "gn:dem":102,
    "gn:feature_class":"P",
    "gn:feature_code":"PPL",
    "gn:name":"Koty",
    "gn:population":0,
    "gn:timezone":"Europe/Warsaw",
    "iso:country":"PL",
    "name:lit_x_preferred":[
        "Kotai"
    ],
    "name:pol_x_preferred":[
        "Koty"
    ],
    "name:ukr_x_preferred":[
        "\u041a\u043e\u0442\u0438"
    ],
    "wof:name":"Koty",
    "wof:placetype":"locality"
},
  "geometry": {"coordinates":[22.28243,53.08966],"type":"Point"}
}