{
  "type": "Feature",
  "properties": {
    "gn:admin1_code":"87.0",
    "gn:admin2_code":"3201.0",
    "gn:admin3_code":"320104.0",
    "gn:asciiname":"Borzyslaw",
    "gn:country_code":"PL",
    "gn:dem":57,
    "gn:feature_class":"P",
    "gn:feature_code":"PPL",
    "gn:name":"Borzys\u0142aw",
    "gn:population":0,
    "gn:timezone":"Europe/Warsaw",
    "iso:country":"PL",
    "name:und_x_variant":[
        "Borzys\u0142aw"
    ],
    "wof:name":"Borzyslaw",
    "wof:placetype":"locality"
},
  "geometry": {"coordinates":[16.20241,53.92904],"type":"Point"}
}