{
  "type": "Feature",
  "properties": {
    "gn:admin1_code":"87.0",
    "gn:admin2_code":"3206.0",
    "gn:admin3_code":"320601.0",
    "gn:asciiname":"Baniewice",
    "gn:country_code":"PL",
    "gn:dem":72,
    "gn:feature_class":"P",
    "gn:feature_code":"PPL",
    "gn:name":"Baniewice",
    "gn:population":0,
    "gn:timezone":"Europe/Warsaw",
    "iso:country":"PL",
    "name:pol_x_preferred":[
        "Baniewice"
    ],
    "name:ukr_x_preferred":[
        "\u0411\u0430\u043d\u0435\u0432\u0456\u0446\u0435"
    ],
    "name:vie_x_preferred":[
        "Baniewice"
    ],
    "wof:name":"Baniewice",
    "wof:placetype":"locality"
},
  "geometry": {"coordinates":[14.61044,53.08391999999999],"type":"Point"}
}