{
  "type": "Feature",
  "properties": {
    "gn:admin1_code":"72",
    "gn:admin2_code":"0204",
    "gn:admin3_code":"20402.0",
    "gn:asciiname":"Choragwice",
    "gn:country_code":"PL",
    "gn:dem":86,
    "gn:feature_class":"P",
    "gn:feature_code":"PPL",
    "gn:name":"Chor\u0105gwice",
    "gn:population":0,
    "gn:timezone":"Europe/Warsaw",
    "iso:country":"PL",
    "name:deu_x_historical":[
        "Korangelwitz",
        "Chorangelwitz"
    ],
    "name:deu_x_preferred":[
        "Korangelwitz"
    ],
    "name:deu_x_variant":[
        "Chorangelwitz"
    ],
    "wof:name":"Choragwice",
    "wof:placetype":"locality"
},
  "geometry": {"coordinates":[16.47022,51.58154],"type":"Point"}
}