{
  "type": "Feature",
  "properties": {
    "gn:admin1_code":"75.0",
    "gn:admin2_code":"603.0",
    "gn:admin3_code":"60315.0",
    "gn:asciiname":"Leonow",
    "gn:country_code":"PL",
    "gn:dem":211,
    "gn:feature_class":"P",
    "gn:feature_code":"PPL",
    "gn:name":"Leon\u00f3w",
    "gn:population":0,
    "gn:timezone":"Europe/Warsaw",
    "iso:country":"PL",
    "name:und_x_variant":[
        "Leon\u00f3w"
    ],
    "wof:name":"Leonow",
    "wof:placetype":"locality"
},
  "geometry": {"coordinates":[23.32637,51.1475],"type":"Point"}
}