{
  "type": "Feature",
  "properties": {
    "gn:population":1400,
    "iso:country":"PL",
    "name:ast_x_preferred":[
        "Trzebiel"
    ],
    "name:ceb_x_preferred":[
        "Trzebiel"
    ],
    "name:deu_x_preferred":[
        "Trzebiel"
    ],
    "name:dsb_x_preferred":[
        "Trjebule"
    ],
    "name:eng_x_preferred":[
        "Trzebiel"
    ],
    "name:fas_x_preferred":[
        "\u0686\u0628\u06cc\u0644"
    ],
    "name:fra_x_preferred":[
        "Trzebiel"
    ],
    "name:hsb_x_preferred":[
        "Trjebule"
    ],
    "name:nld_x_preferred":[
        "Trzebiel"
    ],
    "name:pol_x_preferred":[
        "Trzebiel"
    ],
    "name:ron_x_preferred":[
        "Trzebiel"
    ],
    "name:ukr_x_preferred":[
        "\u0422\u0448\u0435\u0431\u0435\u043b\u044c"
    ],
    "name:und_x_variant":[
        "Triebel"
    ],
    "name:vol_x_preferred":[
        "Trzebiel"
    ],
    "qs:a0":"Rzeczpospolita Polska",
    "qs:a1":"*Lubuskie",
    "qs:a1r":"0",
    "qs:a2":"Zarski",
    "qs:adm0":"Rzeczpospolita Polska",
    "qs:la":"Trzebiel",
    "qs:la_lc":"*PL0811082",
    "qs:level":"locality",
    "qs:loc":"Trzebiel",
    "qs:loc_alt":"Trzebiel",
    "qs:pop":0,
    "qs:type":"rural point-in-poly",
    "wd:wordcount":191,
    "wof:name":"Trzebiel",
    "wof:placetype":"locality",
    "wof:population":1400
},
  "geometry": {"coordinates":[14.8268602257025,51.5837851257334],"type":"Point"}
}