{
  "type": "Feature",
  "properties": {
    "gn:admin1_code":"72.0",
    "gn:admin2_code":"201.0",
    "gn:admin3_code":"20102.0",
    "gn:asciiname":"Ozar",
    "gn:country_code":"PL",
    "gn:dem":254,
    "gn:feature_class":"P",
    "gn:feature_code":"PPL",
    "gn:name":"O\u017car",
    "gn:population":0,
    "gn:timezone":"Europe/Warsaw",
    "iso:country":"PL",
    "wof:name":"Ozar",
    "wof:placetype":"locality"
},
  "geometry": {"coordinates":[15.58333,51.21667],"type":"Point"}
}