{
  "type": "Feature",
  "properties": {
    "iso:country":"PL",
    "name:ast_x_preferred":[
        "Zawoja"
    ],
    "name:azb_x_preferred":[
        "\u0632\u0627\u0648\u0648\u06cc\u0627"
    ],
    "name:deu_x_preferred":[
        "Zawoja"
    ],
    "name:eng_x_preferred":[
        "Zawoja"
    ],
    "name:fas_x_preferred":[
        "\u0632\u0627\u0648\u0648\u06cc\u0627"
    ],
    "name:fra_x_preferred":[
        "Zawoja"
    ],
    "name:ind_x_preferred":[
        "Zawoja"
    ],
    "name:ita_x_preferred":[
        "Zawoja"
    ],
    "name:nld_x_preferred":[
        "Zawoja"
    ],
    "name:pol_x_preferred":[
        "Zawoja"
    ],
    "name:rus_x_preferred":[
        "\u0417\u0430\u0432\u043e\u044f"
    ],
    "name:swe_x_preferred":[
        "Zawoja"
    ],
    "name:ukr_x_preferred":[
        "\u0417\u0430\u0432\u043e\u044f"
    ],
    "qs_pg:aaroncc":"PL",
    "qs_pg:name":"Zawoja",
    "qs_pg:name_adm0":"Polska",
    "qs_pg:name_adm1":"Ma\u0142opolskie",
    "qs_pg:photos":686,
    "qs_pg:photos_1k":139,
    "qs_pg:photos_9k":3,
    "qs_pg:photos_9r":5,
    "qs_pg:photos_all":686,
    "qs_pg:photos_sr":8,
    "qs_pg:pop_sr":0,
    "qs_pg:qs_pg_placetype":"locality",
    "qs_pg:qs_pg_placetype_gp":"Town",
    "qs_pg:woe_adm0":23424923,
    "woe:adm0_id":23424923,
    "woe:name_adm0":"Polska",
    "woe:name_adm1":"Ma\u0142opolskie",
    "woe:placetype":"Town",
    "wof:name":"Zawoja",
    "wof:placetype":"locality"
},
  "geometry": {"coordinates":[19.531631,49.582031],"type":"Point"}
}