{
  "type": "Feature",
  "properties": {
    "gn:admin1_code":"84.0",
    "gn:admin2_code":"2603.0",
    "gn:admin3_code":"260302.0",
    "gn:asciiname":"Ciuslice",
    "gn:country_code":"PL",
    "gn:dem":219,
    "gn:feature_class":"P",
    "gn:feature_code":"PPL",
    "gn:name":"Ciu\u015blice",
    "gn:population":0,
    "gn:timezone":"Europe/Warsaw",
    "iso:country":"PL",
    "name:und_x_variant":[
        "Ciu\u015blice"
    ],
    "wof:name":"Ciuslice",
    "wof:placetype":"locality"
},
  "geometry": {"coordinates":[20.47663,50.34809],"type":"Point"}
}