{
  "type": "Feature",
  "properties": {
    "gn:admin1_code":"84.0",
    "gn:admin2_code":"2603.0",
    "gn:admin3_code":"260302.0",
    "gn:asciiname":"Ciuslice",
    "gn:country_code":"PL",
    "gn:dem":219,
    "gn:feature_class":"P",
    "gn:feature_code":"PPL",
    "gn:name":"Ciu\u015blice",
    "gn:population":0,
    "gn:timezone":"Europe/Warsaw",
    "iso:country":"PL",
    "name:pol_x_preferred":[
        "Ciu\u015blice"
    ],
    "name:ukr_x_preferred":[
        "\u0426\u044e\u0441\u043b\u0456\u0446\u0435"
    ],
    "wof:name":"Ciuslice",
    "wof:placetype":"locality"
},
  "geometry": {"coordinates":[20.47663,50.34809],"type":"Point"}
}