{
  "type": "Feature",
  "properties": {
    "gn:admin1_code":"86.0",
    "gn:admin2_code":"3064.0",
    "gn:admin3_code":"306401.0",
    "gn:asciiname":"Junikowo",
    "gn:country_code":"PL",
    "gn:dem":78,
    "gn:feature_class":"P",
    "gn:feature_code":"PPL",
    "gn:name":"Junikowo",
    "gn:population":0,
    "gn:timezone":"Europe/Warsaw",
    "iso:country":"PL",
    "name:eng_x_preferred":[
        "Junikowo"
    ],
    "name:pol_x_preferred":[
        "Junikowo"
    ],
    "wof:name":"Junikowo",
    "wof:placetype":"neighbourhood"
},
  "geometry": {"coordinates":[16.844749,52.387159],"type":"Point"}
}