{
  "type": "Feature",
  "properties": {
    "iso:country":"PL",
    "name:eng_x_preferred":[
        "Junikowo"
    ],
    "name:pol_x_preferred":[
        "Junikowo"
    ],
    "wof:name":"Junikowo",
    "wof:placetype":"neighbourhood"
},
  "geometry": {"coordinates":[16.84474941916889,52.38715936766751],"type":"Point"}
}