{
  "type": "Feature",
  "properties": {
    "gn:admin1_code":"79.0",
    "gn:admin2_code":"1609.0",
    "gn:admin3_code":"160908.0",
    "gn:asciiname":"Chobie",
    "gn:country_code":"PL",
    "gn:dem":203,
    "gn:feature_class":"P",
    "gn:feature_code":"PPL",
    "gn:name":"Chobie",
    "gn:population":0,
    "gn:timezone":"Europe/Warsaw",
    "iso:country":"PL",
    "name:pol_x_preferred":[
        "Chobie"
    ],
    "name:ukr_x_preferred":[
        "\u0425\u043e\u0431\u0435"
    ],
    "wof:name":"Chobie",
    "wof:placetype":"locality"
},
  "geometry": {"coordinates":[18.29594,50.72042],"type":"Point"}
}