{
  "type": "Feature",
  "properties": {
    "iso:country":"PL",
    "name:pol_x_preferred":[
        "Lewand\u00f3w"
    ],
    "wof:name":"Lewandow",
    "wof:placetype":"neighbourhood"
},
  "geometry": {"coordinates":[21.06570315874204,52.31209019641237],"type":"Point"}
}