{
  "type": "Feature",
  "properties": {
    "gn:gn_country":"PL",
    "gn:gn_fcode":"PPL",
    "gn:gn_pop":0,
    "iso:country":"PL",
    "name:dut_x_preferred":[
        "Sucha Rzeczka"
    ],
    "name:eng_x_preferred":[
        "Sucha Rzeczka"
    ],
    "name:fre_x_preferred":[
        "Sucha Rzeczka"
    ],
    "name:lit_x_preferred":[
        "Sausup\u0117"
    ],
    "name:pol_x_preferred":[
        "Sucha Rzeczka"
    ],
    "qs_pg:aaroncc":"PL",
    "qs_pg:gn_country":"PL",
    "qs_pg:gn_fcode":"PPL",
    "qs_pg:gn_pop":0,
    "qs_pg:name":"Sucha Rzeczka",
    "qs_pg:name_adm0":"Polska",
    "qs_pg:name_adm1":"Podlaskie",
    "qs_pg:photos":7,
    "qs_pg:photos_1k":1,
    "qs_pg:photos_9k":1,
    "qs_pg:photos_9r":1,
    "qs_pg:photos_all":7,
    "qs_pg:photos_sr":1,
    "qs_pg:pop_sr":0,
    "qs_pg:qs_pg_placetype":"locality",
    "qs_pg:qs_pg_placetype_gp":"Town",
    "qs_pg:woe_adm0":23424923,
    "woe:adm0_id":23424923,
    "woe:name_adm0":"Polska",
    "woe:name_adm1":"Podlaskie",
    "woe:placetype":"Town",
    "wof:name":"Sucha Rzeczka",
    "wof:placetype":"locality"
},
  "geometry": {"coordinates":[23.20072,53.88947],"type":"Point"}
}