{
  "type": "Feature",
  "properties": {
    "gn:admin1_code":"78.0",
    "gn:admin2_code":"1462.0",
    "gn:admin3_code":"146201.0",
    "gn:asciiname":"Boryszewo Nowe",
    "gn:country_code":"PL",
    "gn:dem":109,
    "gn:feature_class":"P",
    "gn:feature_code":"PPL",
    "gn:name":"Boryszewo Nowe",
    "gn:population":0,
    "gn:timezone":"Europe/Warsaw",
    "iso:country":"PL",
    "name:fra_x_preferred":[
        "Nowe Boryszewo"
    ],
    "name:pol_x_preferred":[
        "Nowe Boryszewo"
    ],
    "name:ukr_x_preferred":[
        "\u041d\u043e\u0432\u0435 \u0411\u043e\u0440\u0438\u0448\u0435\u0432\u043e"
    ],
    "wof:name":"Boryszewo Nowe",
    "wof:placetype":"neighbourhood"
},
  "geometry": {"coordinates":[19.75702,52.55266],"type":"Point"}
}