{
  "type": "Feature",
  "properties": {
    "gn:admin1_code":"78.0",
    "gn:admin2_code":"1426.0",
    "gn:admin3_code":"142612.0",
    "gn:asciiname":"Seroczyn",
    "gn:country_code":"PL",
    "gn:dem":164,
    "gn:feature_class":"P",
    "gn:feature_code":"PPL",
    "gn:name":"Seroczyn",
    "gn:population":0,
    "gn:timezone":"Europe/Warsaw",
    "iso:country":"PL",
    "name:ceb_x_preferred":[
        "Seroczyn"
    ],
    "name:fra_x_preferred":[
        "Seroczyn"
    ],
    "name:pol_x_preferred":[
        "Seroczyn"
    ],
    "name:szl_x_preferred":[
        "Seroczyn"
    ],
    "name:ukr_x_preferred":[
        "\u0421\u0435\u0440\u043e\u0447\u0438\u043d"
    ],
    "wof:name":"Seroczyn",
    "wof:placetype":"locality"
},
  "geometry": {"coordinates":[21.9203,52.01146],"type":"Point"}
}