{
  "type": "Feature",
  "properties": {
    "gn:admin1_code":"79.0",
    "gn:admin2_code":"1609.0",
    "gn:admin3_code":"160901.0",
    "gn:asciiname":"Dabrowice",
    "gn:country_code":"PL",
    "gn:dem":171,
    "gn:feature_class":"P",
    "gn:feature_code":"PPL",
    "gn:name":"D\u0105browice",
    "gn:population":0,
    "gn:timezone":"Europe/Warsaw",
    "iso:country":"PL",
    "name:azb_x_preferred":[
        "\u062f\u0627\u0646\u0628\u0631\u0648\u0648\u06cc\u062a\u0633\u0647"
    ],
    "name:deu_x_preferred":[
        "Dombrowitz"
    ],
    "name:fas_x_preferred":[
        "\u062f\u0627\u0646\u0628\u0631\u0648\u0648\u06cc\u062a\u0633\u0647"
    ],
    "name:pol_x_preferred":[
        "D\u0105browice"
    ],
    "name:ukr_x_preferred":[
        "\u0414\u043e\u043c\u0431\u0440\u043e\u0432\u0456\u0446\u0435"
    ],
    "name:und_x_variant":[
        "D\u0105browice"
    ],
    "wof:name":"Dabrowice",
    "wof:placetype":"locality"
},
  "geometry": {"coordinates":[18.08508,50.62078],"type":"Point"}
}