{
  "type": "Feature",
  "properties": {
    "gn:admin1_code":"83.0",
    "gn:admin2_code":"2404.0",
    "gn:admin3_code":"240411.0",
    "gn:asciiname":"Wola Kiedrzynska",
    "gn:country_code":"PL",
    "gn:dem":235,
    "gn:feature_class":"P",
    "gn:feature_code":"PPL",
    "gn:name":"Wola Kiedrzy\u0144ska",
    "gn:population":0,
    "gn:timezone":"Europe/Warsaw",
    "iso:country":"PL",
    "name:und_x_variant":[
        "Kiedrzy\u0144ska Wola",
        "Wola Kiedrzy\u0144ska"
    ],
    "wof:name":"Wola Kiedrzynska",
    "wof:placetype":"locality"
},
  "geometry": {"coordinates":[19.11071,50.87697],"type":"Point"}
}