{
  "type": "Feature",
  "properties": {
    "gn:admin1_code":"83.0",
    "gn:admin2_code":"2404.0",
    "gn:admin3_code":"240411.0",
    "gn:asciiname":"Wola Kiedrzynska",
    "gn:country_code":"PL",
    "gn:dem":235,
    "gn:feature_class":"P",
    "gn:feature_code":"PPL",
    "gn:name":"Wola Kiedrzy\u0144ska",
    "gn:population":0,
    "gn:timezone":"Europe/Warsaw",
    "iso:country":"PL",
    "name:ceb_x_preferred":[
        "Wola Kiedrzy\u0144ska"
    ],
    "name:pol_x_preferred":[
        "Wola Kiedrzy\u0144ska"
    ],
    "name:ukr_x_preferred":[
        "\u0412\u043e\u043b\u044f-\u041a\u0435\u0434\u0436\u0438\u043d\u0441\u044c\u043a\u0430"
    ],
    "name:und_x_variant":[
        "Kiedrzy\u0144ska Wola"
    ],
    "wof:name":"Wola Kiedrzynska",
    "wof:placetype":"locality"
},
  "geometry": {"coordinates":[19.11071,50.87697],"type":"Point"}
}