{
  "type": "Feature",
  "properties": {
    "gn:country":"PL",
    "gn:fcode":"PPL",
    "gn:population":1200,
    "iso:country":"PL",
    "name:ceb_x_preferred":[
        "Jaworznik"
    ],
    "name:pol_x_preferred":[
        "Jaworznik"
    ],
    "name:ukr_x_preferred":[
        "\u042f\u0432\u043e\u0436\u043d\u0438\u043a"
    ],
    "qs_pg:aaroncc":"PL",
    "qs_pg:gn_country":"PL",
    "qs_pg:gn_fcode":"PPL",
    "qs_pg:gn_pop":1200,
    "qs_pg:name":"Jaworznik",
    "qs_pg:name_adm0":"Polska",
    "qs_pg:name_adm1":"Podkarpackie",
    "qs_pg:photos_9r":0,
    "qs_pg:photos_sr":0,
    "qs_pg:pop_sr":3,
    "qs_pg:qs_pg_placetype":"locality",
    "qs_pg:qs_pg_placetype_gp":"Town",
    "qs_pg:woe_adm0":23424923,
    "woe:adm0_id":23424923,
    "woe:name_adm0":"Polska",
    "woe:name_adm1":"Podkarpackie",
    "woe:placetype":"Town",
    "wof:name":"Jaworznik",
    "wof:placetype":"locality",
    "wof:population":1200
},
  "geometry": {"coordinates":[21.89404,49.8464],"type":"Point"}
}