{
  "type": "Feature",
  "properties": {
    "gn:admin1_code":"80.0",
    "gn:admin2_code":"1818.0",
    "gn:admin3_code":"181804.0",
    "gn:asciiname":"Dabrowa Rzeczycka",
    "gn:country_code":"PL",
    "gn:dem":147,
    "gn:feature_class":"P",
    "gn:feature_code":"PPL",
    "gn:name":"D\u0105browa Rzeczycka",
    "gn:population":0,
    "gn:timezone":"Europe/Warsaw",
    "iso:country":"PL",
    "name:und_x_variant":[
        "D\u0105browa",
        "D\u0105browa Rzeczycka"
    ],
    "wof:name":"Dabrowa Rzeczycka",
    "wof:placetype":"locality"
},
  "geometry": {"coordinates":[22.0443,50.65658],"type":"Point"}
}