{
  "type": "Feature",
  "properties": {
    "gn:admin1_code":"80.0",
    "gn:admin2_code":"1818.0",
    "gn:admin3_code":"181804.0",
    "gn:asciiname":"Dabrowa Rzeczycka",
    "gn:country_code":"PL",
    "gn:dem":147,
    "gn:feature_class":"P",
    "gn:feature_code":"PPL",
    "gn:name":"D\u0105browa Rzeczycka",
    "gn:population":0,
    "gn:timezone":"Europe/Warsaw",
    "iso:country":"PL",
    "name:msa_x_preferred":[
        "D\u0105browa Rzeczycka"
    ],
    "name:pol_x_preferred":[
        "D\u0105browa Rzeczycka"
    ],
    "name:ukr_x_preferred":[
        "\u0414\u043e\u043c\u0431\u0440\u043e\u0432\u0430-\u0416\u0435\u0447\u0438\u0446\u044c\u043a\u0430"
    ],
    "name:und_x_variant":[
        "D\u0105browa"
    ],
    "wof:name":"Dabrowa Rzeczycka",
    "wof:placetype":"locality"
},
  "geometry": {"coordinates":[22.0443,50.65658],"type":"Point"}
}