{
  "type": "Feature",
  "properties": {
    "gn:admin1_code":"73.0",
    "gn:admin2_code":"417.0",
    "gn:admin3_code":"41702.0",
    "gn:asciiname":"Kolonia Lipnica",
    "gn:country_code":"PL",
    "gn:dem":93,
    "gn:feature_class":"P",
    "gn:feature_code":"PPL",
    "gn:name":"Kolonia Lipnica",
    "gn:population":0,
    "gn:timezone":"Europe/Warsaw",
    "iso:country":"PL",
    "wof:name":"Kolonia Lipnica",
    "wof:placetype":"locality"
},
  "geometry": {"coordinates":[19.04629,53.17819],"type":"Point"}
}