{
  "type": "Feature",
  "properties": {
    "gn:admin1_code":"78.0",
    "gn:admin2_code":"1407.0",
    "gn:admin3_code":"140706.0",
    "gn:asciiname":"Zelazna Stara",
    "gn:country_code":"PL",
    "gn:dem":99,
    "gn:feature_class":"P",
    "gn:feature_code":"PPL",
    "gn:name":"\u017belazna Stara",
    "gn:population":0,
    "gn:timezone":"Europe/Warsaw",
    "iso:country":"PL",
    "name:fra_x_preferred":[
        "\u017belazna Stara"
    ],
    "name:pol_x_preferred":[
        "\u017belazna Stara"
    ],
    "name:ukr_x_preferred":[
        "\u0416\u0435\u043b\u044f\u0437\u043d\u0430-\u0421\u0442\u0430\u0440\u0430"
    ],
    "wof:name":"Zelazna Stara",
    "wof:placetype":"locality"
},
  "geometry": {"coordinates":[21.33882,51.80281],"type":"Point"}
}