{
  "type": "Feature",
  "properties": {
    "gn:admin1_code":"78.0",
    "gn:admin2_code":"1407.0",
    "gn:admin3_code":"140706.0",
    "gn:asciiname":"Zelazna Stara",
    "gn:country_code":"PL",
    "gn:dem":99,
    "gn:feature_class":"P",
    "gn:feature_code":"PPL",
    "gn:name":"\u017belazna Stara",
    "gn:population":0,
    "gn:timezone":"Europe/Warsaw",
    "iso:country":"PL",
    "name:und_x_variant":[
        "\u017belazna Stara"
    ],
    "wof:name":"Zelazna Stara",
    "wof:placetype":"locality"
},
  "geometry": {"coordinates":[21.33882,51.80281],"type":"Point"}
}