{
  "type": "Feature",
  "properties": {
    "gn:admin1_code":"73.0",
    "gn:admin2_code":"410.0",
    "gn:admin3_code":"41003.0",
    "gn:asciiname":"Wystep",
    "gn:country_code":"PL",
    "gn:dem":60,
    "gn:feature_class":"P",
    "gn:feature_code":"PPL",
    "gn:name":"Wyst\u0119p",
    "gn:population":0,
    "gn:timezone":"Europe/Warsaw",
    "iso:country":"PL",
    "name:ceb_x_preferred":[
        "Wyst\u0119p"
    ],
    "name:pol_x_preferred":[
        "Wyst\u0119p"
    ],
    "name:ukr_x_preferred":[
        "\u0412\u0438\u0441\u0442\u0435\u043c\u043f"
    ],
    "wof:name":"Wystep",
    "wof:placetype":"locality"
},
  "geometry": {"coordinates":[17.65092000000001,53.12177],"type":"Point"}
}