{
  "type": "Feature",
  "properties": {
    "gn:admin1_code":"73.0",
    "gn:admin2_code":"403.0",
    "gn:admin3_code":"40303.0",
    "gn:asciiname":"Wudzynek",
    "gn:country_code":"PL",
    "gn:dem":95,
    "gn:feature_class":"P",
    "gn:feature_code":"PPL",
    "gn:name":"Wudzynek",
    "gn:population":0,
    "gn:timezone":"Europe/Warsaw",
    "iso:country":"PL",
    "name:pol_x_preferred":[
        "Wudzynek"
    ],
    "name:ukr_x_preferred":[
        "\u0412\u0443\u0434\u0437\u0438\u043d\u0435\u043a"
    ],
    "wof:name":"Wudzynek",
    "wof:placetype":"locality"
},
  "geometry": {"coordinates":[18.10454,53.32184],"type":"Point"}
}