{
  "type": "Feature",
  "properties": {
    "gn:admin1_code":"73.0",
    "gn:admin2_code":"403.0",
    "gn:admin3_code":"40303.0",
    "gn:asciiname":"Wudzynek",
    "gn:country_code":"PL",
    "gn:dem":95,
    "gn:feature_class":"P",
    "gn:feature_code":"PPL",
    "gn:name":"Wudzynek",
    "gn:population":0,
    "gn:timezone":"Europe/Warsaw",
    "iso:country":"PL",
    "wof:name":"Wudzynek",
    "wof:placetype":"locality"
},
  "geometry": {"coordinates":[18.10454,53.32184],"type":"Point"}
}