{
  "type": "Feature",
  "properties": {
    "gn:population":1450,
    "iso:country":"PL",
    "name:ast_x_preferred":[
        "Stare Bogaczowice"
    ],
    "name:azb_x_preferred":[
        "\u0633\u062a\u0627\u0631\u0647 \u0628\u0648\u0642\u0627\u0686\u0648\u0648\u06cc\u062a\u0633\u0647"
    ],
    "name:ceb_x_preferred":[
        "Stare Bogaczowice"
    ],
    "name:deu_x_preferred":[
        "Stare Bogaczowice"
    ],
    "name:eng_x_preferred":[
        "Stare Bogaczowice"
    ],
    "name:fas_x_preferred":[
        "\u0633\u062a\u0627\u0631\u0647 \u0628\u0648\u06af\u0627\u0686\u0648\u0648\u06cc\u062a\u0633\u0647"
    ],
    "name:fra_x_preferred":[
        "Stare Bogaczowice"
    ],
    "name:ita_x_preferred":[
        "Stare Bogaczowice"
    ],
    "name:nld_x_preferred":[
        "Stare Bogaczowice"
    ],
    "name:pol_x_preferred":[
        "Stare Bogaczowice"
    ],
    "name:rus_x_preferred":[
        "\u0421\u0442\u0430\u0440\u0435-\u0411\u043e\u0433\u0430\u0447\u043e\u0432\u0438\u0446\u0435"
    ],
    "name:swe_x_preferred":[
        "Stare Bogaczowice"
    ],
    "name:ukr_x_preferred":[
        "\u0421\u0442\u0430\u0440\u0435 \u0411\u043e\u0491\u0430\u0447\u043e\u0432\u0456\u0446\u0435"
    ],
    "qs:a0":"Rzeczpospolita Polska",
    "qs:a1":"*Dolnoslaskie",
    "qs:a1r":"0",
    "qs:a2":"Walbrzyski",
    "qs:adm0":"Rzeczpospolita Polska",
    "qs:la":"Stare Bogaczowice",
    "qs:la_lc":"*PL0221072",
    "qs:level":"locality",
    "qs:loc":"Stare Bogaczowice",
    "qs:loc_alt":"Stare Bogaczowice",
    "qs:pop":0,
    "qs:type":"rural point-in-poly",
    "wd:wordcount":130,
    "wof:name":"Stare Bogaczowice",
    "wof:placetype":"locality",
    "wof:population":1450
},
  "geometry": {"coordinates":[16.2034808437103,50.8351471189682],"type":"Point"}
}