{
  "type": "Feature",
  "properties": {
    "gn:admin1_code":"73.0",
    "gn:admin2_code":"415.0",
    "gn:admin3_code":"41508.0",
    "gn:asciiname":"Pieczenia",
    "gn:country_code":"PL",
    "gn:dem":66,
    "gn:feature_class":"P",
    "gn:feature_code":"PPL",
    "gn:name":"Pieczenia",
    "gn:population":0,
    "gn:timezone":"Europe/Warsaw",
    "iso:country":"PL",
    "name:pol_x_preferred":[
        "Pieczenia"
    ],
    "name:rus_x_preferred":[
        "\u041f\u0435\u0447\u0435\u043d\u044f"
    ],
    "wof:name":"Pieczenia",
    "wof:placetype":"locality"
},
  "geometry": {"coordinates":[18.63247,52.89378000000001],"type":"Point"}
}