{
  "type": "Feature",
  "properties": {
    "gn:admin1_code":"87.0",
    "gn:admin2_code":"3201.0",
    "gn:admin3_code":"320102.0",
    "gn:asciiname":"Pustkowo",
    "gn:country_code":"PL",
    "gn:dem":24,
    "gn:feature_class":"P",
    "gn:feature_code":"PPL",
    "gn:name":"Pustkowo",
    "gn:population":0,
    "gn:timezone":"Europe/Warsaw",
    "iso:country":"PL",
    "name:deu_x_preferred":[
        "Pustkowo"
    ],
    "name:pol_x_preferred":[
        "Pustkowo"
    ],
    "name:ukr_x_preferred":[
        "\u041f\u0443\u0441\u0442\u043a\u043e\u0432\u043e"
    ],
    "wof:name":"Pustkowo",
    "wof:placetype":"locality"
},
  "geometry": {"coordinates":[16.02633,54.06526],"type":"Point"}
}