{
  "type": "Feature",
  "properties": {
    "gn:admin1_code":"79.0",
    "gn:admin2_code":"1607.0",
    "gn:admin3_code":"160706.0",
    "gn:asciiname":"Ulanowice",
    "gn:country_code":"PL",
    "gn:dem":255,
    "gn:feature_class":"P",
    "gn:feature_code":"PPL",
    "gn:name":"Ulanowice",
    "gn:population":0,
    "gn:timezone":"Europe/Warsaw",
    "iso:country":"PL",
    "wof:name":"Ulanowice",
    "wof:placetype":"locality"
},
  "geometry": {"coordinates":[17.20922,50.48624],"type":"Point"}
}