{
  "type": "Feature",
  "properties": {
    "gn:admin1_code":"83.0",
    "gn:admin2_code":"2416.0",
    "gn:admin3_code":"241602.0",
    "gn:asciiname":"Blanowice",
    "gn:country_code":"PL",
    "gn:dem":376,
    "gn:feature_class":"P",
    "gn:feature_code":"PPL",
    "gn:name":"Blanowice",
    "gn:population":0,
    "gn:timezone":"Europe/Warsaw",
    "iso:country":"PL",
    "wof:name":"Blanowice",
    "wof:placetype":"locality"
},
  "geometry": {"coordinates":[19.45728,50.51066],"type":"Point"}
}