{
  "type": "Feature",
  "properties": {
    "gn:admin1_code":"78.0",
    "gn:admin2_code":"1415.0",
    "gn:admin3_code":"141509.0",
    "gn:asciiname":"Antonie",
    "gn:country_code":"PL",
    "gn:dem":98,
    "gn:feature_class":"P",
    "gn:feature_code":"PPL",
    "gn:name":"Antonie",
    "gn:population":0,
    "gn:timezone":"Europe/Warsaw",
    "iso:country":"PL",
    "name:fra_x_preferred":[
        "Antonie"
    ],
    "name:pol_x_preferred":[
        "Antonie"
    ],
    "name:srp_x_preferred":[
        "\u0410\u043d\u0442\u043e\u045a\u0435"
    ],
    "name:ukr_x_preferred":[
        "\u0410\u043d\u0442\u043e\u043d\u0435"
    ],
    "wof:name":"Antonie",
    "wof:placetype":"locality"
},
  "geometry": {"coordinates":[21.5234,53.1169],"type":"Point"}
}