{
  "type": "Feature",
  "properties": {
    "gn:admin1_code":"84.0",
    "gn:admin2_code":"2603.0",
    "gn:admin3_code":"260301.0",
    "gn:asciiname":"Stojanowice",
    "gn:country_code":"PL",
    "gn:dem":181,
    "gn:feature_class":"P",
    "gn:feature_code":"PPL",
    "gn:name":"Stojanowice",
    "gn:population":0,
    "gn:timezone":"Europe/Warsaw",
    "iso:country":"PL",
    "name:pol_x_preferred":[
        "Stojanowice"
    ],
    "name:ukr_x_preferred":[
        "\u0421\u0442\u043e\u044f\u043d\u043e\u0432\u0456\u0446\u0435"
    ],
    "wof:name":"Stojanowice",
    "wof:placetype":"locality"
},
  "geometry": {"coordinates":[20.56616,50.2274],"type":"Point"}
}