{
  "type": "Feature",
  "properties": {
    "gn:admin1_code":"81.0",
    "gn:admin2_code":"2003.0",
    "gn:admin3_code":"200303.0",
    "gn:asciiname":"Sierakowizna",
    "gn:country_code":"PL",
    "gn:dem":156,
    "gn:feature_class":"P",
    "gn:feature_code":"PPL",
    "gn:name":"Sierakowizna",
    "gn:population":0,
    "gn:timezone":"Europe/Warsaw",
    "iso:country":"PL",
    "name:azb_x_preferred":[
        "\u0634\u0631\u0627\u06a9\u0648\u0648\u06cc\u0632\u0646\u0627"
    ],
    "name:fas_x_preferred":[
        "\u0634\u0631\u0627\u06a9\u0648\u0648\u06cc\u0632\u0646\u0627"
    ],
    "name:fra_x_preferred":[
        "Sierakowizna"
    ],
    "name:lit_x_preferred":[
        "Serakovizna"
    ],
    "name:pol_x_preferred":[
        "Sierakowizna"
    ],
    "name:ukr_x_preferred":[
        "\u0421\u0435\u0440\u0430\u043a\u043e\u0432\u0456\u0437\u043d\u0430"
    ],
    "name:und_x_variant":[
        "Sierakowizny"
    ],
    "wof:name":"Sierakowizna",
    "wof:placetype":"locality"
},
  "geometry": {"coordinates":[23.00563,52.74343],"type":"Point"}
}