{
  "type": "Feature",
  "properties": {
    "gn:admin1_code":"84.0",
    "gn:admin2_code":"2608.0",
    "gn:admin3_code":"260805.0",
    "gn:asciiname":"Chroberz",
    "gn:country_code":"PL",
    "gn:dem":180,
    "gn:feature_class":"P",
    "gn:feature_code":"PPL",
    "gn:name":"Chroberz",
    "gn:population":0,
    "gn:timezone":"Europe/Warsaw",
    "iso:country":"PL",
    "name:azb_x_preferred":[
        "\u062e\u0631\u0648\u0628\u0698"
    ],
    "name:ceb_x_preferred":[
        "Chroberz"
    ],
    "name:fas_x_preferred":[
        "\u062e\u0631\u0648\u0628\u0698"
    ],
    "name:ita_x_preferred":[
        "Chroberz"
    ],
    "name:nld_x_preferred":[
        "Chroberz"
    ],
    "name:pol_x_preferred":[
        "Chroberz"
    ],
    "name:ukr_x_preferred":[
        "\u0425\u0440\u043e\u0431\u0435\u0436"
    ],
    "wof:name":"Chroberz",
    "wof:placetype":"locality"
},
  "geometry": {"coordinates":[20.55696,50.42394],"type":"Point"}
}