{
  "type": "Feature",
  "properties": {
    "gn:admin1_code":"72.0",
    "gn:admin2_code":"217.0",
    "gn:admin3_code":"21705.0",
    "gn:asciiname":"Gutow",
    "gn:country_code":"PL",
    "gn:dem":151,
    "gn:feature_class":"P",
    "gn:feature_code":"PPL",
    "gn:name":"Gut\u00f3w",
    "gn:population":0,
    "gn:timezone":"Europe/Warsaw",
    "iso:country":"PL",
    "name:ceb_x_preferred":[
        "Gutow"
    ],
    "name:deu_x_preferred":[
        "Gutow"
    ],
    "name:nld_x_preferred":[
        "Gutow"
    ],
    "name:swe_x_preferred":[
        "Gutow"
    ],
    "wof:name":"Gutow",
    "wof:placetype":"locality"
},
  "geometry": {"coordinates":[17.17,50.83245],"type":"Point"}
}