{
  "type": "Feature",
  "properties": {
    "gn:admin1_code":"86.0",
    "gn:admin2_code":"3021.0",
    "gn:admin3_code":"302109.0",
    "gn:asciiname":"Blazejewko",
    "gn:country_code":"PL",
    "gn:dem":72,
    "gn:feature_class":"P",
    "gn:feature_code":"PPL",
    "gn:name":"B\u0142a\u017cejewko",
    "gn:population":0,
    "gn:timezone":"Europe/Warsaw",
    "iso:country":"PL",
    "name:ceb_x_preferred":[
        "B\u0142a\u017cejewko"
    ],
    "name:fra_x_preferred":[
        "B\u0142a\u017cejewko"
    ],
    "name:pol_x_preferred":[
        "B\u0142a\u017cejewko"
    ],
    "name:und_x_variant":[
        "B\u0142a\u017cejewko"
    ],
    "wof:name":"Blazejewko",
    "wof:placetype":"locality"
},
  "geometry": {"coordinates":[17.1106,52.19989],"type":"Point"}
}