{
  "type": "Feature",
  "properties": {
    "gn:country":"PL",
    "gn:fcode":"PPL",
    "gn:population":0,
    "iso:country":"PL",
    "name:ast_x_preferred":[
        "Budy Grabskie"
    ],
    "name:eng_x_preferred":[
        "Budy Grabskie"
    ],
    "name:fra_x_preferred":[
        "Budy Grabskie"
    ],
    "name:pol_x_preferred":[
        "Budy Grabskie"
    ],
    "name:und_x_variant":[
        "Grabskie Budy"
    ],
    "qs_pg:aaroncc":"PL",
    "qs_pg:gn_country":"PL",
    "qs_pg:gn_fcode":"PPL",
    "qs_pg:gn_pop":0,
    "qs_pg:name":"Budy Grabskie",
    "qs_pg:name_adm0":"Polska",
    "qs_pg:name_adm1":"\u0141\u00f3dzkie",
    "qs_pg:photos_9k":1,
    "qs_pg:photos_9r":1,
    "qs_pg:photos_all":14,
    "qs_pg:photos_sr":0,
    "qs_pg:pop_sr":0,
    "qs_pg:qs_pg_placetype":"locality",
    "qs_pg:qs_pg_placetype_gp":"Town",
    "qs_pg:woe_adm0":23424923,
    "woe:adm0_id":23424923,
    "woe:name_adm0":"Polska",
    "woe:name_adm1":"\u0141\u00f3dzkie",
    "woe:placetype":"Town",
    "wof:name":"Budy Grabskie",
    "wof:placetype":"locality"
},
  "geometry": {"coordinates":[20.21168,52.00953],"type":"Point"}
}