{
  "type": "Feature",
  "properties": {
    "gn:country":"PL",
    "gn:fcode":"PPLA3",
    "gn:population":700,
    "iso:country":"PL",
    "name:azb_x_preferred":[
        "\u0633\u0648\u0628\u06cc\u0646\u0642-\u06cc\u0698\u0648\u0631\u0647"
    ],
    "name:deu_x_preferred":[
        "Sobienie-Jeziory"
    ],
    "name:fas_x_preferred":[
        "\u0633\u0648\u0628\u06cc\u0646\u06af-\u06cc\u0698\u0648\u0631\u0647"
    ],
    "name:fra_x_preferred":[
        "Sobienie-Jeziory"
    ],
    "name:heb_x_preferred":[
        "\u05e1\u05d5\u05d1\u05d9\u05d9\u05e0\u05d9\u05d4 \u05d9\u05d6'\u05d9\u05d5\u05e8\u05d9"
    ],
    "name:nld_x_preferred":[
        "Sobienie-Jeziory"
    ],
    "name:pol_x_preferred":[
        "Sobienie-Jeziory"
    ],
    "name:ukr_x_preferred":[
        "\u0421\u043e\u0431\u0435\u043d\u0435-\u0404\u0437\u044c\u043e\u0440\u0438"
    ],
    "qs_pg:aaroncc":"PL",
    "qs_pg:gn_country":"PL",
    "qs_pg:gn_fcode":"PPLA3",
    "qs_pg:gn_pop":700,
    "qs_pg:name":"Sobienie-Jeziory",
    "qs_pg:name_adm0":"Polska",
    "qs_pg:name_adm1":"Mazowieckie",
    "qs_pg:photos":6,
    "qs_pg:photos_1k":1,
    "qs_pg:photos_9k":1,
    "qs_pg:photos_9r":1,
    "qs_pg:photos_all":6,
    "qs_pg:photos_sr":1,
    "qs_pg:pop_sr":2,
    "qs_pg:qs_pg_placetype":"localadmin",
    "qs_pg:qs_pg_placetype_gp":"LocalAdmin",
    "qs_pg:woe_adm0":23424923,
    "woe:adm0_id":23424923,
    "woe:name_adm0":"Polska",
    "woe:name_adm1":"Mazowieckie",
    "woe:placetype":"LocalAdmin",
    "wof:name":"Sobienie-Jeziory",
    "wof:placetype":"localadmin",
    "wof:population":700
},
  "geometry": {"coordinates":[21.30335,51.93273],"type":"Point"}
}