{
  "type": "Feature",
  "properties": {
    "gn:admin1_code":"77.0",
    "gn:admin2_code":"1202.0",
    "gn:admin3_code":"120207.0",
    "gn:asciiname":"Rajsko",
    "gn:country_code":"PL",
    "gn:dem":178,
    "gn:feature_class":"P",
    "gn:feature_code":"PPL",
    "gn:name":"Rajsko",
    "gn:population":0,
    "gn:timezone":"Europe/Warsaw",
    "iso:country":"PL",
    "name:pol_x_preferred":[
        "Rajsko"
    ],
    "name:ukr_x_preferred":[
        "\u0420\u0430\u0439\u0441\u044c\u043a\u043e"
    ],
    "wof:name":"Rajsko",
    "wof:placetype":"locality"
},
  "geometry": {"coordinates":[20.59876,50.10517],"type":"Point"}
}