{
  "type": "Feature",
  "properties": {
    "gn:admin1_code":"81.0",
    "gn:admin2_code":"2002.0",
    "gn:admin3_code":"200214.0",
    "gn:asciiname":"Skrybicze",
    "gn:country_code":"PL",
    "gn:dem":152,
    "gn:feature_class":"P",
    "gn:feature_code":"PPL",
    "gn:name":"Skrybicze",
    "gn:population":0,
    "gn:timezone":"Europe/Warsaw",
    "iso:country":"PL",
    "name:lit_x_preferred":[
        "Skribi\u010d\u0117"
    ],
    "name:pol_x_preferred":[
        "Skrybicze"
    ],
    "name:ukr_x_preferred":[
        "\u0421\u043a\u0440\u0438\u0431\u0456\u0447\u0435"
    ],
    "wof:name":"Skrybicze",
    "wof:placetype":"locality"
},
  "geometry": {"coordinates":[23.23079,53.05555],"type":"Point"}
}