{
  "type": "Feature",
  "properties": {
    "gn:admin1_code":"86.0",
    "gn:admin2_code":"3008.0",
    "gn:admin3_code":"300802.0",
    "gn:asciiname":"Nowawies Ksiazeca",
    "gn:country_code":"PL",
    "gn:dem":182,
    "gn:feature_class":"P",
    "gn:feature_code":"PPL",
    "gn:name":"Nowawie\u015b Ksi\u0105\u017c\u0119ca",
    "gn:population":0,
    "gn:timezone":"Europe/Warsaw",
    "iso:country":"PL",
    "name:und_x_variant":[
        "Nowa Wie\u015b Ksi\u0105\u017c\u0119ca",
        "Nowawie\u015b Ksi\u0105\u017c\u0119ca"
    ],
    "wof:name":"Nowawies Ksiazeca",
    "wof:placetype":"locality"
},
  "geometry": {"coordinates":[17.86322000000001,51.23702],"type":"Point"}
}