{
  "type": "Feature",
  "properties": {
    "gn:admin1_code":"83.0",
    "gn:admin2_code":"2469.0",
    "gn:admin3_code":"246901.0",
    "gn:asciiname":"Zespol dzielnic zachodnich",
    "gn:country_code":"PL",
    "gn:dem":282,
    "gn:feature_class":"P",
    "gn:feature_code":"PPL",
    "gn:name":"Zesp\u00f3\u0142 dzielnic zachodnich",
    "gn:population":0,
    "gn:timezone":"Europe/Warsaw",
    "iso:country":"PL",
    "wof:name":"Zespol dzielnic zachodnich",
    "wof:placetype":"locality"
},
  "geometry": {"coordinates":[18.98918,50.25153],"type":"Point"}
}