{
  "type": "Feature",
  "properties": {
    "gn:admin1_code":"85.0",
    "gn:admin2_code":"2806.0",
    "gn:admin3_code":"280608.0",
    "gn:asciiname":"Mrowki",
    "gn:country_code":"PL",
    "gn:dem":117,
    "gn:feature_class":"P",
    "gn:feature_code":"PPL",
    "gn:name":"Mr\u00f3wki",
    "gn:population":0,
    "gn:timezone":"Europe/Warsaw",
    "iso:country":"PL",
    "name:und_x_variant":[
        "Neuforst",
        "Mrowken",
        "Mr\u00f3wki"
    ],
    "wof:name":"Mrowki",
    "wof:placetype":"locality"
},
  "geometry": {"coordinates":[21.49153,53.89892],"type":"Point"}
}