{
  "type": "Feature",
  "properties": {
    "gn:admin1_code":"86.0",
    "gn:admin2_code":"3012.0",
    "gn:admin3_code":"301204.0",
    "gn:asciiname":"Dzierzanow",
    "gn:country_code":"PL",
    "gn:dem":109,
    "gn:feature_class":"P",
    "gn:feature_code":"PPL",
    "gn:name":"Dzier\u017can\u00f3w",
    "gn:population":0,
    "gn:timezone":"Europe/Warsaw",
    "iso:country":"PL",
    "name:und_x_variant":[
        "Dier\u017can\u00f3w",
        "Dzier\u017can\u00f3w"
    ],
    "wof:name":"Dzierzanow",
    "wof:placetype":"locality"
},
  "geometry": {"coordinates":[17.34498,51.7122],"type":"Point"}
}