{
  "type": "Feature",
  "properties": {
    "gn:admin1_code":"74.0",
    "gn:admin2_code":"1019.0",
    "gn:admin3_code":"101901.0",
    "gn:asciiname":"Nowe Miasto",
    "gn:country_code":"PL",
    "gn:dem":171,
    "gn:feature_class":"P",
    "gn:feature_code":"PPL",
    "gn:name":"Nowe Miasto",
    "gn:population":0,
    "gn:timezone":"Europe/Warsaw",
    "iso:country":"PL",
    "name:ceb_x_preferred":[
        "Nowe Miasto"
    ],
    "name:deu_x_preferred":[
        "Nowe Miasto"
    ],
    "name:fra_x_preferred":[
        "Nowe Miasto"
    ],
    "name:heb_x_preferred":[
        "\u05e0\u05d5\u05d1\u05d4 \u05de\u05d9\u05d0\u05e1\u05d8\u05d5"
    ],
    "name:lit_x_preferred":[
        "Naujamiestis"
    ],
    "name:nld_x_preferred":[
        "Nowe Miasto"
    ],
    "name:pol_x_preferred":[
        "Nowe Miasto"
    ],
    "name:rus_x_preferred":[
        "\u041d\u043e\u0432\u0435-\u041c\u044f\u0441\u0442\u043e"
    ],
    "name:swe_x_preferred":[
        "Nowe Miasto"
    ],
    "wof:name":"Nowe Miasto",
    "wof:placetype":"neighbourhood"
},
  "geometry": {"coordinates":[18.98333,51.58333],"type":"Point"}
}