{
  "type": "Feature",
  "properties": {
    "iso:country":"PL",
    "name:ast_x_preferred":[
        "Staniszcze Ma\u0142e"
    ],
    "name:azb_x_preferred":[
        "\u0633\u062a\u0627\u0646\u0642\u0634\u0686\u0647 \u0645\u0627\u0648\u0647"
    ],
    "name:deu_x_preferred":[
        "Klein Stanisch"
    ],
    "name:eng_x_preferred":[
        "Staniszcze Ma\u0142e"
    ],
    "name:fas_x_preferred":[
        "\u0633\u062a\u0627\u0646\u06af\u0634\u0686\u0647 \u0645\u0627\u0648\u0647"
    ],
    "name:fra_x_preferred":[
        "Staniszcze Ma\u0142e"
    ],
    "name:nan_x_preferred":[
        "Staniszcze Ma\u0142e"
    ],
    "name:nld_x_preferred":[
        "Staniszcze Ma\u0142e"
    ],
    "name:pol_x_preferred":[
        "Staniszcze Ma\u0142e"
    ],
    "name:ukr_x_preferred":[
        "\u0421\u0442\u0430\u043d\u0456\u0449\u0435-\u041c\u0430\u043b\u0435"
    ],
    "name:unk_x_variant":[
        "Staniszcze-Ma\u0142e"
    ],
    "name:zho_min_nan_x_preferred":[
        "Staniszcze Ma\u0142e"
    ],
    "qs:a0":"Rzeczpospolita Polska",
    "qs:a1":"*Opolskie",
    "qs:a1r":"0",
    "qs:a2":"Strzelecki",
    "qs:adm0":"Rzeczpospolita Polska",
    "qs:la_lc":"*",
    "qs:level":"locality",
    "qs:loc":"Staniszcze Ma\u0142e",
    "qs:loc_alt":"Staniszcze Male",
    "qs:pop":0,
    "qs:type":"buffered point",
    "wd:wordcount":113,
    "wof:name":"Staniszcze Ma\u0142e",
    "wof:placetype":"locality"
},
  "geometry": {"coordinates":[18.318056,50.663192],"type":"Point"}
}