{
  "type": "Feature",
  "properties": {
    "gn:admin1_code":"79.0",
    "gn:admin2_code":"1607.0",
    "gn:admin3_code":"160704.0",
    "gn:asciiname":"Wierzbie",
    "gn:country_code":"PL",
    "gn:dem":196,
    "gn:feature_class":"P",
    "gn:feature_code":"PPL",
    "gn:name":"Wierzbie",
    "gn:population":0,
    "gn:timezone":"Europe/Warsaw",
    "iso:country":"PL",
    "name:ceb_x_preferred":[
        "Wierzbie"
    ],
    "name:deu_x_preferred":[
        "Wierzbie"
    ],
    "name:pol_x_preferred":[
        "Wierzbie"
    ],
    "name:ukr_x_preferred":[
        "\u0412\u0435\u0436\u0431\u0435"
    ],
    "name:und_x_variant":[
        "Weidengut",
        "Wiedengut",
        "Wiersbel",
        "Wierzbie"
    ],
    "wof:name":"Wierzbie",
    "wof:placetype":"locality"
},
  "geometry": {"coordinates":[17.59072,50.52905],"type":"Point"}
}