{
  "type": "Feature",
  "properties": {
    "gn:admin1_code":"77.0",
    "gn:admin2_code":"1208.0",
    "gn:admin3_code":"120806.0",
    "gn:asciiname":"Gorka Kosciejowska",
    "gn:country_code":"PL",
    "gn:dem":328,
    "gn:feature_class":"P",
    "gn:feature_code":"PPL",
    "gn:name":"G\u00f3rka Ko\u015bciejowska",
    "gn:population":0,
    "gn:timezone":"Europe/Warsaw",
    "iso:country":"PL",
    "name:azb_x_preferred":[
        "\u0642\u0648\u0631\u06a9\u0627 \u06a9\u0648\u0634\u0686\u06cc\u06cc\u0648\u0648\u0633\u06a9\u0627"
    ],
    "name:ceb_x_preferred":[
        "G\u00f3rka Ko\u015bciejowska"
    ],
    "name:fas_x_preferred":[
        "\u06af\u0648\u0631\u06a9\u0627 \u06a9\u0648\u0634\u0686\u06cc\u06cc\u0648\u0648\u0633\u06a9\u0627"
    ],
    "name:nld_x_preferred":[
        "G\u00f3rka Ko\u015bciejowska"
    ],
    "name:pol_x_preferred":[
        "G\u00f3rka Ko\u015bciejowska"
    ],
    "name:rus_x_preferred":[
        "\u0413\u0443\u0440\u043a\u0430-\u041a\u043e\u0441\u044c\u0446\u0435\u0451\u0432\u0441\u043a\u0430"
    ],
    "name:ukr_x_preferred":[
        "\u0490\u0443\u0440\u043a\u0430-\u041a\u043e\u0441\u044c\u0446\u0435\u0439\u043e\u0432\u0441\u044c\u043a\u0430"
    ],
    "wof:name":"Gorka Kosciejowska",
    "wof:placetype":"locality"
},
  "geometry": {"coordinates":[20.25725,50.31211],"type":"Point"}
}