{
  "type": "Feature",
  "properties": {
    "gn:admin1_code":"77.0",
    "gn:admin2_code":"1208.0",
    "gn:admin3_code":"120806.0",
    "gn:asciiname":"Gorka Kosciejowska",
    "gn:country_code":"PL",
    "gn:dem":328,
    "gn:feature_class":"P",
    "gn:feature_code":"PPL",
    "gn:name":"G\u00f3rka Ko\u015bciejowska",
    "gn:population":0,
    "gn:timezone":"Europe/Warsaw",
    "iso:country":"PL",
    "name:und_x_variant":[
        "G\u00f3rka Ko\u015bciejowska"
    ],
    "wof:name":"Gorka Kosciejowska",
    "wof:placetype":"locality"
},
  "geometry": {"coordinates":[20.25725,50.31211],"type":"Point"}
}