{
  "type": "Feature",
  "properties": {
    "gn:admin1_code":"84.0",
    "gn:admin2_code":"2610.0",
    "gn:admin3_code":"261002.0",
    "gn:asciiname":"Sorbin",
    "gn:country_code":"PL",
    "gn:dem":282,
    "gn:feature_class":"P",
    "gn:feature_code":"PPL",
    "gn:name":"Sorbin",
    "gn:population":0,
    "gn:timezone":"Europe/Warsaw",
    "iso:country":"PL",
    "wof:name":"Sorbin",
    "wof:placetype":"locality"
},
  "geometry": {"coordinates":[20.69115,51.10448],"type":"Point"}
}