{
  "type": "Feature",
  "properties": {
    "gn:admin1_code":"84.0",
    "gn:admin2_code":"2605.0",
    "gn:admin3_code":"260508.0",
    "gn:asciiname":"Koprusa",
    "gn:country_code":"PL",
    "gn:dem":268,
    "gn:feature_class":"P",
    "gn:feature_code":"PPL",
    "gn:name":"Koprusa",
    "gn:population":0,
    "gn:timezone":"Europe/Warsaw",
    "iso:country":"PL",
    "wof:name":"Koprusa",
    "wof:placetype":"locality"
},
  "geometry": {"coordinates":[20.56174,51.14472],"type":"Point"}
}