{
  "type": "Feature",
  "properties": {
    "gn:admin1_code":"78.0",
    "gn:admin2_code":"1406.0",
    "gn:admin3_code":"140608.0",
    "gn:asciiname":"Gilowka",
    "gn:country_code":"PL",
    "gn:dem":147,
    "gn:feature_class":"P",
    "gn:feature_code":"PPL",
    "gn:name":"Gil\u00f3wka",
    "gn:population":0,
    "gn:timezone":"Europe/Warsaw",
    "iso:country":"PL",
    "name:und_x_variant":[
        "Gil\u00f3wka"
    ],
    "wof:name":"Gilowka",
    "wof:placetype":"locality"
},
  "geometry": {"coordinates":[20.52241,51.5648],"type":"Point"}
}