{
  "type": "Feature",
  "properties": {
    "gn:admin1_code":"72.0",
    "gn:admin2_code":"218.0",
    "gn:admin3_code":"21801.0",
    "gn:asciiname":"Osiek",
    "gn:country_code":"PL",
    "gn:dem":174,
    "gn:feature_class":"P",
    "gn:feature_code":"PPL",
    "gn:name":"Osiek",
    "gn:population":450,
    "gn:timezone":"Europe/Warsaw",
    "iso:country":"PL",
    "wof:name":"Osiek",
    "wof:placetype":"locality",
    "wof:population":450
},
  "geometry": {"coordinates":[16.54867,51.00922],"type":"Point"}
}