{
  "type": "Feature",
  "properties": {
    "gn:admin1_code":"84.0",
    "gn:admin2_code":"2604.0",
    "gn:admin3_code":"260401.0",
    "gn:asciiname":"Huta Szklana",
    "gn:country_code":"PL",
    "gn:dem":455,
    "gn:feature_class":"P",
    "gn:feature_code":"PPL",
    "gn:name":"Huta Szklana",
    "gn:population":0,
    "gn:timezone":"Europe/Warsaw",
    "iso:country":"PL",
    "name:und_x_variant":[
        "Huta",
        "Huta Szklana"
    ],
    "wof:name":"Huta Szklana",
    "wof:placetype":"locality"
},
  "geometry": {"coordinates":[21.02171,50.86104],"type":"Point"}
}