{
  "type": "Feature",
  "properties": {
    "gn:admin1_code":"84.0",
    "gn:admin2_code":"2605.0",
    "gn:admin3_code":"260505.0",
    "gn:asciiname":"Wyszyna Rudzka",
    "gn:country_code":"PL",
    "gn:dem":230,
    "gn:feature_class":"P",
    "gn:feature_code":"PPL",
    "gn:name":"Wyszyna Rudzka",
    "gn:population":0,
    "gn:timezone":"Europe/Warsaw",
    "iso:country":"PL",
    "name:ceb_x_preferred":[
        "Wyszyna Rudzka"
    ],
    "name:pol_x_preferred":[
        "Wyszyna Rudzka"
    ],
    "name:ukr_x_preferred":[
        "\u0412\u0438\u0448\u0438\u043d\u0430-\u0420\u0443\u0434\u0437\u044c\u043a\u0430"
    ],
    "wof:name":"Wyszyna Rudzka",
    "wof:placetype":"locality"
},
  "geometry": {"coordinates":[20.19871,51.14977],"type":"Point"}
}