{
  "type": "Feature",
  "properties": {
    "gn:admin1_code":"84.0",
    "gn:admin2_code":"2612.0",
    "gn:admin3_code":"261202.0",
    "gn:asciiname":"Gace Slupieckie",
    "gn:country_code":"PL",
    "gn:dem":160,
    "gn:feature_class":"P",
    "gn:feature_code":"PPL",
    "gn:name":"Gace S\u0142upieckie",
    "gn:population":0,
    "gn:timezone":"Europe/Warsaw",
    "iso:country":"PL",
    "name:nld_x_preferred":[
        "Gace S\u0142upieckie"
    ],
    "name:pol_x_preferred":[
        "Gace S\u0142upieckie"
    ],
    "name:ukr_x_preferred":[
        "\u0490\u0430\u0446\u0435-\u0421\u043b\u0443\u043f\u0435\u0446\u044c\u043a\u0456"
    ],
    "wof:name":"Gace Slupieckie",
    "wof:placetype":"locality"
},
  "geometry": {"coordinates":[21.1516,50.36693],"type":"Point"}
}