{
  "type": "Feature",
  "properties": {
    "gn:admin1_code":"84.0",
    "gn:admin2_code":"2612.0",
    "gn:admin3_code":"261202.0",
    "gn:asciiname":"Gace Slupieckie",
    "gn:country_code":"PL",
    "gn:dem":160,
    "gn:feature_class":"P",
    "gn:feature_code":"PPL",
    "gn:name":"Gace S\u0142upieckie",
    "gn:population":0,
    "gn:timezone":"Europe/Warsaw",
    "iso:country":"PL",
    "wof:name":"Gace Slupieckie",
    "wof:placetype":"locality"
},
  "geometry": {"coordinates":[21.1516,50.36693],"type":"Point"}
}