{
  "type": "Feature",
  "properties": {
    "gn:admin1_code":"72.0",
    "gn:admin2_code":"216.0",
    "gn:admin3_code":"21603.0",
    "gn:asciiname":"Krzydlowice",
    "gn:country_code":"PL",
    "gn:dem":97,
    "gn:feature_class":"P",
    "gn:feature_code":"PPL",
    "gn:name":"Krzydlowice",
    "gn:population":0,
    "gn:timezone":"Europe/Warsaw",
    "iso:country":"PL",
    "name:pol_x_preferred":[
        "Krzyd\u0142owice"
    ],
    "name:ukr_x_preferred":[
        "\u041a\u0448\u0438\u0434\u043b\u043e\u0432\u0456\u0446\u0435"
    ],
    "wof:name":"Krzydlowice",
    "wof:placetype":"locality"
},
  "geometry": {"coordinates":[16.23226,51.54582],"type":"Point"}
}