{
  "type": "Feature",
  "properties": {
    "gn:admin1_code":"72.0",
    "gn:admin2_code":"216.0",
    "gn:admin3_code":"21603.0",
    "gn:asciiname":"Krzydlowice",
    "gn:country_code":"PL",
    "gn:dem":97,
    "gn:feature_class":"P",
    "gn:feature_code":"PPL",
    "gn:name":"Krzydlowice",
    "gn:population":0,
    "gn:timezone":"Europe/Warsaw",
    "iso:country":"PL",
    "wof:name":"Krzydlowice",
    "wof:placetype":"locality"
},
  "geometry": {"coordinates":[16.23226,51.54582],"type":"Point"}
}