{
  "type": "Feature",
  "properties": {
    "gn:admin1_code":"75.0",
    "gn:admin2_code":"607.0",
    "gn:admin3_code":"60706.0",
    "gn:asciiname":"Moczydla Stare",
    "gn:country_code":"PL",
    "gn:dem":284,
    "gn:feature_class":"P",
    "gn:feature_code":"PPL",
    "gn:name":"Moczyd\u0142a Stare",
    "gn:population":0,
    "gn:timezone":"Europe/Warsaw",
    "iso:country":"PL",
    "name:und_x_variant":[
        "Moczydla",
        "Moczyd\u0142a Stare"
    ],
    "wof:name":"Moczydla Stare",
    "wof:placetype":"locality"
},
  "geometry": {"coordinates":[22.39724,50.84429],"type":"Point"}
}