{
  "type": "Feature",
  "properties": {
    "gn:admin1_code":"72.0",
    "gn:admin2_code":"207.0",
    "gn:admin3_code":"20704.0",
    "gn:asciiname":"Marciszow Dolny",
    "gn:country_code":"PL",
    "gn:dem":421,
    "gn:feature_class":"P",
    "gn:feature_code":"PPL",
    "gn:name":"Marcisz\u00f3w Dolny",
    "gn:population":0,
    "gn:timezone":"Europe/Warsaw",
    "iso:country":"PL",
    "name:deu_x_historical":[
        "Nieder Wernersdorf"
    ],
    "name:deu_x_preferred":[
        "Nieder Wernersdorf"
    ],
    "name:und_x_variant":[
        "Marcisz\u00f3w Dolny"
    ],
    "wof:name":"Marciszow Dolny",
    "wof:placetype":"locality"
},
  "geometry": {"coordinates":[16.0084,50.85274],"type":"Point"}
}