{
  "type": "Feature",
  "properties": {
    "gn:population":1177,
    "iso:country":"PL",
    "name:ast_x_preferred":[
        "Wola Zabierzowska"
    ],
    "name:ceb_x_preferred":[
        "Wola Zabierzowska"
    ],
    "name:eng_x_preferred":[
        "Wola Zabierzowska"
    ],
    "name:fra_x_preferred":[
        "Wola Zabierzowska"
    ],
    "name:nld_x_preferred":[
        "Wola Zabierzowska"
    ],
    "name:pol_x_preferred":[
        "Wola Zabierzowska"
    ],
    "name:ukr_x_preferred":[
        "\u0412\u043e\u043b\u044f-\u0417\u0430\u0431\u0435\u0436\u043e\u0432\u0441\u044c\u043a\u0430"
    ],
    "qs:a0":"Rzeczpospolita Polska",
    "qs:a1":"*Malopolskie",
    "qs:a1r":"0",
    "qs:a2":"Wielicki",
    "qs:adm0":"Rzeczpospolita Polska",
    "qs:la_lc":"*",
    "qs:level":"locality",
    "qs:loc":"Wola Zabierzowska",
    "qs:loc_alt":"Wola Zabierzowska",
    "qs:pop":0,
    "qs:type":"buffered point",
    "wd:wordcount":82,
    "wof:name":"Wola Zabierzowska",
    "wof:placetype":"locality",
    "wof:population":1177
},
  "geometry": {"coordinates":[20.340599,50.075192],"type":"Point"}
}