{
  "type": "Feature",
  "properties": {
    "gn:gn_country":"PL",
    "gn:gn_fcode":"PPLA3",
    "gn:gn_pop":1800,
    "gn:population":1800,
    "iso:country":"PL",
    "name:azb_x_preferred":[
        "\u0642\u0648\u0633\u062a\u062a\u0633\u0646"
    ],
    "name:ceb_x_preferred":[
        "Gostycyn"
    ],
    "name:deu_x_preferred":[
        "Gostycyn"
    ],
    "name:fas_x_preferred":[
        "\u06af\u0648\u0633\u062a\u062a\u0633\u0646"
    ],
    "name:nld_x_preferred":[
        "Gostycyn"
    ],
    "name:pol_x_preferred":[
        "Gostycyn"
    ],
    "name:ukr_x_preferred":[
        "\u0490\u043e\u0441\u0442\u0438\u0446\u0438\u043d"
    ],
    "name:unk_x_variant":[
        "Gostyczyn"
    ],
    "qs_pg:aaroncc":"PL",
    "qs_pg:gn_country":"PL",
    "qs_pg:gn_fcode":"PPLA3",
    "qs_pg:gn_pop":1800,
    "qs_pg:name":"Gostycyn",
    "qs_pg:name_adm0":"Polska",
    "qs_pg:name_adm1":"Kujawsko-Pomorskie",
    "qs_pg:photos_9k":1,
    "qs_pg:photos_9r":1,
    "qs_pg:photos_all":11,
    "qs_pg:photos_sr":0,
    "qs_pg:pop_sr":3,
    "qs_pg:qs_pg_placetype":"localadmin",
    "qs_pg:qs_pg_placetype_gp":"LocalAdmin",
    "qs_pg:woe_adm0":23424923,
    "woe:adm0_id":23424923,
    "woe:name_adm0":"Polska",
    "woe:name_adm1":"Kujawsko-Pomorskie",
    "woe:placetype":"LocalAdmin",
    "wof:name":"Gostycyn",
    "wof:placetype":"localadmin",
    "wof:population":1800
},
  "geometry": {"coordinates":[17.80978,53.49014],"type":"Point"}
}