{
  "type": "Feature",
  "properties": {
    "gn:admin1_code":"75.0",
    "gn:admin2_code":"602.0",
    "gn:admin3_code":"60209.0",
    "gn:asciiname":"Szarajowka",
    "gn:country_code":"PL",
    "gn:dem":224,
    "gn:feature_class":"P",
    "gn:feature_code":"PPL",
    "gn:name":"Szaraj\u00f3wka",
    "gn:population":0,
    "gn:timezone":"Europe/Warsaw",
    "iso:country":"PL",
    "name:und_x_variant":[
        "Szaraj\u00f3wka"
    ],
    "wof:name":"Szarajowka",
    "wof:placetype":"locality"
},
  "geometry": {"coordinates":[22.86667000000001,50.38333],"type":"Point"}
}