{
  "type": "Feature",
  "properties": {
    "gn:gn_country":"PL",
    "gn:gn_fcode":"PPL",
    "gn:gn_pop":284,
    "gn:population":284,
    "iso:country":"PL",
    "qs_pg:aaroncc":"PL",
    "qs_pg:gn_country":"PL",
    "qs_pg:gn_fcode":"PPL",
    "qs_pg:gn_pop":284,
    "qs_pg:name":"Dymaczewo Nowe",
    "qs_pg:photos_9r":0,
    "qs_pg:photos_sr":0,
    "qs_pg:pop_sr":2,
    "qs_pg:qs_pg_placetype":"locality",
    "wof:name":"Dymaczewo Nowe",
    "wof:placetype":"locality",
    "wof:population":284
},
  "geometry": {"coordinates":[16.75445,52.22938],"type":"Point"}
}