{
  "type": "Feature",
  "properties": {
    "gn:gn_country":"PL",
    "gn:gn_fcode":"PPL",
    "gn:gn_pop":285,
    "gn:population":285,
    "iso:country":"PL",
    "name:cat_x_preferred":[
        "Zduny"
    ],
    "name:deu_x_preferred":[
        "Zduny"
    ],
    "name:epo_x_preferred":[
        "Zduny"
    ],
    "name:fra_x_preferred":[
        "Zduny"
    ],
    "name:jav_x_preferred":[
        "Zduny"
    ],
    "name:lav_x_preferred":[
        "Zduni"
    ],
    "name:msa_x_preferred":[
        "Zduny"
    ],
    "name:nld_x_preferred":[
        "Zduny"
    ],
    "name:pol_x_preferred":[
        "Zduny"
    ],
    "name:por_x_preferred":[
        "Zduny"
    ],
    "name:ron_x_preferred":[
        "Zduny"
    ],
    "name:rus_x_preferred":[
        "\u0417\u0434\u0443\u043d\u044b"
    ],
    "name:slk_x_preferred":[
        "Zduny"
    ],
    "name:srp_x_preferred":[
        "\u0417\u0434\u0443\u043d\u0438"
    ],
    "name:ukr_x_preferred":[
        "\u0417\u0434\u0443\u043d\u0438"
    ],
    "name:vie_x_preferred":[
        "Zduny"
    ],
    "name:zho_x_preferred":[
        "\u8332\u675c\u5167"
    ],
    "qs_pg:aaroncc":"PL",
    "qs_pg:gn_country":"PL",
    "qs_pg:gn_fcode":"PPL",
    "qs_pg:gn_pop":285,
    "qs_pg:name":"Zduny",
    "qs_pg:name_adm0":"Polska",
    "qs_pg:name_adm1":"\u0141\u00f3dzkie",
    "qs_pg:photos_9r":0,
    "qs_pg:photos_sr":0,
    "qs_pg:pop_sr":2,
    "qs_pg:qs_pg_placetype":"locality",
    "qs_pg:qs_pg_placetype_gp":"Town",
    "qs_pg:woe_adm0":23424923,
    "woe:adm0_id":23424923,
    "woe:name_adm0":"Polska",
    "woe:name_adm1":"\u0141\u00f3dzkie",
    "woe:placetype":"Town",
    "wof:name":"Zduny",
    "wof:placetype":"locality",
    "wof:population":285
},
  "geometry": {"coordinates":[19.11887,52.03106],"type":"Point"}
}