{
  "type": "Feature",
  "properties": {
    "gn:admin1_code":"79.0",
    "gn:admin2_code":"1605.0",
    "gn:admin3_code":"160501.0",
    "gn:asciiname":"Obrowiec",
    "gn:country_code":"PL",
    "gn:dem":167,
    "gn:feature_class":"P",
    "gn:feature_code":"PPL",
    "gn:name":"Obrowiec",
    "gn:population":0,
    "gn:timezone":"Europe/Warsaw",
    "iso:country":"PL",
    "name:azb_x_preferred":[
        "\u0627\u0648\u0628\u0631\u0648\u0648\u06cc\u062a\u0633"
    ],
    "name:deu_x_preferred":[
        "Oberwitz"
    ],
    "name:fas_x_preferred":[
        "\u0627\u0648\u0628\u0631\u0648\u0648\u06cc\u062a\u0633"
    ],
    "name:pol_x_preferred":[
        "Obrowiec"
    ],
    "name:ukr_x_preferred":[
        "\u041e\u0431\u0440\u043e\u0432\u0435\u0446\u044c"
    ],
    "wof:name":"Obrowiec",
    "wof:placetype":"locality"
},
  "geometry": {"coordinates":[18.02601,50.46125],"type":"Point"}
}