{
  "type": "Feature",
  "properties": {
    "gn:admin1_code":"82.0",
    "gn:admin2_code":"2216.0",
    "gn:admin3_code":"221605.0",
    "gn:asciiname":"Gronajny",
    "gn:country_code":"PL",
    "gn:dem":48,
    "gn:feature_class":"P",
    "gn:feature_code":"PPL",
    "gn:name":"Gronajny",
    "gn:population":0,
    "gn:timezone":"Europe/Warsaw",
    "iso:country":"PL",
    "name:und_x_variant":[
        "Gr\u00fcnhagen",
        "Gronajny"
    ],
    "wof:name":"Gronajny",
    "wof:placetype":"locality"
},
  "geometry": {"coordinates":[19.05154,53.98151],"type":"Point"}
}