{
  "type": "Feature",
  "properties": {
    "gn:admin1_code":"82.0",
    "gn:admin2_code":"2216.0",
    "gn:admin3_code":"221605.0",
    "gn:asciiname":"Gronajny",
    "gn:country_code":"PL",
    "gn:dem":48,
    "gn:feature_class":"P",
    "gn:feature_code":"PPL",
    "gn:name":"Gronajny",
    "gn:population":0,
    "gn:timezone":"Europe/Warsaw",
    "iso:country":"PL",
    "name:azb_x_preferred":[
        "\u0642\u0631\u0648\u0646\u0627\u06cc\u0646\u0647"
    ],
    "name:ceb_x_preferred":[
        "Gronajny"
    ],
    "name:fas_x_preferred":[
        "\u06af\u0631\u0648\u0646\u0627\u06cc\u0646\u0647"
    ],
    "name:nld_x_preferred":[
        "Gronajny"
    ],
    "name:pol_x_preferred":[
        "Gronajny"
    ],
    "name:ukr_x_preferred":[
        "\u0490\u0440\u043e\u043d\u0430\u0439\u043d\u0438"
    ],
    "name:und_x_variant":[
        "Gr\u00fcnhagen"
    ],
    "wof:name":"Gronajny",
    "wof:placetype":"locality"
},
  "geometry": {"coordinates":[19.05154,53.98151],"type":"Point"}
}