{
  "type": "Feature",
  "properties": {
    "iso:country":"PL",
    "name:azb_x_preferred":[
        "\u0634\u0644\u06a9\u0648\u0648"
    ],
    "name:ceb_x_preferred":[
        "Szelk\u00f3w"
    ],
    "name:deu_x_preferred":[
        "Szelk\u00f3w"
    ],
    "name:fas_x_preferred":[
        "\u0634\u0644\u06a9\u0648\u0648"
    ],
    "name:fra_x_preferred":[
        "Szelk\u00f3w"
    ],
    "name:nld_x_preferred":[
        "Szelk\u00f3w"
    ],
    "name:pol_x_preferred":[
        "Szelk\u00f3w"
    ],
    "name:pol_x_variant":[
        "Stary Szelk\u00f3w"
    ],
    "name:ukr_x_preferred":[
        "\u0421\u0442\u0430\u0440\u0438\u0439 \u0428\u0435\u043b\u044c\u043a\u0443\u0432"
    ],
    "wof:coterminous":[
        1125304225
    ],
    "wof:name":"Szelk\u00f3w",
    "wof:placetype":"locality"
},
  "geometry": {"coordinates":[21.2018701595861,52.8120184692457],"type":"Point"}
}