{
  "type": "Feature",
  "properties": {
    "iso:country":"PL",
    "name:pol_x_preferred":[
        "Szelk\u00f3w"
    ],
    "wof:name":"Szelk\u00f3w",
    "wof:placetype":"locality"
},
  "geometry": {"coordinates":[21.2018701595861,52.8120184692457],"type":"Point"}
}