{
  "type": "Feature",
  "properties": {
    "gn:admin1_code":"86.0",
    "gn:admin2_code":"3028.0",
    "gn:admin3_code":"302807.0",
    "gn:asciiname":"Legowo",
    "gn:country_code":"PL",
    "gn:dem":77,
    "gn:feature_class":"P",
    "gn:feature_code":"PPL",
    "gn:name":"\u0141\u0119gowo",
    "gn:population":0,
    "gn:timezone":"Europe/Warsaw",
    "iso:country":"PL",
    "name:fra_x_preferred":[
        "\u0141\u0119gowo"
    ],
    "name:pol_x_preferred":[
        "\u0141\u0119gowo"
    ],
    "name:ukr_x_preferred":[
        "\u041b\u0435\u043d\u0491\u043e\u0432\u043e"
    ],
    "wof:name":"Legowo",
    "wof:placetype":"locality"
},
  "geometry": {"coordinates":[17.16871,52.78865],"type":"Point"}
}