{
  "type": "Feature",
  "properties": {
    "gn:admin1_code":"81.0",
    "gn:admin2_code":"2003.0",
    "gn:admin3_code":"200308.0",
    "gn:asciiname":"Niewino Poplawskie",
    "gn:country_code":"PL",
    "gn:dem":141,
    "gn:feature_class":"P",
    "gn:feature_code":"PPL",
    "gn:name":"Niewino Pop\u0142awskie",
    "gn:population":0,
    "gn:timezone":"Europe/Warsaw",
    "iso:country":"PL",
    "name:fra_x_preferred":[
        "Niewino Pop\u0142awskie"
    ],
    "name:lit_x_preferred":[
        "Nevino Poplavskiai"
    ],
    "name:pol_x_preferred":[
        "Niewino Pop\u0142awskie"
    ],
    "name:ukr_x_preferred":[
        "\u041d\u0435\u0432\u0456\u043d\u043e-\u041f\u043e\u043f\u043b\u0430\u0432\u0441\u044c\u043a\u0435"
    ],
    "wof:name":"Niewino Poplawskie",
    "wof:placetype":"locality"
},
  "geometry": {"coordinates":[23.05756,52.8273],"type":"Point"}
}