{
  "type": "Feature",
  "properties": {
    "gn:admin1_code":"81.0",
    "gn:admin2_code":"2003.0",
    "gn:admin3_code":"200308.0",
    "gn:asciiname":"Niewino Poplawskie",
    "gn:country_code":"PL",
    "gn:dem":141,
    "gn:feature_class":"P",
    "gn:feature_code":"PPL",
    "gn:name":"Niewino Pop\u0142awskie",
    "gn:population":0,
    "gn:timezone":"Europe/Warsaw",
    "iso:country":"PL",
    "name:und_x_variant":[
        "Niewino Pop\u0142awskie"
    ],
    "wof:name":"Niewino Poplawskie",
    "wof:placetype":"locality"
},
  "geometry": {"coordinates":[23.05756,52.8273],"type":"Point"}
}