{
  "type": "Feature",
  "properties": {
    "gn:admin1_code":"80.0",
    "gn:admin2_code":"1813.0",
    "gn:admin3_code":"181304.0",
    "gn:asciiname":"Tarnawce",
    "gn:country_code":"PL",
    "gn:dem":223,
    "gn:feature_class":"P",
    "gn:feature_code":"PPL",
    "gn:name":"Tarnawce",
    "gn:population":0,
    "gn:timezone":"Europe/Warsaw",
    "iso:country":"PL",
    "name:ceb_x_preferred":[
        "Tarnawce"
    ],
    "name:pol_x_preferred":[
        "Tarnawce"
    ],
    "name:szl_x_preferred":[
        "Tarnawcy"
    ],
    "name:ukr_x_preferred":[
        "\u0422\u0435\u0440\u043d\u0456\u0432\u0446\u0456"
    ],
    "wof:name":"Tarnawce",
    "wof:placetype":"locality"
},
  "geometry": {"coordinates":[22.68168,49.7919],"type":"Point"}
}