{
  "type": "Feature",
  "properties": {
    "gn:admin1_code":"72.0",
    "gn:admin2_code":"224.0",
    "gn:admin3_code":"22406.0",
    "gn:asciiname":"Boznowice",
    "gn:cc2":"PL",
    "gn:country_code":"PL",
    "gn:dem":252,
    "gn:feature_class":"P",
    "gn:feature_code":"PPL",
    "gn:name":"Bo\u017cnowice",
    "gn:population":0,
    "gn:timezone":"Europe/Warsaw",
    "iso:country":"PL",
    "name:azb_x_preferred":[
        "\u0628\u0648\u0698\u0646\u0648\u0648\u06cc\u062a\u0633\u0647"
    ],
    "name:ceb_x_preferred":[
        "Bo\u017cnowice"
    ],
    "name:deu_x_preferred":[
        "Bo\u017cnowice"
    ],
    "name:fas_x_preferred":[
        "\u0628\u0648\u0698\u0646\u0648\u0648\u06cc\u062a\u0633\u0647"
    ],
    "name:nld_x_preferred":[
        "Bo\u017cnowice"
    ],
    "name:pol_x_preferred":[
        "Bo\u017cnowice"
    ],
    "name:ukr_x_preferred":[
        "\u0411\u043e\u0436\u043d\u043e\u0432\u0456\u0446\u0435"
    ],
    "name:und_x_variant":[
        "Berzdorf",
        "Bergdorf"
    ],
    "wof:name":"Boznowice",
    "wof:placetype":"locality"
},
  "geometry": {"coordinates":[17.10915,50.65458],"type":"Point"}
}