{
  "type": "Feature",
  "properties": {
    "gn:admin1_code":"72.0",
    "gn:admin2_code":"224.0",
    "gn:admin3_code":"22406.0",
    "gn:asciiname":"Boznowice",
    "gn:cc2":"PL",
    "gn:country_code":"PL",
    "gn:dem":252,
    "gn:feature_class":"P",
    "gn:feature_code":"PPL",
    "gn:name":"Bo\u017cnowice",
    "gn:population":0,
    "gn:timezone":"Europe/Warsaw",
    "iso:country":"PL",
    "name:und_x_variant":[
        "Berzdorf",
        "Bergdorf",
        "Bo\u017cnowice"
    ],
    "wof:name":"Boznowice",
    "wof:placetype":"locality"
},
  "geometry": {"coordinates":[17.10915,50.65458],"type":"Point"}
}