{
  "type": "Feature",
  "properties": {
    "gn:admin1_code":"78.0",
    "gn:admin2_code":"1436.0",
    "gn:admin3_code":"143605.0",
    "gn:asciiname":"Jasieniec Solecki",
    "gn:country_code":"PL",
    "gn:dem":164,
    "gn:feature_class":"P",
    "gn:feature_code":"PPL",
    "gn:name":"Jasieniec Solecki",
    "gn:population":0,
    "gn:timezone":"Europe/Warsaw",
    "iso:country":"PL",
    "name:azb_x_preferred":[
        "\u06cc\u0627\u0634\u0646\u0642\u062a\u0633 \u0633\u0648\u0644\u062a\u0633\u06a9\u06cc"
    ],
    "name:ceb_x_preferred":[
        "Jasieniec Solecki"
    ],
    "name:fas_x_preferred":[
        "\u06cc\u0627\u0634\u0646\u06af\u062a\u0633 \u0633\u0648\u0644\u062a\u0633\u06a9\u06cc"
    ],
    "name:fra_x_preferred":[
        "Jasieniec Solecki"
    ],
    "name:pol_x_preferred":[
        "Jasieniec Solecki"
    ],
    "name:ukr_x_preferred":[
        "\u042f\u0441\u0435\u043d\u0435\u0446\u044c-\u0421\u043e\u043b\u0435\u0446\u044c\u043a\u0438\u0439"
    ],
    "name:urd_x_preferred":[
        "\u062c\u0633\u06cc\u0646\u06cc\u06a9 \u0633\u0648\u0644\u06a9\u06a9\u06cc"
    ],
    "wof:name":"Jasieniec Solecki",
    "wof:placetype":"locality"
},
  "geometry": {"coordinates":[21.61515,51.29201],"type":"Point"}
}