{
  "type": "Feature",
  "properties": {
    "gn:admin1_code":"78.0",
    "gn:admin2_code":"1436.0",
    "gn:admin3_code":"143605.0",
    "gn:asciiname":"Jasieniec Solecki",
    "gn:country_code":"PL",
    "gn:dem":164,
    "gn:feature_class":"P",
    "gn:feature_code":"PPL",
    "gn:name":"Jasieniec Solecki",
    "gn:population":0,
    "gn:timezone":"Europe/Warsaw",
    "iso:country":"PL",
    "wof:name":"Jasieniec Solecki",
    "wof:placetype":"locality"
},
  "geometry": {"coordinates":[21.61515,51.29201],"type":"Point"}
}