{
  "type": "Feature",
  "properties": {
    "gn:admin1_code":"87.0",
    "gn:admin2_code":"3209.0",
    "gn:admin3_code":"320907.0",
    "gn:asciiname":"Ratajki",
    "gn:country_code":"PL",
    "gn:dem":55,
    "gn:feature_class":"P",
    "gn:feature_code":"PPL",
    "gn:name":"Ratajki",
    "gn:population":0,
    "gn:timezone":"Europe/Warsaw",
    "iso:country":"PL",
    "name:und_x_variant":[
        "Ratteick",
        "Ratajki"
    ],
    "wof:name":"Ratajki",
    "wof:placetype":"locality"
},
  "geometry": {"coordinates":[16.46307,54.20988000000001],"type":"Point"}
}