{
  "type": "Feature",
  "properties": {
    "gn:admin1_code":"81.0",
    "gn:admin2_code":"2002.0",
    "gn:admin3_code":"200212.0",
    "gn:asciiname":"Nieciece",
    "gn:country_code":"PL",
    "gn:dem":105,
    "gn:feature_class":"P",
    "gn:feature_code":"PPL",
    "gn:name":"Nieciece",
    "gn:population":0,
    "gn:timezone":"Europe/Warsaw",
    "iso:country":"PL",
    "name:eng_x_preferred":[
        "Nieciece"
    ],
    "name:lit_x_preferred":[
        "Necec\u0117"
    ],
    "name:pol_x_preferred":[
        "Nieciece"
    ],
    "name:rus_x_preferred":[
        "\u041d\u0435\u0446\u0435\u0446\u0435"
    ],
    "name:ukr_x_preferred":[
        "\u041d\u0435\u0446\u0435\u0446\u0435"
    ],
    "wof:name":"Nieciece",
    "wof:placetype":"locality"
},
  "geometry": {"coordinates":[22.67713,53.20778000000001],"type":"Point"}
}