{
  "type": "Feature",
  "properties": {
    "gn:country":"PL",
    "gn:fcode":"PPL",
    "gn:population":316,
    "iso:country":"PL",
    "name:ast_x_preferred":[
        "Osina"
    ],
    "name:ceb_x_preferred":[
        "Osina"
    ],
    "name:ces_x_preferred":[
        "Osina"
    ],
    "name:che_x_preferred":[
        "\u041e\u0441\u0438\u043d\u0430"
    ],
    "name:eng_x_preferred":[
        "Osina"
    ],
    "name:fra_x_preferred":[
        "Osina"
    ],
    "name:ido_x_preferred":[
        "Osina"
    ],
    "name:nan_x_preferred":[
        "Osina"
    ],
    "name:pol_x_preferred":[
        "Osina"
    ],
    "name:tat_x_preferred":[
        "\u041e\u0441\u0438\u043d\u0430"
    ],
    "name:ukr_x_preferred":[
        "\u041e\u0441\u0456\u043d\u0430"
    ],
    "qs_pg:aaroncc":"PL",
    "qs_pg:gn_country":"PL",
    "qs_pg:gn_fcode":"PPL",
    "qs_pg:gn_pop":316,
    "qs_pg:name":"Osina",
    "qs_pg:name_adm0":"Polska",
    "qs_pg:name_adm1":"\u0141\u00f3dzkie",
    "qs_pg:photos_9r":0,
    "qs_pg:photos_sr":0,
    "qs_pg:pop_sr":2,
    "qs_pg:qs_pg_placetype":"locality",
    "qs_pg:qs_pg_placetype_gp":"Town",
    "qs_pg:woe_adm0":23424923,
    "woe:adm0_id":23424923,
    "woe:name_adm0":"Polska",
    "woe:name_adm1":"\u0141\u00f3dzkie",
    "woe:placetype":"Town",
    "wof:name":"Osina",
    "wof:placetype":"locality",
    "wof:population":316
},
  "geometry": {"coordinates":[19.1835,51.35265],"type":"Point"}
}