{
  "type": "Feature",
  "properties": {
    "gn:admin1_code":"75.0",
    "gn:admin2_code":"611.0",
    "gn:admin3_code":"61108.0",
    "gn:asciiname":"Kienkowka",
    "gn:country_code":"PL",
    "gn:dem":187,
    "gn:feature_class":"P",
    "gn:feature_code":"PPL",
    "gn:name":"Kienk\u00f3wka",
    "gn:population":0,
    "gn:timezone":"Europe/Warsaw",
    "iso:country":"PL",
    "name:fra_x_preferred":[
        "Kienk\u00f3wka"
    ],
    "name:pol_x_preferred":[
        "Kienk\u00f3wka"
    ],
    "name:ukr_x_preferred":[
        "\u041a\u0435\u043d\u043a\u0443\u0432\u043a\u0430"
    ],
    "wof:name":"Kienkowka",
    "wof:placetype":"locality"
},
  "geometry": {"coordinates":[21.88339,51.94966],"type":"Point"}
}