{
  "type": "Feature",
  "properties": {
    "gn:admin1_code":"80.0",
    "gn:admin2_code":"1807.0",
    "gn:admin3_code":"180702.0",
    "gn:asciiname":"Nowa Wies",
    "gn:country_code":"PL",
    "gn:dem":350,
    "gn:feature_class":"P",
    "gn:feature_code":"PPL",
    "gn:name":"Nowa Wie\u015b",
    "gn:population":0,
    "gn:timezone":"Europe/Warsaw",
    "iso:country":"PL",
    "wof:name":"Nowa Wies",
    "wof:placetype":"locality"
},
  "geometry": {"coordinates":[21.69333,49.52704],"type":"Point"}
}