{
  "type": "Feature",
  "properties": {
    "gn:admin1_code":"86.0",
    "gn:admin2_code":"3014.0",
    "gn:admin3_code":"301404.0",
    "gn:asciiname":"Lutomek",
    "gn:country_code":"PL",
    "gn:dem":61,
    "gn:feature_class":"P",
    "gn:feature_code":"PPL",
    "gn:name":"Lutomek",
    "gn:population":0,
    "gn:timezone":"Europe/Warsaw",
    "iso:country":"PL",
    "name:azb_x_preferred":[
        "\u0644\u0648\u062a\u0648\u0645\u06a9"
    ],
    "name:ceb_x_preferred":[
        "Lutomek"
    ],
    "name:fas_x_preferred":[
        "\u0644\u0648\u062a\u0648\u0645\u06a9"
    ],
    "name:fra_x_preferred":[
        "Lutomek"
    ],
    "name:nld_x_preferred":[
        "Lutomek"
    ],
    "name:pol_x_preferred":[
        "Lutomek"
    ],
    "name:ukr_x_preferred":[
        "\u041b\u044e\u0442\u043e\u043c\u0435\u043a"
    ],
    "wof:name":"Lutomek",
    "wof:placetype":"locality"
},
  "geometry": {"coordinates":[16.14905,52.60324],"type":"Point"}
}