{
  "type": "Feature",
  "properties": {
    "gn:admin1_code":"86.0",
    "gn:admin2_code":"3014.0",
    "gn:admin3_code":"301404.0",
    "gn:asciiname":"Lutomek",
    "gn:country_code":"PL",
    "gn:dem":61,
    "gn:feature_class":"P",
    "gn:feature_code":"PPL",
    "gn:name":"Lutomek",
    "gn:population":0,
    "gn:timezone":"Europe/Warsaw",
    "iso:country":"PL",
    "wof:name":"Lutomek",
    "wof:placetype":"locality"
},
  "geometry": {"coordinates":[16.14905,52.60324],"type":"Point"}
}