{
  "type": "Feature",
  "properties": {
    "gn:admin1_code":"77.0",
    "gn:admin2_code":"1216.0",
    "gn:admin3_code":"121614.0",
    "gn:asciiname":"Wola Stroska",
    "gn:country_code":"PL",
    "gn:dem":292,
    "gn:feature_class":"P",
    "gn:feature_code":"PPL",
    "gn:name":"Wola Str\u00f3ska",
    "gn:population":0,
    "gn:timezone":"Europe/Warsaw",
    "iso:country":"PL",
    "name:pol_x_preferred":[
        "Wola Str\u00f3ska"
    ],
    "name:ukr_x_preferred":[
        "\u0412\u043e\u043b\u044f-\u0421\u0442\u0440\u0443\u0441\u044c\u043a\u0430"
    ],
    "name:und_x_variant":[
        "Wola St\u00f3ska",
        "Wola Str\u00f3\u017cka"
    ],
    "wof:name":"Wola Stroska",
    "wof:placetype":"locality"
},
  "geometry": {"coordinates":[20.77089,49.83089],"type":"Point"}
}