{
  "type": "Feature",
  "properties": {
    "gn:admin1_code":"84.0",
    "gn:admin2_code":"2604.0",
    "gn:admin3_code":"260404.0",
    "gn:asciiname":"Szyszczyce",
    "gn:country_code":"PL",
    "gn:dem":222,
    "gn:feature_class":"P",
    "gn:feature_code":"PPL",
    "gn:name":"Szyszczyce",
    "gn:population":0,
    "gn:timezone":"Europe/Warsaw",
    "iso:country":"PL",
    "name:und_x_variant":[
        "Szyszozyce",
        "Szyszczyce"
    ],
    "wof:name":"Szyszczyce",
    "wof:placetype":"locality"
},
  "geometry": {"coordinates":[20.7758,50.58333],"type":"Point"}
}