{
  "type": "Feature",
  "properties": {
    "gn:admin1_code":"84.0",
    "gn:admin2_code":"2605.0",
    "gn:admin3_code":"260508.0",
    "gn:asciiname":"Wolow",
    "gn:country_code":"PL",
    "gn:dem":265,
    "gn:feature_class":"P",
    "gn:feature_code":"PPL",
    "gn:name":"Wo\u0142\u00f3w",
    "gn:population":0,
    "gn:timezone":"Europe/Warsaw",
    "iso:country":"PL",
    "wof:name":"Wolow",
    "wof:placetype":"locality"
},
  "geometry": {"coordinates":[20.58924,51.13657],"type":"Point"}
}