{
  "type": "Feature",
  "properties": {
    "gn:admin1_code":"75.0",
    "gn:admin2_code":"663.0",
    "gn:admin3_code":"66301.0",
    "gn:asciiname":"Czechowka Gorna",
    "gn:country_code":"PL",
    "gn:dem":213,
    "gn:feature_class":"P",
    "gn:feature_code":"PPL",
    "gn:name":"Czechowka G\u00f3rna",
    "gn:population":0,
    "gn:timezone":"Europe/Warsaw",
    "iso:country":"PL",
    "wof:name":"Czechowka Gorna",
    "wof:placetype":"locality"
},
  "geometry": {"coordinates":[22.55,51.27581],"type":"Point"}
}