{
  "type": "Feature",
  "properties": {
    "gn:admin1_code":"78.0",
    "gn:admin2_code":"1434.0",
    "gn:admin3_code":"143411.0",
    "gn:asciiname":"Mokra Wies",
    "gn:country_code":"PL",
    "gn:dem":104,
    "gn:feature_class":"P",
    "gn:feature_code":"PPL",
    "gn:name":"Mokra Wie\u015b",
    "gn:population":0,
    "gn:timezone":"Europe/Warsaw",
    "iso:country":"PL",
    "name:fra_x_preferred":[
        "Mokra Wie\u015b"
    ],
    "name:pol_x_preferred":[
        "Mokra Wie\u015b"
    ],
    "name:ukr_x_preferred":[
        "\u041c\u043e\u043a\u0440\u0430-\u0412\u0435\u0441\u044c"
    ],
    "wof:name":"Mokra Wies",
    "wof:placetype":"locality"
},
  "geometry": {"coordinates":[21.5096,52.46706],"type":"Point"}
}