{
  "type": "Feature",
  "properties": {
    "gn:admin1_code":"74.0",
    "gn:admin2_code":"1020.0",
    "gn:admin3_code":"102004.0",
    "gn:asciiname":"Ksiestwo",
    "gn:country_code":"PL",
    "gn:dem":173,
    "gn:feature_class":"P",
    "gn:feature_code":"PPL",
    "gn:name":"Ksi\u0119stwo",
    "gn:population":0,
    "gn:timezone":"Europe/Warsaw",
    "iso:country":"PL",
    "name:ceb_x_preferred":[
        "Ksi\u0119stwo"
    ],
    "name:pol_x_preferred":[
        "Ksi\u0119stwo"
    ],
    "name:ukr_x_preferred":[
        "\u041a\u0441\u0435\u043d\u0441\u0442\u0432\u043e"
    ],
    "wof:name":"Ksiestwo",
    "wof:placetype":"locality"
},
  "geometry": {"coordinates":[19.30321,51.84479],"type":"Point"}
}