{
  "type": "Feature",
  "properties": {
    "gn:admin1_code":"82.0",
    "gn:admin2_code":"2212.0",
    "gn:admin3_code":"221205.0",
    "gn:asciiname":"Mzdowo",
    "gn:country_code":"PL",
    "gn:dem":119,
    "gn:feature_class":"P",
    "gn:feature_code":"PPL",
    "gn:name":"Mzdowo",
    "gn:population":0,
    "gn:timezone":"Europe/Warsaw",
    "iso:country":"PL",
    "wof:name":"Mzdowo",
    "wof:placetype":"locality"
},
  "geometry": {"coordinates":[16.7787,54.15201],"type":"Point"}
}