{
  "type": "Feature",
  "properties": {
    "gn:admin1_code":"82.0",
    "gn:admin2_code":"2212.0",
    "gn:admin3_code":"221205.0",
    "gn:asciiname":"Mzdowo",
    "gn:country_code":"PL",
    "gn:dem":119,
    "gn:feature_class":"P",
    "gn:feature_code":"PPL",
    "gn:name":"Mzdowo",
    "gn:population":0,
    "gn:timezone":"Europe/Warsaw",
    "iso:country":"PL",
    "name:ceb_x_preferred":[
        "Mzdowo"
    ],
    "name:csb_x_preferred":[
        "Mzdow\u00f2"
    ],
    "name:nld_x_preferred":[
        "Mzdowo"
    ],
    "name:pol_x_preferred":[
        "Mzdowo"
    ],
    "name:ukr_x_preferred":[
        "\u041c\u0437\u0434\u043e\u0432\u043e"
    ],
    "wof:name":"Mzdowo",
    "wof:placetype":"locality"
},
  "geometry": {"coordinates":[16.7787,54.15201],"type":"Point"}
}