{
  "type": "Feature",
  "properties": {
    "gn:admin1_code":"81.0",
    "gn:admin2_code":"2009.0",
    "gn:admin3_code":"200903.0",
    "gn:asciiname":"Smolany Dab",
    "gn:country_code":"PL",
    "gn:dem":135,
    "gn:feature_class":"P",
    "gn:feature_code":"PPL",
    "gn:name":"Smolany D\u0105b",
    "gn:population":0,
    "gn:timezone":"Europe/Warsaw",
    "iso:country":"PL",
    "name:und_x_variant":[
        "Smolany D\u0105b"
    ],
    "wof:name":"Smolany Dab",
    "wof:placetype":"locality"
},
  "geometry": {"coordinates":[23.19243,54.09295],"type":"Point"}
}