{
  "type": "Feature",
  "properties": {
    "gn:admin1_code":"81.0",
    "gn:admin2_code":"2009.0",
    "gn:admin3_code":"200903.0",
    "gn:asciiname":"Smolany Dab",
    "gn:country_code":"PL",
    "gn:dem":135,
    "gn:feature_class":"P",
    "gn:feature_code":"PPL",
    "gn:name":"Smolany D\u0105b",
    "gn:population":0,
    "gn:timezone":"Europe/Warsaw",
    "iso:country":"PL",
    "name:lit_x_preferred":[
        "Smal\u0117n\u0173 Dombas"
    ],
    "name:pol_x_preferred":[
        "Smolany D\u0105b"
    ],
    "name:ukr_x_preferred":[
        "\u0421\u043c\u043e\u043b\u044f\u043d\u0438-\u0414\u043e\u043c\u0431"
    ],
    "name:und_x_variant":[
        "Smolany D\u0105b"
    ],
    "wof:name":"Smolany Dab",
    "wof:placetype":"locality"
},
  "geometry": {"coordinates":[23.19243,54.09295],"type":"Point"}
}