{
  "type": "Feature",
  "properties": {
    "gn:admin1_code":"79.0",
    "gn:admin2_code":"1606.0",
    "gn:admin3_code":"160602.0",
    "gn:asciiname":"Rychnow",
    "gn:country_code":"PL",
    "gn:dem":172,
    "gn:feature_class":"P",
    "gn:feature_code":"PPL",
    "gn:name":"Rychn\u00f3w",
    "gn:population":0,
    "gn:timezone":"Europe/Warsaw",
    "iso:country":"PL",
    "name:und_x_variant":[
        "Rychn\u00f3w"
    ],
    "wof:name":"Rychnow",
    "wof:placetype":"locality"
},
  "geometry": {"coordinates":[17.78635,51.07826],"type":"Point"}
}