{
  "type": "Feature",
  "properties": {
    "gn:admin1_code":"84.0",
    "gn:admin2_code":"2612.0",
    "gn:admin3_code":"261207.0",
    "gn:asciiname":"Sztombergi",
    "gn:country_code":"PL",
    "gn:dem":219,
    "gn:feature_class":"P",
    "gn:feature_code":"PPL",
    "gn:name":"Sztombergi",
    "gn:population":0,
    "gn:timezone":"Europe/Warsaw",
    "iso:country":"PL",
    "name:pol_x_preferred":[
        "Sztombergi"
    ],
    "name:ukr_x_preferred":[
        "\u0428\u0442\u043e\u043c\u0431\u0435\u0440\u0491\u0456"
    ],
    "name:und_x_variant":[
        "Kolonia Sztamberg\u00f3w",
        "Sztomberg\u00f3w"
    ],
    "wof:name":"Sztombergi",
    "wof:placetype":"locality"
},
  "geometry": {"coordinates":[21.21439,50.60896],"type":"Point"}
}