{
  "type": "Feature",
  "properties": {
    "iso:country":"PL",
    "name:azb_x_preferred":[
        "\u0644\u06cc\u067e\u06cc\u0646\u0633\u0627 \u0645\u0648\u0631\u0648\u0648\u0627\u0646\u0627"
    ],
    "name:ceb_x_preferred":[
        "Lipnica Murowana"
    ],
    "name:deu_x_preferred":[
        "Lipnica Murowana"
    ],
    "name:fas_x_preferred":[
        "\u0644\u06cc\u067e\u06cc\u0646\u0633\u0627 \u0645\u0648\u0631\u0648\u0648\u0627\u0646\u0627"
    ],
    "name:nld_x_preferred":[
        "Lipnica Murowana"
    ],
    "name:pol_x_preferred":[
        "Lipnica Murowana"
    ],
    "name:ukr_x_preferred":[
        "\u041b\u0456\u043f\u043d\u0438\u0446\u044f-\u041c\u0443\u0440\u043e\u0432\u0430\u043d\u0430"
    ],
    "name:vie_x_preferred":[
        "Lipnica Murowana"
    ],
    "qs_pg:aaroncc":"PL",
    "qs_pg:name":"Lipnica Murowana",
    "qs_pg:name_adm0":"Polska",
    "qs_pg:name_adm1":"Ma\u0142opolskie",
    "qs_pg:photos":1,
    "qs_pg:photos_1k":1,
    "qs_pg:photos_9k":1,
    "qs_pg:photos_9r":1,
    "qs_pg:photos_all":6,
    "qs_pg:photos_sr":1,
    "qs_pg:pop_sr":0,
    "qs_pg:qs_pg_placetype":"localadmin",
    "qs_pg:qs_pg_placetype_gp":"LocalAdmin",
    "qs_pg:woe_adm0":23424923,
    "woe:adm0_id":23424923,
    "woe:name_adm0":"Polska",
    "woe:name_adm1":"Ma\u0142opolskie",
    "woe:placetype":"LocalAdmin",
    "wof:name":"Lipnica Murowana",
    "wof:placetype":"localadmin"
},
  "geometry": {"coordinates":[20.478,49.850602],"type":"Point"}
}