{
  "type": "Feature",
  "properties": {
    "iso:country":"PL",
    "name:bel_x_preferred":[
        "\u041a\u0443\u0442\u043d\u0430"
    ],
    "name:bul_x_preferred":[
        "\u041a\u0443\u0442\u043d\u043e"
    ],
    "name:ceb_x_preferred":[
        "Kutno"
    ],
    "name:ces_x_preferred":[
        "Kutno"
    ],
    "name:dan_x_preferred":[
        "Kutno"
    ],
    "name:deu_x_preferred":[
        "Kutno"
    ],
    "name:dsb_x_preferred":[
        "Kutno"
    ],
    "name:epo_x_preferred":[
        "Kutno"
    ],
    "name:eus_x_preferred":[
        "Kutno"
    ],
    "name:fas_x_preferred":[
        "\u06a9\u0648\u062a\u0646\u0648"
    ],
    "name:fin_x_preferred":[
        "Kutno"
    ],
    "name:fra_x_preferred":[
        "Kutno"
    ],
    "name:heb_x_preferred":[
        "\u05e7\u05d5\u05d8\u05e0\u05d5"
    ],
    "name:ind_x_preferred":[
        "Kutno"
    ],
    "name:ita_x_preferred":[
        "Kutno"
    ],
    "name:jav_x_preferred":[
        "Kutno"
    ],
    "name:kor_x_preferred":[
        "\ucfe0\ud2b8\ub178"
    ],
    "name:lav_x_preferred":[
        "Kutno"
    ],
    "name:lit_x_preferred":[
        "Kutnas"
    ],
    "name:msa_x_preferred":[
        "Kutno"
    ],
    "name:nld_x_preferred":[
        "Kutno"
    ],
    "name:nor_x_preferred":[
        "Kutno"
    ],
    "name:pol_x_preferred":[
        "Kutno"
    ],
    "name:por_x_preferred":[
        "Kutno"
    ],
    "name:ron_x_preferred":[
        "Kutno"
    ],
    "name:rus_x_preferred":[
        "\u041a\u0443\u0442\u043d\u043e"
    ],
    "name:sco_x_preferred":[
        "Kutno"
    ],
    "name:slk_x_preferred":[
        "Kutno"
    ],
    "name:spa_x_preferred":[
        "Kutno"
    ],
    "name:srp_x_preferred":[
        "\u041a\u0443\u0442\u043d\u043e"
    ],
    "name:swe_x_preferred":[
        "Kutno"
    ],
    "name:szl_x_preferred":[
        "Kutno"
    ],
    "name:tur_x_preferred":[
        "Kutno"
    ],
    "name:ukr_x_preferred":[
        "\u041a\u0443\u0442\u043d\u043e"
    ],
    "name:vie_x_preferred":[
        "Kutno"
    ],
    "name:war_x_preferred":[
        "Kutno"
    ],
    "name:zho_x_preferred":[
        "\u5e93\u7279\u5a1c"
    ],
    "qs_pg:aaroncc":"PL",
    "qs_pg:name":"Kutno",
    "qs_pg:name_adm0":"Polska",
    "qs_pg:name_adm1":"\u0141\u00f3dzkie",
    "qs_pg:photos":1,
    "qs_pg:photos_1k":1,
    "qs_pg:photos_9k":1,
    "qs_pg:photos_9r":1,
    "qs_pg:photos_all":1,
    "qs_pg:photos_sr":1,
    "qs_pg:pop_sr":0,
    "qs_pg:qs_pg_placetype":"localadmin",
    "qs_pg:qs_pg_placetype_gp":"LocalAdmin",
    "qs_pg:woe_adm0":23424923,
    "woe:adm0_id":23424923,
    "woe:name_adm0":"Polska",
    "woe:name_adm1":"\u0141\u00f3dzkie",
    "woe:placetype":"LocalAdmin",
    "wof:name":"Kutno",
    "wof:placetype":"localadmin"
},
  "geometry": {"coordinates":[19.373874,52.239705],"type":"Point"}
}