{
  "type": "Feature",
  "properties": {
    "gn:admin1_code":"74.0",
    "gn:admin2_code":"1003.0",
    "gn:admin3_code":"100303.0",
    "gn:asciiname":"Brzeski",
    "gn:country_code":"PL",
    "gn:dem":160,
    "gn:feature_class":"P",
    "gn:feature_code":"PPL",
    "gn:name":"Brzeski",
    "gn:population":0,
    "gn:timezone":"Europe/Warsaw",
    "iso:country":"PL",
    "name:fra_x_preferred":[
        "Brzeski"
    ],
    "name:pol_x_preferred":[
        "Brzeski"
    ],
    "name:ukr_x_preferred":[
        "\u0411\u0436\u0435\u0441\u043a\u0456"
    ],
    "name:urd_x_preferred":[
        "\u0628\u0631\u0632\u0633\u06a9\u06cc"
    ],
    "wof:name":"Brzeski",
    "wof:placetype":"locality"
},
  "geometry": {"coordinates":[18.96321,51.52098],"type":"Point"}
}