{
  "type": "Feature",
  "properties": {
    "gn:admin1_code":"73.0",
    "gn:admin2_code":"413.0",
    "gn:admin3_code":"41304.0",
    "gn:asciiname":"Peperzyn",
    "gn:country_code":"PL",
    "gn:dem":113,
    "gn:feature_class":"P",
    "gn:feature_code":"PPL",
    "gn:name":"P\u0119perzyn",
    "gn:population":0,
    "gn:timezone":"Europe/Warsaw",
    "iso:country":"PL",
    "name:und_x_variant":[
        "P\u0119perzyn"
    ],
    "wof:name":"Peperzyn",
    "wof:placetype":"locality"
},
  "geometry": {"coordinates":[17.5499,53.30314],"type":"Point"}
}