{
  "type": "Feature",
  "properties": {
    "gn:gn_country":"PL",
    "gn:gn_fcode":"PPLA3",
    "gn:gn_pop":4252,
    "gn:population":4252,
    "iso:country":"PL",
    "name:ceb_x_preferred":[
        "Ch\u0119ciny"
    ],
    "name:deu_x_preferred":[
        "Ch\u0119ciny"
    ],
    "name:epo_x_preferred":[
        "Ch\u0119ciny"
    ],
    "name:fra_x_preferred":[
        "Ch\u0119ciny"
    ],
    "name:hak_x_preferred":[
        "Ch\u0119ciny"
    ],
    "name:heb_x_preferred":[
        "\u05d7\u05e0\u05d8\u05e9\u05d9\u05df"
    ],
    "name:jav_x_preferred":[
        "Ch\u0119ciny"
    ],
    "name:lav_x_preferred":[
        "Hencini"
    ],
    "name:msa_x_preferred":[
        "Ch\u0119ciny"
    ],
    "name:nld_x_preferred":[
        "Ch\u0119ciny"
    ],
    "name:pol_x_preferred":[
        "Ch\u0119ciny"
    ],
    "name:por_x_preferred":[
        "Ch\u0119ciny"
    ],
    "name:ron_x_preferred":[
        "Ch\u0119ciny"
    ],
    "name:rus_x_preferred":[
        "\u0425\u0435\u043d\u0446\u0438\u043d\u044b"
    ],
    "name:slk_x_preferred":[
        "Ch\u0119ciny"
    ],
    "name:srp_x_preferred":[
        "\u0425\u0435\u043d\u045b\u0438\u043d\u0438"
    ],
    "name:ukr_x_preferred":[
        "\u0425\u0435\u043d\u0446\u0438\u043d\u0438"
    ],
    "name:vie_x_preferred":[
        "Ch\u0119ciny"
    ],
    "name:yid_x_preferred":[
        "\u05db\u05e2\u05e0\u05d8\u05e9\u05d9\u05df"
    ],
    "name:zho_x_preferred":[
        "\u4ea8\u9f4a\u5167"
    ],
    "qs_pg:aaroncc":"PL",
    "qs_pg:gn_country":"PL",
    "qs_pg:gn_fcode":"PPLA3",
    "qs_pg:gn_pop":4252,
    "qs_pg:name":"Ch\u0119ciny",
    "qs_pg:name_adm0":"Polska",
    "qs_pg:name_adm1":"Swi\u0119tokrzyskie",
    "qs_pg:photos":413,
    "qs_pg:photos_1k":84,
    "qs_pg:photos_9k":2,
    "qs_pg:photos_9r":5,
    "qs_pg:photos_all":413,
    "qs_pg:photos_sr":6,
    "qs_pg:pop_sr":4,
    "qs_pg:qs_pg_placetype":"localadmin",
    "qs_pg:qs_pg_placetype_gp":"LocalAdmin",
    "qs_pg:woe_adm0":23424923,
    "woe:adm0_id":23424923,
    "woe:name_adm0":"Polska",
    "woe:name_adm1":"Swi\u0119tokrzyskie",
    "woe:placetype":"LocalAdmin",
    "wof:name":"Ch\u0119ciny",
    "wof:placetype":"localadmin",
    "wof:population":4252
},
  "geometry": {"coordinates":[20.46229,50.80021],"type":"Point"}
}