{
  "type": "Feature",
  "properties": {
    "gn:admin1_code":"78.0",
    "gn:admin2_code":"1410.0",
    "gn:admin3_code":"141004.0",
    "gn:asciiname":"Falatycze",
    "gn:country_code":"PL",
    "gn:dem":158,
    "gn:feature_class":"P",
    "gn:feature_code":"PPL",
    "gn:name":"Falatycze",
    "gn:population":0,
    "gn:timezone":"Europe/Warsaw",
    "iso:country":"PL",
    "name:azb_x_preferred":[
        "\u0641\u0627\u0644\u0627\u062a\u0686\u0647"
    ],
    "name:ceb_x_preferred":[
        "Falatycze"
    ],
    "name:fas_x_preferred":[
        "\u0641\u0627\u0644\u0627\u062a\u0686\u0647"
    ],
    "name:fra_x_preferred":[
        "Falatycze"
    ],
    "name:lit_x_preferred":[
        "Falati\u010d\u0117"
    ],
    "name:pol_x_preferred":[
        "Falatycze"
    ],
    "name:ukr_x_preferred":[
        "\u0424\u0430\u043b\u044f\u0442\u0438\u0447\u0435"
    ],
    "name:urd_x_preferred":[
        "\u0641\u0627\u0644\u0627\u0679\u06cc\u06a9\u0632\u06cc"
    ],
    "wof:name":"Falatycze",
    "wof:placetype":"locality"
},
  "geometry": {"coordinates":[22.82401,52.22334],"type":"Point"}
}