{
  "type": "Feature",
  "properties": {
    "gn:admin1_code":"84.0",
    "gn:admin2_code":"2610.0",
    "gn:admin3_code":"261003.0",
    "gn:asciiname":"Oselkow",
    "gn:country_code":"PL",
    "gn:dem":302,
    "gn:feature_class":"P",
    "gn:feature_code":"PPL",
    "gn:name":"Ose\u0142k\u00f3w",
    "gn:population":0,
    "gn:timezone":"Europe/Warsaw",
    "iso:country":"PL",
    "name:pol_x_preferred":[
        "Ose\u0142k\u00f3w"
    ],
    "wof:name":"Oselkow",
    "wof:placetype":"locality"
},
  "geometry": {"coordinates":[20.78794,51.00285],"type":"Point"}
}