{
  "type": "Feature",
  "properties": {
    "gn:admin1_code":"73.0",
    "gn:admin2_code":"464.0",
    "gn:admin3_code":"46401.0",
    "gn:asciiname":"Korabniki",
    "gn:country_code":"PL",
    "gn:dem":44,
    "gn:feature_class":"P",
    "gn:feature_code":"PPL",
    "gn:name":"Korabniki",
    "gn:population":0,
    "gn:timezone":"Europe/Warsaw",
    "iso:country":"PL",
    "wof:name":"Korabniki",
    "wof:placetype":"neighbourhood"
},
  "geometry": {"coordinates":[18.99758,52.69472],"type":"Point"}
}