{
  "type": "Feature",
  "properties": {
    "gn:admin1_code":"85.0",
    "gn:admin2_code":"2818.0",
    "gn:admin3_code":"281803.0",
    "gn:asciiname":"Wilkasy",
    "gn:country_code":"PL",
    "gn:dem":226,
    "gn:feature_class":"P",
    "gn:feature_code":"PPL",
    "gn:name":"Wilkasy",
    "gn:population":0,
    "gn:timezone":"Europe/Warsaw",
    "iso:country":"PL",
    "name:deu_x_preferred":[
        "Wilkasy"
    ],
    "name:nld_x_preferred":[
        "Wilkasy"
    ],
    "name:pol_x_preferred":[
        "Wilkasy"
    ],
    "name:ukr_x_preferred":[
        "\u0412\u0456\u043b\u044c\u043a\u0430\u0441\u0438"
    ],
    "name:und_x_variant":[
        "Brunshof",
        "Wilkassen",
        "Kleineichicht"
    ],
    "wof:name":"Wilkasy",
    "wof:placetype":"locality"
},
  "geometry": {"coordinates":[22.37263,54.21103000000001],"type":"Point"}
}