{
  "type": "Feature",
  "properties": {
    "gn:admin1_code":"82.0",
    "gn:admin2_code":"2203.0",
    "gn:admin3_code":"220305.0",
    "gn:asciiname":"Lekinia",
    "gn:country_code":"PL",
    "gn:dem":167,
    "gn:feature_class":"P",
    "gn:feature_code":"PPL",
    "gn:name":"\u0141\u0119kinia",
    "gn:population":0,
    "gn:timezone":"Europe/Warsaw",
    "iso:country":"PL",
    "name:ceb_x_preferred":[
        "\u0141\u0119kinia"
    ],
    "name:csb_x_preferred":[
        "\u0141\u00e3czini\u00f4"
    ],
    "name:nld_x_preferred":[
        "\u0141\u0119kinia"
    ],
    "name:pol_x_preferred":[
        "\u0141\u0119kinia"
    ],
    "name:ukr_x_preferred":[
        "\u041b\u0435\u043d\u043a\u0456\u043d\u044f"
    ],
    "wof:name":"Lekinia",
    "wof:placetype":"locality"
},
  "geometry": {"coordinates":[17.02005,53.90393],"type":"Point"}
}