{
  "type": "Feature",
  "properties": {
    "gn:country":"PL",
    "gn:fcode":"PPL",
    "gn:population":136,
    "iso:country":"PL",
    "name:ast_x_preferred":[
        "S\u0142upia Nadbrze\u017cna-Kolonia"
    ],
    "name:ceb_x_preferred":[
        "S\u0142upia Nadbrze\u017cna-Kolonia"
    ],
    "name:eng_x_preferred":[
        "S\u0142upia Nadbrze\u017cna-Kolonia"
    ],
    "name:fra_x_preferred":[
        "S\u0142upia Nadbrze\u017cna-Kolonia"
    ],
    "name:pol_x_preferred":[
        "S\u0142upia Nadbrze\u017cna-Kolonia"
    ],
    "name:ukr_x_preferred":[
        "\u0421\u043b\u0443\u043f\u044f-\u041d\u0430\u0434\u0431\u0436\u0435\u0436\u043d\u0430-\u041a\u043e\u043b\u044c\u043e\u043d\u0456\u044f"
    ],
    "qs_pg:aaroncc":"PL",
    "qs_pg:gn_country":"PL",
    "qs_pg:gn_fcode":"PPL",
    "qs_pg:gn_pop":136,
    "qs_pg:name":"S\u0142upia Nadbrze\u017cna-Kolonia",
    "qs_pg:name_adm0":"Polska",
    "qs_pg:name_adm1":"Swi\u0119tokrzyskie",
    "qs_pg:photos_9r":0,
    "qs_pg:photos_sr":0,
    "qs_pg:pop_sr":1,
    "qs_pg:qs_pg_placetype":"locality",
    "qs_pg:qs_pg_placetype_gp":"Town",
    "qs_pg:woe_adm0":23424923,
    "woe:adm0_id":23424923,
    "woe:name_adm0":"Polska",
    "woe:name_adm1":"Swi\u0119tokrzyskie",
    "woe:placetype":"Town",
    "wof:name":"S\u0142upia Nadbrze\u017cna-Kolonia",
    "wof:placetype":"locality",
    "wof:population":136
},
  "geometry": {"coordinates":[21.80348,50.94626],"type":"Point"}
}