{
  "type": "Feature",
  "properties": {
    "gn:admin1_code":"81.0",
    "gn:admin2_code":"2006.0",
    "gn:admin3_code":"200606.0",
    "gn:asciiname":"Szablaki",
    "gn:country_code":"PL",
    "gn:dem":109,
    "gn:feature_class":"P",
    "gn:feature_code":"PPL",
    "gn:name":"Szablaki",
    "gn:population":0,
    "gn:timezone":"Europe/Warsaw",
    "iso:country":"PL",
    "name:ceb_x_preferred":[
        "Szablaki"
    ],
    "name:lit_x_preferred":[
        "\u0160ablakai"
    ],
    "name:pol_x_preferred":[
        "Szablaki"
    ],
    "name:ukr_x_preferred":[
        "\u0428\u0430\u0431\u043b\u044f\u043a\u0438"
    ],
    "wof:name":"Szablaki",
    "wof:placetype":"locality"
},
  "geometry": {"coordinates":[21.7932,53.42242],"type":"Point"}
}