{
  "type": "Feature",
  "properties": {
    "gn:admin1_code":"78.0",
    "gn:admin2_code":"1430.0",
    "gn:admin3_code":"143005.0",
    "gn:asciiname":"Korzyce",
    "gn:country_code":"PL",
    "gn:dem":189,
    "gn:feature_class":"P",
    "gn:feature_code":"PPL",
    "gn:name":"Korzyce",
    "gn:population":0,
    "gn:timezone":"Europe/Warsaw",
    "iso:country":"PL",
    "name:ceb_x_preferred":[
        "Korzyce"
    ],
    "name:fra_x_preferred":[
        "Korzyce"
    ],
    "name:pol_x_preferred":[
        "Korzyce"
    ],
    "name:ukr_x_preferred":[
        "\u041a\u043e\u0436\u0438\u0446\u0435"
    ],
    "wof:name":"Korzyce",
    "wof:placetype":"locality"
},
  "geometry": {"coordinates":[20.82029,51.30669],"type":"Point"}
}