{
  "type": "Feature",
  "properties": {
    "gn:admin1_code":"87.0",
    "gn:admin2_code":"3206.0",
    "gn:admin3_code":"320602.0",
    "gn:asciiname":"Orzechow",
    "gn:country_code":"PL",
    "gn:dem":78,
    "gn:feature_class":"P",
    "gn:feature_code":"PPL",
    "gn:name":"Orzechow",
    "gn:population":0,
    "gn:timezone":"Europe/Warsaw",
    "iso:country":"PL",
    "name:deu_x_preferred":[
        "Orzech\u00f3w"
    ],
    "name:pol_x_preferred":[
        "Orzech\u00f3w"
    ],
    "name:ukr_x_preferred":[
        "\u041e\u0436\u0435\u0445\u0443\u0432"
    ],
    "name:und_x_variant":[
        "Wrechow",
        "Orzechow"
    ],
    "wof:name":"Orzechow",
    "wof:placetype":"locality"
},
  "geometry": {"coordinates":[14.28647,52.88696],"type":"Point"}
}