{
  "type": "Feature",
  "properties": {
    "gn:admin1_code":"79.0",
    "gn:admin2_code":"1602.0",
    "gn:admin3_code":"160201.0",
    "gn:asciiname":"Ksieze Pole",
    "gn:country_code":"PL",
    "gn:dem":254,
    "gn:feature_class":"P",
    "gn:feature_code":"PPL",
    "gn:name":"Ksi\u0119\u017ce Pole",
    "gn:population":0,
    "gn:timezone":"Europe/Warsaw",
    "iso:country":"PL",
    "wof:name":"Ksieze Pole",
    "wof:placetype":"locality"
},
  "geometry": {"coordinates":[17.96298999999999,50.10847],"type":"Point"}
}