{
  "type": "Feature",
  "properties": {
    "gn:admin1_code":"79.0",
    "gn:admin2_code":"1602.0",
    "gn:admin3_code":"160201.0",
    "gn:asciiname":"Ksieze Pole",
    "gn:country_code":"PL",
    "gn:dem":254,
    "gn:feature_class":"P",
    "gn:feature_code":"PPL",
    "gn:name":"Ksi\u0119\u017ce Pole",
    "gn:population":0,
    "gn:timezone":"Europe/Warsaw",
    "iso:country":"PL",
    "name:ces_x_preferred":[
        "Kn\u011b\u017epole"
    ],
    "name:pol_x_preferred":[
        "Ksi\u0119\u017ce Pole"
    ],
    "name:ukr_x_preferred":[
        "\u041a\u0441\u0435\u043d\u0436\u0435-\u041f\u043e\u043b\u0435"
    ],
    "wof:name":"Ksieze Pole",
    "wof:placetype":"locality"
},
  "geometry": {"coordinates":[17.96298999999999,50.10847],"type":"Point"}
}