{
  "type": "Feature",
  "properties": {
    "gn:gn_country":"PL",
    "gn:gn_fcode":"PPL",
    "gn:gn_pop":280,
    "gn:population":280,
    "iso:country":"PL",
    "name:ast_x_preferred":[
        "Tomice"
    ],
    "name:ceb_x_preferred":[
        "Tomice"
    ],
    "name:eng_x_preferred":[
        "Tomice"
    ],
    "name:fra_x_preferred":[
        "Tomice"
    ],
    "name:pol_x_preferred":[
        "Tomice"
    ],
    "name:ukr_x_preferred":[
        "\u0422\u043e\u043c\u0456\u0446\u0435"
    ],
    "qs_pg:aaroncc":"PL",
    "qs_pg:gn_country":"PL",
    "qs_pg:gn_fcode":"PPL",
    "qs_pg:gn_pop":280,
    "qs_pg:name":"Tomice",
    "qs_pg:name_adm0":"Polska",
    "qs_pg:name_adm1":"Mazowieckie",
    "qs_pg:photos_9r":0,
    "qs_pg:photos_sr":0,
    "qs_pg:pop_sr":2,
    "qs_pg:qs_pg_placetype":"locality",
    "qs_pg:qs_pg_placetype_gp":"Town",
    "qs_pg:woe_adm0":23424923,
    "woe:adm0_id":23424923,
    "woe:name_adm0":"Polska",
    "woe:name_adm1":"Mazowieckie",
    "woe:placetype":"Town",
    "wof:name":"Tomice",
    "wof:placetype":"locality",
    "wof:population":280
},
  "geometry": {"coordinates":[21.15761,52.00829],"type":"Point"}
}