{
  "type": "Feature",
  "properties": {
    "gn:country":"PL",
    "gn:fcode":"PPL",
    "gn:population":1239,
    "iso:country":"PL",
    "name:ast_x_preferred":[
        "Malec"
    ],
    "name:ceb_x_preferred":[
        "Malec"
    ],
    "name:deu_x_preferred":[
        "Malec"
    ],
    "name:eng_x_preferred":[
        "Malec"
    ],
    "name:fra_x_preferred":[
        "Malec"
    ],
    "name:pol_x_preferred":[
        "Malec"
    ],
    "name:ukr_x_preferred":[
        "\u041c\u0430\u043b\u0435\u0446\u044c"
    ],
    "name:vie_x_preferred":[
        "L\u00e0ng Malec"
    ],
    "qs_pg:aaroncc":"PL",
    "qs_pg:gn_country":"PL",
    "qs_pg:gn_fcode":"PPL",
    "qs_pg:gn_pop":1239,
    "qs_pg:name":"Malec",
    "qs_pg:name_adm0":"Polska",
    "qs_pg:name_adm1":"Ma\u0142opolskie",
    "qs_pg:photos_9r":0,
    "qs_pg:photos_sr":0,
    "qs_pg:pop_sr":3,
    "qs_pg:qs_pg_placetype":"locality",
    "qs_pg:qs_pg_placetype_gp":"Town",
    "qs_pg:woe_adm0":23424923,
    "woe:adm0_id":23424923,
    "woe:name_adm0":"Polska",
    "woe:name_adm1":"Ma\u0142opolskie",
    "woe:placetype":"Town",
    "wof:name":"Malec",
    "wof:placetype":"locality",
    "wof:population":1239
},
  "geometry": {"coordinates":[19.2453,49.92106],"type":"Point"}
}