{
  "type": "Feature",
  "properties": {
    "gn:admin1_code":"76.0",
    "gn:admin2_code":"802.0",
    "gn:admin3_code":"80205.0",
    "gn:asciiname":"Polanowice",
    "gn:country_code":"PL",
    "gn:dem":57,
    "gn:feature_class":"P",
    "gn:feature_code":"PPL",
    "gn:name":"Polanowice",
    "gn:population":0,
    "gn:timezone":"Europe/Warsaw",
    "iso:country":"PL",
    "wof:name":"Polanowice",
    "wof:placetype":"locality"
},
  "geometry": {"coordinates":[14.68812,51.88931],"type":"Point"}
}