{
  "type": "Feature",
  "properties": {
    "gn:admin1_code":"76.0",
    "gn:admin2_code":"802.0",
    "gn:admin3_code":"80205.0",
    "gn:asciiname":"Polanowice",
    "gn:country_code":"PL",
    "gn:dem":57,
    "gn:feature_class":"P",
    "gn:feature_code":"PPL",
    "gn:name":"Polanowice",
    "gn:population":0,
    "gn:timezone":"Europe/Warsaw",
    "iso:country":"PL",
    "name:fra_x_preferred":[
        "Polanowice"
    ],
    "name:pol_x_preferred":[
        "Polanowice"
    ],
    "name:ron_x_preferred":[
        "Polanowice"
    ],
    "name:ukr_x_preferred":[
        "\u041f\u043e\u043b\u044f\u043d\u043e\u0432\u0456\u0446\u0435"
    ],
    "wof:name":"Polanowice",
    "wof:placetype":"locality"
},
  "geometry": {"coordinates":[14.68812,51.88931],"type":"Point"}
}