{
  "type": "Feature",
  "properties": {
    "gn:admin1_code":"82.0",
    "gn:admin2_code":"2202.0",
    "gn:admin3_code":"220203.0",
    "gn:asciiname":"Raclawki",
    "gn:country_code":"PL",
    "gn:dem":146,
    "gn:feature_class":"P",
    "gn:feature_code":"PPL",
    "gn:name":"Rac\u0142awki",
    "gn:population":0,
    "gn:timezone":"Europe/Warsaw",
    "iso:country":"PL",
    "name:ceb_x_preferred":[
        "Rac\u0142awki"
    ],
    "name:pol_x_preferred":[
        "Rac\u0142awki"
    ],
    "name:ukr_x_preferred":[
        "\u0420\u0430\u0446\u043b\u0430\u0432\u043a\u0456"
    ],
    "wof:name":"Raclawki",
    "wof:placetype":"locality"
},
  "geometry": {"coordinates":[17.66949,53.66921],"type":"Point"}
}