{
  "type": "Feature",
  "properties": {
    "gn:admin1_code":"78.0",
    "gn:admin2_code":"1405.0",
    "gn:admin3_code":"140504.0",
    "gn:asciiname":"Wolka Grodziska",
    "gn:country_code":"PL",
    "gn:dem":100,
    "gn:feature_class":"P",
    "gn:feature_code":"PPL",
    "gn:name":"W\u00f3lka Grodziska",
    "gn:population":0,
    "gn:timezone":"Europe/Warsaw",
    "iso:country":"PL",
    "name:fra_x_preferred":[
        "W\u00f3lka Grodziska"
    ],
    "name:pol_x_preferred":[
        "W\u00f3lka Grodziska"
    ],
    "name:ukr_x_preferred":[
        "\u0412\u0443\u043b\u044c\u043a\u0430-\u0490\u0440\u043e\u0434\u0437\u0438\u0441\u044c\u043a\u0430"
    ],
    "wof:name":"Wolka Grodziska",
    "wof:placetype":"locality"
},
  "geometry": {"coordinates":[20.59902,52.11067],"type":"Point"}
}