{
  "type": "Feature",
  "properties": {
    "gn:admin1_code":"86.0",
    "gn:admin2_code":"3019.0",
    "gn:admin3_code":"301907.0",
    "gn:asciiname":"Jablonowko",
    "gn:country_code":"PL",
    "gn:dem":105,
    "gn:feature_class":"P",
    "gn:feature_code":"PPL",
    "gn:name":"Jab\u0142on\u00f3wko",
    "gn:population":0,
    "gn:timezone":"Europe/Warsaw",
    "iso:country":"PL",
    "wof:name":"Jablonowko",
    "wof:placetype":"locality"
},
  "geometry": {"coordinates":[16.72263,53.01167],"type":"Point"}
}