{
  "type": "Feature",
  "properties": {
    "gn:admin1_code":"73.0",
    "gn:admin2_code":"408.0",
    "gn:admin3_code":"40803.0",
    "gn:asciiname":"Chojno",
    "gn:country_code":"PL",
    "gn:dem":113,
    "gn:feature_class":"P",
    "gn:feature_code":"PPL",
    "gn:name":"Chojno",
    "gn:population":0,
    "gn:timezone":"Europe/Warsaw",
    "iso:country":"PL",
    "name:fra_x_preferred":[
        "Chojno"
    ],
    "name:pol_x_preferred":[
        "Chojno"
    ],
    "name:ukr_x_preferred":[
        "\u0425\u043e\u0439\u043d\u043e"
    ],
    "wof:name":"Chojno",
    "wof:placetype":"locality"
},
  "geometry": {"coordinates":[19.25532,52.98983000000001],"type":"Point"}
}