{
  "type": "Feature",
  "properties": {
    "gn:country":"PL",
    "gn:fcode":"PPL",
    "gn:population":0,
    "iso:country":"PL",
    "name:ast_x_preferred":[
        "Obojna"
    ],
    "name:eng_x_preferred":[
        "Obojnia"
    ],
    "name:fra_x_preferred":[
        "Obojna"
    ],
    "name:pol_x_preferred":[
        "Obojna"
    ],
    "name:ukr_x_preferred":[
        "\u041e\u0431\u043e\u0439\u043d\u0430"
    ],
    "name:und_x_variant":[
        "Oboina"
    ],
    "qs_pg:aaroncc":"PL",
    "qs_pg:gn_country":"PL",
    "qs_pg:gn_fcode":"PPL",
    "qs_pg:gn_pop":0,
    "qs_pg:name":"Obojnia",
    "qs_pg:name_adm0":"Polska",
    "qs_pg:name_adm1":"Podkarpackie",
    "qs_pg:photos":4,
    "qs_pg:photos_1k":1,
    "qs_pg:photos_9k":1,
    "qs_pg:photos_9r":1,
    "qs_pg:photos_all":4,
    "qs_pg:photos_sr":1,
    "qs_pg:pop_sr":0,
    "qs_pg:qs_pg_placetype":"locality",
    "qs_pg:qs_pg_placetype_gp":"Town",
    "qs_pg:woe_adm0":23424923,
    "woe:adm0_id":23424923,
    "woe:name_adm0":"Polska",
    "woe:name_adm1":"Podkarpackie",
    "woe:placetype":"Town",
    "wof:name":"Obojnia",
    "wof:placetype":"locality"
},
  "geometry": {"coordinates":[21.98506,50.60629],"type":"Point"}
}