{
  "type": "Feature",
  "properties": {
    "gn:admin1_code":"81.0",
    "gn:admin2_code":"2005.0",
    "gn:admin3_code":"200509.0",
    "gn:asciiname":"Olchowka",
    "gn:country_code":"PL",
    "gn:dem":150,
    "gn:feature_class":"P",
    "gn:feature_code":"PPL",
    "gn:name":"Olch\u00f3wka",
    "gn:population":0,
    "gn:timezone":"Europe/Warsaw",
    "iso:country":"PL",
    "name:azb_x_preferred":[
        "\u0627\u0648\u0644\u062e\u0648\u0648\u06a9\u0627"
    ],
    "name:bul_x_preferred":[
        "\u041e\u043b\u0445\u0443\u0432\u043a\u0430"
    ],
    "name:ceb_x_preferred":[
        "Olch\u00f3wka"
    ],
    "name:deu_x_preferred":[
        "Olch\u00f3wka"
    ],
    "name:fas_x_preferred":[
        "\u0627\u0648\u0644\u062e\u0648\u0648\u06a9\u0627"
    ],
    "name:fra_x_preferred":[
        "Olch\u00f3wka"
    ],
    "name:lit_x_preferred":[
        "Olchuvka"
    ],
    "name:nld_x_preferred":[
        "Olch\u00f3wka"
    ],
    "name:pol_x_preferred":[
        "Olch\u00f3wka"
    ],
    "name:ukr_x_preferred":[
        "\u041e\u043b\u044c\u0445\u0443\u0432\u043a\u0430"
    ],
    "wof:name":"Olchowka",
    "wof:placetype":"locality"
},
  "geometry": {"coordinates":[23.82921,52.85412],"type":"Point"}
}