{
  "type": "Feature",
  "properties": {
    "gn:admin1_code":"81.0",
    "gn:admin2_code":"2005.0",
    "gn:admin3_code":"200509.0",
    "gn:asciiname":"Olchowka",
    "gn:country_code":"PL",
    "gn:dem":150,
    "gn:feature_class":"P",
    "gn:feature_code":"PPL",
    "gn:name":"Olch\u00f3wka",
    "gn:population":0,
    "gn:timezone":"Europe/Warsaw",
    "iso:country":"PL",
    "name:und_x_variant":[
        "Olch\u00f3wka"
    ],
    "wof:name":"Olchowka",
    "wof:placetype":"locality"
},
  "geometry": {"coordinates":[23.82921,52.85412],"type":"Point"}
}