{
  "type": "Feature",
  "properties": {
    "gn:admin1_code":"75.0",
    "gn:admin2_code":"611.0",
    "gn:admin3_code":"61107.0",
    "gn:asciiname":"Wolka Zastawska",
    "gn:country_code":"PL",
    "gn:dem":169,
    "gn:feature_class":"P",
    "gn:feature_code":"PPL",
    "gn:name":"W\u00f3lka Zastawska",
    "gn:population":0,
    "gn:timezone":"Europe/Warsaw",
    "iso:country":"PL",
    "name:ara_x_preferred":[
        "\u0641\u0648\u0644\u0643\u0627 \u0632\u0627\u0633\u062a\u0627\u0641\u0633\u0643\u0627"
    ],
    "name:fra_x_preferred":[
        "W\u00f3lka Zastawska"
    ],
    "name:pol_x_preferred":[
        "W\u00f3lka Zastawska"
    ],
    "name:ukr_x_preferred":[
        "\u0412\u0443\u043b\u044c\u043a\u0430-\u0417\u0430\u0441\u0442\u0430\u0432\u0441\u044c\u043a\u0430"
    ],
    "wof:name":"Wolka Zastawska",
    "wof:placetype":"locality"
},
  "geometry": {"coordinates":[22.19458,51.93558],"type":"Point"}
}