{
  "type": "Feature",
  "properties": {
    "gn:admin1_code":"75.0",
    "gn:admin2_code":"611.0",
    "gn:admin3_code":"61107.0",
    "gn:asciiname":"Wolka Zastawska",
    "gn:country_code":"PL",
    "gn:dem":169,
    "gn:feature_class":"P",
    "gn:feature_code":"PPL",
    "gn:name":"W\u00f3lka Zastawska",
    "gn:population":0,
    "gn:timezone":"Europe/Warsaw",
    "iso:country":"PL",
    "name:und_x_variant":[
        "W\u00f3lka Zastawska"
    ],
    "wof:name":"Wolka Zastawska",
    "wof:placetype":"locality"
},
  "geometry": {"coordinates":[22.19458,51.93558],"type":"Point"}
}