{
  "type": "Feature",
  "properties": {
    "gn:admin1_code":"81.0",
    "gn:admin2_code":"2001.0",
    "gn:admin3_code":"200105.0",
    "gn:asciiname":"Krusznik",
    "gn:country_code":"PL",
    "gn:dem":145,
    "gn:feature_class":"P",
    "gn:feature_code":"PPL",
    "gn:name":"Krusznik",
    "gn:population":0,
    "gn:timezone":"Europe/Warsaw",
    "iso:country":"PL",
    "name:lit_x_preferred":[
        "Kru\u0161nikas"
    ],
    "name:pol_x_preferred":[
        "Krusznik"
    ],
    "name:ukr_x_preferred":[
        "\u041a\u0440\u0443\u0448\u043d\u0438\u043a"
    ],
    "wof:name":"Krusznik",
    "wof:placetype":"locality"
},
  "geometry": {"coordinates":[23.11097,54.00762],"type":"Point"}
}