{
  "type": "Feature",
  "properties": {
    "gn:admin1_code":"85.0",
    "gn:admin2_code":"2816.0",
    "gn:admin3_code":"281603.0",
    "gn:asciiname":"Nowy Wadolek",
    "gn:country_code":"PL",
    "gn:dem":116,
    "gn:feature_class":"P",
    "gn:feature_code":"PPL",
    "gn:name":"Nowy W\u0105do\u0142ek",
    "gn:population":0,
    "gn:timezone":"Europe/Warsaw",
    "iso:country":"PL",
    "name:und_x_variant":[
        "Heinriettental",
        "Nowy W\u0105do\u0142ek"
    ],
    "wof:name":"Nowy Wadolek",
    "wof:placetype":"locality"
},
  "geometry": {"coordinates":[21.78333,53.51667],"type":"Point"}
}