{
  "type": "Feature",
  "properties": {
    "gn:admin1_code":"87.0",
    "gn:admin2_code":"3202.0",
    "gn:admin3_code":"320204.0",
    "gn:asciiname":"Przybyslaw",
    "gn:country_code":"PL",
    "gn:dem":99,
    "gn:feature_class":"P",
    "gn:feature_code":"PPL",
    "gn:name":"Przybys\u0142aw",
    "gn:population":0,
    "gn:timezone":"Europe/Warsaw",
    "iso:country":"PL",
    "name:pol_x_preferred":[
        "Przybys\u0142aw"
    ],
    "name:vie_x_preferred":[
        "Przybys\u0142aw"
    ],
    "wof:name":"Przybyslaw",
    "wof:placetype":"locality"
},
  "geometry": {"coordinates":[15.45325,53.0327],"type":"Point"}
}