{
  "type": "Feature",
  "properties": {
    "gn:admin1_code":"85.0",
    "gn:admin2_code":"2804.0",
    "gn:admin3_code":"280402.0",
    "gn:asciiname":"Milosna",
    "gn:country_code":"PL",
    "gn:dem":54,
    "gn:feature_class":"P",
    "gn:feature_code":"PPL",
    "gn:name":"Mi\u0142osna",
    "gn:population":0,
    "gn:timezone":"Europe/Warsaw",
    "iso:country":"PL",
    "name:pol_x_preferred":[
        "Mi\u0142osna"
    ],
    "name:ukr_x_preferred":[
        "\u041c\u0456\u043b\u043e\u0441\u043d\u0430"
    ],
    "name:und_x_variant":[
        "Liebenau"
    ],
    "wof:name":"Milosna",
    "wof:placetype":"locality"
},
  "geometry": {"coordinates":[19.82248,54.10019000000001],"type":"Point"}
}