{
  "type": "Feature",
  "properties": {
    "gn:admin1_code":"84.0",
    "gn:admin2_code":"2613.0",
    "gn:admin3_code":"261305.0",
    "gn:asciiname":"Zaleze",
    "gn:country_code":"PL",
    "gn:dem":239,
    "gn:feature_class":"P",
    "gn:feature_code":"PPL",
    "gn:name":"Za\u0142\u0119\u017ce",
    "gn:population":0,
    "gn:timezone":"Europe/Warsaw",
    "iso:country":"PL",
    "wof:name":"Zaleze",
    "wof:placetype":"locality"
},
  "geometry": {"coordinates":[19.75,50.73333],"type":"Point"}
}