{
  "type": "Feature",
  "properties": {
    "gn:admin1_code":"82.0",
    "gn:admin2_code":"2202.0",
    "gn:admin3_code":"220204.0",
    "gn:asciiname":"Kaliska",
    "gn:country_code":"PL",
    "gn:dem":120,
    "gn:feature_class":"P",
    "gn:feature_code":"PPL",
    "gn:name":"Kaliska",
    "gn:population":0,
    "gn:timezone":"Europe/Warsaw",
    "iso:country":"PL",
    "name:ceb_x_preferred":[
        "Kaliska"
    ],
    "name:fra_x_preferred":[
        "Kaliska"
    ],
    "name:nld_x_preferred":[
        "Kaliska"
    ],
    "name:pol_x_preferred":[
        "Kaliska"
    ],
    "name:ukr_x_preferred":[
        "\u041a\u0430\u043b\u0438\u0441\u044c\u043a\u0430"
    ],
    "wof:name":"Kaliska",
    "wof:placetype":"locality"
},
  "geometry": {"coordinates":[17.80532999999999,53.75597],"type":"Point"}
}