{
  "type": "Feature",
  "properties": {
    "gn:admin1_code":"78.0",
    "gn:admin2_code":"1437.0",
    "gn:admin3_code":"143702.0",
    "gn:asciiname":"Bagienice Male",
    "gn:country_code":"PL",
    "gn:dem":144,
    "gn:feature_class":"P",
    "gn:feature_code":"PPL",
    "gn:name":"Bagienice Ma\u0142e",
    "gn:population":0,
    "gn:timezone":"Europe/Warsaw",
    "iso:country":"PL",
    "name:fra_x_preferred":[
        "Bagienice Ma\u0142e"
    ],
    "name:pol_x_preferred":[
        "Bagienice Ma\u0142e"
    ],
    "name:ukr_x_preferred":[
        "\u0411\u0430\u0491\u0435\u043d\u0456\u0446\u0435-\u041c\u0430\u043b\u0456"
    ],
    "wof:name":"Bagienice Male",
    "wof:placetype":"locality"
},
  "geometry": {"coordinates":[20.01863,53.14327],"type":"Point"}
}