{
  "type": "Feature",
  "properties": {
    "gn:admin1_code":"74.0",
    "gn:admin2_code":"1002.0",
    "gn:admin3_code":"100205.0",
    "gn:asciiname":"Wojciechowice Male",
    "gn:country_code":"PL",
    "gn:dem":101,
    "gn:feature_class":"P",
    "gn:feature_code":"PPL",
    "gn:name":"Wojciechowice Ma\u0142e",
    "gn:population":0,
    "gn:timezone":"Europe/Warsaw",
    "iso:country":"PL",
    "name:fra_x_preferred":[
        "Wojciechowice Ma\u0142e"
    ],
    "name:pol_x_preferred":[
        "Wojciechowice Ma\u0142e"
    ],
    "wof:name":"Wojciechowice Male",
    "wof:placetype":"locality"
},
  "geometry": {"coordinates":[19.41667,52.18333],"type":"Point"}
}