{
  "type": "Feature",
  "properties": {
    "gn:admin1_code":"76.0",
    "gn:admin2_code":"806.0",
    "gn:admin3_code":"80604.0",
    "gn:asciiname":"Przyleg",
    "gn:country_code":"PL",
    "gn:dem":37,
    "gn:feature_class":"P",
    "gn:feature_code":"PPL",
    "gn:name":"Przy\u0142\u0119g",
    "gn:population":0,
    "gn:timezone":"Europe/Warsaw",
    "iso:country":"PL",
    "name:fra_x_preferred":[
        "Przy\u0142\u0119g"
    ],
    "name:pol_x_preferred":[
        "Przy\u0142\u0119g"
    ],
    "name:ukr_x_preferred":[
        "\u041f\u0448\u0438\u043b\u0435\u043d\u0491"
    ],
    "name:und_x_variant":[
        "Altenflie\u00df",
        "Przy\u0142\u0119g"
    ],
    "wof:name":"Przyleg",
    "wof:placetype":"locality"
},
  "geometry": {"coordinates":[15.46221,52.83758],"type":"Point"}
}