{
  "type": "Feature",
  "properties": {
    "gn:gn_country":"PL",
    "gn:gn_fcode":"PPLA3",
    "gn:gn_pop":432,
    "gn:population":432,
    "iso:country":"PL",
    "name:eng_x_preferred":[
        "Gmina Siemi\u0105tkowo"
    ],
    "name:pol_x_preferred":[
        "Siemi\u0105tkowo Koziebrodzkie"
    ],
    "name:por_x_preferred":[
        "Comuna de Siemi\u0105tkowo"
    ],
    "name:rus_x_preferred":[
        "\u0421\u0435\u043c\u0451\u043d\u0442\u043a\u043e\u0432\u043e"
    ],
    "name:slk_x_preferred":[
        "Gmina Siemi\u0105tkowo"
    ],
    "name:ukr_x_preferred":[
        "\u0490\u043c\u0456\u043d\u0430 \u0421\u0435\u043c\u044c\u043e\u043d\u0442\u043a\u043e\u0432\u043e"
    ],
    "name:war_x_preferred":[
        "Gmina Siemi\u0105tkowo"
    ],
    "qs_pg:aaroncc":"PL",
    "qs_pg:gn_country":"PL",
    "qs_pg:gn_fcode":"PPLA3",
    "qs_pg:gn_pop":432,
    "qs_pg:name":"Siemi\u0105tkowo",
    "qs_pg:photos_9r":0,
    "qs_pg:photos_sr":0,
    "qs_pg:pop_sr":2,
    "qs_pg:qs_pg_placetype":"locality",
    "wof:name":"Siemi\u0105tkowo",
    "wof:placetype":"locality",
    "wof:population":432
},
  "geometry": {"coordinates":[20.02893,52.8811],"type":"Point"}
}