{
  "type": "Feature",
  "properties": {
    "gn:admin1_code":"83.0",
    "gn:admin2_code":"2415.0",
    "gn:admin3_code":"241505.0",
    "gn:asciiname":"Skrbensko",
    "gn:country_code":"PL",
    "gn:dem":226,
    "gn:feature_class":"P",
    "gn:feature_code":"PPL",
    "gn:name":"Skrbe\u0144sko",
    "gn:population":0,
    "gn:timezone":"Europe/Warsaw",
    "iso:country":"PL",
    "name:ceb_x_preferred":[
        "Skrbe\u0144sko"
    ],
    "name:pol_x_preferred":[
        "Skrbe\u0144sko"
    ],
    "name:ukr_x_preferred":[
        "\u0421\u043a\u0440\u0431\u0435\u043d\u0441\u044c\u043a\u043e"
    ],
    "name:und_x_variant":[
        "Skrbe\u0144sko"
    ],
    "wof:name":"Skrbensko",
    "wof:placetype":"locality"
},
  "geometry": {"coordinates":[18.5281,49.90685],"type":"Point"}
}