{
  "type": "Feature",
  "properties": {
    "gn:admin1_code":"82.0",
    "gn:admin2_code":"2203.0",
    "gn:admin3_code":"220303.0",
    "gn:asciiname":"Debnica",
    "gn:country_code":"PL",
    "gn:dem":158,
    "gn:feature_class":"P",
    "gn:feature_code":"PPL",
    "gn:name":"D\u0119bnica",
    "gn:population":0,
    "gn:timezone":"Europe/Warsaw",
    "iso:country":"PL",
    "name:ceb_x_preferred":[
        "D\u0119bnica"
    ],
    "name:csb_x_preferred":[
        "D\u00e3bnica"
    ],
    "name:pol_x_preferred":[
        "D\u0119bnica"
    ],
    "name:ukr_x_preferred":[
        "\u0414\u0435\u043c\u0431\u043d\u0438\u0446\u044f"
    ],
    "wof:name":"Debnica",
    "wof:placetype":"locality"
},
  "geometry": {"coordinates":[17.35901,53.63562],"type":"Point"}
}