{
  "type": "Feature",
  "properties": {
    "gn:admin1_code":"77.0",
    "gn:admin2_code":"1210.0",
    "gn:admin3_code":"121013.0",
    "gn:asciiname":"Kokuszka",
    "gn:country_code":"PL",
    "gn:dem":439,
    "gn:feature_class":"P",
    "gn:feature_code":"PPL",
    "gn:name":"Kokuszka",
    "gn:population":0,
    "gn:timezone":"Europe/Warsaw",
    "iso:country":"PL",
    "name:ceb_x_preferred":[
        "Kokuszka"
    ],
    "name:pol_x_preferred":[
        "Kokuszka"
    ],
    "name:srp_x_preferred":[
        "\u041a\u043e\u043a\u0443\u0441\u043a\u0430"
    ],
    "name:ukr_x_preferred":[
        "\u041a\u043e\u043a\u0443\u0448\u043a\u0430"
    ],
    "wof:name":"Kokuszka",
    "wof:placetype":"locality"
},
  "geometry": {"coordinates":[20.71794,49.45973],"type":"Point"}
}