{
  "type": "Feature",
  "properties": {
    "iso:country":"PL",
    "name:eng_x_preferred":[
        "Kielpino Gorne"
    ],
    "name:pol_x_preferred":[
        "Kie\u0142pino G\u00f3rne"
    ],
    "wof:name":"Kielpino Gorne",
    "wof:placetype":"neighbourhood"
},
  "geometry": {"coordinates":[18.50764116009442,54.33999536379574],"type":"Point"}
}