{
  "type": "Feature",
  "properties": {
    "gn:admin1_code":"82.0",
    "gn:admin2_code":"2213.0",
    "gn:admin3_code":"221306.0",
    "gn:asciiname":"Smolniki",
    "gn:country_code":"PL",
    "gn:dem":93,
    "gn:feature_class":"P",
    "gn:feature_code":"PPL",
    "gn:name":"Smolniki",
    "gn:population":0,
    "gn:timezone":"Europe/Warsaw",
    "iso:country":"PL",
    "wof:name":"Smolniki",
    "wof:placetype":"locality"
},
  "geometry": {"coordinates":[18.42348,53.77033],"type":"Point"}
}