{
  "type": "Feature",
  "properties": {
    "gn:admin1_code":"86.0",
    "gn:admin2_code":"3010.0",
    "gn:admin3_code":"301009.0",
    "gn:asciiname":"Buszkowo",
    "gn:country_code":"PL",
    "gn:dem":98,
    "gn:feature_class":"P",
    "gn:feature_code":"PPL",
    "gn:name":"Buszkowo",
    "gn:population":0,
    "gn:timezone":"Europe/Warsaw",
    "iso:country":"PL",
    "name:pol_x_preferred":[
        "Buszkowo"
    ],
    "name:ukr_x_preferred":[
        "\u0411\u0443\u0448\u043a\u043e\u0432\u043e"
    ],
    "wof:name":"Buszkowo",
    "wof:placetype":"locality"
},
  "geometry": {"coordinates":[18.29155,52.4764],"type":"Point"}
}