{
  "type": "Feature",
  "properties": {
    "gn:admin1_code":"74.0",
    "gn:admin2_code":"1005.0",
    "gn:admin3_code":"100510.0",
    "gn:asciiname":"Bakow Gorny",
    "gn:country_code":"PL",
    "gn:dem":93,
    "gn:feature_class":"P",
    "gn:feature_code":"PPL",
    "gn:name":"B\u0105k\u00f3w G\u00f3rny",
    "gn:population":0,
    "gn:timezone":"Europe/Warsaw",
    "iso:country":"PL",
    "name:fra_x_preferred":[
        "B\u0105k\u00f3w G\u00f3rny"
    ],
    "name:pol_x_preferred":[
        "B\u0105k\u00f3w G\u00f3rny"
    ],
    "name:ukr_x_preferred":[
        "\u0411\u043e\u043d\u043a\u0443\u0432-\u0490\u0443\u0440\u043d\u0438"
    ],
    "wof:name":"Bakow Gorny",
    "wof:placetype":"locality"
},
  "geometry": {"coordinates":[19.72389,52.16477],"type":"Point"}
}