{
  "type": "Feature",
  "properties": {
    "gn:admin1_code":"81.0",
    "gn:admin2_code":"2011.0",
    "gn:admin3_code":"201108.0",
    "gn:asciiname":"Maczalna Nowa",
    "gn:country_code":"PL",
    "gn:dem":148,
    "gn:feature_class":"P",
    "gn:feature_code":"PPL",
    "gn:name":"Maczalna Nowa",
    "gn:population":0,
    "gn:timezone":"Europe/Warsaw",
    "iso:country":"PL",
    "wof:name":"Maczalna Nowa",
    "wof:placetype":"locality"
},
  "geometry": {"coordinates":[23.43333,53.35],"type":"Point"}
}