{
  "type": "Feature",
  "properties": {
    "iso:country":"PL",
    "name:bel_x_preferred":[
        "\u0425\u0430\u0439\u043d\u0456\u0446\u044b"
    ],
    "name:bul_x_preferred":[
        "\u0425\u043e\u0439\u043d\u0438\u0446\u0435"
    ],
    "name:ceb_x_preferred":[
        "Chojnice"
    ],
    "name:ces_x_preferred":[
        "Chojnice"
    ],
    "name:csb_x_preferred":[
        "Ch\u00f2nice"
    ],
    "name:deu_x_preferred":[
        "Chojnice"
    ],
    "name:dsb_x_preferred":[
        "Chojnice"
    ],
    "name:epo_x_preferred":[
        "Chojnice"
    ],
    "name:eus_x_preferred":[
        "Chojnice"
    ],
    "name:fas_x_preferred":[
        "\u062e\u0648\u06cc\u0646\u06cc\u062a\u0633\u0647"
    ],
    "name:fin_x_preferred":[
        "Chojnice"
    ],
    "name:fra_x_preferred":[
        "Chojnice"
    ],
    "name:hak_x_preferred":[
        "Chojnice"
    ],
    "name:ind_x_preferred":[
        "Chojnice"
    ],
    "name:ita_x_preferred":[
        "Chojnice"
    ],
    "name:jav_x_preferred":[
        "Chojnice"
    ],
    "name:lav_x_preferred":[
        "Hoj\u0146ice"
    ],
    "name:lit_x_preferred":[
        "Choinic\u0117s"
    ],
    "name:msa_x_preferred":[
        "Chojnice"
    ],
    "name:nau_x_preferred":[
        "Chojnice"
    ],
    "name:nld_x_preferred":[
        "Chojnice"
    ],
    "name:pol_x_preferred":[
        "Chojnice"
    ],
    "name:por_x_preferred":[
        "Chojnice"
    ],
    "name:ron_x_preferred":[
        "Chojnice"
    ],
    "name:rus_x_preferred":[
        "\u0425\u043e\u0439\u043d\u0438\u0446\u0435"
    ],
    "name:slk_x_preferred":[
        "Chojnice"
    ],
    "name:spa_x_preferred":[
        "Chojnice"
    ],
    "name:srp_x_preferred":[
        "\u0425\u043e\u0458\u045a\u0438\u0446\u0435"
    ],
    "name:swe_x_preferred":[
        "Chojnice"
    ],
    "name:szl_x_preferred":[
        "Choj\u0144icy"
    ],
    "name:ukr_x_preferred":[
        "\u0425\u043e\u0439\u043d\u0456\u0446\u0435"
    ],
    "name:vie_x_preferred":[
        "Chojnice"
    ],
    "name:war_x_preferred":[
        "Chojnice"
    ],
    "name:zho_x_preferred":[
        "\u970d\u4f0a\u5c3c\u91c7"
    ],
    "qs_pg:aaroncc":"PL",
    "qs_pg:name":"Chojnice",
    "qs_pg:name_adm0":"Polska",
    "qs_pg:name_adm1":"Pomorskie",
    "qs_pg:photos":4,
    "qs_pg:photos_1k":1,
    "qs_pg:photos_9k":1,
    "qs_pg:photos_9r":1,
    "qs_pg:photos_all":4,
    "qs_pg:photos_sr":1,
    "qs_pg:pop_sr":0,
    "qs_pg:qs_pg_placetype":"localadmin",
    "qs_pg:qs_pg_placetype_gp":"LocalAdmin",
    "qs_pg:woe_adm0":23424923,
    "woe:adm0_id":23424923,
    "woe:name_adm0":"Polska",
    "woe:name_adm1":"Pomorskie",
    "woe:placetype":"LocalAdmin",
    "wof:name":"Chojnice",
    "wof:placetype":"localadmin"
},
  "geometry": {"coordinates":[17.561291,53.695696],"type":"Point"}
}