{
  "type": "Feature",
  "properties": {
    "gn:admin1_code":"83.0",
    "gn:admin2_code":"2417.0",
    "gn:admin3_code":"241704.0",
    "gn:asciiname":"Gluchaczki",
    "gn:country_code":"PL",
    "gn:dem":720,
    "gn:feature_class":"P",
    "gn:feature_code":"PPL",
    "gn:name":"G\u0142uchaczki",
    "gn:population":0,
    "gn:timezone":"Europe/Warsaw",
    "iso:country":"PL",
    "wof:name":"Gluchaczki",
    "wof:placetype":"locality"
},
  "geometry": {"coordinates":[19.42014,49.60253],"type":"Point"}
}