{
  "type": "Feature",
  "properties": {
    "gn:admin1_code":"82.0",
    "gn:admin2_code":"2206.0",
    "gn:admin3_code":"220607.0",
    "gn:asciiname":"Szatarpy",
    "gn:country_code":"PL",
    "gn:dem":183,
    "gn:feature_class":"P",
    "gn:feature_code":"PPL",
    "gn:name":"Szatarpy",
    "gn:population":0,
    "gn:timezone":"Europe/Warsaw",
    "iso:country":"PL",
    "wof:name":"Szatarpy",
    "wof:placetype":"locality"
},
  "geometry": {"coordinates":[18.29239,54.13782],"type":"Point"}
}