{
  "type": "Feature",
  "properties": {
    "gn:admin1_code":"75.0",
    "gn:admin2_code":"602.0",
    "gn:admin3_code":"60209.0",
    "gn:asciiname":"Osuchy",
    "gn:country_code":"PL",
    "gn:dem":194,
    "gn:feature_class":"P",
    "gn:feature_code":"PPL",
    "gn:name":"Osuchy",
    "gn:population":0,
    "gn:timezone":"Europe/Warsaw",
    "iso:country":"PL",
    "name:ceb_x_preferred":[
        "Osuchy"
    ],
    "name:fra_x_preferred":[
        "Osuchy"
    ],
    "name:pol_x_preferred":[
        "Osuchy"
    ],
    "name:ukr_x_preferred":[
        "\u041e\u0441\u0443\u0445\u0438"
    ],
    "wof:name":"Osuchy",
    "wof:placetype":"locality"
},
  "geometry": {"coordinates":[22.96349,50.40184],"type":"Point"}
}