{
  "type": "Feature",
  "properties": {
    "gn:admin1_code":"83.0",
    "gn:admin2_code":"2404.0",
    "gn:admin3_code":"240405.0",
    "gn:asciiname":"Nieznanice",
    "gn:country_code":"PL",
    "gn:dem":255,
    "gn:feature_class":"P",
    "gn:feature_code":"PPL",
    "gn:name":"Nieznanice",
    "gn:population":0,
    "gn:timezone":"Europe/Warsaw",
    "iso:country":"PL",
    "name:ceb_x_preferred":[
        "Nieznanice"
    ],
    "name:pol_x_preferred":[
        "Nieznanice"
    ],
    "name:ukr_x_preferred":[
        "\u041d\u0435\u0437\u043d\u0430\u043d\u0456\u0446\u0435"
    ],
    "wof:name":"Nieznanice",
    "wof:placetype":"locality"
},
  "geometry": {"coordinates":[19.30933,50.91948],"type":"Point"}
}