{
  "type": "Feature",
  "properties": {
    "gn:admin1_code":"81.0",
    "gn:asciiname":"Milewo-Tosie",
    "gn:country_code":"PL",
    "gn:dem":114,
    "gn:feature_class":"P",
    "gn:feature_code":"PPL",
    "gn:name":"Milewo-Tosie",
    "gn:population":0,
    "gn:timezone":"Europe/Warsaw",
    "iso:country":"PL",
    "name:fra_x_preferred":[
        "Milewo-Tosie"
    ],
    "name:pol_x_preferred":[
        "Milewo-Tosie"
    ],
    "name:ukr_x_preferred":[
        "\u041c\u0456\u043b\u0435\u0432\u043e-\u0422\u043e\u0441\u0435"
    ],
    "wof:name":"Milewo-Tosie",
    "wof:placetype":"locality"
},
  "geometry": {"coordinates":[21.84219,52.99805],"type":"Point"}
}