{
  "type": "Feature",
  "properties": {
    "gn:admin1_code":"78.0",
    "gn:admin2_code":"1416.0",
    "gn:admin3_code":"141611.0",
    "gn:asciiname":"Uscianek Wielki",
    "gn:country_code":"PL",
    "gn:dem":109,
    "gn:feature_class":"P",
    "gn:feature_code":"PPL",
    "gn:name":"U\u015bcianek Wielki",
    "gn:population":0,
    "gn:timezone":"Europe/Warsaw",
    "iso:country":"PL",
    "name:fra_x_preferred":[
        "U\u015bcianek Wielki"
    ],
    "name:pol_x_preferred":[
        "U\u015bcianek Wielki"
    ],
    "name:ukr_x_preferred":[
        "\u0423\u0441\u0446\u044f\u043d\u0435\u043a-\u0412\u0435\u043b\u0438\u043a\u0438\u0439"
    ],
    "name:und_x_variant":[
        "U\u015bcianek Wielki"
    ],
    "wof:name":"Uscianek Wielki",
    "wof:placetype":"locality"
},
  "geometry": {"coordinates":[22.14422,52.7409],"type":"Point"}
}