{
  "type": "Feature",
  "properties": {
    "gn:gn_country":"PL",
    "gn:gn_fcode":"PPLA3",
    "gn:gn_pop":2003,
    "gn:population":2003,
    "iso:country":"PL",
    "name:eng_x_preferred":[
        "Gmina D\u0105bie"
    ],
    "name:rus_x_preferred":[
        "\u0414\u043e\u043c\u0431\u0435"
    ],
    "name:slk_x_preferred":[
        "Gmina D\u0105bie"
    ],
    "name:ukr_x_preferred":[
        "\u0490\u043c\u0456\u043d\u0430 \u0414\u043e\u043c\u0431\u0435"
    ],
    "name:war_x_preferred":[
        "Gmina D\u0105bie"
    ],
    "qs_pg:aaroncc":"PL",
    "qs_pg:gn_country":"PL",
    "qs_pg:gn_fcode":"PPLA3",
    "qs_pg:gn_pop":2003,
    "qs_pg:name":"D\u0105bie",
    "qs_pg:name_adm0":"Polska",
    "qs_pg:name_adm1":"Wielkopolskie",
    "qs_pg:photos_9r":0,
    "qs_pg:photos_sr":0,
    "qs_pg:pop_sr":4,
    "qs_pg:qs_pg_placetype":"localadmin",
    "qs_pg:qs_pg_placetype_gp":"LocalAdmin",
    "qs_pg:woe_adm0":23424923,
    "woe:adm0_id":23424923,
    "woe:name_adm0":"Polska",
    "woe:name_adm1":"Wielkopolskie",
    "woe:placetype":"LocalAdmin",
    "wof:name":"D\u0105bie",
    "wof:placetype":"localadmin",
    "wof:population":2003
},
  "geometry": {"coordinates":[18.8225,52.08668],"type":"Point"}
}