{
  "type": "Feature",
  "properties": {
    "gn:admin1_code":"85.0",
    "gn:admin2_code":"2802.0",
    "gn:admin3_code":"280206.0",
    "gn:asciiname":"Trabki",
    "gn:cc2":"PL",
    "gn:country_code":"PL",
    "gn:dem":33,
    "gn:feature_class":"P",
    "gn:feature_code":"PPL",
    "gn:name":"Tr\u0105bki",
    "gn:population":0,
    "gn:timezone":"Europe/Warsaw",
    "iso:country":"PL",
    "name:fra_x_preferred":[
        "Tr\u0105bki"
    ],
    "name:pol_x_preferred":[
        "Tr\u0105bki"
    ],
    "name:und_x_variant":[
        "Klein Tromp"
    ],
    "wof:name":"Trabki",
    "wof:placetype":"locality"
},
  "geometry": {"coordinates":[19.84663,54.28006],"type":"Point"}
}