{
  "type": "Feature",
  "properties": {
    "gn:admin1_code":"78.0",
    "gn:admin2_code":"1406.0",
    "gn:admin3_code":"140609.0",
    "gn:asciiname":"Jeziora Laczki",
    "gn:country_code":"PL",
    "gn:dem":167,
    "gn:feature_class":"P",
    "gn:feature_code":"PPL",
    "gn:name":"Jeziora \u0141\u0105czki",
    "gn:population":0,
    "gn:timezone":"Europe/Warsaw",
    "iso:country":"PL",
    "wof:name":"Jeziora Laczki",
    "wof:placetype":"locality"
},
  "geometry": {"coordinates":[20.76685,51.88144000000001],"type":"Point"}
}