{
  "type": "Feature",
  "properties": {
    "gn:admin1_code":"73.0",
    "gn:admin2_code":"411.0",
    "gn:admin3_code":"41106.0",
    "gn:asciiname":"Broniewo",
    "gn:country_code":"PL",
    "gn:dem":95,
    "gn:feature_class":"P",
    "gn:feature_code":"PPL",
    "gn:name":"Broniewo",
    "gn:population":0,
    "gn:timezone":"Europe/Warsaw",
    "iso:country":"PL",
    "name:pol_x_preferred":[
        "Broniewo"
    ],
    "name:ukr_x_preferred":[
        "\u0411\u0440\u043e\u043d\u0435\u0432\u043e"
    ],
    "wof:name":"Broniewo",
    "wof:placetype":"locality"
},
  "geometry": {"coordinates":[18.50436,52.65518],"type":"Point"}
}