{
  "type": "Feature",
  "properties": {
    "gn:admin1_code":"73.0",
    "gn:admin2_code":"417.0",
    "gn:admin3_code":"41705.0",
    "gn:asciiname":"Orzechowo",
    "gn:country_code":"PL",
    "gn:dem":96,
    "gn:feature_class":"P",
    "gn:feature_code":"PPL",
    "gn:name":"Orzechowo",
    "gn:population":0,
    "gn:timezone":"Europe/Warsaw",
    "iso:country":"PL",
    "name:pol_x_preferred":[
        "Orzechowo"
    ],
    "name:ukr_x_preferred":[
        "\u041e\u0436\u0435\u0445\u043e\u0432\u043e"
    ],
    "wof:name":"Orzechowo",
    "wof:placetype":"locality"
},
  "geometry": {"coordinates":[18.82129,53.19726],"type":"Point"}
}