{
  "type": "Feature",
  "properties": {
    "iso:country":"PL",
    "name:azb_x_preferred":[
        "\u0642\u0645\u06cc\u0646\u0627 \u0645\u0648\u0631\u0648\u0648\u0627\u0646\u0627 \u0642\u0648\u0634\u0644\u06cc\u0646\u0627"
    ],
    "name:bel_x_preferred":[
        "\u041c\u0443\u0440\u0430\u0432\u0430\u043d\u0430 \u0413\u0430\u0441\u043b\u0456\u043d\u0430"
    ],
    "name:ceb_x_preferred":[
        "Murowana Go\u015blina"
    ],
    "name:eus_x_preferred":[
        "Murowana Go\u015blina udalerria"
    ],
    "name:fas_x_preferred":[
        "\u06af\u0645\u06cc\u0646\u0627 \u0645\u0648\u0631\u0648\u0648\u0627\u0646\u0627 \u06af\u0648\u0634\u0644\u06cc\u0646\u0627"
    ],
    "name:fra_x_preferred":[
        "Murowana Go\u015blina"
    ],
    "name:ita_x_preferred":[
        "Murowana Go\u015blina"
    ],
    "name:nld_x_preferred":[
        "Murowana Go\u015blina"
    ],
    "name:pol_x_preferred":[
        "Murowana Go\u015blina"
    ],
    "name:rus_x_preferred":[
        "\u041c\u0443\u0440\u043e\u0432\u0430\u043d\u0430-\u0413\u043e\u0441\u043b\u0438\u043d\u0430"
    ],
    "name:slk_x_preferred":[
        "Gmina Murowana Go\u015blina"
    ],
    "name:ukr_x_preferred":[
        "\u0413\u043c\u0456\u043d\u0430 \u041c\u0443\u0440\u043e\u0432\u0430\u043d\u0430 \u0490\u043e\u0441\u043b\u0456\u043d\u0430"
    ],
    "name:vie_x_preferred":[
        "Gmina Murowana Go\u015blina"
    ],
    "name:war_x_preferred":[
        "Gmina Murowana Go\u015blina"
    ],
    "qs_pg:aaroncc":"PL",
    "qs_pg:name":"Gmina Murowana Go\u015blina",
    "qs_pg:name_adm0":"Polska",
    "qs_pg:name_adm1":"Wielkopolskie",
    "qs_pg:photos":35,
    "qs_pg:photos_1k":7,
    "qs_pg:photos_9k":1,
    "qs_pg:photos_9r":2,
    "qs_pg:photos_all":66,
    "qs_pg:photos_sr":2,
    "qs_pg:pop_sr":0,
    "qs_pg:qs_pg_placetype":"localadmin",
    "qs_pg:qs_pg_placetype_gp":"LocalAdmin",
    "qs_pg:woe_adm0":23424923,
    "woe:adm0_id":23424923,
    "woe:name_adm0":"Polska",
    "woe:name_adm1":"Wielkopolskie",
    "woe:placetype":"LocalAdmin",
    "wof:name":"Gmina Murowana Go\u015blina",
    "wof:placetype":"localadmin"
},
  "geometry": {"coordinates":[17.035492,52.633323],"type":"Point"}
}