{
  "type": "Feature",
  "properties": {
    "gn:admin1_code":"74.0",
    "gn:admin2_code":"1007.0",
    "gn:admin3_code":"100707.0",
    "gn:asciiname":"Owadow",
    "gn:country_code":"PL",
    "gn:dem":202,
    "gn:feature_class":"P",
    "gn:feature_code":"PPL",
    "gn:name":"Owad\u00f3w",
    "gn:population":0,
    "gn:timezone":"Europe/Warsaw",
    "iso:country":"PL",
    "name:fra_x_preferred":[
        "Owad\u00f3w"
    ],
    "name:pol_x_preferred":[
        "Owad\u00f3w"
    ],
    "name:ukr_x_preferred":[
        "\u041e\u0432\u0430\u0434\u0443\u0432"
    ],
    "wof:name":"Owadow",
    "wof:placetype":"locality"
},
  "geometry": {"coordinates":[20.13768,51.36655],"type":"Point"}
}