{
  "type": "Feature",
  "properties": {
    "gn:admin1_code":"74.0",
    "gn:admin2_code":"1017.0",
    "gn:admin3_code":"101704.0",
    "gn:asciiname":"Poreby",
    "gn:country_code":"PL",
    "gn:dem":201,
    "gn:feature_class":"P",
    "gn:feature_code":"PPL",
    "gn:name":"Por\u0119by",
    "gn:population":0,
    "gn:timezone":"Europe/Warsaw",
    "iso:country":"PL",
    "name:pol_x_preferred":[
        "Por\u0119by"
    ],
    "name:ukr_x_preferred":[
        "\u041f\u043e\u0440\u0435\u043c\u0431\u0438"
    ],
    "wof:name":"Poreby",
    "wof:placetype":"locality"
},
  "geometry": {"coordinates":[18.4409,51.14188],"type":"Point"}
}