{
  "type": "Feature",
  "properties": {
    "gn:admin1_code":"80.0",
    "gn:admin2_code":"1817.0",
    "gn:admin3_code":"181708.0",
    "gn:asciiname":"Lazy",
    "gn:country_code":"PL",
    "gn:dem":427,
    "gn:feature_class":"P",
    "gn:feature_code":"PPL",
    "gn:name":"\u0141azy",
    "gn:population":0,
    "gn:timezone":"Europe/Warsaw",
    "iso:country":"PL",
    "name:ceb_x_preferred":[
        "Lazy"
    ],
    "name:ces_x_preferred":[
        "Lazy"
    ],
    "name:deu_x_preferred":[
        "Lazy"
    ],
    "name:fra_x_preferred":[
        "Lazy"
    ],
    "name:nld_x_preferred":[
        "Lazy"
    ],
    "name:pol_x_preferred":[
        "Lazy"
    ],
    "name:por_x_preferred":[
        "Lazy"
    ],
    "name:spa_x_preferred":[
        "Lazy"
    ],
    "wof:name":"Lazy",
    "wof:placetype":"locality"
},
  "geometry": {"coordinates":[22.01667,49.53333],"type":"Point"}
}