{
  "type": "Feature",
  "properties": {
    "gn:admin1_code":"85.0",
    "gn:admin2_code":"2810.0",
    "gn:admin3_code":"281004.0",
    "gn:asciiname":"Nowe Kielbonki",
    "gn:country_code":"PL",
    "gn:dem":136,
    "gn:feature_class":"P",
    "gn:feature_code":"PPL",
    "gn:name":"Nowe Kie\u0142bonki",
    "gn:population":0,
    "gn:timezone":"Europe/Warsaw",
    "iso:country":"PL",
    "name:deu_x_preferred":[
        "Nowe Kie\u0142bonki"
    ],
    "name:fra_x_preferred":[
        "Nowe Kie\u0142bonki"
    ],
    "name:pol_x_preferred":[
        "Nowe Kie\u0142bonki"
    ],
    "name:ukr_x_preferred":[
        "\u041d\u043e\u0432\u0435 \u041a\u0435\u043b\u0431\u043e\u043d\u043a\u0456"
    ],
    "name:und_x_variant":[
        "Neukelbunken",
        "Nowe Kie\u0142bonk",
        "Neu Kelbonken"
    ],
    "wof:name":"Nowe Kielbonki",
    "wof:placetype":"locality"
},
  "geometry": {"coordinates":[21.31855,53.67204],"type":"Point"}
}