{
  "type": "Feature",
  "properties": {
    "gn:admin1_code":"86.0",
    "gn:admin2_code":"3030.0",
    "gn:admin3_code":"303002.0",
    "gn:asciiname":"Mikuszewo",
    "gn:country_code":"PL",
    "gn:dem":90,
    "gn:feature_class":"P",
    "gn:feature_code":"PPL",
    "gn:name":"Mikuszewo",
    "gn:population":0,
    "gn:timezone":"Europe/Warsaw",
    "iso:country":"PL",
    "name:fra_x_preferred":[
        "Mikuszewo"
    ],
    "name:pol_x_preferred":[
        "Mikuszewo"
    ],
    "name:ukr_x_preferred":[
        "\u041c\u0456\u043a\u0443\u0448\u0435\u0432\u043e"
    ],
    "wof:name":"Mikuszewo",
    "wof:placetype":"locality"
},
  "geometry": {"coordinates":[17.55076,52.17924],"type":"Point"}
}