{
  "type": "Feature",
  "properties": {
    "gn:admin1_code":"76.0",
    "gn:admin2_code":"811.0",
    "gn:admin3_code":"81103.0",
    "gn:asciiname":"Wierzchno",
    "gn:country_code":"PL",
    "gn:dem":62,
    "gn:feature_class":"P",
    "gn:feature_code":"PPL",
    "gn:name":"Wierzchno",
    "gn:population":0,
    "gn:timezone":"Europe/Warsaw",
    "iso:country":"PL",
    "name:fra_x_preferred":[
        "Wierzchno"
    ],
    "name:pol_x_preferred":[
        "Wierzchno"
    ],
    "name:ukr_x_preferred":[
        "\u0412\u0435\u0436\u0445\u043d\u043e"
    ],
    "wof:name":"Wierzchno",
    "wof:placetype":"locality"
},
  "geometry": {"coordinates":[14.76871,51.84776],"type":"Point"}
}