{
  "type": "Feature",
  "properties": {
    "gn:admin1_code":"76.0",
    "gn:admin2_code":"805.0",
    "gn:admin3_code":"80503.0",
    "gn:asciiname":"Polecko",
    "gn:country_code":"PL",
    "gn:dem":90,
    "gn:feature_class":"P",
    "gn:feature_code":"PPL",
    "gn:name":"Po\u0142\u0119cko",
    "gn:population":0,
    "gn:timezone":"Europe/Warsaw",
    "iso:country":"PL",
    "name:ceb_x_preferred":[
        "Po\u0142\u0119cko"
    ],
    "name:fra_x_preferred":[
        "Po\u0142\u0119cko"
    ],
    "name:pol_x_preferred":[
        "Po\u0142\u0119cko"
    ],
    "name:ukr_x_preferred":[
        "\u041f\u043e\u043b\u0435\u043d\u0446\u044c\u043a\u043e"
    ],
    "wof:name":"Polecko",
    "wof:placetype":"locality"
},
  "geometry": {"coordinates":[14.89609,52.40766],"type":"Point"}
}