{
  "type": "Feature",
  "properties": {
    "gn:admin1_code":"75.0",
    "gn:admin2_code":"618.0",
    "gn:admin3_code":"61811.0",
    "gn:asciiname":"Pasieki",
    "gn:country_code":"PL",
    "gn:dem":337,
    "gn:feature_class":"P",
    "gn:feature_code":"PPL",
    "gn:name":"Pasieki",
    "gn:population":0,
    "gn:timezone":"Europe/Warsaw",
    "iso:country":"PL",
    "name:fra_x_preferred":[
        "Pasieki"
    ],
    "name:pol_x_preferred":[
        "Pasieki"
    ],
    "name:ukr_x_preferred":[
        "\u041f\u0430\u0441\u0456\u043a\u0438"
    ],
    "wof:name":"Pasieki",
    "wof:placetype":"locality"
},
  "geometry": {"coordinates":[23.33718,50.44305],"type":"Point"}
}