{
  "type": "Feature",
  "properties": {
    "gn:admin1_code":"75.0",
    "gn:admin2_code":"601.0",
    "gn:admin3_code":"60110.0",
    "gn:asciiname":"Kozuszki",
    "gn:country_code":"PL",
    "gn:dem":163,
    "gn:feature_class":"P",
    "gn:feature_code":"PPL",
    "gn:name":"Ko\u017cuszki",
    "gn:population":0,
    "gn:timezone":"Europe/Warsaw",
    "iso:country":"PL",
    "name:fra_x_preferred":[
        "Ko\u017cuszki"
    ],
    "name:lit_x_preferred":[
        "Ko\u017eu\u0161kai"
    ],
    "name:pol_x_preferred":[
        "Ko\u017cuszki"
    ],
    "name:ukr_x_preferred":[
        "\u041a\u043e\u0436\u0443\u0448\u043a\u0456"
    ],
    "wof:name":"Kozuszki",
    "wof:placetype":"locality"
},
  "geometry": {"coordinates":[22.69501,52.09997],"type":"Point"}
}