{
  "type": "Feature",
  "properties": {
    "gn:gn_country":"PL",
    "gn:gn_fcode":"PPL",
    "gn:gn_pop":0,
    "iso:country":"PL",
    "name:ceb_x_preferred":[
        "Bukowiec"
    ],
    "name:deu_x_preferred":[
        "Bukowiec"
    ],
    "name:fra_x_preferred":[
        "Bukowiec"
    ],
    "name:nld_x_preferred":[
        "Bukowiec"
    ],
    "name:pol_x_preferred":[
        "Bukowiec"
    ],
    "qs_pg:aaroncc":"PL",
    "qs_pg:gn_country":"PL",
    "qs_pg:gn_fcode":"PPL",
    "qs_pg:gn_pop":0,
    "qs_pg:name":"Bukowiec",
    "qs_pg:name_adm0":"Polska",
    "qs_pg:name_adm1":"Wielkopolskie",
    "qs_pg:photos_9r":0,
    "qs_pg:photos_sr":0,
    "qs_pg:pop_sr":0,
    "qs_pg:qs_pg_placetype":"locality",
    "qs_pg:qs_pg_placetype_gp":"Town",
    "qs_pg:woe_adm0":23424923,
    "woe:adm0_id":23424923,
    "woe:name_adm0":"Polska",
    "woe:name_adm1":"Wielkopolskie",
    "woe:placetype":"Town",
    "wof:name":"Bukowiec",
    "wof:placetype":"locality"
},
  "geometry": {"coordinates":[16.24741,52.29326],"type":"Point"}
}