{
  "type": "Feature",
  "properties": {
    "gn:admin1_code":"74.0",
    "gn:admin2_code":"1014.0",
    "gn:admin3_code":"101402.0",
    "gn:asciiname":"Kamienna",
    "gn:country_code":"PL",
    "gn:dem":148,
    "gn:feature_class":"P",
    "gn:feature_code":"PPL",
    "gn:name":"Kamienna",
    "gn:population":0,
    "gn:timezone":"Europe/Warsaw",
    "iso:country":"PL",
    "name:ceb_x_preferred":[
        "Kamienna"
    ],
    "name:deu_x_preferred":[
        "Kamienna"
    ],
    "name:fra_x_preferred":[
        "Kamienna"
    ],
    "name:pol_x_preferred":[
        "Kamienna"
    ],
    "name:rus_x_preferred":[
        "\u041a\u0430\u043c\u0435\u043d\u043d\u0430"
    ],
    "name:ukr_x_preferred":[
        "\u041a\u0430\u043c\u0435\u043d\u043d\u0430"
    ],
    "wof:name":"Kamienna",
    "wof:placetype":"locality"
},
  "geometry": {"coordinates":[18.38322,51.66478],"type":"Point"}
}