{
  "type": "Feature",
  "properties": {
    "gn:admin1_code":"78.0",
    "gn:admin2_code":"1402.0",
    "gn:admin3_code":"140201.0",
    "gn:asciiname":"Bielin",
    "gn:country_code":"PL",
    "gn:dem":106,
    "gn:feature_class":"P",
    "gn:feature_code":"PPL",
    "gn:name":"Bielin",
    "gn:population":0,
    "gn:timezone":"Europe/Warsaw",
    "iso:country":"PL",
    "name:fra_x_preferred":[
        "Bielin"
    ],
    "name:pol_x_preferred":[
        "Bielin"
    ],
    "name:ukr_x_preferred":[
        "\u0411\u0435\u043b\u0456\u043d"
    ],
    "wof:name":"Bielin",
    "wof:placetype":"locality"
},
  "geometry": {"coordinates":[20.61667000000001,52.85],"type":"Point"}
}