{
  "type": "Feature",
  "properties": {
    "gn:admin1_code":"82.0",
    "gn:admin2_code":"2213.0",
    "gn:admin3_code":"221312.0",
    "gn:asciiname":"Jablowo",
    "gn:country_code":"PL",
    "gn:dem":76,
    "gn:feature_class":"P",
    "gn:feature_code":"PPL",
    "gn:name":"Jab\u0142owo",
    "gn:population":0,
    "gn:timezone":"Europe/Warsaw",
    "iso:country":"PL",
    "name:ceb_x_preferred":[
        "Jab\u0142owo"
    ],
    "name:nld_x_preferred":[
        "Jab\u0142owo"
    ],
    "name:pol_x_preferred":[
        "Jab\u0142owo"
    ],
    "name:ukr_x_preferred":[
        "\u042f\u0431\u043b\u043e\u0432\u043e"
    ],
    "name:urd_x_preferred":[
        "\u062c\u0628\u0648\u0627\u0648\u0648"
    ],
    "wof:name":"Jablowo",
    "wof:placetype":"locality"
},
  "geometry": {"coordinates":[18.57681,53.92562],"type":"Point"}
}