{
  "type": "Feature",
  "properties": {
    "gn:admin1_code":"74.0",
    "gn:admin2_code":"1020.0",
    "gn:admin3_code":"102009.0",
    "gn:asciiname":"Wola Branicka",
    "gn:country_code":"PL",
    "gn:dem":139,
    "gn:feature_class":"P",
    "gn:feature_code":"PPL",
    "gn:name":"Wola Branicka",
    "gn:population":0,
    "gn:timezone":"Europe/Warsaw",
    "iso:country":"PL",
    "wof:name":"Wola Branicka",
    "wof:placetype":"locality"
},
  "geometry": {"coordinates":[19.4696,51.9307],"type":"Point"}
}