{
  "type": "Feature",
  "properties": {
    "gn:admin1_code":"74.0",
    "gn:admin2_code":"1004.0",
    "gn:admin3_code":"100406.0",
    "gn:asciiname":"Czernikow",
    "gn:country_code":"PL",
    "gn:dem":104,
    "gn:feature_class":"P",
    "gn:feature_code":"PPL",
    "gn:name":"Czernik\u00f3w",
    "gn:population":0,
    "gn:timezone":"Europe/Warsaw",
    "iso:country":"PL",
    "name:und_x_variant":[
        "Czernik\u00f3w"
    ],
    "wof:name":"Czernikow",
    "wof:placetype":"locality"
},
  "geometry": {"coordinates":[19.41716,52.04377],"type":"Point"}
}