{
  "type": "Feature",
  "properties": {
    "gn:admin1_code":"82.0",
    "gn:admin2_code":"2201.0",
    "gn:admin3_code":"220103.0",
    "gn:asciiname":"Klosy",
    "gn:country_code":"PL",
    "gn:dem":145,
    "gn:feature_class":"P",
    "gn:feature_code":"PPL",
    "gn:name":"K\u0142osy",
    "gn:population":0,
    "gn:timezone":"Europe/Warsaw",
    "iso:country":"PL",
    "name:csb_x_preferred":[
        "K\u0142os\u00eb"
    ],
    "name:pol_x_preferred":[
        "K\u0142osy"
    ],
    "name:ukr_x_preferred":[
        "\u041a\u043b\u043e\u0441\u0438"
    ],
    "wof:name":"Klosy",
    "wof:placetype":"locality"
},
  "geometry": {"coordinates":[17.65709,54.32523000000001],"type":"Point"}
}