{
  "type": "Feature",
  "properties": {
    "gn:admin1_code":"76.0",
    "gn:admin2_code":"809.0",
    "gn:admin3_code":"80901.0",
    "gn:asciiname":"Podmokle Male",
    "gn:country_code":"PL",
    "gn:dem":60,
    "gn:feature_class":"P",
    "gn:feature_code":"PPL",
    "gn:name":"Podmok\u0142e Ma\u0142e",
    "gn:population":0,
    "gn:timezone":"Europe/Warsaw",
    "iso:country":"PL",
    "name:deu_x_preferred":[
        "Klein Posemuckel"
    ],
    "name:und_x_variant":[
        "Podmokle Ma\u0142e"
    ],
    "wof:name":"Podmokle Male",
    "wof:placetype":"locality"
},
  "geometry": {"coordinates":[15.80598,52.19161],"type":"Point"}
}