{
  "type": "Feature",
  "properties": {
    "gn:admin1_code":"76.0",
    "gn:admin2_code":"809.0",
    "gn:admin3_code":"80901.0",
    "gn:asciiname":"Podmokle Male",
    "gn:country_code":"PL",
    "gn:dem":60,
    "gn:feature_class":"P",
    "gn:feature_code":"PPL",
    "gn:name":"Podmok\u0142e Ma\u0142e",
    "gn:population":0,
    "gn:timezone":"Europe/Warsaw",
    "iso:country":"PL",
    "name:deu_x_preferred":[
        "Klein Posemuckel"
    ],
    "name:deu_x_variant":[
        "Podmokle Ma\u0142e"
    ],
    "name:fra_x_preferred":[
        "Podmokle Ma\u0142e"
    ],
    "name:pol_x_preferred":[
        "Podmokle Ma\u0142e"
    ],
    "name:ukr_x_preferred":[
        "\u041f\u043e\u0434\u043c\u043e\u043a\u043b\u0435-\u041c\u0430\u043b\u0435"
    ],
    "wof:name":"Podmokle Male",
    "wof:placetype":"locality"
},
  "geometry": {"coordinates":[15.80598,52.19161],"type":"Point"}
}