{
  "type": "Feature",
  "properties": {
    "gn:admin1_code":"76.0",
    "gn:admin2_code":"808.0",
    "gn:admin3_code":"80805.0",
    "gn:asciiname":"Rudgerzowice",
    "gn:country_code":"PL",
    "gn:dem":86,
    "gn:feature_class":"P",
    "gn:feature_code":"PPL",
    "gn:name":"Rudgerzowice",
    "gn:population":0,
    "gn:timezone":"Europe/Warsaw",
    "iso:country":"PL",
    "name:fra_x_preferred":[
        "Rudgerzowice"
    ],
    "name:pol_x_preferred":[
        "Rudgerzowice"
    ],
    "name:ukr_x_preferred":[
        "\u0420\u0443\u0434\u0491\u0435\u0436\u043e\u0432\u0456\u0446\u0435"
    ],
    "wof:name":"Rudgerzowice",
    "wof:placetype":"locality"
},
  "geometry": {"coordinates":[15.55485,52.19138],"type":"Point"}
}