{
  "type": "Feature",
  "properties": {
    "iso:country":"PL",
    "name:eng_x_preferred":[
        "Osiedle Hetmanskie"
    ],
    "name:pol_x_preferred":[
        "Osiedle Hetma\u0144skie"
    ],
    "wof:name":"Osiedle Hetmanskie",
    "wof:placetype":"neighbourhood"
},
  "geometry": {"coordinates":[16.89537660812032,52.38873087303581],"type":"Point"}
}