{
  "type": "Feature",
  "properties": {
    "gn:admin1_code":"85.0",
    "gn:admin2_code":"2806.0",
    "gn:admin3_code":"280604.0",
    "gn:asciiname":"Upalty Srednie",
    "gn:country_code":"PL",
    "gn:dem":130,
    "gn:feature_class":"P",
    "gn:feature_code":"PPL",
    "gn:name":"Upa\u0142ty \u015arednie",
    "gn:population":0,
    "gn:timezone":"Europe/Warsaw",
    "iso:country":"PL",
    "wof:name":"Upalty Srednie",
    "wof:placetype":"locality"
},
  "geometry": {"coordinates":[21.88548,54.02047],"type":"Point"}
}