{
  "type": "Feature",
  "properties": {
    "gn:admin1_code":"86.0",
    "gn:admin2_code":"3064.0",
    "gn:admin3_code":"306401.0",
    "gn:asciiname":"Piatkowo",
    "gn:country_code":"PL",
    "gn:dem":92,
    "gn:feature_class":"P",
    "gn:feature_code":"PPL",
    "gn:name":"Pi\u0105tkowo",
    "gn:population":0,
    "gn:timezone":"Europe/Warsaw",
    "iso:country":"PL",
    "wof:name":"Piatkowo",
    "wof:placetype":"neighbourhood"
},
  "geometry": {"coordinates":[16.91225,52.45321],"type":"Point"}
}