{
  "type": "Feature",
  "properties": {
    "gn:admin1_code":"75.0",
    "gn:admin2_code":"614.0",
    "gn:admin3_code":"61409.0",
    "gn:asciiname":"Janow",
    "gn:country_code":"PL",
    "gn:dem":149,
    "gn:feature_class":"P",
    "gn:feature_code":"PPL",
    "gn:name":"Jan\u00f3w",
    "gn:population":0,
    "gn:timezone":"Europe/Warsaw",
    "iso:country":"PL",
    "name:fra_x_preferred":[
        "Jan\u00f3w"
    ],
    "name:pol_x_preferred":[
        "Jan\u00f3w"
    ],
    "name:szl_x_preferred":[
        "Jan\u016fw"
    ],
    "name:ukr_x_preferred":[
        "\u042f\u043d\u0443\u0432"
    ],
    "name:urd_x_preferred":[
        "\u062c\u0646\u0648\u0648"
    ],
    "wof:name":"Janow",
    "wof:placetype":"locality"
},
  "geometry": {"coordinates":[21.85215,51.41045],"type":"Point"}
}