{
  "type": "Feature",
  "properties": {
    "gn:admin1_code":"75.0",
    "gn:admin2_code":"614.0",
    "gn:admin3_code":"61409.0",
    "gn:asciiname":"Janow",
    "gn:country_code":"PL",
    "gn:dem":149,
    "gn:feature_class":"P",
    "gn:feature_code":"PPL",
    "gn:name":"Jan\u00f3w",
    "gn:population":0,
    "gn:timezone":"Europe/Warsaw",
    "iso:country":"PL",
    "wof:name":"Janow",
    "wof:placetype":"locality"
},
  "geometry": {"coordinates":[21.85215,51.41045],"type":"Point"}
}