{
  "type": "Feature",
  "properties": {
    "gn:admin1_code":"74.0",
    "gn:admin2_code":"1005.0",
    "gn:admin3_code":"100507.0",
    "gn:asciiname":"Dabkowice",
    "gn:country_code":"PL",
    "gn:dem":101,
    "gn:feature_class":"P",
    "gn:feature_code":"PPL",
    "gn:name":"D\u0105bkowice",
    "gn:population":0,
    "gn:timezone":"Europe/Warsaw",
    "iso:country":"PL",
    "name:azb_x_preferred":[
        "\u062f\u0627\u0646\u0628\u06a9\u0648\u0648\u06cc\u062a\u0633\u0647 \u0642\u0648\u0631\u0646\u0647"
    ],
    "name:fas_x_preferred":[
        "\u062f\u0627\u0646\u0628\u06a9\u0648\u0648\u06cc\u062a\u0633\u0647 \u06af\u0648\u0631\u0646\u0647"
    ],
    "name:fra_x_preferred":[
        "D\u0105bkowice G\u00f3rne"
    ],
    "name:nld_x_preferred":[
        "D\u0105bkowice G\u00f3rne"
    ],
    "name:pol_x_preferred":[
        "D\u0105bkowice G\u00f3rne"
    ],
    "name:ukr_x_preferred":[
        "\u0414\u043e\u043c\u0431\u043a\u043e\u0432\u0456\u0446\u0435-\u0490\u0443\u0440\u043d\u0435"
    ],
    "name:und_x_variant":[
        "D\u0105bkowice G\u00f3rne",
        "D\u0105bkowice"
    ],
    "wof:name":"Dabkowice",
    "wof:placetype":"locality"
},
  "geometry": {"coordinates":[19.85503,52.0617],"type":"Point"}
}