{
  "type": "Feature",
  "properties": {
    "gn:admin1_code":"74.0",
    "gn:admin2_code":"1005.0",
    "gn:admin3_code":"100507.0",
    "gn:asciiname":"Dabkowice",
    "gn:country_code":"PL",
    "gn:dem":101,
    "gn:feature_class":"P",
    "gn:feature_code":"PPL",
    "gn:name":"D\u0105bkowice",
    "gn:population":0,
    "gn:timezone":"Europe/Warsaw",
    "iso:country":"PL",
    "name:und_x_variant":[
        "D\u0105bkowice G\u00f3rne",
        "D\u0105bkowice"
    ],
    "wof:name":"Dabkowice",
    "wof:placetype":"locality"
},
  "geometry": {"coordinates":[19.85503,52.0617],"type":"Point"}
}