{
  "type": "Feature",
  "properties": {
    "gn:admin1_code":"80.0",
    "gn:admin2_code":"1805.0",
    "gn:admin3_code":"180503.0",
    "gn:asciiname":"Dobrynia",
    "gn:country_code":"PL",
    "gn:dem":302,
    "gn:feature_class":"P",
    "gn:feature_code":"PPL",
    "gn:name":"Dobrynia",
    "gn:population":0,
    "gn:timezone":"Europe/Warsaw",
    "iso:country":"PL",
    "name:pol_x_preferred":[
        "Dobrynia"
    ],
    "name:ukr_x_preferred":[
        "\u0414\u043e\u0431\u0440\u0438\u043d\u044f"
    ],
    "wof:name":"Dobrynia",
    "wof:placetype":"locality"
},
  "geometry": {"coordinates":[21.41305,49.63438],"type":"Point"}
}