{
  "type": "Feature",
  "properties": {
    "gn:admin1_code":"77.0",
    "gn:admin2_code":"1206.0",
    "gn:admin3_code":"120613.0",
    "gn:asciiname":"Wielmoza",
    "gn:country_code":"PL",
    "gn:dem":412,
    "gn:feature_class":"P",
    "gn:feature_code":"PPL",
    "gn:name":"Wielmo\u017ca",
    "gn:population":0,
    "gn:timezone":"Europe/Warsaw",
    "iso:country":"PL",
    "name:ceb_x_preferred":[
        "Wielmo\u017ca"
    ],
    "name:pol_x_preferred":[
        "Wielmo\u017ca"
    ],
    "name:rus_x_preferred":[
        "\u0412\u0435\u043b\u044c\u043c\u043e\u0436\u0430"
    ],
    "name:ukr_x_preferred":[
        "\u0412\u0435\u043b\u044c\u043c\u043e\u0436\u0430"
    ],
    "wof:name":"Wielmoza",
    "wof:placetype":"locality"
},
  "geometry": {"coordinates":[19.8159,50.26071],"type":"Point"}
}