{
  "type": "Feature",
  "properties": {
    "gn:gn_country":"PL",
    "gn:gn_fcode":"PPLA3",
    "gn:gn_pop":1876,
    "gn:population":1876,
    "iso:country":"PL",
    "name:azb_x_preferred":[
        "\u0645\u0646\u0642\u0648\u0648"
    ],
    "name:ceb_x_preferred":[
        "Mni\u00f3w"
    ],
    "name:deu_x_preferred":[
        "Mni\u00f3w"
    ],
    "name:fas_x_preferred":[
        "\u0645\u0646\u06af\u0648\u0648"
    ],
    "name:fra_x_preferred":[
        "Mni\u00f3w"
    ],
    "name:nld_x_preferred":[
        "Mni\u00f3w"
    ],
    "name:pol_x_preferred":[
        "Mni\u00f3w"
    ],
    "name:ukr_x_preferred":[
        "\u041c\u043d\u044e\u0432"
    ],
    "qs_pg:aaroncc":"PL",
    "qs_pg:gn_country":"PL",
    "qs_pg:gn_fcode":"PPLA3",
    "qs_pg:gn_pop":1876,
    "qs_pg:name":"Mni\u00f3w",
    "qs_pg:name_adm0":"Polska",
    "qs_pg:name_adm1":"Swi\u0119tokrzyskie",
    "qs_pg:photos_9k":1,
    "qs_pg:photos_9r":1,
    "qs_pg:photos_all":1,
    "qs_pg:photos_sr":0,
    "qs_pg:pop_sr":3,
    "qs_pg:qs_pg_placetype":"localadmin",
    "qs_pg:qs_pg_placetype_gp":"LocalAdmin",
    "qs_pg:woe_adm0":23424923,
    "woe:adm0_id":23424923,
    "woe:name_adm0":"Polska",
    "woe:name_adm1":"Swi\u0119tokrzyskie",
    "woe:placetype":"LocalAdmin",
    "wof:name":"Mni\u00f3w",
    "wof:placetype":"localadmin",
    "wof:population":1876
},
  "geometry": {"coordinates":[20.48427,51.01224],"type":"Point"}
}