{
  "type": "Feature",
  "properties": {
    "gn:admin1_code":"86.0",
    "gn:admin2_code":"3007.0",
    "gn:admin3_code":"300704.0",
    "gn:asciiname":"Kolonia Kakawa",
    "gn:country_code":"PL",
    "gn:dem":123,
    "gn:feature_class":"P",
    "gn:feature_code":"PPL",
    "gn:name":"Kolonia Kakawa",
    "gn:population":0,
    "gn:timezone":"Europe/Warsaw",
    "iso:country":"PL",
    "name:pol_x_preferred":[
        "Kakawa-Kolonia"
    ],
    "name:ukr_x_preferred":[
        "\u041a\u0430\u043a\u0430\u0432\u0430-\u041a\u043e\u043b\u044c\u043e\u043d\u0456\u044f"
    ],
    "name:und_x_variant":[
        "Kakawa",
        "Kolonja Kakawa",
        "Kolonia Kakawa"
    ],
    "wof:name":"Kolonia Kakawa",
    "wof:placetype":"locality"
},
  "geometry": {"coordinates":[18.17548,51.60845],"type":"Point"}
}