{
  "type": "Feature",
  "properties": {
    "gn:country":"PL",
    "gn:fcode":"PPL",
    "gn:population":0,
    "iso:country":"PL",
    "name:ast_x_preferred":[
        "\u0141ugi Ujskie"
    ],
    "name:azb_x_preferred":[
        "\u0648\u0648\u0642\u06cc \u0627\u0648\u06cc\u0633\u06a9\u06cc\u0647"
    ],
    "name:ces_x_preferred":[
        "\u0141ugi Ujskie"
    ],
    "name:che_x_preferred":[
        "\u041b\u0443\u0433\u0438-\u0423\u0439\u0441\u043a\u0438"
    ],
    "name:deu_x_preferred":[
        "\u0141ugi Ujskie"
    ],
    "name:eng_x_preferred":[
        "\u0141ugi Ujskie"
    ],
    "name:fas_x_preferred":[
        "\u0648\u0648\u06af\u06cc \u0627\u0648\u06cc\u0633\u06a9\u06cc\u0647"
    ],
    "name:fra_x_preferred":[
        "\u0141ugi Ujskie"
    ],
    "name:nan_x_preferred":[
        "\u0141ugi Ujskie"
    ],
    "name:nld_x_preferred":[
        "\u0141ugi Ujskie"
    ],
    "name:pol_x_preferred":[
        "\u0141ugi Ujskie"
    ],
    "name:tat_x_preferred":[
        "\u041b\u0443\u0433\u0438-\u0423\u0439\u0441\u043a\u0438"
    ],
    "name:ukr_x_preferred":[
        "\u041b\u0443\u0491\u0456-\u0423\u0439\u0441\u044c\u043a\u0456"
    ],
    "name:und_x_variant":[
        "Usch Hauland"
    ],
    "qs_pg:aaroncc":"PL",
    "qs_pg:gn_country":"PL",
    "qs_pg:gn_fcode":"PPL",
    "qs_pg:gn_pop":0,
    "qs_pg:name":"\u0141ugi Ujskie",
    "qs_pg:name_adm0":"Polska",
    "qs_pg:name_adm1":"Wielkopolskie",
    "qs_pg:photos":7,
    "qs_pg:photos_1k":1,
    "qs_pg:photos_9k":1,
    "qs_pg:photos_9r":1,
    "qs_pg:photos_all":7,
    "qs_pg:photos_sr":1,
    "qs_pg:pop_sr":0,
    "qs_pg:qs_pg_placetype":"locality",
    "qs_pg:qs_pg_placetype_gp":"Town",
    "qs_pg:woe_adm0":23424923,
    "woe:adm0_id":23424923,
    "woe:name_adm0":"Polska",
    "woe:name_adm1":"Wielkopolskie",
    "woe:placetype":"Town",
    "wof:name":"\u0141ugi Ujskie",
    "wof:placetype":"locality"
},
  "geometry": {"coordinates":[16.71104,53.07788],"type":"Point"}
}