{
  "type": "Feature",
  "properties": {
    "gn:admin1_code":"72.0",
    "gn:admin2_code":"208.0",
    "gn:admin3_code":"20806.0",
    "gn:asciiname":"Nowa Lomnica",
    "gn:cc2":"PL",
    "gn:country_code":"PL",
    "gn:dem":425,
    "gn:feature_class":"P",
    "gn:feature_code":"PPL",
    "gn:name":"Nowa \u0141omnica",
    "gn:population":0,
    "gn:timezone":"Europe/Warsaw",
    "iso:country":"PL",
    "name:deu_x_preferred":[
        "Neu Lomnitz"
    ],
    "name:deu_x_variant":[
        "Neu Lommnitz",
        "Nowa \u0141omnica"
    ],
    "name:pol_x_preferred":[
        "Nowa \u0141omnica"
    ],
    "name:ukr_x_preferred":[
        "\u041d\u043e\u0432\u0430 \u041b\u043e\u043c\u043d\u0438\u0446\u044f"
    ],
    "wof:name":"Nowa Lomnica",
    "wof:placetype":"locality"
},
  "geometry": {"coordinates":[16.56361,50.35641],"type":"Point"}
}