{
  "type": "Feature",
  "properties": {
    "gn:admin1_code":"84.0",
    "gn:admin2_code":"2610.0",
    "gn:admin3_code":"261003.0",
    "gn:asciiname":"Wystepa",
    "gn:country_code":"PL",
    "gn:dem":431,
    "gn:feature_class":"P",
    "gn:feature_code":"PPL",
    "gn:name":"Wyst\u0119pa",
    "gn:population":0,
    "gn:timezone":"Europe/Warsaw",
    "iso:country":"PL",
    "wof:name":"Wystepa",
    "wof:placetype":"locality"
},
  "geometry": {"coordinates":[20.74373,50.98005],"type":"Point"}
}