{
  "type": "Feature",
  "properties": {
    "gn:admin1_code":"82.0",
    "gn:admin2_code":"2215.0",
    "gn:admin3_code":"221502.0",
    "gn:asciiname":"Zagorze",
    "gn:country_code":"PL",
    "gn:dem":38,
    "gn:feature_class":"P",
    "gn:feature_code":"PPL",
    "gn:name":"Zag\u00f3rze",
    "gn:population":0,
    "gn:timezone":"Europe/Warsaw",
    "iso:country":"PL",
    "wof:name":"Zagorze",
    "wof:placetype":"neighbourhood"
},
  "geometry": {"coordinates":[18.38064,54.56112],"type":"Point"}
}