{
  "type": "Feature",
  "properties": {
    "gn:admin1_code":"72.0",
    "gn:admin2_code":"208.0",
    "gn:admin3_code":"20813.0",
    "gn:asciiname":"Goszow",
    "gn:country_code":"PL",
    "gn:dem":529,
    "gn:feature_class":"P",
    "gn:feature_code":"PPL",
    "gn:name":"Gosz\u00f3w",
    "gn:population":0,
    "gn:timezone":"Europe/Warsaw",
    "iso:country":"PL",
    "name:azb_x_preferred":[
        "\u0642\u0648\u0634\u0648\u0648"
    ],
    "name:deu_x_preferred":[
        "Gosz\u00f3w"
    ],
    "name:fas_x_preferred":[
        "\u06af\u0648\u0634\u0648\u0648"
    ],
    "name:pol_x_preferred":[
        "Gosz\u00f3w"
    ],
    "name:ukr_x_preferred":[
        "\u0490\u043e\u0448\u0443\u0432"
    ],
    "wof:name":"Goszow",
    "wof:placetype":"neighbourhood"
},
  "geometry": {"coordinates":[16.88332999999999,50.28333],"type":"Point"}
}