{
  "type": "Feature",
  "properties": {
    "gn:admin1_code":"87.0",
    "gn:admin2_code":"3203.0",
    "gn:admin3_code":"320303.0",
    "gn:asciiname":"Gizyno",
    "gn:country_code":"PL",
    "gn:dem":107,
    "gn:feature_class":"P",
    "gn:feature_code":"PPL",
    "gn:name":"Gi\u017cyno",
    "gn:population":0,
    "gn:timezone":"Europe/Warsaw",
    "iso:country":"PL",
    "name:pol_x_preferred":[
        "Gi\u017cyno"
    ],
    "name:ukr_x_preferred":[
        "\u0490\u0456\u0436\u0438\u043d\u043e"
    ],
    "name:vie_x_preferred":[
        "Gi\u017cyno"
    ],
    "wof:name":"Gizyno",
    "wof:placetype":"locality"
},
  "geometry": {"coordinates":[15.94144,53.33591],"type":"Point"}
}