{
  "type": "Feature",
  "properties": {
    "gn:admin1_code":"86.0",
    "gn:admin2_code":"3026.0",
    "gn:admin3_code":"302601.0",
    "gn:asciiname":"Brodniczka",
    "gn:country_code":"PL",
    "gn:dem":60,
    "gn:feature_class":"P",
    "gn:feature_code":"PPL",
    "gn:name":"Brodniczka",
    "gn:population":0,
    "gn:timezone":"Europe/Warsaw",
    "iso:country":"PL",
    "wof:name":"Brodniczka",
    "wof:placetype":"locality"
},
  "geometry": {"coordinates":[16.91884,52.16682],"type":"Point"}
}