{
  "type": "Feature",
  "properties": {
    "gn:admin1_code":"74.0",
    "gn:admin2_code":"1010.0",
    "gn:admin3_code":"101009.0",
    "gn:asciiname":"Kolo",
    "gn:country_code":"PL",
    "gn:dem":184,
    "gn:feature_class":"P",
    "gn:feature_code":"PPL",
    "gn:name":"Ko\u0142o",
    "gn:population":0,
    "gn:timezone":"Europe/Warsaw",
    "iso:country":"PL",
    "wof:name":"Kolo",
    "wof:placetype":"locality"
},
  "geometry": {"coordinates":[19.83032,51.42683],"type":"Point"}
}