{
  "type": "Feature",
  "properties": {
    "gn:admin1_code":"78.0",
    "gn:admin2_code":"1425.0",
    "gn:admin3_code":"142509.0",
    "gn:asciiname":"Wrzeszczowska Wola",
    "gn:country_code":"PL",
    "gn:dem":166,
    "gn:feature_class":"P",
    "gn:feature_code":"PPL",
    "gn:name":"Wrzeszczowska Wola",
    "gn:population":0,
    "gn:timezone":"Europe/Warsaw",
    "iso:country":"PL",
    "name:fra_x_preferred":[
        "Wola Wrzeszczowska"
    ],
    "name:pol_x_preferred":[
        "Wola Wrzeszczowska"
    ],
    "name:ukr_x_preferred":[
        "\u0412\u043e\u043b\u044f-\u0412\u0436\u0435\u0449\u043e\u0432\u0441\u044c\u043a\u0430"
    ],
    "name:und_x_variant":[
        "Wola Wrzeszczowska",
        "Wrzeszczowska Wola"
    ],
    "wof:name":"Wrzeszczowska Wola",
    "wof:placetype":"locality"
},
  "geometry": {"coordinates":[20.80977,51.50422],"type":"Point"}
}