{
  "type": "Feature",
  "properties": {
    "gn:admin1_code":"73.0",
    "gn:admin2_code":"414.0",
    "gn:admin3_code":"41408.0",
    "gn:asciiname":"Nieciszewo",
    "gn:country_code":"PL",
    "gn:dem":95,
    "gn:feature_class":"P",
    "gn:feature_code":"PPL",
    "gn:name":"Nieciszewo",
    "gn:population":0,
    "gn:timezone":"Europe/Warsaw",
    "iso:country":"PL",
    "name:pol_x_preferred":[
        "Nieciszewo"
    ],
    "name:ukr_x_preferred":[
        "\u041d\u0435\u0446\u0438\u0448\u0435\u0432\u043e"
    ],
    "wof:name":"Nieciszewo",
    "wof:placetype":"locality"
},
  "geometry": {"coordinates":[18.15654,53.32502],"type":"Point"}
}