{
  "type": "Feature",
  "properties": {
    "gn:country":"PL",
    "gn:fcode":"PPLA3",
    "gn:population":14209,
    "iso:country":"PL",
    "name:bel_x_preferred":[
        "\u0425\u043e\u0439\u043d\u0430\u045e"
    ],
    "name:cat_x_preferred":[
        "Chojn\u00f3w"
    ],
    "name:ceb_x_preferred":[
        "Chojn\u00f3w"
    ],
    "name:ces_x_preferred":[
        "Chojn\u00f3w"
    ],
    "name:deu_x_historical":[
        "Haynau"
    ],
    "name:deu_x_preferred":[
        "Haynau"
    ],
    "name:deu_x_variant":[
        "Chojn\u00f3w"
    ],
    "name:eng_x_preferred":[
        "Chojn\u00f3w"
    ],
    "name:epo_x_preferred":[
        "Chojn\u00f3w"
    ],
    "name:eus_x_preferred":[
        "Chojn\u00f3w"
    ],
    "name:fas_x_preferred":[
        "\u062e\u0648\u06cc\u0646\u0648\u0641"
    ],
    "name:fra_x_preferred":[
        "Chojn\u00f3w"
    ],
    "name:hun_x_preferred":[
        "Chojn\u00f3w"
    ],
    "name:ind_x_preferred":[
        "Chojn\u00f3w"
    ],
    "name:ita_x_preferred":[
        "Chojn\u00f3w"
    ],
    "name:jav_x_preferred":[
        "Chojn\u00f3w"
    ],
    "name:lat_x_preferred":[
        "Hainovia"
    ],
    "name:lav_x_preferred":[
        "Hojnova"
    ],
    "name:msa_x_preferred":[
        "Chojn\u00f3w"
    ],
    "name:nld_x_preferred":[
        "Chojn\u00f3w"
    ],
    "name:nor_x_preferred":[
        "Chojn\u00f3w"
    ],
    "name:pol_x_preferred":[
        "Chojn\u00f3w"
    ],
    "name:por_x_preferred":[
        "Chojn\u00f3w"
    ],
    "name:ron_x_preferred":[
        "Chojn\u00f3w"
    ],
    "name:rus_x_preferred":[
        "\u0425\u043e\u0439\u043d\u0443\u0432"
    ],
    "name:slk_x_preferred":[
        "Chojn\u00f3w"
    ],
    "name:spa_x_preferred":[
        "Chojn\u00f3w"
    ],
    "name:srp_x_preferred":[
        "\u0425\u043e\u0458\u043d\u043e\u0432"
    ],
    "name:swe_x_preferred":[
        "Chojn\u00f3w"
    ],
    "name:szl_x_preferred":[
        "Chojn\u016fw"
    ],
    "name:tur_x_preferred":[
        "Chojn\u00f3w"
    ],
    "name:ukr_x_preferred":[
        "\u0425\u043e\u0439\u043d\u0443\u0432"
    ],
    "name:vie_x_preferred":[
        "Chojn\u00f3w"
    ],
    "name:war_x_preferred":[
        "Chojn\u00f3w"
    ],
    "name:zho_x_preferred":[
        "\u970d\u4f0a\u52aa\u592b"
    ],
    "qs_pg:aaroncc":"PL",
    "qs_pg:gn_country":"PL",
    "qs_pg:gn_fcode":"PPLA3",
    "qs_pg:gn_pop":14209,
    "qs_pg:name":"Chojn\u00f3w",
    "qs_pg:name_adm0":"Polska",
    "qs_pg:name_adm1":"Dolnosl\u0105skie",
    "qs_pg:photos":8,
    "qs_pg:photos_1k":2,
    "qs_pg:photos_9k":1,
    "qs_pg:photos_9r":1,
    "qs_pg:photos_all":8,
    "qs_pg:photos_sr":1,
    "qs_pg:pop_sr":6,
    "qs_pg:qs_pg_placetype":"localadmin",
    "qs_pg:qs_pg_placetype_gp":"LocalAdmin",
    "qs_pg:woe_adm0":23424923,
    "woe:adm0_id":23424923,
    "woe:name_adm0":"Polska",
    "woe:name_adm1":"Dolnosl\u0105skie",
    "woe:placetype":"LocalAdmin",
    "wof:name":"Chojn\u00f3w",
    "wof:placetype":"localadmin",
    "wof:population":14209
},
  "geometry": {"coordinates":[15.93661,51.27373],"type":"Point"}
}