{
  "type": "Feature",
  "properties": {
    "gn:admin1_code":"75.0",
    "gn:admin2_code":"611.0",
    "gn:admin3_code":"61105.0",
    "gn:asciiname":"Sieciaszka Pierwsza",
    "gn:country_code":"PL",
    "gn:dem":164,
    "gn:feature_class":"P",
    "gn:feature_code":"PPL",
    "gn:name":"Si\u0119ciaszka Pierwsza",
    "gn:population":0,
    "gn:timezone":"Europe/Warsaw",
    "iso:country":"PL",
    "name:fra_x_preferred":[
        "Si\u0119ciaszka Pierwsza"
    ],
    "name:pol_x_preferred":[
        "Si\u0119ciaszka Pierwsza"
    ],
    "name:ukr_x_preferred":[
        "\u0421\u0435\u043d\u0446\u044f\u0448\u043a\u0430-\u041f\u0435\u0440\u0448\u0430"
    ],
    "name:und_x_variant":[
        "Sienciaszka"
    ],
    "wof:name":"Sieciaszka Pierwsza",
    "wof:placetype":"locality"
},
  "geometry": {"coordinates":[22.31094,51.92567],"type":"Point"}
}