{
  "type": "Feature",
  "properties": {
    "gn:admin1_code":"75.0",
    "gn:admin2_code":"603.0",
    "gn:admin3_code":"60308.0",
    "gn:asciiname":"Wolka Kanska",
    "gn:country_code":"PL",
    "gn:dem":176,
    "gn:feature_class":"P",
    "gn:feature_code":"PPL",
    "gn:name":"W\u00f3lka Ka\u0144ska",
    "gn:population":0,
    "gn:timezone":"Europe/Warsaw",
    "iso:country":"PL",
    "name:fra_x_preferred":[
        "W\u00f3lka Ka\u0144ska"
    ],
    "name:pol_x_preferred":[
        "W\u00f3lka Ka\u0144ska"
    ],
    "name:ukr_x_preferred":[
        "\u0412\u0443\u043b\u044c\u043a\u0430-\u041a\u0430\u043d\u0441\u044c\u043a\u0430"
    ],
    "wof:name":"Wolka Kanska",
    "wof:placetype":"locality"
},
  "geometry": {"coordinates":[23.07374,51.13377],"type":"Point"}
}