{
  "type": "Feature",
  "properties": {
    "gn:admin1_code":"73.0",
    "gn:admin2_code":"407.0",
    "gn:admin3_code":"40708.0",
    "gn:asciiname":"Glinki",
    "gn:country_code":"PL",
    "gn:dem":69,
    "gn:feature_class":"P",
    "gn:feature_code":"PPL",
    "gn:name":"Glinki",
    "gn:population":0,
    "gn:timezone":"Europe/Warsaw",
    "iso:country":"PL",
    "name:pol_x_preferred":[
        "Glinki"
    ],
    "name:ukr_x_preferred":[
        "\u0490\u043b\u0456\u043d\u043a\u0456"
    ],
    "wof:name":"Glinki",
    "wof:placetype":"locality"
},
  "geometry": {"coordinates":[18.34315,52.94899],"type":"Point"}
}