{
  "type": "Feature",
  "properties": {
    "gn:admin1_code":"86.0",
    "gn:admin2_code":"3002.0",
    "gn:admin3_code":"300205.0",
    "gn:asciiname":"Milkowo",
    "gn:country_code":"PL",
    "gn:dem":76,
    "gn:feature_class":"P",
    "gn:feature_code":"PPL",
    "gn:name":"Mi\u0142kowo",
    "gn:population":0,
    "gn:timezone":"Europe/Warsaw",
    "iso:country":"PL",
    "name:ceb_x_preferred":[
        "Mi\u0142kowo"
    ],
    "name:fra_x_preferred":[
        "Mi\u0142kowo"
    ],
    "name:pol_x_preferred":[
        "Mi\u0142kowo"
    ],
    "name:ukr_x_preferred":[
        "\u041c\u0456\u043b\u043a\u043e\u0432\u043e"
    ],
    "wof:name":"Milkowo",
    "wof:placetype":"locality"
},
  "geometry": {"coordinates":[16.52233,52.81811],"type":"Point"}
}