{
  "type": "Feature",
  "properties": {
    "gn:admin1_code":"74.0",
    "gn:admin2_code":"1020.0",
    "gn:admin3_code":"102004.0",
    "gn:asciiname":"Chrosno",
    "gn:country_code":"PL",
    "gn:dem":152,
    "gn:feature_class":"P",
    "gn:feature_code":"PPL",
    "gn:name":"Chro\u015bno",
    "gn:population":0,
    "gn:timezone":"Europe/Warsaw",
    "iso:country":"PL",
    "name:pol_x_preferred":[
        "Chro\u015bno"
    ],
    "name:ukr_x_preferred":[
        "\u0425\u0440\u043e\u0441\u044c\u043d\u043e"
    ],
    "wof:name":"Chrosno",
    "wof:placetype":"locality"
},
  "geometry": {"coordinates":[19.20868,51.8541],"type":"Point"}
}