{
  "type": "Feature",
  "properties": {
    "gn:admin1_code":"79.0",
    "gn:admin2_code":"1604.0",
    "gn:admin3_code":"160404.0",
    "gn:asciiname":"Komorzno",
    "gn:country_code":"PL",
    "gn:dem":188,
    "gn:feature_class":"P",
    "gn:feature_code":"PPL",
    "gn:name":"Komorzno",
    "gn:population":0,
    "gn:timezone":"Europe/Warsaw",
    "iso:country":"PL",
    "name:und_x_variant":[
        "Reinersdorf",
        "Kamarzno",
        "Komorzno"
    ],
    "wof:name":"Komorzno",
    "wof:placetype":"locality"
},
  "geometry": {"coordinates":[18.07002,51.11872],"type":"Point"}
}