{
  "type": "Feature",
  "properties": {
    "gn:admin1_code":"78.0",
    "gn:admin2_code":"1424.0",
    "gn:admin3_code":"142402.0",
    "gn:asciiname":"Bartodzieje",
    "gn:country_code":"PL",
    "gn:dem":101,
    "gn:feature_class":"P",
    "gn:feature_code":"PPL",
    "gn:name":"Bartodzieje",
    "gn:population":0,
    "gn:timezone":"Europe/Warsaw",
    "iso:country":"PL",
    "wof:name":"Bartodzieje",
    "wof:placetype":"locality"
},
  "geometry": {"coordinates":[21.19473,52.68885],"type":"Point"}
}