{
  "type": "Feature",
  "properties": {
    "gn:admin1_code":"73.0",
    "gn:admin2_code":"410.0",
    "gn:admin3_code":"41005.0",
    "gn:asciiname":"Nowy Swiat",
    "gn:country_code":"PL",
    "gn:dem":77,
    "gn:feature_class":"P",
    "gn:feature_code":"PPL",
    "gn:name":"Nowy \u015awiat",
    "gn:population":0,
    "gn:timezone":"Europe/Warsaw",
    "iso:country":"PL",
    "wof:name":"Nowy Swiat",
    "wof:placetype":"locality"
},
  "geometry": {"coordinates":[17.73315,52.98418],"type":"Point"}
}