{
  "type": "Feature",
  "properties": {
    "gn:admin1_code":"78.0",
    "gn:admin2_code":"1410.0",
    "gn:admin3_code":"141006.0",
    "gn:asciiname":"Koszelowka",
    "gn:country_code":"PL",
    "gn:dem":162,
    "gn:feature_class":"P",
    "gn:feature_code":"PPL",
    "gn:name":"Koszel\u00f3wka",
    "gn:population":0,
    "gn:timezone":"Europe/Warsaw",
    "iso:country":"PL",
    "name:ceb_x_preferred":[
        "Koszel\u00f3wka"
    ],
    "name:fra_x_preferred":[
        "Koszel\u00f3wka"
    ],
    "name:lit_x_preferred":[
        "Ko\u0161eluvka"
    ],
    "name:pol_x_preferred":[
        "Koszel\u00f3wka"
    ],
    "name:ukr_x_preferred":[
        "\u041a\u043e\u0448\u0435\u043b\u044e\u0432\u043a\u0430"
    ],
    "wof:name":"Koszelowka",
    "wof:placetype":"locality"
},
  "geometry": {"coordinates":[22.98383,52.20645],"type":"Point"}
}