{
  "type": "Feature",
  "properties": {
    "gn:admin1_code":"74.0",
    "gn:admin2_code":"1020.0",
    "gn:admin3_code":"102006.0",
    "gn:asciiname":"Skromnica",
    "gn:country_code":"PL",
    "gn:dem":112,
    "gn:feature_class":"P",
    "gn:feature_code":"PPL",
    "gn:name":"Skromnica",
    "gn:population":0,
    "gn:timezone":"Europe/Warsaw",
    "iso:country":"PL",
    "name:ceb_x_preferred":[
        "Skromnica"
    ],
    "name:pol_x_preferred":[
        "Skromnica"
    ],
    "name:ukr_x_preferred":[
        "\u0421\u043a\u0440\u043e\u043c\u043d\u0438\u0446\u044f"
    ],
    "wof:name":"Skromnica",
    "wof:placetype":"locality"
},
  "geometry": {"coordinates":[19.18479,52.00956],"type":"Point"}
}