{
  "type": "Feature",
  "properties": {
    "gn:admin1_code":"83.0",
    "gn:admin2_code":"2407.0",
    "gn:admin3_code":"240701.0",
    "gn:asciiname":"Wymyslacz",
    "gn:country_code":"PL",
    "gn:dem":251,
    "gn:feature_class":"P",
    "gn:feature_code":"PPL",
    "gn:name":"Wymy\u015blacz",
    "gn:population":0,
    "gn:timezone":"Europe/Warsaw",
    "iso:country":"PL",
    "wof:name":"Wymyslacz",
    "wof:placetype":"locality"
},
  "geometry": {"coordinates":[18.64214,50.66287],"type":"Point"}
}