{
  "type": "Feature",
  "properties": {
    "gn:gn_country":"PL",
    "gn:gn_fcode":"PPL",
    "gn:gn_pop":630,
    "gn:population":630,
    "iso:country":"PL",
    "name:ast_x_preferred":[
        "Lemierzyce"
    ],
    "name:ceb_x_preferred":[
        "Lemierzyce"
    ],
    "name:eng_x_preferred":[
        "Lemierzyce"
    ],
    "name:fas_x_preferred":[
        "\u0644\u0645\u06cc\u0698\u062a\u0633\u0647"
    ],
    "name:fra_x_preferred":[
        "Lemierzyce"
    ],
    "name:nan_x_preferred":[
        "Lemierzyce"
    ],
    "name:nld_x_preferred":[
        "Lemierzyce"
    ],
    "name:pol_x_preferred":[
        "Lemierzyce"
    ],
    "name:ukr_x_preferred":[
        "\u041b\u0435\u043c\u0435\u0436\u0438\u0446\u0435"
    ],
    "name:unk_x_variant":[
        "Alt Limmritz"
    ],
    "qs_pg:aaroncc":"PL",
    "qs_pg:gn_country":"PL",
    "qs_pg:gn_fcode":"PPL",
    "qs_pg:gn_pop":630,
    "qs_pg:name":"Lemierzyce",
    "qs_pg:name_adm0":"Polska",
    "qs_pg:name_adm1":"Lubuskie",
    "qs_pg:photos_9r":0,
    "qs_pg:photos_sr":0,
    "qs_pg:pop_sr":2,
    "qs_pg:qs_pg_placetype":"locality",
    "qs_pg:qs_pg_placetype_gp":"Town",
    "qs_pg:woe_adm0":23424923,
    "woe:adm0_id":23424923,
    "woe:name_adm0":"Polska",
    "woe:name_adm1":"Lubuskie",
    "woe:placetype":"Town",
    "wof:name":"Lemierzyce",
    "wof:placetype":"locality",
    "wof:population":630
},
  "geometry": {"coordinates":[14.9148,52.5668],"type":"Point"}
}