{
  "type": "Feature",
  "properties": {
    "gn:admin1_code":"86.0",
    "gn:admin2_code":"3016.0",
    "gn:admin3_code":"301601.0",
    "gn:asciiname":"Zukowo",
    "gn:country_code":"PL",
    "gn:dem":62,
    "gn:feature_class":"P",
    "gn:feature_code":"PPL",
    "gn:name":"\u017bukowo",
    "gn:population":0,
    "gn:timezone":"Europe/Warsaw",
    "iso:country":"PL",
    "name:fra_x_preferred":[
        "\u017bukowo"
    ],
    "name:pol_x_preferred":[
        "\u017bukowo"
    ],
    "name:ukr_x_preferred":[
        "\u0416\u0443\u043a\u043e\u0432\u043e"
    ],
    "name:und_x_variant":[
        "\u017bukowo"
    ],
    "wof:name":"Zukowo",
    "wof:placetype":"locality"
},
  "geometry": {"coordinates":[16.72399,52.61599],"type":"Point"}
}