{
  "type": "Feature",
  "properties": {
    "gn:admin1_code":"82.0",
    "gn:admin2_code":"2206.0",
    "gn:admin3_code":"220604.0",
    "gn:asciiname":"Lisaki",
    "gn:country_code":"PL",
    "gn:dem":152,
    "gn:feature_class":"P",
    "gn:feature_code":"PPL",
    "gn:name":"Lisaki",
    "gn:population":0,
    "gn:timezone":"Europe/Warsaw",
    "iso:country":"PL",
    "wof:name":"Lisaki",
    "wof:placetype":"locality"
},
  "geometry": {"coordinates":[17.92442,54.07794000000001],"type":"Point"}
}