{
  "type": "Feature",
  "properties": {
    "gn:admin1_code":"72.0",
    "gn:admin2_code":"205.0",
    "gn:admin3_code":"20505.0",
    "gn:asciiname":"Grobia",
    "gn:country_code":"PL",
    "gn:dem":267,
    "gn:feature_class":"P",
    "gn:feature_code":"PPL",
    "gn:name":"Grobia",
    "gn:population":0,
    "gn:timezone":"Europe/Warsaw",
    "iso:country":"PL",
    "name:azb_x_preferred":[
        "\u0642\u0631\u0648\u0628\u06cc\u0627"
    ],
    "name:ceb_x_preferred":[
        "Grobia"
    ],
    "name:deu_x_preferred":[
        "Grobia"
    ],
    "name:fas_x_preferred":[
        "\u06af\u0631\u0648\u0628\u06cc\u0627"
    ],
    "name:fra_x_preferred":[
        "Grobia"
    ],
    "name:nld_x_preferred":[
        "Grobia"
    ],
    "name:pol_x_preferred":[
        "Grobia"
    ],
    "name:ukr_x_preferred":[
        "\u0490\u0440\u043e\u0431\u044f"
    ],
    "wof:name":"Grobia",
    "wof:placetype":"locality"
},
  "geometry": {"coordinates":[16.11864,50.98307],"type":"Point"}
}