{
  "type": "Feature",
  "properties": {
    "gn:admin1_code":"87.0",
    "gn:admin2_code":"3208.0",
    "gn:admin3_code":"320802.0",
    "gn:asciiname":"Piotrowice",
    "gn:country_code":"PL",
    "gn:dem":38,
    "gn:feature_class":"P",
    "gn:feature_code":"PPL",
    "gn:name":"Piotrowice",
    "gn:population":0,
    "gn:timezone":"Europe/Warsaw",
    "iso:country":"PL",
    "wof:name":"Piotrowice",
    "wof:placetype":"locality"
},
  "geometry": {"coordinates":[15.77115,54.09336],"type":"Point"}
}