{
  "type": "Feature",
  "properties": {
    "gn:admin1_code":"87.0",
    "gn:admin2_code":"3208.0",
    "gn:admin3_code":"320802.0",
    "gn:asciiname":"Piotrowice",
    "gn:country_code":"PL",
    "gn:dem":38,
    "gn:feature_class":"P",
    "gn:feature_code":"PPL",
    "gn:name":"Piotrowice",
    "gn:population":0,
    "gn:timezone":"Europe/Warsaw",
    "iso:country":"PL",
    "name:deu_x_preferred":[
        "Piotrowice"
    ],
    "name:pol_x_preferred":[
        "Piotrowice"
    ],
    "name:ukr_x_preferred":[
        "\u041f\u0439\u043e\u0442\u0440\u043e\u0432\u0456\u0446\u0435"
    ],
    "name:vie_x_preferred":[
        "Piotrowice"
    ],
    "wof:name":"Piotrowice",
    "wof:placetype":"locality"
},
  "geometry": {"coordinates":[15.77115,54.09336],"type":"Point"}
}