{
  "type": "Feature",
  "properties": {
    "gn:country":"PL",
    "gn:fcode":"PPL",
    "gn:population":0,
    "iso:country":"PL",
    "name:ast_x_preferred":[
        "Kaletnik"
    ],
    "name:eng_x_preferred":[
        "Kaletnik"
    ],
    "name:fra_x_preferred":[
        "Kaletnik"
    ],
    "name:lit_x_preferred":[
        "Kaletnikas"
    ],
    "name:pol_x_preferred":[
        "Kaletnik"
    ],
    "name:ukr_x_preferred":[
        "\u041a\u0430\u043b\u0435\u0442\u043d\u0438\u043a"
    ],
    "qs_pg:aaroncc":"PL",
    "qs_pg:gn_country":"PL",
    "qs_pg:gn_fcode":"PPL",
    "qs_pg:gn_pop":0,
    "qs_pg:name":"Kaletnik",
    "qs_pg:name_adm0":"Polska",
    "qs_pg:name_adm1":"Podlaskie",
    "qs_pg:photos_9k":1,
    "qs_pg:photos_9r":1,
    "qs_pg:photos_all":8,
    "qs_pg:photos_sr":0,
    "qs_pg:pop_sr":0,
    "qs_pg:qs_pg_placetype":"locality",
    "qs_pg:qs_pg_placetype_gp":"Town",
    "qs_pg:woe_adm0":23424923,
    "woe:adm0_id":23424923,
    "woe:name_adm0":"Polska",
    "woe:name_adm1":"Podlaskie",
    "woe:placetype":"Town",
    "wof:name":"Kaletnik",
    "wof:placetype":"locality"
},
  "geometry": {"coordinates":[23.0874,54.17584],"type":"Point"}
}