{
  "type": "Feature",
  "properties": {
    "gn:admin1_code":"77.0",
    "gn:admin2_code":"1209.0",
    "gn:admin3_code":"120909.0",
    "gn:asciiname":"Wierzbanowa",
    "gn:country_code":"PL",
    "gn:dem":422,
    "gn:feature_class":"P",
    "gn:feature_code":"PPL",
    "gn:name":"Wierzbanowa",
    "gn:population":0,
    "gn:timezone":"Europe/Warsaw",
    "iso:country":"PL",
    "name:ceb_x_preferred":[
        "Wierzbanowa"
    ],
    "name:pol_x_preferred":[
        "Wierzbanowa"
    ],
    "name:ukr_x_preferred":[
        "\u0412\u0435\u0436\u0431\u0430\u043d\u043e\u0432\u0430"
    ],
    "wof:name":"Wierzbanowa",
    "wof:placetype":"locality"
},
  "geometry": {"coordinates":[20.11889,49.76585],"type":"Point"}
}