{
  "type": "Feature",
  "properties": {
    "gn:admin1_code":"77.0",
    "gn:admin2_code":"1209.0",
    "gn:admin3_code":"120904.0",
    "gn:asciiname":"Malakowka",
    "gn:country_code":"PL",
    "gn:dem":491,
    "gn:feature_class":"P",
    "gn:feature_code":"PPL",
    "gn:name":"Malak\u00f3wka",
    "gn:population":0,
    "gn:timezone":"Europe/Warsaw",
    "iso:country":"PL",
    "name:und_x_variant":[
        "Maryl\u00f3wka",
        "Malak\u00f3wka"
    ],
    "wof:name":"Malakowka",
    "wof:placetype":"locality"
},
  "geometry": {"coordinates":[19.94052000000001,49.79831],"type":"Point"}
}