{
  "type": "Feature",
  "properties": {
    "gn:admin1_code":"79.0",
    "gn:admin2_code":"1601.0",
    "gn:admin3_code":"160104.0",
    "gn:asciiname":"Boguslaw",
    "gn:country_code":"PL",
    "gn:dem":153,
    "gn:feature_class":"P",
    "gn:feature_code":"PPL",
    "gn:name":"Bogus\u0142aw",
    "gn:population":0,
    "gn:timezone":"Europe/Warsaw",
    "iso:country":"PL",
    "wof:name":"Boguslaw",
    "wof:placetype":"locality"
},
  "geometry": {"coordinates":[17.73333,50.75],"type":"Point"}
}