{
  "type": "Feature",
  "properties": {
    "gn:admin1_code":"75.0",
    "gn:admin2_code":"602.0",
    "gn:admin3_code":"60205.0",
    "gn:asciiname":"Kolonia Katy",
    "gn:country_code":"PL",
    "gn:dem":245,
    "gn:feature_class":"P",
    "gn:feature_code":"PPL",
    "gn:name":"Kolonia K\u0105ty",
    "gn:population":0,
    "gn:timezone":"Europe/Warsaw",
    "iso:country":"PL",
    "name:fra_x_preferred":[
        "Kolonia K\u0105ty"
    ],
    "name:pol_x_preferred":[
        "Kolonia K\u0105ty"
    ],
    "wof:name":"Kolonia Katy",
    "wof:placetype":"locality"
},
  "geometry": {"coordinates":[22.73333,50.66667],"type":"Point"}
}