{
  "type": "Feature",
  "properties": {
    "gn:admin1_code":"80.0",
    "gn:admin2_code":"1801.0",
    "gn:admin3_code":"180108.0",
    "gn:asciiname":"Ustjanowa Gorna",
    "gn:country_code":"PL",
    "gn:dem":499,
    "gn:feature_class":"P",
    "gn:feature_code":"PPL",
    "gn:name":"Ustjanowa G\u00f3rna",
    "gn:population":0,
    "gn:timezone":"Europe/Warsaw",
    "iso:country":"PL",
    "name:azb_x_preferred":[
        "\u0627\u0648\u0633\u062a\u06cc\u0627\u0646\u0648\u0648\u0627 \u0642\u0648\u0631\u0646\u0627"
    ],
    "name:ceb_x_preferred":[
        "Ustjanowa G\u00f3rna"
    ],
    "name:fas_x_preferred":[
        "\u0627\u0648\u0633\u062a\u06cc\u0627\u0646\u0648\u0648\u0627 \u06af\u0648\u0631\u0646\u0627"
    ],
    "name:hun_x_preferred":[
        "Ustjanowa G\u00f3rna"
    ],
    "name:pol_x_preferred":[
        "Ustjanowa G\u00f3rna"
    ],
    "name:rus_x_preferred":[
        "\u0423\u0441\u0442\u044f\u043d\u043e\u0432\u0430 \u0413\u0443\u0440\u043d\u0430"
    ],
    "name:ukr_x_preferred":[
        "\u0423\u0441\u0442\u044f\u043d\u043e\u0432\u0430"
    ],
    "wof:name":"Ustjanowa Gorna",
    "wof:placetype":"locality"
},
  "geometry": {"coordinates":[22.54618,49.4265],"type":"Point"}
}