{
  "type": "Feature",
  "properties": {
    "gn:admin1_code":"80.0",
    "gn:admin2_code":"1801.0",
    "gn:admin3_code":"180108.0",
    "gn:asciiname":"Ustjanowa Gorna",
    "gn:country_code":"PL",
    "gn:dem":499,
    "gn:feature_class":"P",
    "gn:feature_code":"PPL",
    "gn:name":"Ustjanowa G\u00f3rna",
    "gn:population":0,
    "gn:timezone":"Europe/Warsaw",
    "iso:country":"PL",
    "wof:name":"Ustjanowa Gorna",
    "wof:placetype":"locality"
},
  "geometry": {"coordinates":[22.54618,49.4265],"type":"Point"}
}