{
  "type": "Feature",
  "properties": {
    "gn:admin1_code":"78.0",
    "gn:admin2_code":"1422.0",
    "gn:admin3_code":"142207.0",
    "gn:asciiname":"Krepa Stara",
    "gn:country_code":"PL",
    "gn:dem":117,
    "gn:feature_class":"P",
    "gn:feature_code":"PPL",
    "gn:name":"Kr\u0119pa Stara",
    "gn:population":0,
    "gn:timezone":"Europe/Warsaw",
    "iso:country":"PL",
    "name:und_x_variant":[
        "Kr\u0119pa",
        "Kr\u0119pa Stara"
    ],
    "wof:name":"Krepa Stara",
    "wof:placetype":"locality"
},
  "geometry": {"coordinates":[20.96667,53.05829],"type":"Point"}
}