{
  "type": "Feature",
  "properties": {
    "gn:country":"PL",
    "gn:fcode":"PPLA3",
    "gn:population":980,
    "iso:country":"PL",
    "name:deu_x_preferred":[
        "So\u015bno"
    ],
    "name:nld_x_preferred":[
        "So\u015bno"
    ],
    "name:pol_x_preferred":[
        "So\u015bno"
    ],
    "name:ukr_x_preferred":[
        "\u0421\u043e\u0441\u044c\u043d\u043e"
    ],
    "qs_pg:aaroncc":"PL",
    "qs_pg:gn_country":"PL",
    "qs_pg:gn_fcode":"PPLA3",
    "qs_pg:gn_pop":980,
    "qs_pg:name":"So\u015bno",
    "qs_pg:name_adm0":"Polska",
    "qs_pg:name_adm1":"Kujawsko-Pomorskie",
    "qs_pg:photos_9r":0,
    "qs_pg:photos_sr":0,
    "qs_pg:pop_sr":2,
    "qs_pg:qs_pg_placetype":"localadmin",
    "qs_pg:qs_pg_placetype_gp":"LocalAdmin",
    "qs_pg:woe_adm0":23424923,
    "woe:adm0_id":23424923,
    "woe:name_adm0":"Polska",
    "woe:name_adm1":"Kujawsko-Pomorskie",
    "woe:placetype":"LocalAdmin",
    "wof:name":"So\u015bno",
    "wof:placetype":"localadmin",
    "wof:population":980
},
  "geometry": {"coordinates":[17.68713,53.38922],"type":"Point"}
}