{
  "type": "Feature",
  "properties": {
    "gn:country":"PL",
    "gn:fcode":"PPL",
    "gn:population":0,
    "iso:country":"PL",
    "name:ast_x_preferred":[
        "Urszulewo"
    ],
    "name:eng_x_preferred":[
        "Urszulewo"
    ],
    "name:fra_x_preferred":[
        "Urszulewo"
    ],
    "name:pol_x_preferred":[
        "Urszulewo"
    ],
    "name:ukr_x_preferred":[
        "\u0423\u0440\u0448\u0443\u043b\u0435\u0432\u043e"
    ],
    "qs_pg:aaroncc":"PL",
    "qs_pg:gn_country":"PL",
    "qs_pg:gn_fcode":"PPL",
    "qs_pg:gn_pop":0,
    "qs_pg:name":"Urszulewo",
    "qs_pg:name_adm0":"Polska",
    "qs_pg:name_adm1":"Kujawsko-Pomorskie",
    "qs_pg:photos_9r":0,
    "qs_pg:photos_sr":0,
    "qs_pg:pop_sr":0,
    "qs_pg:qs_pg_placetype":"locality",
    "qs_pg:qs_pg_placetype_gp":"Town",
    "qs_pg:woe_adm0":23424923,
    "woe:adm0_id":23424923,
    "woe:name_adm0":"Polska",
    "woe:name_adm1":"Kujawsko-Pomorskie",
    "woe:placetype":"Town",
    "wof:name":"Urszulewo",
    "wof:placetype":"locality"
},
  "geometry": {"coordinates":[19.54914,52.98069],"type":"Point"}
}