{
  "type": "Feature",
  "properties": {
    "gn:admin1_code":"79.0",
    "gn:admin2_code":"1611.0",
    "gn:admin3_code":"161106.0",
    "gn:asciiname":"Balcarzowice",
    "gn:country_code":"PL",
    "gn:dem":254,
    "gn:feature_class":"P",
    "gn:feature_code":"PPL",
    "gn:name":"Balcarzowice",
    "gn:population":0,
    "gn:timezone":"Europe/Warsaw",
    "iso:country":"PL",
    "name:azb_x_preferred":[
        "\u0628\u0627\u0644\u062a\u0633\u0627\u0698\u0648\u0648\u06cc\u062a\u0633\u0647"
    ],
    "name:ceb_x_preferred":[
        "Balcarzowice"
    ],
    "name:deu_x_preferred":[
        "Balzarowitz"
    ],
    "name:fas_x_preferred":[
        "\u0628\u0627\u0644\u062a\u0633\u0627\u0698\u0648\u0648\u06cc\u062a\u0633\u0647"
    ],
    "name:pol_x_preferred":[
        "Balcarzowice"
    ],
    "name:ukr_x_preferred":[
        "\u0411\u0430\u043b\u044c\u0446\u0430\u0436\u043e\u0432\u0456\u0446\u0435"
    ],
    "wof:name":"Balcarzowice",
    "wof:placetype":"locality"
},
  "geometry": {"coordinates":[18.37772,50.46362],"type":"Point"}
}