{
  "type": "Feature",
  "properties": {
    "gn:admin1_code":"78.0",
    "gn:admin2_code":"1406.0",
    "gn:admin3_code":"140611.0",
    "gn:asciiname":"Wrociszew",
    "gn:country_code":"PL",
    "gn:dem":121,
    "gn:feature_class":"P",
    "gn:feature_code":"PPL",
    "gn:name":"Wrociszew",
    "gn:population":0,
    "gn:timezone":"Europe/Warsaw",
    "iso:country":"PL",
    "name:fra_x_preferred":[
        "Wrociszew"
    ],
    "name:pol_x_preferred":[
        "Wrociszew"
    ],
    "name:ukr_x_preferred":[
        "\u0412\u0440\u043e\u0446\u0438\u0448\u0435\u0432"
    ],
    "wof:name":"Wrociszew",
    "wof:placetype":"locality"
},
  "geometry": {"coordinates":[21.07212,51.74553],"type":"Point"}
}