{
  "type": "Feature",
  "properties": {
    "gn:admin1_code":"86.0",
    "gn:admin2_code":"3006.0",
    "gn:admin3_code":"300601.0",
    "gn:asciiname":"Noskow",
    "gn:country_code":"PL",
    "gn:dem":115,
    "gn:feature_class":"P",
    "gn:feature_code":"PPL",
    "gn:name":"Nosk\u00f3w",
    "gn:population":0,
    "gn:timezone":"Europe/Warsaw",
    "iso:country":"PL",
    "name:und_x_variant":[
        "Nosk\u00f3w"
    ],
    "wof:name":"Noskow",
    "wof:placetype":"locality"
},
  "geometry": {"coordinates":[17.39781,51.93195],"type":"Point"}
}