{
  "type": "Feature",
  "properties": {
    "gn:admin1_code":"86.0",
    "gn:admin2_code":"3006.0",
    "gn:admin3_code":"300601.0",
    "gn:asciiname":"Noskow",
    "gn:country_code":"PL",
    "gn:dem":115,
    "gn:feature_class":"P",
    "gn:feature_code":"PPL",
    "gn:name":"Nosk\u00f3w",
    "gn:population":0,
    "gn:timezone":"Europe/Warsaw",
    "iso:country":"PL",
    "name:azb_x_preferred":[
        "\u0646\u0648\u0633\u06a9\u0648\u0648"
    ],
    "name:ceb_x_preferred":[
        "Nosk\u00f3w"
    ],
    "name:fas_x_preferred":[
        "\u0646\u0648\u0633\u06a9\u0648\u0648"
    ],
    "name:fra_x_preferred":[
        "Nosk\u00f3w"
    ],
    "name:pol_x_preferred":[
        "Nosk\u00f3w"
    ],
    "name:ukr_x_preferred":[
        "\u041d\u043e\u0441\u043a\u0443\u0432"
    ],
    "name:und_x_variant":[
        "Nosk\u00f3w"
    ],
    "wof:name":"Noskow",
    "wof:placetype":"locality"
},
  "geometry": {"coordinates":[17.39781,51.93195],"type":"Point"}
}