{
  "type": "Feature",
  "properties": {
    "gn:admin1_code":"77.0",
    "gn:admin2_code":"1205.0",
    "gn:admin3_code":"120502.0",
    "gn:asciiname":"Grudna Kepska",
    "gn:country_code":"PL",
    "gn:dem":250,
    "gn:feature_class":"P",
    "gn:feature_code":"PPL",
    "gn:name":"Grudna K\u0119pska",
    "gn:population":0,
    "gn:timezone":"Europe/Warsaw",
    "iso:country":"PL",
    "name:ceb_x_preferred":[
        "Grudna K\u0119pska"
    ],
    "name:pol_x_preferred":[
        "Grudna K\u0119pska"
    ],
    "name:ukr_x_preferred":[
        "\u0490\u0440\u0443\u0434\u043d\u0430-\u041a\u0435\u043c\u043f\u0441\u044c\u043a\u0430"
    ],
    "wof:name":"Grudna Kepska",
    "wof:placetype":"locality"
},
  "geometry": {"coordinates":[21.29562,49.74151],"type":"Point"}
}