{
  "type": "Feature",
  "properties": {
    "gn:admin1_code":"75.0",
    "gn:admin2_code":"618.0",
    "gn:admin3_code":"61812.0",
    "gn:asciiname":"Czermno",
    "gn:country_code":"PL",
    "gn:dem":201,
    "gn:feature_class":"P",
    "gn:feature_code":"PPL",
    "gn:name":"Czermno",
    "gn:population":0,
    "gn:timezone":"Europe/Warsaw",
    "iso:country":"PL",
    "name:azb_x_preferred":[
        "\u0686\u0631\u0645\u0646\u0648"
    ],
    "name:deu_x_preferred":[
        "Czermno"
    ],
    "name:fas_x_preferred":[
        "\u0686\u0631\u0645\u0646\u0648"
    ],
    "name:fra_x_preferred":[
        "Czermno"
    ],
    "name:nld_x_preferred":[
        "Czermno"
    ],
    "name:pol_x_preferred":[
        "Czermno"
    ],
    "name:rus_x_preferred":[
        "\u0427\u0435\u0440\u043c\u043d\u043e"
    ],
    "name:ukr_x_preferred":[
        "\u0427\u0435\u0440\u043c\u043d\u043e"
    ],
    "wof:name":"Czermno",
    "wof:placetype":"locality"
},
  "geometry": {"coordinates":[23.68415,50.66357],"type":"Point"}
}