{
  "type": "Feature",
  "properties": {
    "gn:admin1_code":"74.0",
    "gn:admin2_code":"1016.0",
    "gn:admin3_code":"101607.0",
    "gn:asciiname":"Eufeminow",
    "gn:country_code":"PL",
    "gn:dem":207,
    "gn:feature_class":"P",
    "gn:feature_code":"PPL",
    "gn:name":"Eufemin\u00f3w",
    "gn:population":0,
    "gn:timezone":"Europe/Warsaw",
    "iso:country":"PL",
    "name:fra_x_preferred":[
        "Eufemin\u00f3w"
    ],
    "name:pol_x_preferred":[
        "Eufemin\u00f3w"
    ],
    "name:ukr_x_preferred":[
        "\u0415\u0443\u0444\u0435\u043c\u0456\u043d\u0443\u0432"
    ],
    "wof:name":"Eufeminow",
    "wof:placetype":"locality"
},
  "geometry": {"coordinates":[19.76667,51.66667],"type":"Point"}
}