{
  "type": "Feature",
  "properties": {
    "gn:admin1_code":"75.0",
    "gn:admin2_code":"613.0",
    "gn:admin3_code":"61306.0",
    "gn:asciiname":"Milkow",
    "gn:country_code":"PL",
    "gn:dem":147,
    "gn:feature_class":"P",
    "gn:feature_code":"PPL",
    "gn:name":"Mi\u0142k\u00f3w",
    "gn:population":0,
    "gn:timezone":"Europe/Warsaw",
    "iso:country":"PL",
    "name:fra_x_preferred":[
        "Mi\u0142k\u00f3w"
    ],
    "name:pol_x_preferred":[
        "Mi\u0142k\u00f3w"
    ],
    "name:ukr_x_preferred":[
        "\u041c\u0456\u043b\u043a\u0443\u0432"
    ],
    "name:und_x_variant":[
        "Mi\u0142k\u00f3w"
    ],
    "wof:name":"Milkow",
    "wof:placetype":"locality"
},
  "geometry": {"coordinates":[22.81067,51.63064],"type":"Point"}
}