{
  "type": "Feature",
  "properties": {
    "gn:admin1_code":"73.0",
    "gn:admin2_code":"402.0",
    "gn:admin3_code":"40204.0",
    "gn:asciiname":"Swiecie",
    "gn:country_code":"PL",
    "gn:dem":100,
    "gn:feature_class":"P",
    "gn:feature_code":"PPL",
    "gn:name":"\u015awiecie",
    "gn:population":0,
    "gn:timezone":"Europe/Warsaw",
    "iso:country":"PL",
    "wof:name":"Swiecie",
    "wof:placetype":"locality"
},
  "geometry": {"coordinates":[19.53,53.28456],"type":"Point"}
}