{
  "type": "Feature",
  "properties": {
    "gn:gn_country":"PL",
    "gn:gn_fcode":"PPLA3",
    "gn:gn_pop":20771,
    "gn:population":20771,
    "iso:country":"PL",
    "name:bul_x_preferred":[
        "\u0413\u043e\u0441\u0442\u0438\u043d"
    ],
    "name:lav_x_preferred":[
        "Gosti\u0146a"
    ],
    "name:lit_x_preferred":[
        "Gostynis"
    ],
    "name:rus_x_preferred":[
        "\u0413\u043e\u0441\u0442\u044b\u043d"
    ],
    "name:rus_x_variant":[
        "\u0413\u043e\u0441\u0442\u044b\u043d\u044c"
    ],
    "name:srp_x_preferred":[
        "\u0413\u043e\u0441\u0442\u0438\u045a"
    ],
    "name:ukr_x_preferred":[
        "\u0413\u043e\u0441\u0442\u0438\u043d\u044c"
    ],
    "name:unk_x_variant":[
        "Gostingen"
    ],
    "name:zho_x_preferred":[
        "\u6208\u65af\u6ed5"
    ],
    "qs_pg:aaroncc":"PL",
    "qs_pg:gn_country":"PL",
    "qs_pg:gn_fcode":"PPLA3",
    "qs_pg:gn_pop":20771,
    "qs_pg:name":"Gosty\u0144",
    "qs_pg:name_adm0":"Polska",
    "qs_pg:name_adm1":"Wielkopolskie",
    "qs_pg:photos":3,
    "qs_pg:photos_1k":1,
    "qs_pg:photos_9k":1,
    "qs_pg:photos_9r":1,
    "qs_pg:photos_all":3,
    "qs_pg:photos_sr":1,
    "qs_pg:pop_sr":7,
    "qs_pg:qs_pg_placetype":"localadmin",
    "qs_pg:qs_pg_placetype_gp":"LocalAdmin",
    "qs_pg:woe_adm0":23424923,
    "woe:adm0_id":23424923,
    "woe:name_adm0":"Polska",
    "woe:name_adm1":"Wielkopolskie",
    "woe:placetype":"LocalAdmin",
    "wof:name":"Gosty\u0144",
    "wof:placetype":"localadmin",
    "wof:population":20771
},
  "geometry": {"coordinates":[17.01226,51.88247],"type":"Point"}
}