{
  "type": "Feature",
  "properties": {
    "gn:admin1_code":"76.0",
    "gn:admin2_code":"807.0",
    "gn:admin3_code":"80703.0",
    "gn:asciiname":"Przyborow",
    "gn:country_code":"PL",
    "gn:dem":15,
    "gn:feature_class":"P",
    "gn:feature_code":"PPL",
    "gn:name":"Przybor\u00f3w",
    "gn:population":0,
    "gn:timezone":"Europe/Warsaw",
    "iso:country":"PL",
    "wof:name":"Przyborow",
    "wof:placetype":"locality"
},
  "geometry": {"coordinates":[14.79103,52.57672],"type":"Point"}
}