{
  "type": "Feature",
  "properties": {
    "gn:admin1_code":"87.0",
    "gn:admin2_code":"3207.0",
    "gn:admin3_code":"320706.0",
    "gn:asciiname":"Skoszewo",
    "gn:country_code":"PL",
    "gn:dem":2,
    "gn:feature_class":"P",
    "gn:feature_code":"PPL",
    "gn:name":"Skoszewo",
    "gn:population":0,
    "gn:timezone":"Europe/Warsaw",
    "iso:country":"PL",
    "name:ceb_x_preferred":[
        "Skoszewo"
    ],
    "name:pol_x_preferred":[
        "Skoszewo"
    ],
    "name:ukr_x_preferred":[
        "\u0421\u043a\u043e\u0448\u0435\u0432\u043e"
    ],
    "wof:name":"Skoszewo",
    "wof:placetype":"locality"
},
  "geometry": {"coordinates":[14.62288,53.78406],"type":"Point"}
}