{
  "type": "Feature",
  "properties": {
    "gn:admin1_code":"84.0",
    "gn:admin2_code":"2603.0",
    "gn:admin3_code":"260303.0",
    "gn:asciiname":"Zyslawice",
    "gn:country_code":"PL",
    "gn:dem":216,
    "gn:feature_class":"P",
    "gn:feature_code":"PPL",
    "gn:name":"Zys\u0142awice",
    "gn:population":0,
    "gn:timezone":"Europe/Warsaw",
    "iso:country":"PL",
    "name:pol_x_preferred":[
        "Zys\u0142awice"
    ],
    "name:ukr_x_preferred":[
        "\u0417\u0438\u0441\u043b\u0430\u0432\u0456\u0446\u0435"
    ],
    "wof:name":"Zyslawice",
    "wof:placetype":"locality"
},
  "geometry": {"coordinates":[20.51628,50.19328],"type":"Point"}
}