{
  "type": "Feature",
  "properties": {
    "gn:admin1_code":"81.0",
    "gn:admin2_code":"2011.0",
    "gn:admin3_code":"201103.0",
    "gn:asciiname":"Laskowszczyzna",
    "gn:country_code":"PL",
    "gn:dem":146,
    "gn:feature_class":"P",
    "gn:feature_code":"PPL",
    "gn:name":"Laskowszczyzna",
    "gn:population":0,
    "gn:timezone":"Europe/Warsaw",
    "iso:country":"PL",
    "name:lit_x_preferred":[
        "Laskov\u0161\u010dizna"
    ],
    "name:pol_x_preferred":[
        "Laskowszczyzna"
    ],
    "name:ukr_x_preferred":[
        "\u041b\u044f\u0441\u043a\u043e\u0432\u0449\u0438\u0437\u043d\u0430"
    ],
    "wof:name":"Laskowszczyzna",
    "wof:placetype":"locality"
},
  "geometry": {"coordinates":[23.17248,53.47261],"type":"Point"}
}