{
  "type": "Feature",
  "properties": {
    "gn:country":"PL",
    "gn:fcode":"PPL",
    "gn:population":0,
    "iso:country":"PL",
    "name:ast_x_preferred":[
        "P\u0142awy"
    ],
    "name:ceb_x_preferred":[
        "P\u0142awy"
    ],
    "name:ces_x_preferred":[
        "P\u0142awy"
    ],
    "name:che_x_preferred":[
        "\u041f\u043b\u0430\u0432\u0438"
    ],
    "name:deu_x_preferred":[
        "P\u0142awy"
    ],
    "name:eng_x_preferred":[
        "P\u0142awy"
    ],
    "name:fra_x_preferred":[
        "P\u0142awy"
    ],
    "name:nan_x_preferred":[
        "P\u0142awy"
    ],
    "name:pol_x_preferred":[
        "P\u0142awy"
    ],
    "name:tat_x_preferred":[
        "\u041f\u043b\u0430\u0432\u0438"
    ],
    "name:ukr_x_preferred":[
        "\u041f\u043b\u0430\u0432\u0438"
    ],
    "qs_pg:aaroncc":"PL",
    "qs_pg:gn_country":"PL",
    "qs_pg:gn_fcode":"PPL",
    "qs_pg:gn_pop":0,
    "qs_pg:name":"P\u0142awy",
    "qs_pg:name_adm0":"Polska",
    "qs_pg:name_adm1":"Ma\u0142opolskie",
    "qs_pg:photos":39,
    "qs_pg:photos_1k":8,
    "qs_pg:photos_9k":1,
    "qs_pg:photos_9r":2,
    "qs_pg:photos_all":39,
    "qs_pg:photos_sr":2,
    "qs_pg:pop_sr":0,
    "qs_pg:qs_pg_placetype":"locality",
    "qs_pg:qs_pg_placetype_gp":"Town",
    "qs_pg:woe_adm0":23424923,
    "woe:adm0_id":23424923,
    "woe:name_adm0":"Polska",
    "woe:name_adm1":"Ma\u0142opolskie",
    "woe:placetype":"Town",
    "wof:name":"P\u0142awy",
    "wof:placetype":"locality"
},
  "geometry": {"coordinates":[19.16325,50.03421],"type":"Point"}
}