{
  "type": "Feature",
  "properties": {
    "gn:country":"PL",
    "gn:fcode":"PPL",
    "gn:population":1010,
    "iso:country":"PL",
    "name:ast_x_preferred":[
        "W\u0119gry"
    ],
    "name:azb_x_preferred":[
        "\u0648\u0646\u0642\u0631\u0647"
    ],
    "name:ceb_x_preferred":[
        "W\u0119gry"
    ],
    "name:deu_x_preferred":[
        "Wengern"
    ],
    "name:eng_x_preferred":[
        "W\u0119gry"
    ],
    "name:fas_x_preferred":[
        "\u0648\u0646\u06af\u0631\u0647"
    ],
    "name:nan_x_preferred":[
        "W\u0119gry"
    ],
    "name:nld_x_preferred":[
        "W\u0119gry"
    ],
    "name:pol_x_preferred":[
        "W\u0119gry"
    ],
    "name:ukr_x_preferred":[
        "\u0412\u0435\u043d\u0491\u0440\u0438"
    ],
    "qs_pg:aaroncc":"PL",
    "qs_pg:gn_country":"PL",
    "qs_pg:gn_fcode":"PPL",
    "qs_pg:gn_pop":1010,
    "qs_pg:name":"W\u0119gry",
    "qs_pg:name_adm0":"Polska",
    "qs_pg:name_adm1":"Opolskie",
    "qs_pg:photos_9r":0,
    "qs_pg:photos_sr":0,
    "qs_pg:pop_sr":3,
    "qs_pg:qs_pg_placetype":"locality",
    "qs_pg:qs_pg_placetype_gp":"Town",
    "qs_pg:woe_adm0":23424923,
    "woe:adm0_id":23424923,
    "woe:name_adm0":"Polska",
    "woe:name_adm1":"Opolskie",
    "woe:placetype":"Town",
    "wof:name":"W\u0119gry",
    "wof:placetype":"locality",
    "wof:population":1010
},
  "geometry": {"coordinates":[18.01741,50.74319],"type":"Point"}
}