{
  "type": "Feature",
  "properties": {
    "gn:admin1_code":"87.0",
    "gn:admin2_code":"3207.0",
    "gn:admin3_code":"320703.0",
    "gn:asciiname":"Zolcino",
    "gn:country_code":"PL",
    "gn:dem":1,
    "gn:feature_class":"P",
    "gn:feature_code":"PPL",
    "gn:name":"\u017b\u00f3\u0142cino",
    "gn:population":0,
    "gn:timezone":"Europe/Warsaw",
    "iso:country":"PL",
    "name:pol_x_preferred":[
        "\u017b\u00f3\u0142cino"
    ],
    "name:ukr_x_preferred":[
        "\u0416\u0443\u043b\u0446\u0438\u043d\u043e"
    ],
    "name:vie_x_preferred":[
        "\u017b\u00f3\u0142cino"
    ],
    "wof:name":"Zolcino",
    "wof:placetype":"locality"
},
  "geometry": {"coordinates":[14.77215,53.99536],"type":"Point"}
}