{
  "type": "Feature",
  "properties": {
    "gn:admin1_code":"81.0",
    "gn:admin2_code":"2007.0",
    "gn:admin3_code":"200702.0",
    "gn:asciiname":"Siemien Nadrzeczny",
    "gn:country_code":"PL",
    "gn:dem":109,
    "gn:feature_class":"P",
    "gn:feature_code":"PPL",
    "gn:name":"Siemie\u0144 Nadrzeczny",
    "gn:population":0,
    "gn:timezone":"Europe/Warsaw",
    "iso:country":"PL",
    "name:lit_x_preferred":[
        "Semien Nad\u017ee\u010dnai"
    ],
    "name:pol_x_preferred":[
        "Siemie\u0144 Nadrzeczny"
    ],
    "name:rus_x_preferred":[
        "\u0421\u0435\u043c\u0435\u043d\u044c-\u041d\u0430\u0434\u0436\u0435\u0447\u043d\u044b"
    ],
    "name:ukr_x_preferred":[
        "\u0421\u0435\u043c\u0435\u043d\u044c-\u041d\u0430\u0434\u0436\u0435\u0447\u043d\u0438"
    ],
    "wof:name":"Siemien Nadrzeczny",
    "wof:placetype":"locality"
},
  "geometry": {"coordinates":[22.16045,53.13071],"type":"Point"}
}