{
  "type": "Feature",
  "properties": {
    "gn:admin1_code":"81.0",
    "gn:admin2_code":"2007.0",
    "gn:admin3_code":"200702.0",
    "gn:asciiname":"Siemien Nadrzeczny",
    "gn:country_code":"PL",
    "gn:dem":109,
    "gn:feature_class":"P",
    "gn:feature_code":"PPL",
    "gn:name":"Siemie\u0144 Nadrzeczny",
    "gn:population":0,
    "gn:timezone":"Europe/Warsaw",
    "iso:country":"PL",
    "wof:name":"Siemien Nadrzeczny",
    "wof:placetype":"locality"
},
  "geometry": {"coordinates":[22.16045,53.13071],"type":"Point"}
}