{
  "type": "Feature",
  "properties": {
    "gn:admin1_code":"83.0",
    "gn:admin2_code":"2406.0",
    "gn:admin3_code":"240604.0",
    "gn:asciiname":"Rywaczki",
    "gn:country_code":"PL",
    "gn:dem":214,
    "gn:feature_class":"P",
    "gn:feature_code":"PPL",
    "gn:name":"Rywaczki",
    "gn:population":0,
    "gn:timezone":"Europe/Warsaw",
    "iso:country":"PL",
    "name:ceb_x_preferred":[
        "Rywaczki"
    ],
    "name:pol_x_preferred":[
        "Rywaczki"
    ],
    "name:ukr_x_preferred":[
        "\u0420\u0438\u0432\u0430\u0447\u043a\u0456"
    ],
    "wof:name":"Rywaczki",
    "wof:placetype":"locality"
},
  "geometry": {"coordinates":[19.07755,50.98369],"type":"Point"}
}