{
  "type": "Feature",
  "properties": {
    "gn:admin1_code":"80.0",
    "gn:admin2_code":"1811.0",
    "gn:admin3_code":"181109.0",
    "gn:asciiname":"Czajkowa",
    "gn:country_code":"PL",
    "gn:dem":158,
    "gn:feature_class":"P",
    "gn:feature_code":"PPL",
    "gn:name":"Czajkowa",
    "gn:population":0,
    "gn:timezone":"Europe/Warsaw",
    "iso:country":"PL",
    "name:pol_x_preferred":[
        "Czajkowa"
    ],
    "name:ukr_x_preferred":[
        "\u0427\u0430\u0439\u043a\u043e\u0432\u0430"
    ],
    "wof:name":"Czajkowa",
    "wof:placetype":"locality"
},
  "geometry": {"coordinates":[21.52285,50.37572],"type":"Point"}
}