{
  "type": "Feature",
  "properties": {
    "gn:admin1_code":"75.0",
    "gn:admin2_code":"619.0",
    "gn:admin3_code":"61908.0",
    "gn:asciiname":"Zahajki",
    "gn:country_code":"PL",
    "gn:dem":160,
    "gn:feature_class":"P",
    "gn:feature_code":"PPL",
    "gn:name":"Zahajki",
    "gn:population":0,
    "gn:timezone":"Europe/Warsaw",
    "iso:country":"PL",
    "wof:name":"Zahajki",
    "wof:placetype":"locality"
},
  "geometry": {"coordinates":[23.28158,51.5994],"type":"Point"}
}