{
  "type": "Feature",
  "properties": {
    "gn:admin1_code":"73.0",
    "gn:admin2_code":"408.0",
    "gn:admin3_code":"40809.0",
    "gn:asciiname":"Miodusy",
    "gn:country_code":"PL",
    "gn:dem":111,
    "gn:feature_class":"P",
    "gn:feature_code":"PPL",
    "gn:name":"Miodusy",
    "gn:population":0,
    "gn:timezone":"Europe/Warsaw",
    "iso:country":"PL",
    "name:fra_x_preferred":[
        "Miodusy"
    ],
    "name:pol_x_preferred":[
        "Miodusy"
    ],
    "name:ukr_x_preferred":[
        "\u041c\u0439\u043e\u0434\u0443\u0441\u0438"
    ],
    "wof:name":"Miodusy",
    "wof:placetype":"locality"
},
  "geometry": {"coordinates":[19.25126,52.74486],"type":"Point"}
}