{
  "type": "Feature",
  "properties": {
    "gn:admin1_code":"84.0",
    "gn:admin2_code":"2604.0",
    "gn:admin3_code":"260405.0",
    "gn:asciiname":"Mojcza",
    "gn:country_code":"PL",
    "gn:dem":272,
    "gn:feature_class":"P",
    "gn:feature_code":"PPL",
    "gn:name":"Mojcza",
    "gn:population":0,
    "gn:timezone":"Europe/Warsaw",
    "iso:country":"PL",
    "name:ceb_x_preferred":[
        "Mojcza"
    ],
    "name:nld_x_preferred":[
        "M\u00f3jcza"
    ],
    "name:pol_x_preferred":[
        "M\u00f3jcza"
    ],
    "name:ukr_x_preferred":[
        "\u041c\u0443\u0439\u0447\u0430"
    ],
    "wof:name":"Mojcza",
    "wof:placetype":"locality"
},
  "geometry": {"coordinates":[20.68267,50.84],"type":"Point"}
}