{
  "type": "Feature",
  "properties": {
    "iso:country":"PL",
    "name:azb_x_preferred":[
        "\u0642\u0645\u06cc\u0646\u0627 \u0648\u0648\u0648\u06cc\u0686"
    ],
    "name:bel_x_preferred":[
        "\u041b\u043e\u0432\u0456\u0447"
    ],
    "name:deu_x_preferred":[
        "\u0141owicz"
    ],
    "name:eus_x_preferred":[
        "\u0141owicz landa-udalerria"
    ],
    "name:fas_x_preferred":[
        "\u06af\u0645\u06cc\u0646\u0627 \u0648\u0648\u0648\u06cc\u0686"
    ],
    "name:fra_x_preferred":[
        "\u0141owicz"
    ],
    "name:ita_x_preferred":[
        "\u0141owicz"
    ],
    "name:nld_x_preferred":[
        "\u0141owicz"
    ],
    "name:pol_x_preferred":[
        "\u0141owicz"
    ],
    "name:rus_x_preferred":[
        "\u041b\u043e\u0432\u0438\u0447"
    ],
    "name:slk_x_preferred":[
        "Gmina \u0141owicz"
    ],
    "name:ukr_x_preferred":[
        "\u0413\u043c\u0456\u043d\u0430 \u041b\u043e\u0432\u0438\u0447"
    ],
    "name:war_x_preferred":[
        "Gmina \u0141owicz"
    ],
    "qs_pg:aaroncc":"PL",
    "qs_pg:name":"Gmina \u0141owicz",
    "qs_pg:name_adm0":"Polska",
    "qs_pg:name_adm1":"\u0141\u00f3dzkie",
    "qs_pg:photos":1,
    "qs_pg:photos_1k":1,
    "qs_pg:photos_9k":1,
    "qs_pg:photos_9r":2,
    "qs_pg:photos_all":56,
    "qs_pg:photos_sr":1,
    "qs_pg:pop_sr":0,
    "qs_pg:qs_pg_placetype":"localadmin",
    "qs_pg:qs_pg_placetype_gp":"LocalAdmin",
    "qs_pg:woe_adm0":23424923,
    "woe:adm0_id":23424923,
    "woe:name_adm0":"Polska",
    "woe:name_adm1":"\u0141\u00f3dzkie",
    "woe:placetype":"LocalAdmin",
    "wof:name":"Gmina \u0141owicz",
    "wof:placetype":"localadmin"
},
  "geometry": {"coordinates":[20.013871,52.084384],"type":"Point"}
}