{
  "type": "Feature",
  "properties": {
    "gn:admin1_code":"81.0",
    "gn:admin2_code":"2012.0",
    "gn:admin3_code":"201203.0",
    "gn:asciiname":"Zarzecze Jeleniewskie",
    "gn:country_code":"PL",
    "gn:dem":191,
    "gn:feature_class":"P",
    "gn:feature_code":"PPL",
    "gn:name":"Zarzecze Jeleniewskie",
    "gn:population":0,
    "gn:timezone":"Europe/Warsaw",
    "iso:country":"PL",
    "name:lit_x_preferred":[
        "Za\u017ee\u010d\u0117s Jelenevskiai"
    ],
    "name:pol_x_preferred":[
        "Zarzecze Jeleniewskie"
    ],
    "name:ukr_x_preferred":[
        "\u0417\u0430\u0436\u0435\u0447\u0435-\u0404\u043b\u0435\u043d\u0435\u0432\u0441\u044c\u043a\u0435"
    ],
    "wof:name":"Zarzecze Jeleniewskie",
    "wof:placetype":"locality"
},
  "geometry": {"coordinates":[22.81946,54.20011],"type":"Point"}
}