{
  "type": "Feature",
  "properties": {
    "gn:admin1_code":"81.0",
    "gn:admin2_code":"2012.0",
    "gn:admin3_code":"201203.0",
    "gn:asciiname":"Zarzecze Jeleniewskie",
    "gn:country_code":"PL",
    "gn:dem":191,
    "gn:feature_class":"P",
    "gn:feature_code":"PPL",
    "gn:name":"Zarzecze Jeleniewskie",
    "gn:population":0,
    "gn:timezone":"Europe/Warsaw",
    "iso:country":"PL",
    "wof:name":"Zarzecze Jeleniewskie",
    "wof:placetype":"locality"
},
  "geometry": {"coordinates":[22.81946,54.20011],"type":"Point"}
}