{
  "type": "Feature",
  "properties": {
    "gn:admin1_code":"73.0",
    "gn:admin2_code":"418.0",
    "gn:admin3_code":"41806.0",
    "gn:asciiname":"Sobiczewy",
    "gn:country_code":"PL",
    "gn:dem":129,
    "gn:feature_class":"P",
    "gn:feature_code":"PPL",
    "gn:name":"Sobiczewy",
    "gn:population":0,
    "gn:timezone":"Europe/Warsaw",
    "iso:country":"PL",
    "wof:name":"Sobiczewy",
    "wof:placetype":"locality"
},
  "geometry": {"coordinates":[19.06648,52.42593],"type":"Point"}
}