{
  "type": "Feature",
  "properties": {
    "gn:gn_country":"PL",
    "gn:gn_fcode":"PPL",
    "gn:gn_pop":360,
    "gn:population":360,
    "iso:country":"PL",
    "name:dut_x_preferred":[
        "Koliszowy"
    ],
    "name:eng_x_preferred":[
        "Koliszowy"
    ],
    "name:fre_x_preferred":[
        "Koliszowy"
    ],
    "name:ger_x_preferred":[
        "Koliszowy"
    ],
    "name:nan_x_preferred":[
        "Koliszowy"
    ],
    "name:pol_x_preferred":[
        "Koliszowy"
    ],
    "qs_pg:aaroncc":"PL",
    "qs_pg:gn_country":"PL",
    "qs_pg:gn_fcode":"PPL",
    "qs_pg:gn_pop":360,
    "qs_pg:name":"Koliszowy",
    "qs_pg:name_adm0":"Polska",
    "qs_pg:name_adm1":"Swi\u0119tokrzyskie",
    "qs_pg:photos_9r":0,
    "qs_pg:photos_sr":0,
    "qs_pg:pop_sr":2,
    "qs_pg:qs_pg_placetype":"locality",
    "qs_pg:qs_pg_placetype_gp":"Town",
    "qs_pg:woe_adm0":23424923,
    "woe:adm0_id":23424923,
    "woe:name_adm0":"Polska",
    "woe:name_adm1":"Swi\u0119tokrzyskie",
    "woe:placetype":"Town",
    "wof:name":"Koliszowy",
    "wof:placetype":"locality",
    "wof:population":360
},
  "geometry": {"coordinates":[20.23235,51.17827],"type":"Point"}
}