{
  "type": "Feature",
  "properties": {
    "gn:admin1_code":"82.0",
    "gn:admin2_code":"2215.0",
    "gn:admin3_code":"221508.0",
    "gn:asciiname":"Swichowo",
    "gn:country_code":"PL",
    "gn:dem":61,
    "gn:feature_class":"P",
    "gn:feature_code":"PPL",
    "gn:name":"Swichowo",
    "gn:population":0,
    "gn:timezone":"Europe/Warsaw",
    "iso:country":"PL",
    "name:pol_x_preferred":[
        "\u015awichowo"
    ],
    "wof:name":"Swichowo",
    "wof:placetype":"locality"
},
  "geometry": {"coordinates":[17.84182000000001,54.65388000000001],"type":"Point"}
}