{
  "type": "Feature",
  "properties": {
    "gn:admin1_code":"75.0",
    "gn:admin2_code":"620.0",
    "gn:admin3_code":"62010.0",
    "gn:asciiname":"Wiszenki",
    "gn:country_code":"PL",
    "gn:dem":256,
    "gn:feature_class":"P",
    "gn:feature_code":"PPL",
    "gn:name":"Wiszenki",
    "gn:population":0,
    "gn:timezone":"Europe/Warsaw",
    "iso:country":"PL",
    "name:fra_x_preferred":[
        "Wiszenki"
    ],
    "name:pol_x_preferred":[
        "Wiszenki"
    ],
    "name:ukr_x_preferred":[
        "\u0412\u0456\u0448\u0435\u043d\u043a\u0456"
    ],
    "name:und_x_variant":[
        "Kolonja Wiszenki",
        "Wiszenki"
    ],
    "wof:name":"Wiszenki",
    "wof:placetype":"locality"
},
  "geometry": {"coordinates":[23.29634,50.90098],"type":"Point"}
}