{
  "type": "Feature",
  "properties": {
    "gn:admin1_code":"78.0",
    "gn:admin2_code":"1412.0",
    "gn:admin3_code":"141214.0",
    "gn:asciiname":"Wolka Czarninska",
    "gn:cc2":"PL",
    "gn:country_code":"PL",
    "gn:dem":142,
    "gn:feature_class":"P",
    "gn:feature_code":"PPL",
    "gn:name":"W\u00f3lka Czarni\u0144ska",
    "gn:population":0,
    "gn:timezone":"Europe/Warsaw",
    "iso:country":"PL",
    "name:und_x_variant":[
        "W\u00f3lka Czerni\u0144ska"
    ],
    "wof:name":"Wolka Czarninska",
    "wof:placetype":"locality"
},
  "geometry": {"coordinates":[21.54822,52.2618],"type":"Point"}
}