{
  "type": "Feature",
  "properties": {
    "gn:admin1_code":"72.0",
    "gn:admin2_code":"224.0",
    "gn:admin3_code":"22405.0",
    "gn:asciiname":"Pawlowice",
    "gn:country_code":"PL",
    "gn:dem":266,
    "gn:feature_class":"P",
    "gn:feature_code":"PPL",
    "gn:name":"Paw\u0142owice",
    "gn:population":0,
    "gn:timezone":"Europe/Warsaw",
    "iso:country":"PL",
    "name:pol_x_preferred":[
        "Paw\u0142owice"
    ],
    "name:ukr_x_preferred":[
        "\u041f\u0430\u0432\u043b\u043e\u0432\u0456\u0446\u0435"
    ],
    "wof:name":"Pawlowice",
    "wof:placetype":"locality"
},
  "geometry": {"coordinates":[16.82213,50.54322],"type":"Point"}
}