{
  "type": "Feature",
  "properties": {
    "gn:admin1_code":"73.0",
    "gn:admin2_code":"405.0",
    "gn:admin3_code":"40505.0",
    "gn:asciiname":"Rodzone",
    "gn:country_code":"PL",
    "gn:dem":71,
    "gn:feature_class":"P",
    "gn:feature_code":"PPL",
    "gn:name":"Rodzone",
    "gn:population":0,
    "gn:timezone":"Europe/Warsaw",
    "iso:country":"PL",
    "name:nld_x_preferred":[
        "Rodzone"
    ],
    "name:pol_x_preferred":[
        "Rodzone"
    ],
    "name:ukr_x_preferred":[
        "\u0420\u043e\u0434\u0437\u043e\u043d\u0435"
    ],
    "wof:name":"Rodzone",
    "wof:placetype":"locality"
},
  "geometry": {"coordinates":[19.17053,53.13884],"type":"Point"}
}