{
  "type": "Feature",
  "properties": {
    "gn:admin1_code":"86.0",
    "gn:admin2_code":"3002.0",
    "gn:admin3_code":"300202.0",
    "gn:asciiname":"Kuznica Czarnkowska",
    "gn:country_code":"PL",
    "gn:dem":56,
    "gn:feature_class":"P",
    "gn:feature_code":"PPL",
    "gn:name":"Ku\u017anica Czarnkowska",
    "gn:population":0,
    "gn:timezone":"Europe/Warsaw",
    "iso:country":"PL",
    "name:fra_x_preferred":[
        "Ku\u017anica Czarnkowska"
    ],
    "name:pol_x_preferred":[
        "Ku\u017anica Czarnkowska"
    ],
    "name:szl_x_preferred":[
        "Czarnkowsko Ku\u017a\u0144ica"
    ],
    "name:ukr_x_preferred":[
        "\u041a\u0443\u0437\u044c\u043d\u0438\u0446\u044f-\u0427\u0430\u0440\u043d\u043a\u043e\u0432\u0441\u044c\u043a\u0430"
    ],
    "name:und_x_variant":[
        "Hammer"
    ],
    "wof:name":"Kuznica Czarnkowska",
    "wof:placetype":"locality"
},
  "geometry": {"coordinates":[16.5149,52.94902],"type":"Point"}
}