{
  "type": "Feature",
  "properties": {
    "gn:admin1_code":"74.0",
    "gn:admin2_code":"1007.0",
    "gn:admin3_code":"100706.0",
    "gn:asciiname":"Ponikla",
    "gn:country_code":"PL",
    "gn:dem":149,
    "gn:feature_class":"P",
    "gn:feature_code":"PPL",
    "gn:name":"Ponik\u0142a",
    "gn:population":0,
    "gn:timezone":"Europe/Warsaw",
    "iso:country":"PL",
    "name:fra_x_preferred":[
        "Ponik\u0142a"
    ],
    "name:pol_x_preferred":[
        "Ponik\u0142a"
    ],
    "name:ukr_x_preferred":[
        "\u041f\u043e\u043d\u0456\u043a\u043b\u0430"
    ],
    "wof:name":"Ponikla",
    "wof:placetype":"locality"
},
  "geometry": {"coordinates":[20.31424,51.55178],"type":"Point"}
}