{
  "type": "Feature",
  "properties": {
    "gn:admin1_code":"78.0",
    "gn:admin2_code":"1425.0",
    "gn:admin3_code":"142504.0",
    "gn:asciiname":"Jastrzebia",
    "gn:country_code":"PL",
    "gn:dem":145,
    "gn:feature_class":"P",
    "gn:feature_code":"PPLA3",
    "gn:name":"Jastrz\u0119bia",
    "gn:population":1011,
    "gn:timezone":"Europe/Warsaw",
    "iso:country":"PL",
    "wof:name":"Jastrzebia",
    "wof:placetype":"locality",
    "wof:population":1011
},
  "geometry": {"coordinates":[21.23709,51.49742],"type":"Point"}
}