{
  "type": "Feature",
  "properties": {
    "gn:gn_country":"PL",
    "gn:gn_fcode":"PPLX",
    "gn:gn_pop":1088,
    "gn:population":1088,
    "iso:country":"PL",
    "name:azb_x_preferred":[
        "\u0633\u062a\u0627\u0631\u0627 \u06a9\u0648\u0631\u0646\u0642\u062a\u0633\u0627"
    ],
    "name:deu_x_preferred":[
        "Stara Kornica"
    ],
    "name:eng_x_preferred":[
        "Kornica Stara"
    ],
    "name:fas_x_preferred":[
        "\u0633\u062a\u0627\u0631\u0627 \u06a9\u0648\u0631\u0646\u06af\u062a\u0633\u0627"
    ],
    "name:fra_x_preferred":[
        "Stara Kornica"
    ],
    "name:lit_x_preferred":[
        "Stara Kornica"
    ],
    "name:nld_x_preferred":[
        "Stara Kornica"
    ],
    "name:pol_x_preferred":[
        "Stara Kornica"
    ],
    "name:rus_x_preferred":[
        "\u0421\u0442\u0430\u0440\u0430-\u041a\u043e\u0440\u043d\u0438\u0446\u0430"
    ],
    "name:spa_x_preferred":[
        "Stara Kornica"
    ],
    "name:ukr_x_preferred":[
        "\u0421\u0442\u0430\u0440\u0430 \u041a\u043e\u0440\u043d\u0438\u0446\u044f"
    ],
    "name:unk_x_variant":[
        "SteraKornica"
    ],
    "qs_pg:aaroncc":"PL",
    "qs_pg:gn_country":"PL",
    "qs_pg:gn_fcode":"PPLX",
    "qs_pg:gn_pop":1088,
    "qs_pg:name":"Stara Kornica",
    "qs_pg:photos_9r":0,
    "qs_pg:photos_sr":0,
    "qs_pg:pop_sr":3,
    "qs_pg:qs_pg_placetype":"neighbourhood",
    "wof:name":"Stara Kornica",
    "wof:placetype":"neighbourhood",
    "wof:population":1088
},
  "geometry": {"coordinates":[22.93752,52.18183],"type":"Point"}
}