{
  "type": "Feature",
  "properties": {
    "gn:admin1_code":"73.0",
    "gn:admin2_code":"401.0",
    "gn:admin3_code":"40104.0",
    "gn:asciiname":"Grabie",
    "gn:country_code":"PL",
    "gn:dem":76,
    "gn:feature_class":"P",
    "gn:feature_code":"PPL",
    "gn:name":"Grabie",
    "gn:population":0,
    "gn:timezone":"Europe/Warsaw",
    "iso:country":"PL",
    "name:ceb_x_preferred":[
        "Grabie"
    ],
    "name:ita_x_preferred":[
        "Grabie"
    ],
    "name:pol_x_preferred":[
        "Grabie"
    ],
    "name:ukr_x_preferred":[
        "\u0490\u0440\u0430\u0431\u0435"
    ],
    "wof:name":"Grabie",
    "wof:placetype":"locality"
},
  "geometry": {"coordinates":[18.57078,52.84743],"type":"Point"}
}