{
  "type": "Feature",
  "properties": {
    "gn:admin1_code":"73.0",
    "gn:admin2_code":"403.0",
    "gn:admin3_code":"40304.0",
    "gn:asciiname":"Olszewka",
    "gn:cc2":"PL",
    "gn:country_code":"PL",
    "gn:dem":92,
    "gn:feature_class":"P",
    "gn:feature_code":"PPL",
    "gn:name":"Olszewka",
    "gn:population":0,
    "gn:timezone":"Europe/Warsaw",
    "iso:country":"PL",
    "name:fra_x_preferred":[
        "Olszewka"
    ],
    "name:pol_x_preferred":[
        "Olszewka"
    ],
    "name:ukr_x_preferred":[
        "\u041e\u043b\u044c\u0448\u0435\u0432\u043a\u0430"
    ],
    "name:und_x_variant":[
        "Olszewko"
    ],
    "wof:name":"Olszewka",
    "wof:placetype":"locality"
},
  "geometry": {"coordinates":[17.98333,53.36666999999999],"type":"Point"}
}