{
  "type": "Feature",
  "properties": {
    "gn:admin1_code":"86.0",
    "gn:admin2_code":"3064.0",
    "gn:admin3_code":"306401.0",
    "gn:asciiname":"Stare Winogrady",
    "gn:country_code":"PL",
    "gn:dem":87,
    "gn:feature_class":"P",
    "gn:feature_code":"PPL",
    "gn:name":"Stare Winogrady",
    "gn:population":0,
    "gn:timezone":"Europe/Warsaw",
    "iso:country":"PL",
    "name:eng_x_preferred":[
        "Stare Winogrady"
    ],
    "name:pol_x_preferred":[
        "Stare Winogrady"
    ],
    "wof:name":"Stare Winogrady",
    "wof:placetype":"neighbourhood"
},
  "geometry": {"coordinates":[16.931753,52.42746],"type":"Point"}
}