{
  "type": "Feature",
  "properties": {
    "iso:country":"PL",
    "name:eng_x_preferred":[
        "Stare Winogrady"
    ],
    "name:pol_x_preferred":[
        "Stare Winogrady"
    ],
    "wof:name":"Stare Winogrady",
    "wof:placetype":"neighbourhood"
},
  "geometry": {"coordinates":[16.93175317083072,52.4274595144719],"type":"Point"}
}