{
  "type": "Feature",
  "properties": {
    "gn:admin1_code":"76.0",
    "gn:admin2_code":"812.0",
    "gn:admin3_code":"81203.0",
    "gn:asciiname":"Konradowo",
    "gn:country_code":"PL",
    "gn:dem":98,
    "gn:feature_class":"P",
    "gn:feature_code":"PPL",
    "gn:name":"Konradowo",
    "gn:population":0,
    "gn:timezone":"Europe/Warsaw",
    "iso:country":"PL",
    "name:deu_x_historical":[
        "Kursdorf"
    ],
    "name:deu_x_preferred":[
        "Kursdorf"
    ],
    "wof:name":"Konradowo",
    "wof:placetype":"locality"
},
  "geometry": {"coordinates":[16.27436,51.77931],"type":"Point"}
}