{
  "type": "Feature",
  "properties": {
    "iso:country":"PL",
    "name:pol_x_preferred":[
        "Zbuczyn"
    ],
    "wof:name":"Zbuczyn",
    "wof:placetype":"locality"
},
  "geometry": {"coordinates":[22.4360649469243,52.093158836563],"type":"Point"}
}