{
  "type": "Feature",
  "properties": {
    "iso:country":"PL",
    "name:azb_x_preferred":[
        "\u0632\u0628\u0648\u0686\u0646"
    ],
    "name:ceb_x_preferred":[
        "Zbuczyn"
    ],
    "name:deu_x_preferred":[
        "Zbuczyn"
    ],
    "name:fas_x_preferred":[
        "\u0632\u0628\u0648\u0686\u0646"
    ],
    "name:fra_x_preferred":[
        "Zbuczyn"
    ],
    "name:nld_x_preferred":[
        "Zbuczyn"
    ],
    "name:pol_x_preferred":[
        "Zbuczyn"
    ],
    "name:szl_x_preferred":[
        "Zbuczyn"
    ],
    "name:ukr_x_preferred":[
        "\u0417\u0431\u0443\u0447\u0438\u043d"
    ],
    "wof:coterminous":[
        1125304445
    ],
    "wof:name":"Zbuczyn",
    "wof:placetype":"locality"
},
  "geometry": {"coordinates":[22.4360649469243,52.093158836563],"type":"Point"}
}