{
  "type": "Feature",
  "properties": {
    "gn:admin1_code":"87.0",
    "gn:admin2_code":"3217.0",
    "gn:admin3_code":"321703.0",
    "gn:asciiname":"Bronikowo",
    "gn:country_code":"PL",
    "gn:dem":121,
    "gn:feature_class":"P",
    "gn:feature_code":"PPL",
    "gn:name":"Bronikowo",
    "gn:population":0,
    "gn:timezone":"Europe/Warsaw",
    "iso:country":"PL",
    "name:deu_x_preferred":[
        "Brunk"
    ],
    "name:fra_x_preferred":[
        "Bronikowo"
    ],
    "name:pol_x_preferred":[
        "Bronikowo"
    ],
    "name:ukr_x_preferred":[
        "\u0411\u0440\u043e\u043d\u0456\u043a\u043e\u0432\u043e"
    ],
    "name:vie_x_preferred":[
        "Bronikowo"
    ],
    "wof:name":"Bronikowo",
    "wof:placetype":"locality"
},
  "geometry": {"coordinates":[16.18844,53.30318000000001],"type":"Point"}
}