{
  "type": "Feature",
  "properties": {
    "gn:admin1_code":"73.0",
    "gn:admin2_code":"407.0",
    "gn:admin3_code":"40703.0",
    "gn:asciiname":"Klepary",
    "gn:country_code":"PL",
    "gn:dem":85,
    "gn:feature_class":"P",
    "gn:feature_code":"PPL",
    "gn:name":"Klepary",
    "gn:population":0,
    "gn:timezone":"Europe/Warsaw",
    "iso:country":"PL",
    "name:ceb_x_preferred":[
        "Klepary"
    ],
    "name:deu_x_preferred":[
        "Klepary"
    ],
    "name:pol_x_preferred":[
        "Klepary"
    ],
    "name:ukr_x_preferred":[
        "\u041a\u043b\u0435\u043f\u0430\u0440\u0438"
    ],
    "wof:name":"Klepary",
    "wof:placetype":"locality"
},
  "geometry": {"coordinates":[18.47536,52.84909],"type":"Point"}
}