{
  "type": "Feature",
  "properties": {
    "gn:admin1_code":"78.0",
    "gn:admin2_code":"1401.0",
    "gn:admin3_code":"140104.0",
    "gn:asciiname":"Kadlubek",
    "gn:country_code":"PL",
    "gn:dem":137,
    "gn:feature_class":"P",
    "gn:feature_code":"PPL",
    "gn:name":"Kad\u0142ubek",
    "gn:population":0,
    "gn:timezone":"Europe/Warsaw",
    "iso:country":"PL",
    "name:ceb_x_preferred":[
        "Kad\u0142ubek"
    ],
    "name:fra_x_preferred":[
        "Stary Kad\u0142ubek"
    ],
    "name:pol_x_preferred":[
        "Stary Kad\u0142ubek"
    ],
    "name:spa_x_preferred":[
        "Stary Kad\u0142ubek"
    ],
    "name:ukr_x_preferred":[
        "\u0421\u0442\u0430\u0440\u0438\u0439 \u041a\u0430\u0434\u043b\u0443\u0431\u0435\u043a"
    ],
    "name:und_x_variant":[
        "Kad\u0142ubek Stary"
    ],
    "wof:name":"Kadlubek",
    "wof:placetype":"locality"
},
  "geometry": {"coordinates":[21.06533,51.58515],"type":"Point"}
}