{
  "type": "Feature",
  "properties": {
    "gn:admin1_code":"87.0",
    "gn:admin2_code":"3215.0",
    "gn:admin3_code":"321506.0",
    "gn:asciiname":"Drawien",
    "gn:cc2":"PL",
    "gn:country_code":"PL",
    "gn:dem":148,
    "gn:feature_class":"P",
    "gn:feature_code":"PPL",
    "gn:name":"Drawie\u0144",
    "gn:population":0,
    "gn:timezone":"Europe/Warsaw",
    "iso:country":"PL",
    "name:und_x_variant":[
        "Trabehn",
        "Drawie\u0144"
    ],
    "wof:name":"Drawien",
    "wof:placetype":"locality"
},
  "geometry": {"coordinates":[16.84977,53.65959],"type":"Point"}
}