{
  "type": "Feature",
  "properties": {
    "gn:admin1_code":"72.0",
    "gn:admin2_code":"219.0",
    "gn:admin3_code":"21908.0",
    "gn:asciiname":"Pozarzysko",
    "gn:country_code":"PL",
    "gn:dem":216,
    "gn:feature_class":"P",
    "gn:feature_code":"PPL",
    "gn:name":"Po\u017carzysko",
    "gn:population":0,
    "gn:timezone":"Europe/Warsaw",
    "iso:country":"PL",
    "name:pol_x_preferred":[
        "Po\u017carzysko"
    ],
    "name:ukr_x_preferred":[
        "\u041f\u043e\u0436\u0430\u0436\u0438\u0441\u044c\u043a\u043e"
    ],
    "wof:name":"Pozarzysko",
    "wof:placetype":"locality"
},
  "geometry": {"coordinates":[16.56155,50.94339],"type":"Point"}
}