{
  "type": "Feature",
  "properties": {
    "gn:admin1_code":"75.0",
    "gn:admin2_code":"618.0",
    "gn:admin3_code":"61806.0",
    "gn:asciiname":"Maloniz",
    "gn:country_code":"PL",
    "gn:dem":205,
    "gn:feature_class":"P",
    "gn:feature_code":"PPL",
    "gn:name":"Ma\u0142oni\u017c",
    "gn:population":0,
    "gn:timezone":"Europe/Warsaw",
    "iso:country":"PL",
    "name:fra_x_preferred":[
        "Ma\u0142oni\u017c"
    ],
    "name:pol_x_preferred":[
        "Ma\u0142oni\u017c"
    ],
    "name:ukr_x_preferred":[
        "\u041c\u0430\u043b\u043e\u043d\u0456\u0436"
    ],
    "wof:name":"Maloniz",
    "wof:placetype":"locality"
},
  "geometry": {"coordinates":[23.69159,50.54016],"type":"Point"}
}