{
  "type": "Feature",
  "properties": {
    "iso:country":"PL",
    "name:eng_x_preferred":[
        "Grunwald"
    ],
    "name:pol_x_preferred":[
        "Grunwald"
    ],
    "wof:name":"Grunwald",
    "wof:placetype":"neighbourhood"
},
  "geometry": {"coordinates":[16.87988279866273,52.40049790829971],"type":"Point"}
}