{
  "type": "Feature",
  "properties": {
    "iso:country":"PL",
    "name:ceb_x_preferred":[
        "Grunwald"
    ],
    "name:deu_x_preferred":[
        "Grunwald"
    ],
    "name:eng_x_preferred":[
        "Grunwald"
    ],
    "name:fra_x_preferred":[
        "Grunwald"
    ],
    "name:nld_x_preferred":[
        "Grunwald"
    ],
    "name:pol_x_preferred":[
        "Grunwald"
    ],
    "name:ron_x_preferred":[
        "Gr\u00fcnwald"
    ],
    "name:rus_x_preferred":[
        "\u0413\u0440\u044e\u043d\u0432\u0430\u043b\u044c\u0434"
    ],
    "name:swe_x_preferred":[
        "Grunwald"
    ],
    "name:ukr_x_preferred":[
        "\u0413\u0440\u044e\u043d\u0432\u0430\u043b\u044c\u0434"
    ],
    "wof:name":"Grunwald",
    "wof:placetype":"neighbourhood"
},
  "geometry": {"coordinates":[16.87988279866273,52.40049790829971],"type":"Point"}
}