{
  "type": "Feature",
  "properties": {
    "gn:admin1_code":"77.0",
    "gn:admin2_code":"1210.0",
    "gn:admin3_code":"121006.0",
    "gn:asciiname":"Koniuszowa",
    "gn:country_code":"PL",
    "gn:dem":419,
    "gn:feature_class":"P",
    "gn:feature_code":"PPL",
    "gn:name":"Koniuszowa",
    "gn:population":0,
    "gn:timezone":"Europe/Warsaw",
    "iso:country":"PL",
    "name:pol_x_preferred":[
        "Koniuszowa"
    ],
    "name:ukr_x_preferred":[
        "\u041a\u043e\u043d\u044e\u0448\u043e\u0432\u0430"
    ],
    "wof:name":"Koniuszowa",
    "wof:placetype":"locality"
},
  "geometry": {"coordinates":[20.79276,49.6558],"type":"Point"}
}