{
  "type": "Feature",
  "properties": {
    "gn:admin1_code":"85.0",
    "gn:admin2_code":"2807.0",
    "gn:admin3_code":"280707.0",
    "gn:asciiname":"Kiemiany",
    "gn:country_code":"PL",
    "gn:dem":102,
    "gn:feature_class":"P",
    "gn:feature_code":"PPL",
    "gn:name":"Kiemiany",
    "gn:population":0,
    "gn:timezone":"Europe/Warsaw",
    "iso:country":"PL",
    "name:pol_x_preferred":[
        "Kiemiany"
    ],
    "name:ukr_x_preferred":[
        "\u041a\u0435\u043c\u044f\u043d\u0438"
    ],
    "name:und_x_variant":[
        "K\u00e4mmen"
    ],
    "name:vie_x_preferred":[
        "Kiemiany"
    ],
    "wof:name":"Kiemiany",
    "wof:placetype":"locality"
},
  "geometry": {"coordinates":[19.54652,53.80349],"type":"Point"}
}