{
  "type": "Feature",
  "properties": {
    "gn:admin1_code":"82.0",
    "gn:admin2_code":"2201.0",
    "gn:admin3_code":"220103.0",
    "gn:asciiname":"Mikorowo",
    "gn:country_code":"PL",
    "gn:dem":110,
    "gn:feature_class":"P",
    "gn:feature_code":"PPL",
    "gn:name":"Mikorowo",
    "gn:population":0,
    "gn:timezone":"Europe/Warsaw",
    "iso:country":"PL",
    "name:azb_x_preferred":[
        "\u0645\u06cc\u06a9\u0648\u0631\u0648\u0648\u0648"
    ],
    "name:ceb_x_preferred":[
        "Mikorowo"
    ],
    "name:csb_x_preferred":[
        "Mikrow\u00f2"
    ],
    "name:deu_x_preferred":[
        "Mikorowo"
    ],
    "name:fas_x_preferred":[
        "\u0645\u06cc\u06a9\u0648\u0631\u0648\u0648\u0648"
    ],
    "name:nld_x_preferred":[
        "Mikorowo"
    ],
    "name:pol_x_preferred":[
        "Mikorowo"
    ],
    "name:ukr_x_preferred":[
        "\u041c\u0456\u043a\u043e\u0440\u043e\u0432\u043e"
    ],
    "wof:name":"Mikorowo",
    "wof:placetype":"locality"
},
  "geometry": {"coordinates":[17.58188,54.41824],"type":"Point"}
}