{
  "type": "Feature",
  "properties": {
    "gn:admin1_code":"86.0",
    "gn:admin2_code":"3031.0",
    "gn:admin3_code":"303107.0",
    "gn:asciiname":"Smiardowo Zlotowskie",
    "gn:country_code":"PL",
    "gn:dem":115,
    "gn:feature_class":"P",
    "gn:feature_code":"PPL",
    "gn:name":"\u015amiardowo Z\u0142otowskie",
    "gn:population":0,
    "gn:timezone":"Europe/Warsaw",
    "iso:country":"PL",
    "name:und_x_variant":[
        "\u015amiardowo Z\u0142otowskie"
    ],
    "wof:name":"Smiardowo Zlotowskie",
    "wof:placetype":"locality"
},
  "geometry": {"coordinates":[17.15159,53.36572],"type":"Point"}
}