{
  "type": "Feature",
  "properties": {
    "gn:admin1_code":"86.0",
    "gn:admin2_code":"3031.0",
    "gn:admin3_code":"303107.0",
    "gn:asciiname":"Smiardowo Zlotowskie",
    "gn:country_code":"PL",
    "gn:dem":115,
    "gn:feature_class":"P",
    "gn:feature_code":"PPL",
    "gn:name":"\u015amiardowo Z\u0142otowskie",
    "gn:population":0,
    "gn:timezone":"Europe/Warsaw",
    "iso:country":"PL",
    "name:ceb_x_preferred":[
        "\u015amiardowo Z\u0142otowskie"
    ],
    "name:fra_x_preferred":[
        "\u015amiardowo Z\u0142otowskie"
    ],
    "name:pol_x_preferred":[
        "\u015amiardowo Z\u0142otowskie"
    ],
    "name:ukr_x_preferred":[
        "\u0421\u044c\u043c\u044f\u0440\u0434\u043e\u0432\u043e-\u0417\u043b\u043e\u0442\u043e\u0432\u0441\u044c\u043a\u0435"
    ],
    "wof:name":"Smiardowo Zlotowskie",
    "wof:placetype":"locality"
},
  "geometry": {"coordinates":[17.15159,53.36572],"type":"Point"}
}