{
  "type": "Feature",
  "properties": {
    "gn:admin1_code":"80.0",
    "gn:admin2_code":"1811.0",
    "gn:admin3_code":"181109.0",
    "gn:asciiname":"Borki Nizinskie",
    "gn:country_code":"PL",
    "gn:dem":159,
    "gn:feature_class":"P",
    "gn:feature_code":"PPL",
    "gn:name":"Borki Nizi\u0144skie",
    "gn:population":0,
    "gn:timezone":"Europe/Warsaw",
    "iso:country":"PL",
    "name:nld_x_preferred":[
        "Borki Nizi\u0144skie"
    ],
    "name:pol_x_preferred":[
        "Borki Nizi\u0144skie"
    ],
    "name:ukr_x_preferred":[
        "\u0411\u043e\u0440\u043a\u0456-\u041d\u0456\u0437\u0456\u043d\u0441\u044c\u043a\u0456"
    ],
    "wof:name":"Borki Nizinskie",
    "wof:placetype":"locality"
},
  "geometry": {"coordinates":[21.4222,50.39247],"type":"Point"}
}