{
  "type": "Feature",
  "properties": {
    "iso:country":"PL",
    "qs_pg:aaroncc":"PL",
    "qs_pg:name":"\u015awierad\u00f3w-Zdr\u00f3j",
    "qs_pg:name_adm0":"Polska",
    "qs_pg:name_adm1":"Dolnosl\u0105skie",
    "qs_pg:photos":1,
    "qs_pg:photos_1k":1,
    "qs_pg:photos_9k":1,
    "qs_pg:photos_9r":2,
    "qs_pg:photos_all":69,
    "qs_pg:photos_sr":1,
    "qs_pg:pop_sr":0,
    "qs_pg:qs_pg_placetype":"localadmin",
    "qs_pg:qs_pg_placetype_gp":"LocalAdmin",
    "qs_pg:woe_adm0":23424923,
    "woe:adm0_id":23424923,
    "woe:name_adm0":"Polska",
    "woe:name_adm1":"Dolnosl\u0105skie",
    "woe:placetype":"LocalAdmin",
    "wof:name":"\u015awierad\u00f3w-Zdr\u00f3j",
    "wof:placetype":"localadmin"
},
  "geometry": {"coordinates":[15.323524,50.896861],"type":"Point"}
}