{
  "type": "Feature",
  "properties": {
    "iso:country":"PL",
    "name:azb_x_preferred":[
        "\u0634\u0648\u06cc\u0631\u0627\u062f\u0648\u0648-\u0632\u062f\u0631\u0648\u06cc"
    ],
    "name:ces_x_preferred":[
        "\u015awierad\u00f3w-Zdr\u00f3j"
    ],
    "name:deu_x_preferred":[
        "\u015awierad\u00f3w-Zdr\u00f3j"
    ],
    "name:epo_x_preferred":[
        "\u015awierad\u00f3w-Zdr\u00f3j"
    ],
    "name:eus_x_preferred":[
        "\u015awierad\u00f3w-Zdr\u00f3j"
    ],
    "name:fas_x_preferred":[
        "\u0634\u0648\u06cc\u0631\u0627\u062f\u0648\u0648-\u0632\u062f\u0631\u0648\u06cc"
    ],
    "name:fra_x_preferred":[
        "\u015awierad\u00f3w-Zdr\u00f3j"
    ],
    "name:isl_x_preferred":[
        "\u015awierad\u00f3w-zdr\u00f3j"
    ],
    "name:ita_x_preferred":[
        "\u015awierad\u00f3w-Zdr\u00f3j"
    ],
    "name:jav_x_preferred":[
        "\u015awierad\u00f3w-Zdr\u00f3j"
    ],
    "name:lav_x_preferred":[
        "Sveradovzdroja"
    ],
    "name:msa_x_preferred":[
        "\u015awierad\u00f3w-Zdr\u00f3j"
    ],
    "name:nld_x_preferred":[
        "\u015awierad\u00f3w-Zdr\u00f3j"
    ],
    "name:pol_x_preferred":[
        "\u015awierad\u00f3w-Zdr\u00f3j"
    ],
    "name:por_x_preferred":[
        "\u015awierad\u00f3w-Zdr\u00f3j"
    ],
    "name:ron_x_preferred":[
        "\u015awierad\u00f3w-Zdr\u00f3j"
    ],
    "name:rus_x_preferred":[
        "\u0421\u0432\u0435\u0440\u0430\u0434\u0443\u0432-\u0417\u0434\u0440\u0443\u0439"
    ],
    "name:slk_x_preferred":[
        "\u015awierad\u00f3w-Zdr\u00f3j"
    ],
    "name:srp_x_preferred":[
        "\u0421\u0432\u0458\u0435\u0440\u0430\u0434\u043e\u0432-\u0417\u0434\u0440\u043e\u0458"
    ],
    "name:swe_x_preferred":[
        "\u015awierad\u00f3w-Zdr\u00f3j"
    ],
    "name:ukr_x_preferred":[
        "\u0421\u0432\u0435\u0440\u0430\u0434\u0443\u0432-\u0417\u0434\u0440\u0443\u0439"
    ],
    "name:vie_x_preferred":[
        "\u015awierad\u00f3w-Zdr\u00f3j"
    ],
    "name:war_x_preferred":[
        "\u015awierad\u00f3w-Zdr\u00f3j"
    ],
    "name:zho_x_preferred":[
        "\u5e0c\u7dad\u62c9\u675c\u592b-\u8332\u5fb7\u9b6f\u4f0a"
    ],
    "qs_pg:aaroncc":"PL",
    "qs_pg:name":"\u015awierad\u00f3w-Zdr\u00f3j",
    "qs_pg:name_adm0":"Polska",
    "qs_pg:name_adm1":"Dolnosl\u0105skie",
    "qs_pg:photos":1,
    "qs_pg:photos_1k":1,
    "qs_pg:photos_9k":1,
    "qs_pg:photos_9r":2,
    "qs_pg:photos_all":69,
    "qs_pg:photos_sr":1,
    "qs_pg:pop_sr":0,
    "qs_pg:qs_pg_placetype":"localadmin",
    "qs_pg:qs_pg_placetype_gp":"LocalAdmin",
    "qs_pg:woe_adm0":23424923,
    "woe:adm0_id":23424923,
    "woe:name_adm0":"Polska",
    "woe:name_adm1":"Dolnosl\u0105skie",
    "woe:placetype":"LocalAdmin",
    "wof:name":"\u015awierad\u00f3w-Zdr\u00f3j",
    "wof:placetype":"localadmin"
},
  "geometry": {"coordinates":[15.323524,50.896861],"type":"Point"}
}