{
  "type": "Feature",
  "properties": {
    "gn:admin1_code":"86.0",
    "gn:admin2_code":"3020.0",
    "gn:admin3_code":"302002.0",
    "gn:asciiname":"Leg",
    "gn:country_code":"PL",
    "gn:dem":83,
    "gn:feature_class":"P",
    "gn:feature_code":"PPL",
    "gn:name":"\u0141\u0119g",
    "gn:population":0,
    "gn:timezone":"Europe/Warsaw",
    "iso:country":"PL",
    "name:pol_x_preferred":[
        "\u0141\u0119g"
    ],
    "name:ukr_x_preferred":[
        "\u041b\u0435\u043d\u0491"
    ],
    "wof:name":"Leg",
    "wof:placetype":"locality"
},
  "geometry": {"coordinates":[17.78875,52.01595],"type":"Point"}
}