{
  "type": "Feature",
  "properties": {
    "gn:admin1_code":"80.0",
    "gn:admin2_code":"1807.0",
    "gn:admin3_code":"180709.0",
    "gn:asciiname":"Rzepnik",
    "gn:country_code":"PL",
    "gn:dem":309,
    "gn:feature_class":"P",
    "gn:feature_code":"PPL",
    "gn:name":"Rzepnik",
    "gn:population":0,
    "gn:timezone":"Europe/Warsaw",
    "iso:country":"PL",
    "name:pol_x_preferred":[
        "Rzepnik"
    ],
    "name:rue_x_preferred":[
        "\u0420\u0456\u043f\u043d\u0438\u043a"
    ],
    "name:ukr_x_preferred":[
        "\u0420\u0456\u043f\u043d\u0438\u043a"
    ],
    "wof:name":"Rzepnik",
    "wof:placetype":"locality"
},
  "geometry": {"coordinates":[21.72535,49.79029],"type":"Point"}
}