{
  "type": "Feature",
  "properties": {
    "gn:admin1_code":"80.0",
    "gn:admin2_code":"1801.0",
    "gn:admin3_code":"180105.0",
    "gn:asciiname":"Dwernik",
    "gn:country_code":"PL",
    "gn:dem":545,
    "gn:feature_class":"P",
    "gn:feature_code":"PPL",
    "gn:name":"Dwernik",
    "gn:population":0,
    "gn:timezone":"Europe/Warsaw",
    "iso:country":"PL",
    "name:azb_x_preferred":[
        "\u062f\u0648\u0631\u0646\u0642\u06a9"
    ],
    "name:ceb_x_preferred":[
        "Dwernik"
    ],
    "name:fas_x_preferred":[
        "\u062f\u0648\u0631\u0646\u06af\u06a9"
    ],
    "name:hun_x_preferred":[
        "Dwernik"
    ],
    "name:nld_x_preferred":[
        "Dwernik"
    ],
    "name:pol_x_preferred":[
        "Dwernik"
    ],
    "name:ukr_x_preferred":[
        "\u0414\u0432\u0435\u0440\u043d\u0438\u043a"
    ],
    "wof:name":"Dwernik",
    "wof:placetype":"locality"
},
  "geometry": {"coordinates":[22.62497,49.20728],"type":"Point"}
}