{
  "type": "Feature",
  "properties": {
    "gn:admin1_code":"80.0",
    "gn:admin2_code":"1801.0",
    "gn:admin3_code":"180105.0",
    "gn:asciiname":"Dwernik",
    "gn:country_code":"PL",
    "gn:dem":545,
    "gn:feature_class":"P",
    "gn:feature_code":"PPL",
    "gn:name":"Dwernik",
    "gn:population":0,
    "gn:timezone":"Europe/Warsaw",
    "iso:country":"PL",
    "wof:name":"Dwernik",
    "wof:placetype":"locality"
},
  "geometry": {"coordinates":[22.62497,49.20728],"type":"Point"}
}