{
  "type": "Feature",
  "properties": {
    "gn:country":"PL",
    "gn:fcode":"PPL",
    "gn:population":90,
    "iso:country":"PL",
    "name:ast_x_preferred":[
        "Budziszewice"
    ],
    "name:ces_x_preferred":[
        "Budziszewice"
    ],
    "name:che_x_preferred":[
        "\u0411\u0443\u0434\u0437\u0438\u0448\u0435\u0432\u0438\u0446\u0435"
    ],
    "name:eng_x_preferred":[
        "Budziszewice"
    ],
    "name:fra_x_preferred":[
        "Budziszewice"
    ],
    "name:nan_x_preferred":[
        "Budziszewice"
    ],
    "name:pol_x_preferred":[
        "Budziszewice"
    ],
    "name:tat_x_preferred":[
        "\u0411\u0443\u0434\u0437\u0438\u0448\u0435\u0432\u0438\u0446\u0435"
    ],
    "name:ukr_x_preferred":[
        "\u0411\u0443\u0434\u0437\u0456\u0448\u0435\u0432\u0456\u0446\u0435"
    ],
    "qs_pg:aaroncc":"PL",
    "qs_pg:gn_country":"PL",
    "qs_pg:gn_fcode":"PPL",
    "qs_pg:gn_pop":90,
    "qs_pg:name":"Budziszewice",
    "qs_pg:name_adm0":"Polska",
    "qs_pg:name_adm1":"Wielkopolskie",
    "qs_pg:photos_9r":0,
    "qs_pg:photos_sr":0,
    "qs_pg:pop_sr":1,
    "qs_pg:qs_pg_placetype":"locality",
    "qs_pg:qs_pg_placetype_gp":"Town",
    "qs_pg:woe_adm0":23424923,
    "woe:adm0_id":23424923,
    "woe:name_adm0":"Polska",
    "woe:name_adm1":"Wielkopolskie",
    "woe:placetype":"Town",
    "wof:name":"Budziszewice",
    "wof:placetype":"locality",
    "wof:population":90
},
  "geometry": {"coordinates":[17.06142,52.67102],"type":"Point"}
}