{
  "type": "Feature",
  "properties": {
    "gn:admin1_code":"76.0",
    "gn:admin2_code":"861.0",
    "gn:admin3_code":"86101.0",
    "gn:asciiname":"Wieprzyce",
    "gn:country_code":"PL",
    "gn:dem":27,
    "gn:feature_class":"P",
    "gn:feature_code":"PPL",
    "gn:name":"Wieprzyce",
    "gn:population":0,
    "gn:timezone":"Europe/Warsaw",
    "iso:country":"PL",
    "name:ceb_x_preferred":[
        "Wieprzyce"
    ],
    "name:deu_x_historical":[
        "Wepritz"
    ],
    "name:deu_x_preferred":[
        "Wepritz"
    ],
    "name:fra_x_preferred":[
        "Wieprzyce Dolne"
    ],
    "name:pol_x_preferred":[
        "Wieprzyce"
    ],
    "name:ukr_x_preferred":[
        "\u0412\u0435\u043f\u0448\u0438\u0446\u0435"
    ],
    "wof:name":"Wieprzyce",
    "wof:placetype":"locality"
},
  "geometry": {"coordinates":[15.17414,52.71715],"type":"Point"}
}