{
  "type": "Feature",
  "properties": {
    "gn:admin1_code":"86.0",
    "gn:admin2_code":"3017.0",
    "gn:admin3_code":"301703.0",
    "gn:asciiname":"Raczyce",
    "gn:country_code":"PL",
    "gn:dem":119,
    "gn:feature_class":"P",
    "gn:feature_code":"PPL",
    "gn:name":"Raczyce",
    "gn:population":0,
    "gn:timezone":"Europe/Warsaw",
    "iso:country":"PL",
    "name:ceb_x_preferred":[
        "Raczyce"
    ],
    "name:pol_x_preferred":[
        "Raczyce"
    ],
    "name:spa_x_preferred":[
        "Raczyce"
    ],
    "name:ukr_x_preferred":[
        "\u0420\u0430\u0447\u0438\u0446\u0435"
    ],
    "wof:name":"Raczyce",
    "wof:placetype":"locality"
},
  "geometry": {"coordinates":[17.62962000000001,51.5743],"type":"Point"}
}