{
  "type": "Feature",
  "properties": {
    "gn:admin1_code":"84.0",
    "gn:admin2_code":"2601.0",
    "gn:admin3_code":"260101.0",
    "gn:asciiname":"Dobrowoda",
    "gn:country_code":"PL",
    "gn:dem":224,
    "gn:feature_class":"P",
    "gn:feature_code":"PPL",
    "gn:name":"Dobrowoda",
    "gn:population":0,
    "gn:timezone":"Europe/Warsaw",
    "iso:country":"PL",
    "name:ceb_x_preferred":[
        "Dobrowoda"
    ],
    "name:pol_x_preferred":[
        "Dobrowoda"
    ],
    "name:ukr_x_preferred":[
        "\u0414\u043e\u0431\u0440\u043e\u0432\u043e\u0434\u0430"
    ],
    "wof:name":"Dobrowoda",
    "wof:placetype":"locality"
},
  "geometry": {"coordinates":[20.77152,50.40043],"type":"Point"}
}