{
  "type": "Feature",
  "properties": {
    "iso:country":"PL",
    "name:eng_x_preferred":[
        "Osiedle Oswiecenia"
    ],
    "name:pol_x_preferred":[
        "Osiedle O\u015bwiecenia"
    ],
    "wof:name":"Osiedle Oswiecenia",
    "wof:placetype":"neighbourhood"
},
  "geometry": {"coordinates":[16.95914884174559,52.39103564637654],"type":"Point"}
}