{
  "type": "Feature",
  "properties": {
    "gn:admin1_code":"75.0",
    "gn:admin2_code":"616.0",
    "gn:admin3_code":"61603.0",
    "gn:asciiname":"Lendowka",
    "gn:country_code":"PL",
    "gn:dem":169,
    "gn:feature_class":"P",
    "gn:feature_code":"PPL",
    "gn:name":"Lend\u00f3wka",
    "gn:population":0,
    "gn:timezone":"Europe/Warsaw",
    "iso:country":"PL",
    "wof:name":"Lendowka",
    "wof:placetype":"locality"
},
  "geometry": {"coordinates":[22.15,51.65],"type":"Point"}
}