{
  "type": "Feature",
  "properties": {
    "gn:admin1_code":"75.0",
    "gn:admin2_code":"602.0",
    "gn:admin3_code":"60214.0",
    "gn:asciiname":"Nowa Wies",
    "gn:country_code":"PL",
    "gn:dem":209,
    "gn:feature_class":"P",
    "gn:feature_code":"PPL",
    "gn:name":"Nowa Wie\u015b",
    "gn:population":0,
    "gn:timezone":"Europe/Warsaw",
    "iso:country":"PL",
    "wof:name":"Nowa Wies",
    "wof:placetype":"locality"
},
  "geometry": {"coordinates":[22.84924,50.79368],"type":"Point"}
}