{
  "type": "Feature",
  "properties": {
    "gn:country":"PL",
    "gn:fcode":"PPLX",
    "gn:population":15308,
    "iso:country":"PL",
    "name:deu_x_preferred":[
        "Jelcz"
    ],
    "name:est_x_preferred":[
        "Jelcz"
    ],
    "name:fra_x_preferred":[
        "Jelcz"
    ],
    "name:ita_x_preferred":[
        "Jelcz"
    ],
    "name:jpn_x_preferred":[
        "\u30a4\u30a7\u30eb\u30c1\u793e"
    ],
    "name:nor_x_preferred":[
        "Jelcz"
    ],
    "name:pol_x_preferred":[
        "Jelcz"
    ],
    "name:rus_x_preferred":[
        "Jelcz"
    ],
    "name:spa_x_preferred":[
        "Zak\u0142ady Samochodowe Jelcz SA"
    ],
    "name:ukr_x_preferred":[
        "Jelcz"
    ],
    "name:und_x_variant":[
        "Jeltsch"
    ],
    "qs_pg:aaroncc":"PL",
    "qs_pg:gn_country":"PL",
    "qs_pg:gn_fcode":"PPLX",
    "qs_pg:gn_pop":15308,
    "qs_pg:name":"Jelcz",
    "qs_pg:photos_9r":0,
    "qs_pg:photos_sr":0,
    "qs_pg:pop_sr":6,
    "qs_pg:qs_pg_placetype":"neighbourhood",
    "wof:name":"Jelcz",
    "wof:placetype":"neighbourhood",
    "wof:population":15308
},
  "geometry": {"coordinates":[17.32095,51.02102],"type":"Point"}
}