{
  "type": "Feature",
  "properties": {
    "gn:admin1_code":"87.0",
    "gn:admin2_code":"3203.0",
    "gn:admin3_code":"320301.0",
    "gn:asciiname":"Nowe Drawsko",
    "gn:country_code":"PL",
    "gn:dem":139,
    "gn:feature_class":"P",
    "gn:feature_code":"PPL",
    "gn:name":"Nowe Drawsko",
    "gn:population":0,
    "gn:timezone":"Europe/Warsaw",
    "iso:country":"PL",
    "name:pol_x_preferred":[
        "Nowe Drawsko"
    ],
    "name:ukr_x_preferred":[
        "\u041d\u043e\u0432\u0435 \u0414\u0440\u0430\u0432\u0441\u044c\u043a\u043e"
    ],
    "name:vie_x_preferred":[
        "Nowe Drawsko"
    ],
    "wof:name":"Nowe Drawsko",
    "wof:placetype":"locality"
},
  "geometry": {"coordinates":[16.2259,53.60541],"type":"Point"}
}