{
  "type": "Feature",
  "properties": {
    "iso:country":"PL",
    "qs_pg:aaroncc":"PL",
    "qs_pg:name":"Marcinowice",
    "qs_pg:name_adm0":"Polska",
    "qs_pg:name_adm1":"Dolnosl\u0105skie",
    "qs_pg:photos":30,
    "qs_pg:photos_1k":6,
    "qs_pg:photos_9k":1,
    "qs_pg:photos_9r":3,
    "qs_pg:photos_all":80,
    "qs_pg:photos_sr":2,
    "qs_pg:pop_sr":0,
    "qs_pg:qs_pg_placetype":"localadmin",
    "qs_pg:qs_pg_placetype_gp":"LocalAdmin",
    "qs_pg:woe_adm0":23424923,
    "woe:adm0_id":23424923,
    "woe:name_adm0":"Polska",
    "woe:name_adm1":"Dolnosl\u0105skie",
    "woe:placetype":"LocalAdmin",
    "wof:name":"Marcinowice",
    "wof:placetype":"localadmin"
},
  "geometry": {"coordinates":[16.693769,50.867728],"type":"Point"}
}