{
  "type": "Feature",
  "properties": {
    "gn:admin1_code":"87.0",
    "gn:admin2_code":"3202.0",
    "gn:admin3_code":"320201.0",
    "gn:asciiname":"Gorzno",
    "gn:country_code":"PL",
    "gn:dem":71,
    "gn:feature_class":"P",
    "gn:feature_code":"PPL",
    "gn:name":"G\u00f3rzno",
    "gn:population":0,
    "gn:timezone":"Europe/Warsaw",
    "iso:country":"PL",
    "wof:name":"Gorzno",
    "wof:placetype":"locality"
},
  "geometry": {"coordinates":[15.59509,53.00001],"type":"Point"}
}