{
  "type": "Feature",
  "properties": {
    "gn:admin1_code":"74.0",
    "gn:admin2_code":"1012.0",
    "gn:admin3_code":"101208.0",
    "gn:asciiname":"Wrzesnia",
    "gn:country_code":"PL",
    "gn:dem":228,
    "gn:feature_class":"P",
    "gn:feature_code":"PPL",
    "gn:name":"Wrze\u015bnia",
    "gn:population":0,
    "gn:timezone":"Europe/Warsaw",
    "iso:country":"PL",
    "wof:name":"Wrzesnia",
    "wof:placetype":"locality"
},
  "geometry": {"coordinates":[19.32096,51.12598],"type":"Point"}
}