{
  "type": "Feature",
  "properties": {
    "gn:admin1_code":"78.0",
    "gn:admin2_code":"1406.0",
    "gn:admin3_code":"140601.0",
    "gn:asciiname":"Belsk Duzy",
    "gn:country_code":"PL",
    "gn:dem":176,
    "gn:feature_class":"P",
    "gn:feature_code":"PPLA3",
    "gn:name":"Belsk Du\u017cy",
    "gn:population":0,
    "gn:timezone":"Europe/Warsaw",
    "iso:country":"PL",
    "name:azb_x_preferred":[
        "\u0628\u0644\u0633\u06a9 \u062f\u0648\u0698\u0647"
    ],
    "name:bul_x_preferred":[
        "\u0411\u0435\u043b\u0441\u043a \u0414\u0443\u0436\u0438"
    ],
    "name:deu_x_preferred":[
        "Belsk Du\u017cy"
    ],
    "name:fas_x_preferred":[
        "\u0628\u0644\u0633\u06a9 \u062f\u0648\u0698\u0647"
    ],
    "name:fra_x_preferred":[
        "Belsk Du\u017cy"
    ],
    "name:nld_x_preferred":[
        "Belsk Du\u017cy"
    ],
    "name:pol_x_preferred":[
        "Belsk Du\u017cy"
    ],
    "name:ukr_x_preferred":[
        "\u0411\u0435\u043b\u044c\u0441\u044c\u043a-\u0414\u0443\u0436\u0438"
    ],
    "name:und_x_variant":[
        "Belsk"
    ],
    "wof:coterminous":[
        1477751929
    ],
    "wof:name":"Belsk Duzy",
    "wof:placetype":"locality"
},
  "geometry": {"coordinates":[20.80847,51.82561],"type":"Point"}
}