{
  "type": "Feature",
  "properties": {
    "gn:admin1_code":"78.0",
    "gn:admin2_code":"1406.0",
    "gn:admin3_code":"140601.0",
    "gn:asciiname":"Belsk Duzy",
    "gn:country_code":"PL",
    "gn:dem":176,
    "gn:feature_class":"P",
    "gn:feature_code":"PPLA3",
    "gn:name":"Belsk Du\u017cy",
    "gn:population":0,
    "gn:timezone":"Europe/Warsaw",
    "iso:country":"PL",
    "name:und_x_variant":[
        "Belsk",
        "Belsk Du\u017cy"
    ],
    "wof:name":"Belsk Duzy",
    "wof:placetype":"locality"
},
  "geometry": {"coordinates":[20.80847,51.82561],"type":"Point"}
}