{
  "type": "Feature",
  "properties": {
    "gn:admin1_code":"72.0",
    "gn:admin2_code":"211.0",
    "gn:admin3_code":"21104.0",
    "gn:asciiname":"Parszowice",
    "gn:country_code":"PL",
    "gn:dem":111,
    "gn:feature_class":"P",
    "gn:feature_code":"PPL",
    "gn:name":"Parszowice",
    "gn:population":0,
    "gn:timezone":"Europe/Warsaw",
    "iso:country":"PL",
    "name:ceb_x_preferred":[
        "Parszowice"
    ],
    "name:nld_x_preferred":[
        "Parszowice"
    ],
    "name:pol_x_preferred":[
        "Parszowice"
    ],
    "name:ukr_x_preferred":[
        "\u041f\u0430\u0440\u0448\u043e\u0432\u0456\u0446\u0435"
    ],
    "wof:name":"Parszowice",
    "wof:placetype":"locality"
},
  "geometry": {"coordinates":[16.37665,51.36246],"type":"Point"}
}