{
  "type": "Feature",
  "properties": {
    "gn:admin1_code":"86.0",
    "gn:admin2_code":"3031.0",
    "gn:admin3_code":"303105.0",
    "gn:asciiname":"Pniewo",
    "gn:country_code":"PL",
    "gn:dem":134,
    "gn:feature_class":"P",
    "gn:feature_code":"PPL",
    "gn:name":"Pniewo",
    "gn:population":0,
    "gn:timezone":"Europe/Warsaw",
    "iso:country":"PL",
    "name:ceb_x_preferred":[
        "Pniewo"
    ],
    "name:fra_x_preferred":[
        "Pniewo"
    ],
    "name:pol_x_preferred":[
        "Pniewo"
    ],
    "name:ukr_x_preferred":[
        "\u041f\u043d\u0435\u0432\u043e"
    ],
    "name:und_x_variant":[
        "Pinnow"
    ],
    "wof:name":"Pniewo",
    "wof:placetype":"locality"
},
  "geometry": {"coordinates":[16.75075,53.46219],"type":"Point"}
}