{
  "type": "Feature",
  "properties": {
    "gn:admin1_code":"84.0",
    "gn:admin2_code":"2601.0",
    "gn:admin3_code":"260102.0",
    "gn:asciiname":"Raczyce",
    "gn:country_code":"PL",
    "gn:dem":230,
    "gn:feature_class":"P",
    "gn:feature_code":"PPL",
    "gn:name":"Raczyce",
    "gn:population":0,
    "gn:timezone":"Europe/Warsaw",
    "iso:country":"PL",
    "name:pol_x_preferred":[
        "Raczyce"
    ],
    "name:ukr_x_preferred":[
        "\u0420\u0430\u0447\u0438\u0446\u0435"
    ],
    "wof:name":"Raczyce",
    "wof:placetype":"locality"
},
  "geometry": {"coordinates":[20.88192,50.57942],"type":"Point"}
}