{
  "type": "Feature",
  "properties": {
    "gn:admin1_code":"73.0",
    "gn:admin2_code":"412.0",
    "gn:admin3_code":"41203.0",
    "gn:asciiname":"Rogowko",
    "gn:country_code":"PL",
    "gn:dem":127,
    "gn:feature_class":"P",
    "gn:feature_code":"PPL",
    "gn:name":"Rog\u00f3wko",
    "gn:population":0,
    "gn:timezone":"Europe/Warsaw",
    "iso:country":"PL",
    "wof:name":"Rogowko",
    "wof:placetype":"locality"
},
  "geometry": {"coordinates":[19.35447000000001,52.97975],"type":"Point"}
}