{
  "type": "Feature",
  "properties": {
    "gn:admin1_code":"76.0",
    "gn:admin2_code":"805.0",
    "gn:admin3_code":"80505.0",
    "gn:asciiname":"Nowy Lubusz",
    "gn:country_code":"PL",
    "gn:dem":18,
    "gn:feature_class":"P",
    "gn:feature_code":"PPL",
    "gn:name":"Nowy Lubusz",
    "gn:population":0,
    "gn:timezone":"Europe/Warsaw",
    "iso:country":"PL",
    "name:ceb_x_preferred":[
        "Nowy Lubusz"
    ],
    "name:fra_x_preferred":[
        "Nowy Lubusz"
    ],
    "name:pol_x_preferred":[
        "Nowy Lubusz"
    ],
    "name:ukr_x_preferred":[
        "\u041d\u043e\u0432\u0438\u0439 \u041b\u044e\u0431\u0443\u0448"
    ],
    "wof:name":"Nowy Lubusz",
    "wof:placetype":"locality"
},
  "geometry": {"coordinates":[14.5495,52.40478],"type":"Point"}
}