{
  "type": "Feature",
  "properties": {
    "gn:admin1_code":"74.0",
    "gn:admin2_code":"1018.0",
    "gn:admin3_code":"101804.0",
    "gn:asciiname":"Popielina",
    "gn:country_code":"PL",
    "gn:dem":171,
    "gn:feature_class":"P",
    "gn:feature_code":"PPL",
    "gn:name":"Popielina",
    "gn:population":0,
    "gn:timezone":"Europe/Warsaw",
    "iso:country":"PL",
    "name:pol_x_preferred":[
        "Popielina"
    ],
    "name:ukr_x_preferred":[
        "\u041f\u043e\u043f\u0435\u043b\u0456\u043d\u0430"
    ],
    "wof:name":"Popielina",
    "wof:placetype":"locality"
},
  "geometry": {"coordinates":[18.38909,51.38889],"type":"Point"}
}