{
  "type": "Feature",
  "properties": {
    "gn:admin1_code":"74.0",
    "gn:admin2_code":"1011.0",
    "gn:admin3_code":"101106.0",
    "gn:asciiname":"Wola Zaleska",
    "gn:cc2":"PL",
    "gn:country_code":"PL",
    "gn:dem":139,
    "gn:feature_class":"P",
    "gn:feature_code":"PPL",
    "gn:name":"Wola Zaleska",
    "gn:population":0,
    "gn:timezone":"Europe/Warsaw",
    "iso:country":"PL",
    "name:fra_x_preferred":[
        "Wola Zaleska"
    ],
    "name:pol_x_preferred":[
        "Wola Zaleska"
    ],
    "name:ukr_x_preferred":[
        "\u0412\u043e\u043b\u044f-\u0417\u0430\u043b\u0435\u0441\u044c\u043a\u0430"
    ],
    "name:und_x_variant":[
        "Zaleska Wola"
    ],
    "wof:name":"Wola Zaleska",
    "wof:placetype":"locality"
},
  "geometry": {"coordinates":[18.88333,51.76667],"type":"Point"}
}