{
  "type": "Feature",
  "properties": {
    "gn:admin1_code":"79.0",
    "gn:admin2_code":"1605.0",
    "gn:admin3_code":"160503.0",
    "gn:asciiname":"Zbychowice",
    "gn:country_code":"PL",
    "gn:dem":178,
    "gn:feature_class":"P",
    "gn:feature_code":"PPL",
    "gn:name":"Zbychowice",
    "gn:population":0,
    "gn:timezone":"Europe/Warsaw",
    "iso:country":"PL",
    "name:pol_x_preferred":[
        "Zbychowice"
    ],
    "wof:name":"Zbychowice",
    "wof:placetype":"locality"
},
  "geometry": {"coordinates":[17.84875,50.46958],"type":"Point"}
}