{
  "type": "Feature",
  "properties": {
    "gn:admin1_code":"74.0",
    "gn:admin2_code":"1010.0",
    "gn:admin3_code":"101003.0",
    "gn:asciiname":"Szczepanowice",
    "gn:country_code":"PL",
    "gn:dem":200,
    "gn:feature_class":"P",
    "gn:feature_code":"PPL",
    "gn:name":"Szczepanowice",
    "gn:population":0,
    "gn:timezone":"Europe/Warsaw",
    "iso:country":"PL",
    "name:fra_x_preferred":[
        "Szczepanowice"
    ],
    "name:pol_x_preferred":[
        "Szczepanowice"
    ],
    "name:ukr_x_preferred":[
        "\u0429\u0435\u043f\u0430\u043d\u043e\u0432\u0456\u0446\u0435"
    ],
    "wof:name":"Szczepanowice",
    "wof:placetype":"locality"
},
  "geometry": {"coordinates":[19.6336,51.23317],"type":"Point"}
}