{
  "type": "Feature",
  "properties": {
    "gn:gn_country":"PL",
    "gn:gn_fcode":"PPL",
    "gn:gn_pop":0,
    "iso:country":"PL",
    "name:ast_x_preferred":[
        "\u0141upki"
    ],
    "name:deu_x_preferred":[
        "\u0141upki"
    ],
    "name:eng_x_preferred":[
        "\u0141upki"
    ],
    "name:fra_x_preferred":[
        "\u0141upki"
    ],
    "name:pol_x_preferred":[
        "\u0141upki"
    ],
    "name:ukr_x_preferred":[
        "\u041b\u0443\u043f\u043a\u0456"
    ],
    "name:unk_x_variant":[
        "Kolonia Lupken"
    ],
    "qs_pg:aaroncc":"PL",
    "qs_pg:gn_country":"PL",
    "qs_pg:gn_fcode":"PPL",
    "qs_pg:gn_pop":0,
    "qs_pg:name":"\u0141upki",
    "qs_pg:name_adm0":"Polska",
    "qs_pg:name_adm1":"Warminsko-Mazurskie",
    "qs_pg:photos_9r":0,
    "qs_pg:photos_sr":0,
    "qs_pg:pop_sr":0,
    "qs_pg:qs_pg_placetype":"locality",
    "qs_pg:qs_pg_placetype_gp":"Town",
    "qs_pg:woe_adm0":23424923,
    "woe:adm0_id":23424923,
    "woe:name_adm0":"Polska",
    "woe:name_adm1":"Warminsko-Mazurskie",
    "woe:placetype":"Town",
    "wof:name":"\u0141upki",
    "wof:placetype":"locality"
},
  "geometry": {"coordinates":[21.85767,53.64747],"type":"Point"}
}