{
  "type": "Feature",
  "properties": {
    "gn:admin1_code":"83.0",
    "gn:admin2_code":"2475.0",
    "gn:admin3_code":"247501.0",
    "gn:asciiname":"Modrzejow",
    "gn:country_code":"PL",
    "gn:dem":245,
    "gn:feature_class":"P",
    "gn:feature_code":"PPL",
    "gn:name":"Modrzej\u00f3w",
    "gn:population":0,
    "gn:timezone":"Europe/Warsaw",
    "iso:country":"PL",
    "wof:name":"Modrzejow",
    "wof:placetype":"neighbourhood"
},
  "geometry": {"coordinates":[19.14831,50.24007],"type":"Point"}
}