{
  "type": "Feature",
  "properties": {
    "iso:country":"PL",
    "name:eng_x_preferred":[
        "Stara Prochownia"
    ],
    "name:nld_x_preferred":[
        "Stara Prochownia"
    ],
    "name:pol_x_preferred":[
        "Prochownia",
        "Brama Mostowa w Warszawie"
    ],
    "qs:gn_adm0_cc":"PL",
    "qs:gn_local":766042,
    "qs:gn_nam_loc":"lomianki",
    "qs:gn_namadm1":"78",
    "qs:local_max":102,
    "qs:local_sum":102,
    "qs:localhoods":1,
    "qs:name":"Prochownia",
    "qs:name_adm0":"Polska",
    "qs:name_adm1":"Mazowieckie",
    "qs:name_adm2":"Warszawski Zachodni",
    "qs:name_lau":"\u0141omianki",
    "qs:name_local":"\u0141omianki",
    "qs:photo_max":56,
    "qs:photo_sum":102,
    "qs:placetype":"Suburb",
    "qs:quad_count":15,
    "qs:woe_adm0":23424923,
    "qs:woe_adm1":12577941,
    "qs:woe_adm2":12591305,
    "qs:woe_lau":24548330,
    "qs:woe_local":24548330,
    "qs:woe_ver":"7.10.0",
    "wd:wordcount":275,
    "wof:name":"Prochownia",
    "wof:placetype":"neighbourhood"
},
  "geometry": {"coordinates":[20.894757,52.345965],"type":"Point"}
}