{
  "type": "Feature",
  "properties": {
    "gn:admin1_code":"86.0",
    "gn:admin2_code":"3026.0",
    "gn:admin3_code":"302602.0",
    "gn:asciiname":"Lipowka",
    "gn:country_code":"PL",
    "gn:dem":112,
    "gn:feature_class":"P",
    "gn:feature_code":"PPL",
    "gn:name":"Lip\u00f3wka",
    "gn:population":0,
    "gn:timezone":"Europe/Warsaw",
    "iso:country":"PL",
    "name:fra_x_preferred":[
        "Lip\u00f3wka"
    ],
    "name:pol_x_preferred":[
        "Lip\u00f3wka"
    ],
    "name:ukr_x_preferred":[
        "\u041b\u0456\u043f\u0443\u0432\u043a\u0430"
    ],
    "name:und_x_variant":[
        "Lip\u00f3wka"
    ],
    "wof:name":"Lipowka",
    "wof:placetype":"locality"
},
  "geometry": {"coordinates":[17.15009,51.97548],"type":"Point"}
}