{
  "type": "Feature",
  "properties": {
    "gn:admin1_code":"83.0",
    "gn:admin2_code":"2407.0",
    "gn:admin3_code":"240705.0",
    "gn:asciiname":"Harbultowice",
    "gn:country_code":"PL",
    "gn:dem":289,
    "gn:feature_class":"P",
    "gn:feature_code":"PPL",
    "gn:name":"Harbu\u0142towice",
    "gn:population":0,
    "gn:timezone":"Europe/Warsaw",
    "iso:country":"PL",
    "name:pol_x_preferred":[
        "Harbu\u0142towice"
    ],
    "name:ukr_x_preferred":[
        "\u0413\u0430\u0440\u0431\u0443\u043b\u0442\u043e\u0432\u0456\u0446\u0435"
    ],
    "wof:name":"Harbultowice",
    "wof:placetype":"locality"
},
  "geometry": {"coordinates":[18.7853,50.68611],"type":"Point"}
}