{
  "type": "Feature",
  "properties": {
    "gn:admin1_code":"82.0",
    "gn:admin2_code":"2210.0",
    "gn:admin3_code":"221004.0",
    "gn:asciiname":"Globica",
    "gn:country_code":"PL",
    "gn:dem":0,
    "gn:feature_class":"P",
    "gn:feature_code":"PPL",
    "gn:name":"G\u0142obica",
    "gn:population":0,
    "gn:timezone":"Europe/Warsaw",
    "iso:country":"PL",
    "name:nld_x_preferred":[
        "G\u0142obica"
    ],
    "name:pol_x_preferred":[
        "G\u0142obica"
    ],
    "name:ukr_x_preferred":[
        "\u0490\u043b\u043e\u0431\u0438\u0446\u044f"
    ],
    "name:und_x_variant":[
        "Glabitsch",
        "G\u0142obica"
    ],
    "wof:name":"Globica",
    "wof:placetype":"locality"
},
  "geometry": {"coordinates":[19.08477,54.29581],"type":"Point"}
}