{
  "type": "Feature",
  "properties": {
    "gn:admin1_code":"74.0",
    "gn:admin2_code":"1008.0",
    "gn:admin3_code":"100806.0",
    "gn:asciiname":"Charbice Dolne",
    "gn:country_code":"PL",
    "gn:dem":153,
    "gn:feature_class":"P",
    "gn:feature_code":"PPL",
    "gn:name":"Charbice Dolne",
    "gn:population":0,
    "gn:timezone":"Europe/Warsaw",
    "iso:country":"PL",
    "wof:name":"Charbice Dolne",
    "wof:placetype":"locality"
},
  "geometry": {"coordinates":[19.14908,51.78951],"type":"Point"}
}