{
  "type": "Feature",
  "properties": {
    "gn:admin1_code":"74.0",
    "gn:admin2_code":"1008.0",
    "gn:admin3_code":"100806.0",
    "gn:asciiname":"Charbice Dolne",
    "gn:country_code":"PL",
    "gn:dem":153,
    "gn:feature_class":"P",
    "gn:feature_code":"PPL",
    "gn:name":"Charbice Dolne",
    "gn:population":0,
    "gn:timezone":"Europe/Warsaw",
    "iso:country":"PL",
    "name:azb_x_preferred":[
        "\u062e\u0627\u0631\u0628\u06cc\u062a\u0633\u0647 \u062f\u0648\u0644\u0646\u0647"
    ],
    "name:deu_x_preferred":[
        "Charbice Dolne"
    ],
    "name:fas_x_preferred":[
        "\u062e\u0627\u0631\u0628\u06cc\u062a\u0633\u0647 \u062f\u0648\u0644\u0646\u0647"
    ],
    "name:fra_x_preferred":[
        "Charbice Dolne"
    ],
    "name:pol_x_preferred":[
        "Charbice Dolne"
    ],
    "name:ukr_x_preferred":[
        "\u0425\u0430\u0440\u0431\u0456\u0446\u0435-\u0414\u043e\u043b\u044c\u043d\u0435"
    ],
    "wof:name":"Charbice Dolne",
    "wof:placetype":"locality"
},
  "geometry": {"coordinates":[19.14908,51.78951],"type":"Point"}
}