{
  "type": "Feature",
  "properties": {
    "gn:admin1_code":"77.0",
    "gn:admin2_code":"1207.0",
    "gn:admin3_code":"120704.0",
    "gn:asciiname":"Raciborzany",
    "gn:country_code":"PL",
    "gn:dem":357,
    "gn:feature_class":"P",
    "gn:feature_code":"PPL",
    "gn:name":"Raciborzany",
    "gn:population":0,
    "gn:timezone":"Europe/Warsaw",
    "iso:country":"PL",
    "wof:name":"Raciborzany",
    "wof:placetype":"locality"
},
  "geometry": {"coordinates":[20.19487,49.7717],"type":"Point"}
}