{
  "type": "Feature",
  "properties": {
    "gn:admin1_code":"86.0",
    "gn:admin2_code":"3019.0",
    "gn:admin3_code":"301909.0",
    "gn:asciiname":"Czajcze",
    "gn:country_code":"PL",
    "gn:dem":102,
    "gn:feature_class":"P",
    "gn:feature_code":"PPL",
    "gn:name":"Czajcze",
    "gn:population":0,
    "gn:timezone":"Europe/Warsaw",
    "iso:country":"PL",
    "name:fra_x_preferred":[
        "Czajcze"
    ],
    "name:pol_x_preferred":[
        "Czajcze"
    ],
    "name:ukr_x_preferred":[
        "\u0427\u0430\u0439\u0447\u0435"
    ],
    "wof:name":"Czajcze",
    "wof:placetype":"locality"
},
  "geometry": {"coordinates":[17.12013,53.19081],"type":"Point"}
}