{
  "type": "Feature",
  "properties": {
    "gn:country":"PL",
    "gn:fcode":"PPL",
    "gn:population":727,
    "iso:country":"PL",
    "name:ast_x_preferred":[
        "Go\u0142otczyzna"
    ],
    "name:azb_x_preferred":[
        "\u0642\u0648\u0648\u0648\u062a\u0686\u0632\u0646\u0627"
    ],
    "name:ceb_x_preferred":[
        "Go\u0142otczyzna"
    ],
    "name:eng_x_preferred":[
        "Go\u0142otczyzna"
    ],
    "name:fas_x_preferred":[
        "\u06af\u0648\u0648\u0648\u062a\u0686\u0632\u0646\u0627"
    ],
    "name:fra_x_preferred":[
        "Go\u0142otczyzna"
    ],
    "name:nan_x_preferred":[
        "Go\u0142otczyzna"
    ],
    "name:nld_x_preferred":[
        "Go\u0142otczyzna"
    ],
    "name:pol_x_preferred":[
        "Go\u0142otczyzna"
    ],
    "name:spa_x_preferred":[
        "Go\u0142otczyzna"
    ],
    "name:ukr_x_preferred":[
        "\u0490\u043e\u043b\u043e\u0442\u0447\u0438\u0437\u043d\u0430"
    ],
    "qs_pg:aaroncc":"PL",
    "qs_pg:gn_country":"PL",
    "qs_pg:gn_fcode":"PPL",
    "qs_pg:gn_pop":727,
    "qs_pg:name":"Go\u0142otczyzna",
    "qs_pg:name_adm0":"Polska",
    "qs_pg:name_adm1":"Mazowieckie",
    "qs_pg:photos_9r":0,
    "qs_pg:photos_sr":0,
    "qs_pg:pop_sr":2,
    "qs_pg:qs_pg_placetype":"locality",
    "qs_pg:qs_pg_placetype_gp":"Town",
    "qs_pg:woe_adm0":23424923,
    "woe:adm0_id":23424923,
    "woe:name_adm0":"Polska",
    "woe:name_adm1":"Mazowieckie",
    "woe:placetype":"Town",
    "wof:name":"Go\u0142otczyzna",
    "wof:placetype":"locality",
    "wof:population":727
},
  "geometry": {"coordinates":[20.69112,52.78901],"type":"Point"}
}