{
  "type": "Feature",
  "properties": {
    "gn:admin1_code":"79.0",
    "gn:admin2_code":"1607.0",
    "gn:admin3_code":"160701.0",
    "gn:asciiname":"Zawsie",
    "gn:country_code":"PL",
    "gn:dem":302,
    "gn:feature_class":"P",
    "gn:feature_code":"PPL",
    "gn:name":"Zawsie",
    "gn:population":0,
    "gn:timezone":"Europe/Warsaw",
    "iso:country":"PL",
    "wof:name":"Zawsie",
    "wof:placetype":"locality"
},
  "geometry": {"coordinates":[17.26667,50.35],"type":"Point"}
}