{
  "type": "Feature",
  "properties": {
    "gn:admin1_code":"86.0",
    "gn:admin2_code":"3026.0",
    "gn:admin3_code":"302602.0",
    "gn:asciiname":"Lubiatowo",
    "gn:country_code":"PL",
    "gn:dem":105,
    "gn:feature_class":"P",
    "gn:feature_code":"PPL",
    "gn:name":"Lubiatowo",
    "gn:population":0,
    "gn:timezone":"Europe/Warsaw",
    "iso:country":"PL",
    "name:ceb_x_preferred":[
        "Lubiatowo"
    ],
    "name:fra_x_preferred":[
        "Lubiatowo"
    ],
    "name:pol_x_preferred":[
        "Lubiatowo"
    ],
    "name:ukr_x_preferred":[
        "\u041b\u044e\u0431\u044f\u0442\u043e\u0432\u043e"
    ],
    "wof:name":"Lubiatowo",
    "wof:placetype":"locality"
},
  "geometry": {"coordinates":[17.02982,52.00305],"type":"Point"}
}