{
  "type": "Feature",
  "properties": {
    "gn:admin1_code":"87.0",
    "gn:admin2_code":"3203.0",
    "gn:admin3_code":"320302.0",
    "gn:asciiname":"Suliszewo",
    "gn:country_code":"PL",
    "gn:dem":120,
    "gn:feature_class":"P",
    "gn:feature_code":"PPL",
    "gn:name":"Suliszewo",
    "gn:population":0,
    "gn:timezone":"Europe/Warsaw",
    "iso:country":"PL",
    "wof:name":"Suliszewo",
    "wof:placetype":"locality"
},
  "geometry": {"coordinates":[15.88958,53.52365],"type":"Point"}
}