{
  "type": "Feature",
  "properties": {
    "gn:admin1_code":"73.0",
    "gn:admin2_code":"407.0",
    "gn:admin3_code":"40709.0",
    "gn:asciiname":"Dzwierzchno",
    "gn:country_code":"PL",
    "gn:dem":76,
    "gn:feature_class":"P",
    "gn:feature_code":"PPL",
    "gn:name":"D\u017awierzchno",
    "gn:population":0,
    "gn:timezone":"Europe/Warsaw",
    "iso:country":"PL",
    "name:und_x_variant":[
        "D\u017awierzchno"
    ],
    "wof:name":"Dzwierzchno",
    "wof:placetype":"locality"
},
  "geometry": {"coordinates":[18.07869,52.87011999999999],"type":"Point"}
}