{
  "type": "Feature",
  "properties": {
    "gn:admin1_code":"75.0",
    "gn:admin2_code":"602.0",
    "gn:admin3_code":"60203.0",
    "gn:asciiname":"Brodziaki",
    "gn:country_code":"PL",
    "gn:dem":201,
    "gn:feature_class":"P",
    "gn:feature_code":"PPL",
    "gn:name":"Brodziaki",
    "gn:population":0,
    "gn:timezone":"Europe/Warsaw",
    "iso:country":"PL",
    "name:azb_x_preferred":[
        "\u0628\u0631\u0648\u062c\u0627\u06a9\u06cc"
    ],
    "name:ceb_x_preferred":[
        "Brodziaki"
    ],
    "name:fas_x_preferred":[
        "\u0628\u0631\u0648\u062c\u0627\u06a9\u06cc"
    ],
    "name:fra_x_preferred":[
        "Brodziaki"
    ],
    "name:nld_x_preferred":[
        "Brodziaki"
    ],
    "name:pol_x_preferred":[
        "Brodziaki"
    ],
    "name:ukr_x_preferred":[
        "\u0411\u0440\u043e\u0434\u0437\u044f\u043a\u0438"
    ],
    "wof:name":"Brodziaki",
    "wof:placetype":"locality"
},
  "geometry": {"coordinates":[22.78704,50.50599],"type":"Point"}
}