{
  "type": "Feature",
  "properties": {
    "gn:admin1_code":"81.0",
    "gn:admin2_code":"2004.0",
    "gn:admin3_code":"200402.0",
    "gn:asciiname":"Grozimy",
    "gn:country_code":"PL",
    "gn:dem":129,
    "gn:feature_class":"P",
    "gn:feature_code":"PPL",
    "gn:name":"Grozimy",
    "gn:population":0,
    "gn:timezone":"Europe/Warsaw",
    "iso:country":"PL",
    "name:azb_x_preferred":[
        "\u0642\u0631\u0648\u0698\u0645\u0647"
    ],
    "name:fas_x_preferred":[
        "\u06af\u0631\u0648\u0698\u0645\u0647"
    ],
    "name:fra_x_preferred":[
        "Grozimy"
    ],
    "name:lit_x_preferred":[
        "Grozimai"
    ],
    "name:pol_x_preferred":[
        "Grozimy"
    ],
    "name:ukr_x_preferred":[
        "\u0490\u0440\u043e\u0437\u0456\u043c\u0438"
    ],
    "wof:name":"Grozimy",
    "wof:placetype":"locality"
},
  "geometry": {"coordinates":[22.43101,53.54597],"type":"Point"}
}