{
  "type": "Feature",
  "properties": {
    "gn:admin1_code":"74.0",
    "gn:admin2_code":"1006.0",
    "gn:admin3_code":"100610.0",
    "gn:asciiname":"Konstantyna",
    "gn:country_code":"PL",
    "gn:dem":193,
    "gn:feature_class":"P",
    "gn:feature_code":"PPL",
    "gn:name":"Konstantyna",
    "gn:population":0,
    "gn:timezone":"Europe/Warsaw",
    "iso:country":"PL",
    "name:pol_x_preferred":[
        "Konstantyna"
    ],
    "name:ukr_x_preferred":[
        "\u041a\u043e\u043d\u0441\u0442\u0430\u043d\u0442\u0438\u043d\u0430"
    ],
    "wof:name":"Konstantyna",
    "wof:placetype":"locality"
},
  "geometry": {"coordinates":[19.51112,51.6932],"type":"Point"}
}