{
  "type": "Feature",
  "properties": {
    "gn:country":"PL",
    "gn:fcode":"PPL",
    "gn:population":356,
    "iso:country":"PL",
    "name:ast_x_preferred":[
        "Jab\u0142onna"
    ],
    "name:azb_x_preferred":[
        "\u06cc\u0627\u0628\u0648\u0648\u0646\u0646\u0627"
    ],
    "name:eng_x_preferred":[
        "Jab\u0142onna"
    ],
    "name:fas_x_preferred":[
        "\u06cc\u0627\u0628\u0648\u0648\u0646\u0646\u0627"
    ],
    "name:fra_x_preferred":[
        "Jab\u0142onna"
    ],
    "name:pol_x_preferred":[
        "Jab\u0142onna"
    ],
    "name:ukr_x_preferred":[
        "\u042f\u0431\u043b\u043e\u043d\u043d\u0430"
    ],
    "name:urd_x_preferred":[
        "\u062c\u0628\u0648\u0627\u0646\u0646\u0627\u060c \u0644\u06cc\u0633\u0632\u0646\u0648 \u06a9\u0627\u0624\u0646\u0679\u06cc"
    ],
    "name:urd_x_variant":[
        "\u062c\u0628\u0648\u0627\u0646\u0646\u0627"
    ],
    "qs_pg:aaroncc":"PL",
    "qs_pg:gn_country":"PL",
    "qs_pg:gn_fcode":"PPL",
    "qs_pg:gn_pop":356,
    "qs_pg:name":"Jab\u0142onna",
    "qs_pg:name_adm0":"Polska",
    "qs_pg:name_adm1":"Wielkopolskie",
    "qs_pg:photos_9r":0,
    "qs_pg:photos_sr":0,
    "qs_pg:pop_sr":2,
    "qs_pg:qs_pg_placetype":"locality",
    "qs_pg:qs_pg_placetype_gp":"Town",
    "qs_pg:woe_adm0":23424923,
    "woe:adm0_id":23424923,
    "woe:name_adm0":"Polska",
    "woe:name_adm1":"Wielkopolskie",
    "woe:placetype":"Town",
    "wof:name":"Jab\u0142onna",
    "wof:placetype":"locality",
    "wof:population":356
},
  "geometry": {"coordinates":[16.66188,51.72299],"type":"Point"}
}