{
  "type": "Feature",
  "properties": {
    "gn:admin1_code":"75.0",
    "gn:admin2_code":"620.0",
    "gn:admin3_code":"62014.0",
    "gn:asciiname":"Bortatycze",
    "gn:country_code":"PL",
    "gn:dem":201,
    "gn:feature_class":"P",
    "gn:feature_code":"PPL",
    "gn:name":"Bortatycze",
    "gn:population":0,
    "gn:timezone":"Europe/Warsaw",
    "iso:country":"PL",
    "name:azb_x_preferred":[
        "\u0628\u0648\u0631\u062a\u0627\u062a\u0686\u0647"
    ],
    "name:fas_x_preferred":[
        "\u0628\u0648\u0631\u062a\u0627\u062a\u0686\u0647"
    ],
    "name:fra_x_preferred":[
        "Bortatycze"
    ],
    "name:pol_x_preferred":[
        "Bortatycze"
    ],
    "name:ukr_x_preferred":[
        "\u0411\u043e\u0440\u0442\u0430\u0442\u0438\u0447\u0435"
    ],
    "name:und_x_variant":[
        "Bortaczyce"
    ],
    "wof:name":"Bortatycze",
    "wof:placetype":"locality"
},
  "geometry": {"coordinates":[23.17635,50.7677],"type":"Point"}
}