{
  "type": "Feature",
  "properties": {
    "gn:admin1_code":"82.0",
    "gn:admin2_code":"2203.0",
    "gn:admin3_code":"220302.0",
    "gn:asciiname":"Bincze",
    "gn:country_code":"PL",
    "gn:dem":168,
    "gn:feature_class":"P",
    "gn:feature_code":"PPL",
    "gn:name":"Bi\u0144cze",
    "gn:population":0,
    "gn:timezone":"Europe/Warsaw",
    "iso:country":"PL",
    "name:ceb_x_preferred":[
        "Bi\u0144cze"
    ],
    "name:csb_x_preferred":[
        "Bi\u0144cz\u00e9"
    ],
    "name:nld_x_preferred":[
        "Bi\u0144cze"
    ],
    "name:pol_x_preferred":[
        "Bi\u0144cze"
    ],
    "name:ukr_x_preferred":[
        "\u0411\u0456\u043d\u044c\u0447\u0435"
    ],
    "wof:name":"Bincze",
    "wof:placetype":"locality"
},
  "geometry": {"coordinates":[17.14551,53.64982],"type":"Point"}
}