{
  "type": "Feature",
  "properties": {
    "gn:admin1_code":"78.0",
    "gn:admin2_code":"1438.0",
    "gn:admin3_code":"143803.0",
    "gn:asciiname":"Lajszczew Stary",
    "gn:cc2":"PL",
    "gn:country_code":"PL",
    "gn:dem":153,
    "gn:feature_class":"P",
    "gn:feature_code":"PPL",
    "gn:name":"\u0141ajszczew Stary",
    "gn:population":0,
    "gn:timezone":"Europe/Warsaw",
    "iso:country":"PL",
    "name:fra_x_preferred":[
        "Stary \u0141ajszczew"
    ],
    "name:pol_x_preferred":[
        "Stary \u0141ajszczew"
    ],
    "name:ukr_x_preferred":[
        "\u0421\u0442\u0430\u0440\u0438\u0439 \u041b\u0430\u0439\u0449\u0435\u0432"
    ],
    "name:und_x_variant":[
        "\u0141ajszew Stary",
        "\u0141ajszczew Stary"
    ],
    "wof:name":"Lajszczew Stary",
    "wof:placetype":"locality"
},
  "geometry": {"coordinates":[20.35149,51.93262],"type":"Point"}
}