{
  "type": "Feature",
  "properties": {
    "gn:admin1_code":"80.0",
    "gn:admin2_code":"1807.0",
    "gn:admin3_code":"180705.0",
    "gn:asciiname":"Weglowka",
    "gn:country_code":"PL",
    "gn:dem":304,
    "gn:feature_class":"P",
    "gn:feature_code":"PPL",
    "gn:name":"W\u0119gl\u00f3wka",
    "gn:population":0,
    "gn:timezone":"Europe/Warsaw",
    "iso:country":"PL",
    "name:ceb_x_preferred":[
        "W\u0119gl\u00f3wka"
    ],
    "name:deu_x_preferred":[
        "W\u0119gl\u00f3wka"
    ],
    "name:pol_x_preferred":[
        "W\u0119gl\u00f3wka"
    ],
    "name:rue_x_preferred":[
        "\u0412\u0430\u043d\u0456\u0432\u043a\u0430"
    ],
    "name:ukr_x_preferred":[
        "\u0412\u0430\u043d\u0456\u0432\u043a\u0430"
    ],
    "wof:name":"Weglowka",
    "wof:placetype":"locality"
},
  "geometry": {"coordinates":[21.77324,49.77762],"type":"Point"}
}