{
  "type": "Feature",
  "properties": {
    "gn:admin1_code":"80.0",
    "gn:admin2_code":"1817.0",
    "gn:admin3_code":"181705.0",
    "gn:asciiname":"Zaluz",
    "gn:country_code":"PL",
    "gn:dem":321,
    "gn:feature_class":"P",
    "gn:feature_code":"PPL",
    "gn:name":"Za\u0142u\u017c",
    "gn:population":0,
    "gn:timezone":"Europe/Warsaw",
    "iso:country":"PL",
    "name:ceb_x_preferred":[
        "Za\u0142u\u017c"
    ],
    "name:nld_x_preferred":[
        "Za\u0142u\u017c"
    ],
    "name:pol_x_preferred":[
        "Za\u0142u\u017c"
    ],
    "name:ukr_x_preferred":[
        "\u0417\u0430\u043b\u0443\u0436\u0436\u044f"
    ],
    "wof:name":"Zaluz",
    "wof:placetype":"locality"
},
  "geometry": {"coordinates":[22.30053,49.53078],"type":"Point"}
}