{
  "type": "Feature",
  "properties": {
    "gn:admin1_code":"75.0",
    "gn:admin2_code":"620.0",
    "gn:admin3_code":"62010.0",
    "gn:asciiname":"Marcinowka",
    "gn:country_code":"PL",
    "gn:dem":263,
    "gn:feature_class":"P",
    "gn:feature_code":"PPL",
    "gn:name":"Marcin\u00f3wka",
    "gn:population":0,
    "gn:timezone":"Europe/Warsaw",
    "iso:country":"PL",
    "name:fra_x_preferred":[
        "Marcin\u00f3wka"
    ],
    "name:pol_x_preferred":[
        "Marcin\u00f3wka"
    ],
    "name:ukr_x_preferred":[
        "\u041c\u0430\u0440\u0446\u0438\u043d\u0443\u0432\u043a\u0430"
    ],
    "wof:name":"Marcinowka",
    "wof:placetype":"locality"
},
  "geometry": {"coordinates":[23.41446,50.88762],"type":"Point"}
}