{
  "type": "Feature",
  "properties": {
    "gn:admin1_code":"75.0",
    "gn:admin2_code":"620.0",
    "gn:admin3_code":"62010.0",
    "gn:asciiname":"Marcinowka",
    "gn:country_code":"PL",
    "gn:dem":263,
    "gn:feature_class":"P",
    "gn:feature_code":"PPL",
    "gn:name":"Marcin\u00f3wka",
    "gn:population":0,
    "gn:timezone":"Europe/Warsaw",
    "iso:country":"PL",
    "name:und_x_variant":[
        "Marcin\u00f3wka"
    ],
    "wof:name":"Marcinowka",
    "wof:placetype":"locality"
},
  "geometry": {"coordinates":[23.41446,50.88762],"type":"Point"}
}