{
  "type": "Feature",
  "properties": {
    "gn:admin1_code":"74.0",
    "gn:admin2_code":"1014.0",
    "gn:admin3_code":"101409.0",
    "gn:asciiname":"Zaspy Milkowskie",
    "gn:country_code":"PL",
    "gn:dem":122,
    "gn:feature_class":"P",
    "gn:feature_code":"PPL",
    "gn:name":"Zaspy Mi\u0142kowskie",
    "gn:population":0,
    "gn:timezone":"Europe/Warsaw",
    "iso:country":"PL",
    "name:und_x_variant":[
        "Zaspy",
        "Zaspy Mi\u0142kowskie"
    ],
    "wof:name":"Zaspy Milkowskie",
    "wof:placetype":"locality"
},
  "geometry": {"coordinates":[18.65496,51.82305],"type":"Point"}
}