{
  "type": "Feature",
  "properties": {
    "gn:admin1_code":"81.0",
    "gn:admin2_code":"2013.0",
    "gn:admin3_code":"201309.0",
    "gn:asciiname":"Nowe Gieralty",
    "gn:cc2":"PL",
    "gn:country_code":"PL",
    "gn:dem":143,
    "gn:feature_class":"P",
    "gn:feature_code":"PPL",
    "gn:name":"Nowe Giera\u0142ty",
    "gn:population":0,
    "gn:timezone":"Europe/Warsaw",
    "iso:country":"PL",
    "name:lit_x_preferred":[
        "Nove Gieraltai"
    ],
    "name:pol_x_preferred":[
        "Nowe Giera\u0142ty"
    ],
    "name:ukr_x_preferred":[
        "\u041d\u043e\u0432\u0435 \u0490\u0435\u0440\u0430\u043b\u0442\u0438"
    ],
    "name:und_x_variant":[
        "Giera\u0142ty Nowe",
        "Gieralaty Nowe"
    ],
    "wof:name":"Nowe Gieralty",
    "wof:placetype":"locality"
},
  "geometry": {"coordinates":[22.56137,52.85182],"type":"Point"}
}