{
  "type": "Feature",
  "properties": {
    "gn:admin1_code":"86.0",
    "gn:admin2_code":"3017.0",
    "gn:admin3_code":"301706.0",
    "gn:asciiname":"Glogowa",
    "gn:country_code":"PL",
    "gn:dem":150,
    "gn:feature_class":"P",
    "gn:feature_code":"PPL",
    "gn:name":"G\u0142ogowa",
    "gn:population":0,
    "gn:timezone":"Europe/Warsaw",
    "iso:country":"PL",
    "name:und_x_variant":[
        "G\u0142ogowa"
    ],
    "wof:name":"Glogowa",
    "wof:placetype":"locality"
},
  "geometry": {"coordinates":[17.71255,51.74412],"type":"Point"}
}