{
  "type": "Feature",
  "properties": {
    "iso:country":"PL",
    "name:pol_x_preferred":[
        "Ba\u0142t\u00f3w"
    ],
    "wof:name":"Ba\u0142t\u00f3w",
    "wof:placetype":"locality"
},
  "geometry": {"coordinates":[21.5760708655786,51.0181210406814],"type":"Point"}
}