{
  "type": "Feature",
  "properties": {
    "iso:country":"PL",
    "name:ceb_x_preferred":[
        "Ba\u0142t\u00f3w"
    ],
    "name:deu_x_preferred":[
        "Ba\u0142t\u00f3w"
    ],
    "name:fra_x_preferred":[
        "Ba\u0142t\u00f3w"
    ],
    "name:nld_x_preferred":[
        "Ba\u0142t\u00f3w"
    ],
    "name:pol_x_preferred":[
        "Ba\u0142t\u00f3w"
    ],
    "name:ukr_x_preferred":[
        "\u0411\u0430\u043b\u0442\u0443\u0432"
    ],
    "wof:coterminous":[
        1125370873
    ],
    "wof:name":"Ba\u0142t\u00f3w",
    "wof:placetype":"locality"
},
  "geometry": {"coordinates":[21.5760708655786,51.0181210406814],"type":"Point"}
}