{
  "type": "Feature",
  "properties": {
    "iso:country":"PL",
    "name:eng_x_preferred":[
        "Zakoniczyn"
    ],
    "name:pol_x_preferred":[
        "Zakoniczyn"
    ],
    "wof:name":"Zakoniczyn",
    "wof:placetype":"neighbourhood"
},
  "geometry": {"coordinates":[18.57689467996235,54.32052372648553],"type":"Point"}
}