{
  "type": "Feature",
  "properties": {
    "gn:admin1_code":"75.0",
    "gn:admin2_code":"609.0",
    "gn:admin3_code":"60905.0",
    "gn:asciiname":"Kliny",
    "gn:country_code":"PL",
    "gn:dem":215,
    "gn:feature_class":"P",
    "gn:feature_code":"PPL",
    "gn:name":"Kliny",
    "gn:population":0,
    "gn:timezone":"Europe/Warsaw",
    "iso:country":"PL",
    "name:fra_x_preferred":[
        "Kliny"
    ],
    "name:pol_x_preferred":[
        "Kliny"
    ],
    "name:und_x_variant":[
        "Kolonia Kliny",
        "Kliny"
    ],
    "wof:name":"Kliny",
    "wof:placetype":"locality"
},
  "geometry": {"coordinates":[22.67908,51.17102],"type":"Point"}
}