{
  "type": "Feature",
  "properties": {
    "gn:admin1_code":"74.0",
    "gn:admin2_code":"1001.0",
    "gn:admin3_code":"100104.0",
    "gn:asciiname":"Zlobnica",
    "gn:country_code":"PL",
    "gn:dem":200,
    "gn:feature_class":"P",
    "gn:feature_code":"PPL",
    "gn:name":"\u017b\u0142obnica",
    "gn:population":0,
    "gn:timezone":"Europe/Warsaw",
    "iso:country":"PL",
    "name:fra_x_preferred":[
        "\u017b\u0142obnica"
    ],
    "name:pol_x_preferred":[
        "\u017b\u0142obnica"
    ],
    "name:ukr_x_preferred":[
        "\u0416\u043b\u043e\u0431\u043d\u0438\u0446\u044f"
    ],
    "wof:name":"Zlobnica",
    "wof:placetype":"locality"
},
  "geometry": {"coordinates":[19.25285,51.22774],"type":"Point"}
}