{
  "type": "Feature",
  "properties": {
    "gn:admin1_code":"85.0",
    "gn:admin2_code":"2803.0",
    "gn:admin3_code":"280303.0",
    "gn:asciiname":"Purgalki",
    "gn:country_code":"PL",
    "gn:dem":164,
    "gn:feature_class":"P",
    "gn:feature_code":"PPL",
    "gn:name":"Purga\u0142ki",
    "gn:population":0,
    "gn:timezone":"Europe/Warsaw",
    "iso:country":"PL",
    "name:pol_x_preferred":[
        "Purga\u0142ki"
    ],
    "name:ukr_x_preferred":[
        "\u041f\u0443\u0440\u0491\u0430\u043b\u043a\u0456"
    ],
    "wof:name":"Purgalki",
    "wof:placetype":"locality"
},
  "geometry": {"coordinates":[20.32673,53.21921],"type":"Point"}
}