{
  "type": "Feature",
  "properties": {
    "gn:admin1_code":"80.0",
    "gn:admin2_code":"1820.0",
    "gn:admin3_code":"182003.0",
    "gn:asciiname":"Zupawa",
    "gn:country_code":"PL",
    "gn:dem":149,
    "gn:feature_class":"P",
    "gn:feature_code":"PPL",
    "gn:name":"\u017bupawa",
    "gn:population":0,
    "gn:timezone":"Europe/Warsaw",
    "iso:country":"PL",
    "name:ceb_x_preferred":[
        "\u017bupawa"
    ],
    "name:pol_x_preferred":[
        "\u017bupawa"
    ],
    "name:ukr_x_preferred":[
        "\u0416\u0443\u043f\u0430\u0432\u0430"
    ],
    "wof:name":"Zupawa",
    "wof:placetype":"locality"
},
  "geometry": {"coordinates":[21.77854,50.57767],"type":"Point"}
}