{
  "type": "Feature",
  "properties": {
    "gn:admin1_code":"73.0",
    "gn:asciiname":"Kobyle Bloto",
    "gn:country_code":"PL",
    "gn:dem":78,
    "gn:feature_class":"P",
    "gn:feature_code":"PPL",
    "gn:name":"Kobyle B\u0142oto",
    "gn:population":0,
    "gn:timezone":"Europe/Warsaw",
    "iso:country":"PL",
    "wof:name":"Kobyle Bloto",
    "wof:placetype":"locality"
},
  "geometry": {"coordinates":[19.35503,52.54328],"type":"Point"}
}