{
  "type": "Feature",
  "properties": {
    "gn:admin1_code":"75.0",
    "gn:admin2_code":"601.0",
    "gn:admin3_code":"60114.0",
    "gn:asciiname":"Parosla",
    "gn:country_code":"PL",
    "gn:dem":144,
    "gn:feature_class":"P",
    "gn:feature_code":"PPL",
    "gn:name":"Paro\u015bla",
    "gn:population":0,
    "gn:timezone":"Europe/Warsaw",
    "iso:country":"PL",
    "name:und_x_variant":[
        "Paro\u015bla"
    ],
    "wof:name":"Parosla",
    "wof:placetype":"locality"
},
  "geometry": {"coordinates":[23.61055,51.81025],"type":"Point"}
}