{
  "type": "Feature",
  "properties": {
    "gn:admin1_code":"73.0",
    "gn:admin2_code":"403.0",
    "gn:admin3_code":"40305.0",
    "gn:asciiname":"Dabrowa",
    "gn:country_code":"PL",
    "gn:dem":70,
    "gn:feature_class":"P",
    "gn:feature_code":"PPL",
    "gn:name":"D\u0105browa",
    "gn:population":0,
    "gn:timezone":"Europe/Warsaw",
    "iso:country":"PL",
    "wof:name":"Dabrowa",
    "wof:placetype":"locality"
},
  "geometry": {"coordinates":[18.18333,52.95],"type":"Point"}
}