{
  "type": "Feature",
  "properties": {
    "gn:admin1_code":"72.0",
    "gn:admin2_code":"203.0",
    "gn:admin3_code":"20305.0",
    "gn:asciiname":"Piersna",
    "gn:country_code":"PL",
    "gn:dem":78,
    "gn:feature_class":"P",
    "gn:feature_code":"PPL",
    "gn:name":"Piersna",
    "gn:population":0,
    "gn:timezone":"Europe/Warsaw",
    "iso:country":"PL",
    "name:pol_x_preferred":[
        "Piersna"
    ],
    "name:spa_x_preferred":[
        "Piersna"
    ],
    "name:ukr_x_preferred":[
        "\u041f\u0435\u0440\u0441\u043d\u0430"
    ],
    "wof:name":"Piersna",
    "wof:placetype":"locality"
},
  "geometry": {"coordinates":[16.27609,51.62776],"type":"Point"}
}