{
  "type": "Feature",
  "properties": {
    "gn:admin1_code":"82.0",
    "gn:admin2_code":"2209.0",
    "gn:admin3_code":"220908.0",
    "gn:asciiname":"Klecie",
    "gn:country_code":"PL",
    "gn:dem":4,
    "gn:feature_class":"P",
    "gn:feature_code":"PPL",
    "gn:name":"Klecie",
    "gn:population":0,
    "gn:timezone":"Europe/Warsaw",
    "iso:country":"PL",
    "name:pol_x_preferred":[
        "Klecie"
    ],
    "name:ukr_x_preferred":[
        "\u041a\u043b\u0435\u0446\u0435"
    ],
    "name:und_x_variant":[
        "Klettendorf",
        "Klecia",
        "Klecie"
    ],
    "wof:name":"Klecie",
    "wof:placetype":"locality"
},
  "geometry": {"coordinates":[19.17258,54.02849000000001],"type":"Point"}
}