{
  "type": "Feature",
  "properties": {
    "gn:country":"PL",
    "gn:fcode":"PPL",
    "gn:population":1174,
    "iso:country":"PL",
    "name:azb_x_preferred":[
        "\u062c\u0627\u062f\u0648\u0648\u0627 \u06a9\u0648\u0648\u062f\u0627"
    ],
    "name:ceb_x_preferred":[
        "Dziadowa K\u0142oda"
    ],
    "name:deu_x_preferred":[
        "Gmina Dziadowa K\u0142oda"
    ],
    "name:fas_x_preferred":[
        "\u062c\u0627\u062f\u0648\u0648\u0627 \u06a9\u0648\u0648\u062f\u0627"
    ],
    "name:nld_x_preferred":[
        "Dziadowa K\u0142oda"
    ],
    "name:pol_x_preferred":[
        "Dziadowa K\u0142oda"
    ],
    "name:spa_x_preferred":[
        "Dziadowa K\u0142oda"
    ],
    "name:ukr_x_preferred":[
        "\u0414\u0437\u044f\u0434\u043e\u0432\u0430-\u041a\u043b\u043e\u0434\u0430"
    ],
    "name:und_x_variant":[
        "Kunzendorf"
    ],
    "qs_pg:aaroncc":"PL",
    "qs_pg:gn_country":"PL",
    "qs_pg:gn_fcode":"PPL",
    "qs_pg:gn_pop":1174,
    "qs_pg:name":"Dziadowa K\u0142oda",
    "qs_pg:name_adm0":"Polska",
    "qs_pg:name_adm1":"Dolnosl\u0105skie",
    "qs_pg:photos_9k":1,
    "qs_pg:photos_9r":1,
    "qs_pg:photos_all":2,
    "qs_pg:photos_sr":0,
    "qs_pg:pop_sr":3,
    "qs_pg:qs_pg_placetype":"locality",
    "qs_pg:qs_pg_placetype_gp":"Town",
    "qs_pg:woe_adm0":23424923,
    "woe:adm0_id":23424923,
    "woe:name_adm0":"Polska",
    "woe:name_adm1":"Dolnosl\u0105skie",
    "woe:placetype":"Town",
    "wof:coterminous":[
        1477751281
    ],
    "wof:name":"Dziadowa K\u0142oda",
    "wof:placetype":"locality",
    "wof:population":1174
},
  "geometry": {"coordinates":[17.70919,51.23543],"type":"Point"}
}