{
  "type": "Feature",
  "properties": {
    "gn:country":"PL",
    "gn:fcode":"PPL",
    "gn:population":750,
    "iso:country":"PL",
    "name:ast_x_preferred":[
        "Baran\u00f3wka"
    ],
    "name:ceb_x_preferred":[
        "Baran\u00f3wka"
    ],
    "name:eng_x_preferred":[
        "Baran\u00f3wka"
    ],
    "name:fra_x_preferred":[
        "Baran\u00f3wka"
    ],
    "name:pol_x_preferred":[
        "Baran\u00f3wka"
    ],
    "name:rus_x_preferred":[
        "\u0411\u0430\u0440\u0430\u043d\u0443\u0432\u043a\u0430"
    ],
    "name:ukr_x_preferred":[
        "\u0411\u0430\u0440\u0430\u043d\u0443\u0432\u043a\u0430"
    ],
    "qs_pg:aaroncc":"PL",
    "qs_pg:gn_country":"PL",
    "qs_pg:gn_fcode":"PPL",
    "qs_pg:gn_pop":750,
    "qs_pg:name":"Baran\u00f3wka",
    "qs_pg:name_adm0":"Polska",
    "qs_pg:name_adm1":"Ma\u0142opolskie",
    "qs_pg:photos_9k":1,
    "qs_pg:photos_9r":1,
    "qs_pg:photos_all":12,
    "qs_pg:photos_sr":0,
    "qs_pg:pop_sr":2,
    "qs_pg:qs_pg_placetype":"locality",
    "qs_pg:qs_pg_placetype_gp":"Town",
    "qs_pg:woe_adm0":23424923,
    "woe:adm0_id":23424923,
    "woe:name_adm0":"Polska",
    "woe:name_adm1":"Ma\u0142opolskie",
    "woe:placetype":"Town",
    "wof:name":"Baran\u00f3wka",
    "wof:placetype":"locality",
    "wof:population":750
},
  "geometry": {"coordinates":[20.10283,50.1444],"type":"Point"}
}