{
  "type": "Feature",
  "properties": {
    "gn:admin1_code":"76.0",
    "gn:admin2_code":"804.0",
    "gn:admin3_code":"80408.0",
    "gn:asciiname":"Borowiec",
    "gn:country_code":"PL",
    "gn:dem":68,
    "gn:feature_class":"P",
    "gn:feature_code":"PPL",
    "gn:name":"Borowiec",
    "gn:population":0,
    "gn:timezone":"Europe/Warsaw",
    "iso:country":"PL",
    "name:ceb_x_preferred":[
        "Borowiec"
    ],
    "name:fra_x_preferred":[
        "Borowiec"
    ],
    "name:pol_x_preferred":[
        "Borowiec"
    ],
    "name:ukr_x_preferred":[
        "\u0411\u043e\u0440\u043e\u0432\u0435\u0446\u044c"
    ],
    "wof:name":"Borowiec",
    "wof:placetype":"locality"
},
  "geometry": {"coordinates":[15.86859,51.7985],"type":"Point"}
}