{
  "type": "Feature",
  "properties": {
    "gn:admin1_code":"72",
    "gn:admin2_code":"0209",
    "gn:admin3_code":"20905.0",
    "gn:asciiname":"Makolice",
    "gn:country_code":"PL",
    "gn:dem":169,
    "gn:feature_class":"P",
    "gn:feature_code":"PPL",
    "gn:name":"M\u0105kolice",
    "gn:population":0,
    "gn:timezone":"Europe/Warsaw",
    "iso:country":"PL",
    "name:deu_x_historical":[
        "Mankelwitz"
    ],
    "name:deu_x_preferred":[
        "Mankelwitz"
    ],
    "wof:name":"Makolice",
    "wof:placetype":"locality"
},
  "geometry": {"coordinates":[16.18072,51.12809],"type":"Point"}
}