{
  "type": "Feature",
  "properties": {
    "gn:admin1_code":"80.0",
    "gn:admin2_code":"1808.0",
    "gn:admin3_code":"180805.0",
    "gn:asciiname":"Gosciniec",
    "gn:country_code":"PL",
    "gn:dem":193,
    "gn:feature_class":"P",
    "gn:feature_code":"PPL",
    "gn:name":"Go\u015bciniec",
    "gn:population":0,
    "gn:timezone":"Europe/Warsaw",
    "iso:country":"PL",
    "name:pol_x_preferred":[
        "Go\u015bciniec"
    ],
    "name:und_x_variant":[
        "Go\u015bciniec"
    ],
    "wof:name":"Gosciniec",
    "wof:placetype":"locality"
},
  "geometry": {"coordinates":[22.21667,50.33333],"type":"Point"}
}