{
  "type": "Feature",
  "properties": {
    "gn:admin1_code":"84.0",
    "gn:admin2_code":"2661.0",
    "gn:admin3_code":"266101.0",
    "gn:asciiname":"Na Stoku",
    "gn:country_code":"PL",
    "gn:dem":328,
    "gn:feature_class":"P",
    "gn:feature_code":"PPL",
    "gn:name":"Na Stoku",
    "gn:population":0,
    "gn:timezone":"Europe/Warsaw",
    "iso:country":"PL",
    "wof:name":"Na Stoku",
    "wof:placetype":"neighbourhood"
},
  "geometry": {"coordinates":[20.667,50.89429000000001],"type":"Point"}
}