{
  "type": "Feature",
  "properties": {
    "gn:admin1_code":"78.0",
    "gn:admin2_code":"1413.0",
    "gn:admin3_code":"141304.0",
    "gn:asciiname":"Bonkowo Podlesne",
    "gn:country_code":"PL",
    "gn:dem":115,
    "gn:feature_class":"P",
    "gn:feature_code":"PPL",
    "gn:name":"Bo\u0144kowo Podle\u015bne",
    "gn:population":0,
    "gn:timezone":"Europe/Warsaw",
    "iso:country":"PL",
    "name:fra_x_preferred":[
        "Bo\u0144kowo-Podle\u015bne"
    ],
    "name:ita_x_preferred":[
        "Bo\u0144kowo-Podle\u015bne"
    ],
    "name:pol_x_preferred":[
        "Bo\u0144kowo Podle\u015bne"
    ],
    "name:ukr_x_preferred":[
        "\u0411\u043e\u043d\u044c\u043a\u043e\u0432\u043e-\u041f\u043e\u0434\u043b\u0435\u0441\u044c\u043d\u0435"
    ],
    "wof:name":"Bonkowo Podlesne",
    "wof:placetype":"locality"
},
  "geometry": {"coordinates":[20.19109,52.9623],"type":"Point"}
}