{
  "type": "Feature",
  "properties": {
    "gn:admin1_code":"81.0",
    "gn:admin2_code":"2013.0",
    "gn:admin3_code":"201302.0",
    "gn:asciiname":"Nowodwory",
    "gn:country_code":"PL",
    "gn:dem":119,
    "gn:feature_class":"P",
    "gn:feature_code":"PPL",
    "gn:name":"Nowodwory",
    "gn:population":0,
    "gn:timezone":"Europe/Warsaw",
    "iso:country":"PL",
    "name:azb_x_preferred":[
        "\u0646\u0648\u0648\u0648\u062f\u0648\u0648\u0631\u0647"
    ],
    "name:ceb_x_preferred":[
        "Nowodwory"
    ],
    "name:fas_x_preferred":[
        "\u0646\u0648\u0648\u0648\u062f\u0648\u0648\u0631\u0647"
    ],
    "name:fra_x_preferred":[
        "Nowodwory"
    ],
    "name:lit_x_preferred":[
        "Novodvorai"
    ],
    "name:pol_x_preferred":[
        "Nowodwory"
    ],
    "name:ukr_x_preferred":[
        "\u041d\u043e\u0432\u043e\u0434\u0432\u043e\u0440\u0438"
    ],
    "wof:name":"Nowodwory",
    "wof:placetype":"locality"
},
  "geometry": {"coordinates":[22.45176,52.70083],"type":"Point"}
}