{
  "type": "Feature",
  "properties": {
    "iso:country":"PL",
    "name:eng_x_preferred":[
        "Redzin"
    ],
    "name:pol_x_preferred":[
        "R\u0119dzin"
    ],
    "wof:name":"Redzin",
    "wof:placetype":"neighbourhood"
},
  "geometry": {"coordinates":[16.96690957305067,51.16568651340486],"type":"Point"}
}