{
  "type": "Feature",
  "properties": {
    "gn:admin1_code":"72.0",
    "gn:admin2_code":"264.0",
    "gn:admin3_code":"26401.0",
    "gn:asciiname":"Redzin",
    "gn:country_code":"PL",
    "gn:dem":113,
    "gn:feature_class":"P",
    "gn:feature_code":"PPL",
    "gn:name":"R\u0119dzin",
    "gn:population":0,
    "gn:timezone":"Europe/Warsaw",
    "iso:country":"PL",
    "name:eng_x_preferred":[
        "Redzin"
    ],
    "name:pol_x_preferred":[
        "R\u0119dzin"
    ],
    "name:und_x_variant":[
        "Ransern",
        "R\u0119dzin"
    ],
    "wof:name":"Redzin",
    "wof:placetype":"neighbourhood"
},
  "geometry": {"coordinates":[16.96691,51.165687],"type":"Point"}
}