{
  "type": "Feature",
  "properties": {
    "gn:admin1_code":"82.0",
    "gn:admin2_code":"2205.0",
    "gn:admin3_code":"220502.0",
    "gn:asciiname":"Mezowo",
    "gn:country_code":"PL",
    "gn:dem":180,
    "gn:feature_class":"P",
    "gn:feature_code":"PPL",
    "gn:name":"Mezowo",
    "gn:population":0,
    "gn:timezone":"Europe/Warsaw",
    "iso:country":"PL",
    "name:ceb_x_preferred":[
        "Mezowo"
    ],
    "name:csb_x_preferred":[
        "M\u00e9zow\u00f2"
    ],
    "name:nld_x_preferred":[
        "Mezowo"
    ],
    "name:pol_x_preferred":[
        "Mezowo"
    ],
    "name:ukr_x_preferred":[
        "\u041c\u0435\u0437\u043e\u0432\u043e"
    ],
    "wof:name":"Mezowo",
    "wof:placetype":"locality"
},
  "geometry": {"coordinates":[18.2421,54.31305],"type":"Point"}
}