{
  "type": "Feature",
  "properties": {
    "gn:admin1_code":"77.0",
    "gn:asciiname":"Borowy Mlyn",
    "gn:country_code":"PL",
    "gn:dem":54,
    "gn:feature_class":"P",
    "gn:feature_code":"PPL",
    "gn:name":"Borowy M\u0142yn",
    "gn:population":0,
    "gn:timezone":"Europe/Warsaw",
    "iso:country":"PL",
    "wof:name":"Borowy Mlyn",
    "wof:placetype":"locality"
},
  "geometry": {"coordinates":[15.81004,52.42843],"type":"Point"}
}