{
  "type": "Feature",
  "properties": {
    "gn:admin1_code":"78.0",
    "gn:admin2_code":"1426.0",
    "gn:admin3_code":"142608.0",
    "gn:asciiname":"Grabianow",
    "gn:country_code":"PL",
    "gn:dem":153,
    "gn:feature_class":"P",
    "gn:feature_code":"PPL",
    "gn:name":"Grabian\u00f3w",
    "gn:population":0,
    "gn:timezone":"Europe/Warsaw",
    "iso:country":"PL",
    "name:ceb_x_preferred":[
        "Grabian\u00f3w"
    ],
    "name:fra_x_preferred":[
        "Grabian\u00f3w"
    ],
    "name:pol_x_preferred":[
        "Grabian\u00f3w"
    ],
    "name:szl_x_preferred":[
        "Grabjan\u016fw"
    ],
    "name:ukr_x_preferred":[
        "\u0490\u0440\u0430\u0431\u044f\u043d\u0443\u0432"
    ],
    "wof:name":"Grabianow",
    "wof:placetype":"locality"
},
  "geometry": {"coordinates":[22.27684,52.13686],"type":"Point"}
}