{
  "type": "Feature",
  "properties": {
    "gn:admin1_code":"76.0",
    "gn:admin2_code":"810.0",
    "gn:admin3_code":"81009.0",
    "gn:asciiname":"Dobrenad Kwisa",
    "gn:country_code":"PL",
    "gn:dem":124,
    "gn:feature_class":"P",
    "gn:feature_code":"PPL",
    "gn:name":"Dobrenad Kwisa",
    "gn:population":0,
    "gn:timezone":"Europe/Warsaw",
    "iso:country":"PL",
    "wof:name":"Dobrenad Kwisa",
    "wof:placetype":"locality"
},
  "geometry": {"coordinates":[15.36499,51.52838],"type":"Point"}
}