{
  "type": "Feature",
  "properties": {
    "gn:country":"PL",
    "gn:fcode":"PPLA3",
    "gn:population":1000,
    "iso:country":"PL",
    "name:azb_x_preferred":[
        "\u06cc\u0648\u0631\u062f\u0627\u0646\u0648\u0641 \u0634\u0644\u0627\u0646\u0633\u06a9\u06cc"
    ],
    "name:ceb_x_preferred":[
        "Jordan\u00f3w \u015al\u0105ski"
    ],
    "name:deu_x_preferred":[
        "Jordan\u00f3w \u015al\u0105ski"
    ],
    "name:fas_x_preferred":[
        "\u06cc\u0648\u0631\u062f\u0627\u0646\u0648\u0641 \u0634\u0644\u0627\u0646\u0633\u06a9\u06cc"
    ],
    "name:nld_x_preferred":[
        "Jordan\u00f3w \u015al\u0105ski"
    ],
    "name:pol_x_preferred":[
        "Jordan\u00f3w \u015al\u0105ski"
    ],
    "name:ukr_x_preferred":[
        "\u0419\u043e\u0440\u0434\u0430\u043d\u0443\u0432-\u0428\u043b\u044c\u043e\u043d\u0441\u044c\u043a\u0438\u0439"
    ],
    "name:und_x_variant":[
        "Jordansm\u00fchl"
    ],
    "qs_pg:aaroncc":"PL",
    "qs_pg:gn_country":"PL",
    "qs_pg:gn_fcode":"PPLA3",
    "qs_pg:gn_pop":1000,
    "qs_pg:name":"Jordan\u00f3w \u015al\u0105ski",
    "qs_pg:name_adm0":"Polska",
    "qs_pg:name_adm1":"Dolnosl\u0105skie",
    "qs_pg:photos_9r":0,
    "qs_pg:photos_sr":0,
    "qs_pg:pop_sr":2,
    "qs_pg:qs_pg_placetype":"localadmin",
    "qs_pg:qs_pg_placetype_gp":"LocalAdmin",
    "qs_pg:woe_adm0":23424923,
    "woe:adm0_id":23424923,
    "woe:name_adm0":"Polska",
    "woe:name_adm1":"Dolnosl\u0105skie",
    "woe:placetype":"LocalAdmin",
    "wof:name":"Jordan\u00f3w \u015al\u0105ski",
    "wof:placetype":"localadmin",
    "wof:population":1000
},
  "geometry": {"coordinates":[16.86873,50.86421],"type":"Point"}
}