{
  "type": "Feature",
  "properties": {
    "gn:admin1_code":"86.0",
    "gn:admin2_code":"3010.0",
    "gn:admin3_code":"301004.0",
    "gn:asciiname":"Wola Splawiecka",
    "gn:country_code":"PL",
    "gn:dem":109,
    "gn:feature_class":"P",
    "gn:feature_code":"PPL",
    "gn:name":"Wola Sp\u0142awiecka",
    "gn:population":0,
    "gn:timezone":"Europe/Warsaw",
    "iso:country":"PL",
    "name:ceb_x_preferred":[
        "Wola Sp\u0142awiecka"
    ],
    "name:fra_x_preferred":[
        "Wola Sp\u0142awiecka"
    ],
    "name:pol_x_preferred":[
        "Wola Sp\u0142awiecka"
    ],
    "name:ukr_x_preferred":[
        "\u0412\u043e\u043b\u044f-\u0421\u043f\u043b\u0430\u0432\u0435\u0446\u044c\u043a\u0430"
    ],
    "wof:name":"Wola Splawiecka",
    "wof:placetype":"locality"
},
  "geometry": {"coordinates":[18.15257,52.42981],"type":"Point"}
}