{
  "type": "Feature",
  "properties": {
    "gn:admin1_code":"85.0",
    "gn:admin2_code":"2808.0",
    "gn:admin3_code":"280804.0",
    "gn:asciiname":"Kraskowo",
    "gn:country_code":"PL",
    "gn:dem":96,
    "gn:feature_class":"P",
    "gn:feature_code":"PPL",
    "gn:name":"Kraskowo",
    "gn:population":0,
    "gn:timezone":"Europe/Warsaw",
    "iso:country":"PL",
    "name:eng_x_preferred":[
        "Kraskowo"
    ],
    "name:rus_x_preferred":[
        "\u041a\u0440\u0430\u0441\u043a\u043e\u0432\u043e"
    ],
    "name:und_x_variant":[
        "Sch\u00f6nflies",
        "Sch\u00f6fliess",
        "Kraskowo"
    ],
    "wof:name":"Kraskowo",
    "wof:placetype":"locality"
},
  "geometry": {"coordinates":[21.18189,54.13499],"type":"Point"}
}