{
  "type": "Feature",
  "properties": {
    "gn:admin1_code":"87.0",
    "gn:admin2_code":"3213.0",
    "gn:admin3_code":"321303.0",
    "gn:asciiname":"Sinczyca",
    "gn:country_code":"PL",
    "gn:dem":12,
    "gn:feature_class":"P",
    "gn:feature_code":"PPL",
    "gn:name":"Si\u0144czyca",
    "gn:population":0,
    "gn:timezone":"Europe/Warsaw",
    "iso:country":"PL",
    "name:ceb_x_preferred":[
        "Si\u0144czyca"
    ],
    "name:deu_x_preferred":[
        "Si\u0144czyca"
    ],
    "name:pol_x_preferred":[
        "Si\u0144czyca"
    ],
    "name:ukr_x_preferred":[
        "\u0421\u0456\u043d\u044c\u0447\u0438\u0446\u044f"
    ],
    "name:und_x_variant":[
        "Sch\u00f6ningswalde",
        "Si\u0144czyca"
    ],
    "name:vie_x_preferred":[
        "Si\u0144czyca"
    ],
    "wof:name":"Sinczyca",
    "wof:placetype":"locality"
},
  "geometry": {"coordinates":[16.49343,54.40505],"type":"Point"}
}