{
  "type": "Feature",
  "properties": {
    "gn:admin1_code":"74.0",
    "gn:admin2_code":"1010.0",
    "gn:admin3_code":"101003.0",
    "gn:asciiname":"Pienki Gorzkowskie",
    "gn:country_code":"PL",
    "gn:dem":223,
    "gn:feature_class":"P",
    "gn:feature_code":"PPL",
    "gn:name":"Pie\u0144ki Gorzkowskie",
    "gn:population":0,
    "gn:timezone":"Europe/Warsaw",
    "iso:country":"PL",
    "name:fra_x_preferred":[
        "Pie\u0144ki Gorzkowskie"
    ],
    "name:pol_x_preferred":[
        "Pie\u0144ki Gorzkowskie"
    ],
    "name:und_x_variant":[
        "Pie\u0144ki Gorzkowskie"
    ],
    "wof:name":"Pienki Gorzkowskie",
    "wof:placetype":"locality"
},
  "geometry": {"coordinates":[19.64313,51.20194],"type":"Point"}
}