{
  "type": "Feature",
  "properties": {
    "gn:admin1_code":"81.0",
    "gn:admin2_code":"2005.0",
    "gn:admin3_code":"200503.0",
    "gn:asciiname":"Polovtsy",
    "gn:country_code":"PL",
    "gn:dem":173,
    "gn:feature_class":"P",
    "gn:feature_code":"PPL",
    "gn:name":"Polovtsy",
    "gn:population":0,
    "gn:timezone":"Europe/Warsaw",
    "iso:country":"PL",
    "wof:name":"Polovtsy",
    "wof:placetype":"locality"
},
  "geometry": {"coordinates":[23.36667000000001,52.48333],"type":"Point"}
}