{
  "type": "Feature",
  "properties": {
    "gn:admin1_code":"78.0",
    "gn:admin2_code":"1407.0",
    "gn:admin3_code":"140701.0",
    "gn:asciiname":"Wygwizdow",
    "gn:cc2":"PL",
    "gn:country_code":"PL",
    "gn:dem":156,
    "gn:feature_class":"P",
    "gn:feature_code":"PPL",
    "gn:name":"Wygwizd\u00f3w",
    "gn:population":0,
    "gn:timezone":"Europe/Warsaw",
    "iso:country":"PL",
    "name:und_x_variant":[
        "Nowa Wie\u015b",
        "Wygwizd\u00f3w"
    ],
    "wof:name":"Wygwizdow",
    "wof:placetype":"locality"
},
  "geometry": {"coordinates":[21.63333,51.48333],"type":"Point"}
}