{
  "type": "Feature",
  "properties": {
    "gn:admin1_code":"85.0",
    "gn:admin2_code":"2802.0",
    "gn:admin3_code":"280202.0",
    "gn:asciiname":"Brzeszczyny",
    "gn:cc2":"PL",
    "gn:country_code":"PL",
    "gn:dem":56,
    "gn:feature_class":"P",
    "gn:feature_code":"PPL",
    "gn:name":"Brzeszczyny",
    "gn:population":0,
    "gn:timezone":"Europe/Warsaw",
    "iso:country":"PL",
    "name:azb_x_preferred":[
        "\u0628\u0698\u0634\u0686\u0646\u0647"
    ],
    "name:ceb_x_preferred":[
        "Brzeszczyny"
    ],
    "name:fas_x_preferred":[
        "\u0628\u0698\u0634\u0686\u0646\u0647"
    ],
    "name:fra_x_preferred":[
        "Brzeszczyny"
    ],
    "name:nld_x_preferred":[
        "Brzeszczyny"
    ],
    "name:pol_x_preferred":[
        "Brzeszczyny"
    ],
    "name:und_x_variant":[
        "Schwillgarben"
    ],
    "name:urd_x_preferred":[
        "\u0628\u0631\u0632\u0633\u0632\u06a9\u0632\u06cc\u0646\u0646\u06d2"
    ],
    "name:vie_x_preferred":[
        "Brzeszczyny"
    ],
    "wof:name":"Brzeszczyny",
    "wof:placetype":"locality"
},
  "geometry": {"coordinates":[19.89161,54.32183000000001],"type":"Point"}
}