{
  "type": "Feature",
  "properties": {
    "gn:admin1_code":"73.0",
    "gn:admin2_code":"403.0",
    "gn:admin3_code":"40301.0",
    "gn:asciiname":"Przyleki",
    "gn:country_code":"PL",
    "gn:dem":67,
    "gn:feature_class":"P",
    "gn:feature_code":"PPL",
    "gn:name":"Przy\u0142\u0119ki",
    "gn:population":0,
    "gn:timezone":"Europe/Warsaw",
    "iso:country":"PL",
    "name:und_x_variant":[
        "Przy\u0142\u0119ki"
    ],
    "wof:name":"Przyleki",
    "wof:placetype":"locality"
},
  "geometry": {"coordinates":[17.96763,53.03771999999999],"type":"Point"}
}