{
  "type": "Feature",
  "properties": {
    "gn:admin1_code":"77.0",
    "gn:admin2_code":"1216.0",
    "gn:admin3_code":"121609.0",
    "gn:asciiname":"Zawada",
    "gn:country_code":"PL",
    "gn:dem":341,
    "gn:feature_class":"P",
    "gn:feature_code":"PPL",
    "gn:name":"Zawada",
    "gn:population":0,
    "gn:timezone":"Europe/Warsaw",
    "iso:country":"PL",
    "name:pol_x_preferred":[
        "Zawada"
    ],
    "name:ukr_x_preferred":[
        "\u0417\u0430\u0432\u0430\u0434\u0430"
    ],
    "wof:name":"Zawada",
    "wof:placetype":"locality"
},
  "geometry": {"coordinates":[21.0141,49.98015],"type":"Point"}
}