{
  "type": "Feature",
  "properties": {
    "gn:admin1_code":"73.0",
    "gn:admin2_code":"413.0",
    "gn:admin3_code":"41301.0",
    "gn:asciiname":"Jerzmionki",
    "gn:country_code":"PL",
    "gn:dem":148,
    "gn:feature_class":"P",
    "gn:feature_code":"PPL",
    "gn:name":"Jerzmionki",
    "gn:population":0,
    "gn:timezone":"Europe/Warsaw",
    "iso:country":"PL",
    "name:pol_x_preferred":[
        "Jerzmionki"
    ],
    "name:ukr_x_preferred":[
        "\u0404\u0436\u043c\u0439\u043e\u043d\u043a\u0456"
    ],
    "wof:name":"Jerzmionki",
    "wof:placetype":"locality"
},
  "geometry": {"coordinates":[17.51001,53.60484],"type":"Point"}
}