{
  "type": "Feature",
  "properties": {
    "gn:admin1_code":"72.0",
    "gn:admin2_code":"226.0",
    "gn:admin3_code":"22601.0",
    "gn:asciiname":"Wojcieszow Gorny",
    "gn:country_code":"PL",
    "gn:dem":379,
    "gn:feature_class":"P",
    "gn:feature_code":"PPL",
    "gn:name":"Wojciesz\u00f3w G\u00f3rny",
    "gn:population":0,
    "gn:timezone":"Europe/Warsaw",
    "iso:country":"PL",
    "name:und_x_variant":[
        "Wojciesz\u00f3w G\u00f3rny"
    ],
    "wof:name":"Wojcieszow Gorny",
    "wof:placetype":"locality"
},
  "geometry": {"coordinates":[15.91667,50.95],"type":"Point"}
}