{
  "type": "Feature",
  "properties": {
    "iso:country":"PL",
    "name:eng_x_preferred":[
        "Lostowice"
    ],
    "name:pol_x_preferred":[
        "\u0141ostowice"
    ],
    "wof:name":"Lostowice",
    "wof:placetype":"neighbourhood"
},
  "geometry": {"coordinates":[18.59095457124423,54.31856892506439],"type":"Point"}
}