{
  "type": "Feature",
  "properties": {
    "gn:admin1_code":"81.0",
    "gn:admin2_code":"2002.0",
    "gn:admin3_code":"200208.0",
    "gn:asciiname":"Lukawica",
    "gn:country_code":"PL",
    "gn:dem":137,
    "gn:feature_class":"P",
    "gn:feature_code":"PPL",
    "gn:name":"\u0141ukawica",
    "gn:population":0,
    "gn:timezone":"Europe/Warsaw",
    "iso:country":"PL",
    "name:lit_x_preferred":[
        "Lukavica"
    ],
    "name:pol_x_preferred":[
        "\u0141ukawica"
    ],
    "name:ukr_x_preferred":[
        "\u041b\u0443\u043a\u0430\u0432\u0438\u0446\u044f"
    ],
    "wof:name":"Lukawica",
    "wof:placetype":"locality"
},
  "geometry": {"coordinates":[22.84531,52.86975],"type":"Point"}
}