{
  "type": "Feature",
  "properties": {
    "gn:admin1_code":"81.0",
    "gn:admin2_code":"2002.0",
    "gn:admin3_code":"200208.0",
    "gn:asciiname":"Lukawica",
    "gn:country_code":"PL",
    "gn:dem":137,
    "gn:feature_class":"P",
    "gn:feature_code":"PPL",
    "gn:name":"\u0141ukawica",
    "gn:population":0,
    "gn:timezone":"Europe/Warsaw",
    "iso:country":"PL",
    "name:und_x_variant":[
        "\u0141ukawica"
    ],
    "wof:name":"Lukawica",
    "wof:placetype":"locality"
},
  "geometry": {"coordinates":[22.84531,52.86975],"type":"Point"}
}