{
  "type": "Feature",
  "properties": {
    "gn:admin1_code":"74.0",
    "gn:admin2_code":"1017.0",
    "gn:admin3_code":"101701.0",
    "gn:asciiname":"Lyskornia",
    "gn:country_code":"PL",
    "gn:dem":187,
    "gn:feature_class":"P",
    "gn:feature_code":"PPL",
    "gn:name":"\u0141yskornia",
    "gn:population":0,
    "gn:timezone":"Europe/Warsaw",
    "iso:country":"PL",
    "name:pol_x_preferred":[
        "\u0141yskornia"
    ],
    "name:ukr_x_preferred":[
        "\u041b\u0438\u0441\u043a\u043e\u0440\u043d\u044f"
    ],
    "wof:name":"Lyskornia",
    "wof:placetype":"locality"
},
  "geometry": {"coordinates":[18.39558,51.26181],"type":"Point"}
}