{
  "type": "Feature",
  "properties": {
    "gn:admin1_code":"76.0",
    "gn:admin2_code":"861.0",
    "gn:admin3_code":"86101.0",
    "gn:asciiname":"Karnin",
    "gn:country_code":"PL",
    "gn:dem":22,
    "gn:feature_class":"P",
    "gn:feature_code":"PPL",
    "gn:name":"Karnin",
    "gn:population":0,
    "gn:timezone":"Europe/Warsaw",
    "iso:country":"PL",
    "name:und_x_variant":[
        "Kernein",
        "Karnin"
    ],
    "wof:name":"Karnin",
    "wof:placetype":"locality"
},
  "geometry": {"coordinates":[15.28164,52.69071],"type":"Point"}
}