{
  "type": "Feature",
  "properties": {
    "gn:admin1_code":"82.0",
    "gn:admin2_code":"2216.0",
    "gn:admin3_code":"221601.0",
    "gn:asciiname":"Pacholy",
    "gn:country_code":"PL",
    "gn:dem":22,
    "gn:feature_class":"P",
    "gn:feature_code":"PPL",
    "gn:name":"Pacho\u0142y",
    "gn:population":0,
    "gn:timezone":"Europe/Warsaw",
    "iso:country":"PL",
    "name:pol_x_preferred":[
        "Pacho\u0142y"
    ],
    "wof:name":"Pacholy",
    "wof:placetype":"locality"
},
  "geometry": {"coordinates":[19.37971,53.93057],"type":"Point"}
}