{
  "type": "Feature",
  "properties": {
    "iso:country":"PL",
    "name:ceb_x_preferred":[
        "Lesnica"
    ],
    "name:eng_x_preferred":[
        "Lesnica"
    ],
    "name:fra_x_preferred":[
        "Lesnica"
    ],
    "name:nld_x_preferred":[
        "Lesnica"
    ],
    "name:pol_x_preferred":[
        "Le\u015bnica"
    ],
    "name:swe_x_preferred":[
        "Lesnica"
    ],
    "wof:name":"Lesnica",
    "wof:placetype":"neighbourhood"
},
  "geometry": {"coordinates":[16.86162423032181,51.14919056468108],"type":"Point"}
}