{
  "type": "Feature",
  "properties": {
    "gn:admin1_code":"73.0",
    "gn:admin2_code":"415.0",
    "gn:admin3_code":"41504.0",
    "gn:asciiname":"Osada Lubicz",
    "gn:country_code":"PL",
    "gn:dem":47,
    "gn:feature_class":"P",
    "gn:feature_code":"PPL",
    "gn:name":"Osada Lubicz",
    "gn:population":0,
    "gn:timezone":"Europe/Warsaw",
    "iso:country":"PL",
    "name:azb_x_preferred":[
        "\u0642\u0645\u06cc\u0646\u0627 \u0644\u0648\u0628\u06cc\u0686"
    ],
    "name:bel_x_preferred":[
        "\u041b\u044e\u0431\u0456\u0447"
    ],
    "name:ceb_x_preferred":[
        "Lubicz"
    ],
    "name:deu_x_preferred":[
        "Gmina Lubicz"
    ],
    "name:eng_x_preferred":[
        "Osada Lubicz"
    ],
    "name:eus_x_preferred":[
        "Lubicz udalerria"
    ],
    "name:fas_x_preferred":[
        "\u06af\u0645\u06cc\u0646\u0627 \u0644\u0648\u0628\u06cc\u0686"
    ],
    "name:fra_x_preferred":[
        "Lubicz"
    ],
    "name:ita_x_preferred":[
        "Lubicz"
    ],
    "name:nld_x_preferred":[
        "Lubicz"
    ],
    "name:pol_x_preferred":[
        "Lubicz"
    ],
    "name:rus_x_preferred":[
        "\u041b\u044e\u0431\u0438\u0447"
    ],
    "name:slk_x_preferred":[
        "Gmina Lubicz"
    ],
    "name:ukr_x_preferred":[
        "\u0413\u043c\u0456\u043d\u0430 \u041b\u044e\u0431\u0438\u0447"
    ],
    "name:war_x_preferred":[
        "Gmina Lubicz"
    ],
    "wof:name":"Osada Lubicz",
    "wof:placetype":"locality"
},
  "geometry": {"coordinates":[18.76226,53.03197],"type":"Point"}
}