{
  "type": "Feature",
  "properties": {
    "gn:admin1_code":"73.0",
    "gn:admin2_code":"415.0",
    "gn:admin3_code":"41504.0",
    "gn:asciiname":"Osada Lubicz",
    "gn:country_code":"PL",
    "gn:dem":47,
    "gn:feature_class":"P",
    "gn:feature_code":"PPL",
    "gn:name":"Osada Lubicz",
    "gn:population":0,
    "gn:timezone":"Europe/Warsaw",
    "iso:country":"PL",
    "name:eng_x_preferred":[
        "Osada Lubicz"
    ],
    "name:rus_x_preferred":[
        "\u041b\u044e\u0431\u0438\u0447"
    ],
    "name:und_x_variant":[
        "Lubicz",
        "Osada Lubicz"
    ],
    "wof:name":"Osada Lubicz",
    "wof:placetype":"locality"
},
  "geometry": {"coordinates":[18.76226,53.03197],"type":"Point"}
}