{
  "type": "Feature",
  "properties": {
    "gn:admin1_code":"81.0",
    "gn:admin2_code":"2013.0",
    "gn:admin3_code":"201305.0",
    "gn:asciiname":"Stypulki Borki",
    "gn:country_code":"PL",
    "gn:dem":131,
    "gn:feature_class":"P",
    "gn:feature_code":"PPL",
    "gn:name":"Stypu\u0142ki Borki",
    "gn:population":0,
    "gn:timezone":"Europe/Warsaw",
    "iso:country":"PL",
    "name:fra_x_preferred":[
        "Stypu\u0142ki-Borki"
    ],
    "name:lit_x_preferred":[
        "Stipulki Borkai"
    ],
    "name:pol_x_preferred":[
        "Stypu\u0142ki-Borki"
    ],
    "name:ukr_x_preferred":[
        "\u0421\u0442\u0438\u043f\u0443\u043b\u043a\u0456-\u0411\u043e\u0440\u043a\u0456"
    ],
    "name:und_x_variant":[
        "Stypu\u0142ki Borki"
    ],
    "wof:name":"Stypulki Borki",
    "wof:placetype":"locality"
},
  "geometry": {"coordinates":[22.64315,53.0248],"type":"Point"}
}