{
  "type": "Feature",
  "properties": {
    "gn:admin1_code":"86.0",
    "gn:admin2_code":"3021.0",
    "gn:admin3_code":"302117.0",
    "gn:asciiname":"Rumianek",
    "gn:country_code":"PL",
    "gn:dem":90,
    "gn:feature_class":"P",
    "gn:feature_code":"PPL",
    "gn:name":"Rumianek",
    "gn:population":0,
    "gn:timezone":"Europe/Warsaw",
    "iso:country":"PL",
    "name:ceb_x_preferred":[
        "Rumianek"
    ],
    "name:fra_x_preferred":[
        "Rumianek"
    ],
    "name:pol_x_preferred":[
        "Rumianek"
    ],
    "name:ukr_x_preferred":[
        "\u0420\u0443\u043c\u044f\u043d\u0435\u043a"
    ],
    "wof:name":"Rumianek",
    "wof:placetype":"locality"
},
  "geometry": {"coordinates":[16.62043,52.4581],"type":"Point"}
}