{
  "type": "Feature",
  "properties": {
    "iso:country":"PL",
    "name:eng_x_preferred":[
        "Zielony Trojkat"
    ],
    "name:pol_x_preferred":[
        "Zielony Tr\u00f3jk\u0105t"
    ],
    "wof:name":"Zielony Trojkat",
    "wof:placetype":"neighbourhood"
},
  "geometry": {"coordinates":[18.63030758076197,54.37843922671372],"type":"Point"}
}