{
  "type": "Feature",
  "properties": {
    "gn:admin1_code":"78.0",
    "gn:admin2_code":"1403.0",
    "gn:admin3_code":"140312.0",
    "gn:asciiname":"Prandocin",
    "gn:country_code":"PL",
    "gn:dem":158,
    "gn:feature_class":"P",
    "gn:feature_code":"PPL",
    "gn:name":"Prandocin",
    "gn:population":0,
    "gn:timezone":"Europe/Warsaw",
    "iso:country":"PL",
    "name:azb_x_preferred":[
        "\u067e\u0631\u0627\u0646\u062f\u0648\u0686\u06cc\u0646"
    ],
    "name:fas_x_preferred":[
        "\u067e\u0631\u0627\u0646\u062f\u0648\u0686\u06cc\u0646"
    ],
    "name:fra_x_preferred":[
        "Prandocin"
    ],
    "name:pol_x_preferred":[
        "Prandocin"
    ],
    "name:ukr_x_preferred":[
        "\u041f\u0440\u0430\u043d\u0434\u043e\u0446\u0438\u043d"
    ],
    "wof:name":"Prandocin",
    "wof:placetype":"locality"
},
  "geometry": {"coordinates":[21.71595,51.69477],"type":"Point"}
}