{
  "type": "Feature",
  "properties": {
    "gn:admin1_code":"78.0",
    "gn:admin2_code":"1410.0",
    "gn:admin3_code":"141006.0",
    "gn:asciiname":"Kolonia Kielbaski",
    "gn:country_code":"PL",
    "gn:dem":159,
    "gn:feature_class":"P",
    "gn:feature_code":"PPL",
    "gn:name":"Kolonia Kie\u0142baski",
    "gn:population":0,
    "gn:timezone":"Europe/Warsaw",
    "iso:country":"PL",
    "name:und_x_variant":[
        "Kolonia Kie\u0142baski"
    ],
    "wof:name":"Kolonia Kielbaski",
    "wof:placetype":"locality"
},
  "geometry": {"coordinates":[22.92124,52.15449],"type":"Point"}
}