{
  "type": "Feature",
  "properties": {
    "gn:admin1_code":"78.0",
    "gn:admin2_code":"1410.0",
    "gn:admin3_code":"141006.0",
    "gn:asciiname":"Kolonia Kielbaski",
    "gn:country_code":"PL",
    "gn:dem":159,
    "gn:feature_class":"P",
    "gn:feature_code":"PPL",
    "gn:name":"Kolonia Kie\u0142baski",
    "gn:population":0,
    "gn:timezone":"Europe/Warsaw",
    "iso:country":"PL",
    "name:azb_x_preferred":[
        "\u06a9\u06cc\u0648\u0628\u0627\u0633\u06a9\u06cc"
    ],
    "name:fas_x_preferred":[
        "\u06a9\u06cc\u0648\u0628\u0627\u0633\u06a9\u06cc"
    ],
    "name:fra_x_preferred":[
        "Kie\u0142baski"
    ],
    "name:lit_x_preferred":[
        "Kelbaskai"
    ],
    "name:pol_x_preferred":[
        "Kie\u0142baski"
    ],
    "name:ukr_x_preferred":[
        "\u041a\u0435\u043b\u0431\u0430\u0441\u043a\u0456"
    ],
    "name:und_x_variant":[
        "Kolonia Kie\u0142baski"
    ],
    "wof:name":"Kolonia Kielbaski",
    "wof:placetype":"locality"
},
  "geometry": {"coordinates":[22.92124,52.15449],"type":"Point"}
}