{
  "type": "Feature",
  "properties": {
    "gn:admin1_code":"77.0",
    "gn:admin2_code":"1202.0",
    "gn:admin3_code":"120205.0",
    "gn:asciiname":"Gnojnik",
    "gn:country_code":"PL",
    "gn:dem":243,
    "gn:feature_class":"P",
    "gn:feature_code":"PPLA3",
    "gn:name":"Gnojnik",
    "gn:population":2344,
    "gn:timezone":"Europe/Warsaw",
    "iso:country":"PL",
    "name:ceb_x_preferred":[
        "Gnojnik"
    ],
    "name:deu_x_preferred":[
        "Gnojnik"
    ],
    "name:nld_x_preferred":[
        "Gnojnik"
    ],
    "name:pol_x_preferred":[
        "Gnojnik"
    ],
    "name:ukr_x_preferred":[
        "\u0490\u043d\u043e\u0439\u043d\u0438\u043a"
    ],
    "wof:coterminous":[
        1477752267
    ],
    "wof:name":"Gnojnik",
    "wof:placetype":"locality",
    "wof:population":2344
},
  "geometry": {"coordinates":[20.60863,49.89397],"type":"Point"}
}