{
  "type": "Feature",
  "properties": {
    "gn:admin1_code":"73.0",
    "gn:admin2_code":"417.0",
    "gn:admin3_code":"41705.0",
    "gn:asciiname":"Wronie",
    "gn:country_code":"PL",
    "gn:dem":102,
    "gn:feature_class":"P",
    "gn:feature_code":"PPL",
    "gn:name":"Wronie",
    "gn:population":0,
    "gn:timezone":"Europe/Warsaw",
    "iso:country":"PL",
    "name:ceb_x_preferred":[
        "Wronie"
    ],
    "name:pol_x_preferred":[
        "Wronie"
    ],
    "name:ukr_x_preferred":[
        "\u0412\u0440\u043e\u043d\u0435"
    ],
    "wof:name":"Wronie",
    "wof:placetype":"locality"
},
  "geometry": {"coordinates":[18.88573,53.30273],"type":"Point"}
}