{
  "type": "Feature",
  "properties": {
    "gn:admin1_code":"79.0",
    "gn:admin2_code":"1611.0",
    "gn:admin3_code":"161104.0",
    "gn:asciiname":"Kadlubiec",
    "gn:country_code":"PL",
    "gn:dem":299,
    "gn:feature_class":"P",
    "gn:feature_code":"PPL",
    "gn:name":"Kad\u0142ubiec",
    "gn:population":0,
    "gn:timezone":"Europe/Warsaw",
    "iso:country":"PL",
    "name:azb_x_preferred":[
        "\u06a9\u0627\u062f\u0648\u0648\u0628\u06cc\u062a\u0633"
    ],
    "name:bul_x_preferred":[
        "\u041a\u0430\u0434\u043b\u0443\u0431\u0435\u0446"
    ],
    "name:deu_x_preferred":[
        "Kadlubietz"
    ],
    "name:fas_x_preferred":[
        "\u06a9\u0627\u062f\u0648\u0648\u0628\u06cc\u062a\u0633"
    ],
    "name:nld_x_preferred":[
        "Kad\u0142ubiec"
    ],
    "name:pol_x_preferred":[
        "Kad\u0142ubiec"
    ],
    "name:ukr_x_preferred":[
        "\u041a\u0430\u0434\u043b\u0443\u0431\u0435\u0446\u044c"
    ],
    "wof:name":"Kadlubiec",
    "wof:placetype":"locality"
},
  "geometry": {"coordinates":[18.18872,50.47193],"type":"Point"}
}