{
  "type": "Feature",
  "properties": {
    "gn:admin1_code":"78.0",
    "gn:admin2_code":"1414.0",
    "gn:admin3_code":"141404.0",
    "gn:asciiname":"Nuna",
    "gn:country_code":"PL",
    "gn:dem":105,
    "gn:feature_class":"P",
    "gn:feature_code":"PPL",
    "gn:name":"Nuna",
    "gn:population":0,
    "gn:timezone":"Europe/Warsaw",
    "iso:country":"PL",
    "name:fra_x_preferred":[
        "Nuna"
    ],
    "name:ind_x_preferred":[
        "Nuna"
    ],
    "name:mkd_x_preferred":[
        "\u041d\u0443\u043d\u0430"
    ],
    "name:pol_x_preferred":[
        "Nuna"
    ],
    "name:ukr_x_preferred":[
        "\u041d\u0443\u043d\u0430"
    ],
    "wof:name":"Nuna",
    "wof:placetype":"locality"
},
  "geometry": {"coordinates":[20.84176,52.53415],"type":"Point"}
}