{
  "type": "Feature",
  "properties": {
    "gn:admin1_code":"74.0",
    "gn:admin2_code":"1015.0",
    "gn:admin3_code":"101506.0",
    "gn:asciiname":"Zagaj",
    "gn:country_code":"PL",
    "gn:dem":124,
    "gn:feature_class":"P",
    "gn:feature_code":"PPL",
    "gn:name":"Zagaj",
    "gn:population":0,
    "gn:timezone":"Europe/Warsaw",
    "iso:country":"PL",
    "name:bos_x_preferred":[
        "Zagaj"
    ],
    "name:fra_x_preferred":[
        "Zagaj"
    ],
    "name:pol_x_preferred":[
        "Zagaj"
    ],
    "name:slv_x_preferred":[
        "Zagaj"
    ],
    "name:ukr_x_preferred":[
        "\u0417\u0430\u0491\u0430\u0439"
    ],
    "wof:name":"Zagaj",
    "wof:placetype":"locality"
},
  "geometry": {"coordinates":[20.03128,51.96133],"type":"Point"}
}