{
  "type": "Feature",
  "properties": {
    "gn:admin1_code":"76.0",
    "gn:admin2_code":"808.0",
    "gn:admin3_code":"80802.0",
    "gn:asciiname":"Sieniawa",
    "gn:country_code":"PL",
    "gn:dem":134,
    "gn:feature_class":"P",
    "gn:feature_code":"PPL",
    "gn:name":"Sieniawa",
    "gn:population":1100,
    "gn:timezone":"Europe/Warsaw",
    "iso:country":"PL",
    "name:deu_x_historical":[
        "Sch\u00f6now"
    ],
    "name:deu_x_preferred":[
        "Sch\u00f6now"
    ],
    "wof:name":"Sieniawa",
    "wof:placetype":"locality",
    "wof:population":1100
},
  "geometry": {"coordinates":[15.37768,52.36344],"type":"Point"}
}