{
  "type": "Feature",
  "properties": {
    "gn:admin1_code":"83.0",
    "gn:admin2_code":"2416.0",
    "gn:admin3_code":"241608.0",
    "gn:asciiname":"Chalupki",
    "gn:country_code":"PL",
    "gn:dem":260,
    "gn:feature_class":"P",
    "gn:feature_code":"PPL",
    "gn:name":"Cha\u0142upki",
    "gn:population":0,
    "gn:timezone":"Europe/Warsaw",
    "iso:country":"PL",
    "wof:name":"Chalupki",
    "wof:placetype":"locality"
},
  "geometry": {"coordinates":[19.86405,50.6223],"type":"Point"}
}