{
  "type": "Feature",
  "properties": {
    "gn:admin1_code":"86.0",
    "gn:admin2_code":"3007.0",
    "gn:admin3_code":"300703.0",
    "gn:asciiname":"Swidle",
    "gn:country_code":"PL",
    "gn:dem":135,
    "gn:feature_class":"P",
    "gn:feature_code":"PPL",
    "gn:name":"\u015awidle",
    "gn:population":0,
    "gn:timezone":"Europe/Warsaw",
    "iso:country":"PL",
    "name:pol_x_preferred":[
        "\u015awidle"
    ],
    "wof:name":"Swidle",
    "wof:placetype":"locality"
},
  "geometry": {"coordinates":[18.40287,51.89339],"type":"Point"}
}