{
  "type": "Feature",
  "properties": {
    "gn:admin1_code":"73.0",
    "gn:admin2_code":"404.0",
    "gn:admin3_code":"40406.0",
    "gn:asciiname":"Gorzuchowo",
    "gn:country_code":"PL",
    "gn:dem":88,
    "gn:feature_class":"P",
    "gn:feature_code":"PPL",
    "gn:name":"Gorzuchowo",
    "gn:population":0,
    "gn:timezone":"Europe/Warsaw",
    "iso:country":"PL",
    "wof:name":"Gorzuchowo",
    "wof:placetype":"locality"
},
  "geometry": {"coordinates":[18.68854,53.35514000000001],"type":"Point"}
}