{
  "type": "Feature",
  "properties": {
    "gn:admin1_code":"87.0",
    "gn:admin2_code":"3203.0",
    "gn:admin3_code":"320305.0",
    "gn:asciiname":"Zabinek",
    "gn:country_code":"PL",
    "gn:dem":148,
    "gn:feature_class":"P",
    "gn:feature_code":"PPL",
    "gn:name":"\u017babinek",
    "gn:population":0,
    "gn:timezone":"Europe/Warsaw",
    "iso:country":"PL",
    "name:ceb_x_preferred":[
        "\u017babinek"
    ],
    "name:pol_x_preferred":[
        "\u017babinek"
    ],
    "name:ukr_x_preferred":[
        "\u0416\u0430\u0431\u0456\u043d\u0435\u043a"
    ],
    "name:und_x_variant":[
        "Klein Sabin"
    ],
    "name:urd_x_preferred":[
        "\u0632\u0627\u0628\u06cc\u0646\u06a9"
    ],
    "name:vie_x_preferred":[
        "\u017babinek"
    ],
    "wof:name":"Zabinek",
    "wof:placetype":"locality"
},
  "geometry": {"coordinates":[16.07436,53.43991],"type":"Point"}
}