{
  "type": "Feature",
  "properties": {
    "gn:admin1_code":"87.0",
    "gn:admin2_code":"3203.0",
    "gn:admin3_code":"320305.0",
    "gn:asciiname":"Zabinek",
    "gn:country_code":"PL",
    "gn:dem":148,
    "gn:feature_class":"P",
    "gn:feature_code":"PPL",
    "gn:name":"\u017babinek",
    "gn:population":0,
    "gn:timezone":"Europe/Warsaw",
    "iso:country":"PL",
    "name:und_x_variant":[
        "Klein Sabin",
        "\u017babinek"
    ],
    "wof:name":"Zabinek",
    "wof:placetype":"locality"
},
  "geometry": {"coordinates":[16.07436,53.43991],"type":"Point"}
}