{
  "type": "Feature",
  "properties": {
    "gn:admin1_code":"72.0",
    "gn:admin2_code":"205.0",
    "gn:admin3_code":"20505.0",
    "gn:asciiname":"Nowa Wies Wielka",
    "gn:country_code":"PL",
    "gn:dem":394,
    "gn:feature_class":"P",
    "gn:feature_code":"PPL",
    "gn:name":"Nowa Wie\u015b Wielka",
    "gn:population":198,
    "gn:timezone":"Europe/Warsaw",
    "iso:country":"PL",
    "wof:name":"Nowa Wies Wielka",
    "wof:placetype":"locality",
    "wof:population":198
},
  "geometry": {"coordinates":[16.04476,50.99037],"type":"Point"}
}