{
  "type": "Feature",
  "properties": {
    "gn:admin1_code":"87.0",
    "gn:admin2_code":"3209.0",
    "gn:admin3_code":"320906.0",
    "gn:asciiname":"Rzeczyca Mala",
    "gn:country_code":"PL",
    "gn:dem":99,
    "gn:feature_class":"P",
    "gn:feature_code":"PPL",
    "gn:name":"Rzeczyca Ma\u0142a",
    "gn:population":0,
    "gn:timezone":"Europe/Warsaw",
    "iso:country":"PL",
    "name:deu_x_preferred":[
        "Rzeczyca Ma\u0142a"
    ],
    "name:pol_x_preferred":[
        "Rzeczyca Ma\u0142a"
    ],
    "name:vie_x_preferred":[
        "Rzeczyca Ma\u0142a"
    ],
    "wof:name":"Rzeczyca Mala",
    "wof:placetype":"locality"
},
  "geometry": {"coordinates":[16.79186,54.11538],"type":"Point"}
}