{
  "type": "Feature",
  "properties": {
    "gn:admin1_code":"75.0",
    "gn:admin2_code":"618.0",
    "gn:admin3_code":"61803.0",
    "gn:asciiname":"Lubcze",
    "gn:country_code":"PL",
    "gn:dem":234,
    "gn:feature_class":"P",
    "gn:feature_code":"PPL",
    "gn:name":"\u0141ubcze",
    "gn:population":0,
    "gn:timezone":"Europe/Warsaw",
    "iso:country":"PL",
    "name:und_x_variant":[
        "\u0141ubcze"
    ],
    "wof:name":"Lubcze",
    "wof:placetype":"locality"
},
  "geometry": {"coordinates":[23.66057,50.45174],"type":"Point"}
}