{
  "type": "Feature",
  "properties": {
    "gn:admin1_code":"84.0",
    "gn:admin2_code":"2607.0",
    "gn:admin3_code":"260704.0",
    "gn:asciiname":"Stoki Male",
    "gn:country_code":"PL",
    "gn:dem":165,
    "gn:feature_class":"P",
    "gn:feature_code":"PPL",
    "gn:name":"Stoki Ma\u0142e",
    "gn:population":0,
    "gn:timezone":"Europe/Warsaw",
    "iso:country":"PL",
    "name:pol_x_preferred":[
        "Stoki Ma\u0142e"
    ],
    "name:ukr_x_preferred":[
        "\u0421\u0442\u043e\u043a\u0456-\u041c\u0430\u043b\u0456"
    ],
    "wof:name":"Stoki Male",
    "wof:placetype":"locality"
},
  "geometry": {"coordinates":[21.54914,50.96552],"type":"Point"}
}