{
  "type": "Feature",
  "properties": {
    "gn:gn_country":"PL",
    "gn:gn_fcode":"PPL",
    "gn:gn_pop":0,
    "iso:country":"PL",
    "name:csb_x_preferred":[
        "G\u00f2l\u00ebbi\u00e9"
    ],
    "name:eng_x_preferred":[
        "Go\u0142ubie"
    ],
    "name:fas_x_preferred":[
        "\u06af\u0648\u0648\u0648\u0628\u06cc\u0647"
    ],
    "name:fra_x_preferred":[
        "Go\u0142ubie"
    ],
    "name:nan_x_preferred":[
        "Go\u0142ubie"
    ],
    "name:nld_x_preferred":[
        "Go\u0142ubie"
    ],
    "name:pol_x_preferred":[
        "Go\u0142ubie"
    ],
    "name:rus_x_preferred":[
        "\u0413\u043e\u043b\u0443\u0431\u0435"
    ],
    "qs_pg:aaroncc":"PL",
    "qs_pg:gn_country":"PL",
    "qs_pg:gn_fcode":"PPL",
    "qs_pg:gn_pop":0,
    "qs_pg:name":"Go\u0142ubie",
    "qs_pg:name_adm0":"Polska",
    "qs_pg:name_adm1":"Pomorskie",
    "qs_pg:photos":90,
    "qs_pg:photos_1k":18,
    "qs_pg:photos_9k":1,
    "qs_pg:photos_9r":3,
    "qs_pg:photos_all":90,
    "qs_pg:photos_sr":3,
    "qs_pg:pop_sr":0,
    "qs_pg:qs_pg_placetype":"locality",
    "qs_pg:qs_pg_placetype_gp":"Town",
    "qs_pg:woe_adm0":23424923,
    "woe:adm0_id":23424923,
    "woe:name_adm0":"Polska",
    "woe:name_adm1":"Pomorskie",
    "woe:placetype":"Town",
    "wof:name":"Go\u0142ubie",
    "wof:placetype":"locality"
},
  "geometry": {"coordinates":[18.04161,54.21334],"type":"Point"}
}