{
  "type": "Feature",
  "properties": {
    "gn:admin1_code":"80.0",
    "gn:admin2_code":"1803.0",
    "gn:admin3_code":"180306.0",
    "gn:asciiname":"Bielowy",
    "gn:country_code":"PL",
    "gn:dem":201,
    "gn:feature_class":"P",
    "gn:feature_code":"PPL",
    "gn:name":"Bielowy",
    "gn:population":0,
    "gn:timezone":"Europe/Warsaw",
    "iso:country":"PL",
    "name:pol_x_preferred":[
        "Bielowy"
    ],
    "name:szl_x_preferred":[
        "Bjelowy"
    ],
    "name:ukr_x_preferred":[
        "\u0411\u0435\u043b\u044c\u043e\u0432\u0438"
    ],
    "wof:name":"Bielowy",
    "wof:placetype":"locality"
},
  "geometry": {"coordinates":[21.32924,49.94209],"type":"Point"}
}