{
  "type": "Feature",
  "properties": {
    "gn:admin1_code":"80.0",
    "gn:admin2_code":"1812.0",
    "gn:admin3_code":"181201.0",
    "gn:asciiname":"Derylaki",
    "gn:country_code":"PL",
    "gn:dem":174,
    "gn:feature_class":"P",
    "gn:feature_code":"PPL",
    "gn:name":"Derylaki",
    "gn:population":0,
    "gn:timezone":"Europe/Warsaw",
    "iso:country":"PL",
    "wof:name":"Derylaki",
    "wof:placetype":"locality"
},
  "geometry": {"coordinates":[22.46824,50.48569000000001],"type":"Point"}
}