{
  "type": "Feature",
  "properties": {
    "gn:admin1_code":"83.0",
    "gn:admin2_code":"2404.0",
    "gn:admin3_code":"240403.0",
    "gn:asciiname":"Ponik",
    "gn:country_code":"PL",
    "gn:dem":271,
    "gn:feature_class":"P",
    "gn:feature_code":"PPL",
    "gn:name":"Ponik",
    "gn:population":0,
    "gn:timezone":"Europe/Warsaw",
    "iso:country":"PL",
    "name:ceb_x_preferred":[
        "Ponik"
    ],
    "name:pol_x_preferred":[
        "Ponik"
    ],
    "wof:name":"Ponik",
    "wof:placetype":"locality"
},
  "geometry": {"coordinates":[19.43902000000001,50.72407000000001],"type":"Point"}
}