{
  "type": "Feature",
  "properties": {
    "gn:admin1_code":"78.0",
    "gn:admin2_code":"1416.0",
    "gn:admin3_code":"141611.0",
    "gn:asciiname":"Kepiste Borowo",
    "gn:country_code":"PL",
    "gn:dem":110,
    "gn:feature_class":"P",
    "gn:feature_code":"PPL",
    "gn:name":"K\u0119piste Borowo",
    "gn:population":0,
    "gn:timezone":"Europe/Warsaw",
    "iso:country":"PL",
    "wof:name":"Kepiste Borowo",
    "wof:placetype":"locality"
},
  "geometry": {"coordinates":[22.11088,52.73471],"type":"Point"}
}