{
  "type": "Feature",
  "properties": {
    "gn:country":"PL",
    "gn:fcode":"PPL",
    "gn:population":0,
    "iso:country":"PL",
    "name:ast_x_preferred":[
        "Prace Du\u017ce"
    ],
    "name:ces_x_preferred":[
        "Prace Du\u017ce"
    ],
    "name:che_x_preferred":[
        "\u041f\u0440\u0430\u0446\u0435-\u0414\u0443\u0436\u0435"
    ],
    "name:eng_x_preferred":[
        "Prace Du\u017ce"
    ],
    "name:fra_x_preferred":[
        "Prace Du\u017ce"
    ],
    "name:nan_x_preferred":[
        "Prace Du\u017ce"
    ],
    "name:pol_x_preferred":[
        "Prace Du\u017ce"
    ],
    "name:spa_x_preferred":[
        "Prace Du\u017ce"
    ],
    "name:szl_x_preferred":[
        "Du\u017ce Prace"
    ],
    "name:tat_x_preferred":[
        "\u041f\u0440\u0430\u0446\u0435-\u0414\u0443\u0436\u0435"
    ],
    "name:ukr_x_preferred":[
        "\u041f\u0440\u0430\u0446\u0435-\u0414\u0443\u0436\u0435"
    ],
    "qs_pg:aaroncc":"PL",
    "qs_pg:gn_country":"PL",
    "qs_pg:gn_fcode":"PPL",
    "qs_pg:gn_pop":0,
    "qs_pg:name":"Prace Du\u017ce",
    "qs_pg:name_adm0":"Polska",
    "qs_pg:name_adm1":"Mazowieckie",
    "qs_pg:photos_9r":0,
    "qs_pg:photos_sr":0,
    "qs_pg:pop_sr":0,
    "qs_pg:qs_pg_placetype":"locality",
    "qs_pg:qs_pg_placetype_gp":"Town",
    "qs_pg:woe_adm0":23424923,
    "woe:adm0_id":23424923,
    "woe:name_adm0":"Polska",
    "woe:name_adm1":"Mazowieckie",
    "woe:placetype":"Town",
    "wof:name":"Prace Du\u017ce",
    "wof:placetype":"locality"
},
  "geometry": {"coordinates":[20.91848,51.97161],"type":"Point"}
}