{
  "type": "Feature",
  "properties": {
    "gn:admin1_code":"78.0",
    "gn:admin2_code":"1411.0",
    "gn:admin3_code":"141110.0",
    "gn:asciiname":"Przeradowo",
    "gn:country_code":"PL",
    "gn:dem":83,
    "gn:feature_class":"P",
    "gn:feature_code":"PPL",
    "gn:name":"Przeradowo",
    "gn:population":0,
    "gn:timezone":"Europe/Warsaw",
    "iso:country":"PL",
    "name:fra_x_preferred":[
        "Przeradowo"
    ],
    "name:pol_x_preferred":[
        "Przeradowo"
    ],
    "name:ukr_x_preferred":[
        "\u041f\u0448\u0435\u0440\u0430\u0434\u043e\u0432\u043e"
    ],
    "wof:name":"Przeradowo",
    "wof:placetype":"locality"
},
  "geometry": {"coordinates":[21.21037,52.78126],"type":"Point"}
}