{
  "type": "Feature",
  "properties": {
    "gn:admin1_code":"73.0",
    "gn:admin2_code":"418.0",
    "gn:admin3_code":"41813.0",
    "gn:asciiname":"Wasielewko",
    "gn:cc2":"PL",
    "gn:country_code":"PL",
    "gn:dem":83,
    "gn:feature_class":"P",
    "gn:feature_code":"PPL",
    "gn:name":"Wasielewko",
    "gn:population":0,
    "gn:timezone":"Europe/Warsaw",
    "iso:country":"PL",
    "name:pol_x_preferred":[
        "Wasielewko"
    ],
    "name:ukr_x_preferred":[
        "\u0412\u0430\u0441\u0435\u043b\u0435\u0432\u043a\u043e"
    ],
    "name:und_x_variant":[
        "Wasilewko"
    ],
    "wof:name":"Wasielewko",
    "wof:placetype":"locality"
},
  "geometry": {"coordinates":[18.96667,52.58333],"type":"Point"}
}