{
  "type": "Feature",
  "properties": {
    "gn:admin1_code":"72.0",
    "gn:admin2_code":"223.0",
    "gn:admin3_code":"22305.0",
    "gn:asciiname":"Pustkow Wilczkowski",
    "gn:country_code":"PL",
    "gn:dem":159,
    "gn:feature_class":"P",
    "gn:feature_code":"PPL",
    "gn:name":"Pustk\u00f3w Wilczkowski",
    "gn:population":0,
    "gn:timezone":"Europe/Warsaw",
    "iso:country":"PL",
    "name:pol_x_preferred":[
        "Pustk\u00f3w Wilczkowski"
    ],
    "name:ukr_x_preferred":[
        "\u041f\u0443\u0441\u0442\u043a\u0443\u0432-\u0412\u0456\u043b\u044c\u0447\u043a\u043e\u0432\u0441\u044c\u043a\u0438\u0439"
    ],
    "wof:name":"Pustkow Wilczkowski",
    "wof:placetype":"locality"
},
  "geometry": {"coordinates":[16.88032,50.90444],"type":"Point"}
}