{
  "type": "Feature",
  "properties": {
    "gn:admin1_code":"80.0",
    "gn:admin2_code":"1801.0",
    "gn:admin3_code":"180105.0",
    "gn:asciiname":"Dzwiniacz Gorny",
    "gn:country_code":"PL",
    "gn:dem":651,
    "gn:feature_class":"P",
    "gn:feature_code":"PPL",
    "gn:name":"D\u017awiniacz G\u00f3rny",
    "gn:population":0,
    "gn:timezone":"Europe/Warsaw",
    "iso:country":"PL",
    "name:azb_x_preferred":[
        "\u0686\u0648\u06cc\u0646\u0642\u0627\u0686 \u0642\u0648\u0631\u0646\u0647"
    ],
    "name:fas_x_preferred":[
        "\u0686\u0648\u06cc\u0646\u06af\u0627\u0686 \u06af\u0648\u0631\u0646\u0647"
    ],
    "name:hun_x_preferred":[
        "D\u017awiniacz G\u00f3rny"
    ],
    "name:nld_x_preferred":[
        "D\u017awiniacz G\u00f3rny"
    ],
    "name:pol_x_preferred":[
        "D\u017awiniacz G\u00f3rny"
    ],
    "name:rus_x_preferred":[
        "\u0414\u0437\u0432\u0438\u043d\u044f\u0447 \u0413\u043e\u0440\u0438\u0448\u043d\u044b\u0439"
    ],
    "name:ukr_x_preferred":[
        "\u0414\u0437\u0432\u0438\u043d\u044f\u0447 \u0413\u043e\u0440\u0456\u0448\u043d\u0456\u0439"
    ],
    "name:und_x_variant":[
        "D\u017awiniacz"
    ],
    "wof:name":"Dzwiniacz Gorny",
    "wof:placetype":"locality"
},
  "geometry": {"coordinates":[22.78713,49.15164],"type":"Point"}
}