{
  "type": "Feature",
  "properties": {
    "gn:admin1_code":"80.0",
    "gn:admin2_code":"1801.0",
    "gn:admin3_code":"180105.0",
    "gn:asciiname":"Dzwiniacz Gorny",
    "gn:country_code":"PL",
    "gn:dem":651,
    "gn:feature_class":"P",
    "gn:feature_code":"PPL",
    "gn:name":"D\u017awiniacz G\u00f3rny",
    "gn:population":0,
    "gn:timezone":"Europe/Warsaw",
    "iso:country":"PL",
    "name:und_x_variant":[
        "D\u017awiniacz",
        "D\u017awiniacz G\u00f3rny"
    ],
    "wof:name":"Dzwiniacz Gorny",
    "wof:placetype":"locality"
},
  "geometry": {"coordinates":[22.78713,49.15164],"type":"Point"}
}