{
  "type": "Feature",
  "properties": {
    "gn:gn_country":"PL",
    "gn:gn_fcode":"PPL",
    "gn:gn_pop":380,
    "gn:population":380,
    "iso:country":"PL",
    "name:eng_x_preferred":[
        "Rusowo"
    ],
    "name:fre_x_preferred":[
        "Rusowo"
    ],
    "name:ger_x_preferred":[
        "Rusowo"
    ],
    "name:pol_x_preferred":[
        "Rusowo"
    ],
    "qs_pg:aaroncc":"PL",
    "qs_pg:gn_country":"PL",
    "qs_pg:gn_fcode":"PPL",
    "qs_pg:gn_pop":380,
    "qs_pg:name":"Rusowo",
    "qs_pg:name_adm0":"Polska",
    "qs_pg:name_adm1":"Zachodniopomorskie",
    "qs_pg:photos_9k":1,
    "qs_pg:photos_9r":1,
    "qs_pg:photos_all":2,
    "qs_pg:photos_sr":0,
    "qs_pg:pop_sr":2,
    "qs_pg:qs_pg_placetype":"locality",
    "qs_pg:qs_pg_placetype_gp":"Town",
    "qs_pg:woe_adm0":23424923,
    "woe:adm0_id":23424923,
    "woe:name_adm0":"Polska",
    "woe:name_adm1":"Zachodniopomorskie",
    "woe:placetype":"Town",
    "wof:name":"Rusowo",
    "wof:placetype":"locality",
    "wof:population":380
},
  "geometry": {"coordinates":[15.80898,54.16525],"type":"Point"}
}