{
  "type": "Feature",
  "properties": {
    "gn:admin1_code":"73.0",
    "gn:admin2_code":"411.0",
    "gn:admin3_code":"41105.0",
    "gn:asciiname":"Swiatniki",
    "gn:country_code":"PL",
    "gn:dem":97,
    "gn:feature_class":"P",
    "gn:feature_code":"PPL",
    "gn:name":"\u015awi\u0105tniki",
    "gn:population":0,
    "gn:timezone":"Europe/Warsaw",
    "iso:country":"PL",
    "name:pol_x_preferred":[
        "\u015awi\u0105tniki"
    ],
    "name:ukr_x_preferred":[
        "\u0421\u044c\u0432\u0439\u043e\u043d\u0442\u043d\u0438\u043a\u0438"
    ],
    "wof:name":"Swiatniki",
    "wof:placetype":"locality"
},
  "geometry": {"coordinates":[18.51881,52.57973000000001],"type":"Point"}
}