{
  "type": "Feature",
  "properties": {
    "gn:admin1_code":"77.0",
    "gn:admin2_code":"1219.0",
    "gn:admin3_code":"121903.0",
    "gn:asciiname":"Brzezie",
    "gn:country_code":"PL",
    "gn:dem":268,
    "gn:feature_class":"P",
    "gn:feature_code":"PPL",
    "gn:name":"Brzezie",
    "gn:population":0,
    "gn:timezone":"Europe/Warsaw",
    "iso:country":"PL",
    "name:pol_x_preferred":[
        "Brzezie"
    ],
    "name:ukr_x_preferred":[
        "\u0411\u0436\u0435\u0437\u0435"
    ],
    "name:urd_x_preferred":[
        "\u0628\u0631\u0632\u0632\u0626\u06d2"
    ],
    "wof:name":"Brzezie",
    "wof:placetype":"locality"
},
  "geometry": {"coordinates":[20.22823,49.98854],"type":"Point"}
}