{
  "type": "Feature",
  "properties": {
    "gn:admin1_code":"78.0",
    "gn:admin2_code":"1420.0",
    "gn:admin3_code":"142004.0",
    "gn:asciiname":"Sielec",
    "gn:country_code":"PL",
    "gn:dem":91,
    "gn:feature_class":"P",
    "gn:feature_code":"PPL",
    "gn:name":"Sielec",
    "gn:population":0,
    "gn:timezone":"Europe/Warsaw",
    "iso:country":"PL",
    "name:fra_x_preferred":[
        "Sielec"
    ],
    "name:pol_x_preferred":[
        "Sielec"
    ],
    "name:ukr_x_preferred":[
        "\u0421\u0435\u043b\u0435\u0446\u044c"
    ],
    "wof:name":"Sielec",
    "wof:placetype":"locality"
},
  "geometry": {"coordinates":[20.34033,52.40263],"type":"Point"}
}