{
  "type": "Feature",
  "properties": {
    "gn:admin1_code":"83.0",
    "gn:admin2_code":"2404.0",
    "gn:admin3_code":"240409.0",
    "gn:asciiname":"Paulinow",
    "gn:country_code":"PL",
    "gn:dem":265,
    "gn:feature_class":"P",
    "gn:feature_code":"PPL",
    "gn:name":"Paulin\u00f3w",
    "gn:population":0,
    "gn:timezone":"Europe/Warsaw",
    "iso:country":"PL",
    "name:pol_x_preferred":[
        "Paulin\u00f3w"
    ],
    "name:ukr_x_preferred":[
        "\u041f\u0430\u0443\u043b\u0456\u043d\u0443\u0432"
    ],
    "wof:name":"Paulinow",
    "wof:placetype":"locality"
},
  "geometry": {"coordinates":[19.67737,50.67226],"type":"Point"}
}