{
  "type": "Feature",
  "properties": {
    "gn:admin1_code":"83.0",
    "gn:admin2_code":"2468.0",
    "gn:admin3_code":"246801.0",
    "gn:asciiname":"Okragle",
    "gn:country_code":"PL",
    "gn:dem":254,
    "gn:feature_class":"P",
    "gn:feature_code":"PPL",
    "gn:name":"Okr\u0105g\u0142e",
    "gn:population":0,
    "gn:timezone":"Europe/Warsaw",
    "iso:country":"PL",
    "wof:name":"Okragle",
    "wof:placetype":"neighbourhood"
},
  "geometry": {"coordinates":[19.27482,50.15839],"type":"Point"}
}