{
  "type": "Feature",
  "properties": {
    "iso:country":"PL",
    "name:eng_x_preferred":[
        "Ostrow Tumski"
    ],
    "name:pol_x_preferred":[
        "Ostrow Tumski"
    ],
    "wof:name":"Ostrow Tumski",
    "wof:placetype":"neighbourhood"
},
  "geometry": {"coordinates":[16.94807667736111,52.41107511603106],"type":"Point"}
}