{
  "type": "Feature",
  "properties": {
    "gn:admin1_code":"85.0",
    "gn:admin2_code":"2804.0",
    "gn:admin3_code":"280404.0",
    "gn:asciiname":"Brudzedy Wielkie",
    "gn:cc2":"PL",
    "gn:country_code":"PL",
    "gn:dem":-1,
    "gn:feature_class":"P",
    "gn:feature_code":"PPL",
    "gn:name":"Brudz\u0119dy Wielkie",
    "gn:population":0,
    "gn:timezone":"Europe/Warsaw",
    "iso:country":"PL",
    "name:und_x_variant":[
        "Gross Brodsende",
        "Brudz\u0119dzy Wielkie",
        "Brudz\u0119dy Wielkie"
    ],
    "wof:name":"Brudzedy Wielkie",
    "wof:placetype":"locality"
},
  "geometry": {"coordinates":[19.38606,54.00706],"type":"Point"}
}