{
  "type": "Feature",
  "properties": {
    "gn:admin1_code":"78.0",
    "gn:admin2_code":"1424.0",
    "gn:admin3_code":"142407.0",
    "gn:asciiname":"Debiny",
    "gn:country_code":"PL",
    "gn:dem":107,
    "gn:feature_class":"P",
    "gn:feature_code":"PPL",
    "gn:name":"D\u0119biny",
    "gn:population":0,
    "gn:timezone":"Europe/Warsaw",
    "iso:country":"PL",
    "name:fra_x_preferred":[
        "D\u0119biny"
    ],
    "name:pol_x_preferred":[
        "D\u0119biny"
    ],
    "name:ukr_x_preferred":[
        "\u0414\u0435\u043c\u0431\u0456\u043d\u0438"
    ],
    "wof:name":"Debiny",
    "wof:placetype":"locality"
},
  "geometry": {"coordinates":[21.24043,52.59627],"type":"Point"}
}