{
  "type": "Feature",
  "properties": {
    "gn:admin1_code":"86.0",
    "gn:admin2_code":"3002.0",
    "gn:admin3_code":"300206.0",
    "gn:asciiname":"Krosin",
    "gn:country_code":"PL",
    "gn:dem":74,
    "gn:feature_class":"P",
    "gn:feature_code":"PPL",
    "gn:name":"Krosin",
    "gn:population":0,
    "gn:timezone":"Europe/Warsaw",
    "iso:country":"PL",
    "name:fra_x_preferred":[
        "Krosin"
    ],
    "name:pol_x_preferred":[
        "Krosin"
    ],
    "name:ukr_x_preferred":[
        "\u041a\u0440\u043e\u0441\u0456\u043d"
    ],
    "wof:name":"Krosin",
    "wof:placetype":"locality"
},
  "geometry": {"coordinates":[16.67067,52.79229],"type":"Point"}
}