{
  "type": "Feature",
  "properties": {
    "gn:admin1_code":"83.0",
    "gn:admin2_code":"2404.0",
    "gn:admin3_code":"240409.0",
    "gn:asciiname":"Zbyczyce",
    "gn:country_code":"PL",
    "gn:dem":259,
    "gn:feature_class":"P",
    "gn:feature_code":"PPL",
    "gn:name":"Zbyczyce",
    "gn:population":0,
    "gn:timezone":"Europe/Warsaw",
    "iso:country":"PL",
    "wof:name":"Zbyczyce",
    "wof:placetype":"locality"
},
  "geometry": {"coordinates":[19.62287,50.68798],"type":"Point"}
}