{
  "type": "Feature",
  "properties": {
    "gn:admin1_code":"85.0",
    "gn:admin2_code":"2817.0",
    "gn:admin3_code":"281707.0",
    "gn:asciiname":"Jerominy",
    "gn:country_code":"PL",
    "gn:dem":139,
    "gn:feature_class":"P",
    "gn:feature_code":"PPL",
    "gn:name":"Jerominy",
    "gn:population":0,
    "gn:timezone":"Europe/Warsaw",
    "iso:country":"PL",
    "name:pol_x_preferred":[
        "Jerominy"
    ],
    "name:ukr_x_preferred":[
        "\u0404\u0440\u043e\u043c\u0456\u043d\u0438"
    ],
    "name:und_x_variant":[
        "Jeromin"
    ],
    "wof:name":"Jerominy",
    "wof:placetype":"locality"
},
  "geometry": {"coordinates":[21.18622,53.52439],"type":"Point"}
}