{
  "type": "Feature",
  "properties": {
    "gn:admin1_code":"72.0",
    "gn:admin2_code":"220.0",
    "gn:admin3_code":"22003.0",
    "gn:asciiname":"Kobylice",
    "gn:country_code":"PL",
    "gn:dem":134,
    "gn:feature_class":"P",
    "gn:feature_code":"PPL",
    "gn:name":"Kobylice",
    "gn:population":0,
    "gn:timezone":"Europe/Warsaw",
    "iso:country":"PL",
    "name:pol_x_preferred":[
        "Kobylice"
    ],
    "name:ukr_x_preferred":[
        "\u041a\u043e\u0431\u0438\u043b\u0456\u0446\u0435"
    ],
    "wof:name":"Kobylice",
    "wof:placetype":"locality"
},
  "geometry": {"coordinates":[17.08964,51.33964],"type":"Point"}
}