{
  "type": "Feature",
  "properties": {
    "gn:admin1_code":"87.0",
    "gn:admin2_code":"3207.0",
    "gn:admin3_code":"320703.0",
    "gn:asciiname":"Rozwarowo",
    "gn:country_code":"PL",
    "gn:dem":2,
    "gn:feature_class":"P",
    "gn:feature_code":"PPL",
    "gn:name":"Rozwarowo",
    "gn:population":0,
    "gn:timezone":"Europe/Warsaw",
    "iso:country":"PL",
    "name:pol_x_preferred":[
        "Rozwarowo"
    ],
    "name:ukr_x_preferred":[
        "\u0420\u043e\u0437\u0432\u0430\u0440\u043e\u0432\u043e"
    ],
    "name:vie_x_preferred":[
        "Rozwarowo"
    ],
    "wof:name":"Rozwarowo",
    "wof:placetype":"locality"
},
  "geometry": {"coordinates":[14.72947,53.89516],"type":"Point"}
}