{
  "type": "Feature",
  "properties": {
    "gn:country":"PL",
    "gn:fcode":"PPL",
    "gn:population":1194,
    "iso:country":"PL",
    "name:azb_x_preferred":[
        "\u0633\u0627\u0631\u0646\u0627\u06a9\u06cc"
    ],
    "name:ceb_x_preferred":[
        "Sarnaki"
    ],
    "name:deu_x_preferred":[
        "Sarnaki"
    ],
    "name:eng_x_preferred":[
        "Sarnaki"
    ],
    "name:eng_x_variant":[
        "Gmina Sarnaki"
    ],
    "name:fas_x_preferred":[
        "\u0633\u0627\u0631\u0646\u0627\u06a9\u06cc"
    ],
    "name:fra_x_preferred":[
        "Sarnaki"
    ],
    "name:heb_x_preferred":[
        "\u05e1\u05e8\u05e0\u05d0\u05e7\u05d9"
    ],
    "name:lit_x_preferred":[
        "Sarnak\u0173 vals\u010dius"
    ],
    "name:lit_x_variant":[
        "Sarnakai"
    ],
    "name:nld_x_preferred":[
        "Sarnaki"
    ],
    "name:pol_x_preferred":[
        "Sarnaki"
    ],
    "name:por_x_preferred":[
        "Comuna de Sarnaki"
    ],
    "name:rus_x_preferred":[
        "\u0421\u0430\u0440\u043d\u0430\u043a\u0438"
    ],
    "name:slk_x_preferred":[
        "Gmina Sarnaki"
    ],
    "name:ukr_x_preferred":[
        "\u0490\u043c\u0456\u043d\u0430 \u0421\u0430\u0440\u043d\u0430\u043a\u0456"
    ],
    "name:ukr_x_variant":[
        "\u0421\u0430\u0440\u043d\u0430\u043a\u0456"
    ],
    "name:war_x_preferred":[
        "Gmina Sarnaki"
    ],
    "qs_pg:aaroncc":"PL",
    "qs_pg:gn_country":"PL",
    "qs_pg:gn_fcode":"PPL",
    "qs_pg:gn_pop":1194,
    "qs_pg:name":"Sarnaki",
    "qs_pg:name_adm0":"Polska",
    "qs_pg:name_adm1":"Mazowieckie",
    "qs_pg:photos_9k":1,
    "qs_pg:photos_9r":1,
    "qs_pg:photos_all":3,
    "qs_pg:photos_sr":0,
    "qs_pg:pop_sr":3,
    "qs_pg:qs_pg_placetype":"locality",
    "qs_pg:qs_pg_placetype_gp":"Town",
    "qs_pg:woe_adm0":23424923,
    "woe:adm0_id":23424923,
    "woe:name_adm0":"Polska",
    "woe:name_adm1":"Mazowieckie",
    "woe:placetype":"Town",
    "wof:name":"Sarnaki",
    "wof:placetype":"locality",
    "wof:population":1194
},
  "geometry": {"coordinates":[22.89044,52.31504],"type":"Point"}
}