{
  "type": "Feature",
  "properties": {
    "gn:admin1_code":"87.0",
    "gn:admin2_code":"3217.0",
    "gn:admin3_code":"321704.0",
    "gn:asciiname":"Rusinowo",
    "gn:country_code":"PL",
    "gn:dem":119,
    "gn:feature_class":"P",
    "gn:feature_code":"PPL",
    "gn:name":"Rusinowo",
    "gn:population":0,
    "gn:timezone":"Europe/Warsaw",
    "iso:country":"PL",
    "name:und_x_variant":[
        "Ruschendorf",
        "Ruszona",
        "Rusinowo"
    ],
    "wof:name":"Rusinowo",
    "wof:placetype":"locality"
},
  "geometry": {"coordinates":[16.2543,53.16183],"type":"Point"}
}