{
  "type": "Feature",
  "properties": {
    "gn:admin1_code":"87.0",
    "gn:admin2_code":"3217.0",
    "gn:admin3_code":"321704.0",
    "gn:asciiname":"Rusinowo",
    "gn:country_code":"PL",
    "gn:dem":119,
    "gn:feature_class":"P",
    "gn:feature_code":"PPL",
    "gn:name":"Rusinowo",
    "gn:population":0,
    "gn:timezone":"Europe/Warsaw",
    "iso:country":"PL",
    "name:ceb_x_preferred":[
        "Rusinowo"
    ],
    "name:deu_x_preferred":[
        "Rusinowo"
    ],
    "name:fra_x_preferred":[
        "Rusinowo"
    ],
    "name:pol_x_preferred":[
        "Rusinowo"
    ],
    "name:rus_x_preferred":[
        "\u0420\u0443\u0441\u0438\u043d\u043e\u0432\u043e"
    ],
    "name:ukr_x_preferred":[
        "\u0420\u0443\u0441\u0456\u043d\u043e\u0432\u043e"
    ],
    "name:und_x_variant":[
        "Ruschendorf",
        "Ruszona"
    ],
    "wof:name":"Rusinowo",
    "wof:placetype":"locality"
},
  "geometry": {"coordinates":[16.2543,53.16183],"type":"Point"}
}