{
  "type": "Feature",
  "properties": {
    "gn:admin1_code":"85.0",
    "gn:admin2_code":"2814.0",
    "gn:admin3_code":"281410.0",
    "gn:asciiname":"Kaletka",
    "gn:cc2":"PL",
    "gn:country_code":"PL",
    "gn:dem":163,
    "gn:feature_class":"P",
    "gn:feature_code":"PPL",
    "gn:name":"Kaletka",
    "gn:population":0,
    "gn:timezone":"Europe/Warsaw",
    "iso:country":"PL",
    "name:pol_x_preferred":[
        "Kaletka"
    ],
    "name:und_x_variant":[
        "Teerwalde-F\u00f6rsterei"
    ],
    "wof:name":"Kaletka",
    "wof:placetype":"locality"
},
  "geometry": {"coordinates":[20.55,53.61666999999999],"type":"Point"}
}