{
  "type": "Feature",
  "properties": {
    "gn:admin1_code":"75.0",
    "gn:admin2_code":"608.0",
    "gn:admin3_code":"60802.0",
    "gn:asciiname":"Ciotcza",
    "gn:country_code":"PL",
    "gn:dem":165,
    "gn:feature_class":"P",
    "gn:feature_code":"PPL",
    "gn:name":"Ciotcza",
    "gn:population":0,
    "gn:timezone":"Europe/Warsaw",
    "iso:country":"PL",
    "name:azb_x_preferred":[
        "\u0686\u06cc\u0648\u062a\u0686\u0627"
    ],
    "name:ceb_x_preferred":[
        "Ciotcza"
    ],
    "name:fas_x_preferred":[
        "\u0686\u06cc\u0648\u062a\u0686\u0627"
    ],
    "name:fra_x_preferred":[
        "Ciotcza"
    ],
    "name:nld_x_preferred":[
        "Ciotcza"
    ],
    "name:pol_x_preferred":[
        "Ciotcza"
    ],
    "name:ukr_x_preferred":[
        "\u0427\u044c\u043e\u0442\u0447\u0430"
    ],
    "wof:name":"Ciotcza",
    "wof:placetype":"locality"
},
  "geometry": {"coordinates":[22.32233,51.49261],"type":"Point"}
}