{
  "type": "Feature",
  "properties": {
    "gn:admin1_code":"75.0",
    "gn:admin2_code":"608.0",
    "gn:admin3_code":"60802.0",
    "gn:asciiname":"Ciotcza",
    "gn:country_code":"PL",
    "gn:dem":165,
    "gn:feature_class":"P",
    "gn:feature_code":"PPL",
    "gn:name":"Ciotcza",
    "gn:population":0,
    "gn:timezone":"Europe/Warsaw",
    "iso:country":"PL",
    "wof:name":"Ciotcza",
    "wof:placetype":"locality"
},
  "geometry": {"coordinates":[22.32233,51.49261],"type":"Point"}
}