{
  "type": "Feature",
  "properties": {
    "gn:admin1_code":"84.0",
    "gn:admin2_code":"2602.0",
    "gn:admin3_code":"260202.0",
    "gn:asciiname":"Chwascice",
    "gn:country_code":"PL",
    "gn:dem":214,
    "gn:feature_class":"P",
    "gn:feature_code":"PPL",
    "gn:name":"Chwa\u015bcice",
    "gn:population":0,
    "gn:timezone":"Europe/Warsaw",
    "iso:country":"PL",
    "name:azb_x_preferred":[
        "\u062e\u0648\u0627\u0634\u0686\u06cc\u062a\u0633\u0647"
    ],
    "name:ceb_x_preferred":[
        "Chwa\u015bcice"
    ],
    "name:fas_x_preferred":[
        "\u062e\u0648\u0627\u0634\u0686\u06cc\u062a\u0633\u0647"
    ],
    "name:nld_x_preferred":[
        "Chwa\u015bcice"
    ],
    "name:pol_x_preferred":[
        "Chwa\u015bcice"
    ],
    "name:ukr_x_preferred":[
        "\u0425\u0432\u0430\u0441\u0446\u0438\u0446\u0435"
    ],
    "wof:name":"Chwascice",
    "wof:placetype":"locality"
},
  "geometry": {"coordinates":[20.43098,50.64484],"type":"Point"}
}