{
  "type": "Feature",
  "properties": {
    "gn:gn_country":"PL",
    "gn:gn_fcode":"PPLA3",
    "gn:gn_pop":4893,
    "gn:population":4893,
    "iso:country":"PL",
    "name:heb_x_preferred":[
        "\u05dc\u05e1\u05e7\u05d6\u05d1"
    ],
    "name:lav_x_preferred":[
        "Laska\u017eeva"
    ],
    "name:rus_x_preferred":[
        "\u041b\u0430\u0441\u043a\u0430\u0436\u0435\u0432"
    ],
    "name:srp_x_preferred":[
        "\u041b\u0430\u0441\u043a\u0430\u0436\u0435\u0432"
    ],
    "name:ukr_x_preferred":[
        "\u041b\u0430\u0441\u043a\u0430\u0436\u0435\u0432"
    ],
    "name:zho_x_preferred":[
        "\u74e6\u65af\u5361\u71b1\u592b"
    ],
    "qs_pg:aaroncc":"PL",
    "qs_pg:gn_country":"PL",
    "qs_pg:gn_fcode":"PPLA3",
    "qs_pg:gn_pop":4893,
    "qs_pg:name":"\u0141askarzew",
    "qs_pg:name_adm0":"Polska",
    "qs_pg:name_adm1":"Mazowieckie",
    "qs_pg:photos":18,
    "qs_pg:photos_1k":4,
    "qs_pg:photos_9k":1,
    "qs_pg:photos_9r":2,
    "qs_pg:photos_all":29,
    "qs_pg:photos_sr":1,
    "qs_pg:pop_sr":4,
    "qs_pg:qs_pg_placetype":"localadmin",
    "qs_pg:qs_pg_placetype_gp":"LocalAdmin",
    "qs_pg:woe_adm0":23424923,
    "woe:adm0_id":23424923,
    "woe:name_adm0":"Polska",
    "woe:name_adm1":"Mazowieckie",
    "woe:placetype":"LocalAdmin",
    "wof:name":"\u0141askarzew",
    "wof:placetype":"localadmin",
    "wof:population":4893
},
  "geometry": {"coordinates":[21.59122,51.78993],"type":"Point"}
}