{
  "type": "Feature",
  "properties": {
    "gn:admin1_code":"81.0",
    "gn:admin2_code":"2008.0",
    "gn:admin3_code":"200807.0",
    "gn:asciiname":"Milewo",
    "gn:country_code":"PL",
    "gn:dem":145,
    "gn:feature_class":"P",
    "gn:feature_code":"PPL",
    "gn:name":"Milewo",
    "gn:population":0,
    "gn:timezone":"Europe/Warsaw",
    "iso:country":"PL",
    "name:lit_x_preferred":[
        "Milevas"
    ],
    "name:mkd_x_preferred":[
        "\u041c\u0438\u043b\u0435\u0432\u043e"
    ],
    "name:pol_x_preferred":[
        "Milewo"
    ],
    "name:ukr_x_preferred":[
        "\u041c\u0456\u043b\u0435\u0432\u043e"
    ],
    "wof:name":"Milewo",
    "wof:placetype":"locality"
},
  "geometry": {"coordinates":[22.70977,53.38056],"type":"Point"}
}