{
  "type": "Feature",
  "properties": {
    "gn:population":3500,
    "iso:country":"PL",
    "name:ast_x_preferred":[
        "Jemielnica"
    ],
    "name:azb_x_preferred":[
        "\u06cc\u0645\u06cc\u0644\u0646\u0642\u062a\u0633\u0627"
    ],
    "name:ceb_x_preferred":[
        "Jemielnica"
    ],
    "name:deu_x_preferred":[
        "Himmelwitz"
    ],
    "name:eng_x_preferred":[
        "Jemielnica"
    ],
    "name:fas_x_preferred":[
        "\u06cc\u0645\u06cc\u0644\u0646\u06af\u062a\u0633\u0627"
    ],
    "name:fra_x_preferred":[
        "Jemielnica"
    ],
    "name:nan_x_preferred":[
        "Jemielnica"
    ],
    "name:pol_x_preferred":[
        "Jemielnica"
    ],
    "name:szl_x_preferred":[
        "Jemielnica"
    ],
    "name:ukr_x_preferred":[
        "\u0404\u043c\u0435\u043b\u044c\u043d\u0438\u0446\u044f"
    ],
    "name:zho_min_nan_x_preferred":[
        "Jemielnica"
    ],
    "qs:a0":"Rzeczpospolita Polska",
    "qs:a1":"*Opolskie",
    "qs:a1r":"0",
    "qs:a2":"Strzelecki",
    "qs:adm0":"Rzeczpospolita Polska",
    "qs:la":"Jemielnica",
    "qs:la_lc":"*PL1611022",
    "qs:level":"locality",
    "qs:loc":"Jemielnica",
    "qs:loc_alt":"Jemielnica",
    "qs:pop":0,
    "qs:type":"rural point-in-poly",
    "wd:wordcount":112,
    "wof:coterminous":[
        1125383115
    ],
    "wof:name":"Jemielnica",
    "wof:placetype":"locality",
    "wof:population":3500
},
  "geometry": {"coordinates":[18.3935107789549,50.5744040376041],"type":"Point"}
}