{
  "type": "Feature",
  "properties": {
    "gn:admin1_code":"81.0",
    "gn:admin2_code":"2010.0",
    "gn:admin3_code":"201006.0",
    "gn:asciiname":"Kolonia Pokaniewo",
    "gn:country_code":"PL",
    "gn:dem":161,
    "gn:feature_class":"P",
    "gn:feature_code":"PPL",
    "gn:name":"Kolonia Pokaniewo",
    "gn:population":0,
    "gn:timezone":"Europe/Warsaw",
    "iso:country":"PL",
    "name:azb_x_preferred":[
        "\u067e\u0648\u06a9\u0627\u0646\u0642\u0648\u0648-\u06a9\u0648\u0644\u0648\u0646\u0642\u0627"
    ],
    "name:fas_x_preferred":[
        "\u067e\u0648\u06a9\u0627\u0646\u06af\u0648\u0648-\u06a9\u0648\u0644\u0648\u0646\u06af\u0627"
    ],
    "name:fra_x_preferred":[
        "Pokaniewo-Kolonia"
    ],
    "name:lit_x_preferred":[
        "Pokanevo Kolonija"
    ],
    "name:pol_x_preferred":[
        "Pokaniewo-Kolonia"
    ],
    "wof:name":"Kolonia Pokaniewo",
    "wof:placetype":"locality"
},
  "geometry": {"coordinates":[23.03759,52.51124],"type":"Point"}
}