{
  "type": "Feature",
  "properties": {
    "gn:admin1_code":"77.0",
    "gn:admin2_code":"1219.0",
    "gn:admin3_code":"121902.0",
    "gn:asciiname":"Podolany",
    "gn:country_code":"PL",
    "gn:dem":238,
    "gn:feature_class":"P",
    "gn:feature_code":"PPL",
    "gn:name":"Podolany",
    "gn:population":0,
    "gn:timezone":"Europe/Warsaw",
    "iso:country":"PL",
    "name:ceb_x_preferred":[
        "Podolany"
    ],
    "name:pol_x_preferred":[
        "Podolany"
    ],
    "name:ukr_x_preferred":[
        "\u041f\u043e\u0434\u043e\u043b\u044f\u043d\u0438"
    ],
    "wof:name":"Podolany",
    "wof:placetype":"locality"
},
  "geometry": {"coordinates":[20.23802,49.89497],"type":"Point"}
}