{
  "type": "Feature",
  "properties": {
    "gn:admin1_code":"73.0",
    "gn:admin2_code":"419.0",
    "gn:admin3_code":"41904.0",
    "gn:asciiname":"Ojrzanowo",
    "gn:country_code":"PL",
    "gn:dem":84,
    "gn:feature_class":"P",
    "gn:feature_code":"PPL",
    "gn:name":"Ojrzanowo",
    "gn:population":0,
    "gn:timezone":"Europe/Warsaw",
    "iso:country":"PL",
    "name:pol_x_preferred":[
        "Ojrzanowo"
    ],
    "name:ukr_x_preferred":[
        "\u041e\u0439\u0436\u0430\u043d\u043e\u0432\u043e"
    ],
    "wof:name":"Ojrzanowo",
    "wof:placetype":"locality"
},
  "geometry": {"coordinates":[17.95867,52.93308],"type":"Point"}
}