{
  "type": "Feature",
  "properties": {
    "gn:country":"PL",
    "gn:fcode":"PPLA3",
    "gn:population":32132,
    "iso:country":"PL",
    "name:azb_x_preferred":[
        "\u0698\u0648\u06cc\u062a\u0633"
    ],
    "name:bel_x_preferred":[
        "\u0416\u044b\u0432\u0435\u0446"
    ],
    "name:bul_x_preferred":[
        "\u0416\u0438\u0432\u0435\u0446"
    ],
    "name:cat_x_preferred":[
        "\u017bywiec"
    ],
    "name:ces_x_preferred":[
        "\u017bywiec"
    ],
    "name:deu_x_preferred":[
        "\u017bywiec"
    ],
    "name:eng_x_preferred":[
        "\u017bywiec"
    ],
    "name:epo_x_preferred":[
        "\u017bywiec"
    ],
    "name:est_x_preferred":[
        "\u017bywiec"
    ],
    "name:eus_x_preferred":[
        "\u017bywiec"
    ],
    "name:fas_x_preferred":[
        "\u0698\u0648\u06cc\u062a\u0633"
    ],
    "name:fra_x_preferred":[
        "\u017bywiec"
    ],
    "name:hun_x_preferred":[
        "\u017bywiec"
    ],
    "name:ita_x_preferred":[
        "\u017bywiec"
    ],
    "name:jav_x_preferred":[
        "\u017bywiec"
    ],
    "name:jpn_x_preferred":[
        "\u30b8\u30f4\u30a3\u30a8\u30c4"
    ],
    "name:kor_x_preferred":[
        "\uc9c0\ube44\uc5d0\uce20"
    ],
    "name:lav_x_preferred":[
        "\u017diveca"
    ],
    "name:lit_x_preferred":[
        "\u017dyvecas"
    ],
    "name:lmo_x_preferred":[
        "\u017bywiec"
    ],
    "name:msa_x_preferred":[
        "\u017bywiec"
    ],
    "name:nld_x_preferred":[
        "\u017bywiec"
    ],
    "name:pol_x_preferred":[
        "\u017bywiec"
    ],
    "name:por_x_preferred":[
        "\u017bywiec"
    ],
    "name:ron_x_preferred":[
        "\u017bywiec"
    ],
    "name:rus_x_preferred":[
        "\u0416\u0438\u0432\u0435\u0446"
    ],
    "name:slk_x_preferred":[
        "\u017bywiec"
    ],
    "name:spa_x_preferred":[
        "\u017bywiec"
    ],
    "name:srp_x_preferred":[
        "\u0416\u0438\u0432\u0458\u0435\u0446"
    ],
    "name:swe_x_preferred":[
        "\u017bywiec"
    ],
    "name:ukr_x_preferred":[
        "\u0416\u0438\u0432\u0435\u0446\u044c"
    ],
    "name:und_x_variant":[
        "Saybusch"
    ],
    "name:vie_x_preferred":[
        "\u017bywiec"
    ],
    "name:war_x_preferred":[
        "\u017bywiec"
    ],
    "name:zho_x_preferred":[
        "\u65e5\u7dad\u8328"
    ],
    "qs_pg:aaroncc":"PL",
    "qs_pg:gn_country":"PL",
    "qs_pg:gn_fcode":"PPLA3",
    "qs_pg:gn_pop":32132,
    "qs_pg:name":"\u017bywiec",
    "qs_pg:name_adm0":"Polska",
    "qs_pg:name_adm1":"Sl\u0105skie",
    "qs_pg:photos":14,
    "qs_pg:photos_1k":3,
    "qs_pg:photos_9k":1,
    "qs_pg:photos_9r":1,
    "qs_pg:photos_all":14,
    "qs_pg:photos_sr":1,
    "qs_pg:pop_sr":7,
    "qs_pg:qs_pg_placetype":"localadmin",
    "qs_pg:qs_pg_placetype_gp":"LocalAdmin",
    "qs_pg:woe_adm0":23424923,
    "woe:adm0_id":23424923,
    "woe:name_adm0":"Polska",
    "woe:name_adm1":"Sl\u0105skie",
    "woe:placetype":"LocalAdmin",
    "wof:name":"\u017bywiec",
    "wof:placetype":"localadmin",
    "wof:population":32132
},
  "geometry": {"coordinates":[19.19243,49.68529],"type":"Point"}
}