{
  "type": "Feature",
  "properties": {
    "gn:admin1_code":"78.0",
    "gn:admin2_code":"1407.0",
    "gn:admin3_code":"140706.0",
    "gn:asciiname":"Mniszew",
    "gn:country_code":"PL",
    "gn:dem":99,
    "gn:feature_class":"P",
    "gn:feature_code":"PPL",
    "gn:name":"Mniszew",
    "gn:population":0,
    "gn:timezone":"Europe/Warsaw",
    "iso:country":"PL",
    "name:ceb_x_preferred":[
        "Mniszew"
    ],
    "name:fra_x_preferred":[
        "Mniszew"
    ],
    "name:pol_x_preferred":[
        "Mniszew"
    ],
    "name:ukr_x_preferred":[
        "\u041c\u043d\u0456\u0448\u0435\u0432"
    ],
    "name:und_x_variant":[
        "Mnisz\u00f3w"
    ],
    "wof:name":"Mniszew",
    "wof:placetype":"locality"
},
  "geometry": {"coordinates":[21.28096,51.84621],"type":"Point"}
}