{
  "type": "Feature",
  "properties": {
    "gn:country":"PL",
    "gn:fcode":"PPL",
    "gn:population":1100,
    "iso:country":"PL",
    "name:ast_x_preferred":[
        "Ratowice"
    ],
    "name:ceb_x_preferred":[
        "Ratowice"
    ],
    "name:eng_x_preferred":[
        "Ratowice"
    ],
    "name:fra_x_preferred":[
        "Ratowice"
    ],
    "name:pol_x_preferred":[
        "Ratowice"
    ],
    "name:rus_x_preferred":[
        "\u0420\u0430\u0442\u043e\u0432\u0438\u0446\u0435"
    ],
    "name:ukr_x_preferred":[
        "\u0420\u0430\u0442\u043e\u0432\u0456\u0446\u0435"
    ],
    "name:und_x_variant":[
        "Ralowice"
    ],
    "qs_pg:aaroncc":"PL",
    "qs_pg:gn_country":"PL",
    "qs_pg:gn_fcode":"PPL",
    "qs_pg:gn_pop":1100,
    "qs_pg:name":"Ratowice",
    "qs_pg:name_adm0":"Polska",
    "qs_pg:name_adm1":"Dolnosl\u0105skie",
    "qs_pg:photos_9k":1,
    "qs_pg:photos_9r":1,
    "qs_pg:photos_all":1,
    "qs_pg:photos_sr":0,
    "qs_pg:pop_sr":3,
    "qs_pg:qs_pg_placetype":"locality",
    "qs_pg:qs_pg_placetype_gp":"Town",
    "qs_pg:woe_adm0":23424923,
    "woe:adm0_id":23424923,
    "woe:name_adm0":"Polska",
    "woe:name_adm1":"Dolnosl\u0105skie",
    "woe:placetype":"Town",
    "wof:name":"Ratowice",
    "wof:placetype":"locality",
    "wof:population":1100
},
  "geometry": {"coordinates":[17.27205,51.03308],"type":"Point"}
}