{
  "type": "Feature",
  "properties": {
    "gn:admin1_code":"78.0",
    "gn:admin2_code":"1427.0",
    "gn:admin3_code":"142703.0",
    "gn:asciiname":"Sniechy",
    "gn:country_code":"PL",
    "gn:dem":108,
    "gn:feature_class":"P",
    "gn:feature_code":"PPL",
    "gn:name":"\u015aniechy",
    "gn:population":0,
    "gn:timezone":"Europe/Warsaw",
    "iso:country":"PL",
    "name:fra_x_preferred":[
        "\u015aniechy"
    ],
    "name:pol_x_preferred":[
        "\u015aniechy"
    ],
    "name:ukr_x_preferred":[
        "\u0421\u044c\u043d\u0435\u0445\u0438"
    ],
    "wof:name":"Sniechy",
    "wof:placetype":"locality"
},
  "geometry": {"coordinates":[19.51859,52.83067],"type":"Point"}
}