{
  "type": "Feature",
  "properties": {
    "gn:admin1_code":"73.0",
    "gn:admin2_code":"411.0",
    "gn:admin3_code":"41105.0",
    "gn:asciiname":"Przewoz",
    "gn:country_code":"PL",
    "gn:dem":83,
    "gn:feature_class":"P",
    "gn:feature_code":"PPL",
    "gn:name":"Przew\u00f3z",
    "gn:population":0,
    "gn:timezone":"Europe/Warsaw",
    "iso:country":"PL",
    "name:pol_x_preferred":[
        "Przew\u00f3z"
    ],
    "name:ukr_x_preferred":[
        "\u041f\u0448\u0435\u0432\u0443\u0437"
    ],
    "wof:name":"Przewoz",
    "wof:placetype":"locality"
},
  "geometry": {"coordinates":[18.39008,52.47964],"type":"Point"}
}