{
  "type": "Feature",
  "properties": {
    "gn:admin1_code":"83.0",
    "gn:admin2_code":"2407.0",
    "gn:admin3_code":"240701.0",
    "gn:asciiname":"Steblow",
    "gn:country_code":"PL",
    "gn:dem":262,
    "gn:feature_class":"P",
    "gn:feature_code":"PPL",
    "gn:name":"Stebl\u00f3w",
    "gn:population":0,
    "gn:timezone":"Europe/Warsaw",
    "iso:country":"PL",
    "name:deu_x_historical":[
        "Steblau"
    ],
    "name:deu_x_preferred":[
        "Steblau"
    ],
    "name:und_x_variant":[
        "Stebl\u00f3w"
    ],
    "wof:name":"Steblow",
    "wof:placetype":"locality"
},
  "geometry": {"coordinates":[18.66897,50.68964],"type":"Point"}
}