{
  "type": "Feature",
  "properties": {
    "gn:admin1_code":"83.0",
    "gn:admin2_code":"2473.0",
    "gn:admin3_code":"247301.0",
    "gn:asciiname":"Grabownia",
    "gn:country_code":"PL",
    "gn:dem":225,
    "gn:feature_class":"P",
    "gn:feature_code":"PPL",
    "gn:name":"Grabownia",
    "gn:population":0,
    "gn:timezone":"Europe/Warsaw",
    "iso:country":"PL",
    "wof:name":"Grabownia",
    "wof:placetype":"locality"
},
  "geometry": {"coordinates":[18.53372,50.13571],"type":"Point"}
}