{
  "type": "Feature",
  "properties": {
    "gn:admin1_code":"83.0",
    "gn:admin2_code":"2404.0",
    "gn:admin3_code":"240405.0",
    "gn:asciiname":"Rzeki Wielkie",
    "gn:country_code":"PL",
    "gn:dem":225,
    "gn:feature_class":"P",
    "gn:feature_code":"PPL",
    "gn:name":"Rzeki Wielkie",
    "gn:population":0,
    "gn:timezone":"Europe/Warsaw",
    "iso:country":"PL",
    "name:und_x_variant":[
        "Rzeki",
        "Rzeki Wielkie"
    ],
    "wof:name":"Rzeki Wielkie",
    "wof:placetype":"locality"
},
  "geometry": {"coordinates":[19.38896,50.87656],"type":"Point"}
}