{
  "type": "Feature",
  "properties": {
    "gn:gn_country":"PL",
    "gn:gn_fcode":"ADM3",
    "gn:gn_pop":0,
    "iso:country":"PL",
    "name:ara_x_preferred":[
        "\u0628\u0648\u0632\u0646\u0627\u0646"
    ],
    "name:bel_x_preferred":[
        "\u0413\u043e\u0440\u0430\u0434 \u041f\u043e\u0437\u043d\u0430\u043d\u044c"
    ],
    "name:bod_x_preferred":[
        "\u0f55\u0fb0\u0f7c\u0f0b\u0f5f\u0f7c\u0f0b\u0f53\u0f53\u0f0d"
    ],
    "name:bos_x_preferred":[
        "Poznanj"
    ],
    "name:bul_x_preferred":[
        "\u041f\u043e\u0437\u043d\u0430\u043d"
    ],
    "name:ces_x_preferred":[
        "Pozna\u0148"
    ],
    "name:crh_x_preferred":[
        "P\u043eznan"
    ],
    "name:csb_x_preferred":[
        "P\u00f2zn\u00f3\u0144"
    ],
    "name:deu_x_preferred":[
        "Posen"
    ],
    "name:ell_x_preferred":[
        "\u03a0\u03cc\u03b6\u03bd\u03b1\u03bd"
    ],
    "name:eng_x_preferred":[
        "Pozna\u0144"
    ],
    "name:fas_x_preferred":[
        "\u067e\u0648\u0632\u0646\u0627\u0646"
    ],
    "name:fra_x_preferred":[
        "Pozna\u0144"
    ],
    "name:fry_x_preferred":[
        "Poznan"
    ],
    "name:hbs_x_preferred":[
        "Poznanj"
    ],
    "name:heb_x_preferred":[
        "\u05e4\u05d5\u05d6\u05e0\u05df"
    ],
    "name:hrv_x_preferred":[
        "Poznanj"
    ],
    "name:jpn_x_preferred":[
        "\u30dd\u30ba\u30ca\u30f3"
    ],
    "name:kat_x_preferred":[
        "\u10de\u10dd\u10d6\u10dc\u10d0\u10dc\u10d8"
    ],
    "name:kor_x_preferred":[
        "\ud3ec\uc988\ub09c"
    ],
    "name:lat_x_preferred":[
        "Posnania"
    ],
    "name:lav_x_preferred":[
        "Pozna\u0146a"
    ],
    "name:lit_x_preferred":[
        "Poznan\u0117"
    ],
    "name:mar_x_preferred":[
        "\u092a\u094b\u091d\u094d\u0928\u093e\u0928"
    ],
    "name:nds_x_preferred":[
        "Posen"
    ],
    "name:oss_x_preferred":[
        "\u041f\u043e\u0437\u043d\u0430\u043d\u044c"
    ],
    "name:pnb_x_preferred":[
        "\u067e\u0648\u0632\u0646\u0627\u0646"
    ],
    "name:pol_x_preferred":[
        "Pozna\u0144"
    ],
    "name:rus_x_preferred":[
        "\u041f\u043e\u0437\u043d\u0430\u043d\u044c"
    ],
    "name:slk_x_preferred":[
        "Pozna\u0148"
    ],
    "name:slv_x_preferred":[
        "Poznanj"
    ],
    "name:srp_x_preferred":[
        "\u041f\u043e\u0437\u043d\u0430\u045a"
    ],
    "name:szl_x_preferred":[
        "Pozna\u0144y"
    ],
    "name:uig_x_preferred":[
        "Poznan"
    ],
    "name:ukr_x_preferred":[
        "\u041f\u043e\u0437\u043d\u0430\u043d\u044c"
    ],
    "name:yid_x_preferred":[
        "\u05e4\u05d5\u05d9\u05d6\u05df"
    ],
    "name:zho_x_preferred":[
        "\u6ce2\u8332\u5357"
    ],
    "qs_pg:aaroncc":"PL",
    "qs_pg:gn_country":"PL",
    "qs_pg:gn_fcode":"ADM3",
    "qs_pg:gn_pop":0,
    "qs_pg:name":"Poznan",
    "qs_pg:name_adm0":"Polska",
    "qs_pg:name_adm1":"Wielkopolskie",
    "qs_pg:photos":8,
    "qs_pg:photos_1k":2,
    "qs_pg:photos_9k":64,
    "qs_pg:photos_9r":18,
    "qs_pg:photos_all":14510,
    "qs_pg:photos_sr":1,
    "qs_pg:pop_sr":0,
    "qs_pg:qs_pg_placetype":"localadmin",
    "qs_pg:qs_pg_placetype_gp":"LocalAdmin",
    "qs_pg:woe_adm0":23424923,
    "woe:adm0_id":23424923,
    "woe:name_adm0":"Polska",
    "woe:name_adm1":"Wielkopolskie",
    "woe:placetype":"LocalAdmin",
    "wof:name":"Poznan",
    "wof:placetype":"localadmin"
},
  "geometry": {"coordinates":[16.92341,52.40619],"type":"Point"}
}