{
  "type": "Feature",
  "properties": {
    "gn:admin1_code":"74.0",
    "gn:admin2_code":"1011.0",
    "gn:admin3_code":"101105.0",
    "gn:asciiname":"Kolonia Spedoszyn",
    "gn:country_code":"PL",
    "gn:dem":112,
    "gn:feature_class":"P",
    "gn:feature_code":"PPL",
    "gn:name":"Kolonia Sp\u0119doszyn",
    "gn:population":0,
    "gn:timezone":"Europe/Warsaw",
    "iso:country":"PL",
    "name:und_x_variant":[
        "Kolonia Sp\u0119doszyn"
    ],
    "wof:name":"Kolonia Spedoszyn",
    "wof:placetype":"locality"
},
  "geometry": {"coordinates":[18.97032,51.95293],"type":"Point"}
}