{
  "type": "Feature",
  "properties": {
    "gn:admin1_code":"74.0",
    "gn:admin2_code":"1011.0",
    "gn:admin3_code":"101105.0",
    "gn:asciiname":"Kolonia Spedoszyn",
    "gn:country_code":"PL",
    "gn:dem":112,
    "gn:feature_class":"P",
    "gn:feature_code":"PPL",
    "gn:name":"Kolonia Sp\u0119doszyn",
    "gn:population":0,
    "gn:timezone":"Europe/Warsaw",
    "iso:country":"PL",
    "name:fra_x_preferred":[
        "Sp\u0119doszyn-Kolonia"
    ],
    "name:pol_x_preferred":[
        "Sp\u0119doszyn-Kolonia"
    ],
    "name:ukr_x_preferred":[
        "\u0421\u043f\u0435\u043d\u0434\u043e\u0448\u0438\u043d-\u041a\u043e\u043b\u044c\u043e\u043d\u0456\u044f"
    ],
    "name:und_x_variant":[
        "Kolonia Sp\u0119doszyn"
    ],
    "wof:name":"Kolonia Spedoszyn",
    "wof:placetype":"locality"
},
  "geometry": {"coordinates":[18.97032,51.95293],"type":"Point"}
}