{
  "type": "Feature",
  "properties": {
    "gn:admin1_code":"86.0",
    "gn:admin2_code":"3010.0",
    "gn:admin3_code":"301012.0",
    "gn:asciiname":"Polwiosek Stary",
    "gn:country_code":"PL",
    "gn:dem":86,
    "gn:feature_class":"P",
    "gn:feature_code":"PPL",
    "gn:name":"P\u00f3\u0142wiosek Stary",
    "gn:population":0,
    "gn:timezone":"Europe/Warsaw",
    "iso:country":"PL",
    "name:ceb_x_preferred":[
        "P\u00f3\u0142wiosek Stary"
    ],
    "name:fra_x_preferred":[
        "P\u00f3\u0142wiosek Stary"
    ],
    "name:pol_x_preferred":[
        "P\u00f3\u0142wiosek Stary"
    ],
    "name:ukr_x_preferred":[
        "\u041f\u0443\u043b\u0432\u0439\u043e\u0441\u0435\u043a-\u0421\u0442\u0430\u0440\u0438\u0439"
    ],
    "wof:name":"Polwiosek Stary",
    "wof:placetype":"locality"
},
  "geometry": {"coordinates":[18.31034,52.35933],"type":"Point"}
}