{
  "type": "Feature",
  "properties": {
    "gn:admin1_code":"73.0",
    "gn:admin2_code":"404.0",
    "gn:admin3_code":"40406.0",
    "gn:asciiname":"Grubno",
    "gn:country_code":"PL",
    "gn:dem":81,
    "gn:feature_class":"P",
    "gn:feature_code":"PPL",
    "gn:name":"Grubno",
    "gn:population":0,
    "gn:timezone":"Europe/Warsaw",
    "iso:country":"PL",
    "wof:name":"Grubno",
    "wof:placetype":"locality"
},
  "geometry": {"coordinates":[18.46802000000001,53.33713],"type":"Point"}
}