{
  "type": "Feature",
  "properties": {
    "gn:admin1_code":"73.0",
    "gn:admin2_code":"404.0",
    "gn:admin3_code":"40406.0",
    "gn:asciiname":"Grubno",
    "gn:country_code":"PL",
    "gn:dem":81,
    "gn:feature_class":"P",
    "gn:feature_code":"PPL",
    "gn:name":"Grubno",
    "gn:population":0,
    "gn:timezone":"Europe/Warsaw",
    "iso:country":"PL",
    "name:azb_x_preferred":[
        "\u0642\u0631\u0648\u0628\u0646\u0648"
    ],
    "name:ceb_x_preferred":[
        "Grubno"
    ],
    "name:fas_x_preferred":[
        "\u06af\u0631\u0648\u0628\u0646\u0648"
    ],
    "name:nld_x_preferred":[
        "Grubno"
    ],
    "name:pol_x_preferred":[
        "Grubno"
    ],
    "name:ukr_x_preferred":[
        "\u0490\u0440\u0443\u0431\u043d\u043e"
    ],
    "wof:name":"Grubno",
    "wof:placetype":"locality"
},
  "geometry": {"coordinates":[18.46802000000001,53.33713],"type":"Point"}
}