{
  "type": "Feature",
  "properties": {
    "gn:admin1_code":"75.0",
    "gn:admin2_code":"620.0",
    "gn:admin3_code":"62014.0",
    "gn:asciiname":"Chyza",
    "gn:country_code":"PL",
    "gn:dem":204,
    "gn:feature_class":"P",
    "gn:feature_code":"PPL",
    "gn:name":"Chy\u017ca",
    "gn:population":0,
    "gn:timezone":"Europe/Warsaw",
    "iso:country":"PL",
    "name:fra_x_preferred":[
        "Chy\u017ca"
    ],
    "name:pol_x_preferred":[
        "Chy\u017ca"
    ],
    "name:ukr_x_preferred":[
        "\u0425\u0438\u0436\u0430"
    ],
    "wof:name":"Chyza",
    "wof:placetype":"locality"
},
  "geometry": {"coordinates":[23.2263,50.73564],"type":"Point"}
}