{
  "type": "Feature",
  "properties": {
    "gn:admin1_code":"78.0",
    "gn:admin2_code":"1429.0",
    "gn:admin3_code":"142908.0",
    "gn:asciiname":"Brzozow",
    "gn:country_code":"PL",
    "gn:dem":161,
    "gn:feature_class":"P",
    "gn:feature_code":"PPL",
    "gn:name":"Brzoz\u00f3w",
    "gn:population":0,
    "gn:timezone":"Europe/Warsaw",
    "iso:country":"PL",
    "name:azb_x_preferred":[
        "\u0628\u0698\u0648\u0632\u0648\u0648"
    ],
    "name:ceb_x_preferred":[
        "Brzoz\u00f3w"
    ],
    "name:fas_x_preferred":[
        "\u0628\u0698\u0648\u0632\u0648\u0648"
    ],
    "name:fra_x_preferred":[
        "Brzoz\u00f3w"
    ],
    "name:lit_x_preferred":[
        "B\u017eozuvas"
    ],
    "name:pol_x_preferred":[
        "Brzoz\u00f3w"
    ],
    "name:ukr_x_preferred":[
        "\u0411\u0436\u043e\u0437\u0443\u0432"
    ],
    "wof:name":"Brzozow",
    "wof:placetype":"locality"
},
  "geometry": {"coordinates":[22.1672,52.41072],"type":"Point"}
}