{
  "type": "Feature",
  "properties": {
    "gn:admin1_code":"78.0",
    "gn:admin2_code":"1429.0",
    "gn:admin3_code":"142908.0",
    "gn:asciiname":"Brzozow",
    "gn:country_code":"PL",
    "gn:dem":161,
    "gn:feature_class":"P",
    "gn:feature_code":"PPL",
    "gn:name":"Brzoz\u00f3w",
    "gn:population":0,
    "gn:timezone":"Europe/Warsaw",
    "iso:country":"PL",
    "name:und_x_variant":[
        "Brzoz\u00f3w"
    ],
    "wof:name":"Brzozow",
    "wof:placetype":"locality"
},
  "geometry": {"coordinates":[22.1672,52.41072],"type":"Point"}
}