{
  "type": "Feature",
  "properties": {
    "gn:admin1_code":"83.0",
    "gn:admin2_code":"2404.0",
    "gn:admin3_code":"240404.0",
    "gn:asciiname":"Wanaty",
    "gn:country_code":"PL",
    "gn:dem":265,
    "gn:feature_class":"P",
    "gn:feature_code":"PPL",
    "gn:name":"Wanaty",
    "gn:population":0,
    "gn:timezone":"Europe/Warsaw",
    "iso:country":"PL",
    "name:ceb_x_preferred":[
        "Wanaty"
    ],
    "name:pol_x_preferred":[
        "Wanaty"
    ],
    "name:ukr_x_preferred":[
        "\u0412\u0430\u043d\u0430\u0442\u0438"
    ],
    "wof:name":"Wanaty",
    "wof:placetype":"locality"
},
  "geometry": {"coordinates":[19.14366,50.68988],"type":"Point"}
}