{
  "type": "Feature",
  "properties": {
    "gn:admin1_code":"75.0",
    "gn:admin2_code":"608.0",
    "gn:admin3_code":"60808.0",
    "gn:asciiname":"Gizyce",
    "gn:country_code":"PL",
    "gn:dem":132,
    "gn:feature_class":"P",
    "gn:feature_code":"PPL",
    "gn:name":"Gi\u017cyce",
    "gn:population":0,
    "gn:timezone":"Europe/Warsaw",
    "iso:country":"PL",
    "name:fra_x_preferred":[
        "Gi\u017cyce"
    ],
    "name:pol_x_preferred":[
        "Gi\u017cyce"
    ],
    "name:ukr_x_preferred":[
        "\u0490\u0456\u0436\u0438\u0446\u0435"
    ],
    "wof:name":"Gizyce",
    "wof:placetype":"locality"
},
  "geometry": {"coordinates":[22.38825,51.59467],"type":"Point"}
}