{
  "type": "Feature",
  "properties": {
    "gn:admin1_code":"79.0",
    "gn:admin2_code":"1604.0",
    "gn:admin3_code":"160404.0",
    "gn:asciiname":"Gieralcice",
    "gn:country_code":"PL",
    "gn:dem":171,
    "gn:feature_class":"P",
    "gn:feature_code":"PPL",
    "gn:name":"Giera\u0142cice",
    "gn:population":0,
    "gn:timezone":"Europe/Warsaw",
    "iso:country":"PL",
    "name:deu_x_historical":[
        "Jeroltsch\u00fctz"
    ],
    "name:deu_x_preferred":[
        "Jeroltsch\u00fctz"
    ],
    "name:und_x_variant":[
        "Giera\u0142cice"
    ],
    "wof:name":"Gieralcice",
    "wof:placetype":"locality"
},
  "geometry": {"coordinates":[18.04854,50.99403],"type":"Point"}
}