{
  "type": "Feature",
  "properties": {
    "gn:admin1_code":"84.0",
    "gn:admin2_code":"2605.0",
    "gn:admin3_code":"260503.0",
    "gn:asciiname":"Gracuch",
    "gn:country_code":"PL",
    "gn:dem":219,
    "gn:feature_class":"P",
    "gn:feature_code":"PPL",
    "gn:name":"Gracuch",
    "gn:population":0,
    "gn:timezone":"Europe/Warsaw",
    "iso:country":"PL",
    "name:ceb_x_preferred":[
        "Gracuch"
    ],
    "name:nld_x_preferred":[
        "Gracuch"
    ],
    "name:pol_x_preferred":[
        "Gracuch"
    ],
    "name:ukr_x_preferred":[
        "\u0490\u0440\u0430\u0446\u0443\u0445"
    ],
    "wof:name":"Gracuch",
    "wof:placetype":"locality"
},
  "geometry": {"coordinates":[20.35844,51.23027],"type":"Point"}
}