{
  "type": "Feature",
  "properties": {
    "gn:admin1_code":"75.0",
    "gn:admin2_code":"603.0",
    "gn:admin3_code":"60314.0",
    "gn:asciiname":"Puszcza",
    "gn:country_code":"PL",
    "gn:dem":176,
    "gn:feature_class":"P",
    "gn:feature_code":"PPL",
    "gn:name":"Puszcza",
    "gn:population":0,
    "gn:timezone":"Europe/Warsaw",
    "iso:country":"PL",
    "name:fra_x_preferred":[
        "Puszcza"
    ],
    "name:pol_x_preferred":[
        "Puszcza"
    ],
    "name:ukr_x_preferred":[
        "\u041f\u0443\u0449\u0430"
    ],
    "wof:name":"Puszcza",
    "wof:placetype":"locality"
},
  "geometry": {"coordinates":[23.70197000000001,51.07678],"type":"Point"}
}