{
  "type": "Feature",
  "properties": {
    "gn:admin1_code":"74.0",
    "gn:admin2_code":"1020.0",
    "gn:admin3_code":"102006.0",
    "gn:asciiname":"Sliwniki",
    "gn:country_code":"PL",
    "gn:dem":127,
    "gn:feature_class":"P",
    "gn:feature_code":"PPL",
    "gn:name":"\u015aliwniki",
    "gn:population":0,
    "gn:timezone":"Europe/Warsaw",
    "iso:country":"PL",
    "wof:name":"Sliwniki",
    "wof:placetype":"locality"
},
  "geometry": {"coordinates":[19.25055,51.97602],"type":"Point"}
}