{
  "type": "Feature",
  "properties": {
    "gn:admin1_code":"87.0",
    "gn:admin2_code":"3218.0",
    "gn:admin3_code":"321805.0",
    "gn:asciiname":"Przyton",
    "gn:country_code":"PL",
    "gn:dem":93,
    "gn:feature_class":"P",
    "gn:feature_code":"PPL",
    "gn:name":"Przyto\u0144",
    "gn:population":0,
    "gn:timezone":"Europe/Warsaw",
    "iso:country":"PL",
    "name:und_x_variant":[
        "Przyto\u0144"
    ],
    "wof:name":"Przyton",
    "wof:placetype":"locality"
},
  "geometry": {"coordinates":[15.61362,53.54204],"type":"Point"}
}