{
  "type": "Feature",
  "properties": {
    "gn:admin1_code":"87.0",
    "gn:admin2_code":"3218.0",
    "gn:admin3_code":"321805.0",
    "gn:asciiname":"Przyton",
    "gn:country_code":"PL",
    "gn:dem":93,
    "gn:feature_class":"P",
    "gn:feature_code":"PPL",
    "gn:name":"Przyto\u0144",
    "gn:population":0,
    "gn:timezone":"Europe/Warsaw",
    "iso:country":"PL",
    "name:pol_x_preferred":[
        "Przyto\u0144"
    ],
    "name:ukr_x_preferred":[
        "\u041f\u0448\u0438\u0442\u043e\u043d\u044c"
    ],
    "name:vie_x_preferred":[
        "Przyto\u0144"
    ],
    "wof:name":"Przyton",
    "wof:placetype":"locality"
},
  "geometry": {"coordinates":[15.61362,53.54204],"type":"Point"}
}