{
  "type": "Feature",
  "properties": {
    "gn:admin1_code":"87.0",
    "gn:admin2_code":"3218.0",
    "gn:admin3_code":"321805.0",
    "gn:asciiname":"Krasnik Lobeski",
    "gn:country_code":"PL",
    "gn:dem":86,
    "gn:feature_class":"P",
    "gn:feature_code":"PPL",
    "gn:name":"Kra\u015bnik \u0141obeski",
    "gn:population":0,
    "gn:timezone":"Europe/Warsaw",
    "iso:country":"PL",
    "name:pol_x_preferred":[
        "Kra\u015bnik \u0141obeski"
    ],
    "name:ukr_x_preferred":[
        "\u041a\u0440\u0430\u0441\u044c\u043d\u0438\u043a-\u041b\u043e\u0431\u0435\u0441\u044c\u043a\u0438\u0439"
    ],
    "name:vie_x_preferred":[
        "Kra\u015bnik \u0141obeski"
    ],
    "wof:name":"Krasnik Lobeski",
    "wof:placetype":"locality"
},
  "geometry": {"coordinates":[15.54102,53.5814],"type":"Point"}
}