{
  "type": "Feature",
  "properties": {
    "iso:country":"PL",
    "name:eng_x_preferred":[
        "Bonin"
    ],
    "name:pol_x_preferred":[
        "Bonin"
    ],
    "wof:name":"Bonin",
    "wof:placetype":"neighbourhood"
},
  "geometry": {"coordinates":[16.90727846957752,52.4303902716428],"type":"Point"}
}