{
  "type": "Feature",
  "properties": {
    "gn:admin1_code":"86.0",
    "gn:admin2_code":"3017.0",
    "gn:admin3_code":"301708.0",
    "gn:asciiname":"Krzyzno",
    "gn:country_code":"PL",
    "gn:dem":126,
    "gn:feature_class":"P",
    "gn:feature_code":"PPL",
    "gn:name":"Krzy\u017ano",
    "gn:population":0,
    "gn:timezone":"Europe/Warsaw",
    "iso:country":"PL",
    "name:und_x_variant":[
        "Krzy\u017ano"
    ],
    "wof:name":"Krzyzno",
    "wof:placetype":"locality"
},
  "geometry": {"coordinates":[17.68958,51.50687],"type":"Point"}
}