{
  "type": "Feature",
  "properties": {
    "gn:gn_country":"PL",
    "gn:gn_fcode":"PPLA3",
    "gn:gn_pop":9143,
    "gn:population":9143,
    "iso:country":"PL",
    "name:lav_x_preferred":[
        "Pu\u0161\u010dikovo"
    ],
    "name:rus_x_preferred":[
        "\u041f\u0443\u0449\u0438\u043a\u043e\u0432\u043e"
    ],
    "name:srp_x_preferred":[
        "\u041f\u0443\u0448\u0447\u0438\u043a\u043e\u0432\u043e"
    ],
    "name:ukr_x_preferred":[
        "\u041f\u0443\u0449\u0438\u043a\u043e\u0432\u043e"
    ],
    "name:zho_x_preferred":[
        "\u666e\u4ec0\u5947\u79d1\u6c83"
    ],
    "qs_pg:aaroncc":"PL",
    "qs_pg:gn_country":"PL",
    "qs_pg:gn_fcode":"PPLA3",
    "qs_pg:gn_pop":9143,
    "qs_pg:name":"Puszczykowo",
    "qs_pg:name_adm0":"Polska",
    "qs_pg:name_adm1":"Wielkopolskie",
    "qs_pg:photos":4,
    "qs_pg:photos_1k":1,
    "qs_pg:photos_9k":1,
    "qs_pg:photos_9r":2,
    "qs_pg:photos_all":49,
    "qs_pg:photos_sr":1,
    "qs_pg:pop_sr":5,
    "qs_pg:qs_pg_placetype":"localadmin",
    "qs_pg:qs_pg_placetype_gp":"LocalAdmin",
    "qs_pg:woe_adm0":23424923,
    "woe:adm0_id":23424923,
    "woe:name_adm0":"Polska",
    "woe:name_adm1":"Wielkopolskie",
    "woe:placetype":"LocalAdmin",
    "wof:name":"Puszczykowo",
    "wof:placetype":"localadmin",
    "wof:population":9143
},
  "geometry": {"coordinates":[16.84925,52.2857],"type":"Point"}
}