{
  "type": "Feature",
  "properties": {
    "gn:admin1_code":"78.0",
    "gn:admin2_code":"1465.0",
    "gn:admin3_code":"146501.0",
    "gn:admin4_code":"146517_8",
    "gn:asciiname":"Gorzkiewki",
    "gn:country_code":"PL",
    "gn:dem":102,
    "gn:feature_class":"P",
    "gn:feature_code":"PPL",
    "gn:name":"Gorzkiewki",
    "gn:population":0,
    "gn:timezone":"Europe/Warsaw",
    "iso:country":"PL",
    "wof:name":"Gorzkiewki",
    "wof:placetype":"locality"
},
  "geometry": {"coordinates":[20.98333,52.15],"type":"Point"}
}