{
  "type": "Feature",
  "properties": {
    "gn:admin1_code":"74.0",
    "gn:admin2_code":"1012.0",
    "gn:admin3_code":"101209.0",
    "gn:asciiname":"Jankowice",
    "gn:country_code":"PL",
    "gn:dem":203,
    "gn:feature_class":"P",
    "gn:feature_code":"PPL",
    "gn:name":"Jankowice",
    "gn:population":0,
    "gn:timezone":"Europe/Warsaw",
    "iso:country":"PL",
    "name:azb_x_preferred":[
        "\u06cc\u0627\u0646\u06a9\u0648\u0648\u06cc\u062a\u0633\u0647"
    ],
    "name:fas_x_preferred":[
        "\u06cc\u0627\u0646\u06a9\u0648\u0648\u06cc\u062a\u0633\u0647"
    ],
    "name:fra_x_preferred":[
        "Jankowice"
    ],
    "name:pol_x_preferred":[
        "Jankowice"
    ],
    "name:ukr_x_preferred":[
        "\u042f\u043d\u043a\u043e\u0432\u0456\u0446\u0435"
    ],
    "name:urd_x_preferred":[
        "\u062c\u0646\u06a9\u0648\u0648\u06a9\u06d2"
    ],
    "wof:name":"Jankowice",
    "wof:placetype":"locality"
},
  "geometry": {"coordinates":[19.26058,51.04237],"type":"Point"}
}