{
  "type": "Feature",
  "properties": {
    "gn:admin1_code":"75.0",
    "gn:admin2_code":"612.0",
    "gn:admin3_code":"61205.0",
    "gn:asciiname":"Dabrowa Puscinska",
    "gn:country_code":"PL",
    "gn:dem":213,
    "gn:feature_class":"P",
    "gn:feature_code":"PPL",
    "gn:name":"D\u0105browa Pusci\u0144ska",
    "gn:population":0,
    "gn:timezone":"Europe/Warsaw",
    "iso:country":"PL",
    "wof:name":"Dabrowa Puscinska",
    "wof:placetype":"locality"
},
  "geometry": {"coordinates":[22.06667,51.08333],"type":"Point"}
}