{
  "type": "Feature",
  "properties": {
    "gn:admin1_code":"74.0",
    "gn:admin2_code":"1014.0",
    "gn:admin3_code":"101410.0",
    "gn:asciiname":"Gesiowka",
    "gn:country_code":"PL",
    "gn:dem":155,
    "gn:feature_class":"P",
    "gn:feature_code":"PPL",
    "gn:name":"G\u0119si\u00f3wka",
    "gn:population":0,
    "gn:timezone":"Europe/Warsaw",
    "iso:country":"PL",
    "wof:name":"Gesiowka",
    "wof:placetype":"locality"
},
  "geometry": {"coordinates":[18.5918,51.55078],"type":"Point"}
}