{
  "type": "Feature",
  "properties": {
    "gn:country":"PL",
    "gn:fcode":"PPL",
    "gn:population":820,
    "iso:country":"PL",
    "name:ast_x_preferred":[
        "Olszewo-Borki"
    ],
    "name:azb_x_preferred":[
        "\u0627\u0648\u0644\u0634\u0648\u0648-\u0628\u0648\u0631\u06a9\u06cc"
    ],
    "name:ceb_x_preferred":[
        "Olszewo-Borki"
    ],
    "name:deu_x_preferred":[
        "Olszewo-Borki"
    ],
    "name:eng_x_preferred":[
        "Olszewo-Borki"
    ],
    "name:fas_x_preferred":[
        "\u0627\u0648\u0644\u0634\u0648\u0648-\u0628\u0648\u0631\u06a9\u06cc"
    ],
    "name:fra_x_preferred":[
        "Olszewo-Borki"
    ],
    "name:nld_x_preferred":[
        "Olszewo-Borki"
    ],
    "name:pol_x_preferred":[
        "Olszewo-Borki"
    ],
    "name:ukr_x_preferred":[
        "\u041e\u043b\u044c\u0448\u0435\u0432\u043e-\u0411\u043e\u0440\u043a\u0456"
    ],
    "qs_pg:aaroncc":"PL",
    "qs_pg:gn_country":"PL",
    "qs_pg:gn_fcode":"PPL",
    "qs_pg:gn_pop":820,
    "qs_pg:name":"Olszewo Borki",
    "qs_pg:photos_9r":0,
    "qs_pg:photos_sr":0,
    "qs_pg:pop_sr":2,
    "qs_pg:qs_pg_placetype":"locality",
    "wof:name":"Olszewo Borki",
    "wof:placetype":"locality",
    "wof:population":820
},
  "geometry": {"coordinates":[21.53595,53.06783],"type":"Point"}
}