{
  "type": "Feature",
  "properties": {
    "gn:population":1480,
    "iso:country":"PL",
    "name:ast_x_preferred":[
        "Mircze"
    ],
    "name:azb_x_preferred":[
        "\u0645\u06cc\u0631\u0686\u0647"
    ],
    "name:ceb_x_preferred":[
        "Mircze"
    ],
    "name:deu_x_preferred":[
        "Mircze"
    ],
    "name:eng_x_preferred":[
        "Mircze"
    ],
    "name:fas_x_preferred":[
        "\u0645\u06cc\u0631\u0686\u0647"
    ],
    "name:fra_x_preferred":[
        "Mircze"
    ],
    "name:nld_x_preferred":[
        "Mircze"
    ],
    "name:pol_x_preferred":[
        "Mircze"
    ],
    "name:ukr_x_preferred":[
        "\u041c\u0456\u0440\u0447\u0435"
    ],
    "qs:a0":"Rzeczpospolita Polska",
    "qs:a1":"*Lubelskie",
    "qs:a1r":"0",
    "qs:a2":"Hrubieszowski",
    "qs:adm0":"Rzeczpospolita Polska",
    "qs:la":"Mircze",
    "qs:la_lc":"*PL0604052",
    "qs:level":"locality",
    "qs:loc":"Mircze",
    "qs:loc_alt":"Mircze",
    "qs:pop":0,
    "qs:type":"rural point-in-poly",
    "wd:wordcount":96,
    "wof:coterminous":[
        1477752115
    ],
    "wof:name":"Mircze",
    "wof:placetype":"locality",
    "wof:population":1480
},
  "geometry": {"coordinates":[23.8940280557906,50.6370868533515],"type":"Point"}
}