{
  "type": "Feature",
  "properties": {
    "gn:admin1_code":"73.0",
    "gn:admin2_code":"407.0",
    "gn:admin3_code":"40703.0",
    "gn:asciiname":"Murzynno",
    "gn:country_code":"PL",
    "gn:dem":83,
    "gn:feature_class":"P",
    "gn:feature_code":"PPL",
    "gn:name":"Murzynno",
    "gn:population":0,
    "gn:timezone":"Europe/Warsaw",
    "iso:country":"PL",
    "name:azb_x_preferred":[
        "\u0645\u0648\u0698\u0646\u0646\u0648"
    ],
    "name:ceb_x_preferred":[
        "Murzynno"
    ],
    "name:deu_x_preferred":[
        "Murzynno"
    ],
    "name:fas_x_preferred":[
        "\u0645\u0648\u0698\u0646\u0646\u0648"
    ],
    "name:nld_x_preferred":[
        "Murzynno"
    ],
    "name:pol_x_preferred":[
        "Murzynno"
    ],
    "name:ukr_x_preferred":[
        "\u041c\u0443\u0436\u0438\u043d\u043d\u043e"
    ],
    "wof:name":"Murzynno",
    "wof:placetype":"locality"
},
  "geometry": {"coordinates":[18.49421,52.85779],"type":"Point"}
}