{
  "type": "Feature",
  "properties": {
    "gn:admin1_code":"75.0",
    "gn:admin2_code":"608.0",
    "gn:admin3_code":"60807.0",
    "gn:asciiname":"Annobor",
    "gn:country_code":"PL",
    "gn:dem":168,
    "gn:feature_class":"P",
    "gn:feature_code":"PPL",
    "gn:name":"Annob\u00f3r",
    "gn:population":0,
    "gn:timezone":"Europe/Warsaw",
    "iso:country":"PL",
    "name:fra_x_preferred":[
        "Annob\u00f3r"
    ],
    "name:pol_x_preferred":[
        "Annob\u00f3r"
    ],
    "name:srp_x_preferred":[
        "\u0410\u043d\u043e\u0431\u043e\u0440"
    ],
    "name:ukr_x_preferred":[
        "\u0410\u043d\u043d\u043e\u0431\u0443\u0440"
    ],
    "wof:name":"Annobor",
    "wof:placetype":"locality"
},
  "geometry": {"coordinates":[22.58968,51.42912000000001],"type":"Point"}
}