{
  "type": "Feature",
  "properties": {
    "gn:gn_country":"PL",
    "gn:gn_fcode":"PPL",
    "gn:gn_pop":288,
    "gn:population":288,
    "iso:country":"PL",
    "name:ast_x_preferred":[
        "\u015awidnica Polska"
    ],
    "name:ceb_x_preferred":[
        "\u015awidnica Polska"
    ],
    "name:eng_x_preferred":[
        "\u015awidnica Polska"
    ],
    "name:fra_x_preferred":[
        "\u015awidnica Polska"
    ],
    "name:nld_x_preferred":[
        "\u015awidnica Polska"
    ],
    "name:pol_x_preferred":[
        "\u015awidnica Polska"
    ],
    "name:ukr_x_preferred":[
        "\u0421\u044c\u0432\u0456\u0434\u043d\u0438\u0446\u044f-\u041f\u043e\u043b\u044c\u0441\u044c\u043a\u0430"
    ],
    "qs_pg:aaroncc":"PL",
    "qs_pg:gn_country":"PL",
    "qs_pg:gn_fcode":"PPL",
    "qs_pg:gn_pop":288,
    "qs_pg:name":"\u015awidnica Polska",
    "qs_pg:name_adm0":"Polska",
    "qs_pg:name_adm1":"Dolnosl\u0105skie",
    "qs_pg:photos_9r":0,
    "qs_pg:photos_sr":0,
    "qs_pg:pop_sr":2,
    "qs_pg:qs_pg_placetype":"locality",
    "qs_pg:qs_pg_placetype_gp":"Town",
    "qs_pg:woe_adm0":23424923,
    "woe:adm0_id":23424923,
    "woe:name_adm0":"Polska",
    "woe:name_adm1":"Dolnosl\u0105skie",
    "woe:placetype":"Town",
    "wof:name":"\u015awidnica Polska",
    "wof:placetype":"locality",
    "wof:population":288
},
  "geometry": {"coordinates":[16.67759,51.07419],"type":"Point"}
}