{
  "type": "Feature",
  "properties": {
    "gn:admin1_code":"72.0",
    "gn:admin2_code":"221.0",
    "gn:admin3_code":"22102.0",
    "gn:asciiname":"Glinica",
    "gn:country_code":"PL",
    "gn:dem":490,
    "gn:feature_class":"P",
    "gn:feature_code":"PPL",
    "gn:name":"Glinica",
    "gn:population":0,
    "gn:timezone":"Europe/Warsaw",
    "iso:country":"PL",
    "wof:name":"Glinica",
    "wof:placetype":"locality"
},
  "geometry": {"coordinates":[16.344,50.7282],"type":"Point"}
}