{
  "type": "Feature",
  "properties": {
    "gn:admin1_code":"87.0",
    "gn:admin2_code":"3216.0",
    "gn:admin3_code":"321606.0",
    "gn:asciiname":"Rusinowo",
    "gn:country_code":"PL",
    "gn:dem":86,
    "gn:feature_class":"P",
    "gn:feature_code":"PPL",
    "gn:name":"Rusinowo",
    "gn:population":0,
    "gn:timezone":"Europe/Warsaw",
    "iso:country":"PL",
    "name:deu_x_preferred":[
        "Rusinowo"
    ],
    "name:pol_x_preferred":[
        "Rusinowo"
    ],
    "name:ukr_x_preferred":[
        "\u0420\u0443\u0441\u0456\u043d\u043e\u0432\u043e"
    ],
    "wof:name":"Rusinowo",
    "wof:placetype":"locality"
},
  "geometry": {"coordinates":[15.59973,53.78128],"type":"Point"}
}