{
  "type": "Feature",
  "properties": {
    "gn:population":3844,
    "iso:country":"PL",
    "name:azb_x_preferred":[
        "\u067e\u0648\u062f\u06a9\u0648\u0648\u0627 \u0644\u0634\u0646\u0627"
    ],
    "name:ceb_x_preferred":[
        "Podkowa Le\u015bna"
    ],
    "name:ces_x_preferred":[
        "Podkowa Le\u015bna"
    ],
    "name:deu_x_preferred":[
        "Podkowa Le\u015bna"
    ],
    "name:eng_x_preferred":[
        "Podkowa Le\u015bna"
    ],
    "name:epo_x_preferred":[
        "Podkowa Le\u015bna"
    ],
    "name:eus_x_preferred":[
        "Podkowa Le\u015bna"
    ],
    "name:fas_x_preferred":[
        "\u067e\u0648\u062f\u06a9\u0648\u0648\u0627 \u0644\u0634\u0646\u0627"
    ],
    "name:fra_x_preferred":[
        "Podkowa Le\u015bna"
    ],
    "name:ita_x_preferred":[
        "Podkowa Le\u015bna"
    ],
    "name:jav_x_preferred":[
        "Podkowa Le\u015bna"
    ],
    "name:lav_x_preferred":[
        "Podkova Lesna"
    ],
    "name:msa_x_preferred":[
        "Podkowa Le\u015bna"
    ],
    "name:nan_x_preferred":[
        "Podkowa Le\u015bna"
    ],
    "name:nld_x_preferred":[
        "Podkowa Le\u015bna"
    ],
    "name:pol_x_preferred":[
        "Podkowa Le\u015bna"
    ],
    "name:por_x_preferred":[
        "Podkowa Le\u015bna"
    ],
    "name:ron_x_preferred":[
        "Podkowa Le\u015bna"
    ],
    "name:rus_x_preferred":[
        "\u041f\u043e\u0434\u043a\u043e\u0432\u0430-\u041b\u0435\u0441\u044c\u043d\u0430"
    ],
    "name:slk_x_preferred":[
        "Podkowa Le\u015bna"
    ],
    "name:srp_x_preferred":[
        "\u041f\u043e\u0434\u043a\u043e\u0432\u0430 \u041b\u0435\u0441\u043d\u0430"
    ],
    "name:tat_x_preferred":[
        "\u041f\u043e\u0434\u043a\u043e\u0432\u0430-\u041b\u0435\u0447\u043d\u0430"
    ],
    "name:ukr_x_preferred":[
        "\u041f\u043e\u0434\u043a\u043e\u0432\u0430-\u041b\u0435\u0441\u044c\u043d\u0430"
    ],
    "name:vie_x_preferred":[
        "Podkowa Le\u015bna"
    ],
    "name:war_x_preferred":[
        "Podkowa Le\u015bna"
    ],
    "name:zho_x_preferred":[
        "\u6ce2\u5fb7\u79d1\u74e6\u840a\u5e0c\u7d0d"
    ],
    "qs:a0":"Rzeczpospolita Polska",
    "qs:a1":"*Mazowieckie",
    "qs:a1r":"0",
    "qs:a2":"Grodziski",
    "qs:adm0":"Rzeczpospolita Polska",
    "qs:la":"Milan\u00f3wek",
    "qs:la_lc":"*PL1405011",
    "qs:level":"locality",
    "qs:loc":"Podkowa Le\u015bna",
    "qs:loc_alt":"Podkowa Lesna",
    "qs:pop":0,
    "qs:type":"rural point-multi-in-poly-resolved",
    "wd:wordcount":169,
    "wof:name":"Podkowa Le\u015bna",
    "wof:placetype":"locality",
    "wof:population":3844
},
  "geometry": {"coordinates":[20.7590634302527,52.106310604822],"type":"Point"}
}