{
  "type": "Feature",
  "properties": {
    "gn:admin1_code":"75.0",
    "gn:admin2_code":"612.0",
    "gn:admin3_code":"61202.0",
    "gn:asciiname":"Boiska Stare",
    "gn:cc2":"PL",
    "gn:country_code":"PL",
    "gn:dem":161,
    "gn:feature_class":"P",
    "gn:feature_code":"PPL",
    "gn:name":"Boiska Stare",
    "gn:population":0,
    "gn:timezone":"Europe/Warsaw",
    "iso:country":"PL",
    "name:fra_x_preferred":[
        "Stare Boiska"
    ],
    "name:pol_x_preferred":[
        "Stare Boiska"
    ],
    "name:ukr_x_preferred":[
        "\u0421\u0442\u0430\u0440\u0435 \u0411\u043e\u0457\u0441\u044c\u043a\u0430"
    ],
    "name:und_x_variant":[
        "Boiska Stara",
        "Boiska Stare",
        "Stare Boiska"
    ],
    "wof:name":"Boiska Stare",
    "wof:placetype":"locality"
},
  "geometry": {"coordinates":[21.96424,50.99183],"type":"Point"}
}