{
  "type": "Feature",
  "properties": {
    "gn:admin1_code":"78.0",
    "gn:admin2_code":"1434.0",
    "gn:admin3_code":"143411.0",
    "gn:asciiname":"Dziecioly",
    "gn:country_code":"PL",
    "gn:dem":100,
    "gn:feature_class":"P",
    "gn:feature_code":"PPL",
    "gn:name":"Dzi\u0119cio\u0142y",
    "gn:population":0,
    "gn:timezone":"Europe/Warsaw",
    "iso:country":"PL",
    "name:fra_x_preferred":[
        "Dzi\u0119cio\u0142y"
    ],
    "name:pol_x_preferred":[
        "Dzi\u0119cio\u0142y"
    ],
    "name:ukr_x_preferred":[
        "\u0414\u0437\u0435\u043d\u0446\u044c\u043e\u043b\u0438"
    ],
    "wof:name":"Dziecioly",
    "wof:placetype":"locality"
},
  "geometry": {"coordinates":[21.46464,52.42244],"type":"Point"}
}