{
  "type": "Feature",
  "properties": {
    "gn:admin1_code":"76.0",
    "gn:admin2_code":"802.0",
    "gn:admin3_code":"80203.0",
    "gn:asciiname":"Struga",
    "gn:country_code":"PL",
    "gn:dem":53,
    "gn:feature_class":"P",
    "gn:feature_code":"PPL",
    "gn:name":"Struga",
    "gn:population":0,
    "gn:timezone":"Europe/Warsaw",
    "iso:country":"PL",
    "wof:name":"Struga",
    "wof:placetype":"locality"
},
  "geometry": {"coordinates":[15.12184,52.10983],"type":"Point"}
}