{
  "type": "Feature",
  "properties": {
    "gn:admin1_code":"76.0",
    "gn:admin2_code":"802.0",
    "gn:admin3_code":"80203.0",
    "gn:asciiname":"Struga",
    "gn:country_code":"PL",
    "gn:dem":53,
    "gn:feature_class":"P",
    "gn:feature_code":"PPL",
    "gn:name":"Struga",
    "gn:population":0,
    "gn:timezone":"Europe/Warsaw",
    "iso:country":"PL",
    "name:ceb_x_preferred":[
        "Struga"
    ],
    "name:fra_x_preferred":[
        "Struga"
    ],
    "name:heb_x_preferred":[
        "\u05e1\u05d8\u05e8\u05d5\u05d2\u05d4"
    ],
    "name:pol_x_preferred":[
        "Struga"
    ],
    "name:ukr_x_preferred":[
        "\u0421\u0442\u0440\u0443\u0491\u0430"
    ],
    "wof:name":"Struga",
    "wof:placetype":"locality"
},
  "geometry": {"coordinates":[15.12184,52.10983],"type":"Point"}
}