{
  "type": "Feature",
  "properties": {
    "gn:country":"PL",
    "gn:fcode":"PPL",
    "gn:population":443,
    "iso:country":"PL",
    "name:ceb_x_preferred":[
        "Micha\u0142\u00f3w"
    ],
    "name:deu_x_preferred":[
        "Micha\u0142\u00f3w"
    ],
    "name:fra_x_preferred":[
        "Micha\u0142\u00f3w"
    ],
    "name:nld_x_preferred":[
        "Micha\u0142\u00f3w"
    ],
    "name:pol_x_preferred":[
        "Micha\u0142\u00f3w"
    ],
    "name:ukr_x_preferred":[
        "\u041c\u0456\u0445\u0430\u043b\u0443\u0432"
    ],
    "qs_pg:aaroncc":"PL",
    "qs_pg:gn_country":"PL",
    "qs_pg:gn_fcode":"PPL",
    "qs_pg:gn_pop":443,
    "qs_pg:name":"Micha\u0142\u00f3w",
    "qs_pg:name_adm0":"Polska",
    "qs_pg:name_adm1":"Mazowieckie",
    "qs_pg:photos_9r":0,
    "qs_pg:photos_sr":0,
    "qs_pg:pop_sr":2,
    "qs_pg:qs_pg_placetype":"locality",
    "qs_pg:qs_pg_placetype_gp":"Town",
    "qs_pg:woe_adm0":23424923,
    "woe:adm0_id":23424923,
    "woe:name_adm0":"Polska",
    "woe:name_adm1":"Mazowieckie",
    "woe:placetype":"Town",
    "wof:name":"Micha\u0142\u00f3w",
    "wof:placetype":"locality",
    "wof:population":443
},
  "geometry": {"coordinates":[21.38429,52.268],"type":"Point"}
}