{
  "type": "Feature",
  "properties": {
    "gn:admin1_code":"80.0",
    "gn:admin2_code":"1806.0",
    "gn:admin3_code":"180601.0",
    "gn:asciiname":"Jagodnik",
    "gn:country_code":"PL",
    "gn:dem":223,
    "gn:feature_class":"P",
    "gn:feature_code":"PPL",
    "gn:name":"Jagodnik",
    "gn:population":0,
    "gn:timezone":"Europe/Warsaw",
    "iso:country":"PL",
    "name:pol_x_preferred":[
        "Jagodnik"
    ],
    "name:ukr_x_preferred":[
        "\u042f\u0491\u043e\u0434\u043d\u0438\u043a"
    ],
    "name:urd_x_preferred":[
        "\u062c\u06af\u0648\u062f\u0646\u06a9"
    ],
    "wof:name":"Jagodnik",
    "wof:placetype":"locality"
},
  "geometry": {"coordinates":[21.70866,50.31619],"type":"Point"}
}