{
  "type": "Feature",
  "properties": {
    "gn:admin1_code":"78.0",
    "gn:admin2_code":"1426.0",
    "gn:admin3_code":"142605.0",
    "gn:asciiname":"Kolonia Stok Ruski",
    "gn:country_code":"PL",
    "gn:dem":168,
    "gn:feature_class":"P",
    "gn:feature_code":"PPL",
    "gn:name":"Kolonia Stok Ruski",
    "gn:population":0,
    "gn:timezone":"Europe/Warsaw",
    "iso:country":"PL",
    "name:und_x_variant":[
        "Stok Ruski Kolonia",
        "Kolonia Stok Ruski"
    ],
    "wof:name":"Kolonia Stok Ruski",
    "wof:placetype":"locality"
},
  "geometry": {"coordinates":[22.46212,52.20813],"type":"Point"}
}