{
  "type": "Feature",
  "properties": {
    "gn:admin1_code":"74.0",
    "gn:admin2_code":"1012.0",
    "gn:admin3_code":"101214.0",
    "gn:asciiname":"Sekursko",
    "gn:country_code":"PL",
    "gn:dem":230,
    "gn:feature_class":"P",
    "gn:feature_code":"PPL",
    "gn:name":"Sekursko",
    "gn:population":0,
    "gn:timezone":"Europe/Warsaw",
    "iso:country":"PL",
    "name:pol_x_preferred":[
        "Sekursko"
    ],
    "name:ukr_x_preferred":[
        "\u0421\u0435\u043a\u0443\u0440\u0441\u044c\u043a\u043e"
    ],
    "wof:name":"Sekursko",
    "wof:placetype":"locality"
},
  "geometry": {"coordinates":[19.61201,50.89015],"type":"Point"}
}