{
  "type": "Feature",
  "properties": {
    "gn:admin1_code":"86.0",
    "gn:admin2_code":"3013.0",
    "gn:admin3_code":"301303.0",
    "gn:asciiname":"Wolkowo",
    "gn:country_code":"PL",
    "gn:dem":98,
    "gn:feature_class":"P",
    "gn:feature_code":"PPL",
    "gn:name":"Wolkowo",
    "gn:population":0,
    "gn:timezone":"Europe/Warsaw",
    "iso:country":"PL",
    "name:fra_x_preferred":[
        "Wolkowo"
    ],
    "name:pol_x_preferred":[
        "Wolkowo"
    ],
    "name:ukr_x_preferred":[
        "\u0412\u043e\u043b\u044c\u043a\u043e\u0432\u043e"
    ],
    "wof:name":"Wolkowo",
    "wof:placetype":"locality"
},
  "geometry": {"coordinates":[16.63839,51.92513],"type":"Point"}
}