{
  "type": "Feature",
  "properties": {
    "gn:admin1_code":"72.0",
    "gn:admin2_code":"202.0",
    "gn:admin3_code":"20205.0",
    "gn:asciiname":"Kietlice",
    "gn:country_code":"PL",
    "gn:dem":288,
    "gn:feature_class":"P",
    "gn:feature_code":"PPL",
    "gn:name":"Kietlice",
    "gn:population":0,
    "gn:timezone":"Europe/Warsaw",
    "iso:country":"PL",
    "name:pol_x_preferred":[
        "Kietlice"
    ],
    "name:ukr_x_preferred":[
        "\u041a\u0435\u0442\u043b\u0456\u0446\u0435"
    ],
    "wof:name":"Kietlice",
    "wof:placetype":"locality"
},
  "geometry": {"coordinates":[16.68333,50.68333],"type":"Point"}
}