{
  "type": "Feature",
  "properties": {
    "gn:admin1_code":"78.0",
    "gn:admin2_code":"1411.0",
    "gn:admin3_code":"141107.0",
    "gn:asciiname":"Szygi",
    "gn:country_code":"PL",
    "gn:dem":103,
    "gn:feature_class":"P",
    "gn:feature_code":"PPL",
    "gn:name":"Szygi",
    "gn:population":0,
    "gn:timezone":"Europe/Warsaw",
    "iso:country":"PL",
    "wof:name":"Szygi",
    "wof:placetype":"locality"
},
  "geometry": {"coordinates":[21.34126,52.91311],"type":"Point"}
}