{
  "type": "Feature",
  "properties": {
    "gn:admin1_code":"75.0",
    "gn:admin2_code":"609.0",
    "gn:admin3_code":"60907.0",
    "gn:asciiname":"Kolonia Debowka",
    "gn:cc2":"PL",
    "gn:country_code":"PL",
    "gn:dem":216,
    "gn:feature_class":"P",
    "gn:feature_code":"PPL",
    "gn:name":"Kolonia D\u0119b\u00f3wka",
    "gn:population":0,
    "gn:timezone":"Europe/Warsaw",
    "iso:country":"PL",
    "name:und_x_variant":[
        "Kolonia Wola S\u0142awi\u0144ska",
        "Kolonia D\u0119b\u00f3wka"
    ],
    "wof:name":"Kolonia Debowka",
    "wof:placetype":"locality"
},
  "geometry": {"coordinates":[22.48333,51.28333],"type":"Point"}
}