{
  "type": "Feature",
  "properties": {
    "gn:population":1198,
    "iso:country":"PL",
    "name:ast_x_preferred":[
        "Cynk\u00f3w"
    ],
    "name:eng_x_preferred":[
        "Cynk\u00f3w"
    ],
    "name:fra_x_preferred":[
        "Cynk\u00f3w"
    ],
    "name:pol_x_preferred":[
        "Cynk\u00f3w"
    ],
    "name:ukr_x_preferred":[
        "\u0426\u0438\u043d\u043a\u0443\u0432"
    ],
    "name:und_x_variant":[
        "Por\u0119ba"
    ],
    "qs:a0":"Rzeczpospolita Polska",
    "qs:a1":"*Slaskie",
    "qs:a1r":"0",
    "qs:a2":"Myszkowski",
    "qs:adm0":"Rzeczpospolita Polska",
    "qs:la_lc":"*",
    "qs:level":"locality",
    "qs:loc":"Cynk\u00f3w",
    "qs:loc_alt":"Cynkow",
    "qs:pop":0,
    "qs:type":"buffered point",
    "wd:wordcount":91,
    "wof:name":"Cynk\u00f3w",
    "wof:placetype":"locality",
    "wof:population":1198
},
  "geometry": {"coordinates":[19.118583,50.558777],"type":"Point"}
}