{
  "type": "Feature",
  "properties": {
    "gn:admin1_code":"84.0",
    "gn:admin2_code":"2606.0",
    "gn:admin3_code":"260606.0",
    "gn:asciiname":"Ruszkow",
    "gn:country_code":"PL",
    "gn:dem":269,
    "gn:feature_class":"P",
    "gn:feature_code":"PPL",
    "gn:name":"Ruszk\u00f3w",
    "gn:population":0,
    "gn:timezone":"Europe/Warsaw",
    "iso:country":"PL",
    "name:pol_x_preferred":[
        "Ruszk\u00f3w"
    ],
    "name:ukr_x_preferred":[
        "\u0420\u0443\u0448\u043a\u0443\u0432"
    ],
    "wof:name":"Ruszkow",
    "wof:placetype":"locality"
},
  "geometry": {"coordinates":[21.34172,50.86353],"type":"Point"}
}