{
  "type": "Feature",
  "properties": {
    "gn:admin1_code":"78.0",
    "gn:admin2_code":"1401.0",
    "gn:admin3_code":"140102.0",
    "gn:asciiname":"Broniszew",
    "gn:country_code":"PL",
    "gn:dem":145,
    "gn:feature_class":"P",
    "gn:feature_code":"PPL",
    "gn:name":"Broniszew",
    "gn:population":0,
    "gn:timezone":"Europe/Warsaw",
    "iso:country":"PL",
    "name:azb_x_preferred":[
        "\u0628\u0631\u0648\u0646\u0642\u0634\u0648"
    ],
    "name:fas_x_preferred":[
        "\u0628\u0631\u0648\u0646\u06af\u0634\u0648"
    ],
    "name:fra_x_preferred":[
        "Broniszew"
    ],
    "name:pol_x_preferred":[
        "Broniszew"
    ],
    "name:spa_x_preferred":[
        "Broniszew"
    ],
    "name:ukr_x_preferred":[
        "\u0411\u0440\u043e\u043d\u0456\u0448\u0435\u0432"
    ],
    "wof:name":"Broniszew",
    "wof:placetype":"locality"
},
  "geometry": {"coordinates":[20.8992,51.73369],"type":"Point"}
}