{
  "type": "Feature",
  "properties": {
    "gn:admin1_code":"85.0",
    "gn:admin2_code":"2809.0",
    "gn:admin3_code":"280903.0",
    "gn:asciiname":"Ignalin",
    "gn:country_code":"PL",
    "gn:dem":93,
    "gn:feature_class":"P",
    "gn:feature_code":"PPL",
    "gn:name":"Ignalin",
    "gn:population":0,
    "gn:timezone":"Europe/Warsaw",
    "iso:country":"PL",
    "name:und_x_variant":[
        "Reimerswalde",
        "Ignalin"
    ],
    "wof:name":"Ignalin",
    "wof:placetype":"locality"
},
  "geometry": {"coordinates":[20.47562000000001,54.14838],"type":"Point"}
}