{
  "type": "Feature",
  "properties": {
    "gn:admin1_code":"75.0",
    "gn:admin2_code":"611.0",
    "gn:admin3_code":"61109.0",
    "gn:asciiname":"Kurow",
    "gn:country_code":"PL",
    "gn:dem":153,
    "gn:feature_class":"P",
    "gn:feature_code":"PPL",
    "gn:name":"Kur\u00f3w",
    "gn:population":0,
    "gn:timezone":"Europe/Warsaw",
    "iso:country":"PL",
    "name:fra_x_preferred":[
        "Kur\u00f3w"
    ],
    "name:pol_x_preferred":[
        "Kur\u00f3w"
    ],
    "name:ukr_x_preferred":[
        "\u041a\u0443\u0440\u0443\u0432"
    ],
    "wof:name":"Kurow",
    "wof:placetype":"locality"
},
  "geometry": {"coordinates":[22.58074,52.01321],"type":"Point"}
}