{
  "type": "Feature",
  "properties": {
    "gn:admin1_code":"72.0",
    "gn:admin2_code":"208.0",
    "gn:admin3_code":"20813.0",
    "gn:asciiname":"Mlynowiec",
    "gn:country_code":"PL",
    "gn:dem":602,
    "gn:feature_class":"P",
    "gn:feature_code":"PPL",
    "gn:name":"M\u0142ynowiec",
    "gn:population":0,
    "gn:timezone":"Europe/Warsaw",
    "iso:country":"PL",
    "name:und_x_variant":[
        "M\u0142ynowiec"
    ],
    "wof:name":"Mlynowiec",
    "wof:placetype":"locality"
},
  "geometry": {"coordinates":[16.90521,50.27694],"type":"Point"}
}