{
  "type": "Feature",
  "properties": {
    "gn:admin1_code":"85.0",
    "gn:admin2_code":"2818.0",
    "gn:admin3_code":"281803.0",
    "gn:asciiname":"Samoniny",
    "gn:country_code":"PL",
    "gn:dem":153,
    "gn:feature_class":"P",
    "gn:feature_code":"PPL",
    "gn:name":"Samoniny",
    "gn:population":0,
    "gn:timezone":"Europe/Warsaw",
    "iso:country":"PL",
    "name:azb_x_preferred":[
        "\u0633\u0627\u0645\u0648\u0646\u0642\u0646\u0647"
    ],
    "name:deu_x_preferred":[
        "Samoniny"
    ],
    "name:fas_x_preferred":[
        "\u0633\u0627\u0645\u0648\u0646\u06af\u0646\u0647"
    ],
    "name:lit_x_preferred":[
        "Samanynai"
    ],
    "name:nld_x_preferred":[
        "Samoniny"
    ],
    "name:pol_x_preferred":[
        "Samoniny"
    ],
    "name:und_x_variant":[
        "Klarfliess",
        "Samonienen",
        "Samonienen Kreis Goldap"
    ],
    "wof:name":"Samoniny",
    "wof:placetype":"locality"
},
  "geometry": {"coordinates":[22.20398,54.32871],"type":"Point"}
}