{
  "type": "Feature",
  "properties": {
    "gn:admin1_code":"74.0",
    "gn:admin2_code":"1009.0",
    "gn:admin3_code":"100901.0",
    "gn:asciiname":"Sadowiec",
    "gn:country_code":"PL",
    "gn:dem":206,
    "gn:feature_class":"P",
    "gn:feature_code":"PPL",
    "gn:name":"Sadowiec",
    "gn:population":0,
    "gn:timezone":"Europe/Warsaw",
    "iso:country":"PL",
    "name:fra_x_preferred":[
        "Sadowiec"
    ],
    "name:pol_x_preferred":[
        "Sadowiec"
    ],
    "name:ukr_x_preferred":[
        "\u0421\u0430\u0434\u043e\u0432\u0435\u0446\u044c"
    ],
    "name:urd_x_preferred":[
        "\u0633\u062f\u0648\u0648\u06cc\u06a9"
    ],
    "wof:name":"Sadowiec",
    "wof:placetype":"locality"
},
  "geometry": {"coordinates":[18.89603,51.14151],"type":"Point"}
}