{
  "type": "Feature",
  "properties": {
    "gn:admin1_code":"78.0",
    "gn:admin2_code":"1406.0",
    "gn:admin3_code":"140601.0",
    "gn:asciiname":"Wilcza Gora",
    "gn:country_code":"PL",
    "gn:dem":161,
    "gn:feature_class":"P",
    "gn:feature_code":"PPL",
    "gn:name":"Wilcza G\u00f3ra",
    "gn:population":0,
    "gn:timezone":"Europe/Warsaw",
    "iso:country":"PL",
    "name:und_x_variant":[
        "Wilczog\u00f3ra",
        "Wilcza G\u00f3ra"
    ],
    "wof:name":"Wilcza Gora",
    "wof:placetype":"locality"
},
  "geometry": {"coordinates":[20.79908,51.85332],"type":"Point"}
}