{
  "type": "Feature",
  "properties": {
    "gn:admin1_code":"84.0",
    "gn:admin2_code":"2608.0",
    "gn:admin3_code":"260801.0",
    "gn:asciiname":"Swierczyna",
    "gn:country_code":"PL",
    "gn:dem":232,
    "gn:feature_class":"P",
    "gn:feature_code":"PPL",
    "gn:name":"\u015awierczyna",
    "gn:population":0,
    "gn:timezone":"Europe/Warsaw",
    "iso:country":"PL",
    "name:und_x_variant":[
        "\u015awierczyna"
    ],
    "wof:name":"Swierczyna",
    "wof:placetype":"locality"
},
  "geometry": {"coordinates":[20.33333,50.41667],"type":"Point"}
}