{
  "type": "Feature",
  "properties": {
    "gn:admin1_code":"72.0",
    "gn:admin2_code":"201.0",
    "gn:admin3_code":"20102.0",
    "gn:asciiname":"Gozdow",
    "gn:country_code":"PL",
    "gn:dem":215,
    "gn:feature_class":"P",
    "gn:feature_code":"PPL",
    "gn:name":"Gozd\u00f3w",
    "gn:population":0,
    "gn:timezone":"Europe/Warsaw",
    "iso:country":"PL",
    "wof:name":"Gozdow",
    "wof:placetype":"locality"
},
  "geometry": {"coordinates":[15.63333,51.26667],"type":"Point"}
}