{
  "type": "Feature",
  "properties": {
    "gn:admin1_code":"82.0",
    "gn:admin2_code":"2213.0",
    "gn:admin3_code":"221308.0",
    "gn:asciiname":"Okarpiec",
    "gn:cc2":"PL",
    "gn:country_code":"PL",
    "gn:dem":86,
    "gn:feature_class":"P",
    "gn:feature_code":"PPL",
    "gn:name":"Okarpiec",
    "gn:population":0,
    "gn:timezone":"Europe/Warsaw",
    "iso:country":"PL",
    "name:und_x_variant":[
        "Okarpice"
    ],
    "wof:name":"Okarpiec",
    "wof:placetype":"locality"
},
  "geometry": {"coordinates":[18.46302,53.69602],"type":"Point"}
}