{
  "type": "Feature",
  "properties": {
    "gn:admin1_code":"72",
    "gn:admin2_code":"0211",
    "gn:admin3_code":"21102.0",
    "gn:asciiname":"Lazek",
    "gn:country_code":"PL",
    "gn:dem":110,
    "gn:feature_class":"P",
    "gn:feature_code":"PPL",
    "gn:name":"\u0141azek",
    "gn:population":0,
    "gn:timezone":"Europe/Warsaw",
    "iso:country":"PL",
    "name:ceb_x_preferred":[
        "Lazek"
    ],
    "name:deu_x_historical":[
        "Rodeh\u00e4user"
    ],
    "name:deu_x_preferred":[
        "Rodeh\u00e4user"
    ],
    "name:deu_x_variant":[
        "Lazek"
    ],
    "name:swe_x_preferred":[
        "Lazek"
    ],
    "wof:name":"Lazek",
    "wof:placetype":"locality"
},
  "geometry": {"coordinates":[16.26522000000001,51.36069000000001],"type":"Point"}
}