{
  "type": "Feature",
  "properties": {
    "gn:population":3900,
    "iso:country":"PL",
    "name:ast_x_preferred":[
        "Hy\u017cne"
    ],
    "name:ceb_x_preferred":[
        "Hy\u017cne"
    ],
    "name:deu_x_preferred":[
        "Hy\u017cne"
    ],
    "name:eng_x_preferred":[
        "Hy\u017cne"
    ],
    "name:fra_x_preferred":[
        "Hy\u017cne"
    ],
    "name:nan_x_preferred":[
        "Hy\u017cne"
    ],
    "name:nld_x_preferred":[
        "Hy\u017cne"
    ],
    "name:pol_x_preferred":[
        "Hy\u017cne"
    ],
    "name:ukr_x_preferred":[
        "\u0413\u0438\u0436\u043d\u0435"
    ],
    "name:zho_min_nan_x_preferred":[
        "Hy\u017cne"
    ],
    "qs:a0":"Rzeczpospolita Polska",
    "qs:a1":"*Podkarpackie",
    "qs:a1r":"0",
    "qs:a2":"Rzeszowski",
    "qs:adm0":"Rzeczpospolita Polska",
    "qs:la_lc":"*",
    "qs:level":"locality",
    "qs:loc":"Hy\u017cne",
    "qs:loc_alt":"Hyzne",
    "qs:pop":0,
    "qs:type":"buffered point",
    "wd:wordcount":85,
    "wof:coterminous":[
        1125384225
    ],
    "wof:name":"Hy\u017cne",
    "wof:placetype":"locality",
    "wof:population":3900
},
  "geometry": {"coordinates":[22.186661,49.915108],"type":"Point"}
}