{
  "type": "Feature",
  "properties": {
    "gn:admin1_code":"86.0",
    "gn:admin2_code":"3028.0",
    "gn:admin3_code":"302804.0",
    "gn:asciiname":"Miloslawice",
    "gn:country_code":"PL",
    "gn:dem":104,
    "gn:feature_class":"P",
    "gn:feature_code":"PPL",
    "gn:name":"Mi\u0142os\u0142awice",
    "gn:population":0,
    "gn:timezone":"Europe/Warsaw",
    "iso:country":"PL",
    "name:fra_x_preferred":[
        "Mi\u0142os\u0142awice"
    ],
    "name:pol_x_preferred":[
        "Mi\u0142os\u0142awice"
    ],
    "name:ukr_x_preferred":[
        "\u041c\u0456\u043b\u043e\u0441\u043b\u0430\u0432\u0456\u0446\u0435"
    ],
    "wof:name":"Miloslawice",
    "wof:placetype":"locality"
},
  "geometry": {"coordinates":[17.35651,52.71259000000001],"type":"Point"}
}