{
  "type": "Feature",
  "properties": {
    "gn:admin1_code":"86.0",
    "gn:admin2_code":"3028.0",
    "gn:admin3_code":"302804.0",
    "gn:asciiname":"Miloslawice",
    "gn:country_code":"PL",
    "gn:dem":104,
    "gn:feature_class":"P",
    "gn:feature_code":"PPL",
    "gn:name":"Mi\u0142os\u0142awice",
    "gn:population":0,
    "gn:timezone":"Europe/Warsaw",
    "iso:country":"PL",
    "wof:name":"Miloslawice",
    "wof:placetype":"locality"
},
  "geometry": {"coordinates":[17.35651,52.71259000000001],"type":"Point"}
}