{
  "type": "Feature",
  "properties": {
    "gn:admin1_code":"78.0",
    "gn:admin2_code":"1411.0",
    "gn:admin3_code":"141106.0",
    "gn:asciiname":"Krzyzewo Borowe",
    "gn:cc2":"PL",
    "gn:country_code":"PL",
    "gn:dem":104,
    "gn:feature_class":"P",
    "gn:feature_code":"PPL",
    "gn:name":"Krzy\u017cewo Borowe",
    "gn:population":0,
    "gn:timezone":"Europe/Warsaw",
    "iso:country":"PL",
    "name:fra_x_preferred":[
        "Krzy\u017cewo Borowe"
    ],
    "name:pol_x_preferred":[
        "Krzy\u017cewo Borowe"
    ],
    "name:ukr_x_preferred":[
        "\u041a\u0448\u0438\u0436\u0435\u0432\u043e-\u0411\u043e\u0440\u043e\u0432\u0435"
    ],
    "name:und_x_variant":[
        "Krzy\u017cowo Borowe",
        "Krzy\u017cewo Borowe"
    ],
    "wof:name":"Krzyzewo Borowe",
    "wof:placetype":"locality"
},
  "geometry": {"coordinates":[21.16667,52.95],"type":"Point"}
}