{
  "type": "Feature",
  "properties": {
    "gn:admin1_code":"77.0",
    "gn:admin2_code":"1218.0",
    "gn:admin3_code":"121808.0",
    "gn:asciiname":"Garca",
    "gn:country_code":"PL",
    "gn:dem":234,
    "gn:feature_class":"P",
    "gn:feature_code":"PPL",
    "gn:name":"Garca",
    "gn:population":0,
    "gn:timezone":"Europe/Warsaw",
    "iso:country":"PL",
    "wof:name":"Garca",
    "wof:placetype":"locality"
},
  "geometry": {"coordinates":[19.46667,49.95],"type":"Point"}
}