{
  "type": "Feature",
  "properties": {
    "gn:gn_country":"PL",
    "gn:gn_fcode":"PPLA3",
    "gn:gn_pop":259,
    "gn:population":259,
    "iso:country":"PL",
    "name:dut_x_preferred":[
        "Jakubowice Murowane"
    ],
    "name:eng_x_preferred":[
        "Jakubowice Murowane"
    ],
    "name:fre_x_preferred":[
        "Jakubowice Murowane"
    ],
    "name:nan_x_preferred":[
        "Jakubowice Murowane"
    ],
    "name:per_x_preferred":[
        "\u06cc\u0627\u06a9\u0648\u0628\u0648\u0648\u06cc\u062a\u0633\u0647 \u0645\u0648\u0631\u0648\u0648\u0627\u0646\u0647"
    ],
    "name:pol_x_preferred":[
        "Jakubowice Murowane"
    ],
    "name:urd_x_preferred":[
        "\u062c\u06a9\u0628\u0648\u0648\u06a9\u06d2 \u0645\u0631\u0648\u0627\u0646\u06d2"
    ],
    "qs_pg:aaroncc":"PL",
    "qs_pg:gn_country":"PL",
    "qs_pg:gn_fcode":"PPLA3",
    "qs_pg:gn_pop":259,
    "qs_pg:name":"Jakubowice Murowane",
    "qs_pg:photos_9r":0,
    "qs_pg:photos_sr":0,
    "qs_pg:pop_sr":2,
    "qs_pg:qs_pg_placetype":"locality",
    "wof:name":"Jakubowice Murowane",
    "wof:placetype":"locality",
    "wof:population":259
},
  "geometry": {"coordinates":[22.63415,51.26992],"type":"Point"}
}