{
  "type": "Feature",
  "properties": {
    "gn:admin1_code":"72.0",
    "gn:admin2_code":"218.0",
    "gn:admin3_code":"21801.0",
    "gn:asciiname":"Chmielow",
    "gn:country_code":"PL",
    "gn:dem":136,
    "gn:feature_class":"P",
    "gn:feature_code":"PPL",
    "gn:name":"Chmiel\u00f3w",
    "gn:population":0,
    "gn:timezone":"Europe/Warsaw",
    "iso:country":"PL",
    "wof:name":"Chmielow",
    "wof:placetype":"locality"
},
  "geometry": {"coordinates":[16.74385,51.07161],"type":"Point"}
}