{
  "type": "Feature",
  "properties": {
    "gn:admin1_code":"72.0",
    "gn:admin2_code":"218.0",
    "gn:admin3_code":"21801.0",
    "gn:asciiname":"Chmielow",
    "gn:country_code":"PL",
    "gn:dem":136,
    "gn:feature_class":"P",
    "gn:feature_code":"PPL",
    "gn:name":"Chmiel\u00f3w",
    "gn:population":0,
    "gn:timezone":"Europe/Warsaw",
    "iso:country":"PL",
    "name:pol_x_preferred":[
        "Chmiel\u00f3w"
    ],
    "name:ukr_x_preferred":[
        "\u0425\u043c\u0435\u043b\u044e\u0432"
    ],
    "wof:name":"Chmielow",
    "wof:placetype":"locality"
},
  "geometry": {"coordinates":[16.74385,51.07161],"type":"Point"}
}