{
  "type": "Feature",
  "properties": {
    "gn:admin1_code":"84.0",
    "gn:admin2_code":"2608.0",
    "gn:admin3_code":"260805.0",
    "gn:asciiname":"Nieprowice",
    "gn:cc2":"PL",
    "gn:country_code":"PL",
    "gn:dem":193,
    "gn:feature_class":"P",
    "gn:feature_code":"PPL",
    "gn:name":"Nieprowice",
    "gn:population":0,
    "gn:timezone":"Europe/Warsaw",
    "iso:country":"PL",
    "name:pol_x_preferred":[
        "Nieprowice"
    ],
    "name:ukr_x_preferred":[
        "\u041d\u0435\u043f\u0440\u043e\u0432\u0456\u0446\u0435"
    ],
    "name:und_x_variant":[
        "Nieprawice"
    ],
    "wof:name":"Nieprowice",
    "wof:placetype":"locality"
},
  "geometry": {"coordinates":[20.57945,50.40234],"type":"Point"}
}