{
  "type": "Feature",
  "properties": {
    "iso:country":"PL",
    "name:pol_x_preferred":[
        "Czarna"
    ],
    "wof:name":"Czarna",
    "wof:placetype":"locality"
},
  "geometry": {"coordinates":[21.2519984938137,50.084333534211],"type":"Point"}
}