{
  "type": "Feature",
  "properties": {
    "gn:admin1_code":"75.0",
    "gn:admin2_code":"620.0",
    "gn:admin3_code":"62011.0",
    "gn:asciiname":"Wislowiec",
    "gn:country_code":"PL",
    "gn:dem":287,
    "gn:feature_class":"P",
    "gn:feature_code":"PPL",
    "gn:name":"Wis\u0142owiec",
    "gn:population":0,
    "gn:timezone":"Europe/Warsaw",
    "iso:country":"PL",
    "name:und_x_variant":[
        "Wis\u0142owiec"
    ],
    "wof:name":"Wislowiec",
    "wof:placetype":"locality"
},
  "geometry": {"coordinates":[23.24834,50.81381],"type":"Point"}
}