{
  "type": "Feature",
  "properties": {
    "gn:admin1_code":"75.0",
    "gn:admin2_code":"620.0",
    "gn:admin3_code":"62011.0",
    "gn:asciiname":"Wislowiec",
    "gn:country_code":"PL",
    "gn:dem":287,
    "gn:feature_class":"P",
    "gn:feature_code":"PPL",
    "gn:name":"Wis\u0142owiec",
    "gn:population":0,
    "gn:timezone":"Europe/Warsaw",
    "iso:country":"PL",
    "name:fra_x_preferred":[
        "Wis\u0142owiec"
    ],
    "name:pol_x_preferred":[
        "Wis\u0142owiec"
    ],
    "name:ukr_x_preferred":[
        "\u0412\u0456\u0441\u043b\u043e\u0432\u0435\u0446\u044c"
    ],
    "wof:name":"Wislowiec",
    "wof:placetype":"locality"
},
  "geometry": {"coordinates":[23.24834,50.81381],"type":"Point"}
}