{
  "type": "Feature",
  "properties": {
    "gn:country":"PL",
    "gn:fcode":"PPLA3",
    "gn:population":8439,
    "iso:country":"PL",
    "name:bul_x_preferred":[
        "\u0417\u0430\u0432\u0430\u0434\u0437\u043a\u0435"
    ],
    "name:ceb_x_preferred":[
        "Zawadzkie"
    ],
    "name:deu_x_preferred":[
        "Zawadzkie"
    ],
    "name:epo_x_preferred":[
        "Zawadzkie"
    ],
    "name:fra_x_preferred":[
        "Zawadzkie"
    ],
    "name:jav_x_preferred":[
        "Zawadzkie"
    ],
    "name:lav_x_preferred":[
        "Zavadzke"
    ],
    "name:msa_x_preferred":[
        "Zawadzkie"
    ],
    "name:nld_x_preferred":[
        "Zawadzkie"
    ],
    "name:pol_x_preferred":[
        "Zawadzkie"
    ],
    "name:por_x_preferred":[
        "Zawadzkie"
    ],
    "name:ron_x_preferred":[
        "Zawadzkie"
    ],
    "name:rus_x_preferred":[
        "\u0417\u0430\u0432\u0430\u0434\u0437\u043a\u0435"
    ],
    "name:slk_x_preferred":[
        "Zawadzkie"
    ],
    "name:srp_x_preferred":[
        "\u0417\u0430\u0432\u0430\u0434\u0441\u043a\u0458\u0435"
    ],
    "name:szl_x_preferred":[
        "Zawadzke"
    ],
    "name:tha_x_preferred":[
        "\u0e0b\u0e32\u0e27\u0e31\u0e15\u0e2a\u0e01\u0e35\u0e41\u0e22"
    ],
    "name:ukr_x_preferred":[
        "\u0417\u0430\u0432\u0430\u0434\u0437\u044c\u043a\u0435"
    ],
    "name:und_x_variant":[
        "Andreash\u00fctte"
    ],
    "name:vie_x_preferred":[
        "Zawadzkie"
    ],
    "name:zho_x_preferred":[
        "\u624e\u74e6\u8332\u51f1"
    ],
    "qs_pg:aaroncc":"PL",
    "qs_pg:gn_country":"PL",
    "qs_pg:gn_fcode":"PPLA3",
    "qs_pg:gn_pop":8439,
    "qs_pg:name":"Zawadzkie",
    "qs_pg:name_adm0":"Polska",
    "qs_pg:name_adm1":"Opolskie",
    "qs_pg:photos_9r":0,
    "qs_pg:photos_sr":0,
    "qs_pg:pop_sr":5,
    "qs_pg:qs_pg_placetype":"localadmin",
    "qs_pg:qs_pg_placetype_gp":"LocalAdmin",
    "qs_pg:woe_adm0":23424923,
    "woe:adm0_id":23424923,
    "woe:name_adm0":"Polska",
    "woe:name_adm1":"Opolskie",
    "woe:placetype":"LocalAdmin",
    "wof:name":"Zawadzkie",
    "wof:placetype":"localadmin",
    "wof:population":8439
},
  "geometry": {"coordinates":[18.48467,50.60503],"type":"Point"}
}