{
  "type": "Feature",
  "properties": {
    "gn:admin1_code":"75.0",
    "gn:admin2_code":"603.0",
    "gn:admin3_code":"60311.0",
    "gn:asciiname":"Lechowka",
    "gn:country_code":"PL",
    "gn:dem":225,
    "gn:feature_class":"P",
    "gn:feature_code":"PPL",
    "gn:name":"Lech\u00f3wka",
    "gn:population":0,
    "gn:timezone":"Europe/Warsaw",
    "iso:country":"PL",
    "name:fra_x_preferred":[
        "Lech\u00f3wka"
    ],
    "name:pol_x_preferred":[
        "Lech\u00f3wka"
    ],
    "wof:name":"Lechowka",
    "wof:placetype":"locality"
},
  "geometry": {"coordinates":[23.26944,51.17348],"type":"Point"}
}