{
  "type": "Feature",
  "properties": {
    "gn:admin1_code":"84.0",
    "gn:admin2_code":"2609.0",
    "gn:admin3_code":"260903.0",
    "gn:asciiname":"Szymanowice",
    "gn:country_code":"PL",
    "gn:dem":197,
    "gn:feature_class":"P",
    "gn:feature_code":"PPL",
    "gn:name":"Szymanowice",
    "gn:population":0,
    "gn:timezone":"Europe/Warsaw",
    "iso:country":"PL",
    "name:fra_x_preferred":[
        "Szymanowice"
    ],
    "name:pol_x_preferred":[
        "Szymanowice"
    ],
    "name:ukr_x_preferred":[
        "\u0428\u0438\u043c\u0430\u043d\u043e\u0432\u0456\u0446\u0435"
    ],
    "wof:name":"Szymanowice",
    "wof:placetype":"locality"
},
  "geometry": {"coordinates":[21.44083,50.64237],"type":"Point"}
}