{
  "type": "Feature",
  "properties": {
    "gn:country":"PL",
    "gn:fcode":"PPL",
    "gn:population":0,
    "iso:country":"PL",
    "name:ceb_x_preferred":[
        "Zaj\u0105czkowo"
    ],
    "name:deu_x_preferred":[
        "Zaj\u0105czkowo"
    ],
    "name:fra_x_preferred":[
        "Zaj\u0105czkowo"
    ],
    "name:pol_x_preferred":[
        "Zaj\u0105czkowo"
    ],
    "name:ukr_x_preferred":[
        "\u0417\u0430\u0439\u043e\u043d\u0447\u043a\u043e\u0432\u043e"
    ],
    "name:und_x_variant":[
        "Damerau"
    ],
    "qs_pg:aaroncc":"PL",
    "qs_pg:gn_country":"PL",
    "qs_pg:gn_fcode":"PPL",
    "qs_pg:gn_pop":0,
    "qs_pg:name":"Zaj\u0105czkowo",
    "qs_pg:name_adm0":"Polska",
    "qs_pg:name_adm1":"Pomorskie",
    "qs_pg:photos_9r":0,
    "qs_pg:photos_sr":0,
    "qs_pg:pop_sr":0,
    "qs_pg:qs_pg_placetype":"locality",
    "qs_pg:qs_pg_placetype_gp":"Town",
    "qs_pg:woe_adm0":23424923,
    "woe:adm0_id":23424923,
    "woe:name_adm0":"Polska",
    "woe:name_adm1":"Pomorskie",
    "woe:placetype":"Town",
    "wof:name":"Zaj\u0105czkowo",
    "wof:placetype":"locality"
},
  "geometry": {"coordinates":[18.72431,54.1196],"type":"Point"}
}