{
  "type": "Feature",
  "properties": {
    "gn:admin1_code":"75.0",
    "gn:admin2_code":"610.0",
    "gn:admin3_code":"61005.0",
    "gn:asciiname":"Albertow",
    "gn:country_code":"PL",
    "gn:dem":174,
    "gn:feature_class":"P",
    "gn:feature_code":"PPL",
    "gn:name":"Albert\u00f3w",
    "gn:population":0,
    "gn:timezone":"Europe/Warsaw",
    "iso:country":"PL",
    "name:azb_x_preferred":[
        "\u0627\u0644\u0628\u0631\u062a\u0648"
    ],
    "name:fas_x_preferred":[
        "\u0627\u0644\u0628\u0631\u062a\u0648"
    ],
    "name:fra_x_preferred":[
        "Albert\u00f3w"
    ],
    "name:pol_x_preferred":[
        "Albert\u00f3w"
    ],
    "name:ukr_x_preferred":[
        "\u0410\u043b\u044c\u0431\u0435\u0440\u0442\u0443\u0432"
    ],
    "name:und_x_variant":[
        "Kolonia Albert\u00f3w"
    ],
    "wof:name":"Albertow",
    "wof:placetype":"locality"
},
  "geometry": {"coordinates":[23.05926,51.29989000000001],"type":"Point"}
}