{
  "type": "Feature",
  "properties": {
    "gn:admin1_code":"81.0",
    "gn:admin2_code":"2012.0",
    "gn:admin3_code":"201207.0",
    "gn:asciiname":"Turowka Stara",
    "gn:country_code":"PL",
    "gn:dem":192,
    "gn:feature_class":"P",
    "gn:feature_code":"PPL",
    "gn:name":"Tur\u00f3wka Stara",
    "gn:population":0,
    "gn:timezone":"Europe/Warsaw",
    "iso:country":"PL",
    "name:fra_x_preferred":[
        "Stara Tur\u00f3wka"
    ],
    "name:lit_x_preferred":[
        "Stara Turuvka"
    ],
    "name:pol_x_preferred":[
        "Tur\u00f3wka Stara"
    ],
    "name:ukr_x_preferred":[
        "\u0422\u0443\u0440\u0443\u0432\u043a\u0430-\u0421\u0442\u0430\u0440\u0430"
    ],
    "name:und_x_variant":[
        "Tur\u00f3wka Stara"
    ],
    "wof:name":"Turowka Stara",
    "wof:placetype":"locality"
},
  "geometry": {"coordinates":[22.82637,54.14497],"type":"Point"}
}