{
  "type": "Feature",
  "properties": {
    "gn:admin1_code":"85.0",
    "gn:admin2_code":"2801.0",
    "gn:admin3_code":"280104.0",
    "gn:asciiname":"Warmiany",
    "gn:country_code":"PL",
    "gn:dem":112,
    "gn:feature_class":"P",
    "gn:feature_code":"PPL",
    "gn:name":"Warmiany",
    "gn:population":0,
    "gn:timezone":"Europe/Warsaw",
    "iso:country":"PL",
    "name:fra_x_preferred":[
        "Warmiany"
    ],
    "name:pol_x_preferred":[
        "Warmiany"
    ],
    "name:ukr_x_preferred":[
        "\u0412\u0430\u0440\u043c\u044f\u043d\u0438"
    ],
    "name:und_x_variant":[
        "Sch\u00f6nwalde"
    ],
    "name:vie_x_preferred":[
        "Warmiany"
    ],
    "wof:name":"Warmiany",
    "wof:placetype":"locality"
},
  "geometry": {"coordinates":[20.91706,54.11789],"type":"Point"}
}