{
  "type": "Feature",
  "properties": {
    "gn:gn_country":"PL",
    "gn:gn_fcode":"PPLA3",
    "gn:gn_pop":916,
    "gn:population":916,
    "iso:country":"PL",
    "name:bel_x_preferred":[
        "\u0420\u0443\u0434\u043d\u0456\u043a\u0456"
    ],
    "name:ceb_x_preferred":[
        "Rudniki"
    ],
    "name:deu_x_preferred":[
        "Rudnyky"
    ],
    "name:fra_x_preferred":[
        "Rudniki"
    ],
    "name:hye_x_preferred":[
        "\u054c\u0578\u0582\u0564\u0576\u056b\u056f\u056b"
    ],
    "name:lit_x_preferred":[
        "Rudnikai"
    ],
    "name:nld_x_preferred":[
        "Rudniki"
    ],
    "name:pol_x_preferred":[
        "Rudniki"
    ],
    "name:rus_x_preferred":[
        "\u0420\u0443\u0434\u043d\u0438\u043a\u0438"
    ],
    "name:ukr_x_preferred":[
        "\u0420\u0443\u0434\u043d\u0438\u043a\u0438"
    ],
    "name:unk_x_variant":[
        "Herrenkirch"
    ],
    "qs_pg:aaroncc":"PL",
    "qs_pg:gn_country":"PL",
    "qs_pg:gn_fcode":"PPLA3",
    "qs_pg:gn_pop":916,
    "qs_pg:name":"Rudniki",
    "qs_pg:name_adm0":"Polska",
    "qs_pg:name_adm1":"Opolskie",
    "qs_pg:photos_9r":0,
    "qs_pg:photos_sr":0,
    "qs_pg:pop_sr":2,
    "qs_pg:qs_pg_placetype":"localadmin",
    "qs_pg:qs_pg_placetype_gp":"LocalAdmin",
    "qs_pg:woe_adm0":23424923,
    "woe:adm0_id":23424923,
    "woe:name_adm0":"Polska",
    "woe:name_adm1":"Opolskie",
    "woe:placetype":"LocalAdmin",
    "wof:name":"Rudniki",
    "wof:placetype":"localadmin",
    "wof:population":916
},
  "geometry": {"coordinates":[18.18598,50.12729],"type":"Point"}
}