{
  "type": "Feature",
  "properties": {
    "gn:country":"PL",
    "gn:fcode":"PPL",
    "gn:population":305,
    "iso:country":"PL",
    "name:ast_x_preferred":[
        "Tarnawa G\u00f3rna"
    ],
    "name:ceb_x_preferred":[
        "Tarnawa G\u00f3rna"
    ],
    "name:deu_x_preferred":[
        "Tarnawa G\u00f3rna"
    ],
    "name:eng_x_preferred":[
        "Tarnawa G\u00f3rna"
    ],
    "name:fra_x_preferred":[
        "Tarnawa G\u00f3rna"
    ],
    "name:ita_x_preferred":[
        "Tarnawa G\u00f3rna"
    ],
    "name:pol_x_preferred":[
        "Tarnawa G\u00f3rna"
    ],
    "name:ukr_x_preferred":[
        "\u0422\u0430\u0440\u043d\u0430\u0432\u0430-\u0490\u0443\u0440\u043d\u0430"
    ],
    "name:und_x_variant":[
        "G\u00f3rna Tarnawa"
    ],
    "qs_pg:aaroncc":"PL",
    "qs_pg:gn_country":"PL",
    "qs_pg:gn_fcode":"PPL",
    "qs_pg:gn_pop":305,
    "qs_pg:name":"Tarnawa G\u00f3rna",
    "qs_pg:photos_9r":0,
    "qs_pg:photos_sr":0,
    "qs_pg:pop_sr":2,
    "qs_pg:qs_pg_placetype":"locality",
    "wof:name":"Tarnawa G\u00f3rna",
    "wof:placetype":"locality",
    "wof:population":305
},
  "geometry": {"coordinates":[19.51378,49.78016],"type":"Point"}
}