{
  "type": "Feature",
  "properties": {
    "gn:admin1_code":"82.0",
    "gn:admin2_code":"2261.0",
    "gn:admin3_code":"226101.0",
    "gn:asciiname":"Matarnia",
    "gn:country_code":"PL",
    "gn:dem":137,
    "gn:feature_class":"P",
    "gn:feature_code":"PPL",
    "gn:name":"Matarnia",
    "gn:population":0,
    "gn:timezone":"Europe/Warsaw",
    "iso:country":"PL",
    "name:csb_x_preferred":[
        "Matarni\u00f4"
    ],
    "name:deu_x_preferred":[
        "Matarnia"
    ],
    "name:ita_x_preferred":[
        "Matarnia"
    ],
    "name:pol_x_preferred":[
        "Matarnia"
    ],
    "name:und_x_variant":[
        "Maternia"
    ],
    "wof:name":"Matarnia",
    "wof:placetype":"locality"
},
  "geometry": {"coordinates":[18.47282,54.38563000000001],"type":"Point"}
}