{
  "type": "Feature",
  "properties": {
    "gn:admin1_code":"84.0",
    "gn:admin2_code":"2604.0",
    "gn:admin3_code":"260408.0",
    "gn:asciiname":"Fanislawice",
    "gn:country_code":"PL",
    "gn:dem":236,
    "gn:feature_class":"P",
    "gn:feature_code":"PPL",
    "gn:name":"Fanis\u0142awice",
    "gn:population":0,
    "gn:timezone":"Europe/Warsaw",
    "iso:country":"PL",
    "name:und_x_variant":[
        "Fanis\u0142awice"
    ],
    "wof:name":"Fanislawice",
    "wof:placetype":"locality"
},
  "geometry": {"coordinates":[20.31725,50.88944],"type":"Point"}
}