{
  "type": "Feature",
  "properties": {
    "gn:admin1_code":"84.0",
    "gn:admin2_code":"2604.0",
    "gn:admin3_code":"260408.0",
    "gn:asciiname":"Fanislawice",
    "gn:country_code":"PL",
    "gn:dem":236,
    "gn:feature_class":"P",
    "gn:feature_code":"PPL",
    "gn:name":"Fanis\u0142awice",
    "gn:population":0,
    "gn:timezone":"Europe/Warsaw",
    "iso:country":"PL",
    "name:azb_x_preferred":[
        "\u0641\u0627\u0646\u0642\u0633\u0648\u0627\u0648\u06cc\u062a\u0633\u0647"
    ],
    "name:ceb_x_preferred":[
        "Fanis\u0142awice"
    ],
    "name:fas_x_preferred":[
        "\u0641\u0627\u0646\u06af\u0633\u0648\u0627\u0648\u06cc\u062a\u0633\u0647"
    ],
    "name:nld_x_preferred":[
        "Fanis\u0142awice"
    ],
    "name:pol_x_preferred":[
        "Fanis\u0142awice"
    ],
    "name:ukr_x_preferred":[
        "\u0424\u0430\u043d\u0456\u0441\u043b\u0430\u0432\u0456\u0446\u0435"
    ],
    "name:und_x_variant":[
        "Fanis\u0142awice"
    ],
    "wof:name":"Fanislawice",
    "wof:placetype":"locality"
},
  "geometry": {"coordinates":[20.31725,50.88944],"type":"Point"}
}