{
  "type": "Feature",
  "properties": {
    "gn:admin1_code":"73.0",
    "gn:asciiname":"Krag",
    "gn:cc2":"PL",
    "gn:country_code":"PL",
    "gn:dem":55,
    "gn:feature_class":"P",
    "gn:feature_code":"PPL",
    "gn:name":"Kr\u0105g",
    "gn:population":0,
    "gn:timezone":"Europe/Warsaw",
    "iso:country":"PL",
    "name:ceb_x_preferred":[
        "Kr\u0105g"
    ],
    "name:deu_x_preferred":[
        "Kr\u0105g"
    ],
    "name:pol_x_preferred":[
        "Kr\u0105g"
    ],
    "name:ukr_x_preferred":[
        "\u041a\u0440\u043e\u043d\u0491"
    ],
    "name:und_x_variant":[
        "Krangen"
    ],
    "name:vie_x_preferred":[
        "Kr\u0105g"
    ],
    "wof:name":"Krag",
    "wof:placetype":"locality"
},
  "geometry": {"coordinates":[16.703,54.21095],"type":"Point"}
}