{
  "type": "Feature",
  "properties": {
    "gn:admin1_code":"73.0",
    "gn:asciiname":"Krag",
    "gn:cc2":"PL",
    "gn:country_code":"PL",
    "gn:dem":55,
    "gn:feature_class":"P",
    "gn:feature_code":"PPL",
    "gn:name":"Kr\u0105g",
    "gn:population":0,
    "gn:timezone":"Europe/Warsaw",
    "iso:country":"PL",
    "name:und_x_variant":[
        "Krangen"
    ],
    "wof:name":"Krag",
    "wof:placetype":"locality"
},
  "geometry": {"coordinates":[16.703,54.21095],"type":"Point"}
}