{
  "type": "Feature",
  "properties": {
    "gn:admin1_code":"78.0",
    "gn:admin2_code":"1435.0",
    "gn:admin3_code":"143502.0",
    "gn:asciiname":"Wolka Grochowa",
    "gn:country_code":"PL",
    "gn:dem":103,
    "gn:feature_class":"P",
    "gn:feature_code":"PPL",
    "gn:name":"W\u00f3lka Grochowa",
    "gn:population":0,
    "gn:timezone":"Europe/Warsaw",
    "iso:country":"PL",
    "wof:name":"Wolka Grochowa",
    "wof:placetype":"locality"
},
  "geometry": {"coordinates":[21.59655,52.79819000000001],"type":"Point"}
}