{
  "type": "Feature",
  "properties": {
    "gn:admin1_code":"86.0",
    "gn:admin2_code":"3012.0",
    "gn:admin3_code":"301203.0",
    "gn:asciiname":"Skalow",
    "gn:country_code":"PL",
    "gn:dem":123,
    "gn:feature_class":"P",
    "gn:feature_code":"PPL",
    "gn:name":"Ska\u0142\u00f3w",
    "gn:population":0,
    "gn:timezone":"Europe/Warsaw",
    "iso:country":"PL",
    "name:fra_x_preferred":[
        "Ska\u0142\u00f3w"
    ],
    "name:pol_x_preferred":[
        "Ska\u0142\u00f3w"
    ],
    "name:ukr_x_preferred":[
        "\u0421\u043a\u0430\u043b\u0443\u0432"
    ],
    "wof:name":"Skalow",
    "wof:placetype":"locality"
},
  "geometry": {"coordinates":[17.38621,51.80469],"type":"Point"}
}