{
  "type": "Feature",
  "properties": {
    "gn:admin1_code":"75.0",
    "gn:admin2_code":"618.0",
    "gn:admin3_code":"61813.0",
    "gn:asciiname":"Dyniska",
    "gn:country_code":"PL",
    "gn:dem":218,
    "gn:feature_class":"P",
    "gn:feature_code":"PPL",
    "gn:name":"Dyniska",
    "gn:population":0,
    "gn:timezone":"Europe/Warsaw",
    "iso:country":"PL",
    "name:azb_x_preferred":[
        "\u062f\u0646\u0642\u0633\u06a9\u0627"
    ],
    "name:ceb_x_preferred":[
        "Dyniska"
    ],
    "name:fas_x_preferred":[
        "\u062f\u0646\u06af\u0633\u06a9\u0627"
    ],
    "name:fra_x_preferred":[
        "Dyniska"
    ],
    "name:nld_x_preferred":[
        "Dyniska"
    ],
    "name:pol_x_preferred":[
        "Dyniska"
    ],
    "name:ukr_x_preferred":[
        "\u0414\u0435\u043d\u0438\u0441\u043a\u0430"
    ],
    "wof:name":"Dyniska",
    "wof:placetype":"locality"
},
  "geometry": {"coordinates":[23.71038,50.41683],"type":"Point"}
}