{
  "type": "Feature",
  "properties": {
    "gn:admin1_code":"82.0",
    "gn:admin2_code":"2209.0",
    "gn:admin3_code":"220907.0",
    "gn:asciiname":"Brzozki",
    "gn:country_code":"PL",
    "gn:dem":-1,
    "gn:feature_class":"P",
    "gn:feature_code":"PPL",
    "gn:name":"Brz\u00f3zki",
    "gn:population":0,
    "gn:timezone":"Europe/Warsaw",
    "iso:country":"PL",
    "name:ceb_x_preferred":[
        "Brz\u00f3zki"
    ],
    "name:pol_x_preferred":[
        "Brz\u00f3zki"
    ],
    "name:ukr_x_preferred":[
        "\u0411\u0436\u0443\u0437\u043a\u0456"
    ],
    "name:und_x_variant":[
        "Brz\u00f3ski",
        "Br\u00f6ske",
        "Brz\u00f3zki"
    ],
    "name:urd_x_preferred":[
        "\u0628\u0631\u0636\u0648\u0632\u06a9\u06cc"
    ],
    "wof:name":"Brzozki",
    "wof:placetype":"locality"
},
  "geometry": {"coordinates":[19.01896,54.17304],"type":"Point"}
}