{
  "type": "Feature",
  "properties": {
    "gn:admin1_code":"78.0",
    "gn:admin2_code":"1406.0",
    "gn:admin3_code":"140609.0",
    "gn:asciiname":"Wola Pniewska",
    "gn:country_code":"PL",
    "gn:dem":172,
    "gn:feature_class":"P",
    "gn:feature_code":"PPL",
    "gn:name":"Wola Pniewska",
    "gn:population":0,
    "gn:timezone":"Europe/Warsaw",
    "iso:country":"PL",
    "name:und_x_variant":[
        "Pniewska Wola",
        "Wola Pniewska"
    ],
    "wof:name":"Wola Pniewska",
    "wof:placetype":"locality"
},
  "geometry": {"coordinates":[20.75889,51.92183],"type":"Point"}
}