{
  "type": "Feature",
  "properties": {
    "gn:admin1_code":"78.0",
    "gn:admin2_code":"1406.0",
    "gn:admin3_code":"140609.0",
    "gn:asciiname":"Wola Pniewska",
    "gn:country_code":"PL",
    "gn:dem":172,
    "gn:feature_class":"P",
    "gn:feature_code":"PPL",
    "gn:name":"Wola Pniewska",
    "gn:population":0,
    "gn:timezone":"Europe/Warsaw",
    "iso:country":"PL",
    "name:fra_x_preferred":[
        "Wola Pniewska"
    ],
    "name:pol_x_preferred":[
        "Wola Pniewska"
    ],
    "name:ukr_x_preferred":[
        "\u0412\u043e\u043b\u044f-\u041f\u043d\u0435\u0432\u0441\u044c\u043a\u0430"
    ],
    "name:und_x_variant":[
        "Pniewska Wola"
    ],
    "wof:name":"Wola Pniewska",
    "wof:placetype":"locality"
},
  "geometry": {"coordinates":[20.75889,51.92183],"type":"Point"}
}