{
  "type": "Feature",
  "properties": {
    "gn:admin1_code":"82.0",
    "gn:admin2_code":"2204.0",
    "gn:admin3_code":"220406.0",
    "gn:asciiname":"Ulkowy",
    "gn:country_code":"PL",
    "gn:dem":62,
    "gn:feature_class":"P",
    "gn:feature_code":"PPL",
    "gn:name":"Ulkowy",
    "gn:population":0,
    "gn:timezone":"Europe/Warsaw",
    "iso:country":"PL",
    "name:ceb_x_preferred":[
        "Ulkowy"
    ],
    "name:pol_x_preferred":[
        "Ulkowy"
    ],
    "name:ukr_x_preferred":[
        "\u0423\u043b\u044c\u043a\u043e\u0432\u0438"
    ],
    "name:und_x_variant":[
        "Uhlkau"
    ],
    "wof:name":"Ulkowy",
    "wof:placetype":"locality"
},
  "geometry": {"coordinates":[18.63639,54.17781],"type":"Point"}
}