{
  "type": "Feature",
  "properties": {
    "gn:admin1_code":"78.0",
    "gn:admin2_code":"1403.0",
    "gn:admin3_code":"140308.0",
    "gn:asciiname":"Ryczyska",
    "gn:country_code":"PL",
    "gn:dem":178,
    "gn:feature_class":"P",
    "gn:feature_code":"PPL",
    "gn:name":"Ryczyska",
    "gn:population":0,
    "gn:timezone":"Europe/Warsaw",
    "iso:country":"PL",
    "name:fra_x_preferred":[
        "Ryczyska"
    ],
    "name:pol_x_preferred":[
        "Ryczyska"
    ],
    "name:spa_x_preferred":[
        "Ryczyska"
    ],
    "name:ukr_x_preferred":[
        "\u0420\u0438\u0447\u0438\u0441\u044c\u043a\u0430"
    ],
    "wof:name":"Ryczyska",
    "wof:placetype":"locality"
},
  "geometry": {"coordinates":[21.8367,51.86356],"type":"Point"}
}