{
  "type": "Feature",
  "properties": {
    "gn:admin1_code":"81.0",
    "gn:admin2_code":"2007.0",
    "gn:admin3_code":"200708.0",
    "gn:asciiname":"Sierbuczyn",
    "gn:country_code":"PL",
    "gn:dem":123,
    "gn:feature_class":"P",
    "gn:feature_code":"PPL",
    "gn:name":"Sierbuczyn",
    "gn:population":0,
    "gn:timezone":"Europe/Warsaw",
    "iso:country":"PL",
    "name:lit_x_preferred":[
        "Sebur\u010dinas"
    ],
    "name:pol_x_preferred":[
        "Sieburczyn"
    ],
    "name:ukr_x_preferred":[
        "\u0421\u0435\u0431\u0443\u0440\u0447\u0438\u043d"
    ],
    "name:und_x_variant":[
        "Sieburczyn",
        "Sierbuczyn"
    ],
    "wof:name":"Sierbuczyn",
    "wof:placetype":"locality"
},
  "geometry": {"coordinates":[22.4354,53.23976],"type":"Point"}
}