{
  "type": "Feature",
  "properties": {
    "gn:gn_country":"PL",
    "gn:gn_fcode":"PPL",
    "gn:gn_pop":0,
    "iso:country":"PL",
    "qs_pg:aaroncc":"PL",
    "qs_pg:gn_country":"PL",
    "qs_pg:gn_fcode":"PPL",
    "qs_pg:gn_pop":0,
    "qs_pg:name":"Pokrzywnik",
    "qs_pg:name_adm0":"Polska",
    "qs_pg:name_adm1":"Dolnosl\u0105skie",
    "qs_pg:photos":46,
    "qs_pg:photos_1k":9,
    "qs_pg:photos_9k":1,
    "qs_pg:photos_9r":2,
    "qs_pg:photos_all":46,
    "qs_pg:photos_sr":2,
    "qs_pg:pop_sr":0,
    "qs_pg:qs_pg_placetype":"locality",
    "qs_pg:qs_pg_placetype_gp":"Town",
    "qs_pg:woe_adm0":23424923,
    "woe:adm0_id":23424923,
    "woe:name_adm0":"Polska",
    "woe:name_adm1":"Dolnosl\u0105skie",
    "woe:placetype":"Town",
    "wof:name":"Pokrzywnik",
    "wof:placetype":"locality"
},
  "geometry": {"coordinates":[15.62428,50.96621],"type":"Point"}
}