{
  "type": "Feature",
  "properties": {
    "gn:admin1_code":"85.0",
    "gn:admin2_code":"2817.0",
    "gn:admin3_code":"281706.0",
    "gn:asciiname":"Waly",
    "gn:country_code":"PL",
    "gn:dem":137,
    "gn:feature_class":"P",
    "gn:feature_code":"PPL",
    "gn:name":"Wa\u0142y",
    "gn:population":0,
    "gn:timezone":"Europe/Warsaw",
    "iso:country":"PL",
    "name:cat_x_preferred":[
        "Waly"
    ],
    "name:ceb_x_preferred":[
        "Waly"
    ],
    "name:che_x_preferred":[
        "\u0412\u0430\u043b\u0438"
    ],
    "name:deu_x_preferred":[
        "Waly"
    ],
    "name:eus_x_preferred":[
        "Waly"
    ],
    "name:fra_x_preferred":[
        "Waly"
    ],
    "name:hun_x_preferred":[
        "Waly"
    ],
    "name:ita_x_preferred":[
        "Waly"
    ],
    "name:kaz_x_preferred":[
        "\u0412\u0430\u043b\u0438"
    ],
    "name:lat_x_preferred":[
        "Waly"
    ],
    "name:ltz_x_preferred":[
        "Waly"
    ],
    "name:msa_x_preferred":[
        "Waly"
    ],
    "name:nld_x_preferred":[
        "Waly"
    ],
    "name:oci_x_preferred":[
        "Waly"
    ],
    "name:pol_x_preferred":[
        "Waly"
    ],
    "name:ron_x_preferred":[
        "Waly"
    ],
    "name:slk_x_preferred":[
        "Waly"
    ],
    "name:spa_x_preferred":[
        "Waly"
    ],
    "name:swe_x_preferred":[
        "Waly"
    ],
    "name:ukr_x_preferred":[
        "\u0412\u0430\u043b\u0456"
    ],
    "name:und_x_variant":[
        "Wallen",
        "Wa\u0142y"
    ],
    "name:uzb_x_preferred":[
        "Waly"
    ],
    "name:vie_x_preferred":[
        "Waly"
    ],
    "name:vol_x_preferred":[
        "Waly"
    ],
    "name:war_x_preferred":[
        "Waly"
    ],
    "name:zho_x_preferred":[
        "\u74e6\u5229"
    ],
    "wof:name":"Waly",
    "wof:placetype":"locality"
},
  "geometry": {"coordinates":[21.13227,53.50569],"type":"Point"}
}