{
  "type": "Feature",
  "properties": {
    "gn:admin1_code":"77.0",
    "gn:admin2_code":"1210.0",
    "gn:admin3_code":"121002.0",
    "gn:asciiname":"Dabrowa",
    "gn:country_code":"PL",
    "gn:dem":289,
    "gn:feature_class":"P",
    "gn:feature_code":"PPL",
    "gn:name":"D\u0105browa",
    "gn:population":0,
    "gn:timezone":"Europe/Warsaw",
    "iso:country":"PL",
    "wof:name":"Dabrowa",
    "wof:placetype":"locality"
},
  "geometry": {"coordinates":[20.67901,49.67981],"type":"Point"}
}