{
  "type": "Feature",
  "properties": {
    "gn:admin1_code":"73.0",
    "gn:asciiname":"Wladyslawowo",
    "gn:country_code":"PL",
    "gn:dem":101,
    "gn:feature_class":"P",
    "gn:feature_code":"PPL",
    "gn:name":"W\u0142adys\u0142awowo",
    "gn:population":0,
    "gn:timezone":"Europe/Warsaw",
    "iso:country":"PL",
    "wof:name":"Wladyslawowo",
    "wof:placetype":"locality"
},
  "geometry": {"coordinates":[18.60102,52.46181],"type":"Point"}
}