{
  "type": "Feature",
  "properties": {
    "gn:admin1_code":"75.0",
    "gn:admin2_code":"620.0",
    "gn:admin3_code":"62003.0",
    "gn:asciiname":"Sniatycze",
    "gn:country_code":"PL",
    "gn:dem":216,
    "gn:feature_class":"P",
    "gn:feature_code":"PPL",
    "gn:name":"\u015aniatycze",
    "gn:population":0,
    "gn:timezone":"Europe/Warsaw",
    "iso:country":"PL",
    "name:fra_x_preferred":[
        "\u015aniatycze"
    ],
    "name:pol_x_preferred":[
        "\u015aniatycze"
    ],
    "name:ukr_x_preferred":[
        "\u0421\u043d\u044f\u0442\u0438\u0447\u0456"
    ],
    "wof:name":"Sniatycze",
    "wof:placetype":"locality"
},
  "geometry": {"coordinates":[23.51316,50.65557],"type":"Point"}
}