{
  "type": "Feature",
  "properties": {
    "gn:admin1_code":"78.0",
    "gn:admin2_code":"1413.0",
    "gn:admin3_code":"141308.0",
    "gn:asciiname":"Mlodynin Wielki",
    "gn:country_code":"PL",
    "gn:dem":143,
    "gn:feature_class":"P",
    "gn:feature_code":"PPL",
    "gn:name":"M\u0142odynin Wielki",
    "gn:population":0,
    "gn:timezone":"Europe/Warsaw",
    "iso:country":"PL",
    "wof:name":"Mlodynin Wielki",
    "wof:placetype":"locality"
},
  "geometry": {"coordinates":[20.48333,53.05],"type":"Point"}
}