{
  "type": "Feature",
  "properties": {
    "gn:admin1_code":"87.0",
    "gn:admin2_code":"3206.0",
    "gn:admin3_code":"320604.0",
    "gn:asciiname":"Radziszewo",
    "gn:country_code":"PL",
    "gn:dem":23,
    "gn:feature_class":"P",
    "gn:feature_code":"PPL",
    "gn:name":"Radziszewo",
    "gn:population":0,
    "gn:timezone":"Europe/Warsaw",
    "iso:country":"PL",
    "name:und_x_variant":[
        "Retzowsfelde",
        "Radziszewo"
    ],
    "wof:name":"Radziszewo",
    "wof:placetype":"locality"
},
  "geometry": {"coordinates":[14.5423,53.32357],"type":"Point"}
}