{
  "type": "Feature",
  "properties": {
    "gn:admin1_code":"87.0",
    "gn:admin2_code":"3206.0",
    "gn:admin3_code":"320604.0",
    "gn:asciiname":"Radziszewo",
    "gn:country_code":"PL",
    "gn:dem":23,
    "gn:feature_class":"P",
    "gn:feature_code":"PPL",
    "gn:name":"Radziszewo",
    "gn:population":0,
    "gn:timezone":"Europe/Warsaw",
    "iso:country":"PL",
    "name:ceb_x_preferred":[
        "Radziszewo"
    ],
    "name:nld_x_preferred":[
        "Radziszewo"
    ],
    "name:pol_x_preferred":[
        "Radziszewo"
    ],
    "name:ukr_x_preferred":[
        "\u0420\u0430\u0434\u0437\u0456\u0448\u0435\u0432\u043e"
    ],
    "name:und_x_variant":[
        "Retzowsfelde"
    ],
    "name:vie_x_preferred":[
        "Radziszewo"
    ],
    "wof:name":"Radziszewo",
    "wof:placetype":"locality"
},
  "geometry": {"coordinates":[14.5423,53.32357],"type":"Point"}
}