{
  "type": "Feature",
  "properties": {
    "gn:admin1_code":"74.0",
    "gn:admin2_code":"1011.0",
    "gn:admin3_code":"101105.0",
    "gn:asciiname":"Wierzbowa",
    "gn:country_code":"PL",
    "gn:dem":108,
    "gn:feature_class":"P",
    "gn:feature_code":"PPL",
    "gn:name":"Wierzbowa",
    "gn:population":0,
    "gn:timezone":"Europe/Warsaw",
    "iso:country":"PL",
    "name:ceb_x_preferred":[
        "\u0412\u0435\u0440\u0431\u043e\u0432\u0430\u044f"
    ],
    "name:fra_x_preferred":[
        "Wierzbowa"
    ],
    "name:jpn_x_preferred":[
        "\u30f4\u30a7\u30eb\u30dc\u30fc\u30f4\u30a1"
    ],
    "name:pol_x_preferred":[
        "Wierzbowa"
    ],
    "name:rus_x_preferred":[
        "\u0412\u0435\u0440\u0431\u043e\u0432\u0430\u044f"
    ],
    "name:spa_x_preferred":[
        "Wierzbowa"
    ],
    "name:ukr_x_preferred":[
        "\u0412\u0435\u0436\u0431\u043e\u0432\u0430"
    ],
    "wof:name":"Wierzbowa",
    "wof:placetype":"locality"
},
  "geometry": {"coordinates":[19.08108,51.98333],"type":"Point"}
}