{
  "type": "Feature",
  "properties": {
    "gn:admin1_code":"75.0",
    "gn:admin2_code":"609.0",
    "gn:admin3_code":"60909.0",
    "gn:asciiname":"Bozy Dar",
    "gn:country_code":"PL",
    "gn:dem":271,
    "gn:feature_class":"P",
    "gn:feature_code":"PPL",
    "gn:name":"Bo\u017cy Dar",
    "gn:population":0,
    "gn:timezone":"Europe/Warsaw",
    "iso:country":"PL",
    "name:fra_x_preferred":[
        "Bo\u017cy Dar"
    ],
    "name:pol_x_preferred":[
        "Bo\u017cy Dar"
    ],
    "name:ukr_x_preferred":[
        "\u0411\u043e\u0436\u0438-\u0414\u0430\u0440"
    ],
    "name:und_x_variant":[
        "Bo\u017cy Day"
    ],
    "wof:name":"Bozy Dar",
    "wof:placetype":"locality"
},
  "geometry": {"coordinates":[22.6574,51.01165],"type":"Point"}
}