{
  "type": "Feature",
  "properties": {
    "gn:admin1_code":"73.0",
    "gn:admin2_code":"418.0",
    "gn:admin3_code":"41810.0",
    "gn:asciiname":"Ustronie",
    "gn:country_code":"PL",
    "gn:dem":85,
    "gn:feature_class":"P",
    "gn:feature_code":"PPL",
    "gn:name":"Ustronie",
    "gn:population":0,
    "gn:timezone":"Europe/Warsaw",
    "iso:country":"PL",
    "name:pol_x_preferred":[
        "Ustronie"
    ],
    "name:ukr_x_preferred":[
        "\u0423\u0441\u0442\u0440\u043e\u043d\u0435"
    ],
    "wof:name":"Ustronie",
    "wof:placetype":"locality"
},
  "geometry": {"coordinates":[18.89013,52.71581],"type":"Point"}
}