{
  "type": "Feature",
  "properties": {
    "gn:admin1_code":"72.0",
    "gn:admin2_code":"208.0",
    "gn:admin3_code":"20809.0",
    "gn:asciiname":"Kulin",
    "gn:country_code":"PL",
    "gn:dem":637,
    "gn:feature_class":"P",
    "gn:feature_code":"PPL",
    "gn:name":"Kulin",
    "gn:population":0,
    "gn:timezone":"Europe/Warsaw",
    "iso:country":"PL",
    "name:pol_x_preferred":[
        "Kulin K\u0142odzki"
    ],
    "wof:name":"Kulin",
    "wof:placetype":"locality"
},
  "geometry": {"coordinates":[16.32955,50.42006],"type":"Point"}
}