{
  "type": "Feature",
  "properties": {
    "gn:admin1_code":"72.0",
    "gn:admin2_code":"208.0",
    "gn:admin3_code":"20809.0",
    "gn:asciiname":"Kulin",
    "gn:country_code":"PL",
    "gn:dem":637,
    "gn:feature_class":"P",
    "gn:feature_code":"PPL",
    "gn:name":"Kulin",
    "gn:population":0,
    "gn:timezone":"Europe/Warsaw",
    "iso:country":"PL",
    "name:azb_x_preferred":[
        "\u06a9\u0648\u0644\u06cc\u0646 \u06a9\u0648\u0648\u0632\u06a9\u06cc"
    ],
    "name:deu_x_preferred":[
        "Kulin K\u0142odzki"
    ],
    "name:fas_x_preferred":[
        "\u06a9\u0648\u0644\u06cc\u0646 \u06a9\u0648\u0648\u0632\u06a9\u06cc"
    ],
    "name:pol_x_preferred":[
        "Kulin K\u0142odzki"
    ],
    "name:ukr_x_preferred":[
        "\u041a\u0443\u043b\u0456\u043d-\u041a\u043b\u043e\u0434\u0437\u044c\u043a\u0438\u0439"
    ],
    "wof:name":"Kulin",
    "wof:placetype":"locality"
},
  "geometry": {"coordinates":[16.32955,50.42006],"type":"Point"}
}