{
  "type": "Feature",
  "properties": {
    "gn:population":1012,
    "iso:country":"PL",
    "name:bel_x_preferred":[
        "\u0413\u043c\u0456\u043d\u0430 \u0420\u0430\u0434\u043e\u043c\u0456\u043d"
    ],
    "name:eng_x_preferred":[
        "Radomin"
    ],
    "name:fra_x_preferred":[
        "Radomin"
    ],
    "name:ita_x_preferred":[
        "Radomin"
    ],
    "name:nld_x_preferred":[
        "Radomin"
    ],
    "name:pol_x_preferred":[
        "Radomin"
    ],
    "name:por_x_preferred":[
        "Comuna de Radomin"
    ],
    "name:ron_x_preferred":[
        "Comuna Radomin"
    ],
    "name:rus_x_preferred":[
        "\u0420\u0430\u0434\u043e\u043c\u0438\u043d"
    ],
    "name:slk_x_preferred":[
        "Gmina Radomin"
    ],
    "name:ukr_x_preferred":[
        "\u0490\u043c\u0456\u043d\u0430 \u0420\u0430\u0434\u043e\u043c\u0456\u043d"
    ],
    "name:war_x_preferred":[
        "Gmina Radomin"
    ],
    "name:zho_min_nan_x_preferred":[
        "Radomin"
    ],
    "qs:a0":"Rzeczpospolita Polska",
    "qs:a1":"*Kujawsko-pomorskie",
    "qs:a1r":"0",
    "qs:a2":"Golubsko-dobrzynski",
    "qs:adm0":"Rzeczpospolita Polska",
    "qs:la_lc":"*",
    "qs:level":"locality",
    "qs:loc":"Radomin",
    "qs:loc_alt":"Radomin",
    "qs:pop":0,
    "qs:type":"buffered point",
    "wd:wordcount":115,
    "wof:name":"Radomin",
    "wof:placetype":"locality",
    "wof:population":1012
},
  "geometry": {"coordinates":[19.194666,53.086666],"type":"Point"}
}