{
  "type": "Feature",
  "properties": {
    "gn:admin1_code":"72.0",
    "gn:admin2_code":"218.0",
    "gn:admin3_code":"21803.0",
    "gn:asciiname":"Zorawiniec",
    "gn:country_code":"PL",
    "gn:dem":135,
    "gn:feature_class":"P",
    "gn:feature_code":"PPL",
    "gn:name":"\u017b\u00f3rawiniec",
    "gn:population":0,
    "gn:timezone":"Europe/Warsaw",
    "iso:country":"PL",
    "wof:name":"Zorawiniec",
    "wof:placetype":"locality"
},
  "geometry": {"coordinates":[16.8187,51.17515],"type":"Point"}
}