{
  "type": "Feature",
  "properties": {
    "gn:admin1_code":"81.0",
    "gn:admin2_code":"2007.0",
    "gn:admin3_code":"200701.0",
    "gn:asciiname":"Karwowo",
    "gn:country_code":"PL",
    "gn:dem":155,
    "gn:feature_class":"P",
    "gn:feature_code":"PPL",
    "gn:name":"Karwowo",
    "gn:population":0,
    "gn:timezone":"Europe/Warsaw",
    "iso:country":"PL",
    "name:fra_x_preferred":[
        "Karwowo"
    ],
    "name:lit_x_preferred":[
        "Karvovas"
    ],
    "name:pol_x_preferred":[
        "Karwowo"
    ],
    "name:ukr_x_preferred":[
        "\u041a\u0430\u0440\u0432\u043e\u0432\u043e"
    ],
    "wof:name":"Karwowo",
    "wof:placetype":"locality"
},
  "geometry": {"coordinates":[22.32268,53.32811],"type":"Point"}
}