{
  "type": "Feature",
  "properties": {
    "gn:admin1_code":"75.0",
    "gn:admin2_code":"611.0",
    "gn:admin3_code":"61104.0",
    "gn:asciiname":"Huta Dabrowa",
    "gn:country_code":"PL",
    "gn:dem":189,
    "gn:feature_class":"P",
    "gn:feature_code":"PPL",
    "gn:name":"Huta D\u0105browa",
    "gn:population":0,
    "gn:timezone":"Europe/Warsaw",
    "iso:country":"PL",
    "name:azb_x_preferred":[
        "\u062e\u0648\u062a\u0627 \u062f\u0627\u0646\u0628\u0631\u0648\u0648\u0627"
    ],
    "name:ceb_x_preferred":[
        "Huta D\u0105browa"
    ],
    "name:fas_x_preferred":[
        "\u062e\u0648\u062a\u0627 \u062f\u0627\u0646\u0628\u0631\u0648\u0648\u0627"
    ],
    "name:fra_x_preferred":[
        "Huta-D\u0105browa"
    ],
    "name:nld_x_preferred":[
        "Huta-D\u0105browa"
    ],
    "name:pol_x_preferred":[
        "Huta-D\u0105browa"
    ],
    "name:szl_x_preferred":[
        "Huta-D\u016fmbrowa"
    ],
    "name:ukr_x_preferred":[
        "\u0413\u0443\u0442\u0430-\u0414\u043e\u043c\u0431\u0440\u043e\u0432\u0430"
    ],
    "wof:name":"Huta Dabrowa",
    "wof:placetype":"locality"
},
  "geometry": {"coordinates":[22.04712,51.80739000000001],"type":"Point"}
}