{
  "type": "Feature",
  "properties": {
    "gn:admin1_code":"75.0",
    "gn:admin2_code":"611.0",
    "gn:admin3_code":"61104.0",
    "gn:asciiname":"Huta Dabrowa",
    "gn:country_code":"PL",
    "gn:dem":189,
    "gn:feature_class":"P",
    "gn:feature_code":"PPL",
    "gn:name":"Huta D\u0105browa",
    "gn:population":0,
    "gn:timezone":"Europe/Warsaw",
    "iso:country":"PL",
    "name:und_x_variant":[
        "Huta D\u0105browa"
    ],
    "wof:name":"Huta Dabrowa",
    "wof:placetype":"locality"
},
  "geometry": {"coordinates":[22.04712,51.80739000000001],"type":"Point"}
}