{
  "type": "Feature",
  "properties": {
    "gn:country":"PL",
    "gn:fcode":"PPLA3",
    "gn:population":5263,
    "iso:country":"PL",
    "name:ceb_x_preferred":[
        "Wyrzysk"
    ],
    "name:ces_x_preferred":[
        "Wyrzysk"
    ],
    "name:csb_x_preferred":[
        "W\u00ebrz\u00ebsk\u00f2"
    ],
    "name:deu_x_preferred":[
        "Wyrzysk"
    ],
    "name:epo_x_preferred":[
        "Wyrzysk"
    ],
    "name:fra_x_preferred":[
        "Wyrzysk"
    ],
    "name:hrv_x_preferred":[
        "Wyrzysk"
    ],
    "name:hun_x_preferred":[
        "Wyrzysk"
    ],
    "name:ind_x_preferred":[
        "Wyrzysk"
    ],
    "name:ita_x_preferred":[
        "Wyrzysk"
    ],
    "name:jav_x_preferred":[
        "Wyrzysk"
    ],
    "name:lav_x_preferred":[
        "Vi\u017eiska"
    ],
    "name:lit_x_preferred":[
        "Vi\u017eiskas"
    ],
    "name:msa_x_preferred":[
        "Wyrzysk"
    ],
    "name:nld_x_preferred":[
        "Wyrzysk"
    ],
    "name:pol_x_preferred":[
        "Wyrzysk"
    ],
    "name:por_x_preferred":[
        "Wyrzysk"
    ],
    "name:ron_x_preferred":[
        "Wyrzysk"
    ],
    "name:rus_x_preferred":[
        "\u0412\u044b\u0436\u0438\u0441\u043a"
    ],
    "name:slk_x_preferred":[
        "Wyrzysk"
    ],
    "name:srp_x_preferred":[
        "\u0412\u0438\u0436\u0438\u0441\u043a"
    ],
    "name:swe_x_preferred":[
        "Wyrzysk"
    ],
    "name:ukr_x_preferred":[
        "\u0412\u0438\u0436\u0438\u0441\u044c\u043a"
    ],
    "name:und_x_variant":[
        "Wirsitz"
    ],
    "name:vie_x_preferred":[
        "Wyrzysk"
    ],
    "name:zho_x_preferred":[
        "\u7dad\u65e5\u65af\u514b"
    ],
    "qs_pg:aaroncc":"PL",
    "qs_pg:gn_country":"PL",
    "qs_pg:gn_fcode":"PPLA3",
    "qs_pg:gn_pop":5263,
    "qs_pg:name":"Wyrzysk",
    "qs_pg:name_adm0":"Polska",
    "qs_pg:name_adm1":"Wielkopolskie",
    "qs_pg:photos_9r":0,
    "qs_pg:photos_sr":0,
    "qs_pg:pop_sr":5,
    "qs_pg:qs_pg_placetype":"localadmin",
    "qs_pg:qs_pg_placetype_gp":"LocalAdmin",
    "qs_pg:woe_adm0":23424923,
    "woe:adm0_id":23424923,
    "woe:name_adm0":"Polska",
    "woe:name_adm1":"Wielkopolskie",
    "woe:placetype":"LocalAdmin",
    "wof:name":"Wyrzysk",
    "wof:placetype":"localadmin",
    "wof:population":5263
},
  "geometry": {"coordinates":[17.26802,53.153],"type":"Point"}
}