{
  "type": "Feature",
  "properties": {
    "iso:country":"PL",
    "name:eng_x_preferred":[
        "City Park Pozna\u0144"
    ],
    "name:pol_x_preferred":[
        "City Park Poznan"
    ],
    "wof:name":"City Park Pozna\u0144",
    "wof:placetype":"neighbourhood"
},
  "geometry": {"coordinates":[16.89414636763315,52.40025353633354],"type":"Point"}
}