{
  "type": "Feature",
  "properties": {
    "gn:admin1_code":"78.0",
    "gn:admin2_code":"1410.0",
    "gn:admin3_code":"141002.0",
    "gn:asciiname":"Czuchleby",
    "gn:country_code":"PL",
    "gn:dem":148,
    "gn:feature_class":"P",
    "gn:feature_code":"PPL",
    "gn:name":"Czuchleby",
    "gn:population":0,
    "gn:timezone":"Europe/Warsaw",
    "iso:country":"PL",
    "name:azb_x_preferred":[
        "\u0686\u0648\u062e\u0644\u0628\u0647"
    ],
    "name:ceb_x_preferred":[
        "Czuchleby"
    ],
    "name:fas_x_preferred":[
        "\u0686\u0648\u062e\u0644\u0628\u0647"
    ],
    "name:fra_x_preferred":[
        "Czuchleby"
    ],
    "name:lit_x_preferred":[
        "\u010cuchlebai"
    ],
    "name:pol_x_preferred":[
        "Czuchleby"
    ],
    "name:ukr_x_preferred":[
        "\u0427\u0443\u0445\u043b\u0435\u0431\u0438"
    ],
    "wof:name":"Czuchleby",
    "wof:placetype":"locality"
},
  "geometry": {"coordinates":[22.79499,52.23906],"type":"Point"}
}