{
  "type": "Feature",
  "properties": {
    "iso:country":"PL",
    "name:pol_x_preferred":[
        "Batorz"
    ],
    "wof:name":"Batorz",
    "wof:placetype":"locality"
},
  "geometry": {"coordinates":[22.4788001278693,50.8556785006487],"type":"Point"}
}