{
  "type": "Feature",
  "properties": {
    "iso:country":"PL",
    "name:azb_x_preferred":[
        "\u0628\u0627\u062a\u0648\u0698"
    ],
    "name:ceb_x_preferred":[
        "Batorz"
    ],
    "name:fas_x_preferred":[
        "\u0628\u0627\u062a\u0648\u0698"
    ],
    "name:fra_x_preferred":[
        "Batorz"
    ],
    "name:nld_x_preferred":[
        "Batorz"
    ],
    "name:pol_x_preferred":[
        "Batorz"
    ],
    "name:ukr_x_preferred":[
        "\u0411\u0430\u0442\u043e\u0436"
    ],
    "wof:coterminous":[
        1125399469
    ],
    "wof:name":"Batorz",
    "wof:placetype":"locality"
},
  "geometry": {"coordinates":[22.4788001278693,50.8556785006487],"type":"Point"}
}