{
  "type": "Feature",
  "properties": {
    "gn:admin1_code":"85.0",
    "gn:admin2_code":"2804.0",
    "gn:admin3_code":"280406.0",
    "gn:asciiname":"Stare Monasterzysko",
    "gn:country_code":"PL",
    "gn:dem":77,
    "gn:feature_class":"P",
    "gn:feature_code":"PPL",
    "gn:name":"Stare Monasterzysko",
    "gn:population":0,
    "gn:timezone":"Europe/Warsaw",
    "iso:country":"PL",
    "name:pol_x_preferred":[
        "Stare Monasterzysko"
    ],
    "name:ukr_x_preferred":[
        "\u0421\u0442\u0430\u0440\u0435 \u041c\u043e\u043d\u0430\u0441\u0442\u0435\u0436\u0438\u0441\u044c\u043a\u043e"
    ],
    "name:und_x_variant":[
        "Alt M\u00fcnsterberg",
        "Stare Monasterzyska"
    ],
    "wof:name":"Stare Monasterzysko",
    "wof:placetype":"locality"
},
  "geometry": {"coordinates":[19.65429,54.21552],"type":"Point"}
}