{
  "type": "Feature",
  "properties": {
    "gn:country":"PL",
    "gn:fcode":"PPL",
    "gn:population":1100,
    "iso:country":"PL",
    "name:ast_x_preferred":[
        "Lublewo Gda\u0144skie"
    ],
    "name:azb_x_preferred":[
        "\u0644\u0648\u0628\u0644\u0648\u0648 \u0642\u062f\u0627\u0646\u0642\u0633\u06a9\u06cc\u0647"
    ],
    "name:ceb_x_preferred":[
        "Lublewo Gda\u0144skie"
    ],
    "name:ces_x_preferred":[
        "Lublewo Gda\u0144skie"
    ],
    "name:che_x_preferred":[
        "\u041b\u044e\u0431\u043b\u0435\u0432\u043e-\u0413\u0434\u0430\u043d\u0441\u043a\u0435"
    ],
    "name:csb_x_preferred":[
        "L\u00ebblew\u00f2"
    ],
    "name:deu_x_preferred":[
        "L\u00f6blau"
    ],
    "name:eng_x_preferred":[
        "Lublewo"
    ],
    "name:eng_x_variant":[
        "Lublewo Gda\u0144skie"
    ],
    "name:fas_x_preferred":[
        "\u0644\u0648\u0628\u0644\u0648\u0648 \u06af\u062f\u0627\u0646\u06af\u0633\u06a9\u06cc\u0647"
    ],
    "name:fra_x_preferred":[
        "Lublewo Gda\u0144skie"
    ],
    "name:nan_x_preferred":[
        "Lublewo Gda\u0144skie"
    ],
    "name:nld_x_preferred":[
        "Lublewo Gda\u0144skie"
    ],
    "name:pol_x_preferred":[
        "Lublewo Gda\u0144skie"
    ],
    "name:rus_x_preferred":[
        "\u041b\u044e\u0431\u043b\u0435\u0432\u043e"
    ],
    "name:tat_x_preferred":[
        "\u041b\u044e\u0431\u043b\u0435\u0432\u043e-\u0413\u0434\u0430\u043d\u0441\u043a\u0435"
    ],
    "name:ukr_x_preferred":[
        "\u041b\u044e\u0431\u043b\u0435\u0432\u043e-\u0490\u0434\u0430\u043d\u0441\u044c\u043a\u0435"
    ],
    "name:und_x_variant":[
        "L\u00f6blau"
    ],
    "qs_pg:aaroncc":"PL",
    "qs_pg:gn_country":"PL",
    "qs_pg:gn_fcode":"PPL",
    "qs_pg:gn_pop":1100,
    "qs_pg:name":"Lublewo Gda\u0144skie",
    "qs_pg:name_adm0":"Polska",
    "qs_pg:name_adm1":"Pomorskie",
    "qs_pg:photos_9k":1,
    "qs_pg:photos_9r":1,
    "qs_pg:photos_all":1,
    "qs_pg:photos_sr":0,
    "qs_pg:pop_sr":3,
    "qs_pg:qs_pg_placetype":"locality",
    "qs_pg:qs_pg_placetype_gp":"Town",
    "qs_pg:woe_adm0":23424923,
    "woe:adm0_id":23424923,
    "woe:name_adm0":"Polska",
    "woe:name_adm1":"Pomorskie",
    "woe:placetype":"Town",
    "wof:name":"Lublewo Gda\u0144skie",
    "wof:placetype":"locality",
    "wof:population":1100
},
  "geometry": {"coordinates":[18.50389,54.28457],"type":"Point"}
}