{
  "type": "Feature",
  "properties": {
    "gn:admin1_code":"77.0",
    "gn:admin2_code":"1216.0",
    "gn:admin3_code":"121614.0",
    "gn:asciiname":"Dzierzaniny",
    "gn:country_code":"PL",
    "gn:dem":411,
    "gn:feature_class":"P",
    "gn:feature_code":"PPL",
    "gn:name":"Dzier\u017caniny",
    "gn:population":0,
    "gn:timezone":"Europe/Warsaw",
    "iso:country":"PL",
    "name:pol_x_preferred":[
        "Dzier\u017caniny"
    ],
    "name:ukr_x_preferred":[
        "\u0414\u0437\u0435\u0440\u0436\u0430\u043d\u0456\u043d\u0438"
    ],
    "name:und_x_variant":[
        "Dzier\u017caniny"
    ],
    "wof:name":"Dzierzaniny",
    "wof:placetype":"locality"
},
  "geometry": {"coordinates":[20.75935,49.79662],"type":"Point"}
}