{
  "type": "Feature",
  "properties": {
    "gn:admin1_code":"84.0",
    "gn:admin2_code":"2609.0",
    "gn:admin3_code":"260905.0",
    "gn:asciiname":"Skwirzowa",
    "gn:country_code":"PL",
    "gn:dem":179,
    "gn:feature_class":"P",
    "gn:feature_code":"PPL",
    "gn:name":"Skwirzowa",
    "gn:population":0,
    "gn:timezone":"Europe/Warsaw",
    "iso:country":"PL",
    "name:pol_x_preferred":[
        "Skwirzowa"
    ],
    "name:ukr_x_preferred":[
        "\u0421\u043a\u0432\u0456\u0436\u043e\u0432\u0430"
    ],
    "wof:name":"Skwirzowa",
    "wof:placetype":"locality"
},
  "geometry": {"coordinates":[21.48685,50.59261],"type":"Point"}
}