{
  "type": "Feature",
  "properties": {
    "iso:country":"PL",
    "name:deu_x_preferred":[
        "Gumie\u0144ce"
    ],
    "name:eng_x_preferred":[
        "Gumie\u0144ce"
    ],
    "name:epo_x_preferred":[
        "Gumie\u0144ce"
    ],
    "name:ger_x_preferred":[
        "Gumie\u0144ce"
    ],
    "name:pol_x_colloquial":[
        "Gumience",
        "Szczecin Gumience"
    ],
    "name:pol_x_preferred":[
        "Gumiece",
        "Gumie\u0144ce"
    ],
    "name:pol_x_variant":[
        "Scheune",
        "Stettin Scheune",
        "Szczecin Gumiece"
    ],
    "name:unk_x_variant":[
        "Szczecin Gumie\u0144ce",
        "Gumiece"
    ],
    "qs:gn_adm0_cc":"PL",
    "qs:gn_fcode":"PPLX",
    "qs:gn_local":3083829,
    "qs:gn_nam_loc":"Szczecin, Szczecin, Zachodniopomorskie, PL",
    "qs:gn_namadm1":"87",
    "qs:gn_name":"Gumie\u0144ce",
    "qs:local_max":2463,
    "qs:local_sum":5955,
    "qs:localhoods":11,
    "qs:name":"Gumiece",
    "qs:name_adm0":"Polska",
    "qs:name_adm1":"Zachodniopomorskie",
    "qs:name_adm2":"Szczecin",
    "qs:name_lau":"Szczecin",
    "qs:name_local":"Szczecin",
    "qs:photo_max":119,
    "qs:photo_sum":602,
    "qs:placetype":"Suburb",
    "qs:quad_count":52,
    "qs:woe_adm0":23424923,
    "qs:woe_adm1":12577950,
    "qs:woe_adm2":12591505,
    "qs:woe_lau":12618080,
    "qs:woe_local":521598,
    "qs:woe_ver":"7.10.0",
    "wd:wordcount":86,
    "wof:lang":[
        "pol"
    ],
    "wof:name":"Gumiece",
    "wof:placetype":"neighbourhood"
},
  "geometry": {"coordinates":[14.500866,53.436799],"type":"Point"}
}