{
  "type": "Feature",
  "properties": {
    "gn:admin1_code":"74.0",
    "gn:admin2_code":"1001.0",
    "gn:admin3_code":"100102.0",
    "gn:asciiname":"Janina",
    "gn:country_code":"PL",
    "gn:dem":224,
    "gn:feature_class":"P",
    "gn:feature_code":"PPL",
    "gn:name":"Janina",
    "gn:population":0,
    "gn:timezone":"Europe/Warsaw",
    "iso:country":"PL",
    "name:fra_x_preferred":[
        "Janina"
    ],
    "name:pol_x_preferred":[
        "Janina"
    ],
    "name:ukr_x_preferred":[
        "\u042f\u043d\u0456\u043d\u0430"
    ],
    "name:und_x_variant":[
        "Kolonia Janina"
    ],
    "name:urd_x_preferred":[
        "\u062c\u0627\u0646\u0646\u0627"
    ],
    "wof:name":"Janina",
    "wof:placetype":"locality"
},
  "geometry": {"coordinates":[19.47043,51.35361],"type":"Point"}
}