{
  "type": "Feature",
  "properties": {
    "gn:gn_country":"PL",
    "gn:gn_fcode":"PPL",
    "gn:gn_pop":0,
    "iso:country":"PL",
    "name:ast_x_preferred":[
        "Bosut\u00f3w"
    ],
    "name:azb_x_preferred":[
        "\u0628\u0648\u0633\u0648\u062a\u0648\u0648"
    ],
    "name:ceb_x_preferred":[
        "Bosut\u00f3w"
    ],
    "name:eng_x_preferred":[
        "Bosut\u00f3w"
    ],
    "name:fas_x_preferred":[
        "\u0628\u0648\u0633\u0648\u062a\u0648\u0648"
    ],
    "name:fra_x_preferred":[
        "Bosut\u00f3w"
    ],
    "name:nan_x_preferred":[
        "Bosut\u00f3w"
    ],
    "name:nld_x_preferred":[
        "Bosut\u00f3w"
    ],
    "name:pol_x_preferred":[
        "Bosut\u00f3w"
    ],
    "name:rus_x_preferred":[
        "\u0411\u043e\u0441\u0443\u0442\u0443\u0432"
    ],
    "name:ukr_x_preferred":[
        "\u0411\u043e\u0441\u0443\u0442\u0443\u0432"
    ],
    "qs_pg:aaroncc":"PL",
    "qs_pg:gn_country":"PL",
    "qs_pg:gn_fcode":"PPL",
    "qs_pg:gn_pop":0,
    "qs_pg:name":"Bosut\u00f3w",
    "qs_pg:name_adm0":"Polska",
    "qs_pg:name_adm1":"Ma\u0142opolskie",
    "qs_pg:photos_9r":0,
    "qs_pg:photos_sr":0,
    "qs_pg:pop_sr":0,
    "qs_pg:qs_pg_placetype":"locality",
    "qs_pg:qs_pg_placetype_gp":"Town",
    "qs_pg:woe_adm0":23424923,
    "woe:adm0_id":23424923,
    "woe:name_adm0":"Polska",
    "woe:name_adm1":"Ma\u0142opolskie",
    "woe:placetype":"Town",
    "wof:name":"Bosut\u00f3w",
    "wof:placetype":"locality"
},
  "geometry": {"coordinates":[19.99348,50.12475],"type":"Point"}
}