{
  "type": "Feature",
  "properties": {
    "gn:admin1_code":"74.0",
    "gn:admin2_code":"1011.0",
    "gn:admin3_code":"101105.0",
    "gn:asciiname":"Sucha Dolna",
    "gn:country_code":"PL",
    "gn:dem":110,
    "gn:feature_class":"P",
    "gn:feature_code":"PPL",
    "gn:name":"Sucha Dolna",
    "gn:population":0,
    "gn:timezone":"Europe/Warsaw",
    "iso:country":"PL",
    "name:fra_x_preferred":[
        "Sucha Dolna"
    ],
    "name:pol_x_preferred":[
        "Sucha Dolna"
    ],
    "wof:name":"Sucha Dolna",
    "wof:placetype":"locality"
},
  "geometry": {"coordinates":[19.10682000000001,51.98651],"type":"Point"}
}