{
  "type": "Feature",
  "properties": {
    "gn:admin1_code":"82.0",
    "gn:admin2_code":"2206.0",
    "gn:admin3_code":"220607.0",
    "gn:asciiname":"Szumles Krolewski",
    "gn:country_code":"PL",
    "gn:dem":205,
    "gn:feature_class":"P",
    "gn:feature_code":"PPL",
    "gn:name":"Szumles Kr\u00f3lewski",
    "gn:population":0,
    "gn:timezone":"Europe/Warsaw",
    "iso:country":"PL",
    "name:pol_x_preferred":[
        "Szumle\u015b Kr\u00f3lewski"
    ],
    "name:ukr_x_preferred":[
        "\u0428\u0443\u043c\u043b\u0435\u0441\u044c-\u041a\u0440\u0443\u043b\u0435\u0432\u0441\u044c\u043a\u0438\u0439"
    ],
    "name:und_x_variant":[
        "Szumles Kr\u00f3lewski"
    ],
    "wof:name":"Szumles Krolewski",
    "wof:placetype":"locality"
},
  "geometry": {"coordinates":[18.2303,54.15942],"type":"Point"}
}