{
  "type": "Feature",
  "properties": {
    "gn:admin1_code":"79.0",
    "gn:asciiname":"Slawikow",
    "gn:country_code":"PL",
    "gn:dem":236,
    "gn:feature_class":"P",
    "gn:feature_code":"PPL",
    "gn:name":"S\u0142awik\u00f3w",
    "gn:population":0,
    "gn:timezone":"Europe/Warsaw",
    "iso:country":"PL",
    "name:und_x_variant":[
        "Bergkirch",
        "Slawikau",
        "S\u0142awik\u00f3w"
    ],
    "wof:name":"Slawikow",
    "wof:placetype":"locality"
},
  "geometry": {"coordinates":[18.21739,50.18481],"type":"Point"}
}