{
  "type": "Feature",
  "properties": {
    "gn:admin1_code":"79.0",
    "gn:asciiname":"Slawikow",
    "gn:country_code":"PL",
    "gn:dem":236,
    "gn:feature_class":"P",
    "gn:feature_code":"PPL",
    "gn:name":"S\u0142awik\u00f3w",
    "gn:population":0,
    "gn:timezone":"Europe/Warsaw",
    "iso:country":"PL",
    "name:ceb_x_preferred":[
        "S\u0142awik\u00f3w"
    ],
    "name:deu_x_preferred":[
        "S\u0142awik\u00f3w"
    ],
    "name:nld_x_preferred":[
        "S\u0142awik\u00f3w"
    ],
    "name:pol_x_preferred":[
        "S\u0142awik\u00f3w"
    ],
    "name:ukr_x_preferred":[
        "\u0421\u043b\u0430\u0432\u0456\u043a\u0443\u0432"
    ],
    "name:und_x_variant":[
        "Bergkirch",
        "Slawikau"
    ],
    "wof:name":"Slawikow",
    "wof:placetype":"locality"
},
  "geometry": {"coordinates":[18.21739,50.18481],"type":"Point"}
}