{
  "type": "Feature",
  "properties": {
    "gn:population":2090,
    "iso:country":"PL",
    "name:ast_x_preferred":[
        "Filipowice"
    ],
    "name:azb_x_preferred":[
        "\u0641\u06cc\u0644\u06cc\u067e\u0648\u0648\u06cc\u062a\u0633\u0647"
    ],
    "name:ceb_x_preferred":[
        "Filipowice"
    ],
    "name:ces_x_preferred":[
        "Filipowice"
    ],
    "name:diq_x_preferred":[
        "Filipowice"
    ],
    "name:eng_x_preferred":[
        "Filipowice"
    ],
    "name:fas_x_preferred":[
        "\u0641\u06cc\u0644\u06cc\u067e\u0648\u0648\u06cc\u062a\u0633\u0647"
    ],
    "name:fra_x_preferred":[
        "Filipowice"
    ],
    "name:pol_x_preferred":[
        "Filipowice"
    ],
    "name:rus_x_preferred":[
        "\u0424\u0438\u043b\u0438\u043f\u043e\u0432\u0438\u0446\u0435"
    ],
    "name:spa_x_preferred":[
        "Filipowice"
    ],
    "name:ukr_x_preferred":[
        "\u0424\u0456\u043b\u0456\u043f\u043e\u0432\u0456\u0446\u0435"
    ],
    "qs:a0":"Rzeczpospolita Polska",
    "qs:a1":"*Malopolskie",
    "qs:a1r":"0",
    "qs:a2":"Krakowski",
    "qs:adm0":"Rzeczpospolita Polska",
    "qs:la_lc":"*",
    "qs:level":"locality",
    "qs:loc":"Filipowice",
    "qs:loc_alt":"Filipowice",
    "qs:pop":0,
    "qs:type":"buffered point",
    "wd:wordcount":103,
    "wof:name":"Filipowice",
    "wof:placetype":"locality",
    "wof:population":2090
},
  "geometry": {"coordinates":[19.564696,50.154999],"type":"Point"}
}