{
  "type": "Feature",
  "properties": {
    "gn:gn_country":"PL",
    "gn:gn_fcode":"PPL",
    "gn:gn_pop":100,
    "gn:population":100,
    "iso:country":"PL",
    "name:ast_x_preferred":[
        "Tarn\u00f3w"
    ],
    "name:eng_x_preferred":[
        "Tarn\u00f3w"
    ],
    "name:fra_x_preferred":[
        "Tarn\u00f3w"
    ],
    "name:pol_x_preferred":[
        "Tarn\u00f3w"
    ],
    "name:tgl_x_preferred":[
        "Tarn\u00f3w"
    ],
    "name:ukr_x_preferred":[
        "\u0422\u0430\u0440\u043d\u0443\u0432"
    ],
    "qs_pg:aaroncc":"PL",
    "qs_pg:gn_country":"PL",
    "qs_pg:gn_fcode":"PPL",
    "qs_pg:gn_pop":100,
    "qs_pg:name":"Tarn\u00f3w",
    "qs_pg:name_adm0":"Polska",
    "qs_pg:name_adm1":"Mazowieckie",
    "qs_pg:photos_9k":1,
    "qs_pg:photos_9r":1,
    "qs_pg:photos_all":4,
    "qs_pg:photos_sr":0,
    "qs_pg:pop_sr":1,
    "qs_pg:qs_pg_placetype":"locality",
    "qs_pg:qs_pg_placetype_gp":"Town",
    "qs_pg:woe_adm0":23424923,
    "woe:adm0_id":23424923,
    "woe:name_adm0":"Polska",
    "woe:name_adm1":"Mazowieckie",
    "woe:placetype":"Town",
    "wof:name":"Tarn\u00f3w",
    "wof:placetype":"locality",
    "wof:population":100
},
  "geometry": {"coordinates":[21.43888,51.7912],"type":"Point"}
}