{
  "type": "Feature",
  "properties": {
    "gn:admin1_code":"72.0",
    "gn:admin2_code":"221.0",
    "gn:admin3_code":"22102.0",
    "gn:asciiname":"Jedlinka",
    "gn:country_code":"PL",
    "gn:dem":416,
    "gn:feature_class":"P",
    "gn:feature_code":"PPL",
    "gn:name":"Jedlinka",
    "gn:population":0,
    "gn:timezone":"Europe/Warsaw",
    "iso:country":"PL",
    "name:cat_x_preferred":[
        "Jedlinka"
    ],
    "name:ces_x_preferred":[
        "Jedlinka"
    ],
    "name:deu_x_historical":[
        "Tannhausen"
    ],
    "name:deu_x_preferred":[
        "Tannhausen"
    ],
    "name:deu_x_variant":[
        "Jedlinka"
    ],
    "name:epo_x_preferred":[
        "Jedlinka"
    ],
    "name:eus_x_preferred":[
        "Jedlinka"
    ],
    "name:fra_x_preferred":[
        "Jedlinka"
    ],
    "name:hun_x_preferred":[
        "Bor\u00f3k\u00e1s"
    ],
    "name:ita_x_preferred":[
        "Jedlinka"
    ],
    "name:msa_x_preferred":[
        "Jedlinka"
    ],
    "name:nld_x_preferred":[
        "Jedlinka"
    ],
    "name:pol_x_preferred":[
        "Jedlinka"
    ],
    "name:ron_x_preferred":[
        "Jedlinka"
    ],
    "name:rue_x_preferred":[
        "\u042f\u043b\u0438\u043d\u043a\u044b"
    ],
    "name:slk_x_preferred":[
        "Jedlinka"
    ],
    "name:spa_x_preferred":[
        "Jedlinka"
    ],
    "name:srp_x_preferred":[
        "\u0408\u0435\u0434\u043b\u0438\u043d\u043a\u0430"
    ],
    "name:ukr_x_preferred":[
        "\u042f\u043b\u0438\u043d\u043a\u0430"
    ],
    "name:war_x_preferred":[
        "Jedlinka"
    ],
    "wof:name":"Jedlinka",
    "wof:placetype":"neighbourhood"
},
  "geometry": {"coordinates":[16.36212,50.71301],"type":"Point"}
}