{
  "type": "Feature",
  "properties": {
    "gn:gn_country":"PL",
    "gn:gn_fcode":"PPLA3",
    "gn:gn_pop":3507,
    "gn:population":3507,
    "iso:country":"PL",
    "name:azb_x_preferred":[
        "\u067e\u0648\u0631\u0648\u0646\u0642\u0646"
    ],
    "name:ceb_x_preferred":[
        "Poronin"
    ],
    "name:deu_x_preferred":[
        "Poronin"
    ],
    "name:epo_x_preferred":[
        "Poronin"
    ],
    "name:fas_x_preferred":[
        "\u067e\u0648\u0631\u0648\u0646\u06af\u0646"
    ],
    "name:fra_x_preferred":[
        "Poronin"
    ],
    "name:nld_x_preferred":[
        "Poronin"
    ],
    "name:pol_x_preferred":[
        "Poronin"
    ],
    "name:ukr_x_preferred":[
        "\u041f\u043e\u0440\u043e\u043d\u0456\u043d"
    ],
    "qs_pg:aaroncc":"PL",
    "qs_pg:gn_country":"PL",
    "qs_pg:gn_fcode":"PPLA3",
    "qs_pg:gn_pop":3507,
    "qs_pg:name":"Poronin",
    "qs_pg:name_adm0":"Polska",
    "qs_pg:name_adm1":"Ma\u0142opolskie",
    "qs_pg:photos":4,
    "qs_pg:photos_1k":1,
    "qs_pg:photos_9k":2,
    "qs_pg:photos_9r":5,
    "qs_pg:photos_all":418,
    "qs_pg:photos_sr":1,
    "qs_pg:pop_sr":4,
    "qs_pg:qs_pg_placetype":"localadmin",
    "qs_pg:qs_pg_placetype_gp":"LocalAdmin",
    "qs_pg:woe_adm0":23424923,
    "woe:adm0_id":23424923,
    "woe:name_adm0":"Polska",
    "woe:name_adm1":"Ma\u0142opolskie",
    "woe:placetype":"LocalAdmin",
    "wof:name":"Poronin",
    "wof:placetype":"localadmin",
    "wof:population":3507
},
  "geometry": {"coordinates":[20.00291,49.33781],"type":"Point"}
}