{
  "type": "Feature",
  "properties": {
    "gn:admin1_code":"78.0",
    "gn:admin2_code":"1422.0",
    "gn:admin3_code":"142207.0",
    "gn:asciiname":"Karwacz",
    "gn:country_code":"PL",
    "gn:dem":109,
    "gn:feature_class":"P",
    "gn:feature_code":"PPL",
    "gn:name":"Karwacz",
    "gn:population":0,
    "gn:timezone":"Europe/Warsaw",
    "iso:country":"PL",
    "name:azb_x_preferred":[
        "\u06a9\u0627\u0631\u0648\u0627\u0686"
    ],
    "name:fas_x_preferred":[
        "\u06a9\u0627\u0631\u0648\u0627\u0686"
    ],
    "name:fra_x_preferred":[
        "Karwacz"
    ],
    "name:pol_x_preferred":[
        "Karwacz"
    ],
    "name:ukr_x_preferred":[
        "\u041a\u0430\u0440\u0432\u0430\u0447"
    ],
    "wof:name":"Karwacz",
    "wof:placetype":"locality"
},
  "geometry": {"coordinates":[20.95859,53.01156999999999],"type":"Point"}
}