{
  "type": "Feature",
  "properties": {
    "gn:country":"PL",
    "gn:fcode":"PPL",
    "gn:population":0,
    "iso:country":"PL",
    "name:ast_x_preferred":[
        "G\u0142obino"
    ],
    "name:azb_x_preferred":[
        "\u0642\u0648\u0648\u0628\u06cc\u0646\u0648"
    ],
    "name:ceb_x_preferred":[
        "G\u0142obino"
    ],
    "name:ces_x_preferred":[
        "G\u0142obino"
    ],
    "name:che_x_preferred":[
        "\u0413\u043b\u043e\u0431\u0438\u043d\u043e"
    ],
    "name:deu_x_preferred":[
        "G\u0142obino"
    ],
    "name:eng_x_preferred":[
        "G\u0142obino"
    ],
    "name:fas_x_preferred":[
        "\u06af\u0648\u0648\u0628\u06cc\u0646\u0648"
    ],
    "name:fra_x_preferred":[
        "G\u0142obino"
    ],
    "name:nan_x_preferred":[
        "G\u0142obino"
    ],
    "name:nld_x_preferred":[
        "G\u0142obino"
    ],
    "name:pol_x_preferred":[
        "G\u0142obino"
    ],
    "name:tat_x_preferred":[
        "\u0413\u043b\u043e\u0431\u0438\u043d\u043e"
    ],
    "name:ukr_x_preferred":[
        "\u0490\u043b\u043e\u0431\u0456\u043d\u043e"
    ],
    "qs_pg:aaroncc":"PL",
    "qs_pg:gn_country":"PL",
    "qs_pg:gn_fcode":"PPL",
    "qs_pg:gn_pop":0,
    "qs_pg:name":"G\u0142obino",
    "qs_pg:name_adm0":"Polska",
    "qs_pg:name_adm1":"Pomorskie",
    "qs_pg:photos_9r":0,
    "qs_pg:photos_sr":0,
    "qs_pg:pop_sr":0,
    "qs_pg:qs_pg_placetype":"locality",
    "qs_pg:qs_pg_placetype_gp":"Town",
    "qs_pg:woe_adm0":23424923,
    "woe:adm0_id":23424923,
    "woe:name_adm0":"Polska",
    "woe:name_adm1":"Pomorskie",
    "woe:placetype":"Town",
    "wof:name":"G\u0142obino",
    "wof:placetype":"locality"
},
  "geometry": {"coordinates":[17.10448,54.44094],"type":"Point"}
}