{
  "type": "Feature",
  "properties": {
    "gn:admin1_code":"86.0",
    "gn:admin2_code":"3025.0",
    "gn:admin3_code":"302502.0",
    "gn:asciiname":"Murzynowo Lesne",
    "gn:country_code":"PL",
    "gn:dem":69,
    "gn:feature_class":"P",
    "gn:feature_code":"PPL",
    "gn:name":"Murzynowo Le\u015bne",
    "gn:population":0,
    "gn:timezone":"Europe/Warsaw",
    "iso:country":"PL",
    "name:fra_x_preferred":[
        "Murzynowo Le\u015bne"
    ],
    "name:pol_x_preferred":[
        "Murzynowo Le\u015bne"
    ],
    "name:ukr_x_preferred":[
        "\u041c\u0443\u0436\u0438\u043d\u043e\u0432\u043e-\u041b\u0435\u0441\u044c\u043d\u0435"
    ],
    "wof:name":"Murzynowo Lesne",
    "wof:placetype":"locality"
},
  "geometry": {"coordinates":[17.33895,52.15552],"type":"Point"}
}