{
  "type": "Feature",
  "properties": {
    "gn:admin1_code":"78.0",
    "gn:admin2_code":"1435.0",
    "gn:admin3_code":"143502.0",
    "gn:asciiname":"Peczyna Nowa",
    "gn:country_code":"PL",
    "gn:dem":102,
    "gn:feature_class":"P",
    "gn:feature_code":"PPL",
    "gn:name":"Peczyna Nowa",
    "gn:population":0,
    "gn:timezone":"Europe/Warsaw",
    "iso:country":"PL",
    "wof:name":"Peczyna Nowa",
    "wof:placetype":"locality"
},
  "geometry": {"coordinates":[21.64518,52.7697],"type":"Point"}
}