{
  "type": "Feature",
  "properties": {
    "gn:admin1_code":"86.0",
    "gn:admin2_code":"3012.0",
    "gn:admin3_code":"301204.0",
    "gn:asciiname":"Duszna Gorka",
    "gn:country_code":"PL",
    "gn:dem":141,
    "gn:feature_class":"P",
    "gn:feature_code":"PPL",
    "gn:name":"Duszna G\u00f3rka",
    "gn:population":0,
    "gn:timezone":"Europe/Warsaw",
    "iso:country":"PL",
    "name:und_x_variant":[
        "Duszna G\u00f3rka"
    ],
    "wof:name":"Duszna Gorka",
    "wof:placetype":"locality"
},
  "geometry": {"coordinates":[17.57855,51.71129000000001],"type":"Point"}
}