{
  "type": "Feature",
  "properties": {
    "gn:admin1_code":"86.0",
    "gn:admin2_code":"3012.0",
    "gn:admin3_code":"301204.0",
    "gn:asciiname":"Duszna Gorka",
    "gn:country_code":"PL",
    "gn:dem":141,
    "gn:feature_class":"P",
    "gn:feature_code":"PPL",
    "gn:name":"Duszna G\u00f3rka",
    "gn:population":0,
    "gn:timezone":"Europe/Warsaw",
    "iso:country":"PL",
    "name:azb_x_preferred":[
        "\u062f\u0648\u0634\u0646\u0627 \u0642\u0648\u0631\u06a9\u0627"
    ],
    "name:fas_x_preferred":[
        "\u062f\u0648\u0634\u0646\u0627 \u06af\u0648\u0631\u06a9\u0627"
    ],
    "name:fra_x_preferred":[
        "Duszna G\u00f3rka"
    ],
    "name:ita_x_preferred":[
        "Duszna G\u00f3rka"
    ],
    "name:pol_x_preferred":[
        "Duszna G\u00f3rka"
    ],
    "name:ukr_x_preferred":[
        "\u0414\u0443\u0448\u043d\u0430-\u0490\u0443\u0440\u043a\u0430"
    ],
    "wof:name":"Duszna Gorka",
    "wof:placetype":"locality"
},
  "geometry": {"coordinates":[17.57855,51.71129000000001],"type":"Point"}
}