{
  "type": "Feature",
  "properties": {
    "gn:admin1_code":"85.0",
    "gn:admin2_code":"2816.0",
    "gn:admin3_code":"281601.0",
    "gn:asciiname":"Danowo",
    "gn:country_code":"PL",
    "gn:dem":171,
    "gn:feature_class":"P",
    "gn:feature_code":"PPL",
    "gn:name":"Danowo",
    "gn:population":0,
    "gn:timezone":"Europe/Warsaw",
    "iso:country":"PL",
    "name:deu_x_preferred":[
        "Danowo"
    ],
    "name:fra_x_preferred":[
        "Danowo"
    ],
    "name:lit_x_preferred":[
        "Danovas"
    ],
    "name:nld_x_preferred":[
        "Danowo"
    ],
    "name:pol_x_preferred":[
        "Danowo"
    ],
    "name:ukr_x_preferred":[
        "\u0414\u0430\u043d\u043e\u0432\u043e"
    ],
    "name:und_x_variant":[
        "Siegenau",
        "Dannowen"
    ],
    "wof:name":"Danowo",
    "wof:placetype":"locality"
},
  "geometry": {"coordinates":[22.11295,53.58002],"type":"Point"}
}