{
  "type": "Feature",
  "properties": {
    "gn:admin1_code":"72",
    "gn:admin2_code":"0204",
    "gn:admin3_code":"20402.0",
    "gn:asciiname":"Piotrowice Male",
    "gn:country_code":"PL",
    "gn:dem":130,
    "gn:feature_class":"P",
    "gn:feature_code":"PPL",
    "gn:name":"Piotrowice Ma\u0142e",
    "gn:population":0,
    "gn:timezone":"Europe/Warsaw",
    "iso:country":"PL",
    "name:deu_x_historical":[
        "Klein Peterwitz"
    ],
    "name:deu_x_preferred":[
        "Klein Peterwitz"
    ],
    "wof:name":"Piotrowice Male",
    "wof:placetype":"locality"
},
  "geometry": {"coordinates":[16.62553,51.52511],"type":"Point"}
}