{
  "type": "Feature",
  "properties": {
    "gn:admin1_code":"72",
    "gn:admin2_code":"0209",
    "gn:admin3_code":"20905.0",
    "gn:asciiname":"Raczkowa",
    "gn:country_code":"PL",
    "gn:dem":133,
    "gn:feature_class":"P",
    "gn:feature_code":"PPL",
    "gn:name":"Raczkowa",
    "gn:population":0,
    "gn:timezone":"Europe/Warsaw",
    "iso:country":"PL",
    "name:deu_x_historical":[
        "Rosenau"
    ],
    "name:deu_x_preferred":[
        "Rosenau"
    ],
    "name:pol_x_preferred":[
        "Raczkowa"
    ],
    "name:ukr_x_preferred":[
        "\u0420\u0430\u0447\u043a\u043e\u0432\u0430"
    ],
    "wof:name":"Raczkowa",
    "wof:placetype":"locality"
},
  "geometry": {"coordinates":[16.20114,51.14048],"type":"Point"}
}