{
  "type": "Feature",
  "properties": {
    "gn:admin1_code":"72.0",
    "gn:admin2_code":"214.0",
    "gn:admin3_code":"21406.0",
    "gn:asciiname":"Smolna",
    "gn:country_code":"PL",
    "gn:dem":150,
    "gn:feature_class":"P",
    "gn:feature_code":"PPL",
    "gn:name":"Smolna",
    "gn:population":0,
    "gn:timezone":"Europe/Warsaw",
    "iso:country":"PL",
    "wof:name":"Smolna",
    "wof:placetype":"locality"
},
  "geometry": {"coordinates":[17.43273,51.15685],"type":"Point"}
}