{
  "type": "Feature",
  "properties": {
    "gn:admin1_code":"72.0",
    "gn:admin2_code":"201.0",
    "gn:admin3_code":"20102.0",
    "gn:asciiname":"Ludowice",
    "gn:country_code":"PL",
    "gn:dem":172,
    "gn:feature_class":"P",
    "gn:feature_code":"PPL",
    "gn:name":"Ludowice",
    "gn:population":0,
    "gn:timezone":"Europe/Warsaw",
    "iso:country":"PL",
    "name:pol_x_preferred":[
        "Ludowice"
    ],
    "name:ukr_x_preferred":[
        "\u041b\u044e\u0434\u043e\u0432\u0456\u0446\u0435"
    ],
    "wof:name":"Ludowice",
    "wof:placetype":"locality"
},
  "geometry": {"coordinates":[15.56667,51.38333],"type":"Point"}
}