{
  "type": "Feature",
  "properties": {
    "gn:admin1_code":"87.0",
    "gn:admin2_code":"3204.0",
    "gn:admin3_code":"320406.0",
    "gn:asciiname":"Trzebianowo",
    "gn:country_code":"PL",
    "gn:dem":4,
    "gn:feature_class":"P",
    "gn:feature_code":"PPL",
    "gn:name":"Trzebianowo",
    "gn:population":0,
    "gn:timezone":"Europe/Warsaw",
    "iso:country":"PL",
    "name:azb_x_preferred":[
        "\u0686\u0628\u0644\u06cc\u0627\u0646\u0648"
    ],
    "name:deu_x_preferred":[
        "Trzebianowo"
    ],
    "name:fas_x_preferred":[
        "\u0686\u0628\u0644\u06cc\u0627\u0646\u0648"
    ],
    "name:pol_x_preferred":[
        "Trzebianowo"
    ],
    "name:vie_x_preferred":[
        "Trzebianowo"
    ],
    "wof:name":"Trzebianowo",
    "wof:placetype":"locality"
},
  "geometry": {"coordinates":[14.72936,53.8061],"type":"Point"}
}