{
  "type": "Feature",
  "properties": {
    "gn:admin1_code":"81.0",
    "gn:admin2_code":"2012.0",
    "gn:admin3_code":"201202.0",
    "gn:asciiname":"Szafranki",
    "gn:country_code":"PL",
    "gn:dem":173,
    "gn:feature_class":"P",
    "gn:feature_code":"PPL",
    "gn:name":"Szafranki",
    "gn:population":0,
    "gn:timezone":"Europe/Warsaw",
    "iso:country":"PL",
    "name:fra_x_preferred":[
        "Szafranki"
    ],
    "name:lit_x_preferred":[
        "\u0160afrankai"
    ],
    "name:pol_x_preferred":[
        "Szafranki"
    ],
    "name:ukr_x_preferred":[
        "\u0428\u0430\u0444\u0440\u0430\u043d\u043a\u0456"
    ],
    "wof:name":"Szafranki",
    "wof:placetype":"locality"
},
  "geometry": {"coordinates":[22.6298,54.14861],"type":"Point"}
}