{
  "type": "Feature",
  "properties": {
    "gn:admin1_code":"78.0",
    "gn:admin2_code":"1418.0",
    "gn:admin3_code":"141805.0",
    "gn:asciiname":"Los",
    "gn:country_code":"PL",
    "gn:dem":122,
    "gn:feature_class":"P",
    "gn:feature_code":"PPL",
    "gn:name":"\u0141o\u015b",
    "gn:population":0,
    "gn:timezone":"Europe/Warsaw",
    "iso:country":"PL",
    "name:azb_x_preferred":[
        "\u0648\u0648\u0634"
    ],
    "name:ceb_x_preferred":[
        "\u0141o\u015b"
    ],
    "name:fas_x_preferred":[
        "\u0648\u0648\u0634"
    ],
    "name:fra_x_preferred":[
        "\u0141o\u015b"
    ],
    "name:nld_x_preferred":[
        "\u0141o\u015b"
    ],
    "name:pol_x_preferred":[
        "\u0141o\u015b"
    ],
    "name:tgl_x_preferred":[
        "\u0141o\u015b"
    ],
    "name:ukr_x_preferred":[
        "\u041b\u043e\u0441\u044c"
    ],
    "wof:name":"Los",
    "wof:placetype":"locality"
},
  "geometry": {"coordinates":[20.94916,51.98201],"type":"Point"}
}