{
  "type": "Feature",
  "properties": {
    "gn:admin1_code":"81.0",
    "gn:admin2_code":"2002.0",
    "gn:admin3_code":"200201.0",
    "gn:asciiname":"Dzikie",
    "gn:country_code":"PL",
    "gn:dem":113,
    "gn:feature_class":"P",
    "gn:feature_code":"PPL",
    "gn:name":"Dzikie",
    "gn:population":0,
    "gn:timezone":"Europe/Warsaw",
    "iso:country":"PL",
    "name:azb_x_preferred":[
        "\u062c\u06a9\u06cc\u0647"
    ],
    "name:ceb_x_preferred":[
        "Dzikie"
    ],
    "name:fas_x_preferred":[
        "\u062c\u06a9\u06cc\u0647"
    ],
    "name:fra_x_preferred":[
        "Dzikie"
    ],
    "name:lit_x_preferred":[
        "Dzikiai"
    ],
    "name:nld_x_preferred":[
        "Dzikie"
    ],
    "name:pol_x_preferred":[
        "Dzikie"
    ],
    "name:ukr_x_preferred":[
        "\u0414\u0437\u0456\u043a\u0435"
    ],
    "name:und_x_variant":[
        "Dziki"
    ],
    "wof:name":"Dzikie",
    "wof:placetype":"locality"
},
  "geometry": {"coordinates":[23.00836,53.17811],"type":"Point"}
}