{
  "type": "Feature",
  "properties": {
    "gn:gn_country":"PL",
    "gn:gn_fcode":"PPLA3",
    "gn:gn_pop":2370,
    "gn:population":2370,
    "iso:country":"PL",
    "name:deu_x_preferred":[
        "Schloppe"
    ],
    "name:lav_x_preferred":[
        "\u010clopa"
    ],
    "name:rus_x_preferred":[
        "\u0427\u043b\u043e\u043f\u0430"
    ],
    "name:srp_x_preferred":[
        "\u0427\u043b\u043e\u043f\u0430"
    ],
    "name:ukr_x_preferred":[
        "\u0427\u043b\u043e\u043f\u0430"
    ],
    "name:zho_x_preferred":[
        "\u5947\u6c83\u5e15"
    ],
    "qs_pg:aaroncc":"PL",
    "qs_pg:gn_country":"PL",
    "qs_pg:gn_fcode":"PPLA3",
    "qs_pg:gn_pop":2370,
    "qs_pg:name":"Cz\u0142opa",
    "qs_pg:name_adm0":"Polska",
    "qs_pg:name_adm1":"Zachodniopomorskie",
    "qs_pg:photos":4,
    "qs_pg:photos_1k":1,
    "qs_pg:photos_9k":1,
    "qs_pg:photos_9r":1,
    "qs_pg:photos_all":4,
    "qs_pg:photos_sr":1,
    "qs_pg:pop_sr":6,
    "qs_pg:qs_pg_placetype":"localadmin",
    "qs_pg:qs_pg_placetype_gp":"LocalAdmin",
    "qs_pg:woe_adm0":23424923,
    "woe:adm0_id":23424923,
    "woe:name_adm0":"Polska",
    "woe:name_adm1":"Zachodniopomorskie",
    "woe:placetype":"LocalAdmin",
    "wof:name":"Cz\u0142opa",
    "wof:placetype":"localadmin",
    "wof:population":2370
},
  "geometry": {"coordinates":[16.12098,53.08856],"type":"Point"}
}