{
  "type": "Feature",
  "properties": {
    "gn:country":"PL",
    "gn:fcode":"PPL",
    "gn:population":130,
    "iso:country":"PL",
    "name:ast_x_preferred":[
        "Kamienica-Wygoda"
    ],
    "name:ceb_x_preferred":[
        "Kamienica-Wygoda"
    ],
    "name:eng_x_preferred":[
        "Kamienica-Wygoda"
    ],
    "name:fra_x_preferred":[
        "Kamienica-Wygoda"
    ],
    "name:nan_x_preferred":[
        "Kamienica-Wygoda"
    ],
    "name:nld_x_preferred":[
        "Kamienica-Wygoda"
    ],
    "name:pol_x_preferred":[
        "Kamienica-Wygoda"
    ],
    "name:ukr_x_preferred":[
        "\u041a\u0430\u043c\u0435\u043d\u0438\u0446\u044f-\u0412\u0438\u0491\u043e\u0434\u0430"
    ],
    "qs_pg:aaroncc":"PL",
    "qs_pg:gn_country":"PL",
    "qs_pg:gn_fcode":"PPL",
    "qs_pg:gn_pop":130,
    "qs_pg:name":"Kamienica-Wygoda",
    "qs_pg:name_adm0":"Polska",
    "qs_pg:name_adm1":"Mazowieckie",
    "qs_pg:photos_9k":1,
    "qs_pg:photos_9r":1,
    "qs_pg:photos_all":8,
    "qs_pg:photos_sr":0,
    "qs_pg:pop_sr":1,
    "qs_pg:qs_pg_placetype":"locality",
    "qs_pg:qs_pg_placetype_gp":"Town",
    "qs_pg:woe_adm0":23424923,
    "woe:adm0_id":23424923,
    "woe:name_adm0":"Polska",
    "woe:name_adm1":"Mazowieckie",
    "woe:placetype":"Town",
    "wof:name":"Kamienica-Wygoda",
    "wof:placetype":"locality",
    "wof:population":130
},
  "geometry": {"coordinates":[20.48573,52.44994],"type":"Point"}
}