{
  "type": "Feature",
  "properties": {
    "gn:admin1_code":"78.0",
    "gn:admin2_code":"1429.0",
    "gn:admin3_code":"142905.0",
    "gn:asciiname":"Tosie",
    "gn:country_code":"PL",
    "gn:dem":113,
    "gn:feature_class":"P",
    "gn:feature_code":"PPL",
    "gn:name":"Tosie",
    "gn:population":0,
    "gn:timezone":"Europe/Warsaw",
    "iso:country":"PL",
    "name:fra_x_preferred":[
        "Tosie"
    ],
    "name:lit_x_preferred":[
        "Tosiai"
    ],
    "name:pol_x_preferred":[
        "Tosie"
    ],
    "name:szl_x_preferred":[
        "To\u015be"
    ],
    "name:ukr_x_preferred":[
        "\u0422\u043e\u0441\u0435"
    ],
    "wof:name":"Tosie",
    "wof:placetype":"locality"
},
  "geometry": {"coordinates":[22.14184,52.62134],"type":"Point"}
}