{
  "type": "Feature",
  "properties": {
    "gn:admin1_code":"75.0",
    "gn:admin2_code":"612.0",
    "gn:admin3_code":"61201.0",
    "gn:asciiname":"Trzciniec",
    "gn:country_code":"PL",
    "gn:dem":221,
    "gn:feature_class":"P",
    "gn:feature_code":"PPL",
    "gn:name":"Trzciniec",
    "gn:population":0,
    "gn:timezone":"Europe/Warsaw",
    "iso:country":"PL",
    "wof:name":"Trzciniec",
    "wof:placetype":"locality"
},
  "geometry": {"coordinates":[22.18553,51.12915],"type":"Point"}
}