{
  "type": "Feature",
  "properties": {
    "gn:admin1_code":"74.0",
    "gn:admin2_code":"1012.0",
    "gn:admin3_code":"101207.0",
    "gn:asciiname":"Wola Malowana",
    "gn:country_code":"PL",
    "gn:dem":252,
    "gn:feature_class":"P",
    "gn:feature_code":"PPL",
    "gn:name":"Wola Malowana",
    "gn:population":0,
    "gn:timezone":"Europe/Warsaw",
    "iso:country":"PL",
    "wof:name":"Wola Malowana",
    "wof:placetype":"locality"
},
  "geometry": {"coordinates":[19.62867,51.06367],"type":"Point"}
}