{
  "type": "Feature",
  "properties": {
    "gn:admin1_code":"81.0",
    "gn:admin2_code":"2002.0",
    "gn:admin3_code":"200204.0",
    "gn:asciiname":"Luzany",
    "gn:country_code":"PL",
    "gn:dem":160,
    "gn:feature_class":"P",
    "gn:feature_code":"PPL",
    "gn:name":"\u0141u\u017cany",
    "gn:population":0,
    "gn:timezone":"Europe/Warsaw",
    "iso:country":"PL",
    "name:azb_x_preferred":[
        "\u0648\u0648\u0698\u0627\u0646\u0647"
    ],
    "name:bel_x_preferred":[
        "\u041b\u0443\u0436\u0430\u043d\u044b"
    ],
    "name:fas_x_preferred":[
        "\u0648\u0648\u0698\u0627\u0646\u0647"
    ],
    "name:fra_x_preferred":[
        "\u0141u\u017cany"
    ],
    "name:lit_x_preferred":[
        "Lu\u017eanai"
    ],
    "name:pol_x_preferred":[
        "\u0141u\u017cany"
    ],
    "name:ukr_x_preferred":[
        "\u041b\u0443\u0436\u0430\u043d\u0438"
    ],
    "wof:name":"Luzany",
    "wof:placetype":"locality"
},
  "geometry": {"coordinates":[23.83875,53.14538],"type":"Point"}
}