{
  "type": "Feature",
  "properties": {
    "gn:admin1_code":"82.0",
    "gn:admin2_code":"2204.0",
    "gn:admin3_code":"220403.0",
    "gn:asciiname":"Pregowo Dolne",
    "gn:country_code":"PL",
    "gn:dem":84,
    "gn:feature_class":"P",
    "gn:feature_code":"PPL",
    "gn:name":"Pr\u0119gowo Dolne",
    "gn:population":0,
    "gn:timezone":"Europe/Warsaw",
    "iso:country":"PL",
    "wof:name":"Pregowo Dolne",
    "wof:placetype":"locality"
},
  "geometry": {"coordinates":[18.47986,54.2565],"type":"Point"}
}