{
  "type": "Feature",
  "properties": {
    "gn:admin1_code":"85.0",
    "gn:admin2_code":"2811.0",
    "gn:admin3_code":"281104.0",
    "gn:asciiname":"Brzezno Lynskie",
    "gn:country_code":"PL",
    "gn:dem":130,
    "gn:feature_class":"P",
    "gn:feature_code":"PPL",
    "gn:name":"Brze\u017ano \u0141y\u0144skie",
    "gn:population":0,
    "gn:timezone":"Europe/Warsaw",
    "iso:country":"PL",
    "name:azb_x_preferred":[
        "\u0628\u0698\u0698\u0646\u0648 \u0648\u0646\u0642\u0633\u06a9\u06cc\u0647"
    ],
    "name:deu_x_preferred":[
        "Brze\u017ano \u0141y\u0144skie"
    ],
    "name:fas_x_preferred":[
        "\u0628\u0698\u0698\u0646\u0648 \u0648\u0646\u06af\u0633\u06a9\u06cc\u0647"
    ],
    "name:fra_x_preferred":[
        "Brze\u017cno \u0141y\u0144skie"
    ],
    "name:nld_x_preferred":[
        "Brze\u017ano \u0141y\u0144skie"
    ],
    "name:pol_x_preferred":[
        "Brze\u017ano \u0141y\u0144skie"
    ],
    "name:ukr_x_preferred":[
        "\u0411\u0436\u0435\u0437\u044c\u043d\u043e-\u041b\u0438\u043d\u0441\u044c\u043a\u0435"
    ],
    "name:und_x_variant":[
        "Persing",
        "Bre\u017ano \u0141y\u0144skie",
        "Brze\u017ano \u0141y\u0144skie"
    ],
    "wof:name":"Brzezno Lynskie",
    "wof:placetype":"locality"
},
  "geometry": {"coordinates":[20.48262,53.50931],"type":"Point"}
}