{
  "type": "Feature",
  "properties": {
    "gn:admin1_code":"77.0",
    "gn:admin2_code":"1212.0",
    "gn:admin3_code":"121201.0",
    "gn:asciiname":"Starczynow",
    "gn:country_code":"PL",
    "gn:dem":317,
    "gn:feature_class":"P",
    "gn:feature_code":"PPL",
    "gn:name":"Starczyn\u00f3w",
    "gn:population":0,
    "gn:timezone":"Europe/Warsaw",
    "iso:country":"PL",
    "wof:name":"Starczynow",
    "wof:placetype":"locality"
},
  "geometry": {"coordinates":[19.48507,50.26767],"type":"Point"}
}