{
  "type": "Feature",
  "properties": {
    "gn:admin1_code":"81.0",
    "gn:admin2_code":"2002.0",
    "gn:admin3_code":"200201.0",
    "gn:asciiname":"Gajowniki",
    "gn:country_code":"PL",
    "gn:dem":125,
    "gn:feature_class":"P",
    "gn:feature_code":"PPL",
    "gn:name":"Gajowniki",
    "gn:population":0,
    "gn:timezone":"Europe/Warsaw",
    "iso:country":"PL",
    "name:azb_x_preferred":[
        "\u0642\u0627\u06cc\u0648\u0648\u0646\u0642\u06a9\u06cc"
    ],
    "name:fas_x_preferred":[
        "\u06af\u0627\u06cc\u0648\u0648\u0646\u06af\u06a9\u06cc"
    ],
    "name:fra_x_preferred":[
        "Gajowniki"
    ],
    "name:lit_x_preferred":[
        "Gajovnikai"
    ],
    "name:pol_x_preferred":[
        "Gajowniki"
    ],
    "name:szl_x_preferred":[
        "Gajow\u0144iki"
    ],
    "name:ukr_x_preferred":[
        "\u0490\u0430\u0439\u043e\u0432\u043d\u0438\u043a\u0438"
    ],
    "wof:name":"Gajowniki",
    "wof:placetype":"locality"
},
  "geometry": {"coordinates":[22.97303,53.10004],"type":"Point"}
}