{
  "type": "Feature",
  "properties": {
    "gn:admin1_code":"81.0",
    "gn:admin2_code":"2002.0",
    "gn:admin3_code":"200201.0",
    "gn:asciiname":"Gajowniki",
    "gn:country_code":"PL",
    "gn:dem":125,
    "gn:feature_class":"P",
    "gn:feature_code":"PPL",
    "gn:name":"Gajowniki",
    "gn:population":0,
    "gn:timezone":"Europe/Warsaw",
    "iso:country":"PL",
    "wof:name":"Gajowniki",
    "wof:placetype":"locality"
},
  "geometry": {"coordinates":[22.97303,53.10004],"type":"Point"}
}