{
  "type": "Feature",
  "properties": {
    "gn:admin1_code":"78.0",
    "gn:admin2_code":"1430.0",
    "gn:admin3_code":"143004.0",
    "gn:asciiname":"Sniadkow Las",
    "gn:country_code":"PL",
    "gn:dem":187,
    "gn:feature_class":"P",
    "gn:feature_code":"PPL",
    "gn:name":"\u015aniadk\u00f3w Las",
    "gn:population":0,
    "gn:timezone":"Europe/Warsaw",
    "iso:country":"PL",
    "wof:name":"Sniadkow Las",
    "wof:placetype":"locality"
},
  "geometry": {"coordinates":[20.98916,51.28249],"type":"Point"}
}