{
  "type": "Feature",
  "properties": {
    "gn:admin1_code":"73.0",
    "gn:admin2_code":"407.0",
    "gn:admin3_code":"40701.0",
    "gn:asciiname":"Szymborze",
    "gn:country_code":"PL",
    "gn:dem":90,
    "gn:feature_class":"P",
    "gn:feature_code":"PPL",
    "gn:name":"Szymborze",
    "gn:population":0,
    "gn:timezone":"Europe/Warsaw",
    "iso:country":"PL",
    "wof:name":"Szymborze",
    "wof:placetype":"neighbourhood"
},
  "geometry": {"coordinates":[18.27438,52.77056999999999],"type":"Point"}
}