{
  "type": "Feature",
  "properties": {
    "gn:admin1_code":"73.0",
    "gn:admin2_code":"406.0",
    "gn:admin3_code":"40601.0",
    "gn:asciiname":"Parsk",
    "gn:country_code":"PL",
    "gn:dem":29,
    "gn:feature_class":"P",
    "gn:feature_code":"PPL",
    "gn:name":"Parsk",
    "gn:population":0,
    "gn:timezone":"Europe/Warsaw",
    "iso:country":"PL",
    "wof:name":"Parsk",
    "wof:placetype":"locality"
},
  "geometry": {"coordinates":[18.77088,53.5328],"type":"Point"}
}