{
  "type": "Feature",
  "properties": {
    "gn:admin1_code":"83.0",
    "gn:admin2_code":"2472.0",
    "gn:admin3_code":"247201.0",
    "gn:asciiname":"Kochlowice",
    "gn:country_code":"PL",
    "gn:dem":273,
    "gn:feature_class":"P",
    "gn:feature_code":"PPL",
    "gn:name":"Koch\u0142owice",
    "gn:population":0,
    "gn:timezone":"Europe/Warsaw",
    "iso:country":"PL",
    "wof:name":"Kochlowice",
    "wof:placetype":"locality"
},
  "geometry": {"coordinates":[18.91138,50.25568],"type":"Point"}
}