{
  "type": "Feature",
  "properties": {
    "gn:admin1_code":"74.0",
    "gn:admin2_code":"1017.0",
    "gn:admin3_code":"101702.0",
    "gn:asciiname":"Platon",
    "gn:country_code":"PL",
    "gn:dem":176,
    "gn:feature_class":"P",
    "gn:feature_code":"PPL",
    "gn:name":"Platon",
    "gn:population":0,
    "gn:timezone":"Europe/Warsaw",
    "iso:country":"PL",
    "name:pol_x_preferred":[
        "Plato\u0144"
    ],
    "name:ukr_x_preferred":[
        "\u041f\u043b\u044f\u0442\u043e\u043d\u044c"
    ],
    "wof:name":"Platon",
    "wof:placetype":"locality"
},
  "geometry": {"coordinates":[18.49465,51.28849],"type":"Point"}
}