{
  "type": "Feature",
  "properties": {
    "gn:admin1_code":"86.0",
    "gn:admin2_code":"3002.0",
    "gn:admin3_code":"300208.0",
    "gn:asciiname":"Kuzniczka",
    "gn:country_code":"PL",
    "gn:dem":59,
    "gn:feature_class":"P",
    "gn:feature_code":"PPL",
    "gn:name":"Ku\u017aniczka",
    "gn:population":0,
    "gn:timezone":"Europe/Warsaw",
    "iso:country":"PL",
    "name:fra_x_preferred":[
        "Ku\u017aniczka"
    ],
    "name:pol_x_preferred":[
        "Ku\u017aniczka"
    ],
    "name:ukr_x_preferred":[
        "\u041a\u0443\u0437\u043d\u0456\u0447\u043a\u0430"
    ],
    "wof:name":"Kuzniczka",
    "wof:placetype":"locality"
},
  "geometry": {"coordinates":[16.23007999999999,52.95126],"type":"Point"}
}