{
  "type": "Feature",
  "properties": {
    "gn:gn_country":"PL",
    "gn:gn_fcode":"PPLA3",
    "gn:gn_pop":2850,
    "gn:population":2850,
    "iso:country":"PL",
    "name:heb_x_preferred":[
        "\u05e7\u05d0\u05de\u05d9\u05d9\u05e0\u05e1\u05e7"
    ],
    "name:lav_x_preferred":[
        "Kame\u0146ska"
    ],
    "name:rus_x_preferred":[
        "\u041a\u0430\u043c\u0435\u043d\u044c\u0441\u043a"
    ],
    "name:srp_x_preferred":[
        "\u041a\u0430\u043c\u0458\u0435\u045a\u0441\u043a"
    ],
    "name:ukr_x_preferred":[
        "\u041a\u0430\u043c\u0435\u043d\u0441\u044c\u043a"
    ],
    "name:zho_x_preferred":[
        "\u5361\u7dec\u65af\u514b"
    ],
    "qs_pg:aaroncc":"PL",
    "qs_pg:gn_country":"PL",
    "qs_pg:gn_fcode":"PPLA3",
    "qs_pg:gn_pop":2850,
    "qs_pg:name":"Kamie\u0144sk",
    "qs_pg:name_adm0":"Polska",
    "qs_pg:name_adm1":"\u0141\u00f3dzkie",
    "qs_pg:photos":1,
    "qs_pg:photos_1k":1,
    "qs_pg:photos_9k":1,
    "qs_pg:photos_9r":1,
    "qs_pg:photos_all":1,
    "qs_pg:photos_sr":1,
    "qs_pg:pop_sr":6,
    "qs_pg:qs_pg_placetype":"localadmin",
    "qs_pg:qs_pg_placetype_gp":"LocalAdmin",
    "qs_pg:woe_adm0":23424923,
    "woe:adm0_id":23424923,
    "woe:name_adm0":"Polska",
    "woe:name_adm1":"\u0141\u00f3dzkie",
    "woe:placetype":"LocalAdmin",
    "wof:name":"Kamie\u0144sk",
    "wof:placetype":"localadmin",
    "wof:population":2850
},
  "geometry": {"coordinates":[19.49661,51.20242],"type":"Point"}
}