{
  "type": "Feature",
  "properties": {
    "gn:admin1_code":"84.0",
    "gn:admin2_code":"2601.0",
    "gn:admin3_code":"260101.0",
    "gn:asciiname":"Las Winiarski",
    "gn:country_code":"PL",
    "gn:dem":256,
    "gn:feature_class":"P",
    "gn:feature_code":"PPL",
    "gn:name":"Las Winiarski",
    "gn:population":0,
    "gn:timezone":"Europe/Warsaw",
    "iso:country":"PL",
    "name:pol_x_preferred":[
        "Las Winiarski"
    ],
    "name:ukr_x_preferred":[
        "\u041b\u044f\u0441-\u0412\u0456\u043d\u044f\u0440\u0441\u044c\u043a\u0438\u0439"
    ],
    "wof:name":"Las Winiarski",
    "wof:placetype":"locality"
},
  "geometry": {"coordinates":[20.65305,50.48752],"type":"Point"}
}