{
  "type": "Feature",
  "properties": {
    "gn:admin1_code":"73.0",
    "gn:admin2_code":"410.0",
    "gn:admin3_code":"41001.0",
    "gn:asciiname":"Kazmierzewo",
    "gn:country_code":"PL",
    "gn:dem":98,
    "gn:feature_class":"P",
    "gn:feature_code":"PPL",
    "gn:name":"Ka\u017amierzewo",
    "gn:population":0,
    "gn:timezone":"Europe/Warsaw",
    "iso:country":"PL",
    "name:pol_x_preferred":[
        "Kazimierzewo"
    ],
    "name:ukr_x_preferred":[
        "\u041a\u0430\u0437\u0456\u043c\u0435\u0436\u0435\u0432\u043e"
    ],
    "name:und_x_variant":[
        "Kazimierzewo",
        "Ka\u017amierzewo"
    ],
    "wof:name":"Kazmierzewo",
    "wof:placetype":"locality"
},
  "geometry": {"coordinates":[17.42619,53.0382],"type":"Point"}
}