{
  "type": "Feature",
  "properties": {
    "gn:admin1_code":"84.0",
    "gn:asciiname":"Parcela I",
    "gn:country_code":"PL",
    "gn:dem":322,
    "gn:elevation":"325.0",
    "gn:feature_class":"P",
    "gn:feature_code":"PPL",
    "gn:name":"Parcela I",
    "gn:population":0,
    "gn:timezone":"Europe/Warsaw",
    "iso:country":"PL",
    "wof:name":"Parcela I",
    "wof:placetype":"locality"
},
  "geometry": {"coordinates":[20.03001,50.32886],"type":"Point"}
}