{
  "type": "Feature",
  "properties": {
    "gn:admin1_code":"84.0",
    "gn:admin2_code":"2611.0",
    "gn:admin3_code":"261102.0",
    "gn:asciiname":"Bor Kunowski",
    "gn:country_code":"PL",
    "gn:dem":227,
    "gn:feature_class":"P",
    "gn:feature_code":"PPL",
    "gn:name":"B\u00f3r Kunowski",
    "gn:population":0,
    "gn:timezone":"Europe/Warsaw",
    "iso:country":"PL",
    "name:ceb_x_preferred":[
        "B\u00f3r Kunowski"
    ],
    "name:nld_x_preferred":[
        "B\u00f3r Kunowski"
    ],
    "name:pol_x_preferred":[
        "B\u00f3r Kunowski"
    ],
    "name:ukr_x_preferred":[
        "\u0411\u0443\u0440-\u041a\u0443\u043d\u043e\u0432\u0441\u044c\u043a\u0438\u0439"
    ],
    "wof:name":"Bor Kunowski",
    "wof:placetype":"locality"
},
  "geometry": {"coordinates":[21.27277,51.02105],"type":"Point"}
}