{
  "type": "Feature",
  "properties": {
    "gn:admin1_code":"77.0",
    "gn:admin2_code":"1216.0",
    "gn:admin3_code":"121611.0",
    "gn:asciiname":"Bobrowniki Male",
    "gn:country_code":"PL",
    "gn:dem":185,
    "gn:feature_class":"P",
    "gn:feature_code":"PPL",
    "gn:name":"Bobrowniki Ma\u0142e",
    "gn:population":0,
    "gn:timezone":"Europe/Warsaw",
    "iso:country":"PL",
    "name:ceb_x_preferred":[
        "Bobrowniki Ma\u0142e"
    ],
    "name:nld_x_preferred":[
        "Bobrowniki Ma\u0142e"
    ],
    "name:pol_x_preferred":[
        "Bobrowniki Ma\u0142e"
    ],
    "name:rus_x_preferred":[
        "\u0411\u043e\u0431\u0440\u043e\u0432\u043d\u0438\u043a\u0438-\u041c\u0430\u043b\u0435"
    ],
    "name:ukr_x_preferred":[
        "\u0411\u043e\u0431\u0440\u043e\u0432\u043d\u0438\u043a\u0438-\u041c\u0430\u043b\u0456"
    ],
    "wof:name":"Bobrowniki Male",
    "wof:placetype":"locality"
},
  "geometry": {"coordinates":[20.88673,50.05907],"type":"Point"}
}