{
  "type": "Feature",
  "properties": {
    "gn:admin1_code":"85.0",
    "gn:admin2_code":"2817.0",
    "gn:admin3_code":"281705.0",
    "gn:asciiname":"Spaliny Wielkie",
    "gn:country_code":"PL",
    "gn:dem":123,
    "gn:feature_class":"P",
    "gn:feature_code":"PPL",
    "gn:name":"Spaliny Wielkie",
    "gn:population":0,
    "gn:timezone":"Europe/Warsaw",
    "iso:country":"PL",
    "name:pol_x_preferred":[
        "Spaliny Wielkie"
    ],
    "name:ukr_x_preferred":[
        "\u0421\u043f\u0430\u043b\u0456\u043d\u0438-\u0412\u0435\u043b\u0438\u043a\u0456"
    ],
    "name:und_x_variant":[
        "Neuwiesen",
        "Gross Spalienen"
    ],
    "wof:name":"Spaliny Wielkie",
    "wof:placetype":"locality"
},
  "geometry": {"coordinates":[21.43845,53.47722],"type":"Point"}
}