{
  "type": "Feature",
  "properties": {
    "gn:admin1_code":"74.0",
    "gn:admin2_code":"1012.0",
    "gn:admin3_code":"101214.0",
    "gn:asciiname":"Ewina",
    "gn:country_code":"PL",
    "gn:dem":243,
    "gn:feature_class":"P",
    "gn:feature_code":"PPL",
    "gn:name":"Ewina",
    "gn:population":0,
    "gn:timezone":"Europe/Warsaw",
    "iso:country":"PL",
    "name:pol_x_preferred":[
        "Ewina"
    ],
    "name:ukr_x_preferred":[
        "\u0415\u0432\u0456\u043d\u0430"
    ],
    "wof:name":"Ewina",
    "wof:placetype":"locality"
},
  "geometry": {"coordinates":[19.56544,50.95959000000001],"type":"Point"}
}