{
  "type": "Feature",
  "properties": {
    "gn:admin1_code":"77.0",
    "gn:admin2_code":"1211.0",
    "gn:admin3_code":"121104.0",
    "gn:asciiname":"Mizerna",
    "gn:country_code":"PL",
    "gn:dem":584,
    "gn:feature_class":"P",
    "gn:feature_code":"PPL",
    "gn:name":"Mizerna",
    "gn:population":0,
    "gn:timezone":"Europe/Warsaw",
    "iso:country":"PL",
    "name:ceb_x_preferred":[
        "Mizerna"
    ],
    "name:deu_x_preferred":[
        "Mizerna"
    ],
    "name:pol_x_preferred":[
        "Mizerna"
    ],
    "name:ukr_x_preferred":[
        "\u041c\u0456\u0437\u0435\u0440\u043d\u0430"
    ],
    "wof:name":"Mizerna",
    "wof:placetype":"locality"
},
  "geometry": {"coordinates":[20.29106,49.45892],"type":"Point"}
}