{
  "type": "Feature",
  "properties": {
    "gn:admin1_code":"85.0",
    "gn:admin2_code":"2818.0",
    "gn:admin3_code":"281802.0",
    "gn:asciiname":"Lysogora",
    "gn:country_code":"PL",
    "gn:dem":235,
    "gn:feature_class":"P",
    "gn:feature_code":"PPL",
    "gn:name":"\u0141ysog\u00f3ra",
    "gn:population":0,
    "gn:timezone":"Europe/Warsaw",
    "iso:country":"PL",
    "name:azb_x_preferred":[
        "\u0648\u0633\u0648\u0642\u0648\u0631\u0627"
    ],
    "name:deu_x_preferred":[
        "\u0141ysog\u00f3ra"
    ],
    "name:fas_x_preferred":[
        "\u0648\u0633\u0648\u06af\u0648\u0631\u0627"
    ],
    "name:lit_x_preferred":[
        "Kepurdegiai"
    ],
    "name:nld_x_preferred":[
        "\u0141ysog\u00f3ra"
    ],
    "name:pol_x_preferred":[
        "\u0141ysog\u00f3ra"
    ],
    "name:ukr_x_preferred":[
        "\u041b\u0438\u0441\u043e\u0491\u0443\u0440\u0430"
    ],
    "wof:name":"Lysogora",
    "wof:placetype":"locality"
},
  "geometry": {"coordinates":[22.73844,54.33735],"type":"Point"}
}