{
  "type": "Feature",
  "properties": {
    "gn:admin1_code":"81.0",
    "gn:admin2_code":"2004.0",
    "gn:admin3_code":"200402.0",
    "gn:asciiname":"Konopki",
    "gn:country_code":"PL",
    "gn:dem":131,
    "gn:feature_class":"P",
    "gn:feature_code":"PPL",
    "gn:name":"Konopki",
    "gn:population":0,
    "gn:timezone":"Europe/Warsaw",
    "iso:country":"PL",
    "name:deu_x_preferred":[
        "Konopki"
    ],
    "name:fra_x_preferred":[
        "Konopki"
    ],
    "name:lit_x_preferred":[
        "Konopkai"
    ],
    "name:pol_x_preferred":[
        "Konopki"
    ],
    "name:szl_x_preferred":[
        "Konopki"
    ],
    "name:ukr_x_preferred":[
        "\u041a\u043e\u043d\u043e\u043f\u043a\u0456"
    ],
    "wof:name":"Konopki",
    "wof:placetype":"locality"
},
  "geometry": {"coordinates":[22.41108,53.65227],"type":"Point"}
}