{
  "type": "Feature",
  "properties": {
    "gn:country":"PL",
    "gn:fcode":"PPL",
    "gn:population":220,
    "iso:country":"PL",
    "name:ast_x_preferred":[
        "Ko\u0142oniec"
    ],
    "name:ceb_x_preferred":[
        "Ko\u0142oniec"
    ],
    "name:ces_x_preferred":[
        "Ko\u0142oniec"
    ],
    "name:che_x_preferred":[
        "\u041a\u043e\u043b\u043e\u043d\u0435\u0446\u044c"
    ],
    "name:eng_x_preferred":[
        "Ko\u0142oniec"
    ],
    "name:fra_x_preferred":[
        "Ko\u0142oniec"
    ],
    "name:nan_x_preferred":[
        "Ko\u0142oniec"
    ],
    "name:nld_x_preferred":[
        "Ko\u0142oniec"
    ],
    "name:pol_x_preferred":[
        "Ko\u0142oniec"
    ],
    "name:tat_x_preferred":[
        "\u041a\u043e\u043b\u043e\u043d\u0435\u0446\u044c"
    ],
    "name:ukr_x_preferred":[
        "\u041a\u043e\u043b\u043e\u043d\u0435\u0446\u044c"
    ],
    "qs_pg:aaroncc":"PL",
    "qs_pg:gn_country":"PL",
    "qs_pg:gn_fcode":"PPL",
    "qs_pg:gn_pop":220,
    "qs_pg:name":"Ko\u0142oniec",
    "qs_pg:name_adm0":"Polska",
    "qs_pg:name_adm1":"Swi\u0119tokrzyskie",
    "qs_pg:photos_9r":0,
    "qs_pg:photos_sr":0,
    "qs_pg:pop_sr":2,
    "qs_pg:qs_pg_placetype":"locality",
    "qs_pg:qs_pg_placetype_gp":"Town",
    "qs_pg:woe_adm0":23424923,
    "woe:adm0_id":23424923,
    "woe:name_adm0":"Polska",
    "woe:name_adm1":"Swi\u0119tokrzyskie",
    "woe:placetype":"Town",
    "wof:name":"Ko\u0142oniec",
    "wof:placetype":"locality",
    "wof:population":220
},
  "geometry": {"coordinates":[20.14451,51.17937],"type":"Point"}
}