{
  "type": "Feature",
  "properties": {
    "gn:admin1_code":"84.0",
    "gn:admin2_code":"2612.0",
    "gn:admin3_code":"261204.0",
    "gn:asciiname":"Niekrasow",
    "gn:country_code":"PL",
    "gn:dem":172,
    "gn:feature_class":"P",
    "gn:feature_code":"PPL",
    "gn:name":"Niekras\u00f3w",
    "gn:population":0,
    "gn:timezone":"Europe/Warsaw",
    "iso:country":"PL",
    "name:pol_x_preferred":[
        "Niekras\u00f3w"
    ],
    "name:ukr_x_preferred":[
        "\u041d\u0435\u043a\u0440\u0430\u0441\u0443\u0432"
    ],
    "wof:name":"Niekrasow",
    "wof:placetype":"locality"
},
  "geometry": {"coordinates":[21.38231,50.49421],"type":"Point"}
}