{
  "type": "Feature",
  "properties": {
    "gn:admin1_code":"82.0",
    "gn:admin2_code":"2215.0",
    "gn:admin3_code":"221509.0",
    "gn:asciiname":"Otalzyno",
    "gn:country_code":"PL",
    "gn:dem":199,
    "gn:feature_class":"P",
    "gn:feature_code":"PPL",
    "gn:name":"Otal\u017cyno",
    "gn:population":0,
    "gn:timezone":"Europe/Warsaw",
    "iso:country":"PL",
    "name:pol_x_preferred":[
        "Otal\u017cyno"
    ],
    "wof:name":"Otalzyno",
    "wof:placetype":"locality"
},
  "geometry": {"coordinates":[18.21667,54.45],"type":"Point"}
}