{
  "type": "Feature",
  "properties": {
    "gn:admin1_code":"84.0",
    "gn:admin2_code":"2605.0",
    "gn:admin3_code":"260507.0",
    "gn:asciiname":"Zazdrosc",
    "gn:country_code":"PL",
    "gn:dem":284,
    "gn:feature_class":"P",
    "gn:feature_code":"PPL",
    "gn:name":"Zazdro\u015b\u0107",
    "gn:population":0,
    "gn:timezone":"Europe/Warsaw",
    "iso:country":"PL",
    "wof:name":"Zazdrosc",
    "wof:placetype":"locality"
},
  "geometry": {"coordinates":[20.41667,51.03333],"type":"Point"}
}