{
  "type": "Feature",
  "properties": {
    "gn:admin1_code":"86.0",
    "gn:admin2_code":"3015.0",
    "gn:admin3_code":"301506.0",
    "gn:asciiname":"Nadnia",
    "gn:country_code":"PL",
    "gn:dem":60,
    "gn:feature_class":"P",
    "gn:feature_code":"PPL",
    "gn:name":"N\u0105dnia",
    "gn:population":0,
    "gn:timezone":"Europe/Warsaw",
    "iso:country":"PL",
    "name:azb_x_preferred":[
        "\u0646\u0627\u0646\u062f\u0646\u0642\u0627"
    ],
    "name:ceb_x_preferred":[
        "N\u0105dnia"
    ],
    "name:deu_x_preferred":[
        "N\u0105dnia"
    ],
    "name:fas_x_preferred":[
        "\u0646\u0627\u0646\u062f\u0646\u06af\u0627"
    ],
    "name:fra_x_preferred":[
        "N\u0105dnia"
    ],
    "name:nld_x_preferred":[
        "N\u0105dnia"
    ],
    "name:pol_x_preferred":[
        "N\u0105dnia"
    ],
    "name:ukr_x_preferred":[
        "\u041d\u043e\u043d\u0434\u043d\u044f"
    ],
    "wof:name":"Nadnia",
    "wof:placetype":"locality"
},
  "geometry": {"coordinates":[15.88115,52.24724000000001],"type":"Point"}
}