{
  "type": "Feature",
  "properties": {
    "gn:admin1_code":"77.0",
    "gn:admin2_code":"1209.0",
    "gn:admin3_code":"120907.0",
    "gn:asciiname":"Rudnik",
    "gn:country_code":"PL",
    "gn:dem":327,
    "gn:feature_class":"P",
    "gn:feature_code":"PPL",
    "gn:name":"Rudnik",
    "gn:population":2641,
    "gn:timezone":"Europe/Warsaw",
    "iso:country":"PL",
    "wof:name":"Rudnik",
    "wof:placetype":"locality",
    "wof:population":2641
},
  "geometry": {"coordinates":[19.8474,49.85243],"type":"Point"}
}