{
  "type": "Feature",
  "properties": {
    "gn:admin1_code":"86.0",
    "gn:admin2_code":"3028.0",
    "gn:admin3_code":"302805.0",
    "gn:asciiname":"Stawiany",
    "gn:country_code":"PL",
    "gn:dem":108,
    "gn:feature_class":"P",
    "gn:feature_code":"PPL",
    "gn:name":"Stawiany",
    "gn:population":0,
    "gn:timezone":"Europe/Warsaw",
    "iso:country":"PL",
    "name:ceb_x_preferred":[
        "Stawiany"
    ],
    "name:fra_x_preferred":[
        "Stawiany"
    ],
    "name:pol_x_preferred":[
        "Stawiany"
    ],
    "name:ukr_x_preferred":[
        "\u0421\u0442\u0430\u0432\u044f\u043d\u0438"
    ],
    "wof:name":"Stawiany",
    "wof:placetype":"locality"
},
  "geometry": {"coordinates":[17.20262,52.62011999999999],"type":"Point"}
}