{
  "type": "Feature",
  "properties": {
    "gn:admin1_code":"83.0",
    "gn:admin2_code":"2477.0",
    "gn:admin3_code":"247701.0",
    "gn:asciiname":"Paprocany",
    "gn:country_code":"PL",
    "gn:dem":239,
    "gn:feature_class":"P",
    "gn:feature_code":"PPL",
    "gn:name":"Paprocany",
    "gn:population":0,
    "gn:timezone":"Europe/Warsaw",
    "iso:country":"PL",
    "name:pol_x_preferred":[
        "Paprocany"
    ],
    "wof:name":"Paprocany",
    "wof:placetype":"neighbourhood"
},
  "geometry": {"coordinates":[18.99416,50.09526],"type":"Point"}
}