{
  "type": "Feature",
  "properties": {
    "gn:admin1_code":"81.0",
    "gn:admin2_code":"2010.0",
    "gn:admin3_code":"201004.0",
    "gn:asciiname":"Zdzichy",
    "gn:country_code":"PL",
    "gn:dem":147,
    "gn:feature_class":"P",
    "gn:feature_code":"PPL",
    "gn:name":"Zdzichy",
    "gn:population":0,
    "gn:timezone":"Europe/Warsaw",
    "iso:country":"PL",
    "wof:name":"Zdzichy",
    "wof:placetype":"locality"
},
  "geometry": {"coordinates":[22.65099,52.54942],"type":"Point"}
}