{
  "type": "Feature",
  "properties": {
    "gn:admin1_code":"72.0",
    "gn:admin2_code":"211.0",
    "gn:admin3_code":"21102.0",
    "gn:asciiname":"Zimna Woda",
    "gn:country_code":"PL",
    "gn:dem":141,
    "gn:feature_class":"P",
    "gn:feature_code":"PPL",
    "gn:name":"Zimna Woda",
    "gn:population":0,
    "gn:timezone":"Europe/Warsaw",
    "iso:country":"PL",
    "name:deu_x_historical":[
        "Kaltwasser"
    ],
    "name:deu_x_preferred":[
        "Kaltwasser"
    ],
    "name:deu_x_variant":[
        "Zimna Woda"
    ],
    "name:pol_x_preferred":[
        "Zimna Woda"
    ],
    "name:ukr_x_preferred":[
        "\u0417\u0456\u043c\u043d\u0430-\u0412\u043e\u0434\u0430"
    ],
    "wof:name":"Zimna Woda",
    "wof:placetype":"locality"
},
  "geometry": {"coordinates":[16.10651,51.31777],"type":"Point"}
}