{
  "type": "Feature",
  "properties": {
    "gn:admin1_code":"80.0",
    "gn:admin2_code":"1804.0",
    "gn:admin3_code":"180410.0",
    "gn:asciiname":"Czastkowice",
    "gn:country_code":"PL",
    "gn:dem":206,
    "gn:feature_class":"P",
    "gn:feature_code":"PPL",
    "gn:name":"Cz\u0105stkowice",
    "gn:population":0,
    "gn:timezone":"Europe/Warsaw",
    "iso:country":"PL",
    "name:pol_x_preferred":[
        "Cz\u0105stkowice"
    ],
    "name:ukr_x_preferred":[
        "\u0427\u0430\u0441\u0442\u043a\u043e\u0432\u0438\u0447\u0456"
    ],
    "wof:name":"Czastkowice",
    "wof:placetype":"locality"
},
  "geometry": {"coordinates":[22.55682,49.95409],"type":"Point"}
}