{
  "type": "Feature",
  "properties": {
    "gn:admin1_code":"73.0",
    "gn:admin2_code":"416.0",
    "gn:admin3_code":"41605.0",
    "gn:asciiname":"Laski Piec",
    "gn:country_code":"PL",
    "gn:dem":90,
    "gn:feature_class":"P",
    "gn:feature_code":"PPL",
    "gn:name":"\u0141\u0105ski Piec",
    "gn:population":0,
    "gn:timezone":"Europe/Warsaw",
    "iso:country":"PL",
    "name:ceb_x_preferred":[
        "\u0141\u0105ski Piec"
    ],
    "name:nld_x_preferred":[
        "\u0141\u0105ski Piec"
    ],
    "name:pol_x_preferred":[
        "\u0141\u0105ski Piec"
    ],
    "name:ukr_x_preferred":[
        "\u041b\u043e\u043d\u0441\u044c\u043a\u0438\u0439-\u041f\u0435\u0446\u044c"
    ],
    "wof:name":"Laski Piec",
    "wof:placetype":"locality"
},
  "geometry": {"coordinates":[18.20971,53.64631],"type":"Point"}
}