{
  "type": "Feature",
  "properties": {
    "gn:admin1_code":"75.0",
    "gn:admin2_code":"601.0",
    "gn:admin3_code":"60103.0",
    "gn:asciiname":"Julkow",
    "gn:country_code":"PL",
    "gn:dem":148,
    "gn:feature_class":"P",
    "gn:feature_code":"PPL",
    "gn:name":"Julk\u00f3w",
    "gn:population":0,
    "gn:timezone":"Europe/Warsaw",
    "iso:country":"PL",
    "name:ceb_x_preferred":[
        "Julk\u00f3w"
    ],
    "name:fra_x_preferred":[
        "Julk\u00f3w"
    ],
    "name:lit_x_preferred":[
        "Julkuvas"
    ],
    "name:pol_x_preferred":[
        "Julk\u00f3w"
    ],
    "name:ukr_x_preferred":[
        "\u042e\u043b\u044c\u043a\u0443\u0432"
    ],
    "wof:name":"Julkow",
    "wof:placetype":"locality"
},
  "geometry": {"coordinates":[23.19784,52.07349],"type":"Point"}
}