{
  "type": "Feature",
  "properties": {
    "gn:population":1600,
    "iso:country":"PL",
    "name:azb_x_preferred":[
        "\u0642\u0645\u06cc\u0646\u0627 \u0645\u0627\u0631\u06a9\u0648\u0634\u0648\u0648"
    ],
    "name:bel_x_preferred":[
        "\u0413\u043c\u0456\u043d\u0430 \u041c\u0430\u0440\u043a\u0443\u0448\u0430\u045e"
    ],
    "name:ceb_x_preferred":[
        "Markusz\u00f3w"
    ],
    "name:deu_x_preferred":[
        "Gmina Markusz\u00f3w"
    ],
    "name:eng_x_preferred":[
        "Gmina Markusz\u00f3w"
    ],
    "name:eus_x_preferred":[
        "Markusz\u00f3w udalerria"
    ],
    "name:fas_x_preferred":[
        "\u06af\u0645\u06cc\u0646\u0627 \u0645\u0627\u0631\u06a9\u0648\u0634\u0648\u0648"
    ],
    "name:fra_x_preferred":[
        "Markusz\u00f3w"
    ],
    "name:ita_x_preferred":[
        "Markusz\u00f3w"
    ],
    "name:nan_x_preferred":[
        "Markusz\u00f3w"
    ],
    "name:nld_x_preferred":[
        "Markusz\u00f3w"
    ],
    "name:pol_x_preferred":[
        "Markusz\u00f3w"
    ],
    "name:por_x_preferred":[
        "Comuna de Markusz\u00f3w"
    ],
    "name:rus_x_preferred":[
        "\u041c\u0430\u0440\u043a\u0443\u0448\u0443\u0432"
    ],
    "name:slk_x_preferred":[
        "Gmina Markusz\u00f3w"
    ],
    "name:ukr_x_preferred":[
        "\u0413\u043c\u0456\u043d\u0430 \u041c\u0430\u0440\u043a\u0443\u0448\u0443\u0432"
    ],
    "name:ukr_x_variant":[
        "\u0490\u043c\u0456\u043d\u0430 \u041c\u0430\u0440\u043a\u0443\u0448\u0443\u0432"
    ],
    "name:war_x_preferred":[
        "Gmina Markusz\u00f3w"
    ],
    "qs:a0":"Rzeczpospolita Polska",
    "qs:a1":"*Lubelskie",
    "qs:a1r":"0",
    "qs:a2":"Pulawski",
    "qs:adm0":"Rzeczpospolita Polska",
    "qs:la":"Markusz\u00f3w",
    "qs:la_lc":"*PL0614072",
    "qs:level":"locality",
    "qs:loc":"Markusz\u00f3w",
    "qs:loc_alt":"Markuszow",
    "qs:pop":0,
    "qs:type":"rural point-in-poly",
    "wd:wordcount":131,
    "wof:name":"Markusz\u00f3w",
    "wof:placetype":"locality",
    "wof:population":1600
},
  "geometry": {"coordinates":[22.2498068492316,51.3827572902193],"type":"Point"}
}