{
  "type": "Feature",
  "properties": {
    "gn:admin1_code":"77.0",
    "gn:admin2_code":"1216.0",
    "gn:admin3_code":"121603.0",
    "gn:asciiname":"Jastrzabka Nowa",
    "gn:country_code":"PL",
    "gn:dem":241,
    "gn:feature_class":"P",
    "gn:feature_code":"PPL",
    "gn:name":"Jastrz\u0105bka Nowa",
    "gn:population":0,
    "gn:timezone":"Europe/Warsaw",
    "iso:country":"PL",
    "name:pol_x_preferred":[
        "Nowa Jastrz\u0105bka"
    ],
    "name:ukr_x_preferred":[
        "\u041d\u043e\u0432\u0430 \u042f\u0441\u0442\u0448\u043e\u043c\u0431\u043a\u0430"
    ],
    "name:und_x_variant":[
        "Jastrz\u0105bka Nowa"
    ],
    "wof:name":"Jastrzabka Nowa",
    "wof:placetype":"locality"
},
  "geometry": {"coordinates":[21.16267,50.12075],"type":"Point"}
}