{
  "type": "Feature",
  "properties": {
    "gn:admin1_code":"85.0",
    "gn:admin2_code":"2813.0",
    "gn:admin3_code":"281304.0",
    "gn:asciiname":"Zatyki",
    "gn:country_code":"PL",
    "gn:dem":152,
    "gn:feature_class":"P",
    "gn:feature_code":"PPL",
    "gn:name":"Zatyki",
    "gn:population":0,
    "gn:timezone":"Europe/Warsaw",
    "iso:country":"PL",
    "name:deu_x_preferred":[
        "Zatyki"
    ],
    "name:nld_x_preferred":[
        "Zatyki"
    ],
    "name:pol_x_preferred":[
        "Zatyki"
    ],
    "name:ukr_x_preferred":[
        "\u0417\u0430\u0442\u0438\u043a\u0456"
    ],
    "name:und_x_variant":[
        "Satticken",
        "Sattycken",
        "Sattyken Kreis Treuburg",
        "Zatyki"
    ],
    "wof:name":"Zatyki",
    "wof:placetype":"locality"
},
  "geometry": {"coordinates":[22.50264,53.94871],"type":"Point"}
}