{
  "type": "Feature",
  "properties": {
    "gn:admin1_code":"74.0",
    "gn:admin2_code":"1012.0",
    "gn:admin3_code":"101206.0",
    "gn:asciiname":"Ujazdowek",
    "gn:country_code":"PL",
    "gn:dem":246,
    "gn:feature_class":"P",
    "gn:feature_code":"PPL",
    "gn:name":"Ujazd\u00f3wek",
    "gn:population":0,
    "gn:timezone":"Europe/Warsaw",
    "iso:country":"PL",
    "name:fra_x_preferred":[
        "Ujazd\u00f3wek"
    ],
    "name:pol_x_preferred":[
        "Ujazd\u00f3wek"
    ],
    "name:ukr_x_preferred":[
        "\u0423\u044f\u0437\u0434\u0443\u0432\u0435\u043a"
    ],
    "name:und_x_variant":[
        "Ujazd\u00f3wek"
    ],
    "wof:name":"Ujazdowek",
    "wof:placetype":"locality"
},
  "geometry": {"coordinates":[19.65176,51.04234],"type":"Point"}
}