{
  "type": "Feature",
  "properties": {
    "gn:admin1_code":"74.0",
    "gn:admin2_code":"1006.0",
    "gn:admin3_code":"100611.0",
    "gn:asciiname":"Wielkopole",
    "gn:country_code":"PL",
    "gn:dem":196,
    "gn:feature_class":"P",
    "gn:feature_code":"PPL",
    "gn:name":"Wielkopole",
    "gn:population":0,
    "gn:timezone":"Europe/Warsaw",
    "iso:country":"PL",
    "name:fra_x_preferred":[
        "Wielkopole"
    ],
    "name:pol_x_preferred":[
        "Wielkopole"
    ],
    "name:ukr_x_preferred":[
        "\u0412\u0435\u043b\u044c\u043a\u043e\u043f\u043e\u043b\u0435"
    ],
    "wof:name":"Wielkopole",
    "wof:placetype":"neighbourhood"
},
  "geometry": {"coordinates":[19.57437,51.61708],"type":"Point"}
}