{
  "type": "Feature",
  "properties": {
    "gn:admin1_code":"83.0",
    "gn:admin2_code":"2406.0",
    "gn:admin3_code":"240607.0",
    "gn:asciiname":"Wiecki",
    "gn:country_code":"PL",
    "gn:dem":208,
    "gn:feature_class":"P",
    "gn:feature_code":"PPL",
    "gn:name":"Wi\u0119cki",
    "gn:population":0,
    "gn:timezone":"Europe/Warsaw",
    "iso:country":"PL",
    "name:ceb_x_preferred":[
        "Wi\u0119cki"
    ],
    "name:pol_x_preferred":[
        "Wi\u0119cki"
    ],
    "name:ukr_x_preferred":[
        "\u0412\u0435\u043d\u0446\u044c\u043a\u0438"
    ],
    "wof:name":"Wiecki",
    "wof:placetype":"locality"
},
  "geometry": {"coordinates":[18.92584,51.07398],"type":"Point"}
}