{
  "type": "Feature",
  "properties": {
    "gn:gn_country":"PL",
    "gn:gn_fcode":"PPL",
    "gn:gn_pop":120,
    "gn:population":120,
    "iso:country":"PL",
    "name:ast_x_preferred":[
        "Osina"
    ],
    "name:ceb_x_preferred":[
        "Osina"
    ],
    "name:eng_x_preferred":[
        "Osina"
    ],
    "name:fra_x_preferred":[
        "Osina"
    ],
    "name:pol_x_preferred":[
        "Osina"
    ],
    "name:ukr_x_preferred":[
        "\u041e\u0441\u0456\u043d\u0430"
    ],
    "name:vie_x_preferred":[
        "Osina"
    ],
    "qs_pg:aaroncc":"PL",
    "qs_pg:gn_country":"PL",
    "qs_pg:gn_fcode":"PPL",
    "qs_pg:gn_pop":120,
    "qs_pg:name":"Osina",
    "qs_pg:name_adm0":"Polska",
    "qs_pg:name_adm1":"Zachodniopomorskie",
    "qs_pg:photos_9k":1,
    "qs_pg:photos_9r":1,
    "qs_pg:photos_all":3,
    "qs_pg:photos_sr":0,
    "qs_pg:pop_sr":1,
    "qs_pg:qs_pg_placetype":"locality",
    "qs_pg:qs_pg_placetype_gp":"Town",
    "qs_pg:woe_adm0":23424923,
    "woe:adm0_id":23424923,
    "woe:name_adm0":"Polska",
    "woe:name_adm1":"Zachodniopomorskie",
    "woe:placetype":"Town",
    "wof:name":"Osina",
    "wof:placetype":"locality",
    "wof:population":120
},
  "geometry": {"coordinates":[15.18345,53.02098],"type":"Point"}
}