{
  "type": "Feature",
  "properties": {
    "gn:gn_country":"PL",
    "gn:gn_fcode":"PPLA3",
    "gn:gn_pop":1341,
    "gn:population":1341,
    "iso:country":"PL",
    "name:azb_x_preferred":[
        "\u067e\u0648\u062a\u0648\u06a9 \u0642\u0648\u0631\u0646\u0647"
    ],
    "name:ceb_x_preferred":[
        "Potok G\u00f3rny"
    ],
    "name:fas_x_preferred":[
        "\u067e\u0648\u062a\u0648\u06a9 \u06af\u0648\u0631\u0646\u0647"
    ],
    "name:fra_x_preferred":[
        "Potok G\u00f3rny"
    ],
    "name:nld_x_preferred":[
        "Potok G\u00f3rny"
    ],
    "name:pol_x_preferred":[
        "Potok G\u00f3rny"
    ],
    "name:rus_x_preferred":[
        "\u041f\u043e\u0442\u043e\u043a-\u0413\u0443\u0440\u043d\u044b"
    ],
    "name:ukr_x_preferred":[
        "\u041f\u043e\u0442\u043e\u043a-\u0490\u0443\u0440\u043d\u0438"
    ],
    "qs_pg:aaroncc":"PL",
    "qs_pg:gn_country":"PL",
    "qs_pg:gn_fcode":"PPLA3",
    "qs_pg:gn_pop":1341,
    "qs_pg:name":"Potok G\u00f3rny",
    "qs_pg:name_adm0":"Polska",
    "qs_pg:name_adm1":"Lubelskie",
    "qs_pg:photos_9r":0,
    "qs_pg:photos_sr":0,
    "qs_pg:pop_sr":3,
    "qs_pg:qs_pg_placetype":"localadmin",
    "qs_pg:qs_pg_placetype_gp":"LocalAdmin",
    "qs_pg:woe_adm0":23424923,
    "woe:adm0_id":23424923,
    "woe:name_adm0":"Polska",
    "woe:name_adm1":"Lubelskie",
    "woe:placetype":"LocalAdmin",
    "wof:name":"Potok G\u00f3rny",
    "wof:placetype":"localadmin",
    "wof:population":1341
},
  "geometry": {"coordinates":[22.56188,50.38477],"type":"Point"}
}