{
  "type": "Feature",
  "properties": {
    "gn:admin1_code":"73.0",
    "gn:admin2_code":"401.0",
    "gn:admin3_code":"40104.0",
    "gn:asciiname":"Podgaj",
    "gn:country_code":"PL",
    "gn:dem":73,
    "gn:feature_class":"P",
    "gn:feature_code":"PPL",
    "gn:name":"Podgaj",
    "gn:population":0,
    "gn:timezone":"Europe/Warsaw",
    "iso:country":"PL",
    "name:bos_x_preferred":[
        "Podgaj"
    ],
    "name:ceb_x_preferred":[
        "Podgaj"
    ],
    "name:fra_x_preferred":[
        "Podgaj"
    ],
    "name:hrv_x_preferred":[
        "Podgaj"
    ],
    "name:pol_x_preferred":[
        "Podgaj"
    ],
    "name:slv_x_preferred":[
        "Podgaj"
    ],
    "name:srp_x_preferred":[
        "\u041f\u043e\u0434\u0433\u0430\u0458"
    ],
    "name:swe_x_preferred":[
        "Podgaj"
    ],
    "name:ukr_x_preferred":[
        "\u041f\u043e\u0434\u0491\u0430\u0439"
    ],
    "wof:name":"Podgaj",
    "wof:placetype":"locality"
},
  "geometry": {"coordinates":[18.61726,52.83956],"type":"Point"}
}