{
  "type": "Feature",
  "properties": {
    "gn:admin1_code":"86.0",
    "gn:admin2_code":"3003.0",
    "gn:admin3_code":"300310.0",
    "gn:asciiname":"Mielzyn",
    "gn:country_code":"PL",
    "gn:dem":99,
    "gn:feature_class":"P",
    "gn:feature_code":"PPL",
    "gn:name":"Miel\u017cyn",
    "gn:population":0,
    "gn:timezone":"Europe/Warsaw",
    "iso:country":"PL",
    "name:ceb_x_preferred":[
        "Miel\u017cyn"
    ],
    "name:deu_x_preferred":[
        "Miel\u017cyn"
    ],
    "name:fra_x_preferred":[
        "Miel\u017cyn"
    ],
    "name:pol_x_preferred":[
        "Miel\u017cyn"
    ],
    "name:ukr_x_preferred":[
        "\u041c\u0435\u043b\u044c\u0436\u0438\u043d"
    ],
    "name:und_x_variant":[
        "Miel\u017cyn"
    ],
    "wof:name":"Mielzyn",
    "wof:placetype":"locality"
},
  "geometry": {"coordinates":[17.77107,52.38287],"type":"Point"}
}