{
  "type": "Feature",
  "properties": {
    "gn:admin1_code":"73.0",
    "gn:admin2_code":"411.0",
    "gn:admin3_code":"41102.0",
    "gn:asciiname":"Czarnocice",
    "gn:country_code":"PL",
    "gn:dem":84,
    "gn:feature_class":"P",
    "gn:feature_code":"PPL",
    "gn:name":"Czarnocice",
    "gn:population":0,
    "gn:timezone":"Europe/Warsaw",
    "iso:country":"PL",
    "name:pol_x_preferred":[
        "Czarnocice"
    ],
    "name:ukr_x_preferred":[
        "\u0427\u0430\u0440\u043d\u043e\u0446\u0438\u0446\u0435"
    ],
    "wof:name":"Czarnocice",
    "wof:placetype":"locality"
},
  "geometry": {"coordinates":[18.6718,52.54847],"type":"Point"}
}