{
  "type": "Feature",
  "properties": {
    "gn:country":"PL",
    "gn:fcode":"PPLA3",
    "gn:population":1545,
    "iso:country":"PL",
    "name:azb_x_preferred":[
        "\u0633\u062a\u0648\u067e\u0646\u0642\u062a\u0633\u0627"
    ],
    "name:ceb_x_preferred":[
        "Stopnica"
    ],
    "name:deu_x_preferred":[
        "Stopnica"
    ],
    "name:est_x_preferred":[
        "Stopnica"
    ],
    "name:fas_x_preferred":[
        "\u0633\u062a\u0648\u067e\u0646\u06af\u062a\u0633\u0627"
    ],
    "name:hak_x_preferred":[
        "Stopnica"
    ],
    "name:heb_x_preferred":[
        "\u05e1\u05d8\u05d5\u05e4\u05e0\u05d9\u05e6\u05d4"
    ],
    "name:nld_x_preferred":[
        "Stopnica"
    ],
    "name:pol_x_preferred":[
        "Stopnica"
    ],
    "qs_pg:aaroncc":"PL",
    "qs_pg:gn_country":"PL",
    "qs_pg:gn_fcode":"PPLA3",
    "qs_pg:gn_pop":1545,
    "qs_pg:name":"Stopnica",
    "qs_pg:name_adm0":"Polska",
    "qs_pg:name_adm1":"Swi\u0119tokrzyskie",
    "qs_pg:photos_9k":1,
    "qs_pg:photos_9r":1,
    "qs_pg:photos_all":2,
    "qs_pg:photos_sr":0,
    "qs_pg:pop_sr":3,
    "qs_pg:qs_pg_placetype":"localadmin",
    "qs_pg:qs_pg_placetype_gp":"LocalAdmin",
    "qs_pg:woe_adm0":23424923,
    "woe:adm0_id":23424923,
    "woe:name_adm0":"Polska",
    "woe:name_adm1":"Swi\u0119tokrzyskie",
    "woe:placetype":"LocalAdmin",
    "wof:name":"Stopnica",
    "wof:placetype":"localadmin",
    "wof:population":1545
},
  "geometry": {"coordinates":[20.9378,50.44018],"type":"Point"}
}