{
  "type": "Feature",
  "properties": {
    "iso:country":"PL",
    "name:pol_x_preferred":[
        "Ruszcza"
    ],
    "name:ukr_x_preferred":[
        "\u0420\u0443\u0449\u0430"
    ],
    "wof:name":"Ruszcza",
    "wof:placetype":"neighbourhood"
},
  "geometry": {"coordinates":[20.14739781728106,50.08744324689891],"type":"Point"}
}