{
  "type": "Feature",
  "properties": {
    "gn:admin1_code":"84.0",
    "gn:admin2_code":"2602.0",
    "gn:admin3_code":"260208.0",
    "gn:asciiname":"Bizorenda",
    "gn:country_code":"PL",
    "gn:dem":229,
    "gn:feature_class":"P",
    "gn:feature_code":"PPL",
    "gn:name":"Bizorenda",
    "gn:population":0,
    "gn:timezone":"Europe/Warsaw",
    "iso:country":"PL",
    "wof:name":"Bizorenda",
    "wof:placetype":"locality"
},
  "geometry": {"coordinates":[20.34801,50.74906],"type":"Point"}
}