{
  "type": "Feature",
  "properties": {
    "gn:admin1_code":"84.0",
    "gn:admin2_code":"2602.0",
    "gn:admin3_code":"260208.0",
    "gn:asciiname":"Bizorenda",
    "gn:country_code":"PL",
    "gn:dem":229,
    "gn:feature_class":"P",
    "gn:feature_code":"PPL",
    "gn:name":"Bizorenda",
    "gn:population":0,
    "gn:timezone":"Europe/Warsaw",
    "iso:country":"PL",
    "name:pol_x_preferred":[
        "Bizor\u0119da"
    ],
    "name:rus_x_preferred":[
        "\u0411\u0438\u0437\u043e\u0440\u0435\u043d\u0434\u0430"
    ],
    "name:ukr_x_preferred":[
        "\u0411\u0456\u0437\u043e\u0440\u0435\u043d\u0434\u0430"
    ],
    "wof:name":"Bizorenda",
    "wof:placetype":"locality"
},
  "geometry": {"coordinates":[20.34801,50.74906],"type":"Point"}
}