{
  "type": "Feature",
  "properties": {
    "gn:gn_country":"PL",
    "gn:gn_fcode":"PPLA3",
    "gn:gn_pop":3844,
    "gn:population":3844,
    "iso:country":"PL",
    "name:eng_x_preferred":[
        "Podkowa Le\u015bna"
    ],
    "name:rus_x_preferred":[
        "\u041f\u043e\u0434\u043a\u043e\u0432\u0430-\u041b\u0435\u0441\u044c\u043d\u0430"
    ],
    "qs_pg:aaroncc":"PL",
    "qs_pg:gn_country":"PL",
    "qs_pg:gn_fcode":"PPLA3",
    "qs_pg:gn_pop":3844,
    "qs_pg:name":"Podkowa Le\u015bna",
    "qs_pg:name_adm0":"Polska",
    "qs_pg:name_adm1":"Mazowieckie",
    "qs_pg:photos":21,
    "qs_pg:photos_1k":4,
    "qs_pg:photos_9k":1,
    "qs_pg:photos_9r":4,
    "qs_pg:photos_all":205,
    "qs_pg:photos_sr":1,
    "qs_pg:pop_sr":4,
    "qs_pg:qs_pg_placetype":"localadmin",
    "qs_pg:qs_pg_placetype_gp":"LocalAdmin",
    "qs_pg:woe_adm0":23424923,
    "woe:adm0_id":23424923,
    "woe:name_adm0":"Polska",
    "woe:name_adm1":"Mazowieckie",
    "woe:placetype":"LocalAdmin",
    "wof:name":"Podkowa Le\u015bna",
    "wof:placetype":"localadmin",
    "wof:population":3844
},
  "geometry": {"coordinates":[20.72665,52.12237],"type":"Point"}
}