{
  "type": "Feature",
  "properties": {
    "gn:gn_country":"PL",
    "gn:gn_fcode":"PPLA3",
    "gn:gn_pop":3844,
    "gn:population":3844,
    "iso:country":"PL",
    "name:azb_x_preferred":[
        "\u067e\u0648\u062f\u06a9\u0648\u0648\u0627 \u0644\u0634\u0646\u0627"
    ],
    "name:ceb_x_preferred":[
        "Podkowa Le\u015bna"
    ],
    "name:ces_x_preferred":[
        "Podkowa Le\u015bna"
    ],
    "name:deu_x_preferred":[
        "Podkowa Le\u015bna"
    ],
    "name:eng_x_preferred":[
        "Podkowa Le\u015bna"
    ],
    "name:epo_x_preferred":[
        "Podkowa Le\u015bna"
    ],
    "name:est_x_preferred":[
        "Podkowa Le\u015bna"
    ],
    "name:eus_x_preferred":[
        "Podkowa Le\u015bna"
    ],
    "name:fas_x_preferred":[
        "\u067e\u0648\u062f\u06a9\u0648\u0648\u0627 \u0644\u0634\u0646\u0627"
    ],
    "name:fra_x_preferred":[
        "Podkowa Le\u015bna"
    ],
    "name:ita_x_preferred":[
        "Podkowa Le\u015bna"
    ],
    "name:jav_x_preferred":[
        "Podkowa Le\u015bna"
    ],
    "name:lav_x_preferred":[
        "Podkova Lesna"
    ],
    "name:msa_x_preferred":[
        "Podkowa Le\u015bna"
    ],
    "name:nld_x_preferred":[
        "Podkowa Le\u015bna"
    ],
    "name:pol_x_preferred":[
        "Podkowa Le\u015bna"
    ],
    "name:por_x_preferred":[
        "Podkowa Le\u015bna"
    ],
    "name:ron_x_preferred":[
        "Podkowa Le\u015bna"
    ],
    "name:rus_x_preferred":[
        "\u041f\u043e\u0434\u043a\u043e\u0432\u0430-\u041b\u0435\u0441\u044c\u043d\u0430"
    ],
    "name:slk_x_preferred":[
        "Podkowa Le\u015bna"
    ],
    "name:srp_x_preferred":[
        "\u041f\u043e\u0434\u043a\u043e\u0432\u0430 \u041b\u0435\u0441\u043d\u0430"
    ],
    "name:ukr_x_preferred":[
        "\u041f\u043e\u0434\u043a\u043e\u0432\u0430-\u041b\u0435\u0441\u044c\u043d\u0430"
    ],
    "name:vie_x_preferred":[
        "Podkowa Le\u015bna"
    ],
    "name:war_x_preferred":[
        "Podkowa Le\u015bna"
    ],
    "name:zho_x_preferred":[
        "\u6ce2\u5fb7\u79d1\u74e6\u840a\u5e0c\u7d0d"
    ],
    "qs_pg:aaroncc":"PL",
    "qs_pg:gn_country":"PL",
    "qs_pg:gn_fcode":"PPLA3",
    "qs_pg:gn_pop":3844,
    "qs_pg:name":"Podkowa Le\u015bna",
    "qs_pg:name_adm0":"Polska",
    "qs_pg:name_adm1":"Mazowieckie",
    "qs_pg:photos":21,
    "qs_pg:photos_1k":4,
    "qs_pg:photos_9k":1,
    "qs_pg:photos_9r":4,
    "qs_pg:photos_all":205,
    "qs_pg:photos_sr":1,
    "qs_pg:pop_sr":4,
    "qs_pg:qs_pg_placetype":"localadmin",
    "qs_pg:qs_pg_placetype_gp":"LocalAdmin",
    "qs_pg:woe_adm0":23424923,
    "woe:adm0_id":23424923,
    "woe:name_adm0":"Polska",
    "woe:name_adm1":"Mazowieckie",
    "woe:placetype":"LocalAdmin",
    "wof:name":"Podkowa Le\u015bna",
    "wof:placetype":"localadmin",
    "wof:population":3844
},
  "geometry": {"coordinates":[20.72665,52.12237],"type":"Point"}
}