{
  "type": "Feature",
  "properties": {
    "gn:admin1_code":"75.0",
    "gn:admin2_code":"619.0",
    "gn:admin3_code":"61905.0",
    "gn:asciiname":"Zastawie",
    "gn:country_code":"PL",
    "gn:dem":171,
    "gn:feature_class":"P",
    "gn:feature_code":"PPL",
    "gn:name":"Zastawie",
    "gn:population":0,
    "gn:timezone":"Europe/Warsaw",
    "iso:country":"PL",
    "name:fra_x_preferred":[
        "Zastawie"
    ],
    "name:pol_x_preferred":[
        "Zastawie"
    ],
    "name:ukr_x_preferred":[
        "\u0417\u0430\u0441\u0442\u0430\u0432\u0435"
    ],
    "wof:name":"Zastawie",
    "wof:placetype":"locality"
},
  "geometry": {"coordinates":[23.23849,51.37258],"type":"Point"}
}