{
  "type": "Feature",
  "properties": {
    "gn:admin1_code":"73.0",
    "gn:admin2_code":"417.0",
    "gn:admin3_code":"41704.0",
    "gn:asciiname":"Czaple",
    "gn:country_code":"PL",
    "gn:dem":102,
    "gn:feature_class":"P",
    "gn:feature_code":"PPL",
    "gn:name":"Czaple",
    "gn:population":0,
    "gn:timezone":"Europe/Warsaw",
    "iso:country":"PL",
    "name:ceb_x_preferred":[
        "Czaple"
    ],
    "name:deu_x_preferred":[
        "Czaple"
    ],
    "name:fra_x_preferred":[
        "Czaple"
    ],
    "name:pol_x_preferred":[
        "Czaple"
    ],
    "name:ukr_x_preferred":[
        "\u0427\u0430\u043f\u043b\u0435"
    ],
    "wof:name":"Czaple",
    "wof:placetype":"locality"
},
  "geometry": {"coordinates":[18.80393,53.29669000000001],"type":"Point"}
}