{
  "type": "Feature",
  "properties": {
    "gn:admin1_code":"72.0",
    "gn:admin2_code":"217.0",
    "gn:admin3_code":"21704.0",
    "gn:asciiname":"Karszowek",
    "gn:country_code":"PL",
    "gn:dem":165,
    "gn:feature_class":"P",
    "gn:feature_code":"PPL",
    "gn:name":"Karsz\u00f3wek",
    "gn:population":0,
    "gn:timezone":"Europe/Warsaw",
    "iso:country":"PL",
    "name:pol_x_preferred":[
        "Karsz\u00f3wek"
    ],
    "name:ukr_x_preferred":[
        "\u041a\u0430\u0440\u0448\u0443\u0432\u0435\u043a"
    ],
    "wof:name":"Karszowek",
    "wof:placetype":"locality"
},
  "geometry": {"coordinates":[17.17609,50.75655],"type":"Point"}
}