{
  "type": "Feature",
  "properties": {
    "gn:admin1_code":"85.0",
    "gn:admin2_code":"2807.0",
    "gn:admin3_code":"280703.0",
    "gn:asciiname":"Stanowo",
    "gn:country_code":"PL",
    "gn:dem":110,
    "gn:feature_class":"P",
    "gn:feature_code":"PPL",
    "gn:name":"Stanowo",
    "gn:population":0,
    "gn:timezone":"Europe/Warsaw",
    "iso:country":"PL",
    "name:pol_x_preferred":[
        "Stanowo"
    ],
    "wof:name":"Stanowo",
    "wof:placetype":"locality"
},
  "geometry": {"coordinates":[19.7691,53.66061],"type":"Point"}
}