{
  "type": "Feature",
  "properties": {
    "gn:admin1_code":"79.0",
    "gn:admin2_code":"1607.0",
    "gn:admin3_code":"160709.0",
    "gn:asciiname":"Sluzejowek",
    "gn:country_code":"PL",
    "gn:dem":245,
    "gn:feature_class":"P",
    "gn:feature_code":"PPL",
    "gn:name":"S\u0142u\u017cej\u00f3wek",
    "gn:population":0,
    "gn:timezone":"Europe/Warsaw",
    "iso:country":"PL",
    "wof:name":"Sluzejowek",
    "wof:placetype":"locality"
},
  "geometry": {"coordinates":[17.28333,50.58333],"type":"Point"}
}