{
  "type": "Feature",
  "properties": {
    "gn:admin1_code":"84.0",
    "gn:admin2_code":"2604.0",
    "gn:admin3_code":"260409.0",
    "gn:asciiname":"Machocice",
    "gn:country_code":"PL",
    "gn:dem":298,
    "gn:feature_class":"P",
    "gn:feature_code":"PPL",
    "gn:name":"M\u0105chocice",
    "gn:population":0,
    "gn:timezone":"Europe/Warsaw",
    "iso:country":"PL",
    "name:und_x_variant":[
        "M\u0105chocice Kapitulne",
        "M\u0105chocice"
    ],
    "wof:name":"Machocice",
    "wof:placetype":"locality"
},
  "geometry": {"coordinates":[20.76933,50.89058],"type":"Point"}
}