{
  "type": "Feature",
  "properties": {
    "gn:admin1_code":"84.0",
    "gn:admin2_code":"2604.0",
    "gn:admin3_code":"260409.0",
    "gn:asciiname":"Machocice",
    "gn:country_code":"PL",
    "gn:dem":298,
    "gn:feature_class":"P",
    "gn:feature_code":"PPL",
    "gn:name":"M\u0105chocice",
    "gn:population":0,
    "gn:timezone":"Europe/Warsaw",
    "iso:country":"PL",
    "name:nld_x_preferred":[
        "M\u0105chocice Kapitulne"
    ],
    "name:pol_x_preferred":[
        "M\u0105chocice Kapitulne"
    ],
    "name:ukr_x_preferred":[
        "\u041c\u043e\u043d\u0445\u043e\u0446\u0438\u0446\u0435-\u041a\u0430\u043f\u0456\u0442\u0443\u043b\u044c\u043d\u0435"
    ],
    "name:und_x_variant":[
        "M\u0105chocice"
    ],
    "wof:name":"Machocice",
    "wof:placetype":"locality"
},
  "geometry": {"coordinates":[20.76933,50.89058],"type":"Point"}
}