{
  "type": "Feature",
  "properties": {
    "iso:country":"PL",
    "name:bul_x_preferred":[
        "\u0412\u0438\u043b\u043a\u043e\u0432"
    ],
    "name:ceb_x_preferred":[
        "Wilk\u00f3w"
    ],
    "name:deu_x_preferred":[
        "Wilk\u00f3w"
    ],
    "name:fra_x_preferred":[
        "Wilk\u00f3w"
    ],
    "name:ita_x_preferred":[
        "Wilk\u00f3w"
    ],
    "name:nld_x_preferred":[
        "Wilk\u00f3w"
    ],
    "name:pol_x_preferred":[
        "Wilk\u00f3w"
    ],
    "name:rus_x_preferred":[
        "\u0412\u0438\u043b\u044c\u043a\u0443\u0432"
    ],
    "name:ukr_x_preferred":[
        "\u0412\u0456\u043b\u044c\u043a\u0443\u0432"
    ],
    "wof:coterminous":[
        1125312967
    ],
    "wof:name":"Wilk\u00f3w",
    "wof:placetype":"locality"
},
  "geometry": {"coordinates":[17.6311506078366,51.1252800623372],"type":"Point"}
}