{
  "type": "Feature",
  "properties": {
    "iso:country":"PL",
    "name:pol_x_preferred":[
        "Wilk\u00f3w"
    ],
    "wof:name":"Wilk\u00f3w",
    "wof:placetype":"locality"
},
  "geometry": {"coordinates":[17.6311506078366,51.1252800623372],"type":"Point"}
}