{
  "type": "Feature",
  "properties": {
    "gn:admin1_code":"83.0",
    "gn:admin2_code":"2405.0",
    "gn:admin3_code":"240505.0",
    "gn:asciiname":"Widow",
    "gn:country_code":"PL",
    "gn:dem":219,
    "gn:feature_class":"P",
    "gn:feature_code":"PPL",
    "gn:name":"Wid\u00f3w",
    "gn:population":0,
    "gn:timezone":"Europe/Warsaw",
    "iso:country":"PL",
    "name:ceb_x_preferred":[
        "Wid\u00f3w"
    ],
    "name:deu_x_preferred":[
        "Wid\u00f3w"
    ],
    "name:pol_x_preferred":[
        "Wid\u00f3w"
    ],
    "name:ukr_x_preferred":[
        "\u0412\u0456\u0434\u0443\u0432"
    ],
    "wof:name":"Widow",
    "wof:placetype":"locality"
},
  "geometry": {"coordinates":[18.43062,50.4126],"type":"Point"}
}