{
  "type": "Feature",
  "properties": {
    "gn:admin1_code":"85.0",
    "gn:admin2_code":"2804.0",
    "gn:admin3_code":"280402.0",
    "gn:asciiname":"Gruzajny",
    "gn:country_code":"PL",
    "gn:dem":75,
    "gn:feature_class":"P",
    "gn:feature_code":"PPL",
    "gn:name":"Gru\u017cajny",
    "gn:population":0,
    "gn:timezone":"Europe/Warsaw",
    "iso:country":"PL",
    "name:und_x_variant":[
        "Gru\u017cajny"
    ],
    "wof:name":"Gruzajny",
    "wof:placetype":"locality"
},
  "geometry": {"coordinates":[19.83867,54.0541],"type":"Point"}
}