{
  "type": "Feature",
  "properties": {
    "gn:admin1_code":"78.0",
    "gn:admin2_code":"1403.0",
    "gn:admin3_code":"140312.0",
    "gn:asciiname":"Kolonia Zyczyn",
    "gn:country_code":"PL",
    "gn:dem":163,
    "gn:feature_class":"P",
    "gn:feature_code":"PPL",
    "gn:name":"Kolonia \u017byczyn",
    "gn:population":0,
    "gn:timezone":"Europe/Warsaw",
    "iso:country":"PL",
    "wof:name":"Kolonia Zyczyn",
    "wof:placetype":"locality"
},
  "geometry": {"coordinates":[21.73309,51.69702],"type":"Point"}
}