{
  "type": "Feature",
  "properties": {
    "gn:admin1_code":"78.0",
    "gn:admin2_code":"1417.0",
    "gn:admin3_code":"141708.0",
    "gn:asciiname":"Wola Karczewska",
    "gn:country_code":"PL",
    "gn:dem":109,
    "gn:feature_class":"P",
    "gn:feature_code":"PPL",
    "gn:name":"Wola Karczewska",
    "gn:population":0,
    "gn:timezone":"Europe/Warsaw",
    "iso:country":"PL",
    "name:fra_x_preferred":[
        "Wola Karczewska"
    ],
    "name:pol_x_preferred":[
        "Wola Karczewska"
    ],
    "name:ukr_x_preferred":[
        "\u0412\u043e\u043b\u044f-\u041a\u0430\u0440\u0447\u0435\u0432\u0441\u044c\u043a\u0430"
    ],
    "wof:name":"Wola Karczewska",
    "wof:placetype":"locality"
},
  "geometry": {"coordinates":[21.39344,52.12657],"type":"Point"}
}