{
  "type": "Feature",
  "properties": {
    "gn:admin1_code":"81.0",
    "gn:admin2_code":"2006.0",
    "gn:admin3_code":"200605.0",
    "gn:asciiname":"Romany",
    "gn:country_code":"PL",
    "gn:dem":151,
    "gn:feature_class":"P",
    "gn:feature_code":"PPL",
    "gn:name":"Romany",
    "gn:population":0,
    "gn:timezone":"Europe/Warsaw",
    "iso:country":"PL",
    "name:ceb_x_preferred":[
        "Romany"
    ],
    "name:lit_x_preferred":[
        "Romanai"
    ],
    "name:pol_x_preferred":[
        "Romany"
    ],
    "name:ukr_x_preferred":[
        "\u0420\u043e\u043c\u0430\u043d\u0438"
    ],
    "wof:name":"Romany",
    "wof:placetype":"locality"
},
  "geometry": {"coordinates":[22.24504,53.40013],"type":"Point"}
}