{
  "type": "Feature",
  "properties": {
    "gn:admin1_code":"78.0",
    "gn:admin2_code":"1416.0",
    "gn:admin3_code":"141605.0",
    "gn:asciiname":"Kutaski Grady",
    "gn:country_code":"PL",
    "gn:dem":99,
    "gn:feature_class":"P",
    "gn:feature_code":"PPL",
    "gn:name":"Kutaski Gr\u0105dy",
    "gn:population":0,
    "gn:timezone":"Europe/Warsaw",
    "iso:country":"PL",
    "wof:name":"Kutaski Grady",
    "wof:placetype":"locality"
},
  "geometry": {"coordinates":[22.01667,52.65],"type":"Point"}
}