{
  "type": "Feature",
  "properties": {
    "gn:admin1_code":"76.0",
    "gn:admin2_code":"804.0",
    "gn:admin3_code":"80402.0",
    "gn:asciiname":"Drogomil",
    "gn:country_code":"PL",
    "gn:dem":102,
    "gn:feature_class":"P",
    "gn:feature_code":"PPL",
    "gn:name":"Drogomil",
    "gn:population":0,
    "gn:timezone":"Europe/Warsaw",
    "iso:country":"PL",
    "name:ceb_x_preferred":[
        "Drogomil"
    ],
    "name:deu_x_historical":[
        "Nenkersdorf"
    ],
    "name:deu_x_preferred":[
        "Nenkersdorf"
    ],
    "name:fra_x_preferred":[
        "Drogomil"
    ],
    "name:pol_x_preferred":[
        "Drogomil"
    ],
    "name:ukr_x_preferred":[
        "\u0414\u0440\u043e\u0491\u043e\u043c\u0456\u043b\u044c"
    ],
    "wof:name":"Drogomil",
    "wof:placetype":"locality"
},
  "geometry": {"coordinates":[15.86168,51.71703],"type":"Point"}
}