{
  "type": "Feature",
  "properties": {
    "gn:admin1_code":"84.0",
    "gn:admin2_code":"2613.0",
    "gn:admin3_code":"261304.0",
    "gn:asciiname":"Krasow",
    "gn:country_code":"PL",
    "gn:dem":242,
    "gn:feature_class":"P",
    "gn:feature_code":"PPL",
    "gn:name":"Kras\u00f3w",
    "gn:population":0,
    "gn:timezone":"Europe/Warsaw",
    "iso:country":"PL",
    "name:fra_x_preferred":[
        "Kras\u00f3w"
    ],
    "name:pol_x_preferred":[
        "Kras\u00f3w"
    ],
    "name:ukr_x_preferred":[
        "\u041a\u0440\u0430\u0441\u0443\u0432"
    ],
    "wof:name":"Krasow",
    "wof:placetype":"locality"
},
  "geometry": {"coordinates":[20.00261,50.73848],"type":"Point"}
}