{
  "type": "Feature",
  "properties": {
    "gn:admin1_code":"78.0",
    "gn:admin2_code":"1428.0",
    "gn:admin3_code":"142808.0",
    "gn:asciiname":"Debowka",
    "gn:country_code":"PL",
    "gn:dem":89,
    "gn:feature_class":"P",
    "gn:feature_code":"PPL",
    "gn:name":"D\u0119b\u00f3wka",
    "gn:population":0,
    "gn:timezone":"Europe/Warsaw",
    "iso:country":"PL",
    "name:pol_x_preferred":[
        "D\u0119b\u00f3wka"
    ],
    "name:ukr_x_preferred":[
        "\u0414\u0435\u043c\u0431\u0443\u0432\u043a\u0430"
    ],
    "name:und_x_variant":[
        "D\u0119b\u00f3wka"
    ],
    "wof:name":"Debowka",
    "wof:placetype":"locality"
},
  "geometry": {"coordinates":[20.34774,52.18631],"type":"Point"}
}