{
  "type": "Feature",
  "properties": {
    "gn:admin1_code":"79.0",
    "gn:admin2_code":"1610.0",
    "gn:admin3_code":"161003.0",
    "gn:asciiname":"Skrzypiec",
    "gn:country_code":"PL",
    "gn:dem":230,
    "gn:feature_class":"P",
    "gn:feature_code":"PPL",
    "gn:name":"Skrzypiec",
    "gn:population":0,
    "gn:timezone":"Europe/Warsaw",
    "iso:country":"PL",
    "name:pol_x_preferred":[
        "Skrzypiec"
    ],
    "name:ukr_x_preferred":[
        "\u0421\u043a\u0448\u0438\u043f\u0435\u0446\u044c"
    ],
    "wof:name":"Skrzypiec",
    "wof:placetype":"locality"
},
  "geometry": {"coordinates":[17.64832999999999,50.31467],"type":"Point"}
}