{
  "type": "Feature",
  "properties": {
    "gn:admin1_code":"86.0",
    "gn:admin2_code":"3024.0",
    "gn:admin3_code":"302406.0",
    "gn:asciiname":"Turowo",
    "gn:country_code":"PL",
    "gn:dem":97,
    "gn:feature_class":"P",
    "gn:feature_code":"PPL",
    "gn:name":"Turowo",
    "gn:population":0,
    "gn:timezone":"Europe/Warsaw",
    "iso:country":"PL",
    "name:azb_x_preferred":[
        "\u062a\u0648\u0631\u0648\u0648"
    ],
    "name:ceb_x_preferred":[
        "Turowo"
    ],
    "name:fas_x_preferred":[
        "\u062a\u0648\u0631\u0648\u0648"
    ],
    "name:fra_x_preferred":[
        "Turowo"
    ],
    "name:pol_x_preferred":[
        "Turowo"
    ],
    "name:ukr_x_preferred":[
        "\u0422\u0443\u0440\u043e\u0432\u043e"
    ],
    "name:urd_x_preferred":[
        "\u062a\u0648\u0631\u0648\u0648\u0648"
    ],
    "wof:name":"Turowo",
    "wof:placetype":"locality"
},
  "geometry": {"coordinates":[16.3056,52.4603],"type":"Point"}
}