{
  "type": "Feature",
  "properties": {
    "gn:admin1_code":"77.0",
    "gn:admin2_code":"1209.0",
    "gn:admin3_code":"120906.0",
    "gn:asciiname":"Zakliczyn",
    "gn:country_code":"PL",
    "gn:dem":358,
    "gn:feature_class":"P",
    "gn:feature_code":"PPL",
    "gn:name":"Zakliczyn",
    "gn:population":0,
    "gn:timezone":"Europe/Warsaw",
    "iso:country":"PL",
    "name:bul_x_preferred":[
        "\u0417\u0430\u043a\u043b\u0438\u0447\u0438\u043d"
    ],
    "name:ceb_x_preferred":[
        "Zakliczyn"
    ],
    "name:deu_x_preferred":[
        "Zakliczyn"
    ],
    "name:epo_x_preferred":[
        "Zakliczyn"
    ],
    "name:est_x_preferred":[
        "Zakliczyn"
    ],
    "name:fra_x_preferred":[
        "Zakliczyn"
    ],
    "name:heb_x_preferred":[
        "\u05d6\u05e7\u05dc\u05d9\u05e6'\u05d9\u05df"
    ],
    "name:hun_x_preferred":[
        "Zakliczyn"
    ],
    "name:jav_x_preferred":[
        "Zakliczyn"
    ],
    "name:lav_x_preferred":[
        "Zakli\u010dina"
    ],
    "name:msa_x_preferred":[
        "Zakliczyn"
    ],
    "name:nld_x_preferred":[
        "Zakliczyn"
    ],
    "name:pol_x_preferred":[
        "Zakliczyn"
    ],
    "name:por_x_preferred":[
        "Zakliczyn"
    ],
    "name:ron_x_preferred":[
        "Zakliczyn"
    ],
    "name:rus_x_preferred":[
        "\u0417\u0430\u043a\u043b\u0438\u0447\u0438\u043d"
    ],
    "name:slk_x_preferred":[
        "Zakliczyn"
    ],
    "name:srp_x_preferred":[
        "\u0417\u0430\u043a\u043b\u0438\u0447\u0438\u043d"
    ],
    "name:szl_x_preferred":[
        "Zakliczyn"
    ],
    "name:ukr_x_preferred":[
        "\u0417\u0430\u043a\u043b\u0438\u0447\u0438\u043d"
    ],
    "name:vie_x_preferred":[
        "Zakliczyn"
    ],
    "name:zho_x_preferred":[
        "\u624e\u514b\u5229\u7434"
    ],
    "wof:name":"Zakliczyn",
    "wof:placetype":"locality"
},
  "geometry": {"coordinates":[20.00271,49.88106],"type":"Point"}
}