{
  "type": "Feature",
  "properties": {
    "gn:admin1_code":"77.0",
    "gn:admin2_code":"1209.0",
    "gn:admin3_code":"120906.0",
    "gn:asciiname":"Zakliczyn",
    "gn:country_code":"PL",
    "gn:dem":358,
    "gn:feature_class":"P",
    "gn:feature_code":"PPL",
    "gn:name":"Zakliczyn",
    "gn:population":0,
    "gn:timezone":"Europe/Warsaw",
    "iso:country":"PL",
    "wof:name":"Zakliczyn",
    "wof:placetype":"locality"
},
  "geometry": {"coordinates":[20.00271,49.88106],"type":"Point"}
}