{
  "type": "Feature",
  "properties": {
    "iso:country":"PL",
    "name:ceb_x_preferred":[
        "Pop\u00f3w"
    ],
    "name:deu_x_preferred":[
        "Pop\u00f3w"
    ],
    "name:fra_x_preferred":[
        "Pop\u00f3w"
    ],
    "name:nld_x_preferred":[
        "Pop\u00f3w"
    ],
    "name:pol_x_preferred":[
        "Pop\u00f3w"
    ],
    "name:ukr_x_preferred":[
        "\u041f\u043e\u043f\u0443\u0432"
    ],
    "wof:coterminous":[
        1125288563
    ],
    "wof:name":"Pop\u00f3w",
    "wof:placetype":"locality"
},
  "geometry": {"coordinates":[18.9339691159253,51.0512545926017],"type":"Point"}
}