{
  "type": "Feature",
  "properties": {
    "iso:country":"PL",
    "name:pol_x_preferred":[
        "Pop\u00f3w"
    ],
    "wof:name":"Pop\u00f3w",
    "wof:placetype":"locality"
},
  "geometry": {"coordinates":[18.9339691159253,51.0512545926017],"type":"Point"}
}