{
  "type": "Feature",
  "properties": {
    "gn:admin1_code":"81.0",
    "gn:admin2_code":"2061.0",
    "gn:admin3_code":"206101.0",
    "gn:asciiname":"Mlodych",
    "gn:country_code":"PL",
    "gn:dem":127,
    "gn:feature_class":"P",
    "gn:feature_code":"PPL",
    "gn:name":"M\u0142odych",
    "gn:population":0,
    "gn:timezone":"Europe/Warsaw",
    "iso:country":"PL",
    "wof:name":"Mlodych",
    "wof:placetype":"neighbourhood"
},
  "geometry": {"coordinates":[23.12584,53.13352],"type":"Point"}
}