{
  "type": "Feature",
  "properties": {
    "gn:country":"PL",
    "gn:fcode":"PPLA3",
    "gn:population":1122,
    "iso:country":"PL",
    "name:azb_x_preferred":[
        "\u06cc\u0627\u0648\u0648\u0631\u0646\u0642\u06a9 \u067e\u0648\u0644\u0633\u06a9\u06cc"
    ],
    "name:ceb_x_preferred":[
        "Jawornik Polski"
    ],
    "name:fas_x_preferred":[
        "\u06cc\u0627\u0648\u0648\u0631\u0646\u06af\u06a9 \u067e\u0648\u0644\u0633\u06a9\u06cc"
    ],
    "name:heb_x_preferred":[
        "\u05d9\u05d0\u05d1\u05d5\u05e8\u05e0\u05d9\u05e7 \u05e4\u05d5\u05dc\u05e1\u05e7\u05d9"
    ],
    "name:nld_x_preferred":[
        "Jawornik Polski"
    ],
    "name:pol_x_preferred":[
        "Jawornik Polski"
    ],
    "name:ukr_x_preferred":[
        "\u042f\u0432\u0456\u0440\u043d\u0438\u043a \u041f\u043e\u043b\u044c\u0441\u044c\u043a\u0438\u0439"
    ],
    "qs_pg:aaroncc":"PL",
    "qs_pg:gn_country":"PL",
    "qs_pg:gn_fcode":"PPLA3",
    "qs_pg:gn_pop":1122,
    "qs_pg:name":"Jawornik Polski",
    "qs_pg:name_adm0":"Polska",
    "qs_pg:name_adm1":"Podkarpackie",
    "qs_pg:photos":58,
    "qs_pg:photos_1k":12,
    "qs_pg:photos_9k":1,
    "qs_pg:photos_9r":2,
    "qs_pg:photos_all":58,
    "qs_pg:photos_sr":2,
    "qs_pg:pop_sr":3,
    "qs_pg:qs_pg_placetype":"localadmin",
    "qs_pg:qs_pg_placetype_gp":"LocalAdmin",
    "qs_pg:woe_adm0":23424923,
    "woe:adm0_id":23424923,
    "woe:name_adm0":"Polska",
    "woe:name_adm1":"Podkarpackie",
    "woe:placetype":"LocalAdmin",
    "wof:name":"Jawornik Polski",
    "wof:placetype":"localadmin",
    "wof:population":1122
},
  "geometry": {"coordinates":[22.28868,49.89082],"type":"Point"}
}