{
  "type": "Feature",
  "properties": {
    "iso:country":"PL",
    "name:ceb_x_preferred":[
        "Grodziec"
    ],
    "name:deu_x_preferred":[
        "Grodziec"
    ],
    "name:fra_x_preferred":[
        "Grodziec"
    ],
    "name:nld_x_preferred":[
        "Grodziec"
    ],
    "name:pol_x_preferred":[
        "Grodziec"
    ],
    "name:ukr_x_preferred":[
        "\u0490\u0440\u043e\u0434\u0437\u0435\u0446\u044c"
    ],
    "qs:gn_adm0_cc":"PL",
    "qs:gn_fcode":"PPLX",
    "qs:gn_local":3102194,
    "qs:gn_nam_loc":"ciezkowice",
    "qs:gn_namadm1":"83",
    "qs:gn_name":"Grodziec",
    "qs:local_max":215,
    "qs:local_sum":215,
    "qs:localhoods":1,
    "qs:name":"Grodziec",
    "qs:name_adm0":"Polska",
    "qs:name_adm1":"Sl\u0105skie",
    "qs:name_adm2":"B\u0119dzi\u0144ski",
    "qs:name_lau":"B\u0119dzin",
    "qs:name_local":"B\u0119dzin",
    "qs:photo_max":57,
    "qs:photo_sum":215,
    "qs:placetype":"Suburb",
    "qs:quad_count":33,
    "qs:woe_adm0":23424923,
    "qs:woe_adm1":12577946,
    "qs:woe_adm2":12591384,
    "qs:woe_lau":12617346,
    "qs:woe_local":485799,
    "qs:woe_ver":"7.10.0",
    "wd:wordcount":66,
    "wof:lang":[
        "pol"
    ],
    "wof:name":"Grodziec",
    "wof:placetype":"neighbourhood"
},
  "geometry": {"coordinates":[19.094475,50.345651],"type":"Point"}
}