{
  "type": "Feature",
  "properties": {
    "gn:admin1_code":"72.0",
    "gn:admin2_code":"264.0",
    "gn:admin3_code":"26401.0",
    "gn:asciiname":"Maslice",
    "gn:country_code":"PL",
    "gn:dem":112,
    "gn:feature_class":"P",
    "gn:feature_code":"PPL",
    "gn:name":"Ma\u015blice",
    "gn:population":0,
    "gn:timezone":"Europe/Warsaw",
    "iso:country":"PL",
    "name:und_x_variant":[
        "Masselwitz",
        "Ma\u015blice"
    ],
    "wof:name":"Maslice",
    "wof:placetype":"locality"
},
  "geometry": {"coordinates":[16.92715,51.15773],"type":"Point"}
}