{
  "type": "Feature",
  "properties": {
    "gn:admin1_code":"72",
    "gn:admin2_code":"0225",
    "gn:admin3_code":"22505.0",
    "gn:asciiname":"Studniska Gorne",
    "gn:country_code":"PL",
    "gn:dem":235,
    "gn:feature_class":"P",
    "gn:feature_code":"PPL",
    "gn:name":"Studniska G\u00f3rne",
    "gn:population":0,
    "gn:timezone":"Europe/Warsaw",
    "iso:country":"PL",
    "name:deu_x_historical":[
        "Obersch\u00f6nbrunn"
    ],
    "name:deu_x_preferred":[
        "Obersch\u00f6nbrunn"
    ],
    "wof:name":"Studniska Gorne",
    "wof:placetype":"locality"
},
  "geometry": {"coordinates":[15.09955,51.11352],"type":"Point"}
}