{
  "type": "Feature",
  "properties": {
    "gn:admin1_code":"86.0",
    "gn:admin2_code":"3016.0",
    "gn:admin3_code":"301601.0",
    "gn:asciiname":"Lulin",
    "gn:country_code":"PL",
    "gn:dem":84,
    "gn:feature_class":"P",
    "gn:feature_code":"PPL",
    "gn:name":"Lulin",
    "gn:population":0,
    "gn:timezone":"Europe/Warsaw",
    "iso:country":"PL",
    "name:ceb_x_preferred":[
        "Lulin"
    ],
    "name:fra_x_preferred":[
        "Lulin"
    ],
    "name:mkd_x_preferred":[
        "\u041b\u0443\u043b\u0438\u043d"
    ],
    "name:pol_x_preferred":[
        "Lulin"
    ],
    "name:ukr_x_preferred":[
        "\u041b\u044e\u043b\u0456\u043d"
    ],
    "wof:name":"Lulin",
    "wof:placetype":"locality"
},
  "geometry": {"coordinates":[16.7078,52.57971],"type":"Point"}
}