{
  "type": "Feature",
  "properties": {
    "gn:admin1_code":"75.0",
    "gn:admin2_code":"616.0",
    "gn:admin3_code":"61601.0",
    "gn:asciiname":"Mierzwiaczka",
    "gn:country_code":"PL",
    "gn:dem":115,
    "gn:feature_class":"P",
    "gn:feature_code":"PPL",
    "gn:name":"Mierzwi\u0105czka",
    "gn:population":0,
    "gn:timezone":"Europe/Warsaw",
    "iso:country":"PL",
    "wof:name":"Mierzwiaczka",
    "wof:placetype":"neighbourhood"
},
  "geometry": {"coordinates":[21.85767,51.56801],"type":"Point"}
}