{
  "type": "Feature",
  "properties": {
    "gn:admin1_code":"80.0",
    "gn:admin2_code":"1820.0",
    "gn:admin3_code":"182003.0",
    "gn:asciiname":"Olendry",
    "gn:country_code":"PL",
    "gn:dem":147,
    "gn:feature_class":"P",
    "gn:feature_code":"PPL",
    "gn:name":"Olendry",
    "gn:population":0,
    "gn:timezone":"Europe/Warsaw",
    "iso:country":"PL",
    "wof:name":"Olendry",
    "wof:placetype":"locality"
},
  "geometry": {"coordinates":[21.85512,50.59063],"type":"Point"}
}