{
  "type": "Feature",
  "properties": {
    "gn:admin1_code":"76.0",
    "gn:admin2_code":"803.0",
    "gn:admin3_code":"80304.0",
    "gn:asciiname":"Policko",
    "gn:country_code":"PL",
    "gn:dem":53,
    "gn:feature_class":"P",
    "gn:feature_code":"PPL",
    "gn:name":"Policko",
    "gn:population":0,
    "gn:timezone":"Europe/Warsaw",
    "iso:country":"PL",
    "name:fra_x_preferred":[
        "Policko"
    ],
    "name:pol_x_preferred":[
        "Policko"
    ],
    "name:ukr_x_preferred":[
        "\u041f\u043e\u043b\u0456\u0446\u044c\u043a\u043e"
    ],
    "name:und_x_variant":[
        "Politzig",
        "Policko"
    ],
    "wof:name":"Policko",
    "wof:placetype":"locality"
},
  "geometry": {"coordinates":[15.69765,52.45596],"type":"Point"}
}