{
  "type": "Feature",
  "properties": {
    "gn:admin1_code":"84.0",
    "gn:admin2_code":"2610.0",
    "gn:admin3_code":"261002.0",
    "gn:asciiname":"Odrowazek",
    "gn:country_code":"PL",
    "gn:dem":292,
    "gn:feature_class":"P",
    "gn:feature_code":"PPL",
    "gn:name":"Odrow\u0105\u017cek",
    "gn:population":0,
    "gn:timezone":"Europe/Warsaw",
    "iso:country":"PL",
    "name:ceb_x_preferred":[
        "Odrow\u0105\u017cek"
    ],
    "name:pol_x_preferred":[
        "Odrow\u0105\u017cek"
    ],
    "name:ukr_x_preferred":[
        "\u041e\u0434\u0440\u043e\u0432\u043e\u043d\u0436\u0435\u043a"
    ],
    "wof:name":"Odrowazek",
    "wof:placetype":"locality"
},
  "geometry": {"coordinates":[20.6519,51.08934],"type":"Point"}
}