{
  "type": "Feature",
  "properties": {
    "gn:admin1_code":"84.0",
    "gn:admin2_code":"2601.0",
    "gn:admin3_code":"260106.0",
    "gn:asciiname":"Szczeglin",
    "gn:country_code":"PL",
    "gn:dem":221,
    "gn:feature_class":"P",
    "gn:feature_code":"PPL",
    "gn:name":"Szczeglin",
    "gn:population":0,
    "gn:timezone":"Europe/Warsaw",
    "iso:country":"PL",
    "name:pol_x_preferred":[
        "Szczeglin"
    ],
    "name:ukr_x_preferred":[
        "\u0429\u0435\u0491\u043b\u0456\u043d"
    ],
    "wof:name":"Szczeglin",
    "wof:placetype":"locality"
},
  "geometry": {"coordinates":[20.99419,50.41372],"type":"Point"}
}