{
  "type": "Feature",
  "properties": {
    "gn:gn_country":"PL",
    "gn:gn_fcode":"ADMD",
    "gn:gn_pop":5164000,
    "gn:population":5164000,
    "iso:country":"PL",
    "name:swe_x_preferred":[
        "Masovien"
    ],
    "qs_pg:aaroncc":"PL",
    "qs_pg:gn_country":"PL",
    "qs_pg:gn_fcode":"ADMD",
    "qs_pg:gn_pop":5164000,
    "qs_pg:name":"Wojew\u00f3dztwo Mazowieckie",
    "qs_pg:photos_9r":0,
    "qs_pg:photos_sr":0,
    "qs_pg:pop_sr":13,
    "qs_pg:qs_pg_placetype":"localadmin",
    "wof:name":"Wojew\u00f3dztwo Mazowieckie",
    "wof:placetype":"localadmin",
    "wof:population":5164000
},
  "geometry": {"coordinates":[21.01118,52.23011],"type":"Point"}
}