{
  "type": "Feature",
  "properties": {
    "gn:admin1_code":"72.0",
    "gn:admin2_code":"208.0",
    "gn:admin3_code":"20808.0",
    "gn:asciiname":"Radochow",
    "gn:country_code":"PL",
    "gn:dem":398,
    "gn:feature_class":"P",
    "gn:feature_code":"PPL",
    "gn:name":"Radoch\u00f3w",
    "gn:population":0,
    "gn:timezone":"Europe/Warsaw",
    "iso:country":"PL",
    "name:und_x_variant":[
        "Radoch\u00f3w"
    ],
    "wof:name":"Radochow",
    "wof:placetype":"locality"
},
  "geometry": {"coordinates":[16.83227999999999,50.35023],"type":"Point"}
}