{
  "type": "Feature",
  "properties": {
    "gn:admin1_code":"72.0",
    "gn:admin2_code":"208.0",
    "gn:admin3_code":"20808.0",
    "gn:asciiname":"Radochow",
    "gn:country_code":"PL",
    "gn:dem":398,
    "gn:feature_class":"P",
    "gn:feature_code":"PPL",
    "gn:name":"Radoch\u00f3w",
    "gn:population":0,
    "gn:timezone":"Europe/Warsaw",
    "iso:country":"PL",
    "name:azb_x_preferred":[
        "\u0631\u0627\u062f\u0648\u062e\u0648\u0648"
    ],
    "name:ceb_x_preferred":[
        "Radoch\u00f3w"
    ],
    "name:deu_x_preferred":[
        "Radoch\u00f3w"
    ],
    "name:fas_x_preferred":[
        "\u0631\u0627\u062f\u0648\u062e\u0648\u0648"
    ],
    "name:nld_x_preferred":[
        "Radoch\u00f3w"
    ],
    "name:pol_x_preferred":[
        "Radoch\u00f3w"
    ],
    "name:ukr_x_preferred":[
        "\u0420\u0430\u0434\u043e\u0445\u0443\u0432"
    ],
    "name:und_x_variant":[
        "Radoch\u00f3w"
    ],
    "wof:name":"Radochow",
    "wof:placetype":"locality"
},
  "geometry": {"coordinates":[16.83227999999999,50.35023],"type":"Point"}
}