{
  "type": "Feature",
  "properties": {
    "gn:admin1_code":"81.0",
    "gn:admin2_code":"2003.0",
    "gn:admin3_code":"200308.0",
    "gn:asciiname":"Niewino Borowe",
    "gn:country_code":"PL",
    "gn:dem":147,
    "gn:feature_class":"P",
    "gn:feature_code":"PPL",
    "gn:name":"Niewino Borowe",
    "gn:population":0,
    "gn:timezone":"Europe/Warsaw",
    "iso:country":"PL",
    "name:lit_x_preferred":[
        "Nevino Borov\u0117"
    ],
    "name:pol_x_preferred":[
        "Niewino Borowe"
    ],
    "name:ukr_x_preferred":[
        "\u041d\u0435\u0432\u0456\u043d\u043e-\u0411\u043e\u0440\u043e\u0432\u0435"
    ],
    "wof:name":"Niewino Borowe",
    "wof:placetype":"locality"
},
  "geometry": {"coordinates":[23.02757,52.81251],"type":"Point"}
}