{
  "type": "Feature",
  "properties": {
    "gn:admin1_code":"81.0",
    "gn:admin2_code":"2003.0",
    "gn:admin3_code":"200308.0",
    "gn:asciiname":"Niewino Borowe",
    "gn:country_code":"PL",
    "gn:dem":147,
    "gn:feature_class":"P",
    "gn:feature_code":"PPL",
    "gn:name":"Niewino Borowe",
    "gn:population":0,
    "gn:timezone":"Europe/Warsaw",
    "iso:country":"PL",
    "wof:name":"Niewino Borowe",
    "wof:placetype":"locality"
},
  "geometry": {"coordinates":[23.02757,52.81251],"type":"Point"}
}