{
  "type": "Feature",
  "properties": {
    "gn:admin1_code":"75.0",
    "gn:admin2_code":"604.0",
    "gn:admin3_code":"60408.0",
    "gn:asciiname":"Kolonia Alojzow",
    "gn:country_code":"PL",
    "gn:dem":204,
    "gn:feature_class":"P",
    "gn:feature_code":"PPL",
    "gn:name":"Kolonia Alojz\u00f3w",
    "gn:population":0,
    "gn:timezone":"Europe/Warsaw",
    "iso:country":"PL",
    "name:und_x_variant":[
        "Alojz\u00f3w",
        "Kolonia Alojz\u00f3w"
    ],
    "wof:name":"Kolonia Alojzow",
    "wof:placetype":"locality"
},
  "geometry": {"coordinates":[23.8245,50.75308],"type":"Point"}
}