{
  "type": "Feature",
  "properties": {
    "gn:admin1_code":"72.0",
    "gn:admin2_code":"217.0",
    "gn:admin3_code":"21705.0",
    "gn:asciiname":"Wyszonowice",
    "gn:country_code":"PL",
    "gn:dem":170,
    "gn:feature_class":"P",
    "gn:feature_code":"PPL",
    "gn:name":"Wyszonowice",
    "gn:population":0,
    "gn:timezone":"Europe/Warsaw",
    "iso:country":"PL",
    "name:deu_x_preferred":[
        "Wyszonowice"
    ],
    "name:pol_x_preferred":[
        "Wyszonowice"
    ],
    "name:ukr_x_preferred":[
        "\u0412\u0438\u0448\u043e\u043d\u043e\u0432\u0456\u0446\u0435"
    ],
    "wof:name":"Wyszonowice",
    "wof:placetype":"locality"
},
  "geometry": {"coordinates":[17.15876,50.7775],"type":"Point"}
}