{
  "type": "Feature",
  "properties": {
    "gn:admin1_code":"86.0",
    "gn:admin2_code":"3009.0",
    "gn:admin3_code":"300908.0",
    "gn:asciiname":"Wakowy",
    "gn:country_code":"PL",
    "gn:dem":87,
    "gn:feature_class":"P",
    "gn:feature_code":"PPL",
    "gn:name":"Wakowy",
    "gn:population":0,
    "gn:timezone":"Europe/Warsaw",
    "iso:country":"PL",
    "name:und_x_variant":[
        "Waki",
        "Wakowy"
    ],
    "wof:name":"Wakowy",
    "wof:placetype":"locality"
},
  "geometry": {"coordinates":[18.4933,52.20042],"type":"Point"}
}