{
  "type": "Feature",
  "properties": {
    "gn:population":2500,
    "iso:country":"PL",
    "name:azb_x_preferred":[
        "\u0642\u0645\u06cc\u0646\u0627 \u0645\u06cc\u0634\u0686\u06cc\u0633\u06a9\u0648"
    ],
    "name:bel_x_preferred":[
        "\u0413\u043c\u0456\u043d\u0430 \u041c\u044f\u0441\u0446\u0456\u0441\u043a\u0430"
    ],
    "name:deu_x_preferred":[
        "Gmina Mie\u015bcisko"
    ],
    "name:eng_x_preferred":[
        "Gmina Mie\u015bcisko"
    ],
    "name:eus_x_preferred":[
        "Mie\u015bcisko udalerria"
    ],
    "name:fas_x_preferred":[
        "\u06af\u0645\u06cc\u0646\u0627 \u0645\u06cc\u0634\u0686\u06cc\u0633\u06a9\u0648"
    ],
    "name:fra_x_preferred":[
        "Mie\u015bcisko"
    ],
    "name:ita_x_preferred":[
        "Mie\u015bcisko"
    ],
    "name:nan_x_preferred":[
        "Mie\u015bcisko"
    ],
    "name:nld_x_preferred":[
        "Mie\u015bcisko"
    ],
    "name:pol_x_preferred":[
        "Mie\u015bcisko"
    ],
    "name:por_x_preferred":[
        "Comuna de Mie\u015bcisko"
    ],
    "name:rus_x_preferred":[
        "\u041c\u0435\u0441\u0446\u0438\u0441\u043a\u043e"
    ],
    "name:slk_x_preferred":[
        "Gmina Mie\u015bcisko"
    ],
    "name:ukr_x_preferred":[
        "\u0490\u043c\u0456\u043d\u0430 \u041c\u0435\u0441\u044c\u0446\u0438\u0441\u044c\u043a\u043e"
    ],
    "name:war_x_preferred":[
        "Gmina Mie\u015bcisko"
    ],
    "qs:a0":"Rzeczpospolita Polska",
    "qs:a1":"*Wielkopolskie",
    "qs:a1r":"0",
    "qs:a2":"Wagrowiecki",
    "qs:adm0":"Rzeczpospolita Polska",
    "qs:la":"Mie\u015bcisko",
    "qs:la_lc":"*PL3028042",
    "qs:level":"locality",
    "qs:loc":"Mie\u015bcisko",
    "qs:loc_alt":"Miescisko",
    "qs:pop":0,
    "qs:type":"rural point-in-poly",
    "wd:wordcount":138,
    "wof:name":"Mie\u015bcisko",
    "wof:placetype":"locality",
    "wof:population":2500
},
  "geometry": {"coordinates":[17.3544971734919,52.7196918447455],"type":"Point"}
}