{
  "type": "Feature",
  "properties": {
    "gn:gn_country":"PL",
    "gn:gn_fcode":"PPL",
    "gn:gn_pop":0,
    "iso:country":"PL",
    "name:ceb_x_preferred":[
        "D\u0105browa"
    ],
    "name:deu_x_preferred":[
        "D\u0105browa"
    ],
    "name:fra_x_preferred":[
        "D\u0105browa"
    ],
    "name:heb_x_preferred":[
        "\u05d3\u05d5\u05de\u05d1\u05e8\u05d5\u05d1\u05d4"
    ],
    "name:ita_x_preferred":[
        "D\u0105browa"
    ],
    "name:lit_x_preferred":[
        "Dombrova"
    ],
    "name:nld_x_preferred":[
        "D\u0105browa"
    ],
    "name:pol_x_preferred":[
        "D\u0105browa"
    ],
    "name:rus_x_preferred":[
        "\u0414\u043e\u043c\u0431\u0440\u043e\u0432\u043e"
    ],
    "name:ukr_x_preferred":[
        "\u0414\u043e\u043c\u0431\u0440\u043e\u0432\u0430"
    ],
    "qs_pg:aaroncc":"PL",
    "qs_pg:gn_country":"PL",
    "qs_pg:gn_fcode":"PPL",
    "qs_pg:gn_pop":0,
    "qs_pg:name":"D\u0105browa",
    "qs_pg:name_adm0":"Polska",
    "qs_pg:name_adm1":"Wielkopolskie",
    "qs_pg:photos_9r":0,
    "qs_pg:photos_sr":0,
    "qs_pg:pop_sr":0,
    "qs_pg:qs_pg_placetype":"locality",
    "qs_pg:qs_pg_placetype_gp":"Town",
    "qs_pg:woe_adm0":23424923,
    "woe:adm0_id":23424923,
    "woe:name_adm0":"Polska",
    "woe:name_adm1":"Wielkopolskie",
    "woe:placetype":"Town",
    "wof:name":"D\u0105browa",
    "wof:placetype":"locality"
},
  "geometry": {"coordinates":[17.11637,52.11592],"type":"Point"}
}