{
  "type": "Feature",
  "properties": {
    "gn:admin1_code":"73.0",
    "gn:admin2_code":"415.0",
    "gn:admin3_code":"41504.0",
    "gn:asciiname":"Zlotoria",
    "gn:country_code":"PL",
    "gn:dem":41,
    "gn:feature_class":"P",
    "gn:feature_code":"PPL",
    "gn:name":"Z\u0142otoria",
    "gn:population":0,
    "gn:timezone":"Europe/Warsaw",
    "iso:country":"PL",
    "name:ceb_x_preferred":[
        "Z\u0142otoria"
    ],
    "name:eng_x_preferred":[
        "Z\u0142otoria"
    ],
    "name:nld_x_preferred":[
        "Z\u0142otoria"
    ],
    "name:pol_x_preferred":[
        "Z\u0142otoria"
    ],
    "name:rus_x_preferred":[
        "\u0417\u043b\u043e\u0442\u043e\u0440\u044f"
    ],
    "name:ukr_x_preferred":[
        "\u0417\u043b\u043e\u0442\u043e\u0440\u0456\u044f"
    ],
    "name:und_x_variant":[
        "Z\u0142otoryja"
    ],
    "wof:name":"Zlotoria",
    "wof:placetype":"locality"
},
  "geometry": {"coordinates":[18.70652,52.99475],"type":"Point"}
}