{
  "type": "Feature",
  "properties": {
    "iso:country":"PL",
    "name:azb_x_preferred":[
        "\u0642\u0645\u06cc\u0646\u0627 \u0648\u0627\u0646\u0642\u062a\u0633\u0648\u062a"
    ],
    "name:bel_x_preferred":[
        "\u041b\u0430\u043d\u044c\u0446\u0443\u0442"
    ],
    "name:deu_x_preferred":[
        "\u0141a\u0144cut"
    ],
    "name:eus_x_preferred":[
        "\u0141a\u0144cut landa-udalerria"
    ],
    "name:fas_x_preferred":[
        "\u06af\u0645\u06cc\u0646\u0627 \u0648\u0627\u0646\u06af\u062a\u0633\u0648\u062a"
    ],
    "name:fra_x_preferred":[
        "\u0141a\u0144cut"
    ],
    "name:ita_x_preferred":[
        "\u0141a\u0144cut"
    ],
    "name:nld_x_preferred":[
        "\u0141a\u0144cut"
    ],
    "name:pol_x_preferred":[
        "\u0141a\u0144cut"
    ],
    "name:rus_x_preferred":[
        "\u041b\u0430\u043d\u044c\u0446\u0443\u0442"
    ],
    "name:slk_x_preferred":[
        "Gmina \u0141a\u0144cut"
    ],
    "name:ukr_x_preferred":[
        "\u0413\u043c\u0456\u043d\u0430 \u041b\u0430\u043d\u044c\u0446\u0443\u0442"
    ],
    "name:war_x_preferred":[
        "Gmina \u0141a\u0144cut"
    ],
    "qs_pg:aaroncc":"PL",
    "qs_pg:name":"Gmina \u0141a\u0144cut",
    "qs_pg:name_adm0":"Polska",
    "qs_pg:name_adm1":"Podkarpackie",
    "qs_pg:photos":1,
    "qs_pg:photos_1k":1,
    "qs_pg:photos_9k":1,
    "qs_pg:photos_9r":1,
    "qs_pg:photos_all":15,
    "qs_pg:photos_sr":1,
    "qs_pg:pop_sr":0,
    "qs_pg:qs_pg_placetype":"localadmin",
    "qs_pg:qs_pg_placetype_gp":"LocalAdmin",
    "qs_pg:woe_adm0":23424923,
    "woe:adm0_id":23424923,
    "woe:name_adm0":"Polska",
    "woe:name_adm1":"Podkarpackie",
    "woe:placetype":"LocalAdmin",
    "wof:name":"Gmina \u0141a\u0144cut",
    "wof:placetype":"localadmin"
},
  "geometry": {"coordinates":[22.36585,50.08332],"type":"Point"}
}