{
  "type": "Feature",
  "properties": {
    "gn:admin1_code":"81.0",
    "gn:admin2_code":"2012.0",
    "gn:admin3_code":"201207.0",
    "gn:asciiname":"Trzciane",
    "gn:country_code":"PL",
    "gn:dem":177,
    "gn:feature_class":"P",
    "gn:feature_code":"PPL",
    "gn:name":"Trzciane",
    "gn:population":0,
    "gn:timezone":"Europe/Warsaw",
    "iso:country":"PL",
    "name:azb_x_preferred":[
        "\u0627\u0634\u0686\u06cc\u0627\u0646"
    ],
    "name:fas_x_preferred":[
        "\u0627\u0634\u0686\u06cc\u0627\u0646"
    ],
    "name:fra_x_preferred":[
        "Trzciane"
    ],
    "name:lit_x_preferred":[
        "T\u017ecan\u0117"
    ],
    "name:pol_x_preferred":[
        "Trzciane"
    ],
    "name:ukr_x_preferred":[
        "\u0422\u0448\u0446\u044f\u043d\u0435"
    ],
    "name:urd_x_preferred":[
        "\u0686\u0686\u0627\u0646\u06d2"
    ],
    "wof:name":"Trzciane",
    "wof:placetype":"locality"
},
  "geometry": {"coordinates":[22.82166,54.09986],"type":"Point"}
}