{
  "type": "Feature",
  "properties": {
    "gn:admin1_code":"81.0",
    "gn:admin2_code":"2012.0",
    "gn:admin3_code":"201207.0",
    "gn:asciiname":"Trzciane",
    "gn:country_code":"PL",
    "gn:dem":177,
    "gn:feature_class":"P",
    "gn:feature_code":"PPL",
    "gn:name":"Trzciane",
    "gn:population":0,
    "gn:timezone":"Europe/Warsaw",
    "iso:country":"PL",
    "wof:name":"Trzciane",
    "wof:placetype":"locality"
},
  "geometry": {"coordinates":[22.82166,54.09986],"type":"Point"}
}