{
  "type": "Feature",
  "properties": {
    "gn:admin1_code":"75.0",
    "gn:admin2_code":"607.0",
    "gn:admin3_code":"60709.0",
    "gn:asciiname":"Kolonia Rudnik Szlachecki",
    "gn:country_code":"PL",
    "gn:dem":234,
    "gn:feature_class":"P",
    "gn:feature_code":"PPL",
    "gn:name":"Kolonia Rudnik Szlachecki",
    "gn:population":0,
    "gn:timezone":"Europe/Warsaw",
    "iso:country":"PL",
    "wof:name":"Kolonia Rudnik Szlachecki",
    "wof:placetype":"locality"
},
  "geometry": {"coordinates":[22.30344,50.96724],"type":"Point"}
}