{
  "type": "Feature",
  "properties": {
    "gn:admin1_code":"74.0",
    "gn:admin2_code":"1008.0",
    "gn:admin3_code":"100806.0",
    "gn:asciiname":"Wrzaca",
    "gn:country_code":"PL",
    "gn:dem":174,
    "gn:feature_class":"P",
    "gn:feature_code":"PPL",
    "gn:name":"Wrz\u0105ca",
    "gn:population":0,
    "gn:timezone":"Europe/Warsaw",
    "iso:country":"PL",
    "name:fra_x_preferred":[
        "Wrz\u0105ca"
    ],
    "name:pol_x_preferred":[
        "Wrz\u0105ca"
    ],
    "name:ukr_x_preferred":[
        "\u0412\u0436\u043e\u043d\u0446\u0430"
    ],
    "wof:name":"Wrzaca",
    "wof:placetype":"locality"
},
  "geometry": {"coordinates":[19.20822,51.73947],"type":"Point"}
}