{
  "type": "Feature",
  "properties": {
    "gn:admin1_code":"79.0",
    "gn:admin2_code":"1609.0",
    "gn:admin3_code":"160907.0",
    "gn:asciiname":"Piotrowa",
    "gn:country_code":"PL",
    "gn:dem":186,
    "gn:feature_class":"P",
    "gn:feature_code":"PPL",
    "gn:name":"Piotrowa",
    "gn:population":0,
    "gn:timezone":"Europe/Warsaw",
    "iso:country":"PL",
    "name:azb_x_preferred":[
        "\u067e\u06cc\u0648\u062a\u0631\u0648\u0648\u0627"
    ],
    "name:deu_x_preferred":[
        "Piotrowa"
    ],
    "name:fas_x_preferred":[
        "\u067e\u06cc\u0648\u062a\u0631\u0648\u0648\u0627"
    ],
    "name:pol_x_preferred":[
        "Piotrowa"
    ],
    "name:ukr_x_preferred":[
        "\u041f\u0439\u043e\u0442\u0440\u043e\u0432\u0430"
    ],
    "wof:name":"Piotrowa",
    "wof:placetype":"locality"
},
  "geometry": {"coordinates":[17.57653,50.64563],"type":"Point"}
}