{
  "type": "Feature",
  "properties": {
    "iso:country":"PL",
    "name:eng_x_preferred":[
        "Mokra"
    ],
    "name:pol_x_preferred":[
        "Mokra"
    ],
    "wof:name":"Mokra",
    "wof:placetype":"neighbourhood"
},
  "geometry": {"coordinates":[16.8364766622055,51.17350104111245],"type":"Point"}
}