{
  "type": "Feature",
  "properties": {
    "iso:country":"PL",
    "name:bul_x_preferred":[
        "\u041c\u043e\u043a\u0440\u0430"
    ],
    "name:ceb_x_preferred":[
        "Mokra"
    ],
    "name:eng_x_preferred":[
        "Mokra"
    ],
    "name:fra_x_preferred":[
        "Mokra"
    ],
    "name:hun_x_preferred":[
        "Mokra"
    ],
    "name:nld_x_preferred":[
        "Mokra"
    ],
    "name:pol_x_preferred":[
        "Mokra"
    ],
    "name:slv_x_preferred":[
        "Mokra"
    ],
    "name:swe_x_preferred":[
        "Mokra"
    ],
    "name:ukr_x_preferred":[
        "\u041c\u043e\u043a\u0440\u0430"
    ],
    "wof:name":"Mokra",
    "wof:placetype":"neighbourhood"
},
  "geometry": {"coordinates":[16.8364766622055,51.17350104111245],"type":"Point"}
}