{
  "type": "Feature",
  "properties": {
    "gn:admin1_code":"78.0",
    "gn:admin2_code":"1422.0",
    "gn:admin3_code":"142204.0",
    "gn:asciiname":"Wolka Kobylaki",
    "gn:country_code":"PL",
    "gn:dem":124,
    "gn:feature_class":"P",
    "gn:feature_code":"PPL",
    "gn:name":"W\u00f3lka Kobylaki",
    "gn:population":0,
    "gn:timezone":"Europe/Warsaw",
    "iso:country":"PL",
    "name:und_x_variant":[
        "Kobylaki W\u00f3lka",
        "W\u00f3lka Kobylaki"
    ],
    "wof:name":"Wolka Kobylaki",
    "wof:placetype":"locality"
},
  "geometry": {"coordinates":[20.95245,53.13506999999999],"type":"Point"}
}