{
  "type": "Feature",
  "properties": {
    "gn:admin1_code":"75.0",
    "gn:admin2_code":"616.0",
    "gn:admin3_code":"61602.0",
    "gn:asciiname":"Wylezin",
    "gn:country_code":"PL",
    "gn:dem":166,
    "gn:feature_class":"P",
    "gn:feature_code":"PPL",
    "gn:name":"Wylezin",
    "gn:population":0,
    "gn:timezone":"Europe/Warsaw",
    "iso:country":"PL",
    "name:fra_x_preferred":[
        "Wylezin"
    ],
    "name:pol_x_preferred":[
        "Wylezin"
    ],
    "name:ukr_x_preferred":[
        "\u0412\u0438\u043b\u0435\u0437\u0456\u043d"
    ],
    "wof:name":"Wylezin",
    "wof:placetype":"locality"
},
  "geometry": {"coordinates":[21.91463,51.70629],"type":"Point"}
}