{
  "type": "Feature",
  "properties": {
    "gn:admin1_code":"87.0",
    "gn:admin2_code":"3202.0",
    "gn:admin3_code":"320201.0",
    "gn:asciiname":"Zieleniewo",
    "gn:country_code":"PL",
    "gn:dem":88,
    "gn:feature_class":"P",
    "gn:feature_code":"PPL",
    "gn:name":"Zieleniewo",
    "gn:population":0,
    "gn:timezone":"Europe/Warsaw",
    "iso:country":"PL",
    "name:pol_x_preferred":[
        "Zieleniewo"
    ],
    "name:ukr_x_preferred":[
        "\u0417\u0435\u043b\u0435\u043d\u0435\u0432\u043e"
    ],
    "name:vie_x_preferred":[
        "Zieleniewo"
    ],
    "wof:name":"Zieleniewo",
    "wof:placetype":"locality"
},
  "geometry": {"coordinates":[15.62203,53.10888000000001],"type":"Point"}
}