{
  "type": "Feature",
  "properties": {
    "gn:admin1_code":"84.0",
    "gn:admin2_code":"2602.0",
    "gn:admin3_code":"260209.0",
    "gn:asciiname":"Wodacz",
    "gn:country_code":"PL",
    "gn:dem":271,
    "gn:feature_class":"P",
    "gn:feature_code":"PPL",
    "gn:name":"Wodacz",
    "gn:population":0,
    "gn:timezone":"Europe/Warsaw",
    "iso:country":"PL",
    "name:pol_x_preferred":[
        "Wodacz"
    ],
    "name:ukr_x_preferred":[
        "\u0412\u043e\u0434\u0430\u0447"
    ],
    "wof:name":"Wodacz",
    "wof:placetype":"locality"
},
  "geometry": {"coordinates":[20.15936,50.48637],"type":"Point"}
}