{
  "type": "Feature",
  "properties": {
    "gn:admin1_code":"81.0",
    "gn:admin2_code":"2013.0",
    "gn:admin3_code":"201305.0",
    "gn:asciiname":"Kropiwnica Gajki",
    "gn:country_code":"PL",
    "gn:dem":124,
    "gn:feature_class":"P",
    "gn:feature_code":"PPL",
    "gn:name":"Kropiwnica Gajki",
    "gn:population":0,
    "gn:timezone":"Europe/Warsaw",
    "iso:country":"PL",
    "name:und_x_variant":[
        "Kropiewnica Gajki",
        "Kropiwnica Gajki"
    ],
    "wof:name":"Kropiwnica Gajki",
    "wof:placetype":"locality"
},
  "geometry": {"coordinates":[22.73742,53.08159000000001],"type":"Point"}
}