{
  "type": "Feature",
  "properties": {
    "gn:admin1_code":"81.0",
    "gn:admin2_code":"2013.0",
    "gn:admin3_code":"201305.0",
    "gn:asciiname":"Kropiwnica Gajki",
    "gn:country_code":"PL",
    "gn:dem":124,
    "gn:feature_class":"P",
    "gn:feature_code":"PPL",
    "gn:name":"Kropiwnica Gajki",
    "gn:population":0,
    "gn:timezone":"Europe/Warsaw",
    "iso:country":"PL",
    "name:azb_x_preferred":[
        "\u06a9\u0631\u0648\u067e\u06cc\u0648\u0646\u0642\u062a\u0633\u0627-\u0642\u0627\u06cc\u06a9\u06cc"
    ],
    "name:fas_x_preferred":[
        "\u06a9\u0631\u0648\u067e\u06cc\u0648\u0646\u06af\u062a\u0633\u0627-\u06af\u0627\u06cc\u06a9\u06cc"
    ],
    "name:fra_x_preferred":[
        "Kropiwnica-Gajki"
    ],
    "name:lit_x_preferred":[
        "Kropivnica Gaikai"
    ],
    "name:pol_x_preferred":[
        "Kropiewnica-Gajki"
    ],
    "name:ukr_x_preferred":[
        "\u041a\u0440\u043e\u043f\u0435\u0432\u043d\u0438\u0446\u044f-\u0490\u0430\u0439\u043a\u0456"
    ],
    "name:und_x_variant":[
        "Kropiewnica Gajki",
        "Kropiwnica Gajki"
    ],
    "wof:name":"Kropiwnica Gajki",
    "wof:placetype":"locality"
},
  "geometry": {"coordinates":[22.73742,53.08159000000001],"type":"Point"}
}