{
  "type": "Feature",
  "properties": {
    "iso:country":"PL",
    "name:ces_x_preferred":[
        "4. polsk\u00e1 fotbalov\u00e1 liga"
    ],
    "name:eng_x_preferred":[
        "Chodak\u00f3w"
    ],
    "name:eng_x_variant":[
        "IV liga"
    ],
    "name:ita_x_preferred":[
        "IV liga"
    ],
    "name:ita_x_variant":[
        "V Liga"
    ],
    "name:nld_x_preferred":[
        "IV liga"
    ],
    "name:pol_x_colloquial":[
        "Chodakow",
        "Chodakow Fabryka"
    ],
    "name:pol_x_preferred":[
        "Chodak\u00f3w",
        "IV liga polska w pi\u0142ce no\u017cnej"
    ],
    "name:pol_x_variant":[
        "Chodak\u00f3w Fabryka"
    ],
    "name:por_x_preferred":[
        "Campeonato Polon\u00eas de Futebol 5\u00aa Divis\u00e3o"
    ],
    "name:rus_x_preferred":[
        "\u0425\u043e\u0434\u0430\u043a\u0443\u0432"
    ],
    "qs:gn_fcode":"PPLX",
    "qs:gn_local":0,
    "qs:gn_namadm1":"78",
    "qs:gn_name":"Chodak\u00f3w",
    "qs:local_max":176,
    "qs:local_sum":176,
    "qs:localhoods":1,
    "qs:name":"Chodak\u00f3w",
    "qs:name_adm0":"Polska",
    "qs:name_adm1":"Mazowieckie",
    "qs:name_adm2":"Sochaczewski",
    "qs:name_lau":"Gmina Sochaczew",
    "qs:name_local":"Gmina Sochaczew",
    "qs:photo_max":84,
    "qs:photo_sum":176,
    "qs:placetype":"Suburb",
    "qs:quad_count":13,
    "qs:woe_adm0":23424923,
    "qs:woe_adm1":12577941,
    "qs:woe_adm2":12591301,
    "qs:woe_lau":24548297,
    "qs:woe_local":24548297,
    "qs:woe_ver":"7.10.0",
    "wd:wordcount":108,
    "wof:lang":[
        "pol"
    ],
    "wof:name":"Chodak\u00f3w",
    "wof:placetype":"neighbourhood"
},
  "geometry": {"coordinates":[20.289204,52.255855],"type":"Point"}
}