{
  "type": "Feature",
  "properties": {
    "gn:population":1400,
    "iso:country":"PL",
    "name:ceb_x_preferred":[
        "P\u0105tn\u00f3w"
    ],
    "name:deu_x_historical":[
        "Panthenau"
    ],
    "name:deu_x_preferred":[
        "Panthenau"
    ],
    "name:deu_x_variant":[
        "P\u0105tn\u00f3w"
    ],
    "name:eng_x_preferred":[
        "P\u0105tn\u00f3w"
    ],
    "name:frr_x_preferred":[
        "P\u0105tn\u00f3w"
    ],
    "name:nld_x_preferred":[
        "P\u0105tn\u00f3w"
    ],
    "name:pol_x_preferred":[
        "P\u0105tn\u00f3w"
    ],
    "name:ukr_x_preferred":[
        "\u041f\u043e\u043d\u0442\u043d\u0443\u0432"
    ],
    "qs:a0":"Rzeczpospolita Polska",
    "qs:a1":"*L\u00f3dzkie",
    "qs:a1r":"0",
    "qs:a2":"Wielunski",
    "qs:adm0":"Rzeczpospolita Polska",
    "qs:la":"P\u0105tn\u00f3w",
    "qs:la_lc":"*PL1017072",
    "qs:level":"locality",
    "qs:loc":"P\u0105tn\u00f3w",
    "qs:loc_alt":"Patnow",
    "qs:pop":0,
    "qs:type":"rural point-in-poly",
    "wd:wordcount":29,
    "wof:coterminous":[
        1477752683
    ],
    "wof:name":"P\u0105tn\u00f3w",
    "wof:placetype":"locality",
    "wof:population":1400
},
  "geometry": {"coordinates":[18.6561652184127,51.0939741059962],"type":"Point"}
}