{
  "type": "Feature",
  "properties": {
    "gn:admin1_code":"77.0",
    "gn:admin2_code":"1204.0",
    "gn:admin3_code":"120403.0",
    "gn:asciiname":"Wola Greboszowska",
    "gn:country_code":"PL",
    "gn:dem":170,
    "gn:feature_class":"P",
    "gn:feature_code":"PPL",
    "gn:name":"Wola Gr\u0119boszowska",
    "gn:population":0,
    "gn:timezone":"Europe/Warsaw",
    "iso:country":"PL",
    "name:pol_x_preferred":[
        "Wola Gr\u0119boszowska"
    ],
    "name:ukr_x_preferred":[
        "\u0412\u043e\u043b\u044f-\u0490\u0440\u0435\u043c\u0431\u043e\u0448\u043e\u0432\u0441\u044c\u043a\u0430"
    ],
    "wof:name":"Wola Greboszowska",
    "wof:placetype":"locality"
},
  "geometry": {"coordinates":[20.79231,50.25149],"type":"Point"}
}