{
  "type": "Feature",
  "properties": {
    "gn:admin1_code":"82.0",
    "gn:admin2_code":"2201.0",
    "gn:admin3_code":"220110.0",
    "gn:asciiname":"Ciemno",
    "gn:country_code":"PL",
    "gn:dem":179,
    "gn:feature_class":"P",
    "gn:feature_code":"PPL",
    "gn:name":"Ciemno",
    "gn:population":0,
    "gn:timezone":"Europe/Warsaw",
    "iso:country":"PL",
    "name:ceb_x_preferred":[
        "Ciemno"
    ],
    "name:csb_x_preferred":[
        "Cemno"
    ],
    "name:pol_x_preferred":[
        "Ciemno"
    ],
    "name:ukr_x_preferred":[
        "\u0426\u0435\u043c\u043d\u043e"
    ],
    "wof:name":"Ciemno",
    "wof:placetype":"locality"
},
  "geometry": {"coordinates":[17.34243,54.08155],"type":"Point"}
}