{
  "type": "Feature",
  "properties": {
    "gn:admin1_code":"75.0",
    "gn:admin2_code":"620.0",
    "gn:admin3_code":"62006.0",
    "gn:asciiname":"Gdeszyn",
    "gn:country_code":"PL",
    "gn:dem":226,
    "gn:feature_class":"P",
    "gn:feature_code":"PPL",
    "gn:name":"Gdeszyn",
    "gn:population":0,
    "gn:timezone":"Europe/Warsaw",
    "iso:country":"PL",
    "name:fra_x_preferred":[
        "Gdeszyn"
    ],
    "name:pol_x_preferred":[
        "Gdeszyn"
    ],
    "name:ukr_x_preferred":[
        "\u0490\u0434\u0435\u0448\u0438\u043d"
    ],
    "wof:name":"Gdeszyn",
    "wof:placetype":"locality"
},
  "geometry": {"coordinates":[23.63829,50.77637],"type":"Point"}
}