{
  "type": "Feature",
  "properties": {
    "gn:admin1_code":"80.0",
    "gn:admin2_code":"1811.0",
    "gn:admin3_code":"181104.0",
    "gn:asciiname":"Ostrowek",
    "gn:country_code":"PL",
    "gn:dem":154,
    "gn:feature_class":"P",
    "gn:feature_code":"PPL",
    "gn:name":"Ostr\u00f3wek",
    "gn:population":0,
    "gn:timezone":"Europe/Warsaw",
    "iso:country":"PL",
    "wof:name":"Ostrowek",
    "wof:placetype":"locality"
},
  "geometry": {"coordinates":[21.35622,50.42974],"type":"Point"}
}