{
  "type": "Feature",
  "properties": {
    "gn:country":"PL",
    "gn:fcode":"PPL",
    "gn:population":238,
    "iso:country":"PL",
    "name:und_x_variant":[
        "Lubienka Szymanowo"
    ],
    "qs_pg:aaroncc":"PL",
    "qs_pg:gn_country":"PL",
    "qs_pg:gn_fcode":"PPL",
    "qs_pg:gn_pop":238,
    "qs_pg:name":"Lubienka",
    "qs_pg:name_adm0":"Polska",
    "qs_pg:name_adm1":"Lubelskie",
    "qs_pg:photos_9r":0,
    "qs_pg:photos_sr":0,
    "qs_pg:pop_sr":2,
    "qs_pg:qs_pg_placetype":"locality",
    "qs_pg:qs_pg_placetype_gp":"Town",
    "qs_pg:woe_adm0":23424923,
    "woe:adm0_id":23424923,
    "woe:name_adm0":"Polska",
    "woe:name_adm1":"Lubelskie",
    "woe:placetype":"Town",
    "wof:name":"Lubienka",
    "wof:placetype":"locality",
    "wof:population":238
},
  "geometry": {"coordinates":[23.21188,51.89863],"type":"Point"}
}