{
  "type": "Feature",
  "properties": {
    "gn:admin1_code":"74.0",
    "gn:admin2_code":"1016.0",
    "gn:admin3_code":"101604.0",
    "gn:asciiname":"Wolka Jagielczynska",
    "gn:country_code":"PL",
    "gn:dem":175,
    "gn:feature_class":"P",
    "gn:feature_code":"PPL",
    "gn:name":"W\u00f3lka Jagielczy\u0144ska",
    "gn:population":0,
    "gn:timezone":"Europe/Warsaw",
    "iso:country":"PL",
    "name:pol_x_preferred":[
        "W\u00f3lka Jagielczy\u0144ska"
    ],
    "name:ukr_x_preferred":[
        "\u0412\u0443\u043b\u044c\u043a\u0430-\u042f\u0491\u0435\u043b\u044c\u0447\u0438\u043d\u0441\u044c\u043a\u0430"
    ],
    "name:und_x_variant":[
        "W\u00f3lka Jagielcza\u0144ska"
    ],
    "wof:name":"Wolka Jagielczynska",
    "wof:placetype":"locality"
},
  "geometry": {"coordinates":[20.18298,51.67852],"type":"Point"}
}