{
  "type": "Feature",
  "properties": {
    "gn:admin1_code":"76.0",
    "gn:admin2_code":"809.0",
    "gn:admin3_code":"80905.0",
    "gn:asciiname":"Sobolice",
    "gn:country_code":"PL",
    "gn:dem":110,
    "gn:feature_class":"P",
    "gn:feature_code":"PPL",
    "gn:name":"Sobolice",
    "gn:population":0,
    "gn:timezone":"Europe/Warsaw",
    "iso:country":"PL",
    "name:fra_x_preferred":[
        "Sobolice"
    ],
    "name:pol_x_preferred":[
        "Sobolice"
    ],
    "name:ukr_x_preferred":[
        "\u0421\u043e\u0431\u043e\u043b\u0456\u0446\u0435"
    ],
    "wof:name":"Sobolice",
    "wof:placetype":"locality"
},
  "geometry": {"coordinates":[15.31779,51.79517],"type":"Point"}
}