{
  "type": "Feature",
  "properties": {
    "gn:admin1_code":"78.0",
    "gn:admin2_code":"1425.0",
    "gn:admin3_code":"142502.0",
    "gn:asciiname":"Niemianowice",
    "gn:country_code":"PL",
    "gn:dem":165,
    "gn:feature_class":"P",
    "gn:feature_code":"PPL",
    "gn:name":"Niemianowice",
    "gn:population":0,
    "gn:timezone":"Europe/Warsaw",
    "iso:country":"PL",
    "name:fra_x_preferred":[
        "Niemianowice"
    ],
    "name:pol_x_preferred":[
        "Niemianowice"
    ],
    "name:ukr_x_preferred":[
        "\u041d\u0435\u043c\u044f\u043d\u043e\u0432\u0456\u0446\u0435"
    ],
    "wof:name":"Niemianowice",
    "wof:placetype":"locality"
},
  "geometry": {"coordinates":[21.33193,51.38383],"type":"Point"}
}