{
  "type": "Feature",
  "properties": {
    "gn:admin1_code":"81.0",
    "gn:admin2_code":"2007.0",
    "gn:admin3_code":"200705.0",
    "gn:asciiname":"Olszyny",
    "gn:country_code":"PL",
    "gn:dem":125,
    "gn:feature_class":"P",
    "gn:feature_code":"PPL",
    "gn:name":"Olszyny",
    "gn:population":0,
    "gn:timezone":"Europe/Warsaw",
    "iso:country":"PL",
    "name:lit_x_preferred":[
        "Ol\u0161inai"
    ],
    "name:pol_x_preferred":[
        "Olszyny"
    ],
    "name:rus_x_preferred":[
        "\u041e\u043b\u044c\u0448\u0438\u043d\u044b"
    ],
    "name:ukr_x_preferred":[
        "\u041e\u043b\u044c\u0448\u0438\u043d\u0438"
    ],
    "wof:name":"Olszyny",
    "wof:placetype":"locality"
},
  "geometry": {"coordinates":[22.24906,53.21399],"type":"Point"}
}