{
  "type": "Feature",
  "properties": {
    "gn:admin1_code":"76",
    "gn:admin2_code":"0808",
    "gn:admin3_code":"80805.0",
    "gn:asciiname":"Kupienino",
    "gn:country_code":"PL",
    "gn:dem":75,
    "gn:feature_class":"P",
    "gn:feature_code":"PPL",
    "gn:name":"Kupienino",
    "gn:population":0,
    "gn:timezone":"Europe/Warsaw",
    "iso:country":"PL",
    "name:deu_x_historical":[
        "Koppen"
    ],
    "name:deu_x_preferred":[
        "Koppen"
    ],
    "wof:name":"Kupienino",
    "wof:placetype":"locality"
},
  "geometry": {"coordinates":[15.60973,52.25938],"type":"Point"}
}