{
  "type": "Feature",
  "properties": {
    "gn:admin1_code":"81.0",
    "gn:admin2_code":"2002.0",
    "gn:admin3_code":"200206.0",
    "gn:asciiname":"Lapy Osse",
    "gn:cc2":"PL",
    "gn:country_code":"PL",
    "gn:dem":125,
    "gn:feature_class":"P",
    "gn:feature_code":"PPL",
    "gn:name":"\u0141apy Osse",
    "gn:population":0,
    "gn:timezone":"Europe/Warsaw",
    "iso:country":"PL",
    "name:und_x_variant":[
        "Osse",
        "\u0141apy Osse"
    ],
    "wof:name":"Lapy Osse",
    "wof:placetype":"locality"
},
  "geometry": {"coordinates":[22.83333,52.98333],"type":"Point"}
}