{
  "type": "Feature",
  "properties": {
    "gn:admin1_code":"78.0",
    "gn:admin2_code":"1418.0",
    "gn:admin3_code":"141801.0",
    "gn:asciiname":"Cedrowice",
    "gn:country_code":"PL",
    "gn:dem":125,
    "gn:feature_class":"P",
    "gn:feature_code":"PPL",
    "gn:name":"Cedrowice",
    "gn:population":0,
    "gn:timezone":"Europe/Warsaw",
    "iso:country":"PL",
    "name:fra_x_preferred":[
        "Cendrowice"
    ],
    "name:pol_x_preferred":[
        "Cendrowice"
    ],
    "name:ukr_x_preferred":[
        "\u0426\u0435\u043d\u0434\u0440\u043e\u0432\u0456\u0446\u0435"
    ],
    "name:und_x_variant":[
        "Cedrowice"
    ],
    "wof:name":"Cedrowice",
    "wof:placetype":"locality"
},
  "geometry": {"coordinates":[21.12953,51.96881],"type":"Point"}
}