{
  "type": "Feature",
  "properties": {
    "gn:admin1_code":"73.0",
    "gn:admin2_code":"416.0",
    "gn:admin3_code":"41601.0",
    "gn:asciiname":"Kowalskie Bloto Wielkie",
    "gn:country_code":"PL",
    "gn:dem":105,
    "gn:feature_class":"P",
    "gn:feature_code":"PPL",
    "gn:name":"Kowalskie B\u0142oto Wielkie",
    "gn:population":0,
    "gn:timezone":"Europe/Warsaw",
    "iso:country":"PL",
    "wof:name":"Kowalskie Bloto Wielkie",
    "wof:placetype":"locality"
},
  "geometry": {"coordinates":[17.98231000000001,53.63214],"type":"Point"}
}