{
  "type": "Feature",
  "properties": {
    "gn:admin1_code":"73.0",
    "gn:admin2_code":"407.0",
    "gn:admin3_code":"40704.0",
    "gn:asciiname":"Borkowo",
    "gn:country_code":"PL",
    "gn:dem":83,
    "gn:feature_class":"P",
    "gn:feature_code":"PPL",
    "gn:name":"Borkowo",
    "gn:population":0,
    "gn:timezone":"Europe/Warsaw",
    "iso:country":"PL",
    "wof:name":"Borkowo",
    "wof:placetype":"locality"
},
  "geometry": {"coordinates":[18.19947,52.83648],"type":"Point"}
}