{
  "type": "Feature",
  "properties": {
    "gn:admin1_code":"73.0",
    "gn:admin2_code":"407.0",
    "gn:admin3_code":"40704.0",
    "gn:asciiname":"Borkowo",
    "gn:country_code":"PL",
    "gn:dem":83,
    "gn:feature_class":"P",
    "gn:feature_code":"PPL",
    "gn:name":"Borkowo",
    "gn:population":0,
    "gn:timezone":"Europe/Warsaw",
    "iso:country":"PL",
    "name:pol_x_preferred":[
        "Borkowo"
    ],
    "name:ukr_x_preferred":[
        "\u0411\u043e\u0440\u043a\u043e\u0432\u043e"
    ],
    "wof:name":"Borkowo",
    "wof:placetype":"locality"
},
  "geometry": {"coordinates":[18.19947,52.83648],"type":"Point"}
}