{
  "type": "Feature",
  "properties": {
    "iso:country":"PL",
    "name:ast_x_preferred":[
        "\u0141\u0105kta G\u00f3rna"
    ],
    "name:eng_x_preferred":[
        "\u0141\u0105kta G\u00f3rna"
    ],
    "name:fra_x_preferred":[
        "\u0141\u0105kta G\u00f3rna"
    ],
    "name:pol_x_preferred":[
        "\u0141\u0105kta G\u00f3rna"
    ],
    "name:ukr_x_preferred":[
        "\u041b\u043e\u043d\u043a\u0442\u0430-\u0490\u0443\u0440\u043d\u0430"
    ],
    "qs:a0":"Rzeczpospolita Polska",
    "qs:a1":"*Malopolskie",
    "qs:a1r":"0",
    "qs:a2":"Bochenski",
    "qs:adm0":"Rzeczpospolita Polska",
    "qs:la_lc":"*",
    "qs:level":"locality",
    "qs:loc":"\u0141\u0105kta G\u00f3rna",
    "qs:loc_alt":"Lakta Gorna",
    "qs:pop":0,
    "qs:type":"buffered point",
    "wd:wordcount":127,
    "wof:name":"\u0141\u0105kta G\u00f3rna",
    "wof:placetype":"locality"
},
  "geometry": {"coordinates":[20.435139,49.838554],"type":"Point"}
}