{
  "type": "Feature",
  "properties": {
    "gn:admin1_code":"81.0",
    "gn:admin2_code":"2001.0",
    "gn:admin3_code":"200104.0",
    "gn:asciiname":"Rakowicze",
    "gn:country_code":"PL",
    "gn:dem":153,
    "gn:feature_class":"P",
    "gn:feature_code":"PPL",
    "gn:name":"Rakowicze",
    "gn:population":0,
    "gn:timezone":"Europe/Warsaw",
    "iso:country":"PL",
    "name:eng_x_preferred":[
        "Rakowicze"
    ],
    "name:rus_x_preferred":[
        "\u0420\u0430\u043a\u043e\u0432\u0438\u0447\u0435"
    ],
    "wof:name":"Rakowicze",
    "wof:placetype":"locality"
},
  "geometry": {"coordinates":[23.56356,53.73905],"type":"Point"}
}