{
  "type": "Feature",
  "properties": {
    "gn:admin1_code":"84.0",
    "gn:admin2_code":"2601.0",
    "gn:admin3_code":"260102.0",
    "gn:asciiname":"Ruda",
    "gn:country_code":"PL",
    "gn:dem":195,
    "gn:feature_class":"P",
    "gn:feature_code":"PPL",
    "gn:name":"Ruda",
    "gn:population":0,
    "gn:timezone":"Europe/Warsaw",
    "iso:country":"PL",
    "wof:name":"Ruda",
    "wof:placetype":"locality"
},
  "geometry": {"coordinates":[20.9178,50.54867],"type":"Point"}
}