{
  "type": "Feature",
  "properties": {
    "gn:admin1_code":"81.0",
    "gn:admin2_code":"2008.0",
    "gn:admin3_code":"200806.0",
    "gn:asciiname":"Ciesze",
    "gn:country_code":"PL",
    "gn:dem":150,
    "gn:feature_class":"P",
    "gn:feature_code":"PPL",
    "gn:name":"Ciesze",
    "gn:population":0,
    "gn:timezone":"Europe/Warsaw",
    "iso:country":"PL",
    "name:azb_x_preferred":[
        "\u0686\u06cc\u0634\u0647"
    ],
    "name:ceb_x_preferred":[
        "Ciesze"
    ],
    "name:fas_x_preferred":[
        "\u0686\u06cc\u0634\u0647"
    ],
    "name:fra_x_preferred":[
        "Ciesze"
    ],
    "name:lit_x_preferred":[
        "Ce\u0161\u0117"
    ],
    "name:nld_x_preferred":[
        "Ciesze"
    ],
    "name:pol_x_preferred":[
        "Ciesze"
    ],
    "name:ukr_x_preferred":[
        "\u0426\u0435\u0448\u0435"
    ],
    "wof:name":"Ciesze",
    "wof:placetype":"locality"
},
  "geometry": {"coordinates":[22.83268,53.38814],"type":"Point"}
}