{
  "type": "Feature",
  "properties": {
    "gn:admin1_code":"86.0",
    "gn:admin2_code":"3013.0",
    "gn:admin3_code":"301307.0",
    "gn:asciiname":"Ujazdowo",
    "gn:country_code":"PL",
    "gn:dem":68,
    "gn:feature_class":"P",
    "gn:feature_code":"PPL",
    "gn:name":"Ujazdowo",
    "gn:population":0,
    "gn:timezone":"Europe/Warsaw",
    "iso:country":"PL",
    "name:pol_x_preferred":[
        "Ujazdowo"
    ],
    "name:ukr_x_preferred":[
        "\u0423\u044f\u0437\u0434\u043e\u0432\u043e"
    ],
    "wof:name":"Ujazdowo",
    "wof:placetype":"locality"
},
  "geometry": {"coordinates":[16.33967,51.95305],"type":"Point"}
}