{
  "type": "Feature",
  "properties": {
    "iso:country":"PL",
    "name:azb_x_preferred":[
        "\u0648\u0628\u0627"
    ],
    "name:ces_x_preferred":[
        "\u0141eba"
    ],
    "name:csb_x_preferred":[
        "\u0141eba"
    ],
    "name:deu_x_preferred":[
        "\u0141eba"
    ],
    "name:dsb_x_preferred":[
        "\u0141eba"
    ],
    "name:epo_x_preferred":[
        "\u0141eba"
    ],
    "name:eus_x_preferred":[
        "\u0141eba"
    ],
    "name:fas_x_preferred":[
        "\u0648\u0628\u0627"
    ],
    "name:fra_x_preferred":[
        "\u0141eba"
    ],
    "name:ita_x_preferred":[
        "\u0141eba"
    ],
    "name:jav_x_preferred":[
        "\u0141eba"
    ],
    "name:lav_x_preferred":[
        "Leba"
    ],
    "name:lit_x_preferred":[
        "Leba"
    ],
    "name:msa_x_preferred":[
        "\u0141eba"
    ],
    "name:nld_x_preferred":[
        "\u0141eba"
    ],
    "name:pol_x_preferred":[
        "\u0141eba"
    ],
    "name:por_x_preferred":[
        "\u0141eba"
    ],
    "name:ron_x_preferred":[
        "\u0141eba"
    ],
    "name:rus_x_preferred":[
        "\u041b\u0435\u0431\u0430"
    ],
    "name:slk_x_preferred":[
        "\u0141eba"
    ],
    "name:spa_x_preferred":[
        "\u0141eba"
    ],
    "name:srp_x_preferred":[
        "\u041b\u0435\u0431\u0430"
    ],
    "name:swe_x_preferred":[
        "\u0141eba"
    ],
    "name:ukr_x_preferred":[
        "\u041b\u0435\u0431\u0430"
    ],
    "name:vie_x_preferred":[
        "\u0141eba"
    ],
    "name:war_x_preferred":[
        "\u0141eba"
    ],
    "qs_pg:aaroncc":"PL",
    "qs_pg:name":"\u0141eba",
    "qs_pg:name_adm0":"Polska",
    "qs_pg:name_adm1":"Pomorskie",
    "qs_pg:photos":215,
    "qs_pg:photos_1k":44,
    "qs_pg:photos_9k":7,
    "qs_pg:photos_9r":7,
    "qs_pg:photos_all":1482,
    "qs_pg:photos_sr":4,
    "qs_pg:pop_sr":0,
    "qs_pg:qs_pg_placetype":"localadmin",
    "qs_pg:qs_pg_placetype_gp":"LocalAdmin",
    "qs_pg:woe_adm0":23424923,
    "woe:adm0_id":23424923,
    "woe:name_adm0":"Polska",
    "woe:name_adm1":"Pomorskie",
    "woe:placetype":"LocalAdmin",
    "wof:name":"\u0141eba",
    "wof:placetype":"localadmin"
},
  "geometry": {"coordinates":[17.553749,54.762076],"type":"Point"}
}