{
  "type": "Feature",
  "properties": {
    "gn:admin1_code":"84.0",
    "gn:admin2_code":"2601.0",
    "gn:admin3_code":"260101.0",
    "gn:asciiname":"Owczary",
    "gn:country_code":"PL",
    "gn:dem":217,
    "gn:feature_class":"P",
    "gn:feature_code":"PPL",
    "gn:name":"Owczary",
    "gn:population":0,
    "gn:timezone":"Europe/Warsaw",
    "iso:country":"PL",
    "name:pol_x_preferred":[
        "Owczary"
    ],
    "name:ukr_x_preferred":[
        "\u041e\u0432\u0447\u0430\u0440\u0438"
    ],
    "wof:name":"Owczary",
    "wof:placetype":"neighbourhood"
},
  "geometry": {"coordinates":[20.75,50.45],"type":"Point"}
}