{
  "type": "Feature",
  "properties": {
    "gn:admin1_code":"84.0",
    "gn:admin2_code":"2612.0",
    "gn:admin3_code":"261202.0",
    "gn:asciiname":"Wolica",
    "gn:country_code":"PL",
    "gn:dem":168,
    "gn:feature_class":"P",
    "gn:feature_code":"PPL",
    "gn:name":"Wolica",
    "gn:population":0,
    "gn:timezone":"Europe/Warsaw",
    "iso:country":"PL",
    "name:pol_x_preferred":[
        "Wolica"
    ],
    "name:por_x_preferred":[
        "Wolica"
    ],
    "name:ukr_x_preferred":[
        "\u0412\u043e\u043b\u0438\u0446\u044f"
    ],
    "wof:name":"Wolica",
    "wof:placetype":"locality"
},
  "geometry": {"coordinates":[21.17942,50.45333],"type":"Point"}
}