{
  "type": "Feature",
  "properties": {
    "gn:admin1_code":"78.0",
    "gn:admin2_code":"1427.0",
    "gn:admin3_code":"142706.0",
    "gn:asciiname":"Gojsk",
    "gn:country_code":"PL",
    "gn:dem":122,
    "gn:feature_class":"P",
    "gn:feature_code":"PPL",
    "gn:name":"G\u00f3jsk",
    "gn:population":0,
    "gn:timezone":"Europe/Warsaw",
    "iso:country":"PL",
    "name:azb_x_preferred":[
        "\u0642\u0648\u06cc\u0633\u06a9"
    ],
    "name:eng_x_preferred":[
        "G\u00f3jsk"
    ],
    "name:fas_x_preferred":[
        "\u06af\u0648\u06cc\u0633\u06a9"
    ],
    "name:fra_x_preferred":[
        "G\u00f3jsk"
    ],
    "name:ita_x_preferred":[
        "G\u00f3jsk"
    ],
    "name:pol_x_preferred":[
        "G\u00f3jsk"
    ],
    "name:rus_x_preferred":[
        "\u0413\u0443\u0439\u0441\u043a"
    ],
    "name:ukr_x_preferred":[
        "\u0490\u0443\u0439\u0441\u044c\u043a"
    ],
    "wof:name":"Gojsk",
    "wof:placetype":"locality"
},
  "geometry": {"coordinates":[19.52597,52.90071999999999],"type":"Point"}
}