{
  "type": "Feature",
  "properties": {
    "gn:admin1_code":"78.0",
    "gn:admin2_code":"1419.0",
    "gn:admin3_code":"141907.0",
    "gn:asciiname":"Ludwikow",
    "gn:country_code":"PL",
    "gn:dem":90,
    "gn:feature_class":"P",
    "gn:feature_code":"PPL",
    "gn:name":"Ludwik\u00f3w",
    "gn:population":0,
    "gn:timezone":"Europe/Warsaw",
    "iso:country":"PL",
    "name:fra_x_preferred":[
        "Ludwik\u00f3w"
    ],
    "name:pol_x_preferred":[
        "Ludwik\u00f3w"
    ],
    "name:ukr_x_preferred":[
        "\u041b\u044e\u0434\u0432\u0456\u043a\u0443\u0432"
    ],
    "wof:name":"Ludwikow",
    "wof:placetype":"locality"
},
  "geometry": {"coordinates":[19.56459,52.4626],"type":"Point"}
}