{
  "type": "Feature",
  "properties": {
    "gn:admin1_code":"86.0",
    "gn:admin2_code":"3003.0",
    "gn:admin3_code":"300308.0",
    "gn:asciiname":"Potrzymowo",
    "gn:country_code":"PL",
    "gn:dem":120,
    "gn:feature_class":"P",
    "gn:feature_code":"PPL",
    "gn:name":"Potrzymowo",
    "gn:population":0,
    "gn:timezone":"Europe/Warsaw",
    "iso:country":"PL",
    "name:fra_x_preferred":[
        "Potrzymowo"
    ],
    "name:pol_x_preferred":[
        "Potrzymowo"
    ],
    "name:ukr_x_preferred":[
        "\u041f\u043e\u0442\u0448\u0438\u043c\u043e\u0432\u043e"
    ],
    "wof:name":"Potrzymowo",
    "wof:placetype":"locality"
},
  "geometry": {"coordinates":[17.62277000000001,52.44313],"type":"Point"}
}