{
  "type": "Feature",
  "properties": {
    "gn:admin1_code":"79.0",
    "gn:admin2_code":"1605.0",
    "gn:admin3_code":"160504.0",
    "gn:asciiname":"Grocholub",
    "gn:country_code":"PL",
    "gn:dem":177,
    "gn:feature_class":"P",
    "gn:feature_code":"PPL",
    "gn:name":"Grocholub",
    "gn:population":0,
    "gn:timezone":"Europe/Warsaw",
    "iso:country":"PL",
    "name:deu_x_preferred":[
        "Grocholub"
    ],
    "name:pol_x_preferred":[
        "Grocholub"
    ],
    "name:ukr_x_preferred":[
        "\u0490\u0440\u043e\u0445\u043e\u043b\u044e\u0431"
    ],
    "wof:name":"Grocholub",
    "wof:placetype":"locality"
},
  "geometry": {"coordinates":[18.01746,50.3947],"type":"Point"}
}