{
  "type": "Feature",
  "properties": {
    "gn:admin1_code":"78.0",
    "gn:admin2_code":"1404.0",
    "gn:admin3_code":"140405.0",
    "gn:asciiname":"Janki",
    "gn:country_code":"PL",
    "gn:dem":104,
    "gn:feature_class":"P",
    "gn:feature_code":"PPL",
    "gn:name":"Janki",
    "gn:population":0,
    "gn:timezone":"Europe/Warsaw",
    "iso:country":"PL",
    "name:ceb_x_preferred":[
        "Janki"
    ],
    "name:deu_x_preferred":[
        "Janki"
    ],
    "name:fra_x_preferred":[
        "Janki"
    ],
    "name:lit_x_preferred":[
        "Jankai"
    ],
    "name:nld_x_preferred":[
        "Janki"
    ],
    "name:pol_x_preferred":[
        "Janki"
    ],
    "wof:name":"Janki",
    "wof:placetype":"locality"
},
  "geometry": {"coordinates":[19.66312000000001,52.32943],"type":"Point"}
}