{
  "type": "Feature",
  "properties": {
    "gn:admin1_code":"80.0",
    "gn:admin2_code":"1820.0",
    "gn:admin3_code":"182003.0",
    "gn:asciiname":"Krawce",
    "gn:country_code":"PL",
    "gn:dem":156,
    "gn:feature_class":"P",
    "gn:feature_code":"PPL",
    "gn:name":"Krawce",
    "gn:population":0,
    "gn:timezone":"Europe/Warsaw",
    "iso:country":"PL",
    "name:pol_x_preferred":[
        "Krawce"
    ],
    "name:ukr_x_preferred":[
        "\u041a\u0440\u0430\u0432\u0446\u0435"
    ],
    "wof:name":"Krawce",
    "wof:placetype":"locality"
},
  "geometry": {"coordinates":[21.91645,50.52102],"type":"Point"}
}