{
  "type": "Feature",
  "properties": {
    "gn:admin1_code":"85.0",
    "gn:admin2_code":"2807.0",
    "gn:admin3_code":"280705.0",
    "gn:asciiname":"Ludwichowo",
    "gn:country_code":"PL",
    "gn:dem":126,
    "gn:feature_class":"P",
    "gn:feature_code":"PPL",
    "gn:name":"Ludwichowo",
    "gn:population":0,
    "gn:timezone":"Europe/Warsaw",
    "iso:country":"PL",
    "wof:name":"Ludwichowo",
    "wof:placetype":"locality"
},
  "geometry": {"coordinates":[19.67034,53.48775],"type":"Point"}
}