{
  "type": "Feature",
  "properties": {
    "gn:admin1_code":"87.0",
    "gn:admin2_code":"3211.0",
    "gn:admin3_code":"321101.0",
    "gn:asciiname":"Wolczkowo",
    "gn:country_code":"PL",
    "gn:dem":23,
    "gn:feature_class":"P",
    "gn:feature_code":"PPL",
    "gn:name":"Wo\u0142czkowo",
    "gn:population":0,
    "gn:timezone":"Europe/Warsaw",
    "iso:country":"PL",
    "name:azb_x_preferred":[
        "\u0648\u0648\u0648\u0686\u06a9\u0648\u0648\u0648"
    ],
    "name:deu_x_preferred":[
        "Wo\u0142czkowo"
    ],
    "name:fas_x_preferred":[
        "\u0648\u0648\u0648\u0686\u06a9\u0648\u0648\u0648"
    ],
    "name:nld_x_preferred":[
        "Wo\u0142czkowo"
    ],
    "name:pol_x_preferred":[
        "Wo\u0142czkowo"
    ],
    "name:ukr_x_preferred":[
        "\u0412\u043e\u043b\u0447\u043a\u043e\u0432\u043e"
    ],
    "name:vie_x_preferred":[
        "Wo\u0142czkowo"
    ],
    "wof:name":"Wolczkowo",
    "wof:placetype":"locality"
},
  "geometry": {"coordinates":[14.44511,53.47582],"type":"Point"}
}