{
  "type": "Feature",
  "properties": {
    "gn:admin1_code":"87.0",
    "gn:admin2_code":"3211.0",
    "gn:admin3_code":"321101.0",
    "gn:asciiname":"Wolczkowo",
    "gn:country_code":"PL",
    "gn:dem":23,
    "gn:feature_class":"P",
    "gn:feature_code":"PPL",
    "gn:name":"Wo\u0142czkowo",
    "gn:population":0,
    "gn:timezone":"Europe/Warsaw",
    "iso:country":"PL",
    "name:und_x_variant":[
        "Wo\u0142czkowo"
    ],
    "wof:name":"Wolczkowo",
    "wof:placetype":"locality"
},
  "geometry": {"coordinates":[14.44511,53.47582],"type":"Point"}
}