{
  "type": "Feature",
  "properties": {
    "gn:admin1_code":"77.0",
    "gn:admin2_code":"1204.0",
    "gn:admin3_code":"120407.0",
    "gn:asciiname":"Delastowice",
    "gn:cc2":"PL",
    "gn:country_code":"PL",
    "gn:dem":166,
    "gn:feature_class":"P",
    "gn:feature_code":"PPL",
    "gn:name":"Delastowice",
    "gn:population":0,
    "gn:timezone":"Europe/Warsaw",
    "iso:country":"PL",
    "name:ceb_x_preferred":[
        "Delastowice"
    ],
    "name:pol_x_preferred":[
        "Delastowice"
    ],
    "name:ukr_x_preferred":[
        "\u0414\u0435\u043b\u044f\u0441\u0442\u043e\u0432\u0456\u0446\u0435"
    ],
    "name:und_x_variant":[
        "Dalastowice",
        "Delastowice"
    ],
    "wof:name":"Delastowice",
    "wof:placetype":"locality"
},
  "geometry": {"coordinates":[21.02509,50.29932],"type":"Point"}
}