{
  "type": "Feature",
  "properties": {
    "gn:admin1_code":"81.0",
    "gn:admin2_code":"2012.0",
    "gn:admin3_code":"201208.0",
    "gn:asciiname":"Wojponie",
    "gn:country_code":"PL",
    "gn:dem":193,
    "gn:feature_class":"P",
    "gn:feature_code":"PPL",
    "gn:name":"Wojponie",
    "gn:population":0,
    "gn:timezone":"Europe/Warsaw",
    "iso:country":"PL",
    "name:lit_x_preferred":[
        "Vaiponia"
    ],
    "name:pol_x_preferred":[
        "Wojponie"
    ],
    "name:ukr_x_preferred":[
        "\u0412\u043e\u0439\u043f\u043e\u043d\u0435"
    ],
    "wof:name":"Wojponie",
    "wof:placetype":"locality"
},
  "geometry": {"coordinates":[23.14141,54.29374],"type":"Point"}
}