{
  "type": "Feature",
  "properties": {
    "gn:admin1_code":"85.0",
    "gn:admin2_code":"2812.0",
    "gn:admin3_code":"281202.0",
    "gn:asciiname":"Gaj",
    "gn:country_code":"PL",
    "gn:dem":100,
    "gn:feature_class":"P",
    "gn:feature_code":"PPL",
    "gn:name":"Gaj",
    "gn:population":0,
    "gn:timezone":"Europe/Warsaw",
    "iso:country":"PL",
    "name:bos_x_preferred":[
        "Gaj"
    ],
    "name:ceb_x_preferred":[
        "Gaj"
    ],
    "name:fra_x_preferred":[
        "Gaj"
    ],
    "name:hrv_x_preferred":[
        "Gaj"
    ],
    "name:hun_x_preferred":[
        "Gaj"
    ],
    "name:hye_x_preferred":[
        "\u0533\u0561\u0575"
    ],
    "name:lit_x_preferred":[
        "Gajas"
    ],
    "name:nld_x_preferred":[
        "Gaj"
    ],
    "name:pol_x_preferred":[
        "Gaj"
    ],
    "name:slv_x_preferred":[
        "Gaj"
    ],
    "name:srp_x_preferred":[
        "\u0413\u0430\u0458"
    ],
    "name:swe_x_preferred":[
        "Gaj"
    ],
    "name:ukr_x_preferred":[
        "\u0490\u0430\u0439"
    ],
    "wof:name":"Gaj",
    "wof:placetype":"locality"
},
  "geometry": {"coordinates":[19.37874,53.46059],"type":"Point"}
}