{
  "type": "Feature",
  "properties": {
    "gn:admin1_code":"78.0",
    "gn:admin2_code":"1416.0",
    "gn:admin3_code":"141605.0",
    "gn:asciiname":"Zachy Pawly",
    "gn:country_code":"PL",
    "gn:dem":110,
    "gn:feature_class":"P",
    "gn:feature_code":"PPL",
    "gn:name":"Zachy Paw\u0142y",
    "gn:population":0,
    "gn:timezone":"Europe/Warsaw",
    "iso:country":"PL",
    "name:und_x_variant":[
        "Zachy",
        "Zachy Paw\u0142y"
    ],
    "wof:name":"Zachy Pawly",
    "wof:placetype":"locality"
},
  "geometry": {"coordinates":[21.99102,52.76154],"type":"Point"}
}