{
  "type": "Feature",
  "properties": {
    "gn:admin1_code":"78.0",
    "gn:admin2_code":"1416.0",
    "gn:admin3_code":"141605.0",
    "gn:asciiname":"Zachy Pawly",
    "gn:country_code":"PL",
    "gn:dem":110,
    "gn:feature_class":"P",
    "gn:feature_code":"PPL",
    "gn:name":"Zachy Paw\u0142y",
    "gn:population":0,
    "gn:timezone":"Europe/Warsaw",
    "iso:country":"PL",
    "name:fra_x_preferred":[
        "\u017bachy-Paw\u0142y"
    ],
    "name:pol_x_preferred":[
        "\u017bachy-Paw\u0142y"
    ],
    "name:ukr_x_preferred":[
        "\u0416\u0430\u0445\u0438-\u041f\u0430\u0432\u043b\u0438"
    ],
    "name:und_x_variant":[
        "Zachy",
        "Zachy Paw\u0142y"
    ],
    "name:urd_x_preferred":[
        "\u0632\u0627\u0686\u06c1\u06d2-\u067e\u0648\u0648\u06cc"
    ],
    "wof:name":"Zachy Pawly",
    "wof:placetype":"locality"
},
  "geometry": {"coordinates":[21.99102,52.76154],"type":"Point"}
}