{
  "type": "Feature",
  "properties": {
    "gn:admin1_code":"84.0",
    "gn:admin2_code":"2605.0",
    "gn:admin3_code":"260507.0",
    "gn:asciiname":"Miedzierza",
    "gn:country_code":"PL",
    "gn:dem":238,
    "gn:feature_class":"P",
    "gn:feature_code":"PPL",
    "gn:name":"Miedzierza",
    "gn:population":0,
    "gn:timezone":"Europe/Warsaw",
    "iso:country":"PL",
    "name:ceb_x_preferred":[
        "Miedzierza"
    ],
    "name:nld_x_preferred":[
        "Miedzierza"
    ],
    "name:pol_x_preferred":[
        "Miedzierza"
    ],
    "name:ukr_x_preferred":[
        "\u041c\u0435\u0434\u0437\u0435\u0436\u0430"
    ],
    "wof:name":"Miedzierza",
    "wof:placetype":"locality"
},
  "geometry": {"coordinates":[20.39026,51.08439],"type":"Point"}
}