{
  "type": "Feature",
  "properties": {
    "gn:admin1_code":"86.0",
    "gn:admin2_code":"3028.0",
    "gn:admin3_code":"302807.0",
    "gn:asciiname":"Kobylec",
    "gn:country_code":"PL",
    "gn:dem":86,
    "gn:feature_class":"P",
    "gn:feature_code":"PPL",
    "gn:name":"Kobylec",
    "gn:population":0,
    "gn:timezone":"Europe/Warsaw",
    "iso:country":"PL",
    "name:ceb_x_preferred":[
        "Kobylec"
    ],
    "name:fra_x_preferred":[
        "Kobylec"
    ],
    "name:pol_x_preferred":[
        "Kobylec"
    ],
    "name:ukr_x_preferred":[
        "\u041a\u043e\u0431\u0438\u043b\u0435\u0446\u044c"
    ],
    "wof:name":"Kobylec",
    "wof:placetype":"locality"
},
  "geometry": {"coordinates":[17.19631,52.84976],"type":"Point"}
}