{
  "type": "Feature",
  "properties": {
    "gn:admin1_code":"77.0",
    "gn:admin2_code":"1210.0",
    "gn:admin3_code":"121009.0",
    "gn:asciiname":"Brzyna",
    "gn:country_code":"PL",
    "gn:dem":445,
    "gn:feature_class":"P",
    "gn:feature_code":"PPL",
    "gn:name":"Brzyna",
    "gn:population":0,
    "gn:timezone":"Europe/Warsaw",
    "iso:country":"PL",
    "name:ceb_x_preferred":[
        "Brzyna"
    ],
    "name:nld_x_preferred":[
        "Brzyna"
    ],
    "name:pol_x_preferred":[
        "Brzyna"
    ],
    "name:ukr_x_preferred":[
        "\u0411\u0436\u0438\u043d\u0430"
    ],
    "wof:name":"Brzyna",
    "wof:placetype":"locality"
},
  "geometry": {"coordinates":[20.48177,49.52529000000001],"type":"Point"}
}