{
  "type": "Feature",
  "properties": {
    "gn:admin1_code":"85.0",
    "gn:admin2_code":"2810.0",
    "gn:admin3_code":"281004.0",
    "gn:asciiname":"Pierslawek",
    "gn:country_code":"PL",
    "gn:dem":141,
    "gn:feature_class":"P",
    "gn:feature_code":"PPL",
    "gn:name":"Piers\u0142awek",
    "gn:population":0,
    "gn:timezone":"Europe/Warsaw",
    "iso:country":"PL",
    "name:deu_x_preferred":[
        "Piers\u0142awek"
    ],
    "name:fra_x_preferred":[
        "Piers\u0142awek"
    ],
    "name:pol_x_preferred":[
        "Piers\u0142awek"
    ],
    "name:und_x_variant":[
        "Kleinort"
    ],
    "wof:name":"Pierslawek",
    "wof:placetype":"locality"
},
  "geometry": {"coordinates":[21.37577000000001,53.75545],"type":"Point"}
}