{
  "type": "Feature",
  "properties": {
    "gn:admin1_code":"73.0",
    "gn:admin2_code":"418.0",
    "gn:admin3_code":"41813.0",
    "gn:asciiname":"Skoki Male",
    "gn:country_code":"PL",
    "gn:dem":59,
    "gn:feature_class":"P",
    "gn:feature_code":"PPL",
    "gn:name":"Skoki Ma\u0142e",
    "gn:population":0,
    "gn:timezone":"Europe/Warsaw",
    "iso:country":"PL",
    "name:pol_x_preferred":[
        "Skoki Ma\u0142e"
    ],
    "name:ukr_x_preferred":[
        "\u0421\u043a\u043e\u043a\u0456-\u041c\u0430\u043b\u0456"
    ],
    "wof:name":"Skoki Male",
    "wof:placetype":"locality"
},
  "geometry": {"coordinates":[19.40443,52.60826],"type":"Point"}
}