{
  "type": "Feature",
  "properties": {
    "gn:admin1_code":"73.0",
    "gn:admin2_code":"405.0",
    "gn:admin3_code":"40506.0",
    "gn:asciiname":"Sitno",
    "gn:country_code":"PL",
    "gn:dem":72,
    "gn:feature_class":"P",
    "gn:feature_code":"PPL",
    "gn:name":"Sitno",
    "gn:population":0,
    "gn:timezone":"Europe/Warsaw",
    "iso:country":"PL",
    "name:pol_x_preferred":[
        "Sitno"
    ],
    "name:ukr_x_preferred":[
        "\u0421\u0456\u0442\u043d\u043e"
    ],
    "wof:name":"Sitno",
    "wof:placetype":"locality"
},
  "geometry": {"coordinates":[19.09947,53.04085],"type":"Point"}
}