{
  "type": "Feature",
  "properties": {
    "gn:admin1_code":"75.0",
    "gn:asciiname":"Chalupki",
    "gn:country_code":"PL",
    "gn:dem":214,
    "gn:feature_class":"P",
    "gn:feature_code":"PPL",
    "gn:name":"Cha\u0142upki",
    "gn:population":0,
    "gn:timezone":"Europe/Warsaw",
    "iso:country":"PL",
    "wof:name":"Chalupki",
    "wof:placetype":"locality"
},
  "geometry": {"coordinates":[22.64151,50.34682],"type":"Point"}
}