{
  "type": "Feature",
  "properties": {
    "gn:admin1_code":"82.0",
    "gn:admin2_code":"2262.0",
    "gn:admin3_code":"226201.0",
    "gn:asciiname":"Dzialki Lesne",
    "gn:country_code":"PL",
    "gn:dem":58,
    "gn:feature_class":"P",
    "gn:feature_code":"PPL",
    "gn:name":"Dzia\u0142ki Le\u015bne",
    "gn:population":0,
    "gn:timezone":"Europe/Warsaw",
    "iso:country":"PL",
    "wof:name":"Dzialki Lesne",
    "wof:placetype":"locality"
},
  "geometry": {"coordinates":[18.52784,54.51577],"type":"Point"}
}