{
  "type": "Feature",
  "properties": {
    "gn:admin1_code":"72.0",
    "gn:admin2_code":"209.0",
    "gn:admin3_code":"20902.0",
    "gn:asciiname":"Niedzwiedzice",
    "gn:country_code":"PL",
    "gn:dem":128,
    "gn:feature_class":"P",
    "gn:feature_code":"PPL",
    "gn:name":"Nied\u017awiedzice",
    "gn:population":0,
    "gn:timezone":"Europe/Warsaw",
    "iso:country":"PL",
    "name:azb_x_preferred":[
        "\u0646\u0642\u0686\u0648\u06cc\u062c\u062a\u0633\u0647"
    ],
    "name:deu_x_preferred":[
        "Nied\u017awiedzice"
    ],
    "name:fas_x_preferred":[
        "\u0646\u06af\u0686\u0648\u06cc\u062c\u062a\u0633\u0647"
    ],
    "name:nld_x_preferred":[
        "Nied\u017awiedzice"
    ],
    "name:pol_x_preferred":[
        "Nied\u017awiedzice"
    ],
    "name:ukr_x_preferred":[
        "\u041d\u0435\u0434\u0437\u044c\u0432\u0435\u0434\u0437\u0456\u0446\u0435"
    ],
    "name:und_x_variant":[
        "Nied\u017awiedzice"
    ],
    "wof:name":"Niedzwiedzice",
    "wof:placetype":"locality"
},
  "geometry": {"coordinates":[16.0241,51.28671],"type":"Point"}
}