{
  "type": "Feature",
  "properties": {
    "gn:admin1_code":"72.0",
    "gn:admin2_code":"209.0",
    "gn:admin3_code":"20902.0",
    "gn:asciiname":"Niedzwiedzice",
    "gn:country_code":"PL",
    "gn:dem":128,
    "gn:feature_class":"P",
    "gn:feature_code":"PPL",
    "gn:name":"Nied\u017awiedzice",
    "gn:population":0,
    "gn:timezone":"Europe/Warsaw",
    "iso:country":"PL",
    "name:und_x_variant":[
        "Nied\u017awiedzice"
    ],
    "wof:name":"Niedzwiedzice",
    "wof:placetype":"locality"
},
  "geometry": {"coordinates":[16.0241,51.28671],"type":"Point"}
}