{
  "type": "Feature",
  "properties": {
    "gn:admin1_code":"85.0",
    "gn:admin2_code":"2804.0",
    "gn:admin3_code":"280409.0",
    "gn:asciiname":"Lecze",
    "gn:cc2":"PL",
    "gn:country_code":"PL",
    "gn:dem":129,
    "gn:feature_class":"P",
    "gn:feature_code":"PPL",
    "gn:name":"\u0141\u0119cze",
    "gn:population":0,
    "gn:timezone":"Europe/Warsaw",
    "iso:country":"PL",
    "name:ceb_x_preferred":[
        "\u0141\u0119cze"
    ],
    "name:nld_x_preferred":[
        "\u0141\u0119cze"
    ],
    "name:pol_x_preferred":[
        "\u0141\u0119cze"
    ],
    "name:ukr_x_preferred":[
        "\u041b\u0435\u043d\u0447\u0435"
    ],
    "name:und_x_variant":[
        "Lenzen",
        "\u0141\u0119cze"
    ],
    "wof:name":"Lecze",
    "wof:placetype":"locality"
},
  "geometry": {"coordinates":[19.47121,54.26964],"type":"Point"}
}