{
  "type": "Feature",
  "properties": {
    "gn:admin1_code":"84.0",
    "gn:admin2_code":"2607.0",
    "gn:admin3_code":"260701.0",
    "gn:asciiname":"Katy Denkowskie",
    "gn:country_code":"PL",
    "gn:dem":184,
    "gn:feature_class":"P",
    "gn:feature_code":"PPL",
    "gn:name":"K\u0105ty Denkowskie",
    "gn:population":0,
    "gn:timezone":"Europe/Warsaw",
    "iso:country":"PL",
    "wof:name":"Katy Denkowskie",
    "wof:placetype":"locality"
},
  "geometry": {"coordinates":[21.45,50.93333],"type":"Point"}
}