{
  "type": "Feature",
  "properties": {
    "iso:country":"PL",
    "name:eng_x_preferred":[
        "Strzyza Dolna"
    ],
    "name:pol_x_preferred":[
        "Strzy\u017ca Dolna"
    ],
    "wof:name":"Strzyza Dolna",
    "wof:placetype":"neighbourhood"
},
  "geometry": {"coordinates":[18.5966619339503,54.38462089487674],"type":"Point"}
}