{
  "type": "Feature",
  "properties": {
    "gn:admin1_code":"84.0",
    "gn:admin2_code":"2605.0",
    "gn:admin3_code":"260502.0",
    "gn:asciiname":"Milakow",
    "gn:country_code":"PL",
    "gn:dem":245,
    "gn:feature_class":"P",
    "gn:feature_code":"PPL",
    "gn:name":"Mi\u0142ak\u00f3w",
    "gn:population":0,
    "gn:timezone":"Europe/Warsaw",
    "iso:country":"PL",
    "name:ceb_x_preferred":[
        "Mi\u0142ak\u00f3w"
    ],
    "name:pol_x_preferred":[
        "Mi\u0142ak\u00f3w"
    ],
    "name:ukr_x_preferred":[
        "\u041c\u0456\u043b\u0430\u043a\u0443\u0432"
    ],
    "wof:name":"Milakow",
    "wof:placetype":"locality"
},
  "geometry": {"coordinates":[20.45817000000001,51.28071],"type":"Point"}
}