{
  "type": "Feature",
  "properties": {
    "gn:admin1_code":"74.0",
    "gn:admin2_code":"1010.0",
    "gn:admin3_code":"101010.0",
    "gn:asciiname":"Mzurki",
    "gn:country_code":"PL",
    "gn:dem":214,
    "gn:feature_class":"P",
    "gn:feature_code":"PPL",
    "gn:name":"Mzurki",
    "gn:population":0,
    "gn:timezone":"Europe/Warsaw",
    "iso:country":"PL",
    "wof:name":"Mzurki",
    "wof:placetype":"locality"
},
  "geometry": {"coordinates":[19.49274,51.42231],"type":"Point"}
}