{
  "type": "Feature",
  "properties": {
    "gn:admin1_code":"78.0",
    "gn:admin2_code":"1421.0",
    "gn:admin3_code":"142104.0",
    "gn:asciiname":"Komorow",
    "gn:country_code":"PL",
    "gn:dem":108,
    "gn:feature_class":"P",
    "gn:feature_code":"PPL",
    "gn:name":"Komor\u00f3w",
    "gn:population":5136,
    "gn:timezone":"Europe/Warsaw",
    "iso:country":"PL",
    "name:ceb_x_preferred":[
        "Komor\u00f3w"
    ],
    "name:fra_x_preferred":[
        "Komor\u00f3w"
    ],
    "name:nld_x_preferred":[
        "Komor\u00f3w"
    ],
    "name:pol_x_preferred":[
        "Komor\u00f3w"
    ],
    "name:ukr_x_preferred":[
        "\u041a\u043e\u043c\u043e\u0440\u0443\u0432"
    ],
    "wof:name":"Komorow",
    "wof:placetype":"neighbourhood",
    "wof:population":5136
},
  "geometry": {"coordinates":[20.81566,52.1456],"type":"Point"}
}