{
  "type": "Feature",
  "properties": {
    "gn:admin1_code":"78.0",
    "gn:admin2_code":"1414.0",
    "gn:admin3_code":"141402.0",
    "gn:asciiname":"Sowia Wola",
    "gn:country_code":"PL",
    "gn:dem":73,
    "gn:feature_class":"P",
    "gn:feature_code":"PPL",
    "gn:name":"Sowia Wola",
    "gn:population":0,
    "gn:timezone":"Europe/Warsaw",
    "iso:country":"PL",
    "name:fra_x_preferred":[
        "Sowia Wola"
    ],
    "name:pol_x_preferred":[
        "Sowia Wola"
    ],
    "name:ukr_x_preferred":[
        "\u0421\u043e\u0432\u044f-\u0412\u043e\u043b\u044f"
    ],
    "wof:name":"Sowia Wola",
    "wof:placetype":"locality"
},
  "geometry": {"coordinates":[20.63516,52.35972],"type":"Point"}
}