{
  "type": "Feature",
  "properties": {
    "gn:admin1_code":"82.0",
    "gn:admin2_code":"2208.0",
    "gn:admin3_code":"220804.0",
    "gn:asciiname":"Zelazkowo",
    "gn:country_code":"PL",
    "gn:dem":17,
    "gn:feature_class":"P",
    "gn:feature_code":"PPL",
    "gn:name":"\u017belazkowo",
    "gn:population":0,
    "gn:timezone":"Europe/Warsaw",
    "iso:country":"PL",
    "name:ceb_x_preferred":[
        "\u017belazkowo"
    ],
    "name:pol_x_preferred":[
        "\u017belazkowo"
    ],
    "name:ukr_x_preferred":[
        "\u0416\u0435\u043b\u044f\u0437\u043a\u043e\u0432\u043e"
    ],
    "wof:name":"Zelazkowo",
    "wof:placetype":"locality"
},
  "geometry": {"coordinates":[17.61107999999999,54.54996],"type":"Point"}
}