{
  "type": "Feature",
  "properties": {
    "gn:admin1_code":"82.0",
    "gn:admin2_code":"2208.0",
    "gn:admin3_code":"220804.0",
    "gn:asciiname":"Zelazkowo",
    "gn:country_code":"PL",
    "gn:dem":17,
    "gn:feature_class":"P",
    "gn:feature_code":"PPL",
    "gn:name":"\u017belazkowo",
    "gn:population":0,
    "gn:timezone":"Europe/Warsaw",
    "iso:country":"PL",
    "wof:name":"Zelazkowo",
    "wof:placetype":"locality"
},
  "geometry": {"coordinates":[17.61107999999999,54.54996],"type":"Point"}
}