{
  "type": "Feature",
  "properties": {
    "gn:admin1_code":"85.0",
    "gn:admin2_code":"2817.0",
    "gn:admin3_code":"281704.0",
    "gn:asciiname":"Otole",
    "gn:country_code":"PL",
    "gn:dem":154,
    "gn:feature_class":"P",
    "gn:feature_code":"PPL",
    "gn:name":"Otole",
    "gn:population":0,
    "gn:timezone":"Europe/Warsaw",
    "iso:country":"PL",
    "name:pol_x_preferred":[
        "Otole"
    ],
    "name:und_x_variant":[
        "Ottilienhof",
        "Otole"
    ],
    "wof:name":"Otole",
    "wof:placetype":"locality"
},
  "geometry": {"coordinates":[20.81156,53.67386],"type":"Point"}
}