{
  "type": "Feature",
  "properties": {
    "iso:country":"PL",
    "wof:name":"Lubocza",
    "wof:placetype":"neighbourhood"
},
  "geometry": {"coordinates":[20.09132173926161,50.09757515154237],"type":"Point"}
}