{
  "type": "Feature",
  "properties": {
    "gn:admin1_code":"87.0",
    "gn:admin2_code":"3202.0",
    "gn:admin3_code":"320205.0",
    "gn:asciiname":"Przekolno",
    "gn:country_code":"PL",
    "gn:dem":87,
    "gn:feature_class":"P",
    "gn:feature_code":"PPL",
    "gn:name":"Przekolno",
    "gn:population":0,
    "gn:timezone":"Europe/Warsaw",
    "iso:country":"PL",
    "name:pol_x_preferred":[
        "Przekolno"
    ],
    "name:ukr_x_preferred":[
        "\u041f\u0448\u0435\u043a\u043e\u043b\u044c\u043d\u043e"
    ],
    "name:vie_x_preferred":[
        "Przekolno"
    ],
    "wof:name":"Przekolno",
    "wof:placetype":"locality"
},
  "geometry": {"coordinates":[15.38166,53.04738],"type":"Point"}
}