{
  "type": "Feature",
  "properties": {
    "iso:country":"PL",
    "name:ast_x_preferred":[
        "Baryczka"
    ],
    "name:ces_x_preferred":[
        "Baryczka"
    ],
    "name:che_x_preferred":[
        "\u0411\u0430\u0440\u0438\u0447\u043a\u0430"
    ],
    "name:eng_x_preferred":[
        "Baryczka"
    ],
    "name:fra_x_preferred":[
        "Baryczka"
    ],
    "name:nan_x_preferred":[
        "Baryczka"
    ],
    "name:pol_x_preferred":[
        "Baryczka"
    ],
    "name:rus_x_preferred":[
        "\u0411\u0430\u0440\u044b\u0447\u043a\u0430"
    ],
    "name:tat_x_preferred":[
        "\u0411\u0430\u0440\u0438\u0447\u043a\u0430"
    ],
    "name:ukr_x_preferred":[
        "\u0411\u0430\u0440\u0438\u0447\u043a\u0430"
    ],
    "qs:a0":"Rzeczpospolita Polska",
    "qs:a1":"*Podkarpackie",
    "qs:a1r":"0",
    "qs:a2":"Strzyzowski",
    "qs:adm0":"Rzeczpospolita Polska",
    "qs:la_lc":"*",
    "qs:level":"locality",
    "qs:loc":"Baryczka",
    "qs:loc_alt":"Baryczka",
    "qs:pop":0,
    "qs:type":"buffered point",
    "wd:wordcount":93,
    "wof:name":"Baryczka",
    "wof:placetype":"locality"
},
  "geometry": {"coordinates":[21.905946,49.871845],"type":"Point"}
}