{
  "type": "Feature",
  "properties": {
    "gn:admin1_code":"85.0",
    "gn:admin2_code":"2819.0",
    "gn:admin3_code":"281902.0",
    "gn:asciiname":"Krzywinskie",
    "gn:country_code":"PL",
    "gn:dem":129,
    "gn:feature_class":"P",
    "gn:feature_code":"PPL",
    "gn:name":"Krzywi\u0144skie",
    "gn:population":0,
    "gn:timezone":"Europe/Warsaw",
    "iso:country":"PL",
    "name:und_x_variant":[
        "Sonnheim",
        "Krzywie\u0144skie",
        "Krzywinsken",
        "Krzywi\u0144skie"
    ],
    "wof:name":"Krzywinskie",
    "wof:placetype":"locality"
},
  "geometry": {"coordinates":[21.86774,54.20414],"type":"Point"}
}