{
  "type": "Feature",
  "properties": {
    "gn:admin1_code":"78.0",
    "gn:admin2_code":"1414.0",
    "gn:admin3_code":"141404.0",
    "gn:asciiname":"Studzianki",
    "gn:country_code":"PL",
    "gn:dem":105,
    "gn:feature_class":"P",
    "gn:feature_code":"PPL",
    "gn:name":"Studzianki",
    "gn:population":0,
    "gn:timezone":"Europe/Warsaw",
    "iso:country":"PL",
    "name:ceb_x_preferred":[
        "Studzianki"
    ],
    "name:fra_x_preferred":[
        "Studzianki"
    ],
    "name:mkd_x_preferred":[
        "\u0421\u0442\u0443\u0453\u0430\u043d\u043a\u0438"
    ],
    "name:pol_x_preferred":[
        "Studzianki"
    ],
    "name:ukr_x_preferred":[
        "\u0421\u0442\u0443\u0434\u0437\u044f\u043d\u043a\u0456"
    ],
    "wof:name":"Studzianki",
    "wof:placetype":"locality"
},
  "geometry": {"coordinates":[20.76159,52.53918],"type":"Point"}
}