{
  "type": "Feature",
  "properties": {
    "gn:admin1_code":"81.0",
    "gn:admin2_code":"2009.0",
    "gn:admin3_code":"200905.0",
    "gn:asciiname":"Lasanka",
    "gn:country_code":"PL",
    "gn:dem":133,
    "gn:feature_class":"P",
    "gn:feature_code":"PPL",
    "gn:name":"Lasanka",
    "gn:population":0,
    "gn:timezone":"Europe/Warsaw",
    "iso:country":"PL",
    "name:lit_x_preferred":[
        "Lasanka"
    ],
    "name:pol_x_preferred":[
        "Lasanka"
    ],
    "name:ukr_x_preferred":[
        "\u041b\u044f\u0441\u0430\u043d\u043a\u0430"
    ],
    "wof:name":"Lasanka",
    "wof:placetype":"locality"
},
  "geometry": {"coordinates":[23.31251,54.09132],"type":"Point"}
}