{
  "type": "Feature",
  "properties": {
    "gn:admin1_code":"74.0",
    "gn:admin2_code":"1001.0",
    "gn:admin3_code":"100102.0",
    "gn:asciiname":"Mikorska Wola",
    "gn:country_code":"PL",
    "gn:dem":215,
    "gn:feature_class":"P",
    "gn:feature_code":"PPL",
    "gn:name":"Mikorska Wola",
    "gn:population":0,
    "gn:timezone":"Europe/Warsaw",
    "iso:country":"PL",
    "name:fra_x_preferred":[
        "Wola Mikorska"
    ],
    "name:nld_x_preferred":[
        "Wola Mikorska"
    ],
    "name:pol_x_preferred":[
        "Wola Mikorska"
    ],
    "name:ukr_x_preferred":[
        "\u0412\u043e\u043b\u044f-\u041c\u0456\u043a\u043e\u0440\u0441\u044c\u043a\u0430"
    ],
    "name:und_x_variant":[
        "Wola Mikorska",
        "Mikorska Wola"
    ],
    "wof:name":"Mikorska Wola",
    "wof:placetype":"locality"
},
  "geometry": {"coordinates":[19.31134,51.40246],"type":"Point"}
}