{
  "type": "Feature",
  "properties": {
    "gn:admin1_code":"82.0",
    "gn:admin2_code":"2212.0",
    "gn:admin3_code":"221206.0",
    "gn:asciiname":"Dobrzecino",
    "gn:country_code":"PL",
    "gn:dem":45,
    "gn:feature_class":"P",
    "gn:feature_code":"PPL",
    "gn:name":"Dobrz\u0119cino",
    "gn:population":0,
    "gn:timezone":"Europe/Warsaw",
    "iso:country":"PL",
    "name:und_x_variant":[
        "Dobrz\u0119cino"
    ],
    "wof:name":"Dobrzecino",
    "wof:placetype":"locality"
},
  "geometry": {"coordinates":[16.8903,54.39364000000001],"type":"Point"}
}