{
  "type": "Feature",
  "properties": {
    "gn:admin1_code":"82.0",
    "gn:admin2_code":"2212.0",
    "gn:admin3_code":"221206.0",
    "gn:asciiname":"Dobrzecino",
    "gn:country_code":"PL",
    "gn:dem":45,
    "gn:feature_class":"P",
    "gn:feature_code":"PPL",
    "gn:name":"Dobrz\u0119cino",
    "gn:population":0,
    "gn:timezone":"Europe/Warsaw",
    "iso:country":"PL",
    "name:azb_x_preferred":[
        "\u062f\u0648\u0628\u0698\u0646\u0686\u06cc\u0646\u0648"
    ],
    "name:deu_x_preferred":[
        "Dobrz\u0119cino"
    ],
    "name:fas_x_preferred":[
        "\u062f\u0648\u0628\u0698\u0646\u0686\u06cc\u0646\u0648"
    ],
    "name:pol_x_preferred":[
        "Dobrz\u0119cino"
    ],
    "name:ukr_x_preferred":[
        "\u0414\u043e\u0431\u0436\u0435\u043d\u0446\u0438\u043d\u043e"
    ],
    "wof:name":"Dobrzecino",
    "wof:placetype":"locality"
},
  "geometry": {"coordinates":[16.8903,54.39364000000001],"type":"Point"}
}