{
  "type": "Feature",
  "properties": {
    "gn:admin1_code":"82.0",
    "gn:admin2_code":"2204.0",
    "gn:admin3_code":"220405.0",
    "gn:asciiname":"Borowina",
    "gn:country_code":"PL",
    "gn:dem":219,
    "gn:feature_class":"P",
    "gn:feature_code":"PPL",
    "gn:name":"Borowina",
    "gn:population":0,
    "gn:timezone":"Europe/Warsaw",
    "iso:country":"PL",
    "name:und_x_variant":[
        "Barenh\u00fctte",
        "Borowina"
    ],
    "wof:name":"Borowina",
    "wof:placetype":"locality"
},
  "geometry": {"coordinates":[18.29914,54.15867],"type":"Point"}
}