{
  "type": "Feature",
  "properties": {
    "gn:admin1_code":"86.0",
    "gn:admin2_code":"3027.0",
    "gn:admin3_code":"302706.0",
    "gn:asciiname":"Jeziorko",
    "gn:country_code":"PL",
    "gn:dem":90,
    "gn:feature_class":"P",
    "gn:feature_code":"PPL",
    "gn:name":"Jeziorko",
    "gn:population":0,
    "gn:timezone":"Europe/Warsaw",
    "iso:country":"PL",
    "name:pol_x_preferred":[
        "Jeziorko"
    ],
    "name:ukr_x_preferred":[
        "\u0404\u0437\u044c\u043e\u0440\u043a\u043e"
    ],
    "wof:name":"Jeziorko",
    "wof:placetype":"locality"
},
  "geometry": {"coordinates":[18.61667000000001,52.01667],"type":"Point"}
}