{
  "type": "Feature",
  "properties": {
    "gn:admin1_code":"86.0",
    "gn:admin2_code":"3001.0",
    "gn:admin3_code":"300102.0",
    "gn:asciiname":"Nowa Wies Wyszynska",
    "gn:country_code":"PL",
    "gn:dem":89,
    "gn:feature_class":"P",
    "gn:feature_code":"PPL",
    "gn:name":"Nowa Wie\u015b Wyszy\u0144ska",
    "gn:population":0,
    "gn:timezone":"Europe/Warsaw",
    "iso:country":"PL",
    "name:pol_x_preferred":[
        "Nowa Wie\u015b Wyszy\u0144ska"
    ],
    "name:ukr_x_preferred":[
        "\u041d\u043e\u0432\u0430 \u0412\u0435\u0441\u044c-\u0412\u0438\u0448\u0438\u043d\u0441\u044c\u043a\u0430"
    ],
    "name:und_x_variant":[
        "Nowa Wie\u015b Wyszy\u0144ska"
    ],
    "wof:name":"Nowa Wies Wyszynska",
    "wof:placetype":"locality"
},
  "geometry": {"coordinates":[16.88637,52.86812],"type":"Point"}
}