{
  "type": "Feature",
  "properties": {
    "gn:admin1_code":"81.0",
    "gn:admin2_code":"2011.0",
    "gn:admin3_code":"201102.0",
    "gn:asciiname":"Budno",
    "gn:country_code":"PL",
    "gn:dem":176,
    "gn:feature_class":"P",
    "gn:feature_code":"PPL",
    "gn:name":"Budno",
    "gn:population":0,
    "gn:timezone":"Europe/Warsaw",
    "iso:country":"PL",
    "name:azb_x_preferred":[
        "\u0628\u0648\u062f\u0646\u0648"
    ],
    "name:fas_x_preferred":[
        "\u0628\u0648\u062f\u0646\u0648"
    ],
    "name:fra_x_preferred":[
        "Budno"
    ],
    "name:lit_x_preferred":[
        "Budnas"
    ],
    "name:pol_x_preferred":[
        "Budno"
    ],
    "name:ukr_x_preferred":[
        "\u0411\u0443\u0434\u043d\u043e"
    ],
    "name:und_x_variant":[
        "Budne"
    ],
    "wof:name":"Budno",
    "wof:placetype":"locality"
},
  "geometry": {"coordinates":[23.28392,53.50551],"type":"Point"}
}