{
  "type": "Feature",
  "properties": {
    "gn:admin1_code":"83.0",
    "gn:admin2_code":"2416.0",
    "gn:admin3_code":"241602.0",
    "gn:asciiname":"Warty",
    "gn:country_code":"PL",
    "gn:dem":352,
    "gn:feature_class":"P",
    "gn:feature_code":"PPL",
    "gn:name":"Warty",
    "gn:population":0,
    "gn:timezone":"Europe/Warsaw",
    "iso:country":"PL",
    "wof:name":"Warty",
    "wof:placetype":"locality"
},
  "geometry": {"coordinates":[19.46091,50.48196],"type":"Point"}
}