{
  "type": "Feature",
  "properties": {
    "iso:country":"PL",
    "name:eng_x_preferred":[
        "Zar"
    ],
    "name:pol_x_preferred":[
        "\u017bar"
    ],
    "wof:name":"Zar",
    "wof:placetype":"neighbourhood"
},
  "geometry": {"coordinates":[16.82732949335376,51.14732791986265],"type":"Point"}
}