{
  "type": "Feature",
  "properties": {
    "iso:country":"PL",
    "name:aze_x_preferred":[
        "Zar"
    ],
    "name:ceb_x_preferred":[
        "Zar"
    ],
    "name:eng_x_preferred":[
        "Zar"
    ],
    "name:kur_x_preferred":[
        "Zar"
    ],
    "name:ltz_x_preferred":[
        "Z\u00e4r"
    ],
    "name:pol_x_preferred":[
        "\u017bar"
    ],
    "name:rus_x_preferred":[
        "\u0417\u0430\u0440"
    ],
    "name:swe_x_preferred":[
        "Zar"
    ],
    "name:tur_x_preferred":[
        "Zar"
    ],
    "name:uzb_x_preferred":[
        "Zar"
    ],
    "wof:name":"Zar",
    "wof:placetype":"neighbourhood"
},
  "geometry": {"coordinates":[16.82732949335376,51.14732791986265],"type":"Point"}
}