{
  "type": "Feature",
  "properties": {
    "gn:admin1_code":"73.0",
    "gn:admin2_code":"413.0",
    "gn:admin3_code":"41302.0",
    "gn:asciiname":"Komierowo",
    "gn:country_code":"PL",
    "gn:dem":133,
    "gn:feature_class":"P",
    "gn:feature_code":"PPL",
    "gn:name":"Komierowo",
    "gn:population":0,
    "gn:timezone":"Europe/Warsaw",
    "iso:country":"PL",
    "name:ceb_x_preferred":[
        "Komierowo"
    ],
    "name:pol_x_preferred":[
        "Komierowo"
    ],
    "name:ukr_x_preferred":[
        "\u041a\u043e\u043c\u0435\u0440\u043e\u0432\u043e"
    ],
    "wof:name":"Komierowo",
    "wof:placetype":"locality"
},
  "geometry": {"coordinates":[17.65038999999999,53.45506999999999],"type":"Point"}
}