{
  "type": "Feature",
  "properties": {
    "gn:admin1_code":"86.0",
    "gn:admin2_code":"3023.0",
    "gn:admin3_code":"302307.0",
    "gn:asciiname":"Ostrowo Koscielne",
    "gn:country_code":"PL",
    "gn:dem":105,
    "gn:feature_class":"P",
    "gn:feature_code":"PPL",
    "gn:name":"Ostrowo Kos\u0107ielne",
    "gn:population":0,
    "gn:timezone":"Europe/Warsaw",
    "iso:country":"PL",
    "wof:name":"Ostrowo Koscielne",
    "wof:placetype":"locality"
},
  "geometry": {"coordinates":[17.83713999999999,52.34822],"type":"Point"}
}