{
  "type": "Feature",
  "properties": {
    "gn:admin1_code":"84.0",
    "gn:admin2_code":"2608.0",
    "gn:admin3_code":"260802.0",
    "gn:asciiname":"Rebow",
    "gn:country_code":"PL",
    "gn:dem":198,
    "gn:feature_class":"P",
    "gn:feature_code":"PPL",
    "gn:name":"R\u0119b\u00f3w",
    "gn:population":0,
    "gn:timezone":"Europe/Warsaw",
    "iso:country":"PL",
    "wof:name":"Rebow",
    "wof:placetype":"locality"
},
  "geometry": {"coordinates":[20.51439,50.62954000000001],"type":"Point"}
}