{
  "type": "Feature",
  "properties": {
    "gn:admin1_code":"74.0",
    "gn:admin2_code":"1012.0",
    "gn:admin3_code":"101205.0",
    "gn:asciiname":"Galkowice Nowe",
    "gn:country_code":"PL",
    "gn:dem":217,
    "gn:feature_class":"P",
    "gn:feature_code":"PPL",
    "gn:name":"Ga\u0142kowice Nowe",
    "gn:population":0,
    "gn:timezone":"Europe/Warsaw",
    "iso:country":"PL",
    "name:fra_x_preferred":[
        "Ga\u0142kowice Nowe"
    ],
    "name:pol_x_preferred":[
        "Ga\u0142kowice Nowe"
    ],
    "name:ukr_x_preferred":[
        "\u0490\u0430\u043b\u043a\u043e\u0432\u0456\u0446\u0435-\u041d\u043e\u0432\u0456"
    ],
    "name:und_x_variant":[
        "Ga\u0142kowice Nowe"
    ],
    "wof:name":"Galkowice Nowe",
    "wof:placetype":"locality"
},
  "geometry": {"coordinates":[19.45022,51.24312000000001],"type":"Point"}
}