{
  "type": "Feature",
  "properties": {
    "gn:country":"PL",
    "gn:fcode":"PPL",
    "gn:population":460,
    "iso:country":"PL",
    "name:ceb_x_preferred":[
        "Paw\u0142\u00f3w"
    ],
    "name:deu_x_preferred":[
        "Paw\u0142\u00f3w"
    ],
    "name:fra_x_preferred":[
        "Paw\u0142\u00f3w"
    ],
    "name:nld_x_preferred":[
        "Paw\u0142\u00f3w"
    ],
    "name:pol_x_preferred":[
        "Paw\u0142\u00f3w"
    ],
    "name:ukr_x_preferred":[
        "\u041f\u0430\u0432\u043b\u0443\u0432"
    ],
    "qs_pg:aaroncc":"PL",
    "qs_pg:gn_country":"PL",
    "qs_pg:gn_fcode":"PPL",
    "qs_pg:gn_pop":460,
    "qs_pg:name":"Paw\u0142\u00f3w",
    "qs_pg:name_adm0":"Polska",
    "qs_pg:name_adm1":"Wielkopolskie",
    "qs_pg:photos_9k":1,
    "qs_pg:photos_9r":1,
    "qs_pg:photos_all":2,
    "qs_pg:photos_sr":0,
    "qs_pg:pop_sr":2,
    "qs_pg:qs_pg_placetype":"locality",
    "qs_pg:qs_pg_placetype_gp":"Town",
    "qs_pg:woe_adm0":23424923,
    "woe:adm0_id":23424923,
    "woe:name_adm0":"Polska",
    "woe:name_adm1":"Wielkopolskie",
    "woe:placetype":"Town",
    "wof:name":"Paw\u0142\u00f3w",
    "wof:placetype":"locality",
    "wof:population":460
},
  "geometry": {"coordinates":[17.65846,51.42656],"type":"Point"}
}