{
  "type": "Feature",
  "properties": {
    "gn:admin1_code":"77.0",
    "gn:admin2_code":"1206.0",
    "gn:admin3_code":"120611.0",
    "gn:asciiname":"Trzebol",
    "gn:country_code":"PL",
    "gn:dem":230,
    "gn:feature_class":"P",
    "gn:feature_code":"PPL",
    "gn:name":"Trzebol",
    "gn:population":0,
    "gn:timezone":"Europe/Warsaw",
    "iso:country":"PL",
    "wof:name":"Trzebol",
    "wof:placetype":"locality"
},
  "geometry": {"coordinates":[19.68684,49.9574],"type":"Point"}
}