{
  "type": "Feature",
  "properties": {
    "gn:admin1_code":"84.0",
    "gn:admin2_code":"2605.0",
    "gn:admin3_code":"260506.0",
    "gn:asciiname":"Hucisko",
    "gn:country_code":"PL",
    "gn:dem":242,
    "gn:feature_class":"P",
    "gn:feature_code":"PPL",
    "gn:name":"Hucisko",
    "gn:population":0,
    "gn:timezone":"Europe/Warsaw",
    "iso:country":"PL",
    "wof:name":"Hucisko",
    "wof:placetype":"locality"
},
  "geometry": {"coordinates":[20.20746,51.01462],"type":"Point"}
}