{
  "type": "Feature",
  "properties": {
    "iso:country":"PL",
    "wof:name":"Kosocice",
    "wof:placetype":"neighbourhood"
},
  "geometry": {"coordinates":[19.99683640882323,49.9942928826385],"type":"Point"}
}