{
  "type": "Feature",
  "properties": {
    "gn:admin1_code":"73.0",
    "gn:admin2_code":"463.0",
    "gn:admin3_code":"46301.0",
    "gn:asciiname":"Grebocin nad Struga",
    "gn:country_code":"PL",
    "gn:dem":70,
    "gn:feature_class":"P",
    "gn:feature_code":"PPL",
    "gn:name":"Gr\u0119bocin nad Strug\u0105",
    "gn:population":0,
    "gn:timezone":"Europe/Warsaw",
    "iso:country":"PL",
    "wof:name":"Grebocin nad Struga",
    "wof:placetype":"locality"
},
  "geometry": {"coordinates":[18.70097,53.04673],"type":"Point"}
}