{
  "type": "Feature",
  "properties": {
    "gn:gn_country":"PL",
    "gn:gn_fcode":"PPLA3",
    "gn:gn_pop":2204,
    "gn:population":2204,
    "iso:country":"PL",
    "name:bul_x_preferred":[
        "\u0419\u0435\u0434\u0432\u0430\u0431\u043d\u0435"
    ],
    "name:deu_x_preferred":[
        "Jedwabne"
    ],
    "name:eng_x_preferred":[
        "Jedwabne"
    ],
    "name:heb_x_preferred":[
        "\u05d9\u05d3\u05d5\u05d5\u05d1\u05e0\u05d4"
    ],
    "name:lav_x_preferred":[
        "Jedvabne"
    ],
    "name:lit_x_preferred":[
        "Jedvabnas"
    ],
    "name:ltz_x_preferred":[
        "Jedwabne"
    ],
    "name:nld_x_preferred":[
        "Jedwabne"
    ],
    "name:pol_x_preferred":[
        "Jedwabne"
    ],
    "name:ron_x_preferred":[
        "Jedwabne"
    ],
    "name:rus_x_preferred":[
        "\u0415\u0434\u0432\u0430\u0431\u043d\u0435"
    ],
    "name:srp_x_preferred":[
        "\u0408\u0435\u0434\u0432\u0430\u0431\u043d\u0435"
    ],
    "name:swe_x_preferred":[
        "Jedwabne"
    ],
    "name:ukr_x_preferred":[
        "\u0404\u0434\u0432\u0430\u0431\u043d\u0435"
    ],
    "name:yid_x_preferred":[
        "\u05d9\u05e2\u05d3\u05d5\u05d5\u05d0\u05d1\u05e0\u05e2"
    ],
    "name:zho_x_preferred":[
        "\u8036\u5fb7\u74e6\u5e03\u5167"
    ],
    "qs_pg:aaroncc":"PL",
    "qs_pg:gn_country":"PL",
    "qs_pg:gn_fcode":"PPLA3",
    "qs_pg:gn_pop":2204,
    "qs_pg:name":"Jedwabne",
    "qs_pg:name_adm0":"Polska",
    "qs_pg:name_adm1":"Podlaskie",
    "qs_pg:photos":1,
    "qs_pg:photos_1k":1,
    "qs_pg:photos_9k":1,
    "qs_pg:photos_9r":1,
    "qs_pg:photos_all":1,
    "qs_pg:photos_sr":1,
    "qs_pg:pop_sr":6,
    "qs_pg:qs_pg_placetype":"localadmin",
    "qs_pg:qs_pg_placetype_gp":"LocalAdmin",
    "qs_pg:woe_adm0":23424923,
    "woe:adm0_id":23424923,
    "woe:name_adm0":"Polska",
    "woe:name_adm1":"Podlaskie",
    "woe:placetype":"LocalAdmin",
    "wof:name":"Jedwabne",
    "wof:placetype":"localadmin",
    "wof:population":2204
},
  "geometry": {"coordinates":[22.30353,53.28554],"type":"Point"}
}