{
  "type": "Feature",
  "properties": {
    "gn:admin1_code":"81.0",
    "gn:asciiname":"Grodzisko",
    "gn:country_code":"PL",
    "gn:dem":120,
    "gn:feature_class":"P",
    "gn:feature_code":"PPL",
    "gn:name":"Grodzisko",
    "gn:population":0,
    "gn:timezone":"Europe/Warsaw",
    "iso:country":"PL",
    "name:deu_x_preferred":[
        "Grodzisko"
    ],
    "name:fra_x_preferred":[
        "Grodzisko"
    ],
    "name:pol_x_preferred":[
        "Grodzisko"
    ],
    "name:ukr_x_preferred":[
        "\u0490\u0440\u043e\u0434\u0437\u0438\u0441\u044c\u043a\u043e"
    ],
    "name:und_x_variant":[
        "Burgdorf"
    ],
    "wof:name":"Grodzisko",
    "wof:placetype":"locality"
},
  "geometry": {"coordinates":[21.95113,53.51107],"type":"Point"}
}