{
  "type": "Feature",
  "properties": {
    "gn:admin1_code":"77.0",
    "gn:admin2_code":"1211.0",
    "gn:admin3_code":"121107.0",
    "gn:asciiname":"Przywarowka",
    "gn:country_code":"PL",
    "gn:dem":914,
    "gn:feature_class":"P",
    "gn:feature_code":"PPL",
    "gn:name":"Przywar\u00f3wka",
    "gn:population":0,
    "gn:timezone":"Europe/Warsaw",
    "iso:country":"PL",
    "wof:name":"Przywarowka",
    "wof:placetype":"locality"
},
  "geometry": {"coordinates":[19.55,49.55],"type":"Point"}
}