{
  "type": "Feature",
  "properties": {
    "gn:admin1_code":"78.0",
    "gn:admin2_code":"1435.0",
    "gn:admin3_code":"143501.0",
    "gn:asciiname":"Branszczyk Nakiel",
    "gn:cc2":"PL",
    "gn:country_code":"PL",
    "gn:dem":90,
    "gn:feature_class":"P",
    "gn:feature_code":"PPL",
    "gn:name":"Bra\u0144szczyk Nakie\u0142",
    "gn:population":0,
    "gn:timezone":"Europe/Warsaw",
    "iso:country":"PL",
    "name:und_x_variant":[
        "Braniszczyki Nakie\u0142",
        "Branszezki-Nakie\u0142",
        "Bra\u0144szczyk Nakie\u0142"
    ],
    "wof:name":"Branszczyk Nakiel",
    "wof:placetype":"locality"
},
  "geometry": {"coordinates":[21.56667,52.61666999999999],"type":"Point"}
}