{
  "type": "Feature",
  "properties": {
    "gn:admin1_code":"74.0",
    "gn:admin2_code":"1014.0",
    "gn:admin3_code":"101402.0",
    "gn:asciiname":"Golkow",
    "gn:country_code":"PL",
    "gn:dem":145,
    "gn:feature_class":"P",
    "gn:feature_code":"PPL",
    "gn:name":"Golk\u00f3w",
    "gn:population":0,
    "gn:timezone":"Europe/Warsaw",
    "iso:country":"PL",
    "name:pol_x_preferred":[
        "Golk\u00f3w"
    ],
    "name:ukr_x_preferred":[
        "\u0490\u043e\u043b\u044c\u043a\u0443\u0432"
    ],
    "wof:name":"Golkow",
    "wof:placetype":"locality"
},
  "geometry": {"coordinates":[18.45394,51.69512],"type":"Point"}
}