{
  "type": "Feature",
  "properties": {
    "gn:admin1_code":"86.0",
    "gn:admin2_code":"3010.0",
    "gn:admin3_code":"301003.0",
    "gn:asciiname":"Sokolki",
    "gn:country_code":"PL",
    "gn:dem":103,
    "gn:feature_class":"P",
    "gn:feature_code":"PPL",
    "gn:name":"Sok\u00f3\u0142ki",
    "gn:population":0,
    "gn:timezone":"Europe/Warsaw",
    "iso:country":"PL",
    "name:pol_x_preferred":[
        "Sok\u00f3\u0142ki"
    ],
    "name:ukr_x_preferred":[
        "\u0421\u043e\u043a\u0443\u043b\u043a\u0456"
    ],
    "name:und_x_variant":[
        "Sok\u00f3\u0142ki"
    ],
    "wof:name":"Sokolki",
    "wof:placetype":"locality"
},
  "geometry": {"coordinates":[18.2143,52.26429],"type":"Point"}
}