{
  "type": "Feature",
  "properties": {
    "gn:admin1_code":"73.0",
    "gn:admin2_code":"408.0",
    "gn:admin3_code":"40806.0",
    "gn:asciiname":"Rumunki Lipnowskie",
    "gn:country_code":"PL",
    "gn:dem":90,
    "gn:feature_class":"P",
    "gn:feature_code":"PPL",
    "gn:name":"Rumunki Lipnowskie",
    "gn:population":0,
    "gn:timezone":"Europe/Warsaw",
    "iso:country":"PL",
    "wof:name":"Rumunki Lipnowskie",
    "wof:placetype":"locality"
},
  "geometry": {"coordinates":[19.20011,52.83456999999999],"type":"Point"}
}