{
  "type": "Feature",
  "properties": {
    "gn:admin1_code":"82.0",
    "gn:admin2_code":"2209.0",
    "gn:admin3_code":"220907.0",
    "gn:asciiname":"Lubstowo",
    "gn:country_code":"PL",
    "gn:dem":-1,
    "gn:feature_class":"P",
    "gn:feature_code":"PPL",
    "gn:name":"Lubstowo",
    "gn:population":0,
    "gn:timezone":"Europe/Warsaw",
    "iso:country":"PL",
    "name:ceb_x_preferred":[
        "Lubstowo"
    ],
    "name:nld_x_preferred":[
        "Lubstowo"
    ],
    "name:pol_x_preferred":[
        "Lubstowo"
    ],
    "name:ukr_x_preferred":[
        "\u041b\u044e\u0431\u0441\u0442\u043e\u0432\u043e"
    ],
    "name:und_x_variant":[
        "Lupushorst"
    ],
    "wof:name":"Lubstowo",
    "wof:placetype":"locality"
},
  "geometry": {"coordinates":[19.19809,54.13267],"type":"Point"}
}