{
  "type": "Feature",
  "properties": {
    "gn:population":1800,
    "iso:country":"PL",
    "name:azb_x_preferred":[
        "\u0642\u0645\u06cc\u0646\u0627 \u0634\u062f\u0644\u06cc\u0633\u06a9\u0648"
    ],
    "name:bel_x_preferred":[
        "\u0413\u043c\u0456\u043d\u0430 \u0421\u044f\u0434\u043b\u0456\u0441\u043a\u0430"
    ],
    "name:ceb_x_preferred":[
        "Siedlisko"
    ],
    "name:deu_x_preferred":[
        "Gmina Siedlisko"
    ],
    "name:eng_x_preferred":[
        "Gmina Siedlisko"
    ],
    "name:eus_x_preferred":[
        "Siedlisko udalerria"
    ],
    "name:fas_x_preferred":[
        "\u06af\u0645\u06cc\u0646\u0627 \u0634\u062f\u0644\u06cc\u0633\u06a9\u0648"
    ],
    "name:fra_x_preferred":[
        "Siedlisko"
    ],
    "name:ita_x_preferred":[
        "Siedlisko"
    ],
    "name:nan_x_preferred":[
        "Siedlisko"
    ],
    "name:nld_x_preferred":[
        "Siedlisko"
    ],
    "name:pol_x_preferred":[
        "Siedlisko"
    ],
    "name:por_x_preferred":[
        "Comuna de Siedlisko"
    ],
    "name:rus_x_preferred":[
        "\u0421\u0435\u0434\u043b\u0438\u0441\u043a\u043e"
    ],
    "name:slk_x_preferred":[
        "Gmina Siedlisko"
    ],
    "name:ukr_x_preferred":[
        "\u0490\u043c\u0456\u043d\u0430 \u0421\u0435\u0434\u043b\u0456\u0441\u044c\u043a\u043e"
    ],
    "name:und_x_variant":[
        "Karolat"
    ],
    "name:war_x_preferred":[
        "Gmina Siedlisko"
    ],
    "name:zho_min_nan_x_preferred":[
        "Siedlisko"
    ],
    "qs:a0":"Rzeczpospolita Polska",
    "qs:a1":"*Lubuskie",
    "qs:a1r":"0",
    "qs:a2":"Nowosolski",
    "qs:adm0":"Rzeczpospolita Polska",
    "qs:la":"Siedlisko",
    "qs:la_lc":"*PL0804082",
    "qs:level":"locality",
    "qs:loc":"Siedlisko",
    "qs:loc_alt":"Siedlisko",
    "qs:pop":0,
    "qs:type":"rural point-in-poly",
    "wd:wordcount":110,
    "wof:name":"Siedlisko",
    "wof:placetype":"locality",
    "wof:population":1800
},
  "geometry": {"coordinates":[15.8733255783057,51.7646106143692],"type":"Point"}
}