{
  "type": "Feature",
  "properties": {
    "gn:admin1_code":"84.0",
    "gn:admin2_code":"2612.0",
    "gn:admin3_code":"261204.0",
    "gn:asciiname":"Trzcianka",
    "gn:country_code":"PL",
    "gn:dem":154,
    "gn:feature_class":"P",
    "gn:feature_code":"PPL",
    "gn:name":"Trzcianka",
    "gn:population":0,
    "gn:timezone":"Europe/Warsaw",
    "iso:country":"PL",
    "name:azb_x_preferred":[
        "\u0627\u0634\u0686\u06cc\u0627\u0646\u06a9\u0627"
    ],
    "name:fas_x_preferred":[
        "\u0627\u0634\u0686\u06cc\u0627\u0646\u06a9\u0627\u060c \u0634\u0647\u0631\u0633\u062a\u0627\u0646 \u0627\u0633\u062a\u0627\u0633\u0632\u0648"
    ],
    "name:fas_x_variant":[
        "\u0627\u0634\u0686\u06cc\u0627\u0646\u06a9\u0627"
    ],
    "name:pol_x_preferred":[
        "Trzcianka"
    ],
    "name:ukr_x_preferred":[
        "\u0422\u0448\u0446\u044f\u043d\u043a\u0430"
    ],
    "name:urd_x_preferred":[
        "\u0686\u0686\u0627\u0646\u06a9\u0627\u060c \u0633\u062a\u0627\u0634\u0648\u0641 \u06a9\u0627\u0624\u0646\u0679\u06cc"
    ],
    "name:urd_x_variant":[
        "\u0686\u0686\u0627\u0646\u06a9\u0627"
    ],
    "wof:name":"Trzcianka",
    "wof:placetype":"locality"
},
  "geometry": {"coordinates":[21.40961,50.48788],"type":"Point"}
}