{
  "type": "Feature",
  "properties": {
    "gn:admin1_code":"75.0",
    "gn:admin2_code":"620.0",
    "gn:admin3_code":"62010.0",
    "gn:asciiname":"Majdan Skierbieszowski",
    "gn:country_code":"PL",
    "gn:dem":230,
    "gn:feature_class":"P",
    "gn:feature_code":"PPL",
    "gn:name":"Majdan Skierbieszowski",
    "gn:population":0,
    "gn:timezone":"Europe/Warsaw",
    "iso:country":"PL",
    "wof:name":"Majdan Skierbieszowski",
    "wof:placetype":"locality"
},
  "geometry": {"coordinates":[23.38454,50.88735],"type":"Point"}
}