{
  "type": "Feature",
  "properties": {
    "gn:admin1_code":"75.0",
    "gn:admin2_code":"620.0",
    "gn:admin3_code":"62010.0",
    "gn:asciiname":"Majdan Skierbieszowski",
    "gn:country_code":"PL",
    "gn:dem":230,
    "gn:feature_class":"P",
    "gn:feature_code":"PPL",
    "gn:name":"Majdan Skierbieszowski",
    "gn:population":0,
    "gn:timezone":"Europe/Warsaw",
    "iso:country":"PL",
    "name:fra_x_preferred":[
        "Majdan Skierbieszowski"
    ],
    "name:pol_x_preferred":[
        "Majdan Skierbieszowski"
    ],
    "name:ukr_x_preferred":[
        "\u041c\u0430\u0439\u0434\u0430\u043d-\u0421\u043a\u0435\u0440\u0431\u0435\u0448\u043e\u0432\u0441\u044c\u043a\u0438\u0439"
    ],
    "wof:name":"Majdan Skierbieszowski",
    "wof:placetype":"locality"
},
  "geometry": {"coordinates":[23.38454,50.88735],"type":"Point"}
}