{
  "type": "Feature",
  "properties": {
    "iso:country":"PL",
    "name:eng_x_preferred":[
        "Osiedle Ulanskie"
    ],
    "name:pol_x_preferred":[
        "Osiedle U\u0142a\u0144skie"
    ],
    "wof:name":"Osiedle Ulanskie",
    "wof:placetype":"neighbourhood"
},
  "geometry": {"coordinates":[16.89377443446261,52.40165001985689],"type":"Point"}
}