{
  "type": "Feature",
  "properties": {
    "gn:admin1_code":"75.0",
    "gn:admin2_code":"616.0",
    "gn:admin3_code":"61605.0",
    "gn:asciiname":"Kletnia",
    "gn:country_code":"PL",
    "gn:dem":128,
    "gn:feature_class":"P",
    "gn:feature_code":"PPL",
    "gn:name":"Kletnia",
    "gn:population":0,
    "gn:timezone":"Europe/Warsaw",
    "iso:country":"PL",
    "name:fra_x_preferred":[
        "Kletnia"
    ],
    "name:pol_x_preferred":[
        "Kletnia"
    ],
    "name:ukr_x_preferred":[
        "\u041a\u043b\u0435\u0442\u043d\u044f"
    ],
    "wof:name":"Kletnia",
    "wof:placetype":"locality"
},
  "geometry": {"coordinates":[21.77181,51.62558],"type":"Point"}
}