{
  "type": "Feature",
  "properties": {
    "gn:admin1_code":"85.0",
    "gn:admin2_code":"2808.0",
    "gn:admin3_code":"280802.0",
    "gn:asciiname":"Momajny",
    "gn:cc2":"PL",
    "gn:country_code":"PL",
    "gn:dem":43,
    "gn:feature_class":"P",
    "gn:feature_code":"PPL",
    "gn:name":"Momajny",
    "gn:population":0,
    "gn:timezone":"Europe/Warsaw",
    "iso:country":"PL",
    "name:und_x_variant":[
        "Momehnen",
        "Momajny"
    ],
    "wof:name":"Momajny",
    "wof:placetype":"locality"
},
  "geometry": {"coordinates":[21.25425,54.31322],"type":"Point"}
}