{
  "type": "Feature",
  "properties": {
    "gn:admin1_code":"85.0",
    "gn:admin2_code":"2808.0",
    "gn:admin3_code":"280802.0",
    "gn:asciiname":"Momajny",
    "gn:cc2":"PL",
    "gn:country_code":"PL",
    "gn:dem":43,
    "gn:feature_class":"P",
    "gn:feature_code":"PPL",
    "gn:name":"Momajny",
    "gn:population":0,
    "gn:timezone":"Europe/Warsaw",
    "iso:country":"PL",
    "name:azb_x_preferred":[
        "\u0645\u0648\u0645\u0627\u06cc\u0646\u0647"
    ],
    "name:deu_x_preferred":[
        "Momajny"
    ],
    "name:fas_x_preferred":[
        "\u0645\u0648\u0645\u0627\u06cc\u0646\u0647"
    ],
    "name:lit_x_preferred":[
        "Mom\u0117nai"
    ],
    "name:pol_x_preferred":[
        "Momajny"
    ],
    "name:ukr_x_preferred":[
        "\u041c\u043e\u043c\u0430\u0439\u043d\u0438"
    ],
    "name:und_x_variant":[
        "Momehnen"
    ],
    "name:vie_x_preferred":[
        "Momajny"
    ],
    "wof:name":"Momajny",
    "wof:placetype":"locality"
},
  "geometry": {"coordinates":[21.25425,54.31322],"type":"Point"}
}