{
  "type": "Feature",
  "properties": {
    "gn:admin1_code":"72.0",
    "gn:admin2_code":"218.0",
    "gn:admin3_code":"21801.0",
    "gn:asciiname":"Mieczkow",
    "gn:country_code":"PL",
    "gn:dem":163,
    "gn:feature_class":"P",
    "gn:feature_code":"PPL",
    "gn:name":"Mieczk\u00f3w",
    "gn:population":0,
    "gn:timezone":"Europe/Warsaw",
    "iso:country":"PL",
    "name:und_x_variant":[
        "Mieczk\u00f3w"
    ],
    "wof:name":"Mieczkow",
    "wof:placetype":"locality"
},
  "geometry": {"coordinates":[16.54009,51.02941],"type":"Point"}
}