{
  "type": "Feature",
  "properties": {
    "gn:admin1_code":"81.0",
    "gn:admin2_code":"2006.0",
    "gn:admin3_code":"200603.0",
    "gn:asciiname":"Kielcze Stare",
    "gn:country_code":"PL",
    "gn:dem":143,
    "gn:feature_class":"P",
    "gn:feature_code":"PPL",
    "gn:name":"Kie\u0142cze Stare",
    "gn:population":0,
    "gn:timezone":"Europe/Warsaw",
    "iso:country":"PL",
    "name:lit_x_preferred":[
        "Stare Kiel\u010d\u0117"
    ],
    "name:pol_x_preferred":[
        "Stare Kie\u0142cze"
    ],
    "name:ukr_x_preferred":[
        "\u0421\u0442\u0430\u0440\u0435 \u041a\u0435\u043b\u0447\u0435"
    ],
    "name:und_x_variant":[
        "Kie\u0142cze",
        "Kie\u0142cze Stare"
    ],
    "wof:name":"Kielcze Stare",
    "wof:placetype":"locality"
},
  "geometry": {"coordinates":[21.984,53.47156999999999],"type":"Point"}
}