{
  "type": "Feature",
  "properties": {
    "gn:admin1_code":"76.0",
    "gn:admin2_code":"810.0",
    "gn:admin3_code":"81007.0",
    "gn:asciiname":"Biernatow",
    "gn:country_code":"PL",
    "gn:dem":150,
    "gn:feature_class":"P",
    "gn:feature_code":"PPL",
    "gn:name":"Biernat\u00f3w",
    "gn:population":0,
    "gn:timezone":"Europe/Warsaw",
    "iso:country":"PL",
    "name:fra_x_preferred":[
        "Biernat\u00f3w"
    ],
    "name:pol_x_preferred":[
        "Biernat\u00f3w"
    ],
    "name:ukr_x_preferred":[
        "\u0411\u0435\u0440\u043d\u0430\u0442\u0443\u0432"
    ],
    "wof:name":"Biernatow",
    "wof:placetype":"locality"
},
  "geometry": {"coordinates":[15.65483,51.4878],"type":"Point"}
}