{
  "type": "Feature",
  "properties": {
    "gn:admin1_code":"84.0",
    "gn:admin2_code":"2609.0",
    "gn:admin3_code":"260904.0",
    "gn:asciiname":"Sosniczany",
    "gn:country_code":"PL",
    "gn:dem":169,
    "gn:feature_class":"P",
    "gn:feature_code":"PPL",
    "gn:name":"So\u015bniczany",
    "gn:population":0,
    "gn:timezone":"Europe/Warsaw",
    "iso:country":"PL",
    "name:nld_x_preferred":[
        "So\u015bniczany"
    ],
    "name:pol_x_preferred":[
        "So\u015bniczany"
    ],
    "name:ukr_x_preferred":[
        "\u0421\u043e\u0441\u043d\u0456\u0447\u0430\u043d\u0438"
    ],
    "wof:name":"Sosniczany",
    "wof:placetype":"locality"
},
  "geometry": {"coordinates":[21.59943,50.61495],"type":"Point"}
}