{
  "type": "Feature",
  "properties": {
    "gn:admin1_code":"84.0",
    "gn:admin2_code":"2601.0",
    "gn:admin3_code":"260101.0",
    "gn:asciiname":"Zbrodzice",
    "gn:country_code":"PL",
    "gn:dem":243,
    "gn:feature_class":"P",
    "gn:feature_code":"PPL",
    "gn:name":"Zbrodzice",
    "gn:population":0,
    "gn:timezone":"Europe/Warsaw",
    "iso:country":"PL",
    "name:pol_x_preferred":[
        "Zbrodzice"
    ],
    "name:ukr_x_preferred":[
        "\u0417\u0431\u0440\u043e\u0434\u0437\u0456\u0446\u0435"
    ],
    "wof:name":"Zbrodzice",
    "wof:placetype":"locality"
},
  "geometry": {"coordinates":[20.76708,50.49039000000001],"type":"Point"}
}