{
  "type": "Feature",
  "properties": {
    "iso:country":"PL",
    "qs_pg:aaroncc":"PL",
    "qs_pg:name":"Gmina Che\u0142mek",
    "qs_pg:name_adm0":"Polska",
    "qs_pg:name_adm1":"Ma\u0142opolskie",
    "qs_pg:photos":5,
    "qs_pg:photos_1k":1,
    "qs_pg:photos_9k":25,
    "qs_pg:photos_9r":14,
    "qs_pg:photos_all":5719,
    "qs_pg:photos_sr":1,
    "qs_pg:pop_sr":0,
    "qs_pg:qs_pg_placetype":"localadmin",
    "qs_pg:qs_pg_placetype_gp":"LocalAdmin",
    "qs_pg:woe_adm0":23424923,
    "woe:adm0_id":23424923,
    "woe:name_adm0":"Polska",
    "woe:name_adm1":"Ma\u0142opolskie",
    "woe:placetype":"LocalAdmin",
    "wof:name":"Gmina Che\u0142mek",
    "wof:placetype":"localadmin"
},
  "geometry": {"coordinates":[19.252853,50.036978],"type":"Point"}
}