{
  "type": "Feature",
  "properties": {
    "gn:admin1_code":"75.0",
    "gn:admin2_code":"620.0",
    "gn:admin3_code":"62002.0",
    "gn:asciiname":"Rogow",
    "gn:country_code":"PL",
    "gn:dem":211,
    "gn:feature_class":"P",
    "gn:feature_code":"PPL",
    "gn:name":"Rog\u00f3w",
    "gn:population":0,
    "gn:timezone":"Europe/Warsaw",
    "iso:country":"PL",
    "name:fra_x_preferred":[
        "Rog\u00f3w"
    ],
    "name:pol_x_preferred":[
        "Rog\u00f3w"
    ],
    "name:ukr_x_preferred":[
        "\u0420\u043e\u0491\u0443\u0432"
    ],
    "wof:name":"Rogow",
    "wof:placetype":"locality"
},
  "geometry": {"coordinates":[23.51469,50.80382],"type":"Point"}
}