{
  "type": "Feature",
  "properties": {
    "gn:admin1_code":"78.0",
    "gn:admin2_code":"1429.0",
    "gn:admin3_code":"142903.0",
    "gn:asciiname":"Olszew",
    "gn:country_code":"PL",
    "gn:dem":130,
    "gn:feature_class":"P",
    "gn:feature_code":"PPL",
    "gn:name":"Olszew",
    "gn:population":0,
    "gn:timezone":"Europe/Warsaw",
    "iso:country":"PL",
    "name:azb_x_preferred":[
        "\u0627\u0648\u0644\u0634\u0648"
    ],
    "name:fas_x_preferred":[
        "\u0627\u0648\u0644\u0634\u0648"
    ],
    "name:fra_x_preferred":[
        "Olszew"
    ],
    "name:lit_x_preferred":[
        "Ol\u0161evas"
    ],
    "name:pol_x_preferred":[
        "Olszew"
    ],
    "name:ukr_x_preferred":[
        "\u041e\u043b\u044c\u0448\u0435\u0432"
    ],
    "wof:name":"Olszew",
    "wof:placetype":"locality"
},
  "geometry": {"coordinates":[22.19948,52.61191],"type":"Point"}
}