{
  "type": "Feature",
  "properties": {
    "gn:admin1_code":"86.0",
    "gn:admin2_code":"3027.0",
    "gn:admin3_code":"302703.0",
    "gn:asciiname":"Skeczniew",
    "gn:country_code":"PL",
    "gn:dem":116,
    "gn:feature_class":"P",
    "gn:feature_code":"PPL",
    "gn:name":"Sk\u0119czniew",
    "gn:population":0,
    "gn:timezone":"Europe/Warsaw",
    "iso:country":"PL",
    "name:ceb_x_preferred":[
        "Sk\u0119czniew"
    ],
    "name:pol_x_preferred":[
        "Sk\u0119czniew"
    ],
    "name:ukr_x_preferred":[
        "\u0421\u043a\u0435\u043d\u0447\u043d\u0435\u0432"
    ],
    "wof:name":"Skeczniew",
    "wof:placetype":"locality"
},
  "geometry": {"coordinates":[18.69135,51.8748],"type":"Point"}
}