{
  "type": "Feature",
  "properties": {
    "gn:admin1_code":"81.0",
    "gn:admin2_code":"2010.0",
    "gn:admin3_code":"201007.0",
    "gn:asciiname":"Wyczolki",
    "gn:country_code":"PL",
    "gn:dem":162,
    "gn:feature_class":"P",
    "gn:feature_code":"PPL",
    "gn:name":"Wycz\u00f3\u0142ki",
    "gn:population":0,
    "gn:timezone":"Europe/Warsaw",
    "iso:country":"PL",
    "name:lit_x_preferred":[
        "Vi\u010dulkai"
    ],
    "name:pol_x_preferred":[
        "Wycz\u00f3\u0142ki"
    ],
    "name:ukr_x_preferred":[
        "\u0412\u0438\u0447\u0443\u043b\u043a\u0456"
    ],
    "wof:name":"Wyczolki",
    "wof:placetype":"locality"
},
  "geometry": {"coordinates":[23.29446,52.40676],"type":"Point"}
}