{
  "type": "Feature",
  "properties": {
    "gn:admin1_code":"82.0",
    "gn:admin2_code":"2212.0",
    "gn:admin3_code":"221210.0",
    "gn:asciiname":"Redwanki",
    "gn:country_code":"PL",
    "gn:dem":35,
    "gn:feature_class":"P",
    "gn:feature_code":"PPL",
    "gn:name":"Redwanki",
    "gn:population":0,
    "gn:timezone":"Europe/Warsaw",
    "iso:country":"PL",
    "name:deu_x_historical":[
        "Rettfang"
    ],
    "name:deu_x_preferred":[
        "Rettfang"
    ],
    "wof:name":"Redwanki",
    "wof:placetype":"locality"
},
  "geometry": {"coordinates":[17.00158,54.57521],"type":"Point"}
}