{
  "type": "Feature",
  "properties": {
    "gn:admin1_code":"72.0",
    "gn:admin2_code":"208.0",
    "gn:admin3_code":"20806.0",
    "gn:asciiname":"Gorzanow",
    "gn:country_code":"PL",
    "gn:dem":315,
    "gn:feature_class":"P",
    "gn:feature_code":"PPL",
    "gn:name":"Gorzan\u00f3w",
    "gn:population":0,
    "gn:timezone":"Europe/Warsaw",
    "iso:country":"PL",
    "name:azb_x_preferred":[
        "\u0642\u0648\u0698\u0627\u0646\u0648\u0648"
    ],
    "name:cat_x_preferred":[
        "Gorzan\u00f3w"
    ],
    "name:ceb_x_preferred":[
        "Gorzan\u00f3w"
    ],
    "name:deu_x_preferred":[
        "Gorzan\u00f3w"
    ],
    "name:fas_x_preferred":[
        "\u06af\u0648\u0698\u0627\u0646\u0648\u0648"
    ],
    "name:nld_x_preferred":[
        "Gorzan\u00f3w"
    ],
    "name:pol_x_preferred":[
        "Gorzan\u00f3w"
    ],
    "name:ukr_x_preferred":[
        "\u0490\u043e\u0436\u0430\u043d\u0443\u0432"
    ],
    "wof:name":"Gorzanow",
    "wof:placetype":"locality"
},
  "geometry": {"coordinates":[16.63496,50.35233],"type":"Point"}
}