{
  "type": "Feature",
  "properties": {
    "gn:admin1_code":"73.0",
    "gn:admin2_code":"418.0",
    "gn:admin3_code":"41813.0",
    "gn:asciiname":"Koszanowo",
    "gn:country_code":"PL",
    "gn:dem":88,
    "gn:feature_class":"P",
    "gn:feature_code":"PPL",
    "gn:name":"Koszanowo",
    "gn:population":0,
    "gn:timezone":"Europe/Warsaw",
    "iso:country":"PL",
    "name:pol_x_preferred":[
        "Koszanowo"
    ],
    "name:ukr_x_preferred":[
        "\u041a\u043e\u0448\u0430\u043d\u043e\u0432\u043e"
    ],
    "wof:name":"Koszanowo",
    "wof:placetype":"locality"
},
  "geometry": {"coordinates":[18.94747000000001,52.55005],"type":"Point"}
}