{
  "type": "Feature",
  "properties": {
    "iso:country":"PL",
    "name:fra_x_preferred":[
        "Zacisze"
    ],
    "name:lit_x_preferred":[
        "Zaci\u0161\u0117"
    ],
    "name:pol_x_preferred":[
        "Zacisze"
    ],
    "name:ukr_x_preferred":[
        "\u0417\u0430\u0446\u0438\u0448\u0435"
    ],
    "qs_pg:aaroncc":"PL",
    "qs_pg:name":"Zacisze",
    "qs_pg:name_adm0":"Polska",
    "qs_pg:name_adm1":"Mazowieckie",
    "qs_pg:photos":60,
    "qs_pg:photos_1k":12,
    "qs_pg:photos_9k":1,
    "qs_pg:photos_9r":2,
    "qs_pg:photos_all":60,
    "qs_pg:photos_sr":2,
    "qs_pg:pop_sr":0,
    "qs_pg:qs_pg_placetype":"neighbourhood",
    "qs_pg:qs_pg_placetype_gp":"Suburb",
    "qs_pg:woe_adm0":23424923,
    "woe:adm0_id":23424923,
    "woe:name_adm0":"Polska",
    "woe:name_adm1":"Mazowieckie",
    "woe:placetype":"Suburb",
    "wof:name":"Zacisze",
    "wof:placetype":"neighbourhood"
},
  "geometry": {"coordinates":[21.063301,52.2941865],"type":"Point"}
}