{
  "type": "Feature",
  "properties": {
    "gn:admin1_code":"87.0",
    "gn:admin2_code":"3205.0",
    "gn:admin3_code":"320501.0",
    "gn:asciiname":"Latno",
    "gn:cc2":"PL",
    "gn:country_code":"PL",
    "gn:dem":28,
    "gn:feature_class":"P",
    "gn:feature_code":"PPL",
    "gn:name":"\u0141atno",
    "gn:population":0,
    "gn:timezone":"Europe/Warsaw",
    "iso:country":"PL",
    "name:deu_x_preferred":[
        "\u0141atno"
    ],
    "name:nld_x_preferred":[
        "\u0141atno"
    ],
    "name:pol_x_preferred":[
        "\u0141atno"
    ],
    "name:und_x_variant":[
        "Altendorf"
    ],
    "name:vie_x_preferred":[
        "\u0141atno"
    ],
    "wof:name":"Latno",
    "wof:placetype":"locality"
},
  "geometry": {"coordinates":[15.37279,53.98506],"type":"Point"}
}