{
  "type": "Feature",
  "properties": {
    "gn:admin1_code":"74.0",
    "gn:admin2_code":"1016.0",
    "gn:admin3_code":"101610.0",
    "gn:asciiname":"Ciosny",
    "gn:country_code":"PL",
    "gn:dem":197,
    "gn:feature_class":"P",
    "gn:feature_code":"PPL",
    "gn:name":"Ciosny",
    "gn:population":0,
    "gn:timezone":"Europe/Warsaw",
    "iso:country":"PL",
    "wof:name":"Ciosny",
    "wof:placetype":"locality"
},
  "geometry": {"coordinates":[19.8577,51.63744000000001],"type":"Point"}
}