{
  "type": "Feature",
  "properties": {
    "gn:admin1_code":"72.0",
    "gn:admin2_code":"222.0",
    "gn:admin3_code":"22203.0",
    "gn:asciiname":"Bozen",
    "gn:country_code":"PL",
    "gn:dem":101,
    "gn:feature_class":"P",
    "gn:feature_code":"PPL",
    "gn:name":"Bo\u017ce\u0144",
    "gn:population":0,
    "gn:timezone":"Europe/Warsaw",
    "iso:country":"PL",
    "name:ceb_x_preferred":[
        "Bo\u017ce\u0144"
    ],
    "name:ita_x_preferred":[
        "Bo\u017ce\u0144"
    ],
    "name:pol_x_preferred":[
        "Bo\u017ce\u0144"
    ],
    "name:ukr_x_preferred":[
        "\u0411\u043e\u0436\u0435\u043d\u044c"
    ],
    "wof:name":"Bozen",
    "wof:placetype":"locality"
},
  "geometry": {"coordinates":[16.63382,51.39171],"type":"Point"}
}