{
  "type": "Feature",
  "properties": {
    "gn:admin1_code":"85.0",
    "gn:admin2_code":"2813.0",
    "gn:admin3_code":"281303.0",
    "gn:asciiname":"Czukty",
    "gn:country_code":"PL",
    "gn:dem":190,
    "gn:feature_class":"P",
    "gn:feature_code":"PPL",
    "gn:name":"Czukty",
    "gn:population":0,
    "gn:timezone":"Europe/Warsaw",
    "iso:country":"PL",
    "name:azb_x_preferred":[
        "\u0686\u0648\u06a9\u062a\u0647"
    ],
    "name:deu_x_preferred":[
        "Czukty"
    ],
    "name:fas_x_preferred":[
        "\u0686\u0648\u06a9\u062a\u0647"
    ],
    "name:nld_x_preferred":[
        "Czukty"
    ],
    "name:pol_x_preferred":[
        "Czukty"
    ],
    "name:ukr_x_preferred":[
        "\u0427\u0443\u043a\u0442\u0438"
    ],
    "name:und_x_variant":[
        "Schuchten",
        "Czukten"
    ],
    "wof:name":"Czukty",
    "wof:placetype":"locality"
},
  "geometry": {"coordinates":[22.34797,54.11003],"type":"Point"}
}