{
  "type": "Feature",
  "properties": {
    "gn:admin1_code":"86.0",
    "gn:admin2_code":"3024.0",
    "gn:admin3_code":"302406.0",
    "gn:asciiname":"Podpniewki",
    "gn:country_code":"PL",
    "gn:dem":97,
    "gn:feature_class":"P",
    "gn:feature_code":"PPL",
    "gn:name":"Podpniewki",
    "gn:population":0,
    "gn:timezone":"Europe/Warsaw",
    "iso:country":"PL",
    "name:ceb_x_preferred":[
        "Podpniewki"
    ],
    "name:fra_x_preferred":[
        "Podpniewki"
    ],
    "name:pol_x_preferred":[
        "Podpniewki"
    ],
    "name:ukr_x_preferred":[
        "\u041f\u043e\u0434\u043f\u043d\u0435\u0432\u043a\u0456"
    ],
    "wof:name":"Podpniewki",
    "wof:placetype":"locality"
},
  "geometry": {"coordinates":[16.28202000000001,52.53571],"type":"Point"}
}