{
  "type": "Feature",
  "properties": {
    "gn:admin1_code":"85.0",
    "gn:admin2_code":"2804.0",
    "gn:admin3_code":"280407.0",
    "gn:asciiname":"Marzewo",
    "gn:cc2":"PL",
    "gn:country_code":"PL",
    "gn:dem":127,
    "gn:feature_class":"P",
    "gn:feature_code":"PPL",
    "gn:name":"Marzewo",
    "gn:population":0,
    "gn:timezone":"Europe/Warsaw",
    "iso:country":"PL",
    "name:ceb_x_preferred":[
        "Marzewo"
    ],
    "name:pol_x_preferred":[
        "Marzewo"
    ],
    "name:ukr_x_preferred":[
        "\u041c\u0430\u0436\u0435\u0432\u043e"
    ],
    "name:und_x_variant":[
        "Mahrau",
        "Mahrau bei Samrodt",
        "Morzewo"
    ],
    "wof:name":"Marzewo",
    "wof:placetype":"locality"
},
  "geometry": {"coordinates":[19.69368,53.96518],"type":"Point"}
}