{
  "type": "Feature",
  "properties": {
    "gn:admin1_code":"83.0",
    "gn:admin2_code":"2415.0",
    "gn:admin3_code":"241503.0",
    "gn:asciiname":"Pietrzkowice",
    "gn:country_code":"PL",
    "gn:dem":264,
    "gn:feature_class":"P",
    "gn:feature_code":"PPL",
    "gn:name":"Pietrzkowice",
    "gn:population":0,
    "gn:timezone":"Europe/Warsaw",
    "iso:country":"PL",
    "wof:name":"Pietrzkowice",
    "wof:placetype":"locality"
},
  "geometry": {"coordinates":[18.42665,50.08202],"type":"Point"}
}