{
  "type": "Feature",
  "properties": {
    "gn:admin1_code":"81.0",
    "gn:admin2_code":"2003.0",
    "gn:admin3_code":"200304.0",
    "gn:asciiname":"Moloczki",
    "gn:country_code":"PL",
    "gn:dem":150,
    "gn:feature_class":"P",
    "gn:feature_code":"PPL",
    "gn:name":"Mo\u0142oczki",
    "gn:population":0,
    "gn:timezone":"Europe/Warsaw",
    "iso:country":"PL",
    "name:azb_x_preferred":[
        "\u0645\u0648\u0648\u0648\u0686\u06a9\u06cc"
    ],
    "name:fas_x_preferred":[
        "\u0645\u0648\u0648\u0648\u0686\u06a9\u06cc"
    ],
    "name:fra_x_preferred":[
        "Mo\u0142oczki"
    ],
    "name:lit_x_preferred":[
        "Molo\u010dkai"
    ],
    "name:pol_x_preferred":[
        "Mo\u0142oczki"
    ],
    "name:ukr_x_preferred":[
        "\u041c\u043e\u043b\u043e\u0447\u043a\u0456"
    ],
    "wof:name":"Moloczki",
    "wof:placetype":"locality"
},
  "geometry": {"coordinates":[23.18647,52.59518000000001],"type":"Point"}
}