{
  "type": "Feature",
  "properties": {
    "gn:gn_country":"PL",
    "gn:gn_fcode":"ADM3",
    "gn:gn_pop":0,
    "iso:country":"PL",
    "name:pol_x_preferred":[
        "D\u0105browa G\u00f3rnicza"
    ],
    "qs_pg:aaroncc":"PL",
    "qs_pg:gn_country":"PL",
    "qs_pg:gn_fcode":"ADM3",
    "qs_pg:gn_pop":0,
    "qs_pg:name":"D\u0105browa G\u00f3rnicza",
    "qs_pg:photos_9r":0,
    "qs_pg:photos_sr":0,
    "qs_pg:pop_sr":0,
    "qs_pg:qs_pg_placetype":"localadmin",
    "wof:name":"D\u0105browa G\u00f3rnicza",
    "wof:placetype":"localadmin"
},
  "geometry": {"coordinates":[19.3213,50.371],"type":"Point"}
}