{
  "type": "Feature",
  "properties": {
    "gn:admin1_code":"73.0",
    "gn:asciiname":"Stypin",
    "gn:country_code":"PL",
    "gn:dem":111,
    "gn:feature_class":"P",
    "gn:feature_code":"PPL",
    "gn:name":"Stypin",
    "gn:population":0,
    "gn:timezone":"Europe/Warsaw",
    "iso:country":"PL",
    "name:pol_x_preferred":[
        "Stypin"
    ],
    "name:ukr_x_preferred":[
        "\u0421\u0442\u0438\u043f\u0456\u043d"
    ],
    "wof:name":"Stypin",
    "wof:placetype":"locality"
},
  "geometry": {"coordinates":[18.81181,52.34122],"type":"Point"}
}