{
  "type": "Feature",
  "properties": {
    "gn:admin1_code":"75.0",
    "gn:admin2_code":"602.0",
    "gn:admin3_code":"60206.0",
    "gn:asciiname":"Sredniowka",
    "gn:country_code":"PL",
    "gn:dem":253,
    "gn:feature_class":"P",
    "gn:feature_code":"PPL",
    "gn:name":"\u015aredni\u00f3wka",
    "gn:population":0,
    "gn:timezone":"Europe/Warsaw",
    "iso:country":"PL",
    "name:ceb_x_preferred":[
        "\u015aredni\u00f3wka"
    ],
    "name:fra_x_preferred":[
        "\u015aredni\u00f3wka"
    ],
    "name:pol_x_preferred":[
        "\u015aredni\u00f3wka"
    ],
    "name:ukr_x_preferred":[
        "\u0421\u044c\u0440\u0435\u0434\u043d\u044e\u0432\u043a\u0430"
    ],
    "name:und_x_variant":[
        "\u015aredni\u00f3wka"
    ],
    "wof:name":"Sredniowka",
    "wof:placetype":"locality"
},
  "geometry": {"coordinates":[22.74815,50.70894000000001],"type":"Point"}
}