{
  "type": "Feature",
  "properties": {
    "gn:admin1_code":"78.0",
    "gn:admin2_code":"1427.0",
    "gn:admin3_code":"142705.0",
    "gn:asciiname":"Rydzewo",
    "gn:country_code":"PL",
    "gn:dem":107,
    "gn:feature_class":"P",
    "gn:feature_code":"PPL",
    "gn:name":"Rydzewo",
    "gn:population":0,
    "gn:timezone":"Europe/Warsaw",
    "iso:country":"PL",
    "name:deu_x_preferred":[
        "Rydzewo"
    ],
    "name:fra_x_preferred":[
        "Rydzewo"
    ],
    "name:lit_x_preferred":[
        "Ridzevas"
    ],
    "name:pol_x_preferred":[
        "Rydzewo"
    ],
    "name:ukr_x_preferred":[
        "\u0420\u0438\u0434\u0437\u0435\u0432\u043e"
    ],
    "wof:name":"Rydzewo",
    "wof:placetype":"locality"
},
  "geometry": {"coordinates":[19.63449,52.88141],"type":"Point"}
}