{
  "type": "Feature",
  "properties": {
    "gn:admin1_code":"78.0",
    "gn:admin2_code":"1416.0",
    "gn:admin3_code":"141605.0",
    "gn:asciiname":"Podgorze Gazdy",
    "gn:country_code":"PL",
    "gn:dem":108,
    "gn:feature_class":"P",
    "gn:feature_code":"PPL",
    "gn:name":"Podg\u00f3rze Gazdy",
    "gn:population":0,
    "gn:timezone":"Europe/Warsaw",
    "iso:country":"PL",
    "name:und_x_variant":[
        "Podg\u00f3rze Gady",
        "Podg\u00f3rze Gazdy"
    ],
    "wof:name":"Podgorze Gazdy",
    "wof:placetype":"locality"
},
  "geometry": {"coordinates":[22.1292,52.69669],"type":"Point"}
}