{
  "type": "Feature",
  "properties": {
    "gn:admin1_code":"73.0",
    "gn:admin2_code":"411.0",
    "gn:admin3_code":"41107.0",
    "gn:asciiname":"Torzewo",
    "gn:country_code":"PL",
    "gn:dem":96,
    "gn:feature_class":"P",
    "gn:feature_code":"PPL",
    "gn:name":"Torzewo",
    "gn:population":0,
    "gn:timezone":"Europe/Warsaw",
    "iso:country":"PL",
    "name:pol_x_preferred":[
        "Torzewo"
    ],
    "name:ukr_x_preferred":[
        "\u0422\u043e\u0436\u0435\u0432\u043e"
    ],
    "wof:name":"Torzewo",
    "wof:placetype":"locality"
},
  "geometry": {"coordinates":[18.72798,52.56788],"type":"Point"}
}