{
  "type": "Feature",
  "properties": {
    "gn:admin1_code":"78.0",
    "gn:admin2_code":"1434.0",
    "gn:admin3_code":"143401.0",
    "gn:asciiname":"Maciolki",
    "gn:country_code":"PL",
    "gn:dem":88,
    "gn:feature_class":"P",
    "gn:feature_code":"PPL",
    "gn:name":"Macio\u0142ki",
    "gn:population":0,
    "gn:timezone":"Europe/Warsaw",
    "iso:country":"PL",
    "wof:name":"Maciolki",
    "wof:placetype":"locality"
},
  "geometry": {"coordinates":[21.1689,52.32677],"type":"Point"}
}