{
  "type": "Feature",
  "properties": {
    "gn:admin1_code":"75.0",
    "gn:admin2_code":"620.0",
    "gn:admin3_code":"62013.0",
    "gn:asciiname":"Szperowka",
    "gn:country_code":"PL",
    "gn:dem":314,
    "gn:feature_class":"P",
    "gn:feature_code":"PPL",
    "gn:name":"Szper\u00f3wka",
    "gn:population":0,
    "gn:timezone":"Europe/Warsaw",
    "iso:country":"PL",
    "wof:name":"Szperowka",
    "wof:placetype":"neighbourhood"
},
  "geometry": {"coordinates":[22.90457,50.70991],"type":"Point"}
}