{
  "type": "Feature",
  "properties": {
    "gn:admin1_code":"73.0",
    "gn:admin2_code":"416.0",
    "gn:admin3_code":"41605.0",
    "gn:asciiname":"Brzozowe Blota",
    "gn:country_code":"PL",
    "gn:dem":117,
    "gn:feature_class":"P",
    "gn:feature_code":"PPL",
    "gn:name":"Brzozowe B\u0142ota",
    "gn:population":0,
    "gn:timezone":"Europe/Warsaw",
    "iso:country":"PL",
    "name:pol_x_preferred":[
        "Brzozowe B\u0142ota"
    ],
    "name:ukr_x_preferred":[
        "\u0411\u0436\u043e\u0437\u043e\u0432\u0435-\u0411\u043b\u043e\u0442\u0430"
    ],
    "wof:name":"Brzozowe Blota",
    "wof:placetype":"locality"
},
  "geometry": {"coordinates":[18.12666,53.6672],"type":"Point"}
}