{
  "type": "Feature",
  "properties": {
    "gn:admin1_code":"86.0",
    "gn:admin2_code":"3006.0",
    "gn:admin3_code":"300604.0",
    "gn:asciiname":"Zerniki",
    "gn:country_code":"PL",
    "gn:dem":77,
    "gn:feature_class":"P",
    "gn:feature_code":"PPL",
    "gn:name":"\u017berniki",
    "gn:population":0,
    "gn:timezone":"Europe/Warsaw",
    "iso:country":"PL",
    "wof:name":"Zerniki",
    "wof:placetype":"locality"
},
  "geometry": {"coordinates":[17.66868999999999,52.06679000000001],"type":"Point"}
}