{
  "type": "Feature",
  "properties": {
    "gn:admin1_code":"87.0",
    "gn:admin2_code":"3213.0",
    "gn:admin3_code":"321303.0",
    "gn:asciiname":"Sulimice",
    "gn:country_code":"PL",
    "gn:dem":14,
    "gn:feature_class":"P",
    "gn:feature_code":"PPL",
    "gn:name":"Sulimice",
    "gn:population":0,
    "gn:timezone":"Europe/Warsaw",
    "iso:country":"PL",
    "name:ceb_x_preferred":[
        "Sulimice"
    ],
    "name:deu_x_preferred":[
        "Sulimice"
    ],
    "name:pol_x_preferred":[
        "Sulimice"
    ],
    "name:ukr_x_preferred":[
        "\u0421\u0443\u043b\u0456\u043c\u0456\u0446\u0435"
    ],
    "name:vie_x_preferred":[
        "Sulimice"
    ],
    "wof:name":"Sulimice",
    "wof:placetype":"locality"
},
  "geometry": {"coordinates":[16.52519,54.46362],"type":"Point"}
}