{
  "type": "Feature",
  "properties": {
    "gn:admin1_code":"87.0",
    "gn:admin2_code":"3213.0",
    "gn:admin3_code":"321303.0",
    "gn:asciiname":"Sulimice",
    "gn:country_code":"PL",
    "gn:dem":14,
    "gn:feature_class":"P",
    "gn:feature_code":"PPL",
    "gn:name":"Sulimice",
    "gn:population":0,
    "gn:timezone":"Europe/Warsaw",
    "iso:country":"PL",
    "wof:name":"Sulimice",
    "wof:placetype":"locality"
},
  "geometry": {"coordinates":[16.52519,54.46362],"type":"Point"}
}