{
  "type": "Feature",
  "properties": {
    "iso:country":"PL",
    "name:azb_x_preferred":[
        "\u067e\u0627\u0631\u062e\u0648\u0648\u0648"
    ],
    "name:csb_x_preferred":[
        "Parch\u00f2w\u00f2"
    ],
    "name:deu_x_preferred":[
        "Parchowo"
    ],
    "name:fas_x_preferred":[
        "\u067e\u0627\u0631\u062e\u0648\u0648\u0648"
    ],
    "name:pol_x_preferred":[
        "Parchowo"
    ],
    "name:szl_x_preferred":[
        "Parchowo"
    ],
    "name:ukr_x_preferred":[
        "\u041f\u0430\u0440\u0445\u043e\u0432\u043e"
    ],
    "wof:coterminous":[
        1125324733
    ],
    "wof:name":"Parchowo",
    "wof:placetype":"locality"
},
  "geometry": {"coordinates":[17.6686913675607,54.217784638317],"type":"Point"}
}