{
  "type": "Feature",
  "properties": {
    "iso:country":"PL",
    "name:pol_x_preferred":[
        "Parchowo"
    ],
    "wof:name":"Parchowo",
    "wof:placetype":"locality"
},
  "geometry": {"coordinates":[17.6686913675607,54.217784638317],"type":"Point"}
}