{
  "type": "Feature",
  "properties": {
    "gn:admin1_code":"78.0",
    "gn:admin2_code":"1403.0",
    "gn:admin3_code":"140306.0",
    "gn:asciiname":"Grabina",
    "gn:country_code":"PL",
    "gn:dem":131,
    "gn:feature_class":"P",
    "gn:feature_code":"PPL",
    "gn:name":"Grabina",
    "gn:population":0,
    "gn:timezone":"Europe/Warsaw",
    "iso:country":"PL",
    "name:deu_x_preferred":[
        "Grabina"
    ],
    "name:fra_x_preferred":[
        "Grabina"
    ],
    "name:pol_x_preferred":[
        "Grabina"
    ],
    "name:ukr_x_preferred":[
        "\u0490\u0440\u0430\u0431\u0456\u043d\u0430"
    ],
    "wof:name":"Grabina",
    "wof:placetype":"locality"
},
  "geometry": {"coordinates":[21.51764,51.82664000000001],"type":"Point"}
}