{
  "type": "Feature",
  "properties": {
    "gn:admin1_code":"86.0",
    "gn:admin2_code":"3029.0",
    "gn:admin3_code":"302902.0",
    "gn:asciiname":"Grojec Wielki",
    "gn:country_code":"PL",
    "gn:dem":56,
    "gn:feature_class":"P",
    "gn:feature_code":"PPL",
    "gn:name":"Gr\u00f3jec Wielki",
    "gn:population":0,
    "gn:timezone":"Europe/Warsaw",
    "iso:country":"PL",
    "name:und_x_variant":[
        "Gr\u00f3jec Wielki"
    ],
    "wof:name":"Grojec Wielki",
    "wof:placetype":"locality"
},
  "geometry": {"coordinates":[15.89305,52.17372],"type":"Point"}
}