{
  "type": "Feature",
  "properties": {
    "gn:admin1_code":"78.0",
    "gn:admin2_code":"1416.0",
    "gn:admin3_code":"141607.0",
    "gn:asciiname":"Koziki Majdan",
    "gn:country_code":"PL",
    "gn:dem":111,
    "gn:feature_class":"P",
    "gn:feature_code":"PPL",
    "gn:name":"Koziki Majdan",
    "gn:population":0,
    "gn:timezone":"Europe/Warsaw",
    "iso:country":"PL",
    "wof:name":"Koziki Majdan",
    "wof:placetype":"locality"
},
  "geometry": {"coordinates":[21.75234,52.80056],"type":"Point"}
}