{
  "type": "Feature",
  "properties": {
    "gn:admin1_code":"87.0",
    "gn:admin2_code":"3213.0",
    "gn:admin3_code":"321304.0",
    "gn:asciiname":"Podgorki",
    "gn:country_code":"PL",
    "gn:dem":60,
    "gn:feature_class":"P",
    "gn:feature_code":"PPL",
    "gn:name":"Podg\u00f3rki",
    "gn:population":0,
    "gn:timezone":"Europe/Warsaw",
    "iso:country":"PL",
    "name:ceb_x_preferred":[
        "Podg\u00f3rki"
    ],
    "name:deu_x_preferred":[
        "Podg\u00f3rki"
    ],
    "name:pol_x_preferred":[
        "Podg\u00f3rki"
    ],
    "name:ukr_x_preferred":[
        "\u041f\u043e\u0434\u0491\u0443\u0440\u043a\u0456"
    ],
    "name:vie_x_preferred":[
        "Podg\u00f3rki"
    ],
    "wof:name":"Podgorki",
    "wof:placetype":"locality"
},
  "geometry": {"coordinates":[16.63492,54.27428000000001],"type":"Point"}
}