{
  "type": "Feature",
  "properties": {
    "gn:admin1_code":"78.0",
    "gn:admin2_code":"1427.0",
    "gn:admin3_code":"142704.0",
    "gn:asciiname":"Rzeszotary Gortaty",
    "gn:country_code":"PL",
    "gn:dem":113,
    "gn:feature_class":"P",
    "gn:feature_code":"PPL",
    "gn:name":"Rzeszotary Gortaty",
    "gn:population":0,
    "gn:timezone":"Europe/Warsaw",
    "iso:country":"PL",
    "name:fra_x_preferred":[
        "Rzeszotary-Gortaty"
    ],
    "name:pol_x_preferred":[
        "Rzeszotary-Gortaty"
    ],
    "name:ukr_x_preferred":[
        "\u0416\u0435\u0448\u043e\u0442\u0430\u0440\u0438-\u0490\u043e\u0440\u0442\u0430\u0442\u0438"
    ],
    "wof:name":"Rzeszotary Gortaty",
    "wof:placetype":"locality"
},
  "geometry": {"coordinates":[19.81249,52.86769],"type":"Point"}
}