{
  "type": "Feature",
  "properties": {
    "gn:admin1_code":"74.0",
    "gn:admin2_code":"1005.0",
    "gn:admin3_code":"100503.0",
    "gn:asciiname":"Karsznice Male",
    "gn:country_code":"PL",
    "gn:dem":94,
    "gn:feature_class":"P",
    "gn:feature_code":"PPL",
    "gn:name":"Karsznice Ma\u0142e",
    "gn:population":0,
    "gn:timezone":"Europe/Warsaw",
    "iso:country":"PL",
    "name:fra_x_preferred":[
        "Karsznice Ma\u0142e"
    ],
    "name:pol_x_preferred":[
        "Karsznice Ma\u0142e"
    ],
    "name:ukr_x_preferred":[
        "\u041a\u0430\u0440\u0448\u043d\u0456\u0446\u0435-\u041c\u0430\u043b\u0456"
    ],
    "name:und_x_variant":[
        "Karsznice Ma\u0142e"
    ],
    "wof:name":"Karsznice Male",
    "wof:placetype":"locality"
},
  "geometry": {"coordinates":[19.87166,52.22525],"type":"Point"}
}