{
  "type": "Feature",
  "properties": {
    "gn:admin1_code":"86.0",
    "gn:admin2_code":"3018.0",
    "gn:admin3_code":"301803.0",
    "gn:asciiname":"Gizyce",
    "gn:country_code":"PL",
    "gn:dem":131,
    "gn:feature_class":"P",
    "gn:feature_code":"PPL",
    "gn:name":"Gi\u017cyce",
    "gn:population":0,
    "gn:timezone":"Europe/Warsaw",
    "iso:country":"PL",
    "name:pol_x_preferred":[
        "Gi\u017cyce"
    ],
    "name:ukr_x_preferred":[
        "\u0490\u0456\u0436\u0438\u0446\u0435"
    ],
    "name:und_x_variant":[
        "Gi\u017cyce"
    ],
    "wof:name":"Gizyce",
    "wof:placetype":"locality"
},
  "geometry": {"coordinates":[18.15598,51.52393],"type":"Point"}
}