{
  "type": "Feature",
  "properties": {
    "gn:admin1_code":"74.0",
    "gn:admin2_code":"1001.0",
    "gn:admin3_code":"100108.0",
    "gn:asciiname":"Ostoja",
    "gn:country_code":"PL",
    "gn:dem":208,
    "gn:feature_class":"P",
    "gn:feature_code":"PPL",
    "gn:name":"Ostoja",
    "gn:population":0,
    "gn:timezone":"Europe/Warsaw",
    "iso:country":"PL",
    "name:fra_x_preferred":[
        "Ostoja"
    ],
    "name:pol_x_preferred":[
        "Ostoja"
    ],
    "name:ukr_x_preferred":[
        "\u041e\u0441\u0442\u043e\u044f"
    ],
    "wof:name":"Ostoja",
    "wof:placetype":"locality"
},
  "geometry": {"coordinates":[19.31525,51.45065],"type":"Point"}
}