{
  "type": "Feature",
  "properties": {
    "gn:gn_country":"PL",
    "gn:gn_fcode":"PPL",
    "gn:gn_pop":380,
    "gn:population":380,
    "iso:country":"PL",
    "name:deu_x_preferred":[
        "Kazimierz"
    ],
    "name:eng_x_preferred":[
        "Kazimierz"
    ],
    "name:fas_x_preferred":[
        "\u06a9\u0627\u0698\u0645\u06cc\u0698"
    ],
    "name:fra_x_preferred":[
        "Kazimierz"
    ],
    "name:nan_x_preferred":[
        "Kazimierz"
    ],
    "name:pol_x_preferred":[
        "Kazimierz"
    ],
    "qs_pg:aaroncc":"PL",
    "qs_pg:gn_country":"PL",
    "qs_pg:gn_fcode":"PPL",
    "qs_pg:gn_pop":380,
    "qs_pg:name":"Kazimierz",
    "qs_pg:name_adm0":"Polska",
    "qs_pg:name_adm1":"Opolskie",
    "qs_pg:photos_9k":1,
    "qs_pg:photos_9r":1,
    "qs_pg:photos_all":1,
    "qs_pg:photos_sr":0,
    "qs_pg:pop_sr":2,
    "qs_pg:qs_pg_placetype":"locality",
    "qs_pg:qs_pg_placetype_gp":"Town",
    "qs_pg:woe_adm0":23424923,
    "woe:adm0_id":23424923,
    "woe:name_adm0":"Polska",
    "woe:name_adm1":"Opolskie",
    "woe:placetype":"Town",
    "wof:name":"Kazimierz",
    "wof:placetype":"locality",
    "wof:population":380
},
  "geometry": {"coordinates":[17.8933,50.29636],"type":"Point"}
}