{
  "type": "Feature",
  "properties": {
    "gn:admin1_code":"85.0",
    "gn:admin2_code":"2817.0",
    "gn:admin3_code":"281708.0",
    "gn:asciiname":"Borki Wielbarskie",
    "gn:country_code":"PL",
    "gn:dem":126,
    "gn:feature_class":"P",
    "gn:feature_code":"PPL",
    "gn:name":"Borki Wielbarskie",
    "gn:population":0,
    "gn:timezone":"Europe/Warsaw",
    "iso:country":"PL",
    "name:pol_x_preferred":[
        "Borki Wielbarskie"
    ],
    "name:ukr_x_preferred":[
        "\u0411\u043e\u0440\u043a\u0456-\u0412\u0435\u043b\u044c\u0431\u0430\u0440\u0441\u044c\u043a\u0456"
    ],
    "name:und_x_variant":[
        "Borki",
        "Borkenheide",
        "Borken bei Willenberg",
        "Borken"
    ],
    "wof:name":"Borki Wielbarskie",
    "wof:placetype":"locality"
},
  "geometry": {"coordinates":[21.0399,53.40253000000001],"type":"Point"}
}