{
  "type": "Feature",
  "properties": {
    "gn:admin1_code":"82.0",
    "gn:admin2_code":"2202.0",
    "gn:admin3_code":"220204.0",
    "gn:asciiname":"Lukowo",
    "gn:country_code":"PL",
    "gn:dem":126,
    "gn:feature_class":"P",
    "gn:feature_code":"PPL",
    "gn:name":"\u0141ukowo",
    "gn:population":0,
    "gn:timezone":"Europe/Warsaw",
    "iso:country":"PL",
    "name:ceb_x_preferred":[
        "\u0141ukowo"
    ],
    "name:pol_x_preferred":[
        "\u0141ukowo"
    ],
    "name:ukr_x_preferred":[
        "\u041b\u0443\u043a\u043e\u0432\u043e"
    ],
    "wof:name":"Lukowo",
    "wof:placetype":"locality"
},
  "geometry": {"coordinates":[17.93123,53.76515],"type":"Point"}
}