{
  "type": "Feature",
  "properties": {
    "gn:admin1_code":"78.0",
    "gn:admin2_code":"1404.0",
    "gn:admin3_code":"140402.0",
    "gn:asciiname":"Gasno",
    "gn:country_code":"PL",
    "gn:dem":96,
    "gn:feature_class":"P",
    "gn:feature_code":"PPL",
    "gn:name":"Ga\u015bno",
    "gn:population":0,
    "gn:timezone":"Europe/Warsaw",
    "iso:country":"PL",
    "name:azb_x_preferred":[
        "\u0642\u0627\u0634\u0646\u0648"
    ],
    "name:deu_x_preferred":[
        "Ga\u015bno"
    ],
    "name:fas_x_preferred":[
        "\u06af\u0627\u0634\u0646\u0648"
    ],
    "name:fra_x_preferred":[
        "Ga\u015bno"
    ],
    "name:pol_x_preferred":[
        "Ga\u015bno"
    ],
    "name:ukr_x_preferred":[
        "\u0490\u0430\u0441\u044c\u043d\u043e"
    ],
    "wof:name":"Gasno",
    "wof:placetype":"locality"
},
  "geometry": {"coordinates":[19.50727,52.42709],"type":"Point"}
}