{
  "type": "Feature",
  "properties": {
    "gn:admin1_code":"78.0",
    "gn:admin2_code":"1404.0",
    "gn:admin3_code":"140402.0",
    "gn:asciiname":"Gasno",
    "gn:country_code":"PL",
    "gn:dem":96,
    "gn:feature_class":"P",
    "gn:feature_code":"PPL",
    "gn:name":"Ga\u015bno",
    "gn:population":0,
    "gn:timezone":"Europe/Warsaw",
    "iso:country":"PL",
    "name:und_x_variant":[
        "Ga\u015bno"
    ],
    "wof:name":"Gasno",
    "wof:placetype":"locality"
},
  "geometry": {"coordinates":[19.50727,52.42709],"type":"Point"}
}