{
  "type": "Feature",
  "properties": {
    "gn:admin1_code":"83.0",
    "gn:admin2_code":"2413.0",
    "gn:admin3_code":"241303.0",
    "gn:asciiname":"Radzionkow Nowy",
    "gn:country_code":"PL",
    "gn:dem":292,
    "gn:feature_class":"P",
    "gn:feature_code":"PPL",
    "gn:name":"Radzionk\u00f3w Nowy",
    "gn:population":0,
    "gn:timezone":"Europe/Warsaw",
    "iso:country":"PL",
    "wof:name":"Radzionkow Nowy",
    "wof:placetype":"locality"
},
  "geometry": {"coordinates":[18.9006,50.3851],"type":"Point"}
}