{
  "type": "Feature",
  "properties": {
    "gn:admin1_code":"72.0",
    "gn:admin2_code":"217.0",
    "gn:admin3_code":"21704.0",
    "gn:asciiname":"Mikoszow",
    "gn:country_code":"PL",
    "gn:dem":162,
    "gn:feature_class":"P",
    "gn:feature_code":"PPL",
    "gn:name":"Mikosz\u00f3w",
    "gn:population":0,
    "gn:timezone":"Europe/Warsaw",
    "iso:country":"PL",
    "name:pol_x_preferred":[
        "Mikosz\u00f3w"
    ],
    "name:ukr_x_preferred":[
        "\u041c\u0456\u043a\u043e\u0448\u0443\u0432"
    ],
    "wof:name":"Mikoszow",
    "wof:placetype":"locality"
},
  "geometry": {"coordinates":[17.03585,50.77929],"type":"Point"}
}