{
  "type": "Feature",
  "properties": {
    "gn:admin1_code":"78.0",
    "gn:admin2_code":"1411.0",
    "gn:admin3_code":"141103.0",
    "gn:asciiname":"Gosciejewo",
    "gn:country_code":"PL",
    "gn:dem":93,
    "gn:feature_class":"P",
    "gn:feature_code":"PPL",
    "gn:name":"Go\u015bciejewo",
    "gn:population":0,
    "gn:timezone":"Europe/Warsaw",
    "iso:country":"PL",
    "name:fra_x_preferred":[
        "Go\u015bciejewo"
    ],
    "name:pol_x_preferred":[
        "Go\u015bciejewo"
    ],
    "name:ukr_x_preferred":[
        "\u0490\u043e\u0441\u0446\u0454\u0454\u0432\u043e"
    ],
    "wof:name":"Gosciejewo",
    "wof:placetype":"locality"
},
  "geometry": {"coordinates":[21.03311,52.78522],"type":"Point"}
}