{
  "type": "Feature",
  "properties": {
    "gn:admin1_code":"81.0",
    "gn:admin2_code":"2007.0",
    "gn:admin3_code":"200701.0",
    "gn:asciiname":"Mocarze",
    "gn:country_code":"PL",
    "gn:dem":109,
    "gn:feature_class":"P",
    "gn:feature_code":"PPL",
    "gn:name":"Mocarze",
    "gn:population":0,
    "gn:timezone":"Europe/Warsaw",
    "iso:country":"PL",
    "name:lit_x_preferred":[
        "Moca\u017e\u0117"
    ],
    "name:pol_x_preferred":[
        "Mocarze"
    ],
    "name:ukr_x_preferred":[
        "\u041c\u043e\u0446\u0430\u0436\u0435"
    ],
    "wof:name":"Mocarze",
    "wof:placetype":"locality"
},
  "geometry": {"coordinates":[22.45417,53.30072],"type":"Point"}
}