{
  "type": "Feature",
  "properties": {
    "gn:admin1_code":"78.0",
    "gn:admin2_code":"1438.0",
    "gn:admin3_code":"143803.0",
    "gn:asciiname":"Studzieniec",
    "gn:country_code":"PL",
    "gn:dem":138,
    "gn:feature_class":"P",
    "gn:feature_code":"PPL",
    "gn:name":"Studzieniec",
    "gn:population":0,
    "gn:timezone":"Europe/Warsaw",
    "iso:country":"PL",
    "name:ceb_x_preferred":[
        "Studzieniec"
    ],
    "name:fra_x_preferred":[
        "Studzieniec"
    ],
    "name:pol_x_preferred":[
        "Studzieniec"
    ],
    "name:ukr_x_preferred":[
        "\u0421\u0442\u0443\u0434\u0437\u0435\u043d\u0435\u0446\u044c"
    ],
    "wof:name":"Studzieniec",
    "wof:placetype":"locality"
},
  "geometry": {"coordinates":[20.3926,51.9918],"type":"Point"}
}