{
  "type": "Feature",
  "properties": {
    "gn:admin1_code":"72.0",
    "gn:admin2_code":"264.0",
    "gn:admin3_code":"26401.0",
    "gn:asciiname":"Stare Miasto",
    "gn:country_code":"PL",
    "gn:dem":121,
    "gn:feature_class":"P",
    "gn:feature_code":"PPL",
    "gn:name":"Stare Miasto",
    "gn:population":0,
    "gn:timezone":"Europe/Warsaw",
    "iso:country":"PL",
    "wof:name":"Stare Miasto",
    "wof:placetype":"locality"
},
  "geometry": {"coordinates":[17.03714,51.11034],"type":"Point"}
}