{
  "type": "Feature",
  "properties": {
    "gn:country":"PL",
    "gn:fcode":"PPL",
    "gn:population":181,
    "iso:country":"PL",
    "name:ast_x_preferred":[
        "Czarnocin"
    ],
    "name:ceb_x_preferred":[
        "Czarnocin"
    ],
    "name:ces_x_preferred":[
        "Czarnocin"
    ],
    "name:che_x_preferred":[
        "\u0427\u0430\u0440\u043d\u043e\u0446\u0438\u043d"
    ],
    "name:eng_x_preferred":[
        "Czarnocin"
    ],
    "name:fra_x_preferred":[
        "Czarnocin"
    ],
    "name:nan_x_preferred":[
        "Czarnocin"
    ],
    "name:pol_x_preferred":[
        "Czarnocin"
    ],
    "name:tat_x_preferred":[
        "\u0427\u0430\u0440\u043d\u043e\u0446\u0438\u043d"
    ],
    "name:ukr_x_preferred":[
        "\u0427\u0430\u0440\u043d\u043e\u0446\u0438\u043d"
    ],
    "qs_pg:aaroncc":"PL",
    "qs_pg:gn_country":"PL",
    "qs_pg:gn_fcode":"PPL",
    "qs_pg:gn_pop":181,
    "qs_pg:name":"Czarnocin",
    "qs_pg:name_adm0":"Polska",
    "qs_pg:name_adm1":"Mazowieckie",
    "qs_pg:photos_9r":0,
    "qs_pg:photos_sr":0,
    "qs_pg:pop_sr":1,
    "qs_pg:qs_pg_placetype":"locality",
    "qs_pg:qs_pg_placetype_gp":"Town",
    "qs_pg:woe_adm0":23424923,
    "woe:adm0_id":23424923,
    "woe:name_adm0":"Polska",
    "woe:name_adm1":"Mazowieckie",
    "woe:placetype":"Town",
    "wof:name":"Czarnocin",
    "wof:placetype":"locality",
    "wof:population":181
},
  "geometry": {"coordinates":[20.38573,52.90916],"type":"Point"}
}