{
  "type": "Feature",
  "properties": {
    "gn:admin1_code":"85.0",
    "gn:admin2_code":"2813.0",
    "gn:admin3_code":"281303.0",
    "gn:asciiname":"Szarejki",
    "gn:country_code":"PL",
    "gn:dem":214,
    "gn:feature_class":"P",
    "gn:feature_code":"PPL",
    "gn:name":"Szarejki",
    "gn:population":0,
    "gn:timezone":"Europe/Warsaw",
    "iso:country":"PL",
    "name:ceb_x_preferred":[
        "Szarejki"
    ],
    "name:deu_x_preferred":[
        "Szarejki"
    ],
    "name:nld_x_preferred":[
        "Szarejki"
    ],
    "name:pol_x_preferred":[
        "Szarejki"
    ],
    "name:ukr_x_preferred":[
        "\u0428\u0430\u0440\u0435\u0439\u043a\u0456"
    ],
    "name:und_x_variant":[
        "Schareyken",
        "Schareiken"
    ],
    "wof:name":"Szarejki",
    "wof:placetype":"locality"
},
  "geometry": {"coordinates":[22.40825,54.13141],"type":"Point"}
}