{
  "type": "Feature",
  "properties": {
    "gn:admin1_code":"75.0",
    "gn:admin2_code":"609.0",
    "gn:admin3_code":"60911.0",
    "gn:asciiname":"Kolonia Majdan Krasieninski",
    "gn:country_code":"PL",
    "gn:dem":202,
    "gn:feature_class":"P",
    "gn:feature_code":"PPL",
    "gn:name":"Kolonia Majdan Krasieni\u0144ski",
    "gn:population":0,
    "gn:timezone":"Europe/Warsaw",
    "iso:country":"PL",
    "wof:name":"Kolonia Majdan Krasieninski",
    "wof:placetype":"locality"
},
  "geometry": {"coordinates":[22.45,51.35],"type":"Point"}
}