{
  "type": "Feature",
  "properties": {
    "gn:admin1_code":"78.0",
    "gn:admin2_code":"1419.0",
    "gn:admin3_code":"141901.0",
    "gn:asciiname":"Zagroba Koscielna",
    "gn:country_code":"PL",
    "gn:dem":139,
    "gn:feature_class":"P",
    "gn:feature_code":"PPL",
    "gn:name":"Zagroba Ko\u015bcielna",
    "gn:population":0,
    "gn:timezone":"Europe/Warsaw",
    "iso:country":"PL",
    "name:fra_x_preferred":[
        "Zagroba"
    ],
    "name:pol_x_preferred":[
        "Zagroba"
    ],
    "name:ukr_x_preferred":[
        "\u0417\u0430\u0491\u0440\u043e\u0431\u0430"
    ],
    "name:und_x_variant":[
        "Zagroba",
        "Zagroba Ko\u015bcielna"
    ],
    "name:urd_x_preferred":[
        "\u0632\u06af\u0631\u0648\u0628\u0627"
    ],
    "wof:name":"Zagroba Koscielna",
    "wof:placetype":"locality"
},
  "geometry": {"coordinates":[19.89459,52.63635],"type":"Point"}
}