{
  "type": "Feature",
  "properties": {
    "gn:admin1_code":"77.0",
    "gn:admin2_code":"1210.0",
    "gn:admin3_code":"121014.0",
    "gn:asciiname":"Stadla",
    "gn:cc2":"PL",
    "gn:country_code":"PL",
    "gn:dem":300,
    "gn:feature_class":"P",
    "gn:feature_code":"PPL",
    "gn:name":"Stad\u0142a",
    "gn:population":0,
    "gn:timezone":"Europe/Warsaw",
    "iso:country":"PL",
    "name:und_x_variant":[
        "Stad\u0142a",
        "Stad\u0142o"
    ],
    "wof:name":"Stadla",
    "wof:placetype":"locality"
},
  "geometry": {"coordinates":[20.61027,49.58434000000001],"type":"Point"}
}