{
  "type": "Feature",
  "properties": {
    "gn:admin1_code":"74.0",
    "gn:admin2_code":"1005.0",
    "gn:admin3_code":"100510.0",
    "gn:asciiname":"Bogoria Gorna",
    "gn:cc2":"PL",
    "gn:country_code":"PL",
    "gn:dem":95,
    "gn:feature_class":"P",
    "gn:feature_code":"PPL",
    "gn:name":"Bogoria G\u00f3rna",
    "gn:population":0,
    "gn:timezone":"Europe/Warsaw",
    "iso:country":"PL",
    "name:fra_x_preferred":[
        "Bogoria G\u00f3rna"
    ],
    "name:pol_x_preferred":[
        "Bogoria G\u00f3rna"
    ],
    "name:ukr_x_preferred":[
        "\u0411\u043e\u0491\u043e\u0440\u0456\u044f-\u0490\u0443\u0440\u043d\u0430"
    ],
    "name:und_x_variant":[
        "Bogorja G\u00f3rna",
        "Bogoria G\u00f3rna"
    ],
    "wof:name":"Bogoria Gorna",
    "wof:placetype":"locality"
},
  "geometry": {"coordinates":[19.74535,52.13507],"type":"Point"}
}