{
  "type": "Feature",
  "properties": {
    "gn:admin1_code":"82.0",
    "gn:admin2_code":"2206.0",
    "gn:admin3_code":"220604.0",
    "gn:asciiname":"Mala Stawiska",
    "gn:country_code":"PL",
    "gn:dem":146,
    "gn:feature_class":"P",
    "gn:feature_code":"PPL",
    "gn:name":"Ma\u0142a Stawiska",
    "gn:population":0,
    "gn:timezone":"Europe/Warsaw",
    "iso:country":"PL",
    "name:und_x_variant":[
        "Stawiska",
        "Ma\u0142a Stawiska"
    ],
    "wof:name":"Mala Stawiska",
    "wof:placetype":"locality"
},
  "geometry": {"coordinates":[18.03496,54.04791],"type":"Point"}
}