{
  "type": "Feature",
  "properties": {
    "gn:admin1_code":"80.0",
    "gn:admin2_code":"1809.0",
    "gn:admin3_code":"180903.0",
    "gn:asciiname":"Puchacze",
    "gn:country_code":"PL",
    "gn:dem":240,
    "gn:feature_class":"P",
    "gn:feature_code":"PPL",
    "gn:name":"Puchacze",
    "gn:population":0,
    "gn:timezone":"Europe/Warsaw",
    "iso:country":"PL",
    "name:fra_x_preferred":[
        "Puchacze"
    ],
    "name:lit_x_preferred":[
        "Pucha\u010d\u0117"
    ],
    "name:pol_x_preferred":[
        "Puchacze"
    ],
    "name:ukr_x_preferred":[
        "\u041f\u0443\u0445\u0430\u0447\u0435"
    ],
    "wof:name":"Puchacze",
    "wof:placetype":"locality"
},
  "geometry": {"coordinates":[23.31011,50.21372],"type":"Point"}
}