{
  "type": "Feature",
  "properties": {
    "gn:admin1_code":"83.0",
    "gn:admin2_code":"2402.0",
    "gn:admin3_code":"240205.0",
    "gn:asciiname":"Landek",
    "gn:country_code":"PL",
    "gn:dem":257,
    "gn:feature_class":"P",
    "gn:feature_code":"PPL",
    "gn:name":"Landek",
    "gn:population":0,
    "gn:timezone":"Europe/Warsaw",
    "iso:country":"PL",
    "wof:name":"Landek",
    "wof:placetype":"locality"
},
  "geometry": {"coordinates":[18.87838,49.88105],"type":"Point"}
}