{
  "type": "Feature",
  "properties": {
    "gn:admin1_code":"83.0",
    "gn:admin2_code":"2402.0",
    "gn:admin3_code":"240205.0",
    "gn:asciiname":"Landek",
    "gn:country_code":"PL",
    "gn:dem":257,
    "gn:feature_class":"P",
    "gn:feature_code":"PPL",
    "gn:name":"Landek",
    "gn:population":0,
    "gn:timezone":"Europe/Warsaw",
    "iso:country":"PL",
    "name:azb_x_preferred":[
        "\u0644\u0627\u0646\u062f\u06a9"
    ],
    "name:ceb_x_preferred":[
        "Landek"
    ],
    "name:ces_x_preferred":[
        "Landek"
    ],
    "name:deu_x_preferred":[
        "Landek"
    ],
    "name:fas_x_preferred":[
        "\u0644\u0627\u0646\u062f\u06a9"
    ],
    "name:pol_x_preferred":[
        "Landek"
    ],
    "name:ukr_x_preferred":[
        "\u041b\u044f\u043d\u0434\u0435\u043a"
    ],
    "name:urd_x_preferred":[
        "\u0644\u0627\u0646\u0688\u06cc\u06a9"
    ],
    "wof:name":"Landek",
    "wof:placetype":"locality"
},
  "geometry": {"coordinates":[18.87838,49.88105],"type":"Point"}
}