{
  "type": "Feature",
  "properties": {
    "gn:admin1_code":"78.0",
    "gn:admin2_code":"1419.0",
    "gn:admin3_code":"141905.0",
    "gn:asciiname":"Rogotworsk",
    "gn:country_code":"PL",
    "gn:dem":132,
    "gn:feature_class":"P",
    "gn:feature_code":"PPL",
    "gn:name":"Rogotworsk",
    "gn:population":0,
    "gn:timezone":"Europe/Warsaw",
    "iso:country":"PL",
    "name:fra_x_preferred":[
        "Rogotw\u00f3rsk"
    ],
    "name:pol_x_preferred":[
        "Rogotw\u00f3rsk"
    ],
    "name:ukr_x_preferred":[
        "\u0420\u043e\u0491\u043e\u0442\u0432\u0443\u0440\u0441\u044c\u043a"
    ],
    "wof:name":"Rogotworsk",
    "wof:placetype":"locality"
},
  "geometry": {"coordinates":[20.04924,52.69105],"type":"Point"}
}