{
  "type": "Feature",
  "properties": {
    "gn:admin1_code":"82.0",
    "gn:admin2_code":"2202.0",
    "gn:admin3_code":"220203.0",
    "gn:asciiname":"Melanowo",
    "gn:country_code":"PL",
    "gn:dem":150,
    "gn:feature_class":"P",
    "gn:feature_code":"PPL",
    "gn:name":"Melanowo",
    "gn:population":0,
    "gn:timezone":"Europe/Warsaw",
    "iso:country":"PL",
    "name:ceb_x_preferred":[
        "Melanowo"
    ],
    "name:pol_x_preferred":[
        "Melanowo"
    ],
    "wof:name":"Melanowo",
    "wof:placetype":"locality"
},
  "geometry": {"coordinates":[17.55,53.61666999999999],"type":"Point"}
}