{
  "type": "Feature",
  "properties": {
    "gn:admin1_code":"81.0",
    "gn:admin2_code":"2012.0",
    "gn:admin3_code":"201209.0",
    "gn:asciiname":"Leszkiemie",
    "gn:country_code":"PL",
    "gn:dem":263,
    "gn:feature_class":"P",
    "gn:feature_code":"PPL",
    "gn:name":"Leszkiemie",
    "gn:population":0,
    "gn:timezone":"Europe/Warsaw",
    "iso:country":"PL",
    "name:lit_x_preferred":[
        "Le\u0161kiemis"
    ],
    "name:pol_x_preferred":[
        "Leszkiemie"
    ],
    "name:ukr_x_preferred":[
        "\u041b\u0435\u0448\u043a\u0435\u043c\u0435"
    ],
    "wof:name":"Leszkiemie",
    "wof:placetype":"locality"
},
  "geometry": {"coordinates":[22.80659,54.3411],"type":"Point"}
}