{
  "type": "Feature",
  "properties": {
    "gn:admin1_code":"81.0",
    "gn:admin2_code":"2005.0",
    "gn:admin3_code":"200503.0",
    "gn:asciiname":"Kuzowa",
    "gn:country_code":"PL",
    "gn:dem":173,
    "gn:feature_class":"P",
    "gn:feature_code":"PPL",
    "gn:name":"Kuzowa",
    "gn:population":0,
    "gn:timezone":"Europe/Warsaw",
    "iso:country":"PL",
    "name:azb_x_preferred":[
        "\u06a9\u0648\u0632\u0627\u0648\u0627"
    ],
    "name:fas_x_preferred":[
        "\u06a9\u0648\u0632\u0627\u0648\u0627"
    ],
    "name:fra_x_preferred":[
        "Kuzawa"
    ],
    "name:lit_x_preferred":[
        "Kuzava"
    ],
    "name:pol_x_preferred":[
        "Kuzawa"
    ],
    "name:ukr_x_preferred":[
        "\u041a\u0443\u0437\u0430\u0432\u0430"
    ],
    "name:und_x_variant":[
        "Kuzowa"
    ],
    "wof:name":"Kuzowa",
    "wof:placetype":"locality"
},
  "geometry": {"coordinates":[23.36257,52.52984],"type":"Point"}
}