{
  "type": "Feature",
  "properties": {
    "gn:admin1_code":"81.0",
    "gn:admin2_code":"2005.0",
    "gn:admin3_code":"200503.0",
    "gn:asciiname":"Kuzowa",
    "gn:country_code":"PL",
    "gn:dem":173,
    "gn:feature_class":"P",
    "gn:feature_code":"PPL",
    "gn:name":"Kuzowa",
    "gn:population":0,
    "gn:timezone":"Europe/Warsaw",
    "iso:country":"PL",
    "name:und_x_variant":[
        "Kuzawa",
        "Kuzowa"
    ],
    "wof:name":"Kuzowa",
    "wof:placetype":"locality"
},
  "geometry": {"coordinates":[23.36257,52.52984],"type":"Point"}
}