{
  "type": "Feature",
  "properties": {
    "gn:admin1_code":"78.0",
    "gn:admin2_code":"1433.0",
    "gn:admin3_code":"143303.0",
    "gn:asciiname":"Pniewnik",
    "gn:country_code":"PL",
    "gn:dem":173,
    "gn:feature_class":"P",
    "gn:feature_code":"PPL",
    "gn:name":"Pniewnik",
    "gn:population":0,
    "gn:timezone":"Europe/Warsaw",
    "iso:country":"PL",
    "name:eng_x_preferred":[
        "Pniewnik"
    ],
    "name:fra_x_preferred":[
        "Pniewnik"
    ],
    "name:pol_x_preferred":[
        "Pniewnik"
    ],
    "name:rus_x_preferred":[
        "\u041f\u043d\u0435\u0432\u043d\u0438\u043a"
    ],
    "name:ukr_x_preferred":[
        "\u041f\u043d\u0435\u0432\u043d\u0438\u043a"
    ],
    "wof:name":"Pniewnik",
    "wof:placetype":"locality"
},
  "geometry": {"coordinates":[21.80451,52.3723],"type":"Point"}
}