{
  "type": "Feature",
  "properties": {
    "gn:admin1_code":"73.0",
    "gn:admin2_code":"461.0",
    "gn:admin3_code":"46101.0",
    "gn:asciiname":"Oplawiec",
    "gn:country_code":"PL",
    "gn:dem":52,
    "gn:feature_class":"P",
    "gn:feature_code":"PPL",
    "gn:name":"Op\u0142awiec",
    "gn:population":0,
    "gn:timezone":"Europe/Warsaw",
    "iso:country":"PL",
    "wof:name":"Oplawiec",
    "wof:placetype":"neighbourhood"
},
  "geometry": {"coordinates":[17.96248,53.19161],"type":"Point"}
}