{
  "type": "Feature",
  "properties": {
    "gn:admin1_code":"83.0",
    "gn:admin2_code":"2464.0",
    "gn:admin3_code":"246401.0",
    "gn:asciiname":"Wrzosowiak",
    "gn:country_code":"PL",
    "gn:dem":261,
    "gn:feature_class":"P",
    "gn:feature_code":"PPL",
    "gn:name":"Wrzosowiak",
    "gn:population":0,
    "gn:timezone":"Europe/Warsaw",
    "iso:country":"PL",
    "wof:name":"Wrzosowiak",
    "wof:placetype":"neighbourhood"
},
  "geometry": {"coordinates":[19.14316,50.77918],"type":"Point"}
}