{
  "type": "Feature",
  "properties": {
    "gn:admin1_code":"87.0",
    "gn:admin2_code":"3204.0",
    "gn:admin3_code":"320406.0",
    "gn:asciiname":"Babigoszcz",
    "gn:country_code":"PL",
    "gn:dem":16,
    "gn:feature_class":"P",
    "gn:feature_code":"PPL",
    "gn:name":"Babigoszcz",
    "gn:population":0,
    "gn:timezone":"Europe/Warsaw",
    "iso:country":"PL",
    "name:ceb_x_preferred":[
        "Babigoszcz"
    ],
    "name:pol_x_preferred":[
        "Babigoszcz"
    ],
    "name:ukr_x_preferred":[
        "\u0411\u0430\u0431\u0456\u0491\u043e\u0449"
    ],
    "name:vie_x_preferred":[
        "Babigoszcz"
    ],
    "wof:name":"Babigoszcz",
    "wof:placetype":"locality"
},
  "geometry": {"coordinates":[14.81289,53.68029],"type":"Point"}
}