{
  "type": "Feature",
  "properties": {
    "gn:admin1_code":"74.0",
    "gn:admin2_code":"1012.0",
    "gn:admin3_code":"101210.0",
    "gn:asciiname":"Huta Przerabska",
    "gn:country_code":"PL",
    "gn:dem":225,
    "gn:feature_class":"P",
    "gn:feature_code":"PPL",
    "gn:name":"Huta Przer\u0105bska",
    "gn:population":0,
    "gn:timezone":"Europe/Warsaw",
    "iso:country":"PL",
    "name:fra_x_preferred":[
        "Huta Przer\u0119bska"
    ],
    "name:pol_x_preferred":[
        "Huta Przer\u0119bska"
    ],
    "name:ukr_x_preferred":[
        "\u0413\u0443\u0442\u0430-\u041f\u0448\u0435\u0440\u0435\u043c\u0431\u0441\u044c\u043a\u0430"
    ],
    "name:und_x_variant":[
        "Przer\u0105bska Huta",
        "Huta Przer\u0119bska",
        "Huta Przer\u0105bska"
    ],
    "wof:name":"Huta Przerabska",
    "wof:placetype":"locality"
},
  "geometry": {"coordinates":[19.70663,51.12761],"type":"Point"}
}