{
  "type": "Feature",
  "properties": {
    "gn:admin1_code":"81.0",
    "gn:admin2_code":"2003.0",
    "gn:admin3_code":"200304.0",
    "gn:asciiname":"Szumki",
    "gn:country_code":"PL",
    "gn:dem":158,
    "gn:feature_class":"P",
    "gn:feature_code":"PPL",
    "gn:name":"Szumki",
    "gn:population":0,
    "gn:timezone":"Europe/Warsaw",
    "iso:country":"PL",
    "name:fra_x_preferred":[
        "Szumki"
    ],
    "name:lit_x_preferred":[
        "\u0160umkai"
    ],
    "name:pol_x_preferred":[
        "Szumki"
    ],
    "name:ukr_x_preferred":[
        "\u0428\u0443\u043c\u043a\u0456"
    ],
    "wof:name":"Szumki",
    "wof:placetype":"locality"
},
  "geometry": {"coordinates":[23.03762,52.70121],"type":"Point"}
}