{
  "type": "Feature",
  "properties": {
    "gn:gn_country":"PL",
    "gn:gn_fcode":"PPL",
    "gn:gn_pop":1192,
    "gn:population":1192,
    "iso:country":"PL",
    "name:ast_x_preferred":[
        "Bojszowy Nowe"
    ],
    "name:ceb_x_preferred":[
        "Bojszowy Nowe"
    ],
    "name:eng_x_preferred":[
        "Bojszowy Nowe"
    ],
    "name:fra_x_preferred":[
        "Nowe Bojszowy"
    ],
    "name:pol_x_preferred":[
        "Bojszowy Nowe"
    ],
    "name:ukr_x_preferred":[
        "\u0411\u043e\u0439\u0448\u043e\u0432\u0438-\u041d\u043e\u0432\u0456"
    ],
    "name:unk_x_variant":[
        "Nowe Bojszowy"
    ],
    "qs_pg:aaroncc":"PL",
    "qs_pg:gn_country":"PL",
    "qs_pg:gn_fcode":"PPL",
    "qs_pg:gn_pop":1192,
    "qs_pg:name":"Bojszowy Nowe",
    "qs_pg:photos_9r":0,
    "qs_pg:photos_sr":0,
    "qs_pg:pop_sr":3,
    "qs_pg:qs_pg_placetype":"locality",
    "wof:name":"Bojszowy Nowe",
    "wof:placetype":"locality",
    "wof:population":1192
},
  "geometry": {"coordinates":[19.05012,50.05284],"type":"Point"}
}