{
  "type": "Feature",
  "properties": {
    "gn:admin1_code":"74.0",
    "gn:admin2_code":"1001.0",
    "gn:admin3_code":"100107.0",
    "gn:asciiname":"Chabielice",
    "gn:country_code":"PL",
    "gn:dem":174,
    "gn:feature_class":"P",
    "gn:feature_code":"PPL",
    "gn:name":"Chabielice",
    "gn:population":0,
    "gn:timezone":"Europe/Warsaw",
    "iso:country":"PL",
    "wof:name":"Chabielice",
    "wof:placetype":"locality"
},
  "geometry": {"coordinates":[19.11688,51.26481],"type":"Point"}
}