{
  "type": "Feature",
  "properties": {
    "gn:admin1_code":"74.0",
    "gn:admin2_code":"1001.0",
    "gn:admin3_code":"100107.0",
    "gn:asciiname":"Chabielice",
    "gn:country_code":"PL",
    "gn:dem":174,
    "gn:feature_class":"P",
    "gn:feature_code":"PPL",
    "gn:name":"Chabielice",
    "gn:population":0,
    "gn:timezone":"Europe/Warsaw",
    "iso:country":"PL",
    "name:azb_x_preferred":[
        "\u062e\u0627\u0628\u06cc\u0644\u06cc\u062a\u0633\u0647"
    ],
    "name:ceb_x_preferred":[
        "Chabielice"
    ],
    "name:fas_x_preferred":[
        "\u062e\u0627\u0628\u06cc\u0644\u06cc\u062a\u0633\u0647"
    ],
    "name:fra_x_preferred":[
        "Chabielice"
    ],
    "name:nld_x_preferred":[
        "Chabielice"
    ],
    "name:pol_x_preferred":[
        "Chabielice"
    ],
    "name:ukr_x_preferred":[
        "\u0425\u0430\u0431\u0435\u043b\u0456\u0446\u0435"
    ],
    "wof:name":"Chabielice",
    "wof:placetype":"locality"
},
  "geometry": {"coordinates":[19.11688,51.26481],"type":"Point"}
}