{
  "type": "Feature",
  "properties": {
    "gn:population":1500,
    "iso:country":"PL",
    "name:ast_x_preferred":[
        "Kik\u00f3\u0142"
    ],
    "name:azb_x_preferred":[
        "\u06a9\u06cc\u06a9\u0648\u0648"
    ],
    "name:ceb_x_preferred":[
        "Kik\u00f3\u0142"
    ],
    "name:deu_x_preferred":[
        "Kik\u00f3\u0142"
    ],
    "name:eng_x_preferred":[
        "Kik\u00f3\u0142"
    ],
    "name:fas_x_preferred":[
        "\u06a9\u06cc\u06a9\u0648\u0648"
    ],
    "name:fra_x_preferred":[
        "Kik\u00f3\u0142"
    ],
    "name:heb_x_preferred":[
        "\u05e7\u05d9\u05e7\u05d5\u05dc"
    ],
    "name:nan_x_preferred":[
        "Kik\u00f3\u0142"
    ],
    "name:nld_x_preferred":[
        "Kik\u00f3\u0142"
    ],
    "name:pol_x_preferred":[
        "Kik\u00f3\u0142"
    ],
    "name:rus_x_preferred":[
        "\u041a\u0438\u043a\u0443\u043b"
    ],
    "name:ukr_x_preferred":[
        "\u041a\u0456\u043a\u0443\u043b"
    ],
    "name:zho_min_nan_x_preferred":[
        "Kik\u00f3\u0142"
    ],
    "qs:a0":"Rzeczpospolita Polska",
    "qs:a1":"*Kujawsko-pomorskie",
    "qs:a1r":"0",
    "qs:a2":"Lipnowski",
    "qs:adm0":"Rzeczpospolita Polska",
    "qs:la":"Kik\u00f3\u0142",
    "qs:la_lc":"*PL0408052",
    "qs:level":"locality",
    "qs:loc":"Kik\u00f3\u0142",
    "qs:loc_alt":"Kikol",
    "qs:pop":0,
    "qs:type":"rural point-in-poly",
    "wd:wordcount":89,
    "wof:coterminous":[
        1125301105
    ],
    "wof:name":"Kik\u00f3\u0142",
    "wof:placetype":"locality",
    "wof:population":1500
},
  "geometry": {"coordinates":[19.1038797282698,52.928625971786],"type":"Point"}
}