{
  "type": "Feature",
  "properties": {
    "iso:country":"PL",
    "name:pol_x_preferred":[
        "Groch\u00f3w-Centrum"
    ],
    "wof:name":"Grochow-Centrum",
    "wof:placetype":"neighbourhood"
},
  "geometry": {"coordinates":[21.08389927385451,52.25110903675933],"type":"Point"}
}