{
  "type": "Feature",
  "properties": {
    "gn:admin1_code":"84.0",
    "gn:admin2_code":"2604.0",
    "gn:admin3_code":"260404.0",
    "gn:asciiname":"Sladkow Duzy",
    "gn:country_code":"PL",
    "gn:dem":250,
    "gn:feature_class":"P",
    "gn:feature_code":"PPL",
    "gn:name":"\u015aladk\u00f3w Du\u017cy",
    "gn:population":0,
    "gn:timezone":"Europe/Warsaw",
    "iso:country":"PL",
    "name:ceb_x_preferred":[
        "\u015aladk\u00f3w Du\u017cy"
    ],
    "name:pol_x_preferred":[
        "\u015aladk\u00f3w Du\u017cy"
    ],
    "name:ukr_x_preferred":[
        "\u0421\u043b\u044f\u0434\u043a\u0443\u0432-\u0414\u0443\u0436\u0438"
    ],
    "wof:name":"Sladkow Duzy",
    "wof:placetype":"locality"
},
  "geometry": {"coordinates":[20.70657000000001,50.57819],"type":"Point"}
}