{
  "type": "Feature",
  "properties": {
    "gn:admin1_code":"84.0",
    "gn:admin2_code":"2604.0",
    "gn:admin3_code":"260404.0",
    "gn:asciiname":"Sladkow Duzy",
    "gn:country_code":"PL",
    "gn:dem":250,
    "gn:feature_class":"P",
    "gn:feature_code":"PPL",
    "gn:name":"\u015aladk\u00f3w Du\u017cy",
    "gn:population":0,
    "gn:timezone":"Europe/Warsaw",
    "iso:country":"PL",
    "name:und_x_variant":[
        "\u015aladk\u00f3w Du\u017cy"
    ],
    "wof:name":"Sladkow Duzy",
    "wof:placetype":"locality"
},
  "geometry": {"coordinates":[20.70657000000001,50.57819],"type":"Point"}
}