{
  "type": "Feature",
  "properties": {
    "gn:admin1_code":"75.0",
    "gn:admin2_code":"616.0",
    "gn:admin3_code":"61604.0",
    "gn:asciiname":"Ogonow",
    "gn:country_code":"PL",
    "gn:dem":156,
    "gn:feature_class":"P",
    "gn:feature_code":"PPL",
    "gn:name":"Ogon\u00f3w",
    "gn:population":0,
    "gn:timezone":"Europe/Warsaw",
    "iso:country":"PL",
    "name:und_x_variant":[
        "Ogon\u00f3w"
    ],
    "wof:name":"Ogonow",
    "wof:placetype":"locality"
},
  "geometry": {"coordinates":[21.98475,51.63039000000001],"type":"Point"}
}