{
  "type": "Feature",
  "properties": {
    "gn:population":1163,
    "iso:country":"PL",
    "name:ast_x_preferred":[
        "Miasteczko Kraje\u0144skie"
    ],
    "name:azb_x_preferred":[
        "\u0645\u06cc\u0627\u0633\u062a\u0686\u06a9\u0648 \u06a9\u0631\u0627\u06cc\u0646\u0642\u0633\u06a9\u06cc\u0647"
    ],
    "name:deu_x_preferred":[
        "Miasteczko Kraje\u0144skie"
    ],
    "name:eng_x_preferred":[
        "Miasteczko Kraje\u0144skie"
    ],
    "name:fas_x_preferred":[
        "\u0645\u06cc\u0627\u0633\u062a\u0686\u06a9\u0648 \u06a9\u0631\u0627\u06cc\u0646\u06af\u0633\u06a9\u06cc\u0647"
    ],
    "name:fra_x_preferred":[
        "Miasteczko Kraje\u0144skie"
    ],
    "name:nld_x_preferred":[
        "Miasteczko Kraje\u0144skie"
    ],
    "name:pol_x_preferred":[
        "Miasteczko Kraje\u0144skie"
    ],
    "name:pol_x_variant":[
        "Miasteczko Krai\u0144skie"
    ],
    "name:ukr_x_preferred":[
        "\u041c\u044f\u0441\u0442\u0435\u0447\u043a\u043e-\u041a\u0440\u0430\u0454\u043d\u0441\u044c\u043a\u0435"
    ],
    "name:und_x_variant":[
        "Miasteczko"
    ],
    "qs:a0":"Rzeczpospolita Polska",
    "qs:a1":"*Wielkopolskie",
    "qs:a1r":"0",
    "qs:a2":"Pilski",
    "qs:adm0":"Rzeczpospolita Polska",
    "qs:la":"Miasteczko Kraje\u0144skie",
    "qs:la_lc":"*PL3019052",
    "qs:level":"locality",
    "qs:loc":"Miasteczko Kraje\u0144skie",
    "qs:loc_alt":"Miasteczko Krajenskie",
    "qs:pop":0,
    "qs:type":"rural point-in-poly",
    "wd:wordcount":97,
    "wof:name":"Miasteczko Kraje\u0144skie",
    "wof:placetype":"locality",
    "wof:population":1163
},
  "geometry": {"coordinates":[17.0131986517128,53.1110820630261],"type":"Point"}
}