{
  "type": "Feature",
  "properties": {
    "gn:admin1_code":"78.0",
    "gn:admin2_code":"1424.0",
    "gn:admin3_code":"142401.0",
    "gn:asciiname":"Kesy",
    "gn:country_code":"PL",
    "gn:dem":110,
    "gn:feature_class":"P",
    "gn:feature_code":"PPL",
    "gn:name":"K\u0119sy",
    "gn:population":0,
    "gn:timezone":"Europe/Warsaw",
    "iso:country":"PL",
    "wof:name":"Kesy",
    "wof:placetype":"locality"
},
  "geometry": {"coordinates":[20.91667,52.71666999999999],"type":"Point"}
}