{
  "type": "Feature",
  "properties": {
    "gn:population":2560,
    "iso:country":"PL",
    "name:ast_x_preferred":[
        "Przytkowice"
    ],
    "name:ceb_x_preferred":[
        "Przytkowice"
    ],
    "name:deu_x_preferred":[
        "Przytkowice"
    ],
    "name:eng_x_preferred":[
        "Przytkowice"
    ],
    "name:fra_x_preferred":[
        "Przytkowice"
    ],
    "name:nld_x_preferred":[
        "Przytkowice"
    ],
    "name:pol_x_preferred":[
        "Przytkowice"
    ],
    "name:ukr_x_preferred":[
        "\u041f\u0448\u0438\u0442\u043a\u043e\u0432\u0456\u0446\u0435"
    ],
    "qs:a0":"Rzeczpospolita Polska",
    "qs:a1":"*Malopolskie",
    "qs:a1r":"0",
    "qs:a2":"Wadowicki",
    "qs:adm0":"Rzeczpospolita Polska",
    "qs:la_lc":"*",
    "qs:level":"locality",
    "qs:loc":"Przytkowice",
    "qs:loc_alt":"Przytkowice",
    "qs:pop":0,
    "qs:type":"buffered point",
    "wd:wordcount":86,
    "wof:name":"Przytkowice",
    "wof:placetype":"locality",
    "wof:population":2560
},
  "geometry": {"coordinates":[19.685278,49.919556],"type":"Point"}
}