{
  "type": "Feature",
  "properties": {
    "gn:admin1_code":"85.0",
    "gn:admin2_code":"2802.0",
    "gn:admin3_code":"280202.0",
    "gn:asciiname":"Zawierz",
    "gn:cc2":"PL",
    "gn:country_code":"PL",
    "gn:dem":27,
    "gn:feature_class":"P",
    "gn:feature_code":"PPL",
    "gn:name":"Zawierz",
    "gn:population":0,
    "gn:timezone":"Europe/Warsaw",
    "iso:country":"PL",
    "name:und_x_variant":[
        "Zagern",
        "Zawierz"
    ],
    "wof:name":"Zawierz",
    "wof:placetype":"locality"
},
  "geometry": {"coordinates":[19.8238,54.34485],"type":"Point"}
}