{
  "type": "Feature",
  "properties": {
    "gn:admin1_code":"84.0",
    "gn:admin2_code":"2608.0",
    "gn:admin3_code":"260805.0",
    "gn:asciiname":"Zurawniki",
    "gn:country_code":"PL",
    "gn:dem":186,
    "gn:feature_class":"P",
    "gn:feature_code":"PPL",
    "gn:name":"\u017burawniki",
    "gn:population":0,
    "gn:timezone":"Europe/Warsaw",
    "iso:country":"PL",
    "name:ceb_x_preferred":[
        "\u017burawniki"
    ],
    "name:pol_x_preferred":[
        "\u017burawniki"
    ],
    "name:ukr_x_preferred":[
        "\u0416\u0443\u0440\u0430\u0432\u043d\u0438\u043a\u0438"
    ],
    "wof:name":"Zurawniki",
    "wof:placetype":"locality"
},
  "geometry": {"coordinates":[20.62855,50.37974000000001],"type":"Point"}
}