{
  "type": "Feature",
  "properties": {
    "gn:admin1_code":"87.0",
    "gn:admin2_code":"3211.0",
    "gn:admin3_code":"321104.0",
    "gn:asciiname":"Nowa Jasienica",
    "gn:country_code":"PL",
    "gn:dem":17,
    "gn:feature_class":"P",
    "gn:feature_code":"PPL",
    "gn:name":"Nowa Jasienica",
    "gn:population":0,
    "gn:timezone":"Europe/Warsaw",
    "iso:country":"PL",
    "wof:name":"Nowa Jasienica",
    "wof:placetype":"locality"
},
  "geometry": {"coordinates":[14.4474,53.60775],"type":"Point"}
}