{
  "type": "Feature",
  "properties": {
    "gn:country":"PL",
    "gn:fcode":"PPL",
    "gn:population":393,
    "iso:country":"PL",
    "name:ast_x_preferred":[
        "Zimna Brze\u017anica"
    ],
    "name:ceb_x_preferred":[
        "Zimna Brze\u017anica"
    ],
    "name:deu_x_historical":[
        "Kalten Briesnitz"
    ],
    "name:deu_x_preferred":[
        "Kalten Briesnitz"
    ],
    "name:eng_x_preferred":[
        "Zimna Brze\u017anica"
    ],
    "name:fra_x_preferred":[
        "Zimna Brze\u017anica"
    ],
    "name:nld_x_preferred":[
        "Zimna Brze\u017anica"
    ],
    "name:pol_x_preferred":[
        "Zimna Brze\u017anica"
    ],
    "name:ukr_x_preferred":[
        "\u0417\u0456\u043c\u043d\u0430-\u0411\u0436\u0435\u0437\u044c\u043d\u0438\u0446\u044f"
    ],
    "qs_pg:aaroncc":"PL",
    "qs_pg:gn_country":"PL",
    "qs_pg:gn_fcode":"PPL",
    "qs_pg:gn_pop":393,
    "qs_pg:name":"Zimna Brze\u017anica",
    "qs_pg:name_adm0":"Polska",
    "qs_pg:name_adm1":"Lubuskie",
    "qs_pg:photos_9k":1,
    "qs_pg:photos_9r":1,
    "qs_pg:photos_all":1,
    "qs_pg:photos_sr":0,
    "qs_pg:pop_sr":2,
    "qs_pg:qs_pg_placetype":"locality",
    "qs_pg:qs_pg_placetype_gp":"Town",
    "qs_pg:woe_adm0":23424923,
    "woe:adm0_id":23424923,
    "woe:name_adm0":"Polska",
    "woe:name_adm1":"Lubuskie",
    "woe:placetype":"Town",
    "wof:name":"Zimna Brze\u017anica",
    "wof:placetype":"locality",
    "wof:population":393
},
  "geometry": {"coordinates":[15.82177,51.65323],"type":"Point"}
}