{
  "type": "Feature",
  "properties": {
    "gn:admin1_code":"86.0",
    "gn:admin2_code":"3006.0",
    "gn:admin3_code":"300601.0",
    "gn:asciiname":"Cerekwica",
    "gn:country_code":"PL",
    "gn:dem":123,
    "gn:feature_class":"P",
    "gn:feature_code":"PPL",
    "gn:name":"Cerekwica",
    "gn:population":0,
    "gn:timezone":"Europe/Warsaw",
    "iso:country":"PL",
    "wof:name":"Cerekwica",
    "wof:placetype":"locality"
},
  "geometry": {"coordinates":[17.36274,51.92702],"type":"Point"}
}