{
  "type": "Feature",
  "properties": {
    "gn:admin1_code":"87.0",
    "gn:admin2_code":"3215.0",
    "gn:admin3_code":"321506.0",
    "gn:asciiname":"Brzezno",
    "gn:country_code":"PL",
    "gn:dem":144,
    "gn:feature_class":"P",
    "gn:feature_code":"PPL",
    "gn:name":"Brze\u017ano",
    "gn:population":0,
    "gn:timezone":"Europe/Warsaw",
    "iso:country":"PL",
    "name:und_x_variant":[
        "Briesen",
        "Brze\u017ano"
    ],
    "wof:name":"Brzezno",
    "wof:placetype":"locality"
},
  "geometry": {"coordinates":[16.60741,53.81263000000001],"type":"Point"}
}