{
  "type": "Feature",
  "properties": {
    "iso:country":"PL",
    "name:azb_x_preferred":[
        "\u0642\u0645\u06cc\u0646\u0627 \u0648\u0648\u0645\u06cc\u0627\u0646\u06a9\u06cc"
    ],
    "name:bel_x_preferred":[
        "\u041b\u0430\u043c\u044f\u043d\u043a\u0456"
    ],
    "name:ceb_x_preferred":[
        "\u0141omianki"
    ],
    "name:eus_x_preferred":[
        "\u0141omianki udalerria"
    ],
    "name:fas_x_preferred":[
        "\u06af\u0645\u06cc\u0646\u0627 \u0648\u0648\u0645\u06cc\u0627\u0646\u06a9\u06cc"
    ],
    "name:fra_x_preferred":[
        "\u0141omianki"
    ],
    "name:ita_x_preferred":[
        "\u0141omianki"
    ],
    "name:nld_x_preferred":[
        "\u0141omianki"
    ],
    "name:pol_x_preferred":[
        "\u0141omianki"
    ],
    "name:rus_x_preferred":[
        "\u041b\u043e\u043c\u044f\u043d\u043a\u0438"
    ],
    "name:slk_x_preferred":[
        "Gmina \u0141omianki"
    ],
    "name:ukr_x_preferred":[
        "\u0413\u043c\u0456\u043d\u0430 \u041b\u043e\u043c\u044f\u043d\u043a\u0456"
    ],
    "name:war_x_preferred":[
        "Gmina \u0141omianki"
    ],
    "qs_pg:aaroncc":"PL",
    "qs_pg:name":"Gmina \u0141omianki",
    "qs_pg:name_adm0":"Polska",
    "qs_pg:name_adm1":"Mazowieckie",
    "qs_pg:photos":50,
    "qs_pg:photos_1k":10,
    "qs_pg:photos_9k":1,
    "qs_pg:photos_9r":2,
    "qs_pg:photos_all":50,
    "qs_pg:photos_sr":2,
    "qs_pg:pop_sr":0,
    "qs_pg:qs_pg_placetype":"localadmin",
    "qs_pg:qs_pg_placetype_gp":"LocalAdmin",
    "qs_pg:woe_adm0":23424923,
    "woe:adm0_id":23424923,
    "woe:name_adm0":"Polska",
    "woe:name_adm1":"Mazowieckie",
    "woe:placetype":"LocalAdmin",
    "wof:name":"Gmina \u0141omianki",
    "wof:placetype":"localadmin"
},
  "geometry": {"coordinates":[20.879775,52.349457],"type":"Point"}
}