{
  "type": "Feature",
  "properties": {
    "gn:admin1_code":"79.0",
    "gn:admin2_code":"1610.0",
    "gn:admin3_code":"161001.0",
    "gn:asciiname":"Prezyna",
    "gn:country_code":"PL",
    "gn:dem":231,
    "gn:feature_class":"P",
    "gn:feature_code":"PPL",
    "gn:name":"Pre\u017cyna",
    "gn:population":0,
    "gn:timezone":"Europe/Warsaw",
    "iso:country":"PL",
    "name:azb_x_preferred":[
        "\u067e\u0631\u0646\u0698\u0646\u0627"
    ],
    "name:deu_x_preferred":[
        "Gro\u00df Pramsen"
    ],
    "name:fas_x_preferred":[
        "\u067e\u0631\u0646\u0698\u0646\u0627"
    ],
    "name:pol_x_preferred":[
        "Pr\u0119\u017cyna"
    ],
    "name:ukr_x_preferred":[
        "\u041f\u0440\u0435\u043d\u0436\u0438\u043d\u0430"
    ],
    "wof:name":"Prezyna",
    "wof:placetype":"locality"
},
  "geometry": {"coordinates":[17.63941,50.37886],"type":"Point"}
}