{
  "type": "Feature",
  "properties": {
    "gn:admin1_code":"87.0",
    "gn:admin2_code":"3201.0",
    "gn:admin3_code":"320103.0",
    "gn:asciiname":"Malonowo",
    "gn:country_code":"PL",
    "gn:dem":35,
    "gn:feature_class":"P",
    "gn:feature_code":"PPL",
    "gn:name":"Malonowo",
    "gn:population":0,
    "gn:timezone":"Europe/Warsaw",
    "iso:country":"PL",
    "name:deu_x_preferred":[
        "Malonowo"
    ],
    "name:pol_x_preferred":[
        "Malonowo"
    ],
    "name:ukr_x_preferred":[
        "\u041c\u0430\u043b\u044c\u043e\u043d\u043e\u0432\u043e"
    ],
    "name:und_x_variant":[
        "Mallnow",
        "Malonowo"
    ],
    "name:vie_x_preferred":[
        "Malonowo"
    ],
    "wof:name":"Malonowo",
    "wof:placetype":"locality"
},
  "geometry": {"coordinates":[15.79279,54.00782],"type":"Point"}
}