{
  "type": "Feature",
  "properties": {
    "gn:admin1_code":"77.0",
    "gn:admin2_code":"1205.0",
    "gn:admin3_code":"120507.0",
    "gn:asciiname":"Staszkowka",
    "gn:country_code":"PL",
    "gn:dem":394,
    "gn:feature_class":"P",
    "gn:feature_code":"PPL",
    "gn:name":"Staszk\u00f3wka",
    "gn:population":0,
    "gn:timezone":"Europe/Warsaw",
    "iso:country":"PL",
    "name:und_x_variant":[
        "Staszk\u00f3wka"
    ],
    "wof:name":"Staszkowka",
    "wof:placetype":"locality"
},
  "geometry": {"coordinates":[21.02099,49.75621],"type":"Point"}
}