{
  "type": "Feature",
  "properties": {
    "gn:admin1_code":"83.0",
    "gn:admin2_code":"2404.0",
    "gn:admin3_code":"240406.0",
    "gn:asciiname":"Zaleze",
    "gn:country_code":"PL",
    "gn:dem":221,
    "gn:feature_class":"P",
    "gn:feature_code":"PPL",
    "gn:name":"Zal\u0119\u017ce",
    "gn:population":0,
    "gn:timezone":"Europe/Warsaw",
    "iso:country":"PL",
    "name:pol_x_preferred":[
        "Za\u0142\u0119\u017ce"
    ],
    "name:ukr_x_preferred":[
        "\u0417\u0430\u043b\u0435\u043d\u0436\u0435"
    ],
    "name:und_x_variant":[
        "Zal\u0119\u017ce"
    ],
    "wof:name":"Zaleze",
    "wof:placetype":"locality"
},
  "geometry": {"coordinates":[19.74257,50.81966],"type":"Point"}
}