{
  "type": "Feature",
  "properties": {
    "gn:admin1_code":"73.0",
    "gn:admin2_code":"403.0",
    "gn:admin3_code":"40304.0",
    "gn:asciiname":"Morzewiec",
    "gn:country_code":"PL",
    "gn:dem":93,
    "gn:feature_class":"P",
    "gn:feature_code":"PPL",
    "gn:name":"Morzewiec",
    "gn:population":0,
    "gn:timezone":"Europe/Warsaw",
    "iso:country":"PL",
    "name:ceb_x_preferred":[
        "Morzewiec"
    ],
    "name:ita_x_preferred":[
        "Morzewiec"
    ],
    "name:pol_x_preferred":[
        "Morzewiec"
    ],
    "name:ukr_x_preferred":[
        "\u041c\u043e\u0436\u0435\u0432\u0435\u0446\u044c"
    ],
    "wof:name":"Morzewiec",
    "wof:placetype":"locality"
},
  "geometry": {"coordinates":[17.90296,53.22001],"type":"Point"}
}