{
  "type": "Feature",
  "properties": {
    "gn:admin1_code":"73.0",
    "gn:admin2_code":"403.0",
    "gn:admin3_code":"40304.0",
    "gn:asciiname":"Morzewiec",
    "gn:country_code":"PL",
    "gn:dem":93,
    "gn:feature_class":"P",
    "gn:feature_code":"PPL",
    "gn:name":"Morzewiec",
    "gn:population":0,
    "gn:timezone":"Europe/Warsaw",
    "iso:country":"PL",
    "wof:name":"Morzewiec",
    "wof:placetype":"locality"
},
  "geometry": {"coordinates":[17.90296,53.22001],"type":"Point"}
}