{
  "type": "Feature",
  "properties": {
    "gn:admin1_code":"82.0",
    "gn:admin2_code":"2202.0",
    "gn:admin3_code":"220204.0",
    "gn:asciiname":"Nadolna Karczma",
    "gn:country_code":"PL",
    "gn:dem":101,
    "gn:feature_class":"P",
    "gn:feature_code":"PPL",
    "gn:name":"Nadolna Karczma",
    "gn:population":0,
    "gn:timezone":"Europe/Warsaw",
    "iso:country":"PL",
    "name:pol_x_preferred":[
        "Nadolna Karczma"
    ],
    "name:ukr_x_preferred":[
        "\u041d\u0430\u0434\u043e\u043b\u044c\u043d\u0430-\u041a\u0430\u0440\u0447\u043c\u0430"
    ],
    "wof:name":"Nadolna Karczma",
    "wof:placetype":"locality"
},
  "geometry": {"coordinates":[17.83527,53.69254],"type":"Point"}
}