{
  "type": "Feature",
  "properties": {
    "gn:country":"PL",
    "gn:fcode":"PPLA3",
    "gn:population":3000,
    "iso:country":"PL",
    "name:ceb_x_preferred":[
        "\u015awilcza"
    ],
    "name:nld_x_preferred":[
        "\u015awilcza"
    ],
    "name:pol_x_preferred":[
        "\u015awilcza"
    ],
    "name:ukr_x_preferred":[
        "\u0421\u044c\u0432\u0456\u043b\u044c\u0447\u0430"
    ],
    "qs_pg:aaroncc":"PL",
    "qs_pg:gn_country":"PL",
    "qs_pg:gn_fcode":"PPLA3",
    "qs_pg:gn_pop":3000,
    "qs_pg:name":"\u015awilcza",
    "qs_pg:name_adm0":"Polska",
    "qs_pg:name_adm1":"Podkarpackie",
    "qs_pg:photos":3,
    "qs_pg:photos_1k":1,
    "qs_pg:photos_9k":1,
    "qs_pg:photos_9r":1,
    "qs_pg:photos_all":3,
    "qs_pg:photos_sr":1,
    "qs_pg:pop_sr":4,
    "qs_pg:qs_pg_placetype":"localadmin",
    "qs_pg:qs_pg_placetype_gp":"LocalAdmin",
    "qs_pg:woe_adm0":23424923,
    "woe:adm0_id":23424923,
    "woe:name_adm0":"Polska",
    "woe:name_adm1":"Podkarpackie",
    "woe:placetype":"LocalAdmin",
    "wof:name":"\u015awilcza",
    "wof:placetype":"localadmin",
    "wof:population":3000
},
  "geometry": {"coordinates":[21.89798,50.07179],"type":"Point"}
}