{
  "type": "Feature",
  "properties": {
    "gn:admin1_code":"74.0",
    "gn:admin2_code":"1015.0",
    "gn:admin3_code":"101508.0",
    "gn:asciiname":"Strobow",
    "gn:country_code":"PL",
    "gn:dem":132,
    "gn:feature_class":"P",
    "gn:feature_code":"PPL",
    "gn:name":"Strob\u00f3w",
    "gn:population":0,
    "gn:timezone":"Europe/Warsaw",
    "iso:country":"PL",
    "name:pol_x_preferred":[
        "Strob\u00f3w"
    ],
    "name:ukr_x_preferred":[
        "\u0421\u0442\u0440\u043e\u0431\u0443\u0432"
    ],
    "wof:name":"Strobow",
    "wof:placetype":"locality"
},
  "geometry": {"coordinates":[20.16579,51.91174],"type":"Point"}
}