{
  "type": "Feature",
  "properties": {
    "gn:admin1_code":"75.0",
    "gn:admin2_code":"609.0",
    "gn:admin3_code":"60908.0",
    "gn:asciiname":"Stasin",
    "gn:country_code":"PL",
    "gn:dem":216,
    "gn:feature_class":"P",
    "gn:feature_code":"PPL",
    "gn:name":"Stasin",
    "gn:population":0,
    "gn:timezone":"Europe/Warsaw",
    "iso:country":"PL",
    "name:fra_x_preferred":[
        "Stasin"
    ],
    "name:pol_x_preferred":[
        "Stasin"
    ],
    "name:ukr_x_preferred":[
        "\u0421\u0442\u0430\u0441\u0456\u043d"
    ],
    "name:und_x_variant":[
        "Kolonia Stasin",
        "Stasin"
    ],
    "wof:name":"Stasin",
    "wof:placetype":"locality"
},
  "geometry": {"coordinates":[22.47048,51.21154],"type":"Point"}
}