{
  "type": "Feature",
  "properties": {
    "gn:admin1_code":"72.0",
    "gn:admin2_code":"225.0",
    "gn:admin3_code":"22503.0",
    "gn:asciiname":"Wiganice Zytawskie",
    "gn:country_code":"PL",
    "gn:dem":247,
    "gn:feature_class":"P",
    "gn:feature_code":"PPL",
    "gn:name":"Wiganice \u017bytawskie",
    "gn:population":0,
    "gn:timezone":"Europe/Warsaw",
    "iso:country":"PL",
    "name:deu_x_historical":[
        "Weigsdorf"
    ],
    "name:deu_x_preferred":[
        "Weigsdorf"
    ],
    "wof:name":"Wiganice Zytawskie",
    "wof:placetype":"locality"
},
  "geometry": {"coordinates":[15.00544,50.96113],"type":"Point"}
}