{
  "type": "Feature",
  "properties": {
    "gn:gn_country":"PL",
    "gn:gn_fcode":"PPL",
    "gn:gn_pop":52,
    "gn:population":52,
    "iso:country":"PL",
    "name:eng_x_preferred":[
        "Olszyna"
    ],
    "name:fre_x_preferred":[
        "Olszyna"
    ],
    "name:pol_x_preferred":[
        "Olszyna"
    ],
    "name:unk_x_variant":[
        "Erlenholz"
    ],
    "qs_pg:aaroncc":"PL",
    "qs_pg:gn_country":"PL",
    "qs_pg:gn_fcode":"PPL",
    "qs_pg:gn_pop":52,
    "qs_pg:name":"Olszyna",
    "qs_pg:name_adm0":"Polska",
    "qs_pg:name_adm1":"Lubuskie",
    "qs_pg:photos_9k":1,
    "qs_pg:photos_9r":1,
    "qs_pg:photos_all":1,
    "qs_pg:photos_sr":0,
    "qs_pg:pop_sr":1,
    "qs_pg:qs_pg_placetype":"locality",
    "qs_pg:qs_pg_placetype_gp":"Town",
    "qs_pg:woe_adm0":23424923,
    "woe:adm0_id":23424923,
    "woe:name_adm0":"Polska",
    "woe:name_adm1":"Lubuskie",
    "woe:placetype":"Town",
    "wof:name":"Olszyna",
    "wof:placetype":"locality",
    "wof:population":52
},
  "geometry": {"coordinates":[14.76631,51.65541],"type":"Point"}
}