{
  "type": "Feature",
  "properties": {
    "gn:admin1_code":"81.0",
    "gn:admin2_code":"2001.0",
    "gn:admin3_code":"200104.0",
    "gn:asciiname":"Lipszczany",
    "gn:country_code":"PL",
    "gn:dem":150,
    "gn:feature_class":"P",
    "gn:feature_code":"PPL",
    "gn:name":"Lipszczany",
    "gn:population":0,
    "gn:timezone":"Europe/Warsaw",
    "iso:country":"PL",
    "name:azb_x_preferred":[
        "\u0644\u06cc\u067e\u0634\u0686\u0627\u0646\u0647"
    ],
    "name:fas_x_preferred":[
        "\u0644\u06cc\u067e\u0634\u0686\u0627\u0646\u0647"
    ],
    "name:lit_x_preferred":[
        "Lip\u0161\u010danai"
    ],
    "name:pol_x_preferred":[
        "Lipszczany"
    ],
    "name:ukr_x_preferred":[
        "\u041b\u0456\u043f\u0449\u0430\u043d\u0438"
    ],
    "wof:name":"Lipszczany",
    "wof:placetype":"locality"
},
  "geometry": {"coordinates":[23.57394,53.72386],"type":"Point"}
}