{
  "type": "Feature",
  "properties": {
    "gn:admin1_code":"86.0",
    "gn:admin2_code":"3002.0",
    "gn:admin3_code":"300205.0",
    "gn:asciiname":"Stajkowo",
    "gn:country_code":"PL",
    "gn:dem":72,
    "gn:feature_class":"P",
    "gn:feature_code":"PPL",
    "gn:name":"Stajkowo",
    "gn:population":0,
    "gn:timezone":"Europe/Warsaw",
    "iso:country":"PL",
    "wof:name":"Stajkowo",
    "wof:placetype":"locality"
},
  "geometry": {"coordinates":[16.4941,52.83608],"type":"Point"}
}