{
  "type": "Feature",
  "properties": {
    "gn:admin1_code":"75.0",
    "gn:admin2_code":"610.0",
    "gn:admin3_code":"61001.0",
    "gn:asciiname":"Podglebokie",
    "gn:country_code":"PL",
    "gn:dem":167,
    "gn:feature_class":"P",
    "gn:feature_code":"PPL",
    "gn:name":"Podg\u0142\u0119bokie",
    "gn:population":0,
    "gn:timezone":"Europe/Warsaw",
    "iso:country":"PL",
    "name:fra_x_preferred":[
        "Podg\u0142\u0119bokie"
    ],
    "name:pol_x_preferred":[
        "Podg\u0142\u0119bokie"
    ],
    "name:und_x_variant":[
        "Kolonia Podg\u0142\u0119bokie"
    ],
    "wof:name":"Podglebokie",
    "wof:placetype":"locality"
},
  "geometry": {"coordinates":[23.09276,51.30808],"type":"Point"}
}