{
  "type": "Feature",
  "properties": {
    "gn:admin1_code":"74.0",
    "gn:admin2_code":"1014.0",
    "gn:admin3_code":"101411.0",
    "gn:asciiname":"Gronowek",
    "gn:country_code":"PL",
    "gn:dem":180,
    "gn:feature_class":"P",
    "gn:feature_code":"PPL",
    "gn:name":"Gron\u00f3wek",
    "gn:population":0,
    "gn:timezone":"Europe/Warsaw",
    "iso:country":"PL",
    "name:pol_x_preferred":[
        "Gron\u00f3wek"
    ],
    "name:ukr_x_preferred":[
        "\u0490\u0440\u043e\u043d\u0443\u0432\u0435\u043a"
    ],
    "name:und_x_variant":[
        "Gron\u00f3wek"
    ],
    "wof:name":"Gronowek",
    "wof:placetype":"locality"
},
  "geometry": {"coordinates":[18.66941,51.42043],"type":"Point"}
}