{
  "type": "Feature",
  "properties": {
    "gn:admin1_code":"86.0",
    "gn:admin2_code":"3030.0",
    "gn:admin3_code":"303001.0",
    "gn:asciiname":"Borzykowo",
    "gn:country_code":"PL",
    "gn:dem":90,
    "gn:feature_class":"P",
    "gn:feature_code":"PPL",
    "gn:name":"Borzykowo",
    "gn:population":0,
    "gn:timezone":"Europe/Warsaw",
    "iso:country":"PL",
    "name:fra_x_preferred":[
        "Borzykowo"
    ],
    "name:pol_x_preferred":[
        "Borzykowo"
    ],
    "name:ukr_x_preferred":[
        "\u0411\u043e\u0436\u0438\u043a\u043e\u0432\u043e"
    ],
    "wof:name":"Borzykowo",
    "wof:placetype":"locality"
},
  "geometry": {"coordinates":[17.66137999999999,52.19824000000001],"type":"Point"}
}