{
  "type": "Feature",
  "properties": {
    "gn:gn_country":"PL",
    "gn:gn_fcode":"PPL",
    "gn:gn_pop":216,
    "gn:population":216,
    "iso:country":"PL",
    "name:ast_x_preferred":[
        "Targowica"
    ],
    "name:ceb_x_preferred":[
        "Targowica"
    ],
    "name:eng_x_preferred":[
        "Targowica"
    ],
    "name:fra_x_preferred":[
        "Targowica"
    ],
    "name:pol_x_preferred":[
        "Targowica"
    ],
    "name:ukr_x_preferred":[
        "\u0422\u0430\u0440\u0491\u043e\u0432\u0438\u0446\u044f"
    ],
    "qs_pg:aaroncc":"PL",
    "qs_pg:gn_country":"PL",
    "qs_pg:gn_fcode":"PPL",
    "qs_pg:gn_pop":216,
    "qs_pg:name":"Targowica",
    "qs_pg:name_adm0":"Polska",
    "qs_pg:name_adm1":"Dolnosl\u0105skie",
    "qs_pg:photos_9r":0,
    "qs_pg:photos_sr":0,
    "qs_pg:pop_sr":2,
    "qs_pg:qs_pg_placetype":"locality",
    "qs_pg:qs_pg_placetype_gp":"Town",
    "qs_pg:woe_adm0":23424923,
    "woe:adm0_id":23424923,
    "woe:name_adm0":"Polska",
    "woe:name_adm1":"Dolnosl\u0105skie",
    "woe:placetype":"Town",
    "wof:name":"Targowica",
    "wof:placetype":"locality",
    "wof:population":216
},
  "geometry": {"coordinates":[16.96238,50.68384],"type":"Point"}
}