{
  "type": "Feature",
  "properties": {
    "gn:admin1_code":"86.0",
    "gn:admin2_code":"3018.0",
    "gn:admin3_code":"301802.0",
    "gn:asciiname":"Mieleszowka",
    "gn:country_code":"PL",
    "gn:dem":139,
    "gn:feature_class":"P",
    "gn:feature_code":"PPL",
    "gn:name":"Mielesz\u00f3wka",
    "gn:population":0,
    "gn:timezone":"Europe/Warsaw",
    "iso:country":"PL",
    "name:ceb_x_preferred":[
        "Mielesz\u00f3wka"
    ],
    "name:pol_x_preferred":[
        "Mielesz\u00f3wka"
    ],
    "name:ukr_x_preferred":[
        "\u041c\u0435\u043b\u0435\u0448\u0443\u0432\u043a\u0430"
    ],
    "wof:name":"Mieleszowka",
    "wof:placetype":"locality"
},
  "geometry": {"coordinates":[18.181,51.43304000000001],"type":"Point"}
}