{
  "type": "Feature",
  "properties": {
    "gn:admin1_code":"74.0",
    "gn:admin2_code":"1012.0",
    "gn:admin3_code":"101203.0",
    "gn:asciiname":"Gorka",
    "gn:country_code":"PL",
    "gn:dem":217,
    "gn:feature_class":"P",
    "gn:feature_code":"PPL",
    "gn:name":"G\u00f3rka",
    "gn:population":0,
    "gn:timezone":"Europe/Warsaw",
    "iso:country":"PL",
    "name:fra_x_preferred":[
        "G\u00f3rka"
    ],
    "name:pol_x_preferred":[
        "G\u00f3rka"
    ],
    "name:ukr_x_preferred":[
        "\u0490\u0443\u0440\u043a\u0430"
    ],
    "name:und_x_variant":[
        "G\u00f3rka"
    ],
    "wof:name":"Gorka",
    "wof:placetype":"locality"
},
  "geometry": {"coordinates":[19.50883,50.95114],"type":"Point"}
}