{
  "type": "Feature",
  "properties": {
    "gn:admin1_code":"78.0",
    "gn:admin2_code":"1415.0",
    "gn:admin3_code":"141511.0",
    "gn:asciiname":"Ojcewo",
    "gn:country_code":"PL",
    "gn:dem":110,
    "gn:feature_class":"P",
    "gn:feature_code":"PPL",
    "gn:name":"Ojcewo",
    "gn:population":0,
    "gn:timezone":"Europe/Warsaw",
    "iso:country":"PL",
    "name:fra_x_preferred":[
        "Ojcewo"
    ],
    "name:pol_x_preferred":[
        "Ojcewo"
    ],
    "name:ukr_x_preferred":[
        "\u041e\u0439\u0446\u0435\u0432\u043e"
    ],
    "wof:name":"Ojcewo",
    "wof:placetype":"locality"
},
  "geometry": {"coordinates":[21.80735,53.04333000000001],"type":"Point"}
}