{
  "type": "Feature",
  "properties": {
    "gn:admin1_code":"86.0",
    "gn:admin2_code":"3011.0",
    "gn:admin3_code":"301105.0",
    "gn:asciiname":"Morownica",
    "gn:country_code":"PL",
    "gn:dem":104,
    "gn:feature_class":"P",
    "gn:feature_code":"PPL",
    "gn:name":"Morownica",
    "gn:population":0,
    "gn:timezone":"Europe/Warsaw",
    "iso:country":"PL",
    "name:azb_x_preferred":[
        "\u0645\u0648\u0631\u0648\u0648\u0646\u0642\u062a\u0633\u0627"
    ],
    "name:ceb_x_preferred":[
        "Morownica"
    ],
    "name:fas_x_preferred":[
        "\u0645\u0648\u0631\u0648\u0648\u0646\u06af\u062a\u0633\u0627"
    ],
    "name:fra_x_preferred":[
        "Morownica"
    ],
    "name:nld_x_preferred":[
        "Morownica"
    ],
    "name:pol_x_preferred":[
        "Morownica"
    ],
    "name:ukr_x_preferred":[
        "\u041c\u043e\u0440\u043e\u0432\u043d\u0438\u0446\u044f"
    ],
    "wof:name":"Morownica",
    "wof:placetype":"locality"
},
  "geometry": {"coordinates":[16.47334,51.9922],"type":"Point"}
}