{
  "type": "Feature",
  "properties": {
    "iso:country":"PL",
    "name:eng_x_preferred":[
        "Gaj"
    ],
    "name:pol_x_preferred":[
        "Gaj"
    ],
    "wof:name":"Gaj",
    "wof:placetype":"neighbourhood"
},
  "geometry": {"coordinates":[17.03766853835056,51.07702708355265],"type":"Point"}
}