{
  "type": "Feature",
  "properties": {
    "gn:admin1_code":"78.0",
    "gn:admin2_code":"1438.0",
    "gn:admin3_code":"143802.0",
    "gn:asciiname":"Wrecza",
    "gn:country_code":"PL",
    "gn:dem":152,
    "gn:feature_class":"P",
    "gn:feature_code":"PPL",
    "gn:name":"Wr\u0119cza",
    "gn:population":0,
    "gn:timezone":"Europe/Warsaw",
    "iso:country":"PL",
    "name:fra_x_preferred":[
        "Wr\u0119cza"
    ],
    "name:pol_x_preferred":[
        "Wr\u0119cza"
    ],
    "name:ukr_x_preferred":[
        "\u0412\u0440\u0435\u043d\u0447\u0430"
    ],
    "wof:name":"Wrecza",
    "wof:placetype":"locality"
},
  "geometry": {"coordinates":[20.45217,51.99593],"type":"Point"}
}