{
  "type": "Feature",
  "properties": {
    "gn:admin1_code":"73.0",
    "gn:admin2_code":"419.0",
    "gn:admin3_code":"41902.0",
    "gn:asciiname":"Laski Wielkie",
    "gn:country_code":"PL",
    "gn:dem":99,
    "gn:feature_class":"P",
    "gn:feature_code":"PPL",
    "gn:name":"Laski Wielkie",
    "gn:population":0,
    "gn:timezone":"Europe/Warsaw",
    "iso:country":"PL",
    "name:ceb_x_preferred":[
        "Laski Wielkie"
    ],
    "name:pol_x_preferred":[
        "Laski Wielkie"
    ],
    "name:ukr_x_preferred":[
        "\u041b\u044f\u0441\u043a\u0456-\u0412\u0435\u043b\u0438\u043a\u0456"
    ],
    "wof:name":"Laski Wielkie",
    "wof:placetype":"locality"
},
  "geometry": {"coordinates":[17.86122,52.7705],"type":"Point"}
}