{
  "type": "Feature",
  "properties": {
    "gn:admin1_code":"79.0",
    "gn:admin2_code":"1610.0",
    "gn:admin3_code":"161002.0",
    "gn:asciiname":"Wierzch",
    "gn:country_code":"PL",
    "gn:dem":207,
    "gn:feature_class":"P",
    "gn:feature_code":"PPL",
    "gn:name":"Wierzch",
    "gn:population":0,
    "gn:timezone":"Europe/Warsaw",
    "iso:country":"PL",
    "name:azb_x_preferred":[
        "\u0648\u06cc\u0698\u062e"
    ],
    "name:deu_x_preferred":[
        "Deutsch M\u00fcllmen"
    ],
    "name:fas_x_preferred":[
        "\u0648\u06cc\u0698\u062e"
    ],
    "name:pol_x_preferred":[
        "Wierzch"
    ],
    "name:ukr_x_preferred":[
        "\u0412\u0435\u0436\u0445"
    ],
    "wof:name":"Wierzch",
    "wof:placetype":"locality"
},
  "geometry": {"coordinates":[17.77845,50.35389],"type":"Point"}
}