{
  "type": "Feature",
  "properties": {
    "gn:admin1_code":"79.0",
    "gn:admin2_code":"1610.0",
    "gn:admin3_code":"161002.0",
    "gn:asciiname":"Wierzch",
    "gn:country_code":"PL",
    "gn:dem":207,
    "gn:feature_class":"P",
    "gn:feature_code":"PPL",
    "gn:name":"Wierzch",
    "gn:population":0,
    "gn:timezone":"Europe/Warsaw",
    "iso:country":"PL",
    "wof:name":"Wierzch",
    "wof:placetype":"locality"
},
  "geometry": {"coordinates":[17.77845,50.35389],"type":"Point"}
}