{
  "type": "Feature",
  "properties": {
    "gn:admin1_code":"80.0",
    "gn:admin2_code":"1811.0",
    "gn:admin3_code":"181105.0",
    "gn:asciiname":"Chorzelow",
    "gn:country_code":"PL",
    "gn:dem":160,
    "gn:feature_class":"P",
    "gn:feature_code":"PPL",
    "gn:name":"Chorzel\u00f3w",
    "gn:population":0,
    "gn:timezone":"Europe/Warsaw",
    "iso:country":"PL",
    "name:ceb_x_preferred":[
        "Chorzel\u00f3w"
    ],
    "name:nld_x_preferred":[
        "Chorzel\u00f3w"
    ],
    "name:pol_x_preferred":[
        "Chorzel\u00f3w"
    ],
    "name:ukr_x_preferred":[
        "\u0425\u043e\u0436\u0435\u043b\u044e\u0432"
    ],
    "wof:name":"Chorzelow",
    "wof:placetype":"locality"
},
  "geometry": {"coordinates":[21.44617,50.3379],"type":"Point"}
}