{
  "type": "Feature",
  "properties": {
    "gn:admin1_code":"85.0",
    "gn:admin2_code":"2819.0",
    "gn:admin3_code":"281903.0",
    "gn:asciiname":"Perly",
    "gn:country_code":"PL",
    "gn:dem":98,
    "gn:feature_class":"P",
    "gn:feature_code":"PPL",
    "gn:name":"Per\u0142y",
    "gn:population":0,
    "gn:timezone":"Europe/Warsaw",
    "iso:country":"PL",
    "name:eng_x_preferred":[
        "Per\u0142y"
    ],
    "name:lit_x_preferred":[
        "Perlai"
    ],
    "name:rus_x_preferred":[
        "\u041f\u0435\u0440\u043b\u044b"
    ],
    "name:und_x_variant":[
        "Perlswalde",
        "Per\u0142y"
    ],
    "wof:name":"Perly",
    "wof:placetype":"locality"
},
  "geometry": {"coordinates":[21.6683,54.29589],"type":"Point"}
}