{
  "type": "Feature",
  "properties": {
    "gn:admin1_code":"86.0",
    "gn:admin2_code":"3017.0",
    "gn:admin3_code":"301706.0",
    "gn:asciiname":"Bieganin",
    "gn:country_code":"PL",
    "gn:dem":153,
    "gn:feature_class":"P",
    "gn:feature_code":"PPL",
    "gn:name":"Bieganin",
    "gn:population":0,
    "gn:timezone":"Europe/Warsaw",
    "iso:country":"PL",
    "name:pol_x_preferred":[
        "Bieganin"
    ],
    "name:ukr_x_preferred":[
        "\u0411\u0435\u0491\u0430\u043d\u0456\u043d"
    ],
    "wof:name":"Bieganin",
    "wof:placetype":"locality"
},
  "geometry": {"coordinates":[17.75717999999999,51.76094000000001],"type":"Point"}
}