{
  "type": "Feature",
  "properties": {
    "gn:admin1_code":"76.0",
    "gn:admin2_code":"804.0",
    "gn:admin3_code":"80402.0",
    "gn:asciiname":"Popowo",
    "gn:country_code":"PL",
    "gn:dem":166,
    "gn:feature_class":"P",
    "gn:feature_code":"PPL",
    "gn:name":"Popowo",
    "gn:population":0,
    "gn:timezone":"Europe/Warsaw",
    "iso:country":"PL",
    "name:deu_x_historical":[
        "Pfaffendorf"
    ],
    "name:deu_x_preferred":[
        "Pfaffendorf"
    ],
    "name:fra_x_preferred":[
        "Popowo"
    ],
    "name:pol_x_preferred":[
        "Popowo"
    ],
    "name:ukr_x_preferred":[
        "\u041f\u043e\u043f\u043e\u0432\u043e"
    ],
    "wof:name":"Popowo",
    "wof:placetype":"locality"
},
  "geometry": {"coordinates":[15.80297,51.69161],"type":"Point"}
}