{
  "type": "Feature",
  "properties": {
    "gn:admin1_code":"86.0",
    "gn:admin2_code":"3023.0",
    "gn:admin3_code":"302306.0",
    "gn:asciiname":"Kowalewo Gory",
    "gn:country_code":"PL",
    "gn:dem":89,
    "gn:feature_class":"P",
    "gn:feature_code":"PPL",
    "gn:name":"Kowalewo G\u00f3ry",
    "gn:population":0,
    "gn:timezone":"Europe/Warsaw",
    "iso:country":"PL",
    "wof:name":"Kowalewo Gory",
    "wof:placetype":"locality"
},
  "geometry": {"coordinates":[17.91821000000001,52.2694],"type":"Point"}
}