{
  "type": "Feature",
  "properties": {
    "gn:admin1_code":"74.0",
    "gn:admin2_code":"1019.0",
    "gn:admin3_code":"101904.0",
    "gn:asciiname":"Zamlynie",
    "gn:country_code":"PL",
    "gn:dem":153,
    "gn:feature_class":"P",
    "gn:feature_code":"PPL",
    "gn:name":"Zam\u0142ynie",
    "gn:population":0,
    "gn:timezone":"Europe/Warsaw",
    "iso:country":"PL",
    "wof:name":"Zamlynie",
    "wof:placetype":"locality"
},
  "geometry": {"coordinates":[18.86057000000001,51.67101],"type":"Point"}
}