{
  "type": "Feature",
  "properties": {
    "gn:admin1_code":"78.0",
    "gn:admin2_code":"1419.0",
    "gn:admin3_code":"141911.0",
    "gn:asciiname":"Nowosiadlo",
    "gn:cc2":"PL",
    "gn:country_code":"PL",
    "gn:dem":58,
    "gn:feature_class":"P",
    "gn:feature_code":"PPL",
    "gn:name":"Nowosiad\u0142o",
    "gn:population":0,
    "gn:timezone":"Europe/Warsaw",
    "iso:country":"PL",
    "name:fra_x_preferred":[
        "Nowosiad\u0142o"
    ],
    "name:pol_x_preferred":[
        "Nowosiad\u0142o"
    ],
    "name:ukr_x_preferred":[
        "\u041d\u043e\u0432\u043e\u0441\u044f\u0434\u043b\u043e"
    ],
    "name:und_x_variant":[
        "Nowosiad\u0142o Stare"
    ],
    "wof:name":"Nowosiadlo",
    "wof:placetype":"locality"
},
  "geometry": {"coordinates":[19.91941,52.42744],"type":"Point"}
}