{
  "type": "Feature",
  "properties": {
    "gn:gn_country":"PL",
    "gn:gn_fcode":"PPL",
    "gn:gn_pop":308,
    "gn:population":308,
    "iso:country":"PL",
    "name:deu_x_preferred":[
        "Trzebie\u0144czyce"
    ],
    "name:eng_x_preferred":[
        "Trzebie\u0144czyce"
    ],
    "name:fas_x_preferred":[
        "\u0686\u0628\u06cc\u0626\u0646\u06a9\u0632\u06cc\u06a9\u0647"
    ],
    "name:fra_x_preferred":[
        "Trzebie\u0144czyce"
    ],
    "name:pol_x_preferred":[
        "Trzebie\u0144czyce"
    ],
    "qs_pg:aaroncc":"PL",
    "qs_pg:gn_country":"PL",
    "qs_pg:gn_fcode":"PPL",
    "qs_pg:gn_pop":308,
    "qs_pg:name":"Trzebie\u0144czyce",
    "qs_pg:name_adm0":"Polska",
    "qs_pg:name_adm1":"Ma\u0142opolskie",
    "qs_pg:photos_9r":0,
    "qs_pg:photos_sr":0,
    "qs_pg:pop_sr":2,
    "qs_pg:qs_pg_placetype":"locality",
    "qs_pg:qs_pg_placetype_gp":"Town",
    "qs_pg:woe_adm0":23424923,
    "woe:adm0_id":23424923,
    "woe:name_adm0":"Polska",
    "woe:name_adm1":"Ma\u0142opolskie",
    "woe:placetype":"Town",
    "wof:name":"Trzebie\u0144czyce",
    "wof:placetype":"locality",
    "wof:population":308
},
  "geometry": {"coordinates":[19.45507,49.97722],"type":"Point"}
}