{
  "type": "Feature",
  "properties": {
    "gn:admin1_code":"78.0",
    "gn:admin2_code":"1406.0",
    "gn:admin3_code":"140611.0",
    "gn:asciiname":"Gaski",
    "gn:country_code":"PL",
    "gn:dem":116,
    "gn:feature_class":"P",
    "gn:feature_code":"PPL",
    "gn:name":"G\u0105ski",
    "gn:population":0,
    "gn:timezone":"Europe/Warsaw",
    "iso:country":"PL",
    "name:ceb_x_preferred":[
        "G\u0105ski"
    ],
    "name:fra_x_preferred":[
        "G\u0105ski"
    ],
    "name:pol_x_preferred":[
        "G\u0105ski"
    ],
    "name:ukr_x_preferred":[
        "\u0490\u043e\u043d\u0441\u043a\u0456"
    ],
    "wof:name":"Gaski",
    "wof:placetype":"locality"
},
  "geometry": {"coordinates":[21.17374,51.84055],"type":"Point"}
}