{
  "type": "Feature",
  "properties": {
    "gn:admin1_code":"84.0",
    "gn:admin2_code":"2661.0",
    "gn:admin3_code":"266101.0",
    "gn:asciiname":"Sady",
    "gn:country_code":"PL",
    "gn:dem":271,
    "gn:feature_class":"P",
    "gn:feature_code":"PPL",
    "gn:name":"Sady",
    "gn:population":0,
    "gn:timezone":"Europe/Warsaw",
    "iso:country":"PL",
    "name:ces_x_preferred":[
        "Sady"
    ],
    "name:deu_x_preferred":[
        "Sady"
    ],
    "name:fra_x_preferred":[
        "Sady"
    ],
    "name:ita_x_preferred":[
        "Sady"
    ],
    "name:pol_x_preferred":[
        "Sady"
    ],
    "name:slk_x_preferred":[
        "Sady"
    ],
    "name:ukr_x_preferred":[
        "\u0421\u0430\u0434\u0438"
    ],
    "wof:name":"Sady",
    "wof:placetype":"locality"
},
  "geometry": {"coordinates":[20.63499,50.88286],"type":"Point"}
}