{
  "type": "Feature",
  "properties": {
    "gn:country":"PL",
    "gn:fcode":"PPL",
    "gn:population":0,
    "iso:country":"PL",
    "name:ast_x_preferred":[
        "W\u0119grzce"
    ],
    "name:azb_x_preferred":[
        "\u0648\u0646\u0642\u0698\u062a\u0633\u0647"
    ],
    "name:ceb_x_preferred":[
        "W\u0119grzce"
    ],
    "name:eng_x_preferred":[
        "W\u0119grzce"
    ],
    "name:fas_x_preferred":[
        "\u0648\u0646\u06af\u0698\u062a\u0633\u0647"
    ],
    "name:fra_x_preferred":[
        "W\u0119grzce"
    ],
    "name:nld_x_preferred":[
        "W\u0119grzce"
    ],
    "name:pol_x_preferred":[
        "W\u0119grzce"
    ],
    "name:rus_x_preferred":[
        "\u0412\u0435\u043d\u0433\u0436\u0446\u0435"
    ],
    "name:szl_x_preferred":[
        "Wyngrzce"
    ],
    "name:ukr_x_preferred":[
        "\u0412\u0435\u043d\u0491\u0436\u0446\u0435"
    ],
    "qs_pg:aaroncc":"PL",
    "qs_pg:gn_country":"PL",
    "qs_pg:gn_fcode":"PPL",
    "qs_pg:gn_pop":0,
    "qs_pg:name":"W\u0119grzce",
    "qs_pg:name_adm0":"Polska",
    "qs_pg:name_adm1":"Ma\u0142opolskie",
    "qs_pg:photos_9k":1,
    "qs_pg:photos_9r":1,
    "qs_pg:photos_all":17,
    "qs_pg:photos_sr":0,
    "qs_pg:pop_sr":0,
    "qs_pg:qs_pg_placetype":"locality",
    "qs_pg:qs_pg_placetype_gp":"Town",
    "qs_pg:woe_adm0":23424923,
    "woe:adm0_id":23424923,
    "woe:name_adm0":"Polska",
    "woe:name_adm1":"Ma\u0142opolskie",
    "woe:placetype":"Town",
    "wof:name":"W\u0119grzce",
    "wof:placetype":"locality"
},
  "geometry": {"coordinates":[19.97268,50.11942],"type":"Point"}
}