{
  "type": "Feature",
  "properties": {
    "gn:admin1_code":"86.0",
    "gn:admin2_code":"3002.0",
    "gn:admin3_code":"300206.0",
    "gn:asciiname":"Boruszyn",
    "gn:country_code":"PL",
    "gn:dem":64,
    "gn:feature_class":"P",
    "gn:feature_code":"PPL",
    "gn:name":"Boruszyn",
    "gn:population":0,
    "gn:timezone":"Europe/Warsaw",
    "iso:country":"PL",
    "name:fra_x_preferred":[
        "Boruszyn"
    ],
    "name:pol_x_preferred":[
        "Boruszyn"
    ],
    "name:ukr_x_preferred":[
        "\u0411\u043e\u0440\u0443\u0448\u0438\u043d"
    ],
    "wof:name":"Boruszyn",
    "wof:placetype":"locality"
},
  "geometry": {"coordinates":[16.64094,52.77104],"type":"Point"}
}