{
  "type": "Feature",
  "properties": {
    "gn:admin1_code":"74.0",
    "gn:admin2_code":"1061.0",
    "gn:admin3_code":"106101.0",
    "gn:asciiname":"Chojny-Dabrowa",
    "gn:country_code":"PL",
    "gn:dem":203,
    "gn:feature_class":"P",
    "gn:feature_code":"PPL",
    "gn:name":"Chojny-D\u0105browa",
    "gn:population":0,
    "gn:timezone":"Europe/Warsaw",
    "iso:country":"PL",
    "wof:name":"Chojny-Dabrowa",
    "wof:placetype":"locality"
},
  "geometry": {"coordinates":[19.49249,51.73205],"type":"Point"}
}