{
  "type": "Feature",
  "properties": {
    "gn:admin1_code":"80.0",
    "gn:admin2_code":"1805.0",
    "gn:admin3_code":"180511.0",
    "gn:asciiname":"Glinik Polski",
    "gn:country_code":"PL",
    "gn:dem":256,
    "gn:feature_class":"P",
    "gn:feature_code":"PPL",
    "gn:name":"Glinik Polski",
    "gn:population":0,
    "gn:timezone":"Europe/Warsaw",
    "iso:country":"PL",
    "name:ceb_x_preferred":[
        "Glinik Polski"
    ],
    "name:pol_x_preferred":[
        "Glinik Polski"
    ],
    "name:ukr_x_preferred":[
        "\u0490\u043b\u0456\u043d\u0438\u043a-\u041f\u043e\u043b\u044c\u0441\u044c\u043a\u0438\u0439"
    ],
    "wof:name":"Glinik Polski",
    "wof:placetype":"locality"
},
  "geometry": {"coordinates":[21.5538,49.6954],"type":"Point"}
}