{
  "type": "Feature",
  "properties": {
    "gn:admin1_code":"77.0",
    "gn:admin2_code":"1214.0",
    "gn:admin3_code":"121401.0",
    "gn:asciiname":"Lyszkowice",
    "gn:country_code":"PL",
    "gn:dem":271,
    "gn:feature_class":"P",
    "gn:feature_code":"PPL",
    "gn:name":"\u0141yszkowice",
    "gn:population":0,
    "gn:timezone":"Europe/Warsaw",
    "iso:country":"PL",
    "name:pol_x_preferred":[
        "\u0141yszkowice"
    ],
    "name:ukr_x_preferred":[
        "\u041b\u0438\u0448\u043a\u043e\u0432\u0456\u0446\u0435"
    ],
    "wof:name":"Lyszkowice",
    "wof:placetype":"locality"
},
  "geometry": {"coordinates":[20.20781,50.1753],"type":"Point"}
}