{
  "type": "Feature",
  "properties": {
    "gn:admin1_code":"82.0",
    "gn:admin2_code":"2212.0",
    "gn:admin3_code":"221204.0",
    "gn:asciiname":"Szczypkowice",
    "gn:country_code":"PL",
    "gn:dem":60,
    "gn:feature_class":"P",
    "gn:feature_code":"PPL",
    "gn:name":"Szczypkowice",
    "gn:population":0,
    "gn:timezone":"Europe/Warsaw",
    "iso:country":"PL",
    "name:azb_x_preferred":[
        "\u0634\u0686\u067e\u06a9\u0648\u0648\u06cc\u062a\u0633\u0647"
    ],
    "name:ceb_x_preferred":[
        "Szczypkowice"
    ],
    "name:csb_x_preferred":[
        "Szcz\u00ebpk\u00f2jce"
    ],
    "name:deu_x_preferred":[
        "Szczypkowice"
    ],
    "name:fas_x_preferred":[
        "\u0634\u0686\u067e\u06a9\u0648\u0648\u06cc\u062a\u0633\u0647"
    ],
    "name:pol_x_preferred":[
        "Szczypkowice"
    ],
    "name:ukr_x_preferred":[
        "\u0429\u0438\u043f\u043a\u043e\u0432\u0456\u0446\u0435"
    ],
    "wof:name":"Szczypkowice",
    "wof:placetype":"locality"
},
  "geometry": {"coordinates":[17.41639,54.57648],"type":"Point"}
}