{
  "type": "Feature",
  "properties": {
    "gn:admin1_code":"82.0",
    "gn:admin2_code":"2212.0",
    "gn:admin3_code":"221204.0",
    "gn:asciiname":"Szczypkowice",
    "gn:country_code":"PL",
    "gn:dem":60,
    "gn:feature_class":"P",
    "gn:feature_code":"PPL",
    "gn:name":"Szczypkowice",
    "gn:population":0,
    "gn:timezone":"Europe/Warsaw",
    "iso:country":"PL",
    "wof:name":"Szczypkowice",
    "wof:placetype":"locality"
},
  "geometry": {"coordinates":[17.41639,54.57648],"type":"Point"}
}