{
  "type": "Feature",
  "properties": {
    "gn:admin1_code":"86.0",
    "gn:admin2_code":"3026.0",
    "gn:admin3_code":"302602.0",
    "gn:asciiname":"Mszczyczyn",
    "gn:country_code":"PL",
    "gn:dem":111,
    "gn:feature_class":"P",
    "gn:feature_code":"PPL",
    "gn:name":"Mszczyczyn",
    "gn:population":0,
    "gn:timezone":"Europe/Warsaw",
    "iso:country":"PL",
    "name:ceb_x_preferred":[
        "Mszczyczyn"
    ],
    "name:fra_x_preferred":[
        "Mszczyczyn"
    ],
    "name:nld_x_preferred":[
        "Mszczyczyn"
    ],
    "name:pol_x_preferred":[
        "Mszczyczyn"
    ],
    "name:ukr_x_preferred":[
        "\u041c\u0449\u0438\u0447\u0438\u043d"
    ],
    "wof:name":"Mszczyczyn",
    "wof:placetype":"locality"
},
  "geometry": {"coordinates":[17.08775,51.93731],"type":"Point"}
}