{
  "type": "Feature",
  "properties": {
    "gn:admin1_code":"85.0",
    "gn:admin2_code":"2814.0",
    "gn:admin3_code":"281409.0",
    "gn:asciiname":"Orzechowo",
    "gn:cc2":"PL",
    "gn:country_code":"PL",
    "gn:dem":161,
    "gn:feature_class":"P",
    "gn:feature_code":"PPL",
    "gn:name":"Orzechowo",
    "gn:population":0,
    "gn:timezone":"Europe/Warsaw",
    "iso:country":"PL",
    "name:deu_x_preferred":[
        "Orzechowo"
    ],
    "name:fra_x_preferred":[
        "Orzechowo"
    ],
    "name:pol_x_preferred":[
        "Orzechowo"
    ],
    "name:ukr_x_preferred":[
        "\u041e\u0436\u0435\u0445\u043e\u0432\u043e"
    ],
    "name:und_x_variant":[
        "Nussthal",
        "Nusstal"
    ],
    "wof:name":"Orzechowo",
    "wof:placetype":"locality"
},
  "geometry": {"coordinates":[20.46667,53.56667],"type":"Point"}
}