{
  "type": "Feature",
  "properties": {
    "gn:admin1_code":"85.0",
    "gn:admin2_code":"2814.0",
    "gn:admin3_code":"281409.0",
    "gn:asciiname":"Orzechowo",
    "gn:cc2":"PL",
    "gn:country_code":"PL",
    "gn:dem":161,
    "gn:feature_class":"P",
    "gn:feature_code":"PPL",
    "gn:name":"Orzechowo",
    "gn:population":0,
    "gn:timezone":"Europe/Warsaw",
    "iso:country":"PL",
    "name:und_x_variant":[
        "Nussthal",
        "Nusstal",
        "Orzechowo"
    ],
    "wof:name":"Orzechowo",
    "wof:placetype":"locality"
},
  "geometry": {"coordinates":[20.46667,53.56667],"type":"Point"}
}