{
  "type": "Feature",
  "properties": {
    "gn:population":1722,
    "iso:country":"PL",
    "name:ast_x_preferred":[
        "Szczurowa"
    ],
    "name:azb_x_preferred":[
        "\u0634\u0686\u0648\u0631\u0648\u0648\u0627"
    ],
    "name:deu_x_preferred":[
        "Szczurowa"
    ],
    "name:eng_x_preferred":[
        "Szczurowa"
    ],
    "name:fas_x_preferred":[
        "\u0634\u0686\u0648\u0631\u0648\u0648\u0627"
    ],
    "name:fra_x_preferred":[
        "Szczurowa"
    ],
    "name:nld_x_preferred":[
        "Szczurowa"
    ],
    "name:pol_x_preferred":[
        "Szczurowa"
    ],
    "name:rus_x_preferred":[
        "\u0429\u0443\u0440\u043e\u0432\u0430"
    ],
    "name:swe_x_preferred":[
        "Szczurowa"
    ],
    "name:ukr_x_preferred":[
        "\u0429\u0443\u0440\u043e\u0432\u0430"
    ],
    "qs:a0":"Rzeczpospolita Polska",
    "qs:a1":"*Malopolskie",
    "qs:a1r":"0",
    "qs:a2":"Brzeski",
    "qs:adm0":"Rzeczpospolita Polska",
    "qs:la":"Szczurowa",
    "qs:la_lc":"*PL1202072",
    "qs:level":"locality",
    "qs:loc":"Szczurowa",
    "qs:loc_alt":"Szczurowa",
    "qs:pop":0,
    "qs:type":"rural point-in-poly",
    "wd:wordcount":90,
    "wof:coterminous":[
        1125376931
    ],
    "wof:name":"Szczurowa",
    "wof:placetype":"locality",
    "wof:population":1722
},
  "geometry": {"coordinates":[20.6173825277811,50.1144936229555],"type":"Point"}
}