{
  "type": "Feature",
  "properties": {
    "gn:admin1_code":"82.0",
    "gn:admin2_code":"2210.0",
    "gn:admin3_code":"221001.0",
    "gn:asciiname":"Wydmy",
    "gn:country_code":"PL",
    "gn:dem":4,
    "gn:feature_class":"P",
    "gn:feature_code":"PPL",
    "gn:name":"Wydmy",
    "gn:population":0,
    "gn:timezone":"Europe/Warsaw",
    "iso:country":"PL",
    "wof:name":"Wydmy",
    "wof:placetype":"locality"
},
  "geometry": {"coordinates":[19.33333,54.36666999999999],"type":"Point"}
}