{
  "type": "Feature",
  "properties": {
    "gn:admin1_code":"78.0",
    "gn:admin2_code":"1415.0",
    "gn:admin3_code":"141511.0",
    "gn:asciiname":"Trzaski",
    "gn:country_code":"PL",
    "gn:dem":109,
    "gn:feature_class":"P",
    "gn:feature_code":"PPL",
    "gn:name":"Trzaski",
    "gn:population":0,
    "gn:timezone":"Europe/Warsaw",
    "iso:country":"PL",
    "name:azb_x_preferred":[
        "\u062a\u0631\u0632\u0627\u0633\u06a9\u06cc"
    ],
    "name:fas_x_preferred":[
        "\u062a\u0631\u0632\u0627\u0633\u06a9\u06cc"
    ],
    "name:fra_x_preferred":[
        "Trzaski"
    ],
    "name:pol_x_preferred":[
        "Trzaski"
    ],
    "name:szl_x_preferred":[
        "Trzaski"
    ],
    "name:ukr_x_preferred":[
        "\u0422\u0448\u0430\u0441\u043a\u0456"
    ],
    "name:urd_x_preferred":[
        "\u062a\u0631\u0632\u0633\u06a9\u06cc"
    ],
    "wof:name":"Trzaski",
    "wof:placetype":"locality"
},
  "geometry": {"coordinates":[21.83601,53.0734],"type":"Point"}
}