{
  "type": "Feature",
  "properties": {
    "gn:admin1_code":"82.0",
    "gn:admin2_code":"2204.0",
    "gn:admin3_code":"220408.0",
    "gn:asciiname":"Mierzeszyn",
    "gn:country_code":"PL",
    "gn:dem":195,
    "gn:feature_class":"P",
    "gn:feature_code":"PPL",
    "gn:name":"Mierzeszyn",
    "gn:population":0,
    "gn:timezone":"Europe/Warsaw",
    "iso:country":"PL",
    "name:ceb_x_preferred":[
        "Mierzeszyn"
    ],
    "name:nld_x_preferred":[
        "Mierzeszyn"
    ],
    "name:pol_x_preferred":[
        "Mierzeszyn"
    ],
    "name:ukr_x_preferred":[
        "\u041c\u0435\u0436\u0435\u0448\u0438\u043d"
    ],
    "name:und_x_variant":[
        "Meisterswalde"
    ],
    "wof:name":"Mierzeszyn",
    "wof:placetype":"locality"
},
  "geometry": {"coordinates":[18.42,54.19905],"type":"Point"}
}