{
  "type": "Feature",
  "properties": {
    "gn:admin1_code":"81.0",
    "gn:admin2_code":"2012.0",
    "gn:admin3_code":"201208.0",
    "gn:asciiname":"Adamowizna",
    "gn:country_code":"PL",
    "gn:dem":161,
    "gn:feature_class":"P",
    "gn:feature_code":"PPL",
    "gn:name":"Adamowizna",
    "gn:population":0,
    "gn:timezone":"Europe/Warsaw",
    "iso:country":"PL",
    "name:azb_x_preferred":[
        "\u0622\u062f\u0627\u0645\u0648\u0648\u06cc\u0632\u0646\u0627"
    ],
    "name:fas_x_preferred":[
        "\u0622\u062f\u0627\u0645\u0648\u0648\u06cc\u0632\u0646\u0627"
    ],
    "name:lit_x_preferred":[
        "Adamovizna"
    ],
    "name:pol_x_preferred":[
        "Adamowizna"
    ],
    "name:ukr_x_preferred":[
        "\u0410\u0434\u0430\u043c\u043e\u0432\u0456\u0437\u043d\u0430"
    ],
    "wof:name":"Adamowizna",
    "wof:placetype":"locality"
},
  "geometry": {"coordinates":[23.13584,54.17633000000001],"type":"Point"}
}