{
  "type": "Feature",
  "properties": {
    "gn:admin1_code":"73.0",
    "gn:admin2_code":"406.0",
    "gn:admin3_code":"40603.0",
    "gn:asciiname":"Nowe Mosty",
    "gn:country_code":"PL",
    "gn:dem":90,
    "gn:feature_class":"P",
    "gn:feature_code":"PPL",
    "gn:name":"Nowe Mosty",
    "gn:population":0,
    "gn:timezone":"Europe/Warsaw",
    "iso:country":"PL",
    "name:pol_x_preferred":[
        "Nowe Mosty"
    ],
    "name:ukr_x_preferred":[
        "\u041d\u043e\u0432\u0435 \u041c\u043e\u0441\u0442\u0438"
    ],
    "wof:name":"Nowe Mosty",
    "wof:placetype":"locality"
},
  "geometry": {"coordinates":[19.01836,53.51786],"type":"Point"}
}