{
  "type": "Feature",
  "properties": {
    "gn:admin1_code":"77.0",
    "gn:admin2_code":"1216.0",
    "gn:admin3_code":"121605.0",
    "gn:asciiname":"Wal Ruda",
    "gn:country_code":"PL",
    "gn:dem":183,
    "gn:feature_class":"P",
    "gn:feature_code":"PPL",
    "gn:name":"Wa\u0142 Ruda",
    "gn:population":0,
    "gn:timezone":"Europe/Warsaw",
    "iso:country":"PL",
    "name:azb_x_preferred":[
        "\u0648\u0627\u0648-\u0631\u0648\u062f\u0627"
    ],
    "name:ces_x_preferred":[
        "Wa\u0142-Ruda"
    ],
    "name:fas_x_preferred":[
        "\u0648\u0627\u0648-\u0631\u0648\u062f\u0627"
    ],
    "name:fra_x_preferred":[
        "Wa\u0142-Ruda"
    ],
    "name:pol_x_preferred":[
        "Wa\u0142-Ruda"
    ],
    "name:rus_x_preferred":[
        "\u0412\u0430\u043b-\u0420\u0443\u0434\u0430"
    ],
    "name:szl_x_preferred":[
        "Wa\u0142-Ruda"
    ],
    "name:ukr_x_preferred":[
        "\u0412\u0430\u043b-\u0420\u0443\u0434\u0430"
    ],
    "name:und_x_variant":[
        "Wa\u0142 Ruda"
    ],
    "wof:name":"Wal Ruda",
    "wof:placetype":"locality"
},
  "geometry": {"coordinates":[20.79839,50.11224],"type":"Point"}
}