{
  "type": "Feature",
  "properties": {
    "gn:admin1_code":"77.0",
    "gn:admin2_code":"1216.0",
    "gn:admin3_code":"121605.0",
    "gn:asciiname":"Wal Ruda",
    "gn:country_code":"PL",
    "gn:dem":183,
    "gn:feature_class":"P",
    "gn:feature_code":"PPL",
    "gn:name":"Wa\u0142 Ruda",
    "gn:population":0,
    "gn:timezone":"Europe/Warsaw",
    "iso:country":"PL",
    "name:und_x_variant":[
        "Wa\u0142 Ruda"
    ],
    "wof:name":"Wal Ruda",
    "wof:placetype":"locality"
},
  "geometry": {"coordinates":[20.79839,50.11224],"type":"Point"}
}