{
  "type": "Feature",
  "properties": {
    "gn:admin1_code":"85.0",
    "gn:admin2_code":"2811.0",
    "gn:admin3_code":"281102.0",
    "gn:asciiname":"Zembrzus Mokry Grunt",
    "gn:cc2":"PL",
    "gn:country_code":"PL",
    "gn:dem":141,
    "gn:feature_class":"P",
    "gn:feature_code":"PPL",
    "gn:name":"Zembrzus Mokry Grunt",
    "gn:population":0,
    "gn:timezone":"Europe/Warsaw",
    "iso:country":"PL",
    "name:fra_x_preferred":[
        "Zembrzus-Mokry Grunt"
    ],
    "name:pol_x_preferred":[
        "Zembrzus-Mokry Grunt"
    ],
    "name:ukr_x_preferred":[
        "\u0417\u0435\u043c\u0431\u0436\u0443\u0441-\u041c\u043e\u043a\u0440\u0438-\u0490\u0440\u0443\u043d\u0442"
    ],
    "name:und_x_variant":[
        "Zembrus Mokry Grunt",
        "Zembrzus Mokry Grunt"
    ],
    "wof:name":"Zembrzus Mokry Grunt",
    "wof:placetype":"locality"
},
  "geometry": {"coordinates":[20.64537,53.28051],"type":"Point"}
}