{
  "type": "Feature",
  "properties": {
    "gn:admin1_code":"85.0",
    "gn:admin2_code":"2811.0",
    "gn:admin3_code":"281102.0",
    "gn:asciiname":"Zembrzus Mokry Grunt",
    "gn:cc2":"PL",
    "gn:country_code":"PL",
    "gn:dem":141,
    "gn:feature_class":"P",
    "gn:feature_code":"PPL",
    "gn:name":"Zembrzus Mokry Grunt",
    "gn:population":0,
    "gn:timezone":"Europe/Warsaw",
    "iso:country":"PL",
    "name:und_x_variant":[
        "Zembrus Mokry Grunt",
        "Zembrzus Mokry Grunt"
    ],
    "wof:name":"Zembrzus Mokry Grunt",
    "wof:placetype":"locality"
},
  "geometry": {"coordinates":[20.64537,53.28051],"type":"Point"}
}