{
  "type": "Feature",
  "properties": {
    "gn:admin1_code":"78.0",
    "gn:admin2_code":"1424.0",
    "gn:admin3_code":"142406.0",
    "gn:asciiname":"Gorki Duze",
    "gn:country_code":"PL",
    "gn:dem":127,
    "gn:feature_class":"P",
    "gn:feature_code":"PPL",
    "gn:name":"G\u00f3rki Du\u017ce",
    "gn:population":0,
    "gn:timezone":"Europe/Warsaw",
    "iso:country":"PL",
    "name:fra_x_preferred":[
        "G\u00f3rki Du\u017ce"
    ],
    "name:pol_x_preferred":[
        "G\u00f3rki Du\u017ce"
    ],
    "name:ukr_x_preferred":[
        "\u0490\u0443\u0440\u043a\u0456-\u0414\u0443\u0436\u0435"
    ],
    "wof:name":"Gorki Duze",
    "wof:placetype":"locality"
},
  "geometry": {"coordinates":[20.87122,52.63397],"type":"Point"}
}