{
  "type": "Feature",
  "properties": {
    "gn:admin1_code":"78.0",
    "gn:admin2_code":"1424.0",
    "gn:admin3_code":"142406.0",
    "gn:asciiname":"Gorki Duze",
    "gn:country_code":"PL",
    "gn:dem":127,
    "gn:feature_class":"P",
    "gn:feature_code":"PPL",
    "gn:name":"G\u00f3rki Du\u017ce",
    "gn:population":0,
    "gn:timezone":"Europe/Warsaw",
    "iso:country":"PL",
    "name:und_x_variant":[
        "G\u00f3rki Du\u017ce"
    ],
    "wof:name":"Gorki Duze",
    "wof:placetype":"locality"
},
  "geometry": {"coordinates":[20.87122,52.63397],"type":"Point"}
}