{
  "type": "Feature",
  "properties": {
    "gn:admin1_code":"73.0",
    "gn:admin2_code":"408.0",
    "gn:admin3_code":"40809.0",
    "gn:asciiname":"Rumunki Czarne",
    "gn:country_code":"PL",
    "gn:dem":109,
    "gn:feature_class":"P",
    "gn:feature_code":"PPL",
    "gn:name":"Rumunki Czarne",
    "gn:population":0,
    "gn:timezone":"Europe/Warsaw",
    "iso:country":"PL",
    "name:und_x_variant":[
        "Czerskie",
        "Rumunki Czerskie",
        "Rumunki Czarne"
    ],
    "wof:name":"Rumunki Czarne",
    "wof:placetype":"locality"
},
  "geometry": {"coordinates":[19.23516,52.7821],"type":"Point"}
}