{
  "type": "Feature",
  "properties": {
    "gn:admin1_code":"81.0",
    "gn:admin2_code":"2005.0",
    "gn:admin3_code":"200503.0",
    "gn:asciiname":"Wolka Terechowska",
    "gn:country_code":"PL",
    "gn:dem":178,
    "gn:feature_class":"P",
    "gn:feature_code":"PPL",
    "gn:name":"W\u00f3lka Terechowska",
    "gn:population":0,
    "gn:timezone":"Europe/Warsaw",
    "iso:country":"PL",
    "name:und_x_variant":[
        "W\u00f3lka Terechowska"
    ],
    "wof:name":"Wolka Terechowska",
    "wof:placetype":"locality"
},
  "geometry": {"coordinates":[23.39138,52.51875],"type":"Point"}
}