{
  "type": "Feature",
  "properties": {
    "gn:admin1_code":"81.0",
    "gn:admin2_code":"2005.0",
    "gn:admin3_code":"200503.0",
    "gn:asciiname":"Wolka Terechowska",
    "gn:country_code":"PL",
    "gn:dem":178,
    "gn:feature_class":"P",
    "gn:feature_code":"PPL",
    "gn:name":"W\u00f3lka Terechowska",
    "gn:population":0,
    "gn:timezone":"Europe/Warsaw",
    "iso:country":"PL",
    "name:azb_x_preferred":[
        "\u0648\u0648\u0644\u06a9\u0627 \u062a\u0631\u062e\u0648\u0648\u0633\u06a9\u0627"
    ],
    "name:fas_x_preferred":[
        "\u0648\u0648\u0644\u06a9\u0627 \u062a\u0631\u062e\u0648\u0648\u0633\u06a9\u0627"
    ],
    "name:fra_x_preferred":[
        "W\u00f3lka Terechowska"
    ],
    "name:lit_x_preferred":[
        "Vulka Terechovska"
    ],
    "name:pol_x_preferred":[
        "W\u00f3lka Terechowska"
    ],
    "name:ukr_x_preferred":[
        "\u0412\u0443\u043b\u044c\u043a\u0430-\u0422\u0435\u0440\u0435\u0445\u043e\u0432\u0441\u044c\u043a\u0430"
    ],
    "name:und_x_variant":[
        "W\u00f3lka Terechowska"
    ],
    "wof:name":"Wolka Terechowska",
    "wof:placetype":"locality"
},
  "geometry": {"coordinates":[23.39138,52.51875],"type":"Point"}
}