{
  "type": "Feature",
  "properties": {
    "gn:admin1_code":"74.0",
    "gn:admin2_code":"1012.0",
    "gn:admin3_code":"101212.0",
    "gn:asciiname":"Kietlin",
    "gn:country_code":"PL",
    "gn:dem":231,
    "gn:feature_class":"P",
    "gn:feature_code":"PPL",
    "gn:name":"Kietlin",
    "gn:population":0,
    "gn:timezone":"Europe/Warsaw",
    "iso:country":"PL",
    "name:fra_x_preferred":[
        "Kietlin"
    ],
    "name:pol_x_preferred":[
        "Kietlin"
    ],
    "name:ukr_x_preferred":[
        "\u041a\u0435\u0442\u043b\u0456\u043d"
    ],
    "name:und_x_variant":[
        "Kietlin-Kolonia"
    ],
    "wof:name":"Kietlin",
    "wof:placetype":"neighbourhood"
},
  "geometry": {"coordinates":[19.50898,51.08877],"type":"Point"}
}