{
  "type": "Feature",
  "properties": {
    "gn:country":"PL",
    "gn:fcode":"PPL",
    "gn:population":441,
    "iso:country":"PL",
    "name:ast_x_preferred":[
        "Wielka Wie\u015b"
    ],
    "name:azb_x_preferred":[
        "\u0648\u06cc\u0644\u06a9\u0627 \u0648\u06cc\u0634"
    ],
    "name:ceb_x_preferred":[
        "Wielka Wie\u015b"
    ],
    "name:csb_x_preferred":[
        "Wi\u00f4lg\u00f4 Wies"
    ],
    "name:deu_x_preferred":[
        "Wielka Wie\u015b"
    ],
    "name:eng_x_preferred":[
        "Wielka Wie\u015b"
    ],
    "name:fas_x_preferred":[
        "\u0648\u06cc\u0644\u06a9\u0627 \u0648\u06cc\u0634"
    ],
    "name:fra_x_preferred":[
        "Wielka Wie\u015b"
    ],
    "name:pol_x_preferred":[
        "Wielka Wie\u015b"
    ],
    "name:ukr_x_preferred":[
        "\u0412\u0435\u043b\u0438\u043a\u0430 \u0412\u0435\u0441\u044c"
    ],
    "qs_pg:aaroncc":"PL",
    "qs_pg:gn_country":"PL",
    "qs_pg:gn_fcode":"PPL",
    "qs_pg:gn_pop":441,
    "qs_pg:name":"Wielka Wie\u015b",
    "qs_pg:name_adm0":"Polska",
    "qs_pg:name_adm1":"Pomorskie",
    "qs_pg:photos_9r":0,
    "qs_pg:photos_sr":0,
    "qs_pg:pop_sr":2,
    "qs_pg:qs_pg_placetype":"locality",
    "qs_pg:qs_pg_placetype_gp":"Town",
    "qs_pg:woe_adm0":23424923,
    "woe:adm0_id":23424923,
    "woe:name_adm0":"Polska",
    "woe:name_adm1":"Pomorskie",
    "woe:placetype":"Town",
    "wof:name":"Wielka Wie\u015b",
    "wof:placetype":"locality",
    "wof:population":441
},
  "geometry": {"coordinates":[17.3608,54.56908],"type":"Point"}
}