{
  "type": "Feature",
  "properties": {
    "gn:admin1_code":"80.0",
    "gn:admin2_code":"1813.0",
    "gn:admin3_code":"181308.0",
    "gn:asciiname":"Nehrybka",
    "gn:country_code":"PL",
    "gn:dem":203,
    "gn:feature_class":"P",
    "gn:feature_code":"PPL",
    "gn:name":"Nehrybka",
    "gn:population":0,
    "gn:timezone":"Europe/Warsaw",
    "iso:country":"PL",
    "name:ceb_x_preferred":[
        "Nehrybka"
    ],
    "name:pol_x_preferred":[
        "Nehrybka"
    ],
    "name:ukr_x_preferred":[
        "\u041d\u0435\u0433\u0440\u0438\u0431\u043a\u0430"
    ],
    "wof:name":"Nehrybka",
    "wof:placetype":"locality"
},
  "geometry": {"coordinates":[22.80607,49.75155],"type":"Point"}
}