{
  "type": "Feature",
  "properties": {
    "gn:admin1_code":"74.0",
    "gn:admin2_code":"1014.0",
    "gn:admin3_code":"101408.0",
    "gn:asciiname":"Mecka Wola",
    "gn:country_code":"PL",
    "gn:dem":155,
    "gn:feature_class":"P",
    "gn:feature_code":"PPL",
    "gn:name":"M\u0119cka Wola",
    "gn:population":0,
    "gn:timezone":"Europe/Warsaw",
    "iso:country":"PL",
    "name:pol_x_preferred":[
        "M\u0119cka Wola"
    ],
    "name:ukr_x_preferred":[
        "\u041c\u0435\u043d\u0446\u044c\u043a\u0430-\u0412\u043e\u043b\u044f"
    ],
    "name:und_x_variant":[
        "M\u0119cka Wola"
    ],
    "wof:name":"Mecka Wola",
    "wof:placetype":"locality"
},
  "geometry": {"coordinates":[18.82585,51.61206],"type":"Point"}
}