{
  "type": "Feature",
  "properties": {
    "gn:admin1_code":"82.0",
    "gn:admin2_code":"2215.0",
    "gn:admin3_code":"221508.0",
    "gn:asciiname":"Bozepole Male",
    "gn:country_code":"PL",
    "gn:dem":45,
    "gn:feature_class":"P",
    "gn:feature_code":"PPL",
    "gn:name":"Bo\u017aepole Ma\u0142e",
    "gn:population":0,
    "gn:timezone":"Europe/Warsaw",
    "iso:country":"PL",
    "name:und_x_variant":[
        "Bo\u017aepole Ma\u0142e"
    ],
    "wof:name":"Bozepole Male",
    "wof:placetype":"locality"
},
  "geometry": {"coordinates":[17.98103,54.56672],"type":"Point"}
}