{
  "type": "Feature",
  "properties": {
    "gn:admin1_code":"82.0",
    "gn:admin2_code":"2215.0",
    "gn:admin3_code":"221508.0",
    "gn:asciiname":"Bozepole Male",
    "gn:country_code":"PL",
    "gn:dem":45,
    "gn:feature_class":"P",
    "gn:feature_code":"PPL",
    "gn:name":"Bo\u017aepole Ma\u0142e",
    "gn:population":0,
    "gn:timezone":"Europe/Warsaw",
    "iso:country":"PL",
    "name:azb_x_preferred":[
        "\u0628\u0648\u0698\u067e\u0648\u0644\u0647 \u0645\u0627\u0648\u0647"
    ],
    "name:csb_x_preferred":[
        "M\u00f4\u0142\u00e9 B\u00f2\u017c\u00e9 P\u00f2l\u00e9"
    ],
    "name:fas_x_preferred":[
        "\u0628\u0648\u0698\u067e\u0648\u0644\u0647 \u0645\u0627\u0648\u0647"
    ],
    "name:nld_x_preferred":[
        "Bo\u017cepole Ma\u0142e"
    ],
    "name:pol_x_preferred":[
        "Bo\u017cepole Ma\u0142e"
    ],
    "name:und_x_variant":[
        "Bo\u017aepole Ma\u0142e"
    ],
    "wof:name":"Bozepole Male",
    "wof:placetype":"locality"
},
  "geometry": {"coordinates":[17.98103,54.56672],"type":"Point"}
}