{
  "type": "Feature",
  "properties": {
    "gn:admin1_code":"87.0",
    "gn:admin2_code":"3213.0",
    "gn:admin3_code":"321306.0",
    "gn:asciiname":"Gwiazdowo",
    "gn:country_code":"PL",
    "gn:dem":54,
    "gn:feature_class":"P",
    "gn:feature_code":"PPL",
    "gn:name":"Gwiazdowo",
    "gn:population":0,
    "gn:timezone":"Europe/Warsaw",
    "iso:country":"PL",
    "name:ceb_x_preferred":[
        "Gwiazdowo"
    ],
    "name:deu_x_preferred":[
        "Gwiazdowo"
    ],
    "name:pol_x_preferred":[
        "Gwiazdowo"
    ],
    "name:ukr_x_preferred":[
        "\u0490\u0432\u044f\u0437\u0434\u043e\u0432\u043e"
    ],
    "name:vie_x_preferred":[
        "Gwiazdowo"
    ],
    "wof:name":"Gwiazdowo",
    "wof:placetype":"locality"
},
  "geometry": {"coordinates":[16.74744,54.30833000000001],"type":"Point"}
}