{
  "type": "Feature",
  "properties": {
    "gn:admin1_code":"84.0",
    "gn:admin2_code":"2608.0",
    "gn:admin3_code":"260804.0",
    "gn:asciiname":"Krzyzanowice Srednie",
    "gn:country_code":"PL",
    "gn:dem":201,
    "gn:feature_class":"P",
    "gn:feature_code":"PPL",
    "gn:name":"Krzy\u017canowice \u015arednie",
    "gn:population":0,
    "gn:timezone":"Europe/Warsaw",
    "iso:country":"PL",
    "name:pol_x_preferred":[
        "Krzy\u017canowice \u015arednie"
    ],
    "name:ukr_x_preferred":[
        "\u041a\u0448\u0438\u0436\u0430\u043d\u043e\u0432\u0456\u0446\u0435-\u0421\u0435\u0440\u0435\u0434\u043d\u0456"
    ],
    "wof:name":"Krzyzanowice Srednie",
    "wof:placetype":"locality"
},
  "geometry": {"coordinates":[20.55902,50.46054],"type":"Point"}
}