{
  "type": "Feature",
  "properties": {
    "gn:admin1_code":"74.0",
    "gn:admin2_code":"1010.0",
    "gn:admin3_code":"101009.0",
    "gn:asciiname":"Poniatow",
    "gn:country_code":"PL",
    "gn:dem":193,
    "gn:feature_class":"P",
    "gn:feature_code":"PPL",
    "gn:name":"Poniat\u00f3w",
    "gn:population":0,
    "gn:timezone":"Europe/Warsaw",
    "iso:country":"PL",
    "name:fra_x_preferred":[
        "Poniat\u00f3w"
    ],
    "name:pol_x_preferred":[
        "Poniat\u00f3w"
    ],
    "name:ukr_x_preferred":[
        "\u041f\u043e\u043d\u044f\u0442\u0443\u0432"
    ],
    "wof:name":"Poniatow",
    "wof:placetype":"locality"
},
  "geometry": {"coordinates":[19.76612,51.38978],"type":"Point"}
}