{
  "type": "Feature",
  "properties": {
    "iso:country":"PL",
    "name:azb_x_preferred":[
        "\u0642\u0645\u06cc\u0646\u0627 \u0634\u0631\u067e\u062a\u0633"
    ],
    "name:bel_x_preferred":[
        "\u0421\u0435\u0440\u043f\u0446"
    ],
    "name:deu_x_preferred":[
        "Sierpc"
    ],
    "name:eus_x_preferred":[
        "Sierpc landa-udalerria"
    ],
    "name:fas_x_preferred":[
        "\u06af\u0645\u06cc\u0646\u0627 \u0634\u0631\u067e\u062a\u0633"
    ],
    "name:fra_x_preferred":[
        "Sierpc"
    ],
    "name:ita_x_preferred":[
        "Sierpc"
    ],
    "name:nld_x_preferred":[
        "Sierpc"
    ],
    "name:pol_x_preferred":[
        "Sierpc"
    ],
    "name:rus_x_preferred":[
        "\u0421\u0435\u0440\u043f\u0446"
    ],
    "name:slk_x_preferred":[
        "Gmina Sierpc"
    ],
    "name:ukr_x_preferred":[
        "\u0413\u043c\u0456\u043d\u0430 \u0421\u0435\u0440\u043f\u0446\u044c"
    ],
    "name:war_x_preferred":[
        "Gmina Sierpc"
    ],
    "qs_pg:aaroncc":"PL",
    "qs_pg:name":"Gmina Sierpc",
    "qs_pg:name_adm0":"Polska",
    "qs_pg:name_adm1":"Mazowieckie",
    "qs_pg:photos":3,
    "qs_pg:photos_1k":1,
    "qs_pg:photos_9k":1,
    "qs_pg:photos_9r":1,
    "qs_pg:photos_all":22,
    "qs_pg:photos_sr":1,
    "qs_pg:pop_sr":0,
    "qs_pg:qs_pg_placetype":"localadmin",
    "qs_pg:qs_pg_placetype_gp":"LocalAdmin",
    "qs_pg:woe_adm0":23424923,
    "woe:adm0_id":23424923,
    "woe:name_adm0":"Polska",
    "woe:name_adm1":"Mazowieckie",
    "woe:placetype":"LocalAdmin",
    "wof:name":"Gmina Sierpc",
    "wof:placetype":"localadmin"
},
  "geometry": {"coordinates":[19.631666,52.863666],"type":"Point"}
}