{
  "type": "Feature",
  "properties": {
    "gn:admin1_code":"77",
    "gn:admin2_code":"1207",
    "gn:admin3_code":"120709.0",
    "gn:asciiname":"Kasinka Mala",
    "gn:country_code":"PL",
    "gn:dem":368,
    "gn:elevation":"0.0",
    "gn:feature_class":"P",
    "gn:feature_code":"PPL",
    "gn:name":"Kasinka Mala",
    "gn:population":0,
    "gn:timezone":"Europe/Warsaw",
    "iso:country":"PL",
    "wof:name":"Kasinka Mala",
    "wof:placetype":"locality"
},
  "geometry": {"coordinates":[20.03553,49.70361],"type":"Point"}
}