{
  "type": "Feature",
  "properties": {
    "gn:admin1_code":"72.0",
    "gn:admin2_code":"224.0",
    "gn:admin3_code":"22406.0",
    "gn:asciiname":"Starczowek",
    "gn:country_code":"PL",
    "gn:dem":263,
    "gn:feature_class":"P",
    "gn:feature_code":"PPL",
    "gn:name":"Starcz\u00f3wek",
    "gn:population":0,
    "gn:timezone":"Europe/Warsaw",
    "iso:country":"PL",
    "name:pol_x_preferred":[
        "Starcz\u00f3wek"
    ],
    "name:ukr_x_preferred":[
        "\u0421\u0442\u0430\u0440\u0447\u0443\u0432\u0435\u043a"
    ],
    "wof:name":"Starczowek",
    "wof:placetype":"locality"
},
  "geometry": {"coordinates":[17.05112,50.55162],"type":"Point"}
}