{
  "type": "Feature",
  "properties": {
    "gn:admin1_code":"80.0",
    "gn:admin2_code":"1802.0",
    "gn:admin3_code":"180202.0",
    "gn:asciiname":"Katy",
    "gn:country_code":"PL",
    "gn:dem":418,
    "gn:feature_class":"P",
    "gn:feature_code":"PPL",
    "gn:name":"K\u0105ty",
    "gn:population":0,
    "gn:timezone":"Europe/Warsaw",
    "iso:country":"PL",
    "name:ceb_x_preferred":[
        "Katy"
    ],
    "name:deu_x_preferred":[
        "Katy"
    ],
    "name:fra_x_preferred":[
        "Katy"
    ],
    "name:ita_x_preferred":[
        "Katy"
    ],
    "name:jpn_x_preferred":[
        "\u30b1\u30a4\u30c6\u30a3"
    ],
    "name:kor_x_preferred":[
        "\ucf00\uc774\ud2f0"
    ],
    "name:nno_x_preferred":[
        "Katy"
    ],
    "name:pol_x_preferred":[
        "Katy"
    ],
    "name:por_x_preferred":[
        "Katy"
    ],
    "name:srp_x_preferred":[
        "\u041a\u0435\u0458\u0442\u0438"
    ],
    "wof:name":"Katy",
    "wof:placetype":"locality"
},
  "geometry": {"coordinates":[21.96667,49.81667],"type":"Point"}
}