{
  "type": "Feature",
  "properties": {
    "gn:gn_country":"PL",
    "gn:gn_fcode":"PPLA2",
    "gn:gn_pop":20261,
    "gn:population":20261,
    "iso:country":"PL",
    "name:bul_x_preferred":[
        "\u0422\u043e\u043c\u0430\u0448\u043e\u0432 \u041b\u044e\u0431\u0435\u043b\u0441\u043a\u0438"
    ],
    "name:heb_x_preferred":[
        "\u05d8\u05d5\u05de\u05e9\u05d5\u05d1 \u05dc\u05d5\u05d1\u05dc\u05e1\u05e7\u05d9"
    ],
    "name:jpn_x_preferred":[
        "\u30c8\u30de\u30b7\u30e5\u30d5\u30fb\u30eb\u30d9\u30eb\u30b9\u30ad"
    ],
    "name:lav_x_preferred":[
        "Toma\u0161ova Lubelska"
    ],
    "name:lit_x_preferred":[
        "Liublino Toma\u0161uvas"
    ],
    "name:rus_x_preferred":[
        "\u0422\u043e\u043c\u0430\u0448\u0443\u0432-\u041b\u044e\u0431\u0435\u043b\u044c\u0441\u043a\u0438"
    ],
    "name:rus_x_variant":[
        "\u0422\u043e\u043c\u0430\u0448\u0443\u0432-\u041b\u044e\u0431\u0435\u043b\u044c\u0441\u043a\u0438\u0439"
    ],
    "name:srp_x_preferred":[
        "\u0422\u043e\u043c\u0430\u0448\u043e\u0432 \u041b\u0443\u0431\u0435\u043b\u0441\u043a\u0438"
    ],
    "name:ukr_x_preferred":[
        "\u0422\u043e\u043c\u0430\u0448\u0456\u0432"
    ],
    "name:unk_x_variant":[
        "Tomasz\u00f3w"
    ],
    "name:yid_x_preferred":[
        "\u05d8\u05d0\u05de\u05d0\u05e9\u05d0\u05d5\u05d5"
    ],
    "name:zho_x_preferred":[
        "\u76e7\u5e03\u6797\u5730\u5340\u6258\u99ac\u8212\u592b"
    ],
    "qs_pg:aaroncc":"PL",
    "qs_pg:gn_country":"PL",
    "qs_pg:gn_fcode":"PPLA2",
    "qs_pg:gn_pop":20261,
    "qs_pg:name":"Tomaszow Lubelski",
    "qs_pg:name_adm0":"Polska",
    "qs_pg:name_adm1":"Lubelskie",
    "qs_pg:photos_9k":1,
    "qs_pg:photos_9r":1,
    "qs_pg:photos_all":5,
    "qs_pg:photos_sr":0,
    "qs_pg:pop_sr":7,
    "qs_pg:qs_pg_placetype":"locality",
    "qs_pg:qs_pg_placetype_gp":"Town",
    "qs_pg:woe_adm0":23424923,
    "woe:adm0_id":23424923,
    "woe:name_adm0":"Polska",
    "woe:name_adm1":"Lubelskie",
    "woe:placetype":"Town",
    "wof:name":"Tomaszow Lubelski",
    "wof:placetype":"locality",
    "wof:population":20261
},
  "geometry": {"coordinates":[23.41616,50.44767],"type":"Point"}
}