{
  "type": "Feature",
  "properties": {
    "gn:admin1_code":"75.0",
    "gn:admin2_code":"620.0",
    "gn:admin3_code":"62003.0",
    "gn:asciiname":"Huta Komarowska",
    "gn:country_code":"PL",
    "gn:dem":301,
    "gn:feature_class":"P",
    "gn:feature_code":"PPL",
    "gn:name":"Huta Komarowska",
    "gn:population":0,
    "gn:timezone":"Europe/Warsaw",
    "iso:country":"PL",
    "name:und_x_variant":[
        "Komarowska Huta",
        "Huta Komarowska"
    ],
    "wof:name":"Huta Komarowska",
    "wof:placetype":"locality"
},
  "geometry": {"coordinates":[23.40547,50.60303],"type":"Point"}
}