{
  "type": "Feature",
  "properties": {
    "gn:admin1_code":"75.0",
    "gn:admin2_code":"620.0",
    "gn:admin3_code":"62003.0",
    "gn:asciiname":"Huta Komarowska",
    "gn:country_code":"PL",
    "gn:dem":301,
    "gn:feature_class":"P",
    "gn:feature_code":"PPL",
    "gn:name":"Huta Komarowska",
    "gn:population":0,
    "gn:timezone":"Europe/Warsaw",
    "iso:country":"PL",
    "name:fra_x_preferred":[
        "Huta Komarowska"
    ],
    "name:pol_x_preferred":[
        "Huta Komarowska"
    ],
    "name:ukr_x_preferred":[
        "\u0413\u0443\u0442\u0430-\u041a\u043e\u043c\u0430\u0440\u043e\u0432\u0441\u044c\u043a\u0430"
    ],
    "name:und_x_variant":[
        "Komarowska Huta"
    ],
    "wof:name":"Huta Komarowska",
    "wof:placetype":"locality"
},
  "geometry": {"coordinates":[23.40547,50.60303],"type":"Point"}
}