{
  "type": "Feature",
  "properties": {
    "gn:admin1_code":"87.0",
    "gn:admin2_code":"3216.0",
    "gn:admin3_code":"321603.0",
    "gn:asciiname":"Ogartowo",
    "gn:country_code":"PL",
    "gn:dem":79,
    "gn:feature_class":"P",
    "gn:feature_code":"PPL",
    "gn:name":"Ogartowo",
    "gn:population":0,
    "gn:timezone":"Europe/Warsaw",
    "iso:country":"PL",
    "name:deu_x_preferred":[
        "Ogartowo"
    ],
    "name:pol_x_preferred":[
        "Ogartowo"
    ],
    "name:ukr_x_preferred":[
        "\u041e\u0491\u0430\u0440\u0442\u043e\u0432\u043e"
    ],
    "name:vie_x_preferred":[
        "Ogartowo"
    ],
    "wof:name":"Ogartowo",
    "wof:placetype":"locality"
},
  "geometry": {"coordinates":[16.13709,53.76848],"type":"Point"}
}