{
  "type": "Feature",
  "properties": {
    "gn:admin1_code":"87.0",
    "gn:admin2_code":"3207.0",
    "gn:admin3_code":"320703.0",
    "gn:asciiname":"Buniewice",
    "gn:country_code":"PL",
    "gn:dem":2,
    "gn:feature_class":"P",
    "gn:feature_code":"PPL",
    "gn:name":"Buniewice",
    "gn:population":0,
    "gn:timezone":"Europe/Warsaw",
    "iso:country":"PL",
    "name:ceb_x_preferred":[
        "Buniewice"
    ],
    "name:deu_x_preferred":[
        "Buniewice"
    ],
    "name:pol_x_preferred":[
        "Buniewice"
    ],
    "name:ukr_x_preferred":[
        "\u0411\u0443\u043d\u0435\u0432\u0456\u0446\u0435"
    ],
    "name:vie_x_preferred":[
        "Buniewice"
    ],
    "wof:name":"Buniewice",
    "wof:placetype":"locality"
},
  "geometry": {"coordinates":[14.72271,53.97265],"type":"Point"}
}