{
  "type": "Feature",
  "properties": {
    "gn:country":"PL",
    "gn:fcode":"PPLA3",
    "gn:population":3087,
    "iso:country":"PL",
    "name:azb_x_preferred":[
        "\u067e\u06cc\u0634\u0686\u0627\u062a\u0633"
    ],
    "name:fas_x_preferred":[
        "\u067e\u06cc\u0634\u0686\u0627\u062a\u0633"
    ],
    "name:fra_x_preferred":[
        "Piszczac"
    ],
    "name:heb_x_preferred":[
        "\u05e4\u05d9\u05e9\u05e6'\u05e5"
    ],
    "name:lit_x_preferred":[
        "Pi\u0161\u010dacas"
    ],
    "name:nld_x_preferred":[
        "Piszczac"
    ],
    "name:pol_x_preferred":[
        "Piszczac"
    ],
    "name:ukr_x_preferred":[
        "\u041f\u0456\u0449\u0430\u0446\u044c"
    ],
    "qs_pg:aaroncc":"PL",
    "qs_pg:gn_country":"PL",
    "qs_pg:gn_fcode":"PPLA3",
    "qs_pg:gn_pop":3087,
    "qs_pg:name":"Piszczac",
    "qs_pg:name_adm0":"Polska",
    "qs_pg:name_adm1":"Lubelskie",
    "qs_pg:photos_9k":1,
    "qs_pg:photos_9r":1,
    "qs_pg:photos_all":6,
    "qs_pg:photos_sr":0,
    "qs_pg:pop_sr":4,
    "qs_pg:qs_pg_placetype":"localadmin",
    "qs_pg:qs_pg_placetype_gp":"LocalAdmin",
    "qs_pg:woe_adm0":23424923,
    "woe:adm0_id":23424923,
    "woe:name_adm0":"Polska",
    "woe:name_adm1":"Lubelskie",
    "woe:placetype":"LocalAdmin",
    "wof:name":"Piszczac",
    "wof:placetype":"localadmin",
    "wof:population":3087
},
  "geometry": {"coordinates":[23.37719,51.98118],"type":"Point"}
}