{
  "type": "Feature",
  "properties": {
    "iso:country":"PL",
    "name:pol_x_preferred":[
        "Nowa Sucha"
    ],
    "wof:name":"Nowa Sucha",
    "wof:placetype":"locality"
},
  "geometry": {"coordinates":[20.2101031633609,52.1545945717651],"type":"Point"}
}