{
  "type": "Feature",
  "properties": {
    "gn:admin1_code":"84.0",
    "gn:admin2_code":"2613.0",
    "gn:admin3_code":"261306.0",
    "gn:asciiname":"Kolonia Boczkowice",
    "gn:country_code":"PL",
    "gn:dem":253,
    "gn:feature_class":"P",
    "gn:feature_code":"PPL",
    "gn:name":"Kolonia Boczkowice",
    "gn:population":0,
    "gn:timezone":"Europe/Warsaw",
    "iso:country":"PL",
    "wof:name":"Kolonia Boczkowice",
    "wof:placetype":"locality"
},
  "geometry": {"coordinates":[20.05,50.76667],"type":"Point"}
}