{
  "type": "Feature",
  "properties": {
    "gn:admin1_code":"81.0",
    "gn:admin2_code":"2002.0",
    "gn:admin3_code":"200212.0",
    "gn:asciiname":"Rzedziany",
    "gn:country_code":"PL",
    "gn:dem":112,
    "gn:feature_class":"P",
    "gn:feature_code":"PPL",
    "gn:name":"Rz\u0119dziany",
    "gn:population":0,
    "gn:timezone":"Europe/Warsaw",
    "iso:country":"PL",
    "name:fra_x_preferred":[
        "Rz\u0119dziany"
    ],
    "name:lit_x_preferred":[
        "\u017dendzianai"
    ],
    "name:pol_x_preferred":[
        "Rz\u0119dziany"
    ],
    "name:ukr_x_preferred":[
        "\u0416\u0435\u043d\u0434\u0437\u044f\u043d\u0438"
    ],
    "wof:name":"Rzedziany",
    "wof:placetype":"locality"
},
  "geometry": {"coordinates":[22.86906,53.15331],"type":"Point"}
}