{
  "type": "Feature",
  "properties": {
    "gn:admin1_code":"86.0",
    "gn:admin2_code":"3011.0",
    "gn:admin3_code":"301105.0",
    "gn:asciiname":"Karmin",
    "gn:country_code":"PL",
    "gn:dem":92,
    "gn:feature_class":"P",
    "gn:feature_code":"PPL",
    "gn:name":"Karmin",
    "gn:population":0,
    "gn:timezone":"Europe/Warsaw",
    "iso:country":"PL",
    "name:fra_x_preferred":[
        "Karmin"
    ],
    "name:pol_x_preferred":[
        "Karmin"
    ],
    "name:ukr_x_preferred":[
        "\u041a\u0430\u0440\u043c\u0456\u043d"
    ],
    "wof:name":"Karmin",
    "wof:placetype":"locality"
},
  "geometry": {"coordinates":[16.6501,51.98133],"type":"Point"}
}