{
  "type": "Feature",
  "properties": {
    "gn:admin1_code":"87.0",
    "gn:admin2_code":"3204.0",
    "gn:admin3_code":"320404.0",
    "gn:asciiname":"Strzelewo",
    "gn:country_code":"PL",
    "gn:dem":44,
    "gn:feature_class":"P",
    "gn:feature_code":"PPL",
    "gn:name":"Strzelewo",
    "gn:population":0,
    "gn:timezone":"Europe/Warsaw",
    "iso:country":"PL",
    "name:pol_x_preferred":[
        "Strzelewo"
    ],
    "name:swe_x_preferred":[
        "Strzelewo"
    ],
    "name:ukr_x_preferred":[
        "\u0421\u0442\u0448\u0435\u043b\u0435\u0432\u043e"
    ],
    "wof:name":"Strzelewo",
    "wof:placetype":"locality"
},
  "geometry": {"coordinates":[15.00183,53.68065],"type":"Point"}
}