{
  "type": "Feature",
  "properties": {
    "gn:admin1_code":"81.0",
    "gn:admin2_code":"2011.0",
    "gn:admin3_code":"201107.0",
    "gn:asciiname":"Siderka",
    "gn:country_code":"PL",
    "gn:dem":135,
    "gn:feature_class":"P",
    "gn:feature_code":"PPL",
    "gn:name":"Siderka",
    "gn:population":0,
    "gn:timezone":"Europe/Warsaw",
    "iso:country":"PL",
    "name:fra_x_preferred":[
        "Siderka"
    ],
    "name:lit_x_preferred":[
        "Siderka"
    ],
    "name:pol_x_preferred":[
        "Siderka"
    ],
    "name:ukr_x_preferred":[
        "\u0421\u0456\u0434\u0435\u0440\u043a\u0430"
    ],
    "wof:name":"Siderka",
    "wof:placetype":"locality"
},
  "geometry": {"coordinates":[23.45953,53.59266],"type":"Point"}
}