{
  "type": "Feature",
  "properties": {
    "gn:admin1_code":"79.0",
    "gn:admin2_code":"1607.0",
    "gn:admin3_code":"160704.0",
    "gn:asciiname":"Sowin",
    "gn:country_code":"PL",
    "gn:dem":196,
    "gn:feature_class":"P",
    "gn:feature_code":"PPL",
    "gn:name":"Sowin",
    "gn:population":0,
    "gn:timezone":"Europe/Warsaw",
    "iso:country":"PL",
    "name:ceb_x_preferred":[
        "Sowin"
    ],
    "name:deu_x_preferred":[
        "Sowin"
    ],
    "name:pol_x_preferred":[
        "Sowin"
    ],
    "name:ukr_x_preferred":[
        "\u0421\u043e\u0432\u0456\u043d"
    ],
    "name:und_x_variant":[
        "Annahof",
        "\u017babina",
        "Sabine",
        "Awnahof",
        "Sowin"
    ],
    "wof:name":"Sowin",
    "wof:placetype":"locality"
},
  "geometry": {"coordinates":[17.6305,50.55116],"type":"Point"}
}