{
  "type": "Feature",
  "properties": {
    "iso:country":"PL",
    "name:ast_x_preferred":[
        "Bilsko"
    ],
    "name:eng_x_preferred":[
        "Bilsko"
    ],
    "name:fra_x_preferred":[
        "Bilsko"
    ],
    "name:pol_x_preferred":[
        "Bilsko"
    ],
    "name:ukr_x_preferred":[
        "\u0411\u0456\u043b\u044c\u0441\u044c\u043a\u043e"
    ],
    "qs:a0":"Rzeczpospolita Polska",
    "qs:a1":"*Malopolskie",
    "qs:a1r":"0",
    "qs:a2":"Nowosadecki",
    "qs:adm0":"Rzeczpospolita Polska",
    "qs:la_lc":"*",
    "qs:level":"locality",
    "qs:loc":"Bilsko",
    "qs:loc_alt":"Bilsko",
    "qs:pop":0,
    "qs:type":"buffered point",
    "wd:wordcount":93,
    "wof:name":"Bilsko",
    "wof:placetype":"locality"
},
  "geometry": {"coordinates":[20.638056,49.744526],"type":"Point"}
}