{
  "type": "Feature",
  "properties": {
    "gn:gn_country":"PL",
    "gn:gn_fcode":"PPL",
    "gn:gn_pop":0,
    "iso:country":"PL",
    "name:eng_x_preferred":[
        "Smerek"
    ],
    "name:fre_x_preferred":[
        "Smerek"
    ],
    "name:hun_x_preferred":[
        "Smerek"
    ],
    "name:per_x_preferred":[
        "\u0633\u0645\u0631\u06a9"
    ],
    "name:pol_x_preferred":[
        "Smerek"
    ],
    "name:rue_x_preferred":[
        "\u0421\u043c\u0435\u0440\u0435\u043a"
    ],
    "name:ukr_x_preferred":[
        "\u0421\u043c\u0435\u0440\u0435\u043a"
    ],
    "qs_pg:aaroncc":"PL",
    "qs_pg:gn_country":"PL",
    "qs_pg:gn_fcode":"PPL",
    "qs_pg:gn_pop":0,
    "qs_pg:name":"Smerek",
    "qs_pg:name_adm0":"Polska",
    "qs_pg:name_adm1":"Podkarpackie",
    "qs_pg:photos":24,
    "qs_pg:photos_1k":5,
    "qs_pg:photos_9k":1,
    "qs_pg:photos_9r":1,
    "qs_pg:photos_all":24,
    "qs_pg:photos_sr":1,
    "qs_pg:pop_sr":0,
    "qs_pg:qs_pg_placetype":"locality",
    "qs_pg:qs_pg_placetype_gp":"Town",
    "qs_pg:woe_adm0":23424923,
    "woe:adm0_id":23424923,
    "woe:name_adm0":"Polska",
    "woe:name_adm1":"Podkarpackie",
    "woe:placetype":"Town",
    "wof:name":"Smerek",
    "wof:placetype":"locality"
},
  "geometry": {"coordinates":[22.43906,49.1757],"type":"Point"}
}