{
  "type": "Feature",
  "properties": {
    "gn:admin1_code":"78.0",
    "gn:admin2_code":"1419.0",
    "gn:admin3_code":"141905.0",
    "gn:asciiname":"Nagorki Dobrskie",
    "gn:country_code":"PL",
    "gn:dem":128,
    "gn:feature_class":"P",
    "gn:feature_code":"PPL",
    "gn:name":"Nag\u00f3rki Dobrskie",
    "gn:population":0,
    "gn:timezone":"Europe/Warsaw",
    "iso:country":"PL",
    "name:ceb_x_preferred":[
        "Nag\u00f3rki Dobrskie"
    ],
    "name:fra_x_preferred":[
        "Nag\u00f3rki Dobrskie"
    ],
    "name:pol_x_preferred":[
        "Nag\u00f3rki Dobrskie"
    ],
    "name:ukr_x_preferred":[
        "\u041d\u0430\u0491\u0443\u0440\u043a\u0456-\u0414\u043e\u0431\u0440\u0441\u044c\u043a\u0456"
    ],
    "wof:name":"Nagorki Dobrskie",
    "wof:placetype":"locality"
},
  "geometry": {"coordinates":[20.04106,52.71136],"type":"Point"}
}