{
  "type": "Feature",
  "properties": {
    "gn:admin1_code":"73.0",
    "gn:admin2_code":"418.0",
    "gn:admin3_code":"41812.0",
    "gn:asciiname":"Golebin Parcele",
    "gn:country_code":"PL",
    "gn:dem":82,
    "gn:feature_class":"P",
    "gn:feature_code":"PPL",
    "gn:name":"Go\u0142\u0119bin Parcele",
    "gn:population":0,
    "gn:timezone":"Europe/Warsaw",
    "iso:country":"PL",
    "name:ita_x_preferred":[
        "Go\u0142\u0119bin-Wie\u015b"
    ],
    "name:pol_x_preferred":[
        "Go\u0142\u0119bin"
    ],
    "name:ukr_x_preferred":[
        "\u0490\u043e\u043b\u0435\u043c\u0431\u0456\u043d"
    ],
    "name:und_x_variant":[
        "Go\u0142\u0119bin Parcele"
    ],
    "wof:name":"Golebin Parcele",
    "wof:placetype":"locality"
},
  "geometry": {"coordinates":[18.91981,52.54916],"type":"Point"}
}