{
  "type": "Feature",
  "properties": {
    "gn:country":"PL",
    "gn:fcode":"PPL",
    "gn:population":1500,
    "iso:country":"PL",
    "name:ast_x_preferred":[
        "Krzywaczka"
    ],
    "name:azb_x_preferred":[
        "\u06a9\u0698\u0648\u0627\u0686\u06a9\u0627"
    ],
    "name:ceb_x_preferred":[
        "Krzywaczka"
    ],
    "name:deu_x_preferred":[
        "Krzywaczka"
    ],
    "name:eng_x_preferred":[
        "Krzywaczka"
    ],
    "name:fas_x_preferred":[
        "\u06a9\u0698\u0648\u0627\u0686\u06a9\u0627"
    ],
    "name:fra_x_preferred":[
        "Krzywaczka"
    ],
    "name:nan_x_preferred":[
        "Krzywaczka"
    ],
    "name:pol_x_preferred":[
        "Krzywaczka"
    ],
    "name:ukr_x_preferred":[
        "\u041a\u0448\u0438\u0432\u0430\u0447\u043a\u0430"
    ],
    "qs_pg:aaroncc":"PL",
    "qs_pg:gn_country":"PL",
    "qs_pg:gn_fcode":"PPL",
    "qs_pg:gn_pop":1500,
    "qs_pg:name":"Krzywaczka",
    "qs_pg:name_adm0":"Polska",
    "qs_pg:name_adm1":"Ma\u0142opolskie",
    "qs_pg:photos_9k":1,
    "qs_pg:photos_9r":1,
    "qs_pg:photos_all":10,
    "qs_pg:photos_sr":0,
    "qs_pg:pop_sr":3,
    "qs_pg:qs_pg_placetype":"locality",
    "qs_pg:qs_pg_placetype_gp":"Town",
    "qs_pg:woe_adm0":23424923,
    "woe:adm0_id":23424923,
    "woe:name_adm0":"Polska",
    "woe:name_adm1":"Ma\u0142opolskie",
    "woe:placetype":"Town",
    "wof:name":"Krzywaczka",
    "wof:placetype":"locality",
    "wof:population":1500
},
  "geometry": {"coordinates":[19.83221,49.89353],"type":"Point"}
}