{
  "type": "Feature",
  "properties": {
    "gn:admin1_code":"81.0",
    "gn:admin2_code":"2002.0",
    "gn:admin3_code":"200210.0",
    "gn:asciiname":"Koncewizna",
    "gn:country_code":"PL",
    "gn:dem":122,
    "gn:feature_class":"P",
    "gn:feature_code":"PPL",
    "gn:name":"Koncewizna",
    "gn:population":0,
    "gn:timezone":"Europe/Warsaw",
    "iso:country":"PL",
    "wof:name":"Koncewizna",
    "wof:placetype":"neighbourhood"
},
  "geometry": {"coordinates":[22.97342,52.92972],"type":"Point"}
}