{
  "type": "Feature",
  "properties": {
    "gn:admin1_code":"73.0",
    "gn:admin2_code":"417.0",
    "gn:admin3_code":"41702.0",
    "gn:asciiname":"Male Pulkowo",
    "gn:country_code":"PL",
    "gn:dem":93,
    "gn:feature_class":"P",
    "gn:feature_code":"PPL",
    "gn:name":"Ma\u0142e Pu\u0142kowo",
    "gn:population":0,
    "gn:timezone":"Europe/Warsaw",
    "iso:country":"PL",
    "name:pol_x_preferred":[
        "Ma\u0142e Pu\u0142kowo"
    ],
    "name:ukr_x_preferred":[
        "\u041c\u0430\u043b\u0435 \u041f\u0443\u043b\u043a\u043e\u0432\u043e"
    ],
    "wof:name":"Male Pulkowo",
    "wof:placetype":"locality"
},
  "geometry": {"coordinates":[19.03287000000001,53.19868],"type":"Point"}
}