{
  "type": "Feature",
  "properties": {
    "gn:country":"PL",
    "gn:fcode":"PPL",
    "gn:population":267,
    "iso:country":"PL",
    "name:ast_x_preferred":[
        "Frywa\u0142d"
    ],
    "name:azb_x_preferred":[
        "\u0641\u0631\u0648\u0627\u0648\u062f"
    ],
    "name:ceb_x_preferred":[
        "Frywa\u0142d"
    ],
    "name:ces_x_preferred":[
        "Frywa\u0142d"
    ],
    "name:deu_x_preferred":[
        "Frywa\u0142d"
    ],
    "name:eng_x_preferred":[
        "Frywa\u0142d"
    ],
    "name:fas_x_preferred":[
        "\u0641\u0631\u0648\u0627\u0648\u062f"
    ],
    "name:fra_x_preferred":[
        "Frywa\u0142d"
    ],
    "name:nan_x_preferred":[
        "Frywa\u0142d"
    ],
    "name:pol_x_preferred":[
        "Frywa\u0142d"
    ],
    "name:spa_x_preferred":[
        "Frywa\u0142d"
    ],
    "name:ukr_x_preferred":[
        "\u0424\u0440\u0438\u0432\u0430\u043b\u0434"
    ],
    "qs_pg:aaroncc":"PL",
    "qs_pg:gn_country":"PL",
    "qs_pg:gn_fcode":"PPL",
    "qs_pg:gn_pop":267,
    "qs_pg:name":"Frywa\u0142d",
    "qs_pg:name_adm0":"Polska",
    "qs_pg:name_adm1":"Ma\u0142opolskie",
    "qs_pg:photos":43,
    "qs_pg:photos_1k":9,
    "qs_pg:photos_9k":1,
    "qs_pg:photos_9r":2,
    "qs_pg:photos_all":43,
    "qs_pg:photos_sr":2,
    "qs_pg:pop_sr":2,
    "qs_pg:qs_pg_placetype":"locality",
    "qs_pg:qs_pg_placetype_gp":"Town",
    "qs_pg:woe_adm0":23424923,
    "woe:adm0_id":23424923,
    "woe:name_adm0":"Polska",
    "woe:name_adm1":"Ma\u0142opolskie",
    "woe:placetype":"Town",
    "wof:name":"Frywa\u0142d",
    "wof:placetype":"locality",
    "wof:population":267
},
  "geometry": {"coordinates":[19.66038,50.09118],"type":"Point"}
}