{
  "type": "Feature",
  "properties": {
    "gn:admin1_code":"86.0",
    "gn:admin2_code":"3019.0",
    "gn:admin3_code":"301908.0",
    "gn:asciiname":"Glesno",
    "gn:country_code":"PL",
    "gn:dem":94,
    "gn:feature_class":"P",
    "gn:feature_code":"PPL",
    "gn:name":"Glesno",
    "gn:population":0,
    "gn:timezone":"Europe/Warsaw",
    "iso:country":"PL",
    "name:azb_x_preferred":[
        "\u0642\u0644\u0633\u0646\u0648"
    ],
    "name:ceb_x_preferred":[
        "Glesno"
    ],
    "name:fas_x_preferred":[
        "\u06af\u0644\u0633\u0646\u0648"
    ],
    "name:fra_x_preferred":[
        "Glesno"
    ],
    "name:pol_x_preferred":[
        "Glesno"
    ],
    "name:ukr_x_preferred":[
        "\u0490\u043b\u0435\u0441\u043d\u043e"
    ],
    "wof:name":"Glesno",
    "wof:placetype":"locality"
},
  "geometry": {"coordinates":[17.30458,53.18019],"type":"Point"}
}