{
  "type": "Feature",
  "properties": {
    "gn:admin1_code":"78.0",
    "gn:admin2_code":"1422.0",
    "gn:admin3_code":"142206.0",
    "gn:asciiname":"Masiak",
    "gn:country_code":"PL",
    "gn:dem":154,
    "gn:feature_class":"P",
    "gn:feature_code":"PPL",
    "gn:name":"Masiak",
    "gn:population":0,
    "gn:timezone":"Europe/Warsaw",
    "iso:country":"PL",
    "name:fra_x_preferred":[
        "Masiak"
    ],
    "name:pol_x_preferred":[
        "Masiak"
    ],
    "name:ukr_x_preferred":[
        "\u041c\u0430\u0441\u044f\u043a"
    ],
    "wof:name":"Masiak",
    "wof:placetype":"locality"
},
  "geometry": {"coordinates":[20.75103,53.17226],"type":"Point"}
}