{
  "type": "Feature",
  "properties": {
    "gn:gn_country":"PL",
    "gn:gn_fcode":"PPLA3",
    "gn:gn_pop":1300,
    "gn:population":1300,
    "iso:country":"PL",
    "name:ceb_x_preferred":[
        "Widawa"
    ],
    "name:deu_x_preferred":[
        "Widawa"
    ],
    "name:eng_x_preferred":[
        "Gmina Widawa"
    ],
    "name:nno_x_preferred":[
        "Widawa"
    ],
    "name:pol_x_preferred":[
        "Widawa"
    ],
    "name:por_x_preferred":[
        "Comuna de Widawa"
    ],
    "name:rus_x_preferred":[
        "\u0412\u0438\u0434\u0430\u0432\u0430"
    ],
    "name:slk_x_preferred":[
        "Gmina Widawa"
    ],
    "name:srp_x_preferred":[
        "\u0412\u0438\u0434\u0430\u0432\u0430"
    ],
    "name:ukr_x_preferred":[
        "\u0490\u043c\u0456\u043d\u0430 \u0412\u0456\u0434\u0430\u0432\u0430"
    ],
    "name:ukr_x_variant":[
        "\u0412\u0456\u0434\u0430\u0432\u0430"
    ],
    "name:war_x_preferred":[
        "Gmina Widawa"
    ],
    "qs_pg:aaroncc":"PL",
    "qs_pg:gn_country":"PL",
    "qs_pg:gn_fcode":"PPLA3",
    "qs_pg:gn_pop":1300,
    "qs_pg:name":"Widawa",
    "qs_pg:name_adm0":"Polska",
    "qs_pg:name_adm1":"\u0141\u00f3dzkie",
    "qs_pg:photos_9k":1,
    "qs_pg:photos_9r":1,
    "qs_pg:photos_all":4,
    "qs_pg:photos_sr":0,
    "qs_pg:pop_sr":3,
    "qs_pg:qs_pg_placetype":"localadmin",
    "qs_pg:qs_pg_placetype_gp":"LocalAdmin",
    "qs_pg:woe_adm0":23424923,
    "woe:adm0_id":23424923,
    "woe:name_adm0":"Polska",
    "woe:name_adm1":"\u0141\u00f3dzkie",
    "woe:placetype":"LocalAdmin",
    "wof:name":"Widawa",
    "wof:placetype":"localadmin",
    "wof:population":1300
},
  "geometry": {"coordinates":[18.94421,51.43855],"type":"Point"}
}