{
  "type": "Feature",
  "properties": {
    "gn:admin1_code":"74.0",
    "gn:admin2_code":"1010.0",
    "gn:admin3_code":"101009.0",
    "gn:asciiname":"Klodzice",
    "gn:country_code":"PL",
    "gn:dem":182,
    "gn:feature_class":"P",
    "gn:feature_code":"PPL",
    "gn:name":"K\u0142odzice",
    "gn:population":0,
    "gn:timezone":"Europe/Warsaw",
    "iso:country":"PL",
    "name:und_x_variant":[
        "K\u0142udice",
        "K\u0142udzice",
        "K\u0142odzice"
    ],
    "wof:name":"Klodzice",
    "wof:placetype":"locality"
},
  "geometry": {"coordinates":[19.775,51.35387],"type":"Point"}
}