{
  "type": "Feature",
  "properties": {
    "gn:admin1_code":"74.0",
    "gn:admin2_code":"1008.0",
    "gn:admin3_code":"100804.0",
    "gn:asciiname":"Chechlo",
    "gn:country_code":"PL",
    "gn:dem":191,
    "gn:feature_class":"P",
    "gn:feature_code":"PPL",
    "gn:name":"Chech\u0142o",
    "gn:population":0,
    "gn:timezone":"Europe/Warsaw",
    "iso:country":"PL",
    "name:und_x_variant":[
        "Chech\u0142o Pierwsze",
        "Chech\u0142o"
    ],
    "wof:name":"Chechlo",
    "wof:placetype":"locality"
},
  "geometry": {"coordinates":[19.28661,51.64417],"type":"Point"}
}