{
  "type": "Feature",
  "properties": {
    "gn:admin1_code":"80.0",
    "gn:admin2_code":"1810.0",
    "gn:admin3_code":"181003.0",
    "gn:asciiname":"Pogwizdow",
    "gn:country_code":"PL",
    "gn:dem":197,
    "gn:feature_class":"P",
    "gn:feature_code":"PPL",
    "gn:name":"Pogwizd\u00f3w",
    "gn:population":0,
    "gn:timezone":"Europe/Warsaw",
    "iso:country":"PL",
    "name:und_x_variant":[
        "Pogwizd\u00f3w"
    ],
    "wof:name":"Pogwizdow",
    "wof:placetype":"locality"
},
  "geometry": {"coordinates":[22.1401,50.12723],"type":"Point"}
}