{
  "type": "Feature",
  "properties": {
    "gn:admin1_code":"85.0",
    "gn:admin2_code":"2814.0",
    "gn:admin3_code":"281405.0",
    "gn:asciiname":"Srodka",
    "gn:country_code":"PL",
    "gn:dem":116,
    "gn:feature_class":"P",
    "gn:feature_code":"PPL",
    "gn:name":"\u015ar\u00f3dka",
    "gn:population":0,
    "gn:timezone":"Europe/Warsaw",
    "iso:country":"PL",
    "name:und_x_variant":[
        "Mitelki",
        "Mittelgut",
        "\u015ar\u00f3dka"
    ],
    "wof:name":"Srodka",
    "wof:placetype":"locality"
},
  "geometry": {"coordinates":[20.2407,53.70515],"type":"Point"}
}