{
  "type": "Feature",
  "properties": {
    "gn:gn_country":"PL",
    "gn:gn_fcode":"PPL",
    "gn:gn_pop":0,
    "iso:country":"PL",
    "name:eng_x_preferred":[
        "Kocierz Rychwa\u0142dzki"
    ],
    "name:fra_x_preferred":[
        "Kocierz Rychwa\u0142dzki"
    ],
    "name:nan_x_preferred":[
        "Kocierz Rychwa\u0142dzki"
    ],
    "name:pol_x_preferred":[
        "Kocierz Rychwa\u0142dzki"
    ],
    "qs_pg:aaroncc":"PL",
    "qs_pg:gn_country":"PL",
    "qs_pg:gn_fcode":"PPL",
    "qs_pg:gn_pop":0,
    "qs_pg:name":"Kocierz Rychwa\u0142dzki",
    "qs_pg:name_adm0":"Polska",
    "qs_pg:name_adm1":"Sl\u0105skie",
    "qs_pg:photos":8,
    "qs_pg:photos_1k":2,
    "qs_pg:photos_9k":1,
    "qs_pg:photos_9r":1,
    "qs_pg:photos_all":8,
    "qs_pg:photos_sr":1,
    "qs_pg:pop_sr":0,
    "qs_pg:qs_pg_placetype":"locality",
    "qs_pg:qs_pg_placetype_gp":"Town",
    "qs_pg:woe_adm0":23424923,
    "woe:adm0_id":23424923,
    "woe:name_adm0":"Polska",
    "woe:name_adm1":"Sl\u0105skie",
    "woe:placetype":"Town",
    "wof:name":"Kocierz Rychwa\u0142dzki",
    "wof:placetype":"locality"
},
  "geometry": {"coordinates":[19.32701,49.76247],"type":"Point"}
}