{
  "type": "Feature",
  "properties": {
    "gn:admin1_code":"86.0",
    "gn:admin2_code":"3009.0",
    "gn:admin3_code":"300904.0",
    "gn:asciiname":"Cichmiana",
    "gn:country_code":"PL",
    "gn:dem":95,
    "gn:feature_class":"P",
    "gn:feature_code":"PPL",
    "gn:name":"Cichmiana",
    "gn:population":0,
    "gn:timezone":"Europe/Warsaw",
    "iso:country":"PL",
    "name:pol_x_preferred":[
        "Cichmiana"
    ],
    "name:ukr_x_preferred":[
        "\u0426\u0438\u0445\u043c\u044f\u043d\u0430"
    ],
    "wof:name":"Cichmiana",
    "wof:placetype":"locality"
},
  "geometry": {"coordinates":[18.78147,52.0794],"type":"Point"}
}