{
  "type": "Feature",
  "properties": {
    "gn:admin1_code":"80.0",
    "gn:admin2_code":"1801.0",
    "gn:admin3_code":"180103.0",
    "gn:asciiname":"Michniowiec",
    "gn:country_code":"PL",
    "gn:dem":573,
    "gn:feature_class":"P",
    "gn:feature_code":"PPL",
    "gn:name":"Michniowiec",
    "gn:population":0,
    "gn:timezone":"Europe/Warsaw",
    "iso:country":"PL",
    "name:azb_x_preferred":[
        "\u0645\u06cc\u062e\u0646\u0642\u0648\u0648\u06cc\u062a\u0633"
    ],
    "name:ceb_x_preferred":[
        "Michniowiec"
    ],
    "name:fas_x_preferred":[
        "\u0645\u06cc\u062e\u0646\u06af\u0648\u0648\u06cc\u062a\u0633"
    ],
    "name:hun_x_preferred":[
        "Michniowiec"
    ],
    "name:nld_x_preferred":[
        "Michniowiec"
    ],
    "name:pol_x_preferred":[
        "Michniowiec"
    ],
    "name:ukr_x_preferred":[
        "\u041c\u0438\u0445\u043d\u043e\u0432\u0435\u0446\u044c"
    ],
    "name:und_x_variant":[
        "Mikhnovets",
        "Michniowiec",
        "Mikhn\u00ebvets"
    ],
    "wof:name":"Michniowiec",
    "wof:placetype":"locality"
},
  "geometry": {"coordinates":[22.73114,49.30219],"type":"Point"}
}