{
  "type": "Feature",
  "properties": {
    "gn:admin1_code":"86.0",
    "gn:admin2_code":"3064.0",
    "gn:admin3_code":"306401.0",
    "gn:asciiname":"Debiec",
    "gn:country_code":"PL",
    "gn:dem":64,
    "gn:feature_class":"P",
    "gn:feature_code":"PPL",
    "gn:name":"D\u0119biec",
    "gn:population":0,
    "gn:timezone":"Europe/Warsaw",
    "iso:country":"PL",
    "wof:name":"Debiec",
    "wof:placetype":"locality"
},
  "geometry": {"coordinates":[16.91667,52.36667],"type":"Point"}
}