{
  "type": "Feature",
  "properties": {
    "gn:admin1_code":"76.0",
    "gn:admin2_code":"802.0",
    "gn:admin3_code":"80204.0",
    "gn:asciiname":"Polupin",
    "gn:country_code":"PL",
    "gn:dem":45,
    "gn:feature_class":"P",
    "gn:feature_code":"PPL",
    "gn:name":"Po\u0142upin",
    "gn:population":0,
    "gn:timezone":"Europe/Warsaw",
    "iso:country":"PL",
    "name:fra_x_preferred":[
        "Po\u0142upin"
    ],
    "name:pol_x_preferred":[
        "Po\u0142upin"
    ],
    "name:ukr_x_preferred":[
        "\u041f\u043e\u043b\u0443\u043f\u0456\u043d"
    ],
    "wof:name":"Polupin",
    "wof:placetype":"locality"
},
  "geometry": {"coordinates":[15.11272,52.02398],"type":"Point"}
}