{
  "type": "Feature",
  "properties": {
    "gn:admin1_code":"82.0",
    "gn:admin2_code":"2210.0",
    "gn:admin3_code":"221004.0",
    "gn:asciiname":"Stegienka",
    "gn:country_code":"PL",
    "gn:dem":2,
    "gn:feature_class":"P",
    "gn:feature_code":"PPL",
    "gn:name":"Stegienka",
    "gn:population":0,
    "gn:timezone":"Europe/Warsaw",
    "iso:country":"PL",
    "name:ceb_x_preferred":[
        "Stegienka"
    ],
    "name:pol_x_preferred":[
        "Stegienka"
    ],
    "name:ukr_x_preferred":[
        "\u0421\u0442\u0435\u0491\u0435\u043d\u043a\u0430"
    ],
    "name:und_x_variant":[
        "Steegnerwerder"
    ],
    "wof:name":"Stegienka",
    "wof:placetype":"locality"
},
  "geometry": {"coordinates":[19.05682,54.31051],"type":"Point"}
}