{
  "type": "Feature",
  "properties": {
    "gn:admin1_code":"80.0",
    "gn:admin2_code":"1807.0",
    "gn:admin3_code":"180702.0",
    "gn:asciiname":"Wilsznia",
    "gn:country_code":"PL",
    "gn:dem":498,
    "gn:feature_class":"P",
    "gn:feature_code":"PPL",
    "gn:name":"Wilsznia",
    "gn:population":0,
    "gn:timezone":"Europe/Warsaw",
    "iso:country":"PL",
    "name:pol_x_preferred":[
        "Wilsznia"
    ],
    "name:ukr_x_preferred":[
        "\u0412\u0438\u043b\u044c\u0448\u043d\u044f"
    ],
    "wof:name":"Wilsznia",
    "wof:placetype":"locality"
},
  "geometry": {"coordinates":[21.65,49.46667],"type":"Point"}
}