{
  "type": "Feature",
  "properties": {
    "gn:admin1_code":"80.0",
    "gn:admin2_code":"1811.0",
    "gn:admin3_code":"181110.0",
    "gn:asciiname":"Zabrnie",
    "gn:country_code":"PL",
    "gn:dem":161,
    "gn:feature_class":"P",
    "gn:feature_code":"PPL",
    "gn:name":"Zabrnie",
    "gn:population":0,
    "gn:timezone":"Europe/Warsaw",
    "iso:country":"PL",
    "name:pol_x_preferred":[
        "Zabrnie"
    ],
    "name:ukr_x_preferred":[
        "\u0417\u0430\u0431\u0440\u043d\u0435"
    ],
    "name:urd_x_preferred":[
        "\u0632\u0628\u0691\u0646\u06d2"
    ],
    "wof:name":"Zabrnie",
    "wof:placetype":"locality"
},
  "geometry": {"coordinates":[21.19812,50.298],"type":"Point"}
}