{
  "type": "Feature",
  "properties": {
    "gn:admin1_code":"80.0",
    "gn:admin2_code":"1808.0",
    "gn:admin3_code":"180802.0",
    "gn:asciiname":"Chodaczow",
    "gn:country_code":"PL",
    "gn:dem":175,
    "gn:feature_class":"P",
    "gn:feature_code":"PPL",
    "gn:name":"Chodacz\u00f3w",
    "gn:population":0,
    "gn:timezone":"Europe/Warsaw",
    "iso:country":"PL",
    "wof:name":"Chodaczow",
    "wof:placetype":"locality"
},
  "geometry": {"coordinates":[22.51837,50.14149000000001],"type":"Point"}
}