{
  "type": "Feature",
  "properties": {
    "gn:admin1_code":"75.0",
    "gn:admin2_code":"614.0",
    "gn:admin3_code":"61402.0",
    "gn:asciiname":"Kolonia Nowomichowska",
    "gn:country_code":"PL",
    "gn:dem":155,
    "gn:feature_class":"P",
    "gn:feature_code":"PPL",
    "gn:name":"Kolonia Nowomichowska",
    "gn:population":0,
    "gn:timezone":"Europe/Warsaw",
    "iso:country":"PL",
    "wof:name":"Kolonia Nowomichowska",
    "wof:placetype":"locality"
},
  "geometry": {"coordinates":[22.21667,51.55],"type":"Point"}
}