{
  "type": "Feature",
  "properties": {
    "gn:admin1_code":"75.0",
    "gn:admin2_code":"614.0",
    "gn:admin3_code":"61402.0",
    "gn:asciiname":"Kolonia Nowomichowska",
    "gn:country_code":"PL",
    "gn:dem":155,
    "gn:feature_class":"P",
    "gn:feature_code":"PPL",
    "gn:name":"Kolonia Nowomichowska",
    "gn:population":0,
    "gn:timezone":"Europe/Warsaw",
    "iso:country":"PL",
    "name:fra_x_preferred":[
        "Nowomichowska"
    ],
    "name:pol_x_preferred":[
        "Nowomichowska"
    ],
    "name:ukr_x_preferred":[
        "\u041d\u043e\u0432\u043e\u043c\u0456\u0445\u043e\u0432\u0441\u044c\u043a\u0430"
    ],
    "wof:name":"Kolonia Nowomichowska",
    "wof:placetype":"locality"
},
  "geometry": {"coordinates":[22.21667,51.55],"type":"Point"}
}