{
  "type": "Feature",
  "properties": {
    "gn:admin1_code":"80.0",
    "gn:admin2_code":"1803.0",
    "gn:admin3_code":"180302.0",
    "gn:asciiname":"Kamienica Gorna",
    "gn:country_code":"PL",
    "gn:dem":298,
    "gn:feature_class":"P",
    "gn:feature_code":"PPL",
    "gn:name":"Kamienica G\u00f3rna",
    "gn:population":0,
    "gn:timezone":"Europe/Warsaw",
    "iso:country":"PL",
    "name:pol_x_preferred":[
        "Kamienica G\u00f3rna"
    ],
    "name:ukr_x_preferred":[
        "\u041a\u0430\u043c\u0435\u043d\u0438\u0446\u044f-\u0490\u0443\u0440\u043d\u0430"
    ],
    "wof:name":"Kamienica Gorna",
    "wof:placetype":"locality"
},
  "geometry": {"coordinates":[21.48754,49.89762],"type":"Point"}
}