{
  "type": "Feature",
  "properties": {
    "gn:admin1_code":"78.0",
    "gn:admin2_code":"1435.0",
    "gn:admin3_code":"143503.0",
    "gn:asciiname":"Zagrudzie",
    "gn:country_code":"PL",
    "gn:dem":102,
    "gn:feature_class":"P",
    "gn:feature_code":"PPL",
    "gn:name":"Zagrudzie",
    "gn:population":0,
    "gn:timezone":"Europe/Warsaw",
    "iso:country":"PL",
    "name:und_x_variant":[
        "D\u0105browa Zagrudzie"
    ],
    "wof:name":"Zagrudzie",
    "wof:placetype":"locality"
},
  "geometry": {"coordinates":[21.34794,52.68864],"type":"Point"}
}