{
  "type": "Feature",
  "properties": {
    "gn:admin1_code":"84.0",
    "gn:admin2_code":"2607.0",
    "gn:admin3_code":"260705.0",
    "gn:asciiname":"Nietulisko",
    "gn:country_code":"PL",
    "gn:dem":193,
    "gn:feature_class":"P",
    "gn:feature_code":"PPL",
    "gn:name":"Nietulisko",
    "gn:population":0,
    "gn:timezone":"Europe/Warsaw",
    "iso:country":"PL",
    "wof:name":"Nietulisko",
    "wof:placetype":"locality"
},
  "geometry": {"coordinates":[21.25,50.98333],"type":"Point"}
}