{
  "type": "Feature",
  "properties": {
    "gn:admin1_code":"73.0",
    "gn:admin2_code":"418.0",
    "gn:admin3_code":"41813.0",
    "gn:asciiname":"Mostki",
    "gn:country_code":"PL",
    "gn:dem":57,
    "gn:feature_class":"P",
    "gn:feature_code":"PPL",
    "gn:name":"Mostki",
    "gn:population":0,
    "gn:timezone":"Europe/Warsaw",
    "iso:country":"PL",
    "name:pol_x_preferred":[
        "Mostki"
    ],
    "name:ukr_x_preferred":[
        "\u041c\u043e\u0441\u0442\u043a\u0456"
    ],
    "wof:name":"Mostki",
    "wof:placetype":"locality"
},
  "geometry": {"coordinates":[19.24265,52.62257],"type":"Point"}
}