{
  "type": "Feature",
  "properties": {
    "gn:admin1_code":"78.0",
    "gn:admin2_code":"1433.0",
    "gn:admin3_code":"143302.0",
    "gn:asciiname":"Trzebucza",
    "gn:country_code":"PL",
    "gn:dem":159,
    "gn:feature_class":"P",
    "gn:feature_code":"PPL",
    "gn:name":"Trzebucza",
    "gn:population":0,
    "gn:timezone":"Europe/Warsaw",
    "iso:country":"PL",
    "name:azb_x_preferred":[
        "\u0686\u0628\u0648\u06a9\u0632\u0627"
    ],
    "name:fas_x_preferred":[
        "\u0686\u0628\u0648\u06a9\u0632\u0627"
    ],
    "name:fra_x_preferred":[
        "Trzebucza"
    ],
    "name:pol_x_preferred":[
        "Trzebucza"
    ],
    "name:ukr_x_preferred":[
        "\u0422\u0448\u0435\u0431\u0443\u0447\u0430"
    ],
    "wof:name":"Trzebucza",
    "wof:placetype":"locality"
},
  "geometry": {"coordinates":[21.88399,52.23345],"type":"Point"}
}