{
  "type": "Feature",
  "properties": {
    "gn:admin1_code":"86.0",
    "gn:admin2_code":"3008.0",
    "gn:admin3_code":"300805.0",
    "gn:asciiname":"Zbyczyna",
    "gn:country_code":"PL",
    "gn:dem":173,
    "gn:feature_class":"P",
    "gn:feature_code":"PPL",
    "gn:name":"Zbyczyna",
    "gn:population":0,
    "gn:timezone":"Europe/Warsaw",
    "iso:country":"PL",
    "name:pol_x_preferred":[
        "Zbyczyna"
    ],
    "name:ukr_x_preferred":[
        "\u0417\u0431\u0438\u0447\u0438\u043d\u0430"
    ],
    "wof:name":"Zbyczyna",
    "wof:placetype":"locality"
},
  "geometry": {"coordinates":[17.81982,51.19822],"type":"Point"}
}