{
  "type": "Feature",
  "properties": {
    "gn:admin1_code":"81.0",
    "gn:admin2_code":"2007.0",
    "gn:admin3_code":"200705.0",
    "gn:asciiname":"Truszki",
    "gn:country_code":"PL",
    "gn:dem":141,
    "gn:feature_class":"P",
    "gn:feature_code":"PPL",
    "gn:name":"Truszki",
    "gn:population":0,
    "gn:timezone":"Europe/Warsaw",
    "iso:country":"PL",
    "name:azb_x_preferred":[
        "\u062a\u0631\u0648\u0634\u06a9\u06cc"
    ],
    "name:fas_x_preferred":[
        "\u062a\u0631\u0648\u0634\u06a9\u06cc"
    ],
    "name:lit_x_preferred":[
        "Tru\u0161kai"
    ],
    "name:pol_x_preferred":[
        "Truszki"
    ],
    "name:ukr_x_preferred":[
        "\u0422\u0440\u0443\u0448\u043a\u0456"
    ],
    "name:urd_x_preferred":[
        "\u062a\u0631\u0634\u06a9\u06cc"
    ],
    "wof:name":"Truszki",
    "wof:placetype":"locality"
},
  "geometry": {"coordinates":[22.24028,53.17302],"type":"Point"}
}