{
  "type": "Feature",
  "properties": {
    "gn:admin1_code":"74.0",
    "gn:admin2_code":"1010.0",
    "gn:admin3_code":"101007.0",
    "gn:asciiname":"Reczno",
    "gn:country_code":"PL",
    "gn:dem":217,
    "gn:feature_class":"P",
    "gn:feature_code":"PPLA3",
    "gn:name":"R\u0119czno",
    "gn:population":690,
    "gn:timezone":"Europe/Warsaw",
    "iso:country":"PL",
    "wof:name":"Reczno",
    "wof:placetype":"locality",
    "wof:population":690
},
  "geometry": {"coordinates":[19.85375,51.19026],"type":"Point"}
}