{
  "type": "Feature",
  "properties": {
    "gn:admin1_code":"74.0",
    "gn:admin2_code":"1010.0",
    "gn:admin3_code":"101007.0",
    "gn:asciiname":"Reczno",
    "gn:country_code":"PL",
    "gn:dem":217,
    "gn:feature_class":"P",
    "gn:feature_code":"PPLA3",
    "gn:name":"R\u0119czno",
    "gn:population":690,
    "gn:timezone":"Europe/Warsaw",
    "iso:country":"PL",
    "name:azb_x_preferred":[
        "\u0631\u0646\u0686\u0646\u0648"
    ],
    "name:ceb_x_preferred":[
        "R\u0119czno"
    ],
    "name:deu_x_preferred":[
        "R\u0119czno"
    ],
    "name:fas_x_preferred":[
        "\u0631\u0646\u0686\u0646\u0648"
    ],
    "name:fra_x_preferred":[
        "R\u0119czno"
    ],
    "name:nld_x_preferred":[
        "R\u0119czno"
    ],
    "name:pol_x_preferred":[
        "R\u0119czno"
    ],
    "name:ukr_x_preferred":[
        "\u0420\u0435\u043d\u0447\u043d\u043e"
    ],
    "wof:coterminous":[
        1477751857
    ],
    "wof:name":"Reczno",
    "wof:placetype":"locality",
    "wof:population":690
},
  "geometry": {"coordinates":[19.85375,51.19026],"type":"Point"}
}