{
  "type": "Feature",
  "properties": {
    "gn:admin1_code":"86.0",
    "gn:admin2_code":"3011.0",
    "gn:admin3_code":"301103.0",
    "gn:asciiname":"Kurowo",
    "gn:country_code":"PL",
    "gn:dem":70,
    "gn:feature_class":"P",
    "gn:feature_code":"PPL",
    "gn:name":"Kurowo",
    "gn:population":0,
    "gn:timezone":"Europe/Warsaw",
    "iso:country":"PL",
    "name:fra_x_preferred":[
        "Kurowo"
    ],
    "name:ind_x_preferred":[
        "Kurowo"
    ],
    "name:pol_x_preferred":[
        "Kurowo"
    ],
    "name:rus_x_preferred":[
        "\u041a\u0443\u0440\u043e\u0432\u043e"
    ],
    "name:ukr_x_preferred":[
        "\u041a\u0443\u0440\u043e\u0432\u043e"
    ],
    "wof:name":"Kurowo",
    "wof:placetype":"locality"
},
  "geometry": {"coordinates":[16.65943,52.12439000000001],"type":"Point"}
}