{
  "type": "Feature",
  "properties": {
    "gn:gn_country":"PL",
    "gn:gn_fcode":"ADM3",
    "gn:gn_pop":0,
    "iso:country":"PL",
    "name:eng_x_preferred":[
        "Gmina Jonkowo"
    ],
    "name:pol_x_preferred":[
        "Jonkowo"
    ],
    "name:por_x_preferred":[
        "Comuna de Jonkowo"
    ],
    "name:rus_x_preferred":[
        "\u0419\u043e\u043d\u043a\u043e\u0432\u043e"
    ],
    "name:slk_x_preferred":[
        "Gmina Jonkowo"
    ],
    "name:ukr_x_preferred":[
        "\u0413\u043c\u0456\u043d\u0430 \u0419\u043e\u043d\u043a\u043e\u0432\u043e"
    ],
    "name:war_x_preferred":[
        "Gmina Jonkowo"
    ],
    "qs_pg:aaroncc":"PL",
    "qs_pg:gn_country":"PL",
    "qs_pg:gn_fcode":"ADM3",
    "qs_pg:gn_pop":0,
    "qs_pg:name":"Jonkowo",
    "qs_pg:name_adm0":"Polska",
    "qs_pg:name_adm1":"Warminsko-Mazurskie",
    "qs_pg:photos":22,
    "qs_pg:photos_1k":4,
    "qs_pg:photos_9k":1,
    "qs_pg:photos_9r":0,
    "qs_pg:photos_all":29,
    "qs_pg:photos_sr":0,
    "qs_pg:pop_sr":0,
    "qs_pg:qs_pg_placetype":"localadmin",
    "qs_pg:qs_pg_placetype_gp":"LocalAdmin",
    "qs_pg:woe_adm0":23424923,
    "wof:name":"Jonkowo",
    "wof:placetype":"localadmin"
},
  "geometry": {"coordinates":[20.2664,53.825],"type":"Point"}
}