{
  "type": "Feature",
  "properties": {
    "gn:admin1_code":"80.0",
    "gn:admin2_code":"1809.0",
    "gn:admin3_code":"180905.0",
    "gn:asciiname":"Maziarnia",
    "gn:country_code":"PL",
    "gn:dem":251,
    "gn:feature_class":"P",
    "gn:feature_code":"PPL",
    "gn:name":"Maziarnia",
    "gn:population":0,
    "gn:timezone":"Europe/Warsaw",
    "iso:country":"PL",
    "name:fra_x_preferred":[
        "Maziarnia"
    ],
    "name:pol_x_preferred":[
        "Maziarnia"
    ],
    "name:ukr_x_preferred":[
        "\u041c\u0430\u0437\u044f\u0440\u043d\u044f"
    ],
    "wof:name":"Maziarnia",
    "wof:placetype":"locality"
},
  "geometry": {"coordinates":[23.20174,50.35757],"type":"Point"}
}