{
  "type": "Feature",
  "properties": {
    "gn:country":"PL",
    "gn:fcode":"PPLA3",
    "gn:population":1700,
    "iso:country":"PL",
    "name:bul_x_preferred":[
        "\u0423\u044f\u0437\u0434"
    ],
    "name:deu_x_preferred":[
        "Ujest"
    ],
    "name:epo_x_preferred":[
        "Ujazd"
    ],
    "name:fra_x_preferred":[
        "Ujazd"
    ],
    "name:heb_x_preferred":[
        "\u05d0\u05d5\u05d9\u05d9\u05d6\u05d3"
    ],
    "name:jav_x_preferred":[
        "Ujazd"
    ],
    "name:lav_x_preferred":[
        "Ujazda"
    ],
    "name:msa_x_preferred":[
        "Ujazd"
    ],
    "name:nld_x_preferred":[
        "Ujazd"
    ],
    "name:pol_x_preferred":[
        "Ujazd"
    ],
    "name:por_x_preferred":[
        "Ujazd"
    ],
    "name:ron_x_preferred":[
        "Ujazd"
    ],
    "name:rus_x_preferred":[
        "\u0423\u044f\u0437\u0434"
    ],
    "name:slk_x_preferred":[
        "Ujazd"
    ],
    "name:srp_x_preferred":[
        "\u0423\u0458\u0430\u0437\u0434"
    ],
    "name:tha_x_preferred":[
        "\u0e2d\u0e39\u0e22\u0e31\u0e2a\u0e15\u0e4c"
    ],
    "name:ukr_x_preferred":[
        "\u0423\u044f\u0437\u0434"
    ],
    "name:vie_x_preferred":[
        "Ujazd"
    ],
    "name:zho_x_preferred":[
        "\u70cf\u4e9e\u8332\u5fb7"
    ],
    "qs_pg:aaroncc":"PL",
    "qs_pg:gn_country":"PL",
    "qs_pg:gn_fcode":"PPLA3",
    "qs_pg:gn_pop":1700,
    "qs_pg:name":"Ujazd",
    "qs_pg:name_adm0":"Polska",
    "qs_pg:name_adm1":"\u0141\u00f3dzkie",
    "qs_pg:photos_9r":0,
    "qs_pg:photos_sr":0,
    "qs_pg:pop_sr":3,
    "qs_pg:qs_pg_placetype":"localadmin",
    "qs_pg:qs_pg_placetype_gp":"LocalAdmin",
    "qs_pg:woe_adm0":23424923,
    "woe:adm0_id":23424923,
    "woe:name_adm0":"Polska",
    "woe:name_adm1":"\u0141\u00f3dzkie",
    "woe:placetype":"LocalAdmin",
    "wof:name":"Ujazd",
    "wof:placetype":"localadmin",
    "wof:population":1700
},
  "geometry": {"coordinates":[19.92225,51.59781],"type":"Point"}
}