{
  "type": "Feature",
  "properties": {
    "gn:gn_country":"PL",
    "gn:gn_fcode":"PPLA3",
    "gn:gn_pop":1700,
    "gn:population":1700,
    "iso:country":"PL",
    "qs_pg:aaroncc":"PL",
    "qs_pg:gn_country":"PL",
    "qs_pg:gn_fcode":"PPLA3",
    "qs_pg:gn_pop":1700,
    "qs_pg:name":"Ujazd",
    "qs_pg:name_adm0":"Polska",
    "qs_pg:name_adm1":"\u0141\u00f3dzkie",
    "qs_pg:photos_9r":0,
    "qs_pg:photos_sr":0,
    "qs_pg:pop_sr":3,
    "qs_pg:qs_pg_placetype":"localadmin",
    "qs_pg:qs_pg_placetype_gp":"LocalAdmin",
    "qs_pg:woe_adm0":23424923,
    "woe:adm0_id":23424923,
    "woe:name_adm0":"Polska",
    "woe:name_adm1":"\u0141\u00f3dzkie",
    "woe:placetype":"LocalAdmin",
    "wof:name":"Ujazd",
    "wof:placetype":"localadmin",
    "wof:population":1700
},
  "geometry": {"coordinates":[19.92225,51.59781],"type":"Point"}
}