{
  "type": "Feature",
  "properties": {
    "gn:admin1_code":"82.0",
    "gn:admin2_code":"2209.0",
    "gn:admin3_code":"220908.0",
    "gn:asciiname":"Zlotowo",
    "gn:country_code":"PL",
    "gn:dem":0,
    "gn:feature_class":"P",
    "gn:feature_code":"PPL",
    "gn:name":"Z\u0142otowo",
    "gn:population":0,
    "gn:timezone":"Europe/Warsaw",
    "iso:country":"PL",
    "name:ceb_x_preferred":[
        "Z\u0142otowo"
    ],
    "name:pol_x_preferred":[
        "Z\u0142otowo"
    ],
    "name:ukr_x_preferred":[
        "\u0417\u043b\u043e\u0442\u043e\u0432\u043e"
    ],
    "name:und_x_variant":[
        "Reichfelde",
        "Z\u0142otowo"
    ],
    "wof:name":"Zlotowo",
    "wof:placetype":"locality"
},
  "geometry": {"coordinates":[19.21698,54.01917],"type":"Point"}
}