{
  "type": "Feature",
  "properties": {
    "gn:admin1_code":"85.0",
    "gn:admin2_code":"2810.0",
    "gn:admin3_code":"281004.0",
    "gn:asciiname":"Prusinowo",
    "gn:country_code":"PL",
    "gn:dem":134,
    "gn:feature_class":"P",
    "gn:feature_code":"PPL",
    "gn:name":"Prusinowo",
    "gn:population":0,
    "gn:timezone":"Europe/Warsaw",
    "iso:country":"PL",
    "name:deu_x_preferred":[
        "Prusinowo"
    ],
    "name:fra_x_preferred":[
        "Prusinowo"
    ],
    "name:pol_x_preferred":[
        "Prusinowo"
    ],
    "name:ukr_x_preferred":[
        "\u041f\u0440\u0443\u0441\u0456\u043d\u043e\u0432\u043e"
    ],
    "name:und_x_variant":[
        "Preussental",
        "Pruschinowen"
    ],
    "wof:name":"Prusinowo",
    "wof:placetype":"locality"
},
  "geometry": {"coordinates":[21.29981,53.69983000000001],"type":"Point"}
}