{
  "type": "Feature",
  "properties": {
    "gn:admin1_code":"74.0",
    "gn:admin2_code":"1021.0",
    "gn:admin3_code":"102104.0",
    "gn:asciiname":"Kolonia Lubiska",
    "gn:country_code":"PL",
    "gn:dem":172,
    "gn:feature_class":"P",
    "gn:feature_code":"PPL",
    "gn:name":"Kolonia Lubiska",
    "gn:population":0,
    "gn:timezone":"Europe/Warsaw",
    "iso:country":"PL",
    "name:fra_x_preferred":[
        "Lubiska-Kolonia"
    ],
    "name:pol_x_preferred":[
        "Lubiska-Kolonia"
    ],
    "wof:name":"Kolonia Lubiska",
    "wof:placetype":"locality"
},
  "geometry": {"coordinates":[19.94856,51.77716],"type":"Point"}
}