{
  "type": "Feature",
  "properties": {
    "gn:admin1_code":"74.0",
    "gn:admin2_code":"1020.0",
    "gn:admin3_code":"102005.0",
    "gn:asciiname":"Makolice",
    "gn:country_code":"PL",
    "gn:dem":113,
    "gn:feature_class":"P",
    "gn:feature_code":"PPL",
    "gn:name":"M\u0105kolice",
    "gn:population":0,
    "gn:timezone":"Europe/Warsaw",
    "iso:country":"PL",
    "name:eng_x_preferred":[
        "M\u0105kolice"
    ],
    "name:rus_x_preferred":[
        "\u041c\u043e\u043d\u043a\u043e\u043b\u0438\u0446\u0435"
    ],
    "name:und_x_variant":[
        "M\u0105kolice"
    ],
    "wof:name":"Makolice",
    "wof:placetype":"locality"
},
  "geometry": {"coordinates":[19.56453,52.01518],"type":"Point"}
}