{
  "type": "Feature",
  "properties": {
    "gn:admin1_code":"85.0",
    "gn:admin2_code":"2804.0",
    "gn:admin3_code":"280404.0",
    "gn:asciiname":"Brudzedy Male",
    "gn:country_code":"PL",
    "gn:dem":0,
    "gn:feature_class":"P",
    "gn:feature_code":"PPL",
    "gn:name":"Brudz\u0119dy Ma\u0142e",
    "gn:population":0,
    "gn:timezone":"Europe/Warsaw",
    "iso:country":"PL",
    "name:eng_x_preferred":[
        "Brudz\u0119dy Ma\u0142e"
    ],
    "name:rus_x_preferred":[
        "\u0411\u0440\u0443\u0434\u0437\u0435\u043d\u0434\u044b"
    ],
    "name:und_x_variant":[
        "Klein Brodsende",
        "Brudz\u0119dzy"
    ],
    "wof:name":"Brudzedy Male",
    "wof:placetype":"locality"
},
  "geometry": {"coordinates":[19.41168,54.0069],"type":"Point"}
}