{
  "type": "Feature",
  "properties": {
    "gn:admin1_code":"79.0",
    "gn:admin2_code":"1609.0",
    "gn:admin3_code":"160909.0",
    "gn:asciiname":"Stare Kolnie",
    "gn:country_code":"PL",
    "gn:dem":140,
    "gn:feature_class":"P",
    "gn:feature_code":"PPL",
    "gn:name":"Stare Kolnie",
    "gn:population":0,
    "gn:timezone":"Europe/Warsaw",
    "iso:country":"PL",
    "name:deu_x_preferred":[
        "Stare Kolnie"
    ],
    "name:pol_x_preferred":[
        "Stare Kolnie"
    ],
    "name:ukr_x_preferred":[
        "\u0421\u0442\u0430\u0440\u0435 \u041a\u043e\u043b\u044c\u043d\u0435"
    ],
    "name:und_x_variant":[
        "Alt C\u00f6ln",
        "Altk\u00f6ln"
    ],
    "wof:name":"Stare Kolnie",
    "wof:placetype":"locality"
},
  "geometry": {"coordinates":[17.66676,50.84652],"type":"Point"}
}