{
  "type": "Feature",
  "properties": {
    "gn:admin1_code":"80.0",
    "gn:admin2_code":"1821.0",
    "gn:admin3_code":"182102.0",
    "gn:asciiname":"Roztoki Gorne",
    "gn:country_code":"PL",
    "gn:dem":699,
    "gn:feature_class":"P",
    "gn:feature_code":"PPL",
    "gn:name":"Roztoki G\u00f3rne",
    "gn:population":0,
    "gn:timezone":"Europe/Warsaw",
    "iso:country":"PL",
    "wof:name":"Roztoki Gorne",
    "wof:placetype":"locality"
},
  "geometry": {"coordinates":[22.31564,49.15555],"type":"Point"}
}