{
  "type": "Feature",
  "properties": {
    "gn:admin1_code":"72.0",
    "gn:admin2_code":"205.0",
    "gn:admin3_code":"20502.0",
    "gn:asciiname":"Dolinka",
    "gn:country_code":"PL",
    "gn:dem":274,
    "gn:feature_class":"P",
    "gn:feature_code":"PPL",
    "gn:name":"Dolinka",
    "gn:population":0,
    "gn:timezone":"Europe/Warsaw",
    "iso:country":"PL",
    "wof:name":"Dolinka",
    "wof:placetype":"locality"
},
  "geometry": {"coordinates":[16.15,50.93333],"type":"Point"}
}