{
  "type": "Feature",
  "properties": {
    "gn:admin1_code":"72.0",
    "gn:admin2_code":"205.0",
    "gn:admin3_code":"20502.0",
    "gn:asciiname":"Dolinka",
    "gn:country_code":"PL",
    "gn:dem":274,
    "gn:feature_class":"P",
    "gn:feature_code":"PPL",
    "gn:name":"Dolinka",
    "gn:population":0,
    "gn:timezone":"Europe/Warsaw",
    "iso:country":"PL",
    "name:ceb_x_preferred":[
        "Dolinka"
    ],
    "name:ces_x_preferred":[
        "Dolinka"
    ],
    "name:deu_x_preferred":[
        "Dolinka"
    ],
    "name:epo_x_preferred":[
        "Dolinka"
    ],
    "name:hye_x_preferred":[
        "\u0534\u0578\u056c\u056b\u0576\u056f\u0561"
    ],
    "name:pol_x_preferred":[
        "Dolinka"
    ],
    "name:rus_x_preferred":[
        "\u0414\u043e\u043b\u0438\u043d\u043a\u0430"
    ],
    "name:slk_x_preferred":[
        "Dolinka"
    ],
    "name:srp_x_preferred":[
        "\u0414\u043e\u043b\u0438\u043d\u043a\u0430"
    ],
    "name:swe_x_preferred":[
        "Dolinka"
    ],
    "name:ukr_x_preferred":[
        "\u0414\u043e\u043b\u0438\u043d\u043a\u0430"
    ],
    "wof:name":"Dolinka",
    "wof:placetype":"locality"
},
  "geometry": {"coordinates":[16.15,50.93333],"type":"Point"}
}