{
  "type": "Feature",
  "properties": {
    "gn:admin1_code":"86.0",
    "gn:admin2_code":"3023.0",
    "gn:admin3_code":"302306.0",
    "gn:asciiname":"Kochowo",
    "gn:country_code":"PL",
    "gn:dem":106,
    "gn:feature_class":"P",
    "gn:feature_code":"PPL",
    "gn:name":"Kochowo",
    "gn:population":0,
    "gn:timezone":"Europe/Warsaw",
    "iso:country":"PL",
    "name:fra_x_preferred":[
        "Kochowo"
    ],
    "name:ita_x_preferred":[
        "Kochowo"
    ],
    "name:pol_x_preferred":[
        "Kochowo"
    ],
    "name:ukr_x_preferred":[
        "\u041a\u043e\u0445\u043e\u0432\u043e"
    ],
    "wof:name":"Kochowo",
    "wof:placetype":"locality"
},
  "geometry": {"coordinates":[17.93766,52.36667],"type":"Point"}
}