{
  "type": "Feature",
  "properties": {
    "gn:admin1_code":"73.0",
    "gn:admin2_code":"419.0",
    "gn:admin3_code":"41903.0",
    "gn:asciiname":"Koldrab",
    "gn:country_code":"PL",
    "gn:dem":107,
    "gn:feature_class":"P",
    "gn:feature_code":"PPL",
    "gn:name":"Ko\u0142dr\u0105b",
    "gn:population":0,
    "gn:timezone":"Europe/Warsaw",
    "iso:country":"PL",
    "name:pol_x_preferred":[
        "Ko\u0142dr\u0105b"
    ],
    "name:ukr_x_preferred":[
        "\u041a\u043e\u043b\u0434\u0440\u043e\u043c\u0431"
    ],
    "name:und_x_variant":[
        "Ko\u0142dr\u0105b"
    ],
    "wof:name":"Koldrab",
    "wof:placetype":"locality"
},
  "geometry": {"coordinates":[17.56754,52.73741],"type":"Point"}
}