{
  "type": "Feature",
  "properties": {
    "gn:admin1_code":"72.0",
    "gn:admin2_code":"202.0",
    "gn:admin3_code":"20205.0",
    "gn:asciiname":"Jozefowek",
    "gn:country_code":"PL",
    "gn:dem":383,
    "gn:feature_class":"P",
    "gn:feature_code":"PPL",
    "gn:name":"J\u00f3zef\u00f3wek",
    "gn:population":0,
    "gn:timezone":"Europe/Warsaw",
    "iso:country":"PL",
    "wof:name":"Jozefowek",
    "wof:placetype":"locality"
},
  "geometry": {"coordinates":[16.62558,50.66023],"type":"Point"}
}