{
  "type": "Feature",
  "properties": {
    "gn:admin1_code":"86.0",
    "gn:admin2_code":"3002.0",
    "gn:admin3_code":"300202.0",
    "gn:asciiname":"Gebice",
    "gn:country_code":"PL",
    "gn:dem":96,
    "gn:feature_class":"P",
    "gn:feature_code":"PPL",
    "gn:name":"G\u0119bice",
    "gn:population":0,
    "gn:timezone":"Europe/Warsaw",
    "iso:country":"PL",
    "name:azb_x_preferred":[
        "\u0642\u0646\u0628\u06cc\u062a\u0633\u0647"
    ],
    "name:ceb_x_preferred":[
        "G\u0119bice"
    ],
    "name:deu_x_preferred":[
        "G\u0119bice"
    ],
    "name:fas_x_preferred":[
        "\u06af\u0646\u0628\u06cc\u062a\u0633\u0647"
    ],
    "name:fra_x_preferred":[
        "G\u0119bice"
    ],
    "name:pol_x_preferred":[
        "G\u0119bice"
    ],
    "name:ukr_x_preferred":[
        "\u0413\u0435\u043c\u0431\u0456\u0446\u0435"
    ],
    "wof:name":"Gebice",
    "wof:placetype":"locality"
},
  "geometry": {"coordinates":[16.69387,52.90486],"type":"Point"}
}