{
  "type": "Feature",
  "properties": {
    "gn:admin1_code":"86.0",
    "gn:admin2_code":"3002.0",
    "gn:admin3_code":"300202.0",
    "gn:asciiname":"Gebice",
    "gn:country_code":"PL",
    "gn:dem":96,
    "gn:feature_class":"P",
    "gn:feature_code":"PPL",
    "gn:name":"G\u0119bice",
    "gn:population":0,
    "gn:timezone":"Europe/Warsaw",
    "iso:country":"PL",
    "name:und_x_variant":[
        "G\u0119bice"
    ],
    "wof:name":"Gebice",
    "wof:placetype":"locality"
},
  "geometry": {"coordinates":[16.69387,52.90486],"type":"Point"}
}