{
  "type": "Feature",
  "properties": {
    "gn:admin1_code":"81.0",
    "gn:admin2_code":"2002.0",
    "gn:admin3_code":"200207.0",
    "gn:asciiname":"Odnoga",
    "gn:country_code":"PL",
    "gn:dem":152,
    "gn:feature_class":"P",
    "gn:feature_code":"PPL",
    "gn:name":"Odnoga",
    "gn:population":0,
    "gn:timezone":"Europe/Warsaw",
    "iso:country":"PL",
    "wof:name":"Odnoga",
    "wof:placetype":"locality"
},
  "geometry": {"coordinates":[23.68333,52.96666999999999],"type":"Point"}
}