{
  "type": "Feature",
  "properties": {
    "iso:country":"PL",
    "name:ceb_x_preferred":[
        "Osiecznica"
    ],
    "name:fra_x_preferred":[
        "Osiecznica"
    ],
    "name:nld_x_preferred":[
        "Osiecznica"
    ],
    "name:pol_x_preferred":[
        "Osiecznica"
    ],
    "name:ukr_x_preferred":[
        "\u041e\u0441\u0435\u0447\u043d\u0438\u0446\u044f"
    ],
    "qs_pg:aaroncc":"PL",
    "qs_pg:name":"Osiecznica",
    "qs_pg:name_adm0":"Polska",
    "qs_pg:name_adm1":"Dolnosl\u0105skie",
    "qs_pg:photos":2,
    "qs_pg:photos_1k":1,
    "qs_pg:photos_9k":1,
    "qs_pg:photos_9r":3,
    "qs_pg:photos_all":82,
    "qs_pg:photos_sr":1,
    "qs_pg:pop_sr":0,
    "qs_pg:qs_pg_placetype":"localadmin",
    "qs_pg:qs_pg_placetype_gp":"LocalAdmin",
    "qs_pg:woe_adm0":23424923,
    "woe:adm0_id":23424923,
    "woe:name_adm0":"Polska",
    "woe:name_adm1":"Dolnosl\u0105skie",
    "woe:placetype":"LocalAdmin",
    "wof:name":"Osiecznica",
    "wof:placetype":"localadmin"
},
  "geometry": {"coordinates":[15.431156,51.331201],"type":"Point"}
}