{
  "type": "Feature",
  "properties": {
    "gn:admin1_code":"75.0",
    "gn:admin2_code":"615.0",
    "gn:admin3_code":"61506.0",
    "gn:asciiname":"Paszki Male",
    "gn:country_code":"PL",
    "gn:dem":142,
    "gn:feature_class":"P",
    "gn:feature_code":"PPL",
    "gn:name":"Paszki Ma\u0142e",
    "gn:population":0,
    "gn:timezone":"Europe/Warsaw",
    "iso:country":"PL",
    "name:fra_x_preferred":[
        "Paszki Ma\u0142e"
    ],
    "name:pol_x_preferred":[
        "Paszki Ma\u0142e"
    ],
    "name:ukr_x_preferred":[
        "\u041f\u0430\u0448\u043a\u0456-\u041c\u0430\u043b\u0456"
    ],
    "wof:name":"Paszki Male",
    "wof:placetype":"locality"
},
  "geometry": {"coordinates":[22.58113,51.74031],"type":"Point"}
}