{
  "type": "Feature",
  "properties": {
    "gn:admin1_code":"74.0",
    "gn:admin2_code":"1007.0",
    "gn:admin3_code":"100703.0",
    "gn:asciiname":"Stok",
    "gn:country_code":"PL",
    "gn:dem":208,
    "gn:feature_class":"P",
    "gn:feature_code":"PPL",
    "gn:name":"Stok",
    "gn:population":0,
    "gn:timezone":"Europe/Warsaw",
    "iso:country":"PL",
    "name:fra_x_preferred":[
        "Stok"
    ],
    "name:pol_x_preferred":[
        "Stok"
    ],
    "name:ukr_x_preferred":[
        "\u0421\u0442\u043e\u043a"
    ],
    "wof:name":"Stok",
    "wof:placetype":"locality"
},
  "geometry": {"coordinates":[20.08627000000001,51.35247],"type":"Point"}
}