{
  "type": "Feature",
  "properties": {
    "gn:admin1_code":"73.0",
    "gn:admin2_code":"408.0",
    "gn:admin3_code":"40809.0",
    "gn:asciiname":"Czarne",
    "gn:country_code":"PL",
    "gn:dem":109,
    "gn:feature_class":"P",
    "gn:feature_code":"PPL",
    "gn:name":"Czarne",
    "gn:population":0,
    "gn:timezone":"Europe/Warsaw",
    "iso:country":"PL",
    "name:pol_x_preferred":[
        "Czarne"
    ],
    "name:ukr_x_preferred":[
        "\u0427\u0430\u0440\u043d\u0435"
    ],
    "wof:name":"Czarne",
    "wof:placetype":"locality"
},
  "geometry": {"coordinates":[19.26085,52.78457],"type":"Point"}
}