{
  "type": "Feature",
  "properties": {
    "gn:admin1_code":"77.0",
    "gn:admin2_code":"1206.0",
    "gn:admin3_code":"120617.0",
    "gn:asciiname":"Januszowice",
    "gn:country_code":"PL",
    "gn:dem":257,
    "gn:feature_class":"P",
    "gn:feature_code":"PPL",
    "gn:name":"Januszowice",
    "gn:population":0,
    "gn:timezone":"Europe/Warsaw",
    "iso:country":"PL",
    "name:azb_x_preferred":[
        "\u06cc\u0627\u0646\u0648\u0634\u0648\u0648\u06cc\u062a\u0633\u0647"
    ],
    "name:fas_x_preferred":[
        "\u06cc\u0627\u0646\u0648\u0634\u0648\u0648\u06cc\u062a\u0633\u0647"
    ],
    "name:fra_x_preferred":[
        "Januszowice"
    ],
    "name:pol_x_preferred":[
        "Januszowice"
    ],
    "name:rus_x_preferred":[
        "\u042f\u043d\u0443\u0448\u043e\u0432\u0438\u0446\u0435"
    ],
    "name:ukr_x_preferred":[
        "\u042f\u043d\u0443\u0448\u043e\u0432\u0456\u0446\u0435"
    ],
    "name:urd_x_preferred":[
        "\u062c\u0627\u0646\u0633\u0632\u0648\u0648\u06a9\u06d2"
    ],
    "wof:name":"Januszowice",
    "wof:placetype":"locality"
},
  "geometry": {"coordinates":[19.89462,50.14587],"type":"Point"}
}