{
  "type": "Feature",
  "properties": {
    "gn:admin1_code":"81.0",
    "gn:admin2_code":"2001.0",
    "gn:admin3_code":"200107.0",
    "gn:asciiname":"Dluzanski Las",
    "gn:cc2":"PL",
    "gn:country_code":"PL",
    "gn:dem":120,
    "gn:feature_class":"P",
    "gn:feature_code":"PPL",
    "gn:name":"D\u0142u\u017ca\u0144ski Las",
    "gn:population":0,
    "gn:timezone":"Europe/Warsaw",
    "iso:country":"PL",
    "name:und_x_variant":[
        "D\u0142uwia\u0144ski Las",
        "D\u0142u\u017ca\u0144ski Las"
    ],
    "wof:name":"Dluzanski Las",
    "wof:placetype":"locality"
},
  "geometry": {"coordinates":[23.15,53.76667],"type":"Point"}
}