{
  "type": "Feature",
  "properties": {
    "gn:admin1_code":"83.0",
    "gn:admin2_code":"2411.0",
    "gn:admin3_code":"241108.0",
    "gn:asciiname":"Jastrzebie",
    "gn:country_code":"PL",
    "gn:dem":228,
    "gn:feature_class":"P",
    "gn:feature_code":"PPL",
    "gn:name":"Jastrz\u0119bie",
    "gn:population":0,
    "gn:timezone":"Europe/Warsaw",
    "iso:country":"PL",
    "name:und_x_variant":[
        "Jastrz\u0119bie"
    ],
    "wof:name":"Jastrzebie",
    "wof:placetype":"locality"
},
  "geometry": {"coordinates":[18.0989,50.1727],"type":"Point"}
}