{
  "type": "Feature",
  "properties": {
    "gn:admin1_code":"83.0",
    "gn:admin2_code":"2411.0",
    "gn:admin3_code":"241108.0",
    "gn:asciiname":"Jastrzebie",
    "gn:country_code":"PL",
    "gn:dem":228,
    "gn:feature_class":"P",
    "gn:feature_code":"PPL",
    "gn:name":"Jastrz\u0119bie",
    "gn:population":0,
    "gn:timezone":"Europe/Warsaw",
    "iso:country":"PL",
    "name:ceb_x_preferred":[
        "Jastrz\u0119bie"
    ],
    "name:deu_x_preferred":[
        "Jastrz\u0119bie"
    ],
    "name:pol_x_preferred":[
        "Jastrz\u0119bie"
    ],
    "name:ukr_x_preferred":[
        "\u042f\u0441\u0442\u0448\u0435\u043c\u0431\u0435"
    ],
    "name:urd_x_preferred":[
        "\u062c\u0633\u062a\u0631\u0632\u06cc\u0628\u06d2"
    ],
    "wof:name":"Jastrzebie",
    "wof:placetype":"locality"
},
  "geometry": {"coordinates":[18.0989,50.1727],"type":"Point"}
}