{
  "type": "Feature",
  "properties": {
    "gn:admin1_code":"86.0",
    "gn:admin2_code":"3010.0",
    "gn:admin3_code":"301004.0",
    "gn:asciiname":"Slawoszewo",
    "gn:country_code":"PL",
    "gn:dem":97,
    "gn:feature_class":"P",
    "gn:feature_code":"PPL",
    "gn:name":"S\u0142awoszewo",
    "gn:population":0,
    "gn:timezone":"Europe/Warsaw",
    "iso:country":"PL",
    "name:fra_x_preferred":[
        "S\u0142awoszewo"
    ],
    "name:pol_x_preferred":[
        "S\u0142awoszewo"
    ],
    "name:ukr_x_preferred":[
        "\u0421\u043b\u0430\u0432\u043e\u0448\u0435\u0432\u043e"
    ],
    "wof:name":"Slawoszewo",
    "wof:placetype":"locality"
},
  "geometry": {"coordinates":[18.23647,52.38581],"type":"Point"}
}