{
  "type": "Feature",
  "properties": {
    "gn:admin1_code":"78.0",
    "gn:admin2_code":"1426.0",
    "gn:admin3_code":"142603.0",
    "gn:asciiname":"Wilczonek",
    "gn:country_code":"PL",
    "gn:dem":144,
    "gn:feature_class":"P",
    "gn:feature_code":"PPL",
    "gn:name":"Wilczonek",
    "gn:population":0,
    "gn:timezone":"Europe/Warsaw",
    "iso:country":"PL",
    "name:azb_x_preferred":[
        "\u0648\u06cc\u0644\u0686\u0648\u0646\u06a9"
    ],
    "name:ceb_x_preferred":[
        "Wilczonek"
    ],
    "name:fas_x_preferred":[
        "\u0648\u06cc\u0644\u0686\u0648\u0646\u06a9"
    ],
    "name:fra_x_preferred":[
        "Wilczonek"
    ],
    "name:oci_x_preferred":[
        "Wilczonek"
    ],
    "name:pol_x_preferred":[
        "Wilczonek"
    ],
    "name:szl_x_preferred":[
        "Wilcz\u016fnek"
    ],
    "name:ukr_x_preferred":[
        "\u0412\u0456\u043b\u044c\u0447\u043e\u043d\u0435\u043a"
    ],
    "wof:name":"Wilczonek",
    "wof:placetype":"locality"
},
  "geometry": {"coordinates":[22.02325,52.18488],"type":"Point"}
}