{
  "type": "Feature",
  "properties": {
    "gn:admin1_code":"78.0",
    "gn:admin2_code":"1426.0",
    "gn:admin3_code":"142603.0",
    "gn:asciiname":"Wilczonek",
    "gn:country_code":"PL",
    "gn:dem":144,
    "gn:feature_class":"P",
    "gn:feature_code":"PPL",
    "gn:name":"Wilczonek",
    "gn:population":0,
    "gn:timezone":"Europe/Warsaw",
    "iso:country":"PL",
    "wof:name":"Wilczonek",
    "wof:placetype":"locality"
},
  "geometry": {"coordinates":[22.02325,52.18488],"type":"Point"}
}