{
  "type": "Feature",
  "properties": {
    "gn:country":"PL",
    "gn:fcode":"PPL",
    "gn:population":1830,
    "iso:country":"PL",
    "name:bel_x_preferred":[
        "\u041b\u044e\u0431\u043e\u043c\u0435\u0436"
    ],
    "name:ceb_x_preferred":[
        "Lubomierz"
    ],
    "name:ces_x_preferred":[
        "Lubomierz"
    ],
    "name:deu_x_preferred":[
        "Lubomierz"
    ],
    "name:epo_x_preferred":[
        "Lubomierz"
    ],
    "name:fra_x_preferred":[
        "Lubomierz"
    ],
    "name:hun_x_preferred":[
        "Lubomierz"
    ],
    "name:jav_x_preferred":[
        "Lubomierz"
    ],
    "name:lav_x_preferred":[
        "Lubome\u017ea"
    ],
    "name:msa_x_preferred":[
        "Lubomierz"
    ],
    "name:nld_x_preferred":[
        "Lubomierz"
    ],
    "name:pol_x_preferred":[
        "Lubomierz"
    ],
    "name:por_x_preferred":[
        "Lubomierz"
    ],
    "name:ron_x_preferred":[
        "Lubomierz"
    ],
    "name:rus_x_preferred":[
        "\u041b\u044e\u0431\u043e\u043c\u0435\u0436"
    ],
    "name:slk_x_preferred":[
        "Lubomierz"
    ],
    "name:srp_x_preferred":[
        "\u041b\u0443\u0431\u043e\u043c\u0458\u0435\u0436"
    ],
    "name:swe_x_preferred":[
        "Lubomierz"
    ],
    "name:tha_x_preferred":[
        "\u0e25\u0e39\u0e1a\u0e2d\u0e21\u0e35\u0e41\u0e22\u0e0a"
    ],
    "name:ukr_x_preferred":[
        "\u041b\u044e\u0431\u043e\u043c\u0435\u0436"
    ],
    "name:vie_x_preferred":[
        "Lubomierz"
    ],
    "qs_pg:aaroncc":"PL",
    "qs_pg:gn_country":"PL",
    "qs_pg:gn_fcode":"PPL",
    "qs_pg:gn_pop":1830,
    "qs_pg:name":"Lubomierz",
    "qs_pg:name_adm0":"Polska",
    "qs_pg:name_adm1":"Ma\u0142opolskie",
    "qs_pg:photos":41,
    "qs_pg:photos_1k":8,
    "qs_pg:photos_9k":1,
    "qs_pg:photos_9r":2,
    "qs_pg:photos_all":41,
    "qs_pg:photos_sr":2,
    "qs_pg:pop_sr":3,
    "qs_pg:qs_pg_placetype":"locality",
    "qs_pg:qs_pg_placetype_gp":"Town",
    "qs_pg:woe_adm0":23424923,
    "woe:adm0_id":23424923,
    "woe:name_adm0":"Polska",
    "woe:name_adm1":"Ma\u0142opolskie",
    "woe:placetype":"Town",
    "wof:name":"Lubomierz",
    "wof:placetype":"locality",
    "wof:population":1830
},
  "geometry": {"coordinates":[20.20214,49.60854],"type":"Point"}
}