{
  "type": "Feature",
  "properties": {
    "gn:admin1_code":"82.0",
    "gn:admin2_code":"2212.0",
    "gn:admin3_code":"221206.0",
    "gn:asciiname":"Plaszewo",
    "gn:country_code":"PL",
    "gn:dem":55,
    "gn:feature_class":"P",
    "gn:feature_code":"PPL",
    "gn:name":"P\u0142aszewo",
    "gn:population":0,
    "gn:timezone":"Europe/Warsaw",
    "iso:country":"PL",
    "name:azb_x_preferred":[
        "\u067e\u0648\u0627\u0634\u0648\u0648"
    ],
    "name:csb_x_preferred":[
        "P\u0142aszew\u00f2"
    ],
    "name:deu_x_preferred":[
        "P\u0142aszewo"
    ],
    "name:fas_x_preferred":[
        "\u067e\u0648\u0627\u0634\u0648\u0648"
    ],
    "name:pol_x_preferred":[
        "P\u0142aszewo"
    ],
    "name:ukr_x_preferred":[
        "\u041f\u043b\u0430\u0448\u0435\u0432\u043e"
    ],
    "name:und_x_variant":[
        "P\u0142aszewo"
    ],
    "wof:name":"Plaszewo",
    "wof:placetype":"locality"
},
  "geometry": {"coordinates":[17.00521,54.32324000000001],"type":"Point"}
}