{
  "type": "Feature",
  "properties": {
    "gn:admin1_code":"75.0",
    "gn:admin2_code":"620.0",
    "gn:admin3_code":"62003.0",
    "gn:asciiname":"Komarow-Osada",
    "gn:country_code":"PL",
    "gn:dem":234,
    "gn:feature_class":"P",
    "gn:feature_code":"PPL",
    "gn:name":"Komar\u00f3w-Osada",
    "gn:population":0,
    "gn:timezone":"Europe/Warsaw",
    "iso:country":"PL",
    "name:und_x_variant":[
        "Komar\u00f3w-Osada",
        "Komar\u00f3w"
    ],
    "wof:name":"Komarow-Osada",
    "wof:placetype":"locality"
},
  "geometry": {"coordinates":[23.46592,50.62491],"type":"Point"}
}