{
  "type": "Feature",
  "properties": {
    "gn:admin1_code":"75.0",
    "gn:admin2_code":"620.0",
    "gn:admin3_code":"62003.0",
    "gn:asciiname":"Komarow-Osada",
    "gn:country_code":"PL",
    "gn:dem":234,
    "gn:feature_class":"P",
    "gn:feature_code":"PPL",
    "gn:name":"Komar\u00f3w-Osada",
    "gn:population":0,
    "gn:timezone":"Europe/Warsaw",
    "iso:country":"PL",
    "name:azb_x_preferred":[
        "\u06a9\u0648\u0645\u0627\u0631\u0648\u0648-\u0627\u0648\u0633\u0627\u062f\u0627"
    ],
    "name:fas_x_preferred":[
        "\u06a9\u0648\u0645\u0627\u0631\u0648\u0648-\u0627\u0648\u0633\u0627\u062f\u0627"
    ],
    "name:fra_x_preferred":[
        "Komar\u00f3w-Osada"
    ],
    "name:heb_x_preferred":[
        "\u05e7\u05d5\u05de\u05d0\u05e8\u05d5\u05d1 \u05d0\u05d5\u05e1\u05d0\u05d3\u05d4"
    ],
    "name:nld_x_preferred":[
        "Komar\u00f3w-Osada"
    ],
    "name:pol_x_preferred":[
        "Komar\u00f3w-Osada"
    ],
    "name:ukr_x_preferred":[
        "\u041a\u043e\u043c\u0430\u0440\u0443\u0432-\u041e\u0441\u0430\u0434\u0430"
    ],
    "name:und_x_variant":[
        "Komar\u00f3w"
    ],
    "name:vie_x_preferred":[
        "Komar\u00f3w-Osada"
    ],
    "wof:name":"Komarow-Osada",
    "wof:placetype":"locality"
},
  "geometry": {"coordinates":[23.46592,50.62491],"type":"Point"}
}