{
  "type": "Feature",
  "properties": {
    "gn:admin1_code":"83.0",
    "gn:admin2_code":"2411.0",
    "gn:admin3_code":"241106.0",
    "gn:asciiname":"Szymocice",
    "gn:country_code":"PL",
    "gn:dem":239,
    "gn:feature_class":"P",
    "gn:feature_code":"PPL",
    "gn:name":"Szymocice",
    "gn:population":0,
    "gn:timezone":"Europe/Warsaw",
    "iso:country":"PL",
    "name:azb_x_preferred":[
        "\u0634\u0645\u0648\u0686\u06cc\u062a\u0633\u0647"
    ],
    "name:ceb_x_preferred":[
        "Szymocice"
    ],
    "name:fas_x_preferred":[
        "\u0634\u0645\u0648\u0686\u06cc\u062a\u0633\u0647"
    ],
    "name:nld_x_preferred":[
        "Szymocice"
    ],
    "name:pol_x_preferred":[
        "Szymocice"
    ],
    "name:ukr_x_preferred":[
        "\u0428\u0438\u043c\u043e\u0446\u0438\u0446\u0435"
    ],
    "wof:name":"Szymocice",
    "wof:placetype":"locality"
},
  "geometry": {"coordinates":[18.37189,50.16238],"type":"Point"}
}