{
  "type": "Feature",
  "properties": {
    "gn:admin1_code":"85.0",
    "gn:admin2_code":"2812.0",
    "gn:admin3_code":"281202.0",
    "gn:asciiname":"Piotrowice",
    "gn:country_code":"PL",
    "gn:dem":90,
    "gn:feature_class":"P",
    "gn:feature_code":"PPL",
    "gn:name":"Piotrowice",
    "gn:population":0,
    "gn:timezone":"Europe/Warsaw",
    "iso:country":"PL",
    "name:und_x_variant":[
        "Gross Peterwitz"
    ],
    "wof:name":"Piotrowice",
    "wof:placetype":"locality"
},
  "geometry": {"coordinates":[19.3416,53.525],"type":"Point"}
}