{
  "type": "Feature",
  "properties": {
    "gn:admin1_code":"79.0",
    "gn:admin2_code":"1602.0",
    "gn:admin3_code":"160203.0",
    "gn:asciiname":"Ciermiecice",
    "gn:country_code":"PL",
    "gn:dem":332,
    "gn:feature_class":"P",
    "gn:feature_code":"PPL",
    "gn:name":"Ciermi\u0119cice",
    "gn:population":0,
    "gn:timezone":"Europe/Warsaw",
    "iso:country":"PL",
    "wof:name":"Ciermiecice",
    "wof:placetype":"locality"
},
  "geometry": {"coordinates":[17.7182,50.11318],"type":"Point"}
}