{
  "type": "Feature",
  "properties": {
    "gn:admin1_code":"78.0",
    "gn:admin2_code":"1426.0",
    "gn:admin3_code":"142613.0",
    "gn:asciiname":"Tarcze",
    "gn:country_code":"PL",
    "gn:dem":167,
    "gn:feature_class":"P",
    "gn:feature_code":"PPL",
    "gn:name":"Tarcze",
    "gn:population":0,
    "gn:timezone":"Europe/Warsaw",
    "iso:country":"PL",
    "name:ceb_x_preferred":[
        "Tarcze"
    ],
    "name:fra_x_preferred":[
        "Tarcze"
    ],
    "name:pol_x_preferred":[
        "Tarcze"
    ],
    "name:szl_x_preferred":[
        "Tarcze"
    ],
    "name:ukr_x_preferred":[
        "\u0422\u0430\u0440\u0447\u0435"
    ],
    "wof:name":"Tarcze",
    "wof:placetype":"locality"
},
  "geometry": {"coordinates":[22.41589,52.13607],"type":"Point"}
}