{
  "type": "Feature",
  "properties": {
    "gn:admin1_code":"84.0",
    "gn:admin2_code":"2612.0",
    "gn:admin3_code":"261206.0",
    "gn:asciiname":"Strzegomek",
    "gn:country_code":"PL",
    "gn:dem":180,
    "gn:feature_class":"P",
    "gn:feature_code":"PPL",
    "gn:name":"Strzegomek",
    "gn:population":0,
    "gn:timezone":"Europe/Warsaw",
    "iso:country":"PL",
    "name:pol_x_preferred":[
        "Strzegomek"
    ],
    "name:ukr_x_preferred":[
        "\u0421\u0442\u0448\u0435\u0491\u043e\u043c\u0435\u043a"
    ],
    "wof:name":"Strzegomek",
    "wof:placetype":"locality"
},
  "geometry": {"coordinates":[21.31013,50.52521],"type":"Point"}
}