{
  "type": "Feature",
  "properties": {
    "gn:admin1_code":"87.0",
    "gn:admin2_code":"3203.0",
    "gn:admin3_code":"320302.0",
    "gn:asciiname":"Mielenko Drawskie",
    "gn:country_code":"PL",
    "gn:dem":100,
    "gn:feature_class":"P",
    "gn:feature_code":"PPL",
    "gn:name":"Mielenko Drawskie",
    "gn:population":0,
    "gn:timezone":"Europe/Warsaw",
    "iso:country":"PL",
    "name:deu_x_historical":[
        "Klein Mellen"
    ],
    "name:deu_x_preferred":[
        "Klein Mellen"
    ],
    "wof:name":"Mielenko Drawskie",
    "wof:placetype":"locality"
},
  "geometry": {"coordinates":[15.79711,53.49169000000001],"type":"Point"}
}