{
  "type": "Feature",
  "properties": {
    "gn:admin1_code":"87.0",
    "gn:admin2_code":"3203.0",
    "gn:admin3_code":"320302.0",
    "gn:asciiname":"Mielenko Drawskie",
    "gn:country_code":"PL",
    "gn:dem":100,
    "gn:feature_class":"P",
    "gn:feature_code":"PPL",
    "gn:name":"Mielenko Drawskie",
    "gn:population":0,
    "gn:timezone":"Europe/Warsaw",
    "iso:country":"PL",
    "name:deu_x_historical":[
        "Klein Mellen"
    ],
    "name:deu_x_preferred":[
        "Klein Mellen"
    ],
    "name:pol_x_preferred":[
        "Mielenko Drawskie"
    ],
    "name:ukr_x_preferred":[
        "\u041c\u0435\u043b\u0435\u043d\u043a\u043e-\u0414\u0440\u0430\u0432\u0441\u044c\u043a\u0435"
    ],
    "name:vie_x_preferred":[
        "Mielenko Drawskie"
    ],
    "wof:name":"Mielenko Drawskie",
    "wof:placetype":"locality"
},
  "geometry": {"coordinates":[15.79711,53.49169000000001],"type":"Point"}
}