{
  "type": "Feature",
  "properties": {
    "gn:admin1_code":"86.0",
    "gn:admin2_code":"3007.0",
    "gn:admin3_code":"300701.0",
    "gn:asciiname":"Jastrzebniki",
    "gn:country_code":"PL",
    "gn:dem":114,
    "gn:feature_class":"P",
    "gn:feature_code":"PPL",
    "gn:name":"Jastrz\u0119bniki",
    "gn:population":0,
    "gn:timezone":"Europe/Warsaw",
    "iso:country":"PL",
    "name:pol_x_preferred":[
        "Jastrz\u0119bniki"
    ],
    "name:ukr_x_preferred":[
        "\u042f\u0441\u0442\u0448\u0435\u043c\u0431\u043d\u0438\u043a\u0438"
    ],
    "name:urd_x_preferred":[
        "\u062c\u0633\u062a\u0631\u0632\u06cc\u0628\u0646\u06a9\u06cc"
    ],
    "wof:name":"Jastrzebniki",
    "wof:placetype":"locality"
},
  "geometry": {"coordinates":[18.03032,51.84916],"type":"Point"}
}