{
  "type": "Feature",
  "properties": {
    "gn:admin1_code":"86.0",
    "gn:admin2_code":"3007.0",
    "gn:admin3_code":"300701.0",
    "gn:asciiname":"Jastrzebniki",
    "gn:country_code":"PL",
    "gn:dem":114,
    "gn:feature_class":"P",
    "gn:feature_code":"PPL",
    "gn:name":"Jastrz\u0119bniki",
    "gn:population":0,
    "gn:timezone":"Europe/Warsaw",
    "iso:country":"PL",
    "name:und_x_variant":[
        "Jastrz\u0119bniki"
    ],
    "wof:name":"Jastrzebniki",
    "wof:placetype":"locality"
},
  "geometry": {"coordinates":[18.03032,51.84916],"type":"Point"}
}