{
  "type": "Feature",
  "properties": {
    "iso:country":"PL",
    "name:ceb_x_preferred":[
        "Boniewo"
    ],
    "name:fra_x_preferred":[
        "Boniewo"
    ],
    "name:nld_x_preferred":[
        "Boniewo"
    ],
    "name:pol_x_preferred":[
        "Boniewo"
    ],
    "name:rus_x_preferred":[
        "\u0411\u043e\u043d\u0435\u0432\u043e"
    ],
    "name:ukr_x_preferred":[
        "\u0411\u043e\u043d\u0435\u0432\u043e"
    ],
    "wof:coterminous":[
        1125397147
    ],
    "wof:name":"Boniewo",
    "wof:placetype":"locality"
},
  "geometry": {"coordinates":[18.891076194165,52.4586474966969],"type":"Point"}
}