{
  "type": "Feature",
  "properties": {
    "iso:country":"PL",
    "name:pol_x_preferred":[
        "Boniewo"
    ],
    "wof:name":"Boniewo",
    "wof:placetype":"locality"
},
  "geometry": {"coordinates":[18.891076194165,52.4586474966969],"type":"Point"}
}