{
  "type": "Feature",
  "properties": {
    "iso:country":"PL",
    "name:eng_x_preferred":[
        "Nowa Ukta"
    ],
    "name:fre_x_preferred":[
        "Nowa Ukta"
    ],
    "name:pol_x_preferred":[
        "Nowa Ukta"
    ],
    "qs_pg:aaroncc":"PL",
    "qs_pg:name":"Nowa Ukta",
    "qs_pg:name_adm0":"Polska",
    "qs_pg:name_adm1":"Warminsko-Mazurskie",
    "qs_pg:photos":63,
    "qs_pg:photos_1k":13,
    "qs_pg:photos_9k":1,
    "qs_pg:photos_9r":2,
    "qs_pg:photos_all":63,
    "qs_pg:photos_sr":2,
    "qs_pg:pop_sr":0,
    "qs_pg:qs_pg_placetype":"locality",
    "qs_pg:qs_pg_placetype_gp":"Town",
    "qs_pg:woe_adm0":23424923,
    "woe:adm0_id":23424923,
    "woe:name_adm0":"Polska",
    "woe:name_adm1":"Warminsko-Mazurskie",
    "woe:placetype":"Town",
    "wof:name":"Nowa Ukta",
    "wof:placetype":"locality"
},
  "geometry": {"coordinates":[21.489257,53.713523],"type":"Point"}
}