{
  "type": "Feature",
  "properties": {
    "gn:admin1_code":"75.0",
    "gn:admin2_code":"607.0",
    "gn:admin3_code":"60706.0",
    "gn:asciiname":"Kaczynice",
    "gn:country_code":"PL",
    "gn:dem":250,
    "gn:feature_class":"P",
    "gn:feature_code":"PPL",
    "gn:name":"Kaczynice",
    "gn:population":0,
    "gn:timezone":"Europe/Warsaw",
    "iso:country":"PL",
    "wof:name":"Kaczynice",
    "wof:placetype":"locality"
},
  "geometry": {"coordinates":[22.38333,50.88333],"type":"Point"}
}