{
  "type": "Feature",
  "properties": {
    "gn:admin1_code":"78.0",
    "gn:admin2_code":"1422.0",
    "gn:admin3_code":"142202.0",
    "gn:asciiname":"Scieciel",
    "gn:cc2":"PL",
    "gn:country_code":"PL",
    "gn:dem":123,
    "gn:feature_class":"P",
    "gn:feature_code":"PPL",
    "gn:name":"\u015aci\u0119ciel",
    "gn:population":0,
    "gn:timezone":"Europe/Warsaw",
    "iso:country":"PL",
    "name:fra_x_preferred":[
        "\u015aci\u0119ciel"
    ],
    "name:pol_x_preferred":[
        "\u015aci\u0119ciel"
    ],
    "name:ukr_x_preferred":[
        "\u0421\u044c\u0446\u0435\u043d\u0446\u0435\u043b\u044c"
    ],
    "name:und_x_variant":[
        "Czencze",
        "Rodefeld"
    ],
    "wof:name":"Scieciel",
    "wof:placetype":"locality"
},
  "geometry": {"coordinates":[20.93445,53.32964000000001],"type":"Point"}
}