{
  "type": "Feature",
  "properties": {
    "gn:admin1_code":"85.0",
    "gn:admin2_code":"2807.0",
    "gn:admin3_code":"280706.0",
    "gn:asciiname":"Krzywiec",
    "gn:country_code":"PL",
    "gn:dem":104,
    "gn:feature_class":"P",
    "gn:feature_code":"PPL",
    "gn:name":"Krzywiec",
    "gn:population":0,
    "gn:timezone":"Europe/Warsaw",
    "iso:country":"PL",
    "name:pol_x_preferred":[
        "Krzywiec"
    ],
    "name:ukr_x_preferred":[
        "\u041a\u0448\u0438\u0432\u0435\u0446\u044c"
    ],
    "name:und_x_variant":[
        "Freiwalde"
    ],
    "wof:name":"Krzywiec",
    "wof:placetype":"locality"
},
  "geometry": {"coordinates":[19.33573,53.65839],"type":"Point"}
}