{
  "type": "Feature",
  "properties": {
    "gn:admin1_code":"80.0",
    "gn:admin2_code":"1817.0",
    "gn:admin3_code":"181708.0",
    "gn:asciiname":"Posada Jacmierska",
    "gn:country_code":"PL",
    "gn:dem":296,
    "gn:feature_class":"P",
    "gn:feature_code":"PPL",
    "gn:name":"Posada Ja\u0107mierska",
    "gn:population":0,
    "gn:timezone":"Europe/Warsaw",
    "iso:country":"PL",
    "name:deu_x_preferred":[
        "Posada Ja\u0107mierska"
    ],
    "name:pol_x_preferred":[
        "Posada Ja\u0107mierska"
    ],
    "name:ukr_x_preferred":[
        "\u041f\u043e\u0441\u0430\u0434\u0430 \u042f\u0447\u043c\u0456\u0440\u0441\u044c\u043a\u0430"
    ],
    "wof:name":"Posada Jacmierska",
    "wof:placetype":"locality"
},
  "geometry": {"coordinates":[22.02175,49.61305],"type":"Point"}
}