{
  "type": "Feature",
  "properties": {
    "gn:admin1_code":"85.0",
    "gn:admin2_code":"2804.0",
    "gn:admin3_code":"280404.0",
    "gn:asciiname":"Stare Dolno",
    "gn:cc2":"PL",
    "gn:country_code":"PL",
    "gn:dem":0,
    "gn:feature_class":"P",
    "gn:feature_code":"PPL",
    "gn:name":"Stare Dolno",
    "gn:population":0,
    "gn:timezone":"Europe/Warsaw",
    "iso:country":"PL",
    "name:ceb_x_preferred":[
        "Stare Dolno"
    ],
    "name:pol_x_preferred":[
        "Stare Dolno"
    ],
    "name:ukr_x_preferred":[
        "\u0421\u0442\u0430\u0440\u0435 \u0414\u043e\u043b\u044c\u043d\u043e"
    ],
    "name:und_x_variant":[
        "Alt Dollst\u00e4dt",
        "Stare Dolno"
    ],
    "wof:name":"Stare Dolno",
    "wof:placetype":"locality"
},
  "geometry": {"coordinates":[19.41765,54.00151],"type":"Point"}
}