{
  "type": "Feature",
  "properties": {
    "gn:admin1_code":"83.0",
    "gn:admin2_code":"2404.0",
    "gn:admin3_code":"240412.0",
    "gn:asciiname":"Biskupice Krzemionka",
    "gn:country_code":"PL",
    "gn:dem":333,
    "gn:feature_class":"P",
    "gn:feature_code":"PPL",
    "gn:name":"Biskupice Krzemionka",
    "gn:population":0,
    "gn:timezone":"Europe/Warsaw",
    "iso:country":"PL",
    "wof:name":"Biskupice Krzemionka",
    "wof:placetype":"locality"
},
  "geometry": {"coordinates":[19.30308,50.7069],"type":"Point"}
}