{
  "type": "Feature",
  "properties": {
    "gn:admin1_code":"75.0",
    "gn:admin2_code":"615.0",
    "gn:admin3_code":"61501.0",
    "gn:asciiname":"Kozirynek Nowy",
    "gn:country_code":"PL",
    "gn:dem":144,
    "gn:feature_class":"P",
    "gn:feature_code":"PPL",
    "gn:name":"Kozirynek Nowy",
    "gn:population":0,
    "gn:timezone":"Europe/Warsaw",
    "iso:country":"PL",
    "wof:name":"Kozirynek Nowy",
    "wof:placetype":"locality"
},
  "geometry": {"coordinates":[22.64523,51.78044000000001],"type":"Point"}
}