{
  "type": "Feature",
  "properties": {
    "gn:admin1_code":"78.0",
    "gn:admin2_code":"1426.0",
    "gn:admin3_code":"142612.0",
    "gn:asciiname":"Mlynki",
    "gn:country_code":"PL",
    "gn:dem":165,
    "gn:feature_class":"P",
    "gn:feature_code":"PPL",
    "gn:name":"M\u0142ynki",
    "gn:population":0,
    "gn:timezone":"Europe/Warsaw",
    "iso:country":"PL",
    "name:fra_x_preferred":[
        "M\u0142ynki"
    ],
    "name:pol_x_preferred":[
        "M\u0142ynki"
    ],
    "name:ukr_x_preferred":[
        "\u041c\u043b\u0438\u043d\u043a\u0456"
    ],
    "name:und_x_variant":[
        "M\u0142ynki"
    ],
    "wof:name":"Mlynki",
    "wof:placetype":"locality"
},
  "geometry": {"coordinates":[22.04461,52.04473],"type":"Point"}
}