{
  "type": "Feature",
  "properties": {
    "gn:admin1_code":"85.0",
    "gn:admin2_code":"2814.0",
    "gn:admin3_code":"281407.0",
    "gn:asciiname":"Balag",
    "gn:country_code":"PL",
    "gn:dem":118,
    "gn:feature_class":"P",
    "gn:feature_code":"PPL",
    "gn:name":"Ba\u0142\u0105g",
    "gn:population":0,
    "gn:timezone":"Europe/Warsaw",
    "iso:country":"PL",
    "name:pol_x_preferred":[
        "Ba\u0142\u0105g"
    ],
    "name:ukr_x_preferred":[
        "\u0411\u0430\u043b\u043e\u043d\u0491"
    ],
    "name:und_x_variant":[
        "Ballingen",
        "Ba\u0142\u0105g"
    ],
    "wof:name":"Balag",
    "wof:placetype":"locality"
},
  "geometry": {"coordinates":[20.21883,53.82569],"type":"Point"}
}