{
  "type": "Feature",
  "properties": {
    "gn:admin1_code":"85.0",
    "gn:admin2_code":"2813.0",
    "gn:admin3_code":"281304.0",
    "gn:asciiname":"Gatno Dierwsze",
    "gn:country_code":"PL",
    "gn:dem":152,
    "gn:feature_class":"P",
    "gn:feature_code":"PPL",
    "gn:name":"Gatno Dierwsze",
    "gn:population":0,
    "gn:timezone":"Europe/Warsaw",
    "iso:country":"PL",
    "wof:name":"Gatno Dierwsze",
    "wof:placetype":"locality"
},
  "geometry": {"coordinates":[22.46667,53.93333000000001],"type":"Point"}
}