{
  "type": "Feature",
  "properties": {
    "gn:country":"PL",
    "gn:fcode":"PPL",
    "gn:population":265,
    "iso:country":"PL",
    "name:ceb_x_preferred":[
        "Pokrzywnica"
    ],
    "name:deu_x_preferred":[
        "Pokrzywnica"
    ],
    "name:fra_x_preferred":[
        "Pokrzywnica"
    ],
    "name:nld_x_preferred":[
        "Pokrzywnica"
    ],
    "name:pol_x_preferred":[
        "Pokrzywnica"
    ],
    "name:ukr_x_preferred":[
        "\u041f\u043e\u043a\u0448\u0438\u0432\u043d\u0438\u0446\u044f"
    ],
    "qs_pg:aaroncc":"PL",
    "qs_pg:gn_country":"PL",
    "qs_pg:gn_fcode":"PPL",
    "qs_pg:gn_pop":265,
    "qs_pg:name":"Pokrzywnica",
    "qs_pg:name_adm0":"Polska",
    "qs_pg:name_adm1":"Wielkopolskie",
    "qs_pg:photos_9r":0,
    "qs_pg:photos_sr":0,
    "qs_pg:pop_sr":2,
    "qs_pg:qs_pg_placetype":"locality",
    "qs_pg:qs_pg_placetype_gp":"Town",
    "qs_pg:woe_adm0":23424923,
    "woe:adm0_id":23424923,
    "woe:name_adm0":"Polska",
    "woe:name_adm1":"Wielkopolskie",
    "woe:placetype":"Town",
    "wof:name":"Pokrzywnica",
    "wof:placetype":"locality",
    "wof:population":265
},
  "geometry": {"coordinates":[16.57803,53.1496],"type":"Point"}
}