{
  "type": "Feature",
  "properties": {
    "gn:country":"PL",
    "gn:fcode":"PPL",
    "gn:population":400,
    "iso:country":"PL",
    "name:ceb_x_preferred":[
        "Niegos\u0142awice"
    ],
    "name:fra_x_preferred":[
        "Niegos\u0142awice"
    ],
    "name:nld_x_preferred":[
        "Niegos\u0142awice"
    ],
    "name:pol_x_preferred":[
        "Niegos\u0142awice"
    ],
    "name:ukr_x_preferred":[
        "\u041d\u0435\u0491\u043e\u0441\u043b\u0430\u0432\u0456\u0446\u0435"
    ],
    "qs_pg:aaroncc":"PL",
    "qs_pg:gn_country":"PL",
    "qs_pg:gn_fcode":"PPL",
    "qs_pg:gn_pop":400,
    "qs_pg:name":"Niegos\u0142awice",
    "qs_pg:name_adm0":"Polska",
    "qs_pg:name_adm1":"Swi\u0119tokrzyskie",
    "qs_pg:photos_9k":1,
    "qs_pg:photos_9r":1,
    "qs_pg:photos_all":1,
    "qs_pg:photos_sr":0,
    "qs_pg:pop_sr":2,
    "qs_pg:qs_pg_placetype":"locality",
    "qs_pg:qs_pg_placetype_gp":"Town",
    "qs_pg:woe_adm0":23424923,
    "woe:adm0_id":23424923,
    "woe:name_adm0":"Polska",
    "woe:name_adm1":"Swi\u0119tokrzyskie",
    "woe:placetype":"Town",
    "wof:name":"Niegos\u0142awice",
    "wof:placetype":"locality",
    "wof:population":400
},
  "geometry": {"coordinates":[20.31767,50.52194],"type":"Point"}
}