{
  "type": "Feature",
  "properties": {
    "gn:admin1_code":"84.0",
    "gn:admin2_code":"2611.0",
    "gn:admin3_code":"261104.0",
    "gn:asciiname":"Bukowka",
    "gn:country_code":"PL",
    "gn:dem":276,
    "gn:feature_class":"P",
    "gn:feature_code":"PPL",
    "gn:name":"Buk\u00f3wka",
    "gn:population":0,
    "gn:timezone":"Europe/Warsaw",
    "iso:country":"PL",
    "name:ceb_x_preferred":[
        "Buk\u00f3wka"
    ],
    "name:fra_x_preferred":[
        "Buk\u00f3wka"
    ],
    "name:pol_x_preferred":[
        "Buk\u00f3wka"
    ],
    "name:ukr_x_preferred":[
        "\u0411\u0443\u043a\u0443\u0432\u043a\u0430"
    ],
    "name:und_x_variant":[
        "Buk\u00f3wka"
    ],
    "wof:name":"Bukowka",
    "wof:placetype":"locality"
},
  "geometry": {"coordinates":[21.14153,50.95057],"type":"Point"}
}