{
  "type": "Feature",
  "properties": {
    "gn:admin1_code":"82.0",
    "gn:admin2_code":"2214.0",
    "gn:admin3_code":"221402.0",
    "gn:asciiname":"Cieple",
    "gn:country_code":"PL",
    "gn:dem":54,
    "gn:feature_class":"P",
    "gn:feature_code":"PPL",
    "gn:name":"Ciep\u0142e",
    "gn:population":0,
    "gn:timezone":"Europe/Warsaw",
    "iso:country":"PL",
    "name:ceb_x_preferred":[
        "Ciep\u0142e"
    ],
    "name:pol_x_preferred":[
        "Ciep\u0142e"
    ],
    "name:ukr_x_preferred":[
        "\u0426\u0435\u043f\u043b\u0435"
    ],
    "wof:name":"Cieple",
    "wof:placetype":"locality"
},
  "geometry": {"coordinates":[18.83917000000001,53.85478000000001],"type":"Point"}
}