{
  "type": "Feature",
  "properties": {
    "gn:admin1_code":"82.0",
    "gn:admin2_code":"2208.0",
    "gn:admin3_code":"220805.0",
    "gn:asciiname":"Bialogarda",
    "gn:country_code":"PL",
    "gn:dem":44,
    "gn:feature_class":"P",
    "gn:feature_code":"PPL",
    "gn:name":"Bia\u0142ogarda",
    "gn:population":0,
    "gn:timezone":"Europe/Warsaw",
    "iso:country":"PL",
    "name:azb_x_preferred":[
        "\u0628\u06cc\u0627\u0648\u0648\u0642\u0627\u0631\u062f\u0627"
    ],
    "name:ceb_x_preferred":[
        "Bia\u0142ogarda"
    ],
    "name:csb_x_preferred":[
        "Bi\u00f4\u0142ogarda"
    ],
    "name:deu_x_preferred":[
        "Bia\u0142ogarda"
    ],
    "name:fas_x_preferred":[
        "\u0628\u06cc\u0627\u0648\u0648\u06af\u0627\u0631\u062f\u0627"
    ],
    "name:fra_x_preferred":[
        "Bia\u0142ogarda"
    ],
    "name:nld_x_preferred":[
        "Bia\u0142ogarda"
    ],
    "name:pol_x_preferred":[
        "Bia\u0142ogarda"
    ],
    "name:ukr_x_preferred":[
        "\u0411\u044f\u043b\u043e\u0491\u0430\u0440\u0434\u0430"
    ],
    "name:und_x_variant":[
        "Belgard",
        "Bia\u0142ogarda"
    ],
    "wof:name":"Bialogarda",
    "wof:placetype":"locality"
},
  "geometry": {"coordinates":[17.65338999999999,54.65255],"type":"Point"}
}