{
  "type": "Feature",
  "properties": {
    "gn:admin1_code":"72.0",
    "gn:admin2_code":"212.0",
    "gn:admin3_code":"21203.0",
    "gn:asciiname":"Wlodzice Wielkie",
    "gn:country_code":"PL",
    "gn:dem":199,
    "gn:feature_class":"P",
    "gn:feature_code":"PPL",
    "gn:name":"W\u0142odzice Wielkie",
    "gn:population":0,
    "gn:timezone":"Europe/Warsaw",
    "iso:country":"PL",
    "name:deu_x_historical":[
        "Gro\u00df Walditz"
    ],
    "name:deu_x_preferred":[
        "Gro\u00df Walditz"
    ],
    "name:epo_x_preferred":[
        "W\u0142odzice Wielkie"
    ],
    "name:nld_x_preferred":[
        "W\u0142odzice Wielkie"
    ],
    "name:pol_x_preferred":[
        "W\u0142odzice Wielkie"
    ],
    "name:ukr_x_preferred":[
        "\u0412\u043b\u043e\u0434\u0437\u0456\u0446\u0435-\u0412\u0435\u043b\u0438\u043a\u0456"
    ],
    "wof:name":"Wlodzice Wielkie",
    "wof:placetype":"locality"
},
  "geometry": {"coordinates":[15.55218,51.18343],"type":"Point"}
}