{
  "type": "Feature",
  "properties": {
    "gn:admin1_code":"85.0",
    "gn:admin2_code":"2809.0",
    "gn:admin3_code":"280904.0",
    "gn:asciiname":"Wojtowo",
    "gn:country_code":"PL",
    "gn:dem":109,
    "gn:feature_class":"P",
    "gn:feature_code":"PPL",
    "gn:name":"W\u00f3jtowo",
    "gn:population":0,
    "gn:timezone":"Europe/Warsaw",
    "iso:country":"PL",
    "name:fra_x_preferred":[
        "W\u00f3jtowo"
    ],
    "name:pol_x_preferred":[
        "W\u00f3jtowo"
    ],
    "name:ukr_x_preferred":[
        "\u0412\u0443\u0439\u0442\u043e\u0432\u043e"
    ],
    "name:und_x_variant":[
        "Voigtsdorf"
    ],
    "wof:name":"Wojtowo",
    "wof:placetype":"locality"
},
  "geometry": {"coordinates":[20.18706,54.05924],"type":"Point"}
}