{
  "type": "Feature",
  "properties": {
    "gn:admin1_code":"85.0",
    "gn:admin2_code":"2809.0",
    "gn:admin3_code":"280905.0",
    "gn:asciiname":"Bogatynskie",
    "gn:country_code":"PL",
    "gn:dem":52,
    "gn:feature_class":"P",
    "gn:feature_code":"PPL",
    "gn:name":"Bogaty\u0144skie",
    "gn:population":0,
    "gn:timezone":"Europe/Warsaw",
    "iso:country":"PL",
    "name:fra_x_preferred":[
        "Bogaty\u0144skie"
    ],
    "name:pol_x_preferred":[
        "Bogaty\u0144skie"
    ],
    "name:ukr_x_preferred":[
        "\u0411\u043e\u0491\u0430\u0442\u0438\u043d\u0441\u044c\u043a\u0435"
    ],
    "name:und_x_variant":[
        "T\u00fcngen"
    ],
    "wof:name":"Bogatynskie",
    "wof:placetype":"locality"
},
  "geometry": {"coordinates":[20.07001,54.08934],"type":"Point"}
}