{
  "type": "Feature",
  "properties": {
    "gn:admin1_code":"84.0",
    "gn:admin2_code":"2602.0",
    "gn:admin3_code":"260203.0",
    "gn:asciiname":"Zlotniki",
    "gn:country_code":"PL",
    "gn:dem":231,
    "gn:feature_class":"P",
    "gn:feature_code":"PPL",
    "gn:name":"Z\u0142otniki",
    "gn:population":0,
    "gn:timezone":"Europe/Warsaw",
    "iso:country":"PL",
    "name:und_x_variant":[
        "Z\u0142otniki"
    ],
    "wof:name":"Zlotniki",
    "wof:placetype":"locality"
},
  "geometry": {"coordinates":[20.23932000000001,50.75657],"type":"Point"}
}