{
  "type": "Feature",
  "properties": {
    "gn:admin1_code":"78.0",
    "gn:admin2_code":"1433.0",
    "gn:admin3_code":"143309.0",
    "gn:asciiname":"Koszewnica",
    "gn:country_code":"PL",
    "gn:dem":141,
    "gn:feature_class":"P",
    "gn:feature_code":"PPL",
    "gn:name":"Koszewnica",
    "gn:population":0,
    "gn:timezone":"Europe/Warsaw",
    "iso:country":"PL",
    "name:fra_x_preferred":[
        "Koszewnica"
    ],
    "name:pol_x_preferred":[
        "Koszewnica"
    ],
    "name:ukr_x_preferred":[
        "\u041a\u043e\u0448\u0435\u0432\u043d\u0438\u0446\u044f"
    ],
    "wof:name":"Koszewnica",
    "wof:placetype":"locality"
},
  "geometry": {"coordinates":[21.87936,52.32637],"type":"Point"}
}