{
  "type": "Feature",
  "properties": {
    "gn:admin1_code":"74.0",
    "gn:admin2_code":"1014.0",
    "gn:admin3_code":"101407.0",
    "gn:asciiname":"Lipicze",
    "gn:country_code":"PL",
    "gn:dem":164,
    "gn:feature_class":"P",
    "gn:feature_code":"PPL",
    "gn:name":"Lipicze",
    "gn:population":0,
    "gn:timezone":"Europe/Warsaw",
    "iso:country":"PL",
    "name:pol_x_preferred":[
        "Lipicze"
    ],
    "name:ukr_x_preferred":[
        "\u041b\u0456\u043f\u0456\u0447\u0435"
    ],
    "wof:name":"Lipicze",
    "wof:placetype":"locality"
},
  "geometry": {"coordinates":[18.48551,51.42903],"type":"Point"}
}