{
  "type": "Feature",
  "properties": {
    "gn:admin1_code":"78.0",
    "gn:admin2_code":"1406.0",
    "gn:admin3_code":"140601.0",
    "gn:asciiname":"Wola Starowiejska",
    "gn:country_code":"PL",
    "gn:dem":163,
    "gn:feature_class":"P",
    "gn:feature_code":"PPL",
    "gn:name":"Wola Starowiejska",
    "gn:population":0,
    "gn:timezone":"Europe/Warsaw",
    "iso:country":"PL",
    "name:fra_x_preferred":[
        "Wola Starowiejska"
    ],
    "name:pol_x_preferred":[
        "Wola Starowiejska"
    ],
    "name:ukr_x_preferred":[
        "\u0412\u043e\u043b\u044f-\u0421\u0442\u0430\u0440\u043e\u0432\u0435\u0439\u0441\u044c\u043a\u0430"
    ],
    "wof:name":"Wola Starowiejska",
    "wof:placetype":"locality"
},
  "geometry": {"coordinates":[20.80949,51.80732],"type":"Point"}
}