{
  "type": "Feature",
  "properties": {
    "gn:country":"PL",
    "gn:fcode":"PPL",
    "gn:population":0,
    "iso:country":"PL",
    "name:ast_x_preferred":[
        "D\u0119bina"
    ],
    "name:ces_x_preferred":[
        "D\u0119bina"
    ],
    "name:che_x_preferred":[
        "\u0414\u0435\u043c\u0431\u0438\u043d\u0430"
    ],
    "name:eng_x_preferred":[
        "D\u0119bina"
    ],
    "name:fra_x_preferred":[
        "D\u0119bina"
    ],
    "name:nan_x_preferred":[
        "D\u0119bina"
    ],
    "name:pol_x_preferred":[
        "D\u0119bina"
    ],
    "name:tat_x_preferred":[
        "\u0414\u0435\u043c\u0431\u0438\u043d\u0430"
    ],
    "name:ukr_x_preferred":[
        "\u0414\u0435\u043c\u0431\u0456\u043d\u0430"
    ],
    "qs_pg:aaroncc":"PL",
    "qs_pg:gn_country":"PL",
    "qs_pg:gn_fcode":"PPL",
    "qs_pg:gn_pop":0,
    "qs_pg:name":"D\u0119bina",
    "qs_pg:name_adm0":"Polska",
    "qs_pg:name_adm1":"Mazowieckie",
    "qs_pg:photos_9k":1,
    "qs_pg:photos_9r":1,
    "qs_pg:photos_all":1,
    "qs_pg:photos_sr":0,
    "qs_pg:pop_sr":0,
    "qs_pg:qs_pg_placetype":"locality",
    "qs_pg:qs_pg_placetype_gp":"Town",
    "qs_pg:woe_adm0":23424923,
    "woe:adm0_id":23424923,
    "woe:name_adm0":"Polska",
    "woe:name_adm1":"Mazowieckie",
    "woe:placetype":"Town",
    "wof:name":"D\u0119bina",
    "wof:placetype":"locality"
},
  "geometry": {"coordinates":[20.70957,52.39168],"type":"Point"}
}