{
  "type": "Feature",
  "properties": {
    "gn:admin1_code":"84.0",
    "gn:admin2_code":"2601.0",
    "gn:admin3_code":"260106.0",
    "gn:asciiname":"Mietel",
    "gn:country_code":"PL",
    "gn:dem":227,
    "gn:feature_class":"P",
    "gn:feature_code":"PPL",
    "gn:name":"Mietel",
    "gn:population":0,
    "gn:timezone":"Europe/Warsaw",
    "iso:country":"PL",
    "name:pol_x_preferred":[
        "Mietel"
    ],
    "name:ukr_x_preferred":[
        "\u041c\u0435\u0442\u0435\u043b\u044c"
    ],
    "wof:name":"Mietel",
    "wof:placetype":"locality"
},
  "geometry": {"coordinates":[20.96667,50.41667],"type":"Point"}
}