{
  "type": "Feature",
  "properties": {
    "gn:admin1_code":"73.0",
    "gn:admin2_code":"411.0",
    "gn:admin3_code":"41102.0",
    "gn:asciiname":"Borowo",
    "gn:country_code":"PL",
    "gn:dem":94,
    "gn:feature_class":"P",
    "gn:feature_code":"PPL",
    "gn:name":"Borowo",
    "gn:population":0,
    "gn:timezone":"Europe/Warsaw",
    "iso:country":"PL",
    "name:deu_x_preferred":[
        "Borowo"
    ],
    "name:fra_x_preferred":[
        "Borowo"
    ],
    "name:pol_x_preferred":[
        "Borowo"
    ],
    "wof:name":"Borowo",
    "wof:placetype":"locality"
},
  "geometry": {"coordinates":[18.58878,52.53318],"type":"Point"}
}