{
  "type": "Feature",
  "properties": {
    "iso:country":"PL",
    "name:eng_x_preferred":[
        "Wrzeszcz Dolny"
    ],
    "name:pol_x_preferred":[
        "Wrzeszcz Dolny"
    ],
    "wof:name":"Wrzeszcz Dolny",
    "wof:placetype":"neighbourhood"
},
  "geometry": {"coordinates":[18.62023677491359,54.38592042635251],"type":"Point"}
}