{
  "type": "Feature",
  "properties": {
    "gn:admin1_code":"86.0",
    "gn:admin2_code":"3022.0",
    "gn:admin3_code":"302204.0",
    "gn:asciiname":"Goreczki Wielkie",
    "gn:country_code":"PL",
    "gn:dem":116,
    "gn:feature_class":"P",
    "gn:feature_code":"PPL",
    "gn:name":"G\u00f3reczki Wielkie",
    "gn:population":0,
    "gn:timezone":"Europe/Warsaw",
    "iso:country":"PL",
    "name:fra_x_preferred":[
        "G\u00f3reczki Wielkie"
    ],
    "name:pol_x_preferred":[
        "G\u00f3reczki Wielkie"
    ],
    "name:ukr_x_preferred":[
        "\u0490\u0443\u0440\u0435\u0447\u043a\u0456-\u0412\u0435\u043b\u0438\u043a\u0456"
    ],
    "wof:name":"Goreczki Wielkie",
    "wof:placetype":"locality"
},
  "geometry": {"coordinates":[17.0856,51.63559],"type":"Point"}
}