{
  "type": "Feature",
  "properties": {
    "gn:admin1_code":"75.0",
    "gn:admin2_code":"610.0",
    "gn:admin3_code":"61001.0",
    "gn:asciiname":"Wolka Nadnybska",
    "gn:country_code":"PL",
    "gn:dem":170,
    "gn:feature_class":"P",
    "gn:feature_code":"PPL",
    "gn:name":"W\u00f3lka Nadnybska",
    "gn:population":0,
    "gn:timezone":"Europe/Warsaw",
    "iso:country":"PL",
    "wof:name":"Wolka Nadnybska",
    "wof:placetype":"locality"
},
  "geometry": {"coordinates":[23.07886,51.35621],"type":"Point"}
}