{
  "type": "Feature",
  "properties": {
    "gn:country":"PL",
    "gn:fcode":"PPLA3",
    "gn:population":5121,
    "iso:country":"PL",
    "name:ceb_x_preferred":[
        "I\u0142\u017ca"
    ],
    "name:deu_x_preferred":[
        "I\u0142\u017ca"
    ],
    "name:epo_x_preferred":[
        "I\u0142\u017ca"
    ],
    "name:fra_x_preferred":[
        "I\u0142\u017ca"
    ],
    "name:heb_x_preferred":[
        "\u05d0\u05d9\u05dc\u05d6\u05d4"
    ],
    "name:heb_x_variant":[
        "\u05d0\u05d9\u05dc\u05d6'\u05d4"
    ],
    "name:jav_x_preferred":[
        "I\u0142\u017ca"
    ],
    "name:lav_x_preferred":[
        "Il\u017ea"
    ],
    "name:msa_x_preferred":[
        "I\u0142\u017ca"
    ],
    "name:nld_x_preferred":[
        "I\u0142\u017ca"
    ],
    "name:pol_x_preferred":[
        "I\u0142\u017ca"
    ],
    "name:por_x_preferred":[
        "I\u0142\u017ca"
    ],
    "name:ron_x_preferred":[
        "I\u0142\u017ca"
    ],
    "name:rus_x_preferred":[
        "\u0418\u043b\u0436\u0430"
    ],
    "name:slk_x_preferred":[
        "I\u0142\u017ca"
    ],
    "name:srp_x_preferred":[
        "\u0418\u043b\u0436\u0430"
    ],
    "name:swe_x_preferred":[
        "I\u0142\u017ca"
    ],
    "name:tha_x_preferred":[
        "\u0e2d\u0e34\u0e27\u0e0a\u0e32"
    ],
    "name:ukr_x_preferred":[
        "\u0406\u043b\u0436\u0430"
    ],
    "name:vie_x_preferred":[
        "I\u0142\u017ca"
    ],
    "name:zho_x_preferred":[
        "\u4f0a\u70cf\u624e"
    ],
    "qs_pg:aaroncc":"PL",
    "qs_pg:gn_country":"PL",
    "qs_pg:gn_fcode":"PPLA3",
    "qs_pg:gn_pop":5121,
    "qs_pg:name":"I\u0142\u017ca",
    "qs_pg:name_adm0":"Polska",
    "qs_pg:name_adm1":"Mazowieckie",
    "qs_pg:photos_9r":0,
    "qs_pg:photos_sr":0,
    "qs_pg:pop_sr":7,
    "qs_pg:qs_pg_placetype":"localadmin",
    "qs_pg:qs_pg_placetype_gp":"LocalAdmin",
    "qs_pg:woe_adm0":23424923,
    "woe:adm0_id":23424923,
    "woe:name_adm0":"Polska",
    "woe:name_adm1":"Mazowieckie",
    "woe:placetype":"LocalAdmin",
    "wof:name":"I\u0142\u017ca",
    "wof:placetype":"localadmin",
    "wof:population":5121
},
  "geometry": {"coordinates":[21.23979,51.16313],"type":"Point"}
}