{
  "type": "Feature",
  "properties": {
    "gn:admin1_code":"74.0",
    "gn:admin2_code":"1002.0",
    "gn:admin3_code":"100206.0",
    "gn:asciiname":"Obidowek",
    "gn:country_code":"PL",
    "gn:dem":97,
    "gn:feature_class":"P",
    "gn:feature_code":"PPL",
    "gn:name":"Obid\u00f3wek",
    "gn:population":0,
    "gn:timezone":"Europe/Warsaw",
    "iso:country":"PL",
    "name:und_x_variant":[
        "Obid\u00f3wek"
    ],
    "wof:name":"Obidowek",
    "wof:placetype":"locality"
},
  "geometry": {"coordinates":[19.35757000000001,52.15567],"type":"Point"}
}