{
  "type": "Feature",
  "properties": {
    "gn:admin1_code":"74.0",
    "gn:admin2_code":"1007.0",
    "gn:admin3_code":"100708.0",
    "gn:asciiname":"Dabie",
    "gn:country_code":"PL",
    "gn:dem":204,
    "gn:feature_class":"P",
    "gn:feature_code":"PPL",
    "gn:name":"D\u0105bie",
    "gn:population":0,
    "gn:timezone":"Europe/Warsaw",
    "iso:country":"PL",
    "name:fra_x_preferred":[
        "D\u0105bie"
    ],
    "name:pol_x_preferred":[
        "D\u0105bie"
    ],
    "name:ukr_x_preferred":[
        "\u0414\u043e\u043c\u0431'\u0454"
    ],
    "wof:name":"Dabie",
    "wof:placetype":"locality"
},
  "geometry": {"coordinates":[20.07571,51.21344000000001],"type":"Point"}
}