{
  "type": "Feature",
  "properties": {
    "gn:admin1_code":"75.0",
    "gn:admin2_code":"601.0",
    "gn:admin3_code":"60104.0",
    "gn:asciiname":"Szachy",
    "gn:country_code":"PL",
    "gn:dem":146,
    "gn:feature_class":"P",
    "gn:feature_code":"PPL",
    "gn:name":"Szachy",
    "gn:population":0,
    "gn:timezone":"Europe/Warsaw",
    "iso:country":"PL",
    "name:ceb_x_preferred":[
        "Szachy"
    ],
    "name:fra_x_preferred":[
        "Szachy"
    ],
    "name:lit_x_preferred":[
        "\u0160achai"
    ],
    "name:pol_x_preferred":[
        "Szachy"
    ],
    "name:ukr_x_preferred":[
        "\u0428\u0430\u0445\u0438"
    ],
    "wof:name":"Szachy",
    "wof:placetype":"locality"
},
  "geometry": {"coordinates":[22.91491,51.98858],"type":"Point"}
}