{
  "type": "Feature",
  "properties": {
    "iso:country":"PL",
    "name:pol_x_preferred":[
        "Praga Po\u0142udnie"
    ],
    "wof:name":"Praga Poludnie",
    "wof:placetype":"neighbourhood"
},
  "geometry": {"coordinates":[21.08442856336639,52.23554399901256],"type":"Point"}
}