{
  "type": "Feature",
  "properties": {
    "gn:country":"PL",
    "gn:fcode":"PPL",
    "gn:population":0,
    "iso:country":"PL",
    "name:ast_x_preferred":[
        "Bobr\u00f3w"
    ],
    "name:eng_x_preferred":[
        "Bobr\u00f3w"
    ],
    "name:fra_x_preferred":[
        "Bobr\u00f3w"
    ],
    "name:pol_x_preferred":[
        "Bobr\u00f3w"
    ],
    "name:ukr_x_preferred":[
        "\u0411\u043e\u0431\u0440\u0443\u0432"
    ],
    "name:und_x_variant":[
        "Boberstein"
    ],
    "qs_pg:aaroncc":"PL",
    "qs_pg:gn_country":"PL",
    "qs_pg:gn_fcode":"PPL",
    "qs_pg:gn_pop":0,
    "qs_pg:name":"Bobrow",
    "qs_pg:name_adm0":"Polska",
    "qs_pg:name_adm1":"Dolnosl\u0105skie",
    "qs_pg:photos":11,
    "qs_pg:photos_1k":2,
    "qs_pg:photos_9k":1,
    "qs_pg:photos_9r":1,
    "qs_pg:photos_all":11,
    "qs_pg:photos_sr":1,
    "qs_pg:pop_sr":0,
    "qs_pg:qs_pg_placetype":"locality",
    "qs_pg:qs_pg_placetype_gp":"Town",
    "qs_pg:woe_adm0":23424923,
    "woe:adm0_id":23424923,
    "woe:name_adm0":"Polska",
    "woe:name_adm1":"Dolnosl\u0105skie",
    "woe:placetype":"Town",
    "wof:name":"Bobrow",
    "wof:placetype":"locality"
},
  "geometry": {"coordinates":[15.84574,50.8762],"type":"Point"}
}