{
  "type": "Feature",
  "properties": {
    "gn:admin1_code":"85.0",
    "gn:admin2_code":"2817.0",
    "gn:admin3_code":"281708.0",
    "gn:asciiname":"Ciemna Dabrowa",
    "gn:country_code":"PL",
    "gn:dem":134,
    "gn:feature_class":"P",
    "gn:feature_code":"PPL",
    "gn:name":"Ciemna D\u0105browa",
    "gn:population":0,
    "gn:timezone":"Europe/Warsaw",
    "iso:country":"PL",
    "name:pol_x_preferred":[
        "Ciemna D\u0105browa"
    ],
    "name:ukr_x_preferred":[
        "\u0426\u0435\u043c\u043d\u0430-\u0414\u043e\u043c\u0431\u0440\u043e\u0432\u0430"
    ],
    "name:und_x_variant":[
        "Finsterdamerau",
        "Czemna Dombrowa"
    ],
    "wof:name":"Ciemna Dabrowa",
    "wof:placetype":"locality"
},
  "geometry": {"coordinates":[21.01775,53.46189],"type":"Point"}
}