{
  "type": "Feature",
  "properties": {
    "gn:admin1_code":"77.0",
    "gn:admin2_code":"1219.0",
    "gn:admin3_code":"121904.0",
    "gn:asciiname":"Jazy",
    "gn:country_code":"PL",
    "gn:dem":189,
    "gn:feature_class":"P",
    "gn:feature_code":"PPL",
    "gn:name":"Jazy",
    "gn:population":0,
    "gn:timezone":"Europe/Warsaw",
    "iso:country":"PL",
    "name:deu_x_preferred":[
        "Jazy"
    ],
    "name:pol_x_preferred":[
        "Jazy"
    ],
    "wof:name":"Jazy",
    "wof:placetype":"locality"
},
  "geometry": {"coordinates":[20.23333,50.05],"type":"Point"}
}