{
  "type": "Feature",
  "properties": {
    "gn:admin1_code":"86.0",
    "gn:admin2_code":"3007.0",
    "gn:admin3_code":"300703.0",
    "gn:asciiname":"Kosmow",
    "gn:country_code":"PL",
    "gn:dem":125,
    "gn:feature_class":"P",
    "gn:feature_code":"PPL",
    "gn:name":"Kosm\u00f3w",
    "gn:population":0,
    "gn:timezone":"Europe/Warsaw",
    "iso:country":"PL",
    "name:pol_x_preferred":[
        "Kosm\u00f3w"
    ],
    "name:ukr_x_preferred":[
        "\u041a\u043e\u0441\u043c\u0443\u0432"
    ],
    "wof:name":"Kosmow",
    "wof:placetype":"locality"
},
  "geometry": {"coordinates":[18.26692,51.88613],"type":"Point"}
}