{
  "type": "Feature",
  "properties": {
    "gn:admin1_code":"78.0",
    "gn:admin2_code":"1422.0",
    "gn:admin3_code":"142206.0",
    "gn:asciiname":"Romany Janowieta",
    "gn:country_code":"PL",
    "gn:dem":127,
    "gn:feature_class":"P",
    "gn:feature_code":"PPL",
    "gn:name":"Romany Janowi\u0119ta",
    "gn:population":0,
    "gn:timezone":"Europe/Warsaw",
    "iso:country":"PL",
    "wof:name":"Romany Janowieta",
    "wof:placetype":"locality"
},
  "geometry": {"coordinates":[20.8667,53.09622],"type":"Point"}
}