{
  "type": "Feature",
  "properties": {
    "gn:admin1_code":"80.0",
    "gn:admin2_code":"1807.0",
    "gn:admin3_code":"180701.0",
    "gn:asciiname":"Faliszowka",
    "gn:country_code":"PL",
    "gn:dem":325,
    "gn:feature_class":"P",
    "gn:feature_code":"PPL",
    "gn:name":"Falisz\u00f3wka",
    "gn:population":0,
    "gn:timezone":"Europe/Warsaw",
    "iso:country":"PL",
    "name:azb_x_preferred":[
        "\u0641\u0627\u0644\u06cc\u0634\u0648\u0648\u06a9\u0627"
    ],
    "name:ceb_x_preferred":[
        "Falisz\u00f3wka"
    ],
    "name:fas_x_preferred":[
        "\u0641\u0627\u0644\u06cc\u0634\u0648\u0648\u06a9\u0627"
    ],
    "name:nld_x_preferred":[
        "Falisz\u00f3wka"
    ],
    "name:pol_x_preferred":[
        "Falisz\u00f3wka"
    ],
    "name:ukr_x_preferred":[
        "\u0424\u0430\u043b\u0456\u0448\u0443\u0432\u043a\u0430"
    ],
    "name:und_x_variant":[
        "Falisz\u00f3wka"
    ],
    "name:urd_x_preferred":[
        "\u0641\u0627\u0644\u06cc\u0633\u0632\u0648\u06a9\u0627"
    ],
    "wof:name":"Faliszowka",
    "wof:placetype":"locality"
},
  "geometry": {"coordinates":[21.60896,49.64458],"type":"Point"}
}