{
  "type": "Feature",
  "properties": {
    "gn:admin1_code":"81.0",
    "gn:admin2_code":"2004.0",
    "gn:admin3_code":"200402.0",
    "gn:asciiname":"Ciemnoszyje",
    "gn:country_code":"PL",
    "gn:dem":115,
    "gn:feature_class":"P",
    "gn:feature_code":"PPL",
    "gn:name":"Ciemnoszyje",
    "gn:population":0,
    "gn:timezone":"Europe/Warsaw",
    "iso:country":"PL",
    "name:azb_x_preferred":[
        "\u0686\u06cc\u0645\u0646\u0648\u0634\u06cc\u0647"
    ],
    "name:fas_x_preferred":[
        "\u0686\u06cc\u0645\u0646\u0648\u0634\u06cc\u0647"
    ],
    "name:fra_x_preferred":[
        "Ciemnoszyje"
    ],
    "name:lit_x_preferred":[
        "Cemno\u0161ij\u0117"
    ],
    "name:pol_x_preferred":[
        "Ciemnoszyje"
    ],
    "name:ukr_x_preferred":[
        "\u0426\u0435\u043c\u043d\u043e\u0448\u0438\u0454"
    ],
    "wof:name":"Ciemnoszyje",
    "wof:placetype":"locality"
},
  "geometry": {"coordinates":[22.55381,53.53402],"type":"Point"}
}