{
  "type": "Feature",
  "properties": {
    "gn:admin1_code":"85.0",
    "gn:admin2_code":"2811.0",
    "gn:admin3_code":"281103.0",
    "gn:asciiname":"Sarnowo",
    "gn:country_code":"PL",
    "gn:dem":167,
    "gn:feature_class":"P",
    "gn:feature_code":"PPL",
    "gn:name":"Sarnowo",
    "gn:population":0,
    "gn:timezone":"Europe/Warsaw",
    "iso:country":"PL",
    "name:ceb_x_preferred":[
        "Sarnowo"
    ],
    "name:deu_x_preferred":[
        "Sarnowo"
    ],
    "name:eng_x_preferred":[
        "Sarnowo"
    ],
    "name:fra_x_preferred":[
        "Sarnowo"
    ],
    "name:pol_x_preferred":[
        "Sarnowo"
    ],
    "name:rus_x_preferred":[
        "\u0421\u0430\u0440\u043d\u043e\u0432\u043e"
    ],
    "name:ukr_x_preferred":[
        "\u0421\u0430\u0440\u043d\u043e\u0432\u043e"
    ],
    "name:und_x_variant":[
        "Scharnau",
        "Sarnowo"
    ],
    "wof:name":"Sarnowo",
    "wof:placetype":"locality"
},
  "geometry": {"coordinates":[20.27236,53.26682],"type":"Point"}
}