{
  "type": "Feature",
  "properties": {
    "gn:admin1_code":"80.0",
    "gn:admin2_code":"1863.0",
    "gn:admin3_code":"186301.0",
    "gn:asciiname":"Budziwoj",
    "gn:country_code":"PL",
    "gn:dem":214,
    "gn:feature_class":"P",
    "gn:feature_code":"PPL",
    "gn:name":"Budziw\u00f3j",
    "gn:population":0,
    "gn:timezone":"Europe/Warsaw",
    "iso:country":"PL",
    "name:pol_x_preferred":[
        "Budziw\u00f3j"
    ],
    "name:ukr_x_preferred":[
        "\u0411\u0443\u0434\u0438\u0432\u043e\u0439"
    ],
    "name:und_x_variant":[
        "Budziw\u00f3j"
    ],
    "wof:name":"Budziwoj",
    "wof:placetype":"locality"
},
  "geometry": {"coordinates":[21.98257000000001,49.96647],"type":"Point"}
}