{
  "type": "Feature",
  "properties": {
    "gn:admin1_code":"74.0",
    "gn:admin2_code":"1007.0",
    "gn:admin3_code":"100706.0",
    "gn:asciiname":"Mysiakowiec",
    "gn:country_code":"PL",
    "gn:dem":142,
    "gn:feature_class":"P",
    "gn:feature_code":"PPL",
    "gn:name":"Mysiakowiec",
    "gn:population":0,
    "gn:timezone":"Europe/Warsaw",
    "iso:country":"PL",
    "name:ceb_x_preferred":[
        "Mysiakowiec"
    ],
    "name:fra_x_preferred":[
        "Mysiakowiec"
    ],
    "name:pol_x_preferred":[
        "Mysiakowiec"
    ],
    "name:ukr_x_preferred":[
        "\u041c\u0438\u0441\u044f\u043a\u043e\u0432\u0435\u0446\u044c"
    ],
    "wof:name":"Mysiakowiec",
    "wof:placetype":"locality"
},
  "geometry": {"coordinates":[20.33758,51.57323],"type":"Point"}
}