{
  "type": "Feature",
  "properties": {
    "gn:admin1_code":"82.0",
    "gn:admin2_code":"2205.0",
    "gn:admin3_code":"220504.0",
    "gn:asciiname":"Stara Huta",
    "gn:country_code":"PL",
    "gn:dem":196,
    "gn:feature_class":"P",
    "gn:feature_code":"PPL",
    "gn:name":"Stara Huta",
    "gn:population":0,
    "gn:timezone":"Europe/Warsaw",
    "iso:country":"PL",
    "name:deu_x_preferred":[
        "Stara Huta"
    ],
    "name:fra_x_preferred":[
        "Stara Huta"
    ],
    "name:pol_x_preferred":[
        "Stara Huta"
    ],
    "name:rus_x_preferred":[
        "\u0421\u0442\u0430\u0440\u0430\u044f \u0413\u0443\u0442\u0430"
    ],
    "name:ukr_x_preferred":[
        "\u0421\u0442\u0430\u0440\u0430 \u0413\u0443\u0442\u0430"
    ],
    "wof:name":"Stara Huta",
    "wof:placetype":"locality"
},
  "geometry": {"coordinates":[17.72085,54.31533],"type":"Point"}
}