{
  "type": "Feature",
  "properties": {
    "gn:admin1_code":"78.0",
    "gn:admin2_code":"1406.0",
    "gn:admin3_code":"140606.0",
    "gn:asciiname":"Lychow",
    "gn:country_code":"PL",
    "gn:dem":134,
    "gn:feature_class":"P",
    "gn:feature_code":"PPL",
    "gn:name":"\u0141ych\u00f3w",
    "gn:population":0,
    "gn:timezone":"Europe/Warsaw",
    "iso:country":"PL",
    "name:und_x_variant":[
        "\u0141ych\u00f3w"
    ],
    "wof:name":"Lychow",
    "wof:placetype":"locality"
},
  "geometry": {"coordinates":[20.97366,51.77648],"type":"Point"}
}