{
  "type": "Feature",
  "properties": {
    "gn:admin1_code":"85.0",
    "gn:admin2_code":"2802.0",
    "gn:admin3_code":"280205.0",
    "gn:asciiname":"Pelty",
    "gn:country_code":"PL",
    "gn:dem":82,
    "gn:feature_class":"P",
    "gn:feature_code":"PPL",
    "gn:name":"Pe\u0142ty",
    "gn:population":0,
    "gn:timezone":"Europe/Warsaw",
    "iso:country":"PL",
    "name:und_x_variant":[
        "Steinbotten",
        "Pe\u0142ty"
    ],
    "wof:name":"Pelty",
    "wof:placetype":"locality"
},
  "geometry": {"coordinates":[20.24715,54.25715],"type":"Point"}
}