{
  "type": "Feature",
  "properties": {
    "gn:admin1_code":"74.0",
    "gn:admin2_code":"1002.0",
    "gn:admin3_code":"100204.0",
    "gn:asciiname":"Szubsk Duzy",
    "gn:country_code":"PL",
    "gn:dem":122,
    "gn:feature_class":"P",
    "gn:feature_code":"PPL",
    "gn:name":"Szubsk Du\u017cy",
    "gn:population":0,
    "gn:timezone":"Europe/Warsaw",
    "iso:country":"PL",
    "name:und_x_variant":[
        "Szubsk Du\u017cy"
    ],
    "wof:name":"Szubsk Duzy",
    "wof:placetype":"locality"
},
  "geometry": {"coordinates":[19.22903,52.22421],"type":"Point"}
}