{
  "type": "Feature",
  "properties": {
    "gn:admin1_code":"82.0",
    "gn:admin2_code":"2210.0",
    "gn:admin3_code":"221002.0",
    "gn:asciiname":"Kepki",
    "gn:cc2":"PL",
    "gn:country_code":"PL",
    "gn:dem":0,
    "gn:feature_class":"P",
    "gn:feature_code":"PPL",
    "gn:name":"K\u0119pki",
    "gn:population":0,
    "gn:timezone":"Europe/Warsaw",
    "iso:country":"PL",
    "name:ceb_x_preferred":[
        "K\u0119pki"
    ],
    "name:deu_x_preferred":[
        "K\u0119pki"
    ],
    "name:pol_x_preferred":[
        "K\u0119pki"
    ],
    "name:ukr_x_preferred":[
        "\u041a\u0435\u043c\u043f\u043a\u0456"
    ],
    "name:und_x_variant":[
        "Marz\u0119cino",
        "Zeyer"
    ],
    "wof:name":"Kepki",
    "wof:placetype":"locality"
},
  "geometry": {"coordinates":[19.31156,54.19076999999999],"type":"Point"}
}