{
  "type": "Feature",
  "properties": {
    "gn:country":"PL",
    "gn:fcode":"PPL",
    "gn:population":389,
    "iso:country":"PL",
    "name:ast_x_preferred":[
        "Sobies\u0119ki"
    ],
    "name:ceb_x_preferred":[
        "Sobies\u0119ki"
    ],
    "name:eng_x_preferred":[
        "Sobies\u0119ki"
    ],
    "name:fra_x_preferred":[
        "Sobies\u0119ki"
    ],
    "name:pol_x_preferred":[
        "Sobies\u0119ki"
    ],
    "name:rus_x_preferred":[
        "\u0421\u043e\u0431\u0435\u0441\u0435\u043d\u043a\u0438"
    ],
    "name:ukr_x_preferred":[
        "\u0421\u043e\u0431\u0435\u0441\u0435\u043d\u043a\u0456"
    ],
    "qs_pg:aaroncc":"PL",
    "qs_pg:gn_country":"PL",
    "qs_pg:gn_fcode":"PPL",
    "qs_pg:gn_pop":389,
    "qs_pg:name":"Sobies\u0119ki",
    "qs_pg:photos_9r":0,
    "qs_pg:photos_sr":0,
    "qs_pg:pop_sr":2,
    "qs_pg:qs_pg_placetype":"locality",
    "wof:name":"Sobies\u0119ki",
    "wof:placetype":"locality",
    "wof:population":389
},
  "geometry": {"coordinates":[19.85624,50.24479],"type":"Point"}
}