{
  "type": "Feature",
  "properties": {
    "gn:admin1_code":"75.0",
    "gn:admin2_code":"616.0",
    "gn:admin3_code":"61604.0",
    "gn:asciiname":"Kleszczowka",
    "gn:country_code":"PL",
    "gn:dem":118,
    "gn:feature_class":"P",
    "gn:feature_code":"PPL",
    "gn:name":"Kleszcz\u00f3wka",
    "gn:population":0,
    "gn:timezone":"Europe/Warsaw",
    "iso:country":"PL",
    "name:fra_x_preferred":[
        "Kleszcz\u00f3wka"
    ],
    "name:nld_x_preferred":[
        "Kleszcz\u00f3wka"
    ],
    "name:pol_x_preferred":[
        "Kleszcz\u00f3wka"
    ],
    "name:ukr_x_preferred":[
        "\u041a\u043b\u0435\u0449\u0443\u0432\u043a\u0430"
    ],
    "wof:name":"Kleszczowka",
    "wof:placetype":"locality"
},
  "geometry": {"coordinates":[21.90674,51.56683],"type":"Point"}
}