{
  "type": "Feature",
  "properties": {
    "gn:admin1_code":"78.0",
    "gn:admin2_code":"1405.0",
    "gn:admin3_code":"140504.0",
    "gn:asciiname":"Kozery",
    "gn:country_code":"PL",
    "gn:dem":100,
    "gn:feature_class":"P",
    "gn:feature_code":"PPL",
    "gn:name":"Kozery",
    "gn:population":0,
    "gn:timezone":"Europe/Warsaw",
    "iso:country":"PL",
    "name:fra_x_preferred":[
        "Kozery"
    ],
    "name:pol_x_preferred":[
        "Kozery"
    ],
    "name:ukr_x_preferred":[
        "\u041a\u043e\u0437\u0435\u0440\u0438"
    ],
    "wof:name":"Kozery",
    "wof:placetype":"locality"
},
  "geometry": {"coordinates":[20.58495,52.10545],"type":"Point"}
}