{
  "type": "Feature",
  "properties": {
    "gn:admin1_code":"87.0",
    "gn:admin2_code":"3205.0",
    "gn:admin3_code":"320508.0",
    "gn:asciiname":"Wlewo",
    "gn:country_code":"PL",
    "gn:dem":19,
    "gn:feature_class":"P",
    "gn:feature_code":"PPL",
    "gn:name":"Wlewo",
    "gn:population":0,
    "gn:timezone":"Europe/Warsaw",
    "iso:country":"PL",
    "wof:name":"Wlewo",
    "wof:placetype":"locality"
},
  "geometry": {"coordinates":[15.25726,54.00565],"type":"Point"}
}