{
  "type": "Feature",
  "properties": {
    "gn:gn_country":"PL",
    "gn:gn_fcode":"PPL",
    "gn:gn_pop":0,
    "iso:country":"PL",
    "name:cat_x_preferred":[
        "Treblinka"
    ],
    "name:ces_x_preferred":[
        "Treblinka"
    ],
    "name:cze_x_preferred":[
        "Treblinka"
    ],
    "name:dan_x_preferred":[
        "Treblinka"
    ],
    "name:deu_x_preferred":[
        "Treblinka"
    ],
    "name:dut_x_preferred":[
        "Treblinka"
    ],
    "name:eng_x_preferred":[
        "Treblinka"
    ],
    "name:fin_x_preferred":[
        "Treblinka"
    ],
    "name:fra_x_preferred":[
        "Treblinka"
    ],
    "name:fre_x_preferred":[
        "Treblinka"
    ],
    "name:fry_x_preferred":[
        "Treblinka"
    ],
    "name:ger_x_preferred":[
        "Treblinka"
    ],
    "name:heb_x_preferred":[
        "\u05d8\u05e8\u05d1\u05dc\u05d9\u05e0\u05e7\u05d4"
    ],
    "name:nld_x_preferred":[
        "Treblinka"
    ],
    "name:nor_x_preferred":[
        "Treblinka"
    ],
    "name:per_x_preferred":[
        "\u062a\u0631\u0628\u0644\u06cc\u0646\u06a9\u0627"
    ],
    "name:pol_x_preferred":[
        "Treblinka"
    ],
    "name:por_x_preferred":[
        "Treblinka"
    ],
    "name:rum_x_preferred":[
        "Treblinka"
    ],
    "name:rus_x_preferred":[
        "\u0422\u0440\u0435\u0431\u043b\u0438\u043d\u043a\u0430"
    ],
    "name:slo_x_preferred":[
        "Treblinka"
    ],
    "name:slv_x_preferred":[
        "Treblinka"
    ],
    "name:swe_x_preferred":[
        "Treblinka"
    ],
    "qs_pg:aaroncc":"PL",
    "qs_pg:gn_country":"PL",
    "qs_pg:gn_fcode":"PPL",
    "qs_pg:gn_pop":0,
    "qs_pg:name":"Treblinka",
    "qs_pg:name_adm0":"Polska",
    "qs_pg:name_adm1":"Mazowieckie",
    "qs_pg:photos":119,
    "qs_pg:photos_1k":24,
    "qs_pg:photos_9k":1,
    "qs_pg:photos_9r":3,
    "qs_pg:photos_all":119,
    "qs_pg:photos_sr":3,
    "qs_pg:pop_sr":0,
    "qs_pg:qs_pg_placetype":"locality",
    "qs_pg:qs_pg_placetype_gp":"Town",
    "qs_pg:woe_adm0":23424923,
    "woe:adm0_id":23424923,
    "woe:name_adm0":"Polska",
    "woe:name_adm1":"Mazowieckie",
    "woe:placetype":"Town",
    "wof:name":"Treblinka",
    "wof:placetype":"locality"
},
  "geometry": {"coordinates":[22.02176,52.66202],"type":"Point"}
}