{
  "type": "Feature",
  "properties": {
    "gn:gn_country":"PL",
    "gn:gn_fcode":"PPL",
    "gn:gn_pop":927,
    "gn:population":927,
    "iso:country":"PL",
    "name:dut_x_preferred":[
        "Niechorze"
    ],
    "name:eng_x_preferred":[
        "Niechorze"
    ],
    "name:fre_x_preferred":[
        "Niechorze"
    ],
    "name:ger_x_preferred":[
        "Niechorze"
    ],
    "name:per_x_preferred":[
        "\u0646\u06af\u062e\u0648\u0698\u0647"
    ],
    "name:pol_x_preferred":[
        "Niechorze"
    ],
    "name:unk_x_variant":[
        "Klein Horst"
    ],
    "qs_pg:aaroncc":"PL",
    "qs_pg:gn_country":"PL",
    "qs_pg:gn_fcode":"PPL",
    "qs_pg:gn_pop":927,
    "qs_pg:name":"Niechorze",
    "qs_pg:name_adm0":"Polska",
    "qs_pg:name_adm1":"Zachodniopomorskie",
    "qs_pg:photos":46,
    "qs_pg:photos_1k":9,
    "qs_pg:photos_9k":1,
    "qs_pg:photos_9r":2,
    "qs_pg:photos_all":46,
    "qs_pg:photos_sr":2,
    "qs_pg:pop_sr":2,
    "qs_pg:qs_pg_placetype":"locality",
    "qs_pg:qs_pg_placetype_gp":"Town",
    "qs_pg:woe_adm0":23424923,
    "woe:adm0_id":23424923,
    "woe:name_adm0":"Polska",
    "woe:name_adm1":"Zachodniopomorskie",
    "woe:placetype":"Town",
    "wof:name":"Niechorze",
    "wof:placetype":"locality",
    "wof:population":927
},
  "geometry": {"coordinates":[15.08062,54.09595],"type":"Point"}
}