{
  "type": "Feature",
  "properties": {
    "gn:gn_country":"PL",
    "gn:gn_fcode":"PPL",
    "gn:gn_pop":9657,
    "gn:population":9657,
    "iso:country":"PL",
    "name:eng_x_preferred":[
        "Gmina Lw\u00f3wek \u015al\u0105ski"
    ],
    "name:epo_x_preferred":[
        "Komunumo Lw\u00f3wek \u015al\u0105ski"
    ],
    "name:por_x_preferred":[
        "Comuna de Lw\u00f3wek \u015al\u0105ski"
    ],
    "name:rus_x_preferred":[
        "\u041b\u044c\u0432\u0443\u0432\u0435\u043a-\u0421\u043b\u0451\u043d\u0441\u043a\u0438"
    ],
    "name:slk_x_preferred":[
        "Gmina Lw\u00f3wek \u015al\u0105ski"
    ],
    "name:ukr_x_preferred":[
        "\u0490\u043c\u0456\u043d\u0430 \u041b\u044c\u0432\u0443\u0432\u0435\u043a-\u0428\u043b\u044c\u043e\u043d\u0441\u044c\u043a\u0438\u0439"
    ],
    "name:unk_x_variant":[
        "L\u00f6wenberg"
    ],
    "name:war_x_preferred":[
        "Gmina Lw\u00f3wek \u015al\u0105ski"
    ],
    "qs_pg:aaroncc":"PL",
    "qs_pg:gn_country":"PL",
    "qs_pg:gn_fcode":"PPL",
    "qs_pg:gn_pop":9657,
    "qs_pg:name":"Lw\u00f3wek \u015al\u0105ski",
    "qs_pg:name_adm0":"Polska",
    "qs_pg:name_adm1":"Dolnosl\u0105skie",
    "qs_pg:photos":336,
    "qs_pg:photos_1k":68,
    "qs_pg:photos_9k":1,
    "qs_pg:photos_9r":5,
    "qs_pg:photos_all":336,
    "qs_pg:photos_sr":5,
    "qs_pg:pop_sr":5,
    "qs_pg:qs_pg_placetype":"locality",
    "qs_pg:qs_pg_placetype_gp":"Town",
    "qs_pg:woe_adm0":23424923,
    "woe:adm0_id":23424923,
    "woe:name_adm0":"Polska",
    "woe:name_adm1":"Dolnosl\u0105skie",
    "woe:placetype":"Town",
    "wof:name":"Lw\u00f3wek \u015al\u0105ski",
    "wof:placetype":"locality",
    "wof:population":9657
},
  "geometry": {"coordinates":[15.58582,51.11074],"type":"Point"}
}