{
  "type": "Feature",
  "properties": {
    "gn:country":"PL",
    "gn:fcode":"PPLA3",
    "gn:population":34308,
    "iso:country":"PL",
    "name:azb_x_preferred":[
        "\u0686\u0644\u0627\u0686"
    ],
    "name:bul_x_preferred":[
        "\u0427\u0435\u043b\u044f\u0434\u0436"
    ],
    "name:ceb_x_preferred":[
        "Czelad\u017a"
    ],
    "name:deu_x_preferred":[
        "Czelad\u017a"
    ],
    "name:epo_x_preferred":[
        "Czelad\u017a"
    ],
    "name:eus_x_preferred":[
        "Czelad\u017a"
    ],
    "name:fas_x_preferred":[
        "\u0686\u0644\u0627\u0686"
    ],
    "name:fra_x_preferred":[
        "Czelad\u017a"
    ],
    "name:heb_x_preferred":[
        "\u05e6'\u05dc\u05d3\u05d6"
    ],
    "name:hsb_x_preferred":[
        "Czelad\u017a"
    ],
    "name:ita_x_preferred":[
        "Czelad\u017a"
    ],
    "name:jav_x_preferred":[
        "Czelad\u017a"
    ],
    "name:jpn_x_preferred":[
        "\u30c1\u30a7\u30e9\u30c1"
    ],
    "name:lav_x_preferred":[
        "\u010celadza"
    ],
    "name:lit_x_preferred":[
        "\u010celiadz\u0117"
    ],
    "name:msa_x_preferred":[
        "Czelad\u017a"
    ],
    "name:nld_x_preferred":[
        "Czelad\u017a"
    ],
    "name:pol_x_preferred":[
        "Czelad\u017a"
    ],
    "name:por_x_preferred":[
        "Czelad\u017a"
    ],
    "name:ron_x_preferred":[
        "Czelad\u017a"
    ],
    "name:rus_x_preferred":[
        "\u0427\u0435\u043b\u044f\u0434\u0437\u044c"
    ],
    "name:slk_x_preferred":[
        "Czelad\u017a"
    ],
    "name:spa_x_preferred":[
        "Czelad\u017a"
    ],
    "name:srp_x_preferred":[
        "\u0427\u0435\u043b\u0430\u0452"
    ],
    "name:szl_x_preferred":[
        "Czelad\u017a"
    ],
    "name:udm_x_preferred":[
        "\u04f4\u0435\u043b\u044f\u04df"
    ],
    "name:ukr_x_preferred":[
        "\u0427\u0435\u043b\u044f\u0434\u0437\u044c"
    ],
    "name:und_x_variant":[
        "Czeladz Piaski"
    ],
    "name:vie_x_preferred":[
        "Czelad\u017a"
    ],
    "name:war_x_preferred":[
        "Czelad\u017a"
    ],
    "name:zho_x_preferred":[
        "\u5207\u62c9\u5b63"
    ],
    "qs_pg:aaroncc":"PL",
    "qs_pg:gn_country":"PL",
    "qs_pg:gn_fcode":"PPLA3",
    "qs_pg:gn_pop":34308,
    "qs_pg:name":"Czelad\u017a",
    "qs_pg:name_adm0":"Polska",
    "qs_pg:name_adm1":"Sl\u0105skie",
    "qs_pg:photos":1,
    "qs_pg:photos_1k":1,
    "qs_pg:photos_9k":1,
    "qs_pg:photos_9r":1,
    "qs_pg:photos_all":17,
    "qs_pg:photos_sr":1,
    "qs_pg:pop_sr":7,
    "qs_pg:qs_pg_placetype":"localadmin",
    "qs_pg:qs_pg_placetype_gp":"LocalAdmin",
    "qs_pg:woe_adm0":23424923,
    "woe:adm0_id":23424923,
    "woe:name_adm0":"Polska",
    "woe:name_adm1":"Sl\u0105skie",
    "woe:placetype":"LocalAdmin",
    "wof:name":"Czelad\u017a",
    "wof:placetype":"localadmin",
    "wof:population":34308
},
  "geometry": {"coordinates":[19.07824,50.31542],"type":"Point"}
}