{
  "type": "Feature",
  "properties": {
    "gn:admin1_code":"74.0",
    "gn:admin2_code":"1013.0",
    "gn:admin3_code":"101304.0",
    "gn:asciiname":"Julianow Raducki",
    "gn:country_code":"PL",
    "gn:dem":132,
    "gn:feature_class":"P",
    "gn:feature_code":"PPL",
    "gn:name":"Julian\u00f3w Raducki",
    "gn:population":0,
    "gn:timezone":"Europe/Warsaw",
    "iso:country":"PL",
    "name:und_x_variant":[
        "Juljan\u00f3w",
        "Julian\u00f3w Raducki"
    ],
    "wof:name":"Julianow Raducki",
    "wof:placetype":"locality"
},
  "geometry": {"coordinates":[20.31633,51.83755],"type":"Point"}
}