{
  "type": "Feature",
  "properties": {
    "gn:admin1_code":"74.0",
    "gn:admin2_code":"1013.0",
    "gn:admin3_code":"101304.0",
    "gn:asciiname":"Julianow Raducki",
    "gn:country_code":"PL",
    "gn:dem":132,
    "gn:feature_class":"P",
    "gn:feature_code":"PPL",
    "gn:name":"Julian\u00f3w Raducki",
    "gn:population":0,
    "gn:timezone":"Europe/Warsaw",
    "iso:country":"PL",
    "name:azb_x_preferred":[
        "\u06cc\u0648\u0644\u06cc\u0627\u0646\u0648\u0641 \u0631\u0627\u062f\u0648\u062a\u0633\u06a9\u06cc"
    ],
    "name:deu_x_preferred":[
        "Julian\u00f3w Raducki"
    ],
    "name:fas_x_preferred":[
        "\u06cc\u0648\u0644\u06cc\u0627\u0646\u0648\u0641 \u0631\u0627\u062f\u0648\u062a\u0633\u06a9\u06cc"
    ],
    "name:pol_x_preferred":[
        "Julian\u00f3w Raducki"
    ],
    "name:srp_x_preferred":[
        "\u0408\u0443\u0459\u0430\u043d\u0443\u0432 \u0420\u0430\u0434\u0443\u0446\u043a\u0438"
    ],
    "name:ukr_x_preferred":[
        "\u042e\u043b\u044c\u044f\u043d\u0443\u0432-\u0420\u0430\u0434\u0443\u0446\u044c\u043a\u0438\u0439"
    ],
    "name:und_x_variant":[
        "Juljan\u00f3w",
        "Julian\u00f3w Raducki"
    ],
    "wof:name":"Julianow Raducki",
    "wof:placetype":"locality"
},
  "geometry": {"coordinates":[20.31633,51.83755],"type":"Point"}
}