{
  "type": "Feature",
  "properties": {
    "gn:country":"PL",
    "gn:fcode":"PPL",
    "gn:population":128,
    "iso:country":"PL",
    "name:ceb_x_preferred":[
        "Karnice"
    ],
    "name:deu_x_preferred":[
        "Karnice"
    ],
    "name:fra_x_preferred":[
        "Karnice"
    ],
    "name:pol_x_preferred":[
        "Karnice"
    ],
    "name:ukr_x_preferred":[
        "\u041a\u0430\u0440\u043d\u0456\u0446\u0435"
    ],
    "qs_pg:aaroncc":"PL",
    "qs_pg:gn_country":"PL",
    "qs_pg:gn_fcode":"PPL",
    "qs_pg:gn_pop":128,
    "qs_pg:name":"Karnice",
    "qs_pg:name_adm0":"Polska",
    "qs_pg:name_adm1":"Dolnosl\u0105skie",
    "qs_pg:photos_9r":0,
    "qs_pg:photos_sr":0,
    "qs_pg:pop_sr":1,
    "qs_pg:qs_pg_placetype":"locality",
    "qs_pg:qs_pg_placetype_gp":"Town",
    "qs_pg:woe_adm0":23424923,
    "woe:adm0_id":23424923,
    "woe:name_adm0":"Polska",
    "woe:name_adm1":"Dolnosl\u0105skie",
    "woe:placetype":"Town",
    "wof:name":"Karnice",
    "wof:placetype":"locality",
    "wof:population":128
},
  "geometry": {"coordinates":[16.48155,51.09738],"type":"Point"}
}