{
  "type": "Feature",
  "properties": {
    "gn:admin1_code":"74.0",
    "gn:admin2_code":"1006.0",
    "gn:admin3_code":"100608.0",
    "gn:asciiname":"Glogowice",
    "gn:country_code":"PL",
    "gn:dem":216,
    "gn:feature_class":"P",
    "gn:feature_code":"PPL",
    "gn:name":"G\u0142ogowice",
    "gn:population":0,
    "gn:timezone":"Europe/Warsaw",
    "iso:country":"PL",
    "name:und_x_variant":[
        "G\u0142ogowiec",
        "G\u0142ogowice"
    ],
    "wof:name":"Glogowice",
    "wof:placetype":"locality"
},
  "geometry": {"coordinates":[19.65164,51.83531],"type":"Point"}
}