{
  "type": "Feature",
  "properties": {
    "iso:country":"PL",
    "name:eng_x_preferred":[
        "Szufnarowa"
    ],
    "name:fre_x_preferred":[
        "Szufnarowa"
    ],
    "name:pol_x_preferred":[
        "Szufnarowa"
    ],
    "qs:a0":"Rzeczpospolita Polska",
    "qs:a1":"*Podkarpackie",
    "qs:a1r":"0",
    "qs:a2":"Strzyzowski",
    "qs:adm0":"Rzeczpospolita Polska",
    "qs:la_lc":"*",
    "qs:level":"locality",
    "qs:loc":"Szufnarowa",
    "qs:loc_alt":"Szufnarowa",
    "qs:pop":0,
    "qs:type":"buffered point",
    "wd:wordcount":92,
    "wof:name":"Szufnarowa",
    "wof:placetype":"locality"
},
  "geometry": {"coordinates":[21.631988,49.902302],"type":"Point"}
}