{
  "type": "Feature",
  "properties": {
    "gn:admin1_code":"74.0",
    "gn:admin2_code":"1014.0",
    "gn:admin3_code":"101411.0",
    "gn:asciiname":"Unikow",
    "gn:country_code":"PL",
    "gn:dem":176,
    "gn:feature_class":"P",
    "gn:feature_code":"PPL",
    "gn:name":"Unik\u00f3w",
    "gn:population":0,
    "gn:timezone":"Europe/Warsaw",
    "iso:country":"PL",
    "name:pol_x_preferred":[
        "Unik\u00f3w"
    ],
    "name:ukr_x_preferred":[
        "\u0423\u043d\u0456\u043a\u0443\u0432"
    ],
    "wof:name":"Unikow",
    "wof:placetype":"locality"
},
  "geometry": {"coordinates":[18.5498,51.40229],"type":"Point"}
}