{
  "type": "Feature",
  "properties": {
    "gn:admin1_code":"87.0",
    "gn:admin2_code":"3206.0",
    "gn:admin3_code":"320607.0",
    "gn:asciiname":"Binowo",
    "gn:country_code":"PL",
    "gn:dem":46,
    "gn:feature_class":"P",
    "gn:feature_code":"PPL",
    "gn:name":"Binowo",
    "gn:population":0,
    "gn:timezone":"Europe/Warsaw",
    "iso:country":"PL",
    "name:ceb_x_preferred":[
        "Binowo"
    ],
    "name:nld_x_preferred":[
        "Binowo"
    ],
    "name:pol_x_preferred":[
        "Binowo"
    ],
    "name:ukr_x_preferred":[
        "\u0411\u0456\u043d\u043e\u0432\u043e"
    ],
    "name:und_x_variant":[
        "Binow"
    ],
    "name:vie_x_preferred":[
        "Binowo"
    ],
    "wof:name":"Binowo",
    "wof:placetype":"locality"
},
  "geometry": {"coordinates":[14.64839,53.30646],"type":"Point"}
}