{
  "type": "Feature",
  "properties": {
    "gn:admin1_code":"75.0",
    "gn:admin2_code":"615.0",
    "gn:admin3_code":"61504.0",
    "gn:asciiname":"Zakowola",
    "gn:country_code":"PL",
    "gn:dem":152,
    "gn:feature_class":"P",
    "gn:feature_code":"PPL",
    "gn:name":"\u017bakowola",
    "gn:population":0,
    "gn:timezone":"Europe/Warsaw",
    "iso:country":"PL",
    "wof:name":"Zakowola",
    "wof:placetype":"locality"
},
  "geometry": {"coordinates":[22.69777,51.87300000000001],"type":"Point"}
}