{
  "type": "Feature",
  "properties": {
    "gn:admin1_code":"82.0",
    "gn:admin2_code":"2213.0",
    "gn:admin3_code":"221305.0",
    "gn:asciiname":"Bartel Wielki",
    "gn:country_code":"PL",
    "gn:dem":145,
    "gn:feature_class":"P",
    "gn:feature_code":"PPL",
    "gn:name":"Bartel Wielki",
    "gn:population":0,
    "gn:timezone":"Europe/Warsaw",
    "iso:country":"PL",
    "name:ceb_x_preferred":[
        "Bartel Wielki"
    ],
    "name:nld_x_preferred":[
        "Bartel Wielki"
    ],
    "name:pol_x_preferred":[
        "Bartel Wielki"
    ],
    "name:ukr_x_preferred":[
        "\u0411\u0430\u0440\u0442\u0435\u043b\u044c-\u0412\u0435\u043b\u0438\u043a\u0438\u0439"
    ],
    "name:und_x_variant":[
        "Wielki Bartel",
        "Bartel Wielki"
    ],
    "wof:name":"Bartel Wielki",
    "wof:placetype":"locality"
},
  "geometry": {"coordinates":[18.14191,53.91336999999999],"type":"Point"}
}