{
  "type": "Feature",
  "properties": {
    "gn:admin1_code":"86.0",
    "gn:admin2_code":"3021.0",
    "gn:admin3_code":"302106.0",
    "gn:asciiname":"Zimin",
    "gn:country_code":"PL",
    "gn:dem":85,
    "gn:feature_class":"P",
    "gn:feature_code":"PPL",
    "gn:name":"Zimin",
    "gn:population":0,
    "gn:timezone":"Europe/Warsaw",
    "iso:country":"PL",
    "name:ceb_x_preferred":[
        "Zimin"
    ],
    "name:fra_x_preferred":[
        "Zimin"
    ],
    "name:pol_x_preferred":[
        "Zimin"
    ],
    "name:ukr_x_preferred":[
        "\u0417\u0456\u043c\u0456\u043d"
    ],
    "wof:name":"Zimin",
    "wof:placetype":"locality"
},
  "geometry": {"coordinates":[17.1578,52.29467],"type":"Point"}
}