{
  "type": "Feature",
  "properties": {
    "gn:admin1_code":"84.0",
    "gn:admin2_code":"2606.0",
    "gn:admin3_code":"260601.0",
    "gn:asciiname":"Stanislawow",
    "gn:country_code":"PL",
    "gn:dem":338,
    "gn:feature_class":"P",
    "gn:feature_code":"PPL",
    "gn:name":"Stanis\u0142aw\u00f3w",
    "gn:population":0,
    "gn:timezone":"Europe/Warsaw",
    "iso:country":"PL",
    "wof:name":"Stanislawow",
    "wof:placetype":"locality"
},
  "geometry": {"coordinates":[21.25525,50.80657],"type":"Point"}
}