{
  "type": "Feature",
  "properties": {
    "gn:admin1_code":"85.0",
    "gn:admin2_code":"2819.0",
    "gn:admin3_code":"281903.0",
    "gn:asciiname":"Guja",
    "gn:country_code":"PL",
    "gn:dem":76,
    "gn:feature_class":"P",
    "gn:feature_code":"PPL",
    "gn:name":"Guja",
    "gn:population":0,
    "gn:timezone":"Europe/Warsaw",
    "iso:country":"PL",
    "name:ceb_x_preferred":[
        "Guja"
    ],
    "name:deu_x_preferred":[
        "Guja"
    ],
    "name:pol_x_preferred":[
        "Guja"
    ],
    "name:ukr_x_preferred":[
        "\u0490\u0443\u044f"
    ],
    "name:und_x_variant":[
        "Gross Guja"
    ],
    "wof:name":"Guja",
    "wof:placetype":"locality"
},
  "geometry": {"coordinates":[21.59518,54.26463],"type":"Point"}
}