{
  "type": "Feature",
  "properties": {
    "gn:population":1400,
    "iso:country":"PL",
    "name:ast_x_preferred":[
        "G\u0105sawa"
    ],
    "name:azb_x_preferred":[
        "\u0642\u0627\u0646\u0633\u0627\u0648\u0627"
    ],
    "name:ceb_x_preferred":[
        "G\u0105sawa"
    ],
    "name:deu_x_preferred":[
        "G\u0105sawa"
    ],
    "name:eng_x_preferred":[
        "G\u0105sawa"
    ],
    "name:fas_x_preferred":[
        "\u06af\u0627\u0646\u0633\u0627\u0648\u0627"
    ],
    "name:fra_x_preferred":[
        "G\u0105sawa"
    ],
    "name:ita_x_preferred":[
        "G\u0105sawa"
    ],
    "name:nan_x_preferred":[
        "G\u0105sawa"
    ],
    "name:nld_x_preferred":[
        "G\u0105sawa"
    ],
    "name:pol_x_preferred":[
        "G\u0105sawa"
    ],
    "name:ukr_x_preferred":[
        "\u041c\u0435\u0434\u0437\u043d\u0430"
    ],
    "name:ukr_x_variant":[
        "\u0490\u043e\u043d\u0441\u0430\u0432\u0430"
    ],
    "name:vie_x_preferred":[
        "G\u0105sawa"
    ],
    "qs:a0":"Rzeczpospolita Polska",
    "qs:a1":"*Kujawsko-pomorskie",
    "qs:a1r":"0",
    "qs:a2":"Zninski",
    "qs:adm0":"Rzeczpospolita Polska",
    "qs:la":"G\u0105sawa",
    "qs:la_lc":"*PL0419022",
    "qs:level":"locality",
    "qs:loc":"G\u0105sawa",
    "qs:loc_alt":"Gasawa",
    "qs:pop":0,
    "qs:type":"rural point-in-poly",
    "wd:wordcount":277,
    "wof:name":"G\u0105sawa",
    "wof:placetype":"locality",
    "wof:population":1400
},
  "geometry": {"coordinates":[17.8006506147494,52.7556636152091],"type":"Point"}
}