{
  "type": "Feature",
  "properties": {
    "gn:admin1_code":"87.0",
    "gn:admin2_code":"3201.0",
    "gn:admin3_code":"320102.0",
    "gn:asciiname":"Bialogorzyno",
    "gn:country_code":"PL",
    "gn:dem":34,
    "gn:feature_class":"P",
    "gn:feature_code":"PPL",
    "gn:name":"Bia\u0142og\u00f3rzyno",
    "gn:population":0,
    "gn:timezone":"Europe/Warsaw",
    "iso:country":"PL",
    "name:deu_x_preferred":[
        "Bia\u0142og\u00f3rzyno"
    ],
    "name:pol_x_preferred":[
        "Bia\u0142og\u00f3rzyno"
    ],
    "name:ukr_x_preferred":[
        "\u0411\u044f\u043b\u043e\u0491\u0443\u0436\u0438\u043d\u043e"
    ],
    "name:und_x_variant":[
        "Bulgrin"
    ],
    "name:vie_x_preferred":[
        "Bia\u0142og\u00f3rzyno"
    ],
    "wof:name":"Bialogorzyno",
    "wof:placetype":"locality"
},
  "geometry": {"coordinates":[16.0902,54.07747],"type":"Point"}
}