{
  "type": "Feature",
  "properties": {
    "gn:admin1_code":"81.0",
    "gn:admin2_code":"2001.0",
    "gn:admin3_code":"200107.0",
    "gn:asciiname":"Janowek",
    "gn:country_code":"PL",
    "gn:dem":129,
    "gn:feature_class":"P",
    "gn:feature_code":"PPL",
    "gn:name":"Jan\u00f3wek",
    "gn:population":0,
    "gn:timezone":"Europe/Warsaw",
    "iso:country":"PL",
    "name:lit_x_preferred":[
        "Januvekas"
    ],
    "name:pol_x_preferred":[
        "Jan\u00f3wek"
    ],
    "name:ukr_x_preferred":[
        "\u042f\u043d\u0443\u0432\u0435\u043a"
    ],
    "name:urd_x_preferred":[
        "\u062c\u0646\u0648\u0648\u06cc\u06a9"
    ],
    "wof:name":"Janowek",
    "wof:placetype":"locality"
},
  "geometry": {"coordinates":[23.04636,53.68544],"type":"Point"}
}