{
  "type": "Feature",
  "properties": {
    "gn:admin1_code":"81.0",
    "gn:admin2_code":"2001.0",
    "gn:admin3_code":"200107.0",
    "gn:asciiname":"Janowek",
    "gn:country_code":"PL",
    "gn:dem":129,
    "gn:feature_class":"P",
    "gn:feature_code":"PPL",
    "gn:name":"Jan\u00f3wek",
    "gn:population":0,
    "gn:timezone":"Europe/Warsaw",
    "iso:country":"PL",
    "name:und_x_variant":[
        "Jan\u00f3wek"
    ],
    "wof:name":"Janowek",
    "wof:placetype":"locality"
},
  "geometry": {"coordinates":[23.04636,53.68544],"type":"Point"}
}