{
  "type": "Feature",
  "properties": {
    "gn:admin1_code":"73.0",
    "gn:admin2_code":"416.0",
    "gn:admin3_code":"41606.0",
    "gn:asciiname":"Jaty",
    "gn:country_code":"PL",
    "gn:dem":124,
    "gn:feature_class":"P",
    "gn:feature_code":"PPL",
    "gn:name":"Jaty",
    "gn:population":0,
    "gn:timezone":"Europe/Warsaw",
    "iso:country":"PL",
    "name:pol_x_preferred":[
        "Jaty"
    ],
    "wof:name":"Jaty",
    "wof:placetype":"locality"
},
  "geometry": {"coordinates":[17.89467,53.7477],"type":"Point"}
}