{
  "type": "Feature",
  "properties": {
    "gn:admin1_code":"83.0",
    "gn:admin2_code":"2401.0",
    "gn:admin3_code":"240106.0",
    "gn:asciiname":"Gora Siewierska",
    "gn:country_code":"PL",
    "gn:dem":372,
    "gn:feature_class":"P",
    "gn:feature_code":"PPL",
    "gn:name":"G\u00f3ra Siewierska",
    "gn:population":0,
    "gn:timezone":"Europe/Warsaw",
    "iso:country":"PL",
    "name:und_x_variant":[
        "G\u00f3ra Siewierska"
    ],
    "wof:name":"Gora Siewierska",
    "wof:placetype":"locality"
},
  "geometry": {"coordinates":[19.08304,50.40174],"type":"Point"}
}