{
  "type": "Feature",
  "properties": {
    "gn:admin1_code":"83.0",
    "gn:admin2_code":"2401.0",
    "gn:admin3_code":"240106.0",
    "gn:asciiname":"Gora Siewierska",
    "gn:country_code":"PL",
    "gn:dem":372,
    "gn:feature_class":"P",
    "gn:feature_code":"PPL",
    "gn:name":"G\u00f3ra Siewierska",
    "gn:population":0,
    "gn:timezone":"Europe/Warsaw",
    "iso:country":"PL",
    "name:azb_x_preferred":[
        "\u0642\u0648\u0631\u0627 \u0634\u0648\u06cc\u0631\u0633\u06a9\u0627"
    ],
    "name:ceb_x_preferred":[
        "G\u00f3ra Siewierska"
    ],
    "name:fas_x_preferred":[
        "\u06af\u0648\u0631\u0627 \u0634\u0648\u06cc\u0631\u0633\u06a9\u0627"
    ],
    "name:nld_x_preferred":[
        "G\u00f3ra Siewierska"
    ],
    "name:pol_x_preferred":[
        "G\u00f3ra Siewierska"
    ],
    "name:ukr_x_preferred":[
        "\u0490\u0443\u0440\u0430-\u0421\u0435\u0432\u0435\u0440\u0441\u044c\u043a\u0430"
    ],
    "wof:name":"Gora Siewierska",
    "wof:placetype":"locality"
},
  "geometry": {"coordinates":[19.08304,50.40174],"type":"Point"}
}