{
  "type": "Feature",
  "properties": {
    "gn:admin1_code":"78",
    "gn:admin2_code":"1465",
    "gn:admin3_code":"146501.0",
    "gn:admin4_code":"146517_8",
    "gn:asciiname":"Solipse",
    "gn:country_code":"PL",
    "gn:dem":110,
    "gn:feature_class":"P",
    "gn:feature_code":"PPL",
    "gn:name":"Solipse",
    "gn:population":0,
    "gn:timezone":"Europe/Warsaw",
    "iso:country":"PL",
    "wof:name":"Solipse",
    "wof:placetype":"locality"
},
  "geometry": {"coordinates":[20.9073,52.20181],"type":"Point"}
}