{
  "type": "Feature",
  "properties": {
    "gn:admin1_code":"72.0",
    "gn:admin2_code":"210.0",
    "gn:admin3_code":"21005.0",
    "gn:asciiname":"Krzewie Male",
    "gn:country_code":"PL",
    "gn:dem":303,
    "gn:feature_class":"P",
    "gn:feature_code":"PPL",
    "gn:name":"Krzewie Ma\u0142e",
    "gn:population":0,
    "gn:timezone":"Europe/Warsaw",
    "iso:country":"PL",
    "name:ceb_x_preferred":[
        "Krzewie Ma\u0142e"
    ],
    "name:deu_x_historical":[
        "Klein St\u00f6ckigt"
    ],
    "name:deu_x_preferred":[
        "Klein St\u00f6ckigt"
    ],
    "name:pol_x_preferred":[
        "Krzewie Ma\u0142e"
    ],
    "name:ukr_x_preferred":[
        "\u041a\u0448\u0435\u0432\u0435-\u041c\u0430\u043b\u0435"
    ],
    "wof:name":"Krzewie Male",
    "wof:placetype":"locality"
},
  "geometry": {"coordinates":[15.36026,51.05014],"type":"Point"}
}