{
  "type": "Feature",
  "properties": {
    "iso:country":"PL",
    "name:pol_x_variant":[
        "Opacz"
    ],
    "wof:name":"Opacz Wielka",
    "wof:placetype":"neighbourhood"
},
  "geometry": {"coordinates":[20.92837398808204,52.17716818859596],"type":"Point"}
}