{
  "type": "Feature",
  "properties": {
    "gn:admin1_code":"78.0",
    "gn:admin2_code":"1414.0",
    "gn:admin3_code":"141404.0",
    "gn:asciiname":"Piescirogi Stare",
    "gn:country_code":"PL",
    "gn:dem":104,
    "gn:feature_class":"P",
    "gn:feature_code":"PPL",
    "gn:name":"Pie\u015bcirogi Stare",
    "gn:population":0,
    "gn:timezone":"Europe/Warsaw",
    "iso:country":"PL",
    "name:fra_x_preferred":[
        "Stare Pie\u015bcirogi"
    ],
    "name:mkd_x_preferred":[
        "\u0421\u0442\u0430\u0440\u0435 \u041f\u0458\u0435\u0448\u045c\u0438\u0440\u043e\u0433\u0438"
    ],
    "name:pol_x_preferred":[
        "Stare Pie\u015bcirogi"
    ],
    "name:ukr_x_preferred":[
        "\u0421\u0442\u0430\u0440\u0435 \u041f\u0435\u0441\u0446\u0438\u0440\u043e\u0491\u0456"
    ],
    "name:und_x_variant":[
        "Pie\u015bcirogi",
        "Pie\u015bcirogi Stare"
    ],
    "wof:name":"Piescirogi Stare",
    "wof:placetype":"locality"
},
  "geometry": {"coordinates":[20.75802,52.58201],"type":"Point"}
}