{
  "type": "Feature",
  "properties": {
    "gn:admin1_code":"78.0",
    "gn:admin2_code":"1414.0",
    "gn:admin3_code":"141404.0",
    "gn:asciiname":"Piescirogi Stare",
    "gn:country_code":"PL",
    "gn:dem":104,
    "gn:feature_class":"P",
    "gn:feature_code":"PPL",
    "gn:name":"Pie\u015bcirogi Stare",
    "gn:population":0,
    "gn:timezone":"Europe/Warsaw",
    "iso:country":"PL",
    "name:und_x_variant":[
        "Stare Pie\u015bcirogi",
        "Pie\u015bcirogi",
        "Pie\u015bcirogi Stare"
    ],
    "wof:name":"Piescirogi Stare",
    "wof:placetype":"locality"
},
  "geometry": {"coordinates":[20.75802,52.58201],"type":"Point"}
}