{
  "type": "Feature",
  "properties": {
    "gn:admin1_code":"81.0",
    "gn:admin2_code":"2003.0",
    "gn:admin3_code":"200308.0",
    "gn:asciiname":"Lyse",
    "gn:country_code":"PL",
    "gn:dem":128,
    "gn:feature_class":"P",
    "gn:feature_code":"PPL",
    "gn:name":"\u0141yse",
    "gn:population":0,
    "gn:timezone":"Europe/Warsaw",
    "iso:country":"PL",
    "name:lit_x_preferred":[
        "Lis\u0117"
    ],
    "name:pol_x_preferred":[
        "\u0141yse"
    ],
    "name:ukr_x_preferred":[
        "\u041b\u0438\u0441\u0435"
    ],
    "wof:name":"Lyse",
    "wof:placetype":"locality"
},
  "geometry": {"coordinates":[23.10811,52.90782],"type":"Point"}
}