{
  "type": "Feature",
  "properties": {
    "gn:admin1_code":"75.0",
    "gn:admin2_code":"620.0",
    "gn:admin3_code":"62002.0",
    "gn:asciiname":"Zurawlow",
    "gn:country_code":"PL",
    "gn:dem":202,
    "gn:feature_class":"P",
    "gn:feature_code":"PPL",
    "gn:name":"\u017burawl\u00f3w",
    "gn:population":0,
    "gn:timezone":"Europe/Warsaw",
    "iso:country":"PL",
    "name:fra_x_preferred":[
        "\u017burawl\u00f3w"
    ],
    "name:pol_x_preferred":[
        "\u017burawl\u00f3w"
    ],
    "name:ukr_x_preferred":[
        "\u0416\u0443\u0440\u0430\u0432\u043b\u044e\u0432"
    ],
    "name:und_x_variant":[
        "\u017burawi\u00f3w"
    ],
    "wof:name":"Zurawlow",
    "wof:placetype":"locality"
},
  "geometry": {"coordinates":[23.48722,50.81738],"type":"Point"}
}