{
  "type": "Feature",
  "properties": {
    "gn:admin1_code":"74.0",
    "gn:admin2_code":"1010.0",
    "gn:admin3_code":"101010.0",
    "gn:asciiname":"Jezow",
    "gn:country_code":"PL",
    "gn:dem":200,
    "gn:feature_class":"P",
    "gn:feature_code":"PPL",
    "gn:name":"Je\u017c\u00f3w",
    "gn:population":303,
    "gn:timezone":"Europe/Warsaw",
    "iso:country":"PL",
    "name:ceb_x_preferred":[
        "Je\u017c\u00f3w"
    ],
    "name:fra_x_preferred":[
        "Je\u017c\u00f3w"
    ],
    "name:pol_x_preferred":[
        "Je\u017c\u00f3w"
    ],
    "name:ukr_x_preferred":[
        "\u0404\u0436\u0443\u0432"
    ],
    "wof:name":"Jezow",
    "wof:placetype":"locality",
    "wof:population":303
},
  "geometry": {"coordinates":[19.59506,51.31806],"type":"Point"}
}