{
  "type": "Feature",
  "properties": {
    "gn:admin1_code":"85.0",
    "gn:admin2_code":"2802.0",
    "gn:admin3_code":"280207.0",
    "gn:asciiname":"Spedy",
    "gn:country_code":"PL",
    "gn:dem":32,
    "gn:feature_class":"P",
    "gn:feature_code":"PPL",
    "gn:name":"Spedy",
    "gn:population":0,
    "gn:timezone":"Europe/Warsaw",
    "iso:country":"PL",
    "name:fra_x_preferred":[
        "Sp\u0119dy"
    ],
    "name:pol_x_preferred":[
        "Sp\u0119dy"
    ],
    "wof:name":"Spedy",
    "wof:placetype":"locality"
},
  "geometry": {"coordinates":[19.94913,54.13885],"type":"Point"}
}