{
  "type": "Feature",
  "properties": {
    "gn:admin1_code":"85.0",
    "gn:admin2_code":"2807.0",
    "gn:admin3_code":"280703.0",
    "gn:asciiname":"Sapy",
    "gn:country_code":"PL",
    "gn:dem":102,
    "gn:feature_class":"P",
    "gn:feature_code":"PPL",
    "gn:name":"S\u0105py",
    "gn:population":0,
    "gn:timezone":"Europe/Warsaw",
    "iso:country":"PL",
    "name:fra_x_preferred":[
        "Sapy"
    ],
    "name:pol_x_preferred":[
        "Sapy"
    ],
    "name:ukr_x_preferred":[
        "\u0421\u0430\u043f\u0438"
    ],
    "name:und_x_variant":[
        "Sumpf",
        "S\u0105py"
    ],
    "wof:name":"Sapy",
    "wof:placetype":"locality"
},
  "geometry": {"coordinates":[19.67508,53.70902],"type":"Point"}
}