{
  "type": "Feature",
  "properties": {
    "gn:admin1_code":"82.0",
    "gn:admin2_code":"2215.0",
    "gn:admin3_code":"221508.0",
    "gn:asciiname":"Rozlazino",
    "gn:country_code":"PL",
    "gn:dem":114,
    "gn:feature_class":"P",
    "gn:feature_code":"PPL",
    "gn:name":"Roz\u0142azino",
    "gn:population":0,
    "gn:timezone":"Europe/Warsaw",
    "iso:country":"PL",
    "name:ceb_x_preferred":[
        "Roz\u0142azino"
    ],
    "name:csb_x_preferred":[
        "Roz\u0142az\u00ebno"
    ],
    "name:pol_x_preferred":[
        "Roz\u0142azino"
    ],
    "name:ukr_x_preferred":[
        "\u0420\u043e\u0437\u043b\u0430\u0437\u0456\u043d\u043e"
    ],
    "name:und_x_variant":[
        "Roslasin"
    ],
    "wof:name":"Rozlazino",
    "wof:placetype":"locality"
},
  "geometry": {"coordinates":[17.91236,54.52588000000001],"type":"Point"}
}