{
  "type": "Feature",
  "properties": {
    "gn:admin1_code":"85.0",
    "gn:admin2_code":"2804.0",
    "gn:admin3_code":"280408.0",
    "gn:asciiname":"Swidy",
    "gn:country_code":"PL",
    "gn:dem":3,
    "gn:feature_class":"P",
    "gn:feature_code":"PPL",
    "gn:name":"\u015awidy",
    "gn:population":0,
    "gn:timezone":"Europe/Warsaw",
    "iso:country":"PL",
    "name:pol_x_preferred":[
        "\u015awidy"
    ],
    "wof:name":"Swidy",
    "wof:placetype":"locality"
},
  "geometry": {"coordinates":[19.38091,53.96457],"type":"Point"}
}