{
  "type": "Feature",
  "properties": {
    "gn:country":"PL",
    "gn:fcode":"PPLA3",
    "gn:population":6714,
    "iso:country":"PL",
    "name:ces_x_preferred":[
        "K\u0142odawa"
    ],
    "name:deu_x_preferred":[
        "K\u0142odawa"
    ],
    "name:dsb_x_preferred":[
        "K\u0142odawa"
    ],
    "name:eng_x_preferred":[
        "K\u0142odawa"
    ],
    "name:epo_x_preferred":[
        "K\u0142odawa"
    ],
    "name:fra_x_preferred":[
        "K\u0142odawa"
    ],
    "name:heb_x_preferred":[
        "\u05e7\u05dc\u05d5\u05d3\u05d0\u05d5\u05d5\u05d4"
    ],
    "name:jav_x_preferred":[
        "K\u0142odawa"
    ],
    "name:jpn_x_preferred":[
        "\u30af\u30a6\u30a9\u30c0\u30f4\u30a1"
    ],
    "name:lav_x_preferred":[
        "Klodava"
    ],
    "name:lit_x_preferred":[
        "Klodava"
    ],
    "name:msa_x_preferred":[
        "K\u0142odawa"
    ],
    "name:nld_x_preferred":[
        "K\u0142odawa"
    ],
    "name:pol_x_preferred":[
        "K\u0142odawa"
    ],
    "name:por_x_preferred":[
        "K\u0142odawa"
    ],
    "name:ron_x_preferred":[
        "K\u0142odawa"
    ],
    "name:rus_x_preferred":[
        "\u041a\u043b\u043e\u0434\u0430\u0432\u0430"
    ],
    "name:slk_x_preferred":[
        "K\u0142odawa"
    ],
    "name:srp_x_preferred":[
        "\u041a\u043b\u043e\u0434\u0430\u0432\u0430"
    ],
    "name:swe_x_preferred":[
        "K\u0142odawa"
    ],
    "name:szl_x_preferred":[
        "K\u0142odawa"
    ],
    "name:ukr_x_preferred":[
        "\u041a\u043b\u043e\u0434\u0430\u0432\u0430"
    ],
    "name:vie_x_preferred":[
        "K\u0142odawa"
    ],
    "name:zho_x_preferred":[
        "\u514b\u6c83\u9054\u74e6"
    ],
    "qs_pg:aaroncc":"PL",
    "qs_pg:gn_country":"PL",
    "qs_pg:gn_fcode":"PPLA3",
    "qs_pg:gn_pop":6714,
    "qs_pg:name":"K\u0142odawa",
    "qs_pg:name_adm0":"Polska",
    "qs_pg:name_adm1":"Wielkopolskie",
    "qs_pg:photos":2,
    "qs_pg:photos_1k":1,
    "qs_pg:photos_9k":1,
    "qs_pg:photos_9r":1,
    "qs_pg:photos_all":2,
    "qs_pg:photos_sr":1,
    "qs_pg:pop_sr":6,
    "qs_pg:qs_pg_placetype":"localadmin",
    "qs_pg:qs_pg_placetype_gp":"LocalAdmin",
    "qs_pg:woe_adm0":23424923,
    "woe:adm0_id":23424923,
    "woe:name_adm0":"Polska",
    "woe:name_adm1":"Wielkopolskie",
    "woe:placetype":"LocalAdmin",
    "wof:name":"K\u0142odawa",
    "wof:placetype":"localadmin",
    "wof:population":6714
},
  "geometry": {"coordinates":[18.91352,52.25447],"type":"Point"}
}