{
  "type": "Feature",
  "properties": {
    "iso:country":"PL",
    "name:ceb_x_preferred":[
        "Nowinka"
    ],
    "name:fra_x_preferred":[
        "Nowinka"
    ],
    "name:lit_x_preferred":[
        "Novinka"
    ],
    "name:nld_x_preferred":[
        "Nowinka"
    ],
    "name:pol_x_preferred":[
        "Nowinka"
    ],
    "name:ukr_x_preferred":[
        "\u041d\u043e\u0432\u0456\u043d\u043a\u0430"
    ],
    "qs_pg:aaroncc":"PL",
    "qs_pg:name":"Nowinka",
    "qs_pg:name_adm0":"Polska",
    "qs_pg:name_adm1":"Podlaskie",
    "qs_pg:photos":4,
    "qs_pg:photos_1k":1,
    "qs_pg:photos_9k":1,
    "qs_pg:photos_9r":2,
    "qs_pg:photos_all":59,
    "qs_pg:photos_sr":1,
    "qs_pg:pop_sr":0,
    "qs_pg:qs_pg_placetype":"localadmin",
    "qs_pg:qs_pg_placetype_gp":"LocalAdmin",
    "qs_pg:woe_adm0":23424923,
    "woe:adm0_id":23424923,
    "woe:name_adm0":"Polska",
    "woe:name_adm1":"Podlaskie",
    "woe:placetype":"LocalAdmin",
    "wof:name":"Nowinka",
    "wof:placetype":"localadmin"
},
  "geometry": {"coordinates":[23.053007,54.000895],"type":"Point"}
}