{
  "type": "Feature",
  "properties": {
    "gn:admin1_code":"87.0",
    "gn:admin2_code":"3213.0",
    "gn:admin3_code":"321303.0",
    "gn:asciiname":"Krupy",
    "gn:country_code":"PL",
    "gn:dem":12,
    "gn:feature_class":"P",
    "gn:feature_code":"PPL",
    "gn:name":"Krupy",
    "gn:population":0,
    "gn:timezone":"Europe/Warsaw",
    "iso:country":"PL",
    "name:und_x_variant":[
        "Grupenhagen",
        "Krupy"
    ],
    "wof:name":"Krupy",
    "wof:placetype":"locality"
},
  "geometry": {"coordinates":[16.51535,54.42379],"type":"Point"}
}