{
  "type": "Feature",
  "properties": {
    "gn:admin1_code":"73.0",
    "gn:admin2_code":"402.0",
    "gn:admin3_code":"40206.0",
    "gn:asciiname":"Zdroje",
    "gn:country_code":"PL",
    "gn:dem":74,
    "gn:feature_class":"P",
    "gn:feature_code":"PPL",
    "gn:name":"Zdroje",
    "gn:population":0,
    "gn:timezone":"Europe/Warsaw",
    "iso:country":"PL",
    "name:ceb_x_preferred":[
        "Zdroje"
    ],
    "name:pol_x_preferred":[
        "Zdroje"
    ],
    "name:ukr_x_preferred":[
        "\u0417\u0434\u0440\u043e\u0454"
    ],
    "wof:name":"Zdroje",
    "wof:placetype":"locality"
},
  "geometry": {"coordinates":[19.61489,53.24231],"type":"Point"}
}