{
  "type": "Feature",
  "properties": {
    "gn:admin1_code":"73.0",
    "gn:admin2_code":"413.0",
    "gn:admin3_code":"41303.0",
    "gn:asciiname":"Obodowo",
    "gn:country_code":"PL",
    "gn:dem":131,
    "gn:feature_class":"P",
    "gn:feature_code":"PPL",
    "gn:name":"Obodowo",
    "gn:population":0,
    "gn:timezone":"Europe/Warsaw",
    "iso:country":"PL",
    "name:pol_x_preferred":[
        "Obodowo"
    ],
    "name:ukr_x_preferred":[
        "\u041e\u0431\u043e\u0434\u043e\u0432\u043e"
    ],
    "wof:name":"Obodowo",
    "wof:placetype":"locality"
},
  "geometry": {"coordinates":[17.70302000000001,53.42648000000001],"type":"Point"}
}