{
  "type": "Feature",
  "properties": {
    "gn:admin1_code":"77.0",
    "gn:asciiname":"Golenice",
    "gn:country_code":"PL",
    "gn:dem":71,
    "gn:feature_class":"P",
    "gn:feature_code":"PPL",
    "gn:name":"Golenice",
    "gn:population":0,
    "gn:timezone":"Europe/Warsaw",
    "iso:country":"PL",
    "name:ceb_x_preferred":[
        "Golenice"
    ],
    "name:pol_x_preferred":[
        "Golenice"
    ],
    "name:ukr_x_preferred":[
        "\u0490\u043e\u043b\u0435\u043d\u0456\u0446\u0435"
    ],
    "name:und_x_variant":[
        "Schildberg"
    ],
    "wof:name":"Golenice",
    "wof:placetype":"locality"
},
  "geometry": {"coordinates":[14.78931,52.94864000000001],"type":"Point"}
}