{
  "type": "Feature",
  "properties": {
    "gn:admin1_code":"77.0",
    "gn:asciiname":"Golenice",
    "gn:country_code":"PL",
    "gn:dem":71,
    "gn:feature_class":"P",
    "gn:feature_code":"PPL",
    "gn:name":"Golenice",
    "gn:population":0,
    "gn:timezone":"Europe/Warsaw",
    "iso:country":"PL",
    "name:und_x_variant":[
        "Schildberg"
    ],
    "wof:name":"Golenice",
    "wof:placetype":"locality"
},
  "geometry": {"coordinates":[14.78931,52.94864000000001],"type":"Point"}
}