{
  "type": "Feature",
  "properties": {
    "gn:admin1_code":"75.0",
    "gn:admin2_code":"620.0",
    "gn:admin3_code":"62002.0",
    "gn:asciiname":"Majdan Tuczepski",
    "gn:country_code":"PL",
    "gn:dem":243,
    "gn:feature_class":"P",
    "gn:feature_code":"PPL",
    "gn:name":"Majdan Tucz\u0119pski",
    "gn:population":0,
    "gn:timezone":"Europe/Warsaw",
    "iso:country":"PL",
    "name:und_x_variant":[
        "Majdan Tucz\u0119pski"
    ],
    "wof:name":"Majdan Tuczepski",
    "wof:placetype":"locality"
},
  "geometry": {"coordinates":[23.48894,50.87148],"type":"Point"}
}