{
  "type": "Feature",
  "properties": {
    "gn:admin1_code":"75.0",
    "gn:admin2_code":"620.0",
    "gn:admin3_code":"62002.0",
    "gn:asciiname":"Majdan Tuczepski",
    "gn:country_code":"PL",
    "gn:dem":243,
    "gn:feature_class":"P",
    "gn:feature_code":"PPL",
    "gn:name":"Majdan Tucz\u0119pski",
    "gn:population":0,
    "gn:timezone":"Europe/Warsaw",
    "iso:country":"PL",
    "name:fra_x_preferred":[
        "Majdan Tucz\u0119pski"
    ],
    "name:pol_x_preferred":[
        "Majdan Tucz\u0119pski"
    ],
    "name:ukr_x_preferred":[
        "\u041c\u0430\u0439\u0434\u0430\u043d-\u0422\u0443\u0447\u0435\u043c\u043f\u0441\u044c\u043a\u0438\u0439"
    ],
    "wof:name":"Majdan Tuczepski",
    "wof:placetype":"locality"
},
  "geometry": {"coordinates":[23.48894,50.87148],"type":"Point"}
}