{
  "type": "Feature",
  "properties": {
    "gn:admin1_code":"87.0",
    "gn:admin2_code":"3201.0",
    "gn:admin3_code":"320102.0",
    "gn:asciiname":"Nawino",
    "gn:country_code":"PL",
    "gn:dem":47,
    "gn:feature_class":"P",
    "gn:feature_code":"PPL",
    "gn:name":"Nawino",
    "gn:population":0,
    "gn:timezone":"Europe/Warsaw",
    "iso:country":"PL",
    "name:deu_x_preferred":[
        "Nawino"
    ],
    "name:pol_x_preferred":[
        "Nawino"
    ],
    "name:ukr_x_preferred":[
        "\u041d\u0430\u0432\u0456\u043d\u043e"
    ],
    "name:vie_x_preferred":[
        "Nawino"
    ],
    "wof:name":"Nawino",
    "wof:placetype":"locality"
},
  "geometry": {"coordinates":[15.98047,53.92106],"type":"Point"}
}