{
  "type": "Feature",
  "properties": {
    "gn:admin1_code":"82.0",
    "gn:asciiname":"Rzeczyca",
    "gn:country_code":"PL",
    "gn:dem":320,
    "gn:feature_class":"P",
    "gn:feature_code":"PPL",
    "gn:name":"Rzeczyca",
    "gn:population":0,
    "gn:timezone":"Europe/Warsaw",
    "iso:country":"PL",
    "name:bel_x_preferred":[
        "\u0420\u044d\u0447\u044b\u0446\u0430"
    ],
    "name:ceb_x_preferred":[
        "Rzeczyca"
    ],
    "name:deu_x_preferred":[
        "Rzeczyca"
    ],
    "name:fra_x_preferred":[
        "Rzeczyca"
    ],
    "name:nld_x_preferred":[
        "Rzeczyca"
    ],
    "name:pol_x_preferred":[
        "Rzeczyca"
    ],
    "name:ukr_x_preferred":[
        "\u0416\u0435\u0447\u0438\u0446\u044f"
    ],
    "wof:name":"Rzeczyca",
    "wof:placetype":"locality"
},
  "geometry": {"coordinates":[16.13332999999999,50.25],"type":"Point"}
}