{
  "type": "Feature",
  "properties": {
    "gn:admin1_code":"82.0",
    "gn:asciiname":"Rzeczyca",
    "gn:country_code":"PL",
    "gn:dem":320,
    "gn:feature_class":"P",
    "gn:feature_code":"PPL",
    "gn:name":"Rzeczyca",
    "gn:population":0,
    "gn:timezone":"Europe/Warsaw",
    "iso:country":"PL",
    "wof:name":"Rzeczyca",
    "wof:placetype":"locality"
},
  "geometry": {"coordinates":[16.13332999999999,50.25],"type":"Point"}
}