{
  "type": "Feature",
  "properties": {
    "gn:admin1_code":"78.0",
    "gn:admin2_code":"1421.0",
    "gn:admin3_code":"142103.0",
    "gn:asciiname":"Terenia",
    "gn:country_code":"PL",
    "gn:dem":123,
    "gn:feature_class":"P",
    "gn:feature_code":"PPL",
    "gn:name":"Terenia",
    "gn:population":0,
    "gn:timezone":"Europe/Warsaw",
    "iso:country":"PL",
    "wof:name":"Terenia",
    "wof:placetype":"locality"
},
  "geometry": {"coordinates":[20.73189,52.09048],"type":"Point"}
}