{
  "type": "Feature",
  "properties": {
    "gn:admin1_code":"78.0",
    "gn:admin2_code":"1402.0",
    "gn:admin3_code":"140203.0",
    "gn:asciiname":"Zeleznia",
    "gn:country_code":"PL",
    "gn:dem":108,
    "gn:feature_class":"P",
    "gn:feature_code":"PPL",
    "gn:name":"\u017bele\u017cnia",
    "gn:population":0,
    "gn:timezone":"Europe/Warsaw",
    "iso:country":"PL",
    "name:fra_x_preferred":[
        "\u017bele\u017ania"
    ],
    "name:pol_x_preferred":[
        "\u017bele\u017ania"
    ],
    "name:spa_x_preferred":[
        "\u017bele\u017ania"
    ],
    "name:ukr_x_preferred":[
        "\u0416\u0435\u043b\u0435\u0437\u043d\u044f"
    ],
    "name:und_x_variant":[
        "\u017bele\u017cnia"
    ],
    "wof:name":"Zeleznia",
    "wof:placetype":"locality"
},
  "geometry": {"coordinates":[20.31324,52.83773000000001],"type":"Point"}
}