{
  "type": "Feature",
  "properties": {
    "gn:admin1_code":"86.0",
    "gn:admin2_code":"3010.0",
    "gn:admin3_code":"301007.0",
    "gn:asciiname":"Zosinki",
    "gn:country_code":"PL",
    "gn:dem":104,
    "gn:feature_class":"P",
    "gn:feature_code":"PPL",
    "gn:name":"Zosinki",
    "gn:population":0,
    "gn:timezone":"Europe/Warsaw",
    "iso:country":"PL",
    "name:fra_x_preferred":[
        "Zosinki"
    ],
    "name:pol_x_preferred":[
        "Zosinki"
    ],
    "name:ukr_x_preferred":[
        "\u0417\u043e\u0441\u0456\u043d\u043a\u0456"
    ],
    "wof:name":"Zosinki",
    "wof:placetype":"locality"
},
  "geometry": {"coordinates":[18.14391,52.02857],"type":"Point"}
}