{
  "type": "Feature",
  "properties": {
    "gn:admin1_code":"80.0",
    "gn:admin2_code":"1817.0",
    "gn:admin3_code":"181707.0",
    "gn:asciiname":"Dolna",
    "gn:country_code":"PL",
    "gn:dem":392,
    "gn:feature_class":"P",
    "gn:feature_code":"PPL",
    "gn:name":"Dolna",
    "gn:population":0,
    "gn:timezone":"Europe/Warsaw",
    "iso:country":"PL",
    "wof:name":"Dolna",
    "wof:placetype":"locality"
},
  "geometry": {"coordinates":[22.26997,49.46902],"type":"Point"}
}