{
  "type": "Feature",
  "properties": {
    "gn:admin1_code":"78.0",
    "gn:admin2_code":"1423.0",
    "gn:admin3_code":"142302.0",
    "gn:asciiname":"Soltysy",
    "gn:country_code":"PL",
    "gn:dem":252,
    "gn:feature_class":"P",
    "gn:feature_code":"PPL",
    "gn:name":"So\u0142tysy",
    "gn:population":0,
    "gn:timezone":"Europe/Warsaw",
    "iso:country":"PL",
    "name:ceb_x_preferred":[
        "So\u0142tysy"
    ],
    "name:fra_x_preferred":[
        "So\u0142tysy"
    ],
    "name:pol_x_preferred":[
        "So\u0142tysy"
    ],
    "name:ukr_x_preferred":[
        "\u0421\u043e\u043b\u0442\u0438\u0441\u0438"
    ],
    "wof:name":"Soltysy",
    "wof:placetype":"locality"
},
  "geometry": {"coordinates":[20.44736,51.34466],"type":"Point"}
}