{
  "type": "Feature",
  "properties": {
    "gn:admin1_code":"86.0",
    "gn:admin2_code":"3023.0",
    "gn:admin3_code":"302307.0",
    "gn:asciiname":"Mlodziejewice",
    "gn:country_code":"PL",
    "gn:dem":95,
    "gn:feature_class":"P",
    "gn:feature_code":"PPL",
    "gn:name":"M\u0142odziejewice",
    "gn:population":0,
    "gn:timezone":"Europe/Warsaw",
    "iso:country":"PL",
    "name:fra_x_preferred":[
        "M\u0142odziejewice"
    ],
    "name:pol_x_preferred":[
        "M\u0142odziejewice"
    ],
    "name:ukr_x_preferred":[
        "\u041c\u043b\u043e\u0434\u0437\u0454\u0454\u0432\u0456\u0446\u0435"
    ],
    "name:und_x_variant":[
        "M\u0142odziejewice"
    ],
    "wof:name":"Mlodziejewice",
    "wof:placetype":"locality"
},
  "geometry": {"coordinates":[17.7125,52.28452],"type":"Point"}
}