{
  "type": "Feature",
  "properties": {
    "gn:admin1_code":"77.0",
    "gn:admin2_code":"1202.0",
    "gn:admin3_code":"120202.0",
    "gn:asciiname":"Zaletownia",
    "gn:country_code":"PL",
    "gn:dem":195,
    "gn:feature_class":"P",
    "gn:feature_code":"PPL",
    "gn:name":"Za\u0142etownia",
    "gn:population":0,
    "gn:timezone":"Europe/Warsaw",
    "iso:country":"PL",
    "wof:name":"Zaletownia",
    "wof:placetype":"locality"
},
  "geometry": {"coordinates":[20.60433,50.04506],"type":"Point"}
}