{
  "type": "Feature",
  "properties": {
    "gn:population":3933,
    "iso:country":"PL",
    "name:azb_x_preferred":[
        "\u0648\u0648\u06cc\u0686\u06cc\u0634\u0648\u0648"
    ],
    "name:ceb_x_preferred":[
        "Wojciesz\u00f3w"
    ],
    "name:deu_x_preferred":[
        "Wojciesz\u00f3w"
    ],
    "name:eng_x_preferred":[
        "Wojciesz\u00f3w"
    ],
    "name:epo_x_preferred":[
        "Wojciesz\u00f3w"
    ],
    "name:eus_x_preferred":[
        "Wojciesz\u00f3w"
    ],
    "name:fas_x_preferred":[
        "\u0648\u0648\u06cc\u0686\u06cc\u0634\u0648\u0648"
    ],
    "name:fra_x_preferred":[
        "Wojciesz\u00f3w"
    ],
    "name:ita_x_preferred":[
        "Wojciesz\u00f3w"
    ],
    "name:jav_x_preferred":[
        "Wojciesz\u00f3w"
    ],
    "name:lav_x_preferred":[
        "Vojce\u0161ova"
    ],
    "name:msa_x_preferred":[
        "Wojciesz\u00f3w"
    ],
    "name:nan_x_preferred":[
        "Wojciesz\u00f3w"
    ],
    "name:nld_x_preferred":[
        "Wojciesz\u00f3w"
    ],
    "name:pol_x_preferred":[
        "Wojciesz\u00f3w"
    ],
    "name:por_x_preferred":[
        "Wojciesz\u00f3w"
    ],
    "name:ron_x_preferred":[
        "Wojciesz\u00f3w"
    ],
    "name:rus_x_preferred":[
        "\u0412\u043e\u0439\u0446\u0435\u0448\u0443\u0432"
    ],
    "name:slk_x_preferred":[
        "Wojciesz\u00f3w"
    ],
    "name:srp_x_preferred":[
        "\u0412\u043e\u0458\u045b\u0435\u0448\u043e\u0432"
    ],
    "name:swe_x_preferred":[
        "Wojciesz\u00f3w"
    ],
    "name:tat_x_preferred":[
        "\u0412\u043e\u0439\u0447\u0435\u0448\u0443\u0432"
    ],
    "name:ukr_x_preferred":[
        "\u0412\u043e\u0439\u0446\u0435\u0448\u0443\u0432"
    ],
    "name:und_x_variant":[
        "Kauffung"
    ],
    "name:vie_x_preferred":[
        "Wojciesz\u00f3w"
    ],
    "name:war_x_preferred":[
        "Wojciesz\u00f3w"
    ],
    "name:zho_x_preferred":[
        "\u6c83\u4f0a\u5207\u8212\u592b"
    ],
    "qs:a0":"Rzeczpospolita Polska",
    "qs:a1":"*Dolnoslaskie",
    "qs:a1r":"0",
    "qs:a2":"Zlotoryjski",
    "qs:adm0":"Rzeczpospolita Polska",
    "qs:la":"Wojciesz\u00f3w",
    "qs:la_lc":"*PL0226011",
    "qs:level":"locality",
    "qs:loc":"Wojciesz\u00f3w",
    "qs:loc_alt":"Wojcieszow",
    "qs:pop":0,
    "qs:type":"rural point-in-poly",
    "wd:wordcount":85,
    "wof:name":"Wojciesz\u00f3w",
    "wof:placetype":"locality",
    "wof:population":3933
},
  "geometry": {"coordinates":[15.9229075062485,50.9528122947639],"type":"Point"}
}