{
  "type": "Feature",
  "properties": {
    "gn:admin1_code":"82.0",
    "gn:admin2_code":"2201.0",
    "gn:admin3_code":"220105.0",
    "gn:asciiname":"Wierzchocina",
    "gn:country_code":"PL",
    "gn:dem":155,
    "gn:feature_class":"P",
    "gn:feature_code":"PPL",
    "gn:name":"Wierzchocina",
    "gn:population":0,
    "gn:timezone":"Europe/Warsaw",
    "iso:country":"PL",
    "name:csb_x_preferred":[
        "Wierzch\u00f2c\u00ebna"
    ],
    "name:pol_x_preferred":[
        "Wierzchocina"
    ],
    "name:ukr_x_preferred":[
        "\u0412\u0435\u0436\u0445\u043e\u0446\u0438\u043d\u0430"
    ],
    "wof:name":"Wierzchocina",
    "wof:placetype":"locality"
},
  "geometry": {"coordinates":[17.25409,53.96038000000001],"type":"Point"}
}