{
  "type": "Feature",
  "properties": {
    "gn:admin1_code":"82.0",
    "gn:admin2_code":"2201.0",
    "gn:admin3_code":"220105.0",
    "gn:asciiname":"Wierzchocina",
    "gn:country_code":"PL",
    "gn:dem":155,
    "gn:feature_class":"P",
    "gn:feature_code":"PPL",
    "gn:name":"Wierzchocina",
    "gn:population":0,
    "gn:timezone":"Europe/Warsaw",
    "iso:country":"PL",
    "wof:name":"Wierzchocina",
    "wof:placetype":"locality"
},
  "geometry": {"coordinates":[17.25409,53.96038000000001],"type":"Point"}
}