{
  "type": "Feature",
  "properties": {
    "gn:admin1_code":"78.0",
    "gn:admin2_code":"1437.0",
    "gn:admin3_code":"143706.0",
    "gn:asciiname":"Kosewo",
    "gn:cc2":"PL",
    "gn:country_code":"PL",
    "gn:dem":129,
    "gn:feature_class":"P",
    "gn:feature_code":"PPL",
    "gn:name":"Kosewo",
    "gn:population":0,
    "gn:timezone":"Europe/Warsaw",
    "iso:country":"PL",
    "name:und_x_variant":[
        "Kossewo",
        "Kosewo"
    ],
    "wof:name":"Kosewo",
    "wof:placetype":"locality"
},
  "geometry": {"coordinates":[19.97915,53.05721],"type":"Point"}
}