{
  "type": "Feature",
  "properties": {
    "gn:admin1_code":"81.0",
    "gn:admin2_code":"2010.0",
    "gn:admin3_code":"201002.0",
    "gn:asciiname":"Tonkiele",
    "gn:country_code":"PL",
    "gn:dem":115,
    "gn:feature_class":"P",
    "gn:feature_code":"PPL",
    "gn:name":"Tonkiele",
    "gn:population":0,
    "gn:timezone":"Europe/Warsaw",
    "iso:country":"PL",
    "wof:name":"Tonkiele",
    "wof:placetype":"locality"
},
  "geometry": {"coordinates":[22.56454,52.41587],"type":"Point"}
}