{
  "type": "Feature",
  "properties": {
    "gn:admin1_code":"86.0",
    "gn:admin2_code":"3007.0",
    "gn:admin3_code":"300701.0",
    "gn:asciiname":"Kolonia Rychnow",
    "gn:country_code":"PL",
    "gn:dem":126,
    "gn:feature_class":"P",
    "gn:feature_code":"PPL",
    "gn:name":"Kolonia Rychn\u00f3w",
    "gn:population":0,
    "gn:timezone":"Europe/Warsaw",
    "iso:country":"PL",
    "wof:name":"Kolonia Rychnow",
    "wof:placetype":"locality"
},
  "geometry": {"coordinates":[18.06287,51.86959],"type":"Point"}
}