{
  "type": "Feature",
  "properties": {
    "gn:admin1_code":"76.0",
    "gn:admin2_code":"803.0",
    "gn:admin3_code":"80301.0",
    "gn:asciiname":"Templewo",
    "gn:country_code":"PL",
    "gn:dem":97,
    "gn:feature_class":"P",
    "gn:feature_code":"PPL",
    "gn:name":"Templewo",
    "gn:population":0,
    "gn:timezone":"Europe/Warsaw",
    "iso:country":"PL",
    "name:fra_x_preferred":[
        "Templewo"
    ],
    "name:pol_x_preferred":[
        "Templewo"
    ],
    "name:ukr_x_preferred":[
        "\u0422\u0435\u043c\u043f\u043b\u0435\u0432\u043e"
    ],
    "wof:name":"Templewo",
    "wof:placetype":"locality"
},
  "geometry": {"coordinates":[15.389,52.44375],"type":"Point"}
}