{
  "type": "Feature",
  "properties": {
    "gn:admin1_code":"84.0",
    "gn:admin2_code":"2606.0",
    "gn:admin3_code":"260608.0",
    "gn:asciiname":"Drygulec",
    "gn:country_code":"PL",
    "gn:dem":186,
    "gn:feature_class":"P",
    "gn:feature_code":"PPL",
    "gn:name":"Drygulec",
    "gn:population":0,
    "gn:timezone":"Europe/Warsaw",
    "iso:country":"PL",
    "name:ceb_x_preferred":[
        "Drygulec"
    ],
    "name:nld_x_preferred":[
        "Drygulec"
    ],
    "name:pol_x_preferred":[
        "Drygulec"
    ],
    "name:ukr_x_preferred":[
        "\u0414\u0440\u0438\u0491\u0443\u043b\u0435\u0446\u044c"
    ],
    "wof:name":"Drygulec",
    "wof:placetype":"locality"
},
  "geometry": {"coordinates":[21.57496,50.87229],"type":"Point"}
}