{
  "type": "Feature",
  "properties": {
    "gn:admin1_code":"78.0",
    "gn:admin2_code":"1411.0",
    "gn:admin3_code":"141104.0",
    "gn:asciiname":"Wola Pienicka",
    "gn:country_code":"PL",
    "gn:dem":105,
    "gn:feature_class":"P",
    "gn:feature_code":"PPL",
    "gn:name":"Wola Pienicka",
    "gn:population":0,
    "gn:timezone":"Europe/Warsaw",
    "iso:country":"PL",
    "wof:name":"Wola Pienicka",
    "wof:placetype":"locality"
},
  "geometry": {"coordinates":[21.18333,52.98333],"type":"Point"}
}