{
  "type": "Feature",
  "properties": {
    "gn:admin1_code":"78.0",
    "gn:admin2_code":"1415.0",
    "gn:admin3_code":"141511.0",
    "gn:asciiname":"Kurpie",
    "gn:country_code":"PL",
    "gn:dem":113,
    "gn:feature_class":"P",
    "gn:feature_code":"PPL",
    "gn:name":"Kurpie",
    "gn:population":0,
    "gn:timezone":"Europe/Warsaw",
    "iso:country":"PL",
    "name:deu_x_preferred":[
        "Kurpie"
    ],
    "name:lit_x_preferred":[
        "Kurpiai"
    ],
    "name:nds_x_preferred":[
        "Kurpen"
    ],
    "name:pol_x_preferred":[
        "Kurpie"
    ],
    "name:rus_x_preferred":[
        "\u041a\u0443\u0440\u043f\u044b"
    ],
    "wof:name":"Kurpie",
    "wof:placetype":"locality"
},
  "geometry": {"coordinates":[21.75435,53.05519],"type":"Point"}
}