{
  "type": "Feature",
  "properties": {
    "gn:admin1_code":"78.0",
    "gn:admin2_code":"1432.0",
    "gn:admin3_code":"143207.0",
    "gn:asciiname":"Koczargi Nowe",
    "gn:cc2":"PL",
    "gn:country_code":"PL",
    "gn:dem":92,
    "gn:feature_class":"P",
    "gn:feature_code":"PPL",
    "gn:name":"Koczargi Nowe",
    "gn:population":0,
    "gn:timezone":"Europe/Warsaw",
    "iso:country":"PL",
    "name:azb_x_preferred":[
        "\u06a9\u0648\u0686\u0627\u0631\u0642\u06cc \u0646\u0648\u0648\u0647"
    ],
    "name:ceb_x_preferred":[
        "Koczargi Nowe"
    ],
    "name:fas_x_preferred":[
        "\u06a9\u0648\u0686\u0627\u0631\u06af\u06cc \u0646\u0648\u0648\u0647"
    ],
    "name:fra_x_preferred":[
        "Koczargi Nowe"
    ],
    "name:pol_x_preferred":[
        "Koczargi Nowe"
    ],
    "name:ukr_x_preferred":[
        "\u041a\u043e\u0447\u0430\u0440\u0491\u0456-\u041d\u043e\u0432\u0456"
    ],
    "name:und_x_variant":[
        "Koczergi Nowe"
    ],
    "wof:name":"Koczargi Nowe",
    "wof:placetype":"locality"
},
  "geometry": {"coordinates":[20.7918,52.25565],"type":"Point"}
}