{
  "type": "Feature",
  "properties": {
    "gn:admin1_code":"78.0",
    "gn:admin2_code":"1437.0",
    "gn:admin3_code":"143701.0",
    "gn:asciiname":"Myslin Watrobki",
    "gn:cc2":"PL",
    "gn:country_code":"PL",
    "gn:dem":110,
    "gn:feature_class":"P",
    "gn:feature_code":"PPL",
    "gn:name":"My\u015blin Watr\u00f3bki",
    "gn:population":0,
    "gn:timezone":"Europe/Warsaw",
    "iso:country":"PL",
    "name:und_x_variant":[
        "My\u015blim Watrobki",
        "My\u015blin Watr\u00f3bki"
    ],
    "wof:name":"Myslin Watrobki",
    "wof:placetype":"locality"
},
  "geometry": {"coordinates":[19.91667,52.93333000000001],"type":"Point"}
}