{
  "type": "Feature",
  "properties": {
    "gn:admin1_code":"72.0",
    "gn:admin2_code":"217.0",
    "gn:admin3_code":"21704.0",
    "gn:asciiname":"Myszkowice",
    "gn:country_code":"PL",
    "gn:dem":269,
    "gn:feature_class":"P",
    "gn:feature_code":"PPL",
    "gn:name":"Myszkowice",
    "gn:population":0,
    "gn:timezone":"Europe/Warsaw",
    "iso:country":"PL",
    "name:pol_x_preferred":[
        "Myszkowice"
    ],
    "wof:name":"Myszkowice",
    "wof:placetype":"locality"
},
  "geometry": {"coordinates":[16.95933,50.69709],"type":"Point"}
}