{
  "type": "Feature",
  "properties": {
    "gn:gn_country":"PL",
    "gn:gn_fcode":"PPLA3",
    "gn:gn_pop":900,
    "gn:population":900,
    "iso:country":"PL",
    "name:azb_x_preferred":[
        "\u062f\u0631\u0644\u0648\u0648"
    ],
    "name:bel_x_preferred":[
        "\u0414\u0440\u044d\u043b\u0435\u045e"
    ],
    "name:fas_x_preferred":[
        "\u062f\u0631\u0644\u0648\u0648"
    ],
    "name:fra_x_preferred":[
        "Drel\u00f3w"
    ],
    "name:lit_x_preferred":[
        "Dreluvas"
    ],
    "name:nld_x_preferred":[
        "Drel\u00f3w"
    ],
    "name:pol_x_preferred":[
        "Drel\u00f3w"
    ],
    "name:ukr_x_preferred":[
        "\u0414\u0440\u0435\u043b\u044e\u0432"
    ],
    "qs_pg:aaroncc":"PL",
    "qs_pg:gn_country":"PL",
    "qs_pg:gn_fcode":"PPLA3",
    "qs_pg:gn_pop":900,
    "qs_pg:name":"Drel\u00f3w",
    "qs_pg:name_adm0":"Polska",
    "qs_pg:name_adm1":"Lubelskie",
    "qs_pg:photos_9k":1,
    "qs_pg:photos_9r":1,
    "qs_pg:photos_all":5,
    "qs_pg:photos_sr":0,
    "qs_pg:pop_sr":2,
    "qs_pg:qs_pg_placetype":"localadmin",
    "qs_pg:qs_pg_placetype_gp":"LocalAdmin",
    "qs_pg:woe_adm0":23424923,
    "woe:adm0_id":23424923,
    "woe:name_adm0":"Polska",
    "woe:name_adm1":"Lubelskie",
    "woe:placetype":"LocalAdmin",
    "wof:name":"Drel\u00f3w",
    "wof:placetype":"localadmin",
    "wof:population":900
},
  "geometry": {"coordinates":[22.87165,51.91219],"type":"Point"}
}