{
  "type": "Feature",
  "properties": {
    "iso:country":"PL",
    "name:pol_x_preferred":[
        "D\u0119bniki"
    ],
    "wof:name":"Debniki",
    "wof:placetype":"neighbourhood"
},
  "geometry": {"coordinates":[19.92623488860215,50.05004954652156],"type":"Point"}
}