{
  "type": "Feature",
  "properties": {
    "gn:admin1_code":"72.0",
    "gn:admin2_code":"224.0",
    "gn:admin3_code":"22407.0",
    "gn:asciiname":"Blotnica",
    "gn:country_code":"PL",
    "gn:dem":237,
    "gn:feature_class":"P",
    "gn:feature_code":"PPL",
    "gn:name":"B\u0142otnica",
    "gn:population":0,
    "gn:timezone":"Europe/Warsaw",
    "iso:country":"PL",
    "wof:name":"Blotnica",
    "wof:placetype":"locality"
},
  "geometry": {"coordinates":[16.93439,50.47368],"type":"Point"}
}