{
  "type": "Feature",
  "properties": {
    "gn:admin1_code":"76.0",
    "gn:admin2_code":"811.0",
    "gn:admin3_code":"81104.0",
    "gn:asciiname":"Jabloniec",
    "gn:country_code":"PL",
    "gn:dem":121,
    "gn:feature_class":"P",
    "gn:feature_code":"PPL",
    "gn:name":"Jab\u0142oniec",
    "gn:population":0,
    "gn:timezone":"Europe/Warsaw",
    "iso:country":"PL",
    "name:ceb_x_preferred":[
        "Jab\u0142oniec"
    ],
    "name:deu_x_preferred":[
        "Jab\u0142oniec"
    ],
    "name:fra_x_preferred":[
        "Jab\u0142oniec"
    ],
    "name:pol_x_preferred":[
        "Jab\u0142oniec"
    ],
    "name:ukr_x_preferred":[
        "\u042f\u0431\u043b\u043e\u043d\u0435\u0446\u044c"
    ],
    "name:urd_x_preferred":[
        "\u062c\u0628\u0648\u0648\u0646\u06cc\u06a9"
    ],
    "wof:name":"Jabloniec",
    "wof:placetype":"locality"
},
  "geometry": {"coordinates":[15.01833,51.72339],"type":"Point"}
}