{
  "type": "Feature",
  "properties": {
    "gn:admin1_code":"76.0",
    "gn:admin2_code":"811.0",
    "gn:admin3_code":"81104.0",
    "gn:asciiname":"Jabloniec",
    "gn:country_code":"PL",
    "gn:dem":121,
    "gn:feature_class":"P",
    "gn:feature_code":"PPL",
    "gn:name":"Jab\u0142oniec",
    "gn:population":0,
    "gn:timezone":"Europe/Warsaw",
    "iso:country":"PL",
    "name:und_x_variant":[
        "Jab\u0142oniec"
    ],
    "wof:name":"Jabloniec",
    "wof:placetype":"locality"
},
  "geometry": {"coordinates":[15.01833,51.72339],"type":"Point"}
}