{
  "type": "Feature",
  "properties": {
    "gn:admin1_code":"72.0",
    "gn:admin2_code":"217.0",
    "gn:admin3_code":"21704.0",
    "gn:asciiname":"Czeszyce",
    "gn:country_code":"PL",
    "gn:dem":157,
    "gn:feature_class":"P",
    "gn:feature_code":"PPL",
    "gn:name":"Cz\u0119szyce",
    "gn:population":0,
    "gn:timezone":"Europe/Warsaw",
    "iso:country":"PL",
    "name:pol_x_preferred":[
        "Cz\u0119szyce"
    ],
    "name:ukr_x_preferred":[
        "\u0427\u0435\u043d\u0448\u0438\u0446\u0435"
    ],
    "name:und_x_variant":[
        "Cz\u0119szyce"
    ],
    "wof:name":"Czeszyce",
    "wof:placetype":"locality"
},
  "geometry": {"coordinates":[17.13429,50.79953],"type":"Point"}
}