{
  "type": "Feature",
  "properties": {
    "gn:admin1_code":"73.0",
    "gn:admin2_code":"410.0",
    "gn:admin3_code":"41005.0",
    "gn:asciiname":"Zielonowo",
    "gn:country_code":"PL",
    "gn:dem":96,
    "gn:feature_class":"P",
    "gn:feature_code":"PPL",
    "gn:name":"Zielonowo",
    "gn:population":0,
    "gn:timezone":"Europe/Warsaw",
    "iso:country":"PL",
    "name:pol_x_preferred":[
        "Zielonowo"
    ],
    "name:ukr_x_preferred":[
        "\u0417\u0435\u043b\u044c\u043e\u043d\u043e\u0432\u043e"
    ],
    "wof:name":"Zielonowo",
    "wof:placetype":"locality"
},
  "geometry": {"coordinates":[17.79397999999999,52.96295],"type":"Point"}
}