{
  "type": "Feature",
  "properties": {
    "gn:admin1_code":"87.0",
    "gn:admin2_code":"3206.0",
    "gn:admin3_code":"320604.0",
    "gn:asciiname":"Weltyn",
    "gn:country_code":"PL",
    "gn:dem":28,
    "gn:feature_class":"P",
    "gn:feature_code":"PPL",
    "gn:name":"We\u0142ty\u0144",
    "gn:population":0,
    "gn:timezone":"Europe/Warsaw",
    "iso:country":"PL",
    "name:und_x_variant":[
        "We\u0142ty\u0144"
    ],
    "wof:name":"Weltyn",
    "wof:placetype":"locality"
},
  "geometry": {"coordinates":[14.57751,53.25941],"type":"Point"}
}