{
  "type": "Feature",
  "properties": {
    "gn:admin1_code":"81.0",
    "gn:admin2_code":"2013.0",
    "gn:admin3_code":"201308.0",
    "gn:asciiname":"Jenki",
    "gn:country_code":"PL",
    "gn:dem":122,
    "gn:feature_class":"P",
    "gn:feature_code":"PPL",
    "gn:name":"Je\u0144ki",
    "gn:population":0,
    "gn:timezone":"Europe/Warsaw",
    "iso:country":"PL",
    "name:azb_x_preferred":[
        "\u06cc\u0646\u0642\u06a9\u06cc"
    ],
    "name:eng_x_preferred":[
        "Je\u0144ki"
    ],
    "name:fas_x_preferred":[
        "\u06cc\u0646\u06af\u06a9\u06cc"
    ],
    "name:lit_x_preferred":[
        "Jenkai"
    ],
    "name:pol_x_preferred":[
        "Je\u0144ki"
    ],
    "name:rus_x_preferred":[
        "\u0415\u043d\u044c\u043a\u0438"
    ],
    "name:ukr_x_preferred":[
        "\u0404\u043d\u044c\u043a\u0456"
    ],
    "wof:name":"Jenki",
    "wof:placetype":"locality"
},
  "geometry": {"coordinates":[22.82471,53.05201],"type":"Point"}
}