{
  "type": "Feature",
  "properties": {
    "gn:admin1_code":"72.0",
    "gn:admin2_code":"226.0",
    "gn:admin3_code":"22604.0",
    "gn:asciiname":"Podgorki",
    "gn:country_code":"PL",
    "gn:dem":442,
    "gn:feature_class":"P",
    "gn:feature_code":"PPL",
    "gn:name":"Podg\u00f3rki",
    "gn:population":0,
    "gn:timezone":"Europe/Warsaw",
    "iso:country":"PL",
    "name:azb_x_preferred":[
        "\u067e\u0648\u062f\u0642\u0648\u0631\u06a9\u06cc"
    ],
    "name:ces_x_preferred":[
        "Podg\u00f3rki"
    ],
    "name:deu_x_preferred":[
        "Podg\u00f3rki"
    ],
    "name:fas_x_preferred":[
        "\u067e\u0648\u062f\u06af\u0648\u0631\u06a9\u06cc"
    ],
    "name:pol_x_preferred":[
        "Podg\u00f3rki"
    ],
    "name:ukr_x_preferred":[
        "\u041f\u043e\u0434\u0491\u0443\u0440\u043a\u0456"
    ],
    "wof:name":"Podgorki",
    "wof:placetype":"locality"
},
  "geometry": {"coordinates":[15.85379,50.95697],"type":"Point"}
}