{
  "type": "Feature",
  "properties": {
    "gn:admin1_code":"72.0",
    "gn:admin2_code":"226.0",
    "gn:admin3_code":"22604.0",
    "gn:asciiname":"Podgorki",
    "gn:country_code":"PL",
    "gn:dem":442,
    "gn:feature_class":"P",
    "gn:feature_code":"PPL",
    "gn:name":"Podg\u00f3rki",
    "gn:population":0,
    "gn:timezone":"Europe/Warsaw",
    "iso:country":"PL",
    "wof:name":"Podgorki",
    "wof:placetype":"locality"
},
  "geometry": {"coordinates":[15.85379,50.95697],"type":"Point"}
}