{
  "type": "Feature",
  "properties": {
    "gn:admin1_code":"74.0",
    "gn:admin2_code":"1018.0",
    "gn:admin3_code":"101802.0",
    "gn:asciiname":"Przywory",
    "gn:country_code":"PL",
    "gn:dem":170,
    "gn:feature_class":"P",
    "gn:feature_code":"PPL",
    "gn:name":"Przywory",
    "gn:population":0,
    "gn:timezone":"Europe/Warsaw",
    "iso:country":"PL",
    "name:pol_x_preferred":[
        "Przywory"
    ],
    "name:ukr_x_preferred":[
        "\u041f\u0448\u0438\u0432\u043e\u0440\u0438"
    ],
    "wof:name":"Przywory",
    "wof:placetype":"locality"
},
  "geometry": {"coordinates":[18.24834,51.2705],"type":"Point"}
}