{
  "type": "Feature",
  "properties": {
    "gn:admin1_code":"76.0",
    "gn:admin2_code":"809.0",
    "gn:admin3_code":"80905.0",
    "gn:asciiname":"Dobroszow Maly",
    "gn:country_code":"PL",
    "gn:dem":83,
    "gn:feature_class":"P",
    "gn:feature_code":"PPL",
    "gn:name":"Dobrosz\u00f3w Ma\u0142y",
    "gn:population":0,
    "gn:timezone":"Europe/Warsaw",
    "iso:country":"PL",
    "name:ceb_x_preferred":[
        "Dobrosz\u00f3w Ma\u0142y"
    ],
    "name:fra_x_preferred":[
        "Dobrosz\u00f3w Ma\u0142y"
    ],
    "name:pol_x_preferred":[
        "Dobrosz\u00f3w Ma\u0142y"
    ],
    "name:ukr_x_preferred":[
        "\u0414\u043e\u0431\u0440\u043e\u0448\u0443\u0432-\u041c\u0430\u043b\u0438"
    ],
    "name:und_x_variant":[
        "Dobrosz\u00f3w Ma\u0142y"
    ],
    "wof:name":"Dobroszow Maly",
    "wof:placetype":"locality"
},
  "geometry": {"coordinates":[15.24279,51.76074000000001],"type":"Point"}
}