{
  "type": "Feature",
  "properties": {
    "gn:admin1_code":"84.0",
    "gn:admin2_code":"2613.0",
    "gn:admin3_code":"261304.0",
    "gn:asciiname":"Jakubowka",
    "gn:country_code":"PL",
    "gn:dem":242,
    "gn:feature_class":"P",
    "gn:feature_code":"PPL",
    "gn:name":"Jakub\u00f3wka",
    "gn:population":0,
    "gn:timezone":"Europe/Warsaw",
    "iso:country":"PL",
    "wof:name":"Jakubowka",
    "wof:placetype":"locality"
},
  "geometry": {"coordinates":[19.976,50.71816],"type":"Point"}
}