{
  "type": "Feature",
  "properties": {
    "gn:admin1_code":"82.0",
    "gn:admin2_code":"2212.0",
    "gn:admin3_code":"221204.0",
    "gn:asciiname":"Czarny Mlyn",
    "gn:country_code":"PL",
    "gn:dem":9,
    "gn:feature_class":"P",
    "gn:feature_code":"PPL",
    "gn:name":"Czarny M\u0142yn",
    "gn:population":0,
    "gn:timezone":"Europe/Warsaw",
    "iso:country":"PL",
    "wof:name":"Czarny Mlyn",
    "wof:placetype":"locality"
},
  "geometry": {"coordinates":[17.19034,54.59922],"type":"Point"}
}