{
  "type": "Feature",
  "properties": {
    "gn:admin1_code":"86.0",
    "gn:admin2_code":"3064.0",
    "gn:admin3_code":"306401.0",
    "gn:asciiname":"Psarskie",
    "gn:country_code":"PL",
    "gn:dem":77,
    "gn:feature_class":"P",
    "gn:feature_code":"PPL",
    "gn:name":"Psarskie",
    "gn:population":0,
    "gn:timezone":"Europe/Warsaw",
    "iso:country":"PL",
    "name:eng_x_preferred":[
        "Psarskie"
    ],
    "name:fra_x_preferred":[
        "Psarskie"
    ],
    "name:pol_x_preferred":[
        "Psarskie"
    ],
    "name:ukr_x_preferred":[
        "\u041f\u0441\u0430\u0440\u0441\u044c\u043a\u0435"
    ],
    "wof:name":"Psarskie",
    "wof:placetype":"neighbourhood"
},
  "geometry": {"coordinates":[16.804625,52.474746],"type":"Point"}
}