{
  "type": "Feature",
  "properties": {
    "iso:country":"PL",
    "name:eng_x_preferred":[
        "Psarskie"
    ],
    "name:fra_x_preferred":[
        "Psarskie"
    ],
    "name:pol_x_preferred":[
        "Psarskie"
    ],
    "name:ukr_x_preferred":[
        "\u041f\u0441\u0430\u0440\u0441\u044c\u043a\u0435"
    ],
    "wof:name":"Psarskie",
    "wof:placetype":"neighbourhood"
},
  "geometry": {"coordinates":[16.80462491450912,52.47474642595478],"type":"Point"}
}