{
  "type": "Feature",
  "properties": {
    "gn:admin1_code":"84.0",
    "gn:asciiname":"Solcza",
    "gn:country_code":"PL",
    "gn:dem":246,
    "gn:feature_class":"P",
    "gn:feature_code":"PPL",
    "gn:name":"Solcza",
    "gn:population":0,
    "gn:timezone":"Europe/Warsaw",
    "iso:country":"PL",
    "name:pol_x_preferred":[
        "Solcza"
    ],
    "name:ukr_x_preferred":[
        "\u0421\u043e\u043b\u044c\u0447\u0430"
    ],
    "wof:name":"Solcza",
    "wof:placetype":"locality"
},
  "geometry": {"coordinates":[20.30972,50.31853],"type":"Point"}
}