{
  "type": "Feature",
  "properties": {
    "gn:gn_country":"PL",
    "gn:gn_fcode":"PPL",
    "gn:gn_pop":450,
    "gn:population":450,
    "iso:country":"PL",
    "name:ces_x_preferred":[
        "Warcino"
    ],
    "name:csb_x_preferred":[
        "Warc\u00ebno"
    ],
    "name:deu_x_preferred":[
        "Warcino"
    ],
    "name:eng_x_preferred":[
        "Warcino"
    ],
    "name:fas_x_preferred":[
        "\u0648\u0627\u0631\u0686\u06cc\u0646\u0648"
    ],
    "name:fra_x_preferred":[
        "Warcino"
    ],
    "name:jpn_x_preferred":[
        "\u30d0\u30eb\u30c1\u30ce"
    ],
    "name:nld_x_preferred":[
        "Warcino"
    ],
    "name:pol_x_preferred":[
        "Warcino"
    ],
    "name:rus_x_preferred":[
        "\u0412\u0430\u0440\u0446\u0438\u043d\u043e"
    ],
    "name:unk_x_variant":[
        "Wrocino"
    ],
    "qs_pg:aaroncc":"PL",
    "qs_pg:gn_country":"PL",
    "qs_pg:gn_fcode":"PPL",
    "qs_pg:gn_pop":450,
    "qs_pg:name":"Warcino",
    "qs_pg:name_adm0":"Polska",
    "qs_pg:name_adm1":"Pomorskie",
    "qs_pg:photos_9r":0,
    "qs_pg:photos_sr":0,
    "qs_pg:pop_sr":2,
    "qs_pg:qs_pg_placetype":"locality",
    "qs_pg:qs_pg_placetype_gp":"Town",
    "qs_pg:woe_adm0":23424923,
    "woe:adm0_id":23424923,
    "woe:name_adm0":"Polska",
    "woe:name_adm1":"Pomorskie",
    "woe:placetype":"Town",
    "wof:name":"Warcino",
    "wof:placetype":"locality",
    "wof:population":450
},
  "geometry": {"coordinates":[16.85715,54.22239],"type":"Point"}
}