{
  "type": "Feature",
  "properties": {
    "gn:admin1_code":"73.0",
    "gn:admin2_code":"402.0",
    "gn:admin3_code":"40209.0",
    "gn:asciiname":"Chlebowo",
    "gn:country_code":"PL",
    "gn:dem":133,
    "gn:feature_class":"P",
    "gn:feature_code":"PPL",
    "gn:name":"Chlebowo",
    "gn:population":0,
    "gn:timezone":"Europe/Warsaw",
    "iso:country":"PL",
    "name:ceb_x_preferred":[
        "Chlebowo"
    ],
    "name:deu_x_preferred":[
        "Chlebowo"
    ],
    "name:fra_x_preferred":[
        "Chlebowo"
    ],
    "name:pol_x_preferred":[
        "Chlebowo"
    ],
    "name:swe_x_preferred":[
        "Chlebowo"
    ],
    "name:ukr_x_preferred":[
        "\u0425\u043b\u0435\u0431\u043e\u0432\u043e"
    ],
    "name:und_x_variant":[
        "Kolonia Chlebowo",
        "Chlebowo"
    ],
    "wof:name":"Chlebowo",
    "wof:placetype":"locality"
},
  "geometry": {"coordinates":[19.50702,53.15096],"type":"Point"}
}