{
  "type": "Feature",
  "properties": {
    "gn:admin1_code":"78.0",
    "gn:admin2_code":"1425.0",
    "gn:admin3_code":"142510.0",
    "gn:asciiname":"Dzierzkowek",
    "gn:country_code":"PL",
    "gn:dem":169,
    "gn:feature_class":"P",
    "gn:feature_code":"PPL",
    "gn:name":"Dzierzk\u00f3wek",
    "gn:population":0,
    "gn:timezone":"Europe/Warsaw",
    "iso:country":"PL",
    "name:und_x_variant":[
        "Stary Dzierzk\u00f3wek",
        "Dzierzk\u00f3wek Stary",
        "Dzierzk\u00f3wek"
    ],
    "wof:name":"Dzierzkowek",
    "wof:placetype":"locality"
},
  "geometry": {"coordinates":[21.29429,51.25696],"type":"Point"}
}