{
  "type": "Feature",
  "properties": {
    "gn:admin1_code":"78.0",
    "gn:admin2_code":"1425.0",
    "gn:admin3_code":"142510.0",
    "gn:asciiname":"Dzierzkowek",
    "gn:country_code":"PL",
    "gn:dem":169,
    "gn:feature_class":"P",
    "gn:feature_code":"PPL",
    "gn:name":"Dzierzk\u00f3wek",
    "gn:population":0,
    "gn:timezone":"Europe/Warsaw",
    "iso:country":"PL",
    "name:azb_x_preferred":[
        "\u0633\u062a\u0627\u0631\u06cc \u062c\u0698\u06a9\u0648\u0648\u06a9"
    ],
    "name:fas_x_preferred":[
        "\u0633\u062a\u0627\u0631\u06cc \u062c\u0698\u06a9\u0648\u0648\u06a9"
    ],
    "name:fra_x_preferred":[
        "Stary Dzierzk\u00f3wek"
    ],
    "name:pol_x_preferred":[
        "Dzierzk\u00f3wek Stary"
    ],
    "name:ukr_x_preferred":[
        "\u0414\u0437\u0435\u0436\u043a\u0443\u0432\u0435\u043a-\u0421\u0442\u0430\u0440\u0438\u0439"
    ],
    "name:und_x_variant":[
        "Dzierzk\u00f3wek"
    ],
    "wof:name":"Dzierzkowek",
    "wof:placetype":"locality"
},
  "geometry": {"coordinates":[21.29429,51.25696],"type":"Point"}
}