{
  "type": "Feature",
  "properties": {
    "gn:admin1_code":"86.0",
    "gn:admin2_code":"3023.0",
    "gn:admin3_code":"302302.0",
    "gn:asciiname":"Piotrowo",
    "gn:country_code":"PL",
    "gn:dem":90,
    "gn:feature_class":"P",
    "gn:feature_code":"PPL",
    "gn:name":"Piotrowo",
    "gn:population":0,
    "gn:timezone":"Europe/Warsaw",
    "iso:country":"PL",
    "name:deu_x_preferred":[
        "Piotrowo"
    ],
    "name:fra_x_preferred":[
        "Piotrowo"
    ],
    "name:pol_x_preferred":[
        "Piotrowo"
    ],
    "name:ukr_x_preferred":[
        "\u041f\u0439\u043e\u0442\u0440\u043e\u0432\u043e"
    ],
    "wof:name":"Piotrowo",
    "wof:placetype":"locality"
},
  "geometry": {"coordinates":[17.98447999999999,52.23012],"type":"Point"}
}