{
  "type": "Feature",
  "properties": {
    "gn:admin1_code":"78",
    "gn:admin2_code":"1418",
    "gn:admin3_code":"141803.0",
    "gn:asciiname":"Stara Iwiczna",
    "gn:country_code":"PL",
    "gn:dem":110,
    "gn:feature_class":"P",
    "gn:feature_code":"PPL",
    "gn:name":"Stara Iwiczna",
    "gn:population":0,
    "gn:timezone":"Europe/Warsaw",
    "iso:country":"PL",
    "name:ceb_x_preferred":[
        "Iwiczna"
    ],
    "name:fra_x_preferred":[
        "Stara Iwiczna"
    ],
    "name:pol_x_preferred":[
        "Iwiczna Stara"
    ],
    "name:pol_x_variant":[
        "Stara Iwiczna"
    ],
    "name:tgl_x_preferred":[
        "Stara Iwiczna"
    ],
    "name:ukr_x_preferred":[
        "\u0421\u0442\u0430\u0440\u0430 \u0406\u0432\u0456\u0447\u043d\u0430"
    ],
    "wof:name":"Stara Iwiczna",
    "wof:placetype":"locality"
},
  "geometry": {"coordinates":[20.98389,52.08267],"type":"Point"}
}