{
  "type": "Feature",
  "properties": {
    "gn:admin1_code":"75.0",
    "gn:admin2_code":"608.0",
    "gn:admin3_code":"60803.0",
    "gn:asciiname":"Antonin Stary",
    "gn:country_code":"PL",
    "gn:dem":144,
    "gn:feature_class":"P",
    "gn:feature_code":"PPL",
    "gn:name":"Antonin Stary",
    "gn:population":0,
    "gn:timezone":"Europe/Warsaw",
    "iso:country":"PL",
    "wof:name":"Antonin Stary",
    "wof:placetype":"locality"
},
  "geometry": {"coordinates":[22.45,51.58333],"type":"Point"}
}