{
  "type": "Feature",
  "properties": {
    "gn:admin1_code":"86.0",
    "gn:admin2_code":"3023.0",
    "gn:admin3_code":"302307.0",
    "gn:asciiname":"Kornaty",
    "gn:country_code":"PL",
    "gn:dem":102,
    "gn:feature_class":"P",
    "gn:feature_code":"PPL",
    "gn:name":"Kornaty",
    "gn:population":0,
    "gn:timezone":"Europe/Warsaw",
    "iso:country":"PL",
    "name:fra_x_preferred":[
        "Kornaty"
    ],
    "name:pol_x_preferred":[
        "Kornaty"
    ],
    "name:ukr_x_preferred":[
        "\u041a\u043e\u0440\u043d\u0430\u0442\u0438"
    ],
    "wof:name":"Kornaty",
    "wof:placetype":"locality"
},
  "geometry": {"coordinates":[17.83527,52.33786],"type":"Point"}
}