{
  "type": "Feature",
  "properties": {
    "gn:admin1_code":"74.0",
    "gn:admin2_code":"1020.0",
    "gn:admin3_code":"102009.0",
    "gn:asciiname":"Warszyce",
    "gn:country_code":"PL",
    "gn:dem":131,
    "gn:feature_class":"P",
    "gn:feature_code":"PPL",
    "gn:name":"Warszyce",
    "gn:population":0,
    "gn:timezone":"Europe/Warsaw",
    "iso:country":"PL",
    "name:pol_x_preferred":[
        "Warszyce"
    ],
    "name:ukr_x_preferred":[
        "\u0412\u0430\u0440\u0448\u0438\u0446\u0435"
    ],
    "wof:name":"Warszyce",
    "wof:placetype":"locality"
},
  "geometry": {"coordinates":[19.45461,51.95523],"type":"Point"}
}