{
  "type": "Feature",
  "properties": {
    "gn:country":"PL",
    "gn:fcode":"PPLA3",
    "gn:population":990,
    "iso:country":"PL",
    "name:azb_x_preferred":[
        "\u067e\u0698\u062a\u06a9"
    ],
    "name:ceb_x_preferred":[
        "Przytyk"
    ],
    "name:deu_x_preferred":[
        "Przytyk"
    ],
    "name:fas_x_preferred":[
        "\u067e\u0698\u062a\u06a9"
    ],
    "name:fra_x_preferred":[
        "Przytyk"
    ],
    "name:heb_x_preferred":[
        "\u05e4\u05e9\u05d9\u05d8\u05d9\u05e7"
    ],
    "name:nld_x_preferred":[
        "Przytyk"
    ],
    "name:pol_x_preferred":[
        "Przytyk"
    ],
    "name:ukr_x_preferred":[
        "\u041f\u0448\u0438\u0442\u0438\u043a"
    ],
    "name:vie_x_preferred":[
        "Przytyk"
    ],
    "qs_pg:aaroncc":"PL",
    "qs_pg:gn_country":"PL",
    "qs_pg:gn_fcode":"PPLA3",
    "qs_pg:gn_pop":990,
    "qs_pg:name":"Przytyk",
    "qs_pg:name_adm0":"Polska",
    "qs_pg:name_adm1":"Mazowieckie",
    "qs_pg:photos_9k":1,
    "qs_pg:photos_9r":1,
    "qs_pg:photos_all":3,
    "qs_pg:photos_sr":0,
    "qs_pg:pop_sr":2,
    "qs_pg:qs_pg_placetype":"localadmin",
    "qs_pg:qs_pg_placetype_gp":"LocalAdmin",
    "qs_pg:woe_adm0":23424923,
    "woe:adm0_id":23424923,
    "woe:name_adm0":"Polska",
    "woe:name_adm1":"Mazowieckie",
    "woe:placetype":"LocalAdmin",
    "wof:name":"Przytyk",
    "wof:placetype":"localadmin",
    "wof:population":990
},
  "geometry": {"coordinates":[20.90587,51.46567],"type":"Point"}
}