{
  "type": "Feature",
  "properties": {
    "gn:admin1_code":"75.0",
    "gn:admin2_code":"617.0",
    "gn:admin3_code":"61703.0",
    "gn:asciiname":"Borkowszczyzna",
    "gn:country_code":"PL",
    "gn:dem":241,
    "gn:feature_class":"P",
    "gn:feature_code":"PPL",
    "gn:name":"Borkowszczyzna",
    "gn:population":0,
    "gn:timezone":"Europe/Warsaw",
    "iso:country":"PL",
    "name:fra_x_preferred":[
        "Borkowszczyzna"
    ],
    "name:pol_x_preferred":[
        "Borkowszczyzna"
    ],
    "name:und_x_variant":[
        "Kozice Du\u017ce"
    ],
    "wof:name":"Borkowszczyzna",
    "wof:placetype":"locality"
},
  "geometry": {"coordinates":[22.76188,51.0902],"type":"Point"}
}