{
  "type": "Feature",
  "properties": {
    "gn:admin1_code":"74.0",
    "gn:admin2_code":"1004.0",
    "gn:admin3_code":"100407.0",
    "gn:asciiname":"Kaznow",
    "gn:country_code":"PL",
    "gn:dem":97,
    "gn:feature_class":"P",
    "gn:feature_code":"PPL",
    "gn:name":"Kazn\u00f3w",
    "gn:population":0,
    "gn:timezone":"Europe/Warsaw",
    "iso:country":"PL",
    "name:fra_x_preferred":[
        "Kazn\u00f3w"
    ],
    "name:pol_x_preferred":[
        "Kazn\u00f3w"
    ],
    "name:ukr_x_preferred":[
        "\u041a\u0430\u0437\u043d\u0443\u0432"
    ],
    "wof:name":"Kaznow",
    "wof:placetype":"locality"
},
  "geometry": {"coordinates":[18.89786,52.07729000000001],"type":"Point"}
}