{
  "type": "Feature",
  "properties": {
    "gn:admin1_code":"82.0",
    "gn:admin2_code":"2201.0",
    "gn:admin3_code":"220109.0",
    "gn:asciiname":"Poborowo",
    "gn:country_code":"PL",
    "gn:dem":99,
    "gn:feature_class":"P",
    "gn:feature_code":"PPL",
    "gn:name":"Poborowo",
    "gn:population":0,
    "gn:timezone":"Europe/Warsaw",
    "iso:country":"PL",
    "wof:name":"Poborowo",
    "wof:placetype":"locality"
},
  "geometry": {"coordinates":[17.16515,54.21151],"type":"Point"}
}