{
  "type": "Feature",
  "properties": {
    "gn:admin1_code":"82.0",
    "gn:admin2_code":"2201.0",
    "gn:admin3_code":"220109.0",
    "gn:asciiname":"Poborowo",
    "gn:country_code":"PL",
    "gn:dem":99,
    "gn:feature_class":"P",
    "gn:feature_code":"PPL",
    "gn:name":"Poborowo",
    "gn:population":0,
    "gn:timezone":"Europe/Warsaw",
    "iso:country":"PL",
    "name:ceb_x_preferred":[
        "Poborowo"
    ],
    "name:csb_x_preferred":[
        "P\u00f2b\u00f2row\u00f2"
    ],
    "name:deu_x_preferred":[
        "Poborowo"
    ],
    "name:pol_x_preferred":[
        "Poborowo"
    ],
    "name:ukr_x_preferred":[
        "\u041f\u043e\u0431\u043e\u0440\u043e\u0432\u043e"
    ],
    "wof:name":"Poborowo",
    "wof:placetype":"locality"
},
  "geometry": {"coordinates":[17.16515,54.21151],"type":"Point"}
}