{
  "type": "Feature",
  "properties": {
    "gn:country":"PL",
    "gn:fcode":"PPL",
    "gn:population":628,
    "iso:country":"PL",
    "name:ast_x_preferred":[
        "Wielgie"
    ],
    "name:ceb_x_preferred":[
        "Wielgie"
    ],
    "name:eng_x_preferred":[
        "Wielgie"
    ],
    "name:fra_x_preferred":[
        "Wielgie"
    ],
    "name:pol_x_preferred":[
        "Wielgie"
    ],
    "name:rus_x_preferred":[
        "\u0412\u0435\u043b\u044c\u0433\u0435"
    ],
    "name:ukr_x_preferred":[
        "\u0412\u0435\u043b\u044c\u0491\u0435"
    ],
    "qs_pg:aaroncc":"PL",
    "qs_pg:gn_country":"PL",
    "qs_pg:gn_fcode":"PPL",
    "qs_pg:gn_pop":628,
    "qs_pg:name":"Wielgie",
    "qs_pg:name_adm0":"Polska",
    "qs_pg:name_adm1":"Mazowieckie",
    "qs_pg:photos_9k":1,
    "qs_pg:photos_9r":1,
    "qs_pg:photos_all":1,
    "qs_pg:photos_sr":0,
    "qs_pg:pop_sr":2,
    "qs_pg:qs_pg_placetype":"locality",
    "qs_pg:qs_pg_placetype_gp":"Town",
    "qs_pg:woe_adm0":23424923,
    "woe:adm0_id":23424923,
    "woe:name_adm0":"Polska",
    "woe:name_adm1":"Mazowieckie",
    "woe:placetype":"Town",
    "wof:name":"Wielgie",
    "wof:placetype":"locality",
    "wof:population":628
},
  "geometry": {"coordinates":[21.49552,51.24193],"type":"Point"}
}