{
  "type": "Feature",
  "properties": {
    "gn:admin1_code":"87.0",
    "gn:admin2_code":"3204.0",
    "gn:admin3_code":"320403.0",
    "gn:asciiname":"Maciejewo",
    "gn:country_code":"PL",
    "gn:dem":57,
    "gn:feature_class":"P",
    "gn:feature_code":"PPL",
    "gn:name":"Maciejewo",
    "gn:population":0,
    "gn:timezone":"Europe/Warsaw",
    "iso:country":"PL",
    "name:pol_x_preferred":[
        "Maciejewo"
    ],
    "name:vie_x_preferred":[
        "Maciejewo"
    ],
    "wof:name":"Maciejewo",
    "wof:placetype":"locality"
},
  "geometry": {"coordinates":[15.00563,53.55351999999999],"type":"Point"}
}