{
  "type": "Feature",
  "properties": {
    "gn:admin1_code":"74.0",
    "gn:admin2_code":"1010.0",
    "gn:admin3_code":"101009.0",
    "gn:asciiname":"Podkalek",
    "gn:country_code":"PL",
    "gn:dem":188,
    "gn:feature_class":"P",
    "gn:feature_code":"PPL",
    "gn:name":"Podka\u0142ek",
    "gn:population":0,
    "gn:timezone":"Europe/Warsaw",
    "iso:country":"PL",
    "name:fra_x_preferred":[
        "Podka\u0142ek"
    ],
    "name:pol_x_preferred":[
        "Podka\u0142ek"
    ],
    "name:ukr_x_preferred":[
        "\u041f\u043e\u0434\u043a\u0430\u043b\u0435\u043a"
    ],
    "wof:name":"Podkalek",
    "wof:placetype":"locality"
},
  "geometry": {"coordinates":[19.7808,51.38507],"type":"Point"}
}