{
  "type": "Feature",
  "properties": {
    "gn:admin1_code":"84.0",
    "gn:admin2_code":"2605.0",
    "gn:admin3_code":"260503.0",
    "gn:asciiname":"Dziebaltow Stary",
    "gn:country_code":"PL",
    "gn:dem":253,
    "gn:feature_class":"P",
    "gn:feature_code":"PPL",
    "gn:name":"Dzieba\u0142t\u00f3w Stary",
    "gn:population":0,
    "gn:timezone":"Europe/Warsaw",
    "iso:country":"PL",
    "name:pol_x_preferred":[
        "Stary Dzieba\u0142t\u00f3w"
    ],
    "name:ukr_x_preferred":[
        "\u0421\u0442\u0430\u0440\u0438\u0439 \u0414\u0437\u0435\u0431\u0430\u043b\u0442\u0443\u0432"
    ],
    "name:und_x_variant":[
        "Dzieba\u0142t\u00f3w",
        "Dzieba\u0142t\u00f3w Stary",
        "Stary Dzieba\u0142t\u00f3w"
    ],
    "wof:name":"Dziebaltow Stary",
    "wof:placetype":"locality"
},
  "geometry": {"coordinates":[20.35089,51.1562],"type":"Point"}
}