{
  "type": "Feature",
  "properties": {
    "gn:admin1_code":"86.0",
    "gn:admin2_code":"3017.0",
    "gn:admin3_code":"301708.0",
    "gn:asciiname":"Katy Slaskie",
    "gn:country_code":"PL",
    "gn:dem":157,
    "gn:feature_class":"P",
    "gn:feature_code":"PPL",
    "gn:name":"K\u0105ty \u015al\u0105skie",
    "gn:population":0,
    "gn:timezone":"Europe/Warsaw",
    "iso:country":"PL",
    "name:azb_x_preferred":[
        "\u06a9\u0627\u0646\u062a \u0634\u0644\u0627\u0646\u0633\u06a9\u06cc\u0647"
    ],
    "name:ceb_x_preferred":[
        "K\u0105ty \u015al\u0105skie"
    ],
    "name:fas_x_preferred":[
        "\u06a9\u0627\u0646\u062a \u0634\u0644\u0627\u0646\u0633\u06a9\u06cc\u0647"
    ],
    "name:pol_x_preferred":[
        "K\u0105ty \u015al\u0105skie"
    ],
    "name:spa_x_preferred":[
        "K\u0105ty \u015al\u0105skie"
    ],
    "name:ukr_x_preferred":[
        "\u041a\u043e\u043d\u0442\u0438-\u0428\u043b\u044c\u043e\u043d\u0441\u044c\u043a\u0456"
    ],
    "wof:name":"Katy Slaskie",
    "wof:placetype":"locality"
},
  "geometry": {"coordinates":[17.68962999999999,51.40838],"type":"Point"}
}