{
  "type": "Feature",
  "properties": {
    "gn:admin1_code":"87.0",
    "gn:admin2_code":"3214.0",
    "gn:admin3_code":"321404.0",
    "gn:asciiname":"Strzebielewo",
    "gn:country_code":"PL",
    "gn:dem":31,
    "gn:feature_class":"P",
    "gn:feature_code":"PPL",
    "gn:name":"Strzebielewo",
    "gn:population":0,
    "gn:timezone":"Europe/Warsaw",
    "iso:country":"PL",
    "name:pol_x_preferred":[
        "Strzebielewo"
    ],
    "name:ukr_x_preferred":[
        "\u0421\u0442\u0448\u0435\u0431\u0435\u043b\u0435\u0432\u043e"
    ],
    "name:vie_x_preferred":[
        "Strzebielewo"
    ],
    "wof:name":"Strzebielewo",
    "wof:placetype":"locality"
},
  "geometry": {"coordinates":[15.08396,53.25576],"type":"Point"}
}