{
  "type": "Feature",
  "properties": {
    "gn:admin1_code":"86.0",
    "gn:admin2_code":"3023.0",
    "gn:admin3_code":"302308.0",
    "gn:asciiname":"Drzewce",
    "gn:country_code":"PL",
    "gn:dem":87,
    "gn:feature_class":"P",
    "gn:feature_code":"PPL",
    "gn:name":"Drzewce",
    "gn:population":0,
    "gn:timezone":"Europe/Warsaw",
    "iso:country":"PL",
    "name:fra_x_preferred":[
        "Drzewce"
    ],
    "name:pol_x_preferred":[
        "Drzewce"
    ],
    "name:ukr_x_preferred":[
        "\u0414\u0436\u0435\u0432\u0446\u0435"
    ],
    "wof:name":"Drzewce",
    "wof:placetype":"locality"
},
  "geometry": {"coordinates":[17.89179,52.14215],"type":"Point"}
}