{
  "type": "Feature",
  "properties": {
    "gn:admin1_code":"78.0",
    "gn:admin2_code":"1422.0",
    "gn:admin3_code":"142206.0",
    "gn:asciiname":"Romany Sedzieta",
    "gn:country_code":"PL",
    "gn:dem":134,
    "gn:feature_class":"P",
    "gn:feature_code":"PPL",
    "gn:name":"Romany S\u0119dzi\u0119ta",
    "gn:population":0,
    "gn:timezone":"Europe/Warsaw",
    "iso:country":"PL",
    "name:und_x_variant":[
        "Romany S\u0105dzi\u0119ta",
        "Romany S\u0119dzi\u0119ta"
    ],
    "wof:name":"Romany Sedzieta",
    "wof:placetype":"locality"
},
  "geometry": {"coordinates":[20.84529,53.17862],"type":"Point"}
}