{
  "type": "Feature",
  "properties": {
    "gn:admin1_code":"78.0",
    "gn:admin2_code":"1427.0",
    "gn:admin3_code":"142704.0",
    "gn:asciiname":"Stopin",
    "gn:country_code":"PL",
    "gn:dem":114,
    "gn:feature_class":"P",
    "gn:feature_code":"PPL",
    "gn:name":"Stopin",
    "gn:population":0,
    "gn:timezone":"Europe/Warsaw",
    "iso:country":"PL",
    "name:fra_x_preferred":[
        "Stopin"
    ],
    "name:pol_x_preferred":[
        "Stopin"
    ],
    "name:ukr_x_preferred":[
        "\u0421\u0442\u043e\u043f\u0456\u043d"
    ],
    "wof:name":"Stopin",
    "wof:placetype":"locality"
},
  "geometry": {"coordinates":[19.72587,52.92434],"type":"Point"}
}