{
  "type": "Feature",
  "properties": {
    "gn:admin1_code":"82.0",
    "gn:admin2_code":"2203.0",
    "gn:admin3_code":"220303.0",
    "gn:asciiname":"Bukowo",
    "gn:country_code":"PL",
    "gn:dem":162,
    "gn:feature_class":"P",
    "gn:feature_code":"PPL",
    "gn:name":"Bukowo",
    "gn:population":0,
    "gn:timezone":"Europe/Warsaw",
    "iso:country":"PL",
    "name:bul_x_preferred":[
        "\u0411\u0443\u043a\u043e\u0432\u043e"
    ],
    "name:ceb_x_preferred":[
        "Bukowo"
    ],
    "name:deu_x_preferred":[
        "Bukowo"
    ],
    "name:fra_x_preferred":[
        "Bukowo"
    ],
    "name:hye_x_preferred":[
        "\u0532\u0578\u0582\u056f\u0578\u057e\u0578"
    ],
    "name:pol_x_preferred":[
        "Bukowo"
    ],
    "name:rus_x_preferred":[
        "\u0411\u0443\u043a\u043e\u0432\u043e"
    ],
    "name:srp_x_preferred":[
        "\u0411\u0443\u043a\u043e\u0432\u043e"
    ],
    "name:ukr_x_preferred":[
        "\u0411\u0443\u043a\u043e\u0432\u043e"
    ],
    "wof:name":"Bukowo",
    "wof:placetype":"locality"
},
  "geometry": {"coordinates":[17.382,53.59108000000001],"type":"Point"}
}