{
  "type": "Feature",
  "properties": {
    "gn:admin1_code":"81.0",
    "gn:admin2_code":"2061.0",
    "gn:admin3_code":"206101.0",
    "gn:asciiname":"Zagorki",
    "gn:country_code":"PL",
    "gn:dem":144,
    "gn:feature_class":"P",
    "gn:feature_code":"PPL",
    "gn:name":"Zag\u00f3rki",
    "gn:population":0,
    "gn:timezone":"Europe/Warsaw",
    "iso:country":"PL",
    "name:ceb_x_preferred":[
        "Zag\u00f3rki"
    ],
    "name:pol_x_preferred":[
        "Zag\u00f3rki"
    ],
    "name:urd_x_preferred":[
        "\u0632\u06af\u0648\u0631\u06a9\u06cc"
    ],
    "wof:name":"Zagorki",
    "wof:placetype":"neighbourhood"
},
  "geometry": {"coordinates":[23.22417,53.10261],"type":"Point"}
}