{
  "type": "Feature",
  "properties": {
    "gn:admin1_code":"83.0",
    "gn:admin2_code":"2404.0",
    "gn:admin3_code":"240405.0",
    "gn:asciiname":"Bartkowice",
    "gn:country_code":"PL",
    "gn:dem":226,
    "gn:feature_class":"P",
    "gn:feature_code":"PPL",
    "gn:name":"Bartkowice",
    "gn:population":0,
    "gn:timezone":"Europe/Warsaw",
    "iso:country":"PL",
    "name:ceb_x_preferred":[
        "Bartkowice"
    ],
    "name:nld_x_preferred":[
        "Bartkowice"
    ],
    "name:pol_x_preferred":[
        "Bartkowice"
    ],
    "name:ukr_x_preferred":[
        "\u0411\u0430\u0440\u0442\u043a\u043e\u0432\u0456\u0446\u0435"
    ],
    "wof:name":"Bartkowice",
    "wof:placetype":"locality"
},
  "geometry": {"coordinates":[19.37336,50.91927],"type":"Point"}
}