{
  "type": "Feature",
  "properties": {
    "gn:admin1_code":"86.0",
    "gn:admin2_code":"3030.0",
    "gn:admin3_code":"303004.0",
    "gn:asciiname":"Zapowiednia",
    "gn:country_code":"PL",
    "gn:dem":71,
    "gn:feature_class":"P",
    "gn:feature_code":"PPL",
    "gn:name":"Zapowiednia",
    "gn:population":0,
    "gn:timezone":"Europe/Warsaw",
    "iso:country":"PL",
    "name:fra_x_preferred":[
        "Zapowiednia"
    ],
    "name:pol_x_preferred":[
        "Zapowiednia"
    ],
    "name:ukr_x_preferred":[
        "\u0417\u0430\u043f\u043e\u0432\u0435\u0434\u043d\u044f"
    ],
    "wof:name":"Zapowiednia",
    "wof:placetype":"locality"
},
  "geometry": {"coordinates":[17.75596,52.16511],"type":"Point"}
}