{
  "type": "Feature",
  "properties": {
    "gn:admin1_code":"86.0",
    "gn:admin2_code":"3030.0",
    "gn:admin3_code":"303004.0",
    "gn:asciiname":"Zapowiednia",
    "gn:country_code":"PL",
    "gn:dem":71,
    "gn:feature_class":"P",
    "gn:feature_code":"PPL",
    "gn:name":"Zapowiednia",
    "gn:population":0,
    "gn:timezone":"Europe/Warsaw",
    "iso:country":"PL",
    "wof:name":"Zapowiednia",
    "wof:placetype":"locality"
},
  "geometry": {"coordinates":[17.75596,52.16511],"type":"Point"}
}