{
  "type": "Feature",
  "properties": {
    "gn:admin1_code":"84.0",
    "gn:admin2_code":"2602.0",
    "gn:admin3_code":"260203.0",
    "gn:asciiname":"Lesnica",
    "gn:country_code":"PL",
    "gn:dem":248,
    "gn:feature_class":"P",
    "gn:feature_code":"PPL",
    "gn:name":"Le\u015bnica",
    "gn:population":0,
    "gn:timezone":"Europe/Warsaw",
    "iso:country":"PL",
    "name:pol_x_preferred":[
        "Le\u015bnica"
    ],
    "name:ukr_x_preferred":[
        "\u041b\u0435\u0441\u044c\u043d\u0438\u0446\u044f"
    ],
    "wof:name":"Lesnica",
    "wof:placetype":"locality"
},
  "geometry": {"coordinates":[20.25115,50.83153],"type":"Point"}
}