{
  "type": "Feature",
  "properties": {
    "gn:admin1_code":"86.0",
    "gn:admin2_code":"3007.0",
    "gn:admin3_code":"300701.0",
    "gn:asciiname":"Pruszkow",
    "gn:country_code":"PL",
    "gn:dem":124,
    "gn:feature_class":"P",
    "gn:feature_code":"PPL",
    "gn:name":"Pruszk\u00f3w",
    "gn:population":0,
    "gn:timezone":"Europe/Warsaw",
    "iso:country":"PL",
    "name:und_x_variant":[
        "Pruszk\u00f3w"
    ],
    "wof:name":"Pruszkow",
    "wof:placetype":"locality"
},
  "geometry": {"coordinates":[18.04134,51.79805],"type":"Point"}
}