{
  "type": "Feature",
  "properties": {
    "gn:admin1_code":"86.0",
    "gn:admin2_code":"3010.0",
    "gn:admin3_code":"301012.0",
    "gn:asciiname":"Wierzelin",
    "gn:country_code":"PL",
    "gn:dem":86,
    "gn:feature_class":"P",
    "gn:feature_code":"PPL",
    "gn:name":"Wierzelin",
    "gn:population":0,
    "gn:timezone":"Europe/Warsaw",
    "iso:country":"PL",
    "name:ceb_x_preferred":[
        "Wierzelin"
    ],
    "name:pol_x_preferred":[
        "Wierzelin"
    ],
    "name:ukr_x_preferred":[
        "\u0412\u0435\u0436\u0435\u043b\u0456\u043d"
    ],
    "wof:name":"Wierzelin",
    "wof:placetype":"locality"
},
  "geometry": {"coordinates":[18.42977,52.37579],"type":"Point"}
}