{
  "type": "Feature",
  "properties": {
    "gn:admin1_code":"80.0",
    "gn:admin2_code":"1802.0",
    "gn:admin3_code":"180204.0",
    "gn:asciiname":"Wzdow",
    "gn:country_code":"PL",
    "gn:dem":293,
    "gn:feature_class":"P",
    "gn:feature_code":"PPL",
    "gn:name":"Wzd\u00f3w",
    "gn:population":0,
    "gn:timezone":"Europe/Warsaw",
    "iso:country":"PL",
    "name:ceb_x_preferred":[
        "Wzd\u00f3w"
    ],
    "name:pol_x_preferred":[
        "Wzd\u00f3w"
    ],
    "name:ukr_x_preferred":[
        "\u0412\u0437\u0434\u0443\u0432"
    ],
    "wof:name":"Wzdow",
    "wof:placetype":"locality"
},
  "geometry": {"coordinates":[21.99333,49.63533],"type":"Point"}
}