{
  "type": "Feature",
  "properties": {
    "gn:admin1_code":"79.0",
    "gn:admin2_code":"1602.0",
    "gn:admin3_code":"160202.0",
    "gn:asciiname":"Bliszczyce",
    "gn:country_code":"PL",
    "gn:dem":308,
    "gn:feature_class":"P",
    "gn:feature_code":"PPL",
    "gn:name":"Bliszczyce",
    "gn:population":0,
    "gn:timezone":"Europe/Warsaw",
    "iso:country":"PL",
    "wof:name":"Bliszczyce",
    "wof:placetype":"locality"
},
  "geometry": {"coordinates":[17.75665,50.08072],"type":"Point"}
}