{
  "type": "Feature",
  "properties": {
    "gn:admin1_code":"79.0",
    "gn:admin2_code":"1602.0",
    "gn:admin3_code":"160202.0",
    "gn:asciiname":"Bliszczyce",
    "gn:country_code":"PL",
    "gn:dem":308,
    "gn:feature_class":"P",
    "gn:feature_code":"PPL",
    "gn:name":"Bliszczyce",
    "gn:population":0,
    "gn:timezone":"Europe/Warsaw",
    "iso:country":"PL",
    "name:azb_x_preferred":[
        "\u0628\u0644\u06cc\u0634\u0686\u062a\u0633\u0647"
    ],
    "name:ces_x_preferred":[
        "Bliszczyce"
    ],
    "name:deu_x_preferred":[
        "Bliszczyce"
    ],
    "name:fas_x_preferred":[
        "\u0628\u0644\u06cc\u0634\u0686\u062a\u0633\u0647"
    ],
    "name:fra_x_preferred":[
        "Bliszczyce"
    ],
    "name:pol_x_preferred":[
        "Bliszczyce"
    ],
    "name:ukr_x_preferred":[
        "\u0411\u043b\u0456\u0449\u0438\u0446\u0435"
    ],
    "wof:name":"Bliszczyce",
    "wof:placetype":"locality"
},
  "geometry": {"coordinates":[17.75665,50.08072],"type":"Point"}
}