{
  "type": "Feature",
  "properties": {
    "gn:gn_country":"PL",
    "gn:gn_fcode":"PPL",
    "gn:gn_pop":413,
    "gn:population":413,
    "iso:country":"PL",
    "name:ast_x_preferred":[
        "Mazurowice"
    ],
    "name:ceb_x_preferred":[
        "Mazurowice"
    ],
    "name:deu_x_preferred":[
        "Mazurowice"
    ],
    "name:eng_x_preferred":[
        "Mazurowice"
    ],
    "name:fra_x_preferred":[
        "Mazurowice"
    ],
    "name:pol_x_preferred":[
        "Mazurowice"
    ],
    "name:ukr_x_preferred":[
        "\u041c\u0430\u0437\u0443\u0440\u043e\u0432\u0456\u0446\u0435"
    ],
    "qs_pg:aaroncc":"PL",
    "qs_pg:gn_country":"PL",
    "qs_pg:gn_fcode":"PPL",
    "qs_pg:gn_pop":413,
    "qs_pg:name":"Mazurowice",
    "qs_pg:name_adm0":"Polska",
    "qs_pg:name_adm1":"Dolnosl\u0105skie",
    "qs_pg:photos_9r":0,
    "qs_pg:photos_sr":0,
    "qs_pg:pop_sr":2,
    "qs_pg:qs_pg_placetype":"locality",
    "qs_pg:qs_pg_placetype_gp":"Town",
    "qs_pg:woe_adm0":23424923,
    "woe:adm0_id":23424923,
    "woe:name_adm0":"Polska",
    "woe:name_adm1":"Dolnosl\u0105skie",
    "woe:placetype":"Town",
    "wof:name":"Mazurowice",
    "wof:placetype":"locality",
    "wof:population":413
},
  "geometry": {"coordinates":[16.46301,51.2128],"type":"Point"}
}