{
  "type": "Feature",
  "properties": {
    "gn:admin1_code":"86.0",
    "gn:admin2_code":"3028.0",
    "gn:admin3_code":"302807.0",
    "gn:asciiname":"Siedleczko",
    "gn:country_code":"PL",
    "gn:dem":91,
    "gn:feature_class":"P",
    "gn:feature_code":"PPL",
    "gn:name":"Siedleczko",
    "gn:population":0,
    "gn:timezone":"Europe/Warsaw",
    "iso:country":"PL",
    "name:fra_x_preferred":[
        "Siedleczko"
    ],
    "name:pol_x_preferred":[
        "Siedleczko"
    ],
    "name:ukr_x_preferred":[
        "\u0421\u0435\u0434\u043b\u0435\u0447\u043a\u043e"
    ],
    "wof:name":"Siedleczko",
    "wof:placetype":"locality"
},
  "geometry": {"coordinates":[17.33238,52.85609],"type":"Point"}
}