{
  "type": "Feature",
  "properties": {
    "gn:admin1_code":"82.0",
    "gn:admin2_code":"2209.0",
    "gn:admin3_code":"220907.0",
    "gn:asciiname":"Lipinka",
    "gn:country_code":"PL",
    "gn:dem":1,
    "gn:feature_class":"P",
    "gn:feature_code":"PPL",
    "gn:name":"Lipinka",
    "gn:population":0,
    "gn:timezone":"Europe/Warsaw",
    "iso:country":"PL",
    "name:ceb_x_preferred":[
        "Lipinka"
    ],
    "name:eng_x_preferred":[
        "Lipinka"
    ],
    "name:pol_x_preferred":[
        "Lipinka"
    ],
    "name:rus_x_preferred":[
        "\u041b\u0438\u043f\u0438\u043d\u043a\u0430"
    ],
    "name:und_x_variant":[
        "Lindenau"
    ],
    "wof:name":"Lipinka",
    "wof:placetype":"locality"
},
  "geometry": {"coordinates":[19.12178,54.12327],"type":"Point"}
}