{
  "type": "Feature",
  "properties": {
    "iso:country":"PL",
    "name:azb_x_preferred":[
        "\u062e\u0648\u0631\u06a9\u0648\u0648\u06a9\u0627"
    ],
    "name:ceb_x_preferred":[
        "Chork\u00f3wka"
    ],
    "name:fas_x_preferred":[
        "\u062e\u0648\u0631\u06a9\u0648\u0648\u06a9\u0627"
    ],
    "name:nld_x_preferred":[
        "Chork\u00f3wka"
    ],
    "name:pol_x_preferred":[
        "Chork\u00f3wka"
    ],
    "name:ukr_x_preferred":[
        "\u0425\u043e\u0440\u043a\u0443\u0432\u043a\u0430"
    ],
    "wof:coterminous":[
        1125332645
    ],
    "wof:name":"Chork\u00f3wka",
    "wof:placetype":"locality"
},
  "geometry": {"coordinates":[21.6475760368177,49.6464253019999],"type":"Point"}
}