{
  "type": "Feature",
  "properties": {
    "iso:country":"PL",
    "name:pol_x_preferred":[
        "Chork\u00f3wka"
    ],
    "wof:name":"Chork\u00f3wka",
    "wof:placetype":"locality"
},
  "geometry": {"coordinates":[21.6475760368177,49.6464253019999],"type":"Point"}
}