{
  "type": "Feature",
  "properties": {
    "gn:admin1_code":"82.0",
    "gn:admin2_code":"2203.0",
    "gn:admin3_code":"220307.0",
    "gn:asciiname":"Przyrzecze",
    "gn:country_code":"PL",
    "gn:dem":137,
    "gn:feature_class":"P",
    "gn:feature_code":"PPL",
    "gn:name":"Przyrzecze",
    "gn:population":0,
    "gn:timezone":"Europe/Warsaw",
    "iso:country":"PL",
    "wof:name":"Przyrzecze",
    "wof:placetype":"locality"
},
  "geometry": {"coordinates":[17.02821,53.74653000000001],"type":"Point"}
}