{
  "type": "Feature",
  "properties": {
    "gn:admin1_code":"79.0",
    "gn:admin2_code":"1608.0",
    "gn:admin3_code":"160803.0",
    "gn:asciiname":"Sowczyce",
    "gn:country_code":"PL",
    "gn:dem":252,
    "gn:feature_class":"P",
    "gn:feature_code":"PPL",
    "gn:name":"Sowczyce",
    "gn:population":0,
    "gn:timezone":"Europe/Warsaw",
    "iso:country":"PL",
    "name:azb_x_preferred":[
        "\u0633\u0648\u0648\u0686\u062a\u0633\u0647"
    ],
    "name:deu_x_preferred":[
        "Sowczyce"
    ],
    "name:fas_x_preferred":[
        "\u0633\u0648\u0648\u0686\u062a\u0633\u0647"
    ],
    "name:pol_x_preferred":[
        "Sowczyce"
    ],
    "name:rus_x_preferred":[
        "\u0421\u043e\u0432\u0447\u0438\u0446\u0435"
    ],
    "name:ukr_x_preferred":[
        "\u0421\u043e\u0432\u0447\u0438\u0446\u0435"
    ],
    "wof:name":"Sowczyce",
    "wof:placetype":"locality"
},
  "geometry": {"coordinates":[18.49842,50.84399000000001],"type":"Point"}
}