{
  "type": "Feature",
  "properties": {
    "gn:admin1_code":"74.0",
    "gn:admin2_code":"1020.0",
    "gn:admin3_code":"102002.0",
    "gn:asciiname":"Gebice",
    "gn:country_code":"PL",
    "gn:dem":124,
    "gn:feature_class":"P",
    "gn:feature_code":"PPL",
    "gn:name":"G\u0119bice",
    "gn:population":0,
    "gn:timezone":"Europe/Warsaw",
    "iso:country":"PL",
    "wof:name":"Gebice",
    "wof:placetype":"neighbourhood"
},
  "geometry": {"coordinates":[19.26981,51.97392],"type":"Point"}
}