{
  "type": "Feature",
  "properties": {
    "gn:admin1_code":"83.0",
    "gn:admin2_code":"2410.0",
    "gn:admin3_code":"241001.0",
    "gn:asciiname":"Goczalkowice Dolne",
    "gn:country_code":"PL",
    "gn:dem":256,
    "gn:feature_class":"P",
    "gn:feature_code":"PPL",
    "gn:name":"Gocza\u0142kowice Dolne",
    "gn:population":0,
    "gn:timezone":"Europe/Warsaw",
    "iso:country":"PL",
    "wof:name":"Goczalkowice Dolne",
    "wof:placetype":"locality"
},
  "geometry": {"coordinates":[18.95448,49.94435],"type":"Point"}
}