{
  "type": "Feature",
  "properties": {
    "gn:admin1_code":"86.0",
    "gn:admin2_code":"3031.0",
    "gn:admin3_code":"303104.0",
    "gn:asciiname":"Debrzno Wies",
    "gn:country_code":"PL",
    "gn:dem":155,
    "gn:feature_class":"P",
    "gn:feature_code":"PPL",
    "gn:name":"Debrzno Wie\u015b",
    "gn:population":0,
    "gn:timezone":"Europe/Warsaw",
    "iso:country":"PL",
    "name:azb_x_preferred":[
        "\u062f\u0628\u0698\u0646\u0648-\u0648\u06cc\u0634"
    ],
    "name:ceb_x_preferred":[
        "Debrzno Wie\u015b"
    ],
    "name:deu_x_preferred":[
        "Debrzno-Wie\u015b"
    ],
    "name:fas_x_preferred":[
        "\u062f\u0628\u0698\u0646\u0648-\u0648\u06cc\u0634"
    ],
    "name:fra_x_preferred":[
        "Debrzno-Wie\u015b"
    ],
    "name:nld_x_preferred":[
        "Debrzno-Wie\u015b"
    ],
    "name:pol_x_preferred":[
        "Debrzno-Wie\u015b"
    ],
    "name:ukr_x_preferred":[
        "\u0414\u0435\u0431\u0436\u043d\u043e-\u0412\u0435\u0441\u044c"
    ],
    "wof:name":"Debrzno Wies",
    "wof:placetype":"locality"
},
  "geometry": {"coordinates":[17.23011,53.52635],"type":"Point"}
}