{
  "type": "Feature",
  "properties": {
    "gn:admin1_code":"86.0",
    "gn:admin2_code":"3031.0",
    "gn:admin3_code":"303104.0",
    "gn:asciiname":"Debrzno Wies",
    "gn:country_code":"PL",
    "gn:dem":155,
    "gn:feature_class":"P",
    "gn:feature_code":"PPL",
    "gn:name":"Debrzno Wie\u015b",
    "gn:population":0,
    "gn:timezone":"Europe/Warsaw",
    "iso:country":"PL",
    "name:und_x_variant":[
        "Debrzno Wie\u015b"
    ],
    "wof:name":"Debrzno Wies",
    "wof:placetype":"locality"
},
  "geometry": {"coordinates":[17.23011,53.52635],"type":"Point"}
}