{
  "type": "Feature",
  "properties": {
    "gn:admin1_code":"79.0",
    "gn:admin2_code":"1602.0",
    "gn:admin3_code":"160203.0",
    "gn:asciiname":"Pomorzowice",
    "gn:country_code":"PL",
    "gn:dem":237,
    "gn:feature_class":"P",
    "gn:feature_code":"PPL",
    "gn:name":"Pomorzowice",
    "gn:population":0,
    "gn:timezone":"Europe/Warsaw",
    "iso:country":"PL",
    "name:pol_x_preferred":[
        "Pomorzowice"
    ],
    "name:ukr_x_preferred":[
        "\u041f\u043e\u043c\u043e\u0436\u043e\u0432\u0456\u0446\u0435"
    ],
    "wof:name":"Pomorzowice",
    "wof:placetype":"locality"
},
  "geometry": {"coordinates":[17.7612,50.28396],"type":"Point"}
}