{
  "type": "Feature",
  "properties": {
    "gn:admin1_code":"84.0",
    "gn:admin2_code":"2605.0",
    "gn:admin3_code":"260508.0",
    "gn:asciiname":"Czarniecka Gora",
    "gn:country_code":"PL",
    "gn:dem":259,
    "gn:feature_class":"P",
    "gn:feature_code":"PPL",
    "gn:name":"Czarniecka G\u00f3ra",
    "gn:population":0,
    "gn:timezone":"Europe/Warsaw",
    "iso:country":"PL",
    "name:ceb_x_preferred":[
        "Czarniecka G\u00f3ra"
    ],
    "name:nld_x_preferred":[
        "Czarniecka G\u00f3ra"
    ],
    "name:pol_x_preferred":[
        "Czarniecka G\u00f3ra"
    ],
    "name:ukr_x_preferred":[
        "\u0427\u0430\u0440\u043d\u0435\u0446\u044c\u043a\u0430-\u0490\u0443\u0440\u0430"
    ],
    "wof:name":"Czarniecka Gora",
    "wof:placetype":"locality"
},
  "geometry": {"coordinates":[20.52042,51.13662],"type":"Point"}
}