{
  "type": "Feature",
  "properties": {
    "gn:admin1_code":"87.0",
    "gn:admin2_code":"3209.0",
    "gn:admin3_code":"320908.0",
    "gn:asciiname":"Giezkowo",
    "gn:country_code":"PL",
    "gn:dem":30,
    "gn:feature_class":"P",
    "gn:feature_code":"PPL",
    "gn:name":"Giezkowo",
    "gn:population":0,
    "gn:timezone":"Europe/Warsaw",
    "iso:country":"PL",
    "wof:name":"Giezkowo",
    "wof:placetype":"locality"
},
  "geometry": {"coordinates":[16.11639,54.13576],"type":"Point"}
}