{
  "type": "Feature",
  "properties": {
    "gn:admin1_code":"84.0",
    "gn:admin2_code":"2605.0",
    "gn:admin3_code":"260502.0",
    "gn:asciiname":"Morzywol",
    "gn:country_code":"PL",
    "gn:dem":211,
    "gn:feature_class":"P",
    "gn:feature_code":"PPL",
    "gn:name":"Morzyw\u00f3\u0142",
    "gn:population":0,
    "gn:timezone":"Europe/Warsaw",
    "iso:country":"PL",
    "name:ceb_x_preferred":[
        "Morzyw\u00f3\u0142"
    ],
    "name:nld_x_preferred":[
        "Morzyw\u00f3\u0142"
    ],
    "name:pol_x_preferred":[
        "Morzyw\u00f3\u0142"
    ],
    "name:ukr_x_preferred":[
        "\u041c\u043e\u0436\u0438\u0432\u0443\u043b"
    ],
    "wof:name":"Morzywol",
    "wof:placetype":"locality"
},
  "geometry": {"coordinates":[20.43427,51.25141],"type":"Point"}
}