{
  "type": "Feature",
  "properties": {
    "gn:admin1_code":"85.0",
    "gn:admin2_code":"2812.0",
    "gn:admin3_code":"281205.0",
    "gn:asciiname":"Jamielnik",
    "gn:country_code":"PL",
    "gn:dem":109,
    "gn:feature_class":"P",
    "gn:feature_code":"PPL",
    "gn:name":"Jamielnik",
    "gn:population":0,
    "gn:timezone":"Europe/Warsaw",
    "iso:country":"PL",
    "name:ceb_x_preferred":[
        "Jamielnik"
    ],
    "name:eng_x_preferred":[
        "Jamielnik"
    ],
    "name:pol_x_preferred":[
        "Jamielnik"
    ],
    "name:rus_x_preferred":[
        "\u042f\u043c\u0435\u043b\u044c\u043d\u0438\u043a"
    ],
    "name:ukr_x_preferred":[
        "\u042f\u043c\u0435\u043b\u044c\u043d\u0438\u043a"
    ],
    "name:urd_x_preferred":[
        "\u062c\u0645\u06cc\u0644\u0646\u06a9"
    ],
    "wof:name":"Jamielnik",
    "wof:placetype":"locality"
},
  "geometry": {"coordinates":[19.5067,53.52676],"type":"Point"}
}