{
  "type": "Feature",
  "properties": {
    "gn:admin1_code":"78.0",
    "gn:admin2_code":"1409.0",
    "gn:admin3_code":"140905.0",
    "gn:asciiname":"Tarnowek",
    "gn:country_code":"PL",
    "gn:dem":205,
    "gn:feature_class":"P",
    "gn:feature_code":"PPL",
    "gn:name":"Tarn\u00f3wek",
    "gn:population":0,
    "gn:timezone":"Europe/Warsaw",
    "iso:country":"PL",
    "name:ceb_x_preferred":[
        "Tarn\u00f3wek"
    ],
    "name:fra_x_preferred":[
        "Tarn\u00f3wek"
    ],
    "name:pol_x_preferred":[
        "Tarn\u00f3wek"
    ],
    "name:ukr_x_preferred":[
        "\u0422\u0430\u0440\u043d\u0443\u0432\u0435\u043a"
    ],
    "name:und_x_variant":[
        "Tarn\u00f3wek"
    ],
    "wof:name":"Tarnowek",
    "wof:placetype":"locality"
},
  "geometry": {"coordinates":[21.4502,51.0722],"type":"Point"}
}