{
  "type": "Feature",
  "properties": {
    "gn:gn_country":"PL",
    "gn:gn_fcode":"PPL",
    "gn:gn_pop":3000,
    "gn:population":3000,
    "iso:country":"PL",
    "name:ast_x_preferred":[
        "Grabownica Starze\u0144ska"
    ],
    "name:ceb_x_preferred":[
        "Grabownica Starze\u0144ska"
    ],
    "name:eng_x_preferred":[
        "Grabownica Starze\u0144ska"
    ],
    "name:fra_x_preferred":[
        "Grabownica Starze\u0144ska"
    ],
    "name:nan_x_preferred":[
        "Grabownica Starze\u0144ska"
    ],
    "name:nld_x_preferred":[
        "Grabownica Starze\u0144ska"
    ],
    "name:pol_x_preferred":[
        "Grabownica Starze\u0144ska"
    ],
    "name:ukr_x_preferred":[
        "\u0413\u0440\u0430\u0431\u0456\u0432\u043d\u0438\u0446\u044f \u0421\u0442\u0430\u0440\u0436\u0435\u043d\u0441\u044c\u043a\u0430"
    ],
    "name:unk_x_variant":[
        "Grabownica"
    ],
    "qs_pg:aaroncc":"PL",
    "qs_pg:gn_country":"PL",
    "qs_pg:gn_fcode":"PPL",
    "qs_pg:gn_pop":3000,
    "qs_pg:name":"Grabownica Starze\u0144ska",
    "qs_pg:name_adm0":"Polska",
    "qs_pg:name_adm1":"Podkarpackie",
    "qs_pg:photos_9k":1,
    "qs_pg:photos_9r":1,
    "qs_pg:photos_all":1,
    "qs_pg:photos_sr":0,
    "qs_pg:pop_sr":4,
    "qs_pg:qs_pg_placetype":"locality",
    "qs_pg:qs_pg_placetype_gp":"Town",
    "qs_pg:woe_adm0":23424923,
    "woe:adm0_id":23424923,
    "woe:name_adm0":"Polska",
    "woe:name_adm1":"Podkarpackie",
    "woe:placetype":"Town",
    "wof:name":"Grabownica Starze\u0144ska",
    "wof:placetype":"locality",
    "wof:population":3000
},
  "geometry": {"coordinates":[22.07754,49.65896],"type":"Point"}
}