{
  "type": "Feature",
  "properties": {
    "gn:country":"PL",
    "gn:fcode":"PPL",
    "gn:population":1789,
    "iso:country":"PL",
    "name:ast_x_preferred":[
        "Mrozy"
    ],
    "name:ceb_x_preferred":[
        "Mrozy"
    ],
    "name:ces_x_preferred":[
        "Mrozy"
    ],
    "name:che_x_preferred":[
        "\u041c\u0440\u043e\u0437\u0438"
    ],
    "name:eng_x_preferred":[
        "Mrozy"
    ],
    "name:fra_x_preferred":[
        "Mrozy"
    ],
    "name:nan_x_preferred":[
        "Mrozy"
    ],
    "name:pol_x_preferred":[
        "Mrozy"
    ],
    "name:tat_x_preferred":[
        "\u041c\u0440\u043e\u0437\u0438"
    ],
    "name:ukr_x_preferred":[
        "\u041c\u0440\u043e\u0437\u0438"
    ],
    "qs_pg:aaroncc":"PL",
    "qs_pg:gn_country":"PL",
    "qs_pg:gn_fcode":"PPL",
    "qs_pg:gn_pop":1789,
    "qs_pg:name":"Mrozy",
    "qs_pg:name_adm0":"Polska",
    "qs_pg:name_adm1":"Mazowieckie",
    "qs_pg:photos_9k":1,
    "qs_pg:photos_9r":1,
    "qs_pg:photos_all":1,
    "qs_pg:photos_sr":0,
    "qs_pg:pop_sr":3,
    "qs_pg:qs_pg_placetype":"locality",
    "qs_pg:qs_pg_placetype_gp":"Town",
    "qs_pg:woe_adm0":23424923,
    "woe:adm0_id":23424923,
    "woe:name_adm0":"Polska",
    "woe:name_adm1":"Mazowieckie",
    "woe:placetype":"Town",
    "wof:name":"Mrozy",
    "wof:placetype":"locality",
    "wof:population":1789
},
  "geometry": {"coordinates":[20.36702,52.01975],"type":"Point"}
}