{
  "type": "Feature",
  "properties": {
    "gn:admin1_code":"75.0",
    "gn:admin2_code":"604.0",
    "gn:admin3_code":"60404.0",
    "gn:asciiname":"Obrowiec",
    "gn:country_code":"PL",
    "gn:dem":195,
    "gn:feature_class":"P",
    "gn:feature_code":"PPL",
    "gn:name":"Obrowiec",
    "gn:population":0,
    "gn:timezone":"Europe/Warsaw",
    "iso:country":"PL",
    "name:ceb_x_preferred":[
        "Obrowiec"
    ],
    "name:fra_x_preferred":[
        "Obrowiec"
    ],
    "name:pol_x_preferred":[
        "Obrowiec"
    ],
    "name:ukr_x_preferred":[
        "\u041e\u0431\u0440\u043e\u0432\u0435\u0446\u044c"
    ],
    "wof:name":"Obrowiec",
    "wof:placetype":"locality"
},
  "geometry": {"coordinates":[23.83293,50.8168],"type":"Point"}
}