{
  "type": "Feature",
  "properties": {
    "gn:admin1_code":"77.0",
    "gn:admin2_code":"1211.0",
    "gn:admin3_code":"121102.0",
    "gn:asciiname":"Pieniny",
    "gn:country_code":"PL",
    "gn:dem":456,
    "gn:feature_class":"P",
    "gn:feature_code":"PPL",
    "gn:name":"Pieniny",
    "gn:population":0,
    "gn:timezone":"Europe/Warsaw",
    "iso:country":"PL",
    "name:und_x_variant":[
        "Pienim",
        "Pieniny"
    ],
    "wof:name":"Pieniny",
    "wof:placetype":"locality"
},
  "geometry": {"coordinates":[20.45,49.41667],"type":"Point"}
}