{
  "type": "Feature",
  "properties": {
    "gn:admin1_code":"77.0",
    "gn:admin2_code":"1211.0",
    "gn:admin3_code":"121102.0",
    "gn:asciiname":"Pieniny",
    "gn:country_code":"PL",
    "gn:dem":456,
    "gn:feature_class":"P",
    "gn:feature_code":"PPL",
    "gn:name":"Pieniny",
    "gn:population":0,
    "gn:timezone":"Europe/Warsaw",
    "iso:country":"PL",
    "name:ceb_x_preferred":[
        "Pieniny"
    ],
    "name:ces_x_preferred":[
        "Pieniny"
    ],
    "name:deu_x_preferred":[
        "Pieninen"
    ],
    "name:epo_x_preferred":[
        "Pieniny"
    ],
    "name:fra_x_preferred":[
        "Pi\u00e9nines"
    ],
    "name:hun_x_preferred":[
        "Pieninek"
    ],
    "name:lit_x_preferred":[
        "Pieninai"
    ],
    "name:nld_x_preferred":[
        "Pieniny"
    ],
    "name:nno_x_preferred":[
        "Pieniny"
    ],
    "name:nor_x_preferred":[
        "Pieniny"
    ],
    "name:pol_x_preferred":[
        "Pieniny"
    ],
    "name:ron_x_preferred":[
        "Pieniny"
    ],
    "name:rus_x_preferred":[
        "\u041f\u0435\u043d\u0438\u043d\u044b"
    ],
    "name:slk_x_preferred":[
        "Pieniny"
    ],
    "name:spa_x_preferred":[
        "Montes Pieninos"
    ],
    "name:ukr_x_preferred":[
        "\u041f'\u0454\u043d\u0456\u043d\u0438"
    ],
    "name:und_x_variant":[
        "Pienim"
    ],
    "name:zho_x_preferred":[
        "\u76ae\u8036\u5c3c\u5167\u5c71\u8108"
    ],
    "wof:name":"Pieniny",
    "wof:placetype":"locality"
},
  "geometry": {"coordinates":[20.45,49.41667],"type":"Point"}
}