{
  "type": "Feature",
  "properties": {
    "gn:admin1_code":"75.0",
    "gn:admin2_code":"611.0",
    "gn:admin3_code":"61103.0",
    "gn:asciiname":"Natalin",
    "gn:country_code":"PL",
    "gn:dem":174,
    "gn:feature_class":"P",
    "gn:feature_code":"PPL",
    "gn:name":"Natalin",
    "gn:population":0,
    "gn:timezone":"Europe/Warsaw",
    "iso:country":"PL",
    "name:fra_x_preferred":[
        "Natalin"
    ],
    "name:pol_x_preferred":[
        "Natalin"
    ],
    "name:ukr_x_preferred":[
        "\u041d\u0430\u0442\u0430\u043b\u0456\u043d"
    ],
    "wof:name":"Natalin",
    "wof:placetype":"locality"
},
  "geometry": {"coordinates":[22.17427,51.67892],"type":"Point"}
}