{
  "type": "Feature",
  "properties": {
    "gn:country":"PL",
    "gn:fcode":"PPL",
    "gn:population":1300,
    "iso:country":"PL",
    "name:ceb_x_preferred":[
        "Tarn\u00f3wka"
    ],
    "name:deu_x_preferred":[
        "Tarn\u00f3wka"
    ],
    "name:fra_x_preferred":[
        "Tarn\u00f3wka"
    ],
    "name:nld_x_preferred":[
        "Tarn\u00f3wka"
    ],
    "name:pol_x_preferred":[
        "Tarn\u00f3wka"
    ],
    "name:ukr_x_preferred":[
        "\u0422\u0430\u0440\u043d\u0443\u0432\u043a\u0430"
    ],
    "name:und_x_variant":[
        "Tarnowke"
    ],
    "qs_pg:aaroncc":"PL",
    "qs_pg:gn_country":"PL",
    "qs_pg:gn_fcode":"PPL",
    "qs_pg:gn_pop":1300,
    "qs_pg:name":"Tarn\u00f3wka",
    "qs_pg:name_adm0":"Polska",
    "qs_pg:name_adm1":"Wielkopolskie",
    "qs_pg:photos_9r":0,
    "qs_pg:photos_sr":0,
    "qs_pg:pop_sr":3,
    "qs_pg:qs_pg_placetype":"locality",
    "qs_pg:qs_pg_placetype_gp":"Town",
    "qs_pg:woe_adm0":23424923,
    "woe:adm0_id":23424923,
    "woe:name_adm0":"Polska",
    "woe:name_adm1":"Wielkopolskie",
    "woe:placetype":"Town",
    "wof:coterminous":[
        1477752321
    ],
    "wof:name":"Tarn\u00f3wka",
    "wof:placetype":"locality",
    "wof:population":1300
},
  "geometry": {"coordinates":[16.85273,53.34174],"type":"Point"}
}