{
  "type": "Feature",
  "properties": {
    "gn:admin1_code":"84.0",
    "gn:admin2_code":"2602.0",
    "gn:admin3_code":"260203.0",
    "gn:asciiname":"Karsznice",
    "gn:country_code":"PL",
    "gn:dem":248,
    "gn:feature_class":"P",
    "gn:feature_code":"PPL",
    "gn:name":"Karsznice",
    "gn:population":0,
    "gn:timezone":"Europe/Warsaw",
    "iso:country":"PL",
    "name:pol_x_preferred":[
        "Karsznice"
    ],
    "name:ukr_x_preferred":[
        "\u041a\u0430\u0440\u0448\u043d\u0456\u0446\u0435"
    ],
    "wof:name":"Karsznice",
    "wof:placetype":"locality"
},
  "geometry": {"coordinates":[20.30176,50.77453],"type":"Point"}
}