{
  "type": "Feature",
  "properties": {
    "gn:admin1_code":"72.0",
    "gn:admin2_code":"222.0",
    "gn:admin3_code":"22202.0",
    "gn:asciiname":"Morzyna",
    "gn:country_code":"PL",
    "gn:dem":106,
    "gn:feature_class":"P",
    "gn:feature_code":"PPL",
    "gn:name":"Morzyna",
    "gn:population":0,
    "gn:timezone":"Europe/Warsaw",
    "iso:country":"PL",
    "name:und_x_variant":[
        "Maibach",
        "Mierzyn",
        "Maybach",
        "Mersine",
        "Morzyna"
    ],
    "wof:name":"Morzyna",
    "wof:placetype":"locality"
},
  "geometry": {"coordinates":[16.6781,51.48654000000001],"type":"Point"}
}