{
  "type": "Feature",
  "properties": {
    "gn:admin1_code":"73.0",
    "gn:admin2_code":"411.0",
    "gn:admin3_code":"41104.0",
    "gn:asciiname":"Kolonia Belszewo",
    "gn:country_code":"PL",
    "gn:dem":86,
    "gn:feature_class":"P",
    "gn:feature_code":"PPL",
    "gn:name":"Kolonia Be\u0142szewo",
    "gn:population":0,
    "gn:timezone":"Europe/Warsaw",
    "iso:country":"PL",
    "name:pol_x_preferred":[
        "Be\u0142szewo-Kolonia"
    ],
    "name:ukr_x_preferred":[
        "\u0411\u0435\u043b\u0448\u0435\u0432\u043e-\u041a\u043e\u043b\u044c\u043e\u043d\u0456\u044f"
    ],
    "name:und_x_variant":[
        "Be\u0142szewo Kolonia",
        "Kolonia Be\u0142szewo"
    ],
    "wof:name":"Kolonia Belszewo",
    "wof:placetype":"locality"
},
  "geometry": {"coordinates":[18.69046,52.64578],"type":"Point"}
}