{
  "type": "Feature",
  "properties": {
    "gn:admin1_code":"74.0",
    "gn:admin2_code":"1003.0",
    "gn:admin3_code":"100302.0",
    "gn:asciiname":"Ostrow",
    "gn:country_code":"PL",
    "gn:dem":193,
    "gn:feature_class":"P",
    "gn:feature_code":"PPL",
    "gn:name":"Ostr\u00f3w",
    "gn:population":0,
    "gn:timezone":"Europe/Warsaw",
    "iso:country":"PL",
    "name:azb_x_preferred":[
        "\u0627\u0648\u0633\u062a\u0631\u0648\u0648"
    ],
    "name:ceb_x_preferred":[
        "Ostr\u00f3w"
    ],
    "name:fas_x_preferred":[
        "\u0627\u0648\u0633\u062a\u0631\u0648\u0648"
    ],
    "name:fra_x_preferred":[
        "Ostr\u00f3w"
    ],
    "name:nld_x_preferred":[
        "Ostr\u00f3w"
    ],
    "name:pol_x_preferred":[
        "Ostr\u00f3w"
    ],
    "name:ukr_x_preferred":[
        "\u041e\u0441\u0442\u0440\u0443\u0432"
    ],
    "name:und_x_variant":[
        "Ostr\u00f3w"
    ],
    "wof:name":"Ostrow",
    "wof:placetype":"locality"
},
  "geometry": {"coordinates":[19.18797,51.58374],"type":"Point"}
}