{
  "type": "Feature",
  "properties": {
    "gn:admin1_code":"75.0",
    "gn:admin2_code":"620.0",
    "gn:admin3_code":"62015.0",
    "gn:asciiname":"Zurawnica",
    "gn:country_code":"PL",
    "gn:dem":234,
    "gn:feature_class":"P",
    "gn:feature_code":"PPL",
    "gn:name":"\u017burawnica",
    "gn:population":0,
    "gn:timezone":"Europe/Warsaw",
    "iso:country":"PL",
    "wof:name":"Zurawnica",
    "wof:placetype":"locality"
},
  "geometry": {"coordinates":[22.96208,50.65098],"type":"Point"}
}