{
  "type": "Feature",
  "properties": {
    "gn:admin1_code":"86.0",
    "gn:admin2_code":"3016.0",
    "gn:admin3_code":"301601.0",
    "gn:asciiname":"Slonawy",
    "gn:country_code":"PL",
    "gn:dem":55,
    "gn:feature_class":"P",
    "gn:feature_code":"PPL",
    "gn:name":"S\u0142onawy",
    "gn:population":0,
    "gn:timezone":"Europe/Warsaw",
    "iso:country":"PL",
    "name:und_x_variant":[
        "S\u0142onawy"
    ],
    "wof:name":"Slonawy",
    "wof:placetype":"locality"
},
  "geometry": {"coordinates":[16.76029,52.66353],"type":"Point"}
}