{
  "type": "Feature",
  "properties": {
    "gn:admin1_code":"74.0",
    "gn:admin2_code":"1001.0",
    "gn:admin3_code":"100107.0",
    "gn:asciiname":"Kolonia Szczercowska Wies",
    "gn:country_code":"PL",
    "gn:dem":168,
    "gn:feature_class":"P",
    "gn:feature_code":"PPL",
    "gn:name":"Kolonia Szczercowska Wie\u015b",
    "gn:population":0,
    "gn:timezone":"Europe/Warsaw",
    "iso:country":"PL",
    "name:fra_x_preferred":[
        "Kolonia Szczercowska"
    ],
    "name:pol_x_preferred":[
        "Kolonia Szczercowska"
    ],
    "name:ukr_x_preferred":[
        "\u041a\u043e\u043b\u044c\u043e\u043d\u0456\u044f-\u0429\u0435\u0440\u0446\u043e\u0432\u0441\u044c\u043a\u0430"
    ],
    "name:und_x_variant":[
        "Kolonia Szczercowska Wie\u015b"
    ],
    "wof:name":"Kolonia Szczercowska Wies",
    "wof:placetype":"locality"
},
  "geometry": {"coordinates":[19.07848,51.35261],"type":"Point"}
}