{
  "type": "Feature",
  "properties": {
    "gn:admin1_code":"77.0",
    "gn:admin2_code":"1212.0",
    "gn:admin3_code":"121206.0",
    "gn:asciiname":"Glanow",
    "gn:country_code":"PL",
    "gn:dem":419,
    "gn:feature_class":"P",
    "gn:feature_code":"PPL",
    "gn:name":"Glan\u00f3w",
    "gn:population":0,
    "gn:timezone":"Europe/Warsaw",
    "iso:country":"PL",
    "name:ceb_x_preferred":[
        "Glan\u00f3w"
    ],
    "name:nld_x_preferred":[
        "Glan\u00f3w"
    ],
    "name:pol_x_preferred":[
        "Glan\u00f3w"
    ],
    "name:ukr_x_preferred":[
        "\u0490\u043b\u044f\u043d\u0443\u0432"
    ],
    "wof:name":"Glanow",
    "wof:placetype":"locality"
},
  "geometry": {"coordinates":[19.82689,50.31686],"type":"Point"}
}