{
  "type": "Feature",
  "properties": {
    "gn:admin1_code":"84.0",
    "gn:admin2_code":"2611.0",
    "gn:admin3_code":"261102.0",
    "gn:asciiname":"Kuczow",
    "gn:country_code":"PL",
    "gn:dem":212,
    "gn:feature_class":"P",
    "gn:feature_code":"PPL",
    "gn:name":"Kucz\u00f3w",
    "gn:population":0,
    "gn:timezone":"Europe/Warsaw",
    "iso:country":"PL",
    "name:ceb_x_preferred":[
        "Kucz\u00f3w"
    ],
    "name:nld_x_preferred":[
        "Kucz\u00f3w"
    ],
    "name:pol_x_preferred":[
        "Kucz\u00f3w"
    ],
    "name:ukr_x_preferred":[
        "\u041a\u0443\u0447\u0443\u0432"
    ],
    "name:und_x_variant":[
        "Kucz\u00f3w"
    ],
    "wof:name":"Kuczow",
    "wof:placetype":"locality"
},
  "geometry": {"coordinates":[21.1242,51.00314],"type":"Point"}
}