{
  "type": "Feature",
  "properties": {
    "iso:country":"PL",
    "name:eng_x_preferred":[
        "Osiedla spolki Strzecha"
    ],
    "name:pol_x_preferred":[
        "Osiedla sp\u00f3\u0142ki Strzecha"
    ],
    "wof:name":"Osiedla spolki Strzecha",
    "wof:placetype":"neighbourhood"
},
  "geometry": {"coordinates":[16.8772949339834,52.39267685099802],"type":"Point"}
}