{
  "type": "Feature",
  "properties": {
    "gn:admin1_code":"78.0",
    "gn:admin2_code":"1425.0",
    "gn:admin3_code":"142508.0",
    "gn:asciiname":"Jedlnia",
    "gn:country_code":"PL",
    "gn:dem":149,
    "gn:feature_class":"P",
    "gn:feature_code":"PPL",
    "gn:name":"Jedlnia",
    "gn:population":0,
    "gn:timezone":"Europe/Warsaw",
    "iso:country":"PL",
    "wof:name":"Jedlnia",
    "wof:placetype":"locality"
},
  "geometry": {"coordinates":[21.36667000000001,51.46667],"type":"Point"}
}