{
  "type": "Feature",
  "properties": {
    "gn:admin1_code":"78.0",
    "gn:admin2_code":"1425.0",
    "gn:admin3_code":"142508.0",
    "gn:asciiname":"Jedlnia",
    "gn:country_code":"PL",
    "gn:dem":149,
    "gn:feature_class":"P",
    "gn:feature_code":"PPL",
    "gn:name":"Jedlnia",
    "gn:population":0,
    "gn:timezone":"Europe/Warsaw",
    "iso:country":"PL",
    "name:azb_x_preferred":[
        "\u06cc\u062f\u0644\u0646\u0642\u0627"
    ],
    "name:ceb_x_preferred":[
        "Jedlnia"
    ],
    "name:fas_x_preferred":[
        "\u06cc\u062f\u0644\u0646\u06af\u0627"
    ],
    "name:fra_x_preferred":[
        "Jedlnia"
    ],
    "name:nld_x_preferred":[
        "Jedlnia"
    ],
    "name:pol_x_preferred":[
        "Jedlnia"
    ],
    "name:ukr_x_preferred":[
        "\u0404\u0434\u043b\u044c\u043d\u044f"
    ],
    "wof:name":"Jedlnia",
    "wof:placetype":"locality"
},
  "geometry": {"coordinates":[21.36667000000001,51.46667],"type":"Point"}
}