{
  "type": "Feature",
  "properties": {
    "gn:admin1_code":"76.0",
    "gn:admin2_code":"802.0",
    "gn:admin3_code":"80205.0",
    "gn:asciiname":"Czarnowice",
    "gn:country_code":"PL",
    "gn:dem":48,
    "gn:feature_class":"P",
    "gn:feature_code":"PPL",
    "gn:name":"Czarnowice",
    "gn:population":0,
    "gn:timezone":"Europe/Warsaw",
    "iso:country":"PL",
    "name:azb_x_preferred":[
        "\u0686\u0627\u0631\u0646\u0648\u0648\u06cc\u062a\u0633\u0647"
    ],
    "name:ceb_x_preferred":[
        "Czarnowice"
    ],
    "name:fas_x_preferred":[
        "\u0686\u0627\u0631\u0646\u0648\u0648\u06cc\u062a\u0633\u0647"
    ],
    "name:fra_x_preferred":[
        "Czarnowice"
    ],
    "name:pol_x_preferred":[
        "Czarnowice"
    ],
    "name:ron_x_preferred":[
        "Czarnowice"
    ],
    "name:ukr_x_preferred":[
        "\u0427\u0430\u0440\u043d\u043e\u0432\u0456\u0446\u0435"
    ],
    "wof:name":"Czarnowice",
    "wof:placetype":"locality"
},
  "geometry": {"coordinates":[14.77058,51.90243],"type":"Point"}
}