{
  "type": "Feature",
  "properties": {
    "gn:admin1_code":"84.0",
    "gn:admin2_code":"2606.0",
    "gn:admin3_code":"260601.0",
    "gn:asciiname":"Piorkow",
    "gn:country_code":"PL",
    "gn:dem":331,
    "gn:feature_class":"P",
    "gn:feature_code":"PPL",
    "gn:name":"Pi\u00f3rk\u00f3w",
    "gn:population":0,
    "gn:timezone":"Europe/Warsaw",
    "iso:country":"PL",
    "name:ceb_x_preferred":[
        "Pi\u00f3rk\u00f3w"
    ],
    "name:pol_x_preferred":[
        "Pi\u00f3rk\u00f3w"
    ],
    "name:ukr_x_preferred":[
        "\u041f\u044e\u0440\u043a\u0443\u0432"
    ],
    "wof:name":"Piorkow",
    "wof:placetype":"locality"
},
  "geometry": {"coordinates":[21.15847,50.79698],"type":"Point"}
}