{
  "type": "Feature",
  "properties": {
    "gn:admin1_code":"81.0",
    "gn:admin2_code":"2009.0",
    "gn:admin3_code":"200903.0",
    "gn:asciiname":"Michnowce",
    "gn:country_code":"PL",
    "gn:dem":139,
    "gn:feature_class":"P",
    "gn:feature_code":"PPL",
    "gn:name":"Michnowce",
    "gn:population":0,
    "gn:timezone":"Europe/Warsaw",
    "iso:country":"PL",
    "name:lit_x_preferred":[
        "Michnovc\u0117"
    ],
    "name:pol_x_preferred":[
        "Michnowce"
    ],
    "name:ukr_x_preferred":[
        "\u041c\u0456\u0445\u043d\u043e\u0432\u0446\u0435"
    ],
    "wof:name":"Michnowce",
    "wof:placetype":"locality"
},
  "geometry": {"coordinates":[23.27601,54.13782],"type":"Point"}
}