{
  "type": "Feature",
  "properties": {
    "gn:admin1_code":"78.0",
    "gn:admin2_code":"1426.0",
    "gn:admin3_code":"142609.0",
    "gn:asciiname":"Zelkow",
    "gn:country_code":"PL",
    "gn:dem":162,
    "gn:feature_class":"P",
    "gn:feature_code":"PPL",
    "gn:name":"\u017belk\u00f3w",
    "gn:population":0,
    "gn:timezone":"Europe/Warsaw",
    "iso:country":"PL",
    "name:fra_x_preferred":[
        "\u017belk\u00f3w"
    ],
    "name:pol_x_preferred":[
        "\u017belk\u00f3w"
    ],
    "name:szl_x_preferred":[
        "\u017belk\u016fw"
    ],
    "name:ukr_x_preferred":[
        "\u0416\u0435\u043b\u044c\u043a\u0443\u0432"
    ],
    "wof:name":"Zelkow",
    "wof:placetype":"locality"
},
  "geometry": {"coordinates":[22.18646,52.14123],"type":"Point"}
}