{
  "type": "Feature",
  "properties": {
    "gn:admin1_code":"86.0",
    "gn:admin2_code":"3010.0",
    "gn:admin3_code":"301002.0",
    "gn:asciiname":"Wycinki",
    "gn:country_code":"PL",
    "gn:dem":99,
    "gn:feature_class":"P",
    "gn:feature_code":"PPL",
    "gn:name":"Wycinki",
    "gn:population":0,
    "gn:timezone":"Europe/Warsaw",
    "iso:country":"PL",
    "name:fra_x_preferred":[
        "Wycinki"
    ],
    "name:pol_x_preferred":[
        "Wycinki"
    ],
    "name:ukr_x_preferred":[
        "\u0412\u0438\u0446\u0438\u043d\u043a\u0456"
    ],
    "wof:name":"Wycinki",
    "wof:placetype":"locality"
},
  "geometry": {"coordinates":[18.04572000000001,52.08267],"type":"Point"}
}