{
  "type": "Feature",
  "properties": {
    "gn:country":"PL",
    "gn:fcode":"PPLA3",
    "gn:population":1000,
    "iso:country":"PL",
    "name:azb_x_preferred":[
        "\u062f\u0648\u0648\u062a\u0648\u0648"
    ],
    "name:ceb_x_preferred":[
        "D\u0142ut\u00f3w"
    ],
    "name:deu_x_preferred":[
        "D\u0142ut\u00f3w"
    ],
    "name:fas_x_preferred":[
        "\u062f\u0648\u0648\u062a\u0648\u0648"
    ],
    "name:nld_x_preferred":[
        "D\u0142ut\u00f3w"
    ],
    "name:pol_x_preferred":[
        "D\u0142ut\u00f3w"
    ],
    "name:ukr_x_preferred":[
        "\u0414\u043b\u0443\u0442\u0443\u0432"
    ],
    "qs_pg:aaroncc":"PL",
    "qs_pg:gn_country":"PL",
    "qs_pg:gn_fcode":"PPLA3",
    "qs_pg:gn_pop":1000,
    "qs_pg:name":"D\u0142ut\u00f3w",
    "qs_pg:name_adm0":"Polska",
    "qs_pg:name_adm1":"\u0141\u00f3dzkie",
    "qs_pg:photos":11,
    "qs_pg:photos_1k":2,
    "qs_pg:photos_9k":1,
    "qs_pg:photos_9r":1,
    "qs_pg:photos_all":11,
    "qs_pg:photos_sr":1,
    "qs_pg:pop_sr":2,
    "qs_pg:qs_pg_placetype":"localadmin",
    "qs_pg:qs_pg_placetype_gp":"LocalAdmin",
    "qs_pg:woe_adm0":23424923,
    "woe:adm0_id":23424923,
    "woe:name_adm0":"Polska",
    "woe:name_adm1":"\u0141\u00f3dzkie",
    "woe:placetype":"LocalAdmin",
    "wof:name":"D\u0142ut\u00f3w",
    "wof:placetype":"localadmin",
    "wof:population":1000
},
  "geometry": {"coordinates":[19.39198,51.55936],"type":"Point"}
}