{
  "type": "Feature",
  "properties": {
    "gn:admin1_code":"72.0",
    "gn:admin2_code":"205.0",
    "gn:admin3_code":"20506.0",
    "gn:asciiname":"Pawlowice Wielkie",
    "gn:country_code":"PL",
    "gn:dem":157,
    "gn:feature_class":"P",
    "gn:feature_code":"PPL",
    "gn:name":"Paw\u0142owice Wielkie",
    "gn:population":0,
    "gn:timezone":"Europe/Warsaw",
    "iso:country":"PL",
    "name:pol_x_preferred":[
        "Paw\u0142owice Wielkie"
    ],
    "name:ukr_x_preferred":[
        "\u041f\u0430\u0432\u043b\u043e\u0432\u0456\u0446\u0435-\u0412\u0435\u043b\u0438\u043a\u0456"
    ],
    "wof:name":"Pawlowice Wielkie",
    "wof:placetype":"locality"
},
  "geometry": {"coordinates":[16.27285,51.10566],"type":"Point"}
}