{
  "type": "Feature",
  "properties": {
    "gn:admin1_code":"72.0",
    "gn:admin2_code":"205.0",
    "gn:admin3_code":"20506.0",
    "gn:asciiname":"Pawlowice Wielkie",
    "gn:country_code":"PL",
    "gn:dem":157,
    "gn:feature_class":"P",
    "gn:feature_code":"PPL",
    "gn:name":"Paw\u0142owice Wielkie",
    "gn:population":0,
    "gn:timezone":"Europe/Warsaw",
    "iso:country":"PL",
    "name:und_x_variant":[
        "Paw\u0142owice Wielkie"
    ],
    "wof:name":"Pawlowice Wielkie",
    "wof:placetype":"locality"
},
  "geometry": {"coordinates":[16.27285,51.10566],"type":"Point"}
}