{
  "type": "Feature",
  "properties": {
    "gn:country":"PL",
    "gn:fcode":"PPL",
    "gn:population":632,
    "iso:country":"PL",
    "name:azb_x_preferred":[
        "\u0642\u06cc\u0628\u0647"
    ],
    "name:ceb_x_preferred":[
        "Giby"
    ],
    "name:eng_x_preferred":[
        "Giby"
    ],
    "name:fas_x_preferred":[
        "\u06af\u06cc\u0628\u0647"
    ],
    "name:fra_x_preferred":[
        "Giby"
    ],
    "name:lit_x_preferred":[
        "Gibai"
    ],
    "name:nld_x_preferred":[
        "Giby"
    ],
    "name:pol_x_preferred":[
        "Giby"
    ],
    "name:rus_x_preferred":[
        "\u0413\u0438\u0431\u044b"
    ],
    "name:ukr_x_preferred":[
        "\u0490\u0456\u0431\u0438"
    ],
    "qs_pg:aaroncc":"PL",
    "qs_pg:gn_country":"PL",
    "qs_pg:gn_fcode":"PPL",
    "qs_pg:gn_pop":632,
    "qs_pg:name":"Giby",
    "qs_pg:photos_9r":0,
    "qs_pg:photos_sr":0,
    "qs_pg:pop_sr":2,
    "qs_pg:qs_pg_placetype":"locality",
    "wof:name":"Giby",
    "wof:placetype":"locality",
    "wof:population":632
},
  "geometry": {"coordinates":[23.35642,54.04256],"type":"Point"}
}