{
  "type": "Feature",
  "properties": {
    "gn:admin1_code":"75.0",
    "gn:admin2_code":"607.0",
    "gn:admin3_code":"60707.0",
    "gn:asciiname":"Agatowka",
    "gn:country_code":"PL",
    "gn:dem":221,
    "gn:feature_class":"P",
    "gn:feature_code":"PPL",
    "gn:name":"Agat\u00f3wka",
    "gn:population":0,
    "gn:timezone":"Europe/Warsaw",
    "iso:country":"PL",
    "name:azb_x_preferred":[
        "\u0627\u0642\u0627\u062a\u0648\u06a9\u0627"
    ],
    "name:ceb_x_preferred":[
        "Agat\u00f3wka"
    ],
    "name:fas_x_preferred":[
        "\u0627\u06af\u0627\u062a\u0648\u06a9\u0627"
    ],
    "name:fra_x_preferred":[
        "Agat\u00f3wka"
    ],
    "name:pol_x_preferred":[
        "Agat\u00f3wka"
    ],
    "name:srp_x_preferred":[
        "\u0410\u0433\u0430\u0442\u043e\u0432\u043a\u0430"
    ],
    "name:ukr_x_preferred":[
        "\u0410\u0491\u0430\u0442\u0443\u0432\u043a\u0430"
    ],
    "wof:name":"Agatowka",
    "wof:placetype":"locality"
},
  "geometry": {"coordinates":[22.07771,50.83522],"type":"Point"}
}