{
  "type": "Feature",
  "properties": {
    "gn:admin1_code":"78.0",
    "gn:admin2_code":"1419.0",
    "gn:admin3_code":"141911.0",
    "gn:asciiname":"Wymysle Polskie",
    "gn:country_code":"PL",
    "gn:dem":65,
    "gn:feature_class":"P",
    "gn:feature_code":"PPL",
    "gn:name":"Wymy\u015ble Polskie",
    "gn:population":0,
    "gn:timezone":"Europe/Warsaw",
    "iso:country":"PL",
    "name:fra_x_preferred":[
        "Wymy\u015ble Polskie"
    ],
    "name:pol_x_preferred":[
        "Wymy\u015ble Polskie"
    ],
    "name:ukr_x_preferred":[
        "\u0412\u0438\u043c\u0438\u0441\u044c\u043b\u0435-\u041f\u043e\u043b\u044c\u0441\u044c\u043a\u0435"
    ],
    "wof:name":"Wymysle Polskie",
    "wof:placetype":"locality"
},
  "geometry": {"coordinates":[19.8444,52.40682],"type":"Point"}
}