{
  "type": "Feature",
  "properties": {
    "gn:admin1_code":"81.0",
    "gn:admin2_code":"2002.0",
    "gn:admin3_code":"200213.0",
    "gn:asciiname":"Usowicze",
    "gn:country_code":"PL",
    "gn:dem":125,
    "gn:feature_class":"P",
    "gn:feature_code":"PPL",
    "gn:name":"Usowicze",
    "gn:population":0,
    "gn:timezone":"Europe/Warsaw",
    "iso:country":"PL",
    "name:lit_x_preferred":[
        "Osovi\u010d\u0117"
    ],
    "name:pol_x_preferred":[
        "Osowicze"
    ],
    "name:ukr_x_preferred":[
        "\u041e\u0441\u043e\u0432\u0456\u0447\u0435"
    ],
    "name:und_x_variant":[
        "Osowicze",
        "Usowicze"
    ],
    "wof:name":"Usowicze",
    "wof:placetype":"locality"
},
  "geometry": {"coordinates":[23.126,53.18072],"type":"Point"}
}