{
  "type": "Feature",
  "properties": {
    "gn:admin1_code":"80.0",
    "gn:admin2_code":"1818.0",
    "gn:admin3_code":"181801.0",
    "gn:asciiname":"Plawo",
    "gn:country_code":"PL",
    "gn:dem":164,
    "gn:feature_class":"P",
    "gn:feature_code":"PPL",
    "gn:name":"P\u0142awo",
    "gn:population":0,
    "gn:timezone":"Europe/Warsaw",
    "iso:country":"PL",
    "wof:name":"Plawo",
    "wof:placetype":"neighbourhood"
},
  "geometry": {"coordinates":[22.07277,50.56994],"type":"Point"}
}