{
  "type": "Feature",
  "properties": {
    "gn:admin1_code":"86.0",
    "gn:admin2_code":"3030.0",
    "gn:admin3_code":"303005.0",
    "gn:asciiname":"Gutowo Male",
    "gn:country_code":"PL",
    "gn:dem":104,
    "gn:feature_class":"P",
    "gn:feature_code":"PPL",
    "gn:name":"Gutowo Ma\u0142e",
    "gn:population":0,
    "gn:timezone":"Europe/Warsaw",
    "iso:country":"PL",
    "name:und_x_variant":[
        "Gutowo Ma\u0142e"
    ],
    "wof:name":"Gutowo Male",
    "wof:placetype":"locality"
},
  "geometry": {"coordinates":[17.61028,52.34066],"type":"Point"}
}