{
  "type": "Feature",
  "properties": {
    "gn:admin1_code":"86.0",
    "gn:admin2_code":"3030.0",
    "gn:admin3_code":"303005.0",
    "gn:asciiname":"Gutowo Male",
    "gn:country_code":"PL",
    "gn:dem":104,
    "gn:feature_class":"P",
    "gn:feature_code":"PPL",
    "gn:name":"Gutowo Ma\u0142e",
    "gn:population":0,
    "gn:timezone":"Europe/Warsaw",
    "iso:country":"PL",
    "name:azb_x_preferred":[
        "\u0642\u0648\u062a\u0648\u0648\u0648 \u0645\u0627\u0648\u0647"
    ],
    "name:fas_x_preferred":[
        "\u06af\u0648\u062a\u0648\u0648\u0648 \u0645\u0627\u0648\u0647"
    ],
    "name:fra_x_preferred":[
        "Gutowo Ma\u0142e"
    ],
    "name:pol_x_preferred":[
        "Gutowo Ma\u0142e"
    ],
    "name:ukr_x_preferred":[
        "\u0490\u0443\u0442\u043e\u0432\u043e-\u041c\u0430\u043b\u0435"
    ],
    "wof:name":"Gutowo Male",
    "wof:placetype":"locality"
},
  "geometry": {"coordinates":[17.61028,52.34066],"type":"Point"}
}