{
  "type": "Feature",
  "properties": {
    "gn:admin1_code":"78.0",
    "gn:admin2_code":"1411.0",
    "gn:admin3_code":"141105.0",
    "gn:asciiname":"Sadykierz",
    "gn:country_code":"PL",
    "gn:dem":100,
    "gn:feature_class":"P",
    "gn:feature_code":"PPL",
    "gn:name":"Sadykierz",
    "gn:population":0,
    "gn:timezone":"Europe/Warsaw",
    "iso:country":"PL",
    "name:fra_x_preferred":[
        "Sadykierz"
    ],
    "name:pol_x_preferred":[
        "Sadykierz"
    ],
    "name:ukr_x_preferred":[
        "\u0421\u0430\u0434\u0438\u043a\u0435\u0436"
    ],
    "wof:name":"Sadykierz",
    "wof:placetype":"locality"
},
  "geometry": {"coordinates":[21.44514,52.98276],"type":"Point"}
}