{
  "type": "Feature",
  "properties": {
    "gn:admin1_code":"72.0",
    "gn:admin2_code":"204.0",
    "gn:admin3_code":"20404.0",
    "gn:asciiname":"Unislawice",
    "gn:country_code":"PL",
    "gn:dem":87,
    "gn:feature_class":"P",
    "gn:feature_code":"PPL",
    "gn:name":"Unis\u0142awice",
    "gn:population":0,
    "gn:timezone":"Europe/Warsaw",
    "iso:country":"PL",
    "name:pol_x_preferred":[
        "Unis\u0142awice"
    ],
    "name:und_x_variant":[
        "Wilhelmsbruch",
        "Unis\u0142awice"
    ],
    "wof:name":"Unislawice",
    "wof:placetype":"locality"
},
  "geometry": {"coordinates":[16.78533,51.53298],"type":"Point"}
}