{
  "type": "Feature",
  "properties": {
    "gn:admin1_code":"81.0",
    "gn:admin2_code":"2014.0",
    "gn:admin3_code":"201403.0",
    "gn:asciiname":"Ozarki-Olszanka",
    "gn:country_code":"PL",
    "gn:dem":111,
    "gn:feature_class":"P",
    "gn:feature_code":"PPL",
    "gn:name":"O\u017carki-Olszanka",
    "gn:population":0,
    "gn:timezone":"Europe/Warsaw",
    "iso:country":"PL",
    "name:lit_x_preferred":[
        "O\u017earki Ol\u0161anka"
    ],
    "name:pol_x_preferred":[
        "O\u017carki-Olszanka"
    ],
    "name:ukr_x_preferred":[
        "\u041e\u0436\u0430\u0440\u043a\u0456-\u041e\u043b\u044c\u0448\u0430\u043d\u043a\u0430"
    ],
    "name:und_x_variant":[
        "O\u017carki"
    ],
    "wof:name":"Ozarki-Olszanka",
    "wof:placetype":"locality"
},
  "geometry": {"coordinates":[22.46392,53.11005],"type":"Point"}
}