{
  "type": "Feature",
  "properties": {
    "gn:admin1_code":"75.0",
    "gn:admin2_code":"603.0",
    "gn:admin3_code":"60311.0",
    "gn:asciiname":"Jankowice",
    "gn:country_code":"PL",
    "gn:dem":208,
    "gn:feature_class":"P",
    "gn:feature_code":"PPL",
    "gn:name":"Jankowice",
    "gn:population":0,
    "gn:timezone":"Europe/Warsaw",
    "iso:country":"PL",
    "name:und_x_variant":[
        "Kolonia Jankowice",
        "Jankowice"
    ],
    "wof:name":"Jankowice",
    "wof:placetype":"locality"
},
  "geometry": {"coordinates":[23.30017,51.1702],"type":"Point"}
}