{
  "type": "Feature",
  "properties": {
    "gn:admin1_code":"87.0",
    "gn:admin2_code":"3213.0",
    "gn:admin3_code":"321305.0",
    "gn:asciiname":"Gorsko",
    "gn:country_code":"PL",
    "gn:dem":8,
    "gn:feature_class":"P",
    "gn:feature_code":"PPL",
    "gn:name":"G\u00f3rsko",
    "gn:population":0,
    "gn:timezone":"Europe/Warsaw",
    "iso:country":"PL",
    "name:deu_x_preferred":[
        "G\u00f3rsko"
    ],
    "name:pol_x_preferred":[
        "G\u00f3rsko"
    ],
    "name:ukr_x_preferred":[
        "\u0490\u0443\u0440\u0441\u044c\u043a\u043e"
    ],
    "name:und_x_variant":[
        "G\u00f3rsko"
    ],
    "name:vie_x_preferred":[
        "G\u00f3rsko"
    ],
    "wof:name":"Gorsko",
    "wof:placetype":"locality"
},
  "geometry": {"coordinates":[16.67984,54.53391],"type":"Point"}
}