{
  "type": "Feature",
  "properties": {
    "gn:admin1_code":"78.0",
    "gn:admin2_code":"1406.0",
    "gn:admin3_code":"140601.0",
    "gn:asciiname":"Bodzew",
    "gn:country_code":"PL",
    "gn:dem":173,
    "gn:feature_class":"P",
    "gn:feature_code":"PPL",
    "gn:name":"Bodzew",
    "gn:population":0,
    "gn:timezone":"Europe/Warsaw",
    "iso:country":"PL",
    "name:fra_x_preferred":[
        "Bodzew"
    ],
    "name:pol_x_preferred":[
        "Bodzew"
    ],
    "name:ukr_x_preferred":[
        "\u0411\u043e\u0434\u0437\u0435\u0432"
    ],
    "wof:name":"Bodzew",
    "wof:placetype":"locality"
},
  "geometry": {"coordinates":[20.81385,51.79382],"type":"Point"}
}