{
  "type": "Feature",
  "properties": {
    "gn:admin1_code":"78.0",
    "gn:admin2_code":"1426.0",
    "gn:admin3_code":"142606.0",
    "gn:asciiname":"Leczycki",
    "gn:country_code":"PL",
    "gn:dem":174,
    "gn:feature_class":"P",
    "gn:feature_code":"PPL",
    "gn:name":"\u0141\u0119czycki",
    "gn:population":0,
    "gn:timezone":"Europe/Warsaw",
    "iso:country":"PL",
    "name:azb_x_preferred":[
        "\u0648\u0646\u0686\u062a\u0633\u06a9\u06cc"
    ],
    "name:ceb_x_preferred":[
        "\u0141\u0119czycki"
    ],
    "name:fas_x_preferred":[
        "\u0648\u0646\u0686\u062a\u0633\u06a9\u06cc"
    ],
    "name:fra_x_preferred":[
        "\u0141\u0119czycki"
    ],
    "name:lit_x_preferred":[
        "Len\u010dickai"
    ],
    "name:pol_x_preferred":[
        "\u0141\u0119czycki"
    ],
    "name:szl_x_preferred":[
        "\u0141ynczycki"
    ],
    "name:ukr_x_preferred":[
        "\u041b\u0435\u043d\u0447\u0438\u0446\u044c\u043a\u0438\u0439"
    ],
    "name:vie_x_preferred":[
        "\u0141\u0119czycki"
    ],
    "wof:name":"Leczycki",
    "wof:placetype":"locality"
},
  "geometry": {"coordinates":[22.51313,52.28769000000001],"type":"Point"}
}