{
  "type": "Feature",
  "properties": {
    "gn:admin1_code":"84.0",
    "gn:admin2_code":"2604.0",
    "gn:admin3_code":"260401.0",
    "gn:asciiname":"Porabki",
    "gn:country_code":"PL",
    "gn:dem":324,
    "gn:feature_class":"P",
    "gn:feature_code":"PPL",
    "gn:name":"Por\u0105bki",
    "gn:population":0,
    "gn:timezone":"Europe/Warsaw",
    "iso:country":"PL",
    "wof:name":"Porabki",
    "wof:placetype":"locality"
},
  "geometry": {"coordinates":[20.89362,50.86629],"type":"Point"}
}