{
  "type": "Feature",
  "properties": {
    "iso:country":"PL",
    "name:ceb_x_preferred":[
        "Bielice"
    ],
    "name:deu_x_preferred":[
        "Bielice"
    ],
    "name:fra_x_preferred":[
        "Bielice"
    ],
    "name:nld_x_preferred":[
        "Bielice"
    ],
    "name:pol_x_preferred":[
        "Bielice"
    ],
    "name:ukr_x_preferred":[
        "\u0411\u0435\u043b\u0456\u0446\u0435"
    ],
    "wof:coterminous":[
        1125350383
    ],
    "wof:name":"Bielice",
    "wof:placetype":"locality"
},
  "geometry": {"coordinates":[14.7494035011546,53.1933761152332],"type":"Point"}
}