{
  "type": "Feature",
  "properties": {
    "iso:country":"PL",
    "name:pol_x_preferred":[
        "Bielice"
    ],
    "wof:name":"Bielice",
    "wof:placetype":"locality"
},
  "geometry": {"coordinates":[14.7494035011546,53.1933761152332],"type":"Point"}
}