{
  "type": "Feature",
  "properties": {
    "gn:admin1_code":"85.0",
    "gn:admin2_code":"2818.0",
    "gn:admin3_code":"281801.0",
    "gn:asciiname":"Jodlowka",
    "gn:country_code":"PL",
    "gn:dem":158,
    "gn:feature_class":"P",
    "gn:feature_code":"PPL",
    "gn:name":"Jod\u0142\u00f3wka",
    "gn:population":0,
    "gn:timezone":"Europe/Warsaw",
    "iso:country":"PL",
    "name:und_x_variant":[
        "Tannenberg",
        "Jod\u0142\u00f3wka"
    ],
    "wof:name":"Jodlowka",
    "wof:placetype":"locality"
},
  "geometry": {"coordinates":[22.03333,54.21666999999999],"type":"Point"}
}