{
  "type": "Feature",
  "properties": {
    "gn:admin1_code":"75.0",
    "gn:admin2_code":"608.0",
    "gn:admin3_code":"60807.0",
    "gn:asciiname":"Skrobow",
    "gn:country_code":"PL",
    "gn:dem":153,
    "gn:feature_class":"P",
    "gn:feature_code":"PPL",
    "gn:name":"Skrob\u00f3w",
    "gn:population":0,
    "gn:timezone":"Europe/Warsaw",
    "iso:country":"PL",
    "name:fra_x_preferred":[
        "Skrob\u00f3w"
    ],
    "name:pol_x_preferred":[
        "Skrob\u00f3w"
    ],
    "name:ukr_x_preferred":[
        "\u0421\u043a\u0440\u043e\u0431\u0443\u0432"
    ],
    "name:und_x_variant":[
        "Strob\u00f3w",
        "Skrob\u00f3w",
        "Skrob\u00f3w-Kolonia"
    ],
    "wof:name":"Skrobow",
    "wof:placetype":"locality"
},
  "geometry": {"coordinates":[22.54927,51.47234],"type":"Point"}
}