{
  "type": "Feature",
  "properties": {
    "gn:admin1_code":"75.0",
    "gn:admin2_code":"605.0",
    "gn:admin3_code":"60503.0",
    "gn:asciiname":"Kocudza Gorna",
    "gn:country_code":"PL",
    "gn:dem":269,
    "gn:feature_class":"P",
    "gn:feature_code":"PPL",
    "gn:name":"Kocudza G\u00f3rna",
    "gn:population":0,
    "gn:timezone":"Europe/Warsaw",
    "iso:country":"PL",
    "name:azb_x_preferred":[
        "\u06a9\u0648\u062a\u0633\u0648\u0632\u0627 \u0642\u0648\u0631\u0646\u0627"
    ],
    "name:fas_x_preferred":[
        "\u06a9\u0648\u062a\u0633\u0648\u0632\u0627 \u06af\u0648\u0631\u0646\u0627"
    ],
    "name:fra_x_preferred":[
        "Kocudza G\u00f3rna"
    ],
    "name:pol_x_preferred":[
        "Kocudza G\u00f3rna"
    ],
    "name:ukr_x_preferred":[
        "\u041a\u043e\u0446\u0443\u0434\u0437\u0430-\u0490\u0443\u0440\u043d\u0430"
    ],
    "wof:name":"Kocudza Gorna",
    "wof:placetype":"locality"
},
  "geometry": {"coordinates":[22.59597,50.71034],"type":"Point"}
}