{
  "type": "Feature",
  "properties": {
    "gn:admin1_code":"78.0",
    "gn:admin2_code":"1420.0",
    "gn:admin3_code":"142004.0",
    "gn:asciiname":"Nieborzyn",
    "gn:country_code":"PL",
    "gn:dem":127,
    "gn:feature_class":"P",
    "gn:feature_code":"PPL",
    "gn:name":"Nieborzyn",
    "gn:population":0,
    "gn:timezone":"Europe/Warsaw",
    "iso:country":"PL",
    "name:fra_x_preferred":[
        "Nieborzyn"
    ],
    "name:pol_x_preferred":[
        "Nieborzyn"
    ],
    "name:ukr_x_preferred":[
        "\u041d\u0435\u0431\u043e\u0436\u0438\u043d"
    ],
    "wof:name":"Nieborzyn",
    "wof:placetype":"locality"
},
  "geometry": {"coordinates":[20.33775,52.46929],"type":"Point"}
}