{
  "type": "Feature",
  "properties": {
    "gn:admin1_code":"78.0",
    "gn:admin2_code":"1429.0",
    "gn:admin3_code":"142909.0",
    "gn:asciiname":"Lebiedzie",
    "gn:country_code":"PL",
    "gn:dem":122,
    "gn:feature_class":"P",
    "gn:feature_code":"PPL",
    "gn:name":"Lebiedzie",
    "gn:population":0,
    "gn:timezone":"Europe/Warsaw",
    "iso:country":"PL",
    "name:azb_x_preferred":[
        "\u0644\u0628\u06cc\u062c\u0647"
    ],
    "name:fas_x_preferred":[
        "\u0644\u0628\u06cc\u062c\u0647"
    ],
    "name:fra_x_preferred":[
        "Lebiedzie"
    ],
    "name:lit_x_preferred":[
        "Lebiedziai"
    ],
    "name:pol_x_preferred":[
        "Lebiedzie"
    ],
    "name:szl_x_preferred":[
        "Lebjyd\u017ae"
    ],
    "name:ukr_x_preferred":[
        "\u041b\u0435\u0431\u0435\u0434\u0437\u0435"
    ],
    "wof:name":"Lebiedzie",
    "wof:placetype":"locality"
},
  "geometry": {"coordinates":[22.28971,52.58323000000001],"type":"Point"}
}