{
  "type": "Feature",
  "properties": {
    "gn:admin1_code":"74.0",
    "gn:admin2_code":"1009.0",
    "gn:admin3_code":"100902.0",
    "gn:asciiname":"Kule",
    "gn:country_code":"PL",
    "gn:dem":180,
    "gn:feature_class":"P",
    "gn:feature_code":"PPL",
    "gn:name":"Kule",
    "gn:population":0,
    "gn:timezone":"Europe/Warsaw",
    "iso:country":"PL",
    "name:fra_x_preferred":[
        "Kule"
    ],
    "name:pol_x_preferred":[
        "Kule"
    ],
    "name:ukr_x_preferred":[
        "\u041a\u0443\u043b\u0435"
    ],
    "wof:name":"Kule",
    "wof:placetype":"locality"
},
  "geometry": {"coordinates":[18.98858,51.24763],"type":"Point"}
}