{
  "type": "Feature",
  "properties": {
    "gn:admin1_code":"83.0",
    "gn:admin2_code":"2405.0",
    "gn:admin3_code":"240508.0",
    "gn:asciiname":"Zacharzowice",
    "gn:country_code":"PL",
    "gn:dem":265,
    "gn:feature_class":"P",
    "gn:feature_code":"PPL",
    "gn:name":"Zacharzowice",
    "gn:population":0,
    "gn:timezone":"Europe/Warsaw",
    "iso:country":"PL",
    "name:azb_x_preferred":[
        "\u0632\u0627\u062e\u0627\u0698\u0648\u0648\u06cc\u062a\u0633\u0647"
    ],
    "name:ceb_x_preferred":[
        "Zacharzowice"
    ],
    "name:ces_x_preferred":[
        "Zacharzowice"
    ],
    "name:deu_x_preferred":[
        "Zacharzowice"
    ],
    "name:fas_x_preferred":[
        "\u0632\u0627\u062e\u0627\u0698\u0648\u0648\u06cc\u062a\u0633\u0647"
    ],
    "name:pol_x_preferred":[
        "Zacharzowice"
    ],
    "name:ukr_x_preferred":[
        "\u0417\u0430\u0445\u0430\u0436\u043e\u0432\u0456\u0446\u0435"
    ],
    "name:urd_x_preferred":[
        "\u0632\u0686\u0631\u0632\u0648\u0648\u06a9\u06d2"
    ],
    "wof:name":"Zacharzowice",
    "wof:placetype":"locality"
},
  "geometry": {"coordinates":[18.60209,50.45073],"type":"Point"}
}