{
  "type": "Feature",
  "properties": {
    "gn:admin1_code":"83.0",
    "gn:admin2_code":"2405.0",
    "gn:admin3_code":"240508.0",
    "gn:asciiname":"Zacharzowice",
    "gn:country_code":"PL",
    "gn:dem":265,
    "gn:feature_class":"P",
    "gn:feature_code":"PPL",
    "gn:name":"Zacharzowice",
    "gn:population":0,
    "gn:timezone":"Europe/Warsaw",
    "iso:country":"PL",
    "wof:name":"Zacharzowice",
    "wof:placetype":"locality"
},
  "geometry": {"coordinates":[18.60209,50.45073],"type":"Point"}
}