{
  "type": "Feature",
  "properties": {
    "gn:admin1_code":"78.0",
    "gn:admin2_code":"1426.0",
    "gn:admin3_code":"142603.0",
    "gn:asciiname":"Rososz",
    "gn:cc2":"PL",
    "gn:country_code":"PL",
    "gn:dem":140,
    "gn:feature_class":"P",
    "gn:feature_code":"PPL",
    "gn:name":"Rososz",
    "gn:population":0,
    "gn:timezone":"Europe/Warsaw",
    "iso:country":"PL",
    "name:fra_x_preferred":[
        "Rososz"
    ],
    "name:pol_x_preferred":[
        "Rososz"
    ],
    "name:szl_x_preferred":[
        "Rososz"
    ],
    "name:und_x_variant":[
        "Rossosz"
    ],
    "wof:name":"Rososz",
    "wof:placetype":"locality"
},
  "geometry": {"coordinates":[22.00089,52.15877],"type":"Point"}
}