{
  "type": "Feature",
  "properties": {
    "gn:admin1_code":"74.0",
    "gn:admin2_code":"1002.0",
    "gn:admin3_code":"100209.0",
    "gn:asciiname":"Szczyt",
    "gn:country_code":"PL",
    "gn:dem":109,
    "gn:feature_class":"P",
    "gn:feature_code":"PPL",
    "gn:name":"Szczyt",
    "gn:population":0,
    "gn:timezone":"Europe/Warsaw",
    "iso:country":"PL",
    "name:fra_x_preferred":[
        "Szczyt"
    ],
    "name:pol_x_preferred":[
        "Szczyt"
    ],
    "name:ukr_x_preferred":[
        "\u0429\u0438\u0442"
    ],
    "wof:name":"Szczyt",
    "wof:placetype":"locality"
},
  "geometry": {"coordinates":[19.49507,52.2381],"type":"Point"}
}