{
  "type": "Feature",
  "properties": {
    "gn:admin1_code":"78.0",
    "gn:admin2_code":"1423.0",
    "gn:admin3_code":"142308.0",
    "gn:asciiname":"Romualdow",
    "gn:country_code":"PL",
    "gn:dem":169,
    "gn:feature_class":"P",
    "gn:feature_code":"PPL",
    "gn:name":"Romuald\u00f3w",
    "gn:population":0,
    "gn:timezone":"Europe/Warsaw",
    "iso:country":"PL",
    "name:fra_x_preferred":[
        "Romuald\u00f3w"
    ],
    "name:pol_x_preferred":[
        "Romuald\u00f3w"
    ],
    "name:ukr_x_preferred":[
        "\u0420\u043e\u043c\u0443\u0430\u043b\u044c\u0434\u0443\u0432"
    ],
    "wof:name":"Romualdow",
    "wof:placetype":"locality"
},
  "geometry": {"coordinates":[20.71515,51.38403],"type":"Point"}
}