{
  "type": "Feature",
  "properties": {
    "iso:country":"PL",
    "name:azb_x_preferred":[
        "\u062f\u0627\u0646\u0628\u0631\u0648\u0648\u0627 \u0698\u0644\u0648\u0646\u0627"
    ],
    "name:deu_x_preferred":[
        "D\u0105browa Zielona"
    ],
    "name:fas_x_preferred":[
        "\u062f\u0627\u0646\u0628\u0631\u0648\u0648\u0627 \u0698\u0644\u0648\u0646\u0627"
    ],
    "name:nld_x_preferred":[
        "D\u0105browa Zielona"
    ],
    "name:pol_x_preferred":[
        "D\u0105browa Zielona"
    ],
    "wof:coterminous":[
        1125399557
    ],
    "wof:name":"D\u0105browa Zielona",
    "wof:placetype":"locality"
},
  "geometry": {"coordinates":[19.5712844923572,50.8537837244428],"type":"Point"}
}