{
  "type": "Feature",
  "properties": {
    "gn:admin1_code":"85.0",
    "gn:admin2_code":"2816.0",
    "gn:admin3_code":"281604.0",
    "gn:asciiname":"Iwanowo",
    "gn:country_code":"PL",
    "gn:dem":125,
    "gn:feature_class":"P",
    "gn:feature_code":"PPL",
    "gn:name":"Iwanowo",
    "gn:population":0,
    "gn:timezone":"Europe/Warsaw",
    "iso:country":"PL",
    "name:deu_x_preferred":[
        "Iwanowo"
    ],
    "name:pol_x_preferred":[
        "Iwanowo"
    ],
    "name:und_x_variant":[
        "Iwanowen"
    ],
    "wof:name":"Iwanowo",
    "wof:placetype":"locality"
},
  "geometry": {"coordinates":[21.46698,53.68583],"type":"Point"}
}