{
  "type": "Feature",
  "properties": {
    "gn:admin1_code":"87.0",
    "gn:admin2_code":"3215.0",
    "gn:admin3_code":"321502.0",
    "gn:asciiname":"Ostropole",
    "gn:country_code":"PL",
    "gn:dem":186,
    "gn:feature_class":"P",
    "gn:feature_code":"PPL",
    "gn:name":"Ostropole",
    "gn:population":0,
    "gn:timezone":"Europe/Warsaw",
    "iso:country":"PL",
    "name:pol_x_preferred":[
        "Ostropole"
    ],
    "name:ukr_x_preferred":[
        "\u041e\u0441\u0442\u0440\u043e\u043f\u043e\u043b\u0435"
    ],
    "name:und_x_variant":[
        "Osterfelde",
        "Ostropole"
    ],
    "name:vie_x_preferred":[
        "Ostropole"
    ],
    "wof:name":"Ostropole",
    "wof:placetype":"locality"
},
  "geometry": {"coordinates":[16.42649,53.71716],"type":"Point"}
}