{
  "type": "Feature",
  "properties": {
    "gn:admin1_code":"80.0",
    "gn:admin2_code":"1805.0",
    "gn:admin3_code":"180507.0",
    "gn:asciiname":"Sadki",
    "gn:country_code":"PL",
    "gn:dem":287,
    "gn:feature_class":"P",
    "gn:feature_code":"PPL",
    "gn:name":"Sadki",
    "gn:population":0,
    "gn:timezone":"Europe/Warsaw",
    "iso:country":"PL",
    "name:pol_x_preferred":[
        "Sadki"
    ],
    "name:ukr_x_preferred":[
        "\u0421\u0430\u0434\u043a\u0456"
    ],
    "name:urd_x_preferred":[
        "\u0633\u0691\u06a9\u06cc"
    ],
    "wof:name":"Sadki",
    "wof:placetype":"locality"
},
  "geometry": {"coordinates":[21.56239,49.61827],"type":"Point"}
}