{
  "type": "Feature",
  "properties": {
    "gn:admin1_code":"78.0",
    "gn:admin2_code":"1429.0",
    "gn:admin3_code":"142904.0",
    "gn:asciiname":"Stara Jablonna Kolonia",
    "gn:country_code":"PL",
    "gn:dem":136,
    "gn:feature_class":"P",
    "gn:feature_code":"PPL",
    "gn:name":"Stara Jab\u0142onna Kolonia",
    "gn:population":0,
    "gn:timezone":"Europe/Warsaw",
    "iso:country":"PL",
    "wof:name":"Stara Jablonna Kolonia",
    "wof:placetype":"locality"
},
  "geometry": {"coordinates":[22.41052,52.48051],"type":"Point"}
}