{
  "type": "Feature",
  "properties": {
    "gn:admin1_code":"82.0",
    "gn:admin2_code":"2202.0",
    "gn:admin3_code":"220203.0",
    "gn:asciiname":"Chojniczki",
    "gn:country_code":"PL",
    "gn:dem":147,
    "gn:feature_class":"P",
    "gn:feature_code":"PPL",
    "gn:name":"Chojniczki",
    "gn:population":0,
    "gn:timezone":"Europe/Warsaw",
    "iso:country":"PL",
    "name:azb_x_preferred":[
        "\u062e\u0648\u06cc\u0646\u0642\u0686\u06a9\u06cc"
    ],
    "name:ceb_x_preferred":[
        "Chojniczki"
    ],
    "name:fas_x_preferred":[
        "\u062e\u0648\u06cc\u0646\u06af\u0686\u06a9\u06cc"
    ],
    "name:nld_x_preferred":[
        "Chojniczki"
    ],
    "name:pol_x_preferred":[
        "Chojniczki"
    ],
    "name:ukr_x_preferred":[
        "\u0425\u043e\u0439\u043d\u0456\u0447\u043a\u0456"
    ],
    "wof:name":"Chojniczki",
    "wof:placetype":"locality"
},
  "geometry": {"coordinates":[17.54345,53.7392],"type":"Point"}
}