{
  "type": "Feature",
  "properties": {
    "gn:admin1_code":"78.0",
    "gn:admin2_code":"1422.0",
    "gn:admin3_code":"142202.0",
    "gn:asciiname":"Opaleniec",
    "gn:country_code":"PL",
    "gn:dem":126,
    "gn:feature_class":"P",
    "gn:feature_code":"PPL",
    "gn:name":"Opaleniec",
    "gn:population":0,
    "gn:timezone":"Europe/Warsaw",
    "iso:country":"PL",
    "name:fra_x_preferred":[
        "Opaleniec"
    ],
    "name:pol_x_preferred":[
        "Opaleniec"
    ],
    "name:ukr_x_preferred":[
        "\u041e\u043f\u0430\u043b\u0435\u043d\u0435\u0446\u044c"
    ],
    "name:und_x_variant":[
        "Flammberg"
    ],
    "wof:name":"Opaleniec",
    "wof:placetype":"locality"
},
  "geometry": {"coordinates":[20.90939,53.28718000000001],"type":"Point"}
}