{
  "type": "Feature",
  "properties": {
    "gn:admin1_code":"80.0",
    "gn:admin2_code":"1803.0",
    "gn:admin3_code":"180304.0",
    "gn:asciiname":"Nagawczyna",
    "gn:country_code":"PL",
    "gn:dem":227,
    "gn:feature_class":"P",
    "gn:feature_code":"PPL",
    "gn:name":"Nagawczyna",
    "gn:population":0,
    "gn:timezone":"Europe/Warsaw",
    "iso:country":"PL",
    "name:ceb_x_preferred":[
        "Nagawczyna"
    ],
    "name:pol_x_preferred":[
        "Nagawczyna"
    ],
    "name:ukr_x_preferred":[
        "\u041d\u0430\u0491\u0430\u0432\u0447\u0438\u043d\u0430"
    ],
    "wof:name":"Nagawczyna",
    "wof:placetype":"locality"
},
  "geometry": {"coordinates":[21.46557,50.04931],"type":"Point"}
}