{
  "type": "Feature",
  "properties": {
    "gn:admin1_code":"85.0",
    "gn:admin2_code":"2810.0",
    "gn:admin3_code":"281005.0",
    "gn:asciiname":"Szarlaty",
    "gn:cc2":"PL",
    "gn:country_code":"PL",
    "gn:dem":148,
    "gn:feature_class":"P",
    "gn:feature_code":"PPL",
    "gn:name":"Szar\u0142aty",
    "gn:population":0,
    "gn:timezone":"Europe/Warsaw",
    "iso:country":"PL",
    "name:deu_x_preferred":[
        "Szar\u0142aty"
    ],
    "name:fra_x_preferred":[
        "Szar\u0142aty"
    ],
    "name:pol_x_preferred":[
        "Szar\u0142aty"
    ],
    "name:und_x_variant":[
        "Charlotten",
        "Szarloty"
    ],
    "wof:name":"Szarlaty",
    "wof:placetype":"locality"
},
  "geometry": {"coordinates":[21.13333,53.81667],"type":"Point"}
}