{
  "type": "Feature",
  "properties": {
    "gn:admin1_code":"78.0",
    "gn:admin2_code":"1435.0",
    "gn:admin3_code":"143505.0",
    "gn:asciiname":"Losinno",
    "gn:country_code":"PL",
    "gn:dem":106,
    "gn:feature_class":"P",
    "gn:feature_code":"PPL",
    "gn:name":"\u0141osinno",
    "gn:population":0,
    "gn:timezone":"Europe/Warsaw",
    "iso:country":"PL",
    "name:fra_x_preferred":[
        "\u0141osinno"
    ],
    "name:pol_x_preferred":[
        "\u0141osinno"
    ],
    "name:ukr_x_preferred":[
        "\u041b\u043e\u0441\u0456\u043d\u043d\u043e"
    ],
    "wof:name":"Losinno",
    "wof:placetype":"locality"
},
  "geometry": {"coordinates":[21.35968,52.61908],"type":"Point"}
}