{
  "type": "Feature",
  "properties": {
    "gn:admin1_code":"80.0",
    "gn:admin2_code":"1806.0",
    "gn:admin3_code":"180606.0",
    "gn:asciiname":"Sudoly",
    "gn:country_code":"PL",
    "gn:dem":183,
    "gn:feature_class":"P",
    "gn:feature_code":"PPL",
    "gn:name":"Sudo\u0142y",
    "gn:population":0,
    "gn:timezone":"Europe/Warsaw",
    "iso:country":"PL",
    "wof:name":"Sudoly",
    "wof:placetype":"locality"
},
  "geometry": {"coordinates":[21.89891,50.38322],"type":"Point"}
}