{
  "type": "Feature",
  "properties": {
    "gn:admin1_code":"73.0",
    "gn:admin2_code":"410.0",
    "gn:admin3_code":"41003.0",
    "gn:asciiname":"Michalin",
    "gn:country_code":"PL",
    "gn:dem":114,
    "gn:feature_class":"P",
    "gn:feature_code":"PPL",
    "gn:name":"Michalin",
    "gn:population":0,
    "gn:timezone":"Europe/Warsaw",
    "iso:country":"PL",
    "name:fra_x_preferred":[
        "Michalin"
    ],
    "name:pol_x_preferred":[
        "Michalin"
    ],
    "name:rus_x_preferred":[
        "\u041c\u0438\u0445\u0430\u043b\u0438\u043d"
    ],
    "name:ukr_x_preferred":[
        "\u041c\u0456\u0445\u0430\u043b\u0456\u043d"
    ],
    "wof:name":"Michalin",
    "wof:placetype":"locality"
},
  "geometry": {"coordinates":[17.69629,53.20268000000001],"type":"Point"}
}