{
  "type": "Feature",
  "properties": {
    "iso:country":"PL",
    "name:pol_x_preferred":[
        "Biegonice"
    ],
    "qs:gn_adm0_cc":"PL",
    "qs:gn_fcode":"PPLX",
    "qs:gn_local":763534,
    "qs:gn_nam_loc":"Nowy S\u0105cz, Nowy S\u0105cz, Ma\u0142opolskie, PL",
    "qs:gn_namadm1":"77",
    "qs:gn_name":"Biegonice",
    "qs:local_max":462,
    "qs:local_sum":462,
    "qs:localhoods":1,
    "qs:name":"Biegonice",
    "qs:name_adm0":"Polska",
    "qs:name_adm1":"Ma\u0142opolskie",
    "qs:name_adm2":"Nowy S\u0105cz",
    "qs:name_lau":"Nowy S\u0105cz",
    "qs:name_local":"Nowy S\u0105cz",
    "qs:photo_max":89,
    "qs:photo_sum":462,
    "qs:placetype":"Suburb",
    "qs:quad_count":43,
    "qs:woe_adm0":23424923,
    "qs:woe_adm1":12577940,
    "qs:woe_adm2":12591260,
    "qs:woe_lau":12618867,
    "qs:woe_local":509923,
    "qs:woe_ver":"7.10.0",
    "wof:lang":[
        "pol"
    ],
    "wof:name":"Biegonice",
    "wof:placetype":"neighbourhood"
},
  "geometry": {"coordinates":[20.682087,49.601624],"type":"Point"}
}