{
  "type": "Feature",
  "properties": {
    "gn:admin1_code":"81.0",
    "gn:admin2_code":"2012.0",
    "gn:admin3_code":"201206.0",
    "gn:asciiname":"Olszanka",
    "gn:country_code":"PL",
    "gn:dem":213,
    "gn:feature_class":"P",
    "gn:feature_code":"PPL",
    "gn:name":"Olszanka",
    "gn:population":0,
    "gn:timezone":"Europe/Warsaw",
    "iso:country":"PL",
    "wof:name":"Olszanka",
    "wof:placetype":"locality"
},
  "geometry": {"coordinates":[22.94712,54.35464],"type":"Point"}
}