{
  "type": "Feature",
  "properties": {
    "gn:admin1_code":"81.0",
    "gn:admin2_code":"2012.0",
    "gn:admin3_code":"201206.0",
    "gn:asciiname":"Olszanka",
    "gn:country_code":"PL",
    "gn:dem":213,
    "gn:feature_class":"P",
    "gn:feature_code":"PPL",
    "gn:name":"Olszanka",
    "gn:population":0,
    "gn:timezone":"Europe/Warsaw",
    "iso:country":"PL",
    "name:ceb_x_preferred":[
        "Olszanka"
    ],
    "name:deu_x_preferred":[
        "Olszanka"
    ],
    "name:fra_x_preferred":[
        "Olszanka"
    ],
    "name:hye_x_preferred":[
        "\u0555\u056c\u056b\u0577\u0561\u0576\u056f\u0561"
    ],
    "name:ita_x_preferred":[
        "Olszanka"
    ],
    "name:kaz_x_preferred":[
        "\u041e\u043b\u044c\u0448\u0430\u043d\u043a\u0430"
    ],
    "name:lit_x_preferred":[
        "Ol\u0161anka"
    ],
    "name:nld_x_preferred":[
        "Olszanka"
    ],
    "name:pol_x_preferred":[
        "Olszanka"
    ],
    "name:rus_x_preferred":[
        "\u041e\u043b\u044c\u0448\u0430\u043d\u043a\u0430"
    ],
    "name:ukr_x_preferred":[
        "\u041e\u043b\u044c\u0448\u0430\u043d\u043a\u0430"
    ],
    "wof:name":"Olszanka",
    "wof:placetype":"locality"
},
  "geometry": {"coordinates":[22.94712,54.35464],"type":"Point"}
}