{
  "type": "Feature",
  "properties": {
    "gn:population":2100,
    "iso:country":"PL",
    "name:ast_x_preferred":[
        "Wola Krzysztoporska"
    ],
    "name:azb_x_preferred":[
        "\u0648\u0648\u0644\u0627 \u06a9\u0698\u0634\u062a\u0648\u067e\u0648\u0631\u0633\u06a9\u0627"
    ],
    "name:deu_x_preferred":[
        "Wola Krzysztoporska"
    ],
    "name:eng_x_preferred":[
        "Wola Krzysztoporska"
    ],
    "name:fas_x_preferred":[
        "\u0648\u0648\u0644\u0627 \u06a9\u0698\u0634\u062a\u0648\u067e\u0648\u0631\u0633\u06a9\u0627"
    ],
    "name:fra_x_preferred":[
        "Wola Krzysztoporska"
    ],
    "name:nld_x_preferred":[
        "Wola Krzysztoporska"
    ],
    "name:pol_x_preferred":[
        "Wola Krzysztoporska"
    ],
    "name:rus_x_preferred":[
        "\u0412\u043e\u043b\u044f-\u041a\u0448\u0438\u0448\u0442\u043e\u043f\u043e\u0440\u0441\u043a\u0430"
    ],
    "name:swe_x_preferred":[
        "Wola Krzysztoporska"
    ],
    "name:ukr_x_preferred":[
        "\u0412\u043e\u043b\u044f-\u041a\u0448\u0438\u0448\u0442\u043e\u043f\u043e\u0440\u0441\u044c\u043a\u0430"
    ],
    "qs:a0":"Rzeczpospolita Polska",
    "qs:a1":"*L\u00f3dzkie",
    "qs:a1r":"0",
    "qs:a2":"Piotrkowski",
    "qs:adm0":"Rzeczpospolita Polska",
    "qs:la":"Wola Krzysztoporska",
    "qs:la_lc":"*PL1010102",
    "qs:level":"locality",
    "qs:loc":"Wola Krzysztoporska",
    "qs:loc_alt":"Wola Krzysztoporska",
    "qs:pop":0,
    "qs:type":"rural point-in-poly",
    "wd:wordcount":94,
    "wof:name":"Wola Krzysztoporska",
    "wof:placetype":"locality",
    "wof:population":2100
},
  "geometry": {"coordinates":[19.5637515016324,51.371497899064],"type":"Point"}
}