{
  "type": "Feature",
  "properties": {
    "gn:admin1_code":"81.0",
    "gn:admin2_code":"2010.0",
    "gn:admin3_code":"201008.0",
    "gn:asciiname":"Leszczka Mala",
    "gn:country_code":"PL",
    "gn:dem":126,
    "gn:feature_class":"P",
    "gn:feature_code":"PPL",
    "gn:name":"Leszczka Ma\u0142a",
    "gn:population":0,
    "gn:timezone":"Europe/Warsaw",
    "iso:country":"PL",
    "name:und_x_variant":[
        "Leszczka Ma\u0142a"
    ],
    "wof:name":"Leszczka Mala",
    "wof:placetype":"locality"
},
  "geometry": {"coordinates":[22.54706,52.57344000000001],"type":"Point"}
}