{
  "type": "Feature",
  "properties": {
    "gn:admin1_code":"81.0",
    "gn:admin2_code":"2010.0",
    "gn:admin3_code":"201008.0",
    "gn:asciiname":"Leszczka Mala",
    "gn:country_code":"PL",
    "gn:dem":126,
    "gn:feature_class":"P",
    "gn:feature_code":"PPL",
    "gn:name":"Leszczka Ma\u0142a",
    "gn:population":0,
    "gn:timezone":"Europe/Warsaw",
    "iso:country":"PL",
    "name:azb_x_preferred":[
        "\u0644\u0634\u0686\u06a9\u0627 \u0645\u0627\u0648\u0627"
    ],
    "name:fas_x_preferred":[
        "\u0644\u0634\u0686\u06a9\u0627 \u0645\u0627\u0648\u0627"
    ],
    "name:fra_x_preferred":[
        "Leszczka Ma\u0142a"
    ],
    "name:lit_x_preferred":[
        "Le\u0161\u010dka Mala"
    ],
    "name:pol_x_preferred":[
        "Leszczka Ma\u0142a"
    ],
    "name:ukr_x_preferred":[
        "\u041b\u0435\u0449\u043a\u0430-\u041c\u0430\u043b\u0430"
    ],
    "name:und_x_variant":[
        "Leszczka Ma\u0142a"
    ],
    "wof:name":"Leszczka Mala",
    "wof:placetype":"locality"
},
  "geometry": {"coordinates":[22.54706,52.57344000000001],"type":"Point"}
}