{
  "type": "Feature",
  "properties": {
    "gn:admin1_code":"86.0",
    "gn:admin2_code":"3018.0",
    "gn:admin3_code":"301801.0",
    "gn:asciiname":"Luszczki",
    "gn:country_code":"PL",
    "gn:dem":152,
    "gn:feature_class":"P",
    "gn:feature_code":"PPL",
    "gn:name":"\u0141uszczki",
    "gn:population":0,
    "gn:timezone":"Europe/Warsaw",
    "iso:country":"PL",
    "wof:name":"Luszczki",
    "wof:placetype":"locality"
},
  "geometry": {"coordinates":[18.33967,51.52086],"type":"Point"}
}