{
  "type": "Feature",
  "properties": {
    "gn:admin1_code":"86.0",
    "gn:admin2_code":"3029.0",
    "gn:admin3_code":"302903.0",
    "gn:asciiname":"Mlynsko",
    "gn:country_code":"PL",
    "gn:dem":77,
    "gn:feature_class":"P",
    "gn:feature_code":"PPL",
    "gn:name":"M\u0142y\u0144sko",
    "gn:population":0,
    "gn:timezone":"Europe/Warsaw",
    "iso:country":"PL",
    "wof:name":"Mlynsko",
    "wof:placetype":"locality"
},
  "geometry": {"coordinates":[16.13332999999999,52.15],"type":"Point"}
}