{
  "type": "Feature",
  "properties": {
    "gn:gn_country":"PL",
    "gn:gn_fcode":"PPL",
    "gn:gn_pop":238,
    "gn:population":238,
    "iso:country":"PL",
    "name:ast_x_preferred":[
        "Zatwarnica"
    ],
    "name:ceb_x_preferred":[
        "Zatwarnica"
    ],
    "name:eng_x_preferred":[
        "Zatwarnica"
    ],
    "name:fra_x_preferred":[
        "Zatwarnica"
    ],
    "name:hun_x_preferred":[
        "Zatwarnica"
    ],
    "name:nld_x_preferred":[
        "Zatwarnica"
    ],
    "name:pol_x_preferred":[
        "Zatwarnica"
    ],
    "name:rue_x_preferred":[
        "\u0417\u0430\u0442\u0432\u0430\u0440\u043d\u0438\u0446\u044f"
    ],
    "name:ukr_x_preferred":[
        "\u0417\u0430\u0442\u0432\u0430\u0440\u043d\u0438\u0446\u044f"
    ],
    "qs_pg:aaroncc":"PL",
    "qs_pg:gn_country":"PL",
    "qs_pg:gn_fcode":"PPL",
    "qs_pg:gn_pop":238,
    "qs_pg:name":"Zatwarnica",
    "qs_pg:name_adm0":"Polska",
    "qs_pg:name_adm1":"Podkarpackie",
    "qs_pg:photos_9k":1,
    "qs_pg:photos_9r":2,
    "qs_pg:photos_all":60,
    "qs_pg:photos_sr":0,
    "qs_pg:pop_sr":2,
    "qs_pg:qs_pg_placetype":"locality",
    "qs_pg:qs_pg_placetype_gp":"Town",
    "qs_pg:woe_adm0":23424923,
    "woe:adm0_id":23424923,
    "woe:name_adm0":"Polska",
    "woe:name_adm1":"Podkarpackie",
    "woe:placetype":"Town",
    "wof:name":"Zatwarnica",
    "wof:placetype":"locality",
    "wof:population":238
},
  "geometry": {"coordinates":[22.5527,49.22657],"type":"Point"}
}