{
  "type": "Feature",
  "properties": {
    "gn:admin1_code":"87.0",
    "gn:admin2_code":"3206.0",
    "gn:admin3_code":"320602.0",
    "gn:asciiname":"Czachow",
    "gn:country_code":"PL",
    "gn:dem":83,
    "gn:feature_class":"P",
    "gn:feature_code":"PPL",
    "gn:name":"Czach\u00f3w",
    "gn:population":0,
    "gn:timezone":"Europe/Warsaw",
    "iso:country":"PL",
    "name:deu_x_preferred":[
        "Czach\u00f3w"
    ],
    "name:pol_x_preferred":[
        "Czach\u00f3w"
    ],
    "name:ukr_x_preferred":[
        "\u0427\u0430\u0445\u0443\u0432"
    ],
    "name:und_x_variant":[
        "Zachow"
    ],
    "wof:name":"Czachow",
    "wof:placetype":"locality"
},
  "geometry": {"coordinates":[14.26781,52.91139],"type":"Point"}
}