{
  "type": "Feature",
  "properties": {
    "gn:admin1_code":"78.0",
    "gn:admin2_code":"1407.0",
    "gn:admin3_code":"140702.0",
    "gn:asciiname":"Podmiescie",
    "gn:country_code":"PL",
    "gn:dem":127,
    "gn:feature_class":"P",
    "gn:feature_code":"PPL",
    "gn:name":"Podmie\u015bcie",
    "gn:population":0,
    "gn:timezone":"Europe/Warsaw",
    "iso:country":"PL",
    "name:fra_x_preferred":[
        "Podmie\u015bcie"
    ],
    "name:pol_x_preferred":[
        "Podmie\u015bcie"
    ],
    "name:ukr_x_preferred":[
        "\u041f\u043e\u0434\u043c\u0435\u0441\u044c\u0446\u0435"
    ],
    "wof:name":"Podmiescie",
    "wof:placetype":"locality"
},
  "geometry": {"coordinates":[21.30318,51.60613],"type":"Point"}
}