{
  "type": "Feature",
  "properties": {
    "gn:admin1_code":"86.0",
    "gn:admin2_code":"3003.0",
    "gn:admin3_code":"300303.0",
    "gn:asciiname":"Piekary",
    "gn:country_code":"PL",
    "gn:dem":118,
    "gn:feature_class":"P",
    "gn:feature_code":"PPL",
    "gn:name":"Piekary",
    "gn:population":0,
    "gn:timezone":"Europe/Warsaw",
    "iso:country":"PL",
    "name:fra_x_preferred":[
        "Piekary"
    ],
    "name:pol_x_preferred":[
        "Piekary"
    ],
    "name:ukr_x_preferred":[
        "\u041f\u0435\u043a\u0430\u0440\u0438"
    ],
    "wof:name":"Piekary",
    "wof:placetype":"locality"
},
  "geometry": {"coordinates":[17.54705,52.54028],"type":"Point"}
}