{
  "type": "Feature",
  "properties": {
    "gn:admin1_code":"78.0",
    "gn:admin2_code":"1406.0",
    "gn:admin3_code":"140608.0",
    "gn:asciiname":"Sacin",
    "gn:country_code":"PL",
    "gn:dem":152,
    "gn:feature_class":"P",
    "gn:feature_code":"PPL",
    "gn:name":"Sacin",
    "gn:population":0,
    "gn:timezone":"Europe/Warsaw",
    "iso:country":"PL",
    "name:fra_x_preferred":[
        "Sacin"
    ],
    "name:pol_x_preferred":[
        "Sacin"
    ],
    "name:ukr_x_preferred":[
        "\u0421\u0430\u0446\u0438\u043d"
    ],
    "name:urd_x_preferred":[
        "\u0633\u06a9\u06cc\u06ba"
    ],
    "wof:name":"Sacin",
    "wof:placetype":"locality"
},
  "geometry": {"coordinates":[20.56984,51.65264000000001],"type":"Point"}
}