{
  "type": "Feature",
  "properties": {
    "gn:admin1_code":"78.0",
    "gn:admin2_code":"1426.0",
    "gn:admin3_code":"142608.0",
    "gn:asciiname":"Opole Nowe",
    "gn:country_code":"PL",
    "gn:dem":160,
    "gn:feature_class":"P",
    "gn:feature_code":"PPL",
    "gn:name":"Opole Nowe",
    "gn:population":0,
    "gn:timezone":"Europe/Warsaw",
    "iso:country":"PL",
    "name:und_x_variant":[
        "Nowe Opole"
    ],
    "wof:name":"Opole Nowe",
    "wof:placetype":"locality"
},
  "geometry": {"coordinates":[22.18294,52.18025],"type":"Point"}
}