{
  "type": "Feature",
  "properties": {
    "gn:admin1_code":"78.0",
    "gn:admin2_code":"1426.0",
    "gn:admin3_code":"142608.0",
    "gn:asciiname":"Opole Nowe",
    "gn:country_code":"PL",
    "gn:dem":160,
    "gn:feature_class":"P",
    "gn:feature_code":"PPL",
    "gn:name":"Opole Nowe",
    "gn:population":0,
    "gn:timezone":"Europe/Warsaw",
    "iso:country":"PL",
    "name:azb_x_preferred":[
        "\u0646\u0648\u0648\u0647 \u0627\u0648\u067e\u0648\u0644\u0647"
    ],
    "name:fas_x_preferred":[
        "\u0646\u0648\u0648\u0647 \u0627\u0648\u067e\u0648\u0644\u0647"
    ],
    "name:fra_x_preferred":[
        "Nowe Opole"
    ],
    "name:nld_x_preferred":[
        "Nowe Opole"
    ],
    "name:pol_x_preferred":[
        "Nowe Opole"
    ],
    "name:szl_x_preferred":[
        "Nowe Uopole"
    ],
    "name:ukr_x_preferred":[
        "\u041d\u043e\u0432\u0435 \u041e\u043f\u043e\u043b\u0435"
    ],
    "name:und_x_variant":[
        "Nowe Opole"
    ],
    "wof:name":"Opole Nowe",
    "wof:placetype":"locality"
},
  "geometry": {"coordinates":[22.18294,52.18025],"type":"Point"}
}