{
  "type": "Feature",
  "properties": {
    "gn:admin1_code":"85.0",
    "gn:admin2_code":"2812.0",
    "gn:admin3_code":"281202.0",
    "gn:asciiname":"Sedzice",
    "gn:country_code":"PL",
    "gn:dem":85,
    "gn:feature_class":"P",
    "gn:feature_code":"PPL",
    "gn:name":"Sedzice",
    "gn:population":0,
    "gn:timezone":"Europe/Warsaw",
    "iso:country":"PL",
    "name:pol_x_preferred":[
        "S\u0119dzice"
    ],
    "name:ukr_x_preferred":[
        "\u0421\u0435\u043d\u0434\u0437\u0456\u0446\u0435"
    ],
    "name:vie_x_preferred":[
        "S\u0119dzice"
    ],
    "wof:name":"Sedzice",
    "wof:placetype":"locality"
},
  "geometry": {"coordinates":[19.31225,53.48672],"type":"Point"}
}