{
  "type": "Feature",
  "properties": {
    "gn:admin1_code":"74.0",
    "gn:admin2_code":"1007.0",
    "gn:admin3_code":"100703.0",
    "gn:asciiname":"Strzelce",
    "gn:country_code":"PL",
    "gn:dem":192,
    "gn:feature_class":"P",
    "gn:feature_code":"PPL",
    "gn:name":"Strzelce",
    "gn:population":0,
    "gn:timezone":"Europe/Warsaw",
    "iso:country":"PL",
    "name:fra_x_preferred":[
        "Strzelce"
    ],
    "name:pol_x_preferred":[
        "Strzelce"
    ],
    "name:ukr_x_preferred":[
        "\u0421\u0442\u0448\u0435\u043b\u044c\u0446\u0435"
    ],
    "wof:name":"Strzelce",
    "wof:placetype":"locality"
},
  "geometry": {"coordinates":[19.94036,51.3631],"type":"Point"}
}