{
  "type": "Feature",
  "properties": {
    "gn:admin1_code":"86.0",
    "gn:admin2_code":"3018.0",
    "gn:admin3_code":"301804.0",
    "gn:asciiname":"Smolarze",
    "gn:country_code":"PL",
    "gn:dem":180,
    "gn:feature_class":"P",
    "gn:feature_code":"PPL",
    "gn:name":"Smolarze",
    "gn:population":0,
    "gn:timezone":"Europe/Warsaw",
    "iso:country":"PL",
    "wof:name":"Smolarze",
    "wof:placetype":"locality"
},
  "geometry": {"coordinates":[17.8242,51.41531],"type":"Point"}
}