{
  "type": "Feature",
  "properties": {
    "gn:admin1_code":"75.0",
    "gn:admin2_code":"609.0",
    "gn:admin3_code":"60907.0",
    "gn:asciiname":"Dabrowica",
    "gn:country_code":"PL",
    "gn:dem":201,
    "gn:feature_class":"P",
    "gn:feature_code":"PPL",
    "gn:name":"D\u0105browica",
    "gn:population":0,
    "gn:timezone":"Europe/Warsaw",
    "iso:country":"PL",
    "wof:name":"Dabrowica",
    "wof:placetype":"locality"
},
  "geometry": {"coordinates":[22.46052,51.27083],"type":"Point"}
}