{
  "type": "Feature",
  "properties": {
    "gn:admin1_code":"75.0",
    "gn:admin2_code":"609.0",
    "gn:admin3_code":"60907.0",
    "gn:asciiname":"Dabrowica",
    "gn:country_code":"PL",
    "gn:dem":201,
    "gn:feature_class":"P",
    "gn:feature_code":"PPL",
    "gn:name":"D\u0105browica",
    "gn:population":0,
    "gn:timezone":"Europe/Warsaw",
    "iso:country":"PL",
    "name:azb_x_preferred":[
        "\u062f\u0627\u0646\u0628\u0631\u0648\u0648\u06cc\u062a\u0633\u0627"
    ],
    "name:ceb_x_preferred":[
        "D\u0105browica"
    ],
    "name:fas_x_preferred":[
        "\u062f\u0627\u0646\u0628\u0631\u0648\u0648\u06cc\u062a\u0633\u0627"
    ],
    "name:fra_x_preferred":[
        "D\u0105browica"
    ],
    "name:pol_x_preferred":[
        "D\u0105browica"
    ],
    "name:rus_x_preferred":[
        "\u0414\u043e\u043c\u0431\u0440\u043e\u0432\u0438\u0446\u0430"
    ],
    "name:ukr_x_preferred":[
        "\u0414\u043e\u043c\u0431\u0440\u043e\u0432\u0438\u0446\u044f"
    ],
    "wof:name":"Dabrowica",
    "wof:placetype":"locality"
},
  "geometry": {"coordinates":[22.46052,51.27083],"type":"Point"}
}