{
  "type": "Feature",
  "properties": {
    "gn:admin1_code":"87.0",
    "gn:admin2_code":"3203.0",
    "gn:admin3_code":"320304.0",
    "gn:asciiname":"Kosobudy",
    "gn:country_code":"PL",
    "gn:dem":145,
    "gn:feature_class":"P",
    "gn:feature_code":"PPL",
    "gn:name":"Kosobudy",
    "gn:population":0,
    "gn:timezone":"Europe/Warsaw",
    "iso:country":"PL",
    "name:pol_x_preferred":[
        "Kosobudy"
    ],
    "name:ukr_x_preferred":[
        "\u041a\u043e\u0441\u043e\u0431\u0443\u0434\u0438"
    ],
    "name:vie_x_preferred":[
        "Kosobudy"
    ],
    "wof:name":"Kosobudy",
    "wof:placetype":"locality"
},
  "geometry": {"coordinates":[15.93333,53.58333],"type":"Point"}
}