{
  "type": "Feature",
  "properties": {
    "gn:admin1_code":"78.0",
    "gn:admin2_code":"1413.0",
    "gn:admin3_code":"141306.0",
    "gn:asciiname":"Dabek",
    "gn:country_code":"PL",
    "gn:dem":139,
    "gn:feature_class":"P",
    "gn:feature_code":"PPL",
    "gn:name":"D\u0105bek",
    "gn:population":0,
    "gn:timezone":"Europe/Warsaw",
    "iso:country":"PL",
    "name:fra_x_preferred":[
        "D\u0105bek"
    ],
    "name:pol_x_preferred":[
        "D\u0105bek"
    ],
    "name:ukr_x_preferred":[
        "\u0414\u043e\u043c\u0431\u0435\u043a"
    ],
    "wof:name":"Dabek",
    "wof:placetype":"locality"
},
  "geometry": {"coordinates":[20.3655,53.01454],"type":"Point"}
}