{
  "type": "Feature",
  "properties": {
    "gn:admin1_code":"78.0",
    "gn:admin2_code":"1427.0",
    "gn:admin3_code":"142703.0",
    "gn:asciiname":"Malanowo Nowe",
    "gn:country_code":"PL",
    "gn:dem":106,
    "gn:feature_class":"P",
    "gn:feature_code":"PPL",
    "gn:name":"Malanowo Nowe",
    "gn:population":0,
    "gn:timezone":"Europe/Warsaw",
    "iso:country":"PL",
    "name:azb_x_preferred":[
        "\u0645\u0627\u0644\u0627\u0646\u0648\u0648\u0648 \u0646\u0648\u0648\u0647"
    ],
    "name:fas_x_preferred":[
        "\u0645\u0627\u0644\u0627\u0646\u0648\u0648\u0648 \u0646\u0648\u0648\u0647"
    ],
    "name:fra_x_preferred":[
        "Malanowo Nowe"
    ],
    "name:pol_x_preferred":[
        "Malanowo Nowe"
    ],
    "name:ukr_x_preferred":[
        "\u041c\u0430\u043b\u044f\u043d\u043e\u0432\u043e-\u041d\u043e\u0432\u0435"
    ],
    "wof:name":"Malanowo Nowe",
    "wof:placetype":"locality"
},
  "geometry": {"coordinates":[19.51807,52.80328000000001],"type":"Point"}
}