{
  "type": "Feature",
  "properties": {
    "gn:admin1_code":"78.0",
    "gn:admin2_code":"1427.0",
    "gn:admin3_code":"142703.0",
    "gn:asciiname":"Malanowo Nowe",
    "gn:country_code":"PL",
    "gn:dem":106,
    "gn:feature_class":"P",
    "gn:feature_code":"PPL",
    "gn:name":"Malanowo Nowe",
    "gn:population":0,
    "gn:timezone":"Europe/Warsaw",
    "iso:country":"PL",
    "wof:name":"Malanowo Nowe",
    "wof:placetype":"locality"
},
  "geometry": {"coordinates":[19.51807,52.80328000000001],"type":"Point"}
}