{
  "type": "Feature",
  "properties": {
    "gn:admin1_code":"86.0",
    "gn:admin2_code":"3013.0",
    "gn:admin3_code":"301302.0",
    "gn:asciiname":"Radomicko",
    "gn:country_code":"PL",
    "gn:dem":93,
    "gn:feature_class":"P",
    "gn:feature_code":"PPL",
    "gn:name":"Radomicko",
    "gn:population":0,
    "gn:timezone":"Europe/Warsaw",
    "iso:country":"PL",
    "name:ceb_x_preferred":[
        "Radomicko"
    ],
    "name:fra_x_preferred":[
        "Radomicko"
    ],
    "name:pol_x_preferred":[
        "Radomicko"
    ],
    "name:ukr_x_preferred":[
        "\u0420\u0430\u0434\u043e\u043c\u0456\u0446\u044c\u043a\u043e"
    ],
    "wof:name":"Radomicko",
    "wof:placetype":"locality"
},
  "geometry": {"coordinates":[16.53657,51.95342],"type":"Point"}
}