{
  "type": "Feature",
  "properties": {
    "gn:admin1_code":"75.0",
    "gn:admin2_code":"611.0",
    "gn:admin3_code":"61110.0",
    "gn:asciiname":"Wola Bystrzycka",
    "gn:country_code":"PL",
    "gn:dem":159,
    "gn:feature_class":"P",
    "gn:feature_code":"PPL",
    "gn:name":"Wola Bystrzycka",
    "gn:population":0,
    "gn:timezone":"Europe/Warsaw",
    "iso:country":"PL",
    "name:fra_x_preferred":[
        "Wola Bystrzycka"
    ],
    "name:pol_x_preferred":[
        "Wola Bystrzycka"
    ],
    "name:ukr_x_preferred":[
        "\u0412\u043e\u043b\u044f-\u0411\u0438\u0441\u0442\u0448\u0438\u0446\u044c\u043a\u0430"
    ],
    "wof:name":"Wola Bystrzycka",
    "wof:placetype":"locality"
},
  "geometry": {"coordinates":[22.35254,51.77735],"type":"Point"}
}