{
  "type": "Feature",
  "properties": {
    "gn:admin1_code":"75.0",
    "gn:admin2_code":"601.0",
    "gn:admin3_code":"60109.0",
    "gn:asciiname":"Korczowka",
    "gn:country_code":"PL",
    "gn:dem":146,
    "gn:feature_class":"P",
    "gn:feature_code":"PPL",
    "gn:name":"Korcz\u00f3wka",
    "gn:population":0,
    "gn:timezone":"Europe/Warsaw",
    "iso:country":"PL",
    "name:und_x_variant":[
        "Korcz\u00f3wka"
    ],
    "wof:name":"Korczowka",
    "wof:placetype":"locality"
},
  "geometry": {"coordinates":[23.04977,51.90666],"type":"Point"}
}