{
  "type": "Feature",
  "properties": {
    "gn:admin1_code":"75.0",
    "gn:admin2_code":"601.0",
    "gn:admin3_code":"60109.0",
    "gn:asciiname":"Korczowka",
    "gn:country_code":"PL",
    "gn:dem":146,
    "gn:feature_class":"P",
    "gn:feature_code":"PPL",
    "gn:name":"Korcz\u00f3wka",
    "gn:population":0,
    "gn:timezone":"Europe/Warsaw",
    "iso:country":"PL",
    "name:fra_x_preferred":[
        "Korcz\u00f3wka"
    ],
    "name:lit_x_preferred":[
        "Kor\u010duvka"
    ],
    "name:pol_x_preferred":[
        "Korcz\u00f3wka"
    ],
    "name:ukr_x_preferred":[
        "\u041a\u043e\u0440\u0447\u0443\u0432\u043a\u0430"
    ],
    "wof:name":"Korczowka",
    "wof:placetype":"locality"
},
  "geometry": {"coordinates":[23.04977,51.90666],"type":"Point"}
}