{
  "type": "Feature",
  "properties": {
    "gn:admin1_code":"78.0",
    "gn:admin2_code":"1412.0",
    "gn:admin3_code":"141211.0",
    "gn:asciiname":"Wolka Ilowiecka",
    "gn:country_code":"PL",
    "gn:dem":147,
    "gn:feature_class":"P",
    "gn:feature_code":"PPL",
    "gn:name":"W\u00f3lka I\u0142owiecka",
    "gn:population":0,
    "gn:timezone":"Europe/Warsaw",
    "iso:country":"PL",
    "name:fra_x_preferred":[
        "W\u00f3lka I\u0142\u00f3wiecka"
    ],
    "name:pol_x_preferred":[
        "W\u00f3lka I\u0142\u00f3wiecka"
    ],
    "name:ukr_x_preferred":[
        "\u0412\u0443\u043b\u044c\u043a\u0430-\u0406\u043b\u0443\u0432\u0435\u0446\u044c\u043a\u0430"
    ],
    "name:und_x_variant":[
        "W\u00f3lka I\u0142owiecka"
    ],
    "wof:name":"Wolka Ilowiecka",
    "wof:placetype":"locality"
},
  "geometry": {"coordinates":[21.53198,52.12528],"type":"Point"}
}