{
  "type": "Feature",
  "properties": {
    "gn:country":"PL",
    "gn:fcode":"PPL",
    "gn:population":0,
    "iso:country":"PL",
    "name:ast_x_preferred":[
        "Jackowo"
    ],
    "name:azb_x_preferred":[
        "\u06cc\u0627\u062a\u0633\u06a9\u0648\u0648\u0648"
    ],
    "name:ceb_x_preferred":[
        "Jackowo"
    ],
    "name:csb_x_preferred":[
        "Jack\u00f2w\u00f2"
    ],
    "name:eng_x_preferred":[
        "Jackowo"
    ],
    "name:fas_x_preferred":[
        "\u06cc\u0627\u062a\u0633\u06a9\u0648\u0648\u0648"
    ],
    "name:fra_x_preferred":[
        "Jackowo"
    ],
    "name:pol_x_preferred":[
        "Jackowo"
    ],
    "name:urd_x_preferred":[
        "\u062c\u06a9\u06a9\u0648\u0648\u0648\u060c \u067e\u0648\u0645\u06cc\u0631\u0627\u0646\u06cc\u0627\u0646 \u0635\u0648\u0628\u06c1"
    ],
    "name:urd_x_variant":[
        "\u062c\u06a9\u06a9\u0648\u0648\u0648"
    ],
    "qs_pg:aaroncc":"PL",
    "qs_pg:gn_country":"PL",
    "qs_pg:gn_fcode":"PPL",
    "qs_pg:gn_pop":0,
    "qs_pg:name":"Jackowo",
    "qs_pg:name_adm0":"Polska",
    "qs_pg:name_adm1":"Pomorskie",
    "qs_pg:photos":34,
    "qs_pg:photos_1k":7,
    "qs_pg:photos_9k":1,
    "qs_pg:photos_9r":2,
    "qs_pg:photos_all":34,
    "qs_pg:photos_sr":2,
    "qs_pg:pop_sr":0,
    "qs_pg:qs_pg_placetype":"locality",
    "qs_pg:qs_pg_placetype_gp":"Town",
    "qs_pg:woe_adm0":23424923,
    "woe:adm0_id":23424923,
    "woe:name_adm0":"Polska",
    "woe:name_adm1":"Pomorskie",
    "woe:placetype":"Town",
    "wof:name":"Jackowo",
    "wof:placetype":"locality"
},
  "geometry": {"coordinates":[17.82995,54.76534],"type":"Point"}
}