{
  "type": "Feature",
  "properties": {
    "gn:admin1_code":"76.0",
    "gn:admin2_code":"808.0",
    "gn:admin3_code":"80803.0",
    "gn:asciiname":"Lakie",
    "gn:country_code":"PL",
    "gn:dem":74,
    "gn:feature_class":"P",
    "gn:feature_code":"PPL",
    "gn:name":"\u0141\u0105kie",
    "gn:population":0,
    "gn:timezone":"Europe/Warsaw",
    "iso:country":"PL",
    "name:ceb_x_preferred":[
        "\u0141\u0105kie"
    ],
    "name:fra_x_preferred":[
        "\u0141\u0105kie"
    ],
    "name:pol_x_preferred":[
        "\u0141\u0105kie"
    ],
    "name:ukr_x_preferred":[
        "\u041b\u043e\u043d\u043a\u0435"
    ],
    "wof:name":"Lakie",
    "wof:placetype":"locality"
},
  "geometry": {"coordinates":[15.4557,52.18456],"type":"Point"}
}