{
  "type": "Feature",
  "properties": {
    "gn:admin1_code":"83.0",
    "gn:admin2_code":"2406.0",
    "gn:admin3_code":"240608.0",
    "gn:asciiname":"Kamiensko",
    "gn:country_code":"PL",
    "gn:dem":244,
    "gn:feature_class":"P",
    "gn:feature_code":"PPL",
    "gn:name":"Kamie\u0144sko",
    "gn:population":0,
    "gn:timezone":"Europe/Warsaw",
    "iso:country":"PL",
    "name:pol_x_preferred":[
        "Kami\u0144sko"
    ],
    "name:ukr_x_preferred":[
        "\u041a\u0430\u043c\u0456\u043d\u0441\u044c\u043a\u043e"
    ],
    "name:und_x_variant":[
        "Kami\u0144sko",
        "Kamie\u0144sko"
    ],
    "wof:name":"Kamiensko",
    "wof:placetype":"locality"
},
  "geometry": {"coordinates":[18.7246,50.79831],"type":"Point"}
}