{
  "type": "Feature",
  "properties": {
    "gn:admin1_code":"85.0",
    "gn:admin2_code":"2818.0",
    "gn:admin3_code":"281802.0",
    "gn:asciiname":"Bedziszewo",
    "gn:country_code":"PL",
    "gn:dem":202,
    "gn:feature_class":"P",
    "gn:feature_code":"PPL",
    "gn:name":"B\u0119dziszewo",
    "gn:population":0,
    "gn:timezone":"Europe/Warsaw",
    "iso:country":"PL",
    "name:und_x_variant":[
        "Padingkehmen",
        "Padingen",
        "B\u0119dzieszewo"
    ],
    "wof:name":"Bedziszewo",
    "wof:placetype":"locality"
},
  "geometry": {"coordinates":[22.61982,54.31242],"type":"Point"}
}