{
  "type": "Feature",
  "properties": {
    "gn:admin1_code":"85.0",
    "gn:admin2_code":"2818.0",
    "gn:admin3_code":"281802.0",
    "gn:asciiname":"Bedziszewo",
    "gn:country_code":"PL",
    "gn:dem":202,
    "gn:feature_class":"P",
    "gn:feature_code":"PPL",
    "gn:name":"B\u0119dziszewo",
    "gn:population":0,
    "gn:timezone":"Europe/Warsaw",
    "iso:country":"PL",
    "name:azb_x_preferred":[
        "\u0628\u0646\u062c\u0634\u0648\u0648"
    ],
    "name:deu_x_preferred":[
        "B\u0119dziszewo"
    ],
    "name:fas_x_preferred":[
        "\u0628\u0646\u062c\u0634\u0648\u0648"
    ],
    "name:nld_x_preferred":[
        "B\u0119dziszewo"
    ],
    "name:pol_x_preferred":[
        "B\u0119dziszewo"
    ],
    "name:ukr_x_preferred":[
        "\u0411\u0435\u043d\u0434\u0437\u0438\u0448\u0435\u0432\u043e"
    ],
    "name:und_x_variant":[
        "Padingkehmen",
        "Padingen",
        "B\u0119dzieszewo"
    ],
    "wof:name":"Bedziszewo",
    "wof:placetype":"locality"
},
  "geometry": {"coordinates":[22.61982,54.31242],"type":"Point"}
}