{
  "type": "Feature",
  "properties": {
    "gn:admin1_code":"72",
    "gn:admin2_code":"0204",
    "gn:admin3_code":"20404.0",
    "gn:asciiname":"Czeladz Wielka",
    "gn:country_code":"PL",
    "gn:dem":93,
    "gn:feature_class":"P",
    "gn:feature_code":"PPL",
    "gn:name":"Czelad\u017a Wielka",
    "gn:population":0,
    "gn:timezone":"Europe/Warsaw",
    "iso:country":"PL",
    "name:deu_x_historical":[
        "Tschilesen"
    ],
    "name:deu_x_preferred":[
        "Tschilesen"
    ],
    "wof:name":"Czeladz Wielka",
    "wof:placetype":"locality"
},
  "geometry": {"coordinates":[16.63424,51.57061],"type":"Point"}
}