{
  "type": "Feature",
  "properties": {
    "gn:gn_country":"PL",
    "gn:gn_fcode":"PPLA3",
    "gn:gn_pop":2718,
    "gn:population":2718,
    "iso:country":"PL",
    "name:eng_x_preferred":[
        "Stoczek \u0141ukowski"
    ],
    "name:epo_x_preferred":[
        "Stoczek \u0141ukowski"
    ],
    "name:heb_x_preferred":[
        "\u05e1\u05d8\u05d5\u05e6\u05e7 \u05dc\u05d5\u05e7\u05d5\u05d1\u05e1\u05e7\u05d9"
    ],
    "name:ido_x_preferred":[
        "Stoczek \u0141ukowski"
    ],
    "name:ina_x_preferred":[
        "Stoczek \u0141ukowski"
    ],
    "name:lat_x_preferred":[
        "Stoczek Lukovski"
    ],
    "name:lav_x_preferred":[
        "Sto\u010deka Lukovska"
    ],
    "name:nap_x_preferred":[
        "Stoczek \u0141ukowski"
    ],
    "name:nld_x_preferred":[
        "Stoczek \u0141ukowski"
    ],
    "name:pol_x_preferred":[
        "Stoczek \u0141ukowski"
    ],
    "name:ron_x_preferred":[
        "Stoczek \u0141ukowski"
    ],
    "name:rus_x_preferred":[
        "\u0421\u0442\u043e\u0447\u0435\u043a-\u041b\u0443\u043a\u043e\u0432\u0441\u043a\u0438\u0439"
    ],
    "name:spa_x_preferred":[
        "Stoczek \u0141ukowski"
    ],
    "name:srp_x_preferred":[
        "\u0421\u0442\u043e\u0447\u0435\u043a \u041b\u0443\u043a\u043e\u0432\u0441\u043a\u0438"
    ],
    "name:ukr_x_preferred":[
        "\u0421\u0442\u043e\u0447\u0435\u043a-\u041b\u0443\u043a\u043e\u0432\u0441\u044c\u043a\u0438\u0439"
    ],
    "name:unk_x_variant":[
        "Stoczek"
    ],
    "name:zho_x_preferred":[
        "\u6b66\u5eab\u592b\u5730\u5340\u65af\u6258\u5207\u514b"
    ],
    "qs_pg:aaroncc":"PL",
    "qs_pg:gn_country":"PL",
    "qs_pg:gn_fcode":"PPLA3",
    "qs_pg:gn_pop":2718,
    "qs_pg:name":"Stoczek \u0141ukowski",
    "qs_pg:name_adm0":"Polska",
    "qs_pg:name_adm1":"Lubelskie",
    "qs_pg:photos_9r":0,
    "qs_pg:photos_sr":0,
    "qs_pg:pop_sr":4,
    "qs_pg:qs_pg_placetype":"localadmin",
    "qs_pg:qs_pg_placetype_gp":"LocalAdmin",
    "qs_pg:woe_adm0":23424923,
    "woe:adm0_id":23424923,
    "woe:name_adm0":"Polska",
    "woe:name_adm1":"Lubelskie",
    "woe:placetype":"LocalAdmin",
    "wof:name":"Stoczek \u0141ukowski",
    "wof:placetype":"localadmin",
    "wof:population":2718
},
  "geometry": {"coordinates":[21.97137,51.96135],"type":"Point"}
}