{
  "type": "Feature",
  "properties": {
    "gn:admin1_code":"81.0",
    "gn:admin2_code":"2013.0",
    "gn:admin3_code":"201309.0",
    "gn:asciiname":"Wyliny Rus",
    "gn:country_code":"PL",
    "gn:dem":132,
    "gn:feature_class":"P",
    "gn:feature_code":"PPL",
    "gn:name":"Wyliny Ru\u015b",
    "gn:population":0,
    "gn:timezone":"Europe/Warsaw",
    "iso:country":"PL",
    "name:und_x_variant":[
        "Wyliny Ru\u015b"
    ],
    "wof:name":"Wyliny Rus",
    "wof:placetype":"locality"
},
  "geometry": {"coordinates":[22.64821,52.80786],"type":"Point"}
}