{
  "type": "Feature",
  "properties": {
    "gn:admin1_code":"74.0",
    "gn:admin2_code":"1020.0",
    "gn:admin3_code":"102006.0",
    "gn:asciiname":"Cedrowice",
    "gn:country_code":"PL",
    "gn:dem":121,
    "gn:feature_class":"P",
    "gn:feature_code":"PPL",
    "gn:name":"Cedrowice",
    "gn:population":0,
    "gn:timezone":"Europe/Warsaw",
    "iso:country":"PL",
    "name:pol_x_preferred":[
        "Cedrowice"
    ],
    "name:ukr_x_preferred":[
        "\u0426\u0435\u0434\u0440\u043e\u0432\u0456\u0446\u0435"
    ],
    "wof:name":"Cedrowice",
    "wof:placetype":"locality"
},
  "geometry": {"coordinates":[19.27614,51.99118],"type":"Point"}
}