{
  "type": "Feature",
  "properties": {
    "gn:admin1_code":"83.0",
    "gn:admin2_code":"2413.0",
    "gn:admin3_code":"241304.0",
    "gn:asciiname":"Repty Stare",
    "gn:country_code":"PL",
    "gn:dem":297,
    "gn:feature_class":"P",
    "gn:feature_code":"PPL",
    "gn:name":"Repty Stare",
    "gn:population":0,
    "gn:timezone":"Europe/Warsaw",
    "iso:country":"PL",
    "name:und_x_variant":[
        "Stare Repty",
        "Repty Stare"
    ],
    "wof:name":"Repty Stare",
    "wof:placetype":"locality"
},
  "geometry": {"coordinates":[18.82619,50.41587],"type":"Point"}
}