{
  "type": "Feature",
  "properties": {
    "gn:admin1_code":"77.0",
    "gn:admin2_code":"1216.0",
    "gn:admin3_code":"121602.0",
    "gn:asciiname":"Brzozowa",
    "gn:country_code":"PL",
    "gn:dem":249,
    "gn:feature_class":"P",
    "gn:feature_code":"PPL",
    "gn:name":"Brzozowa",
    "gn:population":0,
    "gn:timezone":"Europe/Warsaw",
    "iso:country":"PL",
    "wof:name":"Brzozowa",
    "wof:placetype":"locality"
},
  "geometry": {"coordinates":[20.89553,49.83593],"type":"Point"}
}