{
  "type": "Feature",
  "properties": {
    "gn:admin1_code":"78.0",
    "gn:admin2_code":"1438.0",
    "gn:admin3_code":"143802.0",
    "gn:asciiname":"Dworzno",
    "gn:country_code":"PL",
    "gn:dem":170,
    "gn:feature_class":"P",
    "gn:feature_code":"PPL",
    "gn:name":"Dw\u00f3rzno",
    "gn:population":0,
    "gn:timezone":"Europe/Warsaw",
    "iso:country":"PL",
    "name:fra_x_preferred":[
        "Dw\u00f3rzno"
    ],
    "name:pol_x_preferred":[
        "Dw\u00f3rzno"
    ],
    "name:ukr_x_preferred":[
        "\u0414\u0432\u0443\u0436\u043d\u043e"
    ],
    "wof:name":"Dworzno",
    "wof:placetype":"locality"
},
  "geometry": {"coordinates":[20.60929,51.95271],"type":"Point"}
}