{
  "type": "Feature",
  "properties": {
    "gn:gn_country":"PL",
    "gn:gn_fcode":"PPLA3",
    "gn:gn_pop":2300,
    "gn:population":2300,
    "iso:country":"PL",
    "name:azb_x_preferred":[
        "\u0646\u0642\u062e\u0627\u0646\u0648\u0648\u0648"
    ],
    "name:deu_x_preferred":[
        "Niechanowo"
    ],
    "name:fas_x_preferred":[
        "\u0646\u06af\u062e\u0627\u0646\u0648\u0648\u0648"
    ],
    "name:fra_x_preferred":[
        "Niechanowo"
    ],
    "name:nld_x_preferred":[
        "Niechanowo"
    ],
    "name:pol_x_preferred":[
        "Niechanowo"
    ],
    "name:ukr_x_preferred":[
        "\u041d\u0435\u0445\u0430\u043d\u043e\u0432\u043e"
    ],
    "qs_pg:aaroncc":"PL",
    "qs_pg:gn_country":"PL",
    "qs_pg:gn_fcode":"PPLA3",
    "qs_pg:gn_pop":2300,
    "qs_pg:name":"Niechanowo",
    "qs_pg:name_adm0":"Polska",
    "qs_pg:name_adm1":"Wielkopolskie",
    "qs_pg:photos_9k":1,
    "qs_pg:photos_9r":1,
    "qs_pg:photos_all":4,
    "qs_pg:photos_sr":0,
    "qs_pg:pop_sr":4,
    "qs_pg:qs_pg_placetype":"localadmin",
    "qs_pg:qs_pg_placetype_gp":"LocalAdmin",
    "qs_pg:woe_adm0":23424923,
    "woe:adm0_id":23424923,
    "woe:name_adm0":"Polska",
    "woe:name_adm1":"Wielkopolskie",
    "woe:placetype":"LocalAdmin",
    "wof:name":"Niechanowo",
    "wof:placetype":"localadmin",
    "wof:population":2300
},
  "geometry": {"coordinates":[17.67812,52.46527],"type":"Point"}
}