{
  "type": "Feature",
  "properties": {
    "gn:admin1_code":"72.0",
    "gn:admin2_code":"202.0",
    "gn:admin3_code":"20203.0",
    "gn:asciiname":"Rosciszow",
    "gn:country_code":"PL",
    "gn:dem":363,
    "gn:feature_class":"P",
    "gn:feature_code":"PPL",
    "gn:name":"Ro\u015bcisz\u00f3w",
    "gn:population":0,
    "gn:timezone":"Europe/Warsaw",
    "iso:country":"PL",
    "name:deu_x_preferred":[
        "Steinseifersdorf"
    ],
    "wof:name":"Rosciszow",
    "wof:placetype":"locality"
},
  "geometry": {"coordinates":[16.5485,50.70896],"type":"Point"}
}