{
  "type": "Feature",
  "properties": {
    "gn:admin1_code":"78.0",
    "gn:admin2_code":"1411.0",
    "gn:admin3_code":"141106.0",
    "gn:asciiname":"Bobin Wielkie",
    "gn:country_code":"PL",
    "gn:dem":113,
    "gn:feature_class":"P",
    "gn:feature_code":"PPL",
    "gn:name":"Bobin Wielkie",
    "gn:population":0,
    "gn:timezone":"Europe/Warsaw",
    "iso:country":"PL",
    "wof:name":"Bobin Wielkie",
    "wof:placetype":"locality"
},
  "geometry": {"coordinates":[21.06532,53.0403],"type":"Point"}
}