{
  "type": "Feature",
  "properties": {
    "gn:admin1_code":"86.0",
    "gn:admin2_code":"3007.0",
    "gn:admin3_code":"300711.0",
    "gn:asciiname":"Zlotniki Wielkie",
    "gn:country_code":"PL",
    "gn:dem":121,
    "gn:feature_class":"P",
    "gn:feature_code":"PPL",
    "gn:name":"Z\u0142otniki Wielkie",
    "gn:population":0,
    "gn:timezone":"Europe/Warsaw",
    "iso:country":"PL",
    "name:pol_x_preferred":[
        "Z\u0142otniki Wielkie"
    ],
    "name:ukr_x_preferred":[
        "\u0417\u043b\u043e\u0442\u043d\u0438\u043a\u0438-\u0412\u0435\u043b\u0438\u043a\u0456"
    ],
    "wof:name":"Zlotniki Wielkie",
    "wof:placetype":"locality"
},
  "geometry": {"coordinates":[18.1769,51.88976],"type":"Point"}
}