{
  "type": "Feature",
  "properties": {
    "gn:admin1_code":"84.0",
    "gn:admin2_code":"2608.0",
    "gn:admin3_code":"260801.0",
    "gn:asciiname":"Debiany",
    "gn:country_code":"PL",
    "gn:dem":268,
    "gn:feature_class":"P",
    "gn:feature_code":"PPL",
    "gn:name":"D\u0119biany",
    "gn:population":0,
    "gn:timezone":"Europe/Warsaw",
    "iso:country":"PL",
    "wof:name":"Debiany",
    "wof:placetype":"locality"
},
  "geometry": {"coordinates":[20.45808,50.37485],"type":"Point"}
}