{
  "type": "Feature",
  "properties": {
    "iso:country":"PL",
    "name:ast_x_preferred":[
        "Widzew \u0141\u00f3d\u017a"
    ],
    "name:bel_x_preferred":[
        "\u0424\u041a \u0412\u0456\u0434\u0437\u0430\u045e \u041b\u043e\u0434\u0437\u044c"
    ],
    "name:bel_x_variant":[
        "\u0412\u0456\u0434\u0437\u044d\u045e \u041b\u043e\u0434\u0437\u044c"
    ],
    "name:bul_x_preferred":[
        "\u0420\u0422\u0421 \u0412\u0438\u0434\u0437\u0435\u0432 \u041b\u043e\u0434\u0437"
    ],
    "name:cat_x_preferred":[
        "KS Widzew \u0141\u00f3d\u017a"
    ],
    "name:ces_x_preferred":[
        "Widzew \u0141\u00f3d\u017a"
    ],
    "name:dan_x_preferred":[
        "Widzew \u0141\u00f3d\u017a"
    ],
    "name:deu_x_preferred":[
        "Widzew \u0141\u00f3d\u017a"
    ],
    "name:ell_x_preferred":[
        "\u0392\u03af\u03c4\u03b6\u03b5\u03b2 \u039b\u03bf\u03c4\u03b6"
    ],
    "name:pol_x_preferred":[
        "Widzew"
    ],
    "name:spa_x_preferred":[
        "Widzew \u0141\u00f3d\u017a"
    ],
    "name:unk_x_variant":[
        "Widzew"
    ],
    "qs:gn_fcode":"PPLX",
    "qs:gn_local":0,
    "qs:gn_namadm1":"74",
    "qs:gn_name":"Widzew",
    "qs:local_max":4879,
    "qs:local_sum":14816,
    "qs:localhoods":8,
    "qs:name":"Widzew",
    "qs:name_adm0":"Polska",
    "qs:name_adm1":"\u0141\u00f3dzkie",
    "qs:name_adm2":"\u0141\u00f3d\u017a",
    "qs:name_lau":"Lodz",
    "qs:name_local":"\u0141\u00f3d\u017a",
    "qs:photo_max":1220,
    "qs:photo_sum":1682,
    "qs:placetype":"Suburb",
    "qs:quad_count":53,
    "qs:woe_adm0":23424923,
    "qs:woe_adm1":12577937,
    "qs:woe_adm2":12591192,
    "qs:woe_lau":12616892,
    "qs:woe_local":505120,
    "qs:woe_ver":"7.10.0",
    "wd:wordcount":822,
    "wof:lang":[
        "pol"
    ],
    "wof:name":"Widzew",
    "wof:placetype":"neighbourhood"
},
  "geometry": {"coordinates":[19.554348,51.767163],"type":"Point"}
}