{
  "type": "Feature",
  "properties": {
    "gn:admin1_code":"73.0",
    "gn:admin2_code":"414.0",
    "gn:admin3_code":"41401.0",
    "gn:asciiname":"Tuszynki",
    "gn:country_code":"PL",
    "gn:dem":101,
    "gn:feature_class":"P",
    "gn:feature_code":"PPL",
    "gn:name":"Tuszynki",
    "gn:population":0,
    "gn:timezone":"Europe/Warsaw",
    "iso:country":"PL",
    "name:azb_x_preferred":[
        "\u062a\u0648\u0686\u06cc\u0646\u06a9\u06cc"
    ],
    "name:ceb_x_preferred":[
        "Tuszynki"
    ],
    "name:fas_x_preferred":[
        "\u062a\u0648\u0686\u06cc\u0646\u06a9\u06cc"
    ],
    "name:pol_x_preferred":[
        "Tuszynki"
    ],
    "name:ukr_x_preferred":[
        "\u0422\u0443\u0448\u0438\u043d\u043a\u0456"
    ],
    "name:urd_x_preferred":[
        "\u062a\u0648\u0686\u06cc\u0646\u06a9\u06cc"
    ],
    "wof:name":"Tuszynki",
    "wof:placetype":"locality"
},
  "geometry": {"coordinates":[18.17972,53.40595],"type":"Point"}
}