{
  "type": "Feature",
  "properties": {
    "gn:gn_country":"PL",
    "gn:gn_fcode":"PPL",
    "gn:gn_pop":238,
    "gn:population":238,
    "iso:country":"PL",
    "name:eng_x_preferred":[
        "Czerkasy"
    ],
    "name:fra_x_preferred":[
        "Czerkasy"
    ],
    "name:pol_x_preferred":[
        "Czerkasy"
    ],
    "qs_pg:aaroncc":"PL",
    "qs_pg:gn_country":"PL",
    "qs_pg:gn_fcode":"PPL",
    "qs_pg:gn_pop":238,
    "qs_pg:name":"Czerkasy",
    "qs_pg:name_adm0":"Polska",
    "qs_pg:name_adm1":"Lubelskie",
    "qs_pg:photos_9r":0,
    "qs_pg:photos_sr":0,
    "qs_pg:pop_sr":2,
    "qs_pg:qs_pg_placetype":"locality",
    "qs_pg:qs_pg_placetype_gp":"Town",
    "qs_pg:woe_adm0":23424923,
    "woe:adm0_id":23424923,
    "woe:name_adm0":"Polska",
    "woe:name_adm1":"Lubelskie",
    "woe:placetype":"Town",
    "wof:name":"Czerkasy",
    "wof:placetype":"locality",
    "wof:population":238
},
  "geometry": {"coordinates":[23.70884,50.53034],"type":"Point"}
}