{
  "type": "Feature",
  "properties": {
    "gn:admin1_code":"78.0",
    "gn:admin2_code":"1425.0",
    "gn:admin3_code":"142510.0",
    "gn:asciiname":"Boguslawice",
    "gn:country_code":"PL",
    "gn:dem":175,
    "gn:feature_class":"P",
    "gn:feature_code":"PPL",
    "gn:name":"Bogus\u0142awice",
    "gn:population":0,
    "gn:timezone":"Europe/Warsaw",
    "iso:country":"PL",
    "wof:name":"Boguslawice",
    "wof:placetype":"locality"
},
  "geometry": {"coordinates":[21.29457,51.34572],"type":"Point"}
}