{
  "type": "Feature",
  "properties": {
    "gn:population":2235,
    "iso:country":"PL",
    "name:ast_x_preferred":[
        "Szerzyny"
    ],
    "name:azb_x_preferred":[
        "\u0634\u0698\u0646\u0647"
    ],
    "name:deu_x_preferred":[
        "Szerzyny"
    ],
    "name:eng_x_preferred":[
        "Szerzyny"
    ],
    "name:fas_x_preferred":[
        "\u0634\u0698\u0646\u0647"
    ],
    "name:fra_x_preferred":[
        "Szerzyny"
    ],
    "name:ita_x_preferred":[
        "Szerzyny"
    ],
    "name:nld_x_preferred":[
        "Szerzyny"
    ],
    "name:pol_x_preferred":[
        "Szerzyny"
    ],
    "name:rus_x_preferred":[
        "\u0428\u0435\u0436\u0438\u043d\u044b"
    ],
    "name:swe_x_preferred":[
        "Szerzyny"
    ],
    "name:ukr_x_preferred":[
        "\u0428\u0435\u0436\u0438\u043d\u0438"
    ],
    "qs:a0":"Rzeczpospolita Polska",
    "qs:a1":"*Malopolskie",
    "qs:a1r":"0",
    "qs:a2":"Tarnowski",
    "qs:adm0":"Rzeczpospolita Polska",
    "qs:la":"Szerzyny",
    "qs:la_lc":"*PL1216162",
    "qs:level":"locality",
    "qs:loc":"Szerzyny",
    "qs:loc_alt":"Szerzyny",
    "qs:pop":0,
    "qs:type":"rural point-near-poly",
    "wd:wordcount":82,
    "wof:name":"Szerzyny",
    "wof:placetype":"locality",
    "wof:population":2235
},
  "geometry": {"coordinates":[21.2227879810815,49.8154261678249],"type":"Point"}
}