{
  "type": "Feature",
  "properties": {
    "gn:admin1_code":"75.0",
    "gn:admin2_code":"603.0",
    "gn:admin3_code":"60304.0",
    "gn:asciiname":"Skordiow",
    "gn:cc2":"PL",
    "gn:country_code":"PL",
    "gn:dem":173,
    "gn:feature_class":"P",
    "gn:feature_code":"PPL",
    "gn:name":"Skordi\u00f3w",
    "gn:population":0,
    "gn:timezone":"Europe/Warsaw",
    "iso:country":"PL",
    "name:fra_x_preferred":[
        "Skordi\u00f3w"
    ],
    "name:pol_x_preferred":[
        "Skordi\u00f3w"
    ],
    "name:ukr_x_preferred":[
        "\u0421\u043a\u043e\u0440\u0434\u044e\u0432"
    ],
    "name:und_x_variant":[
        "Skordj\u00f3w"
    ],
    "wof:name":"Skordiow",
    "wof:placetype":"locality"
},
  "geometry": {"coordinates":[23.72292,51.08962],"type":"Point"}
}