{
  "type": "Feature",
  "properties": {
    "gn:gn_country":"PL",
    "gn:gn_fcode":"PPLA3",
    "gn:gn_pop":410,
    "gn:population":410,
    "iso:country":"PL",
    "name:ceb_x_preferred":[
        "Czarnocin"
    ],
    "name:deu_x_preferred":[
        "Czarnocin"
    ],
    "name:eng_x_preferred":[
        "Gmina Czarnocin"
    ],
    "name:fra_x_preferred":[
        "Czarnocin"
    ],
    "name:ita_x_preferred":[
        "Czarnocin"
    ],
    "name:nld_x_preferred":[
        "Czarnocin"
    ],
    "name:pol_x_preferred":[
        "Czarnocin"
    ],
    "name:rus_x_preferred":[
        "\u0427\u0430\u0440\u043d\u043e\u0446\u0438\u043d"
    ],
    "name:slk_x_preferred":[
        "Gmina Czarnocin"
    ],
    "name:ukr_x_preferred":[
        "\u0490\u043c\u0456\u043d\u0430 \u0427\u0430\u0440\u043d\u043e\u0446\u0438\u043d"
    ],
    "name:ukr_x_variant":[
        "\u0427\u0430\u0440\u043d\u043e\u0446\u0438\u043d"
    ],
    "name:war_x_preferred":[
        "Gmina Czarnocin"
    ],
    "qs_pg:aaroncc":"PL",
    "qs_pg:gn_country":"PL",
    "qs_pg:gn_fcode":"PPLA3",
    "qs_pg:gn_pop":410,
    "qs_pg:name":"Czarnocin",
    "qs_pg:name_adm0":"Polska",
    "qs_pg:name_adm1":"Swi\u0119tokrzyskie",
    "qs_pg:photos_9k":1,
    "qs_pg:photos_9r":1,
    "qs_pg:photos_all":4,
    "qs_pg:photos_sr":0,
    "qs_pg:pop_sr":2,
    "qs_pg:qs_pg_placetype":"localadmin",
    "qs_pg:qs_pg_placetype_gp":"LocalAdmin",
    "qs_pg:woe_adm0":23424923,
    "woe:adm0_id":23424923,
    "woe:name_adm0":"Polska",
    "woe:name_adm1":"Swi\u0119tokrzyskie",
    "woe:placetype":"LocalAdmin",
    "wof:name":"Czarnocin",
    "wof:placetype":"localadmin",
    "wof:population":410
},
  "geometry": {"coordinates":[20.5162,50.3408],"type":"Point"}
}