{
  "type": "Feature",
  "properties": {
    "gn:admin1_code":"80.0",
    "gn:admin2_code":"1803.0",
    "gn:admin3_code":"180302.0",
    "gn:asciiname":"Globikowka",
    "gn:country_code":"PL",
    "gn:dem":286,
    "gn:feature_class":"P",
    "gn:feature_code":"PPL",
    "gn:name":"G\u0142obik\u00f3wka",
    "gn:population":0,
    "gn:timezone":"Europe/Warsaw",
    "iso:country":"PL",
    "name:azb_x_preferred":[
        "\u0642\u0648\u0648\u0628\u06cc\u06a9\u0648\u0648\u06a9\u0627"
    ],
    "name:ceb_x_preferred":[
        "G\u0142obik\u00f3wka"
    ],
    "name:fas_x_preferred":[
        "\u06af\u0648\u0648\u0628\u06cc\u06a9\u0648\u0648\u06a9\u0627"
    ],
    "name:nld_x_preferred":[
        "G\u0142obik\u00f3wka"
    ],
    "name:pol_x_preferred":[
        "G\u0142obik\u00f3wka"
    ],
    "name:ukr_x_preferred":[
        "\u0490\u043b\u043e\u0431\u0456\u043a\u0443\u0432\u043a\u0430"
    ],
    "wof:name":"Globikowka",
    "wof:placetype":"locality"
},
  "geometry": {"coordinates":[21.44162,49.93952],"type":"Point"}
}