{
  "type": "Feature",
  "properties": {
    "gn:admin1_code":"80.0",
    "gn:admin2_code":"1803.0",
    "gn:admin3_code":"180302.0",
    "gn:asciiname":"Globikowka",
    "gn:country_code":"PL",
    "gn:dem":286,
    "gn:feature_class":"P",
    "gn:feature_code":"PPL",
    "gn:name":"G\u0142obik\u00f3wka",
    "gn:population":0,
    "gn:timezone":"Europe/Warsaw",
    "iso:country":"PL",
    "name:und_x_variant":[
        "G\u0142obik\u00f3wka"
    ],
    "wof:name":"Globikowka",
    "wof:placetype":"locality"
},
  "geometry": {"coordinates":[21.44162,49.93952],"type":"Point"}
}