{
  "type": "Feature",
  "properties": {
    "gn:admin1_code":"78.0",
    "gn:admin2_code":"1411.0",
    "gn:admin3_code":"141105.0",
    "gn:asciiname":"Glazewo",
    "gn:country_code":"PL",
    "gn:dem":102,
    "gn:feature_class":"P",
    "gn:feature_code":"PPL",
    "gn:name":"G\u0142a\u017cewo",
    "gn:population":0,
    "gn:timezone":"Europe/Warsaw",
    "iso:country":"PL",
    "wof:name":"Glazewo",
    "wof:placetype":"locality"
},
  "geometry": {"coordinates":[21.35,52.95],"type":"Point"}
}