{
  "type": "Feature",
  "properties": {
    "gn:admin1_code":"84.0",
    "gn:admin2_code":"2613.0",
    "gn:admin3_code":"261301.0",
    "gn:asciiname":"Komparzow",
    "gn:country_code":"PL",
    "gn:dem":222,
    "gn:feature_class":"P",
    "gn:feature_code":"PPL",
    "gn:name":"Komparz\u00f3w",
    "gn:population":0,
    "gn:timezone":"Europe/Warsaw",
    "iso:country":"PL",
    "name:pol_x_preferred":[
        "Komparz\u00f3w"
    ],
    "name:ukr_x_preferred":[
        "\u041a\u043e\u043c\u043f\u0430\u0436\u0443\u0432"
    ],
    "name:und_x_variant":[
        "K\u0105parz\u00f3w"
    ],
    "wof:name":"Komparzow",
    "wof:placetype":"locality"
},
  "geometry": {"coordinates":[19.88897,50.91411],"type":"Point"}
}