{
  "type": "Feature",
  "properties": {
    "gn:gn_country":"PL",
    "gn:gn_fcode":"PPL",
    "gn:gn_pop":237,
    "gn:population":237,
    "iso:country":"PL",
    "name:ast_x_preferred":[
        "Wysoka Braniewska"
    ],
    "name:ceb_x_preferred":[
        "Wysoka Braniewska"
    ],
    "name:eng_x_preferred":[
        "Wysoka Braniewska"
    ],
    "name:fra_x_preferred":[
        "Wysoka Braniewska"
    ],
    "name:nld_x_preferred":[
        "Wysoka Braniewska"
    ],
    "name:pol_x_preferred":[
        "Wysoka Braniewska"
    ],
    "name:ukr_x_preferred":[
        "\u0412\u0438\u0441\u043e\u043a\u0430 \u0411\u0440\u0430\u043d\u0435\u0432\u0441\u044c\u043a\u0430"
    ],
    "name:unk_x_variant":[
        "Hogendorf"
    ],
    "qs_pg:aaroncc":"PL",
    "qs_pg:gn_country":"PL",
    "qs_pg:gn_fcode":"PPL",
    "qs_pg:gn_pop":237,
    "qs_pg:name":"Wysoka Braniewska",
    "qs_pg:name_adm0":"Polska",
    "qs_pg:name_adm1":"Warminsko-Mazurskie",
    "qs_pg:photos_9r":0,
    "qs_pg:photos_sr":0,
    "qs_pg:pop_sr":2,
    "qs_pg:qs_pg_placetype":"locality",
    "qs_pg:qs_pg_placetype_gp":"Town",
    "qs_pg:woe_adm0":23424923,
    "woe:adm0_id":23424923,
    "woe:name_adm0":"Polska",
    "woe:name_adm1":"Warminsko-Mazurskie",
    "woe:placetype":"Town",
    "wof:name":"Wysoka Braniewska",
    "wof:placetype":"locality",
    "wof:population":237
},
  "geometry": {"coordinates":[20.04129,54.27846],"type":"Point"}
}