{
  "type": "Feature",
  "properties": {
    "gn:admin1_code":"72.0",
    "gn:admin2_code":"207.0",
    "gn:admin3_code":"20704.0",
    "gn:asciiname":"Pastewnik",
    "gn:country_code":"PL",
    "gn:dem":517,
    "gn:feature_class":"P",
    "gn:feature_code":"PPL",
    "gn:name":"Pastewnik",
    "gn:population":0,
    "gn:timezone":"Europe/Warsaw",
    "iso:country":"PL",
    "name:nld_x_preferred":[
        "Pastewnik"
    ],
    "name:pol_x_preferred":[
        "Pastewnik"
    ],
    "name:ukr_x_preferred":[
        "\u041f\u0430\u0441\u0442\u0435\u0432\u043d\u0438\u043a"
    ],
    "wof:name":"Pastewnik",
    "wof:placetype":"locality"
},
  "geometry": {"coordinates":[16.03037,50.88205],"type":"Point"}
}