{
  "type": "Feature",
  "properties": {
    "gn:admin1_code":"81.0",
    "gn:admin2_code":"2008.0",
    "gn:admin3_code":"200805.0",
    "gn:asciiname":"Penskie",
    "gn:country_code":"PL",
    "gn:dem":127,
    "gn:feature_class":"P",
    "gn:feature_code":"PPL",
    "gn:name":"Pe\u0144skie",
    "gn:population":0,
    "gn:timezone":"Europe/Warsaw",
    "iso:country":"PL",
    "name:fra_x_preferred":[
        "Pe\u0144skie"
    ],
    "name:lit_x_preferred":[
        "Penskiai"
    ],
    "name:pol_x_preferred":[
        "Pe\u0144skie"
    ],
    "name:ukr_x_preferred":[
        "\u041f\u0435\u043d\u0441\u044c\u043a\u0435"
    ],
    "wof:name":"Penskie",
    "wof:placetype":"locality"
},
  "geometry": {"coordinates":[22.81328,53.30708000000001],"type":"Point"}
}