{
  "type": "Feature",
  "properties": {
    "gn:admin1_code":"73.0",
    "gn:admin2_code":"409.0",
    "gn:admin3_code":"40903.0",
    "gn:asciiname":"Janowo",
    "gn:country_code":"PL",
    "gn:dem":134,
    "gn:feature_class":"P",
    "gn:feature_code":"PPL",
    "gn:name":"Janowo",
    "gn:population":0,
    "gn:timezone":"Europe/Warsaw",
    "iso:country":"PL",
    "name:bel_x_preferred":[
        "\u042f\u043d\u0430\u0432\u0430"
    ],
    "name:bul_x_preferred":[
        "\u042f\u043d\u043e\u0432\u043e"
    ],
    "name:ceb_x_preferred":[
        "Janowo"
    ],
    "name:deu_x_preferred":[
        "Janowo"
    ],
    "name:fra_x_preferred":[
        "Janowo"
    ],
    "name:hye_x_preferred":[
        "\u0545\u0561\u0576\u0578\u057e\u0578"
    ],
    "name:lit_x_preferred":[
        "Janovas"
    ],
    "name:nld_x_preferred":[
        "Janowo"
    ],
    "name:pol_x_preferred":[
        "Janowo"
    ],
    "name:rus_x_preferred":[
        "\u042f\u043d\u043e\u0432\u043e"
    ],
    "name:ukr_x_preferred":[
        "\u042f\u043d\u043e\u0432\u043e"
    ],
    "wof:name":"Janowo",
    "wof:placetype":"locality"
},
  "geometry": {"coordinates":[17.86667000000001,52.65],"type":"Point"}
}