{
  "type": "Feature",
  "properties": {
    "iso:country":"PL",
    "name:ast_x_preferred":[
        "Dukla"
    ],
    "name:bel_x_preferred":[
        "\u0414\u0443\u043a\u043b\u044f"
    ],
    "name:bul_x_preferred":[
        "\u0414\u0443\u043a\u043b\u044f"
    ],
    "name:ceb_x_preferred":[
        "Dukla"
    ],
    "name:ces_x_preferred":[
        "Dukla"
    ],
    "name:deu_x_preferred":[
        "Dukla"
    ],
    "name:eng_x_preferred":[
        "Dukla"
    ],
    "name:epo_x_preferred":[
        "Dukla"
    ],
    "name:fin_x_preferred":[
        "Dukla"
    ],
    "name:fra_x_preferred":[
        "Dukla"
    ],
    "name:heb_x_preferred":[
        "\u05d3\u05d5\u05e7\u05dc\u05d4"
    ],
    "name:hun_x_preferred":[
        "Dukla"
    ],
    "name:jav_x_preferred":[
        "Dukla"
    ],
    "name:lav_x_preferred":[
        "Dukla"
    ],
    "name:msa_x_preferred":[
        "Dukla"
    ],
    "name:nld_x_preferred":[
        "Dukla"
    ],
    "name:pol_x_preferred":[
        "Dukla"
    ],
    "name:por_x_preferred":[
        "Dukla"
    ],
    "name:ron_x_preferred":[
        "Dukla"
    ],
    "name:rus_x_preferred":[
        "\u0414\u0443\u043a\u043b\u044f"
    ],
    "name:slk_x_preferred":[
        "Dukla"
    ],
    "name:srp_x_preferred":[
        "\u0414\u0443\u043a\u043b\u0430"
    ],
    "name:tat_x_preferred":[
        "\u0414\u0443\u043a\u043b\u04d9"
    ],
    "name:ukr_x_preferred":[
        "\u0414\u0443\u043a\u043b\u044f"
    ],
    "name:vie_x_preferred":[
        "Dukla"
    ],
    "name:zho_x_preferred":[
        "\u675c\u514b\u62c9"
    ],
    "qs_pg:aaroncc":"PL",
    "qs_pg:name":"Dukla",
    "qs_pg:name_adm0":"Polska",
    "qs_pg:name_adm1":"Podkarpackie",
    "qs_pg:photos":47,
    "qs_pg:photos_1k":10,
    "qs_pg:photos_9k":1,
    "qs_pg:photos_9r":2,
    "qs_pg:photos_all":47,
    "qs_pg:photos_sr":2,
    "qs_pg:pop_sr":0,
    "qs_pg:qs_pg_placetype":"locality",
    "qs_pg:qs_pg_placetype_gp":"Town",
    "qs_pg:woe_adm0":23424923,
    "woe:adm0_id":23424923,
    "woe:name_adm0":"Polska",
    "woe:name_adm1":"Podkarpackie",
    "woe:placetype":"Town",
    "wof:name":"Dukla",
    "wof:placetype":"locality"
},
  "geometry": {"coordinates":[21.685209,49.555952],"type":"Point"}
}