{
  "type": "Feature",
  "properties": {
    "gn:admin1_code":"84.0",
    "gn:admin2_code":"2610.0",
    "gn:admin3_code":"261002.0",
    "gn:asciiname":"Piety",
    "gn:country_code":"PL",
    "gn:dem":297,
    "gn:feature_class":"P",
    "gn:feature_code":"PPL",
    "gn:name":"Pi\u0119ty",
    "gn:population":0,
    "gn:timezone":"Europe/Warsaw",
    "iso:country":"PL",
    "name:ara_x_preferred":[
        "\u062a\u0642\u0648\u0649"
    ],
    "name:ben_x_preferred":[
        "\u09aa\u09c1\u09a3\u09cd\u09af"
    ],
    "name:ces_x_preferred":[
        "Blaho\u010dest\u00ed"
    ],
    "name:deu_x_preferred":[
        "Fr\u00f6mmigkeit"
    ],
    "name:epo_x_preferred":[
        "Pieco"
    ],
    "name:fas_x_preferred":[
        "\u067e\u0631\u0647\u06cc\u0632\u06af\u0627\u0631\u06cc"
    ],
    "name:fin_x_preferred":[
        "Hurskaus"
    ],
    "name:fra_x_preferred":[
        "Pi\u00e9t\u00e9"
    ],
    "name:hye_x_preferred":[
        "\u0532\u0561\u0580\u0565\u057a\u0561\u0577\u057f\u0578\u0582\u0569\u0575\u0578\u0582\u0576"
    ],
    "name:ind_x_preferred":[
        "Kesalehan"
    ],
    "name:ita_x_preferred":[
        "Piet\u00e0"
    ],
    "name:lat_x_preferred":[
        "Pietas"
    ],
    "name:lfn_x_preferred":[
        "Pietas"
    ],
    "name:msa_x_preferred":[
        "Warak"
    ],
    "name:nld_x_preferred":[
        "Vroomheid"
    ],
    "name:pol_x_preferred":[
        "Pobo\u017cno\u015b\u0107"
    ],
    "name:pus_x_preferred":[
        "\u062a\u0642\u0648\u0627"
    ],
    "name:rus_x_preferred":[
        "\u0411\u043b\u0430\u0433\u043e\u0447\u0435\u0441\u0442\u0438\u0435"
    ],
    "name:slk_x_preferred":[
        "Pieta"
    ],
    "name:swe_x_preferred":[
        "Fromhet"
    ],
    "name:tur_x_preferred":[
        "Diyanet"
    ],
    "name:ukr_x_preferred":[
        "\u0411\u043b\u0430\u0433\u043e\u0447\u0435\u0441\u0442\u044f"
    ],
    "name:yid_x_preferred":[
        "\u05e2\u05e8\u05dc\u05d9\u05db\u05e7\u05d9\u05d9\u05d8"
    ],
    "wof:name":"Piety",
    "wof:placetype":"locality"
},
  "geometry": {"coordinates":[20.68658,51.1361],"type":"Point"}
}