{
  "type": "Feature",
  "properties": {
    "gn:admin1_code":"81.0",
    "gn:admin2_code":"2002.0",
    "gn:admin3_code":"200214.0",
    "gn:asciiname":"Gnieciuki",
    "gn:country_code":"PL",
    "gn:dem":149,
    "gn:feature_class":"P",
    "gn:feature_code":"PPL",
    "gn:name":"Gnieciuki",
    "gn:population":0,
    "gn:timezone":"Europe/Warsaw",
    "iso:country":"PL",
    "name:azb_x_preferred":[
        "\u0642\u0646\u0642\u0686\u06cc\u0648\u06a9\u06cc"
    ],
    "name:fas_x_preferred":[
        "\u06af\u0646\u06af\u0686\u06cc\u0648\u06a9\u06cc"
    ],
    "name:lit_x_preferred":[
        "Gneciukai"
    ],
    "name:pol_x_preferred":[
        "Gnieciuki"
    ],
    "name:ukr_x_preferred":[
        "\u0490\u043d\u0435\u0446\u044e\u043a\u0438"
    ],
    "wof:name":"Gnieciuki",
    "wof:placetype":"locality"
},
  "geometry": {"coordinates":[23.36707,52.99216],"type":"Point"}
}