{
  "type": "Feature",
  "properties": {
    "gn:admin1_code":"78.0",
    "gn:admin2_code":"1403.0",
    "gn:admin3_code":"140312.0",
    "gn:asciiname":"Elzbietow",
    "gn:country_code":"PL",
    "gn:dem":182,
    "gn:feature_class":"P",
    "gn:feature_code":"PPL",
    "gn:name":"El\u017cbiet\u00f3w",
    "gn:population":0,
    "gn:timezone":"Europe/Warsaw",
    "iso:country":"PL",
    "wof:name":"Elzbietow",
    "wof:placetype":"locality"
},
  "geometry": {"coordinates":[21.81531,51.73241],"type":"Point"}
}