{
  "type": "Feature",
  "properties": {
    "gn:admin1_code":"78.0",
    "gn:asciiname":"Tychow Nowy",
    "gn:country_code":"PL",
    "gn:dem":195,
    "gn:feature_class":"P",
    "gn:feature_code":"PPL",
    "gn:name":"Tych\u00f3w Nowy",
    "gn:population":0,
    "gn:timezone":"Europe/Warsaw",
    "iso:country":"PL",
    "name:ceb_x_preferred":[
        "Tych\u00f3w Nowy"
    ],
    "name:pol_x_preferred":[
        "Tych\u00f3w Nowy"
    ],
    "name:szl_x_preferred":[
        "Nowy Tych\u016fw"
    ],
    "name:ukr_x_preferred":[
        "\u0422\u0438\u0445\u0443\u0432-\u041d\u043e\u0432\u0438\u0439"
    ],
    "wof:name":"Tychow Nowy",
    "wof:placetype":"locality"
},
  "geometry": {"coordinates":[21.10791,51.13877],"type":"Point"}
}