{
  "type": "Feature",
  "properties": {
    "gn:admin1_code":"74.0",
    "gn:admin2_code":"1021.0",
    "gn:admin3_code":"102105.0",
    "gn:asciiname":"Przylek Duzy",
    "gn:country_code":"PL",
    "gn:dem":212,
    "gn:feature_class":"P",
    "gn:feature_code":"PPL",
    "gn:name":"Przy\u0142\u0119k Du\u017cy",
    "gn:population":0,
    "gn:timezone":"Europe/Warsaw",
    "iso:country":"PL",
    "name:fra_x_preferred":[
        "Przy\u0142\u0119k Du\u017cy"
    ],
    "name:pol_x_preferred":[
        "Przy\u0142\u0119k Du\u017cy"
    ],
    "name:ukr_x_preferred":[
        "\u041f\u0448\u0438\u043b\u0435\u043d\u043a-\u0414\u0443\u0436\u0438"
    ],
    "name:und_x_variant":[
        "Przy\u0142\u0119k Du\u017cy"
    ],
    "wof:name":"Przylek Duzy",
    "wof:placetype":"locality"
},
  "geometry": {"coordinates":[19.90772,51.84341],"type":"Point"}
}