{
  "type": "Feature",
  "properties": {
    "gn:admin1_code":"79.0",
    "gn:admin2_code":"1606.0",
    "gn:admin3_code":"160602.0",
    "gn:asciiname":"Jastrzebie",
    "gn:country_code":"PL",
    "gn:dem":162,
    "gn:feature_class":"P",
    "gn:feature_code":"PPL",
    "gn:name":"Jastrz\u0119bie",
    "gn:population":0,
    "gn:timezone":"Europe/Warsaw",
    "iso:country":"PL",
    "name:azb_x_preferred":[
        "\u06cc\u0627\u0633\u062a\u0698\u0646\u0628\u06cc\u0647"
    ],
    "name:deu_x_preferred":[
        "Jastrz\u0119bie"
    ],
    "name:fas_x_preferred":[
        "\u06cc\u0627\u0633\u062a\u0698\u0646\u0628\u06cc\u0647"
    ],
    "name:pol_x_preferred":[
        "Jastrz\u0119bie"
    ],
    "name:ukr_x_preferred":[
        "\u042f\u0441\u0442\u0448\u0435\u043c\u0431\u0435"
    ],
    "name:und_x_variant":[
        "Nassadel"
    ],
    "name:urd_x_preferred":[
        "\u062c\u0633\u062a\u0631\u0632\u06cc\u0628\u06d2"
    ],
    "wof:name":"Jastrzebie",
    "wof:placetype":"locality"
},
  "geometry": {"coordinates":[17.75416,51.01595],"type":"Point"}
}