{
  "type": "Feature",
  "properties": {
    "gn:admin1_code":"79.0",
    "gn:admin2_code":"1606.0",
    "gn:admin3_code":"160602.0",
    "gn:asciiname":"Jastrzebie",
    "gn:country_code":"PL",
    "gn:dem":162,
    "gn:feature_class":"P",
    "gn:feature_code":"PPL",
    "gn:name":"Jastrz\u0119bie",
    "gn:population":0,
    "gn:timezone":"Europe/Warsaw",
    "iso:country":"PL",
    "name:und_x_variant":[
        "Nassadel",
        "Jastrz\u0119bie"
    ],
    "wof:name":"Jastrzebie",
    "wof:placetype":"locality"
},
  "geometry": {"coordinates":[17.75416,51.01595],"type":"Point"}
}