{
  "type": "Feature",
  "properties": {
    "gn:admin1_code":"74.0",
    "gn:admin2_code":"1021.0",
    "gn:admin3_code":"102103.0",
    "gn:asciiname":"Teresin",
    "gn:country_code":"PL",
    "gn:dem":182,
    "gn:feature_class":"P",
    "gn:feature_code":"PPL",
    "gn:name":"Teresin",
    "gn:population":0,
    "gn:timezone":"Europe/Warsaw",
    "iso:country":"PL",
    "name:ceb_x_preferred":[
        "Teresin"
    ],
    "name:deu_x_preferred":[
        "Teresin"
    ],
    "name:fra_x_preferred":[
        "Teresin"
    ],
    "name:nld_x_preferred":[
        "Teresin"
    ],
    "name:pol_x_preferred":[
        "Teresin"
    ],
    "name:ukr_x_preferred":[
        "\u0422\u0435\u0440\u0435\u0441\u0456\u043d"
    ],
    "wof:name":"Teresin",
    "wof:placetype":"locality"
},
  "geometry": {"coordinates":[19.86518,51.91684],"type":"Point"}
}