{
  "type": "Feature",
  "properties": {
    "gn:admin1_code":"74.0",
    "gn:admin2_code":"1021.0",
    "gn:admin3_code":"102103.0",
    "gn:asciiname":"Teresin",
    "gn:country_code":"PL",
    "gn:dem":182,
    "gn:feature_class":"P",
    "gn:feature_code":"PPL",
    "gn:name":"Teresin",
    "gn:population":0,
    "gn:timezone":"Europe/Warsaw",
    "iso:country":"PL",
    "wof:name":"Teresin",
    "wof:placetype":"locality"
},
  "geometry": {"coordinates":[19.86518,51.91684],"type":"Point"}
}