{
  "type": "Feature",
  "properties": {
    "gn:admin1_code":"86.0",
    "gn:admin2_code":"3012.0",
    "gn:admin3_code":"301203.0",
    "gn:asciiname":"Lipowiec",
    "gn:country_code":"PL",
    "gn:dem":139,
    "gn:feature_class":"P",
    "gn:feature_code":"PPL",
    "gn:name":"Lipowiec",
    "gn:population":0,
    "gn:timezone":"Europe/Warsaw",
    "iso:country":"PL",
    "name:fra_x_preferred":[
        "Lipowiec"
    ],
    "name:pol_x_preferred":[
        "Lipowiec"
    ],
    "name:ukr_x_preferred":[
        "\u041b\u0456\u043f\u043e\u0432\u0435\u0446\u044c"
    ],
    "wof:name":"Lipowiec",
    "wof:placetype":"locality"
},
  "geometry": {"coordinates":[17.46191,51.80861],"type":"Point"}
}