{
  "type": "Feature",
  "properties": {
    "gn:admin1_code":"84.0",
    "gn:admin2_code":"2604.0",
    "gn:admin3_code":"260404.0",
    "gn:asciiname":"Grabowiec",
    "gn:cc2":"PL",
    "gn:country_code":"PL",
    "gn:dem":261,
    "gn:feature_class":"P",
    "gn:feature_code":"PPL",
    "gn:name":"Grabowiec",
    "gn:population":0,
    "gn:timezone":"Europe/Warsaw",
    "iso:country":"PL",
    "name:ceb_x_preferred":[
        "Grabowiec"
    ],
    "name:pol_x_preferred":[
        "Grabowiec"
    ],
    "name:ukr_x_preferred":[
        "\u0490\u0440\u0430\u0431\u043e\u0432\u0435\u0446\u044c"
    ],
    "name:und_x_variant":[
        "Grabowice"
    ],
    "wof:name":"Grabowiec",
    "wof:placetype":"locality"
},
  "geometry": {"coordinates":[20.64142,50.67057],"type":"Point"}
}