{
  "type": "Feature",
  "properties": {
    "gn:admin1_code":"80.0",
    "gn:admin2_code":"1820.0",
    "gn:admin3_code":"182001.0",
    "gn:asciiname":"Suchorzow",
    "gn:country_code":"PL",
    "gn:dem":147,
    "gn:feature_class":"P",
    "gn:feature_code":"PPL",
    "gn:name":"Suchorz\u00f3w",
    "gn:population":0,
    "gn:timezone":"Europe/Warsaw",
    "iso:country":"PL",
    "name:pol_x_preferred":[
        "Suchorz\u00f3w"
    ],
    "name:ukr_x_preferred":[
        "\u0421\u0443\u0445\u043e\u0436\u0443\u0432"
    ],
    "wof:name":"Suchorzow",
    "wof:placetype":"locality"
},
  "geometry": {"coordinates":[21.57286,50.50349],"type":"Point"}
}