{
  "type": "Feature",
  "properties": {
    "gn:admin1_code":"75.0",
    "gn:admin2_code":"620.0",
    "gn:admin3_code":"62003.0",
    "gn:asciiname":"Wolica Sniatycka",
    "gn:country_code":"PL",
    "gn:dem":222,
    "gn:feature_class":"P",
    "gn:feature_code":"PPL",
    "gn:name":"Wolica \u015aniatycka",
    "gn:population":0,
    "gn:timezone":"Europe/Warsaw",
    "iso:country":"PL",
    "name:und_x_variant":[
        "Wolica \u015aniatycka"
    ],
    "wof:name":"Wolica Sniatycka",
    "wof:placetype":"locality"
},
  "geometry": {"coordinates":[23.44095,50.66061],"type":"Point"}
}