{
  "type": "Feature",
  "properties": {
    "gn:admin1_code":"75.0",
    "gn:admin2_code":"620.0",
    "gn:admin3_code":"62003.0",
    "gn:asciiname":"Wolica Sniatycka",
    "gn:country_code":"PL",
    "gn:dem":222,
    "gn:feature_class":"P",
    "gn:feature_code":"PPL",
    "gn:name":"Wolica \u015aniatycka",
    "gn:population":0,
    "gn:timezone":"Europe/Warsaw",
    "iso:country":"PL",
    "name:fra_x_preferred":[
        "Wolica \u015aniatycka"
    ],
    "name:pol_x_preferred":[
        "Wolica \u015aniatycka"
    ],
    "name:ukr_x_preferred":[
        "\u0412\u043e\u043b\u0438\u0446\u044f-\u0421\u043d\u044f\u0442\u0438\u0446\u044c\u043a\u0430"
    ],
    "wof:name":"Wolica Sniatycka",
    "wof:placetype":"locality"
},
  "geometry": {"coordinates":[23.44095,50.66061],"type":"Point"}
}