{
  "type": "Feature",
  "properties": {
    "gn:admin1_code":"73.0",
    "gn:admin2_code":"418.0",
    "gn:admin3_code":"41806.0",
    "gn:asciiname":"Prosno",
    "gn:country_code":"PL",
    "gn:dem":126,
    "gn:feature_class":"P",
    "gn:feature_code":"PPL",
    "gn:name":"Prosno",
    "gn:population":0,
    "gn:timezone":"Europe/Warsaw",
    "iso:country":"PL",
    "name:pol_x_preferred":[
        "Prosno"
    ],
    "name:ukr_x_preferred":[
        "\u041f\u0440\u043e\u0441\u043d\u043e"
    ],
    "wof:name":"Prosno",
    "wof:placetype":"locality"
},
  "geometry": {"coordinates":[19.10354,52.38983],"type":"Point"}
}