{
  "type": "Feature",
  "properties": {
    "gn:admin1_code":"82.0",
    "gn:admin2_code":"2212.0",
    "gn:admin3_code":"221206.0",
    "gn:asciiname":"Lebun",
    "gn:country_code":"PL",
    "gn:dem":46,
    "gn:feature_class":"P",
    "gn:feature_code":"PPL",
    "gn:name":"Lebu\u0144",
    "gn:population":0,
    "gn:timezone":"Europe/Warsaw",
    "iso:country":"PL",
    "wof:name":"Lebun",
    "wof:placetype":"locality"
},
  "geometry": {"coordinates":[17.07175,54.38346],"type":"Point"}
}