{
  "type": "Feature",
  "properties": {
    "gn:gn_country":"PL",
    "gn:gn_fcode":"PPL",
    "gn:gn_pop":198,
    "gn:population":198,
    "iso:country":"PL",
    "name:ceb_x_preferred":[
        "Adam\u00f3w"
    ],
    "name:deu_x_preferred":[
        "Adamow"
    ],
    "name:fra_x_preferred":[
        "Adam\u00f3w"
    ],
    "name:ita_x_preferred":[
        "Adam\u00f3w"
    ],
    "name:nld_x_preferred":[
        "Adam\u00f3w"
    ],
    "name:pol_x_preferred":[
        "Adam\u00f3w"
    ],
    "name:rus_x_preferred":[
        "\u0410\u0434\u0430\u043c\u0443\u0432"
    ],
    "name:ukr_x_preferred":[
        "\u0410\u0434\u0430\u043c\u0443\u0432"
    ],
    "qs_pg:aaroncc":"PL",
    "qs_pg:gn_country":"PL",
    "qs_pg:gn_fcode":"PPL",
    "qs_pg:gn_pop":198,
    "qs_pg:name":"Adam\u00f3w",
    "qs_pg:name_adm0":"Polska",
    "qs_pg:name_adm1":"Mazowieckie",
    "qs_pg:photos_9r":0,
    "qs_pg:photos_sr":0,
    "qs_pg:pop_sr":1,
    "qs_pg:qs_pg_placetype":"locality",
    "qs_pg:qs_pg_placetype_gp":"Town",
    "qs_pg:woe_adm0":23424923,
    "woe:adm0_id":23424923,
    "woe:name_adm0":"Polska",
    "woe:name_adm1":"Mazowieckie",
    "woe:placetype":"Town",
    "wof:name":"Adam\u00f3w",
    "wof:placetype":"locality",
    "wof:population":198
},
  "geometry": {"coordinates":[19.64381,52.34058],"type":"Point"}
}