{
  "type": "Feature",
  "properties": {
    "gn:admin1_code":"73.0",
    "gn:admin2_code":"411.0",
    "gn:admin3_code":"41103.0",
    "gn:asciiname":"Klonowo",
    "gn:country_code":"PL",
    "gn:dem":90,
    "gn:feature_class":"P",
    "gn:feature_code":"PPL",
    "gn:name":"Klonowo",
    "gn:population":0,
    "gn:timezone":"Europe/Warsaw",
    "iso:country":"PL",
    "name:pol_x_preferred":[
        "K\u0142onowo"
    ],
    "name:ukr_x_preferred":[
        "\u041a\u043b\u043e\u043d\u043e\u0432\u043e"
    ],
    "wof:name":"Klonowo",
    "wof:placetype":"locality"
},
  "geometry": {"coordinates":[18.60336,52.65016],"type":"Point"}
}