{
  "type": "Feature",
  "properties": {
    "gn:admin1_code":"78.0",
    "gn:asciiname":"Jukow",
    "gn:country_code":"PL",
    "gn:dem":122,
    "gn:feature_class":"P",
    "gn:feature_code":"PPL",
    "gn:name":"Juk\u00f3w",
    "gn:population":0,
    "gn:timezone":"Europe/Warsaw",
    "iso:country":"PL",
    "name:fra_x_preferred":[
        "Juk\u00f3w"
    ],
    "name:pol_x_preferred":[
        "Juk\u00f3w"
    ],
    "name:ukr_x_preferred":[
        "\u042e\u043a\u0443\u0432"
    ],
    "wof:name":"Jukow",
    "wof:placetype":"locality"
},
  "geometry": {"coordinates":[19.31465,52.36271],"type":"Point"}
}