{
  "type": "Feature",
  "properties": {
    "gn:admin1_code":"78.0",
    "gn:admin2_code":"1426.0",
    "gn:admin3_code":"142607.0",
    "gn:asciiname":"Tarkow",
    "gn:country_code":"PL",
    "gn:dem":171,
    "gn:feature_class":"P",
    "gn:feature_code":"PPL",
    "gn:name":"Tark\u00f3w",
    "gn:population":0,
    "gn:timezone":"Europe/Warsaw",
    "iso:country":"PL",
    "name:azb_x_preferred":[
        "\u062a\u0627\u0631\u06a9\u0648\u0648"
    ],
    "name:fas_x_preferred":[
        "\u062a\u0627\u0631\u06a9\u0648\u0648"
    ],
    "name:fra_x_preferred":[
        "Tark\u00f3w"
    ],
    "name:lit_x_preferred":[
        "Tarkuvas"
    ],
    "name:pol_x_preferred":[
        "Tark\u00f3w"
    ],
    "name:szl_x_preferred":[
        "Tark\u016fw"
    ],
    "name:ukr_x_preferred":[
        "\u0422\u0430\u0440\u043a\u0443\u0432"
    ],
    "wof:name":"Tarkow",
    "wof:placetype":"locality"
},
  "geometry": {"coordinates":[22.52343,52.26049],"type":"Point"}
}