{
  "type": "Feature",
  "properties": {
    "gn:population":2276,
    "iso:country":"PL",
    "name:ast_x_preferred":[
        "Lubichowo"
    ],
    "name:ceb_x_preferred":[
        "Lubichowo"
    ],
    "name:deu_x_preferred":[
        "Lubichowo"
    ],
    "name:eng_x_preferred":[
        "Lubichowo"
    ],
    "name:fas_x_preferred":[
        "\u0644\u0648\u0628\u06cc\u062e\u0648\u0648\u0648"
    ],
    "name:fra_x_preferred":[
        "Lubichowo"
    ],
    "name:gle_x_preferred":[
        "Lubichowo"
    ],
    "name:glv_x_preferred":[
        "Lubichowo"
    ],
    "name:nan_x_preferred":[
        "Lubichowo"
    ],
    "name:nld_x_preferred":[
        "Lubichowo"
    ],
    "name:pol_x_preferred":[
        "Lubichowo"
    ],
    "name:ukr_x_preferred":[
        "\u041b\u044e\u0431\u0456\u0445\u043e\u0432\u043e"
    ],
    "name:zho_min_nan_x_preferred":[
        "Lubichowo"
    ],
    "qs:a0":"Rzeczpospolita Polska",
    "qs:a1":"*Pomorskie",
    "qs:a1r":"0",
    "qs:a2":"Starogardzki",
    "qs:adm0":"Rzeczpospolita Polska",
    "qs:la":"Lubichowo",
    "qs:la_lc":"*PL2213062",
    "qs:level":"locality",
    "qs:loc":"Lubichowo",
    "qs:loc_alt":"Lubichowo",
    "qs:pop":0,
    "qs:type":"rural point-in-poly",
    "wd:wordcount":105,
    "wof:name":"Lubichowo",
    "wof:placetype":"locality",
    "wof:population":2276
},
  "geometry": {"coordinates":[18.3723321113276,53.8251544211832],"type":"Point"}
}