{
  "type": "Feature",
  "properties": {
    "gn:admin1_code":"84.0",
    "gn:admin2_code":"2606.0",
    "gn:admin3_code":"260605.0",
    "gn:asciiname":"Srodborze-Klin",
    "gn:country_code":"PL",
    "gn:dem":175,
    "gn:feature_class":"P",
    "gn:feature_code":"PPL",
    "gn:name":"Sr\u00f3dborze-Klin",
    "gn:population":0,
    "gn:timezone":"Europe/Warsaw",
    "iso:country":"PL",
    "wof:name":"Srodborze-Klin",
    "wof:placetype":"locality"
},
  "geometry": {"coordinates":[21.60477,50.90466],"type":"Point"}
}