{
  "type": "Feature",
  "properties": {
    "gn:admin1_code":"75.0",
    "gn:admin2_code":"612.0",
    "gn:admin3_code":"61205.0",
    "gn:asciiname":"Grobla",
    "gn:country_code":"PL",
    "gn:dem":151,
    "gn:feature_class":"P",
    "gn:feature_code":"PPL",
    "gn:name":"Grobla",
    "gn:population":0,
    "gn:timezone":"Europe/Warsaw",
    "iso:country":"PL",
    "name:fra_x_preferred":[
        "Grobla"
    ],
    "name:pol_x_preferred":[
        "Grobla"
    ],
    "name:ukr_x_preferred":[
        "\u0490\u0440\u043e\u0431\u043b\u044f"
    ],
    "wof:name":"Grobla",
    "wof:placetype":"locality"
},
  "geometry": {"coordinates":[21.95,51.18333],"type":"Point"}
}