{
  "type": "Feature",
  "properties": {
    "gn:admin1_code":"85.0",
    "gn:admin2_code":"2805.0",
    "gn:admin3_code":"280504.0",
    "gn:asciiname":"Dlugosze",
    "gn:country_code":"PL",
    "gn:dem":126,
    "gn:feature_class":"P",
    "gn:feature_code":"PPL",
    "gn:name":"D\u0142ugosze",
    "gn:population":0,
    "gn:timezone":"Europe/Warsaw",
    "iso:country":"PL",
    "name:azb_x_preferred":[
        "\u062f\u0648\u0648\u0642\u0648\u0634\u0647"
    ],
    "name:deu_x_preferred":[
        "D\u0142ugosze"
    ],
    "name:fas_x_preferred":[
        "\u062f\u0648\u0648\u06af\u0648\u0634\u0647"
    ],
    "name:fra_x_preferred":[
        "D\u0142ugosze"
    ],
    "name:pol_x_preferred":[
        "D\u0142ugosze"
    ],
    "name:ukr_x_preferred":[
        "\u0414\u043b\u0443\u0491\u043e\u0448\u0435"
    ],
    "name:und_x_variant":[
        "Langheide",
        "Dlugossen",
        "D\u0142ugosze"
    ],
    "wof:name":"Dlugosze",
    "wof:placetype":"locality"
},
  "geometry": {"coordinates":[22.49571,53.71561],"type":"Point"}
}