{
  "type": "Feature",
  "properties": {
    "gn:admin1_code":"84.0",
    "gn:admin2_code":"2609.0",
    "gn:admin3_code":"260902.0",
    "gn:asciiname":"Msciow",
    "gn:country_code":"PL",
    "gn:dem":138,
    "gn:feature_class":"P",
    "gn:feature_code":"PPL",
    "gn:name":"M\u015bci\u00f3w",
    "gn:population":0,
    "gn:timezone":"Europe/Warsaw",
    "iso:country":"PL",
    "name:ceb_x_preferred":[
        "M\u015bci\u00f3w"
    ],
    "name:pol_x_preferred":[
        "M\u015bci\u00f3w"
    ],
    "name:ukr_x_preferred":[
        "\u041c\u0441\u0446\u044e\u0432"
    ],
    "wof:name":"Msciow",
    "wof:placetype":"locality"
},
  "geometry": {"coordinates":[21.807,50.71266],"type":"Point"}
}