{
  "type": "Feature",
  "properties": {
    "gn:admin1_code":"80.0",
    "gn:admin2_code":"1805.0",
    "gn:admin3_code":"180506.0",
    "gn:asciiname":"Rostajne",
    "gn:country_code":"PL",
    "gn:dem":419,
    "gn:feature_class":"P",
    "gn:feature_code":"PPL",
    "gn:name":"Rostajne",
    "gn:population":0,
    "gn:timezone":"Europe/Warsaw",
    "iso:country":"PL",
    "wof:name":"Rostajne",
    "wof:placetype":"locality"
},
  "geometry": {"coordinates":[21.42523,49.49523],"type":"Point"}
}