{
  "type": "Feature",
  "properties": {
    "gn:admin1_code":"72.0",
    "gn:admin2_code":"225.0",
    "gn:admin3_code":"22506.0",
    "gn:asciiname":"Nowiny",
    "gn:country_code":"PL",
    "gn:dem":153,
    "gn:feature_class":"P",
    "gn:feature_code":"PPL",
    "gn:name":"Nowiny",
    "gn:population":0,
    "gn:timezone":"Europe/Warsaw",
    "iso:country":"PL",
    "wof:name":"Nowiny",
    "wof:placetype":"locality"
},
  "geometry": {"coordinates":[15.26667,51.43333],"type":"Point"}
}