{
  "type": "Feature",
  "properties": {
    "iso:country":"PL",
    "name:eng_x_preferred":[
        "Psie Pole"
    ],
    "name:pol_x_preferred":[
        "Psie Pole"
    ],
    "wof:name":"Psie Pole",
    "wof:placetype":"neighbourhood"
},
  "geometry": {"coordinates":[17.11348580767418,51.14510207147143],"type":"Point"}
}