{
  "type": "Feature",
  "properties": {
    "gn:admin1_code":"84.0",
    "gn:admin2_code":"2605.0",
    "gn:admin3_code":"260503.0",
    "gn:asciiname":"Bedlno",
    "gn:country_code":"PL",
    "gn:dem":223,
    "gn:feature_class":"P",
    "gn:feature_code":"PPL",
    "gn:name":"Bedlno",
    "gn:population":0,
    "gn:timezone":"Europe/Warsaw",
    "iso:country":"PL",
    "name:ceb_x_preferred":[
        "Bedlno"
    ],
    "name:pol_x_preferred":[
        "Bedlno"
    ],
    "name:ukr_x_preferred":[
        "\u0411\u0435\u0434\u043b\u044c\u043d\u043e"
    ],
    "wof:name":"Bedlno",
    "wof:placetype":"locality"
},
  "geometry": {"coordinates":[20.2699,51.20433],"type":"Point"}
}