{
  "type": "Feature",
  "properties": {
    "gn:admin1_code":"72.0",
    "gn:admin2_code":"223.0",
    "gn:admin3_code":"22304.0",
    "gn:asciiname":"Sadkow",
    "gn:country_code":"PL",
    "gn:dem":137,
    "gn:feature_class":"P",
    "gn:feature_code":"PPL",
    "gn:name":"Sadk\u00f3w",
    "gn:population":0,
    "gn:timezone":"Europe/Warsaw",
    "iso:country":"PL",
    "name:bul_x_preferred":[
        "\u0421\u0430\u0434\u043a\u0443\u0432"
    ],
    "name:pol_x_preferred":[
        "Sadk\u00f3w"
    ],
    "name:ukr_x_preferred":[
        "\u0421\u0430\u0434\u043a\u0443\u0432"
    ],
    "wof:name":"Sadkow",
    "wof:placetype":"locality"
},
  "geometry": {"coordinates":[16.83655,51.04927],"type":"Point"}
}