{
  "type": "Feature",
  "properties": {
    "gn:admin1_code":"80.0",
    "gn:admin2_code":"1804.0",
    "gn:admin3_code":"180404.0",
    "gn:asciiname":"Sobiecin",
    "gn:country_code":"PL",
    "gn:dem":183,
    "gn:feature_class":"P",
    "gn:feature_code":"PPL",
    "gn:name":"Sobiecin",
    "gn:population":0,
    "gn:timezone":"Europe/Warsaw",
    "iso:country":"PL",
    "name:pol_x_preferred":[
        "Sobiecin"
    ],
    "name:ukr_x_preferred":[
        "\u0421\u043e\u0431'\u044f\u0442\u0438\u043d"
    ],
    "wof:name":"Sobiecin",
    "wof:placetype":"locality"
},
  "geometry": {"coordinates":[22.73734,50.01943],"type":"Point"}
}