{
  "type": "Feature",
  "properties": {
    "gn:admin1_code":"82.0",
    "gn:admin2_code":"2205.0",
    "gn:admin3_code":"220502.0",
    "gn:asciiname":"Brodnica Dolna",
    "gn:country_code":"PL",
    "gn:dem":164,
    "gn:feature_class":"P",
    "gn:feature_code":"PPL",
    "gn:name":"Brodnica Dolna",
    "gn:population":0,
    "gn:timezone":"Europe/Warsaw",
    "iso:country":"PL",
    "name:ceb_x_preferred":[
        "Brodnica Dolna"
    ],
    "name:csb_x_preferred":[
        "D\u00f3ln\u00f4 Brodnica"
    ],
    "name:deu_x_preferred":[
        "Brodnica Dolna"
    ],
    "name:eng_x_preferred":[
        "Brodnica Dolna"
    ],
    "name:pol_x_preferred":[
        "Brodnica Dolna"
    ],
    "name:rus_x_preferred":[
        "\u0411\u0440\u043e\u0434\u043d\u0438\u0446\u0430 \u0413\u0443\u0440\u043d\u0430"
    ],
    "name:ukr_x_preferred":[
        "\u0411\u0440\u043e\u0434\u043d\u0438\u0446\u044f-\u0414\u043e\u043b\u044c\u043d\u0430"
    ],
    "wof:name":"Brodnica Dolna",
    "wof:placetype":"locality"
},
  "geometry": {"coordinates":[18.09724,54.264],"type":"Point"}
}