{
  "type": "Feature",
  "properties": {
    "gn:admin1_code":"87.0",
    "gn:admin2_code":"3213.0",
    "gn:admin3_code":"321304.0",
    "gn:asciiname":"Bartolino",
    "gn:country_code":"PL",
    "gn:dem":19,
    "gn:feature_class":"P",
    "gn:feature_code":"PPL",
    "gn:name":"Bartolino",
    "gn:population":0,
    "gn:timezone":"Europe/Warsaw",
    "iso:country":"PL",
    "wof:name":"Bartolino",
    "wof:placetype":"locality"
},
  "geometry": {"coordinates":[16.51111,54.27531],"type":"Point"}
}