{
  "type": "Feature",
  "properties": {
    "gn:admin1_code":"87.0",
    "gn:admin2_code":"3213.0",
    "gn:admin3_code":"321304.0",
    "gn:asciiname":"Bartolino",
    "gn:country_code":"PL",
    "gn:dem":19,
    "gn:feature_class":"P",
    "gn:feature_code":"PPL",
    "gn:name":"Bartolino",
    "gn:population":0,
    "gn:timezone":"Europe/Warsaw",
    "iso:country":"PL",
    "name:azb_x_preferred":[
        "\u0628\u0627\u0631\u062a\u0648\u0644\u06cc\u0646\u0648"
    ],
    "name:ceb_x_preferred":[
        "Bartolino"
    ],
    "name:deu_x_preferred":[
        "Bartolino"
    ],
    "name:fas_x_preferred":[
        "\u0628\u0627\u0631\u062a\u0648\u0644\u06cc\u0646\u0648"
    ],
    "name:nld_x_preferred":[
        "Bartolino"
    ],
    "name:pol_x_preferred":[
        "Bartolino"
    ],
    "name:ukr_x_preferred":[
        "\u0411\u0430\u0440\u0442\u043e\u043b\u0456\u043d\u043e"
    ],
    "name:vie_x_preferred":[
        "Bartolino"
    ],
    "wof:name":"Bartolino",
    "wof:placetype":"locality"
},
  "geometry": {"coordinates":[16.51111,54.27531],"type":"Point"}
}