{
  "type": "Feature",
  "properties": {
    "gn:admin1_code":"83.0",
    "gn:admin2_code":"2473.0",
    "gn:admin3_code":"247301.0",
    "gn:asciiname":"Klokocin",
    "gn:country_code":"PL",
    "gn:dem":261,
    "gn:feature_class":"P",
    "gn:feature_code":"PPL",
    "gn:name":"K\u0142okocin",
    "gn:population":0,
    "gn:timezone":"Europe/Warsaw",
    "iso:country":"PL",
    "name:pol_x_preferred":[
        "K\u0142okocin"
    ],
    "name:vie_x_preferred":[
        "K\u0142okocin"
    ],
    "wof:name":"Klokocin",
    "wof:placetype":"neighbourhood"
},
  "geometry": {"coordinates":[18.63148,50.05238],"type":"Point"}
}