{
  "type": "Feature",
  "properties": {
    "gn:admin1_code":"84.0",
    "gn:admin2_code":"2604.0",
    "gn:admin3_code":"260416.0",
    "gn:asciiname":"Rembow",
    "gn:cc2":"PL",
    "gn:country_code":"PL",
    "gn:dem":265,
    "gn:feature_class":"P",
    "gn:feature_code":"PPL",
    "gn:name":"Remb\u00f3w",
    "gn:population":0,
    "gn:timezone":"Europe/Warsaw",
    "iso:country":"PL",
    "name:pol_x_preferred":[
        "Remb\u00f3w"
    ],
    "name:ukr_x_preferred":[
        "\u0420\u0435\u043c\u0431\u0443\u0432"
    ],
    "name:und_x_variant":[
        "R\u0119b\u00f3w"
    ],
    "wof:name":"Rembow",
    "wof:placetype":"locality"
},
  "geometry": {"coordinates":[21.04757,50.70929],"type":"Point"}
}