{
  "type": "Feature",
  "properties": {
    "iso:country":"PL",
    "name:eng_x_preferred":[
        "Osiedle Kopernika"
    ],
    "name:pol_x_preferred":[
        "Osiedle Kopernika"
    ],
    "name:pol_x_variant":[
        "Osiedle im. Miko\u0142aja Kopernika"
    ],
    "wof:name":"Osiedle Kopernika",
    "wof:placetype":"neighbourhood"
},
  "geometry": {"coordinates":[16.86336174521019,52.38550049575002],"type":"Point"}
}