{
  "type": "Feature",
  "properties": {
    "gn:admin1_code":"73.0",
    "gn:admin2_code":"403.0",
    "gn:admin3_code":"40307.0",
    "gn:asciiname":"Kruszyn",
    "gn:country_code":"PL",
    "gn:dem":89,
    "gn:feature_class":"P",
    "gn:feature_code":"PPL",
    "gn:name":"Kruszyn",
    "gn:population":0,
    "gn:timezone":"Europe/Warsaw",
    "iso:country":"PL",
    "name:fra_x_preferred":[
        "Kruszyn"
    ],
    "name:pol_x_preferred":[
        "Kruszyn"
    ],
    "name:ukr_x_preferred":[
        "\u041a\u0440\u0443\u0448\u0438\u043d"
    ],
    "wof:name":"Kruszyn",
    "wof:placetype":"locality"
},
  "geometry": {"coordinates":[17.84019,53.15792],"type":"Point"}
}