{
  "type": "Feature",
  "properties": {
    "gn:admin1_code":"80.0",
    "gn:admin2_code":"1803.0",
    "gn:admin3_code":"180307.0",
    "gn:asciiname":"Straszecin",
    "gn:country_code":"PL",
    "gn:dem":191,
    "gn:feature_class":"P",
    "gn:feature_code":"PPL",
    "gn:name":"Strasz\u0119cin",
    "gn:population":0,
    "gn:timezone":"Europe/Warsaw",
    "iso:country":"PL",
    "name:ceb_x_preferred":[
        "Strasz\u0119cin"
    ],
    "name:pol_x_preferred":[
        "Strasz\u0119cin"
    ],
    "name:ukr_x_preferred":[
        "\u0421\u0442\u0440\u0430\u0448\u0435\u043d\u0446\u0438\u043d"
    ],
    "wof:name":"Straszecin",
    "wof:placetype":"locality"
},
  "geometry": {"coordinates":[21.35848,50.06296],"type":"Point"}
}