{
  "type": "Feature",
  "properties": {
    "iso:country":"PL",
    "name:ast_x_preferred":[
        "Tuczna"
    ],
    "name:azb_x_preferred":[
        "\u062a\u0648\u0686\u0646\u0627"
    ],
    "name:deu_x_preferred":[
        "Tuczna"
    ],
    "name:eng_x_preferred":[
        "Tuczna"
    ],
    "name:fas_x_preferred":[
        "\u062a\u0648\u0686\u0646\u0627"
    ],
    "name:fra_x_preferred":[
        "Tuczna"
    ],
    "name:lit_x_preferred":[
        "Tu\u010dna"
    ],
    "name:nld_x_preferred":[
        "Tuczna"
    ],
    "name:pol_x_preferred":[
        "Tuczna"
    ],
    "name:ukr_x_preferred":[
        "\u0422\u0443\u0447\u043d\u0430"
    ],
    "qs:a0":"Rzeczpospolita Polska",
    "qs:a1":"*Lubelskie",
    "qs:a1r":"0",
    "qs:a2":"Bialski",
    "qs:adm0":"Rzeczpospolita Polska",
    "qs:la":"Tuczna",
    "qs:la_lc":"*PL0601172",
    "qs:level":"locality",
    "qs:loc":"Tuczna",
    "qs:loc_alt":"Tuczna",
    "qs:pop":0,
    "qs:type":"rural point-in-poly",
    "wd:wordcount":84,
    "wof:coterminous":[
        1477752173
    ],
    "wof:name":"Tuczna",
    "wof:placetype":"locality"
},
  "geometry": {"coordinates":[23.4317566001325,51.8594274669158],"type":"Point"}
}