{
  "type": "Feature",
  "properties": {
    "gn:admin1_code":"78.0",
    "gn:admin2_code":"1411.0",
    "gn:admin3_code":"141103.0",
    "gn:asciiname":"Rafaly",
    "gn:country_code":"PL",
    "gn:dem":107,
    "gn:feature_class":"P",
    "gn:feature_code":"PPL",
    "gn:name":"Rafa\u0142y",
    "gn:population":0,
    "gn:timezone":"Europe/Warsaw",
    "iso:country":"PL",
    "name:fra_x_preferred":[
        "Rafa\u0142y"
    ],
    "name:pol_x_preferred":[
        "Rafa\u0142y"
    ],
    "name:ukr_x_preferred":[
        "\u0420\u0430\u0444\u0430\u043b\u0438"
    ],
    "wof:name":"Rafaly",
    "wof:placetype":"locality"
},
  "geometry": {"coordinates":[20.95199,52.83941],"type":"Point"}
}