{
  "type": "Feature",
  "properties": {
    "gn:admin1_code":"87.0",
    "gn:admin2_code":"3206.0",
    "gn:admin3_code":"320609.0",
    "gn:asciiname":"Zarczyn",
    "gn:country_code":"PL",
    "gn:dem":78,
    "gn:feature_class":"P",
    "gn:feature_code":"PPL",
    "gn:name":"\u017barczyn",
    "gn:population":0,
    "gn:timezone":"Europe/Warsaw",
    "iso:country":"PL",
    "name:pol_x_preferred":[
        "\u017barczyn"
    ],
    "name:ukr_x_preferred":[
        "\u0416\u0430\u0440\u0447\u0438\u043d"
    ],
    "wof:name":"Zarczyn",
    "wof:placetype":"locality"
},
  "geometry": {"coordinates":[14.54899,53.09629],"type":"Point"}
}