{
  "type": "Feature",
  "properties": {
    "gn:admin1_code":"84.0",
    "gn:admin2_code":"2610.0",
    "gn:admin3_code":"261002.0",
    "gn:asciiname":"Zbrojow",
    "gn:country_code":"PL",
    "gn:dem":274,
    "gn:feature_class":"P",
    "gn:feature_code":"PPL",
    "gn:name":"Zbroj\u00f3w",
    "gn:population":0,
    "gn:timezone":"Europe/Warsaw",
    "iso:country":"PL",
    "name:ceb_x_preferred":[
        "Zbroj\u00f3w"
    ],
    "name:pol_x_preferred":[
        "Zbroj\u00f3w"
    ],
    "name:ukr_x_preferred":[
        "\u0417\u0431\u0440\u043e\u044e\u0432"
    ],
    "wof:name":"Zbrojow",
    "wof:placetype":"locality"
},
  "geometry": {"coordinates":[20.70582000000001,51.10591],"type":"Point"}
}