{
  "type": "Feature",
  "properties": {
    "gn:admin1_code":"79.0",
    "gn:admin2_code":"1602.0",
    "gn:admin3_code":"160203.0",
    "gn:asciiname":"Kietlice",
    "gn:country_code":"PL",
    "gn:dem":227,
    "gn:feature_class":"P",
    "gn:feature_code":"PPL",
    "gn:name":"Kietlice",
    "gn:population":0,
    "gn:timezone":"Europe/Warsaw",
    "iso:country":"PL",
    "name:pol_x_preferred":[
        "Kietlice"
    ],
    "name:ukr_x_preferred":[
        "\u041a\u0435\u0442\u043b\u0456\u0446\u0435"
    ],
    "wof:name":"Kietlice",
    "wof:placetype":"locality"
},
  "geometry": {"coordinates":[17.81322,50.27612],"type":"Point"}
}