{
  "type": "Feature",
  "properties": {
    "gn:admin1_code":"81.0",
    "gn:admin2_code":"2003.0",
    "gn:admin3_code":"200305.0",
    "gn:asciiname":"Chojewo",
    "gn:country_code":"PL",
    "gn:dem":139,
    "gn:feature_class":"P",
    "gn:feature_code":"PPL",
    "gn:name":"Chojewo",
    "gn:population":0,
    "gn:timezone":"Europe/Warsaw",
    "iso:country":"PL",
    "name:azb_x_preferred":[
        "\u062e\u0648\u06cc\u0648\u0648"
    ],
    "name:bel_x_preferred":[
        "\u0425\u0430\u0435\u0432\u0430"
    ],
    "name:fas_x_preferred":[
        "\u062e\u0648\u06cc\u0648\u0648"
    ],
    "name:fra_x_preferred":[
        "Chojewo"
    ],
    "name:lit_x_preferred":[
        "Chojevas"
    ],
    "name:pol_x_preferred":[
        "Chojewo"
    ],
    "name:ukr_x_preferred":[
        "\u0425\u043e\u0454\u0432\u043e"
    ],
    "wof:name":"Chojewo",
    "wof:placetype":"locality"
},
  "geometry": {"coordinates":[22.96332,52.70528],"type":"Point"}
}