{
  "type": "Feature",
  "properties": {
    "gn:admin1_code":"84.0",
    "gn:admin2_code":"2613.0",
    "gn:admin3_code":"261306.0",
    "gn:asciiname":"Nieznanowice",
    "gn:country_code":"PL",
    "gn:dem":236,
    "gn:feature_class":"P",
    "gn:feature_code":"PPL",
    "gn:name":"Nieznanowice",
    "gn:population":0,
    "gn:timezone":"Europe/Warsaw",
    "iso:country":"PL",
    "wof:name":"Nieznanowice",
    "wof:placetype":"locality"
},
  "geometry": {"coordinates":[19.91667,50.83333],"type":"Point"}
}