{
  "type": "Feature",
  "properties": {
    "gn:admin1_code":"83.0",
    "gn:admin2_code":"2416.0",
    "gn:admin3_code":"241607.0",
    "gn:asciiname":"Sierbowice",
    "gn:country_code":"PL",
    "gn:dem":350,
    "gn:feature_class":"P",
    "gn:feature_code":"PPL",
    "gn:name":"Sierbowice",
    "gn:population":0,
    "gn:timezone":"Europe/Warsaw",
    "iso:country":"PL",
    "name:deu_x_preferred":[
        "Sierbowice"
    ],
    "name:pol_x_preferred":[
        "Sierbowice"
    ],
    "name:ukr_x_preferred":[
        "\u0421\u0435\u0440\u0431\u043e\u0432\u0456\u0446\u0435"
    ],
    "wof:name":"Sierbowice",
    "wof:placetype":"locality"
},
  "geometry": {"coordinates":[19.65838,50.5222],"type":"Point"}
}