{
  "type": "Feature",
  "properties": {
    "gn:admin1_code":"86.0",
    "gn:admin2_code":"3005.0",
    "gn:admin3_code":"300504.0",
    "gn:asciiname":"Gnin",
    "gn:country_code":"PL",
    "gn:dem":92,
    "gn:feature_class":"P",
    "gn:feature_code":"PPL",
    "gn:name":"Gnin",
    "gn:population":0,
    "gn:timezone":"Europe/Warsaw",
    "iso:country":"PL",
    "name:fra_x_preferred":[
        "Gnin"
    ],
    "name:pol_x_preferred":[
        "Gnin"
    ],
    "name:ukr_x_preferred":[
        "\u0490\u043d\u0456\u043d"
    ],
    "wof:name":"Gnin",
    "wof:placetype":"locality"
},
  "geometry": {"coordinates":[16.30856,52.1931],"type":"Point"}
}