{
  "type": "Feature",
  "properties": {
    "gn:admin1_code":"86.0",
    "gn:admin2_code":"3003.0",
    "gn:admin3_code":"300306.0",
    "gn:asciiname":"Rzegnowo",
    "gn:country_code":"PL",
    "gn:dem":119,
    "gn:feature_class":"P",
    "gn:feature_code":"PPL",
    "gn:name":"Rzegnowo",
    "gn:population":0,
    "gn:timezone":"Europe/Warsaw",
    "iso:country":"PL",
    "name:fra_x_preferred":[
        "Rzegnowo"
    ],
    "name:pol_x_preferred":[
        "Rzegnowo"
    ],
    "name:ukr_x_preferred":[
        "\u0416\u0435\u0491\u043d\u043e\u0432\u043e"
    ],
    "wof:name":"Rzegnowo",
    "wof:placetype":"locality"
},
  "geometry": {"coordinates":[17.48457,52.53032],"type":"Point"}
}