{
  "type": "Feature",
  "properties": {
    "gn:population":1800,
    "iso:country":"PL",
    "name:azb_x_preferred":[
        "\u0642\u0645\u06cc\u0646\u0627 \u0686\u06cc\u0634\u06a9\u0648\u0648"
    ],
    "name:bel_x_preferred":[
        "\u0413\u043c\u0456\u043d\u0430 \u0426\u0435\u0448\u043a\u0430\u045e"
    ],
    "name:deu_x_preferred":[
        "Gmina Cieszk\u00f3w"
    ],
    "name:eng_x_preferred":[
        "Gmina Cieszk\u00f3w"
    ],
    "name:eus_x_preferred":[
        "Cieszk\u00f3w udalerria"
    ],
    "name:fas_x_preferred":[
        "\u06af\u0645\u06cc\u0646\u0627 \u0686\u06cc\u0634\u06a9\u0648\u0648"
    ],
    "name:fra_x_preferred":[
        "Cieszk\u00f3w"
    ],
    "name:ita_x_preferred":[
        "Cieszk\u00f3w"
    ],
    "name:nan_x_preferred":[
        "Cieszk\u00f3w"
    ],
    "name:nld_x_preferred":[
        "Cieszk\u00f3w"
    ],
    "name:pol_x_preferred":[
        "Cieszk\u00f3w"
    ],
    "name:por_x_preferred":[
        "Comuna de Cieszk\u00f3w"
    ],
    "name:rus_x_preferred":[
        "\u0426\u0435\u0448\u043a\u0443\u0432"
    ],
    "name:slk_x_preferred":[
        "Gmina Cieszk\u00f3w"
    ],
    "name:swe_x_preferred":[
        "Cieszk\u00f3ws kommun"
    ],
    "name:ukr_x_preferred":[
        "\u0490\u043c\u0456\u043d\u0430 \u0426\u0435\u0448\u043a\u0443\u0432"
    ],
    "name:und_x_variant":[
        "Frejno"
    ],
    "name:war_x_preferred":[
        "Gmina Cieszk\u00f3w"
    ],
    "qs:a0":"Rzeczpospolita Polska",
    "qs:a1":"*Dolnoslaskie",
    "qs:a1r":"0",
    "qs:a2":"Milicki",
    "qs:adm0":"Rzeczpospolita Polska",
    "qs:la":"Cieszk\u00f3w",
    "qs:la_lc":"*PL0213012",
    "qs:level":"locality",
    "qs:loc":"Cieszk\u00f3w",
    "qs:loc_alt":"Cieszkow",
    "qs:pop":0,
    "qs:type":"rural point-in-poly",
    "wd:wordcount":119,
    "wof:coterminous":[
        1477752641
    ],
    "wof:name":"Cieszk\u00f3w",
    "wof:placetype":"locality",
    "wof:population":1800
},
  "geometry": {"coordinates":[17.3242216906428,51.6197935018395],"type":"Point"}
}