{
  "type": "Feature",
  "properties": {
    "gn:admin1_code":"72.0",
    "gn:admin2_code":"215.0",
    "gn:admin3_code":"21502.0",
    "gn:asciiname":"Kuchary",
    "gn:country_code":"PL",
    "gn:dem":142,
    "gn:feature_class":"P",
    "gn:feature_code":"PPL",
    "gn:name":"Kuchary",
    "gn:population":0,
    "gn:timezone":"Europe/Warsaw",
    "iso:country":"PL",
    "name:pol_x_preferred":[
        "Kuchary"
    ],
    "name:ukr_x_preferred":[
        "\u041a\u0443\u0445\u0430\u0440\u0438"
    ],
    "wof:name":"Kuchary",
    "wof:placetype":"locality"
},
  "geometry": {"coordinates":[17.08271,50.89329],"type":"Point"}
}