{
  "type": "Feature",
  "properties": {
    "gn:gn_country":"PL",
    "gn:gn_fcode":"PPLA3",
    "gn:gn_pop":35161,
    "gn:population":35161,
    "iso:country":"PL",
    "name:bul_x_preferred":[
        "\u041b\u0435\u043c\u0431\u043e\u0440\u043a"
    ],
    "name:cat_x_preferred":[
        "L\u0119bork"
    ],
    "name:csb_x_preferred":[
        "L\u00e3b\u00f3rg"
    ],
    "name:deu_x_preferred":[
        "L\u0119bork"
    ],
    "name:dsb_x_preferred":[
        "L\u0119bork"
    ],
    "name:epo_x_preferred":[
        "L\u0119bork"
    ],
    "name:eus_x_preferred":[
        "L\u0119bork"
    ],
    "name:fas_x_preferred":[
        "\u0644\u0645\u0628\u0648\u0631\u06a9"
    ],
    "name:fra_x_preferred":[
        "L\u0119bork"
    ],
    "name:ita_x_preferred":[
        "L\u0119bork"
    ],
    "name:jav_x_preferred":[
        "L\u0119bork"
    ],
    "name:jpn_x_preferred":[
        "\u30ec\u30f3\u30dc\u30eb\u30af"
    ],
    "name:lav_x_preferred":[
        "Lemborka"
    ],
    "name:lit_x_preferred":[
        "Lemborkas"
    ],
    "name:msa_x_preferred":[
        "L\u0119bork"
    ],
    "name:nau_x_preferred":[
        "L\u0119bork"
    ],
    "name:nds_x_preferred":[
        "Lauenburg"
    ],
    "name:nld_x_preferred":[
        "L\u0119bork"
    ],
    "name:pol_x_preferred":[
        "L\u0119bork"
    ],
    "name:por_x_preferred":[
        "L\u0119bork"
    ],
    "name:ron_x_preferred":[
        "L\u0119bork"
    ],
    "name:rus_x_preferred":[
        "\u041b\u0435\u043c\u0431\u043e\u0440\u043a"
    ],
    "name:slk_x_preferred":[
        "L\u0119bork"
    ],
    "name:spa_x_preferred":[
        "L\u0119bork"
    ],
    "name:srp_x_preferred":[
        "\u041b\u0435\u043c\u0431\u043e\u0440\u043a"
    ],
    "name:swe_x_preferred":[
        "L\u0119bork"
    ],
    "name:szl_x_preferred":[
        "Lymbork"
    ],
    "name:tha_x_preferred":[
        "\u0e41\u0e25\u0e21\u0e1a\u0e2d\u0e23\u0e4c\u0e01"
    ],
    "name:tur_x_preferred":[
        "L\u0119bork"
    ],
    "name:ukr_x_preferred":[
        "\u041b\u0435\u043c\u0431\u043e\u0440\u043a"
    ],
    "name:unk_x_variant":[
        "Lembork"
    ],
    "name:vie_x_preferred":[
        "L\u0119bork"
    ],
    "name:war_x_preferred":[
        "L\u0119bork"
    ],
    "name:zho_x_preferred":[
        "\u502b\u5821"
    ],
    "qs_pg:aaroncc":"PL",
    "qs_pg:gn_country":"PL",
    "qs_pg:gn_fcode":"PPLA3",
    "qs_pg:gn_pop":35161,
    "qs_pg:name":"L\u0119bork",
    "qs_pg:name_adm0":"Polska",
    "qs_pg:name_adm1":"Pomorskie",
    "qs_pg:photos":18,
    "qs_pg:photos_1k":4,
    "qs_pg:photos_9k":1,
    "qs_pg:photos_9r":1,
    "qs_pg:photos_all":18,
    "qs_pg:photos_sr":1,
    "qs_pg:pop_sr":7,
    "qs_pg:qs_pg_placetype":"localadmin",
    "qs_pg:qs_pg_placetype_gp":"LocalAdmin",
    "qs_pg:woe_adm0":23424923,
    "woe:adm0_id":23424923,
    "woe:name_adm0":"Polska",
    "woe:name_adm1":"Pomorskie",
    "woe:placetype":"LocalAdmin",
    "wof:name":"L\u0119bork",
    "wof:placetype":"localadmin",
    "wof:population":35161
},
  "geometry": {"coordinates":[17.75012,54.53921],"type":"Point"}
}