{
  "type": "Feature",
  "properties": {
    "gn:admin1_code":"80.0",
    "gn:admin2_code":"1861.0",
    "gn:admin3_code":"186101.0",
    "gn:asciiname":"Suchodol",
    "gn:country_code":"PL",
    "gn:dem":317,
    "gn:feature_class":"P",
    "gn:feature_code":"PPL",
    "gn:name":"Suchod\u00f3\u0142",
    "gn:population":0,
    "gn:timezone":"Europe/Warsaw",
    "iso:country":"PL",
    "wof:name":"Suchodol",
    "wof:placetype":"locality"
},
  "geometry": {"coordinates":[21.76354,49.66257],"type":"Point"}
}