{
  "type": "Feature",
  "properties": {
    "gn:admin1_code":"79.0",
    "gn:admin2_code":"1605.0",
    "gn:admin3_code":"160503.0",
    "gn:asciiname":"Komorniki",
    "gn:country_code":"PL",
    "gn:dem":170,
    "gn:feature_class":"P",
    "gn:feature_code":"PPL",
    "gn:name":"Komorniki",
    "gn:population":0,
    "gn:timezone":"Europe/Warsaw",
    "iso:country":"PL",
    "name:azb_x_preferred":[
        "\u06a9\u0648\u0645\u0648\u0631\u0646\u0642\u06a9\u06cc"
    ],
    "name:ceb_x_preferred":[
        "Komorniki"
    ],
    "name:deu_x_preferred":[
        "Komornik"
    ],
    "name:fas_x_preferred":[
        "\u06a9\u0648\u0645\u0648\u0631\u0646\u06af\u06a9\u06cc"
    ],
    "name:pol_x_preferred":[
        "Komorniki"
    ],
    "name:ukr_x_preferred":[
        "\u041a\u043e\u043c\u043e\u0440\u043d\u0438\u043a\u0438"
    ],
    "wof:name":"Komorniki",
    "wof:placetype":"locality"
},
  "geometry": {"coordinates":[17.90789,50.43717],"type":"Point"}
}