{
  "type": "Feature",
  "properties": {
    "gn:country":"PL",
    "gn:fcode":"PPL",
    "gn:population":376,
    "iso:country":"PL",
    "name:bos_x_preferred":[
        "Golice"
    ],
    "name:ceb_x_preferred":[
        "Golice"
    ],
    "name:deu_x_preferred":[
        "Golice"
    ],
    "name:fra_x_preferred":[
        "Golice"
    ],
    "name:pol_x_preferred":[
        "Golice"
    ],
    "name:slv_x_preferred":[
        "Golice"
    ],
    "name:srp_x_preferred":[
        "\u0413\u043e\u043b\u0438\u0446\u0435"
    ],
    "name:ukr_x_preferred":[
        "\u0490\u043e\u043b\u0456\u0446\u0435"
    ],
    "qs_pg:aaroncc":"PL",
    "qs_pg:gn_country":"PL",
    "qs_pg:gn_fcode":"PPL",
    "qs_pg:gn_pop":376,
    "qs_pg:name":"Golice",
    "qs_pg:name_adm0":"Polska",
    "qs_pg:name_adm1":"Lubuskie",
    "qs_pg:photos_9r":0,
    "qs_pg:photos_sr":0,
    "qs_pg:pop_sr":2,
    "qs_pg:qs_pg_placetype":"locality",
    "qs_pg:qs_pg_placetype_gp":"Town",
    "qs_pg:woe_adm0":23424923,
    "woe:adm0_id":23424923,
    "woe:name_adm0":"Polska",
    "woe:name_adm1":"Lubuskie",
    "woe:placetype":"Town",
    "wof:name":"Golice",
    "wof:placetype":"locality",
    "wof:population":376
},
  "geometry": {"coordinates":[14.66018,52.43417],"type":"Point"}
}