{
  "type": "Feature",
  "properties": {
    "gn:admin1_code":"87.0",
    "gn:admin2_code":"3214.0",
    "gn:admin3_code":"321402.0",
    "gn:asciiname":"Oswino",
    "gn:country_code":"PL",
    "gn:dem":94,
    "gn:feature_class":"P",
    "gn:feature_code":"PPL",
    "gn:name":"O\u015bwino",
    "gn:population":0,
    "gn:timezone":"Europe/Warsaw",
    "iso:country":"PL",
    "name:ceb_x_preferred":[
        "O\u015bwino"
    ],
    "name:pol_x_preferred":[
        "O\u015bwino"
    ],
    "name:ukr_x_preferred":[
        "\u041e\u0441\u044c\u0432\u0456\u043d\u043e"
    ],
    "name:und_x_variant":[
        "O\u015bwino"
    ],
    "name:vie_x_preferred":[
        "O\u015bwino"
    ],
    "wof:name":"Oswino",
    "wof:placetype":"locality"
},
  "geometry": {"coordinates":[15.38585,53.53305],"type":"Point"}
}