{
  "type": "Feature",
  "properties": {
    "gn:population":14028,
    "iso:country":"PL",
    "name:bul_x_preferred":[
        "\u041f\u0448\u0443\u0432"
    ],
    "name:ceb_x_preferred":[
        "Psz\u00f3w"
    ],
    "name:ces_x_preferred":[
        "Psz\u00f3w"
    ],
    "name:deu_x_preferred":[
        "Psz\u00f3w"
    ],
    "name:deu_x_variant":[
        "Pschow"
    ],
    "name:eng_x_preferred":[
        "Psz\u00f3w"
    ],
    "name:epo_x_preferred":[
        "Psz\u00f3w"
    ],
    "name:eus_x_preferred":[
        "Psz\u00f3w"
    ],
    "name:fra_x_preferred":[
        "Psz\u00f3w"
    ],
    "name:ita_x_preferred":[
        "Psz\u00f3w"
    ],
    "name:jav_x_preferred":[
        "Psz\u00f3w"
    ],
    "name:lav_x_preferred":[
        "P\u0161ova"
    ],
    "name:msa_x_preferred":[
        "Psz\u00f3w"
    ],
    "name:nan_x_preferred":[
        "Psz\u00f3w"
    ],
    "name:nld_x_preferred":[
        "Psz\u00f3w"
    ],
    "name:pol_x_preferred":[
        "Psz\u00f3w"
    ],
    "name:por_x_preferred":[
        "Psz\u00f3w"
    ],
    "name:ron_x_preferred":[
        "Psz\u00f3w"
    ],
    "name:rus_x_preferred":[
        "\u041f\u0448\u0443\u0432"
    ],
    "name:slk_x_preferred":[
        "Psz\u00f3w"
    ],
    "name:srp_x_preferred":[
        "\u041f\u0448\u043e\u0432"
    ],
    "name:szl_x_preferred":[
        "Psz\u016fw"
    ],
    "name:tat_x_preferred":[
        "\u041f\u0448\u0443\u0432"
    ],
    "name:ukr_x_preferred":[
        "\u041f\u0448\u0443\u0432"
    ],
    "name:vie_x_preferred":[
        "Psz\u00f3w"
    ],
    "name:war_x_preferred":[
        "Psz\u00f3w"
    ],
    "name:zho_x_preferred":[
        "\u666e\u8212\u592b"
    ],
    "qs:a0":"Rzeczpospolita Polska",
    "qs:a1":"*Slaskie",
    "qs:a1r":"0",
    "qs:a2":"Wodzislawski",
    "qs:adm0":"Rzeczpospolita Polska",
    "qs:la":"Czerwionka-Leszczyny",
    "qs:la_lc":"*PL2412013",
    "qs:level":"locality",
    "qs:loc":"Psz\u00f3w",
    "qs:loc_alt":"Pszow",
    "qs:pop":0,
    "qs:type":"suburbs point-in-poly",
    "wd:wordcount":227,
    "wof:name":"Psz\u00f3w",
    "wof:placetype":"locality",
    "wof:population":14028
},
  "geometry": {"coordinates":[18.3813478986048,50.0450114540839],"type":"Point"}
}