{
  "type": "Feature",
  "properties": {
    "gn:admin1_code":"78.0",
    "gn:admin2_code":"1416.0",
    "gn:admin3_code":"141607.0",
    "gn:asciiname":"Dybki",
    "gn:country_code":"PL",
    "gn:dem":108,
    "gn:feature_class":"P",
    "gn:feature_code":"PPL",
    "gn:name":"Dybki",
    "gn:population":0,
    "gn:timezone":"Europe/Warsaw",
    "iso:country":"PL",
    "name:ceb_x_preferred":[
        "Dybki"
    ],
    "name:fra_x_preferred":[
        "Dybki"
    ],
    "name:pol_x_preferred":[
        "Dybki"
    ],
    "name:ukr_x_preferred":[
        "\u0414\u0438\u0431\u043a\u0456"
    ],
    "wof:name":"Dybki",
    "wof:placetype":"locality"
},
  "geometry": {"coordinates":[21.7109,52.71977],"type":"Point"}
}