{
  "type": "Feature",
  "properties": {
    "gn:admin1_code":"74.0",
    "gn:admin2_code":"1014.0",
    "gn:admin3_code":"101402.0",
    "gn:asciiname":"Stok",
    "gn:country_code":"PL",
    "gn:dem":164,
    "gn:feature_class":"P",
    "gn:feature_code":"PPL",
    "gn:name":"Stok",
    "gn:population":0,
    "gn:timezone":"Europe/Warsaw",
    "iso:country":"PL",
    "name:fra_x_preferred":[
        "Stok"
    ],
    "name:por_x_preferred":[
        "Stok"
    ],
    "wof:name":"Stok",
    "wof:placetype":"locality"
},
  "geometry": {"coordinates":[18.38596,51.59765],"type":"Point"}
}