{
  "type": "Feature",
  "properties": {
    "gn:admin1_code":"79.0",
    "gn:admin2_code":"1601.0",
    "gn:admin3_code":"160106.0",
    "gn:asciiname":"Gierszowice",
    "gn:country_code":"PL",
    "gn:dem":148,
    "gn:feature_class":"P",
    "gn:feature_code":"PPL",
    "gn:name":"Gierszowice",
    "gn:population":0,
    "gn:timezone":"Europe/Warsaw",
    "iso:country":"PL",
    "name:deu_x_preferred":[
        "Gierszowice"
    ],
    "name:pol_x_preferred":[
        "Gierszowice"
    ],
    "name:ukr_x_preferred":[
        "\u0490\u0435\u0440\u0448\u043e\u0432\u0456\u0446\u0435"
    ],
    "wof:name":"Gierszowice",
    "wof:placetype":"locality"
},
  "geometry": {"coordinates":[17.49865,50.81114],"type":"Point"}
}