{
  "type": "Feature",
  "properties": {
    "gn:admin1_code":"78.0",
    "gn:admin2_code":"1404.0",
    "gn:admin3_code":"140405.0",
    "gn:asciiname":"Kunki",
    "gn:country_code":"PL",
    "gn:dem":109,
    "gn:feature_class":"P",
    "gn:feature_code":"PPL",
    "gn:name":"Kunki",
    "gn:population":0,
    "gn:timezone":"Europe/Warsaw",
    "iso:country":"PL",
    "wof:name":"Kunki",
    "wof:placetype":"locality"
},
  "geometry": {"coordinates":[19.66511,52.39618],"type":"Point"}
}