{
  "type": "Feature",
  "properties": {
    "gn:admin1_code":"75.0",
    "gn:admin2_code":"606.0",
    "gn:admin3_code":"60605.0",
    "gn:asciiname":"Lany",
    "gn:country_code":"PL",
    "gn:dem":242,
    "gn:feature_class":"P",
    "gn:feature_code":"PPL",
    "gn:name":"\u0141any",
    "gn:population":0,
    "gn:timezone":"Europe/Warsaw",
    "iso:country":"PL",
    "name:ceb_x_preferred":[
        "Lany"
    ],
    "name:swe_x_preferred":[
        "Lany"
    ],
    "wof:name":"Lany",
    "wof:placetype":"locality"
},
  "geometry": {"coordinates":[23.25357,50.97387],"type":"Point"}
}