{
  "type": "Feature",
  "properties": {
    "gn:admin1_code":"84.0",
    "gn:admin2_code":"2604.0",
    "gn:admin3_code":"260418.0",
    "gn:asciiname":"Strawczynek",
    "gn:country_code":"PL",
    "gn:dem":270,
    "gn:feature_class":"P",
    "gn:feature_code":"PPL",
    "gn:name":"Strawczynek",
    "gn:population":0,
    "gn:timezone":"Europe/Warsaw",
    "iso:country":"PL",
    "name:ceb_x_preferred":[
        "Strawczynek"
    ],
    "name:pol_x_preferred":[
        "Strawczyn"
    ],
    "name:pol_x_variant":[
        "Strawczynek"
    ],
    "name:ukr_x_preferred":[
        "\u0421\u0442\u0440\u0430\u0432\u0447\u0438\u043d\u0435\u043a"
    ],
    "wof:coterminous":[
        1125332943
    ],
    "wof:name":"Strawczynek",
    "wof:placetype":"locality"
},
  "geometry": {"coordinates":[20.45329,50.93967],"type":"Point"}
}