{
  "type": "Feature",
  "properties": {
    "gn:admin1_code":"75.0",
    "gn:admin2_code":"602.0",
    "gn:admin3_code":"60209.0",
    "gn:asciiname":"Szostaki",
    "gn:country_code":"PL",
    "gn:dem":195,
    "gn:feature_class":"P",
    "gn:feature_code":"PPL",
    "gn:name":"Szostaki",
    "gn:population":0,
    "gn:timezone":"Europe/Warsaw",
    "iso:country":"PL",
    "name:fra_x_preferred":[
        "Szostaki"
    ],
    "name:lit_x_preferred":[
        "\u0160ostakai"
    ],
    "name:pol_x_preferred":[
        "Szostaki"
    ],
    "name:ukr_x_preferred":[
        "\u0428\u043e\u0441\u0442\u0430\u043a\u0456"
    ],
    "wof:name":"Szostaki",
    "wof:placetype":"locality"
},
  "geometry": {"coordinates":[22.90969,50.41198],"type":"Point"}
}