{
  "type": "Feature",
  "properties": {
    "gn:admin1_code":"78.0",
    "gn:admin2_code":"1412.0",
    "gn:admin3_code":"141204.0",
    "gn:asciiname":"Posiadaly",
    "gn:country_code":"PL",
    "gn:dem":167,
    "gn:feature_class":"P",
    "gn:feature_code":"PPL",
    "gn:name":"Posiada\u0142y",
    "gn:population":0,
    "gn:timezone":"Europe/Warsaw",
    "iso:country":"PL",
    "name:ceb_x_preferred":[
        "Posiada\u0142y"
    ],
    "name:fra_x_preferred":[
        "Posiada\u0142y"
    ],
    "name:pol_x_preferred":[
        "Posiada\u0142y"
    ],
    "name:spa_x_preferred":[
        "Posiada\u0142y"
    ],
    "name:ukr_x_preferred":[
        "\u041f\u043e\u0441\u044f\u0434\u0430\u043b\u0438"
    ],
    "name:und_x_variant":[
        "Posiada\u0142y"
    ],
    "wof:name":"Posiadaly",
    "wof:placetype":"locality"
},
  "geometry": {"coordinates":[21.72384,52.10372],"type":"Point"}
}