{
  "type": "Feature",
  "properties": {
    "iso:country":"PL",
    "name:eng_x_preferred":[
        "Grunwald Poludnie"
    ],
    "name:pol_x_preferred":[
        "Grunwald Po\u0142udnie"
    ],
    "wof:name":"Grunwald Poludnie",
    "wof:placetype":"neighbourhood"
},
  "geometry": {"coordinates":[16.8721580328131,52.39354980561676],"type":"Point"}
}