{
  "type": "Feature",
  "properties": {
    "gn:admin1_code":"79.0",
    "gn:admin2_code":"1604.0",
    "gn:admin3_code":"160401.0",
    "gn:asciiname":"Janowka",
    "gn:country_code":"PL",
    "gn:dem":179,
    "gn:feature_class":"P",
    "gn:feature_code":"PPL",
    "gn:name":"Jan\u00f3wka",
    "gn:population":0,
    "gn:timezone":"Europe/Warsaw",
    "iso:country":"PL",
    "wof:name":"Janowka",
    "wof:placetype":"locality"
},
  "geometry": {"coordinates":[18.09036,51.15453],"type":"Point"}
}