{
  "type": "Feature",
  "properties": {
    "gn:admin1_code":"79.0",
    "gn:admin2_code":"1604.0",
    "gn:admin3_code":"160401.0",
    "gn:asciiname":"Janowka",
    "gn:country_code":"PL",
    "gn:dem":179,
    "gn:feature_class":"P",
    "gn:feature_code":"PPL",
    "gn:name":"Jan\u00f3wka",
    "gn:population":0,
    "gn:timezone":"Europe/Warsaw",
    "iso:country":"PL",
    "name:azb_x_preferred":[
        "\u06cc\u0627\u0646\u0648\u0648\u06a9\u0627"
    ],
    "name:deu_x_preferred":[
        "Jan\u00f3wka"
    ],
    "name:fas_x_preferred":[
        "\u06cc\u0627\u0646\u0648\u0648\u06a9\u0627"
    ],
    "name:pol_x_preferred":[
        "Jan\u00f3wka"
    ],
    "name:ukr_x_preferred":[
        "\u042f\u043d\u0443\u0432\u043a\u0430"
    ],
    "name:urd_x_preferred":[
        "\u062c\u0646\u0648\u0648\u06a9\u0627"
    ],
    "wof:name":"Janowka",
    "wof:placetype":"locality"
},
  "geometry": {"coordinates":[18.09036,51.15453],"type":"Point"}
}