{
  "type": "Feature",
  "properties": {
    "gn:admin1_code":"74.0",
    "gn:admin2_code":"1020.0",
    "gn:admin3_code":"102008.0",
    "gn:asciiname":"Tymianka",
    "gn:country_code":"PL",
    "gn:dem":162,
    "gn:feature_class":"P",
    "gn:feature_code":"PPL",
    "gn:name":"Tymianka",
    "gn:population":0,
    "gn:timezone":"Europe/Warsaw",
    "iso:country":"PL",
    "name:azb_x_preferred":[
        "\u062a\u06cc\u0645\u06cc\u0627\u0646\u06a9\u0627"
    ],
    "name:ceb_x_preferred":[
        "Tymianka"
    ],
    "name:fas_x_preferred":[
        "\u062a\u06cc\u0645\u06cc\u0627\u0646\u06a9\u0627"
    ],
    "name:pol_x_preferred":[
        "Tymianka"
    ],
    "name:ukr_x_preferred":[
        "\u0422\u0438\u043c\u044f\u043d\u043a\u0430"
    ],
    "wof:name":"Tymianka",
    "wof:placetype":"locality"
},
  "geometry": {"coordinates":[19.57919,51.92038],"type":"Point"}
}