{
  "type": "Feature",
  "properties": {
    "gn:admin1_code":"74.0",
    "gn:admin2_code":"1020.0",
    "gn:admin3_code":"102008.0",
    "gn:asciiname":"Tymianka",
    "gn:country_code":"PL",
    "gn:dem":162,
    "gn:feature_class":"P",
    "gn:feature_code":"PPL",
    "gn:name":"Tymianka",
    "gn:population":0,
    "gn:timezone":"Europe/Warsaw",
    "iso:country":"PL",
    "wof:name":"Tymianka",
    "wof:placetype":"locality"
},
  "geometry": {"coordinates":[19.57919,51.92038],"type":"Point"}
}