{
  "type": "Feature",
  "properties": {
    "gn:admin1_code":"80.0",
    "gn:admin2_code":"1817.0",
    "gn:admin3_code":"181703.0",
    "gn:asciiname":"Tokarnia",
    "gn:cc2":"PL",
    "gn:country_code":"PL",
    "gn:dem":475,
    "gn:feature_class":"P",
    "gn:feature_code":"PPL",
    "gn:name":"Tokarnia",
    "gn:population":0,
    "gn:timezone":"Europe/Warsaw",
    "iso:country":"PL",
    "name:azb_x_preferred":[
        "\u062a\u0648\u06a9\u0627\u0631\u0646\u0642\u0627"
    ],
    "name:fas_x_preferred":[
        "\u062a\u0648\u06a9\u0627\u0631\u0646\u06af\u0627"
    ],
    "name:nld_x_preferred":[
        "Tokarnia"
    ],
    "name:pol_x_preferred":[
        "Tokarnia"
    ],
    "name:rue_x_preferred":[
        "\u0422\u043e\u043a\u0430\u0440\u043d\u044f"
    ],
    "name:ukr_x_preferred":[
        "\u0422\u043e\u043a\u0430\u0440\u043d\u044f"
    ],
    "name:und_x_variant":[
        "Takarnia"
    ],
    "wof:name":"Tokarnia",
    "wof:placetype":"locality"
},
  "geometry": {"coordinates":[22.0233,49.46679],"type":"Point"}
}