{
  "type": "Feature",
  "properties": {
    "gn:admin1_code":"72.0",
    "gn:admin2_code":"219.0",
    "gn:admin3_code":"21908.0",
    "gn:asciiname":"Marcinowiczki",
    "gn:country_code":"PL",
    "gn:dem":196,
    "gn:feature_class":"P",
    "gn:feature_code":"PPL",
    "gn:name":"Marcinowiczki",
    "gn:population":0,
    "gn:timezone":"Europe/Warsaw",
    "iso:country":"PL",
    "wof:name":"Marcinowiczki",
    "wof:placetype":"locality"
},
  "geometry": {"coordinates":[16.54387,50.97578],"type":"Point"}
}