{
  "type": "Feature",
  "properties": {
    "gn:admin1_code":"87.0",
    "gn:admin2_code":"3206.0",
    "gn:admin3_code":"320607.0",
    "gn:asciiname":"Komorowko",
    "gn:country_code":"PL",
    "gn:dem":16,
    "gn:feature_class":"P",
    "gn:feature_code":"PPL",
    "gn:name":"Komor\u00f3wko",
    "gn:population":0,
    "gn:timezone":"Europe/Warsaw",
    "iso:country":"PL",
    "name:pol_x_preferred":[
        "Komor\u00f3wko"
    ],
    "name:ukr_x_preferred":[
        "\u041a\u043e\u043c\u043e\u0440\u0443\u0432\u043a\u043e"
    ],
    "wof:name":"Komorowko",
    "wof:placetype":"locality"
},
  "geometry": {"coordinates":[14.83199,53.25646],"type":"Point"}
}