{
  "type": "Feature",
  "properties": {
    "gn:admin1_code":"86.0",
    "gn:admin2_code":"3025.0",
    "gn:admin3_code":"302504.0",
    "gn:asciiname":"Brodowo",
    "gn:country_code":"PL",
    "gn:dem":84,
    "gn:feature_class":"P",
    "gn:feature_code":"PPL",
    "gn:name":"Brodowo",
    "gn:population":0,
    "gn:timezone":"Europe/Warsaw",
    "iso:country":"PL",
    "name:ceb_x_preferred":[
        "Brodowo"
    ],
    "name:fra_x_preferred":[
        "Brodowo"
    ],
    "name:pol_x_preferred":[
        "Brodowo"
    ],
    "name:swe_x_preferred":[
        "Brodowo"
    ],
    "name:ukr_x_preferred":[
        "\u0411\u0440\u043e\u0434\u043e\u0432\u043e"
    ],
    "wof:name":"Brodowo",
    "wof:placetype":"locality"
},
  "geometry": {"coordinates":[17.31886,52.19009000000001],"type":"Point"}
}