{
  "type": "Feature",
  "properties": {
    "gn:admin1_code":"82.0",
    "gn:admin2_code":"2262.0",
    "gn:admin3_code":"226201.0",
    "gn:asciiname":"Witomino Lesniczowka",
    "gn:country_code":"PL",
    "gn:dem":128,
    "gn:feature_class":"P",
    "gn:feature_code":"PPL",
    "gn:name":"Witomino Le\u015bnicz\u00f3wka",
    "gn:population":0,
    "gn:timezone":"Europe/Warsaw",
    "iso:country":"PL",
    "wof:name":"Witomino Lesniczowka",
    "wof:placetype":"neighbourhood"
},
  "geometry": {"coordinates":[18.49815,54.49808],"type":"Point"}
}