{
  "type": "Feature",
  "properties": {
    "iso:country":"PL",
    "name:azb_x_preferred":[
        "\u0648\u0627\u06cc\u0646\u062a\u0633\u0648\u062a"
    ],
    "name:bel_x_preferred":[
        "\u041b\u0430\u043d\u044c\u0446\u0443\u0442"
    ],
    "name:bul_x_preferred":[
        "\u041b\u0430\u043d\u0446\u0443\u0442"
    ],
    "name:ceb_x_preferred":[
        "\u0141a\u0144cut"
    ],
    "name:ces_x_preferred":[
        "\u0141a\u0144cut"
    ],
    "name:deu_x_preferred":[
        "\u0141a\u0144cut"
    ],
    "name:dsb_x_preferred":[
        "\u0141a\u0144cut"
    ],
    "name:epo_x_preferred":[
        "\u0141a\u0144cut"
    ],
    "name:eus_x_preferred":[
        "\u0141a\u0144cut"
    ],
    "name:fas_x_preferred":[
        "\u0648\u0627\u06cc\u0646\u062a\u0633\u0648\u062a"
    ],
    "name:fra_x_preferred":[
        "\u0141a\u0144cut"
    ],
    "name:heb_x_preferred":[
        "\u05dc\u05e0\u05e6\u05d5\u05d8"
    ],
    "name:ita_x_preferred":[
        "\u0141a\u0144cut"
    ],
    "name:jav_x_preferred":[
        "\u0141a\u0144cut"
    ],
    "name:kor_x_preferred":[
        "\uc644\ucd94\ud2b8"
    ],
    "name:lav_x_preferred":[
        "La\u0146cuta"
    ],
    "name:msa_x_preferred":[
        "\u0141a\u0144cut"
    ],
    "name:nld_x_preferred":[
        "\u0141a\u0144cut"
    ],
    "name:nor_x_preferred":[
        "\u0141a\u0144cut"
    ],
    "name:pol_x_preferred":[
        "\u0141a\u0144cut"
    ],
    "name:por_x_preferred":[
        "\u0141a\u0144cut"
    ],
    "name:ron_x_preferred":[
        "\u0141a\u0144cut"
    ],
    "name:rus_x_preferred":[
        "\u041b\u0430\u043d\u044c\u0446\u0443\u0442"
    ],
    "name:slk_x_preferred":[
        "\u0141a\u0144cut"
    ],
    "name:srp_x_preferred":[
        "\u041b\u0430\u045a\u0446\u0443\u0442"
    ],
    "name:szl_x_preferred":[
        "\u0141a\u0144cut"
    ],
    "name:tur_x_preferred":[
        "\u0141a\u0144cut"
    ],
    "name:ukr_x_preferred":[
        "\u041b\u0430\u043d\u044c\u0446\u0443\u0442"
    ],
    "name:vie_x_preferred":[
        "\u0141a\u0144cut"
    ],
    "name:war_x_preferred":[
        "\u0141a\u0144cut"
    ],
    "name:yid_x_preferred":[
        "\u05dc\u05d0\u05e0\u05e6\u05d4\u05d5\u05d8"
    ],
    "name:zho_x_preferred":[
        "\u842c\u695a\u7279"
    ],
    "qs_pg:aaroncc":"PL",
    "qs_pg:name":"\u0141a\u0144cut",
    "qs_pg:name_adm0":"Polska",
    "qs_pg:name_adm1":"Podkarpackie",
    "qs_pg:photos":27,
    "qs_pg:photos_1k":5,
    "qs_pg:photos_9k":1,
    "qs_pg:photos_9r":2,
    "qs_pg:photos_all":27,
    "qs_pg:photos_sr":2,
    "qs_pg:pop_sr":0,
    "qs_pg:qs_pg_placetype":"localadmin",
    "qs_pg:qs_pg_placetype_gp":"LocalAdmin",
    "qs_pg:woe_adm0":23424923,
    "woe:adm0_id":23424923,
    "woe:name_adm0":"Polska",
    "woe:name_adm1":"Podkarpackie",
    "woe:placetype":"LocalAdmin",
    "wof:name":"\u0141a\u0144cut",
    "wof:placetype":"localadmin"
},
  "geometry": {"coordinates":[22.231693,50.068709],"type":"Point"}
}