{
  "type": "Feature",
  "properties": {
    "gn:admin1_code":"84.0",
    "gn:admin2_code":"2612.0",
    "gn:admin3_code":"261207.0",
    "gn:asciiname":"Wola Osowa",
    "gn:country_code":"PL",
    "gn:dem":238,
    "gn:feature_class":"P",
    "gn:feature_code":"PPL",
    "gn:name":"Wola Osowa",
    "gn:population":0,
    "gn:timezone":"Europe/Warsaw",
    "iso:country":"PL",
    "name:nld_x_preferred":[
        "Wola Osowa"
    ],
    "name:pol_x_preferred":[
        "Wola Osowa"
    ],
    "name:ukr_x_preferred":[
        "\u0412\u043e\u043b\u044f-\u041e\u0441\u043e\u0432\u0430"
    ],
    "wof:name":"Wola Osowa",
    "wof:placetype":"locality"
},
  "geometry": {"coordinates":[21.10896,50.61857],"type":"Point"}
}