{
  "type": "Feature",
  "properties": {
    "gn:admin1_code":"78.0",
    "gn:admin2_code":"1422.0",
    "gn:admin3_code":"142207.0",
    "gn:asciiname":"Wielodroz",
    "gn:country_code":"PL",
    "gn:dem":102,
    "gn:feature_class":"P",
    "gn:feature_code":"PPL",
    "gn:name":"Wielodr\u00f3\u017c",
    "gn:population":0,
    "gn:timezone":"Europe/Warsaw",
    "iso:country":"PL",
    "name:fra_x_preferred":[
        "Wielodr\u00f3\u017c"
    ],
    "name:pol_x_preferred":[
        "Wielodr\u00f3\u017c"
    ],
    "name:ukr_x_preferred":[
        "\u0412\u0435\u043b\u044c\u043e\u0434\u0440\u0443\u0436"
    ],
    "wof:name":"Wielodroz",
    "wof:placetype":"locality"
},
  "geometry": {"coordinates":[21.00184,52.95087],"type":"Point"}
}