{
  "type": "Feature",
  "properties": {
    "gn:admin1_code":"81.0",
    "gn:admin2_code":"2012.0",
    "gn:admin3_code":"201207.0",
    "gn:asciiname":"Taciewo",
    "gn:country_code":"PL",
    "gn:dem":202,
    "gn:feature_class":"P",
    "gn:feature_code":"PPL",
    "gn:name":"Taciewo",
    "gn:population":0,
    "gn:timezone":"Europe/Warsaw",
    "iso:country":"PL",
    "name:fra_x_preferred":[
        "Taciewo"
    ],
    "name:lit_x_preferred":[
        "Tacevas"
    ],
    "name:pol_x_preferred":[
        "Taciewo"
    ],
    "name:ukr_x_preferred":[
        "\u0422\u0430\u0446\u0435\u0432\u043e"
    ],
    "wof:name":"Taciewo",
    "wof:placetype":"locality"
},
  "geometry": {"coordinates":[22.79722000000001,54.15382],"type":"Point"}
}