{
  "type": "Feature",
  "properties": {
    "gn:admin1_code":"85.0",
    "gn:admin2_code":"2814.0",
    "gn:admin3_code":"281405.0",
    "gn:asciiname":"Podlejki",
    "gn:country_code":"PL",
    "gn:dem":117,
    "gn:feature_class":"P",
    "gn:feature_code":"PPL",
    "gn:name":"Podlejki",
    "gn:population":0,
    "gn:timezone":"Europe/Warsaw",
    "iso:country":"PL",
    "name:deu_x_preferred":[
        "Podlejki"
    ],
    "name:pol_x_preferred":[
        "Podlejki"
    ],
    "name:ukr_x_preferred":[
        "\u041f\u043e\u0434\u043b\u0435\u0439\u043a\u0456"
    ],
    "wof:name":"Podlejki",
    "wof:placetype":"locality"
},
  "geometry": {"coordinates":[20.19172,53.7302],"type":"Point"}
}