{
  "type": "Feature",
  "properties": {
    "gn:admin1_code":"77.0",
    "gn:admin2_code":"1209.0",
    "gn:admin3_code":"120903.0",
    "gn:asciiname":"Chelm",
    "gn:country_code":"PL",
    "gn:dem":370,
    "gn:feature_class":"P",
    "gn:feature_code":"PPL",
    "gn:name":"Che\u0142m",
    "gn:population":0,
    "gn:timezone":"Europe/Warsaw",
    "iso:country":"PL",
    "wof:name":"Chelm",
    "wof:placetype":"locality"
},
  "geometry": {"coordinates":[19.95,49.81667],"type":"Point"}
}