{
  "type": "Feature",
  "properties": {
    "gn:admin1_code":"80.0",
    "gn:admin2_code":"1805.0",
    "gn:admin3_code":"180507.0",
    "gn:asciiname":"Siedliska",
    "gn:country_code":"PL",
    "gn:dem":302,
    "gn:feature_class":"P",
    "gn:feature_code":"PPL",
    "gn:name":"Siedliska",
    "gn:population":0,
    "gn:timezone":"Europe/Warsaw",
    "iso:country":"PL",
    "name:ceb_x_preferred":[
        "Siedliska"
    ],
    "name:deu_x_preferred":[
        "Siedliska"
    ],
    "name:fra_x_preferred":[
        "Siedliska"
    ],
    "name:nld_x_preferred":[
        "Siedliska"
    ],
    "name:pol_x_preferred":[
        "Siedliska"
    ],
    "name:rus_x_preferred":[
        "\u0421\u0435\u0434\u043b\u0438\u0441\u043a\u0430"
    ],
    "name:ukr_x_preferred":[
        "\u0421\u0435\u0434\u043b\u0438\u0441\u044c\u043a\u0430"
    ],
    "wof:name":"Siedliska",
    "wof:placetype":"locality"
},
  "geometry": {"coordinates":[21.57704,49.60228],"type":"Point"}
}