{
  "type": "Feature",
  "properties": {
    "gn:admin1_code":"73.0",
    "gn:admin2_code":"462.0",
    "gn:admin3_code":"46201.0",
    "gn:asciiname":"Male Tarpno",
    "gn:country_code":"PL",
    "gn:dem":27,
    "gn:feature_class":"P",
    "gn:feature_code":"PPL",
    "gn:name":"Ma\u0142e Tarpno",
    "gn:population":0,
    "gn:timezone":"Europe/Warsaw",
    "iso:country":"PL",
    "wof:name":"Male Tarpno",
    "wof:placetype":"locality"
},
  "geometry": {"coordinates":[18.79326,53.50366999999999],"type":"Point"}
}