{
  "type": "Feature",
  "properties": {
    "gn:admin1_code":"84.0",
    "gn:admin2_code":"2613.0",
    "gn:admin3_code":"261305.0",
    "gn:asciiname":"Zelislawiczki",
    "gn:country_code":"PL",
    "gn:dem":238,
    "gn:feature_class":"P",
    "gn:feature_code":"PPL",
    "gn:name":"\u017belis\u0142awiczki",
    "gn:population":0,
    "gn:timezone":"Europe/Warsaw",
    "iso:country":"PL",
    "name:ceb_x_preferred":[
        "\u017belis\u0142awiczki"
    ],
    "name:pol_x_preferred":[
        "\u017belis\u0142awiczki"
    ],
    "name:ukr_x_preferred":[
        "\u0416\u0435\u043b\u0456\u0441\u043b\u0430\u0432\u0456\u0447\u043a\u0456"
    ],
    "wof:name":"Zelislawiczki",
    "wof:placetype":"locality"
},
  "geometry": {"coordinates":[19.87873,50.80572],"type":"Point"}
}