{
  "type": "Feature",
  "properties": {
    "gn:admin1_code":"72.0",
    "gn:admin2_code":"202.0",
    "gn:admin3_code":"20206.0",
    "gn:asciiname":"Trzebnik",
    "gn:country_code":"PL",
    "gn:dem":161,
    "gn:feature_class":"P",
    "gn:feature_code":"PPL",
    "gn:name":"Trzebnik",
    "gn:population":0,
    "gn:timezone":"Europe/Warsaw",
    "iso:country":"PL",
    "name:azb_x_preferred":[
        "\u0686\u0628\u0646\u06cc\u06a9"
    ],
    "name:fas_x_preferred":[
        "\u0686\u0628\u0646\u06cc\u06a9"
    ],
    "name:pol_x_preferred":[
        "Trzebnik"
    ],
    "name:spa_x_preferred":[
        "Trzebnik"
    ],
    "name:ukr_x_preferred":[
        "\u0422\u0448\u0435\u0431\u043d\u0438\u043a"
    ],
    "wof:name":"Trzebnik",
    "wof:placetype":"locality"
},
  "geometry": {"coordinates":[16.86812999999999,50.82275],"type":"Point"}
}