{
  "type": "Feature",
  "properties": {
    "gn:admin1_code":"87.0",
    "gn:admin2_code":"3207.0",
    "gn:admin3_code":"320706.0",
    "gn:asciiname":"Swietousc",
    "gn:country_code":"PL",
    "gn:dem":4,
    "gn:feature_class":"P",
    "gn:feature_code":"PPL",
    "gn:name":"Swi\u0119tou\u015b\u0107",
    "gn:population":0,
    "gn:timezone":"Europe/Warsaw",
    "iso:country":"PL",
    "name:pol_x_preferred":[
        "\u015awi\u0119tou\u015b\u0107"
    ],
    "name:und_x_variant":[
        "Swi\u0119tou\u015b\u0107"
    ],
    "name:vie_x_preferred":[
        "\u015awi\u0119tou\u015b\u0107"
    ],
    "wof:name":"Swietousc",
    "wof:placetype":"locality"
},
  "geometry": {"coordinates":[14.63366,53.9883],"type":"Point"}
}