{
  "type": "Feature",
  "properties": {
    "gn:admin1_code":"85.0",
    "gn:admin2_code":"2814.0",
    "gn:admin3_code":"281402.0",
    "gn:asciiname":"Bredynki",
    "gn:country_code":"PL",
    "gn:dem":162,
    "gn:feature_class":"P",
    "gn:feature_code":"PPL",
    "gn:name":"Bredynki",
    "gn:population":0,
    "gn:timezone":"Europe/Warsaw",
    "iso:country":"PL",
    "name:eng_x_preferred":[
        "Bredynki"
    ],
    "name:pol_x_preferred":[
        "Bredynki"
    ],
    "name:rus_x_preferred":[
        "\u0411\u0440\u0435\u0434\u044b\u043d\u043a\u0438"
    ],
    "name:ukr_x_preferred":[
        "\u0411\u0440\u0435\u0434\u0438\u043d\u043a\u0456"
    ],
    "name:und_x_variant":[
        "Bredinken"
    ],
    "name:vie_x_preferred":[
        "Bredynki"
    ],
    "wof:name":"Bredynki",
    "wof:placetype":"locality"
},
  "geometry": {"coordinates":[21.03954,53.89352],"type":"Point"}
}