{
  "type": "Feature",
  "properties": {
    "gn:admin1_code":"74.0",
    "gn:admin2_code":"1020.0",
    "gn:admin3_code":"102001.0",
    "gn:asciiname":"Warchalow Nowy",
    "gn:cc2":"PL",
    "gn:country_code":"PL",
    "gn:dem":121,
    "gn:feature_class":"P",
    "gn:feature_code":"PPL",
    "gn:name":"Warcha\u0142\u00f3w Nowy",
    "gn:population":0,
    "gn:timezone":"Europe/Warsaw",
    "iso:country":"PL",
    "name:und_x_variant":[
        "Warcha\u0142\u00f3w",
        "Warcha\u0142\u00f3w Nowy"
    ],
    "wof:name":"Warchalow Nowy",
    "wof:placetype":"locality"
},
  "geometry": {"coordinates":[19.71667,51.96667],"type":"Point"}
}