{
  "type": "Feature",
  "properties": {
    "gn:admin1_code":"77.0",
    "gn:admin2_code":"1214.0",
    "gn:admin3_code":"121401.0",
    "gn:asciiname":"Rzedowice",
    "gn:country_code":"PL",
    "gn:dem":216,
    "gn:feature_class":"P",
    "gn:feature_code":"PPL",
    "gn:name":"Rz\u0119dowice",
    "gn:population":0,
    "gn:timezone":"Europe/Warsaw",
    "iso:country":"PL",
    "wof:name":"Rzedowice",
    "wof:placetype":"locality"
},
  "geometry": {"coordinates":[20.24369,50.22049000000001],"type":"Point"}
}