{
  "type": "Feature",
  "properties": {
    "gn:admin1_code":"78.0",
    "gn:admin2_code":"1420.0",
    "gn:admin3_code":"142007.0",
    "gn:asciiname":"Dlutowo",
    "gn:country_code":"PL",
    "gn:dem":128,
    "gn:feature_class":"P",
    "gn:feature_code":"PPL",
    "gn:name":"D\u0142utowo",
    "gn:population":0,
    "gn:timezone":"Europe/Warsaw",
    "iso:country":"PL",
    "name:fra_x_preferred":[
        "D\u0142utowo"
    ],
    "name:pol_x_preferred":[
        "D\u0142utowo"
    ],
    "name:ukr_x_preferred":[
        "\u0414\u043b\u0443\u0442\u043e\u0432\u043e"
    ],
    "wof:name":"Dlutowo",
    "wof:placetype":"locality"
},
  "geometry": {"coordinates":[20.4382,52.49716],"type":"Point"}
}