{
  "type": "Feature",
  "properties": {
    "gn:gn_country":"PL",
    "gn:gn_fcode":"PPL",
    "gn:gn_pop":217,
    "gn:population":217,
    "iso:country":"PL",
    "name:unk_x_variant":[
        "Gross B\u00f6lkau"
    ],
    "qs_pg:aaroncc":"PL",
    "qs_pg:gn_country":"PL",
    "qs_pg:gn_fcode":"PPL",
    "qs_pg:gn_pop":217,
    "qs_pg:name":"Bielkowo",
    "qs_pg:photos_9r":0,
    "qs_pg:photos_sr":0,
    "qs_pg:pop_sr":2,
    "qs_pg:qs_pg_placetype":"locality",
    "wof:name":"Bielkowo",
    "wof:placetype":"locality",
    "wof:population":217
},
  "geometry": {"coordinates":[18.5111,54.26021],"type":"Point"}
}