{
  "type": "Feature",
  "properties": {
    "gn:admin1_code":"72.0",
    "gn:admin2_code":"224.0",
    "gn:admin3_code":"22407.0",
    "gn:asciiname":"Makolno",
    "gn:country_code":"PL",
    "gn:dem":357,
    "gn:feature_class":"P",
    "gn:feature_code":"PPL",
    "gn:name":"M\u0105kolno",
    "gn:population":0,
    "gn:timezone":"Europe/Warsaw",
    "iso:country":"PL",
    "wof:name":"Makolno",
    "wof:placetype":"locality"
},
  "geometry": {"coordinates":[16.83758,50.44767],"type":"Point"}
}