{
  "type": "Feature",
  "properties": {
    "gn:admin1_code":"75.0",
    "gn:admin2_code":"610.0",
    "gn:admin3_code":"61001.0",
    "gn:asciiname":"Garbatowka",
    "gn:country_code":"PL",
    "gn:dem":174,
    "gn:feature_class":"P",
    "gn:feature_code":"PPL",
    "gn:name":"Garbat\u00f3wka",
    "gn:population":0,
    "gn:timezone":"Europe/Warsaw",
    "iso:country":"PL",
    "name:und_x_variant":[
        "Garbat\u00f3wka"
    ],
    "wof:name":"Garbatowka",
    "wof:placetype":"locality"
},
  "geometry": {"coordinates":[23.11515,51.35935],"type":"Point"}
}