{
  "type": "Feature",
  "properties": {
    "gn:admin1_code":"74.0",
    "gn:admin2_code":"1014.0",
    "gn:admin3_code":"101408.0",
    "gn:asciiname":"Dzigorzew",
    "gn:country_code":"PL",
    "gn:dem":134,
    "gn:feature_class":"P",
    "gn:feature_code":"PPL",
    "gn:name":"Dzigorzew",
    "gn:population":0,
    "gn:timezone":"Europe/Warsaw",
    "iso:country":"PL",
    "name:pol_x_preferred":[
        "Dzigorzew"
    ],
    "name:ukr_x_preferred":[
        "\u0414\u0437\u0456\u0491\u043e\u0436\u0435\u0432"
    ],
    "wof:name":"Dzigorzew",
    "wof:placetype":"locality"
},
  "geometry": {"coordinates":[18.71339,51.61563],"type":"Point"}
}