{
  "type": "Feature",
  "properties": {
    "gn:admin1_code":"73.0",
    "gn:admin2_code":"414.0",
    "gn:admin3_code":"41405.0",
    "gn:asciiname":"Mukrz",
    "gn:country_code":"PL",
    "gn:dem":105,
    "gn:feature_class":"P",
    "gn:feature_code":"PPL",
    "gn:name":"Mukrz",
    "gn:population":0,
    "gn:timezone":"Europe/Warsaw",
    "iso:country":"PL",
    "name:pol_x_preferred":[
        "Mukrz"
    ],
    "name:ukr_x_preferred":[
        "\u041c\u0443\u043a\u0448"
    ],
    "wof:name":"Mukrz",
    "wof:placetype":"locality"
},
  "geometry": {"coordinates":[18.12102,53.52409],"type":"Point"}
}