{
  "type": "Feature",
  "properties": {
    "gn:admin1_code":"72.0",
    "gn:admin2_code":"208.0",
    "gn:admin3_code":"20812.0",
    "gn:asciiname":"Gorzuchowek",
    "gn:country_code":"PL",
    "gn:dem":314,
    "gn:feature_class":"P",
    "gn:feature_code":"PPL",
    "gn:name":"Gorzuch\u00f3wek",
    "gn:population":0,
    "gn:timezone":"Europe/Warsaw",
    "iso:country":"PL",
    "wof:name":"Gorzuchowek",
    "wof:placetype":"locality"
},
  "geometry": {"coordinates":[16.55065,50.48343],"type":"Point"}
}