{
  "type": "Feature",
  "properties": {
    "gn:gn_country":"PL",
    "gn:gn_fcode":"PPLA3",
    "gn:gn_pop":6770,
    "gn:population":6770,
    "iso:country":"PL",
    "name:bul_x_preferred":[
        "\u0420\u0443\u0434\u043d\u0438\u043a \u043d\u0430\u0434 \u0421\u0430\u043d\u0435\u043c"
    ],
    "name:ceb_x_preferred":[
        "Rudnik nad Sanem"
    ],
    "name:deu_x_preferred":[
        "Rudnik nad Sanem"
    ],
    "name:epo_x_preferred":[
        "Rudnik nad Sanem"
    ],
    "name:fra_x_preferred":[
        "Rudnik nad Sanem"
    ],
    "name:heb_x_preferred":[
        "\u05e8\u05d5\u05d3\u05e0\u05d9\u05e7 \u05e2\u05dc \u05e0\u05d4\u05e8 \u05e1\u05df"
    ],
    "name:jav_x_preferred":[
        "Rudnik nad Sanem"
    ],
    "name:lav_x_preferred":[
        "Rud\u0146ika pie Sanas"
    ],
    "name:msa_x_preferred":[
        "Rudnik nad Sanem"
    ],
    "name:nld_x_preferred":[
        "Rudnik nad Sanem"
    ],
    "name:pol_x_preferred":[
        "Rudnik nad Sanem"
    ],
    "name:por_x_preferred":[
        "Rudnik nad Sanem"
    ],
    "name:ron_x_preferred":[
        "Rudnik nad Sanem"
    ],
    "name:rus_x_preferred":[
        "\u0420\u0443\u0434\u043d\u0438\u043a-\u043d\u0430\u0434-\u0421\u0430\u043d\u0435\u043c"
    ],
    "name:slk_x_preferred":[
        "Rudnik nad Sanem"
    ],
    "name:srp_x_preferred":[
        "\u0420\u0443\u0434\u043d\u0438\u043a \u043d\u0430\u0434 \u0421\u0430\u043d\u0435\u043c"
    ],
    "name:ukr_x_preferred":[
        "\u0420\u0443\u0434\u043d\u0438\u043a-\u043d\u0430\u0434-\u0421\u044f\u043d\u043e\u043c"
    ],
    "name:vie_x_preferred":[
        "Rudnik nad Sanem"
    ],
    "name:yid_x_preferred":[
        "\u05e8\u05d5\u05d3\u05e0\u05d9\u05e7"
    ],
    "name:zho_x_preferred":[
        "\u6851\u6cb3\u7554\u9c81\u5fb7\u5c3c\u514b"
    ],
    "qs_pg:aaroncc":"PL",
    "qs_pg:gn_country":"PL",
    "qs_pg:gn_fcode":"PPLA3",
    "qs_pg:gn_pop":6770,
    "qs_pg:name":"Rudnik nad Sanem",
    "qs_pg:name_adm0":"Polska",
    "qs_pg:name_adm1":"Podkarpackie",
    "qs_pg:photos":4,
    "qs_pg:photos_1k":1,
    "qs_pg:photos_9k":1,
    "qs_pg:photos_9r":1,
    "qs_pg:photos_all":4,
    "qs_pg:photos_sr":1,
    "qs_pg:pop_sr":7,
    "qs_pg:qs_pg_placetype":"localadmin",
    "qs_pg:qs_pg_placetype_gp":"LocalAdmin",
    "qs_pg:woe_adm0":23424923,
    "woe:adm0_id":23424923,
    "woe:name_adm0":"Polska",
    "woe:name_adm1":"Podkarpackie",
    "woe:placetype":"LocalAdmin",
    "wof:name":"Rudnik nad Sanem",
    "wof:placetype":"localadmin",
    "wof:population":6770
},
  "geometry": {"coordinates":[22.24856,50.44152],"type":"Point"}
}