{
  "type": "Feature",
  "properties": {
    "gn:admin1_code":"72.0",
    "gn:admin2_code":"208.0",
    "gn:admin3_code":"20806.0",
    "gn:asciiname":"Dlugopole Dolne",
    "gn:country_code":"PL",
    "gn:dem":358,
    "gn:feature_class":"P",
    "gn:feature_code":"PPL",
    "gn:name":"D\u0142ugopole Dolne",
    "gn:population":0,
    "gn:timezone":"Europe/Warsaw",
    "iso:country":"PL",
    "name:und_x_variant":[
        "D\u0142ugopole Dolne"
    ],
    "wof:name":"Dlugopole Dolne",
    "wof:placetype":"locality"
},
  "geometry": {"coordinates":[16.63764,50.25792],"type":"Point"}
}