{
  "type": "Feature",
  "properties": {
    "gn:admin1_code":"86.0",
    "gn:admin2_code":"3001.0",
    "gn:admin3_code":"300102.0",
    "gn:asciiname":"Kakolewice",
    "gn:country_code":"PL",
    "gn:dem":87,
    "gn:feature_class":"P",
    "gn:feature_code":"PPL",
    "gn:name":"K\u0105kolewice",
    "gn:population":0,
    "gn:timezone":"Europe/Warsaw",
    "iso:country":"PL",
    "name:azb_x_preferred":[
        "\u06a9\u0627\u0646\u06a9\u0648\u0644\u0648\u06cc\u062a\u0633\u0647"
    ],
    "name:fas_x_preferred":[
        "\u06a9\u0627\u0646\u06a9\u0648\u0644\u0648\u06cc\u062a\u0633\u0647"
    ],
    "name:fra_x_preferred":[
        "K\u0105kolewice"
    ],
    "name:pol_x_preferred":[
        "K\u0105kolewice"
    ],
    "name:ukr_x_preferred":[
        "\u041a\u043e\u043d\u043a\u043e\u043b\u0435\u0432\u0456\u0446\u0435"
    ],
    "wof:name":"Kakolewice",
    "wof:placetype":"locality"
},
  "geometry": {"coordinates":[16.95791,52.91149],"type":"Point"}
}