{
  "type": "Feature",
  "properties": {
    "gn:admin1_code":"81.0",
    "gn:admin2_code":"2001.0",
    "gn:admin3_code":"200102.0",
    "gn:asciiname":"Topilowka",
    "gn:country_code":"PL",
    "gn:dem":150,
    "gn:feature_class":"P",
    "gn:feature_code":"PPL",
    "gn:name":"Topi\u0142\u00f3wka",
    "gn:population":0,
    "gn:timezone":"Europe/Warsaw",
    "iso:country":"PL",
    "name:und_x_variant":[
        "Topi\u0142\u00f3wka"
    ],
    "wof:name":"Topilowka",
    "wof:placetype":"locality"
},
  "geometry": {"coordinates":[22.88533,53.90728000000001],"type":"Point"}
}