{
  "type": "Feature",
  "properties": {
    "gn:country":"PL",
    "gn:fcode":"PPL",
    "gn:population":0,
    "iso:country":"PL",
    "name:ast_x_preferred":[
        "Weremie\u0144"
    ],
    "name:eng_x_preferred":[
        "Weremie\u0144"
    ],
    "name:fra_x_preferred":[
        "Weremie\u0144"
    ],
    "name:hun_x_preferred":[
        "Weremie\u0144"
    ],
    "name:pol_x_preferred":[
        "Weremie\u0144"
    ],
    "name:ukr_x_preferred":[
        "\u0412\u0435\u0440\u0435\u043c\u0456\u043d\u044c"
    ],
    "qs_pg:aaroncc":"PL",
    "qs_pg:gn_country":"PL",
    "qs_pg:gn_fcode":"PPL",
    "qs_pg:gn_pop":0,
    "qs_pg:name":"Weremie\u0144",
    "qs_pg:name_adm0":"Polska",
    "qs_pg:name_adm1":"Podkarpackie",
    "qs_pg:photos_9r":0,
    "qs_pg:photos_sr":0,
    "qs_pg:pop_sr":0,
    "qs_pg:qs_pg_placetype":"locality",
    "qs_pg:qs_pg_placetype_gp":"Town",
    "qs_pg:woe_adm0":23424923,
    "woe:adm0_id":23424923,
    "woe:name_adm0":"Polska",
    "woe:name_adm1":"Podkarpackie",
    "woe:placetype":"Town",
    "wof:name":"Weremie\u0144",
    "wof:placetype":"locality"
},
  "geometry": {"coordinates":[22.32937,49.45395],"type":"Point"}
}