{
  "type": "Feature",
  "properties": {
    "gn:admin1_code":"79.0",
    "gn:admin2_code":"1609.0",
    "gn:admin3_code":"160907.0",
    "gn:asciiname":"Wydrowice",
    "gn:country_code":"PL",
    "gn:dem":163,
    "gn:feature_class":"P",
    "gn:feature_code":"PPL",
    "gn:name":"Wydrowice",
    "gn:population":0,
    "gn:timezone":"Europe/Warsaw",
    "iso:country":"PL",
    "name:deu_x_preferred":[
        "Wydrowice"
    ],
    "name:pol_x_preferred":[
        "Wydrowice"
    ],
    "name:ukr_x_preferred":[
        "\u0412\u0438\u0434\u0440\u043e\u0432\u0456\u0446\u0435"
    ],
    "wof:name":"Wydrowice",
    "wof:placetype":"locality"
},
  "geometry": {"coordinates":[17.63662,50.62514],"type":"Point"}
}