{
  "type": "Feature",
  "properties": {
    "gn:admin1_code":"79.0",
    "gn:admin2_code":"1609.0",
    "gn:admin3_code":"160907.0",
    "gn:asciiname":"Wydrowice",
    "gn:country_code":"PL",
    "gn:dem":163,
    "gn:feature_class":"P",
    "gn:feature_code":"PPL",
    "gn:name":"Wydrowice",
    "gn:population":0,
    "gn:timezone":"Europe/Warsaw",
    "iso:country":"PL",
    "wof:name":"Wydrowice",
    "wof:placetype":"locality"
},
  "geometry": {"coordinates":[17.63662,50.62514],"type":"Point"}
}