{
  "type": "Feature",
  "properties": {
    "gn:admin1_code":"78.0",
    "gn:admin2_code":"1411.0",
    "gn:admin3_code":"141110.0",
    "gn:asciiname":"Dzierzanowo",
    "gn:country_code":"PL",
    "gn:dem":100,
    "gn:feature_class":"P",
    "gn:feature_code":"PPL",
    "gn:name":"Dzier\u017canowo",
    "gn:population":0,
    "gn:timezone":"Europe/Warsaw",
    "iso:country":"PL",
    "wof:name":"Dzierzanowo",
    "wof:placetype":"locality"
},
  "geometry": {"coordinates":[21.07439,52.79991999999999],"type":"Point"}
}