{
  "type": "Feature",
  "properties": {
    "gn:country":"PL",
    "gn:fcode":"PPLA3",
    "gn:population":5145,
    "iso:country":"PL",
    "name:azb_x_preferred":[
        "\u0698\u0648\u0648\u0646\u0642\u0627"
    ],
    "name:ceb_x_preferred":[
        "\u017bo\u0142ynia"
    ],
    "name:fas_x_preferred":[
        "\u0698\u0648\u0648\u0646\u06af\u0627"
    ],
    "name:fra_x_preferred":[
        "\u017bo\u0142ynia"
    ],
    "name:heb_x_preferred":[
        "\u05d6'\u05d5\u05dc\u05d9\u05e0\u05d9\u05d4"
    ],
    "name:nld_x_preferred":[
        "\u017bo\u0142ynia"
    ],
    "name:pol_x_preferred":[
        "\u017bo\u0142ynia"
    ],
    "name:ukr_x_preferred":[
        "\u0416\u043e\u043b\u0438\u043d\u044f"
    ],
    "qs_pg:aaroncc":"PL",
    "qs_pg:gn_country":"PL",
    "qs_pg:gn_fcode":"PPLA3",
    "qs_pg:gn_pop":5145,
    "qs_pg:name":"\u017bo\u0142ynia",
    "qs_pg:name_adm0":"Polska",
    "qs_pg:name_adm1":"Podkarpackie",
    "qs_pg:photos":12,
    "qs_pg:photos_1k":2,
    "qs_pg:photos_9k":1,
    "qs_pg:photos_9r":1,
    "qs_pg:photos_all":12,
    "qs_pg:photos_sr":1,
    "qs_pg:pop_sr":5,
    "qs_pg:qs_pg_placetype":"localadmin",
    "qs_pg:qs_pg_placetype_gp":"LocalAdmin",
    "qs_pg:woe_adm0":23424923,
    "woe:adm0_id":23424923,
    "woe:name_adm0":"Polska",
    "woe:name_adm1":"Podkarpackie",
    "woe:placetype":"LocalAdmin",
    "wof:name":"\u017bo\u0142ynia",
    "wof:placetype":"localadmin",
    "wof:population":5145
},
  "geometry": {"coordinates":[22.30825,50.162],"type":"Point"}
}