{
  "type": "Feature",
  "properties": {
    "gn:admin1_code":"76.0",
    "gn:admin2_code":"802.0",
    "gn:admin3_code":"80202.0",
    "gn:asciiname":"Welmice",
    "gn:country_code":"PL",
    "gn:dem":72,
    "gn:feature_class":"P",
    "gn:feature_code":"PPL",
    "gn:name":"We\u0142mice",
    "gn:population":0,
    "gn:timezone":"Europe/Warsaw",
    "iso:country":"PL",
    "name:ceb_x_preferred":[
        "We\u0142mice"
    ],
    "name:fra_x_preferred":[
        "We\u0142mice"
    ],
    "name:pol_x_preferred":[
        "We\u0142mice"
    ],
    "name:ukr_x_preferred":[
        "\u0412\u0435\u043b\u043c\u0456\u0446\u0435"
    ],
    "wof:name":"Welmice",
    "wof:placetype":"locality"
},
  "geometry": {"coordinates":[14.97776,51.90922],"type":"Point"}
}