{
  "type": "Feature",
  "properties": {
    "gn:admin1_code":"76.0",
    "gn:admin2_code":"811.0",
    "gn:admin3_code":"81103.0",
    "gn:asciiname":"Jalowice",
    "gn:country_code":"PL",
    "gn:dem":58,
    "gn:feature_class":"P",
    "gn:feature_code":"PPL",
    "gn:name":"Ja\u0142owice",
    "gn:population":0,
    "gn:timezone":"Europe/Warsaw",
    "iso:country":"PL",
    "name:und_x_variant":[
        "Ja\u0142owice"
    ],
    "wof:name":"Jalowice",
    "wof:placetype":"locality"
},
  "geometry": {"coordinates":[14.84072,51.84377],"type":"Point"}
}