{
  "type": "Feature",
  "properties": {
    "gn:admin1_code":"76.0",
    "gn:admin2_code":"811.0",
    "gn:admin3_code":"81103.0",
    "gn:asciiname":"Jalowice",
    "gn:country_code":"PL",
    "gn:dem":58,
    "gn:feature_class":"P",
    "gn:feature_code":"PPL",
    "gn:name":"Ja\u0142owice",
    "gn:population":0,
    "gn:timezone":"Europe/Warsaw",
    "iso:country":"PL",
    "name:ceb_x_preferred":[
        "Ja\u0142owice"
    ],
    "name:fas_x_preferred":[
        "\u06cc\u0627\u0648\u0648\u0648\u06cc\u062a\u0633\u0647"
    ],
    "name:fra_x_preferred":[
        "Ja\u0142owice"
    ],
    "name:pol_x_preferred":[
        "Ja\u0142owice"
    ],
    "name:ukr_x_preferred":[
        "\u042f\u043b\u043e\u0432\u0456\u0446\u0435"
    ],
    "name:urd_x_preferred":[
        "\u062c\u0627\u0648\u0627\u0648\u06a9\u06d2"
    ],
    "wof:name":"Jalowice",
    "wof:placetype":"locality"
},
  "geometry": {"coordinates":[14.84072,51.84377],"type":"Point"}
}