{
  "type": "Feature",
  "properties": {
    "gn:admin1_code":"86.0",
    "gn:admin2_code":"3018.0",
    "gn:admin3_code":"301807.0",
    "gn:asciiname":"Szklarka Myslniewska",
    "gn:country_code":"PL",
    "gn:dem":159,
    "gn:feature_class":"P",
    "gn:feature_code":"PPL",
    "gn:name":"Szklarka My\u015blniewska",
    "gn:population":0,
    "gn:timezone":"Europe/Warsaw",
    "iso:country":"PL",
    "name:und_x_variant":[
        "Szklarka My\u015bleniewska",
        "Szklarka My\u015blniewska"
    ],
    "wof:name":"Szklarka Myslniewska",
    "wof:placetype":"locality"
},
  "geometry": {"coordinates":[17.83132,51.43915],"type":"Point"}
}