{
  "type": "Feature",
  "properties": {
    "gn:admin1_code":"86.0",
    "gn:admin2_code":"3018.0",
    "gn:admin3_code":"301807.0",
    "gn:asciiname":"Szklarka Myslniewska",
    "gn:country_code":"PL",
    "gn:dem":159,
    "gn:feature_class":"P",
    "gn:feature_code":"PPL",
    "gn:name":"Szklarka My\u015blniewska",
    "gn:population":0,
    "gn:timezone":"Europe/Warsaw",
    "iso:country":"PL",
    "name:pol_x_preferred":[
        "Szklarka My\u015blniewska"
    ],
    "name:spa_x_preferred":[
        "Szklarka My\u015blniewska"
    ],
    "name:ukr_x_preferred":[
        "\u0428\u043a\u043b\u044f\u0440\u043a\u0430-\u041c\u0438\u0441\u043b\u044c\u043d\u0435\u0432\u0441\u044c\u043a\u0430"
    ],
    "name:und_x_variant":[
        "Szklarka My\u015bleniewska"
    ],
    "wof:name":"Szklarka Myslniewska",
    "wof:placetype":"locality"
},
  "geometry": {"coordinates":[17.83132,51.43915],"type":"Point"}
}