{
  "type": "Feature",
  "properties": {
    "gn:admin1_code":"78.0",
    "gn:admin2_code":"1414.0",
    "gn:admin3_code":"141402.0",
    "gn:asciiname":"Kazun Polski",
    "gn:country_code":"PL",
    "gn:dem":73,
    "gn:feature_class":"P",
    "gn:feature_code":"PPL",
    "gn:name":"Kazu\u0144 Polski",
    "gn:population":0,
    "gn:timezone":"Europe/Warsaw",
    "iso:country":"PL",
    "name:und_x_variant":[
        "Kazu\u0144 Polski"
    ],
    "wof:name":"Kazun Polski",
    "wof:placetype":"locality"
},
  "geometry": {"coordinates":[20.66261,52.40041],"type":"Point"}
}