{
  "type": "Feature",
  "properties": {
    "gn:admin1_code":"78.0",
    "gn:admin2_code":"1414.0",
    "gn:admin3_code":"141402.0",
    "gn:asciiname":"Kazun Polski",
    "gn:country_code":"PL",
    "gn:dem":73,
    "gn:feature_class":"P",
    "gn:feature_code":"PPL",
    "gn:name":"Kazu\u0144 Polski",
    "gn:population":0,
    "gn:timezone":"Europe/Warsaw",
    "iso:country":"PL",
    "name:azb_x_preferred":[
        "\u06a9\u0627\u0632\u0648\u0646\u0642 \u067e\u0648\u0644\u0633\u06a9\u06cc"
    ],
    "name:ceb_x_preferred":[
        "Kazu\u0144 Polski"
    ],
    "name:fas_x_preferred":[
        "\u06a9\u0627\u0632\u0648\u0646\u06af \u067e\u0648\u0644\u0633\u06a9\u06cc"
    ],
    "name:fra_x_preferred":[
        "Kazu\u0144 Polski"
    ],
    "name:nld_x_preferred":[
        "Kazu\u0144 Polski"
    ],
    "name:pol_x_preferred":[
        "Kazu\u0144 Polski"
    ],
    "name:ukr_x_preferred":[
        "\u041a\u0430\u0437\u0443\u043d\u044c-\u041f\u043e\u043b\u044c\u0441\u044c\u043a\u0438\u0439"
    ],
    "wof:name":"Kazun Polski",
    "wof:placetype":"locality"
},
  "geometry": {"coordinates":[20.66261,52.40041],"type":"Point"}
}