{
  "type": "Feature",
  "properties": {
    "gn:admin1_code":"87.0",
    "gn:admin2_code":"3218.0",
    "gn:admin3_code":"321804.0",
    "gn:asciiname":"Zerzyno",
    "gn:country_code":"PL",
    "gn:dem":35,
    "gn:feature_class":"P",
    "gn:feature_code":"PPL",
    "gn:name":"\u017berzyno",
    "gn:population":0,
    "gn:timezone":"Europe/Warsaw",
    "iso:country":"PL",
    "name:pol_x_preferred":[
        "\u017berzyno"
    ],
    "name:vie_x_preferred":[
        "\u017berzyno"
    ],
    "wof:name":"Zerzyno",
    "wof:placetype":"locality"
},
  "geometry": {"coordinates":[15.25,53.73333],"type":"Point"}
}