{
  "type": "Feature",
  "properties": {
    "gn:admin1_code":"82.0",
    "gn:admin2_code":"2206.0",
    "gn:admin3_code":"220608.0",
    "gn:asciiname":"Lipy",
    "gn:country_code":"PL",
    "gn:dem":126,
    "gn:feature_class":"P",
    "gn:feature_code":"PPL",
    "gn:name":"Lipy",
    "gn:population":0,
    "gn:timezone":"Europe/Warsaw",
    "iso:country":"PL",
    "name:ceb_x_preferred":[
        "Lipy"
    ],
    "name:pol_x_preferred":[
        "Lipy"
    ],
    "name:ukr_x_preferred":[
        "\u041b\u0456\u043f\u0438"
    ],
    "name:und_x_variant":[
        "Blumfeld"
    ],
    "wof:name":"Lipy",
    "wof:placetype":"locality"
},
  "geometry": {"coordinates":[18.22293,53.9634],"type":"Point"}
}