{
  "type": "Feature",
  "properties": {
    "gn:admin1_code":"78.0",
    "gn:admin2_code":"1413.0",
    "gn:admin3_code":"141306.0",
    "gn:asciiname":"Rosochy",
    "gn:country_code":"PL",
    "gn:dem":122,
    "gn:feature_class":"P",
    "gn:feature_code":"PPL",
    "gn:name":"Rosochy",
    "gn:population":0,
    "gn:timezone":"Europe/Warsaw",
    "iso:country":"PL",
    "name:fra_x_preferred":[
        "Rosochy"
    ],
    "name:pol_x_preferred":[
        "Rosochy"
    ],
    "name:ukr_x_preferred":[
        "\u0420\u043e\u0441\u043e\u0445\u0438"
    ],
    "wof:name":"Rosochy",
    "wof:placetype":"locality"
},
  "geometry": {"coordinates":[20.48007,52.98887],"type":"Point"}
}