{
  "type": "Feature",
  "properties": {
    "gn:admin1_code":"83.0",
    "gn:admin2_code":"2461.0",
    "gn:admin3_code":"246101.0",
    "gn:asciiname":"Lipnik Gorny",
    "gn:country_code":"PL",
    "gn:dem":370,
    "gn:feature_class":"P",
    "gn:feature_code":"PPL",
    "gn:name":"Lipnik G\u00f3rny",
    "gn:population":0,
    "gn:timezone":"Europe/Warsaw",
    "iso:country":"PL",
    "wof:name":"Lipnik Gorny",
    "wof:placetype":"neighbourhood"
},
  "geometry": {"coordinates":[19.08849,49.82569],"type":"Point"}
}