{
  "type": "Feature",
  "properties": {
    "gn:admin1_code":"72.0",
    "gn:admin2_code":"205.0",
    "gn:admin3_code":"20506.0",
    "gn:asciiname":"Postolice",
    "gn:cc2":"PL",
    "gn:country_code":"PL",
    "gn:dem":155,
    "gn:feature_class":"P",
    "gn:feature_code":"PPL",
    "gn:name":"Postolice",
    "gn:population":0,
    "gn:timezone":"Europe/Warsaw",
    "iso:country":"PL",
    "name:pol_x_preferred":[
        "Postolice"
    ],
    "name:ukr_x_preferred":[
        "\u041f\u043e\u0441\u0442\u043e\u043b\u0456\u0446\u0435"
    ],
    "name:und_x_variant":[
        "Poselwitz"
    ],
    "wof:name":"Postolice",
    "wof:placetype":"locality"
},
  "geometry": {"coordinates":[16.42817,51.10686],"type":"Point"}
}