{
  "type": "Feature",
  "properties": {
    "gn:admin1_code":"84.0",
    "gn:admin2_code":"2603.0",
    "gn:admin3_code":"260302.0",
    "gn:asciiname":"Stropieszyn",
    "gn:country_code":"PL",
    "gn:dem":221,
    "gn:feature_class":"P",
    "gn:feature_code":"PPL",
    "gn:name":"Stropieszyn",
    "gn:population":0,
    "gn:timezone":"Europe/Warsaw",
    "iso:country":"PL",
    "name:pol_x_preferred":[
        "Stropieszyn"
    ],
    "name:ukr_x_preferred":[
        "\u0421\u0442\u0440\u043e\u043f\u0435\u0448\u0438\u043d"
    ],
    "wof:name":"Stropieszyn",
    "wof:placetype":"locality"
},
  "geometry": {"coordinates":[20.61627,50.28989],"type":"Point"}
}