{
  "type": "Feature",
  "properties": {
    "gn:admin1_code":"87.0",
    "gn:admin2_code":"3206.0",
    "gn:admin3_code":"320603.0",
    "gn:asciiname":"Bialegi",
    "gn:country_code":"PL",
    "gn:dem":69,
    "gn:feature_class":"P",
    "gn:feature_code":"PPL",
    "gn:name":"Bia\u0142\u0119gi",
    "gn:population":0,
    "gn:timezone":"Europe/Warsaw",
    "iso:country":"PL",
    "name:pol_x_preferred":[
        "Bia\u0142\u0119gi"
    ],
    "name:ukr_x_preferred":[
        "\u0411\u044f\u043b\u0435\u043d\u0491\u0456"
    ],
    "name:und_x_variant":[
        "Belgen"
    ],
    "wof:name":"Bialegi",
    "wof:placetype":"locality"
},
  "geometry": {"coordinates":[14.52959,52.86291],"type":"Point"}
}