{
  "type": "Feature",
  "properties": {
    "gn:admin1_code":"85.0",
    "gn:admin2_code":"2806.0",
    "gn:admin3_code":"280605.0",
    "gn:asciiname":"Mozdzany",
    "gn:country_code":"PL",
    "gn:dem":147,
    "gn:feature_class":"P",
    "gn:feature_code":"PPL",
    "gn:name":"Mo\u017cd\u017cany",
    "gn:population":0,
    "gn:timezone":"Europe/Warsaw",
    "iso:country":"PL",
    "name:azb_x_preferred":[
        "\u0645\u0648\u0698\u0686\u0627\u0646\u0647"
    ],
    "name:deu_x_preferred":[
        "Mo\u017cd\u017cany"
    ],
    "name:fas_x_preferred":[
        "\u0645\u0648\u0698\u0686\u0627\u0646\u0647"
    ],
    "name:fra_x_preferred":[
        "Mo\u017cd\u017cany"
    ],
    "name:pol_x_preferred":[
        "Mo\u017cd\u017cany"
    ],
    "name:swe_x_preferred":[
        "Mo\u017cd\u017cany"
    ],
    "name:ukr_x_preferred":[
        "\u041c\u043e\u0436\u0434\u0436\u0430\u043d\u0438"
    ],
    "name:und_x_variant":[
        "Borkenwalde",
        "Mosdzehnen"
    ],
    "wof:name":"Mozdzany",
    "wof:placetype":"locality"
},
  "geometry": {"coordinates":[22.03008,54.0722],"type":"Point"}
}