{
  "type": "Feature",
  "properties": {
    "gn:admin1_code":"85.0",
    "gn:admin2_code":"2806.0",
    "gn:admin3_code":"280605.0",
    "gn:asciiname":"Mozdzany",
    "gn:country_code":"PL",
    "gn:dem":147,
    "gn:feature_class":"P",
    "gn:feature_code":"PPL",
    "gn:name":"Mo\u017cd\u017cany",
    "gn:population":0,
    "gn:timezone":"Europe/Warsaw",
    "iso:country":"PL",
    "name:und_x_variant":[
        "Borkenwalde",
        "Mosdzehnen",
        "Mo\u017cd\u017cany"
    ],
    "wof:name":"Mozdzany",
    "wof:placetype":"locality"
},
  "geometry": {"coordinates":[22.03008,54.0722],"type":"Point"}
}