{
  "type": "Feature",
  "properties": {
    "gn:country":"PL",
    "gn:fcode":"PPL",
    "gn:population":0,
    "iso:country":"PL",
    "name:ast_x_preferred":[
        "Bibice"
    ],
    "name:azb_x_preferred":[
        "\u0628\u06cc\u0628\u06cc\u062a\u0633\u0647"
    ],
    "name:ceb_x_preferred":[
        "Bibice"
    ],
    "name:eng_x_preferred":[
        "Bibice"
    ],
    "name:fas_x_preferred":[
        "\u0628\u06cc\u0628\u06cc\u062a\u0633\u0647"
    ],
    "name:fra_x_preferred":[
        "Bibice"
    ],
    "name:nld_x_preferred":[
        "Bibice"
    ],
    "name:pol_x_preferred":[
        "Bibice"
    ],
    "name:rus_x_preferred":[
        "\u0411\u0438\u0431\u0438\u0446\u0435"
    ],
    "name:ukr_x_preferred":[
        "\u0411\u0456\u0431\u0456\u0446\u0435"
    ],
    "qs_pg:aaroncc":"PL",
    "qs_pg:gn_country":"PL",
    "qs_pg:gn_fcode":"PPL",
    "qs_pg:gn_pop":0,
    "qs_pg:name":"Bibice",
    "qs_pg:name_adm0":"Polska",
    "qs_pg:name_adm1":"Ma\u0142opolskie",
    "qs_pg:photos_9r":0,
    "qs_pg:photos_sr":0,
    "qs_pg:pop_sr":0,
    "qs_pg:qs_pg_placetype":"locality",
    "qs_pg:qs_pg_placetype_gp":"Town",
    "qs_pg:woe_adm0":23424923,
    "woe:adm0_id":23424923,
    "woe:name_adm0":"Polska",
    "woe:name_adm1":"Ma\u0142opolskie",
    "woe:placetype":"Town",
    "wof:name":"Bibice",
    "wof:placetype":"locality"
},
  "geometry": {"coordinates":[19.95358,50.12586],"type":"Point"}
}