{
  "type": "Feature",
  "properties": {
    "gn:admin1_code":"79.0",
    "gn:admin2_code":"1608.0",
    "gn:admin3_code":"160802.0",
    "gn:asciiname":"Gola",
    "gn:country_code":"PL",
    "gn:dem":227,
    "gn:feature_class":"P",
    "gn:feature_code":"PPL",
    "gn:name":"Go\u0142a",
    "gn:population":0,
    "gn:timezone":"Europe/Warsaw",
    "iso:country":"PL",
    "name:azb_x_preferred":[
        "\u0642\u0648\u0644\u0627"
    ],
    "name:ceb_x_preferred":[
        "Go\u0142a"
    ],
    "name:fas_x_preferred":[
        "\u06af\u0648\u0644\u0627"
    ],
    "name:pol_x_preferred":[
        "Go\u0142a"
    ],
    "name:rus_x_preferred":[
        "\u0413\u043e\u043b\u0430"
    ],
    "name:ukr_x_preferred":[
        "\u0490\u043e\u043b\u0430"
    ],
    "wof:name":"Gola",
    "wof:placetype":"locality"
},
  "geometry": {"coordinates":[18.3736,51.07204],"type":"Point"}
}