{
  "type": "Feature",
  "properties": {
    "gn:admin1_code":"87.0",
    "gn:admin2_code":"3208.0",
    "gn:admin3_code":"320802.0",
    "gn:asciiname":"Bardy",
    "gn:cc2":"PL",
    "gn:country_code":"PL",
    "gn:dem":37,
    "gn:feature_class":"P",
    "gn:feature_code":"PPL",
    "gn:name":"Bardy",
    "gn:population":0,
    "gn:timezone":"Europe/Warsaw",
    "iso:country":"PL",
    "name:deu_x_preferred":[
        "Bardy"
    ],
    "name:ita_x_preferred":[
        "Bardy"
    ],
    "name:pol_x_preferred":[
        "Bardy"
    ],
    "name:ukr_x_preferred":[
        "\u0411\u0430\u0440\u0434\u0438"
    ],
    "name:und_x_variant":[
        "Bartin",
        "Bardy"
    ],
    "name:vie_x_preferred":[
        "Bardy"
    ],
    "wof:name":"Bardy",
    "wof:placetype":"locality"
},
  "geometry": {"coordinates":[15.70599,54.10953000000001],"type":"Point"}
}