{
  "type": "Feature",
  "properties": {
    "gn:admin1_code":"85.0",
    "gn:admin2_code":"2811.0",
    "gn:admin3_code":"281103.0",
    "gn:asciiname":"Satop",
    "gn:country_code":"PL",
    "gn:dem":186,
    "gn:feature_class":"P",
    "gn:feature_code":"PPL",
    "gn:name":"S\u0105top",
    "gn:population":0,
    "gn:timezone":"Europe/Warsaw",
    "iso:country":"PL",
    "name:und_x_variant":[
        "Santop",
        "Sontopp",
        "S\u0105top"
    ],
    "wof:name":"Satop",
    "wof:placetype":"locality"
},
  "geometry": {"coordinates":[20.31367,53.32619],"type":"Point"}
}