{
  "type": "Feature",
  "properties": {
    "gn:admin1_code":"87.0",
    "gn:admin2_code":"3202.0",
    "gn:admin3_code":"320206.0",
    "gn:asciiname":"Wielgoszcz",
    "gn:country_code":"PL",
    "gn:dem":87,
    "gn:feature_class":"P",
    "gn:feature_code":"PPL",
    "gn:name":"Wielgoszcz",
    "gn:population":0,
    "gn:timezone":"Europe/Warsaw",
    "iso:country":"PL",
    "name:pol_x_preferred":[
        "Wielgoszcz"
    ],
    "name:ukr_x_preferred":[
        "\u0412\u0435\u043b\u044c\u0491\u043e\u0449"
    ],
    "name:vie_x_preferred":[
        "Wielgoszcz"
    ],
    "wof:name":"Wielgoszcz",
    "wof:placetype":"locality"
},
  "geometry": {"coordinates":[15.57135,53.27519],"type":"Point"}
}