{
  "type": "Feature",
  "properties": {
    "gn:admin1_code":"78.0",
    "gn:admin2_code":"1429.0",
    "gn:admin3_code":"142902.0",
    "gn:asciiname":"Blonie Duze",
    "gn:country_code":"PL",
    "gn:dem":166,
    "gn:feature_class":"P",
    "gn:feature_code":"PPL",
    "gn:name":"B\u0142onie Du\u017ce",
    "gn:population":0,
    "gn:timezone":"Europe/Warsaw",
    "iso:country":"PL",
    "name:azb_x_preferred":[
        "\u0628\u0648\u0648\u0646\u0642\u0647 \u062f\u0648\u0698\u0647"
    ],
    "name:fas_x_preferred":[
        "\u0628\u0648\u0648\u0646\u06af\u0647 \u062f\u0648\u0698\u0647"
    ],
    "name:fra_x_preferred":[
        "B\u0142onie Du\u017ce"
    ],
    "name:lit_x_preferred":[
        "Blone Du\u017e\u0117"
    ],
    "name:pol_x_preferred":[
        "B\u0142onie Du\u017ce"
    ],
    "name:ukr_x_preferred":[
        "\u0411\u043b\u043e\u043d\u0435-\u0414\u0443\u0436\u0435"
    ],
    "name:und_x_variant":[
        "B\u0142onie Wielkie"
    ],
    "wof:name":"Blonie Duze",
    "wof:placetype":"locality"
},
  "geometry": {"coordinates":[22.2856,52.35844],"type":"Point"}
}