{
  "type": "Feature",
  "properties": {
    "gn:admin1_code":"78.0",
    "gn:admin2_code":"1429.0",
    "gn:admin3_code":"142902.0",
    "gn:asciiname":"Blonie Duze",
    "gn:country_code":"PL",
    "gn:dem":166,
    "gn:feature_class":"P",
    "gn:feature_code":"PPL",
    "gn:name":"B\u0142onie Du\u017ce",
    "gn:population":0,
    "gn:timezone":"Europe/Warsaw",
    "iso:country":"PL",
    "name:und_x_variant":[
        "B\u0142onie Wielkie",
        "B\u0142onie Du\u017ce"
    ],
    "wof:name":"Blonie Duze",
    "wof:placetype":"locality"
},
  "geometry": {"coordinates":[22.2856,52.35844],"type":"Point"}
}