{
  "type": "Feature",
  "properties": {
    "gn:admin1_code":"86.0",
    "gn:admin2_code":"3029.0",
    "gn:admin3_code":"302902.0",
    "gn:asciiname":"Jaromierz",
    "gn:country_code":"PL",
    "gn:dem":56,
    "gn:feature_class":"P",
    "gn:feature_code":"PPL",
    "gn:name":"Jaromierz",
    "gn:population":0,
    "gn:timezone":"Europe/Warsaw",
    "iso:country":"PL",
    "name:ceb_x_preferred":[
        "Jaromierz"
    ],
    "name:fra_x_preferred":[
        "Jaromierz"
    ],
    "name:pol_x_preferred":[
        "Jaromierz"
    ],
    "name:ukr_x_preferred":[
        "\u042f\u0440\u043e\u043c\u0435\u0436"
    ],
    "name:urd_x_preferred":[
        "\u062c\u0631\u0648\u0645\u06cc\u0631\u0632"
    ],
    "wof:name":"Jaromierz",
    "wof:placetype":"locality"
},
  "geometry": {"coordinates":[15.94963,52.09868],"type":"Point"}
}