{
  "type": "Feature",
  "properties": {
    "gn:admin1_code":"87.0",
    "gn:admin2_code":"3207.0",
    "gn:admin3_code":"320706.0",
    "gn:asciiname":"Dobropole",
    "gn:country_code":"PL",
    "gn:dem":13,
    "gn:feature_class":"P",
    "gn:feature_code":"PPL",
    "gn:name":"Dobropole",
    "gn:population":0,
    "gn:timezone":"Europe/Warsaw",
    "iso:country":"PL",
    "name:ceb_x_preferred":[
        "Dobropole"
    ],
    "name:pol_x_preferred":[
        "Dobropole"
    ],
    "name:ukr_x_preferred":[
        "\u0414\u043e\u0431\u0440\u043e\u043f\u043e\u043b\u0435"
    ],
    "name:und_x_variant":[
        "Dobberphul",
        "Dobropole"
    ],
    "wof:name":"Dobropole",
    "wof:placetype":"locality"
},
  "geometry": {"coordinates":[14.7577,53.85868000000001],"type":"Point"}
}