{
  "type": "Feature",
  "properties": {
    "gn:admin1_code":"74.0",
    "gn:admin2_code":"1015.0",
    "gn:admin3_code":"101504.0",
    "gn:asciiname":"Budy Chojnackie",
    "gn:country_code":"PL",
    "gn:dem":193,
    "gn:feature_class":"P",
    "gn:feature_code":"PPL",
    "gn:name":"Budy Chojnackie",
    "gn:population":0,
    "gn:timezone":"Europe/Warsaw",
    "iso:country":"PL",
    "name:pol_x_preferred":[
        "Budy Chojnackie"
    ],
    "name:ukr_x_preferred":[
        "\u0411\u0443\u0434\u0438-\u0425\u043e\u0439\u043d\u0430\u0446\u044c\u043a\u0456"
    ],
    "wof:name":"Budy Chojnackie",
    "wof:placetype":"locality"
},
  "geometry": {"coordinates":[20.48161,51.89122],"type":"Point"}
}