{
  "type": "Feature",
  "properties": {
    "gn:admin1_code":"86.0",
    "gn:admin2_code":"3007.0",
    "gn:admin3_code":"300702.0",
    "gn:asciiname":"Czempisz",
    "gn:country_code":"PL",
    "gn:dem":137,
    "gn:feature_class":"P",
    "gn:feature_code":"PPL",
    "gn:name":"Czempisz",
    "gn:population":0,
    "gn:timezone":"Europe/Warsaw",
    "iso:country":"PL",
    "name:pol_x_preferred":[
        "Czempisz"
    ],
    "name:ukr_x_preferred":[
        "\u0427\u0435\u043c\u043f\u0456\u0448"
    ],
    "wof:name":"Czempisz",
    "wof:placetype":"locality"
},
  "geometry": {"coordinates":[18.28504,51.57713],"type":"Point"}
}