{
  "type": "Feature",
  "properties": {
    "gn:admin1_code":"77.0",
    "gn:admin2_code":"1208.0",
    "gn:admin3_code":"120807.0",
    "gn:asciiname":"Kalina Wysiolek",
    "gn:country_code":"PL",
    "gn:dem":362,
    "gn:feature_class":"P",
    "gn:feature_code":"PPL",
    "gn:name":"Kalina Wysi\u00f3lek",
    "gn:population":0,
    "gn:timezone":"Europe/Warsaw",
    "iso:country":"PL",
    "wof:name":"Kalina Wysiolek",
    "wof:placetype":"locality"
},
  "geometry": {"coordinates":[20.16667,50.36667],"type":"Point"}
}