{
  "type": "Feature",
  "properties": {
    "gn:admin1_code":"75.0",
    "gn:admin2_code":"606.0",
    "gn:admin3_code":"60611.0",
    "gn:asciiname":"Poperczyn",
    "gn:country_code":"PL",
    "gn:dem":212,
    "gn:feature_class":"P",
    "gn:feature_code":"PPL",
    "gn:name":"Poperczyn",
    "gn:population":0,
    "gn:timezone":"Europe/Warsaw",
    "iso:country":"PL",
    "wof:name":"Poperczyn",
    "wof:placetype":"locality"
},
  "geometry": {"coordinates":[22.90207,50.92528],"type":"Point"}
}