{
  "type": "Feature",
  "properties": {
    "gn:admin1_code":"78.0",
    "gn:admin2_code":"1407.0",
    "gn:admin3_code":"140702.0",
    "gn:asciiname":"Moniochy",
    "gn:country_code":"PL",
    "gn:dem":143,
    "gn:feature_class":"P",
    "gn:feature_code":"PPL",
    "gn:name":"Moniochy",
    "gn:population":0,
    "gn:timezone":"Europe/Warsaw",
    "iso:country":"PL",
    "name:fra_x_preferred":[
        "Moniochy"
    ],
    "name:pol_x_preferred":[
        "Moniochy"
    ],
    "name:ukr_x_preferred":[
        "\u041c\u043e\u043d\u044c\u043e\u0445\u0438"
    ],
    "wof:name":"Moniochy",
    "wof:placetype":"locality"
},
  "geometry": {"coordinates":[21.30858,51.64236],"type":"Point"}
}