{
  "type": "Feature",
  "properties": {
    "gn:admin1_code":"81.0",
    "gn:admin2_code":"2013.0",
    "gn:admin3_code":"201309.0",
    "gn:asciiname":"Pulazie Swierze",
    "gn:country_code":"PL",
    "gn:dem":130,
    "gn:feature_class":"P",
    "gn:feature_code":"PPL",
    "gn:name":"Pu\u0142azie \u015awierze",
    "gn:population":0,
    "gn:timezone":"Europe/Warsaw",
    "iso:country":"PL",
    "wof:name":"Pulazie Swierze",
    "wof:placetype":"locality"
},
  "geometry": {"coordinates":[22.61321,52.84151],"type":"Point"}
}