{
  "type": "Feature",
  "properties": {
    "gn:country":"PL",
    "gn:fcode":"PPL",
    "gn:population":1110,
    "iso:country":"PL",
    "name:ast_x_preferred":[
        "Ryma\u0144"
    ],
    "name:ceb_x_preferred":[
        "Ryma\u0144"
    ],
    "name:deu_x_preferred":[
        "Ryma\u0144"
    ],
    "name:eng_x_preferred":[
        "Ryma\u0144"
    ],
    "name:fra_x_preferred":[
        "Ryma\u0144"
    ],
    "name:nld_x_preferred":[
        "Ryma\u0144"
    ],
    "name:pol_x_preferred":[
        "Ryma\u0144"
    ],
    "name:ukr_x_preferred":[
        "\u0420\u0438\u043c\u0430\u043d\u044c"
    ],
    "name:und_x_variant":[
        "Roman"
    ],
    "name:vie_x_preferred":[
        "Ryma\u0144"
    ],
    "qs_pg:aaroncc":"PL",
    "qs_pg:gn_country":"PL",
    "qs_pg:gn_fcode":"PPL",
    "qs_pg:gn_pop":1110,
    "qs_pg:name":"Ryma\u0144",
    "qs_pg:name_adm0":"Polska",
    "qs_pg:name_adm1":"Zachodniopomorskie",
    "qs_pg:photos_9k":1,
    "qs_pg:photos_9r":1,
    "qs_pg:photos_all":1,
    "qs_pg:photos_sr":0,
    "qs_pg:pop_sr":3,
    "qs_pg:qs_pg_placetype":"locality",
    "qs_pg:qs_pg_placetype_gp":"Town",
    "qs_pg:woe_adm0":23424923,
    "woe:adm0_id":23424923,
    "woe:name_adm0":"Polska",
    "woe:name_adm1":"Zachodniopomorskie",
    "woe:placetype":"Town",
    "wof:name":"Ryma\u0144",
    "wof:placetype":"locality",
    "wof:population":1110
},
  "geometry": {"coordinates":[15.52866,53.94391],"type":"Point"}
}