{
  "type": "Feature",
  "properties": {
    "gn:admin1_code":"77.0",
    "gn:admin2_code":"1203.0",
    "gn:admin3_code":"120304.0",
    "gn:asciiname":"Moczydlo",
    "gn:country_code":"PL",
    "gn:dem":258,
    "gn:feature_class":"P",
    "gn:feature_code":"PPL",
    "gn:name":"Moczyd\u0142o",
    "gn:population":0,
    "gn:timezone":"Europe/Warsaw",
    "iso:country":"PL",
    "wof:name":"Moczydlo",
    "wof:placetype":"locality"
},
  "geometry": {"coordinates":[19.33333,50.08333],"type":"Point"}
}