{
  "type": "Feature",
  "properties": {
    "gn:admin1_code":"85.0",
    "gn:admin2_code":"2802.0",
    "gn:admin3_code":"280204.0",
    "gn:asciiname":"Krzekoty",
    "gn:country_code":"PL",
    "gn:dem":104,
    "gn:feature_class":"P",
    "gn:feature_code":"PPL",
    "gn:name":"Krzekoty",
    "gn:population":0,
    "gn:timezone":"Europe/Warsaw",
    "iso:country":"PL",
    "name:und_x_variant":[
        "Gross Hasselberg",
        "Krzekoty"
    ],
    "wof:name":"Krzekoty",
    "wof:placetype":"locality"
},
  "geometry": {"coordinates":[20.1662,54.33953],"type":"Point"}
}