{
  "type": "Feature",
  "properties": {
    "gn:admin1_code":"85.0",
    "gn:admin2_code":"2802.0",
    "gn:admin3_code":"280204.0",
    "gn:asciiname":"Krzekoty",
    "gn:country_code":"PL",
    "gn:dem":104,
    "gn:feature_class":"P",
    "gn:feature_code":"PPL",
    "gn:name":"Krzekoty",
    "gn:population":0,
    "gn:timezone":"Europe/Warsaw",
    "iso:country":"PL",
    "name:azb_x_preferred":[
        "\u06a9\u0698\u06a9\u0648\u062a\u0647"
    ],
    "name:fas_x_preferred":[
        "\u06a9\u0698\u06a9\u0648\u062a\u0647"
    ],
    "name:fra_x_preferred":[
        "Krzekoty"
    ],
    "name:nld_x_preferred":[
        "Krzekoty"
    ],
    "name:pol_x_preferred":[
        "Krzekoty"
    ],
    "name:ukr_x_preferred":[
        "\u041a\u0448\u0435\u043a\u043e\u0442\u0438"
    ],
    "name:und_x_variant":[
        "Gross Hasselberg",
        "Krzekoty"
    ],
    "wof:name":"Krzekoty",
    "wof:placetype":"locality"
},
  "geometry": {"coordinates":[20.1662,54.33953],"type":"Point"}
}