{
  "type": "Feature",
  "properties": {
    "gn:admin1_code":"76.0",
    "gn:admin2_code":"809.0",
    "gn:admin3_code":"80902.0",
    "gn:asciiname":"Belcze",
    "gn:country_code":"PL",
    "gn:dem":56,
    "gn:feature_class":"P",
    "gn:feature_code":"PPL",
    "gn:name":"Be\u0142cze",
    "gn:population":0,
    "gn:timezone":"Europe/Warsaw",
    "iso:country":"PL",
    "name:fra_x_preferred":[
        "Be\u0142cze"
    ],
    "name:pol_x_preferred":[
        "Be\u0142cze"
    ],
    "name:ukr_x_preferred":[
        "\u0411\u0435\u043b\u0447\u0435"
    ],
    "wof:name":"Belcze",
    "wof:placetype":"locality"
},
  "geometry": {"coordinates":[15.84573,51.98141],"type":"Point"}
}