{
  "type": "Feature",
  "properties": {
    "gn:admin1_code":"84.0",
    "gn:admin2_code":"2604.0",
    "gn:admin3_code":"260408.0",
    "gn:asciiname":"Jozefina",
    "gn:country_code":"PL",
    "gn:dem":269,
    "gn:feature_class":"P",
    "gn:feature_code":"PPL",
    "gn:name":"J\u00f3zefina",
    "gn:population":0,
    "gn:timezone":"Europe/Warsaw",
    "iso:country":"PL",
    "name:ceb_x_preferred":[
        "J\u00f3zefina"
    ],
    "name:pol_x_preferred":[
        "J\u00f3zefina"
    ],
    "name:ukr_x_preferred":[
        "\u042e\u0437\u0435\u0444\u0456\u043d\u0430"
    ],
    "name:und_x_variant":[
        "J\u00f3zefina"
    ],
    "wof:name":"Jozefina",
    "wof:placetype":"locality"
},
  "geometry": {"coordinates":[20.26878,50.96362],"type":"Point"}
}