{
  "type": "Feature",
  "properties": {
    "gn:admin1_code":"81.0",
    "gn:admin2_code":"2002.0",
    "gn:admin3_code":"200202.0",
    "gn:asciiname":"Czarna Wies",
    "gn:country_code":"PL",
    "gn:dem":145,
    "gn:feature_class":"P",
    "gn:feature_code":"PPL",
    "gn:name":"Czarna Wie\u015b",
    "gn:population":0,
    "gn:timezone":"Europe/Warsaw",
    "iso:country":"PL",
    "name:und_x_variant":[
        "Czarna Wie\u015b Ko\u015bcielna",
        "Czarna Wie\u015b"
    ],
    "wof:name":"Czarna Wies",
    "wof:placetype":"locality"
},
  "geometry": {"coordinates":[23.22645,53.29745],"type":"Point"}
}