{
  "type": "Feature",
  "properties": {
    "gn:admin1_code":"81.0",
    "gn:admin2_code":"2002.0",
    "gn:admin3_code":"200202.0",
    "gn:asciiname":"Czarna Wies",
    "gn:country_code":"PL",
    "gn:dem":145,
    "gn:feature_class":"P",
    "gn:feature_code":"PPL",
    "gn:name":"Czarna Wie\u015b",
    "gn:population":0,
    "gn:timezone":"Europe/Warsaw",
    "iso:country":"PL",
    "name:azb_x_preferred":[
        "\u0686\u0627\u0631\u0646\u0627 \u0648\u06cc\u0634 \u06a9\u0648\u0634\u0686\u06cc\u0644\u0646\u0627"
    ],
    "name:fas_x_preferred":[
        "\u0686\u0627\u0631\u0646\u0627 \u0648\u06cc\u0634 \u06a9\u0648\u0634\u0686\u06cc\u0644\u0646\u0627"
    ],
    "name:fra_x_preferred":[
        "Czarna Wie\u015b Ko\u015bcielna"
    ],
    "name:lit_x_preferred":[
        "\u010carna Vie\u0161 Ko\u0161celna"
    ],
    "name:nld_x_preferred":[
        "Czarna Wie\u015b Ko\u015bcielna"
    ],
    "name:pol_x_preferred":[
        "Czarna Wie\u015b Ko\u015bcielna"
    ],
    "name:rus_x_preferred":[
        "\u0427\u0430\u0440\u043d\u0430-\u0412\u0435\u0441\u044c-\u041a\u043e\u0441\u044c\u0446\u0435\u043b\u044c\u043d\u0430"
    ],
    "name:ukr_x_preferred":[
        "\u0427\u0430\u0440\u043d\u0430-\u0412\u0435\u0441\u044c-\u041a\u043e\u0441\u044c\u0446\u0435\u043b\u044c\u043d\u0430"
    ],
    "name:und_x_variant":[
        "Czarna Wie\u015b"
    ],
    "wof:name":"Czarna Wies",
    "wof:placetype":"locality"
},
  "geometry": {"coordinates":[23.22645,53.29745],"type":"Point"}
}