{
  "type": "Feature",
  "properties": {
    "gn:admin1_code":"85.0",
    "gn:admin2_code":"2815.0",
    "gn:admin3_code":"281508.0",
    "gn:asciiname":"Chojnik",
    "gn:country_code":"PL",
    "gn:dem":153,
    "gn:feature_class":"P",
    "gn:feature_code":"PPL",
    "gn:name":"Chojnik",
    "gn:population":0,
    "gn:timezone":"Europe/Warsaw",
    "iso:country":"PL",
    "name:fra_x_preferred":[
        "Chojnik"
    ],
    "name:pol_x_preferred":[
        "Chojnik"
    ],
    "name:ukr_x_preferred":[
        "\u0425\u043e\u0439\u043d\u0438\u043a"
    ],
    "name:und_x_variant":[
        "Hagenau",
        "Chojnik"
    ],
    "wof:name":"Chojnik",
    "wof:placetype":"locality"
},
  "geometry": {"coordinates":[19.79823,53.96379],"type":"Point"}
}