{
  "type": "Feature",
  "properties": {
    "gn:admin1_code":"86.0",
    "gn:admin2_code":"3018.0",
    "gn:admin3_code":"301801.0",
    "gn:asciiname":"Galki",
    "gn:country_code":"PL",
    "gn:dem":156,
    "gn:feature_class":"P",
    "gn:feature_code":"PPL",
    "gn:name":"Ga\u0142ki",
    "gn:population":0,
    "gn:timezone":"Europe/Warsaw",
    "iso:country":"PL",
    "wof:name":"Galki",
    "wof:placetype":"locality"
},
  "geometry": {"coordinates":[18.35566,51.48257],"type":"Point"}
}