{
  "type": "Feature",
  "properties": {
    "gn:admin1_code":"72.0",
    "gn:admin2_code":"202.0",
    "gn:admin3_code":"20203.0",
    "gn:asciiname":"Dorotka",
    "gn:country_code":"PL",
    "gn:dem":285,
    "gn:feature_class":"P",
    "gn:feature_code":"PPL",
    "gn:name":"Dorotka",
    "gn:population":0,
    "gn:timezone":"Europe/Warsaw",
    "iso:country":"PL",
    "name:deu_x_historical":[
        "Dorotheenthal"
    ],
    "name:deu_x_preferred":[
        "Dorotheenthal"
    ],
    "wof:name":"Dorotka",
    "wof:placetype":"locality"
},
  "geometry": {"coordinates":[16.56364,50.72797],"type":"Point"}
}