{
  "type": "Feature",
  "properties": {
    "gn:admin1_code":"84.0",
    "gn:admin2_code":"2606.0",
    "gn:admin3_code":"260605.0",
    "gn:asciiname":"Wojciechowka",
    "gn:country_code":"PL",
    "gn:dem":180,
    "gn:feature_class":"P",
    "gn:feature_code":"PPL",
    "gn:name":"Wojciech\u00f3wka",
    "gn:population":0,
    "gn:timezone":"Europe/Warsaw",
    "iso:country":"PL",
    "name:pol_x_preferred":[
        "Wojciech\u00f3wka"
    ],
    "name:ukr_x_preferred":[
        "\u0412\u043e\u0439\u0446\u0435\u0445\u0443\u0432\u043a\u0430"
    ],
    "name:und_x_variant":[
        "Wojciech\u00f3wka"
    ],
    "wof:name":"Wojciechowka",
    "wof:placetype":"locality"
},
  "geometry": {"coordinates":[21.61904,50.90248],"type":"Point"}
}