{
  "type": "Feature",
  "properties": {
    "gn:admin1_code":"74.0",
    "gn:admin2_code":"1017.0",
    "gn:admin3_code":"101709.0",
    "gn:asciiname":"Olewin",
    "gn:country_code":"PL",
    "gn:dem":180,
    "gn:feature_class":"P",
    "gn:feature_code":"PPL",
    "gn:name":"Olewin",
    "gn:population":0,
    "gn:timezone":"Europe/Warsaw",
    "iso:country":"PL",
    "name:pol_x_preferred":[
        "Olewin"
    ],
    "name:ukr_x_preferred":[
        "\u041e\u043b\u0435\u0432\u0456\u043d"
    ],
    "wof:name":"Olewin",
    "wof:placetype":"locality"
},
  "geometry": {"coordinates":[18.64488,51.22612],"type":"Point"}
}