{
  "type": "Feature",
  "properties": {
    "gn:admin1_code":"87.0",
    "gn:admin2_code":"3214.0",
    "gn:admin3_code":"321408.0",
    "gn:asciiname":"Wiechowo",
    "gn:country_code":"PL",
    "gn:dem":67,
    "gn:feature_class":"P",
    "gn:feature_code":"PPL",
    "gn:name":"Wiechowo",
    "gn:population":0,
    "gn:timezone":"Europe/Warsaw",
    "iso:country":"PL",
    "name:pol_x_preferred":[
        "Wiechowo"
    ],
    "name:ukr_x_preferred":[
        "\u0412\u0435\u0445\u043e\u0432\u043e"
    ],
    "name:vie_x_preferred":[
        "Wiechowo"
    ],
    "wof:name":"Wiechowo",
    "wof:placetype":"locality"
},
  "geometry": {"coordinates":[15.31362,53.36991],"type":"Point"}
}