{
  "type": "Feature",
  "properties": {
    "gn:country":"PL",
    "gn:fcode":"PPL",
    "gn:population":190,
    "iso:country":"PL",
    "name:bos_x_preferred":[
        "Solina"
    ],
    "name:ceb_x_preferred":[
        "Solina"
    ],
    "name:fra_x_preferred":[
        "Solina"
    ],
    "name:ita_x_preferred":[
        "Solina"
    ],
    "name:nld_x_preferred":[
        "Solina"
    ],
    "name:pol_x_preferred":[
        "Solina"
    ],
    "name:srp_x_preferred":[
        "\u0421\u043e\u043b\u0438\u043d\u0430"
    ],
    "name:swe_x_preferred":[
        "Solina"
    ],
    "qs_pg:aaroncc":"PL",
    "qs_pg:gn_country":"PL",
    "qs_pg:gn_fcode":"PPL",
    "qs_pg:gn_pop":190,
    "qs_pg:name":"Solina",
    "qs_pg:name_adm0":"Polska",
    "qs_pg:name_adm1":"Podkarpackie",
    "qs_pg:photos":258,
    "qs_pg:photos_1k":52,
    "qs_pg:photos_9k":1,
    "qs_pg:photos_9r":4,
    "qs_pg:photos_all":258,
    "qs_pg:photos_sr":5,
    "qs_pg:pop_sr":1,
    "qs_pg:qs_pg_placetype":"locality",
    "qs_pg:qs_pg_placetype_gp":"Town",
    "qs_pg:woe_adm0":23424923,
    "woe:adm0_id":23424923,
    "woe:name_adm0":"Polska",
    "woe:name_adm1":"Podkarpackie",
    "woe:placetype":"Town",
    "wof:coterminous":[
        1125326581
    ],
    "wof:name":"Solina",
    "wof:placetype":"locality",
    "wof:population":190
},
  "geometry": {"coordinates":[22.45966,49.39489],"type":"Point"}
}