{
  "type": "Feature",
  "properties": {
    "gn:admin1_code":"85.0",
    "gn:admin2_code":"2819.0",
    "gn:admin3_code":"281902.0",
    "gn:asciiname":"Okowizna",
    "gn:country_code":"PL",
    "gn:dem":124,
    "gn:feature_class":"P",
    "gn:feature_code":"PPL",
    "gn:name":"Okowizna",
    "gn:population":0,
    "gn:timezone":"Europe/Warsaw",
    "iso:country":"PL",
    "name:deu_x_preferred":[
        "Okowizna"
    ],
    "name:nld_x_preferred":[
        "Okowizna"
    ],
    "name:pol_x_preferred":[
        "Okowizna"
    ],
    "wof:name":"Okowizna",
    "wof:placetype":"locality"
},
  "geometry": {"coordinates":[21.79305,54.16068000000001],"type":"Point"}
}