{
  "type": "Feature",
  "properties": {
    "gn:admin1_code":"81.0",
    "gn:admin2_code":"2007.0",
    "gn:admin3_code":"200703.0",
    "gn:asciiname":"Korytki Lesne",
    "gn:country_code":"PL",
    "gn:dem":118,
    "gn:feature_class":"P",
    "gn:feature_code":"PPL",
    "gn:name":"Korytki Le\u015bne",
    "gn:population":0,
    "gn:timezone":"Europe/Warsaw",
    "iso:country":"PL",
    "name:und_x_variant":[
        "Korytki",
        "Korytki Le\u015bne"
    ],
    "wof:name":"Korytki Lesne",
    "wof:placetype":"locality"
},
  "geometry": {"coordinates":[21.8457,53.16922],"type":"Point"}
}