{
  "type": "Feature",
  "properties": {
    "gn:admin1_code":"81.0",
    "gn:admin2_code":"2007.0",
    "gn:admin3_code":"200703.0",
    "gn:asciiname":"Korytki Lesne",
    "gn:country_code":"PL",
    "gn:dem":118,
    "gn:feature_class":"P",
    "gn:feature_code":"PPL",
    "gn:name":"Korytki Le\u015bne",
    "gn:population":0,
    "gn:timezone":"Europe/Warsaw",
    "iso:country":"PL",
    "name:azb_x_preferred":[
        "\u06a9\u0648\u0631\u062a\u06a9\u06cc \u0644\u0634\u0646\u0647"
    ],
    "name:fas_x_preferred":[
        "\u06a9\u0648\u0631\u062a\u06a9\u06cc \u0644\u0634\u0646\u0647"
    ],
    "name:lit_x_preferred":[
        "Koritki Le\u0161n\u0117"
    ],
    "name:pol_x_preferred":[
        "Korytki Le\u015bne"
    ],
    "name:ukr_x_preferred":[
        "\u041a\u043e\u0440\u0438\u0442\u043a\u0456-\u041b\u0435\u0441\u044c\u043d\u0435"
    ],
    "name:und_x_variant":[
        "Korytki"
    ],
    "wof:name":"Korytki Lesne",
    "wof:placetype":"locality"
},
  "geometry": {"coordinates":[21.8457,53.16922],"type":"Point"}
}