{
  "type": "Feature",
  "properties": {
    "gn:admin1_code":"80.0",
    "gn:admin2_code":"1818.0",
    "gn:admin3_code":"181802.0",
    "gn:asciiname":"Ruda",
    "gn:country_code":"PL",
    "gn:dem":164,
    "gn:feature_class":"P",
    "gn:feature_code":"PPL",
    "gn:name":"Ruda",
    "gn:population":0,
    "gn:timezone":"Europe/Warsaw",
    "iso:country":"PL",
    "wof:name":"Ruda",
    "wof:placetype":"locality"
},
  "geometry": {"coordinates":[21.99226,50.50076],"type":"Point"}
}