{
  "type": "Feature",
  "properties": {
    "gn:admin1_code":"72.0",
    "gn:admin2_code":"201.0",
    "gn:admin3_code":"20105.0",
    "gn:asciiname":"Parowa",
    "gn:country_code":"PL",
    "gn:dem":166,
    "gn:feature_class":"P",
    "gn:feature_code":"PPL",
    "gn:name":"Parowa",
    "gn:population":0,
    "gn:timezone":"Europe/Warsaw",
    "iso:country":"PL",
    "name:ceb_x_preferred":[
        "Parowa"
    ],
    "name:pol_x_preferred":[
        "Parowa"
    ],
    "name:spa_x_preferred":[
        "Parowa"
    ],
    "name:ukr_x_preferred":[
        "\u041f\u0430\u0440\u043e\u0432\u0430"
    ],
    "wof:name":"Parowa",
    "wof:placetype":"locality"
},
  "geometry": {"coordinates":[15.28211,51.36276],"type":"Point"}
}