{
  "type": "Feature",
  "properties": {
    "gn:admin1_code":"82.0",
    "gn:admin2_code":"2210.0",
    "gn:admin3_code":"221002.0",
    "gn:asciiname":"Stobna",
    "gn:country_code":"PL",
    "gn:dem":-2,
    "gn:feature_class":"P",
    "gn:feature_code":"PPL",
    "gn:name":"Stobna",
    "gn:population":0,
    "gn:timezone":"Europe/Warsaw",
    "iso:country":"PL",
    "name:ceb_x_preferred":[
        "Stobna"
    ],
    "name:pol_x_preferred":[
        "Stobna"
    ],
    "name:swe_x_preferred":[
        "Stobna"
    ],
    "name:ukr_x_preferred":[
        "\u0421\u0442\u043e\u0431\u043d\u0430"
    ],
    "name:und_x_variant":[
        "Stuba"
    ],
    "wof:name":"Stobna",
    "wof:placetype":"locality"
},
  "geometry": {"coordinates":[19.28015,54.20271999999999],"type":"Point"}
}