{
  "type": "Feature",
  "properties": {
    "gn:admin1_code":"78.0",
    "gn:admin2_code":"1428.0",
    "gn:admin3_code":"142801.0",
    "gn:asciiname":"Nowa Wies",
    "gn:country_code":"PL",
    "gn:dem":84,
    "gn:feature_class":"P",
    "gn:feature_code":"PPL",
    "gn:name":"Nowa Wie\u015b",
    "gn:population":0,
    "gn:timezone":"Europe/Warsaw",
    "iso:country":"PL",
    "wof:name":"Nowa Wies",
    "wof:placetype":"locality"
},
  "geometry": {"coordinates":[20.27611,52.24878],"type":"Point"}
}