{
  "type": "Feature",
  "properties": {
    "gn:admin1_code":"74.0",
    "gn:admin2_code":"1019.0",
    "gn:admin3_code":"101904.0",
    "gn:asciiname":"Simowa",
    "gn:country_code":"PL",
    "gn:dem":172,
    "gn:feature_class":"P",
    "gn:feature_code":"PPL",
    "gn:name":"Simowa",
    "gn:population":0,
    "gn:timezone":"Europe/Warsaw",
    "iso:country":"PL",
    "wof:name":"Simowa",
    "wof:placetype":"locality"
},
  "geometry": {"coordinates":[19.03942,51.59064],"type":"Point"}
}