{
  "type": "Feature",
  "properties": {
    "gn:admin1_code":"86.0",
    "gn:admin2_code":"3018.0",
    "gn:admin3_code":"301802.0",
    "gn:asciiname":"Emilianow",
    "gn:country_code":"PL",
    "gn:dem":162,
    "gn:feature_class":"P",
    "gn:feature_code":"PPL",
    "gn:name":"Emilian\u00f3w",
    "gn:population":0,
    "gn:timezone":"Europe/Warsaw",
    "iso:country":"PL",
    "name:und_x_variant":[
        "Emiljan\u00f3w",
        "Emilian\u00f3w"
    ],
    "wof:name":"Emilianow",
    "wof:placetype":"locality"
},
  "geometry": {"coordinates":[18.06907,51.40428],"type":"Point"}
}