{
  "type": "Feature",
  "properties": {
    "gn:country":"PL",
    "gn:fcode":"PPL",
    "gn:population":2795,
    "iso:country":"PL",
    "name:pol_x_preferred":[
        "Smolne"
    ],
    "name:ukr_x_preferred":[
        "\u0421\u043c\u043e\u043b\u044c\u043d\u0435"
    ],
    "name:und_x_variant":[
        "Schmolz"
    ],
    "qs_pg:aaroncc":"PL",
    "qs_pg:gn_country":"PL",
    "qs_pg:gn_fcode":"PPL",
    "qs_pg:gn_pop":2795,
    "qs_pg:name":"Smolne",
    "qs_pg:name_adm0":"Polska",
    "qs_pg:name_adm1":"Dolnosl\u0105skie",
    "qs_pg:photos_9r":0,
    "qs_pg:photos_sr":0,
    "qs_pg:pop_sr":4,
    "qs_pg:qs_pg_placetype":"locality",
    "qs_pg:qs_pg_placetype_gp":"Town",
    "qs_pg:woe_adm0":23424923,
    "woe:adm0_id":23424923,
    "woe:name_adm0":"Polska",
    "woe:name_adm1":"Dolnosl\u0105skie",
    "woe:placetype":"Town",
    "wof:name":"Smolne",
    "wof:placetype":"locality",
    "wof:population":2795
},
  "geometry": {"coordinates":[16.88221,51.07322],"type":"Point"}
}