{
  "type": "Feature",
  "properties": {
    "gn:admin1_code":"74.0",
    "gn:admin2_code":"1015.0",
    "gn:admin3_code":"101505.0",
    "gn:asciiname":"Retniowiec",
    "gn:country_code":"PL",
    "gn:dem":160,
    "gn:feature_class":"P",
    "gn:feature_code":"PPL",
    "gn:name":"Retniowiec",
    "gn:population":0,
    "gn:timezone":"Europe/Warsaw",
    "iso:country":"PL",
    "name:pol_x_preferred":[
        "Retniowiec"
    ],
    "name:ukr_x_preferred":[
        "\u0420\u0435\u0442\u043d\u044c\u043e\u0432\u0435\u0446\u044c"
    ],
    "wof:name":"Retniowiec",
    "wof:placetype":"locality"
},
  "geometry": {"coordinates":[19.955,51.93785],"type":"Point"}
}