{
  "type": "Feature",
  "properties": {
    "gn:admin1_code":"78.0",
    "gn:admin2_code":"1427.0",
    "gn:admin3_code":"142703.0",
    "gn:asciiname":"Zurawin",
    "gn:country_code":"PL",
    "gn:dem":103,
    "gn:feature_class":"P",
    "gn:feature_code":"PPL",
    "gn:name":"\u017burawin",
    "gn:population":0,
    "gn:timezone":"Europe/Warsaw",
    "iso:country":"PL",
    "name:fra_x_preferred":[
        "\u017burawin"
    ],
    "name:pol_x_preferred":[
        "\u017burawin"
    ],
    "name:ukr_x_preferred":[
        "\u0416\u0443\u0440\u0430\u0432\u0456\u043d"
    ],
    "wof:name":"Zurawin",
    "wof:placetype":"locality"
},
  "geometry": {"coordinates":[19.53963,52.78998000000001],"type":"Point"}
}