{
  "type": "Feature",
  "properties": {
    "gn:admin1_code":"77.0",
    "gn:admin2_code":"1213.0",
    "gn:admin3_code":"121302.0",
    "gn:asciiname":"Leskie Zasole",
    "gn:country_code":"PL",
    "gn:dem":265,
    "gn:feature_class":"P",
    "gn:feature_code":"PPL",
    "gn:name":"\u0141\u0119skie Zasole",
    "gn:population":0,
    "gn:timezone":"Europe/Warsaw",
    "iso:country":"PL",
    "wof:name":"Leskie Zasole",
    "wof:placetype":"locality"
},
  "geometry": {"coordinates":[19.18333,49.96667],"type":"Point"}
}