{
  "type": "Feature",
  "properties": {
    "gn:population":40050,
    "iso:country":"PL",
    "name:ast_x_preferred":[
        "\u015awidnik Du\u017cy"
    ],
    "name:eng_x_preferred":[
        "\u015awidnik Du\u017cy"
    ],
    "name:fra_x_preferred":[
        "\u015awidnik Du\u017cy"
    ],
    "name:pol_x_preferred":[
        "\u015awidnik"
    ],
    "name:pol_x_variant":[
        "\u015awidnik Du\u017cy"
    ],
    "name:ukr_x_preferred":[
        "\u0421\u044c\u0432\u0456\u0434\u043d\u0438\u043a-\u0414\u0443\u0436\u0438"
    ],
    "qs:a0":"Rzeczpospolita Polska",
    "qs:a1":"*Lubelskie",
    "qs:a1r":"0",
    "qs:a2":"Swidnicki",
    "qs:adm0":"Rzeczpospolita Polska",
    "qs:la":"W\u00f3lka",
    "qs:la_lc":"*PL0609142",
    "qs:level":"locality",
    "qs:loc":"\u015awidnik",
    "qs:loc_alt":"Swidnik",
    "qs:pop":0,
    "qs:type":"rural point-in-poly",
    "wd:wordcount":69,
    "wof:name":"\u015awidnik",
    "wof:placetype":"locality",
    "wof:population":40050
},
  "geometry": {"coordinates":[22.6822645705597,51.219196057193],"type":"Point"}
}