{
  "type": "Feature",
  "properties": {
    "gn:admin1_code":"75.0",
    "gn:admin2_code":"602.0",
    "gn:admin3_code":"60205.0",
    "gn:asciiname":"Chlopkow",
    "gn:country_code":"PL",
    "gn:dem":219,
    "gn:feature_class":"P",
    "gn:feature_code":"PPL",
    "gn:name":"Ch\u0142opk\u00f3w",
    "gn:population":0,
    "gn:timezone":"Europe/Warsaw",
    "iso:country":"PL",
    "name:ceb_x_preferred":[
        "Ch\u0142opk\u00f3w"
    ],
    "name:fra_x_preferred":[
        "Ch\u0142opk\u00f3w"
    ],
    "name:pol_x_preferred":[
        "Ch\u0142opk\u00f3w"
    ],
    "name:rus_x_preferred":[
        "\u0425\u043b\u043e\u043f\u043a\u0443\u0432"
    ],
    "name:ukr_x_preferred":[
        "\u0425\u043b\u043e\u043f\u043a\u0443\u0432"
    ],
    "name:und_x_variant":[
        "Ch\u0142opk\u00f3w"
    ],
    "wof:name":"Chlopkow",
    "wof:placetype":"locality"
},
  "geometry": {"coordinates":[22.81699,50.7146],"type":"Point"}
}