{
  "type": "Feature",
  "properties": {
    "gn:admin1_code":"75.0",
    "gn:admin2_code":"618.0",
    "gn:admin3_code":"61808.0",
    "gn:asciiname":"Banachy",
    "gn:country_code":"PL",
    "gn:dem":273,
    "gn:feature_class":"P",
    "gn:feature_code":"PPL",
    "gn:name":"Banachy",
    "gn:population":0,
    "gn:timezone":"Europe/Warsaw",
    "iso:country":"PL",
    "name:ceb_x_preferred":[
        "Banachy"
    ],
    "name:pol_x_preferred":[
        "Banachy"
    ],
    "name:ukr_x_preferred":[
        "\u0411\u0430\u043d\u0430\u0445\u0438"
    ],
    "wof:name":"Banachy",
    "wof:placetype":"locality"
},
  "geometry": {"coordinates":[23.25078,50.36858],"type":"Point"}
}