{
  "type": "Feature",
  "properties": {
    "gn:admin1_code":"79.0",
    "gn:admin2_code":"1606.0",
    "gn:admin3_code":"160602.0",
    "gn:asciiname":"Smarchowice Wielkie",
    "gn:country_code":"PL",
    "gn:dem":163,
    "gn:feature_class":"P",
    "gn:feature_code":"PPL",
    "gn:name":"Smarchowice Wielkie",
    "gn:population":0,
    "gn:timezone":"Europe/Warsaw",
    "iso:country":"PL",
    "name:pol_x_preferred":[
        "Smarchowice Wielkie"
    ],
    "name:ukr_x_preferred":[
        "\u0421\u043c\u0430\u0440\u0445\u043e\u0432\u0456\u0446\u0435-\u0412\u0435\u043b\u0438\u043a\u0456"
    ],
    "wof:name":"Smarchowice Wielkie",
    "wof:placetype":"locality"
},
  "geometry": {"coordinates":[17.68904,51.04715],"type":"Point"}
}