{
  "type": "Feature",
  "properties": {
    "gn:admin1_code":"78.0",
    "gn:admin2_code":"1429.0",
    "gn:admin3_code":"142902.0",
    "gn:asciiname":"Ksiezopole Komory",
    "gn:country_code":"PL",
    "gn:dem":160,
    "gn:feature_class":"P",
    "gn:feature_code":"PPL",
    "gn:name":"Ksi\u0119\u017copole Komory",
    "gn:population":0,
    "gn:timezone":"Europe/Warsaw",
    "iso:country":"PL",
    "wof:name":"Ksiezopole Komory",
    "wof:placetype":"locality"
},
  "geometry": {"coordinates":[22.12596,52.32321],"type":"Point"}
}