{
  "type": "Feature",
  "properties": {
    "gn:admin1_code":"78.0",
    "gn:admin2_code":"1465.0",
    "gn:admin3_code":"146501.0",
    "gn:admin4_code":"146503_8",
    "gn:asciiname":"Konstantynow",
    "gn:cc2":"PL",
    "gn:country_code":"PL",
    "gn:dem":81,
    "gn:feature_class":"P",
    "gn:feature_code":"PPL",
    "gn:name":"Konstantyn\u00f3w",
    "gn:population":0,
    "gn:timezone":"Europe/Warsaw",
    "iso:country":"PL",
    "name:und_x_variant":[
        "Kolonia Konstantyn\u00f3w",
        "Konstantyn\u00f3w"
    ],
    "wof:name":"Konstantynow",
    "wof:placetype":"neighbourhood"
},
  "geometry": {"coordinates":[21.01667,52.31667],"type":"Point"}
}