{
  "type": "Feature",
  "properties": {
    "gn:admin1_code":"86.0",
    "gn:admin2_code":"3061.0",
    "gn:admin3_code":"306101.0",
    "gn:asciiname":"Chmielnik",
    "gn:country_code":"PL",
    "gn:dem":128,
    "gn:feature_class":"P",
    "gn:feature_code":"PPL",
    "gn:name":"Chmielnik",
    "gn:population":0,
    "gn:timezone":"Europe/Warsaw",
    "iso:country":"PL",
    "name:deu_x_preferred":[
        "Chmielnik"
    ],
    "name:epo_x_preferred":[
        "Chmielnik"
    ],
    "name:fra_x_preferred":[
        "Chmielnik"
    ],
    "name:hak_x_preferred":[
        "Chmielnik"
    ],
    "name:heb_x_preferred":[
        "\u05d7\u05de\u05d9\u05d9\u05dc\u05e0\u05d9\u05e7"
    ],
    "name:lav_x_preferred":[
        "Hmel\u0146ika"
    ],
    "name:msa_x_preferred":[
        "Chmielnik"
    ],
    "name:nld_x_preferred":[
        "Chmielnik"
    ],
    "name:pol_x_preferred":[
        "Chmielnik"
    ],
    "name:por_x_preferred":[
        "Chmielnik"
    ],
    "name:ron_x_preferred":[
        "Chmielnik"
    ],
    "name:rus_x_preferred":[
        "\u0425\u043c\u0435\u043b\u044c\u043d\u0438\u043a"
    ],
    "name:slk_x_preferred":[
        "Chmielnik"
    ],
    "name:srp_x_preferred":[
        "\u0425\u043c\u0458\u0435\u043b\u045a\u0438\u043a"
    ],
    "name:ukr_x_preferred":[
        "\u0425\u043c\u0435\u043b\u044c\u043d\u0438\u043a"
    ],
    "name:vie_x_preferred":[
        "Chmielnik"
    ],
    "name:yid_x_preferred":[
        "\u05db\u05de\u05e2\u05dc\u05e0\u05d9\u05e7"
    ],
    "name:zho_x_preferred":[
        "\u8d6b\u6885\u723e\u5c3c\u514b"
    ],
    "wof:name":"Chmielnik",
    "wof:placetype":"locality"
},
  "geometry": {"coordinates":[18.08751,51.7766],"type":"Point"}
}