{
  "type": "Feature",
  "properties": {
    "gn:admin1_code":"82.0",
    "gn:admin2_code":"2211.0",
    "gn:admin3_code":"221106.0",
    "gn:asciiname":"Jeldzino",
    "gn:country_code":"PL",
    "gn:dem":46,
    "gn:feature_class":"P",
    "gn:feature_code":"PPL",
    "gn:name":"Jeldzino",
    "gn:population":0,
    "gn:timezone":"Europe/Warsaw",
    "iso:country":"PL",
    "name:azb_x_preferred":[
        "\u06cc\u0644\u062c\u0646\u0648"
    ],
    "name:ceb_x_preferred":[
        "Jeldzino"
    ],
    "name:fas_x_preferred":[
        "\u06cc\u0644\u062c\u0646\u0648"
    ],
    "name:fra_x_preferred":[
        "Jeldzino"
    ],
    "name:nld_x_preferred":[
        "Jeldzino"
    ],
    "name:pol_x_preferred":[
        "Jeldzino"
    ],
    "name:ukr_x_preferred":[
        "\u0404\u043b\u044c\u0434\u0437\u0456\u043d\u043e"
    ],
    "wof:name":"Jeldzino",
    "wof:placetype":"locality"
},
  "geometry": {"coordinates":[18.14203,54.77158000000001],"type":"Point"}
}