{
  "type": "Feature",
  "properties": {
    "gn:admin1_code":"86.0",
    "gn:admin2_code":"3011.0",
    "gn:admin3_code":"301105.0",
    "gn:asciiname":"Zegrowo",
    "gn:country_code":"PL",
    "gn:dem":79,
    "gn:feature_class":"P",
    "gn:feature_code":"PPL",
    "gn:name":"\u017begrowo",
    "gn:population":0,
    "gn:timezone":"Europe/Warsaw",
    "iso:country":"PL",
    "name:fra_x_preferred":[
        "\u017begrowo"
    ],
    "name:pol_x_preferred":[
        "\u017begrowo"
    ],
    "name:ukr_x_preferred":[
        "\u0416\u0435\u0491\u0440\u043e\u0432\u043e"
    ],
    "wof:name":"Zegrowo",
    "wof:placetype":"locality"
},
  "geometry": {"coordinates":[16.47515,52.03057],"type":"Point"}
}