{
  "type": "Feature",
  "properties": {
    "gn:country":"PL",
    "gn:fcode":"PPL",
    "gn:population":861,
    "iso:country":"PL",
    "name:ast_x_preferred":[
        "Ogrodzona"
    ],
    "name:azb_x_preferred":[
        "\u0627\u0648\u0642\u0631\u0648\u0632\u0648\u0646\u0627"
    ],
    "name:ces_x_preferred":[
        "Ohrazen\u00e1"
    ],
    "name:deu_x_preferred":[
        "Ogrodzona"
    ],
    "name:eng_x_preferred":[
        "Ogrodzona"
    ],
    "name:fas_x_preferred":[
        "\u0627\u0648\u06af\u0631\u0648\u0632\u0648\u0646\u0627"
    ],
    "name:fra_x_preferred":[
        "Ogrodzona"
    ],
    "name:nld_x_preferred":[
        "Ogrodzona"
    ],
    "name:pol_x_preferred":[
        "Ogrodzona"
    ],
    "name:ukr_x_preferred":[
        "\u041e\u0491\u0440\u043e\u0434\u0437\u043e\u043d\u0430"
    ],
    "qs_pg:aaroncc":"PL",
    "qs_pg:gn_country":"PL",
    "qs_pg:gn_fcode":"PPL",
    "qs_pg:gn_pop":861,
    "qs_pg:name":"Ogrodzona",
    "qs_pg:name_adm0":"Polska",
    "qs_pg:name_adm1":"Sl\u0105skie",
    "qs_pg:photos_9k":1,
    "qs_pg:photos_9r":1,
    "qs_pg:photos_all":4,
    "qs_pg:photos_sr":0,
    "qs_pg:pop_sr":2,
    "qs_pg:qs_pg_placetype":"locality",
    "qs_pg:qs_pg_placetype_gp":"Town",
    "qs_pg:woe_adm0":23424923,
    "woe:adm0_id":23424923,
    "woe:name_adm0":"Polska",
    "woe:name_adm1":"Sl\u0105skie",
    "woe:placetype":"Town",
    "wof:name":"Ogrodzona",
    "wof:placetype":"locality",
    "wof:population":861
},
  "geometry": {"coordinates":[18.72886,49.76791],"type":"Point"}
}