{
  "type": "Feature",
  "properties": {
    "gn:admin1_code":"74.0",
    "gn:admin2_code":"1010.0",
    "gn:admin3_code":"101007.0",
    "gn:asciiname":"MajLowice",
    "gn:country_code":"PL",
    "gn:dem":191,
    "gn:feature_class":"P",
    "gn:feature_code":"PPL",
    "gn:name":"MajLowice",
    "gn:population":0,
    "gn:timezone":"Europe/Warsaw",
    "iso:country":"PL",
    "wof:name":"MajLowice",
    "wof:placetype":"locality"
},
  "geometry": {"coordinates":[19.88492,51.1694],"type":"Point"}
}