{
  "type": "Feature",
  "properties": {
    "gn:admin1_code":"85.0",
    "gn:admin2_code":"2810.0",
    "gn:admin3_code":"281003.0",
    "gn:asciiname":"Gronowo",
    "gn:country_code":"PL",
    "gn:dem":152,
    "gn:feature_class":"P",
    "gn:feature_code":"PPL",
    "gn:name":"Gronowo",
    "gn:population":0,
    "gn:timezone":"Europe/Warsaw",
    "iso:country":"PL",
    "name:deu_x_preferred":[
        "Gronowo"
    ],
    "name:fra_x_preferred":[
        "Gronowo"
    ],
    "name:pol_x_preferred":[
        "Gronowo"
    ],
    "name:ukr_x_preferred":[
        "\u0490\u0440\u043e\u043d\u043e\u0432\u043e"
    ],
    "name:und_x_variant":[
        "Grunau"
    ],
    "wof:name":"Gronowo",
    "wof:placetype":"locality"
},
  "geometry": {"coordinates":[21.36213,53.9809],"type":"Point"}
}