{
  "type": "Feature",
  "properties": {
    "gn:admin1_code":"73.0",
    "gn:admin2_code":"418.0",
    "gn:admin3_code":"41806.0",
    "gn:asciiname":"Biele",
    "gn:country_code":"PL",
    "gn:dem":128,
    "gn:feature_class":"P",
    "gn:feature_code":"PPL",
    "gn:name":"Biele",
    "gn:population":0,
    "gn:timezone":"Europe/Warsaw",
    "iso:country":"PL",
    "name:deu_x_preferred":[
        "Biele"
    ],
    "name:fra_x_preferred":[
        "Biele"
    ],
    "name:pol_x_preferred":[
        "Biele"
    ],
    "name:ukr_x_preferred":[
        "\u0411\u0435\u043b\u0435"
    ],
    "wof:name":"Biele",
    "wof:placetype":"locality"
},
  "geometry": {"coordinates":[19.03758,52.43851],"type":"Point"}
}