{
  "type": "Feature",
  "properties": {
    "gn:gn_country":"PL",
    "gn:gn_fcode":"PPL",
    "gn:gn_pop":342,
    "gn:population":342,
    "iso:country":"PL",
    "name:eng_x_preferred":[
        "Uchylsko"
    ],
    "name:fre_x_preferred":[
        "Uchylsko"
    ],
    "name:per_x_preferred":[
        "\u06cc\u0648\u0686\u06cc\u0644\u0633\u06a9\u0648"
    ],
    "name:pol_x_preferred":[
        "Uchylsko"
    ],
    "name:urd_x_preferred":[
        "\u0627\u0686\u06cc\u0644\u0633\u06a9\u0648"
    ],
    "qs_pg:aaroncc":"PL",
    "qs_pg:gn_country":"PL",
    "qs_pg:gn_fcode":"PPL",
    "qs_pg:gn_pop":342,
    "qs_pg:name":"Uchylsko",
    "qs_pg:name_adm0":"Polska",
    "qs_pg:name_adm1":"Sl\u0105skie",
    "qs_pg:photos_9r":0,
    "qs_pg:photos_sr":0,
    "qs_pg:pop_sr":2,
    "qs_pg:qs_pg_placetype":"locality",
    "qs_pg:qs_pg_placetype_gp":"Town",
    "qs_pg:woe_adm0":23424923,
    "woe:adm0_id":23424923,
    "woe:name_adm0":"Polska",
    "woe:name_adm1":"Sl\u0105skie",
    "woe:placetype":"Town",
    "wof:name":"Uchylsko",
    "wof:placetype":"locality",
    "wof:population":342
},
  "geometry": {"coordinates":[18.37944,49.94592],"type":"Point"}
}