{
  "type": "Feature",
  "properties": {
    "gn:admin1_code":"76.0",
    "gn:admin2_code":"811.0",
    "gn:admin3_code":"81107.0",
    "gn:asciiname":"Wlochow",
    "gn:country_code":"PL",
    "gn:dem":134,
    "gn:feature_class":"P",
    "gn:feature_code":"PPL",
    "gn:name":"W\u0142och\u00f3w",
    "gn:population":0,
    "gn:timezone":"Europe/Warsaw",
    "iso:country":"PL",
    "name:deu_x_preferred":[
        "W\u0142och\u00f3w"
    ],
    "name:fra_x_preferred":[
        "W\u0142och\u00f3w"
    ],
    "name:pol_x_preferred":[
        "W\u0142och\u00f3w"
    ],
    "name:ukr_x_preferred":[
        "\u0412\u043b\u043e\u0445\u0443\u0432"
    ],
    "wof:name":"Wlochow",
    "wof:placetype":"locality"
},
  "geometry": {"coordinates":[14.91068,51.52231],"type":"Point"}
}