{
  "type": "Feature",
  "properties": {
    "gn:admin1_code":"74.0",
    "gn:admin2_code":"1004.0",
    "gn:admin3_code":"100408.0",
    "gn:asciiname":"Gledzianowek",
    "gn:country_code":"PL",
    "gn:dem":100,
    "gn:feature_class":"P",
    "gn:feature_code":"PPL",
    "gn:name":"Gl\u0119dzian\u00f3wek",
    "gn:population":0,
    "gn:timezone":"Europe/Warsaw",
    "iso:country":"PL",
    "name:fra_x_preferred":[
        "Gledzian\u00f3wek"
    ],
    "name:pol_x_preferred":[
        "Gledzian\u00f3wek"
    ],
    "name:ukr_x_preferred":[
        "\u0490\u043b\u0435\u0434\u0437\u044f\u043d\u0443\u0432\u0435\u043a"
    ],
    "name:und_x_variant":[
        "Gl\u0119dzian\u00f3wek"
    ],
    "wof:name":"Gledzianowek",
    "wof:placetype":"locality"
},
  "geometry": {"coordinates":[19.34387000000001,52.13041],"type":"Point"}
}