{
  "type": "Feature",
  "properties": {
    "gn:admin1_code":"78.0",
    "gn:admin2_code":"1416.0",
    "gn:admin3_code":"141607.0",
    "gn:asciiname":"Ugniewo",
    "gn:country_code":"PL",
    "gn:dem":128,
    "gn:feature_class":"P",
    "gn:feature_code":"PPL",
    "gn:name":"Ugniewo",
    "gn:population":0,
    "gn:timezone":"Europe/Warsaw",
    "iso:country":"PL",
    "name:ceb_x_preferred":[
        "Ugniewo"
    ],
    "name:fra_x_preferred":[
        "Ugniewo"
    ],
    "name:pol_x_preferred":[
        "Ugniewo"
    ],
    "name:ukr_x_preferred":[
        "\u0423\u0491\u043d\u0435\u0432\u043e"
    ],
    "wof:name":"Ugniewo",
    "wof:placetype":"locality"
},
  "geometry": {"coordinates":[21.95642,52.7951],"type":"Point"}
}