{
  "type": "Feature",
  "properties": {
    "gn:gn_country":"PL",
    "gn:gn_fcode":"PPLA3",
    "gn:gn_pop":2466,
    "gn:population":2466,
    "iso:country":"PL",
    "name:ara_x_preferred":[
        "\u062a\u0648\u0631\u0632\u064a\u0645"
    ],
    "name:lav_x_preferred":[
        "To\u017eima"
    ],
    "name:rus_x_preferred":[
        "\u0422\u043e\u0436\u0438\u043c"
    ],
    "name:srp_x_preferred":[
        "\u0422\u043e\u0436\u0438\u043c"
    ],
    "name:ukr_x_preferred":[
        "\u0422\u043e\u0436\u0438\u043c"
    ],
    "name:unk_x_variant":[
        "Sternberg"
    ],
    "name:zho_x_preferred":[
        "\u6258\u65e5\u59c6"
    ],
    "qs_pg:aaroncc":"PL",
    "qs_pg:gn_country":"PL",
    "qs_pg:gn_fcode":"PPLA3",
    "qs_pg:gn_pop":2466,
    "qs_pg:name":"Torzym",
    "qs_pg:name_adm0":"Polska",
    "qs_pg:name_adm1":"Lubuskie",
    "qs_pg:photos":1,
    "qs_pg:photos_1k":1,
    "qs_pg:photos_9k":1,
    "qs_pg:photos_9r":1,
    "qs_pg:photos_all":1,
    "qs_pg:photos_sr":1,
    "qs_pg:pop_sr":4,
    "qs_pg:qs_pg_placetype":"localadmin",
    "qs_pg:qs_pg_placetype_gp":"LocalAdmin",
    "qs_pg:woe_adm0":23424923,
    "woe:adm0_id":23424923,
    "woe:name_adm0":"Polska",
    "woe:name_adm1":"Lubuskie",
    "woe:placetype":"LocalAdmin",
    "wof:name":"Torzym",
    "wof:placetype":"localadmin",
    "wof:population":2466
},
  "geometry": {"coordinates":[15.08243,52.31331],"type":"Point"}
}