{
  "type": "Feature",
  "properties": {
    "gn:admin1_code":"84.0",
    "gn:admin2_code":"2604.0",
    "gn:admin3_code":"260409.0",
    "gn:asciiname":"Domaszewice Stara Wies",
    "gn:country_code":"PL",
    "gn:dem":264,
    "gn:feature_class":"P",
    "gn:feature_code":"PPL",
    "gn:name":"Domaszewice Stara Wie\u015b",
    "gn:population":0,
    "gn:timezone":"Europe/Warsaw",
    "iso:country":"PL",
    "wof:name":"Domaszewice Stara Wies",
    "wof:placetype":"locality"
},
  "geometry": {"coordinates":[20.68333,50.86667],"type":"Point"}
}