{
  "type": "Feature",
  "properties": {
    "gn:admin1_code":"85.0",
    "gn:admin2_code":"2809.0",
    "gn:admin3_code":"280903.0",
    "gn:asciiname":"Jagoty",
    "gn:country_code":"PL",
    "gn:dem":90,
    "gn:feature_class":"P",
    "gn:feature_code":"PPL",
    "gn:name":"Jagoty",
    "gn:population":0,
    "gn:timezone":"Europe/Warsaw",
    "iso:country":"PL",
    "name:und_x_variant":[
        "Jegothen",
        "Jagoty"
    ],
    "wof:name":"Jagoty",
    "wof:placetype":"locality"
},
  "geometry": {"coordinates":[20.56401,54.19105],"type":"Point"}
}