{
  "type": "Feature",
  "properties": {
    "gn:admin1_code":"85.0",
    "gn:admin2_code":"2809.0",
    "gn:admin3_code":"280903.0",
    "gn:asciiname":"Jagoty",
    "gn:country_code":"PL",
    "gn:dem":90,
    "gn:feature_class":"P",
    "gn:feature_code":"PPL",
    "gn:name":"Jagoty",
    "gn:population":0,
    "gn:timezone":"Europe/Warsaw",
    "iso:country":"PL",
    "name:azb_x_preferred":[
        "\u06cc\u0627\u0642\u0648\u062a\u0647"
    ],
    "name:fas_x_preferred":[
        "\u06cc\u0627\u06af\u0648\u062a\u0647"
    ],
    "name:fra_x_preferred":[
        "Jagoty"
    ],
    "name:pol_x_preferred":[
        "Jagoty"
    ],
    "name:ukr_x_preferred":[
        "\u042f\u0491\u043e\u0442\u0438"
    ],
    "name:und_x_variant":[
        "Jegothen",
        "Jagoty"
    ],
    "name:urd_x_preferred":[
        "\u062c\u06af\u0648\u062a\u06d2"
    ],
    "wof:name":"Jagoty",
    "wof:placetype":"locality"
},
  "geometry": {"coordinates":[20.56401,54.19105],"type":"Point"}
}