{
  "type": "Feature",
  "properties": {
    "gn:country":"PL",
    "gn:fcode":"PPL",
    "gn:population":597,
    "iso:country":"PL",
    "name:ceb_x_preferred":[
        "Krasne"
    ],
    "name:deu_x_preferred":[
        "Krasne"
    ],
    "name:est_x_preferred":[
        "Krasne"
    ],
    "name:fra_x_preferred":[
        "Krasne"
    ],
    "name:ita_x_preferred":[
        "Krasne"
    ],
    "name:jpn_x_preferred":[
        "\u30af\u30e9\u30fc\u30b9\u30cd"
    ],
    "name:lit_x_preferred":[
        "Krasn\u0117"
    ],
    "name:nld_x_preferred":[
        "Krasne"
    ],
    "name:pol_x_preferred":[
        "Krasne"
    ],
    "name:spa_x_preferred":[
        "Krasne"
    ],
    "name:srp_x_preferred":[
        "\u041a\u0440\u0430\u0441\u043d\u0435"
    ],
    "name:swe_x_preferred":[
        "Krasne"
    ],
    "name:ukr_x_preferred":[
        "\u041a\u0440\u0430\u0441\u043d\u0435"
    ],
    "name:zho_x_preferred":[
        "\u514b\u62c9\u65af\u5185"
    ],
    "qs_pg:aaroncc":"PL",
    "qs_pg:gn_country":"PL",
    "qs_pg:gn_fcode":"PPL",
    "qs_pg:gn_pop":597,
    "qs_pg:name":"Krasne",
    "qs_pg:photos_9r":0,
    "qs_pg:photos_sr":0,
    "qs_pg:pop_sr":2,
    "qs_pg:qs_pg_placetype":"locality",
    "wof:name":"Krasne",
    "wof:placetype":"locality",
    "wof:population":597
},
  "geometry": {"coordinates":[23.19025,51.13326],"type":"Point"}
}