{
  "type": "Feature",
  "properties": {
    "gn:admin1_code":"86.0",
    "gn:admin2_code":"3002.0",
    "gn:admin3_code":"300206.0",
    "gn:asciiname":"Ludomicko",
    "gn:country_code":"PL",
    "gn:dem":65,
    "gn:feature_class":"P",
    "gn:feature_code":"PPL",
    "gn:name":"Ludomicko",
    "gn:population":0,
    "gn:timezone":"Europe/Warsaw",
    "iso:country":"PL",
    "name:pol_x_preferred":[
        "Ludomicko"
    ],
    "name:ukr_x_preferred":[
        "\u041b\u044e\u0434\u043e\u043c\u0456\u0446\u044c\u043a\u043e"
    ],
    "wof:name":"Ludomicko",
    "wof:placetype":"locality"
},
  "geometry": {"coordinates":[16.74023,52.74655],"type":"Point"}
}