{
  "type": "Feature",
  "properties": {
    "gn:admin1_code":"76.0",
    "gn:admin2_code":"862.0",
    "gn:admin3_code":"86201.0",
    "gn:asciiname":"Jany",
    "gn:country_code":"PL",
    "gn:dem":57,
    "gn:feature_class":"P",
    "gn:feature_code":"PPL",
    "gn:name":"Jany",
    "gn:population":0,
    "gn:timezone":"Europe/Warsaw",
    "iso:country":"PL",
    "name:ceb_x_preferred":[
        "Jany"
    ],
    "name:fra_x_preferred":[
        "Jany"
    ],
    "name:pol_x_preferred":[
        "Jany"
    ],
    "name:urd_x_preferred":[
        "\u062c\u0627\u0646\u06d2"
    ],
    "wof:name":"Jany",
    "wof:placetype":"locality"
},
  "geometry": {"coordinates":[15.60782,51.97473],"type":"Point"}
}