{
  "type": "Feature",
  "properties": {
    "gn:admin1_code":"72.0",
    "gn:admin2_code":"208.0",
    "gn:admin3_code":"20808.0",
    "gn:asciiname":"Konradow",
    "gn:country_code":"PL",
    "gn:dem":471,
    "gn:feature_class":"P",
    "gn:feature_code":"PPL",
    "gn:name":"Konradow",
    "gn:population":0,
    "gn:timezone":"Europe/Warsaw",
    "iso:country":"PL",
    "name:deu_x_historical":[
        "Konradswalde"
    ],
    "name:deu_x_preferred":[
        "Konradswalde"
    ],
    "wof:name":"Konradow",
    "wof:placetype":"locality"
},
  "geometry": {"coordinates":[16.79398,50.30897],"type":"Point"}
}