{
  "type": "Feature",
  "properties": {
    "gn:admin1_code":"72.0",
    "gn:admin2_code":"208.0",
    "gn:admin3_code":"20808.0",
    "gn:asciiname":"Konradow",
    "gn:country_code":"PL",
    "gn:dem":471,
    "gn:feature_class":"P",
    "gn:feature_code":"PPL",
    "gn:name":"Konradow",
    "gn:population":0,
    "gn:timezone":"Europe/Warsaw",
    "iso:country":"PL",
    "name:azb_x_preferred":[
        "\u06a9\u0648\u0646\u0631\u0627\u062f\u0648\u0648"
    ],
    "name:ceb_x_preferred":[
        "Konradow"
    ],
    "name:deu_x_historical":[
        "Konradswalde"
    ],
    "name:deu_x_preferred":[
        "Konradswalde"
    ],
    "name:deu_x_variant":[
        "Konrad\u00f3w"
    ],
    "name:fas_x_preferred":[
        "\u06a9\u0648\u0646\u0631\u0627\u062f\u0648\u0648"
    ],
    "name:nld_x_preferred":[
        "Konrad\u00f3w"
    ],
    "name:pol_x_preferred":[
        "Konrad\u00f3w"
    ],
    "name:ukr_x_preferred":[
        "\u041a\u043e\u043d\u0440\u0430\u0434\u0443\u0432"
    ],
    "wof:name":"Konradow",
    "wof:placetype":"locality"
},
  "geometry": {"coordinates":[16.79398,50.30897],"type":"Point"}
}