{
  "type": "Feature",
  "properties": {
    "gn:country":"PL",
    "gn:fcode":"PPL",
    "gn:population":161,
    "iso:country":"PL",
    "name:ceb_x_preferred":[
        "Koz\u0142\u00f3w"
    ],
    "name:deu_x_preferred":[
        "Koz\u0142\u00f3w"
    ],
    "name:fra_x_preferred":[
        "Koz\u0142\u00f3w"
    ],
    "name:nld_x_preferred":[
        "Koz\u0142\u00f3w"
    ],
    "name:pol_x_preferred":[
        "Koz\u0142\u00f3w"
    ],
    "name:ukr_x_preferred":[
        "\u041a\u043e\u0437\u043b\u0443\u0432"
    ],
    "qs_pg:aaroncc":"PL",
    "qs_pg:gn_country":"PL",
    "qs_pg:gn_fcode":"PPL",
    "qs_pg:gn_pop":161,
    "qs_pg:name":"Koz\u0142\u00f3w",
    "qs_pg:photos_9r":0,
    "qs_pg:photos_sr":0,
    "qs_pg:pop_sr":1,
    "qs_pg:qs_pg_placetype":"locality",
    "wof:name":"Koz\u0142\u00f3w",
    "wof:placetype":"locality",
    "wof:population":161
},
  "geometry": {"coordinates":[20.81978,50.26926],"type":"Point"}
}