{
  "type": "Feature",
  "properties": {
    "gn:admin1_code":"75.0",
    "gn:admin2_code":"604.0",
    "gn:admin3_code":"60402.0",
    "gn:asciiname":"Chochlow",
    "gn:country_code":"PL",
    "gn:dem":218,
    "gn:feature_class":"P",
    "gn:feature_code":"PPL",
    "gn:name":"Choch\u0142\u00f3w",
    "gn:population":0,
    "gn:timezone":"Europe/Warsaw",
    "iso:country":"PL",
    "name:azb_x_preferred":[
        "\u062e\u0648\u062e\u0648\u0648\u0648"
    ],
    "name:fas_x_preferred":[
        "\u062e\u0648\u062e\u0648\u0648\u0648"
    ],
    "name:fra_x_preferred":[
        "Choch\u0142\u00f3w"
    ],
    "name:nld_x_preferred":[
        "Choch\u0142\u00f3w"
    ],
    "name:pol_x_preferred":[
        "Choch\u0142\u00f3w"
    ],
    "name:ukr_x_preferred":[
        "\u0425\u043e\u0445\u043b\u0443\u0432"
    ],
    "wof:name":"Chochlow",
    "wof:placetype":"locality"
},
  "geometry": {"coordinates":[24.02118,50.489],"type":"Point"}
}