{
  "type": "Feature",
  "properties": {
    "gn:admin1_code":"87.0",
    "gn:admin2_code":"3217.0",
    "gn:admin3_code":"321704.0",
    "gn:asciiname":"Wrzosy",
    "gn:country_code":"PL",
    "gn:dem":102,
    "gn:feature_class":"P",
    "gn:feature_code":"PPL",
    "gn:name":"Wrzosy",
    "gn:population":0,
    "gn:timezone":"Europe/Warsaw",
    "iso:country":"PL",
    "name:ceb_x_preferred":[
        "Wrzosy"
    ],
    "name:fra_x_preferred":[
        "Wrzosy"
    ],
    "name:pol_x_preferred":[
        "Wrzosy"
    ],
    "wof:name":"Wrzosy",
    "wof:placetype":"locality"
},
  "geometry": {"coordinates":[16.15992,53.23389],"type":"Point"}
}