{
  "type": "Feature",
  "properties": {
    "gn:admin1_code":"74.0",
    "gn:admin2_code":"1019.0",
    "gn:admin3_code":"101903.0",
    "gn:asciiname":"Swierzyny",
    "gn:country_code":"PL",
    "gn:dem":170,
    "gn:feature_class":"P",
    "gn:feature_code":"PPL",
    "gn:name":"\u015awierzyny",
    "gn:population":0,
    "gn:timezone":"Europe/Warsaw",
    "iso:country":"PL",
    "name:pol_x_preferred":[
        "\u015awierzyny"
    ],
    "name:ukr_x_preferred":[
        "\u0421\u044c\u0432\u0435\u0436\u0438\u043d\u0438"
    ],
    "wof:name":"Swierzyny",
    "wof:placetype":"locality"
},
  "geometry": {"coordinates":[18.91287,51.54784],"type":"Point"}
}