{
  "type": "Feature",
  "properties": {
    "gn:admin1_code":"72.0",
    "gn:admin2_code":"208.0",
    "gn:admin3_code":"20807.0",
    "gn:asciiname":"Mikowice",
    "gn:country_code":"PL",
    "gn:dem":341,
    "gn:feature_class":"P",
    "gn:feature_code":"PPL",
    "gn:name":"Mikowice",
    "gn:population":0,
    "gn:timezone":"Europe/Warsaw",
    "iso:country":"PL",
    "name:deu_x_preferred":[
        "Mikowice"
    ],
    "name:pol_x_preferred":[
        "Mikowice"
    ],
    "name:ukr_x_preferred":[
        "\u041c\u0456\u043a\u043e\u0432\u0456\u0446\u0435"
    ],
    "wof:name":"Mikowice",
    "wof:placetype":"locality"
},
  "geometry": {"coordinates":[16.60582999999999,50.44319],"type":"Point"}
}