{
  "type": "Feature",
  "properties": {
    "gn:country":"PL",
    "gn:fcode":"PPL",
    "gn:population":0,
    "iso:country":"PL",
    "name:ast_x_preferred":[
        "Tomaszkowo"
    ],
    "name:eng_x_preferred":[
        "Tomaszkowo"
    ],
    "name:fra_x_preferred":[
        "Tomaszkowo"
    ],
    "name:pol_x_preferred":[
        "Tomaszkowo"
    ],
    "name:ukr_x_preferred":[
        "\u0422\u043e\u043c\u0430\u0448\u043a\u043e\u0432\u043e"
    ],
    "name:und_x_variant":[
        "Thomsdorf"
    ],
    "qs_pg:aaroncc":"PL",
    "qs_pg:gn_country":"PL",
    "qs_pg:gn_fcode":"PPL",
    "qs_pg:gn_pop":0,
    "qs_pg:name":"Tomaszkowo",
    "qs_pg:name_adm0":"Polska",
    "qs_pg:name_adm1":"Warminsko-Mazurskie",
    "qs_pg:photos_9k":1,
    "qs_pg:photos_9r":1,
    "qs_pg:photos_all":5,
    "qs_pg:photos_sr":0,
    "qs_pg:pop_sr":0,
    "qs_pg:qs_pg_placetype":"locality",
    "qs_pg:qs_pg_placetype_gp":"Town",
    "qs_pg:woe_adm0":23424923,
    "woe:adm0_id":23424923,
    "woe:name_adm0":"Polska",
    "woe:name_adm1":"Warminsko-Mazurskie",
    "woe:placetype":"Town",
    "wof:name":"Tomaszkowo",
    "wof:placetype":"locality"
},
  "geometry": {"coordinates":[20.40934,53.71748],"type":"Point"}
}