{
  "type": "Feature",
  "properties": {
    "gn:admin1_code":"74.0",
    "gn:admin2_code":"1002.0",
    "gn:admin3_code":"100206.0",
    "gn:asciiname":"Strzegocin",
    "gn:country_code":"PL",
    "gn:dem":105,
    "gn:feature_class":"P",
    "gn:feature_code":"PPL",
    "gn:name":"Strzegocin",
    "gn:population":0,
    "gn:timezone":"Europe/Warsaw",
    "iso:country":"PL",
    "name:fra_x_preferred":[
        "Strzegocin"
    ],
    "name:pol_x_preferred":[
        "Strzegocin"
    ],
    "name:ukr_x_preferred":[
        "\u0421\u0442\u0448\u0435\u0491\u043e\u0446\u0438\u043d"
    ],
    "wof:name":"Strzegocin",
    "wof:placetype":"locality"
},
  "geometry": {"coordinates":[19.34556,52.15865],"type":"Point"}
}