{
  "type": "Feature",
  "properties": {
    "gn:admin1_code":"73.0",
    "gn:admin2_code":"415.0",
    "gn:admin3_code":"41508.0",
    "gn:asciiname":"Brzeczka",
    "gn:country_code":"PL",
    "gn:dem":78,
    "gn:feature_class":"P",
    "gn:feature_code":"PPL",
    "gn:name":"Brzeczka",
    "gn:population":0,
    "gn:timezone":"Europe/Warsaw",
    "iso:country":"PL",
    "wof:name":"Brzeczka",
    "wof:placetype":"locality"
},
  "geometry": {"coordinates":[18.59334,52.86384],"type":"Point"}
}