{
  "type": "Feature",
  "properties": {
    "gn:population":2175,
    "iso:country":"PL",
    "name:ast_x_preferred":[
        "Ha\u017clach"
    ],
    "name:azb_x_preferred":[
        "\u062e\u0627\u0698\u0644\u0627\u062e"
    ],
    "name:ces_x_preferred":[
        "Ha\u017elach"
    ],
    "name:deu_x_preferred":[
        "Ha\u017clach"
    ],
    "name:eng_x_preferred":[
        "Ha\u017clach"
    ],
    "name:fas_x_preferred":[
        "\u062e\u0627\u0698\u0644\u0627\u062e"
    ],
    "name:fra_x_preferred":[
        "Ha\u017clach"
    ],
    "name:mdf_x_preferred":[
        "\u0425\u0430\u0436\u043b\u0430\u0445"
    ],
    "name:nan_x_preferred":[
        "Ha\u017clach"
    ],
    "name:nld_x_preferred":[
        "Ha\u017clach"
    ],
    "name:pol_x_preferred":[
        "Ha\u017clach"
    ],
    "name:por_x_preferred":[
        "Ha\u017clach"
    ],
    "name:ukr_x_preferred":[
        "\u0413\u0430\u0436\u043b\u044f\u0445"
    ],
    "name:zho_min_nan_x_preferred":[
        "Ha\u017clach"
    ],
    "qs:a0":"Rzeczpospolita Polska",
    "qs:a1":"*Slaskie",
    "qs:a1r":"0",
    "qs:a2":"Cieszynski",
    "qs:adm0":"Rzeczpospolita Polska",
    "qs:la_lc":"*",
    "qs:level":"locality",
    "qs:loc":"Ha\u017clach",
    "qs:loc_alt":"Hazlach",
    "qs:pop":0,
    "qs:type":"buffered point",
    "wd:wordcount":793,
    "wof:coterminous":[
        1477752841
    ],
    "wof:name":"Ha\u017clach",
    "wof:placetype":"locality",
    "wof:population":2175
},
  "geometry": {"coordinates":[18.670355,49.807762],"type":"Point"}
}