{
  "type": "Feature",
  "properties": {
    "gn:admin1_code":"75.0",
    "gn:admin2_code":"619.0",
    "gn:admin3_code":"61903.0",
    "gn:asciiname":"Rudka Lowiecka",
    "gn:country_code":"PL",
    "gn:dem":174,
    "gn:feature_class":"P",
    "gn:feature_code":"PPL",
    "gn:name":"Rudka \u0141owiecka",
    "gn:population":0,
    "gn:timezone":"Europe/Warsaw",
    "iso:country":"PL",
    "name:fra_x_preferred":[
        "Rudka \u0141owiecka"
    ],
    "name:pol_x_preferred":[
        "Rudka \u0141owiecka"
    ],
    "name:ukr_x_preferred":[
        "\u0420\u0443\u0434\u043a\u0430-\u041b\u043e\u0432\u0435\u0446\u044c\u043a\u0430"
    ],
    "wof:name":"Rudka Lowiecka",
    "wof:placetype":"locality"
},
  "geometry": {"coordinates":[23.44534,51.36171],"type":"Point"}
}