{
  "type": "Feature",
  "properties": {
    "gn:admin1_code":"85.0",
    "gn:admin2_code":"2808.0",
    "gn:admin3_code":"280802.0",
    "gn:asciiname":"Ogrodki",
    "gn:country_code":"PL",
    "gn:dem":73,
    "gn:feature_class":"P",
    "gn:feature_code":"PPL",
    "gn:name":"Ogr\u00f3dki",
    "gn:population":0,
    "gn:timezone":"Europe/Warsaw",
    "iso:country":"PL",
    "name:und_x_variant":[
        "Baumgarten",
        "Ogr\u00f3dki"
    ],
    "wof:name":"Ogrodki",
    "wof:placetype":"locality"
},
  "geometry": {"coordinates":[21.41872,54.20925],"type":"Point"}
}