{
  "type": "Feature",
  "properties": {
    "gn:admin1_code":"87.0",
    "gn:admin2_code":"3205.0",
    "gn:admin3_code":"320508.0",
    "gn:asciiname":"Wlodarka",
    "gn:cc2":"PL",
    "gn:country_code":"PL",
    "gn:dem":5,
    "gn:feature_class":"P",
    "gn:feature_code":"PPL",
    "gn:name":"W\u0142odarka",
    "gn:population":0,
    "gn:timezone":"Europe/Warsaw",
    "iso:country":"PL",
    "name:deu_x_historical":[
        "Voigtshagen"
    ],
    "name:deu_x_preferred":[
        "Voigtshagen"
    ],
    "name:und_x_variant":[
        "W\u0142odarka"
    ],
    "wof:name":"Wlodarka",
    "wof:placetype":"locality"
},
  "geometry": {"coordinates":[15.21263,54.08729],"type":"Point"}
}