{
  "type": "Feature",
  "properties": {
    "gn:admin1_code":"75.0",
    "gn:admin2_code":"607.0",
    "gn:admin3_code":"60707.0",
    "gn:asciiname":"Owczarnia",
    "gn:country_code":"PL",
    "gn:dem":264,
    "gn:feature_class":"P",
    "gn:feature_code":"PPL",
    "gn:name":"Owczarnia",
    "gn:population":0,
    "gn:timezone":"Europe/Warsaw",
    "iso:country":"PL",
    "name:fra_x_preferred":[
        "Owczarnia"
    ],
    "name:pol_x_preferred":[
        "Owczarnia"
    ],
    "name:rus_x_preferred":[
        "\u041e\u0432\u0447\u0430\u0440\u043d\u044f"
    ],
    "name:ukr_x_preferred":[
        "\u041e\u0432\u0447\u0430\u0440\u043d\u044f"
    ],
    "wof:name":"Owczarnia",
    "wof:placetype":"locality"
},
  "geometry": {"coordinates":[22.20143,50.88448],"type":"Point"}
}