{
  "type": "Feature",
  "properties": {
    "gn:admin1_code":"78.0",
    "gn:admin2_code":"1419.0",
    "gn:admin3_code":"141912.0",
    "gn:asciiname":"Swiecieniec",
    "gn:country_code":"PL",
    "gn:dem":115,
    "gn:feature_class":"P",
    "gn:feature_code":"PPL",
    "gn:name":"\u015awi\u0119cieniec",
    "gn:population":0,
    "gn:timezone":"Europe/Warsaw",
    "iso:country":"PL",
    "name:und_x_variant":[
        "\u015awi\u0119cieniec"
    ],
    "wof:name":"Swiecieniec",
    "wof:placetype":"locality"
},
  "geometry": {"coordinates":[19.90598,52.52553],"type":"Point"}
}