{
  "type": "Feature",
  "properties": {
    "gn:admin1_code":"86.0",
    "gn:admin2_code":"3003.0",
    "gn:admin3_code":"300302.0",
    "gn:asciiname":"Kosowo",
    "gn:country_code":"PL",
    "gn:dem":110,
    "gn:feature_class":"P",
    "gn:feature_code":"PPL",
    "gn:name":"Kosowo",
    "gn:population":0,
    "gn:timezone":"Europe/Warsaw",
    "iso:country":"PL",
    "name:fra_x_preferred":[
        "Kosowo"
    ],
    "name:pol_x_preferred":[
        "Kosowo"
    ],
    "name:ukr_x_preferred":[
        "\u041a\u043e\u0441\u043e\u0432\u043e"
    ],
    "wof:name":"Kosowo",
    "wof:placetype":"locality"
},
  "geometry": {"coordinates":[17.56914,52.43114],"type":"Point"}
}