{
  "type": "Feature",
  "properties": {
    "gn:admin1_code":"78.0",
    "gn:admin2_code":"1433.0",
    "gn:admin3_code":"143305.0",
    "gn:asciiname":"Wolka Paplinska",
    "gn:country_code":"PL",
    "gn:dem":107,
    "gn:feature_class":"P",
    "gn:feature_code":"PPL",
    "gn:name":"W\u00f3lka Papli\u0144ska",
    "gn:population":0,
    "gn:timezone":"Europe/Warsaw",
    "iso:country":"PL",
    "name:und_x_variant":[
        "W\u00f3lka Papli\u0144ska"
    ],
    "wof:name":"Wolka Paplinska",
    "wof:placetype":"locality"
},
  "geometry": {"coordinates":[21.81429,52.48243000000001],"type":"Point"}
}