{
  "type": "Feature",
  "properties": {
    "gn:admin1_code":"81.0",
    "gn:admin2_code":"2014.0",
    "gn:admin3_code":"201405.0",
    "gn:asciiname":"Tabadz",
    "gn:country_code":"PL",
    "gn:dem":124,
    "gn:feature_class":"P",
    "gn:feature_code":"PPL",
    "gn:name":"Tab\u0105d\u017c",
    "gn:population":0,
    "gn:timezone":"Europe/Warsaw",
    "iso:country":"PL",
    "name:und_x_variant":[
        "Tab\u0119d\u017c",
        "Tab\u0105d\u017c"
    ],
    "wof:name":"Tabadz",
    "wof:placetype":"locality"
},
  "geometry": {"coordinates":[22.13499,53.00275],"type":"Point"}
}