{
  "type": "Feature",
  "properties": {
    "gn:admin1_code":"85.0",
    "gn:admin2_code":"2813.0",
    "gn:admin3_code":"281303.0",
    "gn:asciiname":"Borkowiny",
    "gn:country_code":"PL",
    "gn:dem":189,
    "gn:feature_class":"P",
    "gn:feature_code":"PPL",
    "gn:name":"Borkowiny",
    "gn:population":0,
    "gn:timezone":"Europe/Warsaw",
    "iso:country":"PL",
    "name:deu_x_preferred":[
        "Borkowiny"
    ],
    "name:nld_x_preferred":[
        "Borkowiny"
    ],
    "name:pol_x_preferred":[
        "Borkowiny"
    ],
    "name:und_x_variant":[
        "Grossjarken",
        "Borkowinnen",
        "Jarken"
    ],
    "wof:name":"Borkowiny",
    "wof:placetype":"locality"
},
  "geometry": {"coordinates":[22.44919,54.20262],"type":"Point"}
}