{
  "type": "Feature",
  "properties": {
    "gn:admin1_code":"80.0",
    "gn:admin2_code":"1817.0",
    "gn:admin3_code":"181703.0",
    "gn:asciiname":"Dudynce",
    "gn:country_code":"PL",
    "gn:dem":331,
    "gn:feature_class":"P",
    "gn:feature_code":"PPL",
    "gn:name":"Dudy\u0144ce",
    "gn:population":0,
    "gn:timezone":"Europe/Warsaw",
    "iso:country":"PL",
    "name:und_x_variant":[
        "Dudy\u0144ce"
    ],
    "wof:name":"Dudynce",
    "wof:placetype":"locality"
},
  "geometry": {"coordinates":[22.07496,49.53468],"type":"Point"}
}