{
  "type": "Feature",
  "properties": {
    "gn:admin1_code":"80.0",
    "gn:admin2_code":"1817.0",
    "gn:admin3_code":"181703.0",
    "gn:asciiname":"Dudynce",
    "gn:country_code":"PL",
    "gn:dem":331,
    "gn:feature_class":"P",
    "gn:feature_code":"PPL",
    "gn:name":"Dudy\u0144ce",
    "gn:population":0,
    "gn:timezone":"Europe/Warsaw",
    "iso:country":"PL",
    "name:azb_x_preferred":[
        "\u062f\u0648\u062f\u0646\u0642\u062a\u0633\u0647"
    ],
    "name:ceb_x_preferred":[
        "Dudy\u0144ce"
    ],
    "name:deu_x_preferred":[
        "Dudy\u0144ce"
    ],
    "name:fas_x_preferred":[
        "\u062f\u0648\u062f\u0646\u06af\u062a\u0633\u0647"
    ],
    "name:nld_x_preferred":[
        "Dudy\u0144ce"
    ],
    "name:pol_x_preferred":[
        "Dudy\u0144ce"
    ],
    "name:rue_x_preferred":[
        "\u0414\u0443\u0434\u0438\u043d\u0446\u0457"
    ],
    "name:ukr_x_preferred":[
        "\u0414\u0443\u0434\u0438\u043d\u0446\u0456"
    ],
    "wof:name":"Dudynce",
    "wof:placetype":"locality"
},
  "geometry": {"coordinates":[22.07496,49.53468],"type":"Point"}
}