{
  "type": "Feature",
  "properties": {
    "gn:admin1_code":"78.0",
    "gn:admin2_code":"1427.0",
    "gn:admin3_code":"142705.0",
    "gn:asciiname":"Bialyszewo",
    "gn:country_code":"PL",
    "gn:dem":122,
    "gn:feature_class":"P",
    "gn:feature_code":"PPL",
    "gn:name":"Bia\u0142yszewo",
    "gn:population":0,
    "gn:timezone":"Europe/Warsaw",
    "iso:country":"PL",
    "name:ceb_x_preferred":[
        "Bia\u0142yszewo"
    ],
    "name:fra_x_preferred":[
        "Bia\u0142yszewo"
    ],
    "name:pol_x_preferred":[
        "Bia\u0142yszewo"
    ],
    "name:ukr_x_preferred":[
        "\u0411\u044f\u043b\u0438\u0448\u0435\u0432\u043e"
    ],
    "name:und_x_variant":[
        "Bia\u0142yszewo"
    ],
    "wof:name":"Bialyszewo",
    "wof:placetype":"locality"
},
  "geometry": {"coordinates":[19.73897,52.78039],"type":"Point"}
}