{
  "type": "Feature",
  "properties": {
    "gn:admin1_code":"78.0",
    "gn:admin2_code":"1421.0",
    "gn:admin3_code":"142106.0",
    "gn:asciiname":"Sekocin Stary",
    "gn:country_code":"PL",
    "gn:dem":110,
    "gn:feature_class":"P",
    "gn:feature_code":"PPL",
    "gn:name":"S\u0119kocin Stary",
    "gn:population":0,
    "gn:timezone":"Europe/Warsaw",
    "iso:country":"PL",
    "name:ceb_x_preferred":[
        "S\u0119kocin Stary"
    ],
    "name:fra_x_preferred":[
        "S\u0119kocin Stary"
    ],
    "name:pol_x_preferred":[
        "S\u0119kocin Stary"
    ],
    "name:ukr_x_preferred":[
        "\u0421\u0435\u043d\u043a\u043e\u0446\u0438\u043d-\u0421\u0442\u0430\u0440\u0438\u0439"
    ],
    "name:und_x_variant":[
        "S\u0119kocin Stary"
    ],
    "wof:name":"Sekocin Stary",
    "wof:placetype":"locality"
},
  "geometry": {"coordinates":[20.88239,52.11116],"type":"Point"}
}