{
  "type": "Feature",
  "properties": {
    "gn:country":"PL",
    "gn:fcode":"PPLA3",
    "gn:population":2671,
    "iso:country":"PL",
    "name:azb_x_preferred":[
        "\u0645\u0627\u06cc\u062f\u0627\u0646 \u06a9\u0631\u0648\u0644\u0648\u0633\u06a9\u06cc"
    ],
    "name:fas_x_preferred":[
        "\u0645\u0627\u06cc\u062f\u0627\u0646 \u06a9\u0631\u0648\u0644\u0648\u0633\u06a9\u06cc"
    ],
    "name:nld_x_preferred":[
        "Majdan Kr\u00f3lewski"
    ],
    "name:pol_x_preferred":[
        "Majdan Kr\u00f3lewski"
    ],
    "name:ukr_x_preferred":[
        "\u041c\u0430\u0439\u0434\u0430\u043d-\u041a\u0440\u0443\u043b\u0435\u0432\u0441\u044c\u043a\u0438\u0439"
    ],
    "name:und_x_variant":[
        "Majdan"
    ],
    "qs_pg:aaroncc":"PL",
    "qs_pg:gn_country":"PL",
    "qs_pg:gn_fcode":"PPLA3",
    "qs_pg:gn_pop":2671,
    "qs_pg:name":"Majdan Kr\u00f3lewski",
    "qs_pg:name_adm0":"Polska",
    "qs_pg:name_adm1":"Podkarpackie",
    "qs_pg:photos":2,
    "qs_pg:photos_1k":1,
    "qs_pg:photos_9k":1,
    "qs_pg:photos_9r":1,
    "qs_pg:photos_all":2,
    "qs_pg:photos_sr":1,
    "qs_pg:pop_sr":4,
    "qs_pg:qs_pg_placetype":"localadmin",
    "qs_pg:qs_pg_placetype_gp":"LocalAdmin",
    "qs_pg:woe_adm0":23424923,
    "woe:adm0_id":23424923,
    "woe:name_adm0":"Polska",
    "woe:name_adm1":"Podkarpackie",
    "woe:placetype":"LocalAdmin",
    "wof:name":"Majdan Kr\u00f3lewski",
    "wof:placetype":"localadmin",
    "wof:population":2671
},
  "geometry": {"coordinates":[21.74615,50.37935],"type":"Point"}
}