{
  "type": "Feature",
  "properties": {
    "gn:admin1_code":"76.0",
    "gn:admin2_code":"803.0",
    "gn:admin3_code":"80302.0",
    "gn:asciiname":"Szumiaca",
    "gn:country_code":"PL",
    "gn:dem":64,
    "gn:feature_class":"P",
    "gn:feature_code":"PPL",
    "gn:name":"Szumi\u0105ca",
    "gn:population":0,
    "gn:timezone":"Europe/Warsaw",
    "iso:country":"PL",
    "name:ceb_x_preferred":[
        "Szumi\u0105ca"
    ],
    "name:fra_x_preferred":[
        "Szumi\u0105ca"
    ],
    "name:pol_x_preferred":[
        "Szumi\u0105ca"
    ],
    "name:ukr_x_preferred":[
        "\u0428\u0443\u043c\u0439\u043e\u043d\u0446\u0430"
    ],
    "wof:name":"Szumiaca",
    "wof:placetype":"locality"
},
  "geometry": {"coordinates":[15.58851,52.35582],"type":"Point"}
}