{
  "type": "Feature",
  "properties": {
    "gn:population":2699,
    "iso:country":"PL",
    "name:ast_x_preferred":[
        "Iwkowa"
    ],
    "name:azb_x_preferred":[
        "\u0627\u06cc\u0648\u06a9\u0648\u0648\u0627"
    ],
    "name:ceb_x_preferred":[
        "Iwkowa"
    ],
    "name:deu_x_preferred":[
        "Iwkowa"
    ],
    "name:eng_x_preferred":[
        "Iwkowa"
    ],
    "name:fas_x_preferred":[
        "\u0627\u06cc\u0648\u06a9\u0648\u0648\u0627"
    ],
    "name:fra_x_preferred":[
        "Iwkowa"
    ],
    "name:nan_x_preferred":[
        "Iwkowa"
    ],
    "name:nld_x_preferred":[
        "Iwkowa"
    ],
    "name:pol_x_preferred":[
        "Iwkowa"
    ],
    "name:rus_x_preferred":[
        "\u0418\u0432\u043a\u043e\u0432\u0430"
    ],
    "name:swe_x_preferred":[
        "Iwkowa"
    ],
    "name:ukr_x_preferred":[
        "\u0406\u0432\u043a\u043e\u0432\u0430"
    ],
    "name:zho_min_nan_x_preferred":[
        "Iwkowa"
    ],
    "qs:a0":"Rzeczpospolita Polska",
    "qs:a1":"*Malopolskie",
    "qs:a1r":"0",
    "qs:a2":"Brzeski",
    "qs:adm0":"Rzeczpospolita Polska",
    "qs:la_lc":"*",
    "qs:level":"locality",
    "qs:loc":"Iwkowa",
    "qs:loc_alt":"Iwkowa",
    "qs:pop":0,
    "qs:type":"buffered point",
    "wd:wordcount":164,
    "wof:name":"Iwkowa",
    "wof:placetype":"locality",
    "wof:population":2699
},
  "geometry": {"coordinates":[20.585528,49.81939],"type":"Point"}
}