{
  "type": "Feature",
  "properties": {
    "gn:admin1_code":"81.0",
    "gn:admin2_code":"2013.0",
    "gn:admin3_code":"201309.0",
    "gn:asciiname":"Dabrowa Moczydly",
    "gn:country_code":"PL",
    "gn:dem":147,
    "gn:feature_class":"P",
    "gn:feature_code":"PPL",
    "gn:name":"D\u0105browa Moczyd\u0142y",
    "gn:population":0,
    "gn:timezone":"Europe/Warsaw",
    "iso:country":"PL",
    "name:lit_x_preferred":[
        "Dombrova Mo\u010didlai"
    ],
    "name:pol_x_preferred":[
        "D\u0105browa-Moczyd\u0142y"
    ],
    "name:ukr_x_preferred":[
        "\u0414\u043e\u043c\u0431\u0440\u043e\u0432\u0430-\u041c\u043e\u0447\u0438\u0434\u043b\u0438"
    ],
    "wof:name":"Dabrowa Moczydly",
    "wof:placetype":"locality"
},
  "geometry": {"coordinates":[22.50103,52.84068000000001],"type":"Point"}
}