{
  "type": "Feature",
  "properties": {
    "gn:admin1_code":"82.0",
    "gn:admin2_code":"2212.0",
    "gn:admin3_code":"221206.0",
    "gn:asciiname":"Bzowo",
    "gn:country_code":"PL",
    "gn:dem":46,
    "gn:feature_class":"P",
    "gn:feature_code":"PPL",
    "gn:name":"Bzowo",
    "gn:population":0,
    "gn:timezone":"Europe/Warsaw",
    "iso:country":"PL",
    "name:deu_x_preferred":[
        "Bzowo"
    ],
    "name:pol_x_preferred":[
        "Bzowo"
    ],
    "name:ukr_x_preferred":[
        "\u0411\u0437\u043e\u0432\u043e"
    ],
    "wof:name":"Bzowo",
    "wof:placetype":"locality"
},
  "geometry": {"coordinates":[16.84265,54.36293000000001],"type":"Point"}
}