{
  "type": "Feature",
  "properties": {
    "gn:gn_country":"PL",
    "gn:gn_fcode":"PPL",
    "gn:gn_pop":400,
    "gn:population":400,
    "iso:country":"PL",
    "name:dut_x_preferred":[
        "Dziwn\u00f3wek"
    ],
    "name:eng_x_preferred":[
        "Dziwn\u00f3wek"
    ],
    "name:fre_x_preferred":[
        "Dziwn\u00f3wek"
    ],
    "name:ger_x_preferred":[
        "Dziwn\u00f3wek"
    ],
    "name:nan_x_preferred":[
        "Dziwn\u00f3wek"
    ],
    "name:per_x_preferred":[
        "\u062c\u0648\u0646\u0648\u0648\u06a9"
    ],
    "name:pol_x_preferred":[
        "Dziwn\u00f3wek"
    ],
    "name:unk_x_variant":[
        "Klein Dievenow"
    ],
    "qs_pg:aaroncc":"PL",
    "qs_pg:gn_country":"PL",
    "qs_pg:gn_fcode":"PPL",
    "qs_pg:gn_pop":400,
    "qs_pg:name":"Dziwn\u00f3wek",
    "qs_pg:name_adm0":"Polska",
    "qs_pg:name_adm1":"Zachodniopomorskie",
    "qs_pg:photos":75,
    "qs_pg:photos_1k":15,
    "qs_pg:photos_9k":1,
    "qs_pg:photos_9r":2,
    "qs_pg:photos_all":75,
    "qs_pg:photos_sr":2,
    "qs_pg:pop_sr":2,
    "qs_pg:qs_pg_placetype":"locality",
    "qs_pg:qs_pg_placetype_gp":"Town",
    "qs_pg:woe_adm0":23424923,
    "woe:adm0_id":23424923,
    "woe:name_adm0":"Polska",
    "woe:name_adm1":"Zachodniopomorskie",
    "woe:placetype":"Town",
    "wof:name":"Dziwn\u00f3wek",
    "wof:placetype":"locality",
    "wof:population":400
},
  "geometry": {"coordinates":[14.80545,54.0348],"type":"Point"}
}