{
  "type": "Feature",
  "properties": {
    "gn:admin1_code":"79.0",
    "gn:admin2_code":"1602.0",
    "gn:admin3_code":"160203.0",
    "gn:asciiname":"Chrostno",
    "gn:country_code":"PL",
    "gn:dem":389,
    "gn:feature_class":"P",
    "gn:feature_code":"PPL",
    "gn:name":"Chr\u00f3stno",
    "gn:population":0,
    "gn:timezone":"Europe/Warsaw",
    "iso:country":"PL",
    "name:ces_x_preferred":[
        "Chr\u00f3stno"
    ],
    "name:pol_x_preferred":[
        "Chr\u00f3stno"
    ],
    "name:ukr_x_preferred":[
        "\u0425\u0440\u0443\u0441\u0442\u043d\u043e"
    ],
    "wof:name":"Chrostno",
    "wof:placetype":"locality"
},
  "geometry": {"coordinates":[17.74343,50.12014],"type":"Point"}
}