{
  "type": "Feature",
  "properties": {
    "gn:admin1_code":"86.0",
    "gn:admin2_code":"3021.0",
    "gn:admin3_code":"302114.0",
    "gn:asciiname":"Modrze",
    "gn:country_code":"PL",
    "gn:dem":72,
    "gn:feature_class":"P",
    "gn:feature_code":"PPL",
    "gn:name":"Modrze",
    "gn:population":0,
    "gn:timezone":"Europe/Warsaw",
    "iso:country":"PL",
    "name:ceb_x_preferred":[
        "Modrze"
    ],
    "name:fra_x_preferred":[
        "Modrze"
    ],
    "name:pol_x_preferred":[
        "Modrze"
    ],
    "name:ukr_x_preferred":[
        "\u041c\u043e\u0434\u0436\u0435"
    ],
    "wof:name":"Modrze",
    "wof:placetype":"locality"
},
  "geometry": {"coordinates":[16.63295,52.21448],"type":"Point"}
}