{
  "type": "Feature",
  "properties": {
    "gn:admin1_code":"80.0",
    "gn:admin2_code":"1817.0",
    "gn:admin3_code":"181704.0",
    "gn:asciiname":"Czystohorb",
    "gn:country_code":"PL",
    "gn:dem":539,
    "gn:feature_class":"P",
    "gn:feature_code":"PPL",
    "gn:name":"Czystohorb",
    "gn:population":0,
    "gn:timezone":"Europe/Warsaw",
    "iso:country":"PL",
    "wof:name":"Czystohorb",
    "wof:placetype":"locality"
},
  "geometry": {"coordinates":[22.02192,49.36035],"type":"Point"}
}