{
  "type": "Feature",
  "properties": {
    "gn:admin1_code":"84.0",
    "gn:asciiname":"Parcela II",
    "gn:country_code":"PL",
    "gn:dem":315,
    "gn:elevation":"318.0",
    "gn:feature_class":"P",
    "gn:feature_code":"PPL",
    "gn:name":"Parcela II",
    "gn:population":0,
    "gn:timezone":"Europe/Warsaw",
    "iso:country":"PL",
    "wof:name":"Parcela II",
    "wof:placetype":"locality"
},
  "geometry": {"coordinates":[20.0216,50.32472],"type":"Point"}
}