{
  "type": "Feature",
  "properties": {
    "gn:admin1_code":"85.0",
    "gn:admin2_code":"2814.0",
    "gn:admin3_code":"281401.0",
    "gn:asciiname":"Odryty",
    "gn:country_code":"PL",
    "gn:dem":136,
    "gn:feature_class":"P",
    "gn:feature_code":"PPL",
    "gn:name":"Odryty",
    "gn:population":0,
    "gn:timezone":"Europe/Warsaw",
    "iso:country":"PL",
    "name:ceb_x_preferred":[
        "Odryty"
    ],
    "name:pol_x_preferred":[
        "Odryty"
    ],
    "name:und_x_variant":[
        "Odritten"
    ],
    "name:vie_x_preferred":[
        "Odryty"
    ],
    "wof:name":"Odryty",
    "wof:placetype":"locality"
},
  "geometry": {"coordinates":[20.77078,53.77459],"type":"Point"}
}