{
  "type": "Feature",
  "properties": {
    "iso:country":"PL",
    "name:ast_x_preferred":[
        "Ocieka"
    ],
    "name:ceb_x_preferred":[
        "Ocieka"
    ],
    "name:eng_x_preferred":[
        "Ocieka"
    ],
    "name:fra_x_preferred":[
        "Ocieka"
    ],
    "name:pol_x_preferred":[
        "Ocieka"
    ],
    "name:ukr_x_preferred":[
        "\u041e\u0446\u0435\u043a\u0430"
    ],
    "qs:a0":"Rzeczpospolita Polska",
    "qs:a1":"*Podkarpackie",
    "qs:a1r":"0",
    "qs:a2":"Ropczycko-sedziszowski",
    "qs:adm0":"Rzeczpospolita Polska",
    "qs:la_lc":"*",
    "qs:level":"locality",
    "qs:loc":"Ocieka",
    "qs:loc_alt":"Ocieka",
    "qs:pop":0,
    "qs:type":"buffered point",
    "wd:wordcount":734,
    "wof:name":"Ocieka",
    "wof:placetype":"locality"
},
  "geometry": {"coordinates":[21.591629,50.139344],"type":"Point"}
}