{
  "type": "Feature",
  "properties": {
    "gn:admin1_code":"78.0",
    "gn:admin2_code":"1428.0",
    "gn:admin3_code":"142808.0",
    "gn:asciiname":"Mikolajew",
    "gn:country_code":"PL",
    "gn:dem":84,
    "gn:feature_class":"P",
    "gn:feature_code":"PPL",
    "gn:name":"Miko\u0142ajew",
    "gn:population":0,
    "gn:timezone":"Europe/Warsaw",
    "iso:country":"PL",
    "name:ara_x_preferred":[
        "\u0645\u064a\u0643\u0648\u0641\u0627\u064a\u064a\u0641"
    ],
    "name:fra_x_preferred":[
        "Miko\u0142ajew"
    ],
    "name:pol_x_preferred":[
        "Miko\u0142ajew"
    ],
    "name:ukr_x_preferred":[
        "\u041c\u0456\u043a\u043e\u043b\u0430\u0454\u0432"
    ],
    "wof:name":"Mikolajew",
    "wof:placetype":"locality"
},
  "geometry": {"coordinates":[20.32119,52.17609],"type":"Point"}
}