{
  "type": "Feature",
  "properties": {
    "gn:admin1_code":"78.0",
    "gn:admin2_code":"1428.0",
    "gn:admin3_code":"142808.0",
    "gn:asciiname":"Mikolajew",
    "gn:country_code":"PL",
    "gn:dem":84,
    "gn:feature_class":"P",
    "gn:feature_code":"PPL",
    "gn:name":"Miko\u0142ajew",
    "gn:population":0,
    "gn:timezone":"Europe/Warsaw",
    "iso:country":"PL",
    "wof:name":"Mikolajew",
    "wof:placetype":"locality"
},
  "geometry": {"coordinates":[20.32119,52.17609],"type":"Point"}
}