{
  "type": "Feature",
  "properties": {
    "gn:population":1500,
    "iso:country":"PL",
    "name:ast_x_preferred":[
        "Handzl\u00f3wka"
    ],
    "name:ceb_x_preferred":[
        "Handzl\u00f3wka"
    ],
    "name:deu_x_preferred":[
        "Handzl\u00f3wka"
    ],
    "name:eng_x_preferred":[
        "Handzl\u00f3wka"
    ],
    "name:fra_x_preferred":[
        "Handzl\u00f3wka"
    ],
    "name:nan_x_preferred":[
        "Handzl\u00f3wka"
    ],
    "name:pol_x_preferred":[
        "Handzl\u00f3wka"
    ],
    "name:ukr_x_preferred":[
        "\u0413\u0430\u043d\u0434\u0437\u043b\u044e\u0432\u043a\u0430"
    ],
    "name:zho_min_nan_x_preferred":[
        "Handzl\u00f3wka"
    ],
    "qs:a0":"Rzeczpospolita Polska",
    "qs:a1":"*Podkarpackie",
    "qs:a1r":"0",
    "qs:a2":"Lancucki",
    "qs:adm0":"Rzeczpospolita Polska",
    "qs:la_lc":"*",
    "qs:level":"locality",
    "qs:loc":"Handzl\u00f3wka",
    "qs:loc_alt":"Handzlowka",
    "qs:pop":0,
    "qs:type":"buffered point",
    "wd:wordcount":87,
    "wof:name":"Handzl\u00f3wka",
    "wof:placetype":"locality",
    "wof:population":1500
},
  "geometry": {"coordinates":[22.224056,49.989296],"type":"Point"}
}