{
  "type": "Feature",
  "properties": {
    "gn:admin1_code":"73.0",
    "gn:admin2_code":"407.0",
    "gn:admin3_code":"40706.0",
    "gn:asciiname":"Wroble",
    "gn:country_code":"PL",
    "gn:dem":81,
    "gn:feature_class":"P",
    "gn:feature_code":"PPL",
    "gn:name":"Wr\u00f3ble",
    "gn:population":0,
    "gn:timezone":"Europe/Warsaw",
    "iso:country":"PL",
    "wof:name":"Wroble",
    "wof:placetype":"locality"
},
  "geometry": {"coordinates":[18.39565,52.69415],"type":"Point"}
}