{
  "type": "Feature",
  "properties": {
    "gn:admin1_code":"78.0",
    "gn:admin2_code":"1432.0",
    "gn:admin3_code":"143201.0",
    "gn:asciiname":"Stare Faszczyce",
    "gn:country_code":"PL",
    "gn:dem":89,
    "gn:feature_class":"P",
    "gn:feature_code":"PPL",
    "gn:name":"Stare Faszczyce",
    "gn:population":0,
    "gn:timezone":"Europe/Warsaw",
    "iso:country":"PL",
    "name:fra_x_preferred":[
        "Stare Faszczyce"
    ],
    "name:pol_x_preferred":[
        "Stare Faszczyce"
    ],
    "name:ukr_x_preferred":[
        "\u0421\u0442\u0430\u0440\u0435 \u0424\u0430\u0449\u0438\u0446\u0435"
    ],
    "wof:name":"Stare Faszczyce",
    "wof:placetype":"locality"
},
  "geometry": {"coordinates":[20.59138,52.1793],"type":"Point"}
}