{
  "type": "Feature",
  "properties": {
    "gn:country":"PL",
    "gn:fcode":"PPL",
    "gn:population":1300,
    "iso:country":"PL",
    "name:azb_x_preferred":[
        "\u0648\u06cc\u0632\u0646\u0627"
    ],
    "name:ceb_x_preferred":[
        "Wizna"
    ],
    "name:eng_x_preferred":[
        "Wizna"
    ],
    "name:fas_x_preferred":[
        "\u0648\u06cc\u0632\u0646\u0627"
    ],
    "name:heb_x_preferred":[
        "\u05d5\u05d9\u05d6\u05e0\u05d4"
    ],
    "name:lit_x_preferred":[
        "Vizna"
    ],
    "name:nld_x_preferred":[
        "Wizna"
    ],
    "name:pol_x_preferred":[
        "Wizna"
    ],
    "name:por_x_preferred":[
        "Wizna"
    ],
    "name:rus_x_preferred":[
        "\u0412\u0438\u0437\u043d\u0430"
    ],
    "name:swe_x_preferred":[
        "Wizna"
    ],
    "name:ukr_x_preferred":[
        "\u0412\u0456\u0437\u043d\u0430"
    ],
    "qs_pg:aaroncc":"PL",
    "qs_pg:gn_country":"PL",
    "qs_pg:gn_fcode":"PPL",
    "qs_pg:gn_pop":1300,
    "qs_pg:name":"Wizna",
    "qs_pg:name_adm0":"Polska",
    "qs_pg:name_adm1":"Podlaskie",
    "qs_pg:photos_9k":1,
    "qs_pg:photos_9r":1,
    "qs_pg:photos_all":5,
    "qs_pg:photos_sr":0,
    "qs_pg:pop_sr":3,
    "qs_pg:qs_pg_placetype":"locality",
    "qs_pg:qs_pg_placetype_gp":"Town",
    "qs_pg:woe_adm0":23424923,
    "woe:adm0_id":23424923,
    "woe:name_adm0":"Polska",
    "woe:name_adm1":"Podlaskie",
    "woe:placetype":"Town",
    "wof:name":"Wizna",
    "wof:placetype":"locality",
    "wof:population":1300
},
  "geometry": {"coordinates":[22.38241,53.19518],"type":"Point"}
}