{
  "type": "Feature",
  "properties": {
    "gn:admin1_code":"87.0",
    "gn:admin2_code":"3207.0",
    "gn:admin3_code":"320701.0",
    "gn:asciiname":"Dziwna",
    "gn:cc2":"PL",
    "gn:country_code":"PL",
    "gn:dem":4,
    "gn:feature_class":"P",
    "gn:feature_code":"PPL",
    "gn:name":"Dziwna",
    "gn:population":0,
    "gn:timezone":"Europe/Warsaw",
    "iso:country":"PL",
    "name:aze_x_preferred":[
        "Dzivna bo\u011faz\u0131"
    ],
    "name:bel_x_preferred":[
        "\u0414\u0437\u0456\u045e\u043d\u0430"
    ],
    "name:ceb_x_preferred":[
        "Dziwna"
    ],
    "name:ces_x_preferred":[
        "Dziwna"
    ],
    "name:deu_x_preferred":[
        "Dziwna"
    ],
    "name:fra_x_preferred":[
        "Dziwna"
    ],
    "name:ita_x_preferred":[
        "Dziwna"
    ],
    "name:kor_x_preferred":[
        "\uc9c0\ube0c\ub098 \ud574\ud611"
    ],
    "name:nld_x_preferred":[
        "Dziwna"
    ],
    "name:nno_x_preferred":[
        "Dziwna"
    ],
    "name:nor_x_preferred":[
        "Dziwna"
    ],
    "name:pol_x_preferred":[
        "Dziwna"
    ],
    "name:por_x_preferred":[
        "Rio Dziwna"
    ],
    "name:rus_x_preferred":[
        "\u0414\u0437\u0438\u0432\u043d\u0430"
    ],
    "name:spa_x_preferred":[
        "Dziwna"
    ],
    "name:swe_x_preferred":[
        "Dziwna"
    ],
    "name:ukr_x_preferred":[
        "\u0414\u0437\u0456\u0432\u043d\u0430"
    ],
    "name:und_x_variant":[
        "West Dievenow",
        "Dievenow",
        "Dziwna"
    ],
    "name:vie_x_preferred":[
        "Dziwna"
    ],
    "wof:name":"Dziwna",
    "wof:placetype":"locality"
},
  "geometry": {"coordinates":[14.73739,54.01665],"type":"Point"}
}