{
  "type": "Feature",
  "properties": {
    "gn:admin1_code":"87.0",
    "gn:admin2_code":"3207.0",
    "gn:admin3_code":"320701.0",
    "gn:asciiname":"Dziwna",
    "gn:cc2":"PL",
    "gn:country_code":"PL",
    "gn:dem":4,
    "gn:feature_class":"P",
    "gn:feature_code":"PPL",
    "gn:name":"Dziwna",
    "gn:population":0,
    "gn:timezone":"Europe/Warsaw",
    "iso:country":"PL",
    "name:und_x_variant":[
        "West Dievenow",
        "Dievenow",
        "Dziwna"
    ],
    "wof:name":"Dziwna",
    "wof:placetype":"locality"
},
  "geometry": {"coordinates":[14.73739,54.01665],"type":"Point"}
}