{
  "type": "Feature",
  "properties": {
    "gn:admin1_code":"83.0",
    "gn:admin2_code":"2411.0",
    "gn:admin3_code":"241108.0",
    "gn:asciiname":"Gamow",
    "gn:country_code":"PL",
    "gn:dem":253,
    "gn:feature_class":"P",
    "gn:feature_code":"PPL",
    "gn:name":"Gam\u00f3w",
    "gn:population":0,
    "gn:timezone":"Europe/Warsaw",
    "iso:country":"PL",
    "name:azb_x_preferred":[
        "\u0642\u0627\u0645\u0648\u0648"
    ],
    "name:ceb_x_preferred":[
        "Gam\u00f3w"
    ],
    "name:deu_x_preferred":[
        "Gam\u00f3w"
    ],
    "name:fas_x_preferred":[
        "\u06af\u0627\u0645\u0648\u0648"
    ],
    "name:nld_x_preferred":[
        "Gam\u00f3w"
    ],
    "name:pol_x_preferred":[
        "Gam\u00f3w"
    ],
    "name:ukr_x_preferred":[
        "\u0490\u0430\u043c\u0443\u0432"
    ],
    "name:und_x_variant":[
        "Gam\u00f3w"
    ],
    "wof:name":"Gamow",
    "wof:placetype":"locality"
},
  "geometry": {"coordinates":[18.12796,50.13629],"type":"Point"}
}