{
  "type": "Feature",
  "properties": {
    "gn:admin1_code":"87.0",
    "gn:admin2_code":"3209.0",
    "gn:admin3_code":"320904.0",
    "gn:asciiname":"Grzybniczka",
    "gn:country_code":"PL",
    "gn:dem":95,
    "gn:feature_class":"P",
    "gn:feature_code":"PPL",
    "gn:name":"Grzybniczka",
    "gn:population":0,
    "gn:timezone":"Europe/Warsaw",
    "iso:country":"PL",
    "name:pol_x_preferred":[
        "Grzybniczka"
    ],
    "name:vie_x_preferred":[
        "Grzybniczka"
    ],
    "wof:name":"Grzybniczka",
    "wof:placetype":"locality"
},
  "geometry": {"coordinates":[16.41784,54.05378],"type":"Point"}
}