{
  "type": "Feature",
  "properties": {
    "gn:admin1_code":"72.0",
    "gn:admin2_code":"226.0",
    "gn:admin3_code":"22606.0",
    "gn:asciiname":"Kwiatow",
    "gn:country_code":"PL",
    "gn:dem":164,
    "gn:feature_class":"P",
    "gn:feature_code":"PPL",
    "gn:name":"Kwiat\u00f3w",
    "gn:population":0,
    "gn:timezone":"Europe/Warsaw",
    "iso:country":"PL",
    "name:deu_x_historical":[
        "Blumen"
    ],
    "name:deu_x_preferred":[
        "Blumen"
    ],
    "wof:name":"Kwiatow",
    "wof:placetype":"locality"
},
  "geometry": {"coordinates":[16.00219,51.2093],"type":"Point"}
}