{
  "type": "Feature",
  "properties": {
    "gn:admin1_code":"81.0",
    "gn:admin2_code":"2011.0",
    "gn:admin3_code":"201101.0",
    "gn:asciiname":"Kropiwna",
    "gn:country_code":"PL",
    "gn:dem":127,
    "gn:feature_class":"P",
    "gn:feature_code":"PPL",
    "gn:name":"Kropiwna",
    "gn:population":0,
    "gn:timezone":"Europe/Warsaw",
    "iso:country":"PL",
    "name:und_x_variant":[
        "Kropiwno",
        "Kropiwna"
    ],
    "wof:name":"Kropiwna",
    "wof:placetype":"locality"
},
  "geometry": {"coordinates":[23.37991,53.69497],"type":"Point"}
}