{
  "type": "Feature",
  "properties": {
    "gn:admin1_code":"81.0",
    "gn:admin2_code":"2011.0",
    "gn:admin3_code":"201101.0",
    "gn:asciiname":"Kropiwna",
    "gn:country_code":"PL",
    "gn:dem":127,
    "gn:feature_class":"P",
    "gn:feature_code":"PPL",
    "gn:name":"Kropiwna",
    "gn:population":0,
    "gn:timezone":"Europe/Warsaw",
    "iso:country":"PL",
    "name:azb_x_preferred":[
        "\u06a9\u0631\u0648\u067e\u06cc\u0648\u0646\u0648"
    ],
    "name:fas_x_preferred":[
        "\u06a9\u0631\u0648\u067e\u06cc\u0648\u0646\u0648"
    ],
    "name:fra_x_preferred":[
        "Kropiwno"
    ],
    "name:lit_x_preferred":[
        "Kropivnas"
    ],
    "name:pol_x_preferred":[
        "Kropiwno"
    ],
    "name:ukr_x_preferred":[
        "\u041a\u0440\u043e\u043f\u0456\u0432\u043d\u043e"
    ],
    "name:und_x_variant":[
        "Kropiwno",
        "Kropiwna"
    ],
    "wof:name":"Kropiwna",
    "wof:placetype":"locality"
},
  "geometry": {"coordinates":[23.37991,53.69497],"type":"Point"}
}