{
  "type": "Feature",
  "properties": {
    "gn:admin1_code":"75.0",
    "gn:admin2_code":"605.0",
    "gn:admin3_code":"60501.0",
    "gn:asciiname":"Weglinek",
    "gn:country_code":"PL",
    "gn:dem":285,
    "gn:feature_class":"P",
    "gn:feature_code":"PPL",
    "gn:name":"W\u0119glinek",
    "gn:population":0,
    "gn:timezone":"Europe/Warsaw",
    "iso:country":"PL",
    "name:fra_x_preferred":[
        "W\u0119glinek"
    ],
    "name:pol_x_preferred":[
        "W\u0119glinek"
    ],
    "name:ukr_x_preferred":[
        "\u0412\u0435\u043d\u0491\u043b\u0456\u043d\u0435\u043a"
    ],
    "wof:name":"Weglinek",
    "wof:placetype":"locality"
},
  "geometry": {"coordinates":[22.44438,50.87737],"type":"Point"}
}