{
  "type": "Feature",
  "properties": {
    "gn:admin1_code":"81.0",
    "gn:admin2_code":"2011.0",
    "gn:admin3_code":"201107.0",
    "gn:asciiname":"Chwaszczewo",
    "gn:country_code":"PL",
    "gn:dem":181,
    "gn:feature_class":"P",
    "gn:feature_code":"PPL",
    "gn:name":"Chwaszczewo",
    "gn:population":0,
    "gn:timezone":"Europe/Warsaw",
    "iso:country":"PL",
    "wof:name":"Chwaszczewo",
    "wof:placetype":"locality"
},
  "geometry": {"coordinates":[23.34719,53.49209000000001],"type":"Point"}
}