{
  "type": "Feature",
  "properties": {
    "gn:admin1_code":"81.0",
    "gn:admin2_code":"2011.0",
    "gn:admin3_code":"201107.0",
    "gn:asciiname":"Chwaszczewo",
    "gn:country_code":"PL",
    "gn:dem":181,
    "gn:feature_class":"P",
    "gn:feature_code":"PPL",
    "gn:name":"Chwaszczewo",
    "gn:population":0,
    "gn:timezone":"Europe/Warsaw",
    "iso:country":"PL",
    "name:azb_x_preferred":[
        "\u062e\u0648\u0627\u0634\u0686\u0648\u0648"
    ],
    "name:fas_x_preferred":[
        "\u062e\u0648\u0627\u0634\u0686\u0648\u0648"
    ],
    "name:fra_x_preferred":[
        "Chwaszczewo"
    ],
    "name:lit_x_preferred":[
        "Chva\u0161\u010devas"
    ],
    "name:pol_x_preferred":[
        "Chwaszczewo"
    ],
    "name:ukr_x_preferred":[
        "\u0425\u0432\u0430\u0449\u0435\u0432\u043e"
    ],
    "wof:name":"Chwaszczewo",
    "wof:placetype":"locality"
},
  "geometry": {"coordinates":[23.34719,53.49209000000001],"type":"Point"}
}