{
  "type": "Feature",
  "properties": {
    "gn:country":"PL",
    "gn:fcode":"PPLA3",
    "gn:population":1100,
    "iso:country":"PL",
    "name:eng_x_preferred":[
        "Gmina Wodzis\u0142aw"
    ],
    "name:por_x_preferred":[
        "Comuna de Wodzis\u0142aw"
    ],
    "name:rus_x_preferred":[
        "\u0412\u043e\u0434\u0437\u0438\u0441\u043b\u0430\u0432"
    ],
    "name:slk_x_preferred":[
        "Gmina Wodzis\u0142aw"
    ],
    "name:ukr_x_preferred":[
        "\u0490\u043c\u0456\u043d\u0430 \u0412\u043e\u0434\u0437\u0456\u0441\u043b\u0430\u0432"
    ],
    "name:war_x_preferred":[
        "Gmina Wodzis\u0142aw"
    ],
    "qs_pg:aaroncc":"PL",
    "qs_pg:gn_country":"PL",
    "qs_pg:gn_fcode":"PPLA3",
    "qs_pg:gn_pop":1100,
    "qs_pg:name":"Wodzis\u0142aw",
    "qs_pg:name_adm0":"Polska",
    "qs_pg:name_adm1":"Swi\u0119tokrzyskie",
    "qs_pg:photos_9k":1,
    "qs_pg:photos_9r":1,
    "qs_pg:photos_all":3,
    "qs_pg:photos_sr":0,
    "qs_pg:pop_sr":3,
    "qs_pg:qs_pg_placetype":"localadmin",
    "qs_pg:qs_pg_placetype_gp":"LocalAdmin",
    "qs_pg:woe_adm0":23424923,
    "woe:adm0_id":23424923,
    "woe:name_adm0":"Polska",
    "woe:name_adm1":"Swi\u0119tokrzyskie",
    "woe:placetype":"LocalAdmin",
    "wof:name":"Wodzis\u0142aw",
    "wof:placetype":"localadmin",
    "wof:population":1100
},
  "geometry": {"coordinates":[20.1915,50.52047],"type":"Point"}
}