{
  "type": "Feature",
  "properties": {
    "gn:admin1_code":"85.0",
    "gn:admin2_code":"2814.0",
    "gn:admin3_code":"281405.0",
    "gn:asciiname":"Tomaryny",
    "gn:country_code":"PL",
    "gn:dem":109,
    "gn:feature_class":"P",
    "gn:feature_code":"PPL",
    "gn:name":"Tomaryny",
    "gn:population":0,
    "gn:timezone":"Europe/Warsaw",
    "iso:country":"PL",
    "name:pol_x_preferred":[
        "Tomaryny"
    ],
    "name:ukr_x_preferred":[
        "\u0422\u043e\u043c\u0430\u0440\u0438\u043d\u0438"
    ],
    "name:und_x_variant":[
        "Thomareinen"
    ],
    "wof:name":"Tomaryny",
    "wof:placetype":"locality"
},
  "geometry": {"coordinates":[20.21606,53.72646999999999],"type":"Point"}
}