{
  "type": "Feature",
  "properties": {
    "gn:country":"PL",
    "gn:fcode":"PPL",
    "gn:population":302,
    "iso:country":"PL",
    "name:fra_x_preferred":[
        "Marcinkowice"
    ],
    "name:pol_x_preferred":[
        "Marcinkowice"
    ],
    "name:ukr_x_preferred":[
        "\u041c\u0430\u0440\u0446\u0438\u043d\u043a\u043e\u0432\u0456\u0446\u0435"
    ],
    "qs_pg:aaroncc":"PL",
    "qs_pg:gn_country":"PL",
    "qs_pg:gn_fcode":"PPL",
    "qs_pg:gn_pop":302,
    "qs_pg:name":"Marcinkowice",
    "qs_pg:name_adm0":"Polska",
    "qs_pg:name_adm1":"Ma\u0142opolskie",
    "qs_pg:photos_9r":0,
    "qs_pg:photos_sr":0,
    "qs_pg:pop_sr":2,
    "qs_pg:qs_pg_placetype":"locality",
    "qs_pg:qs_pg_placetype_gp":"Town",
    "qs_pg:woe_adm0":23424923,
    "woe:adm0_id":23424923,
    "woe:name_adm0":"Polska",
    "woe:name_adm1":"Ma\u0142opolskie",
    "woe:placetype":"Town",
    "wof:name":"Marcinkowice",
    "wof:placetype":"locality",
    "wof:population":302
},
  "geometry": {"coordinates":[20.82167,50.14743],"type":"Point"}
}