{
  "type": "Feature",
  "properties": {
    "gn:admin1_code":"73.0",
    "gn:admin2_code":"411.0",
    "gn:admin3_code":"41105.0",
    "gn:asciiname":"Polajewek",
    "gn:cc2":"PL",
    "gn:country_code":"PL",
    "gn:dem":81,
    "gn:feature_class":"P",
    "gn:feature_code":"PPL",
    "gn:name":"Po\u0142ajewek",
    "gn:population":0,
    "gn:timezone":"Europe/Warsaw",
    "iso:country":"PL",
    "name:pol_x_preferred":[
        "Po\u0142ajewek"
    ],
    "name:ukr_x_preferred":[
        "\u041f\u043e\u043b\u0430\u0454\u0432\u0435\u043a"
    ],
    "name:und_x_variant":[
        "Potj\u00e9wek"
    ],
    "wof:name":"Polajewek",
    "wof:placetype":"locality"
},
  "geometry": {"coordinates":[18.39146,52.53356],"type":"Point"}
}