{
  "type": "Feature",
  "properties": {
    "gn:admin1_code":"74.0",
    "gn:admin2_code":"1007.0",
    "gn:admin3_code":"100707.0",
    "gn:asciiname":"Gawrony",
    "gn:country_code":"PL",
    "gn:dem":199,
    "gn:feature_class":"P",
    "gn:feature_code":"PPL",
    "gn:name":"Gawrony",
    "gn:population":0,
    "gn:timezone":"Europe/Warsaw",
    "iso:country":"PL",
    "name:fra_x_preferred":[
        "Gawrony"
    ],
    "name:pol_x_preferred":[
        "Gawrony"
    ],
    "name:ukr_x_preferred":[
        "\u0490\u0430\u0432\u0440\u043e\u043d\u0438"
    ],
    "wof:name":"Gawrony",
    "wof:placetype":"locality"
},
  "geometry": {"coordinates":[20.19759,51.39728],"type":"Point"}
}