{
  "type": "Feature",
  "properties": {
    "gn:admin1_code":"86.0",
    "gn:admin2_code":"3003.0",
    "gn:admin3_code":"300309.0",
    "gn:asciiname":"Miaty",
    "gn:country_code":"PL",
    "gn:dem":115,
    "gn:feature_class":"P",
    "gn:feature_code":"PPL",
    "gn:name":"Miaty",
    "gn:population":0,
    "gn:timezone":"Europe/Warsaw",
    "iso:country":"PL",
    "name:azb_x_preferred":[
        "\u0645\u06cc\u0627\u062a\u0647"
    ],
    "name:fas_x_preferred":[
        "\u0645\u06cc\u0627\u062a\u0647"
    ],
    "name:fra_x_preferred":[
        "Miaty"
    ],
    "name:nld_x_preferred":[
        "Miaty"
    ],
    "name:pol_x_preferred":[
        "Miaty"
    ],
    "name:ukr_x_preferred":[
        "\u041c\u044f\u0442\u0438"
    ],
    "wof:name":"Miaty",
    "wof:placetype":"locality"
},
  "geometry": {"coordinates":[17.79969,52.53426],"type":"Point"}
}