{
  "type": "Feature",
  "properties": {
    "gn:admin1_code":"85.0",
    "gn:admin2_code":"2811.0",
    "gn:admin3_code":"281103.0",
    "gn:asciiname":"Dziurdziewo",
    "gn:country_code":"PL",
    "gn:dem":182,
    "gn:feature_class":"P",
    "gn:feature_code":"PPL",
    "gn:name":"Dziurdziewo",
    "gn:population":0,
    "gn:timezone":"Europe/Warsaw",
    "iso:country":"PL",
    "name:und_x_variant":[
        "Thalheim",
        "Dziurdzi\u00f3w",
        "Dziurdziau",
        "Dziurdziewo"
    ],
    "wof:name":"Dziurdziewo",
    "wof:placetype":"locality"
},
  "geometry": {"coordinates":[20.21493,53.37433000000001],"type":"Point"}
}