{
  "type": "Feature",
  "properties": {
    "gn:admin1_code":"75.0",
    "gn:asciiname":"Horoszki Male",
    "gn:country_code":"PL",
    "gn:dem":166,
    "gn:feature_class":"P",
    "gn:feature_code":"PPL",
    "gn:name":"Horoszki Ma\u0142e",
    "gn:population":0,
    "gn:timezone":"Europe/Warsaw",
    "iso:country":"PL",
    "wof:name":"Horoszki Male",
    "wof:placetype":"locality"
},
  "geometry": {"coordinates":[23.03988,52.23884],"type":"Point"}
}