{
  "type": "Feature",
  "properties": {
    "gn:admin1_code":"75.0",
    "gn:asciiname":"Horoszki Male",
    "gn:country_code":"PL",
    "gn:dem":166,
    "gn:feature_class":"P",
    "gn:feature_code":"PPL",
    "gn:name":"Horoszki Ma\u0142e",
    "gn:population":0,
    "gn:timezone":"Europe/Warsaw",
    "iso:country":"PL",
    "name:azb_x_preferred":[
        "\u062e\u0648\u0631\u0648\u0634\u06a9\u06cc \u0645\u0627\u0648\u0647"
    ],
    "name:fas_x_preferred":[
        "\u062e\u0648\u0631\u0648\u0634\u06a9\u06cc \u0645\u0627\u0648\u0647"
    ],
    "name:fra_x_preferred":[
        "Horoszki Ma\u0142e"
    ],
    "name:lit_x_preferred":[
        "Horo\u0161ki Mal\u0117"
    ],
    "name:pol_x_preferred":[
        "Horoszki Ma\u0142e"
    ],
    "name:ukr_x_preferred":[
        "\u0413\u043e\u0440\u043e\u0448\u043a\u0456-\u041c\u0430\u043b\u0456"
    ],
    "wof:name":"Horoszki Male",
    "wof:placetype":"locality"
},
  "geometry": {"coordinates":[23.03988,52.23884],"type":"Point"}
}