{
  "type": "Feature",
  "properties": {
    "gn:country":"PL",
    "gn:fcode":"PPLA3",
    "gn:population":1262,
    "iso:country":"PL",
    "name:azb_x_preferred":[
        "\u0627\u0648\u0644\u062e\u0648\u0648\u06a9"
    ],
    "name:fas_x_preferred":[
        "\u0627\u0648\u0644\u062e\u0648\u0648\u06a9"
    ],
    "name:fra_x_preferred":[
        "Ulh\u00f3wek"
    ],
    "name:nld_x_preferred":[
        "Ulh\u00f3wek"
    ],
    "name:pol_x_preferred":[
        "Ulh\u00f3wek"
    ],
    "name:ukr_x_preferred":[
        "\u0423\u043b\u044c\u0433\u0456\u0432\u043e\u043a"
    ],
    "qs_pg:aaroncc":"PL",
    "qs_pg:gn_country":"PL",
    "qs_pg:gn_fcode":"PPLA3",
    "qs_pg:gn_pop":1262,
    "qs_pg:name":"Ulh\u00f3wek",
    "qs_pg:name_adm0":"Polska",
    "qs_pg:name_adm1":"Lubelskie",
    "qs_pg:photos_9k":1,
    "qs_pg:photos_9r":1,
    "qs_pg:photos_all":1,
    "qs_pg:photos_sr":0,
    "qs_pg:pop_sr":3,
    "qs_pg:qs_pg_placetype":"localadmin",
    "qs_pg:qs_pg_placetype_gp":"LocalAdmin",
    "qs_pg:woe_adm0":23424923,
    "woe:adm0_id":23424923,
    "woe:name_adm0":"Polska",
    "woe:name_adm1":"Lubelskie",
    "woe:placetype":"LocalAdmin",
    "wof:name":"Ulh\u00f3wek",
    "wof:placetype":"localadmin",
    "wof:population":1262
},
  "geometry": {"coordinates":[23.79956,50.44969],"type":"Point"}
}