{
  "type": "Feature",
  "properties": {
    "gn:admin1_code":"86.0",
    "gn:admin2_code":"3023.0",
    "gn:admin3_code":"302306.0",
    "gn:asciiname":"Meszna",
    "gn:country_code":"PL",
    "gn:dem":96,
    "gn:feature_class":"P",
    "gn:feature_code":"PPL",
    "gn:name":"Meszna",
    "gn:population":0,
    "gn:timezone":"Europe/Warsaw",
    "iso:country":"PL",
    "name:fra_x_preferred":[
        "Meszna"
    ],
    "name:pol_x_preferred":[
        "Meszna"
    ],
    "name:ukr_x_preferred":[
        "\u041c\u0435\u0448\u043d\u0430"
    ],
    "wof:name":"Meszna",
    "wof:placetype":"locality"
},
  "geometry": {"coordinates":[17.94714,52.32114],"type":"Point"}
}