{
  "type": "Feature",
  "properties": {
    "gn:admin1_code":"74.0",
    "gn:admin2_code":"1003.0",
    "gn:admin3_code":"100303.0",
    "gn:asciiname":"Siedlce",
    "gn:country_code":"PL",
    "gn:dem":165,
    "gn:feature_class":"P",
    "gn:feature_code":"PPL",
    "gn:name":"Siedlce",
    "gn:population":331,
    "gn:timezone":"Europe/Warsaw",
    "iso:country":"PL",
    "name:ceb_x_preferred":[
        "Siedlce"
    ],
    "name:fra_x_preferred":[
        "Siedlce"
    ],
    "name:pol_x_preferred":[
        "Siedlce"
    ],
    "name:ukr_x_preferred":[
        "\u0421\u0435\u0434\u043b\u044c\u0446\u0435"
    ],
    "wof:name":"Siedlce",
    "wof:placetype":"locality",
    "wof:population":331
},
  "geometry": {"coordinates":[19.02231,51.45829000000001],"type":"Point"}
}