{
  "type": "Feature",
  "properties": {
    "gn:admin1_code":"87.0",
    "gn:admin2_code":"3205.0",
    "gn:admin3_code":"320503.0",
    "gn:asciiname":"Skalno",
    "gn:cc2":"PL",
    "gn:country_code":"PL",
    "gn:dem":5,
    "gn:feature_class":"P",
    "gn:feature_code":"PPL",
    "gn:name":"Skalno",
    "gn:population":0,
    "gn:timezone":"Europe/Warsaw",
    "iso:country":"PL",
    "name:und_x_variant":[
        "Eiersberg",
        "Neu-Eiersberg",
        "Skalno"
    ],
    "wof:name":"Skalno",
    "wof:placetype":"locality"
},
  "geometry": {"coordinates":[15.10912,54.08175],"type":"Point"}
}