{
  "type": "Feature",
  "properties": {
    "gn:admin1_code":"86.0",
    "gn:admin2_code":"3005.0",
    "gn:admin3_code":"300503.0",
    "gn:asciiname":"Maksymilianowo",
    "gn:country_code":"PL",
    "gn:dem":69,
    "gn:feature_class":"P",
    "gn:feature_code":"PPL",
    "gn:name":"Maksymilianowo",
    "gn:population":0,
    "gn:timezone":"Europe/Warsaw",
    "iso:country":"PL",
    "name:und_x_variant":[
        "Maksymiljanowo",
        "Maksymilianowo"
    ],
    "wof:name":"Maksymilianowo",
    "wof:placetype":"locality"
},
  "geometry": {"coordinates":[16.55351,52.15493],"type":"Point"}
}