{
  "type": "Feature",
  "properties": {
    "gn:admin1_code":"86.0",
    "gn:admin2_code":"3005.0",
    "gn:admin3_code":"300503.0",
    "gn:asciiname":"Maksymilianowo",
    "gn:country_code":"PL",
    "gn:dem":69,
    "gn:feature_class":"P",
    "gn:feature_code":"PPL",
    "gn:name":"Maksymilianowo",
    "gn:population":0,
    "gn:timezone":"Europe/Warsaw",
    "iso:country":"PL",
    "name:ceb_x_preferred":[
        "Maksymilianowo"
    ],
    "name:fra_x_preferred":[
        "Maksymilianowo"
    ],
    "name:pol_x_preferred":[
        "Maksymilianowo"
    ],
    "name:ukr_x_preferred":[
        "\u041c\u0430\u043a\u0441\u0438\u043c\u0456\u043b\u044c\u044f\u043d\u043e\u0432\u043e"
    ],
    "name:und_x_variant":[
        "Maksymiljanowo"
    ],
    "wof:name":"Maksymilianowo",
    "wof:placetype":"locality"
},
  "geometry": {"coordinates":[16.55351,52.15493],"type":"Point"}
}