{
  "type": "Feature",
  "properties": {
    "gn:admin1_code":"78.0",
    "gn:admin2_code":"1411.0",
    "gn:admin3_code":"141106.0",
    "gn:asciiname":"Retka",
    "gn:cc2":"PL",
    "gn:country_code":"PL",
    "gn:dem":107,
    "gn:feature_class":"P",
    "gn:feature_code":"PPL",
    "gn:name":"Retka",
    "gn:population":0,
    "gn:timezone":"Europe/Warsaw",
    "iso:country":"PL",
    "name:fra_x_preferred":[
        "Retka"
    ],
    "name:pol_x_preferred":[
        "Retka"
    ],
    "name:ukr_x_preferred":[
        "\u0420\u0435\u0442\u043a\u0430"
    ],
    "name:und_x_variant":[
        "Retki"
    ],
    "wof:name":"Retka",
    "wof:placetype":"locality"
},
  "geometry": {"coordinates":[21.07083,52.93793],"type":"Point"}
}