{
  "type": "Feature",
  "properties": {
    "gn:admin1_code":"78.0",
    "gn:admin2_code":"1415.0",
    "gn:admin3_code":"141505.0",
    "gn:asciiname":"Siarcza Laka",
    "gn:country_code":"PL",
    "gn:dem":112,
    "gn:feature_class":"P",
    "gn:feature_code":"PPL",
    "gn:name":"Siarcza \u0141\u0105ka",
    "gn:population":0,
    "gn:timezone":"Europe/Warsaw",
    "iso:country":"PL",
    "name:ceb_x_preferred":[
        "Siarcza \u0141\u0105ka"
    ],
    "name:fra_x_preferred":[
        "Siarcza \u0141\u0105ka"
    ],
    "name:pol_x_preferred":[
        "Siarcza \u0141\u0105ka"
    ],
    "name:ukr_x_preferred":[
        "\u0421\u044f\u0440\u0447\u0430-\u041b\u043e\u043d\u043a\u0430"
    ],
    "wof:name":"Siarcza Laka",
    "wof:placetype":"locality"
},
  "geometry": {"coordinates":[21.4199,53.2659],"type":"Point"}
}