{
  "type": "Feature",
  "properties": {
    "gn:admin1_code":"73.0",
    "gn:admin2_code":"418.0",
    "gn:admin3_code":"41809.0",
    "gn:asciiname":"Dobrzelewice",
    "gn:country_code":"PL",
    "gn:dem":117,
    "gn:feature_class":"P",
    "gn:feature_code":"PPL",
    "gn:name":"Dobrzelewice",
    "gn:population":0,
    "gn:timezone":"Europe/Warsaw",
    "iso:country":"PL",
    "name:pol_x_preferred":[
        "Dobrzelewice"
    ],
    "name:ukr_x_preferred":[
        "\u0414\u043e\u0431\u0436\u0435\u043b\u0435\u0432\u0456\u0446\u0435"
    ],
    "wof:name":"Dobrzelewice",
    "wof:placetype":"locality"
},
  "geometry": {"coordinates":[19.19509,52.48786],"type":"Point"}
}