{
  "type": "Feature",
  "properties": {
    "gn:admin1_code":"85.0",
    "gn:admin2_code":"2814.0",
    "gn:admin3_code":"281401.0",
    "gn:asciiname":"Dobrag",
    "gn:cc2":"PL",
    "gn:country_code":"PL",
    "gn:dem":140,
    "gn:feature_class":"P",
    "gn:feature_code":"PPL",
    "gn:name":"Dobr\u0105g",
    "gn:population":0,
    "gn:timezone":"Europe/Warsaw",
    "iso:country":"PL",
    "name:pol_x_preferred":[
        "Dobr\u0105g"
    ],
    "name:und_x_variant":[
        "Debrong",
        "Dobr\u0105g"
    ],
    "name:vie_x_preferred":[
        "Dobr\u0105g"
    ],
    "wof:name":"Dobrag",
    "wof:placetype":"locality"
},
  "geometry": {"coordinates":[20.79969,53.83065],"type":"Point"}
}