{
  "type": "Feature",
  "properties": {
    "gn:admin1_code":"85.0",
    "gn:admin2_code":"2805.0",
    "gn:admin3_code":"280504.0",
    "gn:asciiname":"Borki",
    "gn:country_code":"PL",
    "gn:dem":170,
    "gn:feature_class":"P",
    "gn:feature_code":"PPL",
    "gn:name":"Borki",
    "gn:population":0,
    "gn:timezone":"Europe/Warsaw",
    "iso:country":"PL",
    "name:und_x_variant":[
        "Kibissen",
        "Borki"
    ],
    "wof:name":"Borki",
    "wof:placetype":"locality"
},
  "geometry": {"coordinates":[22.29622,53.70989],"type":"Point"}
}