{
  "type": "Feature",
  "properties": {
    "gn:admin1_code":"85.0",
    "gn:admin2_code":"2805.0",
    "gn:admin3_code":"280504.0",
    "gn:asciiname":"Borki",
    "gn:country_code":"PL",
    "gn:dem":170,
    "gn:feature_class":"P",
    "gn:feature_code":"PPL",
    "gn:name":"Borki",
    "gn:population":0,
    "gn:timezone":"Europe/Warsaw",
    "iso:country":"PL",
    "name:bel_x_preferred":[
        "\u0411\u043e\u0440\u043a\u0456"
    ],
    "name:bos_x_preferred":[
        "Borki"
    ],
    "name:ceb_x_preferred":[
        "Borki"
    ],
    "name:crh_x_preferred":[
        "Birk\u0131"
    ],
    "name:deu_x_preferred":[
        "Borki"
    ],
    "name:fra_x_preferred":[
        "Borki"
    ],
    "name:hye_x_preferred":[
        "\u0532\u0578\u0580\u056f\u056b"
    ],
    "name:lit_x_preferred":[
        "Borkai"
    ],
    "name:nld_x_preferred":[
        "Borki"
    ],
    "name:pol_x_preferred":[
        "Borki"
    ],
    "name:rus_x_preferred":[
        "\u0411\u043e\u0440\u043a\u0438"
    ],
    "name:ukr_x_preferred":[
        "\u0411\u043e\u0440\u043a\u0438"
    ],
    "name:und_x_variant":[
        "Kibissen"
    ],
    "wof:name":"Borki",
    "wof:placetype":"locality"
},
  "geometry": {"coordinates":[22.29622,53.70989],"type":"Point"}
}