{
  "type": "Feature",
  "properties": {
    "gn:admin1_code":"81.0",
    "gn:admin2_code":"2003.0",
    "gn:admin3_code":"200303.0",
    "gn:asciiname":"Ogrodniki",
    "gn:country_code":"PL",
    "gn:dem":138,
    "gn:feature_class":"P",
    "gn:feature_code":"PPL",
    "gn:name":"Ogrodniki",
    "gn:population":0,
    "gn:timezone":"Europe/Warsaw",
    "iso:country":"PL",
    "name:azb_x_preferred":[
        "\u0627\u0648\u0642\u0631\u0648\u062f\u0646\u0642\u06a9\u06cc"
    ],
    "name:fas_x_preferred":[
        "\u0627\u0648\u06af\u0631\u0648\u062f\u0646\u06af\u06a9\u06cc"
    ],
    "name:fra_x_preferred":[
        "Ogrodniki"
    ],
    "name:lit_x_preferred":[
        "Ogrodnikai"
    ],
    "name:pol_x_preferred":[
        "Ogrodniki"
    ],
    "name:ukr_x_preferred":[
        "\u041e\u0491\u0440\u043e\u0434\u043d\u0438\u043a\u0438"
    ],
    "wof:name":"Ogrodniki",
    "wof:placetype":"locality"
},
  "geometry": {"coordinates":[23.29642,52.77639],"type":"Point"}
}