{
  "type": "Feature",
  "properties": {
    "gn:admin1_code":"84.0",
    "gn:admin2_code":"2603.0",
    "gn:admin3_code":"260304.0",
    "gn:asciiname":"Rogow",
    "gn:cc2":"PL",
    "gn:country_code":"PL",
    "gn:dem":182,
    "gn:feature_class":"P",
    "gn:feature_code":"PPL",
    "gn:name":"Rog\u00f3w",
    "gn:population":0,
    "gn:timezone":"Europe/Warsaw",
    "iso:country":"PL",
    "name:pol_x_preferred":[
        "Rog\u00f3w"
    ],
    "name:ukr_x_preferred":[
        "\u0420\u043e\u0491\u0443\u0432"
    ],
    "name:und_x_variant":[
        "Rag\u00f3w"
    ],
    "wof:name":"Rogow",
    "wof:placetype":"locality"
},
  "geometry": {"coordinates":[20.69241,50.22744],"type":"Point"}
}