{
  "type": "Feature",
  "properties": {
    "gn:gn_country":"PL",
    "gn:gn_fcode":"PPLA3",
    "gn:gn_pop":8670,
    "gn:population":8670,
    "iso:country":"PL",
    "name:azb_x_preferred":[
        "\u06a9\u0627\u0644\u062a\u0647"
    ],
    "name:bul_x_preferred":[
        "\u041a\u0430\u043b\u0435\u0442\u0438"
    ],
    "name:ceb_x_preferred":[
        "Kalety"
    ],
    "name:deu_x_preferred":[
        "Kalety"
    ],
    "name:epo_x_preferred":[
        "Kalety"
    ],
    "name:eus_x_preferred":[
        "Kalety"
    ],
    "name:fas_x_preferred":[
        "\u06a9\u0627\u0644\u062a\u0647"
    ],
    "name:fra_x_preferred":[
        "Kalety"
    ],
    "name:ita_x_preferred":[
        "Kalety"
    ],
    "name:jav_x_preferred":[
        "Kalety"
    ],
    "name:lav_x_preferred":[
        "Kaleti"
    ],
    "name:msa_x_preferred":[
        "Kalety"
    ],
    "name:nld_x_preferred":[
        "Kalety"
    ],
    "name:pol_x_preferred":[
        "Kalety"
    ],
    "name:por_x_preferred":[
        "Kalety"
    ],
    "name:ron_x_preferred":[
        "Kalety"
    ],
    "name:rus_x_preferred":[
        "\u041a\u0430\u043b\u0435\u0442\u044b"
    ],
    "name:slk_x_preferred":[
        "Kalety"
    ],
    "name:srp_x_preferred":[
        "\u041a\u0430\u043b\u0435\u0442\u0438"
    ],
    "name:szl_x_preferred":[
        "Kalyty"
    ],
    "name:ukr_x_preferred":[
        "\u041a\u0430\u043b\u0435\u0442\u0438"
    ],
    "name:vie_x_preferred":[
        "Kalety"
    ],
    "name:war_x_preferred":[
        "Kalety"
    ],
    "name:zho_x_preferred":[
        "\u5361\u840a\u8482"
    ],
    "qs_pg:aaroncc":"PL",
    "qs_pg:gn_country":"PL",
    "qs_pg:gn_fcode":"PPLA3",
    "qs_pg:gn_pop":8670,
    "qs_pg:name":"Kalety",
    "qs_pg:name_adm0":"Polska",
    "qs_pg:name_adm1":"Sl\u0105skie",
    "qs_pg:photos":29,
    "qs_pg:photos_1k":6,
    "qs_pg:photos_9k":1,
    "qs_pg:photos_9r":2,
    "qs_pg:photos_all":29,
    "qs_pg:photos_sr":2,
    "qs_pg:pop_sr":5,
    "qs_pg:qs_pg_placetype":"localadmin",
    "qs_pg:qs_pg_placetype_gp":"LocalAdmin",
    "qs_pg:woe_adm0":23424923,
    "woe:adm0_id":23424923,
    "woe:name_adm0":"Polska",
    "woe:name_adm1":"Sl\u0105skie",
    "woe:placetype":"LocalAdmin",
    "wof:name":"Kalety",
    "wof:placetype":"localadmin",
    "wof:population":8670
},
  "geometry": {"coordinates":[18.8926,50.5627],"type":"Point"}
}