{
  "type": "Feature",
  "properties": {
    "gn:admin1_code":"73.0",
    "gn:admin2_code":"406.0",
    "gn:admin3_code":"40606.0",
    "gn:asciiname":"Lisnowko",
    "gn:country_code":"PL",
    "gn:dem":90,
    "gn:feature_class":"P",
    "gn:feature_code":"PPL",
    "gn:name":"Lisn\u00f3wko",
    "gn:population":0,
    "gn:timezone":"Europe/Warsaw",
    "iso:country":"PL",
    "name:ceb_x_preferred":[
        "Lisn\u00f3wko"
    ],
    "name:nld_x_preferred":[
        "Lisn\u00f3wko"
    ],
    "name:pol_x_preferred":[
        "Lisn\u00f3wko"
    ],
    "name:ukr_x_preferred":[
        "\u041b\u0456\u0441\u043d\u0443\u0432\u043a\u043e"
    ],
    "wof:name":"Lisnowko",
    "wof:placetype":"locality"
},
  "geometry": {"coordinates":[19.13166,53.48171],"type":"Point"}
}