{
  "type": "Feature",
  "properties": {
    "gn:admin1_code":"80.0",
    "gn:admin2_code":"1811.0",
    "gn:admin3_code":"181101.0",
    "gn:asciiname":"Luze",
    "gn:country_code":"PL",
    "gn:dem":195,
    "gn:feature_class":"P",
    "gn:feature_code":"PPL",
    "gn:name":"\u0141u\u017ce",
    "gn:population":0,
    "gn:timezone":"Europe/Warsaw",
    "iso:country":"PL",
    "name:ceb_x_preferred":[
        "Luze"
    ],
    "name:deu_x_preferred":[
        "Luze"
    ],
    "name:fra_x_preferred":[
        "Luze"
    ],
    "name:ita_x_preferred":[
        "Luze"
    ],
    "name:scn_x_preferred":[
        "Luze"
    ],
    "name:swe_x_preferred":[
        "Luze"
    ],
    "wof:name":"Luze",
    "wof:placetype":"locality"
},
  "geometry": {"coordinates":[21.56857,50.26123],"type":"Point"}
}