{
  "type": "Feature",
  "properties": {
    "iso:country":"PL",
    "name:eng_x_preferred":[
        "Dolina"
    ],
    "name:pol_x_preferred":[
        "Dolina"
    ],
    "wof:name":"Dolina",
    "wof:placetype":"neighbourhood"
},
  "geometry": {"coordinates":[18.61981719835461,54.34887875514073],"type":"Point"}
}