{
  "type": "Feature",
  "properties": {
    "iso:country":"PL",
    "name:bel_x_preferred":[
        "\u0414\u0430\u043b\u0456\u043d\u0430"
    ],
    "name:bos_x_preferred":[
        "Dolina"
    ],
    "name:bul_x_preferred":[
        "\u0414\u043e\u043b\u0438\u043d\u0430"
    ],
    "name:ceb_x_preferred":[
        "Dolina"
    ],
    "name:ces_x_preferred":[
        "Dolina"
    ],
    "name:deu_x_preferred":[
        "Dolina"
    ],
    "name:eng_x_preferred":[
        "Dolina"
    ],
    "name:fra_x_preferred":[
        "Dolina"
    ],
    "name:hrv_x_preferred":[
        "Dolina"
    ],
    "name:hye_x_preferred":[
        "\u0534\u0578\u056c\u056b\u0576\u0561"
    ],
    "name:ita_x_preferred":[
        "Dolina"
    ],
    "name:nld_x_preferred":[
        "Dolina"
    ],
    "name:pol_x_preferred":[
        "Dolina"
    ],
    "name:ron_x_preferred":[
        "Dolina"
    ],
    "name:rus_x_preferred":[
        "\u0414\u043e\u043b\u0438\u043d\u0430"
    ],
    "name:slk_x_preferred":[
        "Dolina"
    ],
    "name:slv_x_preferred":[
        "Dolina"
    ],
    "name:srp_x_preferred":[
        "\u0414\u043e\u043b\u0438\u043d\u0430"
    ],
    "name:swe_x_preferred":[
        "Dolina"
    ],
    "name:tgk_x_preferred":[
        "\u0412\u043e\u0434\u04e3"
    ],
    "name:ukr_x_preferred":[
        "\u0414\u043e\u043b\u0438\u043d\u0430"
    ],
    "wof:name":"Dolina",
    "wof:placetype":"neighbourhood"
},
  "geometry": {"coordinates":[18.61981719835461,54.34887875514073],"type":"Point"}
}