{
  "type": "Feature",
  "properties": {
    "gn:admin1_code":"84.0",
    "gn:admin2_code":"2613.0",
    "gn:admin3_code":"261306.0",
    "gn:asciiname":"Gosciecin",
    "gn:country_code":"PL",
    "gn:dem":208,
    "gn:feature_class":"P",
    "gn:feature_code":"PPL",
    "gn:name":"Go\u015bci\u0119cin",
    "gn:population":0,
    "gn:timezone":"Europe/Warsaw",
    "iso:country":"PL",
    "name:nld_x_preferred":[
        "Go\u015bciencin"
    ],
    "name:pol_x_preferred":[
        "Go\u015bciencin"
    ],
    "name:ukr_x_preferred":[
        "\u0490\u043e\u0441\u044c\u0446\u0435\u043d\u0446\u0438\u043d"
    ],
    "name:und_x_variant":[
        "Go\u015bci\u0119cin"
    ],
    "wof:name":"Gosciecin",
    "wof:placetype":"locality"
},
  "geometry": {"coordinates":[19.80226,50.89351],"type":"Point"}
}