{
  "type": "Feature",
  "properties": {
    "gn:admin1_code":"82.0",
    "gn:admin2_code":"2206.0",
    "gn:admin3_code":"220604.0",
    "gn:asciiname":"Bedominek",
    "gn:country_code":"PL",
    "gn:dem":178,
    "gn:feature_class":"P",
    "gn:feature_code":"PPL",
    "gn:name":"B\u0119dominek",
    "gn:population":0,
    "gn:timezone":"Europe/Warsaw",
    "iso:country":"PL",
    "name:csb_x_preferred":[
        "B\u00e3domink"
    ],
    "name:pol_x_preferred":[
        "B\u0119dominek"
    ],
    "name:szl_x_preferred":[
        "Bynd\u016fminek"
    ],
    "name:ukr_x_preferred":[
        "\u0411\u0435\u043d\u0434\u043e\u043c\u0456\u043d\u0435\u043a"
    ],
    "wof:name":"Bedominek",
    "wof:placetype":"locality"
},
  "geometry": {"coordinates":[18.10571,54.13162],"type":"Point"}
}