{
  "type": "Feature",
  "properties": {
    "gn:admin1_code":"72.0",
    "gn:admin2_code":"216.0",
    "gn:admin3_code":"21601.0",
    "gn:asciiname":"Chocianowiec",
    "gn:country_code":"PL",
    "gn:dem":158,
    "gn:feature_class":"P",
    "gn:feature_code":"PPL",
    "gn:name":"Chocianowiec",
    "gn:population":0,
    "gn:timezone":"Europe/Warsaw",
    "iso:country":"PL",
    "name:pol_x_preferred":[
        "Chocianowiec"
    ],
    "name:ukr_x_preferred":[
        "\u0425\u043e\u0446\u044f\u043d\u043e\u0432\u0435\u0446\u044c"
    ],
    "wof:name":"Chocianowiec",
    "wof:placetype":"locality"
},
  "geometry": {"coordinates":[15.95922,51.38859],"type":"Point"}
}