{
  "type": "Feature",
  "properties": {
    "gn:admin1_code":"85.0",
    "gn:admin2_code":"2816.0",
    "gn:admin3_code":"281601.0",
    "gn:asciiname":"Jakuby",
    "gn:country_code":"PL",
    "gn:dem":144,
    "gn:feature_class":"P",
    "gn:feature_code":"PPL",
    "gn:name":"Jakuby",
    "gn:population":0,
    "gn:timezone":"Europe/Warsaw",
    "iso:country":"PL",
    "name:deu_x_preferred":[
        "Jakuby"
    ],
    "name:fra_x_preferred":[
        "Jakuby"
    ],
    "name:pol_x_preferred":[
        "Jakuby"
    ],
    "name:ukr_x_preferred":[
        "\u042f\u043a\u0443\u0431\u0438"
    ],
    "name:und_x_variant":[
        "Jakubben",
        "Jakuby"
    ],
    "name:urd_x_preferred":[
        "\u062c\u06a9\u0628\u06d2"
    ],
    "name:vie_x_preferred":[
        "Jakuby"
    ],
    "wof:name":"Jakuby",
    "wof:placetype":"locality"
},
  "geometry": {"coordinates":[22.01082,53.52137],"type":"Point"}
}