{
  "type": "Feature",
  "properties": {
    "gn:admin1_code":"81.0",
    "gn:admin2_code":"2013.0",
    "gn:admin3_code":"201301.0",
    "gn:asciiname":"Wysokie Mazowieckie",
    "gn:country_code":"PL",
    "gn:dem":143,
    "gn:feature_class":"P",
    "gn:feature_code":"PPL",
    "gn:name":"Wysokie Mazowieckie",
    "gn:population":9203,
    "gn:timezone":"Europe/Warsaw",
    "iso:country":"PL",
    "name:bul_x_preferred":[
        "\u0412\u0438\u0441\u043e\u043a\u0435 \u041c\u0430\u0437\u043e\u0432\u0435\u0446\u043a\u0435"
    ],
    "name:deu_x_preferred":[
        "Wysokie Mazowieckie"
    ],
    "name:dsb_x_preferred":[
        "Wysokie Mazowieckie"
    ],
    "name:epo_x_preferred":[
        "Wysokie Mazowieckie"
    ],
    "name:eus_x_preferred":[
        "Wysokie Mazowieckie"
    ],
    "name:fas_x_preferred":[
        "\u0648\u0633\u0648\u06a9\u06cc\u0647 \u0645\u0627\u0632\u0648\u0648\u06cc\u062a\u0633\u06a9\u06cc\u0647"
    ],
    "name:fra_x_preferred":[
        "Wysokie Mazowieckie"
    ],
    "name:heb_x_preferred":[
        "\u05d5\u05d9\u05e1\u05d5\u05e7\u05d4 \u05de\u05d6\u05d5\u05d1\u05d9\u05d9\u05e6\u05e7"
    ],
    "name:ita_x_preferred":[
        "Wysokie Mazowieckie"
    ],
    "name:jav_x_preferred":[
        "Wysokie Mazowieckie"
    ],
    "name:lav_x_preferred":[
        "Visoke Mazovecke"
    ],
    "name:lit_x_preferred":[
        "Mazovijos Vysokis"
    ],
    "name:msa_x_preferred":[
        "Wysokie Mazowieckie"
    ],
    "name:nld_x_preferred":[
        "Wysokie Mazowieckie"
    ],
    "name:pol_x_preferred":[
        "Wysokie Mazowieckie"
    ],
    "name:por_x_preferred":[
        "Wysokie Mazowieckie"
    ],
    "name:ron_x_preferred":[
        "Wysokie Mazowieckie"
    ],
    "name:rus_x_preferred":[
        "\u0412\u044b\u0441\u043e\u043a\u0435-\u041c\u0430\u0437\u043e\u0432\u0435\u0446\u043a\u0435"
    ],
    "name:slk_x_preferred":[
        "Wysokie Mazowieckie"
    ],
    "name:srp_x_preferred":[
        "\u0412\u0438\u0441\u043e\u043a\u0458\u0435 \u041c\u0430\u0437\u043e\u0432\u0458\u0435\u0446\u043a\u0458\u0435"
    ],
    "name:ukr_x_preferred":[
        "\u0412\u0438\u0441\u043e\u043a\u0435-\u041c\u0430\u0437\u043e\u0432\u0435\u0446\u044c\u043a\u0435"
    ],
    "name:vie_x_preferred":[
        "Wysokie Mazowieckie"
    ],
    "name:war_x_preferred":[
        "Wysokie Mazowieckie"
    ],
    "name:zho_x_preferred":[
        "\u99ac\u4f50\u592b\u820d\u5730\u5340\u7dad\u7d22\u51f1"
    ],
    "wof:name":"Wysokie Mazowieckie",
    "wof:placetype":"locality",
    "wof:population":9203
},
  "geometry": {"coordinates":[22.51712,52.91661],"type":"Point"}
}