{
  "type": "Feature",
  "properties": {
    "gn:admin1_code":"78.0",
    "gn:admin2_code":"1463.0",
    "gn:admin3_code":"146301.0",
    "gn:asciiname":"Rajec Poduchowny",
    "gn:country_code":"PL",
    "gn:dem":156,
    "gn:feature_class":"P",
    "gn:feature_code":"PPL",
    "gn:name":"Rajec Poduchowny",
    "gn:population":0,
    "gn:timezone":"Europe/Warsaw",
    "iso:country":"PL",
    "name:ceb_x_preferred":[
        "Rajec Poduchowny"
    ],
    "name:fra_x_preferred":[
        "Rajec Poduchowny"
    ],
    "name:pol_x_preferred":[
        "Rajec Poduchowny"
    ],
    "name:ukr_x_preferred":[
        "\u0420\u0430\u0454\u0446\u044c-\u041f\u043e\u0434\u0443\u0445\u043e\u0432\u043d\u0438"
    ],
    "name:und_x_variant":[
        "Kolonia Rajec Poduchowny"
    ],
    "wof:name":"Rajec Poduchowny",
    "wof:placetype":"locality"
},
  "geometry": {"coordinates":[21.23692,51.43354],"type":"Point"}
}