{
  "type": "Feature",
  "properties": {
    "gn:admin1_code":"78.0",
    "gn:admin2_code":"1463.0",
    "gn:admin3_code":"146301.0",
    "gn:asciiname":"Rajec Poduchowny",
    "gn:country_code":"PL",
    "gn:dem":156,
    "gn:feature_class":"P",
    "gn:feature_code":"PPL",
    "gn:name":"Rajec Poduchowny",
    "gn:population":0,
    "gn:timezone":"Europe/Warsaw",
    "iso:country":"PL",
    "name:und_x_variant":[
        "Kolonia Rajec Poduchowny"
    ],
    "wof:name":"Rajec Poduchowny",
    "wof:placetype":"locality"
},
  "geometry": {"coordinates":[21.23692,51.43354],"type":"Point"}
}