{
  "type": "Feature",
  "properties": {
    "gn:admin1_code":"78.0",
    "gn:admin2_code":"1416.0",
    "gn:admin3_code":"141607.0",
    "gn:asciiname":"Grabniak",
    "gn:country_code":"PL",
    "gn:dem":113,
    "gn:feature_class":"P",
    "gn:feature_code":"PPL",
    "gn:name":"Grabniak",
    "gn:population":0,
    "gn:timezone":"Europe/Warsaw",
    "iso:country":"PL",
    "name:fra_x_preferred":[
        "Grabniak"
    ],
    "name:pol_x_preferred":[
        "Grabniak"
    ],
    "name:ukr_x_preferred":[
        "\u0490\u0440\u0430\u0431\u043d\u044f\u043a"
    ],
    "wof:name":"Grabniak",
    "wof:placetype":"locality"
},
  "geometry": {"coordinates":[21.68896,52.72756999999999],"type":"Point"}
}