{
  "type": "Feature",
  "properties": {
    "gn:admin1_code":"78.0",
    "gn:admin2_code":"1402.0",
    "gn:admin3_code":"140205.0",
    "gn:asciiname":"Strzelnia",
    "gn:country_code":"PL",
    "gn:dem":140,
    "gn:feature_class":"P",
    "gn:feature_code":"PPL",
    "gn:name":"Strzelnia",
    "gn:population":0,
    "gn:timezone":"Europe/Warsaw",
    "iso:country":"PL",
    "name:fra_x_preferred":[
        "Strzelnia"
    ],
    "name:pol_x_preferred":[
        "Strzelnia"
    ],
    "name:spa_x_preferred":[
        "Strzelnia"
    ],
    "name:ukr_x_preferred":[
        "\u0421\u0442\u0448\u0435\u043b\u044c\u043d\u044f"
    ],
    "wof:name":"Strzelnia",
    "wof:placetype":"locality"
},
  "geometry": {"coordinates":[20.63117,53.0368],"type":"Point"}
}