{
  "type": "Feature",
  "properties": {
    "gn:population":4861,
    "iso:country":"PL",
    "name:cat_x_preferred":[
        "Budzy\u0144"
    ],
    "name:ceb_x_preferred":[
        "Budzy\u0144"
    ],
    "name:deu_x_preferred":[
        "Budzy\u0144"
    ],
    "name:eng_x_preferred":[
        "Budzy\u0144"
    ],
    "name:fra_x_preferred":[
        "Budzy\u0144"
    ],
    "name:frr_x_preferred":[
        "Budzy\u0144"
    ],
    "name:nld_x_preferred":[
        "Budzy\u0144"
    ],
    "name:pol_x_preferred":[
        "Budzy\u0144"
    ],
    "name:por_x_preferred":[
        "Budzy\u0144"
    ],
    "name:spa_x_preferred":[
        "Budzy\u0144"
    ],
    "name:ukr_x_preferred":[
        "\u0411\u0443\u0434\u0437\u0438\u043d\u044c"
    ],
    "qs:a0":"Rzeczpospolita Polska",
    "qs:a1":"*Wielkopolskie",
    "qs:a1r":"0",
    "qs:a2":"Chodzieski",
    "qs:adm0":"Rzeczpospolita Polska",
    "qs:la":"Budzy\u0144",
    "qs:la_lc":"*PL3001022",
    "qs:level":"locality",
    "qs:loc":"Budzy\u0144",
    "qs:loc_alt":"Budzyn",
    "qs:pop":0,
    "qs:type":"rural point-in-poly",
    "wd:wordcount":66,
    "wof:name":"Budzy\u0144",
    "wof:placetype":"locality",
    "wof:population":4861
},
  "geometry": {"coordinates":[16.955799356269,52.8833516317923],"type":"Point"}
}