{
  "type": "Feature",
  "properties": {
    "gn:country":"PL",
    "gn:fcode":"PPLA3",
    "gn:population":936,
    "iso:country":"PL",
    "name:azb_x_preferred":[
        "\u0632\u0648\u0648\u0644\u0627"
    ],
    "name:ceb_x_preferred":[
        "Dzwola"
    ],
    "name:fas_x_preferred":[
        "\u0632\u0648\u0648\u0644\u0627"
    ],
    "name:fra_x_preferred":[
        "Dzwola"
    ],
    "name:nld_x_preferred":[
        "Dzwola"
    ],
    "name:pol_x_preferred":[
        "Dzwola"
    ],
    "name:ukr_x_preferred":[
        "\u0414\u0437\u0432\u043e\u043b\u044f"
    ],
    "qs_pg:aaroncc":"PL",
    "qs_pg:gn_country":"PL",
    "qs_pg:gn_fcode":"PPLA3",
    "qs_pg:gn_pop":936,
    "qs_pg:name":"Dzwola",
    "qs_pg:name_adm0":"Polska",
    "qs_pg:name_adm1":"Lubelskie",
    "qs_pg:photos_9k":1,
    "qs_pg:photos_9r":1,
    "qs_pg:photos_all":2,
    "qs_pg:photos_sr":0,
    "qs_pg:pop_sr":2,
    "qs_pg:qs_pg_placetype":"localadmin",
    "qs_pg:qs_pg_placetype_gp":"LocalAdmin",
    "qs_pg:woe_adm0":23424923,
    "woe:adm0_id":23424923,
    "woe:name_adm0":"Polska",
    "woe:name_adm1":"Lubelskie",
    "woe:placetype":"LocalAdmin",
    "wof:name":"Dzwola",
    "wof:placetype":"localadmin",
    "wof:population":936
},
  "geometry": {"coordinates":[22.56729,50.69657],"type":"Point"}
}