{
  "type": "Feature",
  "properties": {
    "gn:admin1_code":"73.0",
    "gn:admin2_code":"419.0",
    "gn:admin3_code":"41906.0",
    "gn:asciiname":"Januszkowo",
    "gn:country_code":"PL",
    "gn:dem":96,
    "gn:feature_class":"P",
    "gn:feature_code":"PPL",
    "gn:name":"Januszkowo",
    "gn:population":0,
    "gn:timezone":"Europe/Warsaw",
    "iso:country":"PL",
    "name:pol_x_preferred":[
        "Januszkowo"
    ],
    "name:ukr_x_preferred":[
        "\u042f\u043d\u0443\u0448\u043a\u043e\u0432\u043e"
    ],
    "name:urd_x_preferred":[
        "\u062c\u0627\u0646\u0633\u0632\u06a9\u0648\u0648\u0648"
    ],
    "wof:name":"Januszkowo",
    "wof:placetype":"locality"
},
  "geometry": {"coordinates":[17.75839,52.87886],"type":"Point"}
}