{
  "type": "Feature",
  "properties": {
    "gn:admin1_code":"81.0",
    "gn:admin2_code":"2009.0",
    "gn:admin3_code":"200904.0",
    "gn:asciiname":"Dziedziule",
    "gn:cc2":"PL",
    "gn:country_code":"PL",
    "gn:dem":157,
    "gn:feature_class":"P",
    "gn:feature_code":"PPL",
    "gn:name":"Dziedziule",
    "gn:population":0,
    "gn:timezone":"Europe/Warsaw",
    "iso:country":"PL",
    "name:und_x_variant":[
        "Dzidziule",
        "Dziedziule"
    ],
    "wof:name":"Dziedziule",
    "wof:placetype":"locality"
},
  "geometry": {"coordinates":[23.2693,54.20638],"type":"Point"}
}