{
  "type": "Feature",
  "properties": {
    "gn:admin1_code":"81.0",
    "gn:admin2_code":"2009.0",
    "gn:admin3_code":"200904.0",
    "gn:asciiname":"Dziedziule",
    "gn:cc2":"PL",
    "gn:country_code":"PL",
    "gn:dem":157,
    "gn:feature_class":"P",
    "gn:feature_code":"PPL",
    "gn:name":"Dziedziule",
    "gn:population":0,
    "gn:timezone":"Europe/Warsaw",
    "iso:country":"PL",
    "name:lit_x_preferred":[
        "Did\u017eiuliai"
    ],
    "name:pol_x_preferred":[
        "Dziedziule"
    ],
    "name:ukr_x_preferred":[
        "\u0414\u0437\u0435\u0434\u0437\u044e\u043b\u0435"
    ],
    "name:und_x_variant":[
        "Dzidziule"
    ],
    "wof:name":"Dziedziule",
    "wof:placetype":"locality"
},
  "geometry": {"coordinates":[23.2693,54.20638],"type":"Point"}
}