{
  "type": "Feature",
  "properties": {
    "gn:admin1_code":"87.0",
    "gn:admin2_code":"3218.0",
    "gn:admin3_code":"321803.0",
    "gn:asciiname":"Strzmiele",
    "gn:country_code":"PL",
    "gn:dem":55,
    "gn:feature_class":"P",
    "gn:feature_code":"PPL",
    "gn:name":"Strzmiele",
    "gn:population":0,
    "gn:timezone":"Europe/Warsaw",
    "iso:country":"PL",
    "name:deu_x_preferred":[
        "Strzmiele"
    ],
    "name:ita_x_preferred":[
        "Strzmiele"
    ],
    "name:pol_x_preferred":[
        "Strzmiele"
    ],
    "name:ukr_x_preferred":[
        "\u0421\u0442\u0448\u043c\u0435\u043b\u0435"
    ],
    "name:vie_x_preferred":[
        "Strzmiele"
    ],
    "wof:name":"Strzmiele",
    "wof:placetype":"locality"
},
  "geometry": {"coordinates":[15.52696,53.65353],"type":"Point"}
}