{
  "type": "Feature",
  "properties": {
    "gn:admin1_code":"77.0",
    "gn:admin2_code":"1212.0",
    "gn:admin3_code":"121203.0",
    "gn:asciiname":"Ujkow Nowy",
    "gn:country_code":"PL",
    "gn:dem":348,
    "gn:feature_class":"P",
    "gn:feature_code":"PPL",
    "gn:name":"Ujk\u00f3w Nowy",
    "gn:population":0,
    "gn:timezone":"Europe/Warsaw",
    "iso:country":"PL",
    "name:pol_x_preferred":[
        "Ujk\u00f3w Nowy"
    ],
    "name:ukr_x_preferred":[
        "\u0423\u0439\u043a\u0443\u0432-\u041d\u043e\u0432\u0438\u0439"
    ],
    "name:und_x_variant":[
        "Ujk\u00f3w Nowy"
    ],
    "wof:name":"Ujkow Nowy",
    "wof:placetype":"locality"
},
  "geometry": {"coordinates":[19.44512000000001,50.30576],"type":"Point"}
}