{
  "type": "Feature",
  "properties": {
    "gn:admin1_code":"79.0",
    "gn:admin2_code":"1607.0",
    "gn:admin3_code":"160706.0",
    "gn:asciiname":"Laskowice",
    "gn:country_code":"PL",
    "gn:dem":230,
    "gn:feature_class":"P",
    "gn:feature_code":"PPL",
    "gn:name":"Laskowice",
    "gn:population":0,
    "gn:timezone":"Europe/Warsaw",
    "iso:country":"PL",
    "name:pol_x_preferred":[
        "Laskowice"
    ],
    "wof:name":"Laskowice",
    "wof:placetype":"locality"
},
  "geometry": {"coordinates":[17.20853,50.5061],"type":"Point"}
}