{
  "type": "Feature",
  "properties": {
    "gn:admin1_code":"84.0",
    "gn:admin2_code":"2603.0",
    "gn:admin3_code":"260304.0",
    "gn:asciiname":"Trebaczow",
    "gn:country_code":"PL",
    "gn:dem":207,
    "gn:feature_class":"P",
    "gn:feature_code":"PPL",
    "gn:name":"Tr\u0119bacz\u00f3w",
    "gn:population":0,
    "gn:timezone":"Europe/Warsaw",
    "iso:country":"PL",
    "name:pol_x_preferred":[
        "Tr\u0119bacz\u00f3w"
    ],
    "name:ukr_x_preferred":[
        "\u0422\u0440\u0435\u043c\u0431\u0430\u0447\u0443\u0432"
    ],
    "wof:name":"Trebaczow",
    "wof:placetype":"locality"
},
  "geometry": {"coordinates":[20.63486,50.27523],"type":"Point"}
}