{
  "type": "Feature",
  "properties": {
    "gn:admin1_code":"78.0",
    "gn:admin2_code":"1434.0",
    "gn:admin3_code":"143410.0",
    "gn:asciiname":"Borucza",
    "gn:country_code":"PL",
    "gn:dem":116,
    "gn:feature_class":"P",
    "gn:feature_code":"PPL",
    "gn:name":"Borucza",
    "gn:population":0,
    "gn:timezone":"Europe/Warsaw",
    "iso:country":"PL",
    "name:azb_x_preferred":[
        "\u0628\u0648\u0631\u0648\u0686\u0627"
    ],
    "name:fas_x_preferred":[
        "\u0628\u0648\u0631\u0648\u0686\u0627"
    ],
    "name:fra_x_preferred":[
        "Borucza"
    ],
    "name:pol_x_preferred":[
        "Borucza"
    ],
    "name:ukr_x_preferred":[
        "\u0411\u043e\u0440\u0443\u0447\u0430"
    ],
    "wof:name":"Borucza",
    "wof:placetype":"locality"
},
  "geometry": {"coordinates":[21.54891,52.37452],"type":"Point"}
}