{
  "type": "Feature",
  "properties": {
    "gn:admin1_code":"77.0",
    "gn:admin2_code":"1210.0",
    "gn:admin3_code":"121013.0",
    "gn:asciiname":"Bukowiec",
    "gn:country_code":"PL",
    "gn:dem":837,
    "gn:feature_class":"P",
    "gn:feature_code":"PPL",
    "gn:name":"Bukowiec",
    "gn:population":0,
    "gn:timezone":"Europe/Warsaw",
    "iso:country":"PL",
    "name:ceb_x_preferred":[
        "Bukowiec"
    ],
    "name:deu_x_preferred":[
        "Bukowiec"
    ],
    "name:fra_x_preferred":[
        "Bukowiec"
    ],
    "name:nld_x_preferred":[
        "Bukowiec"
    ],
    "name:pol_x_preferred":[
        "Bukowiec"
    ],
    "wof:name":"Bukowiec",
    "wof:placetype":"locality"
},
  "geometry": {"coordinates":[20.63333,49.43333],"type":"Point"}
}