{
  "type": "Feature",
  "properties": {
    "gn:admin1_code":"78.0",
    "gn:admin2_code":"1435.0",
    "gn:admin3_code":"143502.0",
    "gn:asciiname":"Kalinowo",
    "gn:country_code":"PL",
    "gn:dem":107,
    "gn:feature_class":"P",
    "gn:feature_code":"PPL",
    "gn:name":"Kalinowo",
    "gn:population":0,
    "gn:timezone":"Europe/Warsaw",
    "iso:country":"PL",
    "name:fra_x_preferred":[
        "Kalinowo"
    ],
    "name:pol_x_preferred":[
        "Kalinowo"
    ],
    "name:ukr_x_preferred":[
        "\u041a\u0430\u043b\u0456\u043d\u043e\u0432\u043e"
    ],
    "name:und_x_variant":[
        "Kalnowo"
    ],
    "wof:name":"Kalinowo",
    "wof:placetype":"locality"
},
  "geometry": {"coordinates":[21.5777,52.72029000000001],"type":"Point"}
}