{
  "type": "Feature",
  "properties": {
    "gn:admin1_code":"74.0",
    "gn:admin2_code":"1011.0",
    "gn:admin3_code":"101105.0",
    "gn:asciiname":"Kludna",
    "gn:country_code":"PL",
    "gn:dem":112,
    "gn:feature_class":"P",
    "gn:feature_code":"PPL",
    "gn:name":"K\u0142udna",
    "gn:population":0,
    "gn:timezone":"Europe/Warsaw",
    "iso:country":"PL",
    "name:und_x_variant":[
        "K\u0142\u00f3dna",
        "K\u0142udna"
    ],
    "wof:name":"Kludna",
    "wof:placetype":"locality"
},
  "geometry": {"coordinates":[18.951,51.97089],"type":"Point"}
}