{
  "type": "Feature",
  "properties": {
    "gn:admin1_code":"85.0",
    "gn:admin2_code":"2817.0",
    "gn:admin3_code":"281702.0",
    "gn:asciiname":"Olszewki",
    "gn:country_code":"PL",
    "gn:dem":164,
    "gn:feature_class":"P",
    "gn:feature_code":"PPL",
    "gn:name":"Olszewki",
    "gn:population":0,
    "gn:timezone":"Europe/Warsaw",
    "iso:country":"PL",
    "name:und_x_variant":[
        "Kornau Ostpreussen",
        "Olsch\u00f6wken",
        "Kornau",
        "Olszewki"
    ],
    "wof:name":"Olszewki",
    "wof:placetype":"locality"
},
  "geometry": {"coordinates":[20.99507,53.67292],"type":"Point"}
}