{
  "type": "Feature",
  "properties": {
    "gn:admin1_code":"81.0",
    "gn:admin2_code":"2006.0",
    "gn:admin3_code":"200605.0",
    "gn:asciiname":"Cedry",
    "gn:country_code":"PL",
    "gn:dem":175,
    "gn:feature_class":"P",
    "gn:feature_code":"PPL",
    "gn:name":"Cedry",
    "gn:population":0,
    "gn:timezone":"Europe/Warsaw",
    "iso:country":"PL",
    "name:ceb_x_preferred":[
        "Cedry"
    ],
    "name:lit_x_preferred":[
        "Cedrai"
    ],
    "name:pol_x_preferred":[
        "Cedry"
    ],
    "name:ukr_x_preferred":[
        "\u0426\u0435\u0434\u0440\u0438"
    ],
    "wof:name":"Cedry",
    "wof:placetype":"locality"
},
  "geometry": {"coordinates":[22.18981,53.36428000000001],"type":"Point"}
}