{
  "type": "Feature",
  "properties": {
    "gn:admin1_code":"76.0",
    "gn:admin2_code":"806.0",
    "gn:admin3_code":"80605.0",
    "gn:asciiname":"Sarbiewo",
    "gn:country_code":"PL",
    "gn:dem":31,
    "gn:feature_class":"P",
    "gn:feature_code":"PPL",
    "gn:name":"Sarbiewo",
    "gn:population":0,
    "gn:timezone":"Europe/Warsaw",
    "iso:country":"PL",
    "name:deu_x_preferred":[
        "Sarbiewo"
    ],
    "name:fra_x_preferred":[
        "Sarbiewo"
    ],
    "name:pol_x_preferred":[
        "Sarbiewo"
    ],
    "name:ukr_x_preferred":[
        "\u0421\u0430\u0440\u0431\u0435\u0432\u043e"
    ],
    "name:und_x_variant":[
        "Muckenburg"
    ],
    "wof:name":"Sarbiewo",
    "wof:placetype":"locality"
},
  "geometry": {"coordinates":[15.5387,52.82455],"type":"Point"}
}