{
  "type": "Feature",
  "properties": {
    "gn:admin1_code":"83.0",
    "gn:admin2_code":"2468.0",
    "gn:admin3_code":"246801.0",
    "gn:asciiname":"Dabrowa Narodowa",
    "gn:country_code":"PL",
    "gn:dem":265,
    "gn:feature_class":"P",
    "gn:feature_code":"PPL",
    "gn:name":"D\u0105browa Narodowa",
    "gn:population":0,
    "gn:timezone":"Europe/Warsaw",
    "iso:country":"PL",
    "name:und_x_variant":[
        "D\u0105browa Narodowa",
        "D\u0105browa"
    ],
    "wof:name":"Dabrowa Narodowa",
    "wof:placetype":"neighbourhood"
},
  "geometry": {"coordinates":[19.21266,50.2277],"type":"Point"}
}