{
  "type": "Feature",
  "properties": {
    "gn:admin1_code":"83.0",
    "gn:admin2_code":"2417.0",
    "gn:admin3_code":"241708.0",
    "gn:asciiname":"Glowaczowa",
    "gn:country_code":"PL",
    "gn:dem":385,
    "gn:feature_class":"P",
    "gn:feature_code":"PPL",
    "gn:name":"Glowaczowa",
    "gn:population":0,
    "gn:timezone":"Europe/Warsaw",
    "iso:country":"PL",
    "wof:name":"Glowaczowa",
    "wof:placetype":"locality"
},
  "geometry": {"coordinates":[19.12531,49.73635],"type":"Point"}
}