{
  "type": "Feature",
  "properties": {
    "gn:admin1_code":"73.0",
    "gn:admin2_code":"408.0",
    "gn:admin3_code":"40804.0",
    "gn:asciiname":"Glewo",
    "gn:country_code":"PL",
    "gn:dem":95,
    "gn:feature_class":"P",
    "gn:feature_code":"PPL",
    "gn:name":"Glewo",
    "gn:population":0,
    "gn:timezone":"Europe/Warsaw",
    "iso:country":"PL",
    "name:pol_x_preferred":[
        "Glewo"
    ],
    "name:ukr_x_preferred":[
        "\u0490\u043b\u0435\u0432\u043e"
    ],
    "wof:name":"Glewo",
    "wof:placetype":"locality"
},
  "geometry": {"coordinates":[19.23102,52.65665],"type":"Point"}
}