{
  "type": "Feature",
  "properties": {
    "gn:admin1_code":"81.0",
    "gn:admin2_code":"2001.0",
    "gn:admin3_code":"200102.0",
    "gn:asciiname":"Turowka",
    "gn:country_code":"PL",
    "gn:dem":136,
    "gn:feature_class":"P",
    "gn:feature_code":"PPL",
    "gn:name":"Tur\u00f3wka",
    "gn:population":0,
    "gn:timezone":"Europe/Warsaw",
    "iso:country":"PL",
    "name:azb_x_preferred":[
        "\u062a\u0648\u0631\u0648\u0648\u06a9\u0627"
    ],
    "name:fas_x_preferred":[
        "\u062a\u0648\u0631\u0648\u0648\u06a9\u0627"
    ],
    "name:fra_x_preferred":[
        "Tur\u00f3wka"
    ],
    "name:lit_x_preferred":[
        "Turuvka"
    ],
    "name:pol_x_preferred":[
        "Tur\u00f3wka"
    ],
    "name:ukr_x_preferred":[
        "\u0422\u0443\u0440\u0443\u0432\u043a\u0430"
    ],
    "name:und_x_variant":[
        "Tur\u00f3wka"
    ],
    "name:urd_x_preferred":[
        "\u062a\u0648\u0631\u0648\u0648\u06a9\u0627"
    ],
    "wof:name":"Turowka",
    "wof:placetype":"locality"
},
  "geometry": {"coordinates":[22.84732,53.85639000000001],"type":"Point"}
}