{
  "type": "Feature",
  "properties": {
    "gn:admin1_code":"81.0",
    "gn:admin2_code":"2001.0",
    "gn:admin3_code":"200102.0",
    "gn:asciiname":"Turowka",
    "gn:country_code":"PL",
    "gn:dem":136,
    "gn:feature_class":"P",
    "gn:feature_code":"PPL",
    "gn:name":"Tur\u00f3wka",
    "gn:population":0,
    "gn:timezone":"Europe/Warsaw",
    "iso:country":"PL",
    "name:und_x_variant":[
        "Tur\u00f3wka"
    ],
    "wof:name":"Turowka",
    "wof:placetype":"locality"
},
  "geometry": {"coordinates":[22.84732,53.85639000000001],"type":"Point"}
}