{
  "type": "Feature",
  "properties": {
    "gn:admin1_code":"87.0",
    "gn:admin2_code":"3204.0",
    "gn:admin3_code":"320406.0",
    "gn:asciiname":"Miodowice",
    "gn:country_code":"PL",
    "gn:dem":17,
    "gn:feature_class":"P",
    "gn:feature_code":"PPL",
    "gn:name":"Miodowice",
    "gn:population":0,
    "gn:timezone":"Europe/Warsaw",
    "iso:country":"PL",
    "name:pol_x_preferred":[
        "Miodowice"
    ],
    "name:ukr_x_preferred":[
        "\u041c\u0439\u043e\u0434\u043e\u0432\u0456\u0446\u0435"
    ],
    "name:vie_x_preferred":[
        "Miodowice"
    ],
    "wof:name":"Miodowice",
    "wof:placetype":"locality"
},
  "geometry": {"coordinates":[14.71813,53.7473],"type":"Point"}
}