{
  "type": "Feature",
  "properties": {
    "gn:admin1_code":"75.0",
    "gn:admin2_code":"616.0",
    "gn:admin3_code":"61604.0",
    "gn:asciiname":"Dabia Stara",
    "gn:country_code":"PL",
    "gn:dem":175,
    "gn:feature_class":"P",
    "gn:feature_code":"PPL",
    "gn:name":"D\u0105bia Stara",
    "gn:population":0,
    "gn:timezone":"Europe/Warsaw",
    "iso:country":"PL",
    "name:fra_x_preferred":[
        "Stara D\u0105bia"
    ],
    "name:pol_x_preferred":[
        "Stara D\u0105bia"
    ],
    "name:ukr_x_preferred":[
        "\u0421\u0442\u0430\u0440\u0430 \u0414\u043e\u043c\u0431\u044f"
    ],
    "name:und_x_variant":[
        "D\u0105bia Stara"
    ],
    "wof:name":"Dabia Stara",
    "wof:placetype":"locality"
},
  "geometry": {"coordinates":[21.888,51.66829],"type":"Point"}
}