{
  "type": "Feature",
  "properties": {
    "gn:population":2500,
    "iso:country":"PL",
    "name:eng_x_preferred":[
        "Niebieszczany"
    ],
    "name:fre_x_preferred":[
        "Niebieszczany"
    ],
    "name:pol_x_preferred":[
        "Niebieszczany"
    ],
    "qs:a0":"Rzeczpospolita Polska",
    "qs:a1":"*Podkarpackie",
    "qs:a1r":"0",
    "qs:a2":"Sanocki",
    "qs:adm0":"Rzeczpospolita Polska",
    "qs:la_lc":"*",
    "qs:level":"locality",
    "qs:loc":"Niebieszczany",
    "qs:loc_alt":"Niebieszczany",
    "qs:pop":0,
    "qs:type":"buffered point",
    "wd:wordcount":79,
    "wof:name":"Niebieszczany",
    "wof:placetype":"locality",
    "wof:population":2500
},
  "geometry": {"coordinates":[22.166082,49.497666],"type":"Point"}
}