{
  "type": "Feature",
  "properties": {
    "gn:admin1_code":"83.0",
    "gn:admin2_code":"2464.0",
    "gn:admin3_code":"246401.0",
    "gn:asciiname":"Brzeziny Wielkie",
    "gn:country_code":"PL",
    "gn:dem":259,
    "gn:feature_class":"P",
    "gn:feature_code":"PPL",
    "gn:name":"Brzeziny Wielkie",
    "gn:population":0,
    "gn:timezone":"Europe/Warsaw",
    "iso:country":"PL",
    "wof:name":"Brzeziny Wielkie",
    "wof:placetype":"locality"
},
  "geometry": {"coordinates":[19.1074,50.76024],"type":"Point"}
}