{
  "type": "Feature",
  "properties": {
    "gn:admin1_code":"74.0",
    "gn:admin2_code":"1004.0",
    "gn:admin3_code":"100402.0",
    "gn:asciiname":"Gasiorow",
    "gn:country_code":"PL",
    "gn:dem":141,
    "gn:feature_class":"P",
    "gn:feature_code":"PPL",
    "gn:name":"G\u0105sior\u00f3w",
    "gn:population":0,
    "gn:timezone":"Europe/Warsaw",
    "iso:country":"PL",
    "name:und_x_variant":[
        "G\u0105sior\u00f3w"
    ],
    "wof:name":"Gasiorow",
    "wof:placetype":"locality"
},
  "geometry": {"coordinates":[19.12131,52.15761],"type":"Point"}
}