{
  "type": "Feature",
  "properties": {
    "iso:country":"PL",
    "name:bar_x_preferred":[
        "Kasinka Ma\u0142a"
    ],
    "name:deu_x_preferred":[
        "Kasinka Ma\u0142a"
    ],
    "name:eng_x_preferred":[
        "Kasinka Ma\u0142a"
    ],
    "name:fra_x_preferred":[
        "Kasinka Ma\u0142a"
    ],
    "name:ind_x_preferred":[
        "Kasinka Ma\u0142a"
    ],
    "name:nan_x_preferred":[
        "Kasinka Ma\u0142a"
    ],
    "name:nld_x_preferred":[
        "Kasinka Ma\u0142a"
    ],
    "name:pol_x_preferred":[
        "Kasinka Ma\u0142a"
    ],
    "name:ukr_x_preferred":[
        "\u0421\u0435\u0434\u043b\u0435\u043d\u0446\u0438\u043d"
    ],
    "name:ukr_x_variant":[
        "\u041a\u0430\u0441\u0456\u043d\u043a\u0430-\u041c\u0430\u043b\u0430"
    ],
    "name:zho_min_nan_x_preferred":[
        "Kasinka Ma\u0142a"
    ],
    "qs:a0":"Rzeczpospolita Polska",
    "qs:a1":"*Malopolskie",
    "qs:a1r":"0",
    "qs:a2":"Limanowski",
    "qs:adm0":"Rzeczpospolita Polska",
    "qs:la_lc":"*",
    "qs:level":"locality",
    "qs:loc":"Kasinka Ma\u0142a",
    "qs:loc_alt":"Kasinka Mala",
    "qs:pop":0,
    "qs:type":"buffered point",
    "wd:wordcount":95,
    "wof:name":"Kasinka Ma\u0142a",
    "wof:placetype":"locality"
},
  "geometry": {"coordinates":[20.034881,49.708393],"type":"Point"}
}