{
  "type": "Feature",
  "properties": {
    "gn:admin1_code":"80.0",
    "gn:admin2_code":"1806.0",
    "gn:admin3_code":"180605.0",
    "gn:asciiname":"Olszowe",
    "gn:country_code":"PL",
    "gn:dem":203,
    "gn:feature_class":"P",
    "gn:feature_code":"PPL",
    "gn:name":"Olszowe",
    "gn:population":0,
    "gn:timezone":"Europe/Warsaw",
    "iso:country":"PL",
    "wof:name":"Olszowe",
    "wof:placetype":"locality"
},
  "geometry": {"coordinates":[22.08651,50.2761],"type":"Point"}
}