{
  "type": "Feature",
  "properties": {
    "gn:admin1_code":"80.0",
    "gn:admin2_code":"1819.0",
    "gn:admin3_code":"181902.0",
    "gn:asciiname":"Pulanki",
    "gn:country_code":"PL",
    "gn:dem":301,
    "gn:feature_class":"P",
    "gn:feature_code":"PPL",
    "gn:name":"Pu\u0142anki",
    "gn:population":0,
    "gn:timezone":"Europe/Warsaw",
    "iso:country":"PL",
    "name:pol_x_preferred":[
        "Pu\u0142anki"
    ],
    "name:ukr_x_preferred":[
        "\u041f\u0443\u043b\u0430\u043d\u043a\u0456"
    ],
    "wof:name":"Pulanki",
    "wof:placetype":"locality"
},
  "geometry": {"coordinates":[21.60144,49.84562],"type":"Point"}
}