{
  "type": "Feature",
  "properties": {
    "gn:country":"PL",
    "gn:fcode":"ADM3",
    "gn:population":4591,
    "iso:country":"PL",
    "name:pol_x_preferred":[
        "Lichnowy"
    ],
    "qs_pg:aaroncc":"PL",
    "qs_pg:gn_country":"PL",
    "qs_pg:gn_fcode":"ADM3",
    "qs_pg:gn_pop":4591,
    "qs_pg:name":"Lichnowy",
    "qs_pg:photos_9r":0,
    "qs_pg:photos_sr":0,
    "qs_pg:pop_sr":4,
    "qs_pg:qs_pg_placetype":"localadmin",
    "wof:name":"Lichnowy",
    "wof:placetype":"localadmin",
    "wof:population":4591
},
  "geometry": {"coordinates":[18.91348,54.11575],"type":"Point"}
}