{
  "type": "Feature",
  "properties": {
    "gn:admin1_code":"79.0",
    "gn:admin2_code":"1609.0",
    "gn:admin3_code":"160912.0",
    "gn:asciiname":"Rogacz",
    "gn:country_code":"PL",
    "gn:dem":205,
    "gn:feature_class":"P",
    "gn:feature_code":"PPL",
    "gn:name":"Rogacz",
    "gn:population":0,
    "gn:timezone":"Europe/Warsaw",
    "iso:country":"PL",
    "name:pol_x_preferred":[
        "Rogacz"
    ],
    "name:ukr_x_preferred":[
        "\u0420\u043e\u0491\u0430\u0447"
    ],
    "wof:name":"Rogacz",
    "wof:placetype":"locality"
},
  "geometry": {"coordinates":[17.75,50.56667],"type":"Point"}
}