{
  "type": "Feature",
  "properties": {
    "gn:gn_country":"PL",
    "gn:gn_fcode":"PPLA3",
    "gn:gn_pop":270,
    "gn:population":270,
    "iso:country":"PL",
    "name:azb_x_preferred":[
        "\u06cc\u0648\u0646\u0642\u062a\u0633"
    ],
    "name:ceb_x_preferred":[
        "Joniec"
    ],
    "name:deu_x_preferred":[
        "Joniec"
    ],
    "name:fas_x_preferred":[
        "\u06cc\u0648\u0646\u06af\u062a\u0633"
    ],
    "name:fra_x_preferred":[
        "Joniec"
    ],
    "name:nld_x_preferred":[
        "Joniec"
    ],
    "name:pol_x_preferred":[
        "Joniec"
    ],
    "name:ukr_x_preferred":[
        "\u0419\u043e\u043d\u0435\u0446\u044c"
    ],
    "qs_pg:aaroncc":"PL",
    "qs_pg:gn_country":"PL",
    "qs_pg:gn_fcode":"PPLA3",
    "qs_pg:gn_pop":270,
    "qs_pg:name":"Joniec",
    "qs_pg:name_adm0":"Polska",
    "qs_pg:name_adm1":"Mazowieckie",
    "qs_pg:photos":85,
    "qs_pg:photos_1k":17,
    "qs_pg:photos_9k":1,
    "qs_pg:photos_9r":3,
    "qs_pg:photos_all":85,
    "qs_pg:photos_sr":3,
    "qs_pg:pop_sr":2,
    "qs_pg:qs_pg_placetype":"localadmin",
    "qs_pg:qs_pg_placetype_gp":"LocalAdmin",
    "qs_pg:woe_adm0":23424923,
    "woe:adm0_id":23424923,
    "woe:name_adm0":"Polska",
    "woe:name_adm1":"Mazowieckie",
    "woe:placetype":"LocalAdmin",
    "wof:name":"Joniec",
    "wof:placetype":"localadmin",
    "wof:population":270
},
  "geometry": {"coordinates":[20.58177,52.60128],"type":"Point"}
}