{
  "type": "Feature",
  "properties": {
    "gn:admin1_code":"75.0",
    "gn:admin2_code":"614.0",
    "gn:admin3_code":"61404.0",
    "gn:asciiname":"Wierzchoniow",
    "gn:country_code":"PL",
    "gn:dem":138,
    "gn:feature_class":"P",
    "gn:feature_code":"PPL",
    "gn:name":"Wierzchoni\u00f3w",
    "gn:population":0,
    "gn:timezone":"Europe/Warsaw",
    "iso:country":"PL",
    "name:fra_x_preferred":[
        "Wierzchoni\u00f3w"
    ],
    "name:pol_x_preferred":[
        "Wierzchoni\u00f3w"
    ],
    "name:ukr_x_preferred":[
        "\u0412\u0435\u0436\u0445\u043e\u043d\u044e\u0432"
    ],
    "wof:name":"Wierzchoniow",
    "wof:placetype":"locality"
},
  "geometry": {"coordinates":[22.03704,51.33419],"type":"Point"}
}