{
  "type": "Feature",
  "properties": {
    "gn:gn_country":"PL",
    "gn:gn_fcode":"PPL",
    "gn:gn_pop":289,
    "gn:population":289,
    "iso:country":"PL",
    "name:ces_x_preferred":[
        "Lou\u010dka"
    ],
    "name:deu_x_preferred":[
        "\u0141\u0105czka"
    ],
    "name:eng_x_preferred":[
        "\u0141\u0105czka"
    ],
    "name:fas_x_preferred":[
        "\u0648\u0627\u0646\u0686\u06a9\u0627"
    ],
    "name:fra_x_preferred":[
        "\u0141\u0105czka"
    ],
    "name:nld_x_preferred":[
        "\u0141\u0105czka"
    ],
    "name:pol_x_preferred":[
        "\u0141\u0105czka"
    ],
    "name:urd_x_preferred":[
        "\u0644\u0627\u06a9\u0632\u06a9\u0627\u060c \u0633\u0644\u06cc\u0633\u06cc\u0646 \u0635\u0648\u0628\u06c1"
    ],
    "qs_pg:aaroncc":"PL",
    "qs_pg:gn_country":"PL",
    "qs_pg:gn_fcode":"PPL",
    "qs_pg:gn_pop":289,
    "qs_pg:name":"\u0141\u0105czka",
    "qs_pg:name_adm0":"Polska",
    "qs_pg:name_adm1":"Sl\u0105skie",
    "qs_pg:photos_9k":1,
    "qs_pg:photos_9r":1,
    "qs_pg:photos_all":1,
    "qs_pg:photos_sr":0,
    "qs_pg:pop_sr":2,
    "qs_pg:qs_pg_placetype":"locality",
    "qs_pg:qs_pg_placetype_gp":"Town",
    "qs_pg:woe_adm0":23424923,
    "woe:adm0_id":23424923,
    "woe:name_adm0":"Polska",
    "woe:name_adm1":"Sl\u0105skie",
    "woe:placetype":"Town",
    "wof:name":"\u0141\u0105czka",
    "wof:placetype":"locality",
    "wof:population":289
},
  "geometry": {"coordinates":[18.7365,49.77677],"type":"Point"}
}