{
  "type": "Feature",
  "properties": {
    "gn:admin1_code":"86.0",
    "gn:admin2_code":"3021.0",
    "gn:admin3_code":"302102.0",
    "gn:asciiname":"Puszczykowko",
    "gn:country_code":"PL",
    "gn:dem":60,
    "gn:feature_class":"P",
    "gn:feature_code":"PPL",
    "gn:name":"Puszczyk\u00f3wko",
    "gn:population":0,
    "gn:timezone":"Europe/Warsaw",
    "iso:country":"PL",
    "wof:name":"Puszczykowko",
    "wof:placetype":"locality"
},
  "geometry": {"coordinates":[16.87466,52.26029000000001],"type":"Point"}
}