{
  "type": "Feature",
  "properties": {
    "gn:admin1_code":"73.0",
    "gn:admin2_code":"418.0",
    "gn:admin3_code":"41805.0",
    "gn:asciiname":"Wichrowice",
    "gn:cc2":"PL",
    "gn:country_code":"PL",
    "gn:dem":91,
    "gn:feature_class":"P",
    "gn:feature_code":"PPL",
    "gn:name":"Wichrowice",
    "gn:population":0,
    "gn:timezone":"Europe/Warsaw",
    "iso:country":"PL",
    "name:pol_x_preferred":[
        "Wichrowice"
    ],
    "name:ukr_x_preferred":[
        "\u0412\u0456\u0445\u0440\u043e\u0432\u0456\u0446\u0435"
    ],
    "name:und_x_variant":[
        "Kolonja Wichrowice"
    ],
    "wof:name":"Wichrowice",
    "wof:placetype":"locality"
},
  "geometry": {"coordinates":[18.96978,52.54118],"type":"Point"}
}