{
  "type": "Feature",
  "properties": {
    "gn:admin1_code":"75.0",
    "gn:admin2_code":"618.0",
    "gn:admin3_code":"61805.0",
    "gn:asciiname":"Zurawce",
    "gn:country_code":"PL",
    "gn:dem":250,
    "gn:feature_class":"P",
    "gn:feature_code":"PPL",
    "gn:name":"\u017burawce",
    "gn:population":0,
    "gn:timezone":"Europe/Warsaw",
    "iso:country":"PL",
    "name:fas_x_preferred":[
        "\u0698\u0648\u0631\u0627\u0641\u062a\u0633\u0647"
    ],
    "name:fra_x_preferred":[
        "\u017burawce"
    ],
    "name:pol_x_preferred":[
        "\u017burawce"
    ],
    "name:szl_x_preferred":[
        "\u017burawce"
    ],
    "name:ukr_x_preferred":[
        "\u0416\u0443\u0440\u0430\u0432\u0447\u0435"
    ],
    "name:und_x_variant":[
        "\u017burawce"
    ],
    "wof:name":"Zurawce",
    "wof:placetype":"locality"
},
  "geometry": {"coordinates":[23.54642,50.38209000000001],"type":"Point"}
}