{
  "type": "Feature",
  "properties": {
    "gn:admin1_code":"81.0",
    "gn:admin2_code":"2004.0",
    "gn:admin3_code":"200405.0",
    "gn:asciiname":"Niedzwiadna",
    "gn:country_code":"PL",
    "gn:dem":153,
    "gn:feature_class":"P",
    "gn:feature_code":"PPL",
    "gn:name":"Nied\u017awiadna",
    "gn:population":0,
    "gn:timezone":"Europe/Warsaw",
    "iso:country":"PL",
    "name:eng_x_preferred":[
        "Nied\u017awiadna"
    ],
    "name:rus_x_preferred":[
        "\u041d\u0435\u0434\u0437\u0432\u044f\u0434\u043d\u0430"
    ],
    "name:und_x_variant":[
        "Nied\u017awiadna"
    ],
    "wof:name":"Niedzwiadna",
    "wof:placetype":"locality"
},
  "geometry": {"coordinates":[22.19196,53.54809],"type":"Point"}
}