{
  "type": "Feature",
  "properties": {
    "gn:admin1_code":"80.0",
    "gn:admin2_code":"1804.0",
    "gn:admin3_code":"180404.0",
    "gn:asciiname":"Brzezina",
    "gn:country_code":"PL",
    "gn:dem":176,
    "gn:feature_class":"P",
    "gn:feature_code":"PPL",
    "gn:name":"Brzezina",
    "gn:population":0,
    "gn:timezone":"Europe/Warsaw",
    "iso:country":"PL",
    "name:ceb_x_preferred":[
        "Brzezina"
    ],
    "name:deu_x_preferred":[
        "Brzezina"
    ],
    "name:epo_x_preferred":[
        "Betularbaro"
    ],
    "name:pol_x_preferred":[
        "Brzezina"
    ],
    "name:ukr_x_preferred":[
        "\u0411\u0436\u0435\u0437\u0456\u043d\u0430"
    ],
    "wof:name":"Brzezina",
    "wof:placetype":"locality"
},
  "geometry": {"coordinates":[22.62608,50.10263],"type":"Point"}
}