{
  "type": "Feature",
  "properties": {
    "gn:gn_country":"PL",
    "gn:gn_fcode":"PPL",
    "gn:gn_pop":648,
    "gn:population":648,
    "iso:country":"PL",
    "name:deu_x_preferred":[
        "Pogorzela"
    ],
    "name:eng_x_preferred":[
        "Pogorzela"
    ],
    "name:fas_x_preferred":[
        "\u067e\u0648\u06af\u0648\u0698\u0644\u0627"
    ],
    "name:fra_x_preferred":[
        "Pogorzela"
    ],
    "name:jpn_x_preferred":[
        "\u30dd\u30b4\u30b8\u30a7\u30e9"
    ],
    "name:nan_x_preferred":[
        "Pogorzela"
    ],
    "name:pol_x_preferred":[
        "Pogorzela"
    ],
    "qs_pg:aaroncc":"PL",
    "qs_pg:gn_country":"PL",
    "qs_pg:gn_fcode":"PPL",
    "qs_pg:gn_pop":648,
    "qs_pg:name":"Pogorzela",
    "qs_pg:name_adm0":"Polska",
    "qs_pg:name_adm1":"Opolskie",
    "qs_pg:photos_9r":0,
    "qs_pg:photos_sr":0,
    "qs_pg:pop_sr":2,
    "qs_pg:qs_pg_placetype":"locality",
    "qs_pg:qs_pg_placetype_gp":"Town",
    "qs_pg:woe_adm0":23424923,
    "woe:adm0_id":23424923,
    "woe:name_adm0":"Polska",
    "woe:name_adm1":"Opolskie",
    "woe:placetype":"Town",
    "wof:name":"Pogorzela",
    "wof:placetype":"locality",
    "wof:population":648
},
  "geometry": {"coordinates":[17.49367,50.78738],"type":"Point"}
}