{
  "type": "Feature",
  "properties": {
    "gn:admin1_code":"79.0",
    "gn:admin2_code":"1609.0",
    "gn:admin3_code":"160908.0",
    "gn:asciiname":"Biestrzynnik",
    "gn:country_code":"PL",
    "gn:dem":187,
    "gn:feature_class":"P",
    "gn:feature_code":"PPL",
    "gn:name":"Biestrzynnik",
    "gn:population":0,
    "gn:timezone":"Europe/Warsaw",
    "iso:country":"PL",
    "name:azb_x_preferred":[
        "\u0628\u06cc\u0633\u062a\u0698\u0646\u0646\u0642\u06a9"
    ],
    "name:deu_x_preferred":[
        "Biestrzynnik"
    ],
    "name:fas_x_preferred":[
        "\u0628\u06cc\u0633\u062a\u0698\u0646\u0646\u06af\u06a9"
    ],
    "name:pol_x_preferred":[
        "Biestrzynnik"
    ],
    "name:ukr_x_preferred":[
        "\u0411\u0435\u0441\u0442\u0448\u0438\u043d\u043d\u0438\u043a"
    ],
    "wof:name":"Biestrzynnik",
    "wof:placetype":"locality"
},
  "geometry": {"coordinates":[18.21368,50.73835],"type":"Point"}
}