{
  "type": "Feature",
  "properties": {
    "gn:admin1_code":"79.0",
    "gn:admin2_code":"1609.0",
    "gn:admin3_code":"160908.0",
    "gn:asciiname":"Biestrzynnik",
    "gn:country_code":"PL",
    "gn:dem":187,
    "gn:feature_class":"P",
    "gn:feature_code":"PPL",
    "gn:name":"Biestrzynnik",
    "gn:population":0,
    "gn:timezone":"Europe/Warsaw",
    "iso:country":"PL",
    "wof:name":"Biestrzynnik",
    "wof:placetype":"locality"
},
  "geometry": {"coordinates":[18.21368,50.73835],"type":"Point"}
}