{
  "type": "Feature",
  "properties": {
    "gn:admin1_code":"82.0",
    "gn:admin2_code":"2202.0",
    "gn:admin3_code":"220204.0",
    "gn:asciiname":"Leska Kolonia",
    "gn:country_code":"PL",
    "gn:dem":138,
    "gn:feature_class":"P",
    "gn:feature_code":"PPL",
    "gn:name":"\u0141\u0119ska Kolonia",
    "gn:population":0,
    "gn:timezone":"Europe/Warsaw",
    "iso:country":"PL",
    "wof:name":"Leska Kolonia",
    "wof:placetype":"locality"
},
  "geometry": {"coordinates":[18.02699,53.8316],"type":"Point"}
}