{
  "type": "Feature",
  "properties": {
    "gn:admin1_code":"77.0",
    "gn:admin2_code":"1209.0",
    "gn:admin3_code":"120906.0",
    "gn:asciiname":"Lyczanka",
    "gn:country_code":"PL",
    "gn:dem":318,
    "gn:feature_class":"P",
    "gn:feature_code":"PPL",
    "gn:name":"\u0141yczanka",
    "gn:population":0,
    "gn:timezone":"Europe/Warsaw",
    "iso:country":"PL",
    "wof:name":"Lyczanka",
    "wof:placetype":"locality"
},
  "geometry": {"coordinates":[19.98207,49.92028],"type":"Point"}
}