{
  "type": "Feature",
  "properties": {
    "gn:admin1_code":"79.0",
    "gn:admin2_code":"1607.0",
    "gn:admin3_code":"160705.0",
    "gn:asciiname":"Chwacowice",
    "gn:country_code":"PL",
    "gn:dem":195,
    "gn:feature_class":"P",
    "gn:feature_code":"PPL",
    "gn:name":"Chwacowice",
    "gn:population":0,
    "gn:timezone":"Europe/Warsaw",
    "iso:country":"PL",
    "wof:name":"Chwacowice",
    "wof:placetype":"neighbourhood"
},
  "geometry": {"coordinates":[17.33333,50.45],"type":"Point"}
}