{
  "type": "Feature",
  "properties": {
    "gn:admin1_code":"86.0",
    "gn:admin2_code":"3004.0",
    "gn:admin3_code":"300404.0",
    "gn:asciiname":"Wilkonice",
    "gn:country_code":"PL",
    "gn:dem":113,
    "gn:feature_class":"P",
    "gn:feature_code":"PPL",
    "gn:name":"Wilkonice",
    "gn:population":0,
    "gn:timezone":"Europe/Warsaw",
    "iso:country":"PL",
    "name:azb_x_preferred":[
        "\u0648\u06cc\u0644\u06a9\u0648\u0646\u0642\u062a\u0633\u0647"
    ],
    "name:fas_x_preferred":[
        "\u0648\u06cc\u0644\u06a9\u0648\u0646\u06af\u062a\u0633\u0647"
    ],
    "name:fra_x_preferred":[
        "Wilkonice"
    ],
    "name:nld_x_preferred":[
        "Wilkonice"
    ],
    "name:pol_x_preferred":[
        "Wilkonice"
    ],
    "name:ukr_x_preferred":[
        "\u0412\u0456\u043b\u044c\u043a\u043e\u043d\u0456\u0446\u0435"
    ],
    "wof:name":"Wilkonice",
    "wof:placetype":"locality"
},
  "geometry": {"coordinates":[17.09541,51.72255],"type":"Point"}
}