{
  "type": "Feature",
  "properties": {
    "gn:country":"PL",
    "gn:fcode":"PPL",
    "gn:population":605,
    "iso:country":"PL",
    "name:ast_x_preferred":[
        "Bia\u0142ka"
    ],
    "name:eng_x_preferred":[
        "Bia\u0142ka"
    ],
    "name:fra_x_preferred":[
        "Bia\u0142ka"
    ],
    "name:pol_x_preferred":[
        "Bia\u0142ka"
    ],
    "name:ukr_x_preferred":[
        "\u0411\u044f\u043b\u043a\u0430"
    ],
    "qs_pg:aaroncc":"PL",
    "qs_pg:gn_country":"PL",
    "qs_pg:gn_fcode":"PPL",
    "qs_pg:gn_pop":605,
    "qs_pg:name":"Bia\u0142ka",
    "qs_pg:name_adm0":"Polska",
    "qs_pg:name_adm1":"Podkarpackie",
    "qs_pg:photos_9k":1,
    "qs_pg:photos_9r":1,
    "qs_pg:photos_all":1,
    "qs_pg:photos_sr":0,
    "qs_pg:pop_sr":2,
    "qs_pg:qs_pg_placetype":"locality",
    "qs_pg:qs_pg_placetype_gp":"Town",
    "qs_pg:woe_adm0":23424923,
    "woe:adm0_id":23424923,
    "woe:name_adm0":"Polska",
    "woe:name_adm1":"Podkarpackie",
    "woe:placetype":"Town",
    "wof:name":"Bia\u0142ka",
    "wof:placetype":"locality",
    "wof:population":605
},
  "geometry": {"coordinates":[22.03514,49.87085],"type":"Point"}
}