{
  "type": "Feature",
  "properties": {
    "gn:country":"PL",
    "gn:fcode":"PPL",
    "gn:population":0,
    "iso:country":"PL",
    "name:ast_x_preferred":[
        "Borzechowo"
    ],
    "name:azb_x_preferred":[
        "\u0628\u0648\u0698\u062e\u0648\u0648\u0648"
    ],
    "name:ceb_x_preferred":[
        "Borzechowo"
    ],
    "name:deu_x_preferred":[
        "Borzechowo"
    ],
    "name:eng_x_preferred":[
        "Borzechowo"
    ],
    "name:fas_x_preferred":[
        "\u0628\u0648\u0698\u062e\u0648\u0648\u0648"
    ],
    "name:fra_x_preferred":[
        "Borzechowo"
    ],
    "name:nan_x_preferred":[
        "Borzechowo"
    ],
    "name:nld_x_preferred":[
        "Borzechowo"
    ],
    "name:pol_x_preferred":[
        "Borzechowo"
    ],
    "name:ukr_x_preferred":[
        "\u0411\u043e\u0436\u0435\u0445\u043e\u0432\u043e"
    ],
    "name:und_x_variant":[
        "Bordzichow"
    ],
    "qs_pg:aaroncc":"PL",
    "qs_pg:gn_country":"PL",
    "qs_pg:gn_fcode":"PPL",
    "qs_pg:gn_pop":0,
    "qs_pg:name":"Borzechowo",
    "qs_pg:name_adm0":"Polska",
    "qs_pg:name_adm1":"Pomorskie",
    "qs_pg:photos":11,
    "qs_pg:photos_1k":2,
    "qs_pg:photos_9k":1,
    "qs_pg:photos_9r":1,
    "qs_pg:photos_all":11,
    "qs_pg:photos_sr":1,
    "qs_pg:pop_sr":0,
    "qs_pg:qs_pg_placetype":"locality",
    "qs_pg:qs_pg_placetype_gp":"Town",
    "qs_pg:woe_adm0":23424923,
    "woe:adm0_id":23424923,
    "woe:name_adm0":"Polska",
    "woe:name_adm1":"Pomorskie",
    "woe:placetype":"Town",
    "wof:name":"Borzechowo",
    "wof:placetype":"locality"
},
  "geometry": {"coordinates":[18.35097,53.88932],"type":"Point"}
}