{
  "type": "Feature",
  "properties": {
    "gn:admin1_code":"84.0",
    "gn:admin2_code":"2609.0",
    "gn:admin3_code":"260907.0",
    "gn:asciiname":"Gorzyczany",
    "gn:country_code":"PL",
    "gn:dem":154,
    "gn:feature_class":"P",
    "gn:feature_code":"PPL",
    "gn:name":"Gorzyczany",
    "gn:population":0,
    "gn:timezone":"Europe/Warsaw",
    "iso:country":"PL",
    "name:ceb_x_preferred":[
        "Gorzyczany"
    ],
    "name:nld_x_preferred":[
        "Gorzyczany"
    ],
    "name:pol_x_preferred":[
        "Gorzyczany"
    ],
    "name:ukr_x_preferred":[
        "\u0490\u043e\u0436\u0438\u0447\u0430\u043d\u0438"
    ],
    "wof:name":"Gorzyczany",
    "wof:placetype":"locality"
},
  "geometry": {"coordinates":[21.61011,50.63759],"type":"Point"}
}