{
  "type": "Feature",
  "properties": {
    "gn:admin1_code":"87.0",
    "gn:admin2_code":"3204.0",
    "gn:admin3_code":"320406.0",
    "gn:asciiname":"Budzieszewice",
    "gn:country_code":"PL",
    "gn:dem":21,
    "gn:feature_class":"P",
    "gn:feature_code":"PPL",
    "gn:name":"Budzieszewice",
    "gn:population":0,
    "gn:timezone":"Europe/Warsaw",
    "iso:country":"PL",
    "name:pol_x_preferred":[
        "Budzieszewice"
    ],
    "name:ukr_x_preferred":[
        "\u0411\u0443\u0434\u0437\u0435\u0448\u0435\u0432\u0456\u0446\u0435"
    ],
    "name:vie_x_preferred":[
        "Budzieszewice"
    ],
    "wof:name":"Budzieszewice",
    "wof:placetype":"locality"
},
  "geometry": {"coordinates":[14.85631,53.69375],"type":"Point"}
}