{
  "type": "Feature",
  "properties": {
    "gn:admin1_code":"76.0",
    "gn:admin2_code":"809.0",
    "gn:admin3_code":"80906.0",
    "gn:asciiname":"Milkowo",
    "gn:country_code":"PL",
    "gn:dem":127,
    "gn:feature_class":"P",
    "gn:feature_code":"PPL",
    "gn:name":"Mi\u0142kowo",
    "gn:population":0,
    "gn:timezone":"Europe/Warsaw",
    "iso:country":"PL",
    "name:fra_x_preferred":[
        "Mi\u0142kowo"
    ],
    "name:pol_x_preferred":[
        "Mi\u0142kowo"
    ],
    "name:und_x_variant":[
        "Mi\u0142kowo"
    ],
    "wof:name":"Milkowo",
    "wof:placetype":"locality"
},
  "geometry": {"coordinates":[15.62505,52.16945],"type":"Point"}
}