{
  "type": "Feature",
  "properties": {
    "gn:admin1_code":"86.0",
    "gn:admin2_code":"3019.0",
    "gn:admin3_code":"301906.0",
    "gn:asciiname":"Dobrzyca",
    "gn:country_code":"PL",
    "gn:dem":66,
    "gn:feature_class":"P",
    "gn:feature_code":"PPL",
    "gn:name":"Dobrzyca",
    "gn:population":0,
    "gn:timezone":"Europe/Warsaw",
    "iso:country":"PL",
    "name:ceb_x_preferred":[
        "Dobrzyca"
    ],
    "name:deu_x_preferred":[
        "Borkendorf"
    ],
    "name:fra_x_preferred":[
        "Dobrzyca"
    ],
    "name:pol_x_preferred":[
        "Dobrzyca"
    ],
    "name:szl_x_preferred":[
        "Dobrzica"
    ],
    "name:ukr_x_preferred":[
        "\u0414\u043e\u0431\u0436\u0438\u0446\u044f"
    ],
    "wof:name":"Dobrzyca",
    "wof:placetype":"locality"
},
  "geometry": {"coordinates":[16.78369,53.22047],"type":"Point"}
}