{
  "type": "Feature",
  "properties": {
    "gn:admin1_code":"81.0",
    "gn:admin2_code":"2005.0",
    "gn:admin3_code":"200503.0",
    "gn:asciiname":"Nowe Jancewicze",
    "gn:country_code":"PL",
    "gn:dem":163,
    "gn:feature_class":"P",
    "gn:feature_code":"PPL",
    "gn:name":"Nowe Jancewicze",
    "gn:population":0,
    "gn:timezone":"Europe/Warsaw",
    "iso:country":"PL",
    "wof:name":"Nowe Jancewicze",
    "wof:placetype":"locality"
},
  "geometry": {"coordinates":[23.27513,52.46251],"type":"Point"}
}