{
  "type": "Feature",
  "properties": {
    "gn:admin1_code":"73.0",
    "gn:admin2_code":"415.0",
    "gn:admin3_code":"41507.0",
    "gn:asciiname":"Zawaly",
    "gn:country_code":"PL",
    "gn:dem":86,
    "gn:feature_class":"P",
    "gn:feature_code":"PPL",
    "gn:name":"Zawa\u0142y",
    "gn:population":0,
    "gn:timezone":"Europe/Warsaw",
    "iso:country":"PL",
    "name:pol_x_preferred":[
        "Zawa\u0142y"
    ],
    "name:ukr_x_preferred":[
        "\u0417\u0430\u0432\u0430\u043b\u0438"
    ],
    "wof:name":"Zawaly",
    "wof:placetype":"locality"
},
  "geometry": {"coordinates":[18.83468,52.98739000000001],"type":"Point"}
}