{
  "type": "Feature",
  "properties": {
    "gn:admin1_code":"86.0",
    "gn:admin2_code":"3024.0",
    "gn:admin3_code":"302408.0",
    "gn:asciiname":"Samolez",
    "gn:country_code":"PL",
    "gn:dem":60,
    "gn:feature_class":"P",
    "gn:feature_code":"PPL",
    "gn:name":"Samo\u0142\u0119\u017c",
    "gn:population":0,
    "gn:timezone":"Europe/Warsaw",
    "iso:country":"PL",
    "name:ceb_x_preferred":[
        "Samo\u0142\u0119\u017c"
    ],
    "name:fra_x_preferred":[
        "Samo\u0142\u0119\u017c"
    ],
    "name:pol_x_preferred":[
        "Samo\u0142\u0119\u017c"
    ],
    "name:ukr_x_preferred":[
        "\u0421\u0430\u043c\u043e\u043b\u0435\u043d\u0436"
    ],
    "name:und_x_variant":[
        "Samo\u0142\u0119\u017c"
    ],
    "wof:name":"Samolez",
    "wof:placetype":"locality"
},
  "geometry": {"coordinates":[16.41933,52.69277],"type":"Point"}
}