{
  "type": "Feature",
  "properties": {
    "gn:admin1_code":"78.0",
    "gn:admin2_code":"1416.0",
    "gn:admin3_code":"141609.0",
    "gn:asciiname":"Brulino Lipskie",
    "gn:cc2":"PL",
    "gn:country_code":"PL",
    "gn:dem":128,
    "gn:feature_class":"P",
    "gn:feature_code":"PPL",
    "gn:name":"Brulino Lipskie",
    "gn:population":0,
    "gn:timezone":"Europe/Warsaw",
    "iso:country":"PL",
    "name:fra_x_preferred":[
        "Brulino-Lipskie"
    ],
    "name:pol_x_preferred":[
        "Brulino-Lipskie"
    ],
    "name:ukr_x_preferred":[
        "\u0411\u0440\u0443\u043b\u0456\u043d\u043e-\u041b\u0456\u043f\u0441\u044c\u043a\u0435"
    ],
    "name:und_x_variant":[
        "Bieliny Brulino Lipskie",
        "Brulino Lipskie"
    ],
    "wof:name":"Brulino Lipskie",
    "wof:placetype":"locality"
},
  "geometry": {"coordinates":[22.2928,52.77338],"type":"Point"}
}