{
  "type": "Feature",
  "properties": {
    "gn:admin1_code":"75.0",
    "gn:admin2_code":"616.0",
    "gn:admin3_code":"61604.0",
    "gn:asciiname":"Budki",
    "gn:country_code":"PL",
    "gn:dem":173,
    "gn:feature_class":"P",
    "gn:feature_code":"PPL",
    "gn:name":"Budki",
    "gn:population":0,
    "gn:timezone":"Europe/Warsaw",
    "iso:country":"PL",
    "name:und_x_variant":[
        "Rososz Budki",
        "Budki"
    ],
    "wof:name":"Budki",
    "wof:placetype":"locality"
},
  "geometry": {"coordinates":[21.99792,51.67623],"type":"Point"}
}