{
  "type": "Feature",
  "properties": {
    "gn:admin1_code":"72.0",
    "gn:admin2_code":"212.0",
    "gn:admin3_code":"21205.0",
    "gn:asciiname":"Klecza",
    "gn:country_code":"PL",
    "gn:dem":359,
    "gn:feature_class":"P",
    "gn:feature_code":"PPL",
    "gn:name":"Klecza",
    "gn:population":0,
    "gn:timezone":"Europe/Warsaw",
    "iso:country":"PL",
    "name:pol_x_preferred":[
        "Klecza"
    ],
    "name:ukr_x_preferred":[
        "\u041a\u043b\u0435\u0447\u0430"
    ],
    "wof:name":"Klecza",
    "wof:placetype":"locality"
},
  "geometry": {"coordinates":[15.63326,51.00824],"type":"Point"}
}