{
  "type": "Feature",
  "properties": {
    "gn:admin1_code":"78.0",
    "gn:admin2_code":"1437.0",
    "gn:admin3_code":"143701.0",
    "gn:asciiname":"Kobylalaka",
    "gn:country_code":"PL",
    "gn:dem":117,
    "gn:feature_class":"P",
    "gn:feature_code":"PPL",
    "gn:name":"Kobyla\u0142\u0105ka",
    "gn:population":0,
    "gn:timezone":"Europe/Warsaw",
    "iso:country":"PL",
    "wof:name":"Kobylalaka",
    "wof:placetype":"locality"
},
  "geometry": {"coordinates":[19.95758,52.96539],"type":"Point"}
}