{
  "type": "Feature",
  "properties": {
    "gn:admin1_code":"77.0",
    "gn:admin2_code":"1201.0",
    "gn:admin3_code":"120105.0",
    "gn:asciiname":"Zbydniow",
    "gn:country_code":"PL",
    "gn:dem":354,
    "gn:feature_class":"P",
    "gn:feature_code":"PPL",
    "gn:name":"Zbydni\u00f3w",
    "gn:population":0,
    "gn:timezone":"Europe/Warsaw",
    "iso:country":"PL",
    "wof:name":"Zbydniow",
    "wof:placetype":"locality"
},
  "geometry": {"coordinates":[20.32969,49.8371],"type":"Point"}
}