{
  "type": "Feature",
  "properties": {
    "gn:admin1_code":"77.0",
    "gn:admin2_code":"1201.0",
    "gn:admin3_code":"120105.0",
    "gn:asciiname":"Zbydniow",
    "gn:country_code":"PL",
    "gn:dem":354,
    "gn:feature_class":"P",
    "gn:feature_code":"PPL",
    "gn:name":"Zbydni\u00f3w",
    "gn:population":0,
    "gn:timezone":"Europe/Warsaw",
    "iso:country":"PL",
    "name:ceb_x_preferred":[
        "Zbydni\u00f3w"
    ],
    "name:pol_x_preferred":[
        "Zbydni\u00f3w"
    ],
    "name:spa_x_preferred":[
        "Zbydni\u00f3w"
    ],
    "name:ukr_x_preferred":[
        "\u0417\u0431\u0438\u0434\u043d\u044e\u0432"
    ],
    "wof:name":"Zbydniow",
    "wof:placetype":"locality"
},
  "geometry": {"coordinates":[20.32969,49.8371],"type":"Point"}
}