{
  "type": "Feature",
  "properties": {
    "iso:country":"PL",
    "name:ceb_x_preferred":[
        "Zakrzew"
    ],
    "name:deu_x_preferred":[
        "Zakrzew"
    ],
    "name:fra_x_preferred":[
        "Zakrzew"
    ],
    "name:ita_x_preferred":[
        "Zakrzew"
    ],
    "name:nld_x_preferred":[
        "Zakrzew"
    ],
    "name:pol_x_preferred":[
        "Zakrzew"
    ],
    "name:rus_x_preferred":[
        "\u0417\u0430\u043a\u0448\u0435\u0432"
    ],
    "name:ukr_x_preferred":[
        "\u0417\u0430\u043a\u0448\u0435\u0432"
    ],
    "wof:coterminous":[
        1125298559
    ],
    "wof:name":"Zakrzew",
    "wof:placetype":"locality"
},
  "geometry": {"coordinates":[21.0268123085498,51.4505115099874],"type":"Point"}
}