{
  "type": "Feature",
  "properties": {
    "iso:country":"PL",
    "name:pol_x_preferred":[
        "Zakrzew"
    ],
    "wof:name":"Zakrzew",
    "wof:placetype":"locality"
},
  "geometry": {"coordinates":[21.0268123085498,51.4505115099874],"type":"Point"}
}