{
  "type": "Feature",
  "properties": {
    "gn:admin1_code":"84.0",
    "gn:admin2_code":"2609.0",
    "gn:admin3_code":"260906.0",
    "gn:asciiname":"Jugoszow",
    "gn:country_code":"PL",
    "gn:dem":205,
    "gn:feature_class":"P",
    "gn:feature_code":"PPL",
    "gn:name":"Jugosz\u00f3w",
    "gn:population":0,
    "gn:timezone":"Europe/Warsaw",
    "iso:country":"PL",
    "name:ceb_x_preferred":[
        "Jugosz\u00f3w"
    ],
    "name:nld_x_preferred":[
        "Jugosz\u00f3w"
    ],
    "name:pol_x_preferred":[
        "Jugosz\u00f3w"
    ],
    "name:ukr_x_preferred":[
        "\u042e\u0491\u043e\u0448\u0443\u0432"
    ],
    "wof:name":"Jugoszow",
    "wof:placetype":"locality"
},
  "geometry": {"coordinates":[21.5447,50.68852],"type":"Point"}
}