{
  "type": "Feature",
  "properties": {
    "gn:gn_country":"PL",
    "gn:gn_fcode":"PPLA3",
    "gn:gn_pop":5173,
    "gn:population":5173,
    "iso:country":"PL",
    "name:azb_x_preferred":[
        "\u0645\u0627\u0631\u06a9\u0644\u0648\u0648\u06cc\u062a\u0633\u0647"
    ],
    "name:deu_x_preferred":[
        "Marklowice"
    ],
    "name:fas_x_preferred":[
        "\u0645\u0627\u0631\u06a9\u0644\u0648\u0648\u06cc\u062a\u0633\u0647"
    ],
    "name:nld_x_preferred":[
        "Marklowice"
    ],
    "name:pol_x_preferred":[
        "Marklowice"
    ],
    "name:szl_x_preferred":[
        "Marklowice"
    ],
    "name:ukr_x_preferred":[
        "\u041c\u0430\u0440\u043a\u043b\u044c\u043e\u0432\u0456\u0446\u0435"
    ],
    "name:unk_x_variant":[
        "Mark\u0142owice"
    ],
    "qs_pg:aaroncc":"PL",
    "qs_pg:gn_country":"PL",
    "qs_pg:gn_fcode":"PPLA3",
    "qs_pg:gn_pop":5173,
    "qs_pg:name":"Marklowice",
    "qs_pg:name_adm0":"Polska",
    "qs_pg:name_adm1":"Sl\u0105skie",
    "qs_pg:photos_9k":1,
    "qs_pg:photos_9r":1,
    "qs_pg:photos_all":2,
    "qs_pg:photos_sr":0,
    "qs_pg:pop_sr":5,
    "qs_pg:qs_pg_placetype":"localadmin",
    "qs_pg:qs_pg_placetype_gp":"LocalAdmin",
    "qs_pg:woe_adm0":23424923,
    "woe:adm0_id":23424923,
    "woe:name_adm0":"Polska",
    "woe:name_adm1":"Sl\u0105skie",
    "woe:placetype":"LocalAdmin",
    "wof:name":"Marklowice",
    "wof:placetype":"localadmin",
    "wof:population":5173
},
  "geometry": {"coordinates":[18.52098,50.01695],"type":"Point"}
}