{
  "type": "Feature",
  "properties": {
    "gn:admin1_code":"78.0",
    "gn:admin2_code":"1435.0",
    "gn:admin3_code":"143506.0",
    "gn:asciiname":"Mosciska",
    "gn:country_code":"PL",
    "gn:dem":96,
    "gn:feature_class":"P",
    "gn:feature_code":"PPL",
    "gn:name":"Mo\u015bciska",
    "gn:population":0,
    "gn:timezone":"Europe/Warsaw",
    "iso:country":"PL",
    "wof:name":"Mosciska",
    "wof:placetype":"locality"
},
  "geometry": {"coordinates":[21.47141,52.48226],"type":"Point"}
}