{
  "type": "Feature",
  "properties": {
    "gn:admin1_code":"77.0",
    "gn:admin2_code":"1206.0",
    "gn:admin3_code":"120608.0",
    "gn:asciiname":"Wola Wieclawska",
    "gn:country_code":"PL",
    "gn:dem":295,
    "gn:feature_class":"P",
    "gn:feature_code":"PPL",
    "gn:name":"Wola Wi\u0119c\u0142awska",
    "gn:population":0,
    "gn:timezone":"Europe/Warsaw",
    "iso:country":"PL",
    "name:pol_x_preferred":[
        "Wola Wi\u0119c\u0142awska"
    ],
    "name:rus_x_preferred":[
        "\u0412\u043e\u043b\u044f-\u0412\u0435\u043d\u0446\u043b\u0430\u0432\u0441\u043a\u0430"
    ],
    "name:ukr_x_preferred":[
        "\u0412\u043e\u043b\u044f-\u0412\u0435\u043d\u0446\u043b\u0430\u0432\u0441\u044c\u043a\u0430"
    ],
    "name:und_x_variant":[
        "Wola Wi\u0119c\u0142awska"
    ],
    "wof:name":"Wola Wieclawska",
    "wof:placetype":"locality"
},
  "geometry": {"coordinates":[20.03333,50.18333],"type":"Point"}
}