{
  "type": "Feature",
  "properties": {
    "gn:admin1_code":"73.0",
    "gn:admin2_code":"416.0",
    "gn:admin3_code":"41605.0",
    "gn:asciiname":"Lubocianik",
    "gn:country_code":"PL",
    "gn:dem":129,
    "gn:feature_class":"P",
    "gn:feature_code":"PPL",
    "gn:name":"Lubocianik",
    "gn:population":0,
    "gn:timezone":"Europe/Warsaw",
    "iso:country":"PL",
    "wof:name":"Lubocianik",
    "wof:placetype":"locality"
},
  "geometry": {"coordinates":[18.11667000000001,53.73333],"type":"Point"}
}