{
  "type": "Feature",
  "properties": {
    "gn:admin1_code":"72.0",
    "gn:admin2_code":"221.0",
    "gn:admin3_code":"22106.0",
    "gn:asciiname":"Rozana",
    "gn:country_code":"PL",
    "gn:dem":557,
    "gn:feature_class":"P",
    "gn:feature_code":"PPL",
    "gn:name":"R\u00f3\u017cana",
    "gn:population":0,
    "gn:timezone":"Europe/Warsaw",
    "iso:country":"PL",
    "name:deu_x_preferred":[
        "R\u00f3\u017cana"
    ],
    "name:pol_x_preferred":[
        "R\u00f3\u017cana"
    ],
    "name:ukr_x_preferred":[
        "\u0420\u0443\u0436\u0430\u043d\u0430"
    ],
    "wof:name":"Rozana",
    "wof:placetype":"locality"
},
  "geometry": {"coordinates":[16.1602,50.67057],"type":"Point"}
}