{
  "type": "Feature",
  "properties": {
    "gn:admin1_code":"78.0",
    "gn:admin2_code":"1424.0",
    "gn:admin3_code":"142406.0",
    "gn:asciiname":"Powielin",
    "gn:country_code":"PL",
    "gn:dem":95,
    "gn:feature_class":"P",
    "gn:feature_code":"PPL",
    "gn:name":"Powielin",
    "gn:population":0,
    "gn:timezone":"Europe/Warsaw",
    "iso:country":"PL",
    "name:fra_x_preferred":[
        "Powielin"
    ],
    "name:pol_x_preferred":[
        "Powielin"
    ],
    "name:ukr_x_preferred":[
        "\u041f\u043e\u0432\u0435\u043b\u0456\u043d"
    ],
    "wof:name":"Powielin",
    "wof:placetype":"locality"
},
  "geometry": {"coordinates":[20.96089,52.55963000000001],"type":"Point"}
}