{
  "type": "Feature",
  "properties": {
    "gn:country":"PL",
    "gn:fcode":"PPL",
    "gn:population":0,
    "iso:country":"PL",
    "name:ast_x_preferred":[
        "Hipolit\u00f3w"
    ],
    "name:eng_x_preferred":[
        "Hipolit\u00f3w"
    ],
    "name:fra_x_preferred":[
        "Hipolit\u00f3w"
    ],
    "name:pol_x_preferred":[
        "Hipolit\u00f3w"
    ],
    "name:szl_x_preferred":[
        "Hipolit\u016fw"
    ],
    "name:ukr_x_preferred":[
        "\u0413\u0456\u043f\u043e\u043b\u0456\u0442\u0443\u0432"
    ],
    "qs_pg:aaroncc":"PL",
    "qs_pg:gn_country":"PL",
    "qs_pg:gn_fcode":"PPL",
    "qs_pg:gn_pop":0,
    "qs_pg:name":"Hipolit\u00f3w",
    "qs_pg:name_adm0":"Polska",
    "qs_pg:name_adm1":"Mazowieckie",
    "qs_pg:photos":7,
    "qs_pg:photos_1k":1,
    "qs_pg:photos_9k":1,
    "qs_pg:photos_9r":1,
    "qs_pg:photos_all":7,
    "qs_pg:photos_sr":1,
    "qs_pg:pop_sr":0,
    "qs_pg:qs_pg_placetype":"locality",
    "qs_pg:qs_pg_placetype_gp":"Town",
    "qs_pg:woe_adm0":23424923,
    "woe:adm0_id":23424923,
    "woe:name_adm0":"Polska",
    "woe:name_adm1":"Mazowieckie",
    "woe:placetype":"Town",
    "wof:name":"Hipolit\u00f3w",
    "wof:placetype":"neighbourhood"
},
  "geometry": {"coordinates":[21.34987,52.22317],"type":"Point"}
}