{
  "type": "Feature",
  "properties": {
    "gn:admin1_code":"78.0",
    "gn:admin2_code":"1420.0",
    "gn:admin3_code":"142004.0",
    "gn:asciiname":"Zarebin",
    "gn:country_code":"PL",
    "gn:dem":99,
    "gn:feature_class":"P",
    "gn:feature_code":"PPL",
    "gn:name":"Zar\u0119bin",
    "gn:population":0,
    "gn:timezone":"Europe/Warsaw",
    "iso:country":"PL",
    "name:fra_x_preferred":[
        "Zar\u0119bin"
    ],
    "name:pol_x_preferred":[
        "Zar\u0119bin"
    ],
    "name:ukr_x_preferred":[
        "\u0417\u0430\u0440\u0435\u043c\u0431\u0456\u043d"
    ],
    "wof:name":"Zarebin",
    "wof:placetype":"locality"
},
  "geometry": {"coordinates":[20.36676,52.41027],"type":"Point"}
}