{
  "type": "Feature",
  "properties": {
    "gn:admin1_code":"78.0",
    "gn:admin2_code":"1424.0",
    "gn:admin3_code":"142402.0",
    "gn:asciiname":"Sokolowo-Parcele",
    "gn:country_code":"PL",
    "gn:dem":83,
    "gn:feature_class":"P",
    "gn:feature_code":"PPL",
    "gn:name":"Soko\u0142owo-Parcele",
    "gn:population":0,
    "gn:timezone":"Europe/Warsaw",
    "iso:country":"PL",
    "wof:name":"Sokolowo-Parcele",
    "wof:placetype":"locality"
},
  "geometry": {"coordinates":[21.3082,52.7582],"type":"Point"}
}