{
  "type": "Feature",
  "properties": {
    "iso:country":"PL",
    "name:eng_x_preferred":[
        "Krzesiny"
    ],
    "name:pol_x_preferred":[
        "Krzesiny"
    ],
    "wof:name":"Krzesiny",
    "wof:placetype":"neighbourhood"
},
  "geometry": {"coordinates":[16.98764464465752,52.3434141614277],"type":"Point"}
}