{
  "type": "Feature",
  "properties": {
    "gn:admin1_code":"87.0",
    "gn:admin2_code":"3204.0",
    "gn:admin3_code":"320404.0",
    "gn:asciiname":"Zabowo",
    "gn:country_code":"PL",
    "gn:dem":51,
    "gn:feature_class":"P",
    "gn:feature_code":"PPL",
    "gn:name":"\u017babowo",
    "gn:population":0,
    "gn:timezone":"Europe/Warsaw",
    "iso:country":"PL",
    "name:und_x_variant":[
        "Gross Sabow",
        "\u017babowo"
    ],
    "wof:name":"Zabowo",
    "wof:placetype":"locality"
},
  "geometry": {"coordinates":[15.19004,53.72107],"type":"Point"}
}