{
  "type": "Feature",
  "properties": {
    "iso:country":"PL",
    "name:eng_x_preferred":[
        "Karolin"
    ],
    "name:pol_x_preferred":[
        "Karolin"
    ],
    "wof:name":"Karolin",
    "wof:placetype":"neighbourhood"
},
  "geometry": {"coordinates":[16.98206564709947,52.43567560041894],"type":"Point"}
}