{
  "type": "Feature",
  "properties": {
    "gn:admin1_code":"85.0",
    "gn:admin2_code":"2814.0",
    "gn:admin3_code":"281410.0",
    "gn:asciiname":"Nerwik",
    "gn:country_code":"PL",
    "gn:dem":135,
    "gn:feature_class":"P",
    "gn:feature_code":"PPL",
    "gn:name":"Nerwik",
    "gn:population":0,
    "gn:timezone":"Europe/Warsaw",
    "iso:country":"PL",
    "name:deu_x_preferred":[
        "Nerwik"
    ],
    "name:nld_x_preferred":[
        "Nerwik"
    ],
    "name:pol_x_preferred":[
        "Nerwik"
    ],
    "name:ukr_x_preferred":[
        "\u041d\u0435\u0440\u0432\u0438\u043a"
    ],
    "name:und_x_variant":[
        "Nerwigk"
    ],
    "wof:name":"Nerwik",
    "wof:placetype":"locality"
},
  "geometry": {"coordinates":[20.81479,53.74734],"type":"Point"}
}