{
  "type": "Feature",
  "properties": {
    "gn:admin1_code":"85.0",
    "gn:admin2_code":"2809.0",
    "gn:admin3_code":"280903.0",
    "gn:asciiname":"Miejska Wola",
    "gn:country_code":"PL",
    "gn:dem":90,
    "gn:feature_class":"P",
    "gn:feature_code":"PPL",
    "gn:name":"Miejska Wola",
    "gn:population":0,
    "gn:timezone":"Europe/Warsaw",
    "iso:country":"PL",
    "name:und_x_variant":[
        "B\u00fcrgerwalde",
        "Miejska Wola"
    ],
    "wof:name":"Miejska Wola",
    "wof:placetype":"locality"
},
  "geometry": {"coordinates":[20.35647,54.15248],"type":"Point"}
}