{
  "type": "Feature",
  "properties": {
    "gn:admin1_code":"85.0",
    "gn:admin2_code":"2816.0",
    "gn:admin3_code":"281603.0",
    "gn:asciiname":"Wiartel",
    "gn:country_code":"PL",
    "gn:dem":124,
    "gn:feature_class":"P",
    "gn:feature_code":"PPL",
    "gn:name":"Wiartel",
    "gn:population":0,
    "gn:timezone":"Europe/Warsaw",
    "iso:country":"PL",
    "name:ceb_x_preferred":[
        "Wiartel"
    ],
    "name:deu_x_preferred":[
        "Wiartel"
    ],
    "name:pol_x_preferred":[
        "Wiartel"
    ],
    "name:ukr_x_preferred":[
        "\u0412\u044f\u0440\u0442\u0435\u043b\u044c"
    ],
    "name:und_x_variant":[
        "Gross Wiartel"
    ],
    "wof:name":"Wiartel",
    "wof:placetype":"locality"
},
  "geometry": {"coordinates":[21.67798,53.59576],"type":"Point"}
}