{
  "type": "Feature",
  "properties": {
    "gn:admin1_code":"82.0",
    "gn:admin2_code":"2215.0",
    "gn:admin3_code":"221505.0",
    "gn:asciiname":"Gniewinko",
    "gn:country_code":"PL",
    "gn:dem":62,
    "gn:feature_class":"P",
    "gn:feature_code":"PPL",
    "gn:name":"Gniewinko",
    "gn:population":0,
    "gn:timezone":"Europe/Warsaw",
    "iso:country":"PL",
    "name:nld_x_preferred":[
        "Gniewinko"
    ],
    "name:pol_x_preferred":[
        "Gniewinko"
    ],
    "name:ukr_x_preferred":[
        "\u0490\u043d\u0435\u0432\u0456\u043d\u043a\u043e"
    ],
    "wof:name":"Gniewinko",
    "wof:placetype":"locality"
},
  "geometry": {"coordinates":[17.97891,54.71533],"type":"Point"}
}