{
  "type": "Feature",
  "properties": {
    "gn:admin1_code":"72.0",
    "gn:admin2_code":"211.0",
    "gn:admin3_code":"21102.0",
    "gn:asciiname":"Pieszkow",
    "gn:country_code":"PL",
    "gn:dem":114,
    "gn:feature_class":"P",
    "gn:feature_code":"PPL",
    "gn:name":"Pieszk\u00f3w",
    "gn:population":0,
    "gn:timezone":"Europe/Warsaw",
    "iso:country":"PL",
    "name:und_x_variant":[
        "Pieszk\u00f3w"
    ],
    "wof:name":"Pieszkow",
    "wof:placetype":"locality"
},
  "geometry": {"coordinates":[16.24004,51.34015],"type":"Point"}
}