{
  "type": "Feature",
  "properties": {
    "gn:admin1_code":"86.0",
    "gn:admin2_code":"3015.0",
    "gn:admin3_code":"301506.0",
    "gn:asciiname":"Stare Czeskie",
    "gn:country_code":"PL",
    "gn:dem":65,
    "gn:feature_class":"P",
    "gn:feature_code":"PPL",
    "gn:name":"Stare Czeskie",
    "gn:population":0,
    "gn:timezone":"Europe/Warsaw",
    "iso:country":"PL",
    "name:pol_x_preferred":[
        "Stare Czeskie"
    ],
    "name:und_x_variant":[
        "Czeskie Stare"
    ],
    "wof:name":"Stare Czeskie",
    "wof:placetype":"locality"
},
  "geometry": {"coordinates":[16.01669,52.25124],"type":"Point"}
}