{
  "type": "Feature",
  "properties": {
    "gn:admin1_code":"81.0",
    "gn:admin2_code":"2006.0",
    "gn:admin3_code":"200602.0",
    "gn:asciiname":"Swidry Dobrzyce",
    "gn:country_code":"PL",
    "gn:dem":169,
    "gn:feature_class":"P",
    "gn:feature_code":"PPL",
    "gn:name":"\u015awidry Dobrzyce",
    "gn:population":0,
    "gn:timezone":"Europe/Warsaw",
    "iso:country":"PL",
    "name:fra_x_preferred":[
        "\u015awidry-Dobrzyce"
    ],
    "name:lit_x_preferred":[
        "\u0160vidr\u0173 Dob\u017eic\u0117"
    ],
    "name:pol_x_preferred":[
        "\u015awidry-Dobrzyce"
    ],
    "name:ukr_x_preferred":[
        "\u0421\u044c\u0432\u0456\u0434\u0440\u0438-\u0414\u043e\u0431\u0436\u0438\u0446\u0435"
    ],
    "name:und_x_variant":[
        "\u015awidry Dobrzyce"
    ],
    "wof:name":"Swidry Dobrzyce",
    "wof:placetype":"locality"
},
  "geometry": {"coordinates":[22.19065,53.45421999999999],"type":"Point"}
}