{
  "type": "Feature",
  "properties": {
    "gn:admin1_code":"75.0",
    "gn:admin2_code":"617.0",
    "gn:admin3_code":"61703.0",
    "gn:asciiname":"Wola Gardzienicka",
    "gn:country_code":"PL",
    "gn:dem":192,
    "gn:feature_class":"P",
    "gn:feature_code":"PPL",
    "gn:name":"Wola Gardzienicka",
    "gn:population":0,
    "gn:timezone":"Europe/Warsaw",
    "iso:country":"PL",
    "name:fra_x_preferred":[
        "Wola Gardzienicka"
    ],
    "name:pol_x_preferred":[
        "Wola Gardzienicka"
    ],
    "name:ukr_x_preferred":[
        "\u0412\u043e\u043b\u044f-\u0490\u0430\u0440\u0434\u0437\u0435\u043d\u0456\u0446\u044c\u043a\u0430"
    ],
    "wof:name":"Wola Gardzienicka",
    "wof:placetype":"locality"
},
  "geometry": {"coordinates":[22.84368,51.08638],"type":"Point"}
}