{
  "type": "Feature",
  "properties": {
    "gn:admin1_code":"81.0",
    "gn:admin2_code":"2008.0",
    "gn:admin3_code":"200802.0",
    "gn:asciiname":"Czarnystok",
    "gn:country_code":"PL",
    "gn:dem":132,
    "gn:feature_class":"P",
    "gn:feature_code":"PPL",
    "gn:name":"Czarnystok",
    "gn:population":0,
    "gn:timezone":"Europe/Warsaw",
    "iso:country":"PL",
    "name:lit_x_preferred":[
        "\u010carnistokas"
    ],
    "name:pol_x_preferred":[
        "Czarnystok"
    ],
    "name:ukr_x_preferred":[
        "\u0427\u0430\u0440\u043d\u0438\u0441\u0442\u043e\u043a"
    ],
    "wof:name":"Czarnystok",
    "wof:placetype":"locality"
},
  "geometry": {"coordinates":[23.07469,53.38795],"type":"Point"}
}