{
  "type": "Feature",
  "properties": {
    "gn:admin1_code":"84.0",
    "gn:admin2_code":"2613.0",
    "gn:admin3_code":"261304.0",
    "gn:asciiname":"Kossow",
    "gn:country_code":"PL",
    "gn:dem":244,
    "gn:feature_class":"P",
    "gn:feature_code":"PPL",
    "gn:name":"Koss\u00f3w",
    "gn:population":0,
    "gn:timezone":"Europe/Warsaw",
    "iso:country":"PL",
    "name:azb_x_preferred":[
        "\u06a9\u0648\u0633\u0633\u0648\u0648"
    ],
    "name:ceb_x_preferred":[
        "Koss\u00f3w"
    ],
    "name:fas_x_preferred":[
        "\u06a9\u0648\u0633\u0633\u0648\u0648"
    ],
    "name:nld_x_preferred":[
        "Koss\u00f3w"
    ],
    "name:pol_x_preferred":[
        "Koss\u00f3w"
    ],
    "name:ukr_x_preferred":[
        "\u041a\u043e\u0441\u0441\u0443\u0432"
    ],
    "wof:name":"Kossow",
    "wof:placetype":"locality"
},
  "geometry": {"coordinates":[20.04096,50.71948],"type":"Point"}
}