{
  "type": "Feature",
  "properties": {
    "gn:admin1_code":"81.0",
    "gn:admin2_code":"2013.0",
    "gn:admin3_code":"201308.0",
    "gn:asciiname":"Jamiolki",
    "gn:cc2":"PL",
    "gn:country_code":"PL",
    "gn:dem":148,
    "gn:feature_class":"P",
    "gn:feature_code":"PPL",
    "gn:name":"Jamio\u0142ki",
    "gn:population":0,
    "gn:timezone":"Europe/Warsaw",
    "iso:country":"PL",
    "name:azb_x_preferred":[
        "\u06cc\u0627\u0645\u06cc\u0648\u0648\u06a9\u06cc-\u0642\u0648\u062c\u0628\u0647"
    ],
    "name:fas_x_preferred":[
        "\u06cc\u0627\u0645\u06cc\u0648\u0648\u06a9\u06cc-\u06af\u0648\u062c\u0628\u0647"
    ],
    "name:lit_x_preferred":[
        "Jamiolki Godzebai"
    ],
    "name:nld_x_preferred":[
        "Jamio\u0142ki-Godzieby"
    ],
    "name:pol_x_preferred":[
        "Jamio\u0142ki-Godzieby"
    ],
    "name:ukr_x_preferred":[
        "\u042f\u043c\u0439\u043e\u043b\u043a\u0456-\u0490\u043e\u0434\u0437\u0435\u0431\u0438"
    ],
    "name:und_x_variant":[
        "Jamio\u0142ki-Godzi\u0119by",
        "Jamio\u0142ki"
    ],
    "name:urd_x_preferred":[
        "\u062c\u0645\u0648\u0648\u06a9\u06cc-\u06af\u0648\u062f\u0632\u06cc\u0628\u06d2"
    ],
    "wof:name":"Jamiolki",
    "wof:placetype":"locality"
},
  "geometry": {"coordinates":[22.66667,53.03333000000001],"type":"Point"}
}