{
  "type": "Feature",
  "properties": {
    "gn:admin1_code":"78.0",
    "gn:admin2_code":"1412.0",
    "gn:admin3_code":"141209.0",
    "gn:asciiname":"Wolka Kaluska",
    "gn:country_code":"PL",
    "gn:dem":181,
    "gn:feature_class":"P",
    "gn:feature_code":"PPL",
    "gn:name":"W\u00f3lka Ka\u0142uska",
    "gn:population":0,
    "gn:timezone":"Europe/Warsaw",
    "iso:country":"PL",
    "name:fra_x_preferred":[
        "W\u00f3lka Ka\u0142uska"
    ],
    "name:pol_x_preferred":[
        "W\u00f3lka Ka\u0142uska"
    ],
    "name:spa_x_preferred":[
        "W\u00f3lka Ka\u0142uska"
    ],
    "name:ukr_x_preferred":[
        "\u0412\u0443\u043b\u044c\u043a\u0430-\u041a\u0430\u043b\u0443\u0441\u044c\u043a\u0430"
    ],
    "wof:name":"Wolka Kaluska",
    "wof:placetype":"locality"
},
  "geometry": {"coordinates":[21.76461,52.23722],"type":"Point"}
}