{
  "type": "Feature",
  "properties": {
    "gn:admin1_code":"75.0",
    "gn:admin2_code":"609.0",
    "gn:admin3_code":"60901.0",
    "gn:asciiname":"Jaroszewice",
    "gn:country_code":"PL",
    "gn:dem":199,
    "gn:feature_class":"P",
    "gn:feature_code":"PPL",
    "gn:name":"Jaroszewice",
    "gn:population":0,
    "gn:timezone":"Europe/Warsaw",
    "iso:country":"PL",
    "wof:name":"Jaroszewice",
    "wof:placetype":"locality"
},
  "geometry": {"coordinates":[22.32851,51.17396],"type":"Point"}
}