{
  "type": "Feature",
  "properties": {
    "gn:admin1_code":"75.0",
    "gn:admin2_code":"609.0",
    "gn:admin3_code":"60901.0",
    "gn:asciiname":"Jaroszewice",
    "gn:country_code":"PL",
    "gn:dem":199,
    "gn:feature_class":"P",
    "gn:feature_code":"PPL",
    "gn:name":"Jaroszewice",
    "gn:population":0,
    "gn:timezone":"Europe/Warsaw",
    "iso:country":"PL",
    "name:azb_x_preferred":[
        "\u06cc\u0627\u0631\u0648\u0634\u0648\u06cc\u062a\u0633\u0647"
    ],
    "name:fas_x_preferred":[
        "\u06cc\u0627\u0631\u0648\u0634\u0648\u06cc\u062a\u0633\u0647"
    ],
    "name:fra_x_preferred":[
        "Jaroszewice"
    ],
    "name:ita_x_preferred":[
        "Jaroszewice"
    ],
    "name:nld_x_preferred":[
        "Jaroszewice"
    ],
    "name:pol_x_preferred":[
        "Jaroszewice"
    ],
    "name:ukr_x_preferred":[
        "\u042f\u0440\u043e\u0448\u0435\u0432\u0456\u0446\u0435"
    ],
    "name:urd_x_preferred":[
        "\u062c\u0631\u0648\u0633\u0632\u0648\u06a9\u06d2"
    ],
    "wof:name":"Jaroszewice",
    "wof:placetype":"locality"
},
  "geometry": {"coordinates":[22.32851,51.17396],"type":"Point"}
}