{
  "type": "Feature",
  "properties": {
    "gn:admin1_code":"78.0",
    "gn:admin2_code":"1401.0",
    "gn:admin3_code":"140102.0",
    "gn:asciiname":"Pacew",
    "gn:country_code":"PL",
    "gn:dem":129,
    "gn:feature_class":"P",
    "gn:feature_code":"PPL",
    "gn:name":"Pacew",
    "gn:population":0,
    "gn:timezone":"Europe/Warsaw",
    "iso:country":"PL",
    "wof:name":"Pacew",
    "wof:placetype":"locality"
},
  "geometry": {"coordinates":[20.88851,51.66768],"type":"Point"}
}