{
  "type": "Feature",
  "properties": {
    "gn:admin1_code":"74.0",
    "gn:admin2_code":"1021.0",
    "gn:admin3_code":"102105.0",
    "gn:asciiname":"Rogow",
    "gn:country_code":"PL",
    "gn:dem":200,
    "gn:feature_class":"P",
    "gn:feature_code":"PPLA3",
    "gn:name":"Rog\u00f3w",
    "gn:population":1500,
    "gn:timezone":"Europe/Warsaw",
    "iso:country":"PL",
    "wof:name":"Rogow",
    "wof:placetype":"locality",
    "wof:population":1500
},
  "geometry": {"coordinates":[19.88654,51.81758],"type":"Point"}
}