{
  "type": "Feature",
  "properties": {
    "gn:admin1_code":"74.0",
    "gn:admin2_code":"1021.0",
    "gn:admin3_code":"102105.0",
    "gn:asciiname":"Rogow",
    "gn:country_code":"PL",
    "gn:dem":200,
    "gn:feature_class":"P",
    "gn:feature_code":"PPLA3",
    "gn:name":"Rog\u00f3w",
    "gn:population":1500,
    "gn:timezone":"Europe/Warsaw",
    "iso:country":"PL",
    "name:azb_x_preferred":[
        "\u0642\u0645\u06cc\u0646\u0627 \u0631\u0648\u0642\u0648\u0648"
    ],
    "name:bel_x_preferred":[
        "\u0420\u043e\u0433\u0430\u045e"
    ],
    "name:ceb_x_preferred":[
        "Rog\u00f3w"
    ],
    "name:eus_x_preferred":[
        "Rog\u00f3w udalerria"
    ],
    "name:fas_x_preferred":[
        "\u06af\u0645\u06cc\u0646\u0627 \u0631\u0648\u06af\u0648\u0648"
    ],
    "name:fra_x_preferred":[
        "Rog\u00f3w"
    ],
    "name:ita_x_preferred":[
        "Rog\u00f3w"
    ],
    "name:nld_x_preferred":[
        "Rog\u00f3w"
    ],
    "name:pol_x_preferred":[
        "Rog\u00f3w"
    ],
    "name:rus_x_preferred":[
        "\u0420\u043e\u0433\u0443\u0432"
    ],
    "name:slk_x_preferred":[
        "Gmina Rog\u00f3w"
    ],
    "name:ukr_x_preferred":[
        "\u0413\u043c\u0456\u043d\u0430 \u0420\u043e\u0491\u0443\u0432"
    ],
    "name:war_x_preferred":[
        "Gmina Rog\u00f3w"
    ],
    "wof:name":"Rogow",
    "wof:placetype":"locality",
    "wof:population":1500
},
  "geometry": {"coordinates":[19.88654,51.81758],"type":"Point"}
}