{
  "type": "Feature",
  "properties": {
    "gn:gn_country":"PL",
    "gn:gn_fcode":"PPL",
    "gn:gn_pop":130,
    "gn:population":130,
    "iso:country":"PL",
    "name:ast_x_preferred":[
        "Witnica"
    ],
    "name:ceb_x_preferred":[
        "Witnica"
    ],
    "name:eng_x_preferred":[
        "Witnica"
    ],
    "name:fra_x_preferred":[
        "Witnica"
    ],
    "name:pol_x_preferred":[
        "Witnica"
    ],
    "name:ukr_x_preferred":[
        "\u0412\u0456\u0442\u043d\u0438\u0446\u044f"
    ],
    "qs_pg:aaroncc":"PL",
    "qs_pg:gn_country":"PL",
    "qs_pg:gn_fcode":"PPL",
    "qs_pg:gn_pop":130,
    "qs_pg:name":"Witnica",
    "qs_pg:name_adm0":"Polska",
    "qs_pg:name_adm1":"Wielkopolskie",
    "qs_pg:photos_9r":0,
    "qs_pg:photos_sr":0,
    "qs_pg:pop_sr":1,
    "qs_pg:qs_pg_placetype":"locality",
    "qs_pg:qs_pg_placetype_gp":"Town",
    "qs_pg:woe_adm0":23424923,
    "woe:adm0_id":23424923,
    "woe:name_adm0":"Polska",
    "woe:name_adm1":"Wielkopolskie",
    "woe:placetype":"Town",
    "wof:name":"Witnica",
    "wof:placetype":"locality",
    "wof:population":130
},
  "geometry": {"coordinates":[18.05011,52.11025],"type":"Point"}
}