{
  "type": "Feature",
  "properties": {
    "gn:admin1_code":"72.0",
    "gn:admin2_code":"209.0",
    "gn:admin3_code":"20902.0",
    "gn:asciiname":"Goliszow",
    "gn:country_code":"PL",
    "gn:dem":136,
    "gn:feature_class":"P",
    "gn:feature_code":"PPL",
    "gn:name":"Golisz\u00f3w",
    "gn:population":0,
    "gn:timezone":"Europe/Warsaw",
    "iso:country":"PL",
    "name:deu_x_historical":[
        "G\u00f6llschau"
    ],
    "name:deu_x_preferred":[
        "G\u00f6llschau"
    ],
    "name:und_x_variant":[
        "Golisz\u00f3w"
    ],
    "wof:name":"Goliszow",
    "wof:placetype":"locality"
},
  "geometry": {"coordinates":[15.98162,51.27997],"type":"Point"}
}