{
  "type": "Feature",
  "properties": {
    "gn:admin1_code":"74.0",
    "gn:admin2_code":"1017.0",
    "gn:admin3_code":"101707.0",
    "gn:asciiname":"Zalecze Male",
    "gn:country_code":"PL",
    "gn:dem":203,
    "gn:feature_class":"P",
    "gn:feature_code":"PPL",
    "gn:name":"Za\u0142\u0119cze Ma\u0142e",
    "gn:population":0,
    "gn:timezone":"Europe/Warsaw",
    "iso:country":"PL",
    "name:pol_x_preferred":[
        "Za\u0142\u0119cze Ma\u0142e"
    ],
    "name:ukr_x_preferred":[
        "\u0417\u0430\u043b\u0435\u043d\u0447\u0435-\u041c\u0430\u043b\u0456"
    ],
    "wof:name":"Zalecze Male",
    "wof:placetype":"locality"
},
  "geometry": {"coordinates":[18.7298,51.0812],"type":"Point"}
}