{
  "type": "Feature",
  "properties": {
    "gn:admin1_code":"84.0",
    "gn:admin2_code":"2601.0",
    "gn:admin3_code":"260107.0",
    "gn:asciiname":"Kargow",
    "gn:country_code":"PL",
    "gn:dem":199,
    "gn:feature_class":"P",
    "gn:feature_code":"PPL",
    "gn:name":"Karg\u00f3w",
    "gn:population":0,
    "gn:timezone":"Europe/Warsaw",
    "iso:country":"PL",
    "name:ita_x_preferred":[
        "Karg\u00f3w"
    ],
    "name:pol_x_preferred":[
        "Karg\u00f3w"
    ],
    "name:ukr_x_preferred":[
        "\u041a\u0430\u0440\u0491\u0443\u0432"
    ],
    "wof:name":"Kargow",
    "wof:placetype":"locality"
},
  "geometry": {"coordinates":[20.92449,50.51594],"type":"Point"}
}