{
  "type": "Feature",
  "properties": {
    "gn:admin1_code":"78.0",
    "gn:admin2_code":"1429.0",
    "gn:admin3_code":"142903.0",
    "gn:asciiname":"Natolin",
    "gn:country_code":"PL",
    "gn:dem":106,
    "gn:feature_class":"P",
    "gn:feature_code":"PPL",
    "gn:name":"Natolin",
    "gn:population":0,
    "gn:timezone":"Europe/Warsaw",
    "iso:country":"PL",
    "name:azb_x_preferred":[
        "\u0646\u0627\u062a\u0648\u0644\u06cc\u0646"
    ],
    "name:fas_x_preferred":[
        "\u0646\u0627\u062a\u0648\u0644\u06cc\u0646"
    ],
    "name:fra_x_preferred":[
        "Natolin"
    ],
    "name:lit_x_preferred":[
        "Natolinas"
    ],
    "name:pol_x_preferred":[
        "Natolin"
    ],
    "name:ukr_x_preferred":[
        "\u041d\u0430\u0442\u043e\u043b\u0456\u043d"
    ],
    "name:und_x_variant":[
        "Natalin"
    ],
    "wof:name":"Natolin",
    "wof:placetype":"locality"
},
  "geometry": {"coordinates":[22.30537,52.65262],"type":"Point"}
}