{
  "type": "Feature",
  "properties": {
    "gn:admin1_code":"78.0",
    "gn:admin2_code":"1429.0",
    "gn:admin3_code":"142903.0",
    "gn:asciiname":"Natolin",
    "gn:country_code":"PL",
    "gn:dem":106,
    "gn:feature_class":"P",
    "gn:feature_code":"PPL",
    "gn:name":"Natolin",
    "gn:population":0,
    "gn:timezone":"Europe/Warsaw",
    "iso:country":"PL",
    "name:und_x_variant":[
        "Natalin",
        "Natolin"
    ],
    "wof:name":"Natolin",
    "wof:placetype":"locality"
},
  "geometry": {"coordinates":[22.30537,52.65262],"type":"Point"}
}