{
  "type": "Feature",
  "properties": {
    "gn:admin1_code":"78.0",
    "gn:admin2_code":"1420.0",
    "gn:admin3_code":"142008.0",
    "gn:asciiname":"Zakobiel Mala",
    "gn:country_code":"PL",
    "gn:dem":94,
    "gn:feature_class":"P",
    "gn:feature_code":"PPL",
    "gn:name":"Zakobiel Ma\u0142a",
    "gn:population":0,
    "gn:timezone":"Europe/Warsaw",
    "iso:country":"PL",
    "wof:name":"Zakobiel Mala",
    "wof:placetype":"locality"
},
  "geometry": {"coordinates":[20.67738,52.61134000000001],"type":"Point"}
}