{
  "type": "Feature",
  "properties": {
    "gn:admin1_code":"85.0",
    "gn:admin2_code":"2819.0",
    "gn:admin3_code":"281903.0",
    "gn:asciiname":"Wilkowo",
    "gn:country_code":"PL",
    "gn:dem":120,
    "gn:feature_class":"P",
    "gn:feature_code":"PPL",
    "gn:name":"Wilkowo",
    "gn:population":0,
    "gn:timezone":"Europe/Warsaw",
    "iso:country":"PL",
    "name:und_x_variant":[
        "Gerolswalde",
        "Wilkowen",
        "Geroldswalde",
        "Wilkowo"
    ],
    "wof:name":"Wilkowo",
    "wof:placetype":"locality"
},
  "geometry": {"coordinates":[21.72855,54.26743],"type":"Point"}
}