{
  "type": "Feature",
  "properties": {
    "gn:admin1_code":"72.0",
    "gn:admin2_code":"208.0",
    "gn:admin3_code":"20806.0",
    "gn:asciiname":"Plawnica",
    "gn:country_code":"PL",
    "gn:dem":358,
    "gn:feature_class":"P",
    "gn:feature_code":"PPL",
    "gn:name":"P\u0142awnica",
    "gn:population":0,
    "gn:timezone":"Europe/Warsaw",
    "iso:country":"PL",
    "name:deu_x_preferred":[
        "P\u0142awnica"
    ],
    "name:pol_x_preferred":[
        "P\u0142awnica"
    ],
    "name:ukr_x_preferred":[
        "\u041f\u043b\u0430\u0432\u043d\u0438\u0446\u044f"
    ],
    "wof:name":"Plawnica",
    "wof:placetype":"locality"
},
  "geometry": {"coordinates":[16.67505,50.29207],"type":"Point"}
}