{
  "type": "Feature",
  "properties": {
    "gn:admin1_code":"72.0",
    "gn:admin2_code":"213.0",
    "gn:admin3_code":"21303.0",
    "gn:asciiname":"Ostrowasy",
    "gn:country_code":"PL",
    "gn:dem":130,
    "gn:feature_class":"P",
    "gn:feature_code":"PPL",
    "gn:name":"Ostrow\u0105sy",
    "gn:population":0,
    "gn:timezone":"Europe/Warsaw",
    "iso:country":"PL",
    "name:pol_x_preferred":[
        "Ostrow\u0105sy"
    ],
    "name:ukr_x_preferred":[
        "\u041e\u0441\u0442\u0440\u043e\u0432\u043e\u043d\u0441\u0438"
    ],
    "name:und_x_variant":[
        "Wiesenthal",
        "Ostrow\u0105s"
    ],
    "wof:name":"Ostrowasy",
    "wof:placetype":"locality"
},
  "geometry": {"coordinates":[17.47476,51.60476],"type":"Point"}
}