{
  "type": "Feature",
  "properties": {
    "gn:admin1_code":"78.0",
    "gn:admin2_code":"1428.0",
    "gn:admin3_code":"142803.0",
    "gn:asciiname":"Brzozowiec",
    "gn:country_code":"PL",
    "gn:dem":86,
    "gn:feature_class":"P",
    "gn:feature_code":"PPL",
    "gn:name":"Brzozowiec",
    "gn:population":0,
    "gn:timezone":"Europe/Warsaw",
    "iso:country":"PL",
    "name:fra_x_preferred":[
        "Brzozowiec"
    ],
    "name:pol_x_preferred":[
        "Brzozowiec"
    ],
    "name:ukr_x_preferred":[
        "\u0411\u0436\u043e\u0437\u043e\u0432\u0435\u0446\u044c"
    ],
    "wof:name":"Brzozowiec",
    "wof:placetype":"locality"
},
  "geometry": {"coordinates":[20.02034,52.31482000000001],"type":"Point"}
}