{
  "type": "Feature",
  "properties": {
    "gn:population":3159,
    "iso:country":"PL",
    "name:ast_x_preferred":[
        "W\u0142oszakowice"
    ],
    "name:azb_x_preferred":[
        "\u0648\u0648\u0648\u0634\u0627\u06a9\u0648\u0648\u06cc\u062a\u0633\u0647"
    ],
    "name:ceb_x_preferred":[
        "W\u0142oszakowice"
    ],
    "name:deu_x_preferred":[
        "W\u0142oszakowice"
    ],
    "name:eng_x_preferred":[
        "W\u0142oszakowice"
    ],
    "name:fas_x_preferred":[
        "\u0648\u0648\u0648\u0634\u0627\u06a9\u0648\u0648\u06cc\u062a\u0633\u0647"
    ],
    "name:fra_x_preferred":[
        "W\u0142oszakowice"
    ],
    "name:hun_x_preferred":[
        "W\u0142oszakowice"
    ],
    "name:nld_x_preferred":[
        "W\u0142oszakowice"
    ],
    "name:pol_x_preferred":[
        "W\u0142oszakowice"
    ],
    "name:ukr_x_preferred":[
        "\u0412\u043b\u043e\u0448\u0430\u043a\u043e\u0432\u0456\u0446\u0435"
    ],
    "qs:a0":"Rzeczpospolita Polska",
    "qs:a1":"*Wielkopolskie",
    "qs:a1r":"0",
    "qs:a2":"Leszczynski",
    "qs:adm0":"Rzeczpospolita Polska",
    "qs:la":"W\u0142oszakowice",
    "qs:la_lc":"*PL3013072",
    "qs:level":"locality",
    "qs:loc":"W\u0142oszakowice",
    "qs:loc_alt":"Wloszakowice",
    "qs:pop":0,
    "qs:type":"rural point-in-poly",
    "wd:wordcount":91,
    "wof:name":"W\u0142oszakowice",
    "wof:placetype":"locality",
    "wof:population":3159
},
  "geometry": {"coordinates":[16.369793061872,51.9289629045575],"type":"Point"}
}