{
  "type": "Feature",
  "properties": {
    "gn:admin1_code":"73.0",
    "gn:admin2_code":"414.0",
    "gn:admin3_code":"41405.0",
    "gn:asciiname":"Cisiny",
    "gn:country_code":"PL",
    "gn:dem":102,
    "gn:feature_class":"P",
    "gn:feature_code":"PPL",
    "gn:name":"Cisiny",
    "gn:population":0,
    "gn:timezone":"Europe/Warsaw",
    "iso:country":"PL",
    "name:pol_x_preferred":[
        "Cisiny"
    ],
    "wof:name":"Cisiny",
    "wof:placetype":"locality"
},
  "geometry": {"coordinates":[18.13749,53.51712],"type":"Point"}
}