{
  "type": "Feature",
  "properties": {
    "gn:admin1_code":"79.0",
    "gn:admin2_code":"1607.0",
    "gn:admin3_code":"160701.0",
    "gn:asciiname":"Gieralcice",
    "gn:country_code":"PL",
    "gn:dem":283,
    "gn:feature_class":"P",
    "gn:feature_code":"PPL",
    "gn:name":"Giera\u0142cice",
    "gn:population":0,
    "gn:timezone":"Europe/Warsaw",
    "iso:country":"PL",
    "name:ceb_x_preferred":[
        "Giera\u0142cice"
    ],
    "name:pol_x_preferred":[
        "Giera\u0142cice"
    ],
    "name:ukr_x_preferred":[
        "\u0490\u0435\u0440\u0430\u043b\u0446\u0438\u0446\u0435"
    ],
    "wof:name":"Gieralcice",
    "wof:placetype":"locality"
},
  "geometry": {"coordinates":[17.31771,50.34623],"type":"Point"}
}