{
  "type": "Feature",
  "properties": {
    "gn:admin1_code":"84.0",
    "gn:admin2_code":"2605.0",
    "gn:admin3_code":"260504.0",
    "gn:asciiname":"Wilczkowice",
    "gn:country_code":"PL",
    "gn:dem":249,
    "gn:feature_class":"P",
    "gn:feature_code":"PPL",
    "gn:name":"Wilczkowice",
    "gn:population":0,
    "gn:timezone":"Europe/Warsaw",
    "iso:country":"PL",
    "wof:name":"Wilczkowice",
    "wof:placetype":"locality"
},
  "geometry": {"coordinates":[20.21667,51.03944],"type":"Point"}
}