{
  "type": "Feature",
  "properties": {
    "gn:admin1_code":"81.0",
    "gn:admin2_code":"2007.0",
    "gn:admin3_code":"200702.0",
    "gn:asciiname":"Jarnuty",
    "gn:country_code":"PL",
    "gn:dem":119,
    "gn:feature_class":"P",
    "gn:feature_code":"PPL",
    "gn:name":"Jarnuty",
    "gn:population":0,
    "gn:timezone":"Europe/Warsaw",
    "iso:country":"PL",
    "name:azb_x_preferred":[
        "\u06cc\u0627\u0631\u0646\u0648\u062a\u0647"
    ],
    "name:fas_x_preferred":[
        "\u06cc\u0627\u0631\u0646\u0648\u062a\u0647"
    ],
    "name:fra_x_preferred":[
        "Jarnuty"
    ],
    "name:lit_x_preferred":[
        "Jarnutai"
    ],
    "name:pol_x_preferred":[
        "Jarnuty"
    ],
    "name:ukr_x_preferred":[
        "\u042f\u0440\u043d\u0443\u0442\u0438"
    ],
    "name:urd_x_preferred":[
        "\u062c\u0631\u0646\u062a\u06d2"
    ],
    "wof:name":"Jarnuty",
    "wof:placetype":"locality"
},
  "geometry": {"coordinates":[22.00253,53.15789],"type":"Point"}
}