{
  "type": "Feature",
  "properties": {
    "gn:admin1_code":"87.0",
    "gn:admin2_code":"3209.0",
    "gn:admin3_code":"320906.0",
    "gn:asciiname":"Jacinki",
    "gn:country_code":"PL",
    "gn:dem":152,
    "gn:feature_class":"P",
    "gn:feature_code":"PPL",
    "gn:name":"Jacinki",
    "gn:population":0,
    "gn:timezone":"Europe/Warsaw",
    "iso:country":"PL",
    "name:und_x_variant":[
        "Jatzingen",
        "Jacinki"
    ],
    "wof:name":"Jacinki",
    "wof:placetype":"locality"
},
  "geometry": {"coordinates":[16.62312,54.13255],"type":"Point"}
}