{
  "type": "Feature",
  "properties": {
    "gn:admin1_code":"87.0",
    "gn:admin2_code":"3209.0",
    "gn:admin3_code":"320906.0",
    "gn:asciiname":"Jacinki",
    "gn:country_code":"PL",
    "gn:dem":152,
    "gn:feature_class":"P",
    "gn:feature_code":"PPL",
    "gn:name":"Jacinki",
    "gn:population":0,
    "gn:timezone":"Europe/Warsaw",
    "iso:country":"PL",
    "name:azb_x_preferred":[
        "\u06cc\u0627\u0686\u06cc\u0646\u06a9\u06cc"
    ],
    "name:ceb_x_preferred":[
        "Jacinki"
    ],
    "name:deu_x_preferred":[
        "Jacinki"
    ],
    "name:fas_x_preferred":[
        "\u06cc\u0627\u0686\u06cc\u0646\u06a9\u06cc"
    ],
    "name:pol_x_preferred":[
        "Jacinki"
    ],
    "name:ukr_x_preferred":[
        "\u042f\u0446\u0438\u043d\u043a\u0456"
    ],
    "name:und_x_variant":[
        "Jatzingen"
    ],
    "name:urd_x_preferred":[
        "\u062c\u06a9\u0646\u06a9\u06cc"
    ],
    "name:vie_x_preferred":[
        "Jacinki"
    ],
    "wof:name":"Jacinki",
    "wof:placetype":"locality"
},
  "geometry": {"coordinates":[16.62312,54.13255],"type":"Point"}
}