{
  "type": "Feature",
  "properties": {
    "gn:admin1_code":"84.0",
    "gn:admin2_code":"2602.0",
    "gn:admin3_code":"260202.0",
    "gn:asciiname":"Laskow",
    "gn:country_code":"PL",
    "gn:dem":239,
    "gn:feature_class":"P",
    "gn:feature_code":"PPL",
    "gn:name":"Lask\u00f3w",
    "gn:population":0,
    "gn:timezone":"Europe/Warsaw",
    "iso:country":"PL",
    "name:und_x_variant":[
        "Lask\u00f3w"
    ],
    "wof:name":"Laskow",
    "wof:placetype":"locality"
},
  "geometry": {"coordinates":[20.28721,50.68474000000001],"type":"Point"}
}