{
  "type": "Feature",
  "properties": {
    "gn:admin1_code":"78.0",
    "gn:admin2_code":"1436.0",
    "gn:admin3_code":"143605.0",
    "gn:asciiname":"Szczescie",
    "gn:country_code":"PL",
    "gn:dem":163,
    "gn:feature_class":"P",
    "gn:feature_code":"PPL",
    "gn:name":"Szcz\u0119\u015bcie",
    "gn:population":0,
    "gn:timezone":"Europe/Warsaw",
    "iso:country":"PL",
    "wof:name":"Szczescie",
    "wof:placetype":"locality"
},
  "geometry": {"coordinates":[21.65302,51.36374],"type":"Point"}
}