{
  "type": "Feature",
  "properties": {
    "gn:admin1_code":"78.0",
    "gn:admin2_code":"1436.0",
    "gn:admin3_code":"143605.0",
    "gn:asciiname":"Szczescie",
    "gn:country_code":"PL",
    "gn:dem":163,
    "gn:feature_class":"P",
    "gn:feature_code":"PPL",
    "gn:name":"Szcz\u0119\u015bcie",
    "gn:population":0,
    "gn:timezone":"Europe/Warsaw",
    "iso:country":"PL",
    "name:ceb_x_preferred":[
        "Szcz\u0119\u015bcie"
    ],
    "name:fra_x_preferred":[
        "Szcz\u0119\u015bcie"
    ],
    "name:pol_x_preferred":[
        "Szcz\u0119\u015bcie"
    ],
    "name:ukr_x_preferred":[
        "\u0429\u0435\u043d\u0441\u044c\u0446\u0435"
    ],
    "wof:name":"Szczescie",
    "wof:placetype":"locality"
},
  "geometry": {"coordinates":[21.65302,51.36374],"type":"Point"}
}