{
  "type": "Feature",
  "properties": {
    "gn:admin1_code":"83.0",
    "gn:admin2_code":"2409.0",
    "gn:admin3_code":"240901.0",
    "gn:asciiname":"Potaznia",
    "gn:country_code":"PL",
    "gn:dem":309,
    "gn:feature_class":"P",
    "gn:feature_code":"PPL",
    "gn:name":"Pota\u017cnia",
    "gn:population":0,
    "gn:timezone":"Europe/Warsaw",
    "iso:country":"PL",
    "name:und_x_variant":[
        "Potasznia",
        "Pota\u017cnia"
    ],
    "wof:name":"Potaznia",
    "wof:placetype":"locality"
},
  "geometry": {"coordinates":[19.28196,50.55829],"type":"Point"}
}