{
  "type": "Feature",
  "properties": {
    "gn:admin1_code":"78.0",
    "gn:admin2_code":"1419.0",
    "gn:admin3_code":"141914.0",
    "gn:asciiname":"Parcele Bromierzyk",
    "gn:country_code":"PL",
    "gn:dem":135,
    "gn:feature_class":"P",
    "gn:feature_code":"PPL",
    "gn:name":"Parcele Bromierzyk",
    "gn:population":0,
    "gn:timezone":"Europe/Warsaw",
    "iso:country":"PL",
    "wof:name":"Parcele Bromierzyk",
    "wof:placetype":"locality"
},
  "geometry": {"coordinates":[20.01667,52.65],"type":"Point"}
}