{
  "type": "Feature",
  "properties": {
    "gn:admin1_code":"83.0",
    "gn:admin2_code":"2413.0",
    "gn:admin3_code":"241307.0",
    "gn:asciiname":"Stare Chechlo",
    "gn:cc2":"PL",
    "gn:country_code":"PL",
    "gn:dem":298,
    "gn:feature_class":"P",
    "gn:feature_code":"PPL",
    "gn:name":"Stare Chech\u0142o",
    "gn:population":0,
    "gn:timezone":"Europe/Warsaw",
    "iso:country":"PL",
    "name:und_x_variant":[
        "Chech\u0142o Stare",
        "Stare Chech\u0142o"
    ],
    "wof:name":"Stare Chechlo",
    "wof:placetype":"locality"
},
  "geometry": {"coordinates":[18.93333,50.45],"type":"Point"}
}