{
  "type": "Feature",
  "properties": {
    "gn:admin1_code":"84.0",
    "gn:admin2_code":"2609.0",
    "gn:admin3_code":"260907.0",
    "gn:asciiname":"Smiechowice",
    "gn:country_code":"PL",
    "gn:dem":160,
    "gn:feature_class":"P",
    "gn:feature_code":"PPL",
    "gn:name":"\u015amiechowice",
    "gn:population":0,
    "gn:timezone":"Europe/Warsaw",
    "iso:country":"PL",
    "name:pol_x_preferred":[
        "\u015amiechowice"
    ],
    "name:ukr_x_preferred":[
        "\u0421\u044c\u043c\u0435\u0445\u043e\u0432\u0456\u0446\u0435"
    ],
    "wof:name":"Smiechowice",
    "wof:placetype":"locality"
},
  "geometry": {"coordinates":[21.62001,50.65896],"type":"Point"}
}