{
  "type": "Feature",
  "properties": {
    "gn:admin1_code":"84.0",
    "gn:admin2_code":"2609.0",
    "gn:admin3_code":"260907.0",
    "gn:asciiname":"Smiechowice",
    "gn:country_code":"PL",
    "gn:dem":160,
    "gn:feature_class":"P",
    "gn:feature_code":"PPL",
    "gn:name":"\u015amiechowice",
    "gn:population":0,
    "gn:timezone":"Europe/Warsaw",
    "iso:country":"PL",
    "name:und_x_variant":[
        "\u015amiechowice"
    ],
    "wof:name":"Smiechowice",
    "wof:placetype":"locality"
},
  "geometry": {"coordinates":[21.62001,50.65896],"type":"Point"}
}