{
  "type": "Feature",
  "properties": {
    "gn:admin1_code":"77.0",
    "gn:admin2_code":"1204.0",
    "gn:admin3_code":"120402.0",
    "gn:asciiname":"Zagrody",
    "gn:country_code":"PL",
    "gn:dem":190,
    "gn:feature_class":"P",
    "gn:feature_code":"PPL",
    "gn:name":"Zagrody",
    "gn:population":0,
    "gn:timezone":"Europe/Warsaw",
    "iso:country":"PL",
    "name:pol_x_preferred":[
        "Zagrody"
    ],
    "name:urd_x_preferred":[
        "\u0632\u06af\u0631\u0648\u062f\u06d2"
    ],
    "wof:name":"Zagrody",
    "wof:placetype":"locality"
},
  "geometry": {"coordinates":[20.99437,50.2003],"type":"Point"}
}