{
  "type": "Feature",
  "properties": {
    "gn:country":"PL",
    "gn:fcode":"PPLA3",
    "gn:population":1722,
    "iso:country":"PL",
    "name:azb_x_preferred":[
        "\u0634\u0686\u0648\u0631\u0648\u0648\u0627"
    ],
    "name:fas_x_preferred":[
        "\u0634\u0686\u0648\u0631\u0648\u0648\u0627"
    ],
    "name:fra_x_preferred":[
        "Szczurowa"
    ],
    "name:nld_x_preferred":[
        "Szczurowa"
    ],
    "name:pol_x_preferred":[
        "Szczurowa"
    ],
    "name:ukr_x_preferred":[
        "\u0429\u0443\u0440\u043e\u0432\u0430"
    ],
    "qs_pg:aaroncc":"PL",
    "qs_pg:gn_country":"PL",
    "qs_pg:gn_fcode":"PPLA3",
    "qs_pg:gn_pop":1722,
    "qs_pg:name":"Szczurowa",
    "qs_pg:name_adm0":"Polska",
    "qs_pg:name_adm1":"Ma\u0142opolskie",
    "qs_pg:photos":3,
    "qs_pg:photos_1k":1,
    "qs_pg:photos_9k":1,
    "qs_pg:photos_9r":1,
    "qs_pg:photos_all":10,
    "qs_pg:photos_sr":1,
    "qs_pg:pop_sr":3,
    "qs_pg:qs_pg_placetype":"localadmin",
    "qs_pg:qs_pg_placetype_gp":"LocalAdmin",
    "qs_pg:woe_adm0":23424923,
    "woe:adm0_id":23424923,
    "woe:name_adm0":"Polska",
    "woe:name_adm1":"Ma\u0142opolskie",
    "woe:placetype":"LocalAdmin",
    "wof:name":"Szczurowa",
    "wof:placetype":"localadmin",
    "wof:population":1722
},
  "geometry": {"coordinates":[20.6361,50.11915],"type":"Point"}
}