{
  "type": "Feature",
  "properties": {
    "gn:admin1_code":"76",
    "gn:admin2_code":"0801",
    "gn:admin3_code":"80102.0",
    "gn:asciiname":"Jeniniec",
    "gn:country_code":"PL",
    "gn:dem":15,
    "gn:feature_class":"P",
    "gn:feature_code":"PPL",
    "gn:name":"Jeniniec",
    "gn:population":0,
    "gn:timezone":"Europe/Warsaw",
    "iso:country":"PL",
    "name:azb_x_preferred":[
        "\u06cc\u0646\u0642\u0646\u0642\u062a\u0633"
    ],
    "name:deu_x_historical":[
        "Ober Gennin"
    ],
    "name:deu_x_preferred":[
        "Ober Gennin"
    ],
    "name:fas_x_preferred":[
        "\u06cc\u0646\u06af\u0646\u06af\u062a\u0633"
    ],
    "name:fra_x_preferred":[
        "Jeniniec"
    ],
    "name:nld_x_preferred":[
        "Jeniniec"
    ],
    "name:pol_x_preferred":[
        "Jeniniec"
    ],
    "name:ukr_x_preferred":[
        "\u0404\u043d\u0456\u043d\u0435\u0446\u044c"
    ],
    "wof:name":"Jeniniec",
    "wof:placetype":"locality"
},
  "geometry": {"coordinates":[15.08663,52.65676],"type":"Point"}
}