{
  "type": "Feature",
  "properties": {
    "gn:country":"PL",
    "gn:fcode":"PPL",
    "gn:population":393,
    "iso:country":"PL",
    "name:ast_x_preferred":[
        "Lubowidz"
    ],
    "name:ceb_x_preferred":[
        "Lubowidz"
    ],
    "name:ces_x_preferred":[
        "Lubowidz"
    ],
    "name:che_x_preferred":[
        "\u041b\u044e\u0431\u043e\u0432\u0438\u0434\u0437"
    ],
    "name:csb_x_preferred":[
        "L\u00ebb\u00f2widz"
    ],
    "name:deu_x_preferred":[
        "Lubowidz"
    ],
    "name:eng_x_preferred":[
        "Lubowidz"
    ],
    "name:fra_x_preferred":[
        "Lubowidz"
    ],
    "name:nan_x_preferred":[
        "Lubowidz"
    ],
    "name:pol_x_preferred":[
        "Lubowidz"
    ],
    "name:tat_x_preferred":[
        "\u041b\u044e\u0431\u043e\u0432\u0438\u0434\u0437"
    ],
    "name:ukr_x_preferred":[
        "\u041b\u044e\u0431\u043e\u0432\u0456\u0434\u0437"
    ],
    "qs_pg:aaroncc":"PL",
    "qs_pg:gn_country":"PL",
    "qs_pg:gn_fcode":"PPL",
    "qs_pg:gn_pop":393,
    "qs_pg:name":"Lubowidz",
    "qs_pg:name_adm0":"Polska",
    "qs_pg:name_adm1":"Pomorskie",
    "qs_pg:photos_9k":1,
    "qs_pg:photos_9r":1,
    "qs_pg:photos_all":1,
    "qs_pg:photos_sr":0,
    "qs_pg:pop_sr":2,
    "qs_pg:qs_pg_placetype":"locality",
    "qs_pg:qs_pg_placetype_gp":"Town",
    "qs_pg:woe_adm0":23424923,
    "woe:adm0_id":23424923,
    "woe:name_adm0":"Polska",
    "woe:name_adm1":"Pomorskie",
    "woe:placetype":"Town",
    "wof:name":"Lubowidz",
    "wof:placetype":"locality",
    "wof:population":393
},
  "geometry": {"coordinates":[17.81407,54.5425],"type":"Point"}
}