{
  "type": "Feature",
  "properties": {
    "gn:admin1_code":"73.0",
    "gn:admin2_code":"414.0",
    "gn:admin3_code":"41407.0",
    "gn:asciiname":"Wierzchy",
    "gn:country_code":"PL",
    "gn:dem":78,
    "gn:feature_class":"P",
    "gn:feature_code":"PPL",
    "gn:name":"Wierzchy",
    "gn:population":0,
    "gn:timezone":"Europe/Warsaw",
    "iso:country":"PL",
    "name:ceb_x_preferred":[
        "Wierzchy"
    ],
    "name:pol_x_preferred":[
        "Wierzchy"
    ],
    "name:ukr_x_preferred":[
        "\u0412\u0435\u0436\u0445\u0438"
    ],
    "wof:name":"Wierzchy",
    "wof:placetype":"locality"
},
  "geometry": {"coordinates":[18.24327000000001,53.60265],"type":"Point"}
}