{
  "type": "Feature",
  "properties": {
    "gn:admin1_code":"85.0",
    "gn:admin2_code":"2811.0",
    "gn:admin3_code":"281102.0",
    "gn:asciiname":"Komorowo",
    "gn:country_code":"PL",
    "gn:dem":135,
    "gn:feature_class":"P",
    "gn:feature_code":"PPL",
    "gn:name":"Komorowo",
    "gn:population":0,
    "gn:timezone":"Europe/Warsaw",
    "iso:country":"PL",
    "name:ceb_x_preferred":[
        "Komorowo"
    ],
    "name:deu_x_preferred":[
        "Komorowo"
    ],
    "name:fra_x_preferred":[
        "Komorowo"
    ],
    "name:pol_x_preferred":[
        "Komorowo"
    ],
    "name:ukr_x_preferred":[
        "\u041a\u043e\u043c\u043e\u0440\u043e\u0432\u043e"
    ],
    "name:und_x_variant":[
        "Camerau",
        "Grossmuckenhausen",
        "Kamerau"
    ],
    "wof:name":"Komorowo",
    "wof:placetype":"locality"
},
  "geometry": {"coordinates":[20.66599,53.32381],"type":"Point"}
}