{
  "type": "Feature",
  "properties": {
    "gn:admin1_code":"78.0",
    "gn:admin2_code":"1432.0",
    "gn:admin3_code":"143203.0",
    "gn:asciiname":"Granica",
    "gn:country_code":"PL",
    "gn:dem":75,
    "gn:feature_class":"P",
    "gn:feature_code":"PPL",
    "gn:name":"Granica",
    "gn:population":0,
    "gn:timezone":"Europe/Warsaw",
    "iso:country":"PL",
    "name:azb_x_preferred":[
        "\u0642\u0631\u0627\u0646\u0642\u062a\u0633\u0627"
    ],
    "name:fas_x_preferred":[
        "\u06af\u0631\u0627\u0646\u06af\u062a\u0633\u0627"
    ],
    "name:fra_x_preferred":[
        "Granica"
    ],
    "name:pol_x_preferred":[
        "Granica"
    ],
    "name:rus_x_preferred":[
        "\u0413\u0440\u0430\u043d\u0438\u0446\u0430"
    ],
    "name:ukr_x_preferred":[
        "\u0490\u0440\u0430\u043d\u0438\u0446\u044f"
    ],
    "wof:name":"Granica",
    "wof:placetype":"locality"
},
  "geometry": {"coordinates":[20.44693,52.28748],"type":"Point"}
}