{
  "type": "Feature",
  "properties": {
    "gn:admin1_code":"86.0",
    "gn:admin2_code":"3011.0",
    "gn:admin3_code":"301104.0",
    "gn:asciiname":"Jurkowo",
    "gn:country_code":"PL",
    "gn:dem":72,
    "gn:feature_class":"P",
    "gn:feature_code":"PPL",
    "gn:name":"Jurkowo",
    "gn:population":0,
    "gn:timezone":"Europe/Warsaw",
    "iso:country":"PL",
    "name:fra_x_preferred":[
        "Jurkowo"
    ],
    "name:pol_x_preferred":[
        "Jurkowo"
    ],
    "name:ukr_x_preferred":[
        "\u042e\u0440\u043a\u043e\u0432\u043e"
    ],
    "wof:name":"Jurkowo",
    "wof:placetype":"locality"
},
  "geometry": {"coordinates":[16.77705,51.99304],"type":"Point"}
}