{
  "type": "Feature",
  "properties": {
    "gn:admin1_code":"75.0",
    "gn:admin2_code":"611.0",
    "gn:admin3_code":"61107.0",
    "gn:asciiname":"Borowina Gasecka",
    "gn:country_code":"PL",
    "gn:dem":161,
    "gn:feature_class":"P",
    "gn:feature_code":"PPL",
    "gn:name":"Borowina G\u0105secka",
    "gn:population":0,
    "gn:timezone":"Europe/Warsaw",
    "iso:country":"PL",
    "name:und_x_variant":[
        "Borowina",
        "Borowina G\u0105secka"
    ],
    "wof:name":"Borowina Gasecka",
    "wof:placetype":"locality"
},
  "geometry": {"coordinates":[22.27894,51.83008],"type":"Point"}
}