{
  "type": "Feature",
  "properties": {
    "gn:population":1325,
    "iso:country":"PL",
    "name:ast_x_preferred":[
        "Try\u0144cza"
    ],
    "name:azb_x_preferred":[
        "\u062a\u0631\u06cc\u0646\u0686\u0627"
    ],
    "name:ceb_x_preferred":[
        "Try\u0144cza"
    ],
    "name:deu_x_preferred":[
        "Try\u0144cza"
    ],
    "name:eng_x_preferred":[
        "Try\u0144cza"
    ],
    "name:epo_x_preferred":[
        "Try\u0144cza"
    ],
    "name:fas_x_preferred":[
        "\u062a\u0631\u06cc\u0646\u0686\u0627"
    ],
    "name:fra_x_preferred":[
        "Try\u0144cza"
    ],
    "name:nld_x_preferred":[
        "Try\u0144cza"
    ],
    "name:pol_x_preferred":[
        "Try\u0144cza"
    ],
    "name:ukr_x_preferred":[
        "\u0422\u0440\u0438\u043d\u0447\u0430"
    ],
    "name:urd_x_preferred":[
        "\u062a\u0631\u06cc\u0646\u0686\u0627"
    ],
    "qs:a0":"Rzeczpospolita Polska",
    "qs:a1":"*Podkarpackie",
    "qs:a1r":"0",
    "qs:a2":"Przeworski",
    "qs:adm0":"Rzeczpospolita Polska",
    "qs:la":"Try\u0144cza",
    "qs:la_lc":"*PL1814082",
    "qs:level":"locality",
    "qs:loc":"Try\u0144cza",
    "qs:loc_alt":"Tryncza",
    "qs:pop":0,
    "qs:type":"rural point-in-poly",
    "wd:wordcount":92,
    "wof:name":"Try\u0144cza",
    "wof:placetype":"locality",
    "wof:population":1325
},
  "geometry": {"coordinates":[22.5561701778414,50.1257466059075],"type":"Point"}
}