{
  "type": "Feature",
  "properties": {
    "gn:admin1_code":"82.0",
    "gn:admin2_code":"2213.0",
    "gn:admin3_code":"221313.0",
    "gn:asciiname":"Maly Bukowiec",
    "gn:country_code":"PL",
    "gn:dem":115,
    "gn:feature_class":"P",
    "gn:feature_code":"PPL",
    "gn:name":"Ma\u0142y Bukowiec",
    "gn:population":0,
    "gn:timezone":"Europe/Warsaw",
    "iso:country":"PL",
    "name:ceb_x_preferred":[
        "Ma\u0142y Bukowiec"
    ],
    "name:nld_x_preferred":[
        "Ma\u0142y Bukowiec"
    ],
    "name:pol_x_preferred":[
        "Ma\u0142y Bukowiec"
    ],
    "name:ukr_x_preferred":[
        "\u041c\u0430\u043b\u0438-\u0411\u0443\u043a\u043e\u0432\u0435\u0446\u044c"
    ],
    "name:und_x_variant":[
        "Bukowiec"
    ],
    "wof:name":"Maly Bukowiec",
    "wof:placetype":"locality"
},
  "geometry": {"coordinates":[18.28759,53.87845],"type":"Point"}
}