{
  "type": "Feature",
  "properties": {
    "gn:admin1_code":"82.0",
    "gn:admin2_code":"2213.0",
    "gn:admin3_code":"221313.0",
    "gn:asciiname":"Maly Bukowiec",
    "gn:country_code":"PL",
    "gn:dem":115,
    "gn:feature_class":"P",
    "gn:feature_code":"PPL",
    "gn:name":"Ma\u0142y Bukowiec",
    "gn:population":0,
    "gn:timezone":"Europe/Warsaw",
    "iso:country":"PL",
    "name:und_x_variant":[
        "Bukowiec",
        "Ma\u0142y Bukowiec"
    ],
    "wof:name":"Maly Bukowiec",
    "wof:placetype":"locality"
},
  "geometry": {"coordinates":[18.28759,53.87845],"type":"Point"}
}