{
  "type": "Feature",
  "properties": {
    "gn:admin1_code":"80.0",
    "gn:admin2_code":"1812.0",
    "gn:admin3_code":"181201.0",
    "gn:asciiname":"Rogoznia",
    "gn:country_code":"PL",
    "gn:dem":179,
    "gn:feature_class":"P",
    "gn:feature_code":"PPL",
    "gn:name":"Rog\u00f3\u017ania",
    "gn:population":0,
    "gn:timezone":"Europe/Warsaw",
    "iso:country":"PL",
    "name:und_x_variant":[
        "Rog\u00f3\u017ania"
    ],
    "wof:name":"Rogoznia",
    "wof:placetype":"locality"
},
  "geometry": {"coordinates":[22.51907000000001,50.49477],"type":"Point"}
}