{
  "type": "Feature",
  "properties": {
    "gn:admin1_code":"81.0",
    "gn:admin2_code":"2005.0",
    "gn:admin3_code":"200506.0",
    "gn:asciiname":"Dubicze Osoczne",
    "gn:country_code":"PL",
    "gn:dem":172,
    "gn:feature_class":"P",
    "gn:feature_code":"PPL",
    "gn:name":"Dubicze Osoczne",
    "gn:population":0,
    "gn:timezone":"Europe/Warsaw",
    "iso:country":"PL",
    "name:azb_x_preferred":[
        "\u062f\u0648\u0628\u06cc\u0686\u0647 \u0627\u0648\u0633\u0648\u0686\u0646\u0647"
    ],
    "name:fas_x_preferred":[
        "\u062f\u0648\u0628\u06cc\u0686\u0647 \u0627\u0648\u0633\u0648\u0686\u0646\u0647"
    ],
    "name:lit_x_preferred":[
        "Dubi\u010de Oso\u010dn\u0117"
    ],
    "name:pol_x_preferred":[
        "Dubicze Osoczne"
    ],
    "name:ukr_x_preferred":[
        "\u0414\u0443\u0431\u0456\u0447\u0435-\u041e\u0441\u043e\u0447\u043d\u0435"
    ],
    "wof:name":"Dubicze Osoczne",
    "wof:placetype":"locality"
},
  "geometry": {"coordinates":[23.49538,52.73404],"type":"Point"}
}