{
  "type": "Feature",
  "properties": {
    "gn:admin1_code":"81.0",
    "gn:admin2_code":"2005.0",
    "gn:admin3_code":"200506.0",
    "gn:asciiname":"Dubicze Osoczne",
    "gn:country_code":"PL",
    "gn:dem":172,
    "gn:feature_class":"P",
    "gn:feature_code":"PPL",
    "gn:name":"Dubicze Osoczne",
    "gn:population":0,
    "gn:timezone":"Europe/Warsaw",
    "iso:country":"PL",
    "wof:name":"Dubicze Osoczne",
    "wof:placetype":"locality"
},
  "geometry": {"coordinates":[23.49538,52.73404],"type":"Point"}
}