{
  "type": "Feature",
  "properties": {
    "gn:admin1_code":"86.0",
    "gn:admin2_code":"3017.0",
    "gn:admin3_code":"301704.0",
    "gn:asciiname":"Lewkowiec",
    "gn:country_code":"PL",
    "gn:dem":145,
    "gn:feature_class":"P",
    "gn:feature_code":"PPL",
    "gn:name":"Lewkowiec",
    "gn:population":0,
    "gn:timezone":"Europe/Warsaw",
    "iso:country":"PL",
    "name:azb_x_preferred":[
        "\u0644\u0648\u06a9\u0648\u0648\u06cc\u062a\u0633"
    ],
    "name:fas_x_preferred":[
        "\u0644\u0648\u06a9\u0648\u0648\u06cc\u062a\u0633"
    ],
    "name:nld_x_preferred":[
        "Lewkowiec"
    ],
    "name:pol_x_preferred":[
        "Lewkowiec"
    ],
    "name:ukr_x_preferred":[
        "\u041b\u0435\u0432\u043a\u043e\u0432\u0435\u0446\u044c"
    ],
    "wof:name":"Lewkowiec",
    "wof:placetype":"locality"
},
  "geometry": {"coordinates":[17.79567999999999,51.69356],"type":"Point"}
}