{
  "type": "Feature",
  "properties": {
    "gn:admin1_code":"75.0",
    "gn:admin2_code":"613.0",
    "gn:admin3_code":"61301.0",
    "gn:asciiname":"Wyhalew",
    "gn:country_code":"PL",
    "gn:dem":158,
    "gn:feature_class":"P",
    "gn:feature_code":"PPL",
    "gn:name":"Wyhalew",
    "gn:population":0,
    "gn:timezone":"Europe/Warsaw",
    "iso:country":"PL",
    "name:fra_x_preferred":[
        "Wyhalew"
    ],
    "name:lit_x_preferred":[
        "Vihalevas"
    ],
    "name:pol_x_preferred":[
        "Wyhalew"
    ],
    "name:ukr_x_preferred":[
        "\u0412\u0438\u0433\u0430\u043b\u0435\u0432"
    ],
    "name:und_x_variant":[
        "Wyhal\u00f3w"
    ],
    "wof:name":"Wyhalew",
    "wof:placetype":"locality"
},
  "geometry": {"coordinates":[23.16753,51.61385],"type":"Point"}
}