{
  "type": "Feature",
  "properties": {
    "gn:admin1_code":"78.0",
    "gn:admin2_code":"1425.0",
    "gn:admin3_code":"142509.0",
    "gn:asciiname":"Wrzos",
    "gn:country_code":"PL",
    "gn:dem":152,
    "gn:feature_class":"P",
    "gn:feature_code":"PPL",
    "gn:name":"Wrzos",
    "gn:population":0,
    "gn:timezone":"Europe/Warsaw",
    "iso:country":"PL",
    "name:fra_x_preferred":[
        "Wrzos"
    ],
    "name:pol_x_preferred":[
        "Wrzos"
    ],
    "name:ukr_x_preferred":[
        "\u0412\u0436\u043e\u0441"
    ],
    "wof:name":"Wrzos",
    "wof:placetype":"locality"
},
  "geometry": {"coordinates":[20.82769,51.46022],"type":"Point"}
}