{
  "type": "Feature",
  "properties": {
    "gn:admin1_code":"80.0",
    "gn:admin2_code":"1808.0",
    "gn:admin3_code":"180802.0",
    "gn:asciiname":"Opaleniska",
    "gn:country_code":"PL",
    "gn:dem":204,
    "gn:feature_class":"P",
    "gn:feature_code":"PPL",
    "gn:name":"Opaleniska",
    "gn:population":0,
    "gn:timezone":"Europe/Warsaw",
    "iso:country":"PL",
    "name:pol_x_preferred":[
        "Opaleniska"
    ],
    "name:ukr_x_preferred":[
        "\u041e\u043f\u0430\u043b\u0435\u043d\u0438\u0441\u044c\u043a\u0430"
    ],
    "name:und_x_variant":[
        "Majdna",
        "Opalenisko"
    ],
    "wof:name":"Opaleniska",
    "wof:placetype":"locality"
},
  "geometry": {"coordinates":[22.41695,50.14675],"type":"Point"}
}