{
  "type": "Feature",
  "properties": {
    "gn:admin1_code":"75.0",
    "gn:admin2_code":"603.0",
    "gn:admin3_code":"60305.0",
    "gn:asciiname":"Tursko",
    "gn:country_code":"PL",
    "gn:dem":197,
    "gn:feature_class":"P",
    "gn:feature_code":"PPL",
    "gn:name":"Tursko",
    "gn:population":0,
    "gn:timezone":"Europe/Warsaw",
    "iso:country":"PL",
    "name:ceb_x_preferred":[
        "Tursko"
    ],
    "name:deu_x_preferred":[
        "Tursko"
    ],
    "name:pol_x_preferred":[
        "Tursko"
    ],
    "name:srp_x_preferred":[
        "\u0422\u0443\u0440\u0441\u043a\u043e"
    ],
    "name:swe_x_preferred":[
        "Tursko"
    ],
    "name:ukr_x_preferred":[
        "\u0422\u0443\u0440\u0441\u044c\u043a\u043e"
    ],
    "name:und_x_variant":[
        "Kolonia Tursko",
        "Tursko"
    ],
    "wof:name":"Tursko",
    "wof:placetype":"locality"
},
  "geometry": {"coordinates":[23.87832,50.97584000000001],"type":"Point"}
}