{
  "type": "Feature",
  "properties": {
    "gn:admin1_code":"86.0",
    "gn:admin2_code":"3010.0",
    "gn:admin3_code":"301010.0",
    "gn:asciiname":"Przystronie",
    "gn:country_code":"PL",
    "gn:dem":130,
    "gn:feature_class":"P",
    "gn:feature_code":"PPL",
    "gn:name":"Przystronie",
    "gn:population":0,
    "gn:timezone":"Europe/Warsaw",
    "iso:country":"PL",
    "name:fra_x_preferred":[
        "Przystronie"
    ],
    "name:pol_x_preferred":[
        "Przystronie"
    ],
    "name:ukr_x_preferred":[
        "\u041f\u0448\u0438\u0441\u0442\u0440\u043e\u043d\u0435"
    ],
    "wof:name":"Przystronie",
    "wof:placetype":"locality"
},
  "geometry": {"coordinates":[18.60431,52.34216],"type":"Point"}
}