{
  "type": "Feature",
  "properties": {
    "gn:admin1_code":"78.0",
    "gn:admin2_code":"1434.0",
    "gn:admin3_code":"143406.0",
    "gn:asciiname":"Ily",
    "gn:country_code":"PL",
    "gn:dem":92,
    "gn:feature_class":"P",
    "gn:feature_code":"PPL",
    "gn:name":"I\u0142y",
    "gn:population":0,
    "gn:timezone":"Europe/Warsaw",
    "iso:country":"PL",
    "name:und_x_variant":[
        "I\u0142y"
    ],
    "wof:name":"Ily",
    "wof:placetype":"locality"
},
  "geometry": {"coordinates":[21.60611,52.52973000000001],"type":"Point"}
}