{
  "type": "Feature",
  "properties": {
    "gn:gn_country":"PL",
    "gn:gn_fcode":"PPLA3",
    "gn:gn_pop":2125,
    "gn:population":2125,
    "iso:country":"PL",
    "name:bul_x_preferred":[
        "\u0428\u0432\u044c\u043e\u043d\u0442\u043d\u0438\u043a\u0438 \u0413\u043e\u0440\u043d\u0435"
    ],
    "name:bul_x_variant":[
        "\u0428\u0432\u044c\u043e\u043d\u0442\u043d\u0438\u043a\u0438 \u0413\u0443\u0440\u043d\u0435"
    ],
    "name:ceb_x_preferred":[
        "\u015awi\u0105tniki G\u00f3rne"
    ],
    "name:epo_x_preferred":[
        "\u015awi\u0105tniki G\u00f3rne"
    ],
    "name:est_x_preferred":[
        "\u015awi\u0105tniki G\u00f3rne"
    ],
    "name:fra_x_preferred":[
        "\u015awi\u0105tniki G\u00f3rne"
    ],
    "name:jav_x_preferred":[
        "\u015awi\u0105tniki G\u00f3rne"
    ],
    "name:lav_x_preferred":[
        "Svjont\u0146iki Gurni"
    ],
    "name:msa_x_preferred":[
        "\u015awi\u0105tniki G\u00f3rne"
    ],
    "name:nld_x_preferred":[
        "\u015awi\u0105tniki G\u00f3rne"
    ],
    "name:pol_x_preferred":[
        "\u015awi\u0105tniki G\u00f3rne"
    ],
    "name:por_x_preferred":[
        "\u015awi\u0105tniki G\u00f3rne"
    ],
    "name:ron_x_preferred":[
        "\u015awi\u0105tniki G\u00f3rne"
    ],
    "name:rus_x_preferred":[
        "\u0421\u0432\u0451\u043d\u0442\u043d\u0438\u043a\u0438-\u0413\u0443\u0440\u043d\u0435"
    ],
    "name:slk_x_preferred":[
        "\u015awi\u0105tniki G\u00f3rne"
    ],
    "name:srp_x_preferred":[
        "\u0421\u0432\u0458\u043e\u043d\u0442\u045a\u0438\u043a\u0438 \u0413\u043e\u0440\u043d\u0435"
    ],
    "name:ukr_x_preferred":[
        "\u0421\u0432\u044c\u043e\u043d\u0442\u043d\u0438\u043a\u0438-\u0490\u0443\u0440\u043d\u0435"
    ],
    "name:ukr_x_variant":[
        "\u0421\u0432\u044c\u043e\u043d\u0442\u043d\u0438\u043a\u0438-\u0413\u0443\u0440\u043d\u0435"
    ],
    "name:vie_x_preferred":[
        "\u015awi\u0105tniki G\u00f3rne"
    ],
    "qs_pg:aaroncc":"PL",
    "qs_pg:gn_country":"PL",
    "qs_pg:gn_fcode":"PPLA3",
    "qs_pg:gn_pop":2125,
    "qs_pg:name":"\u015awi\u0105tniki G\u00f3rne",
    "qs_pg:name_adm0":"Polska",
    "qs_pg:name_adm1":"Ma\u0142opolskie",
    "qs_pg:photos_9k":1,
    "qs_pg:photos_9r":1,
    "qs_pg:photos_all":1,
    "qs_pg:photos_sr":0,
    "qs_pg:pop_sr":4,
    "qs_pg:qs_pg_placetype":"localadmin",
    "qs_pg:qs_pg_placetype_gp":"LocalAdmin",
    "qs_pg:woe_adm0":23424923,
    "woe:adm0_id":23424923,
    "woe:name_adm0":"Polska",
    "woe:name_adm1":"Ma\u0142opolskie",
    "woe:placetype":"LocalAdmin",
    "wof:name":"\u015awi\u0105tniki G\u00f3rne",
    "wof:placetype":"localadmin",
    "wof:population":2125
},
  "geometry": {"coordinates":[19.95364,49.93429],"type":"Point"}
}