{
  "type": "Feature",
  "properties": {
    "iso:country":"PL",
    "name:azb_x_preferred":[
        "\u0642\u0645\u06cc\u0646\u0627 \u0646\u0648\u0648 \u0648\u06cc\u0634\u0646\u0642\u0686"
    ],
    "name:bel_x_preferred":[
        "\u041d\u043e\u0432\u044b \u0412\u0456\u0441\u043d\u0456\u0447"
    ],
    "name:deu_x_preferred":[
        "Gmina Nowy Wi\u015bnicz"
    ],
    "name:eus_x_preferred":[
        "Nowy Wi\u015bnicz udalerria"
    ],
    "name:fas_x_preferred":[
        "\u06af\u0645\u06cc\u0646\u0627 \u0646\u0648\u0648 \u0648\u06cc\u0634\u0646\u06af\u0686"
    ],
    "name:fra_x_preferred":[
        "Nowy Wi\u015bnicz"
    ],
    "name:ita_x_preferred":[
        "Nowy Wi\u015bnicz"
    ],
    "name:nld_x_preferred":[
        "Nowy Wi\u015bnicz"
    ],
    "name:pol_x_preferred":[
        "Nowy Wi\u015bnicz"
    ],
    "name:rus_x_preferred":[
        "\u041d\u043e\u0432\u044b-\u0412\u0438\u0441\u043d\u0438\u0447"
    ],
    "name:slk_x_preferred":[
        "Gmina Nowy Wi\u015bnicz"
    ],
    "name:ukr_x_preferred":[
        "\u0413\u043c\u0456\u043d\u0430 \u041d\u043e\u0432\u0438\u0439 \u0412\u0456\u0441\u044c\u043d\u0438\u0447"
    ],
    "name:war_x_preferred":[
        "Gmina Nowy Wi\u015bnicz"
    ],
    "qs_pg:aaroncc":"PL",
    "qs_pg:name":"Gmina Nowy Wi\u015bnicz",
    "qs_pg:name_adm0":"Polska",
    "qs_pg:name_adm1":"Ma\u0142opolskie",
    "qs_pg:photos":12,
    "qs_pg:photos_1k":2,
    "qs_pg:photos_9k":1,
    "qs_pg:photos_9r":3,
    "qs_pg:photos_all":118,
    "qs_pg:photos_sr":1,
    "qs_pg:pop_sr":0,
    "qs_pg:qs_pg_placetype":"localadmin",
    "qs_pg:qs_pg_placetype_gp":"LocalAdmin",
    "qs_pg:woe_adm0":23424923,
    "woe:adm0_id":23424923,
    "woe:name_adm0":"Polska",
    "woe:name_adm1":"Ma\u0142opolskie",
    "woe:placetype":"LocalAdmin",
    "wof:name":"Gmina Nowy Wi\u015bnicz",
    "wof:placetype":"localadmin"
},
  "geometry": {"coordinates":[20.468902,49.917934],"type":"Point"}
}