{
  "type": "Feature",
  "properties": {
    "gn:admin1_code":"81.0",
    "gn:asciiname":"Milewo Wielkie",
    "gn:country_code":"PL",
    "gn:dem":111,
    "gn:feature_class":"P",
    "gn:feature_code":"PPL",
    "gn:name":"Milewo Wielkie",
    "gn:population":0,
    "gn:timezone":"Europe/Warsaw",
    "iso:country":"PL",
    "name:fra_x_preferred":[
        "Milewo Wielkie"
    ],
    "name:pol_x_preferred":[
        "Milewo Wielkie"
    ],
    "name:ukr_x_preferred":[
        "\u041c\u0456\u043b\u0435\u0432\u043e-\u0412\u0435\u043b\u0438\u043a\u0435"
    ],
    "wof:name":"Milewo Wielkie",
    "wof:placetype":"locality"
},
  "geometry": {"coordinates":[21.8367,53.01478],"type":"Point"}
}