{
  "type": "Feature",
  "properties": {
    "gn:gn_country":"PL",
    "gn:gn_fcode":"PPLA3",
    "gn:gn_pop":6171,
    "gn:population":6171,
    "iso:country":"PL",
    "name:bul_x_preferred":[
        "\u0414\u043e\u0431\u0447\u0438\u0446\u0435"
    ],
    "name:heb_x_preferred":[
        "\u05d3\u05d5\u05d1\u05e6\u05d9\u05e6\u05d4"
    ],
    "name:lav_x_preferred":[
        "Dob\u010dice"
    ],
    "name:rus_x_preferred":[
        "\u0414\u043e\u0431\u0447\u0438\u0446\u0435"
    ],
    "name:srp_x_preferred":[
        "\u0414\u043e\u043f\u0447\u0438\u0446\u0435"
    ],
    "name:ukr_x_preferred":[
        "\u0414\u043e\u0431\u0447\u0438\u0446\u0435"
    ],
    "name:zho_x_preferred":[
        "\u591a\u5e03\u5947\u91c7"
    ],
    "qs_pg:aaroncc":"PL",
    "qs_pg:gn_country":"PL",
    "qs_pg:gn_fcode":"PPLA3",
    "qs_pg:gn_pop":6171,
    "qs_pg:name":"Dobczyce",
    "qs_pg:name_adm0":"Polska",
    "qs_pg:name_adm1":"Ma\u0142opolskie",
    "qs_pg:photos":1,
    "qs_pg:photos_1k":1,
    "qs_pg:photos_9k":1,
    "qs_pg:photos_9r":1,
    "qs_pg:photos_all":1,
    "qs_pg:photos_sr":1,
    "qs_pg:pop_sr":5,
    "qs_pg:qs_pg_placetype":"localadmin",
    "qs_pg:qs_pg_placetype_gp":"LocalAdmin",
    "qs_pg:woe_adm0":23424923,
    "woe:adm0_id":23424923,
    "woe:name_adm0":"Polska",
    "woe:name_adm1":"Ma\u0142opolskie",
    "woe:placetype":"LocalAdmin",
    "wof:name":"Dobczyce",
    "wof:placetype":"localadmin",
    "wof:population":6171
},
  "geometry": {"coordinates":[20.08936,49.88109],"type":"Point"}
}