{
  "type": "Feature",
  "properties": {
    "gn:admin1_code":"81.0",
    "gn:admin2_code":"2005.0",
    "gn:admin3_code":"200507.0",
    "gn:asciiname":"Dobrowody",
    "gn:country_code":"PL",
    "gn:dem":172,
    "gn:feature_class":"P",
    "gn:feature_code":"PPL",
    "gn:name":"Dobrowody",
    "gn:population":0,
    "gn:timezone":"Europe/Warsaw",
    "iso:country":"PL",
    "name:und_x_variant":[
        "Dobrowoda",
        "Dobrowody"
    ],
    "wof:name":"Dobrowody",
    "wof:placetype":"locality"
},
  "geometry": {"coordinates":[23.38333,52.56166],"type":"Point"}
}