{
  "type": "Feature",
  "properties": {
    "gn:admin1_code":"87.0",
    "gn:admin2_code":"3216.0",
    "gn:admin3_code":"321604.0",
    "gn:asciiname":"Swierznica",
    "gn:country_code":"PL",
    "gn:dem":82,
    "gn:feature_class":"P",
    "gn:feature_code":"PPL",
    "gn:name":"Swierznica",
    "gn:population":0,
    "gn:timezone":"Europe/Warsaw",
    "iso:country":"PL",
    "name:deu_x_preferred":[
        "\u015awierznica"
    ],
    "name:pol_x_preferred":[
        "\u015awierznica"
    ],
    "name:ukr_x_preferred":[
        "\u0421\u044c\u0432\u0435\u0436\u043d\u0438\u0446\u044f"
    ],
    "name:vie_x_preferred":[
        "\u015awierznica"
    ],
    "wof:name":"Swierznica",
    "wof:placetype":"locality"
},
  "geometry": {"coordinates":[15.9959,53.85989],"type":"Point"}
}