{
  "type": "Feature",
  "properties": {
    "gn:gn_country":"PL",
    "gn:gn_fcode":"PPL",
    "gn:gn_pop":2222,
    "gn:population":2222,
    "iso:country":"PL",
    "name:dut_x_preferred":[
        "Godziszka"
    ],
    "name:eng_x_preferred":[
        "Godziszka"
    ],
    "name:fre_x_preferred":[
        "Godziszka"
    ],
    "name:ger_x_preferred":[
        "Godziszka"
    ],
    "name:nan_x_preferred":[
        "Godziszka"
    ],
    "name:per_x_preferred":[
        "\u06af\u0648\u062c\u0634\u06a9\u0627"
    ],
    "name:pol_x_preferred":[
        "Godziszka"
    ],
    "qs_pg:aaroncc":"PL",
    "qs_pg:gn_country":"PL",
    "qs_pg:gn_fcode":"PPL",
    "qs_pg:gn_pop":2222,
    "qs_pg:name":"Godziszka",
    "qs_pg:name_adm0":"Polska",
    "qs_pg:name_adm1":"Sl\u0105skie",
    "qs_pg:photos":19,
    "qs_pg:photos_1k":4,
    "qs_pg:photos_9k":1,
    "qs_pg:photos_9r":1,
    "qs_pg:photos_all":19,
    "qs_pg:photos_sr":1,
    "qs_pg:pop_sr":4,
    "qs_pg:qs_pg_placetype":"locality",
    "qs_pg:qs_pg_placetype_gp":"Town",
    "qs_pg:woe_adm0":23424923,
    "woe:adm0_id":23424923,
    "woe:name_adm0":"Polska",
    "woe:name_adm1":"Sl\u0105skie",
    "woe:placetype":"Town",
    "wof:name":"Godziszka",
    "wof:placetype":"locality",
    "wof:population":2222
},
  "geometry": {"coordinates":[19.07587,49.71288],"type":"Point"}
}