{
  "type": "Feature",
  "properties": {
    "gn:admin1_code":"73.0",
    "gn:admin2_code":"403.0",
    "gn:admin3_code":"40305.0",
    "gn:asciiname":"Dobromierz",
    "gn:country_code":"PL",
    "gn:dem":86,
    "gn:feature_class":"P",
    "gn:feature_code":"PPL",
    "gn:name":"Dobromierz",
    "gn:population":0,
    "gn:timezone":"Europe/Warsaw",
    "iso:country":"PL",
    "wof:name":"Dobromierz",
    "wof:placetype":"locality"
},
  "geometry": {"coordinates":[18.10616,52.99226],"type":"Point"}
}