{
  "type": "Feature",
  "properties": {
    "gn:admin1_code":"78.0",
    "gn:admin2_code":"1419.0",
    "gn:admin3_code":"141914.0",
    "gn:asciiname":"Teodorowo",
    "gn:country_code":"PL",
    "gn:dem":151,
    "gn:feature_class":"P",
    "gn:feature_code":"PPL",
    "gn:name":"Teodorowo",
    "gn:population":0,
    "gn:timezone":"Europe/Warsaw",
    "iso:country":"PL",
    "name:fra_x_preferred":[
        "Teodorowo"
    ],
    "name:pol_x_preferred":[
        "Teodorowo"
    ],
    "name:ukr_x_preferred":[
        "\u0422\u0435\u043e\u0434\u043e\u0440\u043e\u0432\u043e"
    ],
    "wof:name":"Teodorowo",
    "wof:placetype":"locality"
},
  "geometry": {"coordinates":[19.93608,52.62191],"type":"Point"}
}