{
  "type": "Feature",
  "properties": {
    "gn:admin1_code":"78.0",
    "gn:admin2_code":"1407.0",
    "gn:admin3_code":"140705.0",
    "gn:asciiname":"Luczynow Stary",
    "gn:country_code":"PL",
    "gn:dem":110,
    "gn:feature_class":"P",
    "gn:feature_code":"PPL",
    "gn:name":"\u0141uczyn\u00f3w Stary",
    "gn:population":0,
    "gn:timezone":"Europe/Warsaw",
    "iso:country":"PL",
    "name:und_x_variant":[
        "\u0141uczyn\u00f3w",
        "\u0141uczyn\u00f3w Stary"
    ],
    "wof:name":"Luczynow Stary",
    "wof:placetype":"locality"
},
  "geometry": {"coordinates":[21.49282,51.6104],"type":"Point"}
}