{
  "type": "Feature",
  "properties": {
    "gn:admin1_code":"87.0",
    "gn:admin2_code":"3216.0",
    "gn:admin3_code":"321605.0",
    "gn:asciiname":"Stare Slepce",
    "gn:country_code":"PL",
    "gn:dem":53,
    "gn:feature_class":"P",
    "gn:feature_code":"PPL",
    "gn:name":"Stare \u015alepce",
    "gn:population":0,
    "gn:timezone":"Europe/Warsaw",
    "iso:country":"PL",
    "name:und_x_variant":[
        "Stare \u015alepce"
    ],
    "wof:name":"Stare Slepce",
    "wof:placetype":"locality"
},
  "geometry": {"coordinates":[15.67148,53.92066],"type":"Point"}
}