{
  "type": "Feature",
  "properties": {
    "gn:admin1_code":"75.0",
    "gn:admin2_code":"611.0",
    "gn:admin3_code":"61104.0",
    "gn:asciiname":"Gole Lazy",
    "gn:country_code":"PL",
    "gn:dem":174,
    "gn:feature_class":"P",
    "gn:feature_code":"PPL",
    "gn:name":"Go\u0142e \u0141azy",
    "gn:population":0,
    "gn:timezone":"Europe/Warsaw",
    "iso:country":"PL",
    "name:und_x_variant":[
        "Go\u0142e \u0141azy"
    ],
    "wof:name":"Gole Lazy",
    "wof:placetype":"locality"
},
  "geometry": {"coordinates":[22.01682000000001,51.80251],"type":"Point"}
}