{
  "type": "Feature",
  "properties": {
    "gn:admin1_code":"75.0",
    "gn:admin2_code":"611.0",
    "gn:admin3_code":"61104.0",
    "gn:asciiname":"Gole Lazy",
    "gn:country_code":"PL",
    "gn:dem":174,
    "gn:feature_class":"P",
    "gn:feature_code":"PPL",
    "gn:name":"Go\u0142e \u0141azy",
    "gn:population":0,
    "gn:timezone":"Europe/Warsaw",
    "iso:country":"PL",
    "name:fra_x_preferred":[
        "Go\u0142e \u0141azy"
    ],
    "name:pol_x_preferred":[
        "Go\u0142e \u0141azy"
    ],
    "name:ukr_x_preferred":[
        "\u0490\u043e\u043b\u0435-\u041b\u0430\u0437\u0438"
    ],
    "wof:name":"Gole Lazy",
    "wof:placetype":"locality"
},
  "geometry": {"coordinates":[22.01682000000001,51.80251],"type":"Point"}
}