{
  "type": "Feature",
  "properties": {
    "gn:country":"PL",
    "gn:fcode":"PPL",
    "gn:population":921,
    "iso:country":"PL",
    "name:ast_x_preferred":[
        "G\u00f3rki \u015al\u0105skie"
    ],
    "name:azb_x_preferred":[
        "\u0642\u0648\u0631\u06a9\u06cc \u0634\u0644\u0627\u0646\u0633\u06a9\u06cc\u0647"
    ],
    "name:ceb_x_preferred":[
        "G\u00f3rki \u015al\u0105skie"
    ],
    "name:ces_x_preferred":[
        "G\u00f3rki \u015al\u0105skie"
    ],
    "name:che_x_preferred":[
        "\u0413\u0443\u0440\u043a\u0438-\u0428\u043b\u0451\u043d\u0441\u043a\u0438"
    ],
    "name:deu_x_preferred":[
        "G\u00f3rki \u015al\u0105skie"
    ],
    "name:eng_x_preferred":[
        "G\u00f3rki \u015al\u0105skie"
    ],
    "name:fas_x_preferred":[
        "\u06af\u0648\u0631\u06a9\u06cc \u0634\u0644\u0627\u0646\u0633\u06a9\u06cc\u0647"
    ],
    "name:fra_x_preferred":[
        "G\u00f3rki \u015al\u0105skie"
    ],
    "name:nan_x_preferred":[
        "G\u00f3rki \u015al\u0105skie"
    ],
    "name:nld_x_preferred":[
        "G\u00f3rki \u015al\u0105skie"
    ],
    "name:pol_x_preferred":[
        "G\u00f3rki \u015al\u0105skie"
    ],
    "name:tat_x_preferred":[
        "\u0413\u0443\u0440\u043a\u0438-\u0428\u043b\u0451\u043d\u0441\u043a\u0438"
    ],
    "name:ukr_x_preferred":[
        "\u0490\u0443\u0440\u043a\u0456-\u0428\u043b\u044c\u043e\u043d\u0441\u044c\u043a\u0456"
    ],
    "name:und_x_variant":[
        "G\u00f3rki"
    ],
    "qs_pg:aaroncc":"PL",
    "qs_pg:gn_country":"PL",
    "qs_pg:gn_fcode":"PPL",
    "qs_pg:gn_pop":921,
    "qs_pg:name":"G\u00f3rki \u015al\u0105skie",
    "qs_pg:photos_9r":0,
    "qs_pg:photos_sr":0,
    "qs_pg:pop_sr":2,
    "qs_pg:qs_pg_placetype":"locality",
    "wof:name":"G\u00f3rki \u015al\u0105skie",
    "wof:placetype":"locality",
    "wof:population":921
},
  "geometry": {"coordinates":[18.38768,50.14149],"type":"Point"}
}