{
  "type": "Feature",
  "properties": {
    "gn:gn_country":"PL",
    "gn:gn_fcode":"PPL",
    "gn:gn_pop":921,
    "gn:population":921,
    "iso:country":"PL",
    "name:dut_x_preferred":[
        "G\u00f3rki \u015al\u0105skie"
    ],
    "name:eng_x_preferred":[
        "G\u00f3rki \u015al\u0105skie"
    ],
    "name:fre_x_preferred":[
        "G\u00f3rki \u015al\u0105skie"
    ],
    "name:nan_x_preferred":[
        "G\u00f3rki \u015al\u0105skie"
    ],
    "name:per_x_preferred":[
        "\u06af\u0648\u0631\u06a9\u06cc \u0634\u0644\u0627\u0646\u0633\u06a9\u06cc\u0647"
    ],
    "name:pol_x_preferred":[
        "G\u00f3rki \u015al\u0105skie"
    ],
    "name:unk_x_variant":[
        "G\u00f3rki"
    ],
    "qs_pg:aaroncc":"PL",
    "qs_pg:gn_country":"PL",
    "qs_pg:gn_fcode":"PPL",
    "qs_pg:gn_pop":921,
    "qs_pg:name":"G\u00f3rki \u015al\u0105skie",
    "qs_pg:photos_9r":0,
    "qs_pg:photos_sr":0,
    "qs_pg:pop_sr":2,
    "qs_pg:qs_pg_placetype":"locality",
    "wof:name":"G\u00f3rki \u015al\u0105skie",
    "wof:placetype":"locality",
    "wof:population":921
},
  "geometry": {"coordinates":[18.38768,50.14149],"type":"Point"}
}