{
  "type": "Feature",
  "properties": {
    "gn:admin1_code":"78.0",
    "gn:admin2_code":"1426.0",
    "gn:admin3_code":"142604.0",
    "gn:asciiname":"Zaliwie Szpinki",
    "gn:country_code":"PL",
    "gn:dem":131,
    "gn:feature_class":"P",
    "gn:feature_code":"PPL",
    "gn:name":"Zaliwie Szpinki",
    "gn:population":0,
    "gn:timezone":"Europe/Warsaw",
    "iso:country":"PL",
    "name:azb_x_preferred":[
        "\u0632\u0627\u0644\u06cc\u0648\u06cc-\u0634\u067e\u06cc\u0646\u06a9\u06cc"
    ],
    "name:fas_x_preferred":[
        "\u0632\u0627\u0644\u06cc\u0648\u06cc-\u0634\u067e\u06cc\u0646\u06a9\u06cc"
    ],
    "name:fra_x_preferred":[
        "Zaliwie-Szpinki"
    ],
    "name:lit_x_preferred":[
        "Zalive \u0160pinkai"
    ],
    "name:pol_x_preferred":[
        "Zaliwie-Szpinki"
    ],
    "name:szl_x_preferred":[
        "Zaliwje-Szpinki"
    ],
    "name:ukr_x_preferred":[
        "\u0417\u0430\u043b\u0456\u0432\u0435-\u0428\u043f\u0456\u043d\u043a\u0456"
    ],
    "wof:name":"Zaliwie Szpinki",
    "wof:placetype":"locality"
},
  "geometry": {"coordinates":[22.082,52.26254],"type":"Point"}
}