{
  "type": "Feature",
  "properties": {
    "gn:admin1_code":"78.0",
    "gn:admin2_code":"1426.0",
    "gn:admin3_code":"142604.0",
    "gn:asciiname":"Zaliwie Szpinki",
    "gn:country_code":"PL",
    "gn:dem":131,
    "gn:feature_class":"P",
    "gn:feature_code":"PPL",
    "gn:name":"Zaliwie Szpinki",
    "gn:population":0,
    "gn:timezone":"Europe/Warsaw",
    "iso:country":"PL",
    "wof:name":"Zaliwie Szpinki",
    "wof:placetype":"locality"
},
  "geometry": {"coordinates":[22.082,52.26254],"type":"Point"}
}