{
  "type": "Feature",
  "properties": {
    "gn:admin1_code":"86.0",
    "gn:admin2_code":"3004.0",
    "gn:admin3_code":"300403.0",
    "gn:asciiname":"Kuczyna",
    "gn:country_code":"PL",
    "gn:dem":109,
    "gn:feature_class":"P",
    "gn:feature_code":"PPL",
    "gn:name":"Kuczyna",
    "gn:population":0,
    "gn:timezone":"Europe/Warsaw",
    "iso:country":"PL",
    "wof:name":"Kuczyna",
    "wof:placetype":"locality"
},
  "geometry": {"coordinates":[16.9586,51.74887],"type":"Point"}
}