{
  "type": "Feature",
  "properties": {
    "gn:admin1_code":"79.0",
    "gn:admin2_code":"1661.0",
    "gn:admin3_code":"166101.0",
    "gn:asciiname":"Grotowice",
    "gn:country_code":"PL",
    "gn:dem":159,
    "gn:feature_class":"P",
    "gn:feature_code":"PPL",
    "gn:name":"Grotowice",
    "gn:population":0,
    "gn:timezone":"Europe/Warsaw",
    "iso:country":"PL",
    "wof:name":"Grotowice",
    "wof:placetype":"locality"
},
  "geometry": {"coordinates":[17.97495,50.59857],"type":"Point"}
}