{
  "type": "Feature",
  "properties": {
    "gn:admin1_code":"73.0",
    "gn:admin2_code":"415.0",
    "gn:admin3_code":"41508.0",
    "gn:asciiname":"Stanislawowo-Poczalkowo",
    "gn:country_code":"PL",
    "gn:dem":72,
    "gn:feature_class":"P",
    "gn:feature_code":"PPL",
    "gn:name":"Stanis\u0142awowo-Pocza\u0142kowo",
    "gn:population":0,
    "gn:timezone":"Europe/Warsaw",
    "iso:country":"PL",
    "wof:name":"Stanislawowo-Poczalkowo",
    "wof:placetype":"locality"
},
  "geometry": {"coordinates":[18.63333,52.91667],"type":"Point"}
}