{
  "type": "Feature",
  "properties": {
    "gn:admin1_code":"74.0",
    "gn:admin2_code":"1020.0",
    "gn:admin3_code":"102009.0",
    "gn:asciiname":"Dabrowka Wielka",
    "gn:country_code":"PL",
    "gn:dem":160,
    "gn:feature_class":"P",
    "gn:feature_code":"PPL",
    "gn:name":"D\u0105br\u00f3wka Wielka",
    "gn:population":0,
    "gn:timezone":"Europe/Warsaw",
    "iso:country":"PL",
    "name:pol_x_preferred":[
        "D\u0105br\u00f3wka Wielka"
    ],
    "name:ukr_x_preferred":[
        "\u0414\u043e\u043c\u0431\u0440\u0443\u0432\u043a\u0430-\u0412\u0435\u043b\u0438\u043a\u0430"
    ],
    "wof:name":"Dabrowka Wielka",
    "wof:placetype":"locality"
},
  "geometry": {"coordinates":[19.42567,51.8879],"type":"Point"}
}