{
  "type": "Feature",
  "properties": {
    "gn:admin1_code":"86.0",
    "gn:admin2_code":"3017.0",
    "gn:admin3_code":"301707.0",
    "gn:asciiname":"Kania",
    "gn:country_code":"PL",
    "gn:dem":133,
    "gn:feature_class":"P",
    "gn:feature_code":"PPL",
    "gn:name":"Kania",
    "gn:population":0,
    "gn:timezone":"Europe/Warsaw",
    "iso:country":"PL",
    "name:azb_x_preferred":[
        "\u06a9\u0627\u0646\u0642\u0627"
    ],
    "name:fas_x_preferred":[
        "\u06a9\u0627\u0646\u06af\u0627"
    ],
    "name:nld_x_preferred":[
        "Kania"
    ],
    "name:pol_x_preferred":[
        "Kania"
    ],
    "name:ukr_x_preferred":[
        "\u041a\u0430\u043d\u044f"
    ],
    "wof:name":"Kania",
    "wof:placetype":"locality"
},
  "geometry": {"coordinates":[18.17508,51.54993],"type":"Point"}
}