{
  "type": "Feature",
  "properties": {
    "gn:admin1_code":"78.0",
    "gn:admin2_code":"1433.0",
    "gn:admin3_code":"143309.0",
    "gn:asciiname":"Rabierz",
    "gn:country_code":"PL",
    "gn:dem":166,
    "gn:feature_class":"P",
    "gn:feature_code":"PPL",
    "gn:name":"R\u0105bierz",
    "gn:population":0,
    "gn:timezone":"Europe/Warsaw",
    "iso:country":"PL",
    "wof:name":"Rabierz",
    "wof:placetype":"locality"
},
  "geometry": {"coordinates":[21.75225,52.31622],"type":"Point"}
}