{
  "type": "Feature",
  "properties": {
    "gn:admin1_code":"73.0",
    "gn:admin2_code":"419.0",
    "gn:admin3_code":"41901.0",
    "gn:asciiname":"Wolice",
    "gn:country_code":"PL",
    "gn:dem":85,
    "gn:feature_class":"P",
    "gn:feature_code":"PPL",
    "gn:name":"Wolice",
    "gn:population":0,
    "gn:timezone":"Europe/Warsaw",
    "iso:country":"PL",
    "name:pol_x_preferred":[
        "Wolice"
    ],
    "name:ukr_x_preferred":[
        "\u0412\u043e\u043b\u0456\u0446\u0435"
    ],
    "wof:name":"Wolice",
    "wof:placetype":"locality"
},
  "geometry": {"coordinates":[17.90806,52.85596999999999],"type":"Point"}
}