{
  "type": "Feature",
  "properties": {
    "gn:admin1_code":"76.0",
    "gn:admin2_code":"808.0",
    "gn:admin3_code":"80803.0",
    "gn:asciiname":"Wegrzynice",
    "gn:country_code":"PL",
    "gn:dem":100,
    "gn:feature_class":"P",
    "gn:feature_code":"PPL",
    "gn:name":"W\u0119grzynice",
    "gn:population":0,
    "gn:timezone":"Europe/Warsaw",
    "iso:country":"PL",
    "name:und_x_variant":[
        "Ulbersdorf",
        "W\u0119grzynice"
    ],
    "wof:name":"Wegrzynice",
    "wof:placetype":"locality"
},
  "geometry": {"coordinates":[15.34437,52.19178],"type":"Point"}
}