{
  "type": "Feature",
  "properties": {
    "gn:admin1_code":"76.0",
    "gn:admin2_code":"808.0",
    "gn:admin3_code":"80803.0",
    "gn:asciiname":"Wegrzynice",
    "gn:country_code":"PL",
    "gn:dem":100,
    "gn:feature_class":"P",
    "gn:feature_code":"PPL",
    "gn:name":"W\u0119grzynice",
    "gn:population":0,
    "gn:timezone":"Europe/Warsaw",
    "iso:country":"PL",
    "name:ceb_x_preferred":[
        "W\u0119grzynice"
    ],
    "name:fra_x_preferred":[
        "W\u0119grzynice"
    ],
    "name:pol_x_preferred":[
        "W\u0119grzynice"
    ],
    "name:ukr_x_preferred":[
        "\u0412\u0435\u043d\u0491\u0436\u0438\u043d\u0456\u0446\u0435"
    ],
    "name:und_x_variant":[
        "Ulbersdorf"
    ],
    "wof:name":"Wegrzynice",
    "wof:placetype":"locality"
},
  "geometry": {"coordinates":[15.34437,52.19178],"type":"Point"}
}