{
  "type": "Feature",
  "properties": {
    "gn:admin1_code":"84.0",
    "gn:admin2_code":"2602.0",
    "gn:admin3_code":"260209.0",
    "gn:asciiname":"Promyk",
    "gn:country_code":"PL",
    "gn:dem":288,
    "gn:feature_class":"P",
    "gn:feature_code":"PPL",
    "gn:name":"Promyk",
    "gn:population":0,
    "gn:timezone":"Europe/Warsaw",
    "iso:country":"PL",
    "name:pol_x_preferred":[
        "Promyk"
    ],
    "name:ukr_x_preferred":[
        "\u041f\u0440\u043e\u043c\u0438\u043a"
    ],
    "wof:name":"Promyk",
    "wof:placetype":"locality"
},
  "geometry": {"coordinates":[20.17811,50.56056],"type":"Point"}
}