{
  "type": "Feature",
  "properties": {
    "gn:admin1_code":"74.0",
    "gn:admin2_code":"1007.0",
    "gn:admin3_code":"100704.0",
    "gn:asciiname":"Janow Karwicki",
    "gn:country_code":"PL",
    "gn:dem":198,
    "gn:feature_class":"P",
    "gn:feature_code":"PPL",
    "gn:name":"Jan\u00f3w Karwicki",
    "gn:population":0,
    "gn:timezone":"Europe/Warsaw",
    "iso:country":"PL",
    "name:azb_x_preferred":[
        "\u06cc\u0627\u0646\u0648\u0641 \u06a9\u0627\u0631\u0648\u06cc\u062a\u0633\u06a9\u06cc"
    ],
    "name:fas_x_preferred":[
        "\u06cc\u0627\u0646\u0648\u0641 \u06a9\u0627\u0631\u0648\u06cc\u062a\u0633\u06a9\u06cc"
    ],
    "name:fra_x_preferred":[
        "Jan\u00f3w Karwicki"
    ],
    "name:pol_x_preferred":[
        "Jan\u00f3w Karwicki"
    ],
    "name:ukr_x_preferred":[
        "\u042f\u043d\u0443\u0432-\u041a\u0430\u0440\u0432\u0456\u0446\u044c\u043a\u0438\u0439"
    ],
    "name:und_x_variant":[
        "Jan\u00f3w Karwicki"
    ],
    "name:urd_x_preferred":[
        "\u062c\u0646\u0648\u0648 \u06a9\u0631\u0648\u06a9\u06a9\u06cc"
    ],
    "wof:name":"Janow Karwicki",
    "wof:placetype":"locality"
},
  "geometry": {"coordinates":[20.36108,51.3695],"type":"Point"}
}