{
  "type": "Feature",
  "properties": {
    "gn:admin1_code":"74.0",
    "gn:admin2_code":"1007.0",
    "gn:admin3_code":"100704.0",
    "gn:asciiname":"Janow Karwicki",
    "gn:country_code":"PL",
    "gn:dem":198,
    "gn:feature_class":"P",
    "gn:feature_code":"PPL",
    "gn:name":"Jan\u00f3w Karwicki",
    "gn:population":0,
    "gn:timezone":"Europe/Warsaw",
    "iso:country":"PL",
    "name:und_x_variant":[
        "Jan\u00f3w Karwicki"
    ],
    "wof:name":"Janow Karwicki",
    "wof:placetype":"locality"
},
  "geometry": {"coordinates":[20.36108,51.3695],"type":"Point"}
}