{
  "type": "Feature",
  "properties": {
    "gn:admin1_code":"85.0",
    "gn:admin2_code":"2818.0",
    "gn:admin3_code":"281801.0",
    "gn:asciiname":"Jagoczany",
    "gn:country_code":"PL",
    "gn:dem":157,
    "gn:feature_class":"P",
    "gn:feature_code":"PPL",
    "gn:name":"Jagoczany",
    "gn:population":0,
    "gn:timezone":"Europe/Warsaw",
    "iso:country":"PL",
    "name:azb_x_preferred":[
        "\u06cc\u0627\u0642\u0648\u0686\u0627\u0646\u0647"
    ],
    "name:ceb_x_preferred":[
        "Jagoczany"
    ],
    "name:deu_x_preferred":[
        "Jagoczany"
    ],
    "name:fas_x_preferred":[
        "\u06cc\u0627\u06af\u0648\u0686\u0627\u0646\u0647"
    ],
    "name:nld_x_preferred":[
        "Jagoczany"
    ],
    "name:pol_x_preferred":[
        "Jagoczany"
    ],
    "name:ukr_x_preferred":[
        "\u042f\u0433\u043e\u0447\u0430\u043d\u0438"
    ],
    "name:und_x_variant":[
        "Gleisgarben",
        "Jagotschen",
        "Gleisgraben"
    ],
    "name:urd_x_preferred":[
        "\u062c\u06af\u0648\u06a9\u0632\u0646\u0646\u06d2"
    ],
    "name:vie_x_preferred":[
        "Jagoczany"
    ],
    "wof:name":"Jagoczany",
    "wof:placetype":"locality"
},
  "geometry": {"coordinates":[22.14586,54.3036],"type":"Point"}
}