{
  "type": "Feature",
  "properties": {
    "gn:admin1_code":"85.0",
    "gn:admin2_code":"2818.0",
    "gn:admin3_code":"281801.0",
    "gn:asciiname":"Jagoczany",
    "gn:country_code":"PL",
    "gn:dem":157,
    "gn:feature_class":"P",
    "gn:feature_code":"PPL",
    "gn:name":"Jagoczany",
    "gn:population":0,
    "gn:timezone":"Europe/Warsaw",
    "iso:country":"PL",
    "name:und_x_variant":[
        "Gleisgarben",
        "Jagotschen",
        "Gleisgraben",
        "Jagoczany"
    ],
    "wof:name":"Jagoczany",
    "wof:placetype":"locality"
},
  "geometry": {"coordinates":[22.14586,54.3036],"type":"Point"}
}