{
  "type": "Feature",
  "properties": {
    "gn:admin1_code":"77.0",
    "gn:admin2_code":"1214.0",
    "gn:admin3_code":"121405.0",
    "gn:asciiname":"Posilow",
    "gn:country_code":"PL",
    "gn:dem":232,
    "gn:feature_class":"P",
    "gn:feature_code":"PPL",
    "gn:name":"Posi\u0142\u00f3w",
    "gn:population":0,
    "gn:timezone":"Europe/Warsaw",
    "iso:country":"PL",
    "name:pol_x_preferred":[
        "Posi\u0142\u00f3w"
    ],
    "name:ukr_x_preferred":[
        "\u041f\u043e\u0441\u0456\u043b\u0443\u0432"
    ],
    "wof:name":"Posilow",
    "wof:placetype":"locality"
},
  "geometry": {"coordinates":[20.36522,50.20998],"type":"Point"}
}