{
  "type": "Feature",
  "properties": {
    "gn:country":"PL",
    "gn:fcode":"PPL",
    "gn:population":489,
    "iso:country":"PL",
    "name:ast_x_preferred":[
        "Gorzyce"
    ],
    "name:ceb_x_preferred":[
        "Gorzyce"
    ],
    "name:eng_x_preferred":[
        "Gorzyce"
    ],
    "name:fra_x_preferred":[
        "Gorzyce"
    ],
    "name:pol_x_preferred":[
        "Gorzyce"
    ],
    "name:ukr_x_preferred":[
        "\u0490\u043e\u0436\u0438\u0446\u0435"
    ],
    "qs_pg:aaroncc":"PL",
    "qs_pg:gn_country":"PL",
    "qs_pg:gn_fcode":"PPL",
    "qs_pg:gn_pop":489,
    "qs_pg:name":"Gorzyce",
    "qs_pg:name_adm0":"Polska",
    "qs_pg:name_adm1":"Podkarpackie",
    "qs_pg:photos_9r":0,
    "qs_pg:photos_sr":0,
    "qs_pg:pop_sr":2,
    "qs_pg:qs_pg_placetype":"locality",
    "qs_pg:qs_pg_placetype_gp":"Town",
    "qs_pg:woe_adm0":23424923,
    "woe:adm0_id":23424923,
    "woe:name_adm0":"Polska",
    "woe:name_adm1":"Podkarpackie",
    "woe:placetype":"Town",
    "wof:name":"Gorzyce",
    "wof:placetype":"locality",
    "wof:population":489
},
  "geometry": {"coordinates":[21.52702,49.63406],"type":"Point"}
}