{
  "type": "Feature",
  "properties": {
    "gn:admin1_code":"86.0",
    "gn:admin2_code":"3027.0",
    "gn:admin3_code":"302706.0",
    "gn:asciiname":"Sarbice",
    "gn:country_code":"PL",
    "gn:dem":98,
    "gn:feature_class":"P",
    "gn:feature_code":"PPL",
    "gn:name":"Sarbice",
    "gn:population":0,
    "gn:timezone":"Europe/Warsaw",
    "iso:country":"PL",
    "name:ceb_x_preferred":[
        "Sarbice"
    ],
    "name:deu_x_preferred":[
        "Sarbice"
    ],
    "name:pol_x_preferred":[
        "Sarbice"
    ],
    "name:ukr_x_preferred":[
        "\u0421\u0430\u0440\u0431\u0456\u0446\u0435"
    ],
    "wof:name":"Sarbice",
    "wof:placetype":"locality"
},
  "geometry": {"coordinates":[18.70749,52.03317],"type":"Point"}
}