{
  "type": "Feature",
  "properties": {
    "gn:admin1_code":"86.0",
    "gn:admin2_code":"3030.0",
    "gn:admin3_code":"303002.0",
    "gn:asciiname":"Keblowo",
    "gn:country_code":"PL",
    "gn:dem":94,
    "gn:feature_class":"P",
    "gn:feature_code":"PPL",
    "gn:name":"K\u0119b\u0142owo",
    "gn:population":0,
    "gn:timezone":"Europe/Warsaw",
    "iso:country":"PL",
    "name:fra_x_preferred":[
        "K\u0119b\u0142owo"
    ],
    "name:pol_x_preferred":[
        "K\u0119b\u0142owo"
    ],
    "name:ukr_x_preferred":[
        "\u041a\u0435\u043c\u0431\u043b\u043e\u0432\u043e"
    ],
    "wof:name":"Keblowo",
    "wof:placetype":"locality"
},
  "geometry": {"coordinates":[17.506,52.222],"type":"Point"}
}