{
  "type": "Feature",
  "properties": {
    "gn:admin1_code":"78.0",
    "gn:admin2_code":"1406.0",
    "gn:admin3_code":"140602.0",
    "gn:asciiname":"Wolka Kurdybanowska",
    "gn:country_code":"PL",
    "gn:dem":161,
    "gn:feature_class":"P",
    "gn:feature_code":"PPL",
    "gn:name":"W\u00f3lka Kurdybanowska",
    "gn:population":0,
    "gn:timezone":"Europe/Warsaw",
    "iso:country":"PL",
    "name:fra_x_preferred":[
        "W\u00f3lka Kurdybanowska"
    ],
    "name:pol_x_preferred":[
        "W\u00f3lka Kurdybanowska"
    ],
    "name:ukr_x_preferred":[
        "\u0412\u0443\u043b\u044c\u043a\u0430-\u041a\u0443\u0440\u0434\u0438\u0431\u0430\u043d\u043e\u0432\u0441\u044c\u043a\u0430"
    ],
    "name:und_x_variant":[
        "W\u00f3lka Kurdybanowska"
    ],
    "wof:name":"Wolka Kurdybanowska",
    "wof:placetype":"locality"
},
  "geometry": {"coordinates":[20.65417,51.78058],"type":"Point"}
}