{
  "type": "Feature",
  "properties": {
    "gn:admin1_code":"85.0",
    "gn:admin2_code":"2810.0",
    "gn:admin3_code":"281003.0",
    "gn:asciiname":"Probark",
    "gn:country_code":"PL",
    "gn:dem":143,
    "gn:feature_class":"P",
    "gn:feature_code":"PPL",
    "gn:name":"Probark",
    "gn:population":0,
    "gn:timezone":"Europe/Warsaw",
    "iso:country":"PL",
    "name:deu_x_preferred":[
        "Probark"
    ],
    "name:fra_x_preferred":[
        "Probark"
    ],
    "name:pol_x_preferred":[
        "Probark"
    ],
    "name:ukr_x_preferred":[
        "\u041f\u0440\u043e\u0431\u0430\u0440\u043a"
    ],
    "name:und_x_variant":[
        "Alt Proberg",
        "Proberg",
        "Probarg"
    ],
    "wof:name":"Probark",
    "wof:placetype":"locality"
},
  "geometry": {"coordinates":[21.36939,53.82978000000001],"type":"Point"}
}