{
  "type": "Feature",
  "properties": {
    "gn:admin1_code":"83.0",
    "gn:admin2_code":"2407.0",
    "gn:admin3_code":"240703.0",
    "gn:asciiname":"Dzielna",
    "gn:country_code":"PL",
    "gn:dem":257,
    "gn:feature_class":"P",
    "gn:feature_code":"PPL",
    "gn:name":"Dzielna",
    "gn:population":0,
    "gn:timezone":"Europe/Warsaw",
    "iso:country":"PL",
    "name:pol_x_preferred":[
        "Dzielna"
    ],
    "wof:name":"Dzielna",
    "wof:placetype":"locality"
},
  "geometry": {"coordinates":[18.55273,50.74297],"type":"Point"}
}