{
  "type": "Feature",
  "properties": {
    "gn:admin1_code":"81.0",
    "gn:admin2_code":"2010.0",
    "gn:admin3_code":"201003.0",
    "gn:asciiname":"Korzeniowka",
    "gn:country_code":"PL",
    "gn:dem":175,
    "gn:feature_class":"P",
    "gn:feature_code":"PPL",
    "gn:name":"Korzeni\u00f3wka",
    "gn:population":0,
    "gn:timezone":"Europe/Warsaw",
    "iso:country":"PL",
    "name:fra_x_preferred":[
        "Korzeni\u00f3wka"
    ],
    "name:lit_x_preferred":[
        "Ko\u017eeniuvka"
    ],
    "name:pol_x_preferred":[
        "Korzeni\u00f3wka"
    ],
    "name:ukr_x_preferred":[
        "\u041a\u043e\u0436\u0435\u043d\u044e\u0432\u043a\u0430"
    ],
    "wof:name":"Korzeniowka",
    "wof:placetype":"locality"
},
  "geometry": {"coordinates":[22.89041,52.55775],"type":"Point"}
}