{
  "type": "Feature",
  "properties": {
    "gn:admin1_code":"80.0",
    "gn:admin2_code":"1812.0",
    "gn:admin3_code":"181201.0",
    "gn:asciiname":"Huta Nowa",
    "gn:country_code":"PL",
    "gn:dem":180,
    "gn:feature_class":"P",
    "gn:feature_code":"PPL",
    "gn:name":"Huta Nowa",
    "gn:population":0,
    "gn:timezone":"Europe/Warsaw",
    "iso:country":"PL",
    "name:pol_x_preferred":[
        "Huta Nowa"
    ],
    "name:ukr_x_preferred":[
        "\u0413\u0443\u0442\u0430-\u041d\u043e\u0432\u0430"
    ],
    "name:und_x_variant":[
        "Huta Krzeszowska Nowa"
    ],
    "wof:name":"Huta Nowa",
    "wof:placetype":"locality"
},
  "geometry": {"coordinates":[22.4764,50.51812],"type":"Point"}
}