{
  "type": "Feature",
  "properties": {
    "gn:admin1_code":"85.0",
    "gn:admin2_code":"2814.0",
    "gn:admin3_code":"281401.0",
    "gn:asciiname":"Ramsowo",
    "gn:cc2":"PL",
    "gn:country_code":"PL",
    "gn:dem":140,
    "gn:feature_class":"P",
    "gn:feature_code":"PPL",
    "gn:name":"Ramsowo",
    "gn:population":0,
    "gn:timezone":"Europe/Warsaw",
    "iso:country":"PL",
    "name:pol_x_preferred":[
        "Ramsowo"
    ],
    "name:ukr_x_preferred":[
        "\u0420\u0430\u043c\u0441\u043e\u0432\u043e"
    ],
    "name:und_x_variant":[
        "Wielkie Ramsowo",
        "Gross Ramsau"
    ],
    "name:vie_x_preferred":[
        "Ramsowo"
    ],
    "wof:name":"Ramsowo",
    "wof:placetype":"locality"
},
  "geometry": {"coordinates":[20.81669,53.85445],"type":"Point"}
}