{
  "type": "Feature",
  "properties": {
    "gn:admin1_code":"81.0",
    "gn:admin2_code":"2013.0",
    "gn:admin3_code":"201308.0",
    "gn:asciiname":"Jablon Spaly",
    "gn:country_code":"PL",
    "gn:dem":147,
    "gn:feature_class":"P",
    "gn:feature_code":"PPL",
    "gn:name":"Jab\u0142o\u0144 Spa\u0142y",
    "gn:population":0,
    "gn:timezone":"Europe/Warsaw",
    "iso:country":"PL",
    "name:und_x_variant":[
        "Jab\u0142o\u0144 Spa\u0142y"
    ],
    "wof:name":"Jablon Spaly",
    "wof:placetype":"locality"
},
  "geometry": {"coordinates":[22.66667,52.95],"type":"Point"}
}