{
  "type": "Feature",
  "properties": {
    "gn:admin1_code":"81.0",
    "gn:admin2_code":"2013.0",
    "gn:admin3_code":"201308.0",
    "gn:asciiname":"Jablon Spaly",
    "gn:country_code":"PL",
    "gn:dem":147,
    "gn:feature_class":"P",
    "gn:feature_code":"PPL",
    "gn:name":"Jab\u0142o\u0144 Spa\u0142y",
    "gn:population":0,
    "gn:timezone":"Europe/Warsaw",
    "iso:country":"PL",
    "name:azb_x_preferred":[
        "\u06cc\u0627\u0628\u0648\u0648\u0646\u0642-\u0633\u067e\u0627\u0648\u0647"
    ],
    "name:fas_x_preferred":[
        "\u06cc\u0627\u0628\u0648\u0648\u0646\u06af-\u0633\u067e\u0627\u0648\u0647"
    ],
    "name:lit_x_preferred":[
        "Jablon Spalai"
    ],
    "name:nld_x_preferred":[
        "Jab\u0142o\u0144-Spa\u0142y"
    ],
    "name:pol_x_preferred":[
        "Jab\u0142o\u0144-Spa\u0142y"
    ],
    "name:ukr_x_preferred":[
        "\u042f\u0431\u043b\u043e\u043d\u044c-\u0421\u043f\u0430\u043b\u0438"
    ],
    "name:und_x_variant":[
        "Jab\u0142o\u0144 Spa\u0142y"
    ],
    "name:urd_x_preferred":[
        "\u062c\u0628\u0648\u0648\u0646-\u0633\u067e\u0627\u0648\u06cc"
    ],
    "wof:name":"Jablon Spaly",
    "wof:placetype":"locality"
},
  "geometry": {"coordinates":[22.66667,52.95],"type":"Point"}
}