{
  "type": "Feature",
  "properties": {
    "gn:admin1_code":"82.0",
    "gn:admin2_code":"2214.0",
    "gn:admin3_code":"221402.0",
    "gn:asciiname":"Pieniazkowo",
    "gn:country_code":"PL",
    "gn:dem":80,
    "gn:feature_class":"P",
    "gn:feature_code":"PPL",
    "gn:name":"Pieni\u0105\u017ckowo",
    "gn:population":0,
    "gn:timezone":"Europe/Warsaw",
    "iso:country":"PL",
    "name:ceb_x_preferred":[
        "Pieni\u0105\u017ckowo"
    ],
    "name:pol_x_preferred":[
        "Pieni\u0105\u017ckowo"
    ],
    "name:ukr_x_preferred":[
        "\u041f\u0435\u043d\u044c\u043e\u043d\u0436\u043a\u043e\u0432\u043e"
    ],
    "name:und_x_variant":[
        "Pieni\u0105\u017ckowo"
    ],
    "wof:name":"Pieniazkowo",
    "wof:placetype":"locality"
},
  "geometry": {"coordinates":[18.7348,53.69479000000001],"type":"Point"}
}