{
  "type": "Feature",
  "properties": {
    "gn:admin1_code":"86.0",
    "gn:admin2_code":"3010.0",
    "gn:admin3_code":"301003.0",
    "gn:asciiname":"Wladyslawow",
    "gn:country_code":"PL",
    "gn:dem":103,
    "gn:feature_class":"P",
    "gn:feature_code":"PPL",
    "gn:name":"W\u0142adys\u0142aw\u00f3w",
    "gn:population":0,
    "gn:timezone":"Europe/Warsaw",
    "iso:country":"PL",
    "name:und_x_variant":[
        "W\u0142adzimir\u00f3w",
        "W\u0142adys\u0142aw\u00f3w"
    ],
    "wof:name":"Wladyslawow",
    "wof:placetype":"locality"
},
  "geometry": {"coordinates":[18.21353,52.28181],"type":"Point"}
}