{
  "type": "Feature",
  "properties": {
    "gn:admin1_code":"75.0",
    "gn:admin2_code":"609.0",
    "gn:admin3_code":"60903.0",
    "gn:asciiname":"Kolonia Bychawka",
    "gn:country_code":"PL",
    "gn:dem":224,
    "gn:feature_class":"P",
    "gn:feature_code":"PPL",
    "gn:name":"Kolonia Bychawka",
    "gn:population":0,
    "gn:timezone":"Europe/Warsaw",
    "iso:country":"PL",
    "wof:name":"Kolonia Bychawka",
    "wof:placetype":"locality"
},
  "geometry": {"coordinates":[22.55,51.05],"type":"Point"}
}