{
  "type": "Feature",
  "properties": {
    "gn:admin1_code":"85.0",
    "gn:admin2_code":"2804.0",
    "gn:admin3_code":"280407.0",
    "gn:asciiname":"Nowa Wies Cierpkie",
    "gn:country_code":"PL",
    "gn:dem":60,
    "gn:feature_class":"P",
    "gn:feature_code":"PPL",
    "gn:name":"Nowa Wie\u015b Cierpkie",
    "gn:population":0,
    "gn:timezone":"Europe/Warsaw",
    "iso:country":"PL",
    "name:pol_x_preferred":[
        "Cierpkie"
    ],
    "name:und_x_variant":[
        "Neudorf Friedheim",
        "Neuendorf-Friedheim",
        "Nowa Wie\u015b Cierpkie",
        "Nowa Wie\u015b"
    ],
    "wof:name":"Nowa Wies Cierpkie",
    "wof:placetype":"locality"
},
  "geometry": {"coordinates":[19.66056,54.03306],"type":"Point"}
}