{
  "type": "Feature",
  "properties": {
    "gn:admin1_code":"82.0",
    "gn:admin2_code":"2206.0",
    "gn:admin3_code":"220604.0",
    "gn:asciiname":"Stawiska",
    "gn:country_code":"PL",
    "gn:dem":145,
    "gn:feature_class":"P",
    "gn:feature_code":"PPL",
    "gn:name":"Stawiska",
    "gn:population":0,
    "gn:timezone":"Europe/Warsaw",
    "iso:country":"PL",
    "name:ceb_x_preferred":[
        "Stawiska"
    ],
    "name:pol_x_preferred":[
        "Stawiska"
    ],
    "name:ukr_x_preferred":[
        "\u0421\u0442\u0430\u0432\u0438\u0441\u044c\u043a\u0430"
    ],
    "wof:name":"Stawiska",
    "wof:placetype":"locality"
},
  "geometry": {"coordinates":[18.02876,54.0561],"type":"Point"}
}