{
  "type": "Feature",
  "properties": {
    "gn:admin1_code":"85.0",
    "gn:admin2_code":"2807.0",
    "gn:admin3_code":"280706.0",
    "gn:asciiname":"Zakowice",
    "gn:cc2":"PL",
    "gn:country_code":"PL",
    "gn:dem":107,
    "gn:feature_class":"P",
    "gn:feature_code":"PPL",
    "gn:name":"\u017bakowice",
    "gn:population":0,
    "gn:timezone":"Europe/Warsaw",
    "iso:country":"PL",
    "name:und_x_variant":[
        "Schakenbruch",
        "\u017bakowice"
    ],
    "wof:name":"Zakowice",
    "wof:placetype":"locality"
},
  "geometry": {"coordinates":[19.23414,53.67383],"type":"Point"}
}