{
  "type": "Feature",
  "properties": {
    "gn:admin1_code":"87.0",
    "gn:admin2_code":"3215.0",
    "gn:admin3_code":"321503.0",
    "gn:asciiname":"Stepien",
    "gn:country_code":"PL",
    "gn:dem":142,
    "gn:feature_class":"P",
    "gn:feature_code":"PPL",
    "gn:name":"Stepie\u0144",
    "gn:population":0,
    "gn:timezone":"Europe/Warsaw",
    "iso:country":"PL",
    "name:ceb_x_preferred":[
        "Stepie\u0144"
    ],
    "name:pol_x_preferred":[
        "Stepie\u0144"
    ],
    "name:und_x_variant":[
        "Stepie\u0144"
    ],
    "name:vie_x_preferred":[
        "St\u0119pie\u0144"
    ],
    "wof:name":"Stepien",
    "wof:placetype":"locality"
},
  "geometry": {"coordinates":[16.7669,53.82252],"type":"Point"}
}