{
  "type": "Feature",
  "properties": {
    "gn:gn_country":"PL",
    "gn:gn_fcode":"PPL",
    "gn:gn_pop":0,
    "iso:country":"PL",
    "name:eng_x_preferred":[
        "Z\u0105b"
    ],
    "name:fra_x_preferred":[
        "Z\u0105b"
    ],
    "name:nld_x_preferred":[
        "Z\u0105b"
    ],
    "name:pol_x_preferred":[
        "Z\u0105b"
    ],
    "name:urd_x_preferred":[
        "\u0632\u0627\u0645\u067e\u060c \u0644\u06cc\u0633\u0631 \u067e\u0648\u0644\u06cc\u0646\u0688 \u0648\u0648\u0626\u06cc \u0648\u0648\u062f\u0634\u067e"
    ],
    "qs_pg:aaroncc":"PL",
    "qs_pg:gn_country":"PL",
    "qs_pg:gn_fcode":"PPL",
    "qs_pg:gn_pop":0,
    "qs_pg:name":"Z\u0105b",
    "qs_pg:name_adm0":"Polska",
    "qs_pg:name_adm1":"Ma\u0142opolskie",
    "qs_pg:photos":54,
    "qs_pg:photos_1k":11,
    "qs_pg:photos_9k":1,
    "qs_pg:photos_9r":2,
    "qs_pg:photos_all":54,
    "qs_pg:photos_sr":2,
    "qs_pg:pop_sr":0,
    "qs_pg:qs_pg_placetype":"locality",
    "qs_pg:qs_pg_placetype_gp":"Town",
    "qs_pg:woe_adm0":23424923,
    "woe:adm0_id":23424923,
    "woe:name_adm0":"Polska",
    "woe:name_adm1":"Ma\u0142opolskie",
    "woe:placetype":"Town",
    "wof:name":"Z\u0105b",
    "wof:placetype":"locality"
},
  "geometry": {"coordinates":[19.94877,49.33765],"type":"Point"}
}