{
  "type": "Feature",
  "properties": {
    "gn:admin1_code":"86.0",
    "gn:admin2_code":"3027.0",
    "gn:admin3_code":"302709.0",
    "gn:asciiname":"Kamionka",
    "gn:country_code":"PL",
    "gn:dem":109,
    "gn:feature_class":"P",
    "gn:feature_code":"PPL",
    "gn:name":"Kamionka",
    "gn:population":0,
    "gn:timezone":"Europe/Warsaw",
    "iso:country":"PL",
    "name:ceb_x_preferred":[
        "Kamionka"
    ],
    "name:deu_x_preferred":[
        "Kamionka"
    ],
    "name:fra_x_preferred":[
        "Kamionka"
    ],
    "name:lit_x_preferred":[
        "Kamionka"
    ],
    "name:pol_x_preferred":[
        "Kamionka"
    ],
    "name:swe_x_preferred":[
        "Kamionka"
    ],
    "name:ukr_x_preferred":[
        "\u041a\u0430\u043c\u0439\u043e\u043d\u043a\u0430"
    ],
    "wof:name":"Kamionka",
    "wof:placetype":"locality"
},
  "geometry": {"coordinates":[18.45612,52.12616],"type":"Point"}
}