{
  "type": "Feature",
  "properties": {
    "iso:country":"PL",
    "name:ces_x_preferred":[
        "Tyniec"
    ],
    "name:deu_x_preferred":[
        "Tyniec"
    ],
    "name:eng_x_preferred":[
        "Tyniec"
    ],
    "name:epo_x_preferred":[
        "Tyniec"
    ],
    "name:nld_x_preferred":[
        "Tyniec"
    ],
    "name:pol_x_preferred":[
        "Tyniec"
    ],
    "name:rus_x_preferred":[
        "\u0422\u044b\u043d\u0435\u0446"
    ],
    "name:ukr_x_preferred":[
        "\u0422\u0438\u043d\u0435\u0446\u044c"
    ],
    "qs:gn_adm0_cc":"PL",
    "qs:gn_fcode":"PPLX",
    "qs:gn_local":7531791,
    "qs:gn_nam_loc":"Krak\u00f3w, Krak\u00f3w, Ma\u0142opolskie, PL",
    "qs:gn_namadm1":"77",
    "qs:gn_name":"Tyniec",
    "qs:local_max":474,
    "qs:local_sum":1006,
    "qs:localhoods":3,
    "qs:name":"Tyniec",
    "qs:name_adm0":"Polska",
    "qs:name_adm1":"Ma\u0142opolskie",
    "qs:name_adm2":"Krak\u00f3w",
    "qs:name_lau":"Krak\u00f3w",
    "qs:name_local":"Krak\u00f3w",
    "qs:photo_max":173,
    "qs:photo_sum":474,
    "qs:placetype":"Suburb",
    "qs:quad_count":53,
    "qs:woe_adm0":23424923,
    "qs:woe_adm1":12577940,
    "qs:woe_adm2":12591253,
    "qs:woe_lau":12618071,
    "qs:woe_local":12618071,
    "qs:woe_ver":"7.10.0",
    "wd:wordcount":957,
    "wof:lang":[
        "pol"
    ],
    "wof:name":"Tyniec",
    "wof:placetype":"neighbourhood"
},
  "geometry": {"coordinates":[19.818832,50.029354],"type":"Point"}
}