{
  "type": "Feature",
  "properties": {
    "gn:admin1_code":"77.0",
    "gn:admin2_code":"1211.0",
    "gn:admin3_code":"121103.0",
    "gn:asciiname":"Gruszkowie",
    "gn:country_code":"PL",
    "gn:dem":647,
    "gn:feature_class":"P",
    "gn:feature_code":"PPL",
    "gn:name":"Gruszkowie",
    "gn:population":0,
    "gn:timezone":"Europe/Warsaw",
    "iso:country":"PL",
    "wof:name":"Gruszkowie",
    "wof:placetype":"locality"
},
  "geometry": {"coordinates":[19.85,49.46667],"type":"Point"}
}