{
  "type": "Feature",
  "properties": {
    "gn:admin1_code":"78.0",
    "gn:admin2_code":"1406.0",
    "gn:admin3_code":"140601.0",
    "gn:asciiname":"Wola Leczeszycka",
    "gn:country_code":"PL",
    "gn:dem":156,
    "gn:feature_class":"P",
    "gn:feature_code":"PPL",
    "gn:name":"Wola \u0141\u0119czeszycka",
    "gn:population":0,
    "gn:timezone":"Europe/Warsaw",
    "iso:country":"PL",
    "name:fra_x_preferred":[
        "Wola \u0141\u0119czeszycka"
    ],
    "name:pol_x_preferred":[
        "Wola \u0141\u0119czeszycka"
    ],
    "name:ukr_x_preferred":[
        "\u0412\u043e\u043b\u044f-\u041b\u0435\u043d\u0447\u0435\u0448\u0438\u0446\u044c\u043a\u0430"
    ],
    "wof:name":"Wola Leczeszycka",
    "wof:placetype":"locality"
},
  "geometry": {"coordinates":[20.7578,51.7647],"type":"Point"}
}