{
  "type": "Feature",
  "properties": {
    "gn:admin1_code":"86.0",
    "gn:admin2_code":"3020.0",
    "gn:admin3_code":"302003.0",
    "gn:asciiname":"Trzebin",
    "gn:country_code":"PL",
    "gn:dem":150,
    "gn:feature_class":"P",
    "gn:feature_code":"PPL",
    "gn:name":"Trzebin",
    "gn:population":0,
    "gn:timezone":"Europe/Warsaw",
    "iso:country":"PL",
    "name:azb_x_preferred":[
        "\u0686\u0628\u06cc\u0646"
    ],
    "name:fas_x_preferred":[
        "\u0686\u0628\u06cc\u0646"
    ],
    "name:pol_x_preferred":[
        "Trzebin"
    ],
    "name:ukr_x_preferred":[
        "\u0422\u0448\u0435\u0431\u0456\u043d"
    ],
    "wof:name":"Trzebin",
    "wof:placetype":"locality"
},
  "geometry": {"coordinates":[17.55046,51.86731],"type":"Point"}
}