{
  "type": "Feature",
  "properties": {
    "gn:population":1834,
    "iso:country":"PL",
    "name:azb_x_preferred":[
        "\u0642\u0645\u06cc\u0646\u0627 \u0633\u062a\u0627\u0631\u0647 \u067e\u0648\u0644\u0647"
    ],
    "name:bel_x_preferred":[
        "\u0413\u043c\u0456\u043d\u0430 \u0421\u0442\u0430\u0440\u044d \u041f\u043e\u043b\u0435"
    ],
    "name:deu_x_preferred":[
        "Gmina Stare Pole"
    ],
    "name:eng_x_preferred":[
        "Stare Pole"
    ],
    "name:eng_x_variant":[
        "Gmina Stare Pole"
    ],
    "name:eus_x_preferred":[
        "Stare Pole udalerria"
    ],
    "name:fas_x_preferred":[
        "\u06af\u0645\u06cc\u0646\u0627 \u0633\u062a\u0627\u0631\u0647 \u067e\u0648\u0644\u0647"
    ],
    "name:fra_x_preferred":[
        "Stare Pole"
    ],
    "name:ita_x_preferred":[
        "Stare Pole"
    ],
    "name:nan_x_preferred":[
        "Stare Pole"
    ],
    "name:nld_x_preferred":[
        "Stare Pole"
    ],
    "name:pol_x_preferred":[
        "Stare Pole"
    ],
    "name:por_x_preferred":[
        "Comuna de Stare Pole"
    ],
    "name:rus_x_preferred":[
        "\u0421\u0442\u0430\u0440\u0435-\u041f\u043e\u043b\u0435"
    ],
    "name:slk_x_preferred":[
        "Gmina Stare Pole"
    ],
    "name:ukr_x_preferred":[
        "\u0490\u043c\u0456\u043d\u0430 \u0421\u0442\u0430\u0440\u0435 \u041f\u043e\u043b\u0435"
    ],
    "name:und_x_variant":[
        "Altfelde"
    ],
    "name:war_x_preferred":[
        "Gmina Stare Pole"
    ],
    "name:zho_min_nan_x_preferred":[
        "Stare Pole"
    ],
    "qs:a0":"Rzeczpospolita Polska",
    "qs:a1":"*Pomorskie",
    "qs:a1r":"0",
    "qs:a2":"Malborski",
    "qs:adm0":"Rzeczpospolita Polska",
    "qs:la":"Stare Pole",
    "qs:la_lc":"*PL2209082",
    "qs:level":"locality",
    "qs:loc":"Stare Pole",
    "qs:loc_alt":"Stare Pole",
    "qs:pop":0,
    "qs:type":"rural point-in-poly",
    "wd:wordcount":128,
    "wof:name":"Stare Pole",
    "wof:placetype":"locality",
    "wof:population":1834
},
  "geometry": {"coordinates":[19.1864759773266,54.0524930727049],"type":"Point"}
}