{
  "type": "Feature",
  "properties": {
    "gn:admin1_code":"78.0",
    "gn:admin2_code":"1419.0",
    "gn:admin3_code":"141908.0",
    "gn:asciiname":"Rakcice",
    "gn:country_code":"PL",
    "gn:dem":118,
    "gn:feature_class":"P",
    "gn:feature_code":"PPL",
    "gn:name":"R\u0105kcice",
    "gn:population":0,
    "gn:timezone":"Europe/Warsaw",
    "iso:country":"PL",
    "name:fra_x_preferred":[
        "R\u0105kcice"
    ],
    "name:pol_x_preferred":[
        "R\u0105kcice"
    ],
    "name:ukr_x_preferred":[
        "\u0420\u043e\u043d\u043a\u0446\u0438\u0446\u0435"
    ],
    "wof:name":"Rakcice",
    "wof:placetype":"locality"
},
  "geometry": {"coordinates":[20.15537,52.5039],"type":"Point"}
}