{
  "type": "Feature",
  "properties": {
    "gn:admin1_code":"87.0",
    "gn:admin2_code":"3218.0",
    "gn:admin3_code":"321802.0",
    "gn:asciiname":"Grabowo",
    "gn:country_code":"PL",
    "gn:dem":106,
    "gn:feature_class":"P",
    "gn:feature_code":"PPL",
    "gn:name":"Grabowo",
    "gn:population":0,
    "gn:timezone":"Europe/Warsaw",
    "iso:country":"PL",
    "name:pol_x_preferred":[
        "Grabowo"
    ],
    "name:vie_x_preferred":[
        "Grabowo"
    ],
    "wof:name":"Grabowo",
    "wof:placetype":"locality"
},
  "geometry": {"coordinates":[15.69001,53.66766],"type":"Point"}
}