{
  "type": "Feature",
  "properties": {
    "gn:admin1_code":"86.0",
    "gn:admin2_code":"3031.0",
    "gn:admin3_code":"303104.0",
    "gn:asciiname":"Osowo",
    "gn:country_code":"PL",
    "gn:dem":130,
    "gn:feature_class":"P",
    "gn:feature_code":"PPL",
    "gn:name":"Osowo",
    "gn:population":0,
    "gn:timezone":"Europe/Warsaw",
    "iso:country":"PL",
    "name:bel_x_preferred":[
        "\u0412\u043e\u0441\u0430\u0432\u0430"
    ],
    "name:ceb_x_preferred":[
        "Osowo"
    ],
    "name:deu_x_preferred":[
        "Osowo"
    ],
    "name:fra_x_preferred":[
        "Osowo"
    ],
    "name:pol_x_preferred":[
        "Osowo"
    ],
    "name:rus_x_preferred":[
        "\u041e\u0441\u043e\u0432\u043e"
    ],
    "name:ukr_x_preferred":[
        "\u041e\u0441\u043e\u0432\u043e"
    ],
    "wof:name":"Osowo",
    "wof:placetype":"locality"
},
  "geometry": {"coordinates":[17.2492,53.44778],"type":"Point"}
}