{
  "type": "Feature",
  "properties": {
    "gn:admin1_code":"76.0",
    "gn:admin2_code":"803.0",
    "gn:admin3_code":"80306.0",
    "gn:asciiname":"Sierczynek",
    "gn:country_code":"PL",
    "gn:dem":61,
    "gn:feature_class":"P",
    "gn:feature_code":"PPL",
    "gn:name":"Sierczynek",
    "gn:population":0,
    "gn:timezone":"Europe/Warsaw",
    "iso:country":"PL",
    "name:ceb_x_preferred":[
        "Sierczynek"
    ],
    "name:fra_x_preferred":[
        "Sierczynek"
    ],
    "name:pol_x_preferred":[
        "Sierczynek"
    ],
    "name:ukr_x_preferred":[
        "\u0421\u0435\u0440\u0447\u0438\u043d\u0435\u043a"
    ],
    "wof:name":"Sierczynek",
    "wof:placetype":"locality"
},
  "geometry": {"coordinates":[15.77479,52.39723],"type":"Point"}
}