{
  "type": "Feature",
  "properties": {
    "iso:country":"PL",
    "name:deu_x_preferred":[
        "Stogi"
    ],
    "name:pol_x_preferred":[
        "Stogi"
    ],
    "name:ukr_x_preferred":[
        "\u0421\u0442\u043e\u0491\u0456"
    ],
    "qs:gn_adm0_cc":"PL",
    "qs:gn_fcode":"PPL",
    "qs:gn_local":3099434,
    "qs:gn_nam_loc":"Gdansk, Gda\u0144sk, Pomorskie, PL",
    "qs:gn_namadm1":"82",
    "qs:gn_name":"Stogi",
    "qs:local_max":11560,
    "qs:local_sum":12109,
    "qs:localhoods":5,
    "qs:name":"Stogi",
    "qs:name_adm0":"Polska",
    "qs:name_adm1":"Pomorskie",
    "qs:name_adm2":"Gdansk",
    "qs:name_lau":"Gdansk",
    "qs:name_local":"Gda\u0144sk",
    "qs:photo_max":30,
    "qs:photo_sum":170,
    "qs:placetype":"Suburb",
    "qs:quad_count":30,
    "qs:woe_adm0":23424923,
    "qs:woe_adm1":12577945,
    "qs:woe_adm2":12591368,
    "qs:woe_lau":12618131,
    "qs:woe_local":493417,
    "qs:woe_ver":"7.10.0",
    "wd:wordcount":28,
    "wof:lang":[
        "pol"
    ],
    "wof:name":"Stogi",
    "wof:placetype":"neighbourhood"
},
  "geometry": {"coordinates":[18.708703,54.363384],"type":"Point"}
}