{
  "type": "Feature",
  "properties": {
    "gn:admin1_code":"85.0",
    "gn:admin2_code":"2815.0",
    "gn:admin3_code":"281507.0",
    "gn:asciiname":"Liwa",
    "gn:country_code":"PL",
    "gn:dem":103,
    "gn:feature_class":"P",
    "gn:feature_code":"PPL",
    "gn:name":"Liwa",
    "gn:population":0,
    "gn:timezone":"Europe/Warsaw",
    "iso:country":"PL",
    "name:ceb_x_preferred":[
        "Liwa"
    ],
    "name:deu_x_preferred":[
        "Liwa"
    ],
    "name:fra_x_preferred":[
        "Liwa"
    ],
    "name:pol_x_preferred":[
        "Liwa"
    ],
    "name:ukr_x_preferred":[
        "\u041b\u0456\u0432\u0430"
    ],
    "name:und_x_variant":[
        "Bieberswalde"
    ],
    "wof:name":"Liwa",
    "wof:placetype":"locality"
},
  "geometry": {"coordinates":[19.82425,53.72846],"type":"Point"}
}