{
  "type": "Feature",
  "properties": {
    "gn:admin1_code":"72.0",
    "gn:admin2_code":"209.0",
    "gn:admin3_code":"20908.0",
    "gn:asciiname":"Wagrodno",
    "gn:country_code":"PL",
    "gn:dem":127,
    "gn:feature_class":"P",
    "gn:feature_code":"PPL",
    "gn:name":"W\u0105grodno",
    "gn:population":0,
    "gn:timezone":"Europe/Warsaw",
    "iso:country":"PL",
    "name:und_x_variant":[
        "W\u0105grodno"
    ],
    "wof:name":"Wagrodno",
    "wof:placetype":"locality"
},
  "geometry": {"coordinates":[16.38441,51.20025],"type":"Point"}
}