{
  "type": "Feature",
  "properties": {
    "gn:admin1_code":"74.0",
    "gn:admin2_code":"1011.0",
    "gn:admin3_code":"101106.0",
    "gn:asciiname":"Kolonia Kazimierz",
    "gn:country_code":"PL",
    "gn:dem":148,
    "gn:feature_class":"P",
    "gn:feature_code":"PPL",
    "gn:name":"Kolonia Kazimierz",
    "gn:population":0,
    "gn:timezone":"Europe/Warsaw",
    "iso:country":"PL",
    "name:fra_x_preferred":[
        "Kazimierzew"
    ],
    "name:pol_x_preferred":[
        "Kazimierzew"
    ],
    "name:ukr_x_preferred":[
        "\u041a\u0430\u0437\u0456\u043c\u0435\u0436\u0435\u0432"
    ],
    "name:und_x_variant":[
        "Kolonia Kazimierzew",
        "Kolonia Kazimierz"
    ],
    "wof:name":"Kolonia Kazimierz",
    "wof:placetype":"locality"
},
  "geometry": {"coordinates":[18.85319,51.77314000000001],"type":"Point"}
}