{
  "type": "Feature",
  "properties": {
    "gn:gn_country":"PL",
    "gn:gn_fcode":"PPL",
    "gn:gn_pop":151,
    "gn:population":151,
    "iso:country":"PL",
    "qs_pg:aaroncc":"PL",
    "qs_pg:gn_country":"PL",
    "qs_pg:gn_fcode":"PPL",
    "qs_pg:gn_pop":151,
    "qs_pg:name":"Psary",
    "qs_pg:name_adm0":"Polska",
    "qs_pg:name_adm1":"Wielkopolskie",
    "qs_pg:photos_9r":0,
    "qs_pg:photos_sr":0,
    "qs_pg:pop_sr":1,
    "qs_pg:qs_pg_placetype":"locality",
    "qs_pg:qs_pg_placetype_gp":"Town",
    "qs_pg:woe_adm0":23424923,
    "woe:adm0_id":23424923,
    "woe:name_adm0":"Polska",
    "woe:name_adm1":"Wielkopolskie",
    "woe:placetype":"Town",
    "wof:name":"Psary",
    "wof:placetype":"locality",
    "wof:population":151
},
  "geometry": {"coordinates":[19.02952,52.35474],"type":"Point"}
}