{
  "type": "Feature",
  "properties": {
    "gn:admin1_code":"79.0",
    "gn:admin2_code":"1607.0",
    "gn:admin3_code":"160708.0",
    "gn:asciiname":"Spiny",
    "gn:country_code":"PL",
    "gn:dem":286,
    "gn:feature_class":"P",
    "gn:feature_code":"PPL",
    "gn:name":"Spiny",
    "gn:population":0,
    "gn:timezone":"Europe/Warsaw",
    "iso:country":"PL",
    "wof:name":"Spiny",
    "wof:placetype":"locality"
},
  "geometry": {"coordinates":[17.23173,50.55741],"type":"Point"}
}