{
  "type": "Feature",
  "properties": {
    "gn:admin1_code":"78.0",
    "gn:admin2_code":"1435.0",
    "gn:admin3_code":"143503.0",
    "gn:asciiname":"Wielatki",
    "gn:country_code":"PL",
    "gn:dem":103,
    "gn:feature_class":"P",
    "gn:feature_code":"PPL",
    "gn:name":"Wiel\u0105tki",
    "gn:population":0,
    "gn:timezone":"Europe/Warsaw",
    "iso:country":"PL",
    "name:fra_x_preferred":[
        "Wiel\u0105tki"
    ],
    "name:pol_x_preferred":[
        "Wiel\u0105tki"
    ],
    "name:ukr_x_preferred":[
        "\u0412\u0435\u043b\u044c\u043e\u043d\u0442\u043a\u0456"
    ],
    "wof:name":"Wielatki",
    "wof:placetype":"locality"
},
  "geometry": {"coordinates":[21.32205,52.65008],"type":"Point"}
}