{
  "type": "Feature",
  "properties": {
    "gn:admin1_code":"87.0",
    "gn:admin2_code":"3215.0",
    "gn:admin3_code":"321504.0",
    "gn:asciiname":"Kielpino",
    "gn:country_code":"PL",
    "gn:dem":158,
    "gn:feature_class":"P",
    "gn:feature_code":"PPL",
    "gn:name":"Kie\u0142pino",
    "gn:population":0,
    "gn:timezone":"Europe/Warsaw",
    "iso:country":"PL",
    "name:und_x_variant":[
        "Kie\u0142pino"
    ],
    "wof:name":"Kielpino",
    "wof:placetype":"locality"
},
  "geometry": {"coordinates":[16.41866,53.68438],"type":"Point"}
}