{
  "type": "Feature",
  "properties": {
    "gn:admin1_code":"80.0",
    "gn:admin2_code":"1820.0",
    "gn:admin3_code":"182003.0",
    "gn:asciiname":"Nowiny",
    "gn:country_code":"PL",
    "gn:dem":145,
    "gn:feature_class":"P",
    "gn:feature_code":"PPL",
    "gn:name":"Nowiny",
    "gn:population":0,
    "gn:timezone":"Europe/Warsaw",
    "iso:country":"PL",
    "name:deu_x_preferred":[
        "Nowiny"
    ],
    "name:fra_x_preferred":[
        "Nowiny"
    ],
    "name:lit_x_preferred":[
        "Novinai"
    ],
    "name:nld_x_preferred":[
        "Nowiny"
    ],
    "name:pol_x_preferred":[
        "Nowiny"
    ],
    "name:ukr_x_preferred":[
        "\u041d\u043e\u0432\u0456\u043d\u0438"
    ],
    "name:und_x_variant":[
        "\u017bupawa Nowiny"
    ],
    "wof:name":"Nowiny",
    "wof:placetype":"locality"
},
  "geometry": {"coordinates":[21.84521,50.58965],"type":"Point"}
}