{
  "type": "Feature",
  "properties": {
    "gn:admin1_code":"80.0",
    "gn:admin2_code":"1820.0",
    "gn:admin3_code":"182003.0",
    "gn:asciiname":"Nowiny",
    "gn:country_code":"PL",
    "gn:dem":145,
    "gn:feature_class":"P",
    "gn:feature_code":"PPL",
    "gn:name":"Nowiny",
    "gn:population":0,
    "gn:timezone":"Europe/Warsaw",
    "iso:country":"PL",
    "name:und_x_variant":[
        "\u017bupawa Nowiny",
        "Nowiny"
    ],
    "wof:name":"Nowiny",
    "wof:placetype":"locality"
},
  "geometry": {"coordinates":[21.84521,50.58965],"type":"Point"}
}