{
  "type": "Feature",
  "properties": {
    "gn:admin1_code":"84.0",
    "gn:admin2_code":"2604.0",
    "gn:admin3_code":"260405.0",
    "gn:asciiname":"Sierakow",
    "gn:country_code":"PL",
    "gn:dem":303,
    "gn:feature_class":"P",
    "gn:feature_code":"PPL",
    "gn:name":"Sierak\u00f3w",
    "gn:population":0,
    "gn:timezone":"Europe/Warsaw",
    "iso:country":"PL",
    "name:ceb_x_preferred":[
        "Sierak\u00f3w"
    ],
    "name:pol_x_preferred":[
        "Sierak\u00f3w"
    ],
    "name:ukr_x_preferred":[
        "\u0421\u0435\u0440\u0430\u043a\u0443\u0432"
    ],
    "wof:name":"Sierakow",
    "wof:placetype":"locality"
},
  "geometry": {"coordinates":[20.89016,50.80626],"type":"Point"}
}