{
  "type": "Feature",
  "properties": {
    "gn:admin1_code":"84.0",
    "gn:admin2_code":"2613.0",
    "gn:admin3_code":"261304.0",
    "gn:asciiname":"Bieganow",
    "gn:country_code":"PL",
    "gn:dem":254,
    "gn:feature_class":"P",
    "gn:feature_code":"PPL",
    "gn:name":"Biegan\u00f3w",
    "gn:population":0,
    "gn:timezone":"Europe/Warsaw",
    "iso:country":"PL",
    "name:pol_x_preferred":[
        "Biegan\u00f3w"
    ],
    "name:ukr_x_preferred":[
        "\u0411\u0435\u0491\u0430\u043d\u0443\u0432"
    ],
    "wof:name":"Bieganow",
    "wof:placetype":"locality"
},
  "geometry": {"coordinates":[19.90409,50.71103],"type":"Point"}
}