{
  "type": "Feature",
  "properties": {
    "iso:country":"PL",
    "name:eng_x_preferred":[
        "Krzyzowniki"
    ],
    "name:pol_x_preferred":[
        "Krzy\u017cowniki"
    ],
    "wof:name":"Krzyzowniki",
    "wof:placetype":"neighbourhood"
},
  "geometry": {"coordinates":[18.6014984679112,54.34672042144085],"type":"Point"}
}