{
  "type": "Feature",
  "properties": {
    "gn:admin1_code":"73.0",
    "gn:admin2_code":"461.0",
    "gn:admin3_code":"46101.0",
    "gn:asciiname":"Brdyujscie",
    "gn:country_code":"PL",
    "gn:dem":43,
    "gn:feature_class":"P",
    "gn:feature_code":"PPL",
    "gn:name":"Brdyuj\u015bcie",
    "gn:population":0,
    "gn:timezone":"Europe/Warsaw",
    "iso:country":"PL",
    "wof:name":"Brdyujscie",
    "wof:placetype":"neighbourhood"
},
  "geometry": {"coordinates":[18.12659,53.13672],"type":"Point"}
}