{
  "type": "Feature",
  "properties": {
    "gn:admin1_code":"85.0",
    "gn:admin2_code":"2801.0",
    "gn:admin3_code":"280105.0",
    "gn:asciiname":"Glady",
    "gn:country_code":"PL",
    "gn:dem":118,
    "gn:feature_class":"P",
    "gn:feature_code":"PPL",
    "gn:name":"Gl\u0105dy",
    "gn:population":0,
    "gn:timezone":"Europe/Warsaw",
    "iso:country":"PL",
    "name:fra_x_preferred":[
        "Glady"
    ],
    "name:und_x_variant":[
        "Glandau",
        "Gl\u0105dy"
    ],
    "wof:name":"Glady",
    "wof:placetype":"locality"
},
  "geometry": {"coordinates":[20.42353,54.23514],"type":"Point"}
}