{
  "type": "Feature",
  "properties": {
    "gn:admin1_code":"74.0",
    "gn:admin2_code":"1016.0",
    "gn:admin3_code":"101606.0",
    "gn:asciiname":"Tarnowska Wola",
    "gn:country_code":"PL",
    "gn:dem":190,
    "gn:feature_class":"P",
    "gn:feature_code":"PPL",
    "gn:name":"Tarnowska Wola",
    "gn:population":0,
    "gn:timezone":"Europe/Warsaw",
    "iso:country":"PL",
    "name:pol_x_preferred":[
        "Tarnowska Wola"
    ],
    "name:ukr_x_preferred":[
        "\u0422\u0430\u0440\u043d\u043e\u0432\u0441\u044c\u043a\u0430-\u0412\u043e\u043b\u044f"
    ],
    "name:und_x_variant":[
        "Wola Tarnowska"
    ],
    "wof:name":"Tarnowska Wola",
    "wof:placetype":"locality"
},
  "geometry": {"coordinates":[20.01526,51.65129],"type":"Point"}
}