{
  "type": "Feature",
  "properties": {
    "gn:admin1_code":"79.0",
    "gn:admin2_code":"1608.0",
    "gn:admin3_code":"160801.0",
    "gn:asciiname":"Szemrowice",
    "gn:country_code":"PL",
    "gn:dem":232,
    "gn:feature_class":"P",
    "gn:feature_code":"PPL",
    "gn:name":"Szemrowice",
    "gn:population":0,
    "gn:timezone":"Europe/Warsaw",
    "iso:country":"PL",
    "name:azb_x_preferred":[
        "\u0634\u0645\u0631\u0648\u0648\u06cc\u062a\u0633\u0647"
    ],
    "name:deu_x_preferred":[
        "Schemrowitz"
    ],
    "name:fas_x_preferred":[
        "\u0634\u0645\u0631\u0648\u0648\u06cc\u062a\u0633\u0647"
    ],
    "name:pol_x_preferred":[
        "Szemrowice"
    ],
    "name:ukr_x_preferred":[
        "\u0428\u0435\u043c\u0440\u043e\u0432\u0456\u0446\u0435"
    ],
    "wof:name":"Szemrowice",
    "wof:placetype":"locality"
},
  "geometry": {"coordinates":[18.38759,50.7534],"type":"Point"}
}