{
  "type": "Feature",
  "properties": {
    "gn:admin1_code":"86.0",
    "gn:admin2_code":"3024.0",
    "gn:admin3_code":"302406.0",
    "gn:asciiname":"Chelmno",
    "gn:country_code":"PL",
    "gn:dem":98,
    "gn:feature_class":"P",
    "gn:feature_code":"PPL",
    "gn:name":"Che\u0142mno",
    "gn:population":0,
    "gn:timezone":"Europe/Warsaw",
    "iso:country":"PL",
    "name:ceb_x_preferred":[
        "Che\u0142mno"
    ],
    "name:fra_x_preferred":[
        "Che\u0142mno"
    ],
    "name:pol_x_preferred":[
        "Che\u0142mno"
    ],
    "name:ukr_x_preferred":[
        "\u0425\u0435\u043b\u043c\u043d\u043e"
    ],
    "wof:name":"Chelmno",
    "wof:placetype":"locality"
},
  "geometry": {"coordinates":[16.32048,52.49726],"type":"Point"}
}