{
  "type": "Feature",
  "properties": {
    "gn:admin1_code":"78.0",
    "gn:admin2_code":"1413.0",
    "gn:admin3_code":"141304.0",
    "gn:asciiname":"Wroblewo Tartak",
    "gn:country_code":"PL",
    "gn:dem":121,
    "gn:feature_class":"P",
    "gn:feature_code":"PPL",
    "gn:name":"Wr\u00f3blewo Tartak",
    "gn:population":0,
    "gn:timezone":"Europe/Warsaw",
    "iso:country":"PL",
    "wof:name":"Wroblewo Tartak",
    "wof:placetype":"locality"
},
  "geometry": {"coordinates":[20.15488,52.97003],"type":"Point"}
}