{
  "type": "Feature",
  "properties": {
    "gn:admin1_code":"75.0",
    "gn:admin2_code":"601.0",
    "gn:admin3_code":"60110.0",
    "gn:asciiname":"Krzewica",
    "gn:country_code":"PL",
    "gn:dem":160,
    "gn:feature_class":"P",
    "gn:feature_code":"PPL",
    "gn:name":"Krzewica",
    "gn:population":0,
    "gn:timezone":"Europe/Warsaw",
    "iso:country":"PL",
    "wof:name":"Krzewica",
    "wof:placetype":"locality"
},
  "geometry": {"coordinates":[22.67314,52.05496],"type":"Point"}
}