{
  "type": "Feature",
  "properties": {
    "gn:admin1_code":"74.0",
    "gn:admin2_code":"1012.0",
    "gn:admin3_code":"101214.0",
    "gn:asciiname":"Grodzisko",
    "gn:country_code":"PL",
    "gn:dem":218,
    "gn:feature_class":"P",
    "gn:feature_code":"PPL",
    "gn:name":"Grodzisko",
    "gn:population":0,
    "gn:timezone":"Europe/Warsaw",
    "iso:country":"PL",
    "name:pol_x_preferred":[
        "Grodzisko"
    ],
    "name:ukr_x_preferred":[
        "\u0490\u0440\u043e\u0434\u0437\u0438\u0441\u044c\u043a\u043e"
    ],
    "wof:name":"Grodzisko",
    "wof:placetype":"locality"
},
  "geometry": {"coordinates":[19.71806,50.85462],"type":"Point"}
}