{
  "type": "Feature",
  "properties": {
    "gn:admin1_code":"87.0",
    "gn:admin2_code":"3211.0",
    "gn:admin3_code":"321104.0",
    "gn:asciiname":"Wegornik",
    "gn:country_code":"PL",
    "gn:dem":14,
    "gn:feature_class":"P",
    "gn:feature_code":"PPL",
    "gn:name":"W\u0119gornik",
    "gn:population":0,
    "gn:timezone":"Europe/Warsaw",
    "iso:country":"PL",
    "name:azb_x_preferred":[
        "\u0648\u0646\u0642\u0648\u0631\u0646\u0642\u06a9"
    ],
    "name:dan_x_preferred":[
        "W\u0119gornik"
    ],
    "name:deu_x_preferred":[
        "W\u0119gornik"
    ],
    "name:fas_x_preferred":[
        "\u0648\u0646\u06af\u0648\u0631\u0646\u06af\u06a9"
    ],
    "name:fra_x_preferred":[
        "W\u0119gornik"
    ],
    "name:pol_x_preferred":[
        "W\u0119gornik"
    ],
    "name:vie_x_preferred":[
        "W\u0119gornik"
    ],
    "wof:name":"Wegornik",
    "wof:placetype":"locality"
},
  "geometry": {"coordinates":[14.39724,53.5554],"type":"Point"}
}