{
  "type": "Feature",
  "properties": {
    "gn:admin1_code":"87.0",
    "gn:admin2_code":"3211.0",
    "gn:admin3_code":"321104.0",
    "gn:asciiname":"Wegornik",
    "gn:country_code":"PL",
    "gn:dem":14,
    "gn:feature_class":"P",
    "gn:feature_code":"PPL",
    "gn:name":"W\u0119gornik",
    "gn:population":0,
    "gn:timezone":"Europe/Warsaw",
    "iso:country":"PL",
    "wof:name":"Wegornik",
    "wof:placetype":"locality"
},
  "geometry": {"coordinates":[14.39724,53.5554],"type":"Point"}
}