{
  "type": "Feature",
  "properties": {
    "gn:admin1_code":"81.0",
    "gn:admin2_code":"2004.0",
    "gn:admin3_code":"200402.0",
    "gn:asciiname":"Przechody",
    "gn:country_code":"PL",
    "gn:dem":114,
    "gn:feature_class":"P",
    "gn:feature_code":"PPL",
    "gn:name":"Przechody",
    "gn:population":0,
    "gn:timezone":"Europe/Warsaw",
    "iso:country":"PL",
    "wof:name":"Przechody",
    "wof:placetype":"locality"
},
  "geometry": {"coordinates":[22.60543,53.55472],"type":"Point"}
}