{
  "type": "Feature",
  "properties": {
    "gn:admin1_code":"76.0",
    "gn:admin2_code":"811.0",
    "gn:admin3_code":"81106.0",
    "gn:asciiname":"Lutol",
    "gn:country_code":"PL",
    "gn:dem":70,
    "gn:feature_class":"P",
    "gn:feature_code":"PPL",
    "gn:name":"Lutol",
    "gn:population":0,
    "gn:timezone":"Europe/Warsaw",
    "iso:country":"PL",
    "name:ceb_x_preferred":[
        "Lutol"
    ],
    "name:fas_x_preferred":[
        "\u0644\u0648\u062a\u0648\u0644"
    ],
    "name:fra_x_preferred":[
        "Lutol"
    ],
    "name:nld_x_preferred":[
        "Lutol"
    ],
    "name:pol_x_preferred":[
        "Lutol"
    ],
    "name:ukr_x_preferred":[
        "\u041b\u044e\u0442\u043e\u043b\u044c"
    ],
    "wof:name":"Lutol",
    "wof:placetype":"locality"
},
  "geometry": {"coordinates":[15.00938,51.81392],"type":"Point"}
}