{
  "type": "Feature",
  "properties": {
    "gn:admin1_code":"78",
    "gn:admin2_code":"1421",
    "gn:admin3_code":"142105.0",
    "gn:asciiname":"Kajetany",
    "gn:country_code":"PL",
    "gn:dem":110,
    "gn:feature_class":"P",
    "gn:feature_code":"PPL",
    "gn:name":"Kajetany",
    "gn:population":0,
    "gn:timezone":"Europe/Warsaw",
    "iso:country":"PL",
    "name:azb_x_preferred":[
        "\u06a9\u0627\u06cc\u062a\u0627\u0646\u0647"
    ],
    "name:ces_x_preferred":[
        "Kajetany"
    ],
    "name:fas_x_preferred":[
        "\u06a9\u0627\u06cc\u062a\u0627\u0646\u0647"
    ],
    "name:fra_x_preferred":[
        "Kajetany"
    ],
    "name:pol_x_preferred":[
        "Kajetany"
    ],
    "name:ukr_x_preferred":[
        "\u041a\u0430\u0454\u0442\u0430\u043d\u0438"
    ],
    "wof:name":"Kajetany",
    "wof:placetype":"neighbourhood"
},
  "geometry": {"coordinates":[20.8141,52.0927],"type":"Point"}
}