{
  "type": "Feature",
  "properties": {
    "gn:admin1_code":"72.0",
    "gn:admin2_code":"220.0",
    "gn:admin3_code":"22006.0",
    "gn:asciiname":"Niezgoda",
    "gn:country_code":"PL",
    "gn:dem":94,
    "gn:feature_class":"P",
    "gn:feature_code":"PPL",
    "gn:name":"Niezgoda",
    "gn:population":0,
    "gn:timezone":"Europe/Warsaw",
    "iso:country":"PL",
    "name:deu_x_preferred":[
        "Niezgoda"
    ],
    "name:pol_x_preferred":[
        "Niezgoda"
    ],
    "name:ukr_x_preferred":[
        "\u041d\u0435\u0437\u0491\u043e\u0434\u0430"
    ],
    "wof:name":"Niezgoda",
    "wof:placetype":"locality"
},
  "geometry": {"coordinates":[17.04715,51.51512],"type":"Point"}
}