{
  "type": "Feature",
  "properties": {
    "gn:admin1_code":"75.0",
    "gn:admin2_code":"610.0",
    "gn:admin3_code":"61002.0",
    "gn:asciiname":"Zezulin",
    "gn:country_code":"PL",
    "gn:dem":170,
    "gn:feature_class":"P",
    "gn:feature_code":"PPL",
    "gn:name":"Zezulin",
    "gn:population":0,
    "gn:timezone":"Europe/Warsaw",
    "iso:country":"PL",
    "wof:name":"Zezulin",
    "wof:placetype":"locality"
},
  "geometry": {"coordinates":[22.84945,51.356],"type":"Point"}
}