{
  "type": "Feature",
  "properties": {
    "gn:population":1477,
    "iso:country":"PL",
    "name:ast_x_preferred":[
        "S\u0119kowa"
    ],
    "name:azb_x_preferred":[
        "\u0633\u06a9\u0648\u0622"
    ],
    "name:bar_x_preferred":[
        "S\u0119kowa"
    ],
    "name:ceb_x_preferred":[
        "S\u0119kowa"
    ],
    "name:deu_x_preferred":[
        "S\u0119kowa"
    ],
    "name:eng_x_preferred":[
        "S\u0119kowa"
    ],
    "name:fas_x_preferred":[
        "\u0633\u06a9\u0648\u0622"
    ],
    "name:fra_x_preferred":[
        "S\u0119kowa"
    ],
    "name:heb_x_preferred":[
        "\u05e1\u05e0\u05e7\u05d5\u05d1\u05d4"
    ],
    "name:jpn_x_preferred":[
        "\u30bb\u30f3\u30b3\u30f4\u30a1"
    ],
    "name:nld_x_preferred":[
        "S\u0119kowa"
    ],
    "name:pol_x_preferred":[
        "S\u0119kowa"
    ],
    "name:rue_x_preferred":[
        "\u0421\u0435\u043d\u044c\u043a\u043e\u0432\u0430"
    ],
    "name:rus_x_preferred":[
        "\u0421\u0435\u043d\u043a\u043e\u0432\u0430"
    ],
    "name:swe_x_preferred":[
        "S\u0119kowa"
    ],
    "name:ukr_x_preferred":[
        "\u0421\u0435\u043d\u043a\u043e\u0432\u0430"
    ],
    "name:vie_x_preferred":[
        "S\u0119kowa"
    ],
    "qs:a0":"Rzeczpospolita Polska",
    "qs:a1":"*Malopolskie",
    "qs:a1r":"0",
    "qs:a2":"Gorlicki",
    "qs:adm0":"Rzeczpospolita Polska",
    "qs:la":"S\u0119kowa",
    "qs:la_lc":"*PL1205092",
    "qs:level":"locality",
    "qs:loc":"S\u0119kowa",
    "qs:loc_alt":"Sekowa",
    "qs:pop":0,
    "qs:type":"rural point-in-poly",
    "wd:wordcount":144,
    "wof:name":"S\u0119kowa",
    "wof:placetype":"locality",
    "wof:population":1477
},
  "geometry": {"coordinates":[21.2790825452603,49.5841682044229],"type":"Point"}
}