{
  "type": "Feature",
  "properties": {
    "gn:admin1_code":"77.0",
    "gn:admin2_code":"1207.0",
    "gn:admin3_code":"120712.0",
    "gn:asciiname":"Zawadka",
    "gn:country_code":"PL",
    "gn:dem":451,
    "gn:feature_class":"P",
    "gn:feature_code":"PPL",
    "gn:name":"Zawadka",
    "gn:population":0,
    "gn:timezone":"Europe/Warsaw",
    "iso:country":"PL",
    "name:pol_x_preferred":[
        "Zawadka"
    ],
    "name:ukr_x_preferred":[
        "\u0417\u0430\u0432\u0430\u0434\u043a\u0430"
    ],
    "wof:name":"Zawadka",
    "wof:placetype":"locality"
},
  "geometry": {"coordinates":[20.28179,49.74301],"type":"Point"}
}