{
  "type": "Feature",
  "properties": {
    "gn:admin1_code":"78.0",
    "gn:admin2_code":"1407.0",
    "gn:admin3_code":"140707.0",
    "gn:asciiname":"Kepice",
    "gn:country_code":"PL",
    "gn:dem":109,
    "gn:feature_class":"P",
    "gn:feature_code":"PPL",
    "gn:name":"K\u0119pice",
    "gn:population":0,
    "gn:timezone":"Europe/Warsaw",
    "iso:country":"PL",
    "name:ceb_x_preferred":[
        "K\u0119pice"
    ],
    "name:fra_x_preferred":[
        "K\u0119pice"
    ],
    "name:pol_x_preferred":[
        "K\u0119pice"
    ],
    "name:ukr_x_preferred":[
        "\u041a\u0435\u043c\u043f\u0456\u0446\u0435"
    ],
    "wof:name":"Kepice",
    "wof:placetype":"locality"
},
  "geometry": {"coordinates":[21.76023,51.54799000000001],"type":"Point"}
}