{
  "type": "Feature",
  "properties": {
    "iso:country":"PL",
    "name:azb_x_preferred":[
        "\u0632\u0628\u0644\u0648\u0648"
    ],
    "name:ceb_x_preferred":[
        "Zblewo"
    ],
    "name:deu_x_preferred":[
        "Zblewo"
    ],
    "name:fas_x_preferred":[
        "\u0632\u0628\u0644\u0648\u0648"
    ],
    "name:fra_x_preferred":[
        "Zblewo"
    ],
    "name:glv_x_preferred":[
        "Zblewo"
    ],
    "name:nld_x_preferred":[
        "Zblewo"
    ],
    "name:pol_x_preferred":[
        "Zblewo"
    ],
    "name:ukr_x_preferred":[
        "\u0417\u0431\u043b\u0435\u0432\u043e"
    ],
    "qs_pg:aaroncc":"PL",
    "qs_pg:name":"Zblewo",
    "qs_pg:name_adm0":"Polska",
    "qs_pg:name_adm1":"Pomorskie",
    "qs_pg:photos":38,
    "qs_pg:photos_1k":8,
    "qs_pg:photos_9k":1,
    "qs_pg:photos_9r":2,
    "qs_pg:photos_all":71,
    "qs_pg:photos_sr":2,
    "qs_pg:pop_sr":0,
    "qs_pg:qs_pg_placetype":"localadmin",
    "qs_pg:qs_pg_placetype_gp":"LocalAdmin",
    "qs_pg:woe_adm0":23424923,
    "woe:adm0_id":23424923,
    "woe:name_adm0":"Polska",
    "woe:name_adm1":"Pomorskie",
    "woe:placetype":"LocalAdmin",
    "wof:name":"Zblewo",
    "wof:placetype":"localadmin"
},
  "geometry": {"coordinates":[18.399653,53.898794],"type":"Point"}
}