{
  "type": "Feature",
  "properties": {
    "gn:admin1_code":"82.0",
    "gn:admin2_code":"2214.0",
    "gn:admin3_code":"221402.0",
    "gn:asciiname":"Wlosienica",
    "gn:country_code":"PL",
    "gn:dem":85,
    "gn:feature_class":"P",
    "gn:feature_code":"PPL",
    "gn:name":"W\u0142osienica",
    "gn:population":0,
    "gn:timezone":"Europe/Warsaw",
    "iso:country":"PL",
    "name:ceb_x_preferred":[
        "W\u0142osienica"
    ],
    "name:pol_x_preferred":[
        "W\u0142osienica"
    ],
    "name:ukr_x_preferred":[
        "\u0412\u043b\u043e\u0441\u0435\u043d\u0438\u0446\u044f"
    ],
    "wof:name":"Wlosienica",
    "wof:placetype":"locality"
},
  "geometry": {"coordinates":[18.70869,53.69996],"type":"Point"}
}