{
  "type": "Feature",
  "properties": {
    "gn:admin1_code":"81.0",
    "gn:admin2_code":"2006.0",
    "gn:admin3_code":"200606.0",
    "gn:asciiname":"Jurki",
    "gn:country_code":"PL",
    "gn:dem":108,
    "gn:feature_class":"P",
    "gn:feature_code":"PPL",
    "gn:name":"Jurki",
    "gn:population":0,
    "gn:timezone":"Europe/Warsaw",
    "iso:country":"PL",
    "name:deu_x_preferred":[
        "Jurki"
    ],
    "name:fra_x_preferred":[
        "Jurki"
    ],
    "name:pol_x_preferred":[
        "Jurki"
    ],
    "name:rus_x_preferred":[
        "\u042e\u0440\u043a\u0438"
    ],
    "name:ukr_x_preferred":[
        "\u042e\u0440\u043a\u0456"
    ],
    "wof:name":"Jurki",
    "wof:placetype":"locality"
},
  "geometry": {"coordinates":[21.78333,53.41667],"type":"Point"}
}