{
  "type": "Feature",
  "properties": {
    "gn:admin1_code":"75.0",
    "gn:admin2_code":"609.0",
    "gn:admin3_code":"60913.0",
    "gn:asciiname":"Stary Gaj",
    "gn:country_code":"PL",
    "gn:dem":196,
    "gn:feature_class":"P",
    "gn:feature_code":"PPL",
    "gn:name":"Stary Gaj",
    "gn:population":0,
    "gn:timezone":"Europe/Warsaw",
    "iso:country":"PL",
    "name:fra_x_preferred":[
        "Stary Gaj"
    ],
    "name:pol_x_preferred":[
        "Stary Gaj"
    ],
    "name:ukr_x_preferred":[
        "\u0421\u0442\u0430\u0440\u0438\u0439 \u0490\u0430\u0439"
    ],
    "name:und_x_variant":[
        "Gaj Stary"
    ],
    "wof:name":"Stary Gaj",
    "wof:placetype":"locality"
},
  "geometry": {"coordinates":[22.19259,51.25552],"type":"Point"}
}