{
  "type": "Feature",
  "properties": {
    "gn:admin1_code":"83.0",
    "gn:admin2_code":"2411.0",
    "gn:admin3_code":"241104.0",
    "gn:asciiname":"Lapacz",
    "gn:country_code":"PL",
    "gn:dem":190,
    "gn:feature_class":"P",
    "gn:feature_code":"PPL",
    "gn:name":"\u0141apacz",
    "gn:population":0,
    "gn:timezone":"Europe/Warsaw",
    "iso:country":"PL",
    "wof:name":"Lapacz",
    "wof:placetype":"locality"
},
  "geometry": {"coordinates":[18.28333,49.98333],"type":"Point"}
}