{
  "type": "Feature",
  "properties": {
    "gn:admin1_code":"77.0",
    "gn:admin2_code":"1219.0",
    "gn:admin3_code":"121905.0",
    "gn:asciiname":"Roznowa",
    "gn:country_code":"PL",
    "gn:dem":374,
    "gn:feature_class":"P",
    "gn:feature_code":"PPL",
    "gn:name":"Ro\u017cnowa",
    "gn:population":0,
    "gn:timezone":"Europe/Warsaw",
    "iso:country":"PL",
    "name:pol_x_preferred":[
        "Ro\u017cnowa"
    ],
    "name:ukr_x_preferred":[
        "\u0420\u043e\u0436\u043d\u043e\u0432\u0430"
    ],
    "wof:name":"Roznowa",
    "wof:placetype":"locality"
},
  "geometry": {"coordinates":[20.0631,49.96933],"type":"Point"}
}