{
  "type": "Feature",
  "properties": {
    "gn:admin1_code":"87.0",
    "gn:admin2_code":"3216.0",
    "gn:admin3_code":"321605.0",
    "gn:asciiname":"Kalina",
    "gn:country_code":"PL",
    "gn:dem":53,
    "gn:feature_class":"P",
    "gn:feature_code":"PPL",
    "gn:name":"Kalina",
    "gn:population":0,
    "gn:timezone":"Europe/Warsaw",
    "iso:country":"PL",
    "name:deu_x_preferred":[
        "Kalina"
    ],
    "name:pol_x_preferred":[
        "Kalina"
    ],
    "name:ukr_x_preferred":[
        "\u041a\u0430\u043b\u0456\u043d\u0430"
    ],
    "name:vie_x_preferred":[
        "Kalina"
    ],
    "wof:name":"Kalina",
    "wof:placetype":"locality"
},
  "geometry": {"coordinates":[15.63807,53.93049],"type":"Point"}
}