{
  "type": "Feature",
  "properties": {
    "gn:admin1_code":"86.0",
    "gn:admin2_code":"3007.0",
    "gn:admin3_code":"300711.0",
    "gn:asciiname":"Borkow Koronka",
    "gn:country_code":"PL",
    "gn:dem":133,
    "gn:feature_class":"P",
    "gn:feature_code":"PPL",
    "gn:name":"Bork\u00f3w Koronka",
    "gn:population":0,
    "gn:timezone":"Europe/Warsaw",
    "iso:country":"PL",
    "wof:name":"Borkow Koronka",
    "wof:placetype":"locality"
},
  "geometry": {"coordinates":[18.13333,51.81667],"type":"Point"}
}