{
  "type": "Feature",
  "properties": {
    "iso:country":"PL",
    "name:azb_x_preferred":[
        "\u0648\u0646\u06a9\u06cc \u0634\u0644\u0627\u062e\u062a\u0633\u06a9\u06cc\u0647"
    ],
    "name:ceb_x_preferred":[
        "\u0141\u0119ki Szlacheckie"
    ],
    "name:deu_x_preferred":[
        "\u0141\u0119ki Szlacheckie"
    ],
    "name:fas_x_preferred":[
        "\u0648\u0646\u06a9\u06cc \u0634\u0644\u0627\u062e\u062a\u0633\u06a9\u06cc\u0647"
    ],
    "name:fra_x_preferred":[
        "\u0141\u0119ki Szlacheckie"
    ],
    "name:nld_x_preferred":[
        "\u0141\u0119ki Szlacheckie"
    ],
    "name:pol_x_preferred":[
        "\u0141\u0119ki Szlacheckie"
    ],
    "name:ukr_x_preferred":[
        "\u041b\u0435\u043d\u043a\u0456-\u0428\u043b\u044f\u0445\u0435\u0446\u044c\u043a\u0456"
    ],
    "wof:coterminous":[
        1125324121
    ],
    "wof:name":"\u0141\u0119ki Szlacheckie",
    "wof:placetype":"locality"
},
  "geometry": {"coordinates":[19.7709420992617,51.1995346438041],"type":"Point"}
}