{
  "type": "Feature",
  "properties": {
    "iso:country":"PL",
    "name:pol_x_preferred":[
        "\u0141\u0119ki Szlacheckie"
    ],
    "wof:coterminous":[
        1125324121
    ],
    "wof:name":"\u0141\u0119ki Szlacheckie",
    "wof:placetype":"locality"
},
  "geometry": {"coordinates":[19.7709420992617,51.1995346438041],"type":"Point"}
}