{
  "type": "Feature",
  "properties": {
    "gn:admin1_code":"86.0",
    "gn:admin2_code":"3003.0",
    "gn:admin3_code":"300303.0",
    "gn:asciiname":"Mnichowo",
    "gn:country_code":"PL",
    "gn:dem":115,
    "gn:feature_class":"P",
    "gn:feature_code":"PPL",
    "gn:name":"Mnichowo",
    "gn:population":0,
    "gn:timezone":"Europe/Warsaw",
    "iso:country":"PL",
    "name:azb_x_preferred":[
        "\u0645\u0646\u0642\u062e\u0648\u0648\u0648"
    ],
    "name:ceb_x_preferred":[
        "Mnichowo"
    ],
    "name:fas_x_preferred":[
        "\u0645\u0646\u06af\u062e\u0648\u0648\u0648"
    ],
    "name:fra_x_preferred":[
        "Mnichowo"
    ],
    "name:pol_x_preferred":[
        "Mnichowo"
    ],
    "name:ukr_x_preferred":[
        "\u041c\u043d\u0456\u0445\u043e\u0432\u043e"
    ],
    "wof:name":"Mnichowo",
    "wof:placetype":"locality"
},
  "geometry": {"coordinates":[17.53908,52.50376],"type":"Point"}
}