{
  "type": "Feature",
  "properties": {
    "gn:admin1_code":"79.0",
    "gn:admin2_code":"1610.0",
    "gn:admin3_code":"161002.0",
    "gn:asciiname":"Mionow",
    "gn:country_code":"PL",
    "gn:dem":202,
    "gn:feature_class":"P",
    "gn:feature_code":"PPL",
    "gn:name":"Mion\u00f3w",
    "gn:population":0,
    "gn:timezone":"Europe/Warsaw",
    "iso:country":"PL",
    "name:azb_x_preferred":[
        "\u0645\u06cc\u0648\u0646\u0648\u0648"
    ],
    "name:deu_x_preferred":[
        "Polnisch M\u00fcllmen"
    ],
    "name:fas_x_preferred":[
        "\u0645\u06cc\u0648\u0646\u0648\u0648"
    ],
    "name:pol_x_preferred":[
        "Mion\u00f3w"
    ],
    "name:ukr_x_preferred":[
        "\u041c\u0439\u043e\u043d\u0443\u0432"
    ],
    "wof:name":"Mionow",
    "wof:placetype":"locality"
},
  "geometry": {"coordinates":[17.79012999999999,50.38072],"type":"Point"}
}