{
  "type": "Feature",
  "properties": {
    "gn:admin1_code":"86.0",
    "gn:admin2_code":"3011.0",
    "gn:admin3_code":"301102.0",
    "gn:asciiname":"Srocko Wielkie",
    "gn:country_code":"PL",
    "gn:dem":82,
    "gn:feature_class":"P",
    "gn:feature_code":"PPL",
    "gn:name":"Srocko Wielkie",
    "gn:population":0,
    "gn:timezone":"Europe/Warsaw",
    "iso:country":"PL",
    "name:fra_x_preferred":[
        "Srocko Wielkie"
    ],
    "name:pol_x_preferred":[
        "Srocko Wielkie"
    ],
    "name:ukr_x_preferred":[
        "\u0421\u0440\u043e\u0446\u044c\u043a\u043e-\u0412\u0435\u043b\u0438\u043a\u0435"
    ],
    "wof:name":"Srocko Wielkie",
    "wof:placetype":"locality"
},
  "geometry": {"coordinates":[16.75015,52.17345],"type":"Point"}
}