{
  "type": "Feature",
  "properties": {
    "gn:admin1_code":"81.0",
    "gn:admin2_code":"2012.0",
    "gn:admin3_code":"201205.0",
    "gn:asciiname":"Szczodruchy",
    "gn:cc2":"PL",
    "gn:country_code":"PL",
    "gn:dem":162,
    "gn:feature_class":"P",
    "gn:feature_code":"PPL",
    "gn:name":"Szczodruchy",
    "gn:population":0,
    "gn:timezone":"Europe/Warsaw",
    "iso:country":"PL",
    "name:lit_x_preferred":[
        "\u0160\u010dodruchai"
    ],
    "name:pol_x_preferred":[
        "Szczodruchy"
    ],
    "name:ukr_x_preferred":[
        "\u0429\u043e\u0434\u0440\u0443\u0445\u0438"
    ],
    "name:und_x_variant":[
        "Kolonia Szczodruchy"
    ],
    "wof:name":"Szczodruchy",
    "wof:placetype":"locality"
},
  "geometry": {"coordinates":[22.69449,54.0236],"type":"Point"}
}