{
  "type": "Feature",
  "properties": {
    "gn:admin1_code":"74.0",
    "gn:admin2_code":"1018.0",
    "gn:admin3_code":"101803.0",
    "gn:asciiname":"Kaski",
    "gn:country_code":"PL",
    "gn:dem":164,
    "gn:feature_class":"P",
    "gn:feature_code":"PPL",
    "gn:name":"Kaski",
    "gn:population":0,
    "gn:timezone":"Europe/Warsaw",
    "iso:country":"PL",
    "name:pol_x_preferred":[
        "Kaski"
    ],
    "name:ukr_x_preferred":[
        "\u041a\u0430\u0441\u043a\u0438"
    ],
    "wof:name":"Kaski",
    "wof:placetype":"locality"
},
  "geometry": {"coordinates":[18.29797,51.34058],"type":"Point"}
}