{
  "type": "Feature",
  "properties": {
    "gn:country":"PL",
    "gn:fcode":"PPL",
    "gn:population":971,
    "iso:country":"PL",
    "name:ceb_x_preferred":[
        "Jod\u0142ownik"
    ],
    "name:nld_x_preferred":[
        "Jod\u0142ownik"
    ],
    "name:pol_x_preferred":[
        "Jod\u0142ownik"
    ],
    "qs_pg:aaroncc":"PL",
    "qs_pg:gn_country":"PL",
    "qs_pg:gn_fcode":"PPL",
    "qs_pg:gn_pop":971,
    "qs_pg:name":"Jod\u0142ownik",
    "qs_pg:name_adm0":"Polska",
    "qs_pg:name_adm1":"Ma\u0142opolskie",
    "qs_pg:photos_9r":0,
    "qs_pg:photos_sr":0,
    "qs_pg:pop_sr":2,
    "qs_pg:qs_pg_placetype":"locality",
    "qs_pg:qs_pg_placetype_gp":"Town",
    "qs_pg:woe_adm0":23424923,
    "woe:adm0_id":23424923,
    "woe:name_adm0":"Polska",
    "woe:name_adm1":"Ma\u0142opolskie",
    "woe:placetype":"Town",
    "wof:name":"Jod\u0142ownik",
    "wof:placetype":"locality",
    "wof:population":971
},
  "geometry": {"coordinates":[20.23647,49.77517],"type":"Point"}
}