{
  "type": "Feature",
  "properties": {
    "gn:admin1_code":"75.0",
    "gn:admin2_code":"614.0",
    "gn:admin3_code":"61406.0",
    "gn:asciiname":"Bronislawka",
    "gn:country_code":"PL",
    "gn:dem":193,
    "gn:feature_class":"P",
    "gn:feature_code":"PPL",
    "gn:name":"Bronis\u0142awka",
    "gn:population":0,
    "gn:timezone":"Europe/Warsaw",
    "iso:country":"PL",
    "wof:name":"Bronislawka",
    "wof:placetype":"locality"
},
  "geometry": {"coordinates":[22.18604,51.4723],"type":"Point"}
}