{
  "type": "Feature",
  "properties": {
    "gn:admin1_code":"77.0",
    "gn:admin2_code":"1206.0",
    "gn:admin3_code":"120603.0",
    "gn:asciiname":"Narama",
    "gn:country_code":"PL",
    "gn:dem":352,
    "gn:feature_class":"P",
    "gn:feature_code":"PPL",
    "gn:name":"Narama",
    "gn:population":0,
    "gn:timezone":"Europe/Warsaw",
    "iso:country":"PL",
    "name:pol_x_preferred":[
        "Narama"
    ],
    "name:rus_x_preferred":[
        "\u041d\u0430\u0440\u0430\u043c\u0430"
    ],
    "name:ukr_x_preferred":[
        "\u041d\u0430\u0440\u0430\u043c\u0430"
    ],
    "wof:name":"Narama",
    "wof:placetype":"locality"
},
  "geometry": {"coordinates":[19.93221,50.18045],"type":"Point"}
}