{
  "type": "Feature",
  "properties": {
    "gn:admin1_code":"77.0",
    "gn:admin2_code":"1206.0",
    "gn:admin3_code":"120612.0",
    "gn:asciiname":"Czechy",
    "gn:country_code":"PL",
    "gn:dem":227,
    "gn:feature_class":"P",
    "gn:feature_code":"PPL",
    "gn:name":"Czechy",
    "gn:population":0,
    "gn:timezone":"Europe/Warsaw",
    "iso:country":"PL",
    "name:ceb_x_preferred":[
        "Czechy"
    ],
    "name:pol_x_preferred":[
        "Czechy"
    ],
    "name:rus_x_preferred":[
        "\u0427\u0435\u0445\u0438"
    ],
    "name:ukr_x_preferred":[
        "\u0427\u0435\u0445\u0438"
    ],
    "wof:name":"Czechy",
    "wof:placetype":"locality"
},
  "geometry": {"coordinates":[20.15322,50.22514],"type":"Point"}
}