{
  "type": "Feature",
  "properties": {
    "gn:admin1_code":"81.0",
    "gn:admin2_code":"2007.0",
    "gn:admin3_code":"200707.0",
    "gn:asciiname":"Ratowo Stare",
    "gn:country_code":"PL",
    "gn:dem":128,
    "gn:feature_class":"P",
    "gn:feature_code":"PPL",
    "gn:name":"Ratowo Stare",
    "gn:population":0,
    "gn:timezone":"Europe/Warsaw",
    "iso:country":"PL",
    "name:lit_x_preferred":[
        "Stare Ratovas"
    ],
    "name:pol_x_preferred":[
        "Stare Ratowo"
    ],
    "name:ukr_x_preferred":[
        "\u0421\u0442\u0430\u0440\u0435 \u0420\u0430\u0442\u043e\u0432\u043e"
    ],
    "wof:name":"Ratowo Stare",
    "wof:placetype":"locality"
},
  "geometry": {"coordinates":[22.00881,53.03953000000001],"type":"Point"}
}