{
  "type": "Feature",
  "properties": {
    "gn:admin1_code":"72",
    "gn:admin2_code":"0204",
    "gn:admin3_code":"20402.0",
    "gn:asciiname":"Daszow",
    "gn:country_code":"PL",
    "gn:dem":106,
    "gn:feature_class":"P",
    "gn:feature_code":"PPL",
    "gn:name":"Dasz\u00f3w",
    "gn:population":0,
    "gn:timezone":"Europe/Warsaw",
    "iso:country":"PL",
    "name:deu_x_historical":[
        "Dahsau"
    ],
    "name:deu_x_preferred":[
        "Dahsau"
    ],
    "wof:name":"Daszow",
    "wof:placetype":"locality"
},
  "geometry": {"coordinates":[16.60154,51.5569],"type":"Point"}
}