{
  "type": "Feature",
  "properties": {
    "gn:population":2242,
    "iso:country":"PL",
    "name:azb_x_preferred":[
        "\u0642\u0645\u06cc\u0646\u0627 \u0642\u0648\u062c\u0634\u0648\u0648"
    ],
    "name:bel_x_preferred":[
        "\u0413\u043c\u0456\u043d\u0430 \u0413\u0430\u0434\u0437\u0456\u0448\u0430\u045e"
    ],
    "name:deu_x_preferred":[
        "Gmina Godzisz\u00f3w"
    ],
    "name:eng_x_preferred":[
        "Gmina Godzisz\u00f3w"
    ],
    "name:eus_x_preferred":[
        "Godzisz\u00f3w udalerria"
    ],
    "name:fas_x_preferred":[
        "\u06af\u0645\u06cc\u0646\u0627 \u06af\u0648\u062c\u0634\u0648\u0648"
    ],
    "name:fra_x_preferred":[
        "Godzisz\u00f3w"
    ],
    "name:ita_x_preferred":[
        "Godzisz\u00f3w"
    ],
    "name:nan_x_preferred":[
        "Godzisz\u00f3w"
    ],
    "name:nld_x_preferred":[
        "Godzisz\u00f3w"
    ],
    "name:pol_x_preferred":[
        "Godzisz\u00f3w"
    ],
    "name:por_x_preferred":[
        "Comuna de Godzisz\u00f3w"
    ],
    "name:rus_x_preferred":[
        "\u0413\u043e\u0434\u0437\u0438\u0448\u0443\u0432"
    ],
    "name:slk_x_preferred":[
        "Gmina Godzisz\u00f3w"
    ],
    "name:ukr_x_preferred":[
        "\u0413\u043c\u0456\u043d\u0430 \u0490\u043e\u0434\u0437\u0456\u0448\u0443\u0432"
    ],
    "name:ukr_x_variant":[
        "\u0490\u043c\u0456\u043d\u0430 \u0490\u043e\u0434\u0437\u0456\u0448\u0443\u0432"
    ],
    "name:war_x_preferred":[
        "Gmina Godzisz\u00f3w"
    ],
    "qs:a0":"Rzeczpospolita Polska",
    "qs:a1":"*Lubelskie",
    "qs:a1r":"0",
    "qs:a2":"Janowski",
    "qs:adm0":"Rzeczpospolita Polska",
    "qs:la":"Godzisz\u00f3w",
    "qs:la_lc":"*PL0605042",
    "qs:level":"locality",
    "qs:loc":"Godzisz\u00f3w",
    "qs:loc_alt":"Godziszow",
    "qs:pop":0,
    "qs:type":"rural point-in-poly",
    "wd:wordcount":119,
    "wof:name":"Godzisz\u00f3w",
    "wof:placetype":"locality",
    "wof:population":2242
},
  "geometry": {"coordinates":[22.4970695711566,50.7720545231941],"type":"Point"}
}