{
  "type": "Feature",
  "properties": {
    "gn:population":2188,
    "iso:country":"PL",
    "name:ast_x_preferred":[
        "Klecza Dolna"
    ],
    "name:azb_x_preferred":[
        "\u06a9\u0644\u0686\u0627 \u062f\u0648\u0644\u0646\u0627"
    ],
    "name:ceb_x_preferred":[
        "Klecza Dolna"
    ],
    "name:deu_x_preferred":[
        "Klecza Dolna"
    ],
    "name:eng_x_preferred":[
        "Klecza Dolna"
    ],
    "name:fas_x_preferred":[
        "\u06a9\u0644\u0686\u0627 \u062f\u0648\u0644\u0646\u0627"
    ],
    "name:fra_x_preferred":[
        "Klecza Dolna"
    ],
    "name:nan_x_preferred":[
        "Klecza Dolna"
    ],
    "name:nld_x_preferred":[
        "Klecza Dolna"
    ],
    "name:pol_x_preferred":[
        "Klecza Dolna"
    ],
    "name:ukr_x_preferred":[
        "\u041a\u043b\u0435\u0447\u0430-\u0414\u043e\u043b\u044c\u043d\u0430"
    ],
    "name:zho_min_nan_x_preferred":[
        "Klecza Dolna"
    ],
    "qs:a0":"Rzeczpospolita Polska",
    "qs:a1":"*Malopolskie",
    "qs:a1r":"0",
    "qs:a2":"Wadowicki",
    "qs:adm0":"Rzeczpospolita Polska",
    "qs:la_lc":"*",
    "qs:level":"locality",
    "qs:loc":"Klecza Dolna",
    "qs:loc_alt":"Klecza Dolna",
    "qs:pop":0,
    "qs:type":"buffered point",
    "wd:wordcount":69,
    "wof:name":"Klecza Dolna",
    "wof:placetype":"locality",
    "wof:population":2188
},
  "geometry": {"coordinates":[19.536473,49.881611],"type":"Point"}
}