{
  "type": "Feature",
  "properties": {
    "gn:admin1_code":"85.0",
    "gn:admin2_code":"2807.0",
    "gn:admin3_code":"280707.0",
    "gn:asciiname":"Jerzwald",
    "gn:cc2":"PL",
    "gn:country_code":"PL",
    "gn:dem":104,
    "gn:feature_class":"P",
    "gn:feature_code":"PPL",
    "gn:name":"Jerzwa\u0142d",
    "gn:population":0,
    "gn:timezone":"Europe/Warsaw",
    "iso:country":"PL",
    "name:azb_x_preferred":[
        "\u06cc\u0698\u0648\u0627\u0648\u062f"
    ],
    "name:ceb_x_preferred":[
        "Jerzwa\u0142d"
    ],
    "name:deu_x_preferred":[
        "Jerzwa\u0142d"
    ],
    "name:fas_x_preferred":[
        "\u06cc\u0698\u0648\u0627\u0648\u062f"
    ],
    "name:nld_x_preferred":[
        "Jerzwa\u0142d"
    ],
    "name:pol_x_preferred":[
        "Jerzwa\u0142d"
    ],
    "name:ukr_x_preferred":[
        "\u0404\u0436\u0432\u0430\u043b\u0434"
    ],
    "name:und_x_variant":[
        "Gerswalde"
    ],
    "wof:name":"Jerzwald",
    "wof:placetype":"locality"
},
  "geometry": {"coordinates":[19.52751,53.78179],"type":"Point"}
}