{
  "type": "Feature",
  "properties": {
    "gn:admin1_code":"73.0",
    "gn:admin2_code":"401.0",
    "gn:admin3_code":"40106.0",
    "gn:asciiname":"Rybno",
    "gn:country_code":"PL",
    "gn:dem":87,
    "gn:feature_class":"P",
    "gn:feature_code":"PPL",
    "gn:name":"Rybno",
    "gn:population":0,
    "gn:timezone":"Europe/Warsaw",
    "iso:country":"PL",
    "name:ceb_x_preferred":[
        "Rybno"
    ],
    "name:deu_x_preferred":[
        "Rybno"
    ],
    "name:fra_x_preferred":[
        "Rybno"
    ],
    "name:ita_x_preferred":[
        "Rybno"
    ],
    "name:nld_x_preferred":[
        "Rybno"
    ],
    "name:pol_x_preferred":[
        "Rybno"
    ],
    "name:rus_x_preferred":[
        "\u0420\u044b\u0431\u043d\u043e"
    ],
    "name:ukr_x_preferred":[
        "\u0420\u0438\u0431\u043d\u043e"
    ],
    "wof:name":"Rybno",
    "wof:placetype":"locality"
},
  "geometry": {"coordinates":[18.682,52.79616],"type":"Point"}
}