{
  "type": "Feature",
  "properties": {
    "gn:admin1_code":"81.0",
    "gn:admin2_code":"2011.0",
    "gn:admin3_code":"201110.0",
    "gn:asciiname":"Harkawicze",
    "gn:country_code":"PL",
    "gn:dem":164,
    "gn:feature_class":"P",
    "gn:feature_code":"PPL",
    "gn:name":"Harkawicze",
    "gn:population":0,
    "gn:timezone":"Europe/Warsaw",
    "iso:country":"PL",
    "name:azb_x_preferred":[
        "\u062e\u0627\u0631\u06a9\u0627\u0648\u06cc\u0686\u0647"
    ],
    "name:fas_x_preferred":[
        "\u062e\u0627\u0631\u06a9\u0627\u0648\u06cc\u0686\u0647"
    ],
    "name:fra_x_preferred":[
        "Harkawicze"
    ],
    "name:lit_x_preferred":[
        "Harkavi\u010d\u0117"
    ],
    "name:pol_x_preferred":[
        "Harkawicze"
    ],
    "name:ukr_x_preferred":[
        "\u0413\u0430\u0440\u043a\u0430\u0432\u0456\u0447\u0435"
    ],
    "wof:name":"Harkawicze",
    "wof:placetype":"locality"
},
  "geometry": {"coordinates":[23.7266,53.32107],"type":"Point"}
}