{
  "type": "Feature",
  "properties": {
    "gn:admin1_code":"77.0",
    "gn:admin2_code":"1215.0",
    "gn:admin3_code":"121508.0",
    "gn:asciiname":"Welcza",
    "gn:country_code":"PL",
    "gn:dem":619,
    "gn:feature_class":"P",
    "gn:feature_code":"PPL",
    "gn:name":"We\u0142cza",
    "gn:population":0,
    "gn:timezone":"Europe/Warsaw",
    "iso:country":"PL",
    "wof:name":"Welcza",
    "wof:placetype":"locality"
},
  "geometry": {"coordinates":[19.51567,49.65307],"type":"Point"}
}