{
  "type": "Feature",
  "properties": {
    "gn:gn_country":"PL",
    "gn:gn_fcode":"PPLA3",
    "gn:gn_pop":26044,
    "gn:population":26044,
    "iso:country":"PL",
    "name:bel_x_preferred":[
        "\u0428\u0447\u044b\u0442\u043d\u0430"
    ],
    "name:bul_x_preferred":[
        "\u0428\u0447\u0438\u0442\u043d\u043e"
    ],
    "name:ceb_x_preferred":[
        "Szczytno"
    ],
    "name:deu_x_preferred":[
        "Ortelsburg"
    ],
    "name:deu_x_variant":[
        "Szczytno"
    ],
    "name:dsb_x_preferred":[
        "Szczytno"
    ],
    "name:epo_x_preferred":[
        "Szczytno"
    ],
    "name:eus_x_preferred":[
        "Szczytno"
    ],
    "name:fas_x_preferred":[
        "\u0634\u0686\u062a\u0646\u0648"
    ],
    "name:fra_x_preferred":[
        "Szczytno"
    ],
    "name:ita_x_preferred":[
        "Szczytno"
    ],
    "name:jav_x_preferred":[
        "Szczytno"
    ],
    "name:lav_x_preferred":[
        "\u0160\u010ditno"
    ],
    "name:lit_x_preferred":[
        "\u0160\u010dytnas"
    ],
    "name:msa_x_preferred":[
        "Szczytno"
    ],
    "name:nld_x_preferred":[
        "Szczytno"
    ],
    "name:nor_x_preferred":[
        "Szczytno"
    ],
    "name:pol_x_preferred":[
        "Szczytno"
    ],
    "name:por_x_preferred":[
        "Szczytno"
    ],
    "name:ron_x_preferred":[
        "Szczytno"
    ],
    "name:rus_x_preferred":[
        "\u0429\u0438\u0442\u043d\u043e"
    ],
    "name:slk_x_preferred":[
        "Szczytno"
    ],
    "name:srp_x_preferred":[
        "\u0428\u0447\u0438\u0442\u043d\u043e"
    ],
    "name:swe_x_preferred":[
        "Szczytno"
    ],
    "name:szl_x_preferred":[
        "Szczytno"
    ],
    "name:tur_x_preferred":[
        "Szczytno"
    ],
    "name:ukr_x_preferred":[
        "\u0429\u0438\u0442\u043d\u043e"
    ],
    "name:unk_x_variant":[
        "Szczyton"
    ],
    "name:vie_x_preferred":[
        "Szczytno"
    ],
    "name:war_x_preferred":[
        "Szczytno"
    ],
    "name:zho_x_preferred":[
        "\u4ec0\u5947\u7279\u8afe"
    ],
    "qs_pg:aaroncc":"PL",
    "qs_pg:gn_country":"PL",
    "qs_pg:gn_fcode":"PPLA3",
    "qs_pg:gn_pop":26044,
    "qs_pg:name":"Szczytno",
    "qs_pg:name_adm0":"Polska",
    "qs_pg:name_adm1":"Warminsko-Mazurskie",
    "qs_pg:photos":4,
    "qs_pg:photos_1k":1,
    "qs_pg:photos_9k":1,
    "qs_pg:photos_9r":1,
    "qs_pg:photos_all":4,
    "qs_pg:photos_sr":1,
    "qs_pg:pop_sr":7,
    "qs_pg:qs_pg_placetype":"localadmin",
    "qs_pg:qs_pg_placetype_gp":"LocalAdmin",
    "qs_pg:woe_adm0":23424923,
    "woe:adm0_id":23424923,
    "woe:name_adm0":"Polska",
    "woe:name_adm1":"Warminsko-Mazurskie",
    "woe:placetype":"LocalAdmin",
    "wof:name":"Szczytno",
    "wof:placetype":"localadmin",
    "wof:population":26044
},
  "geometry": {"coordinates":[20.98747,53.56259],"type":"Point"}
}