{
  "type": "Feature",
  "properties": {
    "gn:admin1_code":"73.0",
    "gn:admin2_code":"418.0",
    "gn:admin3_code":"41802.0",
    "gn:asciiname":"Boza Wola",
    "gn:country_code":"PL",
    "gn:dem":117,
    "gn:feature_class":"P",
    "gn:feature_code":"PPL",
    "gn:name":"Bo\u017ca Wola",
    "gn:population":0,
    "gn:timezone":"Europe/Warsaw",
    "iso:country":"PL",
    "wof:name":"Boza Wola",
    "wof:placetype":"locality"
},
  "geometry": {"coordinates":[19.22095,52.48251],"type":"Point"}
}