{
  "type": "Feature",
  "properties": {
    "gn:admin1_code":"78.0",
    "gn:admin2_code":"1434.0",
    "gn:admin3_code":"143406.0",
    "gn:asciiname":"Strachow",
    "gn:country_code":"PL",
    "gn:dem":94,
    "gn:feature_class":"P",
    "gn:feature_code":"PPL",
    "gn:name":"Strach\u00f3w",
    "gn:population":0,
    "gn:timezone":"Europe/Warsaw",
    "iso:country":"PL",
    "name:ceb_x_preferred":[
        "Strach\u00f3w"
    ],
    "name:fra_x_preferred":[
        "Strach\u00f3w"
    ],
    "name:pol_x_preferred":[
        "Strach\u00f3w"
    ],
    "name:ukr_x_preferred":[
        "\u0421\u0442\u0440\u0430\u0445\u0443\u0432"
    ],
    "wof:name":"Strachow",
    "wof:placetype":"locality"
},
  "geometry": {"coordinates":[21.59743,52.54041],"type":"Point"}
}