{
  "type": "Feature",
  "properties": {
    "gn:admin1_code":"80.0",
    "gn:admin2_code":"1803.0",
    "gn:admin3_code":"180307.0",
    "gn:asciiname":"Zawierzbie",
    "gn:country_code":"PL",
    "gn:dem":186,
    "gn:feature_class":"P",
    "gn:feature_code":"PPL",
    "gn:name":"Zawierzbie",
    "gn:population":0,
    "gn:timezone":"Europe/Warsaw",
    "iso:country":"PL",
    "name:ceb_x_preferred":[
        "Zawierzbie"
    ],
    "name:pol_x_preferred":[
        "Zawierzbie"
    ],
    "name:ukr_x_preferred":[
        "\u0417\u0430\u0432\u0435\u0436\u0431\u0435"
    ],
    "wof:name":"Zawierzbie",
    "wof:placetype":"locality"
},
  "geometry": {"coordinates":[21.39125,50.07095],"type":"Point"}
}