{
  "type": "Feature",
  "properties": {
    "gn:admin1_code":"75.0",
    "gn:admin2_code":"619.0",
    "gn:admin3_code":"61903.0",
    "gn:asciiname":"Osowa",
    "gn:country_code":"PL",
    "gn:dem":169,
    "gn:feature_class":"P",
    "gn:feature_code":"PPL",
    "gn:name":"Osowa",
    "gn:population":0,
    "gn:timezone":"Europe/Warsaw",
    "iso:country":"PL",
    "name:csb_x_preferred":[
        "\u00d2sow\u00f4"
    ],
    "name:deu_x_preferred":[
        "Osowa"
    ],
    "name:ita_x_preferred":[
        "Osowa"
    ],
    "name:nld_x_preferred":[
        "Osowa"
    ],
    "name:pol_x_preferred":[
        "Osowa"
    ],
    "wof:name":"Osowa",
    "wof:placetype":"locality"
},
  "geometry": {"coordinates":[23.51814,51.41105],"type":"Point"}
}