{
  "type": "Feature",
  "properties": {
    "gn:admin1_code":"80.0",
    "gn:admin2_code":"1818.0",
    "gn:admin3_code":"181803.0",
    "gn:asciiname":"Palenie",
    "gn:country_code":"PL",
    "gn:dem":154,
    "gn:feature_class":"P",
    "gn:feature_code":"PPL",
    "gn:name":"Palenie",
    "gn:population":0,
    "gn:timezone":"Europe/Warsaw",
    "iso:country":"PL",
    "wof:name":"Palenie",
    "wof:placetype":"locality"
},
  "geometry": {"coordinates":[22.11524,50.59422],"type":"Point"}
}