{
  "type": "Feature",
  "properties": {
    "gn:admin1_code":"74.0",
    "gn:admin2_code":"1014.0",
    "gn:admin3_code":"101409.0",
    "gn:asciiname":"Ostrow Warcki",
    "gn:cc2":"PL",
    "gn:country_code":"PL",
    "gn:dem":118,
    "gn:feature_class":"P",
    "gn:feature_code":"PPL",
    "gn:name":"Ostr\u00f3w Warcki",
    "gn:population":0,
    "gn:timezone":"Europe/Warsaw",
    "iso:country":"PL",
    "name:pol_x_preferred":[
        "Ostr\u00f3w Warcki"
    ],
    "name:ukr_x_preferred":[
        "\u041e\u0441\u0442\u0440\u0443\u0432-\u0412\u0430\u0440\u0446\u044c\u043a\u0438\u0439"
    ],
    "name:und_x_variant":[
        "Ostr\u00f3w Wartski"
    ],
    "wof:name":"Ostrow Warcki",
    "wof:placetype":"locality"
},
  "geometry": {"coordinates":[18.65204,51.81217],"type":"Point"}
}