{
  "type": "Feature",
  "properties": {
    "gn:admin1_code":"74.0",
    "gn:admin2_code":"1014.0",
    "gn:admin3_code":"101409.0",
    "gn:asciiname":"Ostrow Warcki",
    "gn:cc2":"PL",
    "gn:country_code":"PL",
    "gn:dem":118,
    "gn:feature_class":"P",
    "gn:feature_code":"PPL",
    "gn:name":"Ostr\u00f3w Warcki",
    "gn:population":0,
    "gn:timezone":"Europe/Warsaw",
    "iso:country":"PL",
    "name:und_x_variant":[
        "Ostr\u00f3w Wartski",
        "Ostr\u00f3w Warcki"
    ],
    "wof:name":"Ostrow Warcki",
    "wof:placetype":"locality"
},
  "geometry": {"coordinates":[18.65204,51.81217],"type":"Point"}
}