{
  "type": "Feature",
  "properties": {
    "gn:admin1_code":"72.0",
    "gn:admin2_code":"201.0",
    "gn:admin3_code":"20103.0",
    "gn:asciiname":"Pasternik",
    "gn:country_code":"PL",
    "gn:dem":147,
    "gn:feature_class":"P",
    "gn:feature_code":"PPL",
    "gn:name":"Pasternik",
    "gn:population":0,
    "gn:timezone":"Europe/Warsaw",
    "iso:country":"PL",
    "name:pol_x_preferred":[
        "Pasternik"
    ],
    "name:spa_x_preferred":[
        "Pasternik"
    ],
    "name:ukr_x_preferred":[
        "\u041f\u0430\u0441\u0442\u0435\u0440\u043d\u0438\u043a"
    ],
    "wof:name":"Pasternik",
    "wof:placetype":"locality"
},
  "geometry": {"coordinates":[15.80589,51.40659],"type":"Point"}
}