{
  "type": "Feature",
  "properties": {
    "gn:admin1_code":"84.0",
    "gn:admin2_code":"2611.0",
    "gn:admin3_code":"261104.0",
    "gn:asciiname":"Jadowniki",
    "gn:country_code":"PL",
    "gn:dem":301,
    "gn:feature_class":"P",
    "gn:feature_code":"PPL",
    "gn:name":"Jadowniki",
    "gn:population":0,
    "gn:timezone":"Europe/Warsaw",
    "iso:country":"PL",
    "wof:name":"Jadowniki",
    "wof:placetype":"locality"
},
  "geometry": {"coordinates":[21.07515,50.94981],"type":"Point"}
}