{
  "type": "Feature",
  "properties": {
    "gn:admin1_code":"80.0",
    "gn:admin2_code":"1821.0",
    "gn:admin3_code":"182102.0",
    "gn:asciiname":"Majdan",
    "gn:country_code":"PL",
    "gn:dem":594,
    "gn:feature_class":"P",
    "gn:feature_code":"PPL",
    "gn:name":"Majdan",
    "gn:population":0,
    "gn:timezone":"Europe/Warsaw",
    "iso:country":"PL",
    "wof:name":"Majdan",
    "wof:placetype":"locality"
},
  "geometry": {"coordinates":[22.29692,49.20661],"type":"Point"}
}