{
  "type": "Feature",
  "properties": {
    "gn:admin1_code":"80.0",
    "gn:admin2_code":"1821.0",
    "gn:admin3_code":"182102.0",
    "gn:asciiname":"Majdan",
    "gn:country_code":"PL",
    "gn:dem":594,
    "gn:feature_class":"P",
    "gn:feature_code":"PPL",
    "gn:name":"Majdan",
    "gn:population":0,
    "gn:timezone":"Europe/Warsaw",
    "iso:country":"PL",
    "name:azb_x_preferred":[
        "\u0645\u0627\u06cc\u062f\u0627\u0646"
    ],
    "name:fas_x_preferred":[
        "\u0645\u0627\u06cc\u062f\u0627\u0646"
    ],
    "name:hun_x_preferred":[
        "Majdan"
    ],
    "name:pol_x_preferred":[
        "Majdan"
    ],
    "name:ukr_x_preferred":[
        "\u041c\u0430\u0439\u0434\u0430\u043d"
    ],
    "wof:name":"Majdan",
    "wof:placetype":"locality"
},
  "geometry": {"coordinates":[22.29692,49.20661],"type":"Point"}
}