{
  "type": "Feature",
  "properties": {
    "gn:admin1_code":"85.0",
    "gn:admin2_code":"2810.0",
    "gn:admin3_code":"281002.0",
    "gn:asciiname":"Cudnochy",
    "gn:country_code":"PL",
    "gn:dem":126,
    "gn:feature_class":"P",
    "gn:feature_code":"PPL",
    "gn:name":"Cudnochy",
    "gn:population":0,
    "gn:timezone":"Europe/Warsaw",
    "iso:country":"PL",
    "name:und_x_variant":[
        "Zudnochen",
        "Siebenh\u00f6fen",
        "Siebenh\u00f6fen Ostpreussen",
        "Cudnochy"
    ],
    "wof:name":"Cudnochy",
    "wof:placetype":"locality"
},
  "geometry": {"coordinates":[21.49061,53.85222],"type":"Point"}
}