{
  "type": "Feature",
  "properties": {
    "gn:admin1_code":"72.0",
    "gn:admin2_code":"221.0",
    "gn:admin3_code":"22108.0",
    "gn:asciiname":"Glinno",
    "gn:country_code":"PL",
    "gn:dem":561,
    "gn:feature_class":"P",
    "gn:feature_code":"PPL",
    "gn:name":"Glinno",
    "gn:population":0,
    "gn:timezone":"Europe/Warsaw",
    "iso:country":"PL",
    "name:ceb_x_preferred":[
        "Glinno"
    ],
    "name:deu_x_historical":[
        "Heinrichau"
    ],
    "name:deu_x_preferred":[
        "Heinrichau"
    ],
    "name:pol_x_preferred":[
        "Glinno"
    ],
    "name:szl_x_preferred":[
        "Glinno"
    ],
    "name:ukr_x_preferred":[
        "\u0490\u043b\u0456\u043d\u043d\u043e"
    ],
    "wof:name":"Glinno",
    "wof:placetype":"locality"
},
  "geometry": {"coordinates":[16.47572000000001,50.71885],"type":"Point"}
}