{
  "type": "Feature",
  "properties": {
    "gn:admin1_code":"78.0",
    "gn:admin2_code":"1434.0",
    "gn:admin3_code":"143409.0",
    "gn:asciiname":"Losie",
    "gn:country_code":"PL",
    "gn:dem":88,
    "gn:feature_class":"P",
    "gn:feature_code":"PPL",
    "gn:name":"\u0141osie",
    "gn:population":0,
    "gn:timezone":"Europe/Warsaw",
    "iso:country":"PL",
    "name:ceb_x_preferred":[
        "\u0141osie"
    ],
    "name:fra_x_preferred":[
        "\u0141osie"
    ],
    "name:pol_x_preferred":[
        "\u0141osie"
    ],
    "name:ukr_x_preferred":[
        "\u041b\u043e\u0441\u0435"
    ],
    "wof:name":"Losie",
    "wof:placetype":"locality"
},
  "geometry": {"coordinates":[21.1813,52.45686],"type":"Point"}
}