{
  "type": "Feature",
  "properties": {
    "gn:admin1_code":"79.0",
    "gn:admin2_code":"1601.0",
    "gn:admin3_code":"160103.0",
    "gn:asciiname":"Jaszow",
    "gn:country_code":"PL",
    "gn:dem":216,
    "gn:feature_class":"P",
    "gn:feature_code":"PPL",
    "gn:name":"Jasz\u00f3w",
    "gn:population":0,
    "gn:timezone":"Europe/Warsaw",
    "iso:country":"PL",
    "name:deu_x_preferred":[
        "Jasz\u00f3w"
    ],
    "name:pol_x_preferred":[
        "Jasz\u00f3w"
    ],
    "name:ukr_x_preferred":[
        "\u042f\u0448\u0443\u0432"
    ],
    "wof:name":"Jaszow",
    "wof:placetype":"locality"
},
  "geometry": {"coordinates":[17.24459,50.59501],"type":"Point"}
}