{
  "type": "Feature",
  "properties": {
    "gn:admin1_code":"85.0",
    "gn:admin2_code":"2817.0",
    "gn:admin3_code":"281703.0",
    "gn:asciiname":"Szuc",
    "gn:country_code":"PL",
    "gn:dem":132,
    "gn:feature_class":"P",
    "gn:feature_code":"PPL",
    "gn:name":"Szu\u0107",
    "gn:population":0,
    "gn:timezone":"Europe/Warsaw",
    "iso:country":"PL",
    "name:ceb_x_preferred":[
        "Szu\u0107"
    ],
    "name:pol_x_preferred":[
        "Szu\u0107"
    ],
    "name:szl_x_preferred":[
        "Szu\u0107"
    ],
    "name:ukr_x_preferred":[
        "\u0428\u0443\u0446\u044c"
    ],
    "name:und_x_variant":[
        "Schuttschen",
        "Sutszy",
        "Sucz"
    ],
    "wof:name":"Szuc",
    "wof:placetype":"locality"
},
  "geometry": {"coordinates":[20.73265,53.50589],"type":"Point"}
}