{
  "type": "Feature",
  "properties": {
    "gn:admin1_code":"82.0",
    "gn:admin2_code":"2212.0",
    "gn:admin3_code":"221203.0",
    "gn:asciiname":"Skarszow Gorny",
    "gn:country_code":"PL",
    "gn:dem":78,
    "gn:feature_class":"P",
    "gn:feature_code":"PPL",
    "gn:name":"Skarsz\u00f3w G\u00f3rny",
    "gn:population":0,
    "gn:timezone":"Europe/Warsaw",
    "iso:country":"PL",
    "name:ceb_x_preferred":[
        "Skarsz\u00f3w G\u00f3rny"
    ],
    "name:deu_x_preferred":[
        "Skarsz\u00f3w G\u00f3rny"
    ],
    "name:pol_x_preferred":[
        "Skarsz\u00f3w G\u00f3rny"
    ],
    "name:ukr_x_preferred":[
        "\u0421\u043a\u0430\u0440\u0448\u0443\u0432-\u0490\u0443\u0440\u043d\u0438"
    ],
    "name:und_x_variant":[
        "Skarsz\u00f3w G\u00f3rny"
    ],
    "wof:name":"Skarszow Gorny",
    "wof:placetype":"locality"
},
  "geometry": {"coordinates":[17.12229,54.37922],"type":"Point"}
}