{
  "type": "Feature",
  "properties": {
    "gn:admin1_code":"84.0",
    "gn:admin2_code":"2605.0",
    "gn:admin3_code":"260501.0",
    "gn:asciiname":"Turowice",
    "gn:country_code":"PL",
    "gn:dem":205,
    "gn:feature_class":"P",
    "gn:feature_code":"PPL",
    "gn:name":"Turowice",
    "gn:population":0,
    "gn:timezone":"Europe/Warsaw",
    "iso:country":"PL",
    "wof:name":"Turowice",
    "wof:placetype":"locality"
},
  "geometry": {"coordinates":[20.05666,51.18139],"type":"Point"}
}