{
  "type": "Feature",
  "properties": {
    "gn:admin1_code":"84.0",
    "gn:admin2_code":"2605.0",
    "gn:admin3_code":"260501.0",
    "gn:asciiname":"Turowice",
    "gn:country_code":"PL",
    "gn:dem":205,
    "gn:feature_class":"P",
    "gn:feature_code":"PPL",
    "gn:name":"Turowice",
    "gn:population":0,
    "gn:timezone":"Europe/Warsaw",
    "iso:country":"PL",
    "name:azb_x_preferred":[
        "\u062a\u0648\u0631\u0648\u06cc\u06a9"
    ],
    "name:ceb_x_preferred":[
        "Turowice"
    ],
    "name:fas_x_preferred":[
        "\u062a\u0648\u0631\u0648\u06cc\u06a9"
    ],
    "name:pol_x_preferred":[
        "Turowice"
    ],
    "name:ukr_x_preferred":[
        "\u0422\u0443\u0440\u043e\u0432\u0456\u0446\u0435"
    ],
    "name:urd_x_preferred":[
        "\u062a\u0648\u0631\u0648\u0648\u06cc\u06a9"
    ],
    "wof:name":"Turowice",
    "wof:placetype":"locality"
},
  "geometry": {"coordinates":[20.05666,51.18139],"type":"Point"}
}