{
  "type": "Feature",
  "properties": {
    "gn:admin1_code":"85.0",
    "gn:admin2_code":"2801.0",
    "gn:admin3_code":"280105.0",
    "gn:asciiname":"Kandyty",
    "gn:cc2":"PL",
    "gn:country_code":"PL",
    "gn:dem":138,
    "gn:feature_class":"P",
    "gn:feature_code":"PPL",
    "gn:name":"Kandyty",
    "gn:population":0,
    "gn:timezone":"Europe/Warsaw",
    "iso:country":"PL",
    "name:azb_x_preferred":[
        "\u06a9\u0627\u0646\u062f\u062a\u0647"
    ],
    "name:ceb_x_preferred":[
        "Kandyty"
    ],
    "name:eng_x_preferred":[
        "Kandyty"
    ],
    "name:fas_x_preferred":[
        "\u06a9\u0627\u0646\u062f\u062a\u0647"
    ],
    "name:fra_x_preferred":[
        "Kandyty"
    ],
    "name:nld_x_preferred":[
        "Kandyty"
    ],
    "name:pol_x_preferred":[
        "Kandyty"
    ],
    "name:rus_x_preferred":[
        "\u041a\u0430\u043d\u0434\u044b\u0442\u044b"
    ],
    "name:ukr_x_preferred":[
        "\u041a\u0430\u043d\u0434\u0438\u0442\u0438"
    ],
    "name:und_x_variant":[
        "Canditten",
        "Kanditten",
        "Kandyty"
    ],
    "wof:name":"Kandyty",
    "wof:placetype":"locality"
},
  "geometry": {"coordinates":[20.36891,54.31692],"type":"Point"}
}