{
  "type": "Feature",
  "properties": {
    "gn:admin1_code":"75.0",
    "gn:admin2_code":"602.0",
    "gn:admin3_code":"60205.0",
    "gn:asciiname":"Pulczynow",
    "gn:country_code":"PL",
    "gn:dem":278,
    "gn:feature_class":"P",
    "gn:feature_code":"PPL",
    "gn:name":"Pulczyn\u00f3w",
    "gn:population":0,
    "gn:timezone":"Europe/Warsaw",
    "iso:country":"PL",
    "name:und_x_variant":[
        "Kolonia Pulczyn\u00f3w",
        "Pulczyn\u00f3w"
    ],
    "wof:name":"Pulczynow",
    "wof:placetype":"locality"
},
  "geometry": {"coordinates":[22.75925,50.64978],"type":"Point"}
}