{
  "type": "Feature",
  "properties": {
    "gn:admin1_code":"75.0",
    "gn:admin2_code":"604.0",
    "gn:admin3_code":"60405.0",
    "gn:asciiname":"Marysin",
    "gn:country_code":"PL",
    "gn:dem":211,
    "gn:feature_class":"P",
    "gn:feature_code":"PPL",
    "gn:name":"Marysin",
    "gn:population":0,
    "gn:timezone":"Europe/Warsaw",
    "iso:country":"PL",
    "name:fra_x_preferred":[
        "Marysin"
    ],
    "name:pol_x_preferred":[
        "Marysin"
    ],
    "name:ukr_x_preferred":[
        "\u041c\u0430\u0440\u0438\u0441\u0456\u043d"
    ],
    "name:und_x_variant":[
        "Kolonia Marysin"
    ],
    "wof:name":"Marysin",
    "wof:placetype":"locality"
},
  "geometry": {"coordinates":[23.8901,50.62786],"type":"Point"}
}