{
  "type": "Feature",
  "properties": {
    "gn:admin1_code":"81.0",
    "gn:admin2_code":"2013.0",
    "gn:admin3_code":"201308.0",
    "gn:asciiname":"Perki Mazowsze",
    "gn:country_code":"PL",
    "gn:dem":132,
    "gn:feature_class":"P",
    "gn:feature_code":"PPL",
    "gn:name":"Perki Mazowsze",
    "gn:population":0,
    "gn:timezone":"Europe/Warsaw",
    "iso:country":"PL",
    "wof:name":"Perki Mazowsze",
    "wof:placetype":"locality"
},
  "geometry": {"coordinates":[22.75663,52.97563],"type":"Point"}
}