{
  "type": "Feature",
  "properties": {
    "gn:admin1_code":"81.0",
    "gn:admin2_code":"2013.0",
    "gn:admin3_code":"201308.0",
    "gn:asciiname":"Perki Mazowsze",
    "gn:country_code":"PL",
    "gn:dem":132,
    "gn:feature_class":"P",
    "gn:feature_code":"PPL",
    "gn:name":"Perki Mazowsze",
    "gn:population":0,
    "gn:timezone":"Europe/Warsaw",
    "iso:country":"PL",
    "name:lit_x_preferred":[
        "Perki Mazov\u0161\u0117"
    ],
    "name:pol_x_preferred":[
        "Perki-Mazowsze"
    ],
    "name:ukr_x_preferred":[
        "\u041f\u0435\u0440\u043a\u0456-\u041c\u0430\u0437\u043e\u0432\u0448\u0435"
    ],
    "wof:name":"Perki Mazowsze",
    "wof:placetype":"locality"
},
  "geometry": {"coordinates":[22.75663,52.97563],"type":"Point"}
}