{
  "type": "Feature",
  "properties": {
    "gn:admin1_code":"76",
    "gn:admin2_code":"0812",
    "gn:admin3_code":"81201.0",
    "gn:asciiname":"Krzydlowiczki",
    "gn:country_code":"PL",
    "gn:dem":96,
    "gn:feature_class":"P",
    "gn:feature_code":"PPL",
    "gn:name":"Krzyd\u0142owiczki",
    "gn:population":0,
    "gn:timezone":"Europe/Warsaw",
    "iso:country":"PL",
    "name:deu_x_historical":[
        "Bergvorwerk"
    ],
    "name:deu_x_preferred":[
        "Bergvorwerk"
    ],
    "wof:name":"Krzydlowiczki",
    "wof:placetype":"locality"
},
  "geometry": {"coordinates":[16.13977,51.82294],"type":"Point"}
}