{
  "type": "Feature",
  "properties": {
    "gn:admin1_code":"75.0",
    "gn:admin2_code":"618.0",
    "gn:admin3_code":"61813.0",
    "gn:asciiname":"Tarnoszyn",
    "gn:country_code":"PL",
    "gn:dem":209,
    "gn:feature_class":"P",
    "gn:feature_code":"PPL",
    "gn:name":"Tarnoszyn",
    "gn:population":0,
    "gn:timezone":"Europe/Warsaw",
    "iso:country":"PL",
    "name:ceb_x_preferred":[
        "Tarnoszyn"
    ],
    "name:fra_x_preferred":[
        "Tarnoszyn"
    ],
    "name:pol_x_preferred":[
        "Tarnoszyn"
    ],
    "name:ukr_x_preferred":[
        "\u0422\u0430\u0440\u043d\u043e\u0448\u0438\u043d"
    ],
    "name:und_x_variant":[
        "Tarnoshin",
        "Tarnoshyn"
    ],
    "wof:name":"Tarnoszyn",
    "wof:placetype":"locality"
},
  "geometry": {"coordinates":[23.79158,50.42225],"type":"Point"}
}