{
  "type": "Feature",
  "properties": {
    "iso:country":"PL",
    "name:eng_x_preferred":[
        "Strzyza Gorna"
    ],
    "name:pol_x_preferred":[
        "Strzy\u017ca G\u00f3rna"
    ],
    "wof:name":"Strzyza Gorna",
    "wof:placetype":"neighbourhood"
},
  "geometry": {"coordinates":[18.585046174932,54.38375451769961],"type":"Point"}
}