{
  "type": "Feature",
  "properties": {
    "gn:admin1_code":"82.0",
    "gn:admin2_code":"2215.0",
    "gn:admin3_code":"221505.0",
    "gn:asciiname":"Toliszczyk",
    "gn:country_code":"PL",
    "gn:dem":65,
    "gn:feature_class":"P",
    "gn:feature_code":"PPL",
    "gn:name":"Toliszczyk",
    "gn:population":0,
    "gn:timezone":"Europe/Warsaw",
    "iso:country":"PL",
    "wof:name":"Toliszczyk",
    "wof:placetype":"locality"
},
  "geometry": {"coordinates":[18.01291,54.74661],"type":"Point"}
}