{
  "type": "Feature",
  "properties": {
    "gn:admin1_code":"74.0",
    "gn:admin2_code":"1002.0",
    "gn:admin3_code":"100202.0",
    "gn:asciiname":"Kujawki",
    "gn:country_code":"PL",
    "gn:dem":102,
    "gn:feature_class":"P",
    "gn:feature_code":"PPL",
    "gn:name":"Kujawki",
    "gn:population":0,
    "gn:timezone":"Europe/Warsaw",
    "iso:country":"PL",
    "wof:name":"Kujawki",
    "wof:placetype":"locality"
},
  "geometry": {"coordinates":[19.62381,52.18907],"type":"Point"}
}