{
  "type": "Feature",
  "properties": {
    "gn:admin1_code":"76.0",
    "gn:admin2_code":"862.0",
    "gn:admin3_code":"86201.0",
    "gn:asciiname":"Winnica",
    "gn:country_code":"PL",
    "gn:dem":127,
    "gn:feature_class":"P",
    "gn:feature_code":"PPL",
    "gn:name":"Winnica",
    "gn:population":0,
    "gn:timezone":"Europe/Warsaw",
    "iso:country":"PL",
    "name:ceb_x_preferred":[
        "Winnica"
    ],
    "name:deu_x_preferred":[
        "Winnica"
    ],
    "name:fin_x_preferred":[
        "Vinnitsa"
    ],
    "name:fra_x_preferred":[
        "Winnica"
    ],
    "name:nld_x_preferred":[
        "Winnica"
    ],
    "name:pol_x_preferred":[
        "Winnica"
    ],
    "name:rus_x_preferred":[
        "\u0412\u0438\u043d\u043d\u0438\u0446\u0430"
    ],
    "name:ukr_x_preferred":[
        "\u0412\u0456\u043d\u043d\u0438\u0446\u044f"
    ],
    "wof:name":"Winnica",
    "wof:placetype":"neighbourhood"
},
  "geometry": {"coordinates":[15.49776,51.94423],"type":"Point"}
}