{
  "type": "Feature",
  "properties": {
    "gn:admin1_code":"87",
    "gn:admin2_code":"3203",
    "gn:admin3_code":"320301.0",
    "gn:asciiname":"Stare Kalensko",
    "gn:country_code":"PL",
    "gn:dem":155,
    "gn:feature_class":"P",
    "gn:feature_code":"PPL",
    "gn:name":"Stare Kale\u0144sko",
    "gn:population":333,
    "gn:timezone":"Europe/Warsaw",
    "iso:country":"PL",
    "name:ceb_x_preferred":[
        "Stare Kale\u0144sko"
    ],
    "name:pol_x_preferred":[
        "Stare Kale\u0144sko"
    ],
    "name:vie_x_preferred":[
        "Stare Kale\u0144sko"
    ],
    "wof:name":"Stare Kalensko",
    "wof:placetype":"locality",
    "wof:population":333
},
  "geometry": {"coordinates":[16.15265,53.52571999999999],"type":"Point"}
}