{
  "type": "Feature",
  "properties": {
    "gn:admin1_code":"78.0",
    "gn:admin2_code":"1414.0",
    "gn:admin3_code":"141406.0",
    "gn:asciiname":"Wygoda Smoszewska",
    "gn:country_code":"PL",
    "gn:dem":95,
    "gn:feature_class":"P",
    "gn:feature_code":"PPL",
    "gn:name":"Wygoda Smoszewska",
    "gn:population":0,
    "gn:timezone":"Europe/Warsaw",
    "iso:country":"PL",
    "name:fra_x_preferred":[
        "Wygoda Smoszewska"
    ],
    "name:mkd_x_preferred":[
        "\u0412\u0438\u0433\u043e\u0434\u0430 \u0421\u043c\u043e\u0448\u0435\u0432\u0441\u043a\u0430"
    ],
    "name:pol_x_preferred":[
        "Wygoda Smoszewska"
    ],
    "name:ukr_x_preferred":[
        "\u0412\u0438\u0491\u043e\u0434\u0430-\u0421\u043c\u043e\u0448\u0435\u0432\u0441\u044c\u043a\u0430"
    ],
    "wof:name":"Wygoda Smoszewska",
    "wof:placetype":"locality"
},
  "geometry": {"coordinates":[20.50804,52.43896],"type":"Point"}
}