{
  "type": "Feature",
  "properties": {
    "gn:population":8670,
    "iso:country":"PL",
    "name:azb_x_preferred":[
        "\u06a9\u0627\u0644\u062a\u0647"
    ],
    "name:bul_x_preferred":[
        "\u041a\u0430\u043b\u0435\u0442\u0438"
    ],
    "name:ceb_x_preferred":[
        "Kalety"
    ],
    "name:deu_x_preferred":[
        "Kalety"
    ],
    "name:eng_x_preferred":[
        "Kalety"
    ],
    "name:epo_x_preferred":[
        "Kalety"
    ],
    "name:eus_x_preferred":[
        "Kalety"
    ],
    "name:fas_x_preferred":[
        "\u06a9\u0627\u0644\u062a\u0647"
    ],
    "name:fra_x_preferred":[
        "Kalety"
    ],
    "name:ita_x_preferred":[
        "Kalety"
    ],
    "name:jav_x_preferred":[
        "Kalety"
    ],
    "name:lav_x_preferred":[
        "Kaleti"
    ],
    "name:msa_x_preferred":[
        "Kalety"
    ],
    "name:nan_x_preferred":[
        "Kalety"
    ],
    "name:nld_x_preferred":[
        "Kalety"
    ],
    "name:pol_x_preferred":[
        "Kalety"
    ],
    "name:por_x_preferred":[
        "Kalety"
    ],
    "name:ron_x_preferred":[
        "Kalety"
    ],
    "name:rus_x_preferred":[
        "\u041a\u0430\u043b\u0435\u0442\u044b"
    ],
    "name:slk_x_preferred":[
        "Kalety"
    ],
    "name:srp_x_preferred":[
        "\u041a\u0430\u043b\u0435\u0442\u0438"
    ],
    "name:szl_x_preferred":[
        "Kalety"
    ],
    "name:tat_x_preferred":[
        "\u041a\u0430\u043b\u0435\u0442\u044b"
    ],
    "name:ukr_x_preferred":[
        "\u041a\u0430\u043b\u0435\u0442\u0438"
    ],
    "name:vie_x_preferred":[
        "Kalety"
    ],
    "name:war_x_preferred":[
        "Kalety"
    ],
    "name:zho_min_nan_x_preferred":[
        "Kalety"
    ],
    "name:zho_x_preferred":[
        "\u5361\u840a\u8482"
    ],
    "qs:a0":"Rzeczpospolita Polska",
    "qs:a1":"*Slaskie",
    "qs:a1r":"0",
    "qs:a2":"Tarnog\u00f3rski",
    "qs:adm0":"Rzeczpospolita Polska",
    "qs:la":"Kosz\u0119cin",
    "qs:la_lc":"*PL2407062",
    "qs:level":"locality",
    "qs:loc":"Kalety",
    "qs:loc_alt":"Kalety",
    "qs:pop":0,
    "qs:type":"rural point-in-poly",
    "wd:wordcount":38,
    "wof:coterminous":[
        1125291959
    ],
    "wof:name":"Kalety",
    "wof:placetype":"locality",
    "wof:population":8670
},
  "geometry": {"coordinates":[18.9267394064324,50.5521934428646],"type":"Point"}
}