{
  "type": "Feature",
  "properties": {
    "gn:admin1_code":"72.0",
    "gn:admin2_code":"215.0",
    "gn:admin3_code":"21504.0",
    "gn:asciiname":"Drzemlikowice",
    "gn:country_code":"PL",
    "gn:dem":140,
    "gn:feature_class":"P",
    "gn:feature_code":"PPL",
    "gn:name":"Drzemlikowice",
    "gn:population":0,
    "gn:timezone":"Europe/Warsaw",
    "iso:country":"PL",
    "name:pol_x_preferred":[
        "Drzemlikowice"
    ],
    "name:ukr_x_preferred":[
        "\u0414\u0436\u0435\u043c\u043b\u0456\u043a\u043e\u0432\u0456\u0446\u0435"
    ],
    "wof:name":"Drzemlikowice",
    "wof:placetype":"locality"
},
  "geometry": {"coordinates":[17.24115,50.87856],"type":"Point"}
}