{
  "type": "Feature",
  "properties": {
    "gn:country":"PL",
    "gn:fcode":"PPL",
    "gn:population":0,
    "iso:country":"PL",
    "name:ast_x_preferred":[
        "Bo\u017catki"
    ],
    "name:ceb_x_preferred":[
        "Bo\u017catki"
    ],
    "name:ces_x_preferred":[
        "Bo\u017catki"
    ],
    "name:che_x_preferred":[
        "\u0411\u043e\u0436\u0430\u0442\u043a\u0438"
    ],
    "name:deu_x_preferred":[
        "Bo\u017catki"
    ],
    "name:eng_x_preferred":[
        "Bo\u017catki"
    ],
    "name:fra_x_preferred":[
        "Bo\u017catki"
    ],
    "name:nan_x_preferred":[
        "Bo\u017catki"
    ],
    "name:nld_x_preferred":[
        "Bo\u017catki"
    ],
    "name:pol_x_preferred":[
        "Bo\u017catki"
    ],
    "name:tat_x_preferred":[
        "\u0411\u043e\u0436\u0430\u0442\u043a\u0438"
    ],
    "name:ukr_x_preferred":[
        "\u0411\u043e\u0436\u0430\u0442\u043a\u0456"
    ],
    "qs_pg:aaroncc":"PL",
    "qs_pg:gn_country":"PL",
    "qs_pg:gn_fcode":"PPL",
    "qs_pg:gn_pop":0,
    "qs_pg:name":"Bo\u017catki",
    "qs_pg:name_adm0":"Polska",
    "qs_pg:name_adm1":"Wielkopolskie",
    "qs_pg:photos_9r":0,
    "qs_pg:photos_sr":0,
    "qs_pg:pop_sr":0,
    "qs_pg:qs_pg_placetype":"locality",
    "qs_pg:qs_pg_placetype_gp":"Town",
    "qs_pg:woe_adm0":23424923,
    "woe:adm0_id":23424923,
    "woe:name_adm0":"Polska",
    "woe:name_adm1":"Wielkopolskie",
    "woe:placetype":"Town",
    "wof:name":"Bo\u017catki",
    "wof:placetype":"locality"
},
  "geometry": {"coordinates":[18.04952,52.12609],"type":"Point"}
}