{
  "type": "Feature",
  "properties": {
    "gn:gn_country":"PL",
    "gn:gn_fcode":"PPLA3",
    "gn:gn_pop":900,
    "gn:population":900,
    "iso:country":"PL",
    "name:bul_x_preferred":[
        "\u0412\u0438\u043b\u043a\u043e\u0432"
    ],
    "name:ceb_x_preferred":[
        "Wilk\u00f3w"
    ],
    "name:deu_x_preferred":[
        "Wilk\u00f3w"
    ],
    "name:fra_x_preferred":[
        "Wilk\u00f3w"
    ],
    "name:ita_x_preferred":[
        "Wilk\u00f3w"
    ],
    "name:nld_x_preferred":[
        "Wilk\u00f3w"
    ],
    "name:pol_x_preferred":[
        "Wilk\u00f3w"
    ],
    "name:rus_x_preferred":[
        "\u0412\u0438\u043b\u044c\u043a\u0443\u0432"
    ],
    "name:ukr_x_preferred":[
        "\u0412\u0456\u043b\u044c\u043a\u0443\u0432"
    ],
    "qs_pg:aaroncc":"PL",
    "qs_pg:gn_country":"PL",
    "qs_pg:gn_fcode":"PPLA3",
    "qs_pg:gn_pop":900,
    "qs_pg:name":"Wilk\u00f3w",
    "qs_pg:name_adm0":"Polska",
    "qs_pg:name_adm1":"Opolskie",
    "qs_pg:photos":6,
    "qs_pg:photos_1k":1,
    "qs_pg:photos_9k":1,
    "qs_pg:photos_9r":1,
    "qs_pg:photos_all":6,
    "qs_pg:photos_sr":1,
    "qs_pg:pop_sr":2,
    "qs_pg:qs_pg_placetype":"localadmin",
    "qs_pg:qs_pg_placetype_gp":"LocalAdmin",
    "qs_pg:woe_adm0":23424923,
    "woe:adm0_id":23424923,
    "woe:name_adm0":"Polska",
    "woe:name_adm1":"Opolskie",
    "woe:placetype":"LocalAdmin",
    "wof:name":"Wilk\u00f3w",
    "wof:placetype":"localadmin",
    "wof:population":900
},
  "geometry": {"coordinates":[17.66284,51.10158],"type":"Point"}
}