{
  "type": "Feature",
  "properties": {
    "gn:admin1_code":"74.0",
    "gn:admin2_code":"1002.0",
    "gn:admin3_code":"100205.0",
    "gn:asciiname":"Psurze",
    "gn:country_code":"PL",
    "gn:dem":118,
    "gn:feature_class":"P",
    "gn:feature_code":"PPL",
    "gn:name":"Psurze",
    "gn:population":0,
    "gn:timezone":"Europe/Warsaw",
    "iso:country":"PL",
    "name:fra_x_preferred":[
        "Psurze"
    ],
    "name:pol_x_preferred":[
        "Psurze"
    ],
    "name:szl_x_preferred":[
        "Psurze"
    ],
    "name:ukr_x_preferred":[
        "\u041f\u0441\u0443\u0436\u0435"
    ],
    "wof:name":"Psurze",
    "wof:placetype":"locality"
},
  "geometry": {"coordinates":[19.44151,52.20855],"type":"Point"}
}