{
  "type": "Feature",
  "properties": {
    "gn:admin1_code":"85.0",
    "gn:admin2_code":"2819.0",
    "gn:admin3_code":"281903.0",
    "gn:asciiname":"Stregiel",
    "gn:country_code":"PL",
    "gn:dem":121,
    "gn:feature_class":"P",
    "gn:feature_code":"PPL",
    "gn:name":"Str\u0119giel",
    "gn:population":0,
    "gn:timezone":"Europe/Warsaw",
    "iso:country":"PL",
    "name:deu_x_preferred":[
        "Str\u0119giel"
    ],
    "name:pol_x_preferred":[
        "Str\u0119giel"
    ],
    "name:ukr_x_preferred":[
        "\u0421\u0442\u0440\u0435\u043d\u0491\u0435\u043b\u044c"
    ],
    "name:und_x_variant":[
        "Gross Strengeln"
    ],
    "wof:name":"Stregiel",
    "wof:placetype":"locality"
},
  "geometry": {"coordinates":[21.84764,54.19979],"type":"Point"}
}