{
  "type": "Feature",
  "properties": {
    "gn:admin1_code":"85.0",
    "gn:admin2_code":"2819.0",
    "gn:admin3_code":"281903.0",
    "gn:asciiname":"Stregiel",
    "gn:country_code":"PL",
    "gn:dem":121,
    "gn:feature_class":"P",
    "gn:feature_code":"PPL",
    "gn:name":"Str\u0119giel",
    "gn:population":0,
    "gn:timezone":"Europe/Warsaw",
    "iso:country":"PL",
    "name:und_x_variant":[
        "Gross Strengeln",
        "Str\u0119giel"
    ],
    "wof:name":"Stregiel",
    "wof:placetype":"locality"
},
  "geometry": {"coordinates":[21.84764,54.19979],"type":"Point"}
}