{
  "type": "Feature",
  "properties": {
    "gn:admin1_code":"80.0",
    "gn:admin2_code":"1801.0",
    "gn:admin3_code":"180108.0",
    "gn:asciiname":"Berehy Dolne",
    "gn:country_code":"PL",
    "gn:dem":504,
    "gn:feature_class":"P",
    "gn:feature_code":"PPL",
    "gn:name":"Berehy Dolne",
    "gn:population":0,
    "gn:timezone":"Europe/Warsaw",
    "iso:country":"PL",
    "wof:name":"Berehy Dolne",
    "wof:placetype":"locality"
},
  "geometry": {"coordinates":[22.63333,49.43333],"type":"Point"}
}