{
  "type": "Feature",
  "properties": {
    "gn:admin1_code":"82.0",
    "gn:admin2_code":"2205.0",
    "gn:admin3_code":"220502.0",
    "gn:asciiname":"Smetowo",
    "gn:country_code":"PL",
    "gn:dem":169,
    "gn:feature_class":"P",
    "gn:feature_code":"PPL",
    "gn:name":"Sm\u0119towo",
    "gn:population":0,
    "gn:timezone":"Europe/Warsaw",
    "iso:country":"PL",
    "wof:name":"Smetowo",
    "wof:placetype":"locality"
},
  "geometry": {"coordinates":[18.14923,54.30343000000001],"type":"Point"}
}