{
  "type": "Feature",
  "properties": {
    "gn:admin1_code":"84.0",
    "gn:admin2_code":"2611.0",
    "gn:admin3_code":"261101.0",
    "gn:asciiname":"Mieszala",
    "gn:country_code":"PL",
    "gn:dem":223,
    "gn:feature_class":"P",
    "gn:feature_code":"PPL",
    "gn:name":"Mi\u0119sza\u0142a",
    "gn:population":0,
    "gn:timezone":"Europe/Warsaw",
    "iso:country":"PL",
    "wof:name":"Mieszala",
    "wof:placetype":"locality"
},
  "geometry": {"coordinates":[21.04191,51.06649],"type":"Point"}
}