{
  "type": "Feature",
  "properties": {
    "gn:admin1_code":"81.0",
    "gn:admin2_code":"2011.0",
    "gn:admin3_code":"201108.0",
    "gn:asciiname":"Zadworzany",
    "gn:country_code":"PL",
    "gn:dem":178,
    "gn:feature_class":"P",
    "gn:feature_code":"PPL",
    "gn:name":"Zadworzany",
    "gn:population":0,
    "gn:timezone":"Europe/Warsaw",
    "iso:country":"PL",
    "name:lit_x_preferred":[
        "Zadvo\u017eanai"
    ],
    "name:pol_x_preferred":[
        "Zadworzany"
    ],
    "name:ukr_x_preferred":[
        "\u0417\u0430\u0434\u0432\u043e\u0436\u0430\u043d\u0438"
    ],
    "name:urd_x_preferred":[
        "\u0632\u0627\u062f\u0648\u0648\u0631\u0632\u0646\u0646\u06d2"
    ],
    "wof:name":"Zadworzany",
    "wof:placetype":"locality"
},
  "geometry": {"coordinates":[23.56486,53.45109],"type":"Point"}
}