{
  "type": "Feature",
  "properties": {
    "gn:admin1_code":"72.0",
    "gn:admin2_code":"215.0",
    "gn:admin3_code":"21501.0",
    "gn:asciiname":"Nowy Otok",
    "gn:country_code":"PL",
    "gn:dem":136,
    "gn:feature_class":"P",
    "gn:feature_code":"PPL",
    "gn:name":"Nowy Otok",
    "gn:population":0,
    "gn:timezone":"Europe/Warsaw",
    "iso:country":"PL",
    "wof:name":"Nowy Otok",
    "wof:placetype":"locality"
},
  "geometry": {"coordinates":[17.26078,50.93581],"type":"Point"}
}