{
  "type": "Feature",
  "properties": {
    "gn:admin1_code":"87.0",
    "gn:admin2_code":"3214.0",
    "gn:admin3_code":"321410.0",
    "gn:asciiname":"Grzedzice",
    "gn:country_code":"PL",
    "gn:dem":27,
    "gn:feature_class":"P",
    "gn:feature_code":"PPL",
    "gn:name":"Grz\u0119dzice",
    "gn:population":0,
    "gn:timezone":"Europe/Warsaw",
    "iso:country":"PL",
    "name:ceb_x_preferred":[
        "Grz\u0119dzice"
    ],
    "name:deu_x_preferred":[
        "Grz\u0119dzice"
    ],
    "name:pol_x_preferred":[
        "Grz\u0119dzice"
    ],
    "name:ukr_x_preferred":[
        "\u0490\u0436\u0435\u043d\u0434\u0437\u0456\u0446\u0435"
    ],
    "name:vie_x_preferred":[
        "Grz\u0119dzice"
    ],
    "wof:name":"Grzedzice",
    "wof:placetype":"locality"
},
  "geometry": {"coordinates":[14.97115,53.37221],"type":"Point"}
}