{
  "type": "Feature",
  "properties": {
    "gn:admin1_code":"78.0",
    "gn:admin2_code":"1412.0",
    "gn:admin3_code":"141205.0",
    "gn:asciiname":"Gorki",
    "gn:country_code":"PL",
    "gn:dem":116,
    "gn:feature_class":"P",
    "gn:feature_code":"PPL",
    "gn:name":"G\u00f3rki",
    "gn:population":0,
    "gn:timezone":"Europe/Warsaw",
    "iso:country":"PL",
    "wof:name":"Gorki",
    "wof:placetype":"locality"
},
  "geometry": {"coordinates":[21.41599,52.17738],"type":"Point"}
}