{
  "type": "Feature",
  "properties": {
    "gn:admin1_code":"80.0",
    "gn:admin2_code":"1812.0",
    "gn:admin3_code":"181201.0",
    "gn:asciiname":"Wolka",
    "gn:country_code":"PL",
    "gn:dem":183,
    "gn:feature_class":"P",
    "gn:feature_code":"PPL",
    "gn:name":"W\u00f3lka",
    "gn:population":0,
    "gn:timezone":"Europe/Warsaw",
    "iso:country":"PL",
    "wof:name":"Wolka",
    "wof:placetype":"locality"
},
  "geometry": {"coordinates":[22.41166,50.45654],"type":"Point"}
}