{
  "type": "Feature",
  "properties": {
    "gn:admin1_code":"82.0",
    "gn:admin2_code":"2215.0",
    "gn:admin3_code":"221505.0",
    "gn:asciiname":"Sluszewo",
    "gn:country_code":"PL",
    "gn:dem":35,
    "gn:feature_class":"P",
    "gn:feature_code":"PPL",
    "gn:name":"Sluszewo",
    "gn:population":0,
    "gn:timezone":"Europe/Warsaw",
    "iso:country":"PL",
    "name:pol_x_preferred":[
        "S\u0142uszewo"
    ],
    "name:ukr_x_preferred":[
        "\u0421\u043b\u0443\u0448\u0435\u0432\u043e"
    ],
    "wof:name":"Sluszewo",
    "wof:placetype":"locality"
},
  "geometry": {"coordinates":[18.06461,54.66202],"type":"Point"}
}