{
  "type": "Feature",
  "properties": {
    "gn:admin1_code":"74.0",
    "gn:admin2_code":"1007.0",
    "gn:admin3_code":"100707.0",
    "gn:asciiname":"Kunice",
    "gn:country_code":"PL",
    "gn:dem":193,
    "gn:feature_class":"P",
    "gn:feature_code":"PPL",
    "gn:name":"Kunice",
    "gn:population":448,
    "gn:timezone":"Europe/Warsaw",
    "iso:country":"PL",
    "name:ceb_x_preferred":[
        "Kunice"
    ],
    "name:fra_x_preferred":[
        "Kunice"
    ],
    "name:pol_x_preferred":[
        "Kunice"
    ],
    "name:ukr_x_preferred":[
        "\u041a\u0443\u043d\u0456\u0446\u0435"
    ],
    "wof:name":"Kunice",
    "wof:placetype":"locality",
    "wof:population":448
},
  "geometry": {"coordinates":[20.18575,51.40092],"type":"Point"}
}