{
  "type": "Feature",
  "properties": {
    "gn:admin1_code":"86.0",
    "gn:admin2_code":"3013.0",
    "gn:admin3_code":"301304.0",
    "gn:asciiname":"Moraczewo",
    "gn:country_code":"PL",
    "gn:dem":94,
    "gn:feature_class":"P",
    "gn:feature_code":"PPL",
    "gn:name":"Moraczewo",
    "gn:population":0,
    "gn:timezone":"Europe/Warsaw",
    "iso:country":"PL",
    "name:fra_x_preferred":[
        "Moraczewo"
    ],
    "name:pol_x_preferred":[
        "Moraczewo"
    ],
    "name:ukr_x_preferred":[
        "\u041c\u043e\u0440\u0430\u0447\u0435\u0432\u043e"
    ],
    "wof:name":"Moraczewo",
    "wof:placetype":"locality"
},
  "geometry": {"coordinates":[16.70016,51.77561],"type":"Point"}
}