{
  "type": "Feature",
  "properties": {
    "gn:admin1_code":"75.0",
    "gn:admin2_code":"617.0",
    "gn:admin3_code":"61702.0",
    "gn:asciiname":"Trzeciakow",
    "gn:country_code":"PL",
    "gn:dem":177,
    "gn:feature_class":"P",
    "gn:feature_code":"PPL",
    "gn:name":"Trzeciak\u00f3w",
    "gn:population":0,
    "gn:timezone":"Europe/Warsaw",
    "iso:country":"PL",
    "name:azb_x_preferred":[
        "\u0686\u06a9\u06cc\u0627\u06a9\u0648"
    ],
    "name:fas_x_preferred":[
        "\u0686\u06a9\u06cc\u0627\u06a9\u0648"
    ],
    "name:fra_x_preferred":[
        "Trzeciak\u00f3w"
    ],
    "name:pol_x_preferred":[
        "Trzeciak\u00f3w"
    ],
    "name:ukr_x_preferred":[
        "\u0422\u0448\u0435\u0446\u044f\u043a\u0443\u0432"
    ],
    "wof:name":"Trzeciakow",
    "wof:placetype":"locality"
},
  "geometry": {"coordinates":[22.80573,51.23355],"type":"Point"}
}