{
  "type": "Feature",
  "properties": {
    "gn:admin1_code":"85.0",
    "gn:admin2_code":"2802.0",
    "gn:admin3_code":"280202.0",
    "gn:asciiname":"Ulowo",
    "gn:country_code":"PL",
    "gn:dem":1,
    "gn:feature_class":"P",
    "gn:feature_code":"PPL",
    "gn:name":"U\u0142owo",
    "gn:population":0,
    "gn:timezone":"Europe/Warsaw",
    "iso:country":"PL",
    "name:ceb_x_preferred":[
        "U\u0142owo"
    ],
    "name:fra_x_preferred":[
        "U\u0142owo"
    ],
    "name:pol_x_preferred":[
        "U\u0142owo"
    ],
    "name:vie_x_preferred":[
        "U\u0142owo"
    ],
    "wof:name":"Ulowo",
    "wof:placetype":"locality"
},
  "geometry": {"coordinates":[19.78346,54.40005],"type":"Point"}
}