{
  "type": "Feature",
  "properties": {
    "gn:country":"PL",
    "gn:fcode":"PPL",
    "gn:population":510,
    "iso:country":"PL",
    "name:ast_x_preferred":[
        "Rybno"
    ],
    "name:ceb_x_preferred":[
        "Rybno"
    ],
    "name:csb_x_preferred":[
        "Ribno"
    ],
    "name:deu_x_preferred":[
        "Rybno"
    ],
    "name:eng_x_preferred":[
        "Rybno"
    ],
    "name:fra_x_preferred":[
        "Rybno"
    ],
    "name:pol_x_preferred":[
        "Rybno"
    ],
    "name:rus_x_preferred":[
        "\u0420\u044b\u0431\u043d\u043e"
    ],
    "name:ukr_x_preferred":[
        "\u0420\u0438\u0431\u043d\u043e"
    ],
    "name:und_x_variant":[
        "Rieben"
    ],
    "qs_pg:aaroncc":"PL",
    "qs_pg:gn_country":"PL",
    "qs_pg:gn_fcode":"PPL",
    "qs_pg:gn_pop":510,
    "qs_pg:name":"Rybno",
    "qs_pg:name_adm0":"Polska",
    "qs_pg:name_adm1":"Pomorskie",
    "qs_pg:photos_9r":0,
    "qs_pg:photos_sr":0,
    "qs_pg:pop_sr":2,
    "qs_pg:qs_pg_placetype":"locality",
    "qs_pg:qs_pg_placetype_gp":"Town",
    "qs_pg:woe_adm0":23424923,
    "woe:adm0_id":23424923,
    "woe:name_adm0":"Polska",
    "woe:name_adm1":"Pomorskie",
    "woe:placetype":"Town",
    "wof:name":"Rybno",
    "wof:placetype":"locality",
    "wof:population":510
},
  "geometry": {"coordinates":[18.08579,54.68377],"type":"Point"}
}