{
  "type": "Feature",
  "properties": {
    "gn:admin1_code":"77.0",
    "gn:admin2_code":"1205.0",
    "gn:admin3_code":"120503.0",
    "gn:asciiname":"Wilczyska",
    "gn:country_code":"PL",
    "gn:dem":289,
    "gn:feature_class":"P",
    "gn:feature_code":"PPL",
    "gn:name":"Wilczyska",
    "gn:population":0,
    "gn:timezone":"Europe/Warsaw",
    "iso:country":"PL",
    "name:ceb_x_preferred":[
        "Wilczyska"
    ],
    "name:pol_x_preferred":[
        "Wilczyska"
    ],
    "name:ukr_x_preferred":[
        "\u0412\u0456\u043b\u044c\u0447\u0438\u0441\u044c\u043a\u0430"
    ],
    "wof:name":"Wilczyska",
    "wof:placetype":"locality"
},
  "geometry": {"coordinates":[20.94326,49.67549],"type":"Point"}
}