{
  "type": "Feature",
  "properties": {
    "gn:admin1_code":"78.0",
    "gn:admin2_code":"1426.0",
    "gn:admin3_code":"142606.0",
    "gn:asciiname":"Nasilow",
    "gn:country_code":"PL",
    "gn:dem":174,
    "gn:feature_class":"P",
    "gn:feature_code":"PPL",
    "gn:name":"Nasi\u0142\u00f3w",
    "gn:population":0,
    "gn:timezone":"Europe/Warsaw",
    "iso:country":"PL",
    "name:fra_x_preferred":[
        "Nasi\u0142\u00f3w"
    ],
    "name:lit_x_preferred":[
        "Nasiluvas"
    ],
    "name:pol_x_preferred":[
        "Nasi\u0142\u00f3w"
    ],
    "name:szl_x_preferred":[
        "Nasi\u0142\u016fw"
    ],
    "name:ukr_x_preferred":[
        "\u041d\u0430\u0441\u0456\u043b\u0443\u0432"
    ],
    "wof:name":"Nasilow",
    "wof:placetype":"locality"
},
  "geometry": {"coordinates":[22.41769,52.30549],"type":"Point"}
}