{
  "type": "Feature",
  "properties": {
    "gn:admin1_code":"85.0",
    "gn:admin2_code":"2862.0",
    "gn:admin3_code":"286201.0",
    "gn:asciiname":"Podgrodzie",
    "gn:country_code":"PL",
    "gn:dem":110,
    "gn:feature_class":"P",
    "gn:feature_code":"PPL",
    "gn:name":"Podgrodzie",
    "gn:population":0,
    "gn:timezone":"Europe/Warsaw",
    "iso:country":"PL",
    "wof:name":"Podgrodzie",
    "wof:placetype":"neighbourhood"
},
  "geometry": {"coordinates":[20.47002,53.76751],"type":"Point"}
}