{
  "type": "Feature",
  "properties": {
    "gn:country":"PL",
    "gn:fcode":"PPL",
    "gn:population":400,
    "iso:country":"PL",
    "name:ast_x_preferred":[
        "Mszanowo"
    ],
    "name:ceb_x_preferred":[
        "Mszanowo"
    ],
    "name:ces_x_preferred":[
        "Mszanowo"
    ],
    "name:che_x_preferred":[
        "\u041c\u0448\u0430\u043d\u043e\u0432\u043e"
    ],
    "name:deu_x_preferred":[
        "Mszanowo"
    ],
    "name:eng_x_preferred":[
        "Mszanowo"
    ],
    "name:fra_x_preferred":[
        "Mszanowo"
    ],
    "name:nan_x_preferred":[
        "Mszanowo"
    ],
    "name:pol_x_preferred":[
        "Mszanowo"
    ],
    "name:tat_x_preferred":[
        "\u041c\u0448\u0430\u043d\u043e\u0432\u043e"
    ],
    "name:ukr_x_preferred":[
        "\u041c\u0448\u0430\u043d\u043e\u0432\u043e"
    ],
    "qs_pg:aaroncc":"PL",
    "qs_pg:gn_country":"PL",
    "qs_pg:gn_fcode":"PPL",
    "qs_pg:gn_pop":400,
    "qs_pg:name":"Mszanowo",
    "qs_pg:photos_9r":0,
    "qs_pg:photos_sr":0,
    "qs_pg:pop_sr":2,
    "qs_pg:qs_pg_placetype":"locality",
    "wof:name":"Mszanowo",
    "wof:placetype":"locality",
    "wof:population":400
},
  "geometry": {"coordinates":[19.60819,53.44216],"type":"Point"}
}