{
  "type": "Feature",
  "properties": {
    "gn:gn_country":"PL",
    "gn:gn_fcode":"PPL",
    "gn:gn_pop":400,
    "gn:population":400,
    "iso:country":"PL",
    "name:deu_x_preferred":[
        "Mszanowo"
    ],
    "name:eng_x_preferred":[
        "Mszanowo"
    ],
    "name:fra_x_preferred":[
        "Mszanowo"
    ],
    "name:pol_x_preferred":[
        "Mszanowo"
    ],
    "qs_pg:aaroncc":"PL",
    "qs_pg:gn_country":"PL",
    "qs_pg:gn_fcode":"PPL",
    "qs_pg:gn_pop":400,
    "qs_pg:name":"Mszanowo",
    "qs_pg:photos_9r":0,
    "qs_pg:photos_sr":0,
    "qs_pg:pop_sr":2,
    "qs_pg:qs_pg_placetype":"locality",
    "wof:name":"Mszanowo",
    "wof:placetype":"locality",
    "wof:population":400
},
  "geometry": {"coordinates":[19.60819,53.44216],"type":"Point"}
}