{
  "type": "Feature",
  "properties": {
    "gn:admin1_code":"82.0",
    "gn:admin2_code":"2214.0",
    "gn:admin3_code":"221405.0",
    "gn:asciiname":"Narkowy",
    "gn:country_code":"PL",
    "gn:dem":26,
    "gn:feature_class":"P",
    "gn:feature_code":"PPL",
    "gn:name":"Narkowy",
    "gn:population":0,
    "gn:timezone":"Europe/Warsaw",
    "iso:country":"PL",
    "name:ceb_x_preferred":[
        "Narkowy"
    ],
    "name:pol_x_preferred":[
        "Narkowy"
    ],
    "name:ukr_x_preferred":[
        "\u041d\u0430\u0440\u043a\u043e\u0432\u0438"
    ],
    "wof:name":"Narkowy",
    "wof:placetype":"locality"
},
  "geometry": {"coordinates":[18.78045,54.03347],"type":"Point"}
}