{
  "type": "Feature",
  "properties": {
    "iso:country":"PL",
    "name:azb_x_preferred":[
        "\u0642\u0645\u06cc\u0646\u0627 \u0698\u0648\u06a9\u0648\u0648\u0648"
    ],
    "name:bel_x_preferred":[
        "\u0416\u0443\u043a\u043e\u0432\u0430"
    ],
    "name:csb_x_preferred":[
        "Gmina \u017buk\u00f2w\u00f2"
    ],
    "name:deu_x_preferred":[
        "Gmina \u017bukowo"
    ],
    "name:eus_x_preferred":[
        "\u017bukowo udalerria"
    ],
    "name:fas_x_preferred":[
        "\u06af\u0645\u06cc\u0646\u0627 \u0698\u0648\u06a9\u0648\u0648\u0648"
    ],
    "name:fra_x_preferred":[
        "\u017bukowo"
    ],
    "name:ita_x_preferred":[
        "\u017bukowo"
    ],
    "name:nld_x_preferred":[
        "\u017bukowo"
    ],
    "name:pol_x_preferred":[
        "\u017bukowo"
    ],
    "name:rus_x_preferred":[
        "\u0416\u0443\u043a\u043e\u0432\u043e"
    ],
    "name:slk_x_preferred":[
        "Gmina \u017bukowo"
    ],
    "name:ukr_x_preferred":[
        "\u0413\u043c\u0456\u043d\u0430 \u0416\u0443\u043a\u043e\u0432\u043e"
    ],
    "name:war_x_preferred":[
        "Gmina \u017bukowo"
    ],
    "qs_pg:aaroncc":"PL",
    "qs_pg:name":"Gmina \u017bukowo",
    "qs_pg:name_adm0":"Polska",
    "qs_pg:name_adm1":"Pomorskie",
    "qs_pg:photos":177,
    "qs_pg:photos_1k":36,
    "qs_pg:photos_9k":4,
    "qs_pg:photos_9r":6,
    "qs_pg:photos_all":973,
    "qs_pg:photos_sr":4,
    "qs_pg:pop_sr":0,
    "qs_pg:qs_pg_placetype":"localadmin",
    "qs_pg:qs_pg_placetype_gp":"LocalAdmin",
    "qs_pg:woe_adm0":23424923,
    "woe:adm0_id":23424923,
    "woe:name_adm0":"Polska",
    "woe:name_adm1":"Pomorskie",
    "woe:placetype":"LocalAdmin",
    "wof:name":"Gmina \u017bukowo",
    "wof:placetype":"localadmin"
},
  "geometry": {"coordinates":[18.441966,54.390005],"type":"Point"}
}