{
  "type": "Feature",
  "properties": {
    "gn:admin1_code":"87.0",
    "gn:admin2_code":"3215.0",
    "gn:admin3_code":"321502.0",
    "gn:asciiname":"Stary Chwalim",
    "gn:country_code":"PL",
    "gn:dem":91,
    "gn:feature_class":"P",
    "gn:feature_code":"PPL",
    "gn:name":"Stary Chwalim",
    "gn:population":0,
    "gn:timezone":"Europe/Warsaw",
    "iso:country":"PL",
    "name:pol_x_preferred":[
        "Stary Chwalim"
    ],
    "name:ukr_x_preferred":[
        "\u0421\u0442\u0430\u0440\u0438\u0439 \u0425\u0432\u0430\u043b\u0456\u043c"
    ],
    "name:vie_x_preferred":[
        "Stary Chwalim"
    ],
    "wof:name":"Stary Chwalim",
    "wof:placetype":"locality"
},
  "geometry": {"coordinates":[16.40913,53.77551999999999],"type":"Point"}
}