{
  "type": "Feature",
  "properties": {
    "gn:admin1_code":"82.0",
    "gn:admin2_code":"2203.0",
    "gn:admin3_code":"220307.0",
    "gn:asciiname":"Pienieznica",
    "gn:country_code":"PL",
    "gn:dem":153,
    "gn:feature_class":"P",
    "gn:feature_code":"PPL",
    "gn:name":"Pieni\u0119\u017cnica",
    "gn:population":0,
    "gn:timezone":"Europe/Warsaw",
    "iso:country":"PL",
    "name:und_x_variant":[
        "Penkuhl",
        "Pieni\u0119\u017cnica"
    ],
    "wof:name":"Pienieznica",
    "wof:placetype":"locality"
},
  "geometry": {"coordinates":[16.96231,53.85763000000001],"type":"Point"}
}