{
  "type": "Feature",
  "properties": {
    "gn:admin1_code":"78.0",
    "gn:admin2_code":"1403.0",
    "gn:admin3_code":"140306.0",
    "gn:asciiname":"Kacprowek",
    "gn:country_code":"PL",
    "gn:dem":146,
    "gn:feature_class":"P",
    "gn:feature_code":"PPL",
    "gn:name":"Kacpr\u00f3wek",
    "gn:population":0,
    "gn:timezone":"Europe/Warsaw",
    "iso:country":"PL",
    "name:azb_x_preferred":[
        "\u06a9\u0627\u062a\u0633\u067e\u0631\u0648\u0648\u06a9"
    ],
    "name:fas_x_preferred":[
        "\u06a9\u0627\u062a\u0633\u067e\u0631\u0648\u0648\u06a9"
    ],
    "name:fra_x_preferred":[
        "Kacpr\u00f3wek"
    ],
    "name:pol_x_preferred":[
        "Kacpr\u00f3wek"
    ],
    "name:spa_x_preferred":[
        "Kacpr\u00f3wek"
    ],
    "name:ukr_x_preferred":[
        "\u041a\u0430\u0446\u043f\u0440\u0443\u0432\u0435\u043a"
    ],
    "wof:name":"Kacprowek",
    "wof:placetype":"locality"
},
  "geometry": {"coordinates":[21.64664,51.80422],"type":"Point"}
}