{
  "type": "Feature",
  "properties": {
    "gn:admin1_code":"84.0",
    "gn:admin2_code":"2606.0",
    "gn:admin3_code":"260601.0",
    "gn:asciiname":"Nieskurzow Stary",
    "gn:country_code":"PL",
    "gn:dem":332,
    "gn:feature_class":"P",
    "gn:feature_code":"PPL",
    "gn:name":"Nieskurz\u00f3w Stary",
    "gn:population":0,
    "gn:timezone":"Europe/Warsaw",
    "iso:country":"PL",
    "name:ceb_x_preferred":[
        "Nieskurz\u00f3w Stary"
    ],
    "name:pol_x_preferred":[
        "Nieskurz\u00f3w Stary"
    ],
    "name:ukr_x_preferred":[
        "\u041d\u0435\u0441\u043a\u0443\u0436\u0443\u0432-\u0421\u0442\u0430\u0440\u0438\u0439"
    ],
    "wof:name":"Nieskurzow Stary",
    "wof:placetype":"locality"
},
  "geometry": {"coordinates":[21.20362,50.80544],"type":"Point"}
}