{
  "type": "Feature",
  "properties": {
    "gn:admin1_code":"83.0",
    "gn:admin2_code":"2412.0",
    "gn:admin3_code":"241202.0",
    "gn:asciiname":"Lukow",
    "gn:country_code":"PL",
    "gn:dem":237,
    "gn:feature_class":"P",
    "gn:feature_code":"PPL",
    "gn:name":"\u0141uk\u00f3w",
    "gn:population":0,
    "gn:timezone":"Europe/Warsaw",
    "iso:country":"PL",
    "name:ceb_x_preferred":[
        "\u0141uk\u00f3w"
    ],
    "name:pol_x_preferred":[
        "\u0141uk\u00f3w \u015al\u0105ski"
    ],
    "name:ukr_x_preferred":[
        "\u041b\u0443\u043a\u0443\u0432-\u0428\u043b\u044c\u043e\u043d\u0441\u044c\u043a\u0438\u0439"
    ],
    "wof:name":"Lukow",
    "wof:placetype":"locality"
},
  "geometry": {"coordinates":[18.40132,50.09452],"type":"Point"}
}