{
  "type": "Feature",
  "properties": {
    "gn:admin1_code":"86.0",
    "gn:admin2_code":"3026.0",
    "gn:admin3_code":"302603.0",
    "gn:asciiname":"Kolacin",
    "gn:country_code":"PL",
    "gn:dem":96,
    "gn:feature_class":"P",
    "gn:feature_code":"PPL",
    "gn:name":"K\u00f3\u0142acin",
    "gn:population":0,
    "gn:timezone":"Europe/Warsaw",
    "iso:country":"PL",
    "name:und_x_variant":[
        "K\u00f3\u0142acin"
    ],
    "wof:name":"Kolacin",
    "wof:placetype":"locality"
},
  "geometry": {"coordinates":[17.26553,52.00629],"type":"Point"}
}