{
  "type": "Feature",
  "properties": {
    "gn:admin1_code":"86.0",
    "gn:admin2_code":"3026.0",
    "gn:admin3_code":"302603.0",
    "gn:asciiname":"Kolacin",
    "gn:country_code":"PL",
    "gn:dem":96,
    "gn:feature_class":"P",
    "gn:feature_code":"PPL",
    "gn:name":"K\u00f3\u0142acin",
    "gn:population":0,
    "gn:timezone":"Europe/Warsaw",
    "iso:country":"PL",
    "name:azb_x_preferred":[
        "\u06a9\u0648\u0648\u0627\u0686\u06cc\u0646"
    ],
    "name:deu_x_preferred":[
        "Ko\u0142acin"
    ],
    "name:fas_x_preferred":[
        "\u06a9\u0648\u0648\u0627\u0686\u06cc\u0646"
    ],
    "name:fra_x_preferred":[
        "Ko\u0142acin"
    ],
    "name:pol_x_preferred":[
        "Ko\u0142acin"
    ],
    "name:ukr_x_preferred":[
        "\u041a\u043e\u043b\u0430\u0446\u0438\u043d"
    ],
    "name:und_x_variant":[
        "K\u00f3\u0142acin"
    ],
    "wof:name":"Kolacin",
    "wof:placetype":"locality"
},
  "geometry": {"coordinates":[17.26553,52.00629],"type":"Point"}
}