{
  "type": "Feature",
  "properties": {
    "iso:country":"PL",
    "qs_pg:aaroncc":"PL",
    "qs_pg:name":"Gmina Oborniki \u015al\u0105skie",
    "qs_pg:name_adm0":"Polska",
    "qs_pg:name_adm1":"Dolnosl\u0105skie",
    "qs_pg:photos":6,
    "qs_pg:photos_1k":1,
    "qs_pg:photos_9k":1,
    "qs_pg:photos_9r":4,
    "qs_pg:photos_all":271,
    "qs_pg:photos_sr":1,
    "qs_pg:pop_sr":0,
    "qs_pg:qs_pg_placetype":"localadmin",
    "qs_pg:qs_pg_placetype_gp":"LocalAdmin",
    "qs_pg:woe_adm0":23424923,
    "woe:adm0_id":23424923,
    "woe:name_adm0":"Polska",
    "woe:name_adm1":"Dolnosl\u0105skie",
    "woe:placetype":"LocalAdmin",
    "wof:name":"Gmina Oborniki \u015al\u0105skie",
    "wof:placetype":"localadmin"
},
  "geometry": {"coordinates":[16.835732,51.353572],"type":"Point"}
}