{
  "type": "Feature",
  "properties": {
    "iso:country":"PL",
    "name:azb_x_preferred":[
        "\u0642\u0645\u06cc\u0646\u0627 \u0627\u0648\u0628\u0648\u0631\u0646\u0642\u06a9\u06cc \u0634\u0644\u0627\u0646\u0633\u06a9\u06cc\u0647"
    ],
    "name:bel_x_preferred":[
        "\u0410\u0431\u0430\u0440\u043d\u0456\u043a\u0456 \u0421\u043b\u0451\u043d\u0441\u043a\u0435"
    ],
    "name:deu_x_preferred":[
        "Gmina Oborniki \u015al\u0105skie"
    ],
    "name:eus_x_preferred":[
        "Oborniki \u015al\u0105skie udalerria"
    ],
    "name:fas_x_preferred":[
        "\u06af\u0645\u06cc\u0646\u0627 \u0627\u0648\u0628\u0648\u0631\u0646\u06af\u06a9\u06cc \u0634\u0644\u0627\u0646\u0633\u06a9\u06cc\u0647"
    ],
    "name:fra_x_preferred":[
        "Oborniki \u015al\u0105skie"
    ],
    "name:ita_x_preferred":[
        "Oborniki \u015al\u0105skie"
    ],
    "name:nld_x_preferred":[
        "Oborniki \u015al\u0105skie"
    ],
    "name:pol_x_preferred":[
        "Oborniki \u015al\u0105skie"
    ],
    "name:rus_x_preferred":[
        "\u041e\u0431\u043e\u0440\u043d\u0438\u043a\u0438-\u0421\u043b\u0451\u043d\u0441\u043a\u0435"
    ],
    "name:slk_x_preferred":[
        "Gmina Oborniki \u015al\u0105skie"
    ],
    "name:ukr_x_preferred":[
        "\u0413\u043c\u0456\u043d\u0430 \u041e\u0431\u043e\u0440\u043d\u0438\u043a\u0438-\u0428\u043b\u044c\u043e\u043d\u0441\u044c\u043a\u0456"
    ],
    "name:war_x_preferred":[
        "Gmina Oborniki \u015al\u0105skie"
    ],
    "qs_pg:aaroncc":"PL",
    "qs_pg:name":"Gmina Oborniki \u015al\u0105skie",
    "qs_pg:name_adm0":"Polska",
    "qs_pg:name_adm1":"Dolnosl\u0105skie",
    "qs_pg:photos":6,
    "qs_pg:photos_1k":1,
    "qs_pg:photos_9k":1,
    "qs_pg:photos_9r":4,
    "qs_pg:photos_all":271,
    "qs_pg:photos_sr":1,
    "qs_pg:pop_sr":0,
    "qs_pg:qs_pg_placetype":"localadmin",
    "qs_pg:qs_pg_placetype_gp":"LocalAdmin",
    "qs_pg:woe_adm0":23424923,
    "woe:adm0_id":23424923,
    "woe:name_adm0":"Polska",
    "woe:name_adm1":"Dolnosl\u0105skie",
    "woe:placetype":"LocalAdmin",
    "wof:name":"Gmina Oborniki \u015al\u0105skie",
    "wof:placetype":"localadmin"
},
  "geometry": {"coordinates":[16.835732,51.353572],"type":"Point"}
}