{
  "type": "Feature",
  "properties": {
    "gn:admin1_code":"73.0",
    "gn:admin2_code":"415.0",
    "gn:admin3_code":"41505.0",
    "gn:asciiname":"Brachnowo",
    "gn:country_code":"PL",
    "gn:dem":88,
    "gn:feature_class":"P",
    "gn:feature_code":"PPL",
    "gn:name":"Br\u0105chnowo",
    "gn:population":0,
    "gn:timezone":"Europe/Warsaw",
    "iso:country":"PL",
    "name:azb_x_preferred":[
        "\u0628\u0631\u0627\u0646\u062e\u0646\u0648\u0648\u0648"
    ],
    "name:ceb_x_preferred":[
        "Br\u0105chnowo"
    ],
    "name:fas_x_preferred":[
        "\u0628\u0631\u0627\u0646\u062e\u0646\u0648\u0648\u0648"
    ],
    "name:nld_x_preferred":[
        "Br\u0105chnowo"
    ],
    "name:pol_x_preferred":[
        "Br\u0105chnowo"
    ],
    "name:rus_x_preferred":[
        "\u0411\u0440\u043e\u043d\u0445\u043d\u043e\u0432\u043e"
    ],
    "name:ukr_x_preferred":[
        "\u0411\u0440\u043e\u043d\u0445\u043d\u043e\u0432\u043e"
    ],
    "wof:name":"Brachnowo",
    "wof:placetype":"locality"
},
  "geometry": {"coordinates":[18.54014,53.13824],"type":"Point"}
}