{
  "type": "Feature",
  "properties": {
    "gn:admin1_code":"72",
    "gn:admin2_code":"0207",
    "gn:admin3_code":"20704.0",
    "gn:asciiname":"Przybkowice",
    "gn:country_code":"PL",
    "gn:dem":463,
    "gn:feature_class":"P",
    "gn:feature_code":"PPL",
    "gn:name":"Przybkowice",
    "gn:population":0,
    "gn:timezone":"Europe/Warsaw",
    "iso:country":"PL",
    "name:deu_x_historical":[
        "Prittwitzdorf"
    ],
    "name:deu_x_preferred":[
        "Prittwitzdorf"
    ],
    "name:pol_x_preferred":[
        "Przybkowice"
    ],
    "wof:name":"Przybkowice",
    "wof:placetype":"locality"
},
  "geometry": {"coordinates":[15.97601,50.8563],"type":"Point"}
}