{
  "type": "Feature",
  "properties": {
    "iso:country":"PL",
    "name:ceb_x_preferred":[
        "Jan\u00f3w"
    ],
    "name:ces_x_preferred":[
        "Jan\u00f3w"
    ],
    "name:deu_x_preferred":[
        "Jan\u00f3w"
    ],
    "name:fra_x_preferred":[
        "Jan\u00f3w"
    ],
    "name:hsb_x_preferred":[
        "Jan\u00f3w"
    ],
    "name:ita_x_preferred":[
        "Jan\u00f3w"
    ],
    "name:nld_x_preferred":[
        "Jan\u00f3w"
    ],
    "name:pol_x_colloquial":[
        "Janow"
    ],
    "name:pol_x_preferred":[
        "Jan\u00f3w"
    ],
    "name:rus_x_preferred":[
        "\u042f\u043d\u0443\u0432"
    ],
    "name:swe_x_preferred":[
        "Jan\u00f3w"
    ],
    "name:ukr_x_preferred":[
        "\u042f\u043d\u0443\u0432"
    ],
    "qs:gn_adm0_cc":"PL",
    "qs:gn_local":758343,
    "qs:gn_nam_loc":"stare babice",
    "qs:gn_namadm1":"78",
    "qs:local_max":55,
    "qs:local_sum":100,
    "qs:localhoods":3,
    "qs:name":"Jan\u00f3w",
    "qs:name_adm0":"Polska",
    "qs:name_adm1":"Mazowieckie",
    "qs:name_adm2":"Warszawski Zachodni",
    "qs:name_lau":"Stare Babice",
    "qs:name_local":"Stare Babice",
    "qs:photo_max":6,
    "qs:photo_sum":28,
    "qs:placetype":"Suburb",
    "qs:quad_count":13,
    "qs:woe_adm0":23424923,
    "qs:woe_adm1":12577941,
    "qs:woe_adm2":12591305,
    "qs:woe_lau":12616994,
    "qs:woe_local":12616994,
    "qs:woe_ver":"7.10.0",
    "wd:wordcount":429,
    "wof:lang":[
        "pol"
    ],
    "wof:name":"Jan\u00f3w",
    "wof:placetype":"neighbourhood"
},
  "geometry": {"coordinates":[20.869193,52.263114],"type":"Point"}
}