{
  "type": "Feature",
  "properties": {
    "gn:admin1_code":"74.0",
    "gn:admin2_code":"1017.0",
    "gn:admin3_code":"101702.0",
    "gn:asciiname":"Lagiewniki",
    "gn:country_code":"PL",
    "gn:dem":183,
    "gn:feature_class":"P",
    "gn:feature_code":"PPL",
    "gn:name":"\u0141agiewniki",
    "gn:population":0,
    "gn:timezone":"Europe/Warsaw",
    "iso:country":"PL",
    "wof:name":"Lagiewniki",
    "wof:placetype":"locality"
},
  "geometry": {"coordinates":[18.51118,51.27522],"type":"Point"}
}