{
  "type": "Feature",
  "properties": {
    "gn:admin1_code":"83.0",
    "gn:admin2_code":"2416.0",
    "gn:admin3_code":"241601.0",
    "gn:asciiname":"Krawce",
    "gn:country_code":"PL",
    "gn:dem":324,
    "gn:feature_class":"P",
    "gn:feature_code":"PPL",
    "gn:name":"Krawce",
    "gn:population":0,
    "gn:timezone":"Europe/Warsaw",
    "iso:country":"PL",
    "name:pol_x_preferred":[
        "Krawce"
    ],
    "name:ukr_x_preferred":[
        "\u041a\u0440\u0430\u0432\u0446\u0435"
    ],
    "wof:name":"Krawce",
    "wof:placetype":"locality"
},
  "geometry": {"coordinates":[19.31467,50.50613],"type":"Point"}
}