{
  "type": "Feature",
  "properties": {
    "gn:admin1_code":"86.0",
    "gn:admin2_code":"3026.0",
    "gn:admin3_code":"302601.0",
    "gn:asciiname":"Sulejewo",
    "gn:country_code":"PL",
    "gn:dem":76,
    "gn:feature_class":"P",
    "gn:feature_code":"PPL",
    "gn:name":"Sulejewo",
    "gn:population":0,
    "gn:timezone":"Europe/Warsaw",
    "iso:country":"PL",
    "wof:name":"Sulejewo",
    "wof:placetype":"locality"
},
  "geometry": {"coordinates":[16.88787,52.15487],"type":"Point"}
}