{
  "type": "Feature",
  "properties": {
    "gn:admin1_code":"77.0",
    "gn:asciiname":"Silna Nowa",
    "gn:country_code":"PL",
    "gn:dem":68,
    "gn:feature_class":"P",
    "gn:feature_code":"PPL",
    "gn:name":"Silna Nowa",
    "gn:population":0,
    "gn:timezone":"Europe/Warsaw",
    "iso:country":"PL",
    "wof:name":"Silna Nowa",
    "wof:placetype":"locality"
},
  "geometry": {"coordinates":[15.88239,52.43416],"type":"Point"}
}