{
  "type": "Feature",
  "properties": {
    "gn:admin1_code":"77.0",
    "gn:asciiname":"Silna Nowa",
    "gn:country_code":"PL",
    "gn:dem":68,
    "gn:feature_class":"P",
    "gn:feature_code":"PPL",
    "gn:name":"Silna Nowa",
    "gn:population":0,
    "gn:timezone":"Europe/Warsaw",
    "iso:country":"PL",
    "name:fra_x_preferred":[
        "Nowa Silna"
    ],
    "name:pol_x_preferred":[
        "Silna Nowa"
    ],
    "name:ukr_x_preferred":[
        "\u0421\u0456\u043b\u044c\u043d\u0430-\u041d\u043e\u0432\u0430"
    ],
    "wof:name":"Silna Nowa",
    "wof:placetype":"locality"
},
  "geometry": {"coordinates":[15.88239,52.43416],"type":"Point"}
}