{
  "type": "Feature",
  "properties": {
    "gn:admin1_code":"85.0",
    "gn:admin2_code":"2809.0",
    "gn:admin3_code":"280902.0",
    "gn:asciiname":"Krekole",
    "gn:country_code":"PL",
    "gn:dem":90,
    "gn:feature_class":"P",
    "gn:feature_code":"PPL",
    "gn:name":"Krekole",
    "gn:population":0,
    "gn:timezone":"Europe/Warsaw",
    "iso:country":"PL",
    "name:fra_x_preferred":[
        "Krekole"
    ],
    "name:pol_x_preferred":[
        "Krekole"
    ],
    "name:ukr_x_preferred":[
        "\u041a\u0440\u0435\u043a\u043e\u043b\u0435"
    ],
    "name:und_x_variant":[
        "Krekollen"
    ],
    "wof:name":"Krekole",
    "wof:placetype":"locality"
},
  "geometry": {"coordinates":[20.75268,54.17943],"type":"Point"}
}