{
  "type": "Feature",
  "properties": {
    "gn:admin1_code":"74.0",
    "gn:admin2_code":"1019.0",
    "gn:admin3_code":"101902.0",
    "gn:asciiname":"Tarnowka",
    "gn:country_code":"PL",
    "gn:dem":159,
    "gn:feature_class":"P",
    "gn:feature_code":"PPL",
    "gn:name":"Tarn\u00f3wka",
    "gn:population":0,
    "gn:timezone":"Europe/Warsaw",
    "iso:country":"PL",
    "name:pol_x_preferred":[
        "Tarn\u00f3wka"
    ],
    "name:ukr_x_preferred":[
        "\u0422\u0430\u0440\u043d\u0443\u0432\u043a\u0430"
    ],
    "wof:name":"Tarnowka",
    "wof:placetype":"locality"
},
  "geometry": {"coordinates":[19.03158,51.70879],"type":"Point"}
}