{
  "type": "Feature",
  "properties": {
    "gn:admin1_code":"72.0",
    "gn:admin2_code":"208.0",
    "gn:admin3_code":"20808.0",
    "gn:asciiname":"Skowronki",
    "gn:country_code":"PL",
    "gn:dem":429,
    "gn:feature_class":"P",
    "gn:feature_code":"PPL",
    "gn:name":"Skowronki",
    "gn:population":0,
    "gn:timezone":"Europe/Warsaw",
    "iso:country":"PL",
    "wof:name":"Skowronki",
    "wof:placetype":"locality"
},
  "geometry": {"coordinates":[16.83234,50.33902],"type":"Point"}
}