{
  "type": "Feature",
  "properties": {
    "gn:admin1_code":"79.0",
    "gn:admin2_code":"1608.0",
    "gn:admin3_code":"160803.0",
    "gn:asciiname":"Kucoby",
    "gn:country_code":"PL",
    "gn:dem":231,
    "gn:feature_class":"P",
    "gn:feature_code":"PPL",
    "gn:name":"Kucoby",
    "gn:population":0,
    "gn:timezone":"Europe/Warsaw",
    "iso:country":"PL",
    "name:pol_x_preferred":[
        "Kucoby"
    ],
    "name:rus_x_preferred":[
        "\u041a\u0443\u0446\u043e\u0431\u044b"
    ],
    "name:ukr_x_preferred":[
        "\u041a\u0443\u0446\u043e\u0431\u0438"
    ],
    "wof:name":"Kucoby",
    "wof:placetype":"locality"
},
  "geometry": {"coordinates":[18.62114,50.87726],"type":"Point"}
}