{
  "type": "Feature",
  "properties": {
    "gn:admin1_code":"78.0",
    "gn:admin2_code":"1411.0",
    "gn:admin3_code":"141104.0",
    "gn:asciiname":"Chlopia Laka",
    "gn:country_code":"PL",
    "gn:dem":106,
    "gn:feature_class":"P",
    "gn:feature_code":"PPL",
    "gn:name":"Ch\u0142opia \u0141\u0105ka",
    "gn:population":0,
    "gn:timezone":"Europe/Warsaw",
    "iso:country":"PL",
    "name:fra_x_preferred":[
        "Ch\u0142opia \u0141\u0105ka"
    ],
    "name:pol_x_preferred":[
        "Ch\u0142opia \u0141\u0105ka"
    ],
    "name:ukr_x_preferred":[
        "\u0425\u043b\u043e\u043f\u044f-\u041b\u043e\u043d\u043a\u0430"
    ],
    "wof:name":"Chlopia Laka",
    "wof:placetype":"locality"
},
  "geometry": {"coordinates":[21.18825,53.04502],"type":"Point"}
}