{
  "type": "Feature",
  "properties": {
    "gn:admin1_code":"86.0",
    "gn:admin2_code":"3003.0",
    "gn:admin3_code":"300306.0",
    "gn:asciiname":"Imielenko",
    "gn:country_code":"PL",
    "gn:dem":117,
    "gn:feature_class":"P",
    "gn:feature_code":"PPL",
    "gn:name":"Imielenko",
    "gn:population":0,
    "gn:timezone":"Europe/Warsaw",
    "iso:country":"PL",
    "name:fra_x_preferred":[
        "Imielenko"
    ],
    "name:pol_x_preferred":[
        "Imielenko"
    ],
    "name:ukr_x_preferred":[
        "\u0406\u043c\u0435\u043b\u0435\u043d\u043a\u043e"
    ],
    "wof:name":"Imielenko",
    "wof:placetype":"locality"
},
  "geometry": {"coordinates":[17.37924,52.48885],"type":"Point"}
}