{
  "type": "Feature",
  "properties": {
    "gn:admin1_code":"85.0",
    "gn:admin2_code":"2818.0",
    "gn:admin3_code":"281802.0",
    "gn:asciiname":"Bludzie Male",
    "gn:country_code":"PL",
    "gn:dem":187,
    "gn:feature_class":"P",
    "gn:feature_code":"PPL",
    "gn:name":"Bludzie Ma\u0142e",
    "gn:population":0,
    "gn:timezone":"Europe/Warsaw",
    "iso:country":"PL",
    "name:azb_x_preferred":[
        "\u0628\u0644\u0648\u062c\u0647 \u0645\u0627\u0648\u0647"
    ],
    "name:deu_x_preferred":[
        "Bludzie Ma\u0142e"
    ],
    "name:fas_x_preferred":[
        "\u0628\u0644\u0648\u062c\u0647 \u0645\u0627\u0648\u0647"
    ],
    "name:nld_x_preferred":[
        "Bludzie Ma\u0142e"
    ],
    "name:pol_x_preferred":[
        "Bludzie Ma\u0142e"
    ],
    "name:ukr_x_preferred":[
        "\u0411\u043b\u044e\u0434\u0437\u0435-\u041c\u0430\u043b\u0435"
    ],
    "name:und_x_variant":[
        "Kleinforsthausen",
        "Klein Bludszen",
        "Klein Bludschen"
    ],
    "wof:name":"Bludzie Male",
    "wof:placetype":"locality"
},
  "geometry": {"coordinates":[22.57982,54.31001],"type":"Point"}
}