{
  "type": "Feature",
  "properties": {
    "gn:admin1_code":"85.0",
    "gn:admin2_code":"2818.0",
    "gn:admin3_code":"281802.0",
    "gn:asciiname":"Bludzie Male",
    "gn:country_code":"PL",
    "gn:dem":187,
    "gn:feature_class":"P",
    "gn:feature_code":"PPL",
    "gn:name":"Bludzie Ma\u0142e",
    "gn:population":0,
    "gn:timezone":"Europe/Warsaw",
    "iso:country":"PL",
    "name:und_x_variant":[
        "Kleinforsthausen",
        "Klein Bludszen",
        "Klein Bludschen",
        "Bludzie Ma\u0142e"
    ],
    "wof:name":"Bludzie Male",
    "wof:placetype":"locality"
},
  "geometry": {"coordinates":[22.57982,54.31001],"type":"Point"}
}