{
  "type": "Feature",
  "properties": {
    "gn:gn_country":"PL",
    "gn:gn_fcode":"PPLA3",
    "gn:gn_pop":16250,
    "gn:population":16250,
    "iso:country":"PL",
    "name:bul_x_preferred":[
        "\u0423\u0441\u0442\u043a\u0430"
    ],
    "name:ces_x_preferred":[
        "Ustka"
    ],
    "name:csb_x_preferred":[
        "\u00d9sk\u00f4"
    ],
    "name:dan_x_preferred":[
        "Ustka"
    ],
    "name:deu_x_preferred":[
        "Ustka"
    ],
    "name:eng_x_preferred":[
        "Ustka"
    ],
    "name:fra_x_preferred":[
        "Ustka"
    ],
    "name:hrv_x_preferred":[
        "Ustka"
    ],
    "name:ind_x_preferred":[
        "Ustka"
    ],
    "name:ita_x_preferred":[
        "Ustka"
    ],
    "name:jav_x_preferred":[
        "Ustka"
    ],
    "name:jpn_x_preferred":[
        "\u30a6\u30b9\u30c8\u30ab"
    ],
    "name:kor_x_preferred":[
        "\uc6b0\uc2a4\ud2b8\uce74"
    ],
    "name:nld_x_preferred":[
        "Ustka"
    ],
    "name:pol_x_preferred":[
        "Ustka"
    ],
    "name:ron_x_preferred":[
        "Ustka"
    ],
    "name:rus_x_preferred":[
        "\u0423\u0441\u0442\u043a\u0430"
    ],
    "name:spa_x_preferred":[
        "Ustka"
    ],
    "name:srp_x_preferred":[
        "\u0423\u0441\u0442\u043a\u0430"
    ],
    "name:swe_x_preferred":[
        "Ustka"
    ],
    "name:ukr_x_preferred":[
        "\u0423\u0441\u0442\u043a\u0430"
    ],
    "name:unk_x_variant":[
        "Stolpm\u00fcnde"
    ],
    "name:zho_x_preferred":[
        "\u4e4c\u65af\u7279\u5361"
    ],
    "qs_pg:aaroncc":"PL",
    "qs_pg:gn_country":"PL",
    "qs_pg:gn_fcode":"PPLA3",
    "qs_pg:gn_pop":16250,
    "qs_pg:name":"Ustka",
    "qs_pg:name_adm0":"Polska",
    "qs_pg:name_adm1":"Pomorskie",
    "qs_pg:photos":192,
    "qs_pg:photos_1k":39,
    "qs_pg:photos_9k":1,
    "qs_pg:photos_9r":4,
    "qs_pg:photos_all":192,
    "qs_pg:photos_sr":4,
    "qs_pg:pop_sr":6,
    "qs_pg:qs_pg_placetype":"localadmin",
    "qs_pg:qs_pg_placetype_gp":"LocalAdmin",
    "qs_pg:woe_adm0":23424923,
    "woe:adm0_id":23424923,
    "woe:name_adm0":"Polska",
    "woe:name_adm1":"Pomorskie",
    "woe:placetype":"LocalAdmin",
    "wof:name":"Ustka",
    "wof:placetype":"localadmin",
    "wof:population":16250
},
  "geometry": {"coordinates":[16.86194,54.58048],"type":"Point"}
}