{
  "type": "Feature",
  "properties": {
    "gn:admin1_code":"78.0",
    "gn:admin2_code":"1415.0",
    "gn:admin3_code":"141506.0",
    "gn:asciiname":"Aleksandrowo",
    "gn:country_code":"PL",
    "gn:dem":110,
    "gn:feature_class":"P",
    "gn:feature_code":"PPL",
    "gn:name":"Aleksandrowo",
    "gn:population":0,
    "gn:timezone":"Europe/Warsaw",
    "iso:country":"PL",
    "name:deu_x_preferred":[
        "Aleksandrowo"
    ],
    "name:fra_x_preferred":[
        "Aleksandrowo"
    ],
    "name:lit_x_preferred":[
        "Aleksandrovas"
    ],
    "name:pol_x_preferred":[
        "Aleksandrowo"
    ],
    "wof:name":"Aleksandrowo",
    "wof:placetype":"locality"
},
  "geometry": {"coordinates":[21.41782000000001,53.16792],"type":"Point"}
}