{
  "type": "Feature",
  "properties": {
    "gn:admin1_code":"72.0",
    "gn:admin2_code":"225.0",
    "gn:admin3_code":"22503.0",
    "gn:asciiname":"Zatonie",
    "gn:cc2":"PL",
    "gn:country_code":"PL",
    "gn:dem":256,
    "gn:feature_class":"P",
    "gn:feature_code":"PPL",
    "gn:name":"Zatonie",
    "gn:population":0,
    "gn:timezone":"Europe/Warsaw",
    "iso:country":"PL",
    "name:ceb_x_preferred":[
        "Zatonie"
    ],
    "name:deu_x_historical":[
        "Seitendorf"
    ],
    "name:deu_x_preferred":[
        "Seitendorf"
    ],
    "name:fra_x_preferred":[
        "Zatonie"
    ],
    "name:nld_x_preferred":[
        "Zatonie"
    ],
    "name:pol_x_preferred":[
        "Zatonie"
    ],
    "wof:name":"Zatonie",
    "wof:placetype":"locality"
},
  "geometry": {"coordinates":[14.93776,50.94615],"type":"Point"}
}