{
  "type": "Feature",
  "properties": {
    "gn:admin1_code":"86.0",
    "gn:admin2_code":"3028.0",
    "gn:admin3_code":"302804.0",
    "gn:asciiname":"Golka",
    "gn:country_code":"PL",
    "gn:dem":111,
    "gn:feature_class":"P",
    "gn:feature_code":"PPL",
    "gn:name":"Go\u0142ka",
    "gn:population":0,
    "gn:timezone":"Europe/Warsaw",
    "iso:country":"PL",
    "name:pol_x_preferred":[
        "G\u00f3\u0142ka"
    ],
    "name:und_x_variant":[
        "Go\u0142ka"
    ],
    "wof:name":"Golka",
    "wof:placetype":"locality"
},
  "geometry": {"coordinates":[17.42515,52.718],"type":"Point"}
}