{
  "type": "Feature",
  "properties": {
    "gn:admin1_code":"86.0",
    "gn:admin2_code":"3028.0",
    "gn:admin3_code":"302805.0",
    "gn:asciiname":"Blizyce",
    "gn:country_code":"PL",
    "gn:dem":105,
    "gn:feature_class":"P",
    "gn:feature_code":"PPL",
    "gn:name":"Bli\u017cyce",
    "gn:population":0,
    "gn:timezone":"Europe/Warsaw",
    "iso:country":"PL",
    "name:fra_x_preferred":[
        "Bli\u017cyce"
    ],
    "name:pol_x_preferred":[
        "Bli\u017cyce"
    ],
    "name:ukr_x_preferred":[
        "\u0411\u043b\u0456\u0436\u0438\u0446\u0435"
    ],
    "wof:name":"Blizyce",
    "wof:placetype":"locality"
},
  "geometry": {"coordinates":[17.24417,52.6369],"type":"Point"}
}