{
  "type": "Feature",
  "properties": {
    "gn:admin1_code":"73.0",
    "gn:admin2_code":"407.0",
    "gn:admin3_code":"40704.0",
    "gn:asciiname":"Tupadly",
    "gn:country_code":"PL",
    "gn:dem":85,
    "gn:feature_class":"P",
    "gn:feature_code":"PPL",
    "gn:name":"Tupad\u0142y",
    "gn:population":0,
    "gn:timezone":"Europe/Warsaw",
    "iso:country":"PL",
    "name:ceb_x_preferred":[
        "Tupadly"
    ],
    "name:ces_x_preferred":[
        "Tupadly"
    ],
    "name:fra_x_preferred":[
        "Tupadly"
    ],
    "name:ita_x_preferred":[
        "Tupadly"
    ],
    "name:nld_x_preferred":[
        "Tupadly"
    ],
    "name:pol_x_preferred":[
        "Tupadly"
    ],
    "name:slk_x_preferred":[
        "Tupadly"
    ],
    "name:srp_x_preferred":[
        "\u0422\u0443\u043f\u0430\u0434\u043b\u0438"
    ],
    "name:swe_x_preferred":[
        "Tupadly"
    ],
    "wof:name":"Tupadly",
    "wof:placetype":"locality"
},
  "geometry": {"coordinates":[18.25248,52.74361999999999],"type":"Point"}
}