{
  "type": "Feature",
  "properties": {
    "gn:admin1_code":"87.0",
    "gn:admin2_code":"3203.0",
    "gn:admin3_code":"320302.0",
    "gn:asciiname":"Gudowo",
    "gn:country_code":"PL",
    "gn:dem":100,
    "gn:feature_class":"P",
    "gn:feature_code":"PPL",
    "gn:name":"Gudowo",
    "gn:population":0,
    "gn:timezone":"Europe/Warsaw",
    "iso:country":"PL",
    "name:deu_x_historical":[
        "Baumgarten"
    ],
    "name:deu_x_preferred":[
        "Baumgarten"
    ],
    "name:pol_x_preferred":[
        "Gudowo"
    ],
    "name:ukr_x_preferred":[
        "\u0490\u0443\u0434\u043e\u0432\u043e"
    ],
    "name:vie_x_preferred":[
        "Gudowo"
    ],
    "wof:name":"Gudowo",
    "wof:placetype":"locality"
},
  "geometry": {"coordinates":[15.85779,53.49363],"type":"Point"}
}