{
  "type": "Feature",
  "properties": {
    "gn:gn_country":"PL",
    "gn:gn_fcode":"PPL",
    "gn:gn_pop":1339,
    "gn:population":1339,
    "iso:country":"PL",
    "name:ast_x_preferred":[
        "Nidek"
    ],
    "name:ceb_x_preferred":[
        "Nidek"
    ],
    "name:deu_x_preferred":[
        "Nidek"
    ],
    "name:eng_x_preferred":[
        "Nidek"
    ],
    "name:fra_x_preferred":[
        "Nidek"
    ],
    "name:nld_x_preferred":[
        "Nidek"
    ],
    "name:pol_x_preferred":[
        "Nidek"
    ],
    "name:ukr_x_preferred":[
        "\u041d\u0456\u0434\u0435\u043a"
    ],
    "qs_pg:aaroncc":"PL",
    "qs_pg:gn_country":"PL",
    "qs_pg:gn_fcode":"PPL",
    "qs_pg:gn_pop":1339,
    "qs_pg:name":"Nidek",
    "qs_pg:name_adm0":"Polska",
    "qs_pg:name_adm1":"Ma\u0142opolskie",
    "qs_pg:photos_9r":0,
    "qs_pg:photos_sr":0,
    "qs_pg:pop_sr":3,
    "qs_pg:qs_pg_placetype":"locality",
    "qs_pg:qs_pg_placetype_gp":"Town",
    "qs_pg:woe_adm0":23424923,
    "woe:adm0_id":23424923,
    "woe:name_adm0":"Polska",
    "woe:name_adm1":"Ma\u0142opolskie",
    "woe:placetype":"Town",
    "wof:name":"Nidek",
    "wof:placetype":"locality",
    "wof:population":1339
},
  "geometry": {"coordinates":[19.32461,49.90492],"type":"Point"}
}