{
  "type": "Feature",
  "properties": {
    "gn:admin1_code":"77.0",
    "gn:admin2_code":"1216.0",
    "gn:admin3_code":"121604.0",
    "gn:asciiname":"Lubinka",
    "gn:country_code":"PL",
    "gn:dem":330,
    "gn:feature_class":"P",
    "gn:feature_code":"PPL",
    "gn:name":"Lubinka",
    "gn:population":0,
    "gn:timezone":"Europe/Warsaw",
    "iso:country":"PL",
    "wof:name":"Lubinka",
    "wof:placetype":"locality"
},
  "geometry": {"coordinates":[20.89437,49.90422],"type":"Point"}
}