{
  "type": "Feature",
  "properties": {
    "gn:admin1_code":"81.0",
    "gn:admin2_code":"2001.0",
    "gn:admin3_code":"200103.0",
    "gn:asciiname":"Kroszowka",
    "gn:country_code":"PL",
    "gn:dem":124,
    "gn:feature_class":"P",
    "gn:feature_code":"PPL",
    "gn:name":"Krosz\u00f3wka",
    "gn:population":0,
    "gn:timezone":"Europe/Warsaw",
    "iso:country":"PL",
    "name:azb_x_preferred":[
        "\u06a9\u0631\u0648\u0634\u0648\u0648\u06a9\u0627"
    ],
    "name:fas_x_preferred":[
        "\u06a9\u0631\u0648\u0634\u0648\u0648\u06a9\u0627"
    ],
    "name:fra_x_preferred":[
        "Krosz\u00f3wka"
    ],
    "name:lit_x_preferred":[
        "Kro\u0161uvka"
    ],
    "name:pol_x_preferred":[
        "Krosz\u00f3wka"
    ],
    "name:ukr_x_preferred":[
        "\u041a\u0440\u043e\u0448\u0443\u0432\u043a\u0430"
    ],
    "wof:name":"Kroszowka",
    "wof:placetype":"locality"
},
  "geometry": {"coordinates":[22.8156,53.73922],"type":"Point"}
}