{
  "type": "Feature",
  "properties": {
    "gn:admin1_code":"81.0",
    "gn:admin2_code":"2001.0",
    "gn:admin3_code":"200103.0",
    "gn:asciiname":"Kroszowka",
    "gn:country_code":"PL",
    "gn:dem":124,
    "gn:feature_class":"P",
    "gn:feature_code":"PPL",
    "gn:name":"Krosz\u00f3wka",
    "gn:population":0,
    "gn:timezone":"Europe/Warsaw",
    "iso:country":"PL",
    "name:und_x_variant":[
        "Krosz\u00f3wka"
    ],
    "wof:name":"Kroszowka",
    "wof:placetype":"locality"
},
  "geometry": {"coordinates":[22.8156,53.73922],"type":"Point"}
}