{
  "type": "Feature",
  "properties": {
    "gn:admin1_code":"73.0",
    "gn:admin2_code":"414.0",
    "gn:admin3_code":"41405.0",
    "gn:asciiname":"Siemkowo",
    "gn:country_code":"PL",
    "gn:dem":102,
    "gn:feature_class":"P",
    "gn:feature_code":"PPL",
    "gn:name":"Siemkowo",
    "gn:population":0,
    "gn:timezone":"Europe/Warsaw",
    "iso:country":"PL",
    "name:pol_x_preferred":[
        "Siemkowo"
    ],
    "name:ukr_x_preferred":[
        "\u0421\u0435\u043c\u043a\u043e\u0432\u043e"
    ],
    "wof:name":"Siemkowo",
    "wof:placetype":"locality"
},
  "geometry": {"coordinates":[18.22462,53.48218000000001],"type":"Point"}
}