{
  "type": "Feature",
  "properties": {
    "gn:admin1_code":"73.0",
    "gn:admin2_code":"418.0",
    "gn:admin3_code":"41811.0",
    "gn:asciiname":"Kretkow",
    "gn:country_code":"PL",
    "gn:dem":126,
    "gn:feature_class":"P",
    "gn:feature_code":"PPL",
    "gn:name":"Kretk\u00f3w",
    "gn:population":0,
    "gn:timezone":"Europe/Warsaw",
    "iso:country":"PL",
    "name:ceb_x_preferred":[
        "Kamienna Kretkowo"
    ],
    "name:pol_x_preferred":[
        "Kretkowo"
    ],
    "wof:name":"Kretkow",
    "wof:placetype":"locality"
},
  "geometry": {"coordinates":[19.18616,52.36349000000001],"type":"Point"}
}