{
  "type": "Feature",
  "properties": {
    "gn:admin1_code":"78.0",
    "gn:admin2_code":"1434.0",
    "gn:admin3_code":"143411.0",
    "gn:asciiname":"Jarzebia Laka",
    "gn:country_code":"PL",
    "gn:dem":101,
    "gn:feature_class":"P",
    "gn:feature_code":"PPL",
    "gn:name":"Jarz\u0119bia \u0141\u0105ka",
    "gn:population":0,
    "gn:timezone":"Europe/Warsaw",
    "iso:country":"PL",
    "name:und_x_variant":[
        "Jarz\u0119bia \u0141\u0105ka"
    ],
    "wof:name":"Jarzebia Laka",
    "wof:placetype":"locality"
},
  "geometry": {"coordinates":[21.44982000000001,52.45882],"type":"Point"}
}