{
  "type": "Feature",
  "properties": {
    "gn:admin1_code":"78.0",
    "gn:admin2_code":"1434.0",
    "gn:admin3_code":"143411.0",
    "gn:asciiname":"Jarzebia Laka",
    "gn:country_code":"PL",
    "gn:dem":101,
    "gn:feature_class":"P",
    "gn:feature_code":"PPL",
    "gn:name":"Jarz\u0119bia \u0141\u0105ka",
    "gn:population":0,
    "gn:timezone":"Europe/Warsaw",
    "iso:country":"PL",
    "name:azb_x_preferred":[
        "\u06cc\u0627\u0698\u0646\u0628\u06cc\u0627 \u0648\u0627\u0646\u06a9\u0627"
    ],
    "name:ceb_x_preferred":[
        "Jarz\u0119bia \u0141\u0105ka"
    ],
    "name:fas_x_preferred":[
        "\u06cc\u0627\u0698\u0646\u0628\u06cc\u0627 \u0648\u0627\u0646\u06a9\u0627"
    ],
    "name:fra_x_preferred":[
        "Jarz\u0119bia \u0141\u0105ka"
    ],
    "name:nld_x_preferred":[
        "Jarz\u0119bia \u0141\u0105ka"
    ],
    "name:pol_x_preferred":[
        "Jarz\u0119bia \u0141\u0105ka"
    ],
    "name:ukr_x_preferred":[
        "\u042f\u0436\u0435\u043c\u0431\u044f-\u041b\u043e\u043d\u043a\u0430"
    ],
    "name:und_x_variant":[
        "Jarz\u0119bia \u0141\u0105ka"
    ],
    "name:urd_x_preferred":[
        "\u062c\u0631\u0632\u06cc\u0628\u0627 \u0648\u0648\u06a9\u0627"
    ],
    "wof:name":"Jarzebia Laka",
    "wof:placetype":"locality"
},
  "geometry": {"coordinates":[21.44982000000001,52.45882],"type":"Point"}
}