{
  "type": "Feature",
  "properties": {
    "gn:admin1_code":"78.0",
    "gn:admin2_code":"1422.0",
    "gn:admin3_code":"142206.0",
    "gn:asciiname":"Romany Karcze",
    "gn:country_code":"PL",
    "gn:dem":134,
    "gn:feature_class":"P",
    "gn:feature_code":"PPL",
    "gn:name":"Romany Karcze",
    "gn:population":0,
    "gn:timezone":"Europe/Warsaw",
    "iso:country":"PL",
    "wof:name":"Romany Karcze",
    "wof:placetype":"locality"
},
  "geometry": {"coordinates":[20.8302,53.17936],"type":"Point"}
}