{
  "type": "Feature",
  "properties": {
    "gn:admin1_code":"72.0",
    "gn:admin2_code":"217.0",
    "gn:admin3_code":"21703.0",
    "gn:asciiname":"Plosa",
    "gn:country_code":"PL",
    "gn:dem":317,
    "gn:feature_class":"P",
    "gn:feature_code":"PPL",
    "gn:name":"P\u0142osa",
    "gn:population":0,
    "gn:timezone":"Europe/Warsaw",
    "iso:country":"PL",
    "name:pol_x_preferred":[
        "P\u0142osa"
    ],
    "wof:name":"Plosa",
    "wof:placetype":"locality"
},
  "geometry": {"coordinates":[17.08855,50.68167],"type":"Point"}
}