{
  "type": "Feature",
  "properties": {
    "gn:population":4769,
    "iso:country":"PL",
    "name:ast_x_preferred":[
        "Czarny B\u00f3r"
    ],
    "name:azb_x_preferred":[
        "\u0686\u0627\u0631\u0646 \u0628\u0648\u0631"
    ],
    "name:ceb_x_preferred":[
        "Czarny B\u00f3r"
    ],
    "name:deu_x_historical":[
        "Schwarzwaldau"
    ],
    "name:deu_x_preferred":[
        "Czarny B\u00f3r"
    ],
    "name:deu_x_variant":[
        "Schwarzwaldau"
    ],
    "name:eng_x_preferred":[
        "Czarny B\u00f3r"
    ],
    "name:fas_x_preferred":[
        "\u0686\u0627\u0631\u0646 \u0628\u0648\u0631"
    ],
    "name:fra_x_preferred":[
        "Czarny B\u00f3r"
    ],
    "name:ita_x_preferred":[
        "Czarny B\u00f3r"
    ],
    "name:nan_x_preferred":[
        "Czarny B\u00f3r"
    ],
    "name:nld_x_preferred":[
        "Czarny B\u00f3r"
    ],
    "name:pol_x_preferred":[
        "Czarny B\u00f3r"
    ],
    "name:rus_x_preferred":[
        "\u0427\u0430\u0440\u043d\u044b-\u0411\u0443\u0440"
    ],
    "name:swe_x_preferred":[
        "Czarny B\u00f3r"
    ],
    "name:ukr_x_preferred":[
        "\u0427\u0430\u0440\u043d\u0438-\u0411\u0443\u0440"
    ],
    "name:zho_min_nan_x_preferred":[
        "Czarny B\u00f3r"
    ],
    "qs:a0":"Rzeczpospolita Polska",
    "qs:a1":"*Dolnoslaskie",
    "qs:a1r":"0",
    "qs:a2":"Walbrzyski",
    "qs:adm0":"Rzeczpospolita Polska",
    "qs:la":"Czarny B\u00f3r",
    "qs:la_lc":"*PL0221042",
    "qs:level":"locality",
    "qs:loc":"Czarny B\u00f3r",
    "qs:loc_alt":"Czarny Bor",
    "qs:pop":0,
    "qs:type":"rural point-in-poly",
    "wd:wordcount":150,
    "wof:name":"Czarny B\u00f3r",
    "wof:placetype":"locality",
    "wof:population":4769
},
  "geometry": {"coordinates":[16.1326764232494,50.7571305842402],"type":"Point"}
}