{
  "type": "Feature",
  "properties": {
    "gn:admin1_code":"78.0",
    "gn:admin2_code":"1404.0",
    "gn:admin3_code":"140405.0",
    "gn:asciiname":"Jozefkow",
    "gn:country_code":"PL",
    "gn:dem":93,
    "gn:feature_class":"P",
    "gn:feature_code":"PPL",
    "gn:name":"J\u00f3zefk\u00f3w",
    "gn:population":0,
    "gn:timezone":"Europe/Warsaw",
    "iso:country":"PL",
    "wof:name":"Jozefkow",
    "wof:placetype":"locality"
},
  "geometry": {"coordinates":[19.57062,52.33575],"type":"Point"}
}