{
  "type": "Feature",
  "properties": {
    "gn:admin1_code":"87.0",
    "gn:admin2_code":"3210.0",
    "gn:admin3_code":"321001.0",
    "gn:asciiname":"Laskowko",
    "gn:country_code":"PL",
    "gn:dem":49,
    "gn:feature_class":"P",
    "gn:feature_code":"PPL",
    "gn:name":"Lask\u00f3wko",
    "gn:population":0,
    "gn:timezone":"Europe/Warsaw",
    "iso:country":"PL",
    "name:pol_x_preferred":[
        "Lask\u00f3wko"
    ],
    "name:vie_x_preferred":[
        "Lask\u00f3wko"
    ],
    "wof:name":"Laskowko",
    "wof:placetype":"locality"
},
  "geometry": {"coordinates":[15.2043,53.074],"type":"Point"}
}