{
  "type": "Feature",
  "properties": {
    "gn:admin1_code":"72.0",
    "gn:admin2_code":"217.0",
    "gn:admin3_code":"21703.0",
    "gn:asciiname":"Struzyna",
    "gn:country_code":"PL",
    "gn:dem":190,
    "gn:feature_class":"P",
    "gn:feature_code":"PPL",
    "gn:name":"Stru\u017cyna",
    "gn:population":0,
    "gn:timezone":"Europe/Warsaw",
    "iso:country":"PL",
    "name:pol_x_preferred":[
        "Stru\u017cyna"
    ],
    "name:ukr_x_preferred":[
        "\u0421\u0442\u0440\u0443\u0436\u0438\u043d\u0430"
    ],
    "wof:name":"Struzyna",
    "wof:placetype":"locality"
},
  "geometry": {"coordinates":[17.18639,50.70418],"type":"Point"}
}