{
  "type": "Feature",
  "properties": {
    "gn:admin1_code":"78.0",
    "gn:admin2_code":"1422.0",
    "gn:admin3_code":"142206.0",
    "gn:asciiname":"Ozumiech",
    "gn:country_code":"PL",
    "gn:dem":154,
    "gn:feature_class":"P",
    "gn:feature_code":"PPL",
    "gn:name":"O\u017cumiech",
    "gn:population":0,
    "gn:timezone":"Europe/Warsaw",
    "iso:country":"PL",
    "name:fra_x_preferred":[
        "O\u017cumiech"
    ],
    "name:pol_x_preferred":[
        "O\u017cumiech"
    ],
    "name:ukr_x_preferred":[
        "\u041e\u0436\u0443\u043c\u0435\u0445"
    ],
    "wof:name":"Ozumiech",
    "wof:placetype":"locality"
},
  "geometry": {"coordinates":[20.71397,53.1328],"type":"Point"}
}