{
  "type": "Feature",
  "properties": {
    "gn:gn_country":"PL",
    "gn:gn_fcode":"PPLA3",
    "gn:gn_pop":922,
    "gn:population":922,
    "iso:country":"PL",
    "name:unk_x_variant":[
        "Grabowez"
    ],
    "qs_pg:aaroncc":"PL",
    "qs_pg:gn_country":"PL",
    "qs_pg:gn_fcode":"PPLA3",
    "qs_pg:gn_pop":922,
    "qs_pg:name":"Grabowiec",
    "qs_pg:name_adm0":"Polska",
    "qs_pg:name_adm1":"Lubelskie",
    "qs_pg:photos_9k":1,
    "qs_pg:photos_9r":2,
    "qs_pg:photos_all":55,
    "qs_pg:photos_sr":0,
    "qs_pg:pop_sr":2,
    "qs_pg:qs_pg_placetype":"localadmin",
    "qs_pg:qs_pg_placetype_gp":"LocalAdmin",
    "qs_pg:woe_adm0":23424923,
    "woe:adm0_id":23424923,
    "woe:name_adm0":"Polska",
    "woe:name_adm1":"Lubelskie",
    "woe:placetype":"LocalAdmin",
    "wof:name":"Grabowiec",
    "wof:placetype":"localadmin",
    "wof:population":922
},
  "geometry": {"coordinates":[23.55057,50.8209],"type":"Point"}
}