{
  "type": "Feature",
  "properties": {
    "gn:admin1_code":"78.0",
    "gn:admin2_code":"1413.0",
    "gn:admin3_code":"141307.0",
    "gn:asciiname":"Przychod",
    "gn:country_code":"PL",
    "gn:dem":116,
    "gn:feature_class":"P",
    "gn:feature_code":"PPL",
    "gn:name":"Przych\u00f3d",
    "gn:population":0,
    "gn:timezone":"Europe/Warsaw",
    "iso:country":"PL",
    "wof:name":"Przychod",
    "wof:placetype":"locality"
},
  "geometry": {"coordinates":[20.13698,53.01669],"type":"Point"}
}