{
  "type": "Feature",
  "properties": {
    "gn:admin1_code":"81.0",
    "gn:admin2_code":"2009.0",
    "gn:admin3_code":"200905.0",
    "gn:asciiname":"Dusznica",
    "gn:country_code":"PL",
    "gn:dem":132,
    "gn:feature_class":"P",
    "gn:feature_code":"PPL",
    "gn:name":"Dusznica",
    "gn:population":0,
    "gn:timezone":"Europe/Warsaw",
    "iso:country":"PL",
    "name:lit_x_preferred":[
        "Dusny\u010dia"
    ],
    "name:pol_x_preferred":[
        "Dusznica"
    ],
    "name:ukr_x_preferred":[
        "\u0414\u0443\u0448\u043d\u0438\u0446\u044f"
    ],
    "name:und_x_variant":[
        "Duznica"
    ],
    "wof:name":"Dusznica",
    "wof:placetype":"locality"
},
  "geometry": {"coordinates":[23.4396,54.17037],"type":"Point"}
}