{
  "type": "Feature",
  "properties": {
    "gn:admin1_code":"78.0",
    "gn:admin2_code":"1435.0",
    "gn:admin3_code":"143503.0",
    "gn:asciiname":"Porzadzie",
    "gn:country_code":"PL",
    "gn:dem":111,
    "gn:feature_class":"P",
    "gn:feature_code":"PPL",
    "gn:name":"Porz\u0105dzie",
    "gn:population":0,
    "gn:timezone":"Europe/Warsaw",
    "iso:country":"PL",
    "name:azb_x_preferred":[
        "\u067e\u0648\u0698\u0627\u0646\u062c\u0647"
    ],
    "name:ceb_x_preferred":[
        "Porz\u0105dzie"
    ],
    "name:fas_x_preferred":[
        "\u067e\u0648\u0698\u0627\u0646\u062c\u0647"
    ],
    "name:fra_x_preferred":[
        "Porz\u0105dzie"
    ],
    "name:pol_x_preferred":[
        "Porz\u0105dzie"
    ],
    "name:ukr_x_preferred":[
        "\u041f\u043e\u0436\u043e\u043d\u0434\u0437\u0435"
    ],
    "wof:name":"Porzadzie",
    "wof:placetype":"locality"
},
  "geometry": {"coordinates":[21.42358,52.69866],"type":"Point"}
}