{
  "type": "Feature",
  "properties": {
    "gn:admin1_code":"78.0",
    "gn:admin2_code":"1435.0",
    "gn:admin3_code":"143503.0",
    "gn:asciiname":"Porzadzie",
    "gn:country_code":"PL",
    "gn:dem":111,
    "gn:feature_class":"P",
    "gn:feature_code":"PPL",
    "gn:name":"Porz\u0105dzie",
    "gn:population":0,
    "gn:timezone":"Europe/Warsaw",
    "iso:country":"PL",
    "name:und_x_variant":[
        "Porz\u0105dzie"
    ],
    "wof:name":"Porzadzie",
    "wof:placetype":"locality"
},
  "geometry": {"coordinates":[21.42358,52.69866],"type":"Point"}
}