{
  "type": "Feature",
  "properties": {
    "iso:country":"PL",
    "name:pol_x_preferred":[
        "Klemb\u00f3w"
    ],
    "wof:name":"Klemb\u00f3w",
    "wof:placetype":"locality"
},
  "geometry": {"coordinates":[21.3084143955961,52.417529787402],"type":"Point"}
}