{
  "type": "Feature",
  "properties": {
    "iso:country":"PL",
    "name:azb_x_preferred":[
        "\u06a9\u0644\u0645\u0628\u0648\u0648"
    ],
    "name:ceb_x_preferred":[
        "Klemb\u00f3w"
    ],
    "name:deu_x_preferred":[
        "Klemb\u00f3w"
    ],
    "name:fas_x_preferred":[
        "\u06a9\u0644\u0645\u0628\u0648\u0648"
    ],
    "name:fra_x_preferred":[
        "Klemb\u00f3w"
    ],
    "name:nld_x_preferred":[
        "Klemb\u00f3w"
    ],
    "name:pol_x_preferred":[
        "Klemb\u00f3w"
    ],
    "name:ukr_x_preferred":[
        "\u041a\u043b\u0435\u043c\u0431\u0443\u0432"
    ],
    "wof:coterminous":[
        1125318521
    ],
    "wof:name":"Klemb\u00f3w",
    "wof:placetype":"locality"
},
  "geometry": {"coordinates":[21.3084143955961,52.417529787402],"type":"Point"}
}