{
  "type": "Feature",
  "properties": {
    "gn:admin1_code":"77.0",
    "gn:admin2_code":"1207.0",
    "gn:admin3_code":"120708.0",
    "gn:asciiname":"Wolica",
    "gn:country_code":"PL",
    "gn:dem":431,
    "gn:feature_class":"P",
    "gn:feature_code":"PPL",
    "gn:name":"Wolica",
    "gn:population":0,
    "gn:timezone":"Europe/Warsaw",
    "iso:country":"PL",
    "wof:name":"Wolica",
    "wof:placetype":"locality"
},
  "geometry": {"coordinates":[20.50839,49.60777],"type":"Point"}
}