{
  "type": "Feature",
  "properties": {
    "gn:admin1_code":"78.0",
    "gn:admin2_code":"1422.0",
    "gn:admin3_code":"142204.0",
    "gn:asciiname":"Zelazna",
    "gn:country_code":"PL",
    "gn:dem":122,
    "gn:feature_class":"P",
    "gn:feature_code":"PPL",
    "gn:name":"\u017belazna",
    "gn:population":0,
    "gn:timezone":"Europe/Warsaw",
    "iso:country":"PL",
    "name:fra_x_preferred":[
        "\u017belazna Rz\u0105dowa"
    ],
    "name:pol_x_preferred":[
        "\u017belazna Rz\u0105dowa"
    ],
    "name:ukr_x_preferred":[
        "\u0416\u0435\u043b\u044f\u0437\u043d\u0430-\u0416\u043e\u043d\u0434\u043e\u0432\u0430"
    ],
    "name:und_x_variant":[
        "\u017belazna"
    ],
    "wof:name":"Zelazna",
    "wof:placetype":"locality"
},
  "geometry": {"coordinates":[21.12872,53.23148000000001],"type":"Point"}
}