{
  "type": "Feature",
  "properties": {
    "gn:admin1_code":"87.0",
    "gn:admin2_code":"3214.0",
    "gn:admin3_code":"321409.0",
    "gn:asciiname":"Leczyca",
    "gn:country_code":"PL",
    "gn:dem":58,
    "gn:feature_class":"P",
    "gn:feature_code":"PPL",
    "gn:name":"\u0141\u0119czyca",
    "gn:population":0,
    "gn:timezone":"Europe/Warsaw",
    "iso:country":"PL",
    "name:pol_x_preferred":[
        "\u0141\u0119czyca"
    ],
    "name:ukr_x_preferred":[
        "\u041b\u0435\u043d\u0447\u0438\u0446\u044f"
    ],
    "name:und_x_variant":[
        "Lenz"
    ],
    "wof:name":"Leczyca",
    "wof:placetype":"locality"
},
  "geometry": {"coordinates":[15.07254,53.4393],"type":"Point"}
}