{
  "type": "Feature",
  "properties": {
    "gn:admin1_code":"78.0",
    "gn:admin2_code":"1415.0",
    "gn:admin3_code":"141506.0",
    "gn:asciiname":"Siemnocha",
    "gn:country_code":"PL",
    "gn:dem":100,
    "gn:feature_class":"P",
    "gn:feature_code":"PPL",
    "gn:name":"Siemnocha",
    "gn:population":0,
    "gn:timezone":"Europe/Warsaw",
    "iso:country":"PL",
    "name:fra_x_preferred":[
        "Siemnocha"
    ],
    "name:pol_x_preferred":[
        "Siemnocha"
    ],
    "name:ukr_x_preferred":[
        "\u0421\u0435\u043c\u043d\u043e\u0445\u0430"
    ],
    "name:und_x_variant":[
        "Siemnocka",
        "Siemnocha"
    ],
    "wof:name":"Siemnocha",
    "wof:placetype":"locality"
},
  "geometry": {"coordinates":[21.53991,53.12658],"type":"Point"}
}