{
  "type": "Feature",
  "properties": {
    "gn:admin1_code":"75.0",
    "gn:admin2_code":"620.0",
    "gn:admin3_code":"62012.0",
    "gn:asciiname":"Kitow",
    "gn:country_code":"PL",
    "gn:dem":207,
    "gn:feature_class":"P",
    "gn:feature_code":"PPL",
    "gn:name":"Kit\u00f3w",
    "gn:population":0,
    "gn:timezone":"Europe/Warsaw",
    "iso:country":"PL",
    "name:azb_x_preferred":[
        "\u06a9\u06cc\u062a\u0648\u0648"
    ],
    "name:fas_x_preferred":[
        "\u06a9\u06cc\u062a\u0648\u0648"
    ],
    "name:fra_x_preferred":[
        "Kit\u00f3w"
    ],
    "name:pol_x_preferred":[
        "Kit\u00f3w"
    ],
    "name:ukr_x_preferred":[
        "\u041a\u0456\u0442\u0443\u0432"
    ],
    "wof:name":"Kitow",
    "wof:placetype":"locality"
},
  "geometry": {"coordinates":[22.93944,50.79335],"type":"Point"}
}