{
  "type": "Feature",
  "properties": {
    "gn:admin1_code":"85.0",
    "gn:admin2_code":"2805.0",
    "gn:admin3_code":"280504.0",
    "gn:asciiname":"Jebramki",
    "gn:country_code":"PL",
    "gn:dem":137,
    "gn:feature_class":"P",
    "gn:feature_code":"PPL",
    "gn:name":"Jebramki",
    "gn:population":0,
    "gn:timezone":"Europe/Warsaw",
    "iso:country":"PL",
    "name:azb_x_preferred":[
        "\u06cc\u0628\u0631\u0627\u0645\u06a9\u06cc"
    ],
    "name:deu_x_preferred":[
        "Jebramki"
    ],
    "name:fas_x_preferred":[
        "\u06cc\u0628\u0631\u0627\u0645\u06a9\u06cc"
    ],
    "name:fra_x_preferred":[
        "Jebramki"
    ],
    "name:pol_x_preferred":[
        "Jebramki"
    ],
    "name:ukr_x_preferred":[
        "\u0404\u0431\u0440\u0430\u043c\u043a\u0456"
    ],
    "name:und_x_variant":[
        "Bachort",
        "Jembramki",
        "Jebrammen",
        "Jebramki"
    ],
    "wof:name":"Jebramki",
    "wof:placetype":"locality"
},
  "geometry": {"coordinates":[22.20307,53.68715],"type":"Point"}
}