{
  "type": "Feature",
  "properties": {
    "gn:admin1_code":"87.0",
    "gn:admin2_code":"3204.0",
    "gn:admin3_code":"320402.0",
    "gn:asciiname":"Stawno",
    "gn:country_code":"PL",
    "gn:dem":17,
    "gn:feature_class":"P",
    "gn:feature_code":"PPL",
    "gn:name":"Stawno",
    "gn:population":0,
    "gn:timezone":"Europe/Warsaw",
    "iso:country":"PL",
    "name:ceb_x_preferred":[
        "Stawno"
    ],
    "name:pol_x_preferred":[
        "Stawno"
    ],
    "name:ukr_x_preferred":[
        "\u0421\u0442\u0430\u0432\u043d\u043e"
    ],
    "wof:name":"Stawno",
    "wof:placetype":"locality"
},
  "geometry": {"coordinates":[14.89919,53.4975],"type":"Point"}
}