{
  "type": "Feature",
  "properties": {
    "gn:admin1_code":"75.0",
    "gn:admin2_code":"608.0",
    "gn:admin3_code":"60803.0",
    "gn:asciiname":"Mieczyslawka Wolka",
    "gn:cc2":"PL",
    "gn:country_code":"PL",
    "gn:dem":160,
    "gn:feature_class":"P",
    "gn:feature_code":"PPL",
    "gn:name":"Mieczys\u0142awka W\u00f3lka",
    "gn:population":0,
    "gn:timezone":"Europe/Warsaw",
    "iso:country":"PL",
    "name:und_x_variant":[
        "Kolonia W\u00f3lka Mieczys\u0142awka",
        "Mieczys\u0142awka W\u00f3lka"
    ],
    "wof:name":"Mieczyslawka Wolka",
    "wof:placetype":"locality"
},
  "geometry": {"coordinates":[22.51667,51.51667],"type":"Point"}
}