{
  "type": "Feature",
  "properties": {
    "gn:admin1_code":"78.0",
    "gn:admin2_code":"1410.0",
    "gn:admin3_code":"141001.0",
    "gn:asciiname":"Siliwonki",
    "gn:country_code":"PL",
    "gn:dem":159,
    "gn:feature_class":"P",
    "gn:feature_code":"PPL",
    "gn:name":"Siliwonki",
    "gn:population":0,
    "gn:timezone":"Europe/Warsaw",
    "iso:country":"PL",
    "name:fra_x_preferred":[
        "Siliwonki"
    ],
    "name:lit_x_preferred":[
        "Silivonkai"
    ],
    "name:pol_x_preferred":[
        "Siliwonki"
    ],
    "name:ukr_x_preferred":[
        "\u0421\u0456\u043b\u0456\u0432\u043e\u043d\u043a\u0456"
    ],
    "wof:name":"Siliwonki",
    "wof:placetype":"locality"
},
  "geometry": {"coordinates":[22.77191,52.09712],"type":"Point"}
}