{
  "type": "Feature",
  "properties": {
    "gn:admin1_code":"78.0",
    "gn:admin2_code":"1410.0",
    "gn:admin3_code":"141001.0",
    "gn:asciiname":"Siliwonki",
    "gn:country_code":"PL",
    "gn:dem":159,
    "gn:feature_class":"P",
    "gn:feature_code":"PPL",
    "gn:name":"Siliwonki",
    "gn:population":0,
    "gn:timezone":"Europe/Warsaw",
    "iso:country":"PL",
    "wof:name":"Siliwonki",
    "wof:placetype":"locality"
},
  "geometry": {"coordinates":[22.77191,52.09712],"type":"Point"}
}