{
  "type": "Feature",
  "properties": {
    "gn:admin1_code":"76",
    "gn:admin2_code":"0808",
    "gn:admin3_code":"80802.0",
    "gn:asciiname":"Pasalka",
    "gn:country_code":"PL",
    "gn:dem":97,
    "gn:feature_class":"P",
    "gn:feature_code":"PPL",
    "gn:name":"Pasa\u0142ka",
    "gn:population":0,
    "gn:timezone":"Europe/Warsaw",
    "iso:country":"PL",
    "name:deu_x_historical":[
        "Bruch"
    ],
    "name:deu_x_preferred":[
        "Bruch"
    ],
    "name:fra_x_preferred":[
        "Pasa\u0142ka"
    ],
    "name:pol_x_preferred":[
        "Pasa\u0142ka"
    ],
    "wof:name":"Pasalka",
    "wof:placetype":"locality"
},
  "geometry": {"coordinates":[15.2404,52.26728],"type":"Point"}
}