{
  "type": "Feature",
  "properties": {
    "gn:admin1_code":"82.0",
    "gn:admin2_code":"2214.0",
    "gn:admin3_code":"221405.0",
    "gn:asciiname":"Subkowskie Pole",
    "gn:country_code":"PL",
    "gn:dem":30,
    "gn:feature_class":"P",
    "gn:feature_code":"PPL",
    "gn:name":"Subkowskie Pole",
    "gn:population":0,
    "gn:timezone":"Europe/Warsaw",
    "iso:country":"PL",
    "wof:name":"Subkowskie Pole",
    "wof:placetype":"locality"
},
  "geometry": {"coordinates":[18.78234,54.01731],"type":"Point"}
}