{
  "type": "Feature",
  "properties": {
    "gn:admin1_code":"87.0",
    "gn:admin2_code":"3201.0",
    "gn:admin3_code":"320104.0",
    "gn:asciiname":"Tyczewo",
    "gn:country_code":"PL",
    "gn:dem":67,
    "gn:feature_class":"P",
    "gn:feature_code":"PPL",
    "gn:name":"Tyczewo",
    "gn:population":0,
    "gn:timezone":"Europe/Warsaw",
    "iso:country":"PL",
    "name:deu_x_preferred":[
        "Tyczewo"
    ],
    "name:pol_x_preferred":[
        "Tyczewo"
    ],
    "name:ukr_x_preferred":[
        "\u0422\u0438\u0447\u0435\u0432\u043e"
    ],
    "wof:name":"Tyczewo",
    "wof:placetype":"locality"
},
  "geometry": {"coordinates":[16.31431,53.98049],"type":"Point"}
}