{
  "type": "Feature",
  "properties": {
    "gn:admin1_code":"72.0",
    "gn:admin2_code":"218.0",
    "gn:admin3_code":"21804.0",
    "gn:asciiname":"Rakoszyce",
    "gn:country_code":"PL",
    "gn:dem":148,
    "gn:feature_class":"P",
    "gn:feature_code":"PPL",
    "gn:name":"Rakoszyce",
    "gn:population":0,
    "gn:timezone":"Europe/Warsaw",
    "iso:country":"PL",
    "name:pol_x_preferred":[
        "Rakoszyce"
    ],
    "name:ukr_x_preferred":[
        "\u0420\u0430\u043a\u043e\u0448\u0438\u0446\u0435"
    ],
    "wof:name":"Rakoszyce",
    "wof:placetype":"locality"
},
  "geometry": {"coordinates":[16.65253,51.09533],"type":"Point"}
}