{
  "type": "Feature",
  "properties": {
    "gn:admin1_code":"77.0",
    "gn:admin2_code":"1219.0",
    "gn:admin3_code":"121905.0",
    "gn:asciiname":"Podstolice",
    "gn:country_code":"PL",
    "gn:dem":326,
    "gn:feature_class":"P",
    "gn:feature_code":"PPL",
    "gn:name":"Podstolice",
    "gn:population":0,
    "gn:timezone":"Europe/Warsaw",
    "iso:country":"PL",
    "name:ceb_x_preferred":[
        "Podstolice"
    ],
    "name:pol_x_preferred":[
        "Podstolice"
    ],
    "name:ukr_x_preferred":[
        "\u041f\u043e\u0434\u0441\u0442\u043e\u043b\u0456\u0446\u0435"
    ],
    "wof:name":"Podstolice",
    "wof:placetype":"locality"
},
  "geometry": {"coordinates":[19.99752,49.95917],"type":"Point"}
}