{
  "type": "Feature",
  "properties": {
    "gn:admin1_code":"78.0",
    "gn:admin2_code":"1435.0",
    "gn:admin3_code":"143505.0",
    "gn:asciiname":"Leszczydol",
    "gn:country_code":"PL",
    "gn:dem":110,
    "gn:feature_class":"P",
    "gn:feature_code":"PPL",
    "gn:name":"Leszczyd\u00f3\u0142",
    "gn:population":0,
    "gn:timezone":"Europe/Warsaw",
    "iso:country":"PL",
    "wof:name":"Leszczydol",
    "wof:placetype":"locality"
},
  "geometry": {"coordinates":[21.38869,52.63586],"type":"Point"}
}