{
  "type": "Feature",
  "properties": {
    "gn:admin1_code":"73.0",
    "gn:admin2_code":"409.0",
    "gn:admin3_code":"40903.0",
    "gn:asciiname":"Niestronno",
    "gn:country_code":"PL",
    "gn:dem":109,
    "gn:feature_class":"P",
    "gn:feature_code":"PPL",
    "gn:name":"Niestronno",
    "gn:population":0,
    "gn:timezone":"Europe/Warsaw",
    "iso:country":"PL",
    "name:pol_x_preferred":[
        "Niestronno"
    ],
    "name:ukr_x_preferred":[
        "\u041d\u0435\u0441\u0442\u0440\u043e\u043d\u043d\u043e"
    ],
    "wof:name":"Niestronno",
    "wof:placetype":"locality"
},
  "geometry": {"coordinates":[17.8291,52.7044],"type":"Point"}
}