{
  "type": "Feature",
  "properties": {
    "gn:admin1_code":"82.0",
    "gn:admin2_code":"2205.0",
    "gn:admin3_code":"220505.0",
    "gn:asciiname":"Slawki",
    "gn:country_code":"PL",
    "gn:dem":224,
    "gn:feature_class":"P",
    "gn:feature_code":"PPL",
    "gn:name":"S\u0142awki",
    "gn:population":0,
    "gn:timezone":"Europe/Warsaw",
    "iso:country":"PL",
    "name:und_x_variant":[
        "S\u0142awki"
    ],
    "wof:name":"Slawki",
    "wof:placetype":"locality"
},
  "geometry": {"coordinates":[18.18763,54.25428],"type":"Point"}
}