{
  "type": "Feature",
  "properties": {
    "gn:admin1_code":"82.0",
    "gn:admin2_code":"2215.0",
    "gn:admin3_code":"221509.0",
    "gn:asciiname":"Warzenska Huta",
    "gn:country_code":"PL",
    "gn:dem":170,
    "gn:feature_class":"P",
    "gn:feature_code":"PPL",
    "gn:name":"Warze\u0144ska Huta",
    "gn:population":0,
    "gn:timezone":"Europe/Warsaw",
    "iso:country":"PL",
    "name:und_x_variant":[
        "Warze\u0144ska Huta"
    ],
    "wof:name":"Warzenska Huta",
    "wof:placetype":"locality"
},
  "geometry": {"coordinates":[18.32657,54.43515],"type":"Point"}
}