{
  "type": "Feature",
  "properties": {
    "gn:admin1_code":"72",
    "gn:admin2_code":"0213",
    "gn:admin3_code":"21303.0",
    "gn:asciiname":"Wrobliniec",
    "gn:country_code":"PL",
    "gn:dem":113,
    "gn:feature_class":"P",
    "gn:feature_code":"PPL",
    "gn:name":"Wr\u00f3bliniec",
    "gn:population":0,
    "gn:timezone":"Europe/Warsaw",
    "iso:country":"PL",
    "wof:name":"Wrobliniec",
    "wof:placetype":"locality"
},
  "geometry": {"coordinates":[17.54817,51.54176],"type":"Point"}
}