{
  "type": "Feature",
  "properties": {
    "gn:admin1_code":"76.0",
    "gn:admin2_code":"808.0",
    "gn:admin3_code":"80802.0",
    "gn:asciiname":"Kijewo",
    "gn:country_code":"PL",
    "gn:dem":87,
    "gn:feature_class":"P",
    "gn:feature_code":"PPL",
    "gn:name":"Kijewo",
    "gn:population":0,
    "gn:timezone":"Europe/Warsaw",
    "iso:country":"PL",
    "name:ceb_x_preferred":[
        "Kijewo"
    ],
    "name:deu_x_preferred":[
        "Kijewo"
    ],
    "name:fra_x_preferred":[
        "Kijewo"
    ],
    "name:pol_x_preferred":[
        "Kijewo"
    ],
    "name:ukr_x_preferred":[
        "\u041a\u0456\u0454\u0432\u043e"
    ],
    "wof:name":"Kijewo",
    "wof:placetype":"locality"
},
  "geometry": {"coordinates":[15.13779,52.22449],"type":"Point"}
}