{
  "type": "Feature",
  "properties": {
    "gn:gn_country":"PL",
    "gn:gn_fcode":"PPL",
    "gn:gn_pop":0,
    "iso:country":"PL",
    "name:ast_x_preferred":[
        "R\u0105bie\u0144"
    ],
    "name:eng_x_preferred":[
        "R\u0105bie\u0144"
    ],
    "name:fra_x_preferred":[
        "R\u0105bie\u0144"
    ],
    "name:nld_x_preferred":[
        "R\u0105bie\u0144"
    ],
    "name:pol_x_preferred":[
        "R\u0105bie\u0144"
    ],
    "name:ukr_x_preferred":[
        "\u0420\u043e\u043c\u0431\u0435\u043d\u044c"
    ],
    "qs_pg:aaroncc":"PL",
    "qs_pg:gn_country":"PL",
    "qs_pg:gn_fcode":"PPL",
    "qs_pg:gn_pop":0,
    "qs_pg:name":"R\u0105bie\u0144",
    "qs_pg:name_adm0":"Polska",
    "qs_pg:name_adm1":"\u0141\u00f3dzkie",
    "qs_pg:photos_9k":1,
    "qs_pg:photos_9r":1,
    "qs_pg:photos_all":5,
    "qs_pg:photos_sr":0,
    "qs_pg:pop_sr":0,
    "qs_pg:qs_pg_placetype":"locality",
    "qs_pg:qs_pg_placetype_gp":"Town",
    "qs_pg:woe_adm0":23424923,
    "woe:adm0_id":23424923,
    "woe:name_adm0":"Polska",
    "woe:name_adm1":"\u0141\u00f3dzkie",
    "woe:placetype":"Town",
    "wof:name":"R\u0105bie\u0144",
    "wof:placetype":"locality"
},
  "geometry": {"coordinates":[19.32721,51.78945],"type":"Point"}
}