{
  "type": "Feature",
  "properties": {
    "gn:admin1_code":"81.0",
    "gn:admin2_code":"2002.0",
    "gn:admin3_code":"200201.0",
    "gn:asciiname":"Klepacze",
    "gn:country_code":"PL",
    "gn:dem":127,
    "gn:feature_class":"P",
    "gn:feature_code":"PPL",
    "gn:name":"Klepacze",
    "gn:population":0,
    "gn:timezone":"Europe/Warsaw",
    "iso:country":"PL",
    "name:ceb_x_preferred":[
        "Klepacze"
    ],
    "name:fra_x_preferred":[
        "Klepacze"
    ],
    "name:lit_x_preferred":[
        "Klepa\u010d\u0117"
    ],
    "name:pol_x_preferred":[
        "Klepacze"
    ],
    "name:rus_x_preferred":[
        "\u041a\u043b\u0435\u043f\u0430\u0447\u0435"
    ],
    "name:ukr_x_preferred":[
        "\u041a\u043b\u0435\u043f\u0430\u0447\u0435"
    ],
    "wof:name":"Klepacze",
    "wof:placetype":"locality"
},
  "geometry": {"coordinates":[23.07621,53.10683],"type":"Point"}
}