{
  "type": "Feature",
  "properties": {
    "gn:admin1_code":"78.0",
    "gn:admin2_code":"1413.0",
    "gn:admin3_code":"141302.0",
    "gn:asciiname":"Brzozowo Dabrowka",
    "gn:country_code":"PL",
    "gn:dem":145,
    "gn:feature_class":"P",
    "gn:feature_code":"PPL",
    "gn:name":"Brzozowo D\u0105br\u00f3wka",
    "gn:population":0,
    "gn:timezone":"Europe/Warsaw",
    "iso:country":"PL",
    "name:fra_x_preferred":[
        "Brzozowo-D\u0105br\u00f3wka"
    ],
    "name:pol_x_preferred":[
        "Brzozowo-D\u0105br\u00f3wka"
    ],
    "name:ukr_x_preferred":[
        "\u0411\u0436\u043e\u0437\u043e\u0432\u043e-\u0414\u043e\u043c\u0431\u0440\u0443\u0432\u043a\u0430"
    ],
    "name:und_x_variant":[
        "Brzozowo D\u0105br\u00f3wka"
    ],
    "wof:name":"Brzozowo Dabrowka",
    "wof:placetype":"locality"
},
  "geometry": {"coordinates":[20.64752,53.18833000000001],"type":"Point"}
}