{
  "type": "Feature",
  "properties": {
    "gn:admin1_code":"72.0",
    "gn:admin2_code":"217.0",
    "gn:admin3_code":"21704.0",
    "gn:asciiname":"Szczawin",
    "gn:country_code":"PL",
    "gn:dem":165,
    "gn:feature_class":"P",
    "gn:feature_code":"PPL",
    "gn:name":"Szczawin",
    "gn:population":0,
    "gn:timezone":"Europe/Warsaw",
    "iso:country":"PL",
    "name:pol_x_preferred":[
        "Szczawin"
    ],
    "name:ukr_x_preferred":[
        "\u0429\u0430\u0432\u0456\u043d"
    ],
    "wof:name":"Szczawin",
    "wof:placetype":"locality"
},
  "geometry": {"coordinates":[17.05712999999999,50.79498],"type":"Point"}
}