{
  "type": "Feature",
  "properties": {
    "gn:admin1_code":"75.0",
    "gn:admin2_code":"618.0",
    "gn:admin3_code":"61805.0",
    "gn:asciiname":"Wolka Wierzbicka",
    "gn:country_code":"PL",
    "gn:dem":230,
    "gn:feature_class":"P",
    "gn:feature_code":"PPL",
    "gn:name":"W\u00f3lka Wierzbicka",
    "gn:population":0,
    "gn:timezone":"Europe/Warsaw",
    "iso:country":"PL",
    "name:fra_x_preferred":[
        "W\u00f3lka Wierzbicka"
    ],
    "name:pol_x_preferred":[
        "W\u00f3lka Wierzbicka"
    ],
    "name:ukr_x_preferred":[
        "\u0412\u0443\u043b\u044c\u043a\u0430 \u0412\u0435\u0440\u0431\u0438\u0446\u044c\u043a\u0430"
    ],
    "wof:name":"Wolka Wierzbicka",
    "wof:placetype":"locality"
},
  "geometry": {"coordinates":[23.67228,50.3678],"type":"Point"}
}