{
  "type": "Feature",
  "properties": {
    "gn:admin1_code":"78.0",
    "gn:admin2_code":"1407.0",
    "gn:admin3_code":"140707.0",
    "gn:asciiname":"Nagornik",
    "gn:country_code":"PL",
    "gn:dem":112,
    "gn:feature_class":"P",
    "gn:feature_code":"PPL",
    "gn:name":"Nag\u00f3rnik",
    "gn:population":0,
    "gn:timezone":"Europe/Warsaw",
    "iso:country":"PL",
    "name:fra_x_preferred":[
        "Nag\u00f3rnik"
    ],
    "name:pol_x_preferred":[
        "Nag\u00f3rnik"
    ],
    "name:ukr_x_preferred":[
        "\u041d\u0430\u0491\u0443\u0440\u043d\u0438\u043a"
    ],
    "name:und_x_variant":[
        "Nag\u00f3rnik"
    ],
    "wof:name":"Nagornik",
    "wof:placetype":"locality"
},
  "geometry": {"coordinates":[21.78782,51.53029],"type":"Point"}
}