{
  "type": "Feature",
  "properties": {
    "gn:admin1_code":"87.0",
    "gn:admin2_code":"3210.0",
    "gn:admin3_code":"321004.0",
    "gn:asciiname":"Roscin",
    "gn:country_code":"PL",
    "gn:dem":79,
    "gn:feature_class":"P",
    "gn:feature_code":"PPL",
    "gn:name":"Ro\u015bcin",
    "gn:population":0,
    "gn:timezone":"Europe/Warsaw",
    "iso:country":"PL",
    "name:pol_x_preferred":[
        "Ro\u015bcin"
    ],
    "name:ukr_x_preferred":[
        "\u0420\u043e\u0441\u0446\u0438\u043d"
    ],
    "name:und_x_variant":[
        "Rostin",
        "Ro\u015bcin"
    ],
    "wof:name":"Roscin",
    "wof:placetype":"locality"
},
  "geometry": {"coordinates":[14.79361,52.89006],"type":"Point"}
}