{
  "type": "Feature",
  "properties": {
    "gn:admin1_code":"75.0",
    "gn:admin2_code":"608.0",
    "gn:admin3_code":"60805.0",
    "gn:asciiname":"Wolka Krasieninska",
    "gn:country_code":"PL",
    "gn:dem":162,
    "gn:feature_class":"P",
    "gn:feature_code":"PPL",
    "gn:name":"W\u00f3lka Krasieni\u0144ska",
    "gn:population":0,
    "gn:timezone":"Europe/Warsaw",
    "iso:country":"PL",
    "name:und_x_variant":[
        "Wola Krasieni\u0144ska",
        "W\u00f3lka Krasieni\u0144ska"
    ],
    "wof:name":"Wolka Krasieninska",
    "wof:placetype":"locality"
},
  "geometry": {"coordinates":[22.47097,51.4114],"type":"Point"}
}