{
  "type": "Feature",
  "properties": {
    "gn:admin1_code":"74.0",
    "gn:admin2_code":"1020.0",
    "gn:admin3_code":"102001.0",
    "gn:asciiname":"Huta Jozefow",
    "gn:country_code":"PL",
    "gn:dem":140,
    "gn:feature_class":"P",
    "gn:feature_code":"PPL",
    "gn:name":"Huta J\u00f3zef\u00f3w",
    "gn:population":0,
    "gn:timezone":"Europe/Warsaw",
    "iso:country":"PL",
    "wof:name":"Huta Jozefow",
    "wof:placetype":"locality"
},
  "geometry": {"coordinates":[19.73702,51.94592],"type":"Point"}
}