{
  "type": "Feature",
  "properties": {
    "gn:admin1_code":"81.0",
    "gn:admin2_code":"2002.0",
    "gn:admin3_code":"200215.0",
    "gn:asciiname":"Gora Strykowa",
    "gn:country_code":"PL",
    "gn:dem":107,
    "gn:feature_class":"P",
    "gn:feature_code":"PPL",
    "gn:name":"G\u00f3ra Strykowa",
    "gn:population":0,
    "gn:timezone":"Europe/Warsaw",
    "iso:country":"PL",
    "name:lit_x_preferred":[
        "Strenkova Gura"
    ],
    "name:pol_x_preferred":[
        "Str\u0119kowa G\u00f3ra"
    ],
    "name:ukr_x_preferred":[
        "\u0421\u0442\u0440\u0435\u043d\u043a\u043e\u0432\u0430-\u0490\u0443\u0440\u0430"
    ],
    "name:und_x_variant":[
        "Str\u0119kowo G\u00f3ra",
        "G\u00f3ra Strykowa"
    ],
    "wof:name":"Gora Strykowa",
    "wof:placetype":"locality"
},
  "geometry": {"coordinates":[22.54986,53.2157],"type":"Point"}
}