{
  "type": "Feature",
  "properties": {
    "gn:admin1_code":"74.0",
    "gn:admin2_code":"1001.0",
    "gn:admin3_code":"100108.0",
    "gn:asciiname":"Kociszew",
    "gn:country_code":"PL",
    "gn:dem":191,
    "gn:feature_class":"P",
    "gn:feature_code":"PPL",
    "gn:name":"Kociszew",
    "gn:population":0,
    "gn:timezone":"Europe/Warsaw",
    "iso:country":"PL",
    "name:fra_x_preferred":[
        "Kociszew"
    ],
    "name:pol_x_preferred":[
        "Kociszew"
    ],
    "name:ukr_x_preferred":[
        "\u041a\u043e\u0446\u0438\u0448\u0435\u0432"
    ],
    "wof:name":"Kociszew",
    "wof:placetype":"locality"
},
  "geometry": {"coordinates":[19.29851,51.49253],"type":"Point"}
}