{
  "type": "Feature",
  "properties": {
    "gn:admin1_code":"74.0",
    "gn:admin2_code":"1017.0",
    "gn:admin3_code":"101706.0",
    "gn:asciiname":"Wygladacze",
    "gn:country_code":"PL",
    "gn:dem":167,
    "gn:feature_class":"P",
    "gn:feature_code":"PPL",
    "gn:name":"Wygl\u0105dacze",
    "gn:population":0,
    "gn:timezone":"Europe/Warsaw",
    "iso:country":"PL",
    "wof:name":"Wygladacze",
    "wof:placetype":"locality"
},
  "geometry": {"coordinates":[18.65779,51.30742],"type":"Point"}
}