{
  "type": "Feature",
  "properties": {
    "gn:admin1_code":"78.0",
    "gn:admin2_code":"1426.0",
    "gn:admin3_code":"142608.0",
    "gn:asciiname":"Strzala",
    "gn:country_code":"PL",
    "gn:dem":139,
    "gn:feature_class":"P",
    "gn:feature_code":"PPL",
    "gn:name":"Strza\u0142a",
    "gn:population":0,
    "gn:timezone":"Europe/Warsaw",
    "iso:country":"PL",
    "name:ceb_x_preferred":[
        "Strza\u0142a"
    ],
    "name:fra_x_preferred":[
        "Strza\u0142a"
    ],
    "name:nld_x_preferred":[
        "Strza\u0142a"
    ],
    "name:pol_x_preferred":[
        "Strza\u0142a"
    ],
    "name:szl_x_preferred":[
        "Strza\u0142a"
    ],
    "name:ukr_x_preferred":[
        "\u0421\u0442\u0448\u0430\u043b\u0430"
    ],
    "wof:name":"Strzala",
    "wof:placetype":"locality"
},
  "geometry": {"coordinates":[22.24998,52.20182],"type":"Point"}
}