{
  "type": "Feature",
  "properties": {
    "gn:admin1_code":"75.0",
    "gn:admin2_code":"603.0",
    "gn:admin3_code":"60306.0",
    "gn:asciiname":"Jozefin",
    "gn:country_code":"PL",
    "gn:dem":183,
    "gn:feature_class":"P",
    "gn:feature_code":"PPL",
    "gn:name":"J\u00f3zefin",
    "gn:population":0,
    "gn:timezone":"Europe/Warsaw",
    "iso:country":"PL",
    "name:fra_x_preferred":[
        "J\u00f3zefin"
    ],
    "name:pol_x_preferred":[
        "J\u00f3zefin"
    ],
    "name:ukr_x_preferred":[
        "\u042e\u0437\u0435\u0444\u0456\u043d"
    ],
    "wof:name":"Jozefin",
    "wof:placetype":"locality"
},
  "geometry": {"coordinates":[23.55031,51.12017],"type":"Point"}
}