{
  "type": "Feature",
  "properties": {
    "gn:admin1_code":"87.0",
    "gn:admin2_code":"3202.0",
    "gn:admin3_code":"320201.0",
    "gn:asciiname":"Ostromecko",
    "gn:country_code":"PL",
    "gn:dem":74,
    "gn:feature_class":"P",
    "gn:feature_code":"PPL",
    "gn:name":"Ostrom\u0119cko",
    "gn:population":0,
    "gn:timezone":"Europe/Warsaw",
    "iso:country":"PL",
    "wof:name":"Ostromecko",
    "wof:placetype":"locality"
},
  "geometry": {"coordinates":[15.63818,53.01143],"type":"Point"}
}