{
  "type": "Feature",
  "properties": {
    "gn:admin1_code":"72.0",
    "gn:admin2_code":"208.0",
    "gn:admin3_code":"20806.0",
    "gn:asciiname":"Niedzwiedna",
    "gn:country_code":"PL",
    "gn:dem":351,
    "gn:feature_class":"P",
    "gn:feature_code":"PPL",
    "gn:name":"Nied\u017awiedna",
    "gn:population":0,
    "gn:timezone":"Europe/Warsaw",
    "iso:country":"PL",
    "name:deu_x_preferred":[
        "Nied\u017awiedna"
    ],
    "name:pol_x_preferred":[
        "Nied\u017awiedna"
    ],
    "wof:name":"Niedzwiedna",
    "wof:placetype":"neighbourhood"
},
  "geometry": {"coordinates":[16.63332999999999,50.28333],"type":"Point"}
}