{
  "type": "Feature",
  "properties": {
    "gn:admin1_code":"81.0",
    "gn:admin2_code":"2011.0",
    "gn:admin3_code":"201103.0",
    "gn:asciiname":"Losiniec",
    "gn:country_code":"PL",
    "gn:dem":164,
    "gn:feature_class":"P",
    "gn:feature_code":"PPL",
    "gn:name":"\u0141osiniec",
    "gn:population":0,
    "gn:timezone":"Europe/Warsaw",
    "iso:country":"PL",
    "name:lit_x_preferred":[
        "Losinecas"
    ],
    "name:pol_x_preferred":[
        "\u0141osiniec"
    ],
    "name:ukr_x_preferred":[
        "\u041b\u043e\u0441\u0456\u043d\u0435\u0446\u044c"
    ],
    "wof:name":"Losiniec",
    "wof:placetype":"locality"
},
  "geometry": {"coordinates":[23.17328,53.38628000000001],"type":"Point"}
}