{
  "type": "Feature",
  "properties": {
    "gn:admin1_code":"81.0",
    "gn:admin2_code":"2011.0",
    "gn:admin3_code":"201103.0",
    "gn:asciiname":"Losiniec",
    "gn:country_code":"PL",
    "gn:dem":164,
    "gn:feature_class":"P",
    "gn:feature_code":"PPL",
    "gn:name":"\u0141osiniec",
    "gn:population":0,
    "gn:timezone":"Europe/Warsaw",
    "iso:country":"PL",
    "name:und_x_variant":[
        "\u0141osiniec"
    ],
    "wof:name":"Losiniec",
    "wof:placetype":"locality"
},
  "geometry": {"coordinates":[23.17328,53.38628000000001],"type":"Point"}
}