{
  "type": "Feature",
  "properties": {
    "gn:admin1_code":"80.0",
    "gn:admin2_code":"1819.0",
    "gn:admin3_code":"181903.0",
    "gn:asciiname":"Gwozdzianka",
    "gn:country_code":"PL",
    "gn:dem":315,
    "gn:feature_class":"P",
    "gn:feature_code":"PPL",
    "gn:name":"Gwo\u017adzianka",
    "gn:population":0,
    "gn:timezone":"Europe/Warsaw",
    "iso:country":"PL",
    "name:und_x_variant":[
        "Gwa\u017cdzianka",
        "Gwo\u017adzianka"
    ],
    "wof:name":"Gwozdzianka",
    "wof:placetype":"locality"
},
  "geometry": {"coordinates":[21.88134,49.86906],"type":"Point"}
}