{
  "type": "Feature",
  "properties": {
    "gn:admin1_code":"80.0",
    "gn:admin2_code":"1819.0",
    "gn:admin3_code":"181903.0",
    "gn:asciiname":"Gwozdzianka",
    "gn:country_code":"PL",
    "gn:dem":315,
    "gn:feature_class":"P",
    "gn:feature_code":"PPL",
    "gn:name":"Gwo\u017adzianka",
    "gn:population":0,
    "gn:timezone":"Europe/Warsaw",
    "iso:country":"PL",
    "name:azb_x_preferred":[
        "\u0642\u0648\u0648\u0698\u062c\u0627\u0646\u06a9\u0627"
    ],
    "name:fas_x_preferred":[
        "\u06af\u0648\u0648\u0698\u062c\u0627\u0646\u06a9\u0627"
    ],
    "name:pol_x_preferred":[
        "Gwo\u017adzianka"
    ],
    "name:rue_x_preferred":[
        "\u0413\u0432\u043e\u0437\u0434\u044f\u043d\u043a\u0430"
    ],
    "name:rus_x_preferred":[
        "\u0413\u0432\u043e\u0437\u044c\u0434\u0437\u044f\u043d\u043a\u0430"
    ],
    "name:ukr_x_preferred":[
        "\u0413\u0432\u043e\u0437\u0434\u044f\u043d\u043a\u0430"
    ],
    "name:und_x_variant":[
        "Gwa\u017cdzianka"
    ],
    "wof:name":"Gwozdzianka",
    "wof:placetype":"locality"
},
  "geometry": {"coordinates":[21.88134,49.86906],"type":"Point"}
}