{
  "type": "Feature",
  "properties": {
    "gn:gn_country":"PL",
    "gn:gn_fcode":"PPLA3",
    "gn:gn_pop":2529,
    "gn:population":2529,
    "iso:country":"PL",
    "name:bul_x_preferred":[
        "\u0424\u0440\u043e\u043c\u0431\u043e\u0440\u043a"
    ],
    "name:ceb_x_preferred":[
        "Frombork"
    ],
    "name:ces_x_preferred":[
        "Frombork"
    ],
    "name:che_x_preferred":[
        "\u0424\u0440\u043e\u043c\u0431\u043e\u0440\u043a"
    ],
    "name:deu_x_preferred":[
        "Frombork"
    ],
    "name:dsb_x_preferred":[
        "Frombork"
    ],
    "name:eng_x_preferred":[
        "Frombork"
    ],
    "name:epo_x_preferred":[
        "Frombork"
    ],
    "name:fin_x_preferred":[
        "Frombork"
    ],
    "name:fra_x_preferred":[
        "Frombork"
    ],
    "name:gla_x_preferred":[
        "Frombork"
    ],
    "name:ind_x_preferred":[
        "Frombork"
    ],
    "name:ita_x_preferred":[
        "Frombork"
    ],
    "name:jav_x_preferred":[
        "Frombork"
    ],
    "name:lat_x_preferred":[
        "Frauenburgum"
    ],
    "name:lav_x_preferred":[
        "Fromborka"
    ],
    "name:lit_x_preferred":[
        "Fromborkas"
    ],
    "name:msa_x_preferred":[
        "Frombork"
    ],
    "name:nds_x_preferred":[
        "Frauenburg"
    ],
    "name:nld_x_preferred":[
        "Frombork"
    ],
    "name:nor_x_preferred":[
        "Frombork"
    ],
    "name:pol_x_preferred":[
        "Frombork"
    ],
    "name:por_x_preferred":[
        "Frombork"
    ],
    "name:ron_x_preferred":[
        "Frombork"
    ],
    "name:rus_x_preferred":[
        "\u0424\u0440\u043e\u043c\u0431\u043e\u0440\u043a"
    ],
    "name:slk_x_preferred":[
        "Frombork"
    ],
    "name:slv_x_preferred":[
        "Frombork"
    ],
    "name:spa_x_preferred":[
        "Frombork"
    ],
    "name:srp_x_preferred":[
        "\u0424\u0440\u043e\u043c\u0431\u043e\u0440\u043a"
    ],
    "name:swe_x_preferred":[
        "Frombork"
    ],
    "name:ukr_x_preferred":[
        "\u0424\u0440\u043e\u043c\u0431\u043e\u0440\u043a"
    ],
    "name:unk_x_variant":[
        "Frauenburg"
    ],
    "name:vie_x_preferred":[
        "Frombork"
    ],
    "name:zho_x_preferred":[
        "\u5f17\u9f99\u5821"
    ],
    "qs_pg:aaroncc":"PL",
    "qs_pg:gn_country":"PL",
    "qs_pg:gn_fcode":"PPLA3",
    "qs_pg:gn_pop":2529,
    "qs_pg:name":"Frombork",
    "qs_pg:name_adm0":"Polska",
    "qs_pg:name_adm1":"Warminsko-Mazurskie",
    "qs_pg:photos":1,
    "qs_pg:photos_1k":1,
    "qs_pg:photos_9k":1,
    "qs_pg:photos_9r":5,
    "qs_pg:photos_all":324,
    "qs_pg:photos_sr":1,
    "qs_pg:pop_sr":4,
    "qs_pg:qs_pg_placetype":"localadmin",
    "qs_pg:qs_pg_placetype_gp":"LocalAdmin",
    "qs_pg:woe_adm0":23424923,
    "woe:adm0_id":23424923,
    "woe:name_adm0":"Polska",
    "woe:name_adm1":"Warminsko-Mazurskie",
    "woe:placetype":"LocalAdmin",
    "wof:name":"Frombork",
    "wof:placetype":"localadmin",
    "wof:population":2529
},
  "geometry": {"coordinates":[19.68029,54.35766],"type":"Point"}
}