{
  "type": "Feature",
  "properties": {
    "gn:gn_country":"PL",
    "gn:gn_fcode":"PPLA3",
    "gn:gn_pop":830,
    "gn:population":830,
    "iso:country":"PL",
    "name:ceb_x_preferred":[
        "Chod\u00f3w"
    ],
    "name:eng_x_preferred":[
        "Gmina Chod\u00f3w"
    ],
    "name:fra_x_preferred":[
        "Chod\u00f3w"
    ],
    "name:nld_x_preferred":[
        "Chod\u00f3w"
    ],
    "name:pol_x_preferred":[
        "Chod\u00f3w"
    ],
    "name:por_x_preferred":[
        "Comuna de Chod\u00f3w"
    ],
    "name:rus_x_preferred":[
        "\u0425\u043e\u0434\u0443\u0432"
    ],
    "name:slk_x_preferred":[
        "Gmina Chod\u00f3w"
    ],
    "name:ukr_x_preferred":[
        "\u0490\u043c\u0456\u043d\u0430 \u0425\u043e\u0434\u0443\u0432"
    ],
    "name:ukr_x_variant":[
        "\u0425\u043e\u0434\u0443\u0432"
    ],
    "name:war_x_preferred":[
        "Gmina Chod\u00f3w"
    ],
    "qs_pg:aaroncc":"PL",
    "qs_pg:gn_country":"PL",
    "qs_pg:gn_fcode":"PPLA3",
    "qs_pg:gn_pop":830,
    "qs_pg:name":"Chod\u00f3w",
    "qs_pg:name_adm0":"Polska",
    "qs_pg:name_adm1":"Wielkopolskie",
    "qs_pg:photos":1,
    "qs_pg:photos_1k":1,
    "qs_pg:photos_9k":1,
    "qs_pg:photos_9r":1,
    "qs_pg:photos_all":1,
    "qs_pg:photos_sr":1,
    "qs_pg:pop_sr":2,
    "qs_pg:qs_pg_placetype":"localadmin",
    "qs_pg:qs_pg_placetype_gp":"LocalAdmin",
    "qs_pg:woe_adm0":23424923,
    "woe:adm0_id":23424923,
    "woe:name_adm0":"Polska",
    "woe:name_adm1":"Wielkopolskie",
    "woe:placetype":"LocalAdmin",
    "wof:name":"Chod\u00f3w",
    "wof:placetype":"localadmin",
    "wof:population":830
},
  "geometry": {"coordinates":[19.01218,52.24961],"type":"Point"}
}