{
  "type": "Feature",
  "properties": {
    "gn:country":"PL",
    "gn:fcode":"PPL",
    "gn:population":0,
    "iso:country":"PL",
    "name:als_x_preferred":[
        "Mory"
    ],
    "name:cat_x_preferred":[
        "Mory"
    ],
    "name:deu_x_preferred":[
        "Mory"
    ],
    "name:fas_x_preferred":[
        "\u0645\u0648\u0631\u06cc"
    ],
    "name:fra_x_preferred":[
        "Mory"
    ],
    "name:pol_x_preferred":[
        "Mory"
    ],
    "name:ukr_x_preferred":[
        "\u041c\u043e\u0440\u0438"
    ],
    "qs_pg:aaroncc":"PL",
    "qs_pg:gn_country":"PL",
    "qs_pg:gn_fcode":"PPL",
    "qs_pg:gn_pop":0,
    "qs_pg:name":"Mory",
    "qs_pg:name_adm0":"Polska",
    "qs_pg:name_adm1":"Mazowieckie",
    "qs_pg:photos":185,
    "qs_pg:photos_1k":37,
    "qs_pg:photos_9k":1,
    "qs_pg:photos_9r":4,
    "qs_pg:photos_all":185,
    "qs_pg:photos_sr":4,
    "qs_pg:pop_sr":0,
    "qs_pg:qs_pg_placetype":"neighbourhood",
    "qs_pg:qs_pg_placetype_gp":"Suburb",
    "qs_pg:woe_adm0":23424923,
    "woe:adm0_id":23424923,
    "woe:name_adm0":"Polska",
    "woe:name_adm1":"Mazowieckie",
    "woe:placetype":"Suburb",
    "wof:name":"Mory",
    "wof:placetype":"neighbourhood"
},
  "geometry": {"coordinates":[20.8681,52.21676],"type":"Point"}
}