{
  "type": "Feature",
  "properties": {
    "gn:admin1_code":"75.0",
    "gn:admin2_code":"618.0",
    "gn:admin3_code":"61805.0",
    "gn:asciiname":"Jedrzejowka",
    "gn:country_code":"PL",
    "gn:dem":232,
    "gn:feature_class":"P",
    "gn:feature_code":"PPL",
    "gn:name":"Jedrzej\u00f3wka",
    "gn:population":0,
    "gn:timezone":"Europe/Warsaw",
    "iso:country":"PL",
    "wof:name":"Jedrzejowka",
    "wof:placetype":"locality"
},
  "geometry": {"coordinates":[23.65,50.36667],"type":"Point"}
}