{
  "type": "Feature",
  "properties": {
    "gn:admin1_code":"77.0",
    "gn:admin2_code":"1213.0",
    "gn:admin3_code":"121303.0",
    "gn:asciiname":"Bobrek",
    "gn:country_code":"PL",
    "gn:dem":228,
    "gn:feature_class":"P",
    "gn:feature_code":"PPL",
    "gn:name":"Bobrek",
    "gn:population":0,
    "gn:timezone":"Europe/Warsaw",
    "iso:country":"PL",
    "name:ceb_x_preferred":[
        "Bobrek"
    ],
    "name:deu_x_preferred":[
        "Bobrek"
    ],
    "name:pol_x_preferred":[
        "Bobrek"
    ],
    "name:ukr_x_preferred":[
        "\u0411\u043e\u0431\u0440\u0435\u043a"
    ],
    "wof:name":"Bobrek",
    "wof:placetype":"locality"
},
  "geometry": {"coordinates":[19.25263,50.05953],"type":"Point"}
}