{
  "type": "Feature",
  "properties": {
    "gn:admin1_code":"77.0",
    "gn:admin2_code":"1208.0",
    "gn:admin3_code":"120805.0",
    "gn:asciiname":"Kamienczyce",
    "gn:country_code":"PL",
    "gn:dem":265,
    "gn:feature_class":"P",
    "gn:feature_code":"PPL",
    "gn:name":"Kamie\u0144czyce",
    "gn:population":0,
    "gn:timezone":"Europe/Warsaw",
    "iso:country":"PL",
    "name:pol_x_preferred":[
        "Kamie\u0144czyce"
    ],
    "name:rus_x_preferred":[
        "\u041a\u0430\u043c\u0435\u043d\u044c\u0447\u0438\u0446\u0435"
    ],
    "name:ukr_x_preferred":[
        "\u041a\u0430\u043c\u0435\u043d\u044c\u0447\u0438\u0446\u0435"
    ],
    "wof:name":"Kamienczyce",
    "wof:placetype":"locality"
},
  "geometry": {"coordinates":[20.00246,50.33522],"type":"Point"}
}