{
  "type": "Feature",
  "properties": {
    "gn:admin1_code":"75.0",
    "gn:admin2_code":"612.0",
    "gn:admin3_code":"61205.0",
    "gn:asciiname":"Stare",
    "gn:country_code":"PL",
    "gn:dem":176,
    "gn:feature_class":"P",
    "gn:feature_code":"PPL",
    "gn:name":"Stare",
    "gn:population":0,
    "gn:timezone":"Europe/Warsaw",
    "iso:country":"PL",
    "name:deu_x_preferred":[
        "Stare"
    ],
    "name:fra_x_preferred":[
        "Stare"
    ],
    "name:pol_x_preferred":[
        "Stare"
    ],
    "name:ron_x_preferred":[
        "Stare"
    ],
    "name:ukr_x_preferred":[
        "\u0421\u0442\u0430\u0440\u0435"
    ],
    "wof:name":"Stare",
    "wof:placetype":"locality"
},
  "geometry": {"coordinates":[22.07105,51.11391],"type":"Point"}
}