{
  "type": "Feature",
  "properties": {
    "gn:admin1_code":"77.0",
    "gn:admin2_code":"1205.0",
    "gn:admin3_code":"120510.0",
    "gn:asciiname":"Skwirtne",
    "gn:cc2":"PL",
    "gn:country_code":"PL",
    "gn:dem":456,
    "gn:feature_class":"P",
    "gn:feature_code":"PPL",
    "gn:name":"Skwirtne",
    "gn:population":0,
    "gn:timezone":"Europe/Warsaw",
    "iso:country":"PL",
    "name:azb_x_preferred":[
        "\u0633\u06a9\u0648\u06cc\u0631\u062a\u0646\u0647"
    ],
    "name:fas_x_preferred":[
        "\u0633\u06a9\u0648\u06cc\u0631\u062a\u0646\u0647"
    ],
    "name:fra_x_preferred":[
        "Skwirtne"
    ],
    "name:pol_x_preferred":[
        "Skwirtne"
    ],
    "name:rue_x_preferred":[
        "\u0421\u043a\u0432\u0456\u0440\u0442\u043d\u0435"
    ],
    "name:rus_x_preferred":[
        "\u0421\u043a\u0432\u0438\u0440\u0442\u043d\u0435"
    ],
    "name:ukr_x_preferred":[
        "\u0421\u043a\u0432\u0456\u0440\u0442\u043d\u0435"
    ],
    "name:und_x_variant":[
        "Skwirte"
    ],
    "wof:name":"Skwirtne",
    "wof:placetype":"locality"
},
  "geometry": {"coordinates":[21.19005,49.49288],"type":"Point"}
}