{
  "type": "Feature",
  "properties": {
    "gn:admin1_code":"77.0",
    "gn:admin2_code":"1205.0",
    "gn:admin3_code":"120510.0",
    "gn:asciiname":"Skwirtne",
    "gn:cc2":"PL",
    "gn:country_code":"PL",
    "gn:dem":456,
    "gn:feature_class":"P",
    "gn:feature_code":"PPL",
    "gn:name":"Skwirtne",
    "gn:population":0,
    "gn:timezone":"Europe/Warsaw",
    "iso:country":"PL",
    "name:und_x_variant":[
        "Skwirte",
        "Skwirtne"
    ],
    "wof:name":"Skwirtne",
    "wof:placetype":"locality"
},
  "geometry": {"coordinates":[21.19005,49.49288],"type":"Point"}
}