{
  "type": "Feature",
  "properties": {
    "gn:admin1_code":"85.0",
    "gn:admin2_code":"2814.0",
    "gn:admin3_code":"281409.0",
    "gn:asciiname":"Jemiolowo",
    "gn:country_code":"PL",
    "gn:dem":197,
    "gn:feature_class":"P",
    "gn:feature_code":"PPL",
    "gn:name":"Jemio\u0142owo",
    "gn:population":0,
    "gn:timezone":"Europe/Warsaw",
    "iso:country":"PL",
    "name:ceb_x_preferred":[
        "Jemio\u0142owo"
    ],
    "name:pol_x_preferred":[
        "Jemio\u0142owo"
    ],
    "name:ukr_x_preferred":[
        "\u0404\u043c\u0439\u043e\u043b\u043e\u0432\u043e"
    ],
    "name:und_x_variant":[
        "Mispelsee"
    ],
    "wof:name":"Jemiolowo",
    "wof:placetype":"locality"
},
  "geometry": {"coordinates":[20.29985,53.56191],"type":"Point"}
}