{
  "type": "Feature",
  "properties": {
    "iso:country":"PL",
    "name:pol_x_preferred":[
        "\u017bubard\u017a"
    ],
    "wof:name":"Zubardz",
    "wof:placetype":"neighbourhood"
},
  "geometry": {"coordinates":[19.42546501839236,51.78498457192448],"type":"Point"}
}