{
  "type": "Feature",
  "properties": {
    "gn:admin1_code":"87.0",
    "gn:admin2_code":"3213.0",
    "gn:admin3_code":"321305.0",
    "gn:asciiname":"Nosalin",
    "gn:country_code":"PL",
    "gn:dem":25,
    "gn:feature_class":"P",
    "gn:feature_code":"PPL",
    "gn:name":"Nosalin",
    "gn:population":0,
    "gn:timezone":"Europe/Warsaw",
    "iso:country":"PL",
    "name:azb_x_preferred":[
        "\u0646\u0648\u0633\u0627\u0644\u06cc\u0646"
    ],
    "name:ceb_x_preferred":[
        "Nosalin"
    ],
    "name:deu_x_preferred":[
        "Nosalin"
    ],
    "name:fas_x_preferred":[
        "\u0646\u0648\u0633\u0627\u0644\u06cc\u0646"
    ],
    "name:pol_x_preferred":[
        "Nosalin"
    ],
    "name:ukr_x_preferred":[
        "\u041d\u043e\u0441\u0430\u043b\u0456\u043d"
    ],
    "wof:name":"Nosalin",
    "wof:placetype":"locality"
},
  "geometry": {"coordinates":[16.77322,54.43245],"type":"Point"}
}