{
  "type": "Feature",
  "properties": {
    "gn:admin1_code":"78.0",
    "gn:admin2_code":"1408.0",
    "gn:admin3_code":"140805.0",
    "gn:asciiname":"Olszewnica Nowa",
    "gn:country_code":"PL",
    "gn:dem":75,
    "gn:feature_class":"P",
    "gn:feature_code":"PPL",
    "gn:name":"Olszewnica Nowa",
    "gn:population":0,
    "gn:timezone":"Europe/Warsaw",
    "iso:country":"PL",
    "name:ceb_x_preferred":[
        "Olszewnica Nowa"
    ],
    "name:fra_x_preferred":[
        "Olszewnica Nowa"
    ],
    "name:pol_x_preferred":[
        "Olszewnica Nowa"
    ],
    "name:ukr_x_preferred":[
        "\u041e\u043b\u044c\u0448\u0435\u0432\u043d\u0438\u0446\u044f-\u041d\u043e\u0432\u0430"
    ],
    "wof:name":"Olszewnica Nowa",
    "wof:placetype":"locality"
},
  "geometry": {"coordinates":[20.84012,52.44147],"type":"Point"}
}