{
  "type": "Feature",
  "properties": {
    "iso:country":"PL",
    "name:eng_x_preferred":[
        "Swiatniki"
    ],
    "name:pol_x_preferred":[
        "\u015awi\u0105tniki"
    ],
    "wof:name":"Swiatniki",
    "wof:placetype":"neighbourhood"
},
  "geometry": {"coordinates":[17.1041831957436,51.08199129188949],"type":"Point"}
}