{
  "type": "Feature",
  "properties": {
    "gn:admin1_code":"81.0",
    "gn:admin2_code":"2014.0",
    "gn:admin3_code":"201403.0",
    "gn:asciiname":"Bobrowa",
    "gn:country_code":"PL",
    "gn:dem":106,
    "gn:feature_class":"P",
    "gn:feature_code":"PPL",
    "gn:name":"Bobrowa",
    "gn:population":0,
    "gn:timezone":"Europe/Warsaw",
    "iso:country":"PL",
    "wof:name":"Bobrowa",
    "wof:placetype":"locality"
},
  "geometry": {"coordinates":[22.37865,53.1106],"type":"Point"}
}