{
  "type": "Feature",
  "properties": {
    "iso:country":"PL",
    "name:csb_x_preferred":[
        "\u00d2ks\u00ebwi\u00e9"
    ],
    "name:deu_x_preferred":[
        "Oksywie"
    ],
    "name:eng_x_preferred":[
        "Oksywie"
    ],
    "name:jpn_x_preferred":[
        "\u30aa\u30af\u30b9\u30a3\u30f4\u30a3\u30a7"
    ],
    "name:nob_x_preferred":[
        "Oksywie"
    ],
    "name:nor_x_preferred":[
        "Oksywie"
    ],
    "name:pol_x_colloquial":[
        "Oxhoeft",
        "Oxhoft"
    ],
    "name:pol_x_preferred":[
        "Oksywie"
    ],
    "name:pol_x_variant":[
        "Oksywje",
        "Oxh\u00f6ft",
        "Port Oksywie",
        "Pt Oksywie"
    ],
    "name:zho_x_preferred":[
        "\u6b50\u514b\u65af\u5a01"
    ],
    "qs:gn_adm0_cc":"PL",
    "qs:gn_fcode":"PPL",
    "qs:gn_local":3099424,
    "qs:gn_nam_loc":"gdynia",
    "qs:gn_namadm1":"82",
    "qs:gn_name":"Oksywie",
    "qs:local_max":4765,
    "qs:local_sum":8081,
    "qs:localhoods":4,
    "qs:name":"Oksywie",
    "qs:name_adm0":"Polska",
    "qs:name_adm1":"Pomorskie",
    "qs:name_adm2":"Gdynia",
    "qs:name_lau":"Gdynia",
    "qs:name_local":"Gdynia",
    "qs:photo_max":254,
    "qs:photo_sum":1365,
    "qs:placetype":"Suburb",
    "qs:quad_count":99,
    "qs:woe_adm0":23424923,
    "qs:woe_adm1":12577945,
    "qs:woe_adm2":12591370,
    "qs:woe_lau":12618455,
    "qs:woe_local":493421,
    "qs:woe_ver":"7.10.0",
    "wd:wordcount":336,
    "wof:lang":[
        "pol"
    ],
    "wof:name":"Oksywie",
    "wof:placetype":"neighbourhood"
},
  "geometry": {"coordinates":[18.529181,54.566466],"type":"Point"}
}