{
  "type": "Feature",
  "properties": {
    "gn:gn_country":"PL",
    "gn:gn_fcode":"PPL",
    "gn:gn_pop":1017,
    "gn:population":1017,
    "iso:country":"PL",
    "name:deu_x_preferred":[
        "Stanis\u0142aw G\u00f3rny"
    ],
    "name:eng_x_preferred":[
        "Stanis\u0142aw G\u00f3rny"
    ],
    "name:fra_x_preferred":[
        "Stanis\u0142aw G\u00f3rny"
    ],
    "name:nld_x_preferred":[
        "Stanis\u0142aw G\u00f3rny"
    ],
    "name:pol_x_preferred":[
        "Stanis\u0142aw G\u00f3rny"
    ],
    "name:unk_x_variant":[
        "Stanistaw Gony"
    ],
    "qs_pg:aaroncc":"PL",
    "qs_pg:gn_country":"PL",
    "qs_pg:gn_fcode":"PPL",
    "qs_pg:gn_pop":1017,
    "qs_pg:name":"Stanis\u0142aw G\u00f3rny",
    "qs_pg:name_adm0":"Polska",
    "qs_pg:name_adm1":"Ma\u0142opolskie",
    "qs_pg:photos_9r":0,
    "qs_pg:photos_sr":0,
    "qs_pg:pop_sr":3,
    "qs_pg:qs_pg_placetype":"locality",
    "qs_pg:qs_pg_placetype_gp":"Town",
    "qs_pg:woe_adm0":23424923,
    "woe:adm0_id":23424923,
    "woe:name_adm0":"Polska",
    "woe:name_adm1":"Ma\u0142opolskie",
    "woe:placetype":"Town",
    "wof:name":"Stanis\u0142aw G\u00f3rny",
    "wof:placetype":"locality",
    "wof:population":1017
},
  "geometry": {"coordinates":[19.62931,49.91155],"type":"Point"}
}