{
  "type": "Feature",
  "properties": {
    "gn:admin1_code":"76.0",
    "gn:admin2_code":"811.0",
    "gn:admin3_code":"81107.0",
    "gn:asciiname":"Dobrzyn",
    "gn:country_code":"PL",
    "gn:dem":137,
    "gn:feature_class":"P",
    "gn:feature_code":"PPL",
    "gn:name":"Dobrzy\u0144",
    "gn:population":0,
    "gn:timezone":"Europe/Warsaw",
    "iso:country":"PL",
    "name:azb_x_preferred":[
        "\u062f\u0648\u0628\u0698\u0646\u0642"
    ],
    "name:deu_x_preferred":[
        "Dobrzy\u0144"
    ],
    "name:fas_x_preferred":[
        "\u062f\u0648\u0628\u0698\u0646\u06af"
    ],
    "name:fra_x_preferred":[
        "Dobrzy\u0144"
    ],
    "name:pol_x_preferred":[
        "Dobrzy\u0144"
    ],
    "name:ukr_x_preferred":[
        "\u0414\u043e\u0431\u0436\u0438\u043d\u044c"
    ],
    "name:und_x_variant":[
        "Dobers"
    ],
    "wof:name":"Dobrzyn",
    "wof:placetype":"locality"
},
  "geometry": {"coordinates":[14.97791,51.42706],"type":"Point"}
}