{
  "type": "Feature",
  "properties": {
    "gn:country":"PL",
    "gn:fcode":"PPL",
    "gn:population":0,
    "iso:country":"PL",
    "name:ast_x_preferred":[
        "Spycimierz"
    ],
    "name:ceb_x_preferred":[
        "Spycimierz"
    ],
    "name:eng_x_preferred":[
        "Spycimierz"
    ],
    "name:fra_x_preferred":[
        "Spycimierz"
    ],
    "name:nld_x_preferred":[
        "Spycimierz"
    ],
    "name:pol_x_preferred":[
        "Spycimierz"
    ],
    "name:ukr_x_preferred":[
        "\u0421\u043f\u0438\u0446\u0438\u043c\u0435\u0436"
    ],
    "name:vie_x_preferred":[
        "L\u00e0ng Spycimierz"
    ],
    "qs_pg:aaroncc":"PL",
    "qs_pg:gn_country":"PL",
    "qs_pg:gn_fcode":"PPL",
    "qs_pg:gn_pop":0,
    "qs_pg:name":"Spycimierz",
    "qs_pg:name_adm0":"Polska",
    "qs_pg:name_adm1":"\u0141\u00f3dzkie",
    "qs_pg:photos":110,
    "qs_pg:photos_1k":22,
    "qs_pg:photos_9k":1,
    "qs_pg:photos_9r":3,
    "qs_pg:photos_all":110,
    "qs_pg:photos_sr":3,
    "qs_pg:pop_sr":0,
    "qs_pg:qs_pg_placetype":"locality",
    "qs_pg:qs_pg_placetype_gp":"Town",
    "qs_pg:woe_adm0":23424923,
    "woe:adm0_id":23424923,
    "woe:name_adm0":"Polska",
    "woe:name_adm1":"\u0141\u00f3dzkie",
    "woe:placetype":"Town",
    "wof:name":"Spycimierz",
    "wof:placetype":"locality"
},
  "geometry": {"coordinates":[18.77615,51.94723],"type":"Point"}
}