{
  "type": "Feature",
  "properties": {
    "gn:admin1_code":"81.0",
    "gn:admin2_code":"2008.0",
    "gn:admin3_code":"200802.0",
    "gn:asciiname":"Dobrzyniowka",
    "gn:country_code":"PL",
    "gn:dem":139,
    "gn:feature_class":"P",
    "gn:feature_code":"PPL",
    "gn:name":"Dobrzyni\u00f3wka",
    "gn:population":0,
    "gn:timezone":"Europe/Warsaw",
    "iso:country":"PL",
    "wof:name":"Dobrzyniowka",
    "wof:placetype":"locality"
},
  "geometry": {"coordinates":[23.0774,53.36164],"type":"Point"}
}