{
  "type": "Feature",
  "properties": {
    "gn:admin1_code":"82.0",
    "gn:admin2_code":"2261.0",
    "gn:admin3_code":"226101.0",
    "gn:asciiname":"Emaus",
    "gn:country_code":"PL",
    "gn:dem":43,
    "gn:feature_class":"P",
    "gn:feature_code":"PPL",
    "gn:name":"Emaus",
    "gn:population":0,
    "gn:timezone":"Europe/Warsaw",
    "iso:country":"PL",
    "wof:name":"Emaus",
    "wof:placetype":"locality"
},
  "geometry": {"coordinates":[18.61667000000001,54.35],"type":"Point"}
}