{
  "type": "Feature",
  "properties": {
    "gn:admin1_code":"85.0",
    "gn:admin2_code":"2819.0",
    "gn:admin3_code":"281902.0",
    "gn:asciiname":"Nowy Harsz",
    "gn:country_code":"PL",
    "gn:dem":133,
    "gn:feature_class":"P",
    "gn:feature_code":"PPL",
    "gn:name":"Nowy Harsz",
    "gn:population":0,
    "gn:timezone":"Europe/Warsaw",
    "iso:country":"PL",
    "name:und_x_variant":[
        "Neu Haarszen",
        "Neu Haarschen",
        "Nowy Harsz"
    ],
    "wof:name":"Nowy Harsz",
    "wof:placetype":"locality"
},
  "geometry": {"coordinates":[21.78333,54.11666999999999],"type":"Point"}
}