{
  "type": "Feature",
  "properties": {
    "gn:admin1_code":"78.0",
    "gn:admin2_code":"1411.0",
    "gn:admin3_code":"141104.0",
    "gn:asciiname":"Kolonia Drazdzewo",
    "gn:country_code":"PL",
    "gn:dem":109,
    "gn:feature_class":"P",
    "gn:feature_code":"PPL",
    "gn:name":"Kolonia Dr\u0105\u017cd\u017cewo",
    "gn:population":0,
    "gn:timezone":"Europe/Warsaw",
    "iso:country":"PL",
    "wof:name":"Kolonia Drazdzewo",
    "wof:placetype":"locality"
},
  "geometry": {"coordinates":[21.13333,53.08333],"type":"Point"}
}