{
  "type": "Feature",
  "properties": {
    "gn:admin1_code":"76.0",
    "gn:admin2_code":"810.0",
    "gn:admin3_code":"81006.0",
    "gn:asciiname":"Miedzylesie",
    "gn:country_code":"PL",
    "gn:dem":134,
    "gn:feature_class":"P",
    "gn:feature_code":"PPL",
    "gn:name":"Mi\u0119dzylesie",
    "gn:population":0,
    "gn:timezone":"Europe/Warsaw",
    "iso:country":"PL",
    "name:deu_x_historical":[
        "Walddorf"
    ],
    "name:deu_x_preferred":[
        "Walddorf"
    ],
    "name:fra_x_preferred":[
        "Mi\u0119dzylesie"
    ],
    "name:pol_x_preferred":[
        "Mi\u0119dzylesie"
    ],
    "wof:name":"Miedzylesie",
    "wof:placetype":"locality"
},
  "geometry": {"coordinates":[15.63389,51.62249],"type":"Point"}
}