{
  "type": "Feature",
  "properties": {
    "gn:admin1_code":"81.0",
    "gn:admin2_code":"2007.0",
    "gn:admin3_code":"200708.0",
    "gn:asciiname":"Rutki",
    "gn:country_code":"PL",
    "gn:dem":126,
    "gn:feature_class":"P",
    "gn:feature_code":"PPL",
    "gn:name":"Rutki",
    "gn:population":0,
    "gn:timezone":"Europe/Warsaw",
    "iso:country":"PL",
    "name:deu_x_preferred":[
        "Rutki"
    ],
    "name:fra_x_preferred":[
        "Rutki"
    ],
    "name:lav_x_preferred":[
        "Rutki"
    ],
    "name:pol_x_preferred":[
        "Rutki"
    ],
    "name:ukr_x_preferred":[
        "\u0420\u0443\u0442\u043a\u0456"
    ],
    "wof:name":"Rutki",
    "wof:placetype":"locality"
},
  "geometry": {"coordinates":[22.34756,53.21796],"type":"Point"}
}