{
  "type": "Feature",
  "properties": {
    "gn:admin1_code":"74.0",
    "gn:admin2_code":"1002.0",
    "gn:admin3_code":"100206.0",
    "gn:asciiname":"Piwki",
    "gn:country_code":"PL",
    "gn:dem":115,
    "gn:feature_class":"P",
    "gn:feature_code":"PPL",
    "gn:name":"Piwki",
    "gn:population":0,
    "gn:timezone":"Europe/Warsaw",
    "iso:country":"PL",
    "name:fra_x_preferred":[
        "Piwki"
    ],
    "name:pol_x_preferred":[
        "Piwki"
    ],
    "name:ukr_x_preferred":[
        "\u041f\u0456\u0432\u043a\u0456"
    ],
    "wof:name":"Piwki",
    "wof:placetype":"locality"
},
  "geometry": {"coordinates":[19.34636,52.21439],"type":"Point"}
}