{
  "type": "Feature",
  "properties": {
    "gn:country":"PL",
    "gn:fcode":"PPL",
    "gn:population":0,
    "iso:country":"PL",
    "name:ast_x_preferred":[
        "Olszewnica Stara"
    ],
    "name:ceb_x_preferred":[
        "Olszewnica Stara"
    ],
    "name:eng_x_preferred":[
        "Olszewnica Stara"
    ],
    "name:fra_x_preferred":[
        "Olszewnica Stara"
    ],
    "name:nld_x_preferred":[
        "Olszewnica Stara"
    ],
    "name:pol_x_preferred":[
        "Olszewnica Stara"
    ],
    "name:ukr_x_preferred":[
        "\u041e\u043b\u044c\u0448\u0435\u0432\u043d\u0438\u0446\u044f-\u0421\u0442\u0430\u0440\u0430"
    ],
    "qs_pg:aaroncc":"PL",
    "qs_pg:gn_country":"PL",
    "qs_pg:gn_fcode":"PPL",
    "qs_pg:gn_pop":0,
    "qs_pg:name":"Olszewnica Stara",
    "qs_pg:name_adm0":"Polska",
    "qs_pg:name_adm1":"Mazowieckie",
    "qs_pg:photos_9r":0,
    "qs_pg:photos_sr":0,
    "qs_pg:pop_sr":0,
    "qs_pg:qs_pg_placetype":"locality",
    "qs_pg:qs_pg_placetype_gp":"Town",
    "qs_pg:woe_adm0":23424923,
    "woe:adm0_id":23424923,
    "woe:name_adm0":"Polska",
    "woe:name_adm1":"Mazowieckie",
    "woe:placetype":"Town",
    "wof:name":"Olszewnica Stara",
    "wof:placetype":"locality"
},
  "geometry": {"coordinates":[20.8643,52.43962],"type":"Point"}
}