{
  "type": "Feature",
  "properties": {
    "gn:admin1_code":"82.0",
    "gn:admin2_code":"2216.0",
    "gn:admin3_code":"221604.0",
    "gn:asciiname":"Trankwice",
    "gn:country_code":"PL",
    "gn:dem":41,
    "gn:feature_class":"P",
    "gn:feature_code":"PPL",
    "gn:name":"Trankwice",
    "gn:population":0,
    "gn:timezone":"Europe/Warsaw",
    "iso:country":"PL",
    "name:ceb_x_preferred":[
        "Trankwice"
    ],
    "name:pol_x_preferred":[
        "Trankwice"
    ],
    "name:und_x_variant":[
        "Trankwitz"
    ],
    "wof:name":"Trankwice",
    "wof:placetype":"locality"
},
  "geometry": {"coordinates":[19.23787,53.97002],"type":"Point"}
}