{
  "type": "Feature",
  "properties": {
    "gn:admin1_code":"78.0",
    "gn:admin2_code":"1403.0",
    "gn:admin3_code":"140313.0",
    "gn:asciiname":"Wicie Stare",
    "gn:country_code":"PL",
    "gn:dem":93,
    "gn:feature_class":"P",
    "gn:feature_code":"PPL",
    "gn:name":"Wicie Stare",
    "gn:population":0,
    "gn:timezone":"Europe/Warsaw",
    "iso:country":"PL",
    "wof:name":"Wicie Stare",
    "wof:placetype":"locality"
},
  "geometry": {"coordinates":[21.31667,51.86667],"type":"Point"}
}